{
  "type": "Feature",
  "properties": {
    "gn:adm1_name":"Shimaneken",
    "gn:adm2_name":"Yatsukagunyatsukachou",
    "gn:name":"Hanyuu",
    "iso:country":"JP",
    "wof:name":"690-1404",
    "wof:placetype":"postalcode"
},
  "geometry": {"coordinates":[133.17679999999999,35.4902],"type":"Point"}
}