{
  "type": "Feature",
  "properties": {
    "gn:adm1_name":"Kyoutofu",
    "gn:adm2_name":"Kyoutoshikitaku",
    "gn:name":"Nishigamohouraidani",
    "iso:country":"JP",
    "wof:name":"603-8856",
    "wof:placetype":"postalcode"
},
  "geometry": {"coordinates":[135.72329999999999,35.0864],"type":"Point"}
}