{
  "type": "Feature",
  "properties": {
    "gn:adm1_name":"Yamaguchiken",
    "gn:adm2_name":"Kumagegunhiraochou",
    "gn:name":"Okuni",
    "iso:country":"JP",
    "wof:name":"742-1113",
    "wof:placetype":"postalcode"
},
  "geometry": {"coordinates":[132.12119999999999,33.8724],"type":"Point"}
}