{
  "type": "Feature",
  "properties": {
    "gn:adm1_name":"Hiroshimaken",
    "gn:adm2_name":"Hiroshimashihigashiku",
    "gn:name":"Hesakaminami",
    "iso:country":"JP",
    "wof:name":"732-0013",
    "wof:placetype":"postalcode"
},
  "geometry": {"coordinates":[132.49170000000001,34.4247],"type":"Point"}
}