{
  "type": "Feature",
  "properties": {
    "gn:adm1_name":"Kyoutofu",
    "gn:adm2_name":"Kameokashi",
    "gn:name":"Higashihonmechounakano",
    "iso:country":"JP",
    "wof:name":"621-0233",
    "wof:placetype":"postalcode"
},
  "geometry": {"coordinates":[135.47450000000001,35.0435],"type":"Point"}
}