{
  "type": "Feature",
  "properties": {
    "gn:adm1_name":"Nagasakiken",
    "gn:adm2_name":"Shimoagatagunmitsushimachou",
    "gn:name":"Kamoise",
    "iso:country":"JP",
    "wof:name":"817-1107",
    "wof:placetype":"postalcode"
},
  "geometry": {"coordinates":[129.38640000000001,34.3375],"type":"Point"}
}