{
  "type": "Feature",
  "properties": {
    "gn:adm1_name":"Miyagiken",
    "gn:adm2_name":"Ishinomakishi",
    "gn:name":"Suimeikita",
    "iso:country":"JP",
    "wof:name":"986-0801",
    "wof:placetype":"postalcode"
},
  "geometry": {"coordinates":[141.3192,38.4442],"type":"Point"}
}