{
  "type": "Feature",
  "properties": {
    "gn:adm1_name":"Miyagiken",
    "gn:adm2_name":"Motoyoshigunmotoyoshichou",
    "gn:name":"Mukaibata",
    "iso:country":"JP",
    "wof:name":"988-0367",
    "wof:placetype":"postalcode"
},
  "geometry": {"coordinates":[141.4436,38.776],"type":"Point"}
}