{
  "type": "Feature",
  "properties": {
    "gn:adm1_name":"Yamagataken",
    "gn:adm2_name":"Mogamigunkaneyamamachi",
    "gn:name":"Kaneyama",
    "iso:country":"JP",
    "wof:name":"999-5402",
    "wof:placetype":"postalcode"
},
  "geometry": {"coordinates":[140.34209999999999,38.8827],"type":"Point"}
}