{
  "type": "Feature",
  "properties": {
    "gn:adm1_name":"Ooitaken",
    "gn:adm2_name":"Usagun'Ajimumachi",
    "gn:name":"Kayagomori",
    "iso:country":"JP",
    "wof:name":"872-0723",
    "wof:placetype":"postalcode"
},
  "geometry": {"coordinates":[131.38069999999999,33.3417],"type":"Point"}
}