{
  "type": "Feature",
  "properties": {
    "gn:adm1_name":"Chibaken",
    "gn:adm2_name":"Naritashi",
    "gn:name":"Naganuma",
    "iso:country":"JP",
    "wof:name":"286-0804",
    "wof:placetype":"postalcode"
},
  "geometry": {"coordinates":[140.30500000000001,35.8361],"type":"Point"}
}