{
  "type": "Feature",
  "properties": {
    "gn:adm1_name":"Kyoutofu",
    "gn:adm2_name":"Kyoutoshishimogyouku",
    "gn:name":"Shinchou",
    "iso:country":"JP",
    "wof:name":"600-8001",
    "wof:placetype":"postalcode"
},
  "geometry": {"coordinates":[135.77000000000001,35.0039],"type":"Point"}
}