{
  "type": "Feature",
  "properties": {
    "gn:adm1_name":"Fukushimaken",
    "gn:adm2_name":"Shirakawashi",
    "gn:name":"Kajimachi",
    "iso:country":"JP",
    "wof:name":"961-0913",
    "wof:placetype":"postalcode"
},
  "geometry": {"coordinates":[140.2217,37.1231],"type":"Point"}
}