{
  "type": "Feature",
  "properties": {
    "gn:adm1_name":"Kanagawaken",
    "gn:adm2_name":"Yokohamashikanagawaku",
    "gn:name":"Tatemachi",
    "iso:country":"JP",
    "wof:name":"221-0063",
    "wof:placetype":"postalcode"
},
  "geometry": {"coordinates":[139.63570000000001,35.482],"type":"Point"}
}