{
  "type": "Feature",
  "properties": {
    "gn:adm1_name":"Aichiken",
    "gn:adm2_name":"Toyotashi",
    "gn:name":"Seishinchou",
    "iso:country":"JP",
    "wof:name":"471-0844",
    "wof:placetype":"postalcode"
},
  "geometry": {"coordinates":[137.11779999999999,35.061],"type":"Point"}
}