{
  "type": "Feature",
  "properties": {
    "gn:adm1_name":"Kanagawaken",
    "gn:adm2_name":"Hiratsukashi",
    "gn:name":"Kidokoro",
    "iso:country":"JP",
    "wof:name":"254-0005",
    "wof:placetype":"postalcode"
},
  "geometry": {"coordinates":[139.32419999999999,35.3748],"type":"Point"}
}