{
  "type": "Feature",
  "properties": {
    "gn:adm1_name":"Fukushimaken",
    "gn:adm2_name":"Shirakawashi",
    "gn:name":"Hatajuku",
    "iso:country":"JP",
    "wof:name":"961-0038",
    "wof:placetype":"postalcode"
},
  "geometry": {"coordinates":[140.22229999999999,37.051],"type":"Point"}
}