{
  "type": "Feature",
  "properties": {
    "gn:adm1_name":"Fukuiken",
    "gn:adm2_name":"Fukuishi",
    "gn:name":"Tennouchou",
    "iso:country":"JP",
    "wof:name":"918-8136",
    "wof:placetype":"postalcode"
},
  "geometry": {"coordinates":[136.23779999999999,36.0273],"type":"Point"}
}