{
  "type": "Feature",
  "properties": {
    "gn:adm1_name":"Kyoutofu",
    "gn:adm2_name":"Kyoutoshinakagyouku",
    "gn:name":"Nishinokyoushikibuchou",
    "iso:country":"JP",
    "wof:name":"604-8384",
    "wof:placetype":"postalcode"
},
  "geometry": {"coordinates":[135.74420000000001,35.0138],"type":"Point"}
}