{
  "type": "Feature",
  "properties": {
    "gn:adm1_name":"Niigataken",
    "gn:adm2_name":"Toyosakashi",
    "gn:name":"Ayano",
    "iso:country":"JP",
    "wof:name":"950-3377",
    "wof:placetype":"postalcode"
},
  "geometry": {"coordinates":[139.1885,37.9201],"type":"Point"}
}