{
  "type": "Feature",
  "properties": {
    "gn:adm1_name":"Kumamotoken",
    "gn:adm2_name":"Kumagun'Itsukimura",
    "gn:name":"Ikanikeisaiganaibaai",
    "iso:country":"JP",
    "wof:name":"868-0200",
    "wof:placetype":"postalcode"
},
  "geometry": {"coordinates":[130.83019999999999,32.421],"type":"Point"}
}