{
  "type": "Feature",
  "properties": {
    "gn:adm1_name":"Nagasakiken",
    "gn:adm2_name":"Shimoagataguntoyotamachou",
    "gn:name":"Koduna",
    "iso:country":"JP",
    "wof:name":"817-1256",
    "wof:placetype":"postalcode"
},
  "geometry": {"coordinates":[129.28270000000001,34.4177],"type":"Point"}
}