{
  "type": "Feature",
  "properties": {
    "gn:adm1_name":"Niigataken",
    "gn:adm2_name":"Niigatashi",
    "gn:name":"Ishizuechoudoorikamiichinochou",
    "iso:country":"JP",
    "wof:name":"951-8054",
    "wof:placetype":"postalcode"
},
  "geometry": {"coordinates":[139.04910000000001,37.9195],"type":"Point"}
}