{
  "type": "Feature",
  "properties": {
    "gn:adm1_name":"Mieken",
    "gn:adm2_name":"Wataraigunnanseichou",
    "gn:name":"Kidani",
    "iso:country":"JP",
    "wof:name":"516-0106",
    "wof:placetype":"postalcode"
},
  "geometry": {"coordinates":[136.71279999999999,34.322],"type":"Point"}
}