{
  "type": "Feature",
  "properties": {
    "gn:adm1_name":"Kyoutofu",
    "gn:adm2_name":"Kyoutoshifushimiku",
    "gn:name":"Daigokitadani",
    "iso:country":"JP",
    "wof:name":"601-1381",
    "wof:placetype":"postalcode"
},
  "geometry": {"coordinates":[135.82820000000001,34.964],"type":"Point"}
}