{
  "type": "Feature",
  "properties": {
    "gn:adm1_name":"Nagasakiken",
    "gn:adm2_name":"Matsuurashi",
    "gn:name":"Mikuriyachouyokokubomen",
    "iso:country":"JP",
    "wof:name":"859-4755",
    "wof:placetype":"postalcode"
},
  "geometry": {"coordinates":[129.66919999999999,33.3485],"type":"Point"}
}