{
  "type": "Feature",
  "properties": {
    "gn:adm1_name":"Oosakafu",
    "gn:adm2_name":"Ibarakishi",
    "gn:name":"Oodatoushibachou",
    "iso:country":"JP",
    "wof:name":"567-0013",
    "wof:placetype":"postalcode"
},
  "geometry": {"coordinates":[135.5772,34.8389],"type":"Point"}
}