{
  "type": "Feature",
  "properties": {
    "gn:adm1_name":"Naraken",
    "gn:adm2_name":"Udagunhaibarachou",
    "gn:name":"Fukuchi",
    "iso:country":"JP",
    "wof:name":"633-0204",
    "wof:placetype":"postalcode"
},
  "geometry": {"coordinates":[135.96369999999999,34.5338],"type":"Point"}
}