{
  "type": "Feature",
  "properties": {
    "gn:adm1_name":"Yamagataken",
    "gn:adm2_name":"Shinjoushi",
    "gn:name":"Horibatamachi",
    "iso:country":"JP",
    "wof:name":"996-0085",
    "wof:placetype":"postalcode"
},
  "geometry": {"coordinates":[140.29400000000001,38.767],"type":"Point"}
}