{
  "type": "Feature",
  "properties": {
    "gn:adm1_name":"Aichiken",
    "gn:adm2_name":"Chitagunmihamachou",
    "gn:name":"Futsuto",
    "iso:country":"JP",
    "wof:name":"470-2401",
    "wof:placetype":"postalcode"
},
  "geometry": {"coordinates":[136.9177,34.8045],"type":"Point"}
}