{
  "type": "Feature",
  "properties": {
    "gn:adm1_name":"Naganoken",
    "gn:adm2_name":"Komoroshi",
    "gn:name":"Kou",
    "iso:country":"JP",
    "wof:name":"384-0801",
    "wof:placetype":"postalcode"
},
  "geometry": {"coordinates":[138.43549999999999,36.3227],"type":"Point"}
}