{
  "type": "Feature",
  "properties": {
    "gn:adm1_name":"Toyamaken",
    "gn:adm2_name":"Nakaniikawaguntateyamamachi",
    "gn:name":"Nishiashihara",
    "iso:country":"JP",
    "wof:name":"930-0224",
    "wof:placetype":"postalcode"
},
  "geometry": {"coordinates":[137.3015,36.669],"type":"Point"}
}