{
  "type": "Feature",
  "properties": {
    "gn:adm1_name":"Yamanashiken",
    "gn:adm2_name":"Ootsukishi",
    "gn:name":"Nigiokamachiokuyama",
    "iso:country":"JP",
    "wof:name":"401-0006",
    "wof:placetype":"postalcode"
},
  "geometry": {"coordinates":[138.92830000000001,35.6352],"type":"Point"}
}