{
  "type": "Feature",
  "properties": {
    "gn:adm1_name":"Aichiken",
    "gn:adm2_name":"Toyokawashi",
    "gn:name":"Futabachou",
    "iso:country":"JP",
    "wof:name":"442-0804",
    "wof:placetype":"postalcode"
},
  "geometry": {"coordinates":[137.4229,34.8287],"type":"Point"}
}