{
  "type": "Feature",
  "properties": {
    "gn:adm1_name":"Ibarakiken",
    "gn:adm2_name":"Shimotsumashi",
    "gn:name":"Ishinomiya",
    "iso:country":"JP",
    "wof:name":"304-0057",
    "wof:placetype":"postalcode"
},
  "geometry": {"coordinates":[139.94499999999999,36.1955],"type":"Point"}
}