{
  "type": "Feature",
  "properties": {
    "gn:adm1_name":"Yamagataken",
    "gn:adm2_name":"Nagaishi",
    "gn:name":"Mamanoue",
    "iso:country":"JP",
    "wof:name":"993-0001",
    "wof:placetype":"postalcode"
},
  "geometry": {"coordinates":[140.0401,38.1068],"type":"Point"}
}