{
  "type": "Feature",
  "properties": {
    "gn:adm1_name":"Chibaken",
    "gn:adm2_name":"Sakurashi",
    "gn:name":"Toujidai",
    "iso:country":"JP",
    "wof:name":"285-0816",
    "wof:placetype":"postalcode"
},
  "geometry": {"coordinates":[140.2354,35.6951],"type":"Point"}
}