{
  "type": "Feature",
  "properties": {
    "gn:adm1_name":"Tottoriken",
    "gn:adm2_name":"Touhakugunhawaichou",
    "gn:name":"Ikanikeisaiganaibaai",
    "iso:country":"JP",
    "wof:name":"682-0700",
    "wof:placetype":"postalcode"
},
  "geometry": {"coordinates":[133.88409999999999,35.4774],"type":"Point"}
}