{
  "type": "Feature",
  "properties": {
    "gn:adm1_name":"Fukuiken",
    "gn:adm2_name":"Sakaigun'Awarachou",
    "gn:name":"Nishionsen",
    "iso:country":"JP",
    "wof:name":"910-4127",
    "wof:placetype":"postalcode"
},
  "geometry": {"coordinates":[136.18469999999999,36.2216],"type":"Point"}
}