{
  "type": "Feature",
  "properties": {
    "gn:adm1_name":"Aichiken",
    "gn:adm2_name":"Nagoyashinakagawaku",
    "gn:name":"Arakoshichou",
    "iso:country":"JP",
    "wof:name":"454-0044",
    "wof:placetype":"postalcode"
},
  "geometry": {"coordinates":[136.88380000000001,35.1342],"type":"Point"}
}