{
  "type": "Feature",
  "properties": {
    "gn:adm1_name":"Tochigiken",
    "gn:adm2_name":"Shimotsugagunmibumachi",
    "gn:name":"Hanyuuda",
    "iso:country":"JP",
    "wof:name":"321-0234",
    "wof:placetype":"postalcode"
},
  "geometry": {"coordinates":[139.7799,36.473],"type":"Point"}
}