{
  "type": "Feature",
  "properties": {
    "gn:adm1_name":"Shimaneken",
    "gn:adm2_name":"Masudashi",
    "gn:name":"Akebononishimachi",
    "iso:country":"JP",
    "wof:name":"698-0025",
    "wof:placetype":"postalcode"
},
  "geometry": {"coordinates":[131.83760000000001,34.6816],"type":"Point"}
}