{
  "type": "Feature",
  "properties": {
    "gn:adm1_name":"Chibaken",
    "gn:adm2_name":"Sodegaurashi",
    "gn:name":"Doumeki",
    "iso:country":"JP",
    "wof:name":"299-0213",
    "wof:placetype":"postalcode"
},
  "geometry": {"coordinates":[140.03739999999999,35.3792],"type":"Point"}
}