{
  "type": "Feature",
  "properties": {
    "gn:adm1_name":"Mieken",
    "gn:adm2_name":"Kameyamashi",
    "gn:name":"Higashimiyukichou",
    "iso:country":"JP",
    "wof:name":"519-0124",
    "wof:placetype":"postalcode"
},
  "geometry": {"coordinates":[136.45580000000001,34.8518],"type":"Point"}
}