{
  "type": "Feature",
  "properties": {
    "gn:adm1_name":"Fukuokaken",
    "gn:adm2_name":"Tagawagun'Itodamachi",
    "gn:name":"Saibu",
    "iso:country":"JP",
    "wof:name":"822-1322",
    "wof:placetype":"postalcode"
},
  "geometry": {"coordinates":[130.767,33.6585],"type":"Point"}
}