{
  "type": "Feature",
  "properties": {
    "gn:adm1_name":"Saitamaken",
    "gn:adm2_name":"Soukashi",
    "gn:name":"Hikawachou",
    "iso:country":"JP",
    "wof:name":"340-0034",
    "wof:placetype":"postalcode"
},
  "geometry": {"coordinates":[139.79990000000001,35.8272],"type":"Point"}
}