{
  "type": "Feature",
  "properties": {
    "gn:adm1_name":"Kumamotoken",
    "gn:adm2_name":"Kumamotoshi",
    "gn:name":"Suzurikawamachi",
    "iso:country":"JP",
    "wof:name":"861-5524",
    "wof:placetype":"postalcode"
},
  "geometry": {"coordinates":[130.6927,32.863],"type":"Point"}
}