{
  "type": "Feature",
  "properties": {
    "gn:adm1_name":"Fukushimaken",
    "gn:adm2_name":"Nishishirakawagunnishigoumura",
    "gn:name":"Tsuryuu",
    "iso:country":"JP",
    "wof:name":"961-8081",
    "wof:placetype":"postalcode"
},
  "geometry": {"coordinates":[140.11699999999999,37.1635],"type":"Point"}
}