{
  "type": "Feature",
  "properties": {
    "gn:adm1_name":"Yamaguchiken",
    "gn:adm2_name":"Shuunanshi",
    "gn:name":"Aioichou",
    "iso:country":"JP",
    "wof:name":"745-0055",
    "wof:placetype":"postalcode"
},
  "geometry": {"coordinates":[131.79920000000001,34.0601],"type":"Point"}
}