{
  "type": "Feature",
  "properties": {
    "gn:adm1_name":"Oosakafu",
    "gn:adm2_name":"Yaoshi",
    "gn:name":"Nishiyamamotochou",
    "iso:country":"JP",
    "wof:name":"581-0868",
    "wof:placetype":"postalcode"
},
  "geometry": {"coordinates":[135.6163,34.631],"type":"Point"}
}