{
  "type": "Feature",
  "properties": {
    "gn:adm1_name":"Niigataken",
    "gn:adm2_name":"Kitauonumagunkoidemachi",
    "gn:name":"Oodukashinden",
    "iso:country":"JP",
    "wof:name":"946-0004",
    "wof:placetype":"postalcode"
},
  "geometry": {"coordinates":[138.9667,37.2352],"type":"Point"}
}