{
  "type": "Feature",
  "properties": {
    "gn:adm1_name":"Oosakafu",
    "gn:adm2_name":"Sakaishi",
    "gn:name":"Hishiki",
    "iso:country":"JP",
    "wof:name":"593-8315",
    "wof:placetype":"postalcode"
},
  "geometry": {"coordinates":[135.4743,34.5101],"type":"Point"}
}