{
  "type": "Feature",
  "properties": {
    "gn:adm1_name":"Toukyouto",
    "gn:adm2_name":"Chuuouku",
    "gn:name":"Nihonbashikoamichou",
    "iso:country":"JP",
    "wof:name":"103-0016",
    "wof:placetype":"postalcode"
},
  "geometry": {"coordinates":[139.7808,35.6832],"type":"Point"}
}