{
  "type": "Feature",
  "properties": {
    "gn:adm1_name":"Saitamaken",
    "gn:adm2_name":"Oosatogunyoriimachi",
    "gn:name":"Kozono",
    "iso:country":"JP",
    "wof:name":"369-1217",
    "wof:placetype":"postalcode"
},
  "geometry": {"coordinates":[139.2261,36.1152],"type":"Point"}
}