{
  "type": "Feature",
  "properties": {
    "gn:adm1_name":"Kagawaken",
    "gn:adm2_name":"Marugameshi",
    "gn:name":"Shichibanchou",
    "iso:country":"JP",
    "wof:name":"763-0027",
    "wof:placetype":"postalcode"
},
  "geometry": {"coordinates":[133.80160000000001,34.2837],"type":"Point"}
}