{
  "type": "Feature",
  "properties": {
    "gn:adm1_name":"Hyougoken",
    "gn:adm2_name":"Yabugun'Ooyachou",
    "gn:name":"Kadono",
    "iso:country":"JP",
    "wof:name":"667-0433",
    "wof:placetype":"postalcode"
},
  "geometry": {"coordinates":[134.6806,35.3075],"type":"Point"}
}