{
  "type": "Feature",
  "properties": {
    "gn:adm1_name":"Naganoken",
    "gn:adm2_name":"Uedashi",
    "gn:name":"Chuuou",
    "iso:country":"JP",
    "wof:name":"386-0012",
    "wof:placetype":"postalcode"
},
  "geometry": {"coordinates":[138.25460000000001,36.4019],"type":"Point"}
}