{
  "type": "Feature",
  "properties": {
    "gn:adm1_name":"Hyougoken",
    "gn:adm2_name":"Shisougunyamasakichou",
    "gn:name":"Shounou",
    "iso:country":"JP",
    "wof:name":"671-2572",
    "wof:placetype":"postalcode"
},
  "geometry": {"coordinates":[134.5454,35.0107],"type":"Point"}
}