{
  "type": "Feature",
  "properties": {
    "gn:adm1_name":"Mieken",
    "gn:adm2_name":"Yokkaichishi",
    "gn:name":"Shimonomiyachou",
    "iso:country":"JP",
    "wof:name":"510-8028",
    "wof:placetype":"postalcode"
},
  "geometry": {"coordinates":[136.6413,35.0156],"type":"Point"}
}