{
  "type": "Feature",
  "properties": {
    "gn:adm1_name":"Gifuken",
    "gn:adm2_name":"Anpachigungoudochou",
    "gn:name":"Sarayashiki",
    "iso:country":"JP",
    "wof:name":"503-2322",
    "wof:placetype":"postalcode"
},
  "geometry": {"coordinates":[136.59129999999999,35.4162],"type":"Point"}
}