{
  "type": "Feature",
  "properties": {
    "gn:adm1_name":"Saitamaken",
    "gn:adm2_name":"Kitakatsushikagunkurihashimachi",
    "gn:name":"Midori",
    "iso:country":"JP",
    "wof:name":"349-1106",
    "wof:placetype":"postalcode"
},
  "geometry": {"coordinates":[139.69499999999999,36.13],"type":"Point"}
}