{
  "type": "Feature",
  "properties": {
    "gn:adm1_name":"Tottoriken",
    "gn:adm2_name":"Touhakuguntouhakuchou",
    "gn:name":"Tsukinoshita",
    "iso:country":"JP",
    "wof:name":"689-2305",
    "wof:placetype":"postalcode"
},
  "geometry": {"coordinates":[133.71360000000001,35.4908],"type":"Point"}
}