{
  "type": "Feature",
  "properties": {
    "gn:adm1_name":"Yamaguchiken",
    "gn:adm2_name":"Ubeshi",
    "gn:name":"Matsuzakichou",
    "iso:country":"JP",
    "wof:name":"755-0809",
    "wof:placetype":"postalcode"
},
  "geometry": {"coordinates":[131.22499999999999,33.9834],"type":"Point"}
}