{
  "type": "Feature",
  "properties": {
    "gn:adm1_name":"Niigataken",
    "gn:adm2_name":"Jouetsushi",
    "gn:name":"Kirihara",
    "iso:country":"JP",
    "wof:name":"943-0183",
    "wof:placetype":"postalcode"
},
  "geometry": {"coordinates":[138.28790000000001,37.1351],"type":"Point"}
}