{
  "type": "Feature",
  "properties": {
    "gn:adm1_name":"Niigataken",
    "gn:adm2_name":"Niigatashi",
    "gn:name":"Sumireno",
    "iso:country":"JP",
    "wof:name":"950-3133",
    "wof:placetype":"postalcode"
},
  "geometry": {"coordinates":[139.1602,37.9197],"type":"Point"}
}