{
  "type": "Feature",
  "properties": {
    "gn:adm1_name":"Okayamaken",
    "gn:adm2_name":"Takahashishi",
    "gn:name":"Haradaminamichou",
    "iso:country":"JP",
    "wof:name":"716-0044",
    "wof:placetype":"postalcode"
},
  "geometry": {"coordinates":[133.613,34.7827],"type":"Point"}
}