{
  "type": "Feature",
  "properties": {
    "gn:adm1_name":"Kagawaken",
    "gn:adm2_name":"Takamatsushi",
    "gn:name":"Enzachou",
    "iso:country":"JP",
    "wof:name":"761-8044",
    "wof:placetype":"postalcode"
},
  "geometry": {"coordinates":[134.00899999999999,34.2879],"type":"Point"}
}