{
  "type": "Feature",
  "properties": {
    "gn:adm1_name":"Tochigiken",
    "gn:adm2_name":"Ashikagashi",
    "gn:name":"Sukedooohashichou",
    "iso:country":"JP",
    "wof:name":"326-0048",
    "wof:placetype":"postalcode"
},
  "geometry": {"coordinates":[139.4649,36.34],"type":"Point"}
}