{
  "type": "Feature",
  "properties": {
    "gn:adm1_name":"Tochigiken",
    "gn:adm2_name":"Shimotsugagun'Oohiramachi",
    "gn:name":"Tomida",
    "iso:country":"JP",
    "wof:name":"329-4404",
    "wof:placetype":"postalcode"
},
  "geometry": {"coordinates":[139.69739999999999,36.338],"type":"Point"}
}