{
  "type": "Feature",
  "properties": {
    "gn:adm1_name":"Fukuokaken",
    "gn:adm2_name":"Iidukashi",
    "gn:name":"Katashima",
    "iso:country":"JP",
    "wof:name":"820-0068",
    "wof:placetype":"postalcode"
},
  "geometry": {"coordinates":[130.68170000000001,33.6465],"type":"Point"}
}