{
  "type": "Feature",
  "properties": {
    "gn:adm1_name":"Yamaguchiken",
    "gn:adm2_name":"Yamaguchishi",
    "gn:name":"Shinbaba",
    "iso:country":"JP",
    "wof:name":"753-0085",
    "wof:placetype":"postalcode"
},
  "geometry": {"coordinates":[131.47819999999999,34.1807],"type":"Point"}
}