{
  "type": "Feature",
  "properties": {
    "gn:adm1_name":"Miyagiken",
    "gn:adm2_name":"Kesennumashi",
    "gn:name":"Nagaisoshimohara",
    "iso:country":"JP",
    "wof:name":"988-0232",
    "wof:placetype":"postalcode"
},
  "geometry": {"coordinates":[141.58439999999999,38.8388],"type":"Point"}
}