{
  "type": "Feature",
  "properties": {
    "gn:adm1_name":"Shigaken",
    "gn:adm2_name":"Koukagunshigarakichou",
    "gn:name":"Kamiasamiya",
    "iso:country":"JP",
    "wof:name":"529-1841",
    "wof:placetype":"postalcode"
},
  "geometry": {"coordinates":[135.98740000000001,34.8549],"type":"Point"}
}