{
  "type": "Feature",
  "properties": {
    "gn:adm1_name":"Aichiken",
    "gn:adm2_name":"Handashi",
    "gn:name":"Sunadanichou",
    "iso:country":"JP",
    "wof:name":"475-0947",
    "wof:placetype":"postalcode"
},
  "geometry": {"coordinates":[136.89400000000001,34.9015],"type":"Point"}
}