{
  "type": "Feature",
  "properties": {
    "gn:adm1_name":"Oosakafu",
    "gn:adm2_name":"Hirakatashi",
    "gn:name":"Makinosaka",
    "iso:country":"JP",
    "wof:name":"573-1146",
    "wof:placetype":"postalcode"
},
  "geometry": {"coordinates":[135.66569999999999,34.8422],"type":"Point"}
}