{
  "type": "Feature",
  "properties": {
    "gn:adm1_name":"Shigaken",
    "gn:adm2_name":"Rittoushi",
    "gn:name":"Ono",
    "iso:country":"JP",
    "wof:name":"520-3016",
    "wof:placetype":"postalcode"
},
  "geometry": {"coordinates":[136.00890000000001,35.0184],"type":"Point"}
}