{
  "type": "Feature",
  "properties": {
    "gn:adm1_name":"Naganoken",
    "gn:adm2_name":"Kamiminochigunshinanomachi",
    "gn:name":"Honami",
    "iso:country":"JP",
    "wof:name":"389-1314",
    "wof:placetype":"postalcode"
},
  "geometry": {"coordinates":[138.2131,36.7786],"type":"Point"}
}