{
  "type": "Feature",
  "properties": {
    "gn:adm1_name":"Toyamaken",
    "gn:adm2_name":"Neigunfuchuumachi",
    "gn:name":"Masuta",
    "iso:country":"JP",
    "wof:name":"939-2714",
    "wof:placetype":"postalcode"
},
  "geometry": {"coordinates":[137.1739,36.6559],"type":"Point"}
}