{
  "type": "Feature",
  "properties": {
    "gn:adm1_name":"Fukuiken",
    "gn:adm2_name":"Yoshidagun'Eiheijichou",
    "gn:name":"Iijima",
    "iso:country":"JP",
    "wof:name":"910-1217",
    "wof:placetype":"postalcode"
},
  "geometry": {"coordinates":[136.35939999999999,36.0895],"type":"Point"}
}