{
  "type": "Feature",
  "properties": {
    "gn:adm1_name":"Shimaneken",
    "gn:adm2_name":"Matsueshi",
    "gn:name":"Sakaemachi",
    "iso:country":"JP",
    "wof:name":"690-0042",
    "wof:placetype":"postalcode"
},
  "geometry": {"coordinates":[133.05289999999999,35.4553],"type":"Point"}
}