{
  "type": "Feature",
  "properties": {
    "gn:adm1_name":"Fukushimaken",
    "gn:adm2_name":"Shirakawashi",
    "gn:name":"Gobanchougawara",
    "iso:country":"JP",
    "wof:name":"961-0076",
    "wof:placetype":"postalcode"
},
  "geometry": {"coordinates":[140.2022,37.1337],"type":"Point"}
}