{
  "type": "Feature",
  "properties": {
    "gn:adm1_name":"Kagawaken",
    "gn:adm2_name":"Takamatsushi",
    "gn:name":"Mineyamachou",
    "iso:country":"JP",
    "wof:name":"760-0009",
    "wof:placetype":"postalcode"
},
  "geometry": {"coordinates":[134.02600000000001,34.3304],"type":"Point"}
}