{
  "type": "Feature",
  "properties": {
    "gn:adm1_name":"Gifuken",
    "gn:adm2_name":"Kaidugunkaiduchou",
    "gn:name":"Morishita",
    "iso:country":"JP",
    "wof:name":"503-0622",
    "wof:placetype":"postalcode"
},
  "geometry": {"coordinates":[136.66669999999999,35.1812],"type":"Point"}
}