{
  "type": "Feature",
  "properties": {
    "gn:adm1_name":"Hyougoken",
    "gn:adm2_name":"Asagogunwadayamachou",
    "gn:name":"Hotsukouji",
    "iso:country":"JP",
    "wof:name":"669-5267",
    "wof:placetype":"postalcode"
},
  "geometry": {"coordinates":[134.85749999999999,35.3251],"type":"Point"}
}