{
  "type": "Feature",
  "properties": {
    "gn:adm1_name":"Okayamaken",
    "gn:adm2_name":"Okayamashi",
    "gn:name":"Hanajirimidorimachi",
    "iso:country":"JP",
    "wof:name":"701-0131",
    "wof:placetype":"postalcode"
},
  "geometry": {"coordinates":[133.87459999999999,34.6595],"type":"Point"}
}