{
  "type": "Feature",
  "properties": {
    "gn:adm1_name":"Yamaguchiken",
    "gn:adm2_name":"Ubeshi",
    "gn:name":"Nishinakachou",
    "iso:country":"JP",
    "wof:name":"755-0053",
    "wof:placetype":"postalcode"
},
  "geometry": {"coordinates":[131.23390000000001,33.9612],"type":"Point"}
}