{
  "type": "Feature",
  "properties": {
    "gn:adm1_name":"Aichiken",
    "gn:adm2_name":"Owariasahishi",
    "gn:name":"Nagasakachouminamyama",
    "iso:country":"JP",
    "wof:name":"488-0821",
    "wof:placetype":"postalcode"
},
  "geometry": {"coordinates":[137.0309,35.2028],"type":"Point"}
}