{
  "type": "Feature",
  "properties": {
    "gn:adm1_name":"Aichiken",
    "gn:adm2_name":"Nagoyashitenpakuku",
    "gn:name":"Tenpakuchouueda",
    "iso:country":"JP",
    "wof:name":"468-0005",
    "wof:placetype":"postalcode"
},
  "geometry": {"coordinates":[136.988,35.1292],"type":"Point"}
}