{
  "type": "Feature",
  "properties": {
    "gn:adm1_name":"Kanagawaken",
    "gn:adm2_name":"Kawasakishinakaharaku",
    "gn:name":"Kosugijinyachou",
    "iso:country":"JP",
    "wof:name":"211-0062",
    "wof:placetype":"postalcode"
},
  "geometry": {"coordinates":[139.65719999999999,35.5851],"type":"Point"}
}