{
  "type": "Feature",
  "properties": {
    "gn:adm1_name":"Tochigiken",
    "gn:adm2_name":"Kanumashi",
    "gn:name":"Asahigaoka",
    "iso:country":"JP",
    "wof:name":"322-0345",
    "wof:placetype":"postalcode"
},
  "geometry": {"coordinates":[139.6994,36.5404],"type":"Point"}
}