{
  "type": "Feature",
  "properties": {
    "gn:adm1_name":"Naganoken",
    "gn:adm2_name":"Naganoshi",
    "gn:name":"Inabakamisenda",
    "iso:country":"JP",
    "wof:name":"380-0915",
    "wof:placetype":"postalcode"
},
  "geometry": {"coordinates":[138.20070000000001,36.6303],"type":"Point"}
}