{
  "type": "Feature",
  "properties": {
    "gn:adm1_name":"Niigataken",
    "gn:adm2_name":"Niitsushi",
    "gn:name":"Kanaya",
    "iso:country":"JP",
    "wof:name":"956-0823",
    "wof:placetype":"postalcode"
},
  "geometry": {"coordinates":[139.16759999999999,37.7906],"type":"Point"}
}