{
  "type": "Feature",
  "properties": {
    "gn:adm1_name":"Fukuokaken",
    "gn:adm2_name":"Tagawagunsoedamachi",
    "gn:name":"Hikosan",
    "iso:country":"JP",
    "wof:name":"824-0721",
    "wof:placetype":"postalcode"
},
  "geometry": {"coordinates":[130.90350000000001,33.4864],"type":"Point"}
}