{
  "type": "Feature",
  "properties": {
    "gn:adm1_name":"Ibarakiken",
    "gn:adm2_name":"Kasamashi",
    "gn:name":"Ikenobe",
    "iso:country":"JP",
    "wof:name":"309-1602",
    "wof:placetype":"postalcode"
},
  "geometry": {"coordinates":[140.3364,36.4046],"type":"Point"}
}