{
  "type": "Feature",
  "properties": {
    "gn:adm1_name":"Shizuokaken",
    "gn:adm2_name":"Shizuokashi",
    "gn:name":"Sakaechou",
    "iso:country":"JP",
    "wof:name":"420-0859",
    "wof:placetype":"postalcode"
},
  "geometry": {"coordinates":[138.39179999999999,34.9744],"type":"Point"}
}