{
  "type": "Feature",
  "properties": {
    "gn:adm1_name":"Naraken",
    "gn:adm2_name":"Goseshi",
    "gn:name":"Asamachi",
    "iso:country":"JP",
    "wof:name":"639-2255",
    "wof:placetype":"postalcode"
},
  "geometry": {"coordinates":[135.73759999999999,34.423],"type":"Point"}
}