{
  "type": "Feature",
  "properties": {
    "gn:adm1_name":"Naraken",
    "gn:adm2_name":"Narashi",
    "gn:name":"Fujinokidai",
    "iso:country":"JP",
    "wof:name":"631-0044",
    "wof:placetype":"postalcode"
},
  "geometry": {"coordinates":[135.75479999999999,34.6783],"type":"Point"}
}