{
  "type": "Feature",
  "properties": {
    "gn:adm1_name":"Aichiken",
    "gn:adm2_name":"Minamishitaraguntsukudemura",
    "gn:name":"Awara",
    "iso:country":"JP",
    "wof:name":"441-1533",
    "wof:placetype":"postalcode"
},
  "geometry": {"coordinates":[137.43549999999999,34.9959],"type":"Point"}
}