{
  "type": "Feature",
  "properties": {
    "gn:adm1_name":"Kagoshimaken",
    "gn:adm2_name":"Kanoyashi",
    "gn:name":"Yokoyamachou",
    "iso:country":"JP",
    "wof:name":"893-0046",
    "wof:placetype":"postalcode"
},
  "geometry": {"coordinates":[130.83189999999999,31.3466],"type":"Point"}
}