{
  "type": "Feature",
  "properties": {
    "gn:adm1_name":"Yamagataken",
    "gn:adm2_name":"Sakatashi",
    "gn:name":"Yoshidashinden",
    "iso:country":"JP",
    "wof:name":"999-8167",
    "wof:placetype":"postalcode"
},
  "geometry": {"coordinates":[139.86340000000001,38.9398],"type":"Point"}
}