{
  "type": "Feature",
  "properties": {
    "gn:adm1_name":"Yamaguchiken",
    "gn:adm2_name":"Ubeshi",
    "gn:name":"Tsumazakigaisaku",
    "iso:country":"JP",
    "wof:name":"759-0204",
    "wof:placetype":"postalcode"
},
  "geometry": {"coordinates":[131.20920000000001,33.977],"type":"Point"}
}