{
  "type": "Feature",
  "properties": {
    "gn:adm1_name":"Toyamaken",
    "gn:adm2_name":"Nishitonamigunfukuokamachi",
    "gn:name":"Kibune",
    "iso:country":"JP",
    "wof:name":"939-0134",
    "wof:placetype":"postalcode"
},
  "geometry": {"coordinates":[137.0111,36.7475],"type":"Point"}
}