{
  "type": "Feature",
  "properties": {
    "gn:adm1_name":"Toyamaken",
    "gn:adm2_name":"Toyamashi",
    "gn:name":"Yasunoyamachi",
    "iso:country":"JP",
    "wof:name":"930-0087",
    "wof:placetype":"postalcode"
},
  "geometry": {"coordinates":[137.20330000000001,36.6925],"type":"Point"}
}