{
  "type": "Feature",
  "properties": {
    "gn:adm1_name":"Ibarakiken",
    "gn:adm2_name":"Namegatagunkitauramachi",
    "gn:name":"Miwa",
    "iso:country":"JP",
    "wof:name":"311-1702",
    "wof:placetype":"postalcode"
},
  "geometry": {"coordinates":[140.51949999999999,36.1115],"type":"Point"}
}