{
  "type": "Feature",
  "properties": {
    "gn:adm1_name":"Aichiken",
    "gn:adm2_name":"Atsumigun'Atsumichou",
    "gn:name":"Fukue",
    "iso:country":"JP",
    "wof:name":"441-3617",
    "wof:placetype":"postalcode"
},
  "geometry": {"coordinates":[137.1011,34.6282],"type":"Point"}
}