{
  "type": "Feature",
  "properties": {
    "gn:adm1_name":"Oosakafu",
    "gn:adm2_name":"Sennanguntajirichou",
    "gn:name":"Rinkuupo^Tominami",
    "iso:country":"JP",
    "wof:name":"598-0094",
    "wof:placetype":"postalcode"
},
  "geometry": {"coordinates":[135.28489999999999,34.3963],"type":"Point"}
}