{
  "type": "Feature",
  "properties": {
    "gn:adm1_name":"Hyougoken",
    "gn:adm2_name":"Amagasakishi",
    "gn:name":"Suehirochou",
    "iso:country":"JP",
    "wof:name":"660-0094",
    "wof:placetype":"postalcode"
},
  "geometry": {"coordinates":[135.3914,34.6963],"type":"Point"}
}