{
  "type": "Feature",
  "properties": {
    "gn:adm1_name":"Niigataken",
    "gn:adm2_name":"Kariwagunkariwamura",
    "gn:name":"Inooka",
    "iso:country":"JP",
    "wof:name":"945-0311",
    "wof:placetype":"postalcode"
},
  "geometry": {"coordinates":[138.63839999999999,37.4303],"type":"Point"}
}