{
  "type": "Feature",
  "properties": {
    "gn:adm1_name":"Kouchiken",
    "gn:adm2_name":"Nankokushi",
    "gn:name":"Oogaino",
    "iso:country":"JP",
    "wof:name":"783-0077",
    "wof:placetype":"postalcode"
},
  "geometry": {"coordinates":[133.57749999999999,33.667],"type":"Point"}
}