{
  "type": "Feature",
  "properties": {
    "gn:adm1_name":"Shizuokaken",
    "gn:adm2_name":"Numadushi",
    "gn:name":"Kitazonochou",
    "iso:country":"JP",
    "wof:name":"410-0061",
    "wof:placetype":"postalcode"
},
  "geometry": {"coordinates":[138.87549999999999,35.1241],"type":"Point"}
}