{
  "type": "Feature",
  "properties": {
    "gn:adm1_name":"Aichiken",
    "gn:adm2_name":"Nagoyashimizuhoku",
    "gn:name":"Doichichou",
    "iso:country":"JP",
    "wof:name":"467-0843",
    "wof:placetype":"postalcode"
},
  "geometry": {"coordinates":[136.9324,35.1166],"type":"Point"}
}