{
  "type": "Feature",
  "properties": {
    "gn:adm1_name":"Aichiken",
    "gn:adm2_name":"Chiryuushi",
    "gn:name":"Raikoujichou",
    "iso:country":"JP",
    "wof:name":"472-0002",
    "wof:placetype":"postalcode"
},
  "geometry": {"coordinates":[137.07149999999999,35.0012],"type":"Point"}
}