{
  "type": "Feature",
  "properties": {
    "gn:adm1_name":"Oosakafu",
    "gn:adm2_name":"Neyagawashi",
    "gn:name":"Nakakamidachou",
    "iso:country":"JP",
    "wof:name":"572-0053",
    "wof:placetype":"postalcode"
},
  "geometry": {"coordinates":[135.61060000000001,34.7522],"type":"Point"}
}