{
  "type": "Feature",
  "properties": {
    "gn:adm1_name":"Saitamaken",
    "gn:adm2_name":"Kawagoeshi",
    "gn:name":"Kamishingashi",
    "iso:country":"JP",
    "wof:name":"350-1135",
    "wof:placetype":"postalcode"
},
  "geometry": {"coordinates":[139.5033,35.8929],"type":"Point"}
}