{
  "type": "Feature",
  "properties": {
    "gn:adm1_name":"Chibaken",
    "gn:adm2_name":"Isumigun'Ooharamachi",
    "gn:name":"Yamada",
    "iso:country":"JP",
    "wof:name":"298-0025",
    "wof:placetype":"postalcode"
},
  "geometry": {"coordinates":[140.2208,35.7259],"type":"Point"}
}