{
  "type": "Feature",
  "properties": {
    "gn:adm1_name":"Gifuken",
    "gn:adm2_name":"Tajimishi",
    "gn:name":"Bentenchou",
    "iso:country":"JP",
    "wof:name":"507-0028",
    "wof:placetype":"postalcode"
},
  "geometry": {"coordinates":[137.12860000000001,35.3409],"type":"Point"}
}