{
  "type": "Feature",
  "properties": {
    "gn:adm1_name":"Yamaguchiken",
    "gn:adm2_name":"Yoshikigun'Ogoorichou",
    "gn:name":"Midorimachi",
    "iso:country":"JP",
    "wof:name":"754-0013",
    "wof:placetype":"postalcode"
},
  "geometry": {"coordinates":[131.46549999999999,34.1706],"type":"Point"}
}