{
  "type": "Feature",
  "properties": {
    "gn:adm1_name":"Fukushimaken",
    "gn:adm2_name":"Aiduwakamatsushi",
    "gn:name":"Ikkimachiyahata",
    "iso:country":"JP",
    "wof:name":"965-0003",
    "wof:placetype":"postalcode"
},
  "geometry": {"coordinates":[139.9452,37.5091],"type":"Point"}
}