{
  "type": "Feature",
  "properties": {
    "gn:adm1_name":"Niigataken",
    "gn:adm2_name":"Santougunkoshijimachi",
    "gn:name":"Kamiya",
    "iso:country":"JP",
    "wof:name":"949-5407",
    "wof:placetype":"postalcode"
},
  "geometry": {"coordinates":[138.80179999999999,37.4018],"type":"Point"}
}