{
  "type": "Feature",
  "properties": {
    "gn:adm1_name":"Kanagawaken",
    "gn:adm2_name":"Miurashi",
    "gn:name":"Suwachou",
    "iso:country":"JP",
    "wof:name":"238-0234",
    "wof:placetype":"postalcode"
},
  "geometry": {"coordinates":[139.62479999999999,35.144],"type":"Point"}
}