{
  "type": "Feature",
  "properties": {
    "gn:adm1_name":"Fukushimaken",
    "gn:adm2_name":"Higashishirakawagunhanawamachi",
    "gn:name":"Kinosori",
    "iso:country":"JP",
    "wof:name":"963-5534",
    "wof:placetype":"postalcode"
},
  "geometry": {"coordinates":[140.4562,36.9092],"type":"Point"}
}