{
  "type": "Feature",
  "properties": {
    "gn:adm1_name":"Chibaken",
    "gn:adm2_name":"Chibashiwakabaku",
    "gn:name":"Kitayatsuchou",
    "iso:country":"JP",
    "wof:name":"265-0067",
    "wof:placetype":"postalcode"
},
  "geometry": {"coordinates":[140.20060000000001,35.6067],"type":"Point"}
}