{
  "type": "Feature",
  "properties": {
    "gn:adm1_name":"Kumamotoken",
    "gn:adm2_name":"Kumamotoshi",
    "gn:name":"Juuzenjimachi",
    "iso:country":"JP",
    "wof:name":"860-0825",
    "wof:placetype":"postalcode"
},
  "geometry": {"coordinates":[130.69810000000001,32.78],"type":"Point"}
}