{
  "type": "Feature",
  "properties": {
    "gn:adm1_name":"Nagasakiken",
    "gn:adm2_name":"Saseboshi",
    "gn:name":"Matsuyamachou",
    "iso:country":"JP",
    "wof:name":"857-0015",
    "wof:placetype":"postalcode"
},
  "geometry": {"coordinates":[129.72239999999999,33.1903],"type":"Point"}
}