{
  "type": "Feature",
  "properties": {
    "gn:adm1_name":"Ooitaken",
    "gn:adm2_name":"Shimogegunsankoumura",
    "gn:name":"Obukuro",
    "iso:country":"JP",
    "wof:name":"871-0114",
    "wof:placetype":"postalcode"
},
  "geometry": {"coordinates":[131.1885,33.5312],"type":"Point"}
}