{
  "type": "Feature",
  "properties": {
    "gn:adm1_name":"Wakayamaken",
    "gn:adm2_name":"Nagagunkokawachou",
    "gn:name":"Umayado",
    "iso:country":"JP",
    "wof:name":"649-6521",
    "wof:placetype":"postalcode"
},
  "geometry": {"coordinates":[135.43270000000001,34.2824],"type":"Point"}
}