{
  "type": "Feature",
  "properties": {
    "gn:adm1_name":"Ishikawaken",
    "gn:adm2_name":"Kahokuguntsubatamachi",
    "gn:name":"Azamidani",
    "iso:country":"JP",
    "wof:name":"929-0403",
    "wof:placetype":"postalcode"
},
  "geometry": {"coordinates":[136.80439999999999,36.6878],"type":"Point"}
}