{
  "type": "Feature",
  "properties": {
    "gn:adm1_name":"Chibaken",
    "gn:adm2_name":"Touganeshi",
    "gn:name":"Yasakadai",
    "iso:country":"JP",
    "wof:name":"283-0801",
    "wof:placetype":"postalcode"
},
  "geometry": {"coordinates":[140.36080000000001,35.5705],"type":"Point"}
}