{
  "type": "Feature",
  "properties": {
    "gn:adm1_name":"Ehimeken",
    "gn:adm2_name":"Imabarishi",
    "gn:name":"Kitahamachou",
    "iso:country":"JP",
    "wof:name":"794-0011",
    "wof:placetype":"postalcode"
},
  "geometry": {"coordinates":[132.99789999999999,34.0771],"type":"Point"}
}