{
  "type": "Feature",
  "properties": {
    "gn:adm1_name":"Ishikawaken",
    "gn:adm2_name":"Komatsushi",
    "gn:name":"Shimamachi",
    "iso:country":"JP",
    "wof:name":"923-0303",
    "wof:placetype":"postalcode"
},
  "geometry": {"coordinates":[136.42859999999999,36.3516],"type":"Point"}
}