{
  "type": "Feature",
  "properties": {
    "gn:adm1_name":"Chibaken",
    "gn:adm2_name":"Shiroishi",
    "gn:name":"Sakuradai",
    "iso:country":"JP",
    "wof:name":"270-1412",
    "wof:placetype":"postalcode"
},
  "geometry": {"coordinates":[140.10570000000001,35.8024],"type":"Point"}
}