{
  "type": "Feature",
  "properties": {
    "gn:adm1_name":"Kumamotoken",
    "gn:adm2_name":"Utoshi",
    "gn:name":"Shinmemachi",
    "iso:country":"JP",
    "wof:name":"869-0424",
    "wof:placetype":"postalcode"
},
  "geometry": {"coordinates":[130.6506,32.678],"type":"Point"}
}