{
  "type": "Feature",
  "properties": {
    "gn:adm1_name":"Hiroshimaken",
    "gn:adm2_name":"Hiroshimashiminamiku",
    "gn:name":"Hijiyamahonmachi",
    "iso:country":"JP",
    "wof:name":"732-0816",
    "wof:placetype":"postalcode"
},
  "geometry": {"coordinates":[132.46969999999999,34.3828],"type":"Point"}
}