{
  "type": "Feature",
  "properties": {
    "gn:adm1_name":"Yamaguchiken",
    "gn:adm2_name":"Abugun'Atouchou",
    "gn:name":"Tokusakami",
    "iso:country":"JP",
    "wof:name":"759-1511",
    "wof:placetype":"postalcode"
},
  "geometry": {"coordinates":[131.74979999999999,34.4152],"type":"Point"}
}