{
  "type": "Feature",
  "properties": {
    "gn:adm1_name":"Naraken",
    "gn:adm2_name":"Yamatokooriyamashi",
    "gn:name":"Kamimitsuhashichou",
    "iso:country":"JP",
    "wof:name":"639-1102",
    "wof:placetype":"postalcode"
},
  "geometry": {"coordinates":[135.81209999999999,34.6458],"type":"Point"}
}