{
  "type": "Feature",
  "properties": {
    "gn:adm1_name":"Toyamaken",
    "gn:adm2_name":"Nakaniikawaguntateyamamachi",
    "gn:name":"Gohyakukoku",
    "iso:country":"JP",
    "wof:name":"930-0214",
    "wof:placetype":"postalcode"
},
  "geometry": {"coordinates":[137.31729999999999,36.6636],"type":"Point"}
}