{
  "type": "Feature",
  "properties": {
    "gn:adm1_name":"Naraken",
    "gn:adm2_name":"Narashi",
    "gn:name":"Okukomorichou",
    "iso:country":"JP",
    "wof:name":"630-8235",
    "wof:placetype":"postalcode"
},
  "geometry": {"coordinates":[135.8246,34.6804],"type":"Point"}
}