{
  "type": "Feature",
  "properties": {
    "gn:adm1_name":"Kagawaken",
    "gn:adm2_name":"Takamatsushi",
    "gn:name":"Yasakamachi",
    "iso:country":"JP",
    "wof:name":"760-0049",
    "wof:placetype":"postalcode"
},
  "geometry": {"coordinates":[134.05369999999999,34.34],"type":"Point"}
}