{
  "type": "Feature",
  "properties": {
    "gn:adm1_name":"Chibaken",
    "gn:adm2_name":"Kimitsushi",
    "gn:name":"Hirayama",
    "iso:country":"JP",
    "wof:name":"292-0502",
    "wof:placetype":"postalcode"
},
  "geometry": {"coordinates":[140.0675,35.2733],"type":"Point"}
}