{
  "type": "Feature",
  "properties": {
    "gn:adm1_name":"Oosakafu",
    "gn:adm2_name":"Oosakasayamashi",
    "gn:name":"Oononishi",
    "iso:country":"JP",
    "wof:name":"589-0016",
    "wof:placetype":"postalcode"
},
  "geometry": {"coordinates":[135.5403,34.4709],"type":"Point"}
}