{
  "type": "Feature",
  "properties": {
    "gn:adm1_name":"Fukuokaken",
    "gn:adm2_name":"Kitakyuushuushiwakamatsuku",
    "gn:name":"Takasuminami",
    "iso:country":"JP",
    "wof:name":"808-0145",
    "wof:placetype":"postalcode"
},
  "geometry": {"coordinates":[130.6918,33.8869],"type":"Point"}
}