{
  "type": "Feature",
  "properties": {
    "gn:adm1_name":"Kyoutofu",
    "gn:adm2_name":"Kyoutoshisakyouku",
    "gn:name":"Daimonjichou",
    "iso:country":"JP",
    "wof:name":"606-8382",
    "wof:placetype":"postalcode"
},
  "geometry": {"coordinates":[135.77330000000001,35.0145],"type":"Point"}
}