{
  "type": "Feature",
  "properties": {
    "gn:adm1_name":"Kumamotoken",
    "gn:adm2_name":"Minamatashi",
    "gn:name":"Ichiwatase",
    "iso:country":"JP",
    "wof:name":"867-0172",
    "wof:placetype":"postalcode"
},
  "geometry": {"coordinates":[130.4701,32.1764],"type":"Point"}
}