{
  "type": "Feature",
  "properties": {
    "gn:adm1_name":"Naraken",
    "gn:adm2_name":"Ikomashi",
    "gn:name":"Asukanominami",
    "iso:country":"JP",
    "wof:name":"630-0133",
    "wof:placetype":"postalcode"
},
  "geometry": {"coordinates":[135.71979999999999,34.7098],"type":"Point"}
}