{
  "type": "Feature",
  "properties": {
    "gn:adm1_name":"Naraken",
    "gn:adm2_name":"Yamatokooriyamashi",
    "gn:name":"Yanagi(Chou)",
    "iso:country":"JP",
    "wof:name":"639-1134",
    "wof:placetype":"postalcode"
},
  "geometry": {"coordinates":[135.78299999999999,34.645],"type":"Point"}
}