{
  "type": "Feature",
  "properties": {
    "gn:adm1_name":"Hyougoken",
    "gn:adm2_name":"Akougunkamigoorichou",
    "gn:name":"Kuribara",
    "iso:country":"JP",
    "wof:name":"678-1242",
    "wof:placetype":"postalcode"
},
  "geometry": {"coordinates":[134.3186,34.8593],"type":"Point"}
}