{
  "type": "Feature",
  "properties": {
    "gn:adm1_name":"Shimaneken",
    "gn:adm2_name":"Yatsukagunhigashiizumochou",
    "gn:name":"Imamiya",
    "iso:country":"JP",
    "wof:name":"699-0107",
    "wof:placetype":"postalcode"
},
  "geometry": {"coordinates":[133.11349999999999,35.4279],"type":"Point"}
}