{
  "type": "Feature",
  "properties": {
    "gn:adm1_name":"Miyagiken",
    "gn:adm2_name":"Kattagunshichikashukumachi",
    "gn:name":"Kokagosawa",
    "iso:country":"JP",
    "wof:name":"989-0634",
    "wof:placetype":"postalcode"
},
  "geometry": {"coordinates":[140.33160000000001,38.006],"type":"Point"}
}