{
  "type": "Feature",
  "properties": {
    "gn:adm1_name":"Naganoken",
    "gn:adm2_name":"Shimotakaigunnozawaonsenmura",
    "gn:name":"Mushou",
    "iso:country":"JP",
    "wof:name":"389-2613",
    "wof:placetype":"postalcode"
},
  "geometry": {"coordinates":[138.44640000000001,36.9543],"type":"Point"}
}