{
  "type": "Feature",
  "properties": {
    "gn:adm1_name":"Tottoriken",
    "gn:adm2_name":"Saihakugunsaihakuchou",
    "gn:name":"Hara",
    "iso:country":"JP",
    "wof:name":"683-0362",
    "wof:placetype":"postalcode"
},
  "geometry": {"coordinates":[133.3227,35.3534],"type":"Point"}
}