{
  "type": "Feature",
  "properties": {
    "gn:adm1_name":"Ehimeken",
    "gn:adm2_name":"Uwajimashi",
    "gn:name":"Takagushi",
    "iso:country":"JP",
    "wof:name":"798-0020",
    "wof:placetype":"postalcode"
},
  "geometry": {"coordinates":[132.5685,33.2539],"type":"Point"}
}