{
  "type": "Feature",
  "properties": {
    "gn:adm1_name":"Naraken",
    "gn:adm2_name":"Ikomagun'Ikarugachou",
    "gn:name":"Meyasu",
    "iso:country":"JP",
    "wof:name":"636-0132",
    "wof:placetype":"postalcode"
},
  "geometry": {"coordinates":[135.7379,34.595],"type":"Point"}
}