{
  "type": "Feature",
  "properties": {
    "gn:adm1_name":"Ishikawaken",
    "gn:adm2_name":"Wajimashi",
    "gn:name":"Nafunemachi",
    "iso:country":"JP",
    "wof:name":"928-0254",
    "wof:placetype":"postalcode"
},
  "geometry": {"coordinates":[137.0206,37.431],"type":"Point"}
}