{
  "type": "Feature",
  "properties": {
    "gn:adm1_name":"Chibaken",
    "gn:adm2_name":"Katorigunyamadamachi",
    "gn:name":"Ogawa",
    "iso:country":"JP",
    "wof:name":"289-0423",
    "wof:placetype":"postalcode"
},
  "geometry": {"coordinates":[140.56139999999999,35.7615],"type":"Point"}
}