{
  "type": "Feature",
  "properties": {
    "gn:adm1_name":"Kumamotoken",
    "gn:adm2_name":"Kamimashikigunkousamachi",
    "gn:name":"Nakayokota",
    "iso:country":"JP",
    "wof:name":"861-4623",
    "wof:placetype":"postalcode"
},
  "geometry": {"coordinates":[130.82310000000001,32.6701],"type":"Point"}
}