{
  "type": "Feature",
  "properties": {
    "gn:adm1_name":"Fukuokaken",
    "gn:adm2_name":"Yamegunhirokawamachi",
    "gn:name":"Hirokawa",
    "iso:country":"JP",
    "wof:name":"834-0121",
    "wof:placetype":"postalcode"
},
  "geometry": {"coordinates":[130.52940000000001,33.2431],"type":"Point"}
}