{
  "type": "Feature",
  "properties": {
    "gn:adm1_name":"Gunmaken",
    "gn:adm2_name":"Ouragun'Ooizumimachi",
    "gn:name":"Sakada",
    "iso:country":"JP",
    "wof:name":"370-0532",
    "wof:placetype":"postalcode"
},
  "geometry": {"coordinates":[139.40260000000001,36.2588],"type":"Point"}
}