{
  "type": "Feature",
  "properties": {
    "gn:adm1_name":"Tokushimaken",
    "gn:adm2_name":"Narutoshi",
    "gn:name":"Narutochoutosadomariura",
    "iso:country":"JP",
    "wof:name":"772-0053",
    "wof:placetype":"postalcode"
},
  "geometry": {"coordinates":[134.62559999999999,34.2047],"type":"Point"}
}