{
  "type": "Feature",
  "properties": {
    "gn:adm1_name":"Fukuokaken",
    "gn:adm2_name":"Itoshimagunnijoumachi",
    "gn:name":"Masue",
    "iso:country":"JP",
    "wof:name":"819-1613",
    "wof:placetype":"postalcode"
},
  "geometry": {"coordinates":[130.14250000000001,33.5267],"type":"Point"}
}