{
  "type": "Feature",
  "properties": {
    "gn:adm1_name":"Hiroshimaken",
    "gn:adm2_name":"Hiroshimashihigashiku",
    "gn:name":"Hesakakurumegi",
    "iso:country":"JP",
    "wof:name":"732-0008",
    "wof:placetype":"postalcode"
},
  "geometry": {"coordinates":[132.4796,34.4324],"type":"Point"}
}