{
  "type": "Feature",
  "properties": {
    "gn:adm1_name":"Saitamaken",
    "gn:adm2_name":"Kasukabeshi",
    "gn:name":"Bingohigashi",
    "iso:country":"JP",
    "wof:name":"344-0032",
    "wof:placetype":"postalcode"
},
  "geometry": {"coordinates":[139.77180000000001,35.9569],"type":"Point"}
}