{
  "type": "Feature",
  "properties": {
    "gn:adm1_name":"Tokushimaken",
    "gn:adm2_name":"Itanogunkitajimachou",
    "gn:name":"Ejiri",
    "iso:country":"JP",
    "wof:name":"771-0205",
    "wof:placetype":"postalcode"
},
  "geometry": {"coordinates":[134.5498,34.1217],"type":"Point"}
}