{
  "type": "Feature",
  "properties": {
    "gn:adm1_name":"Kyoutofu",
    "gn:adm2_name":"Miyadushi",
    "gn:name":"Nanbano",
    "iso:country":"JP",
    "wof:name":"629-2243",
    "wof:placetype":"postalcode"
},
  "geometry": {"coordinates":[135.20269999999999,35.5854],"type":"Point"}
}