{
  "type": "Feature",
  "properties": {
    "gn:adm1_name":"Naraken",
    "gn:adm2_name":"Kitakatsuragigunshinjouchou",
    "gn:name":"Shimura",
    "iso:country":"JP",
    "wof:name":"639-2121",
    "wof:placetype":"postalcode"
},
  "geometry": {"coordinates":[135.74639999999999,34.4773],"type":"Point"}
}