{
  "type": "Feature",
  "properties": {
    "gn:adm1_name":"Hyougoken",
    "gn:adm2_name":"Mikishi",
    "gn:name":"Jiyuugaokahonmachi",
    "iso:country":"JP",
    "wof:name":"673-0424",
    "wof:placetype":"postalcode"
},
  "geometry": {"coordinates":[135.00630000000001,34.7896],"type":"Point"}
}