{
  "type": "Feature",
  "properties": {
    "gn:adm1_name":"Okayamaken",
    "gn:adm2_name":"Tsuyamashi",
    "gn:name":"Togawamachi",
    "iso:country":"JP",
    "wof:name":"708-0037",
    "wof:placetype":"postalcode"
},
  "geometry": {"coordinates":[133.999,35.0595],"type":"Point"}
}