{
  "type": "Feature",
  "properties": {
    "gn:adm1_name":"Kyoutofu",
    "gn:adm2_name":"Kyoutoshihigashiyamaku",
    "gn:name":"Nushiyachou",
    "iso:country":"JP",
    "wof:name":"605-0934",
    "wof:placetype":"postalcode"
},
  "geometry": {"coordinates":[135.77029999999999,34.9906],"type":"Point"}
}