{
  "type": "Feature",
  "properties": {
    "gn:adm1_name":"Tochigiken",
    "gn:adm2_name":"Utsunomiyashi",
    "gn:name":"Wakamatsuhara",
    "iso:country":"JP",
    "wof:name":"321-0139",
    "wof:placetype":"postalcode"
},
  "geometry": {"coordinates":[139.86660000000001,36.5016],"type":"Point"}
}