{
  "type": "Feature",
  "properties": {
    "gn:adm1_name":"Ibarakiken",
    "gn:adm2_name":"Makabegun'Akenomachi",
    "gn:name":"Teraueno",
    "iso:country":"JP",
    "wof:name":"300-4525",
    "wof:placetype":"postalcode"
},
  "geometry": {"coordinates":[140.0343,36.2256],"type":"Point"}
}