{
  "type": "Feature",
  "properties": {
    "gn:adm1_name":"Kanagawaken",
    "gn:adm2_name":"Kawasakishikawasakiku",
    "gn:name":"Asada",
    "iso:country":"JP",
    "wof:name":"210-0847",
    "wof:placetype":"postalcode"
},
  "geometry": {"coordinates":[139.70160000000001,35.5069],"type":"Point"}
}