{
  "type": "Feature",
  "properties": {
    "gn:adm1_name":"Tochigiken",
    "gn:adm2_name":"Kawachigunkawachimachi",
    "gn:name":"Nagamine",
    "iso:country":"JP",
    "wof:name":"329-1107",
    "wof:placetype":"postalcode"
},
  "geometry": {"coordinates":[139.92760000000001,36.6424],"type":"Point"}
}