{
  "type": "Feature",
  "properties": {
    "gn:adm1_name":"Aichiken",
    "gn:adm2_name":"Nagoyashishouwaku",
    "gn:name":"Kitayamahonmachi",
    "iso:country":"JP",
    "wof:name":"466-0016",
    "wof:placetype":"postalcode"
},
  "geometry": {"coordinates":[136.92760000000001,35.1538],"type":"Point"}
}