{
  "type": "Feature",
  "properties": {
    "gn:adm1_name":"Mieken",
    "gn:adm2_name":"Tsushi",
    "gn:name":"Kamibezaichou",
    "iso:country":"JP",
    "wof:name":"514-0806",
    "wof:placetype":"postalcode"
},
  "geometry": {"coordinates":[136.5094,34.7032],"type":"Point"}
}