{
  "type": "Feature",
  "properties": {
    "gn:adm1_name":"Chibaken",
    "gn:adm2_name":"Kimitsushi",
    "gn:name":"Kaminitta",
    "iso:country":"JP",
    "wof:name":"292-0452",
    "wof:placetype":"postalcode"
},
  "geometry": {"coordinates":[140.0642,35.3155],"type":"Point"}
}