{
  "type": "Feature",
  "properties": {
    "gn:adm1_name":"Aichiken",
    "gn:adm2_name":"Nagoyashinishiku",
    "gn:name":"Enmeichou",
    "iso:country":"JP",
    "wof:name":"452-0831",
    "wof:placetype":"postalcode"
},
  "geometry": {"coordinates":[136.8725,35.2291],"type":"Point"}
}