{
  "type": "Feature",
  "properties": {
    "gn:adm1_name":"Tottoriken",
    "gn:adm2_name":"Saihakugundaisenchou",
    "gn:name":"Hiragi",
    "iso:country":"JP",
    "wof:name":"689-3304",
    "wof:placetype":"postalcode"
},
  "geometry": {"coordinates":[133.47190000000001,35.474],"type":"Point"}
}