{
  "type": "Feature",
  "properties": {
    "gn:adm1_name":"Niigataken",
    "gn:adm2_name":"Jouetsushi",
    "gn:name":"Honshinbo",
    "iso:country":"JP",
    "wof:name":"943-0123",
    "wof:placetype":"postalcode"
},
  "geometry": {"coordinates":[138.29849999999999,37.1058],"type":"Point"}
}