{
  "type": "Feature",
  "properties": {
    "gn:adm1_name":"Hyougoken",
    "gn:adm2_name":"Toyookashi",
    "gn:name":"Chuuoumachi",
    "iso:country":"JP",
    "wof:name":"668-0033",
    "wof:placetype":"postalcode"
},
  "geometry": {"coordinates":[134.82149999999999,35.5436],"type":"Point"}
}