{
  "type": "Feature",
  "properties": {
    "gn:adm1_name":"Yamanashiken",
    "gn:adm2_name":"Minamiarupusushi",
    "gn:name":"Doudou",
    "iso:country":"JP",
    "wof:name":"400-0214",
    "wof:placetype":"postalcode"
},
  "geometry": {"coordinates":[138.46449999999999,35.6564],"type":"Point"}
}