{
  "type": "Feature",
  "properties": {
    "gn:adm1_name":"Shizuokaken",
    "gn:adm2_name":"Shizuokashi",
    "gn:name":"Kawanabechou",
    "iso:country":"JP",
    "wof:name":"420-0043",
    "wof:placetype":"postalcode"
},
  "geometry": {"coordinates":[138.37979999999999,34.9684],"type":"Point"}
}