{
  "type": "Feature",
  "properties": {
    "gn:adm1_name":"Fukuiken",
    "gn:adm2_name":"Fukuishi",
    "gn:name":"Doujimachou",
    "iso:country":"JP",
    "wof:name":"910-0818",
    "wof:placetype":"postalcode"
},
  "geometry": {"coordinates":[136.25960000000001,36.0935],"type":"Point"}
}