{
  "type": "Feature",
  "properties": {
    "gn:adm1_name":"Kanagawaken",
    "gn:adm2_name":"Yokohamashiasahiku",
    "gn:name":"Nakazawa",
    "iso:country":"JP",
    "wof:name":"241-0814",
    "wof:placetype":"postalcode"
},
  "geometry": {"coordinates":[139.5256,35.4715],"type":"Point"}
}