{
  "type": "Feature",
  "properties": {
    "gn:adm1_name":"Ishikawaken",
    "gn:adm2_name":"Kanazawashi",
    "gn:name":"Wakamiya",
    "iso:country":"JP",
    "wof:name":"920-0054",
    "wof:placetype":"postalcode"
},
  "geometry": {"coordinates":[136.6317,36.5746],"type":"Point"}
}