{
  "type": "Feature",
  "properties": {
    "gn:adm1_name":"Aichiken",
    "gn:adm2_name":"Kitashitaragunshitarachou",
    "gn:name":"Nagae",
    "iso:country":"JP",
    "wof:name":"441-2312",
    "wof:placetype":"postalcode"
},
  "geometry": {"coordinates":[137.59649999999999,35.1113],"type":"Point"}
}