{
  "type": "Feature",
  "properties": {
    "gn:adm1_name":"Gifuken",
    "gn:adm2_name":"Kanishi",
    "gn:name":"Kakishita",
    "iso:country":"JP",
    "wof:name":"509-0233",
    "wof:placetype":"postalcode"
},
  "geometry": {"coordinates":[137.10230000000001,35.3974],"type":"Point"}
}