{
  "type": "Feature",
  "properties": {
    "gn:adm1_name":"Chibaken",
    "gn:adm2_name":"Naritashi",
    "gn:name":"Honjou",
    "iso:country":"JP",
    "wof:name":"286-0114",
    "wof:placetype":"postalcode"
},
  "geometry": {"coordinates":[140.3699,35.7397],"type":"Point"}
}