{
  "type": "Feature",
  "properties": {
    "gn:adm1_name":"Saitamaken",
    "gn:adm2_name":"Kodamagunkamiizumimura",
    "gn:name":"Kamiaguhara",
    "iso:country":"JP",
    "wof:name":"367-0312",
    "wof:placetype":"postalcode"
},
  "geometry": {"coordinates":[139.09440000000001,36.2047],"type":"Point"}
}