{
  "type": "Feature",
  "properties": {
    "gn:adm1_name":"Kyoutofu",
    "gn:adm2_name":"Kyoutoshihigashiyamaku",
    "gn:name":"Ishibashichou",
    "iso:country":"JP",
    "wof:name":"605-0066",
    "wof:placetype":"postalcode"
},
  "geometry": {"coordinates":[135.77760000000001,35.0069],"type":"Point"}
}