{
  "type": "Feature",
  "properties": {
    "gn:adm1_name":"Aichiken",
    "gn:adm2_name":"Kasugaishi",
    "gn:name":"Nishiyamachou",
    "iso:country":"JP",
    "wof:name":"486-0803",
    "wof:placetype":"postalcode"
},
  "geometry": {"coordinates":[136.9752,35.2756],"type":"Point"}
}