{
  "type": "Feature",
  "properties": {
    "gn:adm1_name":"Fukuiken",
    "gn:adm2_name":"Fukuishi",
    "gn:name":"Shihiguchi",
    "iso:country":"JP",
    "wof:name":"910-0845",
    "wof:placetype":"postalcode"
},
  "geometry": {"coordinates":[136.2364,36.0711],"type":"Point"}
}