{
  "type": "Feature",
  "properties": {
    "gn:adm1_name":"Hiroshimaken",
    "gn:adm2_name":"Onomichishi",
    "gn:name":"Kinoshouchouichibara",
    "iso:country":"JP",
    "wof:name":"722-0233",
    "wof:placetype":"postalcode"
},
  "geometry": {"coordinates":[133.1739,34.4727],"type":"Point"}
}