{
  "type": "Feature",
  "properties": {
    "gn:adm1_name":"Miyagiken",
    "gn:adm2_name":"Sendaishiizumiku",
    "gn:name":"Kamo",
    "iso:country":"JP",
    "wof:name":"981-3122",
    "wof:placetype":"postalcode"
},
  "geometry": {"coordinates":[140.8544,38.3146],"type":"Point"}
}