{
  "type": "Feature",
  "properties": {
    "gn:adm1_name":"Oosakafu",
    "gn:adm2_name":"Kadomashi",
    "gn:name":"Kuwazai",
    "iso:country":"JP",
    "wof:name":"571-0035",
    "wof:placetype":"postalcode"
},
  "geometry": {"coordinates":[135.5899,34.7221],"type":"Point"}
}