{
  "type": "Feature",
  "properties": {
    "gn:adm1_name":"Kyoutofu",
    "gn:adm2_name":"Sourakugunwadukachou",
    "gn:name":"Kamatsuka",
    "iso:country":"JP",
    "wof:name":"619-1212",
    "wof:placetype":"postalcode"
},
  "geometry": {"coordinates":[135.90710000000001,34.7969],"type":"Point"}
}