{
  "type": "Feature",
  "properties": {
    "gn:adm1_name":"Chibaken",
    "gn:adm2_name":"Funabashishi",
    "gn:name":"Yakigaya",
    "iso:country":"JP",
    "wof:name":"274-0802",
    "wof:placetype":"postalcode"
},
  "geometry": {"coordinates":[140.03129999999999,35.7625],"type":"Point"}
}