{
  "type": "Feature",
  "properties": {
    "gn:adm1_name":"Gifuken",
    "gn:adm2_name":"Gujougunyamatochou",
    "gn:name":"Maki",
    "iso:country":"JP",
    "wof:name":"501-4608",
    "wof:placetype":"postalcode"
},
  "geometry": {"coordinates":[136.9221,35.8114],"type":"Point"}
}