{
  "type": "Feature",
  "properties": {
    "gn:adm1_name":"Toyamaken",
    "gn:adm2_name":"Toyamashi",
    "gn:name":"Sengokumachi",
    "iso:country":"JP",
    "wof:name":"930-0066",
    "wof:placetype":"postalcode"
},
  "geometry": {"coordinates":[137.21019999999999,36.6855],"type":"Point"}
}