{
  "type": "Feature",
  "properties": {
    "gn:adm1_name":"Kumamotoken",
    "gn:adm2_name":"Shimomashikigunchuuoumachi",
    "gn:name":"Nagaono",
    "iso:country":"JP",
    "wof:name":"861-4422",
    "wof:placetype":"postalcode"
},
  "geometry": {"coordinates":[130.8092,32.6154],"type":"Point"}
}