{
  "type": "Feature",
  "properties": {
    "gn:adm1_name":"Yamaguchiken",
    "gn:adm2_name":"Kumagegunyamatochou",
    "gn:name":"Miwa",
    "iso:country":"JP",
    "wof:name":"743-0102",
    "wof:placetype":"postalcode"
},
  "geometry": {"coordinates":[131.9991,33.976],"type":"Point"}
}