{
  "type": "Feature",
  "properties": {
    "gn:adm1_name":"Okayamaken",
    "gn:adm2_name":"Kurashikishi",
    "gn:name":"Mizushimaminamimizuhochou",
    "iso:country":"JP",
    "wof:name":"712-8026",
    "wof:placetype":"postalcode"
},
  "geometry": {"coordinates":[133.74039999999999,34.5446],"type":"Point"}
}