{
  "type": "Feature",
  "properties": {
    "gn:adm1_name":"Aichiken",
    "gn:adm2_name":"Setoshi",
    "gn:name":"Yodokochou",
    "iso:country":"JP",
    "wof:name":"489-0002",
    "wof:placetype":"postalcode"
},
  "geometry": {"coordinates":[137.1122,35.2682],"type":"Point"}
}