{
  "type": "Feature",
  "properties": {
    "gn:adm1_name":"Hyougoken",
    "gn:adm2_name":"Mikatagunhamasakachou",
    "gn:name":"Kutani",
    "iso:country":"JP",
    "wof:name":"669-6721",
    "wof:placetype":"postalcode"
},
  "geometry": {"coordinates":[134.51910000000001,35.6266],"type":"Point"}
}