{
  "type": "Feature",
  "properties": {
    "gn:adm1_name":"Aichiken",
    "gn:adm2_name":"Owariasahishi",
    "gn:name":"Shiromaechoushiromae",
    "iso:country":"JP",
    "wof:name":"488-0861",
    "wof:placetype":"postalcode"
},
  "geometry": {"coordinates":[137.02680000000001,35.2167],"type":"Point"}
}