{
  "type": "Feature",
  "properties": {
    "gn:adm1_name":"Hiroshimaken",
    "gn:adm2_name":"Hiroshimashiminamiku",
    "gn:name":"Kitaookouchou",
    "iso:country":"JP",
    "wof:name":"734-0042",
    "wof:placetype":"postalcode"
},
  "geometry": {"coordinates":[132.4811,34.3724],"type":"Point"}
}