{
  "type": "Feature",
  "properties": {
    "gn:adm1_name":"Mieken",
    "gn:adm2_name":"Suzukashi",
    "gn:name":"Jishimachi",
    "iso:country":"JP",
    "wof:name":"513-0821",
    "wof:placetype":"postalcode"
},
  "geometry": {"coordinates":[136.56729999999999,34.8692],"type":"Point"}
}