{
  "type": "Feature",
  "properties": {
    "gn:adm1_name":"Aichiken",
    "gn:adm2_name":"Nagoyashichikusaku",
    "gn:name":"Kouyouchou",
    "iso:country":"JP",
    "wof:name":"464-0062",
    "wof:placetype":"postalcode"
},
  "geometry": {"coordinates":[136.94999999999999,35.1705],"type":"Point"}
}