{
  "type": "Feature",
  "properties": {
    "gn:adm1_name":"Yamagataken",
    "gn:adm2_name":"Sakatashi",
    "gn:name":"Makisone",
    "iso:country":"JP",
    "wof:name":"999-8166",
    "wof:placetype":"postalcode"
},
  "geometry": {"coordinates":[139.8742,38.9358],"type":"Point"}
}