{
  "type": "Feature",
  "properties": {
    "gn:adm1_name":"Niigataken",
    "gn:adm2_name":"Nishikubikigunnoumachi",
    "gn:name":"Sakuragi",
    "iso:country":"JP",
    "wof:name":"949-1354",
    "wof:placetype":"postalcode"
},
  "geometry": {"coordinates":[137.9846,37.0983],"type":"Point"}
}