{
  "type": "Feature",
  "properties": {
    "gn:adm1_name":"Ooitaken",
    "gn:adm2_name":"Usagun'Ajimumachi",
    "gn:name":"Tounoo",
    "iso:country":"JP",
    "wof:name":"872-0664",
    "wof:placetype":"postalcode"
},
  "geometry": {"coordinates":[131.40719999999999,33.407],"type":"Point"}
}