{
  "type": "Feature",
  "properties": {
    "gn:adm1_name":"Saitamaken",
    "gn:adm2_name":"Gyoudashi",
    "gn:name":"Nishishinmachi",
    "iso:country":"JP",
    "wof:name":"361-0042",
    "wof:placetype":"postalcode"
},
  "geometry": {"coordinates":[139.4393,36.1247],"type":"Point"}
}