{
  "type": "Feature",
  "properties": {
    "gn:adm1_name":"Okayamaken",
    "gn:adm2_name":"Takahashishi",
    "gn:name":"Yokochou",
    "iso:country":"JP",
    "wof:name":"716-0046",
    "wof:placetype":"postalcode"
},
  "geometry": {"coordinates":[133.6112,34.7869],"type":"Point"}
}