{
  "type": "Feature",
  "properties": {
    "gn:adm1_name":"Gunmaken",
    "gn:adm2_name":"Sawaguntamamuramachi",
    "gn:name":"Iiduka",
    "iso:country":"JP",
    "wof:name":"370-1102",
    "wof:placetype":"postalcode"
},
  "geometry": {"coordinates":[139.1326,36.3299],"type":"Point"}
}