{
  "type": "Feature",
  "properties": {
    "gn:adm1_name":"Kanagawaken",
    "gn:adm2_name":"Aikougunkiyokawamura",
    "gn:name":"Susugaya(Sonota)",
    "iso:country":"JP",
    "wof:name":"243-0112",
    "wof:placetype":"postalcode"
},
  "geometry": {"coordinates":[139.28049999999999,35.4789],"type":"Point"}
}