{
  "type": "Feature",
  "properties": {
    "gn:adm1_name":"Gifuken",
    "gn:adm2_name":"Kanishi",
    "gn:name":"Katabirashinmachi",
    "iso:country":"JP",
    "wof:name":"509-0266",
    "wof:placetype":"postalcode"
},
  "geometry": {"coordinates":[137.011,35.4034],"type":"Point"}
}