{
  "type": "Feature",
  "properties": {
    "gn:adm1_name":"Okayamaken",
    "gn:adm2_name":"Kawakamigunnariwachou",
    "gn:name":"Osaji",
    "iso:country":"JP",
    "wof:name":"716-0334",
    "wof:placetype":"postalcode"
},
  "geometry": {"coordinates":[133.46629999999999,34.8011],"type":"Point"}
}