{
  "type": "Feature",
  "properties": {
    "gn:adm1_name":"Sagaken",
    "gn:adm2_name":"Tosushi",
    "gn:name":"Gitokumachi",
    "iso:country":"JP",
    "wof:name":"841-0066",
    "wof:placetype":"postalcode"
},
  "geometry": {"coordinates":[130.49289999999999,33.3524],"type":"Point"}
}