{
  "type": "Feature",
  "properties": {
    "gn:adm1_name":"Aichiken",
    "gn:adm2_name":"Nishikasugaigunshinkawachou",
    "gn:name":"Sukaguchiekimae",
    "iso:country":"JP",
    "wof:name":"452-0912",
    "wof:placetype":"postalcode"
},
  "geometry": {"coordinates":[136.84549999999999,35.1984],"type":"Point"}
}