{
  "type": "Feature",
  "properties": {
    "gn:adm1_name":"Fukushimaken",
    "gn:adm2_name":"Yamagunshiokawamachi",
    "gn:name":"Kaichi",
    "iso:country":"JP",
    "wof:name":"969-3535",
    "wof:placetype":"postalcode"
},
  "geometry": {"coordinates":[139.85300000000001,37.6042],"type":"Point"}
}