{
  "type": "Feature",
  "properties": {
    "gn:adm1_name":"Niigataken",
    "gn:adm2_name":"Nakakubikigunyoshikawamachi",
    "gn:name":"Kaminagi",
    "iso:country":"JP",
    "wof:name":"949-3555",
    "wof:placetype":"postalcode"
},
  "geometry": {"coordinates":[138.49109999999999,37.1882],"type":"Point"}
}