{
  "type": "Feature",
  "properties": {
    "gn:adm1_name":"Kumamotoken",
    "gn:adm2_name":"Kamimashikigunmashikimachi",
    "gn:name":"Shimada",
    "iso:country":"JP",
    "wof:name":"861-2224",
    "wof:placetype":"postalcode"
},
  "geometry": {"coordinates":[130.79060000000001,32.7589],"type":"Point"}
}