{
  "type": "Feature",
  "properties": {
    "gn:adm1_name":"Tochigiken",
    "gn:adm2_name":"Utsunomiyashi",
    "gn:name":"Karinumamachi",
    "iso:country":"JP",
    "wof:name":"321-3224",
    "wof:placetype":"postalcode"
},
  "geometry": {"coordinates":[139.98589999999999,36.5726],"type":"Point"}
}