{
  "type": "Feature",
  "properties": {
    "gn:adm1_name":"Aichiken",
    "gn:adm2_name":"Inazawashi",
    "gn:name":"Okudasakaichou",
    "iso:country":"JP",
    "wof:name":"492-8232",
    "wof:placetype":"postalcode"
},
  "geometry": {"coordinates":[136.81700000000001,35.231],"type":"Point"}
}