{
  "type": "Feature",
  "properties": {
    "gn:adm1_name":"Chibaken",
    "gn:adm2_name":"Kimitsushi",
    "gn:name":"Nishibara",
    "iso:country":"JP",
    "wof:name":"292-0402",
    "wof:placetype":"postalcode"
},
  "geometry": {"coordinates":[140.0497,35.3371],"type":"Point"}
}