{
  "type": "Feature",
  "properties": {
    "gn:adm1_name":"Naraken",
    "gn:adm2_name":"Narashi",
    "gn:name":"Kyoubatejikatahigashigawachou",
    "iso:country":"JP",
    "wof:name":"630-8323",
    "wof:placetype":"postalcode"
},
  "geometry": {"coordinates":[135.82769999999999,34.6729],"type":"Point"}
}