{
  "type": "Feature",
  "properties": {
    "gn:adm1_name":"Tokushimaken",
    "gn:adm2_name":"Itanogun'Itanochou",
    "gn:name":"Matsudani",
    "iso:country":"JP",
    "wof:name":"779-0112",
    "wof:placetype":"postalcode"
},
  "geometry": {"coordinates":[134.43539999999999,34.1445],"type":"Point"}
}