{
  "type": "Feature",
  "properties": {
    "gn:adm1_name":"Miyagiken",
    "gn:adm2_name":"Kuriharaguntakashimizumachi",
    "gn:name":"Tennousawa",
    "iso:country":"JP",
    "wof:name":"987-2152",
    "wof:placetype":"postalcode"
},
  "geometry": {"coordinates":[141.00970000000001,38.639],"type":"Point"}
}