{
  "type": "Feature",
  "properties": {
    "gn:adm1_name":"Hyougoken",
    "gn:adm2_name":"Kinosakiguntakenochou",
    "gn:name":"Hayashi",
    "iso:country":"JP",
    "wof:name":"669-6227",
    "wof:placetype":"postalcode"
},
  "geometry": {"coordinates":[134.74719999999999,35.6014],"type":"Point"}
}