{
  "type": "Feature",
  "properties": {
    "gn:adm1_name":"Niigataken",
    "gn:adm2_name":"Niigatashi",
    "gn:name":"Shindoorinishi",
    "iso:country":"JP",
    "wof:name":"950-2036",
    "wof:placetype":"postalcode"
},
  "geometry": {"coordinates":[138.9486,37.8631],"type":"Point"}
}