{
  "type": "Feature",
  "properties": {
    "gn:adm1_name":"Kagawaken",
    "gn:adm2_name":"Takamatsushi",
    "gn:name":"Nakanochou",
    "iso:country":"JP",
    "wof:name":"760-0008",
    "wof:placetype":"postalcode"
},
  "geometry": {"coordinates":[134.04409999999999,34.3341],"type":"Point"}
}