{
  "type": "Feature",
  "properties": {
    "gn:adm1_name":"Tochigiken",
    "gn:adm2_name":"Ashikagashi",
    "gn:name":"Agatachou",
    "iso:country":"JP",
    "wof:name":"326-0328",
    "wof:placetype":"postalcode"
},
  "geometry": {"coordinates":[139.46360000000001,36.2865],"type":"Point"}
}