{
  "type": "Feature",
  "properties": {
    "gn:adm1_name":"Okayamaken",
    "gn:adm2_name":"Kurashikishi",
    "gn:name":"Kawanishimachi",
    "iso:country":"JP",
    "wof:name":"710-0821",
    "wof:placetype":"postalcode"
},
  "geometry": {"coordinates":[133.7646,34.5978],"type":"Point"}
}