{
  "type": "Feature",
  "properties": {
    "gn:adm1_name":"Aichiken",
    "gn:adm2_name":"Nishikasugaiguntoyoyamachou",
    "gn:name":"Ikanikeisaiganaibaai",
    "iso:country":"JP",
    "wof:name":"480-0200",
    "wof:placetype":"postalcode"
},
  "geometry": {"coordinates":[136.91319999999999,35.2461],"type":"Point"}
}