{
  "type": "Feature",
  "properties": {
    "gn:adm1_name":"Aichiken",
    "gn:adm2_name":"Kasugaishi",
    "gn:name":"Moriyamadachou",
    "iso:country":"JP",
    "wof:name":"486-0935",
    "wof:placetype":"postalcode"
},
  "geometry": {"coordinates":[136.95349999999999,35.2229],"type":"Point"}
}