{
  "type": "Feature",
  "properties": {
    "gn:adm1_name":"Ishikawaken",
    "gn:adm2_name":"Komatsushi",
    "gn:name":"Midorimachi",
    "iso:country":"JP",
    "wof:name":"923-0072",
    "wof:placetype":"postalcode"
},
  "geometry": {"coordinates":[136.52610000000001,36.3936],"type":"Point"}
}