{
  "type": "Feature",
  "properties": {
    "gn:adm1_name":"Aichiken",
    "gn:adm2_name":"Toyotashi",
    "gn:name":"Oouchichou",
    "iso:country":"JP",
    "wof:name":"444-2217",
    "wof:placetype":"postalcode"
},
  "geometry": {"coordinates":[137.23050000000001,35.055],"type":"Point"}
}