{
  "type": "Feature",
  "properties": {
    "gn:adm1_name":"Gunmaken",
    "gn:adm2_name":"Setagunmiyagimura",
    "gn:name":"Oomaeta",
    "iso:country":"JP",
    "wof:name":"371-0243",
    "wof:placetype":"postalcode"
},
  "geometry": {"coordinates":[139.18629999999999,36.4264],"type":"Point"}
}