{
  "type": "Feature",
  "properties": {
    "gn:adm1_name":"Chibaken",
    "gn:adm2_name":"Chouseigunchouseimura",
    "gn:name":"Kitamyoguchi",
    "iso:country":"JP",
    "wof:name":"299-4337",
    "wof:placetype":"postalcode"
},
  "geometry": {"coordinates":[140.33860000000001,35.411],"type":"Point"}
}