{
  "type": "Feature",
  "properties": {
    "gn:adm1_name":"Aichiken",
    "gn:adm2_name":"Inazawashi",
    "gn:name":"Hokkejichou",
    "iso:country":"JP",
    "wof:name":"492-8335",
    "wof:placetype":"postalcode"
},
  "geometry": {"coordinates":[136.767,35.2448],"type":"Point"}
}