{
  "type": "Feature",
  "properties": {
    "gn:adm1_name":"Wakayamaken",
    "gn:adm2_name":"Hidakagunminabechou",
    "gn:name":"Haneta",
    "iso:country":"JP",
    "wof:name":"645-0004",
    "wof:placetype":"postalcode"
},
  "geometry": {"coordinates":[135.32640000000001,33.7589],"type":"Point"}
}