{
  "type": "Feature",
  "properties": {
    "gn:adm1_name":"Wakayamaken",
    "gn:adm2_name":"Kaisougunshimotsuchou",
    "gn:name":"Oosaki",
    "iso:country":"JP",
    "wof:name":"649-0112",
    "wof:placetype":"postalcode"
},
  "geometry": {"coordinates":[135.13419999999999,34.1326],"type":"Point"}
}