{
  "type": "Feature",
  "properties": {
    "gn:adm1_name":"Saitamaken",
    "gn:adm2_name":"Kawagoeshi",
    "gn:name":"Kujiraishinden",
    "iso:country":"JP",
    "wof:name":"350-0809",
    "wof:placetype":"postalcode"
},
  "geometry": {"coordinates":[139.42019999999999,35.9324],"type":"Point"}
}