{
  "type": "Feature",
  "properties": {
    "gn:adm1_name":"Naganoken",
    "gn:adm2_name":"Iidashi",
    "gn:name":"Tenmachou",
    "iso:country":"JP",
    "wof:name":"395-0016",
    "wof:placetype":"postalcode"
},
  "geometry": {"coordinates":[137.82849999999999,35.5176],"type":"Point"}
}