{
  "type": "Feature",
  "properties": {
    "gn:adm1_name":"Aichiken",
    "gn:adm2_name":"Nishikasugaigunshinkawachou",
    "gn:name":"Terano",
    "iso:country":"JP",
    "wof:name":"452-0908",
    "wof:placetype":"postalcode"
},
  "geometry": {"coordinates":[136.85059999999999,35.2083],"type":"Point"}
}