{
  "type": "Feature",
  "properties": {
    "gn:adm1_name":"Gifuken",
    "gn:adm2_name":"Kakamigaharashi",
    "gn:name":"Soharasarukochou",
    "iso:country":"JP",
    "wof:name":"504-0845",
    "wof:placetype":"postalcode"
},
  "geometry": {"coordinates":[136.85599999999999,35.4105],"type":"Point"}
}