{
  "type": "Feature",
  "properties": {
    "gn:adm1_name":"Fukuokaken",
    "gn:adm2_name":"Mizumagunmidumamachi",
    "gn:name":"Tagawa",
    "iso:country":"JP",
    "wof:name":"830-0102",
    "wof:placetype":"postalcode"
},
  "geometry": {"coordinates":[130.47540000000001,33.2586],"type":"Point"}
}