{
  "type": "Feature",
  "properties": {
    "gn:adm1_name":"Kyoutofu",
    "gn:adm2_name":"Ayabeshi",
    "gn:name":"Tsukudachou",
    "iso:country":"JP",
    "wof:name":"629-1252",
    "wof:placetype":"postalcode"
},
  "geometry": {"coordinates":[135.36529999999999,35.3285],"type":"Point"}
}