{
  "type": "Feature",
  "properties": {
    "gn:adm1_name":"Aichiken",
    "gn:adm2_name":"Chiryuushi",
    "gn:name":"Kamishigeharachou",
    "iso:country":"JP",
    "wof:name":"472-0026",
    "wof:placetype":"postalcode"
},
  "geometry": {"coordinates":[137.02789999999999,34.9991],"type":"Point"}
}