{
  "type": "Feature",
  "properties": {
    "gn:adm1_name":"Mieken",
    "gn:adm2_name":"Kuwanashi",
    "gn:name":"Tonomachi",
    "iso:country":"JP",
    "wof:name":"511-0015",
    "wof:placetype":"postalcode"
},
  "geometry": {"coordinates":[136.69319999999999,35.0664],"type":"Point"}
}