{
  "type": "Feature",
  "properties": {
    "gn:adm1_name":"Fukuokaken",
    "gn:adm2_name":"Ongagun'Okagakimachi",
    "gn:name":"Kouyoudai",
    "iso:country":"JP",
    "wof:name":"811-4227",
    "wof:placetype":"postalcode"
},
  "geometry": {"coordinates":[130.62979999999999,33.8424],"type":"Point"}
}