{
  "type": "Feature",
  "properties": {
    "gn:adm1_name":"Kyoutofu",
    "gn:adm2_name":"Kyoutoshiukyouku",
    "gn:name":"Sagamizuokitagaichichou",
    "iso:country":"JP",
    "wof:name":"616-8468",
    "wof:placetype":"postalcode"
},
  "geometry": {"coordinates":[135.62370000000001,35.047],"type":"Point"}
}