{
  "type": "Feature",
  "properties": {
    "gn:adm1_name":"Ibarakiken",
    "gn:adm2_name":"Makabegun'Akenomachi",
    "gn:name":"Arita",
    "iso:country":"JP",
    "wof:name":"300-4512",
    "wof:placetype":"postalcode"
},
  "geometry": {"coordinates":[140.0557,36.2446],"type":"Point"}
}