{
  "type": "Feature",
  "properties": {
    "gn:adm1_name":"Ishikawaken",
    "gn:adm2_name":"Nanaoshi",
    "gn:name":"Matsumotochou",
    "iso:country":"JP",
    "wof:name":"926-0865",
    "wof:placetype":"postalcode"
},
  "geometry": {"coordinates":[136.95959999999999,37.0492],"type":"Point"}
}