{
  "type": "Feature",
  "properties": {
    "gn:adm1_name":"Chibaken",
    "gn:adm2_name":"Inbagunmotonomura",
    "gn:name":"Takino",
    "iso:country":"JP",
    "wof:name":"270-2329",
    "wof:placetype":"postalcode"
},
  "geometry": {"coordinates":[140.17779999999999,35.8098],"type":"Point"}
}