{
  "type": "Feature",
  "properties": {
    "gn:adm1_name":"Fukushimaken",
    "gn:adm2_name":"Aiduwakamatsushi",
    "gn:name":"Nanokamachi",
    "iso:country":"JP",
    "wof:name":"965-0044",
    "wof:placetype":"postalcode"
},
  "geometry": {"coordinates":[139.9229,37.5006],"type":"Point"}
}