{
  "type": "Feature",
  "properties": {
    "gn:adm1_name":"Kyoutofu",
    "gn:adm2_name":"Kyoutoshifushimiku",
    "gn:name":"Higashikumichou",
    "iso:country":"JP",
    "wof:name":"612-8063",
    "wof:placetype":"postalcode"
},
  "geometry": {"coordinates":[135.7611,34.9353],"type":"Point"}
}