{
  "type": "Feature",
  "properties": {
    "gn:adm1_name":"Shizuokaken",
    "gn:adm2_name":"Shizuokashi",
    "gn:name":"Maebayashi",
    "iso:country":"JP",
    "wof:name":"420-0957",
    "wof:placetype":"postalcode"
},
  "geometry": {"coordinates":[138.38079999999999,34.9994],"type":"Point"}
}