{
  "type": "Feature",
  "properties": {
    "gn:adm1_name":"Saitamaken",
    "gn:adm2_name":"Kitasaitamagunkisaimachi",
    "gn:name":"Nakanome",
    "iso:country":"JP",
    "wof:name":"347-0124",
    "wof:placetype":"postalcode"
},
  "geometry": {"coordinates":[139.55629999999999,36.094],"type":"Point"}
}