{
  "type": "Feature",
  "properties": {
    "gn:adm1_name":"Chibaken",
    "gn:adm2_name":"Sodegaurashi",
    "gn:name":"Iitomi",
    "iso:country":"JP",
    "wof:name":"299-0256",
    "wof:placetype":"postalcode"
},
  "geometry": {"coordinates":[139.98560000000001,35.4195],"type":"Point"}
}