{
  "type": "Feature",
  "properties": {
    "gn:adm1_name":"Fukuokaken",
    "gn:adm2_name":"Fukuokashinishiku",
    "gn:name":"Nishiiribe",
    "iso:country":"JP",
    "wof:name":"819-0039",
    "wof:placetype":"postalcode"
},
  "geometry": {"coordinates":[130.31909999999999,33.5178],"type":"Point"}
}