{
  "type": "Feature",
  "properties": {
    "gn:adm1_name":"Tochigiken",
    "gn:adm2_name":"Nasugunkurobanemachi",
    "gn:name":"Kurobanemukoumachi",
    "iso:country":"JP",
    "wof:name":"324-0241",
    "wof:placetype":"postalcode"
},
  "geometry": {"coordinates":[140.114,36.8703],"type":"Point"}
}