{
  "type": "Feature",
  "properties": {
    "gn:adm1_name":"Gifuken",
    "gn:adm2_name":"Gifushi",
    "gn:name":"Minamikagashima",
    "iso:country":"JP",
    "wof:name":"501-0115",
    "wof:placetype":"postalcode"
},
  "geometry": {"coordinates":[136.721,35.414],"type":"Point"}
}