{
  "type": "Feature",
  "properties": {
    "gn:adm1_name":"Kouchiken",
    "gn:adm2_name":"Tosagun'Ookawamura",
    "gn:name":"Kokitagawa",
    "iso:country":"JP",
    "wof:name":"781-3716",
    "wof:placetype":"postalcode"
},
  "geometry": {"coordinates":[133.4187,33.7942],"type":"Point"}
}