{
  "type": "Feature",
  "properties": {
    "gn:adm1_name":"Kyoutofu",
    "gn:adm2_name":"Kyoutoshiyamashinaku",
    "gn:name":"Takehanajizoujiminamichou",
    "iso:country":"JP",
    "wof:name":"607-8088",
    "wof:placetype":"postalcode"
},
  "geometry": {"coordinates":[135.81479999999999,34.987],"type":"Point"}
}