{
  "type": "Feature",
  "properties": {
    "gn:adm1_name":"Ooitaken",
    "gn:adm2_name":"Usagun'Innaimachi",
    "gn:name":"Dai",
    "iso:country":"JP",
    "wof:name":"872-0461",
    "wof:placetype":"postalcode"
},
  "geometry": {"coordinates":[131.27969999999999,33.3686],"type":"Point"}
}