{
  "type": "Feature",
  "properties": {
    "gn:adm1_name":"Aichiken",
    "gn:adm2_name":"Nagoyashiminatoku",
    "gn:name":"Houjinchou",
    "iso:country":"JP",
    "wof:name":"455-0833",
    "wof:placetype":"postalcode"
},
  "geometry": {"coordinates":[136.8433,35.0973],"type":"Point"}
}