{
  "type": "Feature",
  "properties": {
    "gn:adm1_name":"Wakayamaken",
    "gn:adm2_name":"Wakayamashi",
    "gn:name":"Nintomechou",
    "iso:country":"JP",
    "wof:name":"640-8326",
    "wof:placetype":"postalcode"
},
  "geometry": {"coordinates":[135.18530000000001,34.2263],"type":"Point"}
}