{
  "type": "Feature",
  "properties": {
    "gn:adm1_name":"Hyougoken",
    "gn:adm2_name":"Miharagunseidanchou",
    "gn:name":"Minato",
    "iso:country":"JP",
    "wof:name":"656-0332",
    "wof:placetype":"postalcode"
},
  "geometry": {"coordinates":[134.72819999999999,34.3263],"type":"Point"}
}