{
  "type": "Feature",
  "properties": {
    "gn:adm1_name":"Hyougoken",
    "gn:adm2_name":"Kawanishishi",
    "gn:name":"Hanayashiki",
    "iso:country":"JP",
    "wof:name":"666-0035",
    "wof:placetype":"postalcode"
},
  "geometry": {"coordinates":[135.4084,34.8296],"type":"Point"}
}