{
  "type": "Feature",
  "properties": {
    "gn:adm1_name":"Aichiken",
    "gn:adm2_name":"Toyoakeshi",
    "gn:name":"Futamuradai",
    "iso:country":"JP",
    "wof:name":"470-1131",
    "wof:placetype":"postalcode"
},
  "geometry": {"coordinates":[137.00710000000001,35.0637],"type":"Point"}
}