{
  "type": "Feature",
  "properties": {
    "gn:adm1_name":"Toyamaken",
    "gn:adm2_name":"Toyamashi",
    "gn:name":"Yokatanishiiwase",
    "iso:country":"JP",
    "wof:name":"930-2241",
    "wof:placetype":"postalcode"
},
  "geometry": {"coordinates":[137.20150000000001,36.758],"type":"Point"}
}