{
  "type": "Feature",
  "properties": {
    "gn:adm1_name":"Kanagawaken",
    "gn:adm2_name":"Yokosukashi",
    "gn:name":"Kaneya",
    "iso:country":"JP",
    "wof:name":"238-0034",
    "wof:placetype":"postalcode"
},
  "geometry": {"coordinates":[139.65209999999999,35.2636],"type":"Point"}
}