{
  "type": "Feature",
  "properties": {
    "gn:adm1_name":"Aichiken",
    "gn:adm2_name":"Handashi",
    "gn:name":"Hamadachou",
    "iso:country":"JP",
    "wof:name":"475-0805",
    "wof:placetype":"postalcode"
},
  "geometry": {"coordinates":[136.94489999999999,34.9032],"type":"Point"}
}