{
  "type": "Feature",
  "properties": {
    "gn:adm1_name":"Kumamotoken",
    "gn:adm2_name":"Ashikitaguntanouramachi",
    "gn:name":"Hatatou",
    "iso:country":"JP",
    "wof:name":"869-5306",
    "wof:placetype":"postalcode"
},
  "geometry": {"coordinates":[130.51150000000001,32.3863],"type":"Point"}
}