{
  "type": "Feature",
  "properties": {
    "gn:adm1_name":"Tokushimaken",
    "gn:adm2_name":"Narutoshi",
    "gn:name":"Muyachouookuwajima",
    "iso:country":"JP",
    "wof:name":"772-0011",
    "wof:placetype":"postalcode"
},
  "geometry": {"coordinates":[134.60720000000001,34.1869],"type":"Point"}
}