{
  "type": "Feature",
  "properties": {
    "gn:adm1_name":"Gifuken",
    "gn:adm2_name":"Tajimishi",
    "gn:name":"Tougenchou",
    "iso:country":"JP",
    "wof:name":"507-0844",
    "wof:placetype":"postalcode"
},
  "geometry": {"coordinates":[137.13650000000001,35.3311],"type":"Point"}
}