{
  "type": "Feature",
  "properties": {
    "gn:adm1_name":"Shigaken",
    "gn:adm2_name":"Koukagunkounanchou",
    "gn:name":"Ikeda",
    "iso:country":"JP",
    "wof:name":"520-3302",
    "wof:placetype":"postalcode"
},
  "geometry": {"coordinates":[136.19239999999999,34.9064],"type":"Point"}
}