{
  "type": "Feature",
  "properties": {
    "gn:adm1_name":"Yamagataken",
    "gn:adm2_name":"Yamagatashi",
    "gn:name":"Teppoumachi",
    "iso:country":"JP",
    "wof:name":"990-2492",
    "wof:placetype":"postalcode"
},
  "geometry": {"coordinates":[140.3322,38.2374],"type":"Point"}
}