{
  "type": "Feature",
  "properties": {
    "gn:adm1_name":"Kagawaken",
    "gn:adm2_name":"Marugameshi",
    "gn:name":"Hachibanchou",
    "iso:country":"JP",
    "wof:name":"763-0028",
    "wof:placetype":"postalcode"
},
  "geometry": {"coordinates":[133.8013,34.2833],"type":"Point"}
}