{
  "type": "Feature",
  "properties": {
    "gn:adm1_name":"Hiroshimaken",
    "gn:adm2_name":"Kureshi",
    "gn:name":"Agaminami",
    "iso:country":"JP",
    "wof:name":"737-0004",
    "wof:placetype":"postalcode"
},
  "geometry": {"coordinates":[132.58949999999999,34.223],"type":"Point"}
}