{
  "type": "Feature",
  "properties": {
    "gn:adm1_name":"Shimaneken",
    "gn:adm2_name":"Yatsukagunshinjichou",
    "gn:name":"Kamikimachi",
    "iso:country":"JP",
    "wof:name":"699-0405",
    "wof:placetype":"postalcode"
},
  "geometry": {"coordinates":[132.9649,35.3946],"type":"Point"}
}