{
  "type": "Feature",
  "properties": {
    "gn:adm1_name":"Shimaneken",
    "gn:adm2_name":"Hiratashi",
    "gn:name":"Okadachou",
    "iso:country":"JP",
    "wof:name":"691-0063",
    "wof:placetype":"postalcode"
},
  "geometry": {"coordinates":[132.83500000000001,35.4569],"type":"Point"}
}