{
  "type": "Feature",
  "properties": {
    "gn:adm1_name":"Kouchiken",
    "gn:adm2_name":"Akishi",
    "gn:name":"Ananaiotsu",
    "iso:country":"JP",
    "wof:name":"784-0032",
    "wof:placetype":"postalcode"
},
  "geometry": {"coordinates":[133.86709999999999,33.5067],"type":"Point"}
}