{
  "type": "Feature",
  "properties": {
    "gn:adm1_name":"Chibaken",
    "gn:adm2_name":"Yachimatashi",
    "gn:name":"Midoridai",
    "iso:country":"JP",
    "wof:name":"289-1145",
    "wof:placetype":"postalcode"
},
  "geometry": {"coordinates":[140.28469999999999,35.6823],"type":"Point"}
}