{
  "type": "Feature",
  "properties": {
    "gn:adm1_name":"Shizuokaken",
    "gn:adm2_name":"Numadushi",
    "gn:name":"Ootsuka",
    "iso:country":"JP",
    "wof:name":"410-0306",
    "wof:placetype":"postalcode"
},
  "geometry": {"coordinates":[138.80789999999999,35.1226],"type":"Point"}
}