{
  "type": "Feature",
  "properties": {
    "gn:adm1_name":"Oosakafu",
    "gn:adm2_name":"Oosakashitaishouku",
    "gn:name":"Minamiokajima",
    "iso:country":"JP",
    "wof:name":"551-0021",
    "wof:placetype":"postalcode"
},
  "geometry": {"coordinates":[135.4692,34.637],"type":"Point"}
}