{
  "type": "Feature",
  "properties": {
    "gn:adm1_name":"Fukuokaken",
    "gn:adm2_name":"Yukuhashishi",
    "gn:name":"Kamikenji",
    "iso:country":"JP",
    "wof:name":"824-0052",
    "wof:placetype":"postalcode"
},
  "geometry": {"coordinates":[130.95050000000001,33.7176],"type":"Point"}
}