{
  "type": "Feature",
  "properties": {
    "gn:adm1_name":"Yamagataken",
    "gn:adm2_name":"Higashitagawagun'Amarumemachi",
    "gn:name":"Fukushima",
    "iso:country":"JP",
    "wof:name":"999-7736",
    "wof:placetype":"postalcode"
},
  "geometry": {"coordinates":[139.94220000000001,38.7977],"type":"Point"}
}