{
  "type": "Feature",
  "properties": {
    "gn:adm1_name":"Mieken",
    "gn:adm2_name":"Kameyamashi",
    "gn:name":"Mizukigaoka",
    "iso:country":"JP",
    "wof:name":"519-0181",
    "wof:placetype":"postalcode"
},
  "geometry": {"coordinates":[136.4691,34.877],"type":"Point"}
}