{
  "type": "Feature",
  "properties": {
    "gn:adm1_name":"Niigataken",
    "gn:adm2_name":"Nakakubikigunsanwamura",
    "gn:name":"Okada",
    "iso:country":"JP",
    "wof:name":"943-0305",
    "wof:placetype":"postalcode"
},
  "geometry": {"coordinates":[138.38,37.1257],"type":"Point"}
}