{
  "type": "Feature",
  "properties": {
    "gn:adm1_name":"Niigataken",
    "gn:adm2_name":"Itoigawashi",
    "gn:name":"Nakabayashi",
    "iso:country":"JP",
    "wof:name":"949-1204",
    "wof:placetype":"postalcode"
},
  "geometry": {"coordinates":[137.976,37.0307],"type":"Point"}
}