{
  "type": "Feature",
  "properties": {
    "gn:adm1_name":"Tokushimaken",
    "gn:adm2_name":"Ananshi",
    "gn:name":"Yoshiichou",
    "iso:country":"JP",
    "wof:name":"771-5172",
    "wof:placetype":"postalcode"
},
  "geometry": {"coordinates":[134.56180000000001,33.9205],"type":"Point"}
}