{
  "type": "Feature",
  "properties": {
    "gn:adm1_name":"Nagasakiken",
    "gn:adm2_name":"Hiradoshi",
    "gn:name":"Iirachou",
    "iso:country":"JP",
    "wof:name":"859-5382",
    "wof:placetype":"postalcode"
},
  "geometry": {"coordinates":[129.428,33.283],"type":"Point"}
}