{
  "type": "Feature",
  "properties": {
    "gn:adm1_name":"Okayamaken",
    "gn:adm2_name":"Mitsugunmitsuchou",
    "gn:name":"Kanagawa",
    "iso:country":"JP",
    "wof:name":"709-2133",
    "wof:placetype":"postalcode"
},
  "geometry": {"coordinates":[133.9331,34.7963],"type":"Point"}
}