{
  "type": "Feature",
  "properties": {
    "gn:adm1_name":"Yamagataken",
    "gn:adm2_name":"Higashiokitamagunkawanishimachi",
    "gn:name":"Kamikomatsu",
    "iso:country":"JP",
    "wof:name":"999-0121",
    "wof:placetype":"postalcode"
},
  "geometry": {"coordinates":[140.0427,38.0035],"type":"Point"}
}