{
  "type": "Feature",
  "properties": {
    "gn:adm1_name":"Okinawaken",
    "gn:adm2_name":"Shimajirigunchinenson",
    "gn:name":"Gushiken",
    "iso:country":"JP",
    "wof:name":"901-1514",
    "wof:placetype":"postalcode"
},
  "geometry": {"coordinates":[127.8091,26.1569],"type":"Point"}
}