{
  "type": "Feature",
  "properties": {
    "gn:adm1_name":"Gifuken",
    "gn:adm2_name":"Kanishi",
    "gn:name":"Aigigaoka",
    "iso:country":"JP",
    "wof:name":"509-0259",
    "wof:placetype":"postalcode"
},
  "geometry": {"coordinates":[137.017,35.3955],"type":"Point"}
}