{
  "type": "Feature",
  "properties": {
    "gn:adm1_name":"Hyougoken",
    "gn:adm2_name":"Akashishi",
    "gn:name":"Taruyamachi",
    "iso:country":"JP",
    "wof:name":"673-0898",
    "wof:placetype":"postalcode"
},
  "geometry": {"coordinates":[134.98589999999999,34.6471],"type":"Point"}
}