{
  "type": "Feature",
  "properties": {
    "gn:adm1_name":"Toukyouto",
    "gn:adm2_name":"Hachioujishi",
    "gn:name":"Kawaguchimachi",
    "iso:country":"JP",
    "wof:name":"193-0801",
    "wof:placetype":"postalcode"
},
  "geometry": {"coordinates":[139.28630000000001,35.691],"type":"Point"}
}