{
  "type": "Feature",
  "properties": {
    "gn:adm1_name":"Miyazakiken",
    "gn:adm2_name":"Nishiusukigunhinokagechou",
    "gn:name":"Ikanikeisaiganaibaai",
    "iso:country":"JP",
    "wof:name":"882-0400",
    "wof:placetype":"postalcode"
},
  "geometry": {"coordinates":[131.38939999999999,32.6611],"type":"Point"}
}