{
  "type": "Feature",
  "properties": {
    "gn:adm1_name":"Hyougoken",
    "gn:adm2_name":"Kakogawashi",
    "gn:name":"Noguchichoumizuashi",
    "iso:country":"JP",
    "wof:name":"675-0019",
    "wof:placetype":"postalcode"
},
  "geometry": {"coordinates":[134.86410000000001,34.7649],"type":"Point"}
}