{
  "type": "Feature",
  "properties": {
    "gn:adm1_name":"Ehimeken",
    "gn:adm2_name":"Houjoushi",
    "gn:name":"Kanda",
    "iso:country":"JP",
    "wof:name":"799-2421",
    "wof:placetype":"postalcode"
},
  "geometry": {"coordinates":[132.80840000000001,33.9694],"type":"Point"}
}