{
  "type": "Feature",
  "properties": {
    "gn:adm1_name":"Sagaken",
    "gn:adm2_name":"Karatsushi",
    "gn:name":"Honmachi",
    "iso:country":"JP",
    "wof:name":"847-0047",
    "wof:placetype":"postalcode"
},
  "geometry": {"coordinates":[129.9708,33.4479],"type":"Point"}
}