{
  "type": "Feature",
  "properties": {
    "gn:adm1_name":"Miyazakiken",
    "gn:adm2_name":"Ebinoshi",
    "gn:name":"Maeda",
    "iso:country":"JP",
    "wof:name":"889-4305",
    "wof:placetype":"postalcode"
},
  "geometry": {"coordinates":[130.85740000000001,32.0453],"type":"Point"}
}