{
  "type": "Feature",
  "properties": {
    "gn:adm1_name":"Aichiken",
    "gn:adm2_name":"Okazakishi",
    "gn:name":"Igachou",
    "iso:country":"JP",
    "wof:name":"444-0075",
    "wof:placetype":"postalcode"
},
  "geometry": {"coordinates":[137.16730000000001,34.9699],"type":"Point"}
}