{
  "type": "Feature",
  "properties": {
    "gn:adm1_name":"Oosakafu",
    "gn:adm2_name":"Hirakatashi",
    "gn:name":"Sakuragaokachou",
    "iso:country":"JP",
    "wof:name":"573-0018",
    "wof:placetype":"postalcode"
},
  "geometry": {"coordinates":[135.67150000000001,34.807],"type":"Point"}
}