{
  "type": "Feature",
  "properties": {
    "gn:adm1_name":"Wakayamaken",
    "gn:adm2_name":"Higashimurogunkumanogawachou",
    "gn:name":"Kujuu",
    "iso:country":"JP",
    "wof:name":"647-1233",
    "wof:placetype":"postalcode"
},
  "geometry": {"coordinates":[135.84100000000001,33.8732],"type":"Point"}
}