{
  "type": "Feature",
  "properties": {
    "gn:adm1_name":"Mieken",
    "gn:adm2_name":"Iinangun'Iinanchou",
    "gn:name":"Fukano",
    "iso:country":"JP",
    "wof:name":"515-1301",
    "wof:placetype":"postalcode"
},
  "geometry": {"coordinates":[136.40649999999999,34.4812],"type":"Point"}
}