{
  "type": "Feature",
  "properties": {
    "gn:adm1_name":"Aichiken",
    "gn:adm2_name":"Nakashimagunsobuechou",
    "gn:name":"Honkou",
    "iso:country":"JP",
    "wof:name":"495-0012",
    "wof:placetype":"postalcode"
},
  "geometry": {"coordinates":[136.7355,35.2454],"type":"Point"}
}