{
  "type": "Feature",
  "properties": {
    "gn:adm1_name":"Tokushimaken",
    "gn:adm2_name":"Nakagun'Aioichou",
    "gn:name":"Ushiwa",
    "iso:country":"JP",
    "wof:name":"771-5404",
    "wof:placetype":"postalcode"
},
  "geometry": {"coordinates":[134.4657,33.8261],"type":"Point"}
}