{
  "type": "Feature",
  "properties": {
    "gn:adm1_name":"Yamagataken",
    "gn:adm2_name":"Nishiokitamagunshiratakamachi",
    "gn:name":"Asadachi",
    "iso:country":"JP",
    "wof:name":"992-0852",
    "wof:placetype":"postalcode"
},
  "geometry": {"coordinates":[140.06700000000001,38.1463],"type":"Point"}
}