{
  "type": "Feature",
  "properties": {
    "gn:adm1_name":"Shizuokaken",
    "gn:adm2_name":"Shuuchigunmorimachi",
    "gn:name":"Mori",
    "iso:country":"JP",
    "wof:name":"437-0215",
    "wof:placetype":"postalcode"
},
  "geometry": {"coordinates":[137.9264,34.8339],"type":"Point"}
}