{
  "type": "Feature",
  "properties": {
    "gn:adm1_name":"Shizuokaken",
    "gn:adm2_name":"Kamogunkawaduchou",
    "gn:name":"Yugano",
    "iso:country":"JP",
    "wof:name":"413-0507",
    "wof:placetype":"postalcode"
},
  "geometry": {"coordinates":[138.95419999999999,34.7762],"type":"Point"}
}