{
  "type": "Feature",
  "properties": {
    "gn:adm1_name":"Niigataken",
    "gn:adm2_name":"Niigatashi",
    "gn:name":"Ishiyamadanchi",
    "iso:country":"JP",
    "wof:name":"950-0834",
    "wof:placetype":"postalcode"
},
  "geometry": {"coordinates":[139.10980000000001,37.9045],"type":"Point"}
}