{
  "type": "Feature",
  "properties": {
    "gn:adm1_name":"Naganoken",
    "gn:adm2_name":"Kitaadumigun'Ikedamachi",
    "gn:name":"Hirotsu",
    "iso:country":"JP",
    "wof:name":"399-8604",
    "wof:placetype":"postalcode"
},
  "geometry": {"coordinates":[137.91499999999999,36.4578],"type":"Point"}
}