{
  "type": "Feature",
  "properties": {
    "gn:adm1_name":"Aichiken",
    "gn:adm2_name":"Kounanshi",
    "gn:name":"Ushirohibochoutakase",
    "iso:country":"JP",
    "wof:name":"483-8345",
    "wof:placetype":"postalcode"
},
  "geometry": {"coordinates":[136.8433,35.3472],"type":"Point"}
}