{
  "type": "Feature",
  "properties": {
    "gn:adm1_name":"Kyoutofu",
    "gn:adm2_name":"Kyoutoshiukyouku",
    "gn:name":"Saganokaminokichou",
    "iso:country":"JP",
    "wof:name":"616-8317",
    "wof:placetype":"postalcode"
},
  "geometry": {"coordinates":[135.69540000000001,35.0155],"type":"Point"}
}