{
  "type": "Feature",
  "properties": {
    "gn:adm1_name":"Tochigiken",
    "gn:adm2_name":"Oyamashi",
    "gn:name":"Shimoizumi",
    "iso:country":"JP",
    "wof:name":"323-0055",
    "wof:placetype":"postalcode"
},
  "geometry": {"coordinates":[139.73699999999999,36.3036],"type":"Point"}
}