{
  "type": "Feature",
  "properties": {
    "gn:adm1_name":"Yamaguchiken",
    "gn:adm2_name":"Houfushi",
    "gn:name":"Niiryouchou",
    "iso:country":"JP",
    "wof:name":"747-0841",
    "wof:placetype":"postalcode"
},
  "geometry": {"coordinates":[131.55500000000001,34.0502],"type":"Point"}
}