{
  "type": "Feature",
  "properties": {
    "gn:adm1_name":"Miyagiken",
    "gn:adm2_name":"Kuriharagunkannarichou",
    "gn:name":"Otsutsumi",
    "iso:country":"JP",
    "wof:name":"989-5183",
    "wof:placetype":"postalcode"
},
  "geometry": {"coordinates":[141.03880000000001,38.8056],"type":"Point"}
}