{
  "type": "Feature",
  "properties": {
    "gn:adm1_name":"Oosakafu",
    "gn:adm2_name":"Oosakashitennoujiku",
    "gn:name":"Katsuyama",
    "iso:country":"JP",
    "wof:name":"543-0043",
    "wof:placetype":"postalcode"
},
  "geometry": {"coordinates":[135.5224,34.6543],"type":"Point"}
}