{
  "type": "Feature",
  "properties": {
    "gn:adm1_name":"Naraken",
    "gn:adm2_name":"Yoshinoguntotsukawamura",
    "gn:name":"Nanairo",
    "iso:country":"JP",
    "wof:name":"637-1557",
    "wof:placetype":"postalcode"
},
  "geometry": {"coordinates":[135.75880000000001,33.8907],"type":"Point"}
}