{
  "type": "Feature",
  "properties": {
    "gn:adm1_name":"Nagasakiken",
    "gn:adm2_name":"Shimabarashi",
    "gn:name":"Fudanomotomachi",
    "iso:country":"JP",
    "wof:name":"855-0882",
    "wof:placetype":"postalcode"
},
  "geometry": {"coordinates":[130.3546,32.7511],"type":"Point"}
}