{
  "type": "Feature",
  "properties": {
    "gn:adm1_name":"Tochigiken",
    "gn:adm2_name":"Shioyaguntakanezawamachi",
    "gn:name":"Ishidue",
    "iso:country":"JP",
    "wof:name":"329-1225",
    "wof:placetype":"postalcode"
},
  "geometry": {"coordinates":[139.9956,36.6327],"type":"Point"}
}