{
  "type": "Feature",
  "properties": {
    "gn:adm1_name":"Miyagiken",
    "gn:adm2_name":"Miyagigunrifuchou",
    "gn:name":"Akanuma",
    "iso:country":"JP",
    "wof:name":"981-0101",
    "wof:placetype":"postalcode"
},
  "geometry": {"coordinates":[141.0342,38.3529],"type":"Point"}
}