{
  "type": "Feature",
  "properties": {
    "gn:adm1_name":"Kagawaken",
    "gn:adm2_name":"Ayautagun'Utaduchou",
    "gn:name":"Shinmachi",
    "iso:country":"JP",
    "wof:name":"769-0225",
    "wof:placetype":"postalcode"
},
  "geometry": {"coordinates":[133.82929999999999,34.3106],"type":"Point"}
}