{
  "type": "Feature",
  "properties": {
    "gn:adm1_name":"Toyamaken",
    "gn:adm2_name":"Shimoniikawagun'Unadukimachi",
    "gn:name":"Unaduki",
    "iso:country":"JP",
    "wof:name":"938-0282",
    "wof:placetype":"postalcode"
},
  "geometry": {"coordinates":[137.4453,36.8759],"type":"Point"}
}