{
  "type": "Feature",
  "properties": {
    "gn:adm1_name":"Hyougoken",
    "gn:adm2_name":"Akoushi",
    "gn:name":"Kyuunotani",
    "iso:country":"JP",
    "wof:name":"678-0253",
    "wof:placetype":"postalcode"
},
  "geometry": {"coordinates":[134.35980000000001,34.7666],"type":"Point"}
}