{
  "type": "Feature",
  "properties": {
    "gn:adm1_name":"Hiroshimaken",
    "gn:adm2_name":"Takatagunmidorichou",
    "gn:name":"Hongou",
    "iso:country":"JP",
    "wof:name":"731-0612",
    "wof:placetype":"postalcode"
},
  "geometry": {"coordinates":[132.6156,34.7176],"type":"Point"}
}