{
  "type": "Feature",
  "properties": {
    "gn:adm1_name":"Ooitaken",
    "gn:adm2_name":"Bungotakadashi",
    "gn:name":"Umenoki",
    "iso:country":"JP",
    "wof:name":"879-0723",
    "wof:placetype":"postalcode"
},
  "geometry": {"coordinates":[131.4744,33.5801],"type":"Point"}
}