{
  "type": "Feature",
  "properties": {
    "gn:adm1_name":"Nagasakiken",
    "gn:adm2_name":"Higashisonogigunhasamichou",
    "gn:name":"Onigigou",
    "iso:country":"JP",
    "wof:name":"859-3713",
    "wof:placetype":"postalcode"
},
  "geometry": {"coordinates":[129.92179999999999,33.1184],"type":"Point"}
}