{
  "type": "Feature",
  "properties": {
    "gn:adm1_name":"Shimaneken",
    "gn:adm2_name":"Masudashi",
    "gn:name":"Tsuchidachou",
    "iso:country":"JP",
    "wof:name":"699-3505",
    "wof:placetype":"postalcode"
},
  "geometry": {"coordinates":[131.8948,34.7557],"type":"Point"}
}