{
  "type": "Feature",
  "properties": {
    "gn:adm1_name":"Shizuokaken",
    "gn:adm2_name":"Tenryuushi",
    "gn:name":"Yokokawa",
    "iso:country":"JP",
    "wof:name":"431-3301",
    "wof:placetype":"postalcode"
},
  "geometry": {"coordinates":[137.8783,34.9044],"type":"Point"}
}