{
  "type": "Feature",
  "properties": {
    "gn:adm1_name":"Shimaneken",
    "gn:adm2_name":"Nogigunhakutachou",
    "gn:name":"Yasudayamagata",
    "iso:country":"JP",
    "wof:name":"692-0201",
    "wof:placetype":"postalcode"
},
  "geometry": {"coordinates":[133.30789999999999,35.3858],"type":"Point"}
}