{
  "type": "Feature",
  "properties": {
    "gn:adm1_name":"Saitamaken",
    "gn:adm2_name":"Hikigunkawajimamachi",
    "gn:name":"Hachiman",
    "iso:country":"JP",
    "wof:name":"350-0151",
    "wof:placetype":"postalcode"
},
  "geometry": {"coordinates":[139.44380000000001,35.9853],"type":"Point"}
}