{
  "type": "Feature",
  "properties": {
    "gn:adm1_name":"Nagasakiken",
    "gn:adm2_name":"Nagasakishi",
    "gn:name":"Irabayashi",
    "iso:country":"JP",
    "wof:name":"850-0802",
    "wof:placetype":"postalcode"
},
  "geometry": {"coordinates":[129.88740000000001,32.7484],"type":"Point"}
}