{
  "type": "Feature",
  "properties": {
    "gn:adm1_name":"Tochigiken",
    "gn:adm2_name":"Utsunomiyashi",
    "gn:name":"Fudoumae",
    "iso:country":"JP",
    "wof:name":"320-0833",
    "wof:placetype":"postalcode"
},
  "geometry": {"coordinates":[139.8801,36.5447],"type":"Point"}
}