{
  "type": "Feature",
  "properties": {
    "gn:adm1_name":"Naraken",
    "gn:adm2_name":"Yamatotakadashi",
    "gn:name":"Imasato",
    "iso:country":"JP",
    "wof:name":"635-0031",
    "wof:placetype":"postalcode"
},
  "geometry": {"coordinates":[135.75200000000001,34.5096],"type":"Point"}
}