{
  "type": "Feature",
  "properties": {
    "gn:adm1_name":"Aichiken",
    "gn:adm2_name":"Toyokawashi",
    "gn:name":"Chitosedoori",
    "iso:country":"JP",
    "wof:name":"442-0888",
    "wof:placetype":"postalcode"
},
  "geometry": {"coordinates":[137.38149999999999,34.8181],"type":"Point"}
}