{
  "type": "Feature",
  "properties": {
    "gn:adm1_name":"Hiroshimaken",
    "gn:adm2_name":"Jinsekigunyukichou",
    "gn:name":"Ikanikeisaiganaibaai",
    "iso:country":"JP",
    "wof:name":"720-1800",
    "wof:placetype":"postalcode"
},
  "geometry": {"coordinates":[133.20310000000001,34.6771],"type":"Point"}
}