{
  "type": "Feature",
  "properties": {
    "gn:adm1_name":"Naganoken",
    "gn:adm2_name":"Suwagunshimosuwamachi",
    "gn:name":"Koyunoue",
    "iso:country":"JP",
    "wof:name":"393-0013",
    "wof:placetype":"postalcode"
},
  "geometry": {"coordinates":[138.0909,36.077],"type":"Point"}
}