{
  "type": "Feature",
  "properties": {
    "gn:adm1_name":"Wakayamaken",
    "gn:adm2_name":"Wakayamashi",
    "gn:name":"Hatayashikienpukuinhigashinochou",
    "iso:country":"JP",
    "wof:name":"640-8383",
    "wof:placetype":"postalcode"
},
  "geometry": {"coordinates":[135.1831,34.2341],"type":"Point"}
}