{
  "type": "Feature",
  "properties": {
    "gn:adm1_name":"Kumamotoken",
    "gn:adm2_name":"Minamatashi",
    "gn:name":"Warabino",
    "iso:country":"JP",
    "wof:name":"867-0004",
    "wof:placetype":"postalcode"
},
  "geometry": {"coordinates":[130.41290000000001,32.2109],"type":"Point"}
}