{
  "type": "Feature",
  "properties": {
    "gn:adm1_name":"Shigaken",
    "gn:adm2_name":"Koukagunshigarakichou",
    "gn:name":"Miyamachi",
    "iso:country":"JP",
    "wof:name":"529-1801",
    "wof:placetype":"postalcode"
},
  "geometry": {"coordinates":[136.08439999999999,34.9344],"type":"Point"}
}