{
  "type": "Feature",
  "properties": {
    "gn:adm1_name":"Shimaneken",
    "gn:adm2_name":"Oochigunsakuraechou",
    "gn:name":"Sakamoto",
    "iso:country":"JP",
    "wof:name":"699-4505",
    "wof:placetype":"postalcode"
},
  "geometry": {"coordinates":[132.429,34.9625],"type":"Point"}
}