{
  "type": "Feature",
  "properties": {
    "gn:adm1_name":"Shigaken",
    "gn:adm2_name":"Takashimagun'Imaduchou",
    "gn:name":"Hiokimae",
    "iso:country":"JP",
    "wof:name":"520-1655",
    "wof:placetype":"postalcode"
},
  "geometry": {"coordinates":[136.0093,35.4249],"type":"Point"}
}