{
  "type": "Feature",
  "properties": {
    "gn:adm1_name":"Fukushimaken",
    "gn:adm2_name":"Nihonmatsushi",
    "gn:name":"Suzuishichou",
    "iso:country":"JP",
    "wof:name":"964-0972",
    "wof:placetype":"postalcode"
},
  "geometry": {"coordinates":[140.46870000000001,37.551],"type":"Point"}
}