{
  "type": "Feature",
  "properties": {
    "gn:adm1_name":"Toyamaken",
    "gn:adm2_name":"Toyamashi",
    "gn:name":"Meirinchou",
    "iso:country":"JP",
    "wof:name":"930-0001",
    "wof:placetype":"postalcode"
},
  "geometry": {"coordinates":[137.2139,36.7014],"type":"Point"}
}