{
  "type": "Feature",
  "properties": {
    "gn:adm1_name":"Gunmaken",
    "gn:adm2_name":"Maebashishi",
    "gn:name":"Kamesatomachi",
    "iso:country":"JP",
    "wof:name":"379-2147",
    "wof:placetype":"postalcode"
},
  "geometry": {"coordinates":[139.09100000000001,36.3421],"type":"Point"}
}