{
  "type": "Feature",
  "properties": {
    "gn:adm1_name":"Kyoutofu",
    "gn:adm2_name":"Kyoutoshisakyouku",
    "gn:name":"Kamitakanokamonhayashichou",
    "iso:country":"JP",
    "wof:name":"606-0072",
    "wof:placetype":"postalcode"
},
  "geometry": {"coordinates":[135.80189999999999,35.0607],"type":"Point"}
}