{
  "type": "Feature",
  "properties": {
    "gn:adm1_name":"Aichiken",
    "gn:adm2_name":"Kasugaishi",
    "gn:name":"Asamiyachou",
    "iso:country":"JP",
    "wof:name":"486-0846",
    "wof:placetype":"postalcode"
},
  "geometry": {"coordinates":[136.95820000000001,35.2512],"type":"Point"}
}