{
  "type": "Feature",
  "properties": {
    "gn:adm1_name":"Hyougoken",
    "gn:adm2_name":"Sasayamashi",
    "gn:name":"Ikushi",
    "iso:country":"JP",
    "wof:name":"669-2541",
    "wof:placetype":"postalcode"
},
  "geometry": {"coordinates":[135.31909999999999,35.0877],"type":"Point"}
}