{
  "type": "Feature",
  "properties": {
    "gn:adm1_name":"Ehimeken",
    "gn:adm2_name":"Minamiuwagunnishiumichou",
    "gn:name":"Uchidomari",
    "iso:country":"JP",
    "wof:name":"798-4206",
    "wof:placetype":"postalcode"
},
  "geometry": {"coordinates":[132.49160000000001,32.9394],"type":"Point"}
}