{
  "type": "Feature",
  "properties": {
    "gn:adm1_name":"Nagasakiken",
    "gn:adm2_name":"Nagasakishi",
    "gn:name":"Oogomorimachi",
    "iso:country":"JP",
    "wof:name":"851-0302",
    "wof:placetype":"postalcode"
},
  "geometry": {"coordinates":[129.82089999999999,32.6716],"type":"Point"}
}