{
  "type": "Feature",
  "properties": {
    "gn:adm1_name":"Fukuokaken",
    "gn:adm2_name":"Kitakyuushuushimojiku",
    "gn:name":"Kurogawa",
    "iso:country":"JP",
    "wof:name":"801-0821",
    "wof:placetype":"postalcode"
},
  "geometry": {"coordinates":[130.9683,33.93],"type":"Point"}
}