{
  "type": "Feature",
  "properties": {
    "gn:adm1_name":"Kyoutofu",
    "gn:adm2_name":"Yawatashi",
    "gn:name":"Hashimotohigashikarimata",
    "iso:country":"JP",
    "wof:name":"614-8333",
    "wof:placetype":"postalcode"
},
  "geometry": {"coordinates":[135.69110000000001,34.8742],"type":"Point"}
}