{
  "type": "Feature",
  "properties": {
    "gn:adm1_name":"Hyougoken",
    "gn:adm2_name":"Nishinomiyashi",
    "gn:name":"Kitashouwachou",
    "iso:country":"JP",
    "wof:name":"662-0833",
    "wof:placetype":"postalcode"
},
  "geometry": {"coordinates":[135.35329999999999,34.7486],"type":"Point"}
}