{
  "type": "Feature",
  "properties": {
    "gn:adm1_name":"Niigataken",
    "gn:adm2_name":"Gosenshi",
    "gn:name":"Kouyagawa",
    "iso:country":"JP",
    "wof:name":"959-1864",
    "wof:placetype":"postalcode"
},
  "geometry": {"coordinates":[139.17959999999999,37.7402],"type":"Point"}
}