{
  "type": "Feature",
  "properties": {
    "gn:adm1_name":"Ehimeken",
    "gn:adm2_name":"Kamiukenagun'Omogomura",
    "gn:name":"Ainoki",
    "iso:country":"JP",
    "wof:name":"791-1709",
    "wof:placetype":"postalcode"
},
  "geometry": {"coordinates":[133.08340000000001,33.6873],"type":"Point"}
}