{
  "type": "Feature",
  "properties": {
    "gn:adm1_name":"Fukuokaken",
    "gn:adm2_name":"Kitakyuushuushitobataku",
    "gn:name":"Motomiyamachi",
    "iso:country":"JP",
    "wof:name":"804-0072",
    "wof:placetype":"postalcode"
},
  "geometry": {"coordinates":[130.8244,33.9003],"type":"Point"}
}