{
  "type": "Feature",
  "properties": {
    "gn:adm1_name":"Kanagawaken",
    "gn:adm2_name":"Kawasakishisaiwaiku",
    "gn:name":"Komukainishimachi",
    "iso:country":"JP",
    "wof:name":"212-0004",
    "wof:placetype":"postalcode"
},
  "geometry": {"coordinates":[139.68870000000001,35.5471],"type":"Point"}
}