{
  "type": "Feature",
  "properties": {
    "gn:adm1_name":"Hyougoken",
    "gn:adm2_name":"Kinosakigunkasumichou",
    "gn:name":"Yasugi",
    "iso:country":"JP",
    "wof:name":"669-6403",
    "wof:placetype":"postalcode"
},
  "geometry": {"coordinates":[134.7047,35.6486],"type":"Point"}
}