{
  "type": "Feature",
  "properties": {
    "gn:adm1_name":"Miyazakiken",
    "gn:adm2_name":"Higashiusukigunshiibason",
    "gn:name":"Shimofukura",
    "iso:country":"JP",
    "wof:name":"883-1601",
    "wof:placetype":"postalcode"
},
  "geometry": {"coordinates":[131.16839999999999,32.4914],"type":"Point"}
}