{
  "type": "Feature",
  "properties": {
    "gn:adm1_name":"Kagoshimaken",
    "gn:adm2_name":"Ooshimagunyamatoson",
    "gn:name":"Ikanikeisaiganaibaai",
    "iso:country":"JP",
    "wof:name":"894-3100",
    "wof:placetype":"postalcode"
},
  "geometry": {"coordinates":[129.39750000000001,28.3574],"type":"Point"}
}