{
  "type": "Feature",
  "properties": {
    "gn:adm1_name":"Hyougoken",
    "gn:adm2_name":"Tatsunoshi",
    "gn:name":"Ibochoutouyou",
    "iso:country":"JP",
    "wof:name":"679-4143",
    "wof:placetype":"postalcode"
},
  "geometry": {"coordinates":[134.5453,34.8198],"type":"Point"}
}