{
  "type": "Feature",
  "properties": {
    "gn:adm1_name":"Toyamaken",
    "gn:adm2_name":"Tonamishi",
    "gn:name":"Kamiwada",
    "iso:country":"JP",
    "wof:name":"939-1411",
    "wof:placetype":"postalcode"
},
  "geometry": {"coordinates":[137.03450000000001,36.6464],"type":"Point"}
}