{
  "type": "Feature",
  "properties": {
    "gn:adm1_name":"Toyamaken",
    "gn:adm2_name":"Toyamashi",
    "gn:name":"Sunamachi",
    "iso:country":"JP",
    "wof:name":"930-0045",
    "wof:placetype":"postalcode"
},
  "geometry": {"coordinates":[137.2208,36.6905],"type":"Point"}
}