{
  "type": "Feature",
  "properties": {
    "gn:adm1_name":"Yamanashiken",
    "gn:adm2_name":"Minamiarupusushi",
    "gn:name":"Tsukuyama",
    "iso:country":"JP",
    "wof:name":"400-0225",
    "wof:placetype":"postalcode"
},
  "geometry": {"coordinates":[138.4316,35.652],"type":"Point"}
}