{
  "type": "Feature",
  "properties": {
    "gn:adm1_name":"Saitamaken",
    "gn:adm2_name":"Kitakatsushikagunsugitomachi",
    "gn:name":"Oojima",
    "iso:country":"JP",
    "wof:name":"345-0042",
    "wof:placetype":"postalcode"
},
  "geometry": {"coordinates":[139.7217,36.048],"type":"Point"}
}