{
  "type": "Feature",
  "properties": {
    "gn:adm1_name":"Mieken",
    "gn:adm2_name":"Uenoshi",
    "gn:name":"Midorigaokanishimachi",
    "iso:country":"JP",
    "wof:name":"518-0837",
    "wof:placetype":"postalcode"
},
  "geometry": {"coordinates":[136.13910000000001,34.7584],"type":"Point"}
}