{
  "type": "Feature",
  "properties": {
    "gn:adm1_name":"Hyougoken",
    "gn:adm2_name":"Kasaishi",
    "gn:name":"Mootanichou",
    "iso:country":"JP",
    "wof:name":"675-2414",
    "wof:placetype":"postalcode"
},
  "geometry": {"coordinates":[134.8972,34.9513],"type":"Point"}
}