{
  "type": "Feature",
  "properties": {
    "gn:adm1_name":"Hiroshimaken",
    "gn:adm2_name":"Hiroshimashiakiku",
    "gn:name":"Nakano",
    "iso:country":"JP",
    "wof:name":"739-0321",
    "wof:placetype":"postalcode"
},
  "geometry": {"coordinates":[132.57300000000001,34.401],"type":"Point"}
}