{
  "type": "Feature",
  "properties": {
    "gn:adm1_name":"Hyougoken",
    "gn:adm2_name":"Kanzakigunkanzakichou",
    "gn:name":"Fukumoto",
    "iso:country":"JP",
    "wof:name":"679-2415",
    "wof:placetype":"postalcode"
},
  "geometry": {"coordinates":[134.78469999999999,35.0491],"type":"Point"}
}