{
  "type": "Feature",
  "properties": {
    "gn:adm1_name":"Shimaneken",
    "gn:adm2_name":"Nimagunyunotsumachi",
    "gn:name":"Yuzatoyuzato",
    "iso:country":"JP",
    "wof:name":"699-2502",
    "wof:placetype":"postalcode"
},
  "geometry": {"coordinates":[132.37960000000001,35.104],"type":"Point"}
}