{
  "type": "Feature",
  "properties": {
    "gn:adm1_name":"Sagaken",
    "gn:adm2_name":"Imarishi",
    "gn:name":"Yamashirochoukubara",
    "iso:country":"JP",
    "wof:name":"849-4256",
    "wof:placetype":"postalcode"
},
  "geometry": {"coordinates":[129.81010000000001,33.3131],"type":"Point"}
}