{
  "type": "Feature",
  "properties": {
    "gn:adm1_name":"Yamaguchiken",
    "gn:adm2_name":"Ubeshi",
    "gn:name":"Hiraki",
    "iso:country":"JP",
    "wof:name":"755-0096",
    "wof:placetype":"postalcode"
},
  "geometry": {"coordinates":[131.27889999999999,33.9615],"type":"Point"}
}