{
  "type": "Feature",
  "properties": {
    "gn:adm1_name":"Kumamotoken",
    "gn:adm2_name":"Asogun'Asomachi",
    "gn:name":"Matoishi",
    "iso:country":"JP",
    "wof:name":"869-2237",
    "wof:placetype":"postalcode"
},
  "geometry": {"coordinates":[130.9932,32.9304],"type":"Point"}
}