{
  "type": "Feature",
  "properties": {
    "gn:adm1_name":"Mieken",
    "gn:adm2_name":"Ayamagun'Ayamachou",
    "gn:name":"Makiyama",
    "iso:country":"JP",
    "wof:name":"518-1326",
    "wof:placetype":"postalcode"
},
  "geometry": {"coordinates":[136.14109999999999,34.8705],"type":"Point"}
}