{
  "type": "Feature",
  "properties": {
    "gn:adm1_name":"Chibaken",
    "gn:adm2_name":"Inbagunsakaemachi",
    "gn:name":"Miwa",
    "iso:country":"JP",
    "wof:name":"270-1536",
    "wof:placetype":"postalcode"
},
  "geometry": {"coordinates":[140.19370000000001,35.8491],"type":"Point"}
}