{
  "type": "Feature",
  "properties": {
    "gn:adm1_name":"Shizuokaken",
    "gn:adm2_name":"Tagatagunshuzenjichou",
    "gn:name":"Hinata",
    "iso:country":"JP",
    "wof:name":"410-2406",
    "wof:placetype":"postalcode"
},
  "geometry": {"coordinates":[138.94739999999999,34.9639],"type":"Point"}
}