{
  "type": "Feature",
  "properties": {
    "gn:adm1_name":"Mieken",
    "gn:adm2_name":"Yokkaichishi",
    "gn:name":"Akuragawashinmachi",
    "iso:country":"JP",
    "wof:name":"510-0810",
    "wof:placetype":"postalcode"
},
  "geometry": {"coordinates":[136.6207,34.9936],"type":"Point"}
}