{
  "type": "Feature",
  "properties": {
    "gn:adm1_name":"Kumamotoken",
    "gn:adm2_name":"Kikuchishi",
    "gn:name":"Koba",
    "iso:country":"JP",
    "wof:name":"861-1301",
    "wof:placetype":"postalcode"
},
  "geometry": {"coordinates":[130.83150000000001,32.986],"type":"Point"}
}