{
  "type": "Feature",
  "properties": {
    "gn:adm1_name":"Gifuken",
    "gn:adm2_name":"Kamogunshirakawachou",
    "gn:name":"Akou",
    "iso:country":"JP",
    "wof:name":"509-1112",
    "wof:placetype":"postalcode"
},
  "geometry": {"coordinates":[137.2603,35.5512],"type":"Point"}
}