{
  "type": "Feature",
  "properties": {
    "gn:adm1_name":"Okayamaken",
    "gn:adm2_name":"Okayamashi",
    "gn:name":"Daikuhonmachi",
    "iso:country":"JP",
    "wof:name":"700-0911",
    "wof:placetype":"postalcode"
},
  "geometry": {"coordinates":[133.91229999999999,34.6528],"type":"Point"}
}