{
  "type": "Feature",
  "properties": {
    "gn:adm1_name":"Tochigiken",
    "gn:adm2_name":"Hagagunmashikomachi",
    "gn:name":"Mashiko",
    "iso:country":"JP",
    "wof:name":"321-4217",
    "wof:placetype":"postalcode"
},
  "geometry": {"coordinates":[140.09960000000001,36.465],"type":"Point"}
}