{
  "type": "Feature",
  "properties": {
    "gn:adm1_name":"Hyougoken",
    "gn:adm2_name":"Himejishi",
    "gn:name":"Katadamachi",
    "iso:country":"JP",
    "wof:name":"670-0045",
    "wof:placetype":"postalcode"
},
  "geometry": {"coordinates":[134.68299999999999,34.8331],"type":"Point"}
}