{
  "type": "Feature",
  "properties": {
    "gn:adm1_name":"Fukuiken",
    "gn:adm2_name":"Sakaigunmikunichou",
    "gn:name":"Takidani",
    "iso:country":"JP",
    "wof:name":"913-0054",
    "wof:placetype":"postalcode"
},
  "geometry": {"coordinates":[136.1455,36.2191],"type":"Point"}
}