{
  "type": "Feature",
  "properties": {
    "gn:adm1_name":"Ehimeken",
    "gn:adm2_name":"Imabarishi",
    "gn:name":"Tsujidou",
    "iso:country":"JP",
    "wof:name":"794-0827",
    "wof:placetype":"postalcode"
},
  "geometry": {"coordinates":[133.00569999999999,34.0395],"type":"Point"}
}