{
  "type": "Feature",
  "properties": {
    "gn:adm1_name":"Fukuokaken",
    "gn:adm2_name":"Ongagun'Okagakimachi",
    "gn:name":"Sakuradai",
    "iso:country":"JP",
    "wof:name":"811-4217",
    "wof:placetype":"postalcode"
},
  "geometry": {"coordinates":[130.62370000000001,33.8497],"type":"Point"}
}