{
  "type": "Feature",
  "properties": {
    "gn:adm1_name":"Wakayamaken",
    "gn:adm2_name":"Hidakagun'Inamichou",
    "gn:name":"Inanbara",
    "iso:country":"JP",
    "wof:name":"649-1532",
    "wof:placetype":"postalcode"
},
  "geometry": {"coordinates":[135.23259999999999,33.8592],"type":"Point"}
}