{
  "type": "Feature",
  "properties": {
    "gn:adm1_name":"Yamagataken",
    "gn:adm2_name":"Yamagatashi",
    "gn:name":"Aota",
    "iso:country":"JP",
    "wof:name":"990-2435",
    "wof:placetype":"postalcode"
},
  "geometry": {"coordinates":[140.3313,38.224],"type":"Point"}
}