{
  "type": "Feature",
  "properties": {
    "gn:adm1_name":"Hyougoken",
    "gn:adm2_name":"Nishinomiyashi",
    "gn:name":"Tsutoiidenchou",
    "iso:country":"JP",
    "wof:name":"663-8242",
    "wof:placetype":"postalcode"
},
  "geometry": {"coordinates":[135.3621,34.7363],"type":"Point"}
}