{
  "type": "Feature",
  "properties": {
    "gn:adm1_name":"Ooitaken",
    "gn:adm2_name":"Usagun'Innaimachi",
    "gn:name":"Koine",
    "iso:country":"JP",
    "wof:name":"872-0325",
    "wof:placetype":"postalcode"
},
  "geometry": {"coordinates":[131.30189999999999,33.4351],"type":"Point"}
}