{
  "type": "Feature",
  "properties": {
    "gn:adm1_name":"Ehimeken",
    "gn:adm2_name":"Matsuyamashi",
    "gn:name":"Shin'Ishite",
    "iso:country":"JP",
    "wof:name":"790-0901",
    "wof:placetype":"postalcode"
},
  "geometry": {"coordinates":[132.80080000000001,33.8459],"type":"Point"}
}