{
  "type": "Feature",
  "properties": {
    "gn:adm1_name":"Gifuken",
    "gn:adm2_name":"Yamagatashi",
    "gn:name":"Isami",
    "iso:country":"JP",
    "wof:name":"501-2102",
    "wof:placetype":"postalcode"
},
  "geometry": {"coordinates":[136.78739999999999,35.5269],"type":"Point"}
}