{
  "type": "Feature",
  "properties": {
    "gn:adm1_name":"Aichiken",
    "gn:adm2_name":"Nagoyashinakaku",
    "gn:name":"Shinsakae",
    "iso:country":"JP",
    "wof:name":"460-0007",
    "wof:placetype":"postalcode"
},
  "geometry": {"coordinates":[136.9203,35.1666],"type":"Point"}
}