{
  "type": "Feature",
  "properties": {
    "gn:adm1_name":"Kanagawaken",
    "gn:adm2_name":"Kawasakishikawasakiku",
    "gn:name":"Tsutsumine",
    "iso:country":"JP",
    "wof:name":"210-0026",
    "wof:placetype":"postalcode"
},
  "geometry": {"coordinates":[139.6909,35.5256],"type":"Point"}
}