{
  "type": "Feature",
  "properties": {
    "gn:adm1_name":"Niigataken",
    "gn:adm2_name":"Tookamachishi",
    "gn:name":"Gejou",
    "iso:country":"JP",
    "wof:name":"949-8603",
    "wof:placetype":"postalcode"
},
  "geometry": {"coordinates":[138.78020000000001,37.193],"type":"Point"}
}