{
  "type": "Feature",
  "properties": {
    "gn:adm1_name":"Ibarakiken",
    "gn:adm2_name":"Tsuchiurashi",
    "gn:name":"Kidamarihigashidai",
    "iso:country":"JP",
    "wof:name":"300-0027",
    "wof:placetype":"postalcode"
},
  "geometry": {"coordinates":[140.2209,36.1035],"type":"Point"}
}