{
  "type": "Feature",
  "properties": {
    "gn:adm1_name":"Ibarakiken",
    "gn:adm2_name":"Mitoshi",
    "gn:name":"Akutsuoono",
    "iso:country":"JP",
    "wof:name":"310-0822",
    "wof:placetype":"postalcode"
},
  "geometry": {"coordinates":[140.5368,36.3617],"type":"Point"}
}