{
  "type": "Feature",
  "properties": {
    "gn:adm1_name":"Gifuken",
    "gn:adm2_name":"Oogakishi",
    "gn:name":"Tawaramachi",
    "iso:country":"JP",
    "wof:name":"503-0876",
    "wof:placetype":"postalcode"
},
  "geometry": {"coordinates":[136.6148,35.3579],"type":"Point"}
}