{
  "type": "Feature",
  "properties": {
    "gn:adm1_name":"Sagaken",
    "gn:adm2_name":"Ogigun'Ashikarichou",
    "gn:name":"Miouzaki",
    "iso:country":"JP",
    "wof:name":"849-0314",
    "wof:placetype":"postalcode"
},
  "geometry": {"coordinates":[130.2029,33.2216],"type":"Point"}
}