{
  "type": "Feature",
  "properties": {
    "gn:adm1_name":"Miyazakiken",
    "gn:adm2_name":"Higashiusukigunshiibason",
    "gn:name":"Matsuo",
    "iso:country":"JP",
    "wof:name":"883-1604",
    "wof:placetype":"postalcode"
},
  "geometry": {"coordinates":[131.24799999999999,32.4882],"type":"Point"}
}