{
  "type": "Feature",
  "properties": {
    "gn:adm1_name":"Miyagiken",
    "gn:adm2_name":"Kesennumashi",
    "gn:name":"Jinyama",
    "iso:country":"JP",
    "wof:name":"988-0011",
    "wof:placetype":"postalcode"
},
  "geometry": {"coordinates":[141.57769999999999,38.9086],"type":"Point"}
}