{
  "type": "Feature",
  "properties": {
    "gn:adm1_name":"Aichiken",
    "gn:adm2_name":"Nagoyashimizuhoku",
    "gn:name":"Kamihochou",
    "iso:country":"JP",
    "wof:name":"467-0847",
    "wof:placetype":"postalcode"
},
  "geometry": {"coordinates":[136.92310000000001,35.1131],"type":"Point"}
}