{
  "type": "Feature",
  "properties": {
    "gn:adm1_name":"Saitamaken",
    "gn:adm2_name":"Saitamashioomiyaku",
    "gn:name":"Oohara",
    "iso:country":"JP",
    "wof:name":"330-0836",
    "wof:placetype":"postalcode"
},
  "geometry": {"coordinates":[139.64179999999999,35.9001],"type":"Point"}
}