{
  "type": "Feature",
  "properties": {
    "gn:adm1_name":"Oosakafu",
    "gn:adm2_name":"Oosakashikitaku",
    "gn:name":"Ooyodokita",
    "iso:country":"JP",
    "wof:name":"531-0077",
    "wof:placetype":"postalcode"
},
  "geometry": {"coordinates":[135.4836,34.7068],"type":"Point"}
}