{
  "type": "Feature",
  "properties": {
    "gn:adm1_name":"Kyoutofu",
    "gn:adm2_name":"Kyoutoshinishikyouku",
    "gn:name":"Ooharanotonohatachou",
    "iso:country":"JP",
    "wof:name":"610-1136",
    "wof:placetype":"postalcode"
},
  "geometry": {"coordinates":[135.6223,34.9661],"type":"Point"}
}