{
  "type": "Feature",
  "properties": {
    "gn:adm1_name":"Hyougoken",
    "gn:adm2_name":"Asagogunwadayamachou",
    "gn:name":"Oka",
    "iso:country":"JP",
    "wof:name":"669-5246",
    "wof:placetype":"postalcode"
},
  "geometry": {"coordinates":[134.81030000000001,35.3466],"type":"Point"}
}