{
  "type": "Feature",
  "properties": {
    "gn:adm1_name":"Toyamaken",
    "gn:adm2_name":"Toyamashi",
    "gn:name":"Ishigane",
    "iso:country":"JP",
    "wof:name":"930-0966",
    "wof:placetype":"postalcode"
},
  "geometry": {"coordinates":[137.2355,36.6879],"type":"Point"}
}