{
  "type": "Feature",
  "properties": {
    "gn:adm1_name":"Yamagataken",
    "gn:adm2_name":"Higashiokitamagunkawanishimachi",
    "gn:name":"Takayama",
    "iso:country":"JP",
    "wof:name":"999-0141",
    "wof:placetype":"postalcode"
},
  "geometry": {"coordinates":[140.0889,38.0172],"type":"Point"}
}