{
  "type": "Feature",
  "properties": {
    "gn:adm1_name":"Chibaken",
    "gn:adm2_name":"Kimitsushi",
    "gn:name":"Aoyagi",
    "iso:country":"JP",
    "wof:name":"292-0454",
    "wof:placetype":"postalcode"
},
  "geometry": {"coordinates":[140.0703,35.3039],"type":"Point"}
}