{
  "type": "Feature",
  "properties": {
    "gn:adm1_name":"Niigataken",
    "gn:adm2_name":"Tsubameshi",
    "gn:name":"Midorichou",
    "iso:country":"JP",
    "wof:name":"959-1285",
    "wof:placetype":"postalcode"
},
  "geometry": {"coordinates":[138.9042,37.6616],"type":"Point"}
}