{
  "type": "Feature",
  "properties": {
    "gn:adm1_name":"Ishikawaken",
    "gn:adm2_name":"Mattoushi",
    "gn:name":"Higashimisawanomachi",
    "iso:country":"JP",
    "wof:name":"924-0041",
    "wof:placetype":"postalcode"
},
  "geometry": {"coordinates":[136.5341,36.5068],"type":"Point"}
}