{
  "type": "Feature",
  "properties": {
    "gn:adm1_name":"Ibarakiken",
    "gn:adm2_name":"Hitachishi",
    "gn:name":"Kashimachou",
    "iso:country":"JP",
    "wof:name":"317-0071",
    "wof:placetype":"postalcode"
},
  "geometry": {"coordinates":[140.65119999999999,36.5937],"type":"Point"}
}