{
  "type": "Feature",
  "properties": {
    "gn:adm1_name":"Fukuokaken",
    "gn:adm2_name":"Ongagunmizumakimachi",
    "gn:name":"Korosueminami",
    "iso:country":"JP",
    "wof:name":"807-0025",
    "wof:placetype":"postalcode"
},
  "geometry": {"coordinates":[130.69710000000001,33.8533],"type":"Point"}
}