{
  "type": "Feature",
  "properties": {
    "gn:adm1_name":"Gunmaken",
    "gn:adm2_name":"Ouragunchiyodamachi",
    "gn:name":"Kamigoka",
    "iso:country":"JP",
    "wof:name":"370-0726",
    "wof:placetype":"postalcode"
},
  "geometry": {"coordinates":[139.464,36.1964],"type":"Point"}
}