{
  "type": "Feature",
  "properties": {
    "gn:adm1_name":"Ooitaken",
    "gn:adm2_name":"Usashi",
    "gn:name":"Kitatsurudashinden",
    "iso:country":"JP",
    "wof:name":"872-0013",
    "wof:placetype":"postalcode"
},
  "geometry": {"coordinates":[131.4109,33.563],"type":"Point"}
}