{
  "type": "Feature",
  "properties": {
    "gn:adm1_name":"Hyougoken",
    "gn:adm2_name":"Mikishi",
    "gn:name":"Midorigaokachounishi",
    "iso:country":"JP",
    "wof:name":"673-0531",
    "wof:placetype":"postalcode"
},
  "geometry": {"coordinates":[135.02709999999999,34.7743],"type":"Point"}
}