{
  "type": "Feature",
  "properties": {
    "gn:adm1_name":"Mieken",
    "gn:adm2_name":"Takiguntakichou",
    "gn:name":"Nita",
    "iso:country":"JP",
    "wof:name":"519-2179",
    "wof:placetype":"postalcode"
},
  "geometry": {"coordinates":[136.54750000000001,34.484],"type":"Point"}
}