{
  "type": "Feature",
  "properties": {
    "gn:adm1_name":"Saitamaken",
    "gn:adm2_name":"Kitakatsushikagunsugitomachi",
    "gn:name":"Kinokawa",
    "iso:country":"JP",
    "wof:name":"345-0003",
    "wof:placetype":"postalcode"
},
  "geometry": {"coordinates":[139.80189999999999,36.0376],"type":"Point"}
}