{
  "type": "Feature",
  "properties": {
    "gn:adm1_name":"Fukushimaken",
    "gn:adm2_name":"Soumagun'Iitatemura",
    "gn:name":"Nagadoro",
    "iso:country":"JP",
    "wof:name":"960-1723",
    "wof:placetype":"postalcode"
},
  "geometry": {"coordinates":[140.75729999999999,37.611],"type":"Point"}
}