{
  "type": "Feature",
  "properties": {
    "gn:adm1_name":"Gifuken",
    "gn:adm2_name":"Gifushi",
    "gn:name":"Kawabe",
    "iso:country":"JP",
    "wof:name":"501-1151",
    "wof:placetype":"postalcode"
},
  "geometry": {"coordinates":[136.70920000000001,35.4385],"type":"Point"}
}