{
  "type": "Feature",
  "properties": {
    "gn:adm1_name":"Hiroshimaken",
    "gn:adm2_name":"Higashihiroshimashi",
    "gn:name":"Shiwachoushichijoukabusaka",
    "iso:country":"JP",
    "wof:name":"739-0264",
    "wof:placetype":"postalcode"
},
  "geometry": {"coordinates":[132.65180000000001,34.4654],"type":"Point"}
}