{
  "type": "Feature",
  "properties": {
    "gn:adm1_name":"Chibaken",
    "gn:adm2_name":"Katoriguntakomachi",
    "gn:name":"Hinoki",
    "iso:country":"JP",
    "wof:name":"289-2302",
    "wof:placetype":"postalcode"
},
  "geometry": {"coordinates":[140.46090000000001,35.7847],"type":"Point"}
}