{
  "type": "Feature",
  "properties": {
    "gn:adm1_name":"Niigataken",
    "gn:adm2_name":"Gosenshi",
    "gn:name":"Maoroshi",
    "iso:country":"JP",
    "wof:name":"959-1614",
    "wof:placetype":"postalcode"
},
  "geometry": {"coordinates":[139.2604,37.7368],"type":"Point"}
}