{
  "type": "Feature",
  "properties": {
    "gn:adm1_name":"Ibarakiken",
    "gn:adm2_name":"Kashimagun'Asahimura",
    "gn:name":"Momiyama",
    "iso:country":"JP",
    "wof:name":"311-1426",
    "wof:placetype":"postalcode"
},
  "geometry": {"coordinates":[140.5478,36.1957],"type":"Point"}
}