{
  "type": "Feature",
  "properties": {
    "gn:adm1_name":"Oosakafu",
    "gn:adm2_name":"Oosakashichuuouku",
    "gn:name":"Kitakyuuhoujimachi",
    "iso:country":"JP",
    "wof:name":"541-0057",
    "wof:placetype":"postalcode"
},
  "geometry": {"coordinates":[135.50470000000001,34.68],"type":"Point"}
}