{
  "type": "Feature",
  "properties": {
    "gn:adm1_name":"Kyoutofu",
    "gn:adm2_name":"Ayabeshi",
    "gn:name":"Takatsuchou",
    "iso:country":"JP",
    "wof:name":"623-0045",
    "wof:placetype":"postalcode"
},
  "geometry": {"coordinates":[135.2081,35.3023],"type":"Point"}
}