{
  "type": "Feature",
  "properties": {
    "gn:adm1_name":"Shimaneken",
    "gn:adm2_name":"Goutsushi",
    "gn:name":"Ninomiyachoukamura",
    "iso:country":"JP",
    "wof:name":"695-0023",
    "wof:placetype":"postalcode"
},
  "geometry": {"coordinates":[132.20869999999999,34.9758],"type":"Point"}
}