{
  "type": "Feature",
  "properties": {
    "gn:adm1_name":"Oosakafu",
    "gn:adm2_name":"Kishiwadashi",
    "gn:name":"Harukimiyamotochou",
    "iso:country":"JP",
    "wof:name":"596-0025",
    "wof:placetype":"postalcode"
},
  "geometry": {"coordinates":[135.38550000000001,34.4816],"type":"Point"}
}