{
  "type": "Feature",
  "properties": {
    "gn:adm1_name":"Hyougoken",
    "gn:adm2_name":"Himejishi",
    "gn:name":"Imajuku",
    "iso:country":"JP",
    "wof:name":"670-0052",
    "wof:placetype":"postalcode"
},
  "geometry": {"coordinates":[134.67230000000001,34.8391],"type":"Point"}
}