{
  "type": "Feature",
  "properties": {
    "gn:adm1_name":"Chibaken",
    "gn:adm2_name":"Abikoshi",
    "gn:name":"Tsukushino",
    "iso:country":"JP",
    "wof:name":"270-1164",
    "wof:placetype":"postalcode"
},
  "geometry": {"coordinates":[140.01220000000001,35.8799],"type":"Point"}
}