{
  "type": "Feature",
  "properties": {
    "gn:adm1_name":"Nagasakiken",
    "gn:adm2_name":"Minamitakakigun'Ariakechou",
    "gn:name":"Oomisakibo",
    "iso:country":"JP",
    "wof:name":"859-1415",
    "wof:placetype":"postalcode"
},
  "geometry": {"coordinates":[130.3305,32.8437],"type":"Point"}
}