{
  "type": "Feature",
  "properties": {
    "gn:adm1_name":"Ishikawaken",
    "gn:adm2_name":"Ishikawagunnonoichimachi",
    "gn:name":"Sumiyoshimachi",
    "iso:country":"JP",
    "wof:name":"921-8813",
    "wof:placetype":"postalcode"
},
  "geometry": {"coordinates":[136.61930000000001,36.5269],"type":"Point"}
}