{
  "type": "Feature",
  "properties": {
    "gn:adm1_name":"Naganoken",
    "gn:adm2_name":"Chikumashi",
    "gn:name":"Senbonyanagi",
    "iso:country":"JP",
    "wof:name":"389-0803",
    "wof:placetype":"postalcode"
},
  "geometry": {"coordinates":[138.1301,36.506],"type":"Point"}
}