{
  "type": "Feature",
  "properties": {
    "gn:adm1_name":"Hyougoken",
    "gn:adm2_name":"Koubeshinadaku",
    "gn:name":"Kunitamadoori",
    "iso:country":"JP",
    "wof:name":"657-0816",
    "wof:placetype":"postalcode"
},
  "geometry": {"coordinates":[135.22,34.7183],"type":"Point"}
}