{
  "type": "Feature",
  "properties": {
    "gn:adm1_name":"Niigataken",
    "gn:adm2_name":"Kitauonumagunkoidemachi",
    "gn:name":"Isejimashinden",
    "iso:country":"JP",
    "wof:name":"946-0038",
    "wof:placetype":"postalcode"
},
  "geometry": {"coordinates":[138.9554,37.2055],"type":"Point"}
}