{
  "type": "Feature",
  "properties": {
    "gn:adm1_name":"Tochigiken",
    "gn:adm2_name":"Nasugunminaminasumachi",
    "gn:name":"Kogawara",
    "iso:country":"JP",
    "wof:name":"321-0511",
    "wof:placetype":"postalcode"
},
  "geometry": {"coordinates":[140.10570000000001,36.6576],"type":"Point"}
}