{
  "type": "Feature",
  "properties": {
    "gn:adm1_name":"Ehimeken",
    "gn:adm2_name":"Kitauwagunhiromichou",
    "gn:name":"Konishinono",
    "iso:country":"JP",
    "wof:name":"798-1324",
    "wof:placetype":"postalcode"
},
  "geometry": {"coordinates":[132.7192,33.275],"type":"Point"}
}