{
  "type": "Feature",
  "properties": {
    "gn:adm1_name":"Fukuokaken",
    "gn:adm2_name":"Asakuragunyasumachi",
    "gn:name":"Sangayama",
    "iso:country":"JP",
    "wof:name":"838-0202",
    "wof:placetype":"postalcode"
},
  "geometry": {"coordinates":[130.64709999999999,33.4931],"type":"Point"}
}