{
  "type": "Feature",
  "properties": {
    "gn:adm1_name":"Ibarakiken",
    "gn:adm2_name":"Makabegunkyouwamachi",
    "gn:name":"Hosota",
    "iso:country":"JP",
    "wof:name":"309-1114",
    "wof:placetype":"postalcode"
},
  "geometry": {"coordinates":[140.0333,36.3199],"type":"Point"}
}