{
  "type": "Feature",
  "properties": {
    "gn:adm1_name":"Yamagataken",
    "gn:adm2_name":"Yamagatashi",
    "gn:name":"Sugesawa",
    "iso:country":"JP",
    "wof:name":"990-2362",
    "wof:placetype":"postalcode"
},
  "geometry": {"coordinates":[140.27250000000001,38.2247],"type":"Point"}
}