{
  "type": "Feature",
  "properties": {
    "gn:adm1_name":"Aichiken",
    "gn:adm2_name":"Nagoyashimizuhoku",
    "gn:name":"Idotachou",
    "iso:country":"JP",
    "wof:name":"467-0835",
    "wof:placetype":"postalcode"
},
  "geometry": {"coordinates":[136.92920000000001,35.1192],"type":"Point"}
}