{
  "type": "Feature",
  "properties": {
    "gn:adm1_name":"Mieken",
    "gn:adm2_name":"Owaseshi",
    "gn:name":"Hayashimachi",
    "iso:country":"JP",
    "wof:name":"519-3612",
    "wof:placetype":"postalcode"
},
  "geometry": {"coordinates":[136.19890000000001,34.0712],"type":"Point"}
}