{
  "type": "Feature",
  "properties": {
    "gn:adm1_name":"Toukyouto",
    "gn:adm2_name":"Edogawaku",
    "gn:name":"Higashikoiwa",
    "iso:country":"JP",
    "wof:name":"133-0052",
    "wof:placetype":"postalcode"
},
  "geometry": {"coordinates":[139.89060000000001,35.7291],"type":"Point"}
}