{
  "type": "Feature",
  "properties": {
    "gn:adm1_name":"Shigaken",
    "gn:adm2_name":"Youkaichishi",
    "gn:name":"Takebekaminakachou",
    "iso:country":"JP",
    "wof:name":"527-0002",
    "wof:placetype":"postalcode"
},
  "geometry": {"coordinates":[136.19980000000001,35.1276],"type":"Point"}
}