{
  "type": "Feature",
  "properties": {
    "gn:adm1_name":"Ooitaken",
    "gn:adm2_name":"Usashi",
    "gn:name":"Naka",
    "iso:country":"JP",
    "wof:name":"879-0513",
    "wof:placetype":"postalcode"
},
  "geometry": {"coordinates":[131.28970000000001,33.4997],"type":"Point"}
}