{
  "type": "Feature",
  "properties": {
    "gn:adm1_name":"Fukushimaken",
    "gn:adm2_name":"Aiduwakamatsushi",
    "gn:name":"Joutoumachi",
    "iso:country":"JP",
    "wof:name":"965-0807",
    "wof:placetype":"postalcode"
},
  "geometry": {"coordinates":[139.93680000000001,37.4871],"type":"Point"}
}