{
  "type": "Feature",
  "properties": {
    "gn:adm1_name":"Shizuokaken",
    "gn:adm2_name":"Fujiedashi",
    "gn:name":"Tsuiji",
    "iso:country":"JP",
    "wof:name":"426-0031",
    "wof:placetype":"postalcode"
},
  "geometry": {"coordinates":[138.27209999999999,34.8592],"type":"Point"}
}