{
  "type": "Feature",
  "properties": {
    "gn:adm1_name":"Kumamotoken",
    "gn:adm2_name":"Asogunsoyoumachi",
    "gn:name":"Takigami",
    "iso:country":"JP",
    "wof:name":"861-3902",
    "wof:placetype":"postalcode"
},
  "geometry": {"coordinates":[131.14779999999999,32.6868],"type":"Point"}
}