{
  "type": "Feature",
  "properties": {
    "gn:adm1_name":"Fukuiken",
    "gn:adm2_name":"Yoshidagunmatsuokachou",
    "gn:name":"Shinmei",
    "iso:country":"JP",
    "wof:name":"910-1117",
    "wof:placetype":"postalcode"
},
  "geometry": {"coordinates":[136.30109999999999,36.0941],"type":"Point"}
}