{
  "type": "Feature",
  "properties": {
    "gn:adm1_name":"Kumamotoken",
    "gn:adm2_name":"Kamimashikigunseiwason",
    "gn:name":"Onojiri",
    "iso:country":"JP",
    "wof:name":"861-3844",
    "wof:placetype":"postalcode"
},
  "geometry": {"coordinates":[131.08789999999999,32.6644],"type":"Point"}
}