{
  "type": "Feature",
  "properties": {
    "gn:adm1_name":"Shigaken",
    "gn:adm2_name":"Inukamiguntoyosatochou",
    "gn:name":"Anjikiminami",
    "iso:country":"JP",
    "wof:name":"529-1172",
    "wof:placetype":"postalcode"
},
  "geometry": {"coordinates":[136.22810000000001,35.2058],"type":"Point"}
}