{
  "type": "Feature",
  "properties": {
    "gn:adm1_name":"Chibaken",
    "gn:adm2_name":"Futtsushi",
    "gn:name":"Hanawa",
    "iso:country":"JP",
    "wof:name":"299-1618",
    "wof:placetype":"postalcode"
},
  "geometry": {"coordinates":[139.88730000000001,35.2138],"type":"Point"}
}