{
  "type": "Feature",
  "properties": {
    "gn:adm1_name":"Oosakafu",
    "gn:adm2_name":"Oosakashimiyakojimaku",
    "gn:name":"Miyakojimanakadoori",
    "iso:country":"JP",
    "wof:name":"534-0022",
    "wof:placetype":"postalcode"
},
  "geometry": {"coordinates":[135.53270000000001,34.7043],"type":"Point"}
}