{
  "type": "Feature",
  "properties": {
    "gn:adm1_name":"Shizuokaken",
    "gn:adm2_name":"Kosaishi",
    "gn:name":"Kanza",
    "iso:country":"JP",
    "wof:name":"431-0405",
    "wof:placetype":"postalcode"
},
  "geometry": {"coordinates":[137.49889999999999,34.7388],"type":"Point"}
}