{
  "type": "Feature",
  "properties": {
    "gn:adm1_name":"Hiroshimaken",
    "gn:adm2_name":"Hiroshimashiakiku",
    "gn:name":"Kamisenochou",
    "iso:country":"JP",
    "wof:name":"739-0302",
    "wof:placetype":"postalcode"
},
  "geometry": {"coordinates":[132.63050000000001,34.4252],"type":"Point"}
}