{
  "type": "Feature",
  "properties": {
    "gn:adm1_name":"Toyamaken",
    "gn:adm2_name":"Neigunyatsuomachi",
    "gn:name":"Maruyama",
    "iso:country":"JP",
    "wof:name":"939-2317",
    "wof:placetype":"postalcode"
},
  "geometry": {"coordinates":[137.15780000000001,36.5915],"type":"Point"}
}