{
  "type": "Feature",
  "properties": {
    "gn:adm1_name":"Mieken",
    "gn:adm2_name":"Suzukashi",
    "gn:name":"Hidachou",
    "iso:country":"JP",
    "wof:name":"513-0819",
    "wof:placetype":"postalcode"
},
  "geometry": {"coordinates":[136.59059999999999,34.8753],"type":"Point"}
}