{
  "type": "Feature",
  "properties": {
    "gn:adm1_name":"Fukuokaken",
    "gn:adm2_name":"Kitakyuushuushikokuraminamiku",
    "gn:name":"Kinoshita",
    "iso:country":"JP",
    "wof:name":"803-0184",
    "wof:placetype":"postalcode"
},
  "geometry": {"coordinates":[130.86689999999999,33.7755],"type":"Point"}
}