{
  "type": "Feature",
  "properties": {
    "gn:adm1_name":"Toukyouto",
    "gn:adm2_name":"Taitouku",
    "gn:name":"Uenosakuragi",
    "iso:country":"JP",
    "wof:name":"110-0002",
    "wof:placetype":"postalcode"
},
  "geometry": {"coordinates":[139.77289999999999,35.7221],"type":"Point"}
}