{
  "type": "Feature",
  "properties": {
    "gn:adm1_name":"Sagaken",
    "gn:adm2_name":"Imarishi",
    "gn:name":"Ookawachichouotsu",
    "iso:country":"JP",
    "wof:name":"848-0025",
    "wof:placetype":"postalcode"
},
  "geometry": {"coordinates":[129.893,33.2386],"type":"Point"}
}