{
  "type": "Feature",
  "properties": {
    "gn:adm1_name":"Hiroshimaken",
    "gn:adm2_name":"Ootakeshi",
    "gn:name":"Ogatachouogata",
    "iso:country":"JP",
    "wof:name":"739-0627",
    "wof:placetype":"postalcode"
},
  "geometry": {"coordinates":[132.20079999999999,34.2323],"type":"Point"}
}