{
  "type": "Feature",
  "properties": {
    "gn:adm1_name":"Kumamotoken",
    "gn:adm2_name":"Araoshi",
    "gn:name":"Kamihirayama",
    "iso:country":"JP",
    "wof:name":"864-0014",
    "wof:placetype":"postalcode"
},
  "geometry": {"coordinates":[130.50839999999999,33.0063],"type":"Point"}
}