{
  "type": "Feature",
  "properties": {
    "gn:adm1_name":"Okayamaken",
    "gn:adm2_name":"Mitsugunmitsuchou",
    "gn:name":"Yabara",
    "iso:country":"JP",
    "wof:name":"709-2107",
    "wof:placetype":"postalcode"
},
  "geometry": {"coordinates":[133.94309999999999,34.8032],"type":"Point"}
}