{
  "type": "Feature",
  "properties": {
    "gn:adm1_name":"Toyamaken",
    "gn:adm2_name":"Shimoniikawagun'Asahimachi",
    "gn:name":"Kubota",
    "iso:country":"JP",
    "wof:name":"939-0728",
    "wof:placetype":"postalcode"
},
  "geometry": {"coordinates":[137.5352,36.928],"type":"Point"}
}