{
  "type": "Feature",
  "properties": {
    "gn:adm1_name":"Hyougoken",
    "gn:adm2_name":"Mikatagun'Onsenchou",
    "gn:name":"Chidani",
    "iso:country":"JP",
    "wof:name":"669-6943",
    "wof:placetype":"postalcode"
},
  "geometry": {"coordinates":[134.43170000000001,35.5276],"type":"Point"}
}