{
  "type": "Feature",
  "properties": {
    "gn:adm1_name":"Yamanashiken",
    "gn:adm2_name":"Koufushi",
    "gn:name":"Kitaguchi",
    "iso:country":"JP",
    "wof:name":"400-0024",
    "wof:placetype":"postalcode"
},
  "geometry": {"coordinates":[138.57040000000001,35.669],"type":"Point"}
}