{
  "type": "Feature",
  "properties": {
    "gn:adm1_name":"Oosakafu",
    "gn:adm2_name":"Ikedashi",
    "gn:name":"Kibechou",
    "iso:country":"JP",
    "wof:name":"563-0014",
    "wof:placetype":"postalcode"
},
  "geometry": {"coordinates":[135.42679999999999,34.8382],"type":"Point"}
}