{
  "type": "Feature",
  "properties": {
    "gn:adm1_name":"Toukyouto",
    "gn:adm2_name":"Setagayaku",
    "gn:name":"Chitosedai",
    "iso:country":"JP",
    "wof:name":"157-0071",
    "wof:placetype":"postalcode"
},
  "geometry": {"coordinates":[139.61240000000001,35.6522],"type":"Point"}
}