{
  "type": "Feature",
  "properties": {
    "gn:adm1_name":"Fukuokaken",
    "gn:adm2_name":"Kitakyuushuushikokuraminamiku",
    "gn:name":"Kikugaoka",
    "iso:country":"JP",
    "wof:name":"802-0981",
    "wof:placetype":"postalcode"
},
  "geometry": {"coordinates":[130.87530000000001,33.8261],"type":"Point"}
}