{
  "type": "Feature",
  "properties": {
    "gn:adm1_name":"Kyoutofu",
    "gn:adm2_name":"Fukuchiyamashi",
    "gn:name":"Sukumoduka",
    "iso:country":"JP",
    "wof:name":"620-0956",
    "wof:placetype":"postalcode"
},
  "geometry": {"coordinates":[135.07499999999999,35.2913],"type":"Point"}
}