{
  "type": "Feature",
  "properties": {
    "gn:adm1_name":"Yamaguchiken",
    "gn:adm2_name":"Kugagunshuutouchou",
    "gn:name":"Kamikubara",
    "iso:country":"JP",
    "wof:name":"742-0413",
    "wof:placetype":"postalcode"
},
  "geometry": {"coordinates":[132.06139999999999,34.0777],"type":"Point"}
}