{
  "type": "Feature",
  "properties": {
    "gn:adm1_name":"Fukuokaken",
    "gn:adm2_name":"Kitakyuushuushikokuraminamiku",
    "gn:name":"Ideura",
    "iso:country":"JP",
    "wof:name":"803-0189",
    "wof:placetype":"postalcode"
},
  "geometry": {"coordinates":[130.88329999999999,33.7777],"type":"Point"}
}