{
  "type": "Feature",
  "properties": {
    "gn:adm1_name":"Shigaken",
    "gn:adm2_name":"Higashiazaigun'Azaichou",
    "gn:name":"Nishikazue",
    "iso:country":"JP",
    "wof:name":"526-0227",
    "wof:placetype":"postalcode"
},
  "geometry": {"coordinates":[136.32820000000001,35.4031],"type":"Point"}
}