{
  "type": "Feature",
  "properties": {
    "gn:adm1_name":"Miyagiken",
    "gn:adm2_name":"Kesennumashi",
    "gn:name":"Minamimachi",
    "iso:country":"JP",
    "wof:name":"988-0017",
    "wof:placetype":"postalcode"
},
  "geometry": {"coordinates":[141.5736,38.9049],"type":"Point"}
}