{
  "type": "Feature",
  "properties": {
    "gn:adm1_name":"Kyoutofu",
    "gn:adm2_name":"Yawatashi",
    "gn:name":"Minoyamahiruduka",
    "iso:country":"JP",
    "wof:name":"614-8271",
    "wof:placetype":"postalcode"
},
  "geometry": {"coordinates":[135.7115,34.8564],"type":"Point"}
}