{
  "type": "Feature",
  "properties": {
    "gn:adm1_name":"Fukushimaken",
    "gn:adm2_name":"Iwakishi",
    "gn:name":"Uedamachi",
    "iso:country":"JP",
    "wof:name":"974-8261",
    "wof:placetype":"postalcode"
},
  "geometry": {"coordinates":[140.79689999999999,36.9188],"type":"Point"}
}