{
  "type": "Feature",
  "properties": {
    "gn:adm1_name":"Kagoshimaken",
    "gn:adm2_name":"Ooshimagunsetouchichou",
    "gn:name":"Ikomo",
    "iso:country":"JP",
    "wof:name":"894-2236",
    "wof:placetype":"postalcode"
},
  "geometry": {"coordinates":[129.24299999999999,28.1076],"type":"Point"}
}