{
  "type": "Feature",
  "properties": {
    "gn:adm1_name":"Fukuokaken",
    "gn:adm2_name":"Nakamashi",
    "gn:name":"Nagatsu",
    "iso:country":"JP",
    "wof:name":"809-0036",
    "wof:placetype":"postalcode"
},
  "geometry": {"coordinates":[130.70750000000001,33.8264],"type":"Point"}
}