{
  "type": "Feature",
  "properties": {
    "gn:adm1_name":"Hyougoken",
    "gn:adm2_name":"Takasagoshi",
    "gn:name":"Takasagochousakaemachi",
    "iso:country":"JP",
    "wof:name":"676-0038",
    "wof:placetype":"postalcode"
},
  "geometry": {"coordinates":[134.80279999999999,34.7503],"type":"Point"}
}