{
  "type": "Feature",
  "properties": {
    "gn:adm1_name":"Ooitaken",
    "gn:adm2_name":"Beppushi",
    "gn:name":"Shouningahamachou",
    "iso:country":"JP",
    "wof:name":"874-0023",
    "wof:placetype":"postalcode"
},
  "geometry": {"coordinates":[131.5001,33.3147],"type":"Point"}
}