{
  "type": "Feature",
  "properties": {
    "gn:adm1_name":"Tochigiken",
    "gn:adm2_name":"Shioyagun'Ujiiemachi",
    "gn:name":"Kitakusagawa",
    "iso:country":"JP",
    "wof:name":"329-1322",
    "wof:placetype":"postalcode"
},
  "geometry": {"coordinates":[139.95320000000001,36.6879],"type":"Point"}
}