{
  "type": "Feature",
  "properties": {
    "gn:adm1_name":"Gifuken",
    "gn:adm2_name":"Sekishi",
    "gn:name":"Minamitenjin",
    "iso:country":"JP",
    "wof:name":"501-3918",
    "wof:placetype":"postalcode"
},
  "geometry": {"coordinates":[136.93369999999999,35.4781],"type":"Point"}
}