{
  "type": "Feature",
  "properties": {
    "gn:adm1_name":"Hyougoken",
    "gn:adm2_name":"Koubeshichuuouku",
    "gn:name":"Motomachidoori",
    "iso:country":"JP",
    "wof:name":"650-0022",
    "wof:placetype":"postalcode"
},
  "geometry": {"coordinates":[135.18450000000001,34.6869],"type":"Point"}
}