{
  "type": "Feature",
  "properties": {
    "gn:adm1_name":"Yamagataken",
    "gn:adm2_name":"Nishiokitamagun'Iidemachi",
    "gn:name":"Ikanikeisaiganaibaai",
    "iso:country":"JP",
    "wof:name":"999-0600",
    "wof:placetype":"postalcode"
},
  "geometry": {"coordinates":[140.01689999999999,38.0287],"type":"Point"}
}