{
  "type": "Feature",
  "properties": {
    "gn:adm1_name":"Fukuokaken",
    "gn:adm2_name":"Kitakyuushuushitobataku",
    "gn:name":"Hatsunechou",
    "iso:country":"JP",
    "wof:name":"804-0066",
    "wof:placetype":"postalcode"
},
  "geometry": {"coordinates":[130.82130000000001,33.8941],"type":"Point"}
}