{
  "type": "Feature",
  "properties": {
    "gn:adm1_name":"Aichiken",
    "gn:adm2_name":"Hekinanshi",
    "gn:name":"Genjishinmeimachi",
    "iso:country":"JP",
    "wof:name":"447-0872",
    "wof:placetype":"postalcode"
},
  "geometry": {"coordinates":[136.9975,34.8824],"type":"Point"}
}