{
  "type": "Feature",
  "properties": {
    "gn:adm1_name":"Yamagataken",
    "gn:adm2_name":"Yamagatashi",
    "gn:name":"Yoshinojuku",
    "iso:country":"JP",
    "wof:name":"990-0883",
    "wof:placetype":"postalcode"
},
  "geometry": {"coordinates":[140.2929,38.2855],"type":"Point"}
}