{
  "type": "Feature",
  "properties": {
    "gn:adm1_name":"Gunmaken",
    "gn:adm2_name":"Numatashi",
    "gn:name":"Kuyaharamachi",
    "iso:country":"JP",
    "wof:name":"378-0005",
    "wof:placetype":"postalcode"
},
  "geometry": {"coordinates":[139.0977,36.6636],"type":"Point"}
}