{
  "type": "Feature",
  "properties": {
    "gn:adm1_name":"Ishikawaken",
    "gn:adm2_name":"Ishikawaguntsurugimachi",
    "gn:name":"Sakajirimachi",
    "iso:country":"JP",
    "wof:name":"920-2102",
    "wof:placetype":"postalcode"
},
  "geometry": {"coordinates":[136.61580000000001,36.4832],"type":"Point"}
}