{
  "type": "Feature",
  "properties": {
    "gn:adm1_name":"Fukuokaken",
    "gn:adm2_name":"Mizumagun'Ookimachi",
    "gn:name":"Oozumi",
    "iso:country":"JP",
    "wof:name":"830-0403",
    "wof:placetype":"postalcode"
},
  "geometry": {"coordinates":[130.44970000000001,33.2262],"type":"Point"}
}