{
  "type": "Feature",
  "properties": {
    "gn:adm1_name":"Niigataken",
    "gn:adm2_name":"Niigatashi",
    "gn:name":"Furuminatomachi",
    "iso:country":"JP",
    "wof:name":"950-0044",
    "wof:placetype":"postalcode"
},
  "geometry": {"coordinates":[139.0712,37.9381],"type":"Point"}
}