{
  "type": "Feature",
  "properties": {
    "gn:adm1_name":"Kouchiken",
    "gn:adm2_name":"Kouchishi",
    "gn:name":"Nishimachi",
    "iso:country":"JP",
    "wof:name":"780-0925",
    "wof:placetype":"postalcode"
},
  "geometry": {"coordinates":[133.5206,33.5592],"type":"Point"}
}