{
  "type": "Feature",
  "properties": {
    "gn:adm1_name":"Kanagawaken",
    "gn:adm2_name":"Yokosukashi",
    "gn:name":"Sahara",
    "iso:country":"JP",
    "wof:name":"239-0835",
    "wof:placetype":"postalcode"
},
  "geometry": {"coordinates":[139.68539999999999,35.2387],"type":"Point"}
}