{
  "type": "Feature",
  "properties": {
    "gn:adm1_name":"Kanagawaken",
    "gn:adm2_name":"Yokosukashi",
    "gn:name":"Tauraminatochou",
    "iso:country":"JP",
    "wof:name":"237-0071",
    "wof:placetype":"postalcode"
},
  "geometry": {"coordinates":[139.63800000000001,35.2946],"type":"Point"}
}