{
  "type": "Feature",
  "properties": {
    "gn:adm1_name":"Saitamaken",
    "gn:adm2_name":"Honjoushi",
    "gn:name":"Wakaizumi",
    "iso:country":"JP",
    "wof:name":"367-0055",
    "wof:placetype":"postalcode"
},
  "geometry": {"coordinates":[139.1858,36.2474],"type":"Point"}
}