{
  "type": "Feature",
  "properties": {
    "gn:adm1_name":"Aichiken",
    "gn:adm2_name":"Komakishi",
    "gn:name":"Noguchi",
    "iso:country":"JP",
    "wof:name":"485-0806",
    "wof:placetype":"postalcode"
},
  "geometry": {"coordinates":[136.99180000000001,35.3145],"type":"Point"}
}