{
  "type": "Feature",
  "properties": {
    "gn:adm1_name":"Okayamaken",
    "gn:adm2_name":"Shitsukigunyoshiichou",
    "gn:name":"Kamishigi",
    "iso:country":"JP",
    "wof:name":"714-2232",
    "wof:placetype":"postalcode"
},
  "geometry": {"coordinates":[133.3948,34.695],"type":"Point"}
}