{
  "type": "Feature",
  "properties": {
    "gn:adm1_name":"Ibarakiken",
    "gn:adm2_name":"Namegatagun'Asoumachi",
    "gn:name":"Igai",
    "iso:country":"JP",
    "wof:name":"311-3803",
    "wof:placetype":"postalcode"
},
  "geometry": {"coordinates":[140.4813,36.0443],"type":"Point"}
}