{
  "type": "Feature",
  "properties": {
    "gn:adm1_name":"Naraken",
    "gn:adm2_name":"Yamatotakadashi",
    "gn:name":"Hongouchou",
    "iso:country":"JP",
    "wof:name":"635-0082",
    "wof:placetype":"postalcode"
},
  "geometry": {"coordinates":[135.7448,34.5141],"type":"Point"}
}