{
  "type": "Feature",
  "properties": {
    "gn:adm1_name":"Kyoutofu",
    "gn:adm2_name":"Kyoutoshiukyouku",
    "gn:name":"Uzumasasugamotochou",
    "iso:country":"JP",
    "wof:name":"616-8126",
    "wof:placetype":"postalcode"
},
  "geometry": {"coordinates":[135.70769999999999,35.0107],"type":"Point"}
}