{
  "type": "Feature",
  "properties": {
    "gn:adm1_name":"Gifuken",
    "gn:adm2_name":"Sekishi",
    "gn:name":"Yayoichou",
    "iso:country":"JP",
    "wof:name":"501-3902",
    "wof:placetype":"postalcode"
},
  "geometry": {"coordinates":[136.9282,35.4778],"type":"Point"}
}