{
  "type": "Feature",
  "properties": {
    "gn:adm1_name":"Fukushimaken",
    "gn:adm2_name":"Shirakawashi",
    "gn:name":"Onigoeyama",
    "iso:country":"JP",
    "wof:name":"961-0887",
    "wof:placetype":"postalcode"
},
  "geometry": {"coordinates":[140.19900000000001,37.1104],"type":"Point"}
}