{
  "type": "Feature",
  "properties": {
    "gn:adm1_name":"Aichiken",
    "gn:adm2_name":"Kounanshi",
    "gn:name":"Hannyachoumaeyama",
    "iso:country":"JP",
    "wof:name":"483-8017",
    "wof:placetype":"postalcode"
},
  "geometry": {"coordinates":[136.88550000000001,35.3634],"type":"Point"}
}