{
  "type": "Feature",
  "properties": {
    "gn:adm1_name":"Tochigiken",
    "gn:adm2_name":"Nasugunminaminasumachi",
    "gn:name":"Shimokawai",
    "iso:country":"JP",
    "wof:name":"321-0504",
    "wof:placetype":"postalcode"
},
  "geometry": {"coordinates":[140.0881,36.6991],"type":"Point"}
}