{
  "type": "Feature",
  "properties": {
    "gn:adm1_name":"Oosakafu",
    "gn:adm2_name":"Hirakatashi",
    "gn:name":"Deguchi",
    "iso:country":"JP",
    "wof:name":"573-0065",
    "wof:placetype":"postalcode"
},
  "geometry": {"coordinates":[135.62469999999999,34.8005],"type":"Point"}
}