{
  "type": "Feature",
  "properties": {
    "gn:adm1_name":"Naganoken",
    "gn:adm2_name":"Suzakashi",
    "gn:name":"Yabumachi",
    "iso:country":"JP",
    "wof:name":"382-0094",
    "wof:placetype":"postalcode"
},
  "geometry": {"coordinates":[138.3066,36.6486],"type":"Point"}
}