{
  "type": "Feature",
  "properties": {
    "gn:adm1_name":"Toyamaken",
    "gn:adm2_name":"Toyamashi",
    "gn:name":"Higashiishiganemachi",
    "iso:country":"JP",
    "wof:name":"930-0964",
    "wof:placetype":"postalcode"
},
  "geometry": {"coordinates":[137.239,36.6842],"type":"Point"}
}