{
  "type": "Feature",
  "properties": {
    "gn:adm1_name":"Aichiken",
    "gn:adm2_name":"Inazawashi",
    "gn:name":"Kitaichibaminamimachi",
    "iso:country":"JP",
    "wof:name":"492-8175",
    "wof:placetype":"postalcode"
},
  "geometry": {"coordinates":[136.8313,35.2223],"type":"Point"}
}