{
  "type": "Feature",
  "properties": {
    "gn:adm1_name":"Nagasakiken",
    "gn:adm2_name":"Higashisonogigunhigashisonogichou",
    "gn:name":"Chiwatashukugou",
    "iso:country":"JP",
    "wof:name":"859-3921",
    "wof:placetype":"postalcode"
},
  "geometry": {"coordinates":[129.9359,33.0249],"type":"Point"}
}