{
  "type": "Feature",
  "properties": {
    "gn:adm1_name":"Kumamotoken",
    "gn:adm2_name":"Minamatashi",
    "gn:name":"Hamamachi",
    "iso:country":"JP",
    "wof:name":"867-0065",
    "wof:placetype":"postalcode"
},
  "geometry": {"coordinates":[130.40270000000001,32.2118],"type":"Point"}
}