{
  "type": "Feature",
  "properties": {
    "gn:adm1_name":"Toukyouto",
    "gn:adm2_name":"Shinjukuku",
    "gn:name":"Nakaochiai",
    "iso:country":"JP",
    "wof:name":"161-0032",
    "wof:placetype":"postalcode"
},
  "geometry": {"coordinates":[139.6884,35.7194],"type":"Point"}
}