{
  "type": "Feature",
  "properties": {
    "gn:adm1_name":"Mieken",
    "gn:adm2_name":"Suzukashi",
    "gn:name":"Shounohayama",
    "iso:country":"JP",
    "wof:name":"513-0834",
    "wof:placetype":"postalcode"
},
  "geometry": {"coordinates":[136.52770000000001,34.8724],"type":"Point"}
}