{
  "type": "Feature",
  "properties": {
    "gn:adm1_name":"Gunmaken",
    "gn:adm2_name":"Gunmagunmisatomachi",
    "gn:name":"Kamishiba",
    "iso:country":"JP",
    "wof:name":"370-3104",
    "wof:placetype":"postalcode"
},
  "geometry": {"coordinates":[138.95840000000001,36.3884],"type":"Point"}
}