{
  "type": "Feature",
  "properties": {
    "gn:adm1_name":"Hyougoken",
    "gn:adm2_name":"Izushiguntantouchou",
    "gn:name":"Okufuji",
    "iso:country":"JP",
    "wof:name":"668-0343",
    "wof:placetype":"postalcode"
},
  "geometry": {"coordinates":[135.03190000000001,35.5106],"type":"Point"}
}