{
  "type": "Feature",
  "properties": {
    "gn:adm1_name":"Yamagataken",
    "gn:adm2_name":"Yamagatashi",
    "gn:name":"Omotezaou",
    "iso:country":"JP",
    "wof:name":"990-2307",
    "wof:placetype":"postalcode"
},
  "geometry": {"coordinates":[140.3135,38.1898],"type":"Point"}
}