{
  "type": "Feature",
  "properties": {
    "gn:adm1_name":"Shizuokaken",
    "gn:adm2_name":"Shizuokashi",
    "gn:name":"Shimizushimonomidorichou",
    "iso:country":"JP",
    "wof:name":"424-0013",
    "wof:placetype":"postalcode"
},
  "geometry": {"coordinates":[138.4676,35.0324],"type":"Point"}
}