{
  "type": "Feature",
  "properties": {
    "gn:adm1_name":"Hiroshimaken",
    "gn:adm2_name":"Toyotagunsetodachou",
    "gn:name":"Mitera",
    "iso:country":"JP",
    "wof:name":"722-2401",
    "wof:placetype":"postalcode"
},
  "geometry": {"coordinates":[133.11689999999999,34.2781],"type":"Point"}
}