{
  "type": "Feature",
  "properties": {
    "gn:adm1_name":"Oosakafu",
    "gn:adm2_name":"Oosakashisumiyoshiku",
    "gn:name":"Tonotsuji",
    "iso:country":"JP",
    "wof:name":"558-0042",
    "wof:placetype":"postalcode"
},
  "geometry": {"coordinates":[135.49889999999999,34.6062],"type":"Point"}
}