{
  "type": "Feature",
  "properties": {
    "gn:adm1_name":"Miyagiken",
    "gn:adm2_name":"Sendaishimiyaginoku",
    "gn:name":"Kurumamachi",
    "iso:country":"JP",
    "wof:name":"983-0863",
    "wof:placetype":"postalcode"
},
  "geometry": {"coordinates":[140.88550000000001,38.2639],"type":"Point"}
}