{
  "type": "Feature",
  "properties": {
    "gn:adm1_name":"Kyoutofu",
    "gn:adm2_name":"Kyoutoshihigashiyamaku",
    "gn:name":"Horiikechou",
    "iso:country":"JP",
    "wof:name":"605-0038",
    "wof:placetype":"postalcode"
},
  "geometry": {"coordinates":[135.7817,35.01],"type":"Point"}
}