{
  "type": "Feature",
  "properties": {
    "gn:adm1_name":"Kagawaken",
    "gn:adm2_name":"Sanukishi",
    "gn:name":"Ookawamachitomidahigashi",
    "iso:country":"JP",
    "wof:name":"761-0903",
    "wof:placetype":"postalcode"
},
  "geometry": {"coordinates":[134.25239999999999,34.2635],"type":"Point"}
}