{
  "type": "Feature",
  "properties": {
    "gn:adm1_name":"Ooitaken",
    "gn:adm2_name":"Tsukumishi",
    "gn:name":"Ajiro",
    "iso:country":"JP",
    "wof:name":"879-2682",
    "wof:placetype":"postalcode"
},
  "geometry": {"coordinates":[131.92570000000001,33.0719],"type":"Point"}
}