{
  "type": "Feature",
  "properties": {
    "gn:adm1_name":"Yamaguchiken",
    "gn:adm2_name":"Shimonosekishi",
    "gn:name":"Hayamachou",
    "iso:country":"JP",
    "wof:name":"750-0046",
    "wof:placetype":"postalcode"
},
  "geometry": {"coordinates":[130.9263,33.9695],"type":"Point"}
}