{
  "type": "Feature",
  "properties": {
    "gn:adm1_name":"Toukyouto",
    "gn:adm2_name":"Fussashi",
    "gn:name":"Minamiden'En",
    "iso:country":"JP",
    "wof:name":"197-0004",
    "wof:placetype":"postalcode"
},
  "geometry": {"coordinates":[139.33090000000001,35.7263],"type":"Point"}
}