{
  "type": "Feature",
  "properties": {
    "gn:adm1_name":"Kyoutofu",
    "gn:adm2_name":"Yawatashi",
    "gn:name":"Kawaguchihama",
    "iso:country":"JP",
    "wof:name":"614-8101",
    "wof:placetype":"postalcode"
},
  "geometry": {"coordinates":[135.71870000000001,34.8788],"type":"Point"}
}