{
  "type": "Feature",
  "properties": {
    "gn:adm1_name":"Toyamaken",
    "gn:adm2_name":"Uodushi",
    "gn:name":"Kawaberi",
    "iso:country":"JP",
    "wof:name":"937-0856",
    "wof:placetype":"postalcode"
},
  "geometry": {"coordinates":[137.39869999999999,36.7947],"type":"Point"}
}