{
  "type": "Feature",
  "properties": {
    "gn:adm1_name":"Gifuken",
    "gn:adm2_name":"Oonogunnyuukawamura",
    "gn:name":"Kute",
    "iso:country":"JP",
    "wof:name":"506-2252",
    "wof:placetype":"postalcode"
},
  "geometry": {"coordinates":[137.48949999999999,36.1777],"type":"Point"}
}