{
  "type": "Feature",
  "properties": {
    "gn:adm1_name":"Toyamaken",
    "gn:adm2_name":"Tonamishi",
    "gn:name":"Miyashin",
    "iso:country":"JP",
    "wof:name":"939-1403",
    "wof:placetype":"postalcode"
},
  "geometry": {"coordinates":[137.0274,36.65],"type":"Point"}
}