{
  "type": "Feature",
  "properties": {
    "gn:adm1_name":"Toyamaken",
    "gn:adm2_name":"Takaokashi",
    "gn:name":"Fushikikofu",
    "iso:country":"JP",
    "wof:name":"933-0114",
    "wof:placetype":"postalcode"
},
  "geometry": {"coordinates":[137.04990000000001,36.7906],"type":"Point"}
}