{
  "type": "Feature",
  "properties": {
    "gn:adm1_name":"Kyoutofu",
    "gn:adm2_name":"Kyoutoshikamigyouku",
    "gn:name":"Shimonochou",
    "iso:country":"JP",
    "wof:name":"602-8365",
    "wof:placetype":"postalcode"
},
  "geometry": {"coordinates":[135.73609999999999,35.0194],"type":"Point"}
}