{
  "type": "Feature",
  "properties": {
    "gn:adm1_name":"Fukuokaken",
    "gn:adm2_name":"Munakatagunfukumamachi",
    "gn:name":"Yatsunami",
    "iso:country":"JP",
    "wof:name":"811-3201",
    "wof:placetype":"postalcode"
},
  "geometry": {"coordinates":[130.5299,33.7721],"type":"Point"}
}