{
  "type": "Feature",
  "properties": {
    "gn:adm1_name":"Ishikawaken",
    "gn:adm2_name":"Kahokugunnanatsukamachi",
    "gn:name":"Kidu",
    "iso:country":"JP",
    "wof:name":"929-1171",
    "wof:placetype":"postalcode"
},
  "geometry": {"coordinates":[136.70760000000001,36.7481],"type":"Point"}
}