{
  "type": "Feature",
  "properties": {
    "gn:adm1_name":"Hyougoken",
    "gn:adm2_name":"Kinosakigunhidakachou",
    "gn:name":"Tsuruoka",
    "iso:country":"JP",
    "wof:name":"669-5313",
    "wof:placetype":"postalcode"
},
  "geometry": {"coordinates":[134.78399999999999,35.4732],"type":"Point"}
}