{
  "type": "Feature",
  "properties": {
    "gn:adm1_name":"Miyagiken",
    "gn:adm2_name":"Igugunmarumorimachi",
    "gn:name":"Nozokikita",
    "iso:country":"JP",
    "wof:name":"981-2162",
    "wof:placetype":"postalcode"
},
  "geometry": {"coordinates":[140.76750000000001,37.9152],"type":"Point"}
}