{
  "type": "Feature",
  "properties": {
    "gn:adm1_name":"Shimaneken",
    "gn:adm2_name":"Ooharagunkamomachi",
    "gn:name":"Mijiro",
    "iso:country":"JP",
    "wof:name":"699-1122",
    "wof:placetype":"postalcode"
},
  "geometry": {"coordinates":[132.8844,35.3304],"type":"Point"}
}