{
  "type": "Feature",
  "properties": {
    "gn:adm1_name":"Ehimeken",
    "gn:adm2_name":"Kitauwagunmimachou",
    "gn:name":"Kanadou",
    "iso:country":"JP",
    "wof:name":"798-1134",
    "wof:placetype":"postalcode"
},
  "geometry": {"coordinates":[132.6336,33.2957],"type":"Point"}
}