{
  "type": "Feature",
  "properties": {
    "gn:adm1_name":"Aichiken",
    "gn:adm2_name":"Owariasahishi",
    "gn:name":"Hirakogaokachou",
    "iso:country":"JP",
    "wof:name":"488-0876",
    "wof:placetype":"postalcode"
},
  "geometry": {"coordinates":[137.01499999999999,35.2221],"type":"Point"}
}