{
  "type": "Feature",
  "properties": {
    "gn:adm1_name":"Yamanashiken",
    "gn:adm2_name":"Minamitsurugundoushimura",
    "gn:name":"Nagamata",
    "iso:country":"JP",
    "wof:name":"402-0228",
    "wof:placetype":"postalcode"
},
  "geometry": {"coordinates":[138.95330000000001,35.4772],"type":"Point"}
}