{
  "type": "Feature",
  "properties": {
    "gn:adm1_name":"Niigataken",
    "gn:adm2_name":"Minamiuonumagunmuikamachi",
    "gn:name":"Uenohara",
    "iso:country":"JP",
    "wof:name":"949-6637",
    "wof:placetype":"postalcode"
},
  "geometry": {"coordinates":[138.84649999999999,37.072],"type":"Point"}
}