{
  "type": "Feature",
  "properties": {
    "gn:adm1_name":"Okayamaken",
    "gn:adm2_name":"Kojimagunnadasakichou",
    "gn:name":"Hazakawa",
    "iso:country":"JP",
    "wof:name":"709-1211",
    "wof:placetype":"postalcode"
},
  "geometry": {"coordinates":[133.87899999999999,34.5347],"type":"Point"}
}