{
  "type": "Feature",
  "properties": {
    "gn:adm1_name":"Oosakafu",
    "gn:adm2_name":"Habikinoshi",
    "gn:name":"Furuichi",
    "iso:country":"JP",
    "wof:name":"583-0852",
    "wof:placetype":"postalcode"
},
  "geometry": {"coordinates":[135.61109999999999,34.5477],"type":"Point"}
}