{
  "type": "Feature",
  "properties": {
    "gn:adm1_name":"Hiroshimaken",
    "gn:adm2_name":"Hiroshimashihigashiku",
    "gn:name":"Hesakashinmachi",
    "iso:country":"JP",
    "wof:name":"732-0012",
    "wof:placetype":"postalcode"
},
  "geometry": {"coordinates":[132.4973,34.4271],"type":"Point"}
}