{
  "type": "Feature",
  "properties": {
    "gn:adm1_name":"Tochigiken",
    "gn:adm2_name":"Yaitashi",
    "gn:name":"Hariu",
    "iso:country":"JP",
    "wof:name":"329-2122",
    "wof:placetype":"postalcode"
},
  "geometry": {"coordinates":[139.9383,36.8161],"type":"Point"}
}