{
  "type": "Feature",
  "properties": {
    "gn:adm1_name":"Shizuokaken",
    "gn:adm2_name":"Iwatashi",
    "gn:name":"Higashiyama",
    "iso:country":"JP",
    "wof:name":"438-0028",
    "wof:placetype":"postalcode"
},
  "geometry": {"coordinates":[137.87469999999999,34.7229],"type":"Point"}
}