{
  "type": "Feature",
  "properties": {
    "gn:adm1_name":"Ishikawaken",
    "gn:adm2_name":"Kanazawashi",
    "gn:name":"Sugiuramachi",
    "iso:country":"JP",
    "wof:name":"920-0972",
    "wof:placetype":"postalcode"
},
  "geometry": {"coordinates":[136.65549999999999,36.5551],"type":"Point"}
}