{
  "type": "Feature",
  "properties": {
    "gn:adm1_name":"Oosakafu",
    "gn:adm2_name":"Kashiwarashi",
    "gn:name":"Enmyouchou",
    "iso:country":"JP",
    "wof:name":"582-0027",
    "wof:placetype":"postalcode"
},
  "geometry": {"coordinates":[135.62530000000001,34.5581],"type":"Point"}
}