{
  "type": "Feature",
  "properties": {
    "gn:adm1_name":"Hiroshimaken",
    "gn:adm2_name":"Yamagatagunkakechou",
    "gn:name":"Shimotsutsuga",
    "iso:country":"JP",
    "wof:name":"731-3621",
    "wof:placetype":"postalcode"
},
  "geometry": {"coordinates":[132.2972,34.5924],"type":"Point"}
}