{
  "type": "Feature",
  "properties": {
    "gn:adm1_name":"Miyagiken",
    "gn:adm2_name":"Kuriharagunkannarichou",
    "gn:name":"Irinosawa",
    "iso:country":"JP",
    "wof:name":"989-5118",
    "wof:placetype":"postalcode"
},
  "geometry": {"coordinates":[141.07220000000001,38.8407],"type":"Point"}
}