{
  "type": "Feature",
  "properties": {
    "gn:adm1_name":"Hiroshimaken",
    "gn:adm2_name":"Onomichishi",
    "gn:name":"Fukuchichou",
    "iso:country":"JP",
    "wof:name":"722-0005",
    "wof:placetype":"postalcode"
},
  "geometry": {"coordinates":[133.15870000000001,34.3978],"type":"Point"}
}