{
  "type": "Feature",
  "properties": {
    "gn:adm1_name":"Toukyouto",
    "gn:adm2_name":"Akishimashi",
    "gn:name":"Jougawarachou",
    "iso:country":"JP",
    "wof:name":"196-0011",
    "wof:placetype":"postalcode"
},
  "geometry": {"coordinates":[139.3603,35.7087],"type":"Point"}
}