{
  "type": "Feature",
  "properties": {
    "gn:adm1_name":"Tochigiken",
    "gn:adm2_name":"Yaitashi",
    "gn:name":"Toyoda",
    "iso:country":"JP",
    "wof:name":"329-2133",
    "wof:placetype":"postalcode"
},
  "geometry": {"coordinates":[139.97819999999999,36.8084],"type":"Point"}
}