{
  "type": "Feature",
  "properties": {
    "gn:adm1_name":"Kanagawaken",
    "gn:adm2_name":"Yokohamashinishiku",
    "gn:name":"Motokubochou",
    "iso:country":"JP",
    "wof:name":"220-0063",
    "wof:placetype":"postalcode"
},
  "geometry": {"coordinates":[139.60550000000001,35.4444],"type":"Point"}
}