{
  "type": "Feature",
  "properties": {
    "gn:adm1_name":"Hiroshimaken",
    "gn:adm2_name":"Shoubarashi",
    "gn:name":"Mizukoshichou",
    "iso:country":"JP",
    "wof:name":"729-6141",
    "wof:placetype":"postalcode"
},
  "geometry": {"coordinates":[132.91220000000001,34.8427],"type":"Point"}
}