{
  "type": "Feature",
  "properties": {
    "gn:adm1_name":"Kagoshimaken",
    "gn:adm2_name":"Hiokigun'Ijuuinchou",
    "gn:name":"Myouenji",
    "iso:country":"JP",
    "wof:name":"899-2503",
    "wof:placetype":"postalcode"
},
  "geometry": {"coordinates":[130.3946,31.6438],"type":"Point"}
}