{
  "type": "Feature",
  "properties": {
    "gn:adm1_name":"Naraken",
    "gn:adm2_name":"Narashi",
    "gn:name":"Saidaijishin'Ikechou",
    "iso:country":"JP",
    "wof:name":"631-0834",
    "wof:placetype":"postalcode"
},
  "geometry": {"coordinates":[135.77199999999999,34.6942],"type":"Point"}
}