{
  "type": "Feature",
  "properties": {
    "gn:adm1_name":"Niigataken",
    "gn:adm2_name":"Ryoutsushi",
    "gn:name":"Haniu",
    "iso:country":"JP",
    "wof:name":"952-3434",
    "wof:placetype":"postalcode"
},
  "geometry": {"coordinates":[138.52860000000001,38.0733],"type":"Point"}
}