{
  "type": "Feature",
  "properties": {
    "gn:adm1_name":"Tottoriken",
    "gn:adm2_name":"Kurayoshishi",
    "gn:name":"Nishiiwakuramachi",
    "iso:country":"JP",
    "wof:name":"682-0874",
    "wof:placetype":"postalcode"
},
  "geometry": {"coordinates":[133.8176,35.4325],"type":"Point"}
}