{
  "type": "Feature",
  "properties": {
    "gn:adm1_name":"Miyagiken",
    "gn:adm2_name":"Ishinomakishi",
    "gn:name":"Hiyorigaoka",
    "iso:country":"JP",
    "wof:name":"986-0833",
    "wof:placetype":"postalcode"
},
  "geometry": {"coordinates":[141.3038,38.4242],"type":"Point"}
}