{
  "type": "Feature",
  "properties": {
    "gn:adm1_name":"Okayamaken",
    "gn:adm2_name":"Aidagunmimasakachou",
    "gn:name":"Wada",
    "iso:country":"JP",
    "wof:name":"707-0011",
    "wof:placetype":"postalcode"
},
  "geometry": {"coordinates":[134.1825,35.0456],"type":"Point"}
}