{
  "type": "Feature",
  "properties": {
    "gn:adm1_name":"Kumamotoken",
    "gn:adm2_name":"Hitoyoshishi",
    "gn:name":"Kanamemachi",
    "iso:country":"JP",
    "wof:name":"868-0078",
    "wof:placetype":"postalcode"
},
  "geometry": {"coordinates":[130.68790000000001,32.1908],"type":"Point"}
}