{
  "type": "Feature",
  "properties": {
    "gn:adm1_name":"Hyougoken",
    "gn:adm2_name":"Himejishi",
    "gn:name":"Funatsuchou",
    "iso:country":"JP",
    "wof:name":"679-2101",
    "wof:placetype":"postalcode"
},
  "geometry": {"coordinates":[134.75530000000001,34.9186],"type":"Point"}
}