{
  "type": "Feature",
  "properties": {
    "gn:adm1_name":"Yamaguchiken",
    "gn:adm2_name":"Shimonosekishi",
    "gn:name":"Yoshidajikata",
    "iso:country":"JP",
    "wof:name":"750-1102",
    "wof:placetype":"postalcode"
},
  "geometry": {"coordinates":[131.08519999999999,34.09],"type":"Point"}
}