{
  "type": "Feature",
  "properties": {
    "gn:adm1_name":"Shizuokaken",
    "gn:adm2_name":"Iwatagunryuuyouchou",
    "gn:name":"Oonagaze",
    "iso:country":"JP",
    "wof:name":"438-0214",
    "wof:placetype":"postalcode"
},
  "geometry": {"coordinates":[137.83420000000001,34.6669],"type":"Point"}
}