{
  "type": "Feature",
  "properties": {
    "gn:adm1_name":"Nagasakiken",
    "gn:adm2_name":"Hiradoshi",
    "gn:name":"Fukagawachou",
    "iso:country":"JP",
    "wof:name":"859-5374",
    "wof:placetype":"postalcode"
},
  "geometry": {"coordinates":[129.47810000000001,33.3085],"type":"Point"}
}