{
  "type": "Feature",
  "properties": {
    "gn:adm1_name":"Gifuken",
    "gn:adm2_name":"Takayamashi",
    "gn:name":"Shimo1nomachi",
    "iso:country":"JP",
    "wof:name":"506-0843",
    "wof:placetype":"postalcode"
},
  "geometry": {"coordinates":[137.25999999999999,36.1449],"type":"Point"}
}