{
  "type": "Feature",
  "properties": {
    "gn:adm1_name":"Oosakafu",
    "gn:adm2_name":"Yaoshi",
    "gn:name":"Minamikyuuhouji",
    "iso:country":"JP",
    "wof:name":"581-0076",
    "wof:placetype":"postalcode"
},
  "geometry": {"coordinates":[135.58799999999999,34.6237],"type":"Point"}
}