{
  "type": "Feature",
  "properties": {
    "gn:adm1_name":"Toyamaken",
    "gn:adm2_name":"Nishitonamigunfukumitsumachi",
    "gn:name":"Kawanishi",
    "iso:country":"JP",
    "wof:name":"939-1613",
    "wof:placetype":"postalcode"
},
  "geometry": {"coordinates":[136.8646,36.5724],"type":"Point"}
}