{
  "type": "Feature",
  "properties": {
    "gn:adm1_name":"Mieken",
    "gn:adm2_name":"Kitamurogunmiyamachou",
    "gn:name":"Oyamaura",
    "iso:country":"JP",
    "wof:name":"519-3407",
    "wof:placetype":"postalcode"
},
  "geometry": {"coordinates":[136.19749999999999,34.0925],"type":"Point"}
}