{
  "type": "Feature",
  "properties": {
    "gn:adm1_name":"Niigataken",
    "gn:adm2_name":"Iwafunegunsanpokumachi",
    "gn:name":"Fuya",
    "iso:country":"JP",
    "wof:name":"959-3907",
    "wof:placetype":"postalcode"
},
  "geometry": {"coordinates":[139.5359,38.5159],"type":"Point"}
}