{
  "type": "Feature",
  "properties": {
    "gn:adm1_name":"Nagasakiken",
    "gn:adm2_name":"Shimoagatagunmitsushimachou",
    "gn:name":"Neo",
    "iso:country":"JP",
    "wof:name":"817-0326",
    "wof:placetype":"postalcode"
},
  "geometry": {"coordinates":[129.31360000000001,34.2425],"type":"Point"}
}