{
  "type": "Feature",
  "properties": {
    "gn:adm1_name":"Sagaken",
    "gn:adm2_name":"Tosushi",
    "gn:name":"Kawachimachi",
    "iso:country":"JP",
    "wof:name":"841-0087",
    "wof:placetype":"postalcode"
},
  "geometry": {"coordinates":[130.47819999999999,33.4092],"type":"Point"}
}