{
  "type": "Feature",
  "properties": {
    "gn:adm1_name":"Kumamotoken",
    "gn:adm2_name":"Kumamotoshi",
    "gn:name":"Enokimachi",
    "iso:country":"JP",
    "wof:name":"862-0917",
    "wof:placetype":"postalcode"
},
  "geometry": {"coordinates":[130.7731,32.7939],"type":"Point"}
}