{
  "type": "Feature",
  "properties": {
    "gn:adm1_name":"Niigataken",
    "gn:adm2_name":"Tsubameshi",
    "gn:name":"Nishitsubamemachi",
    "iso:country":"JP",
    "wof:name":"959-1282",
    "wof:placetype":"postalcode"
},
  "geometry": {"coordinates":[138.92509999999999,37.6644],"type":"Point"}
}