{
  "type": "Feature",
  "properties": {
    "gn:adm1_name":"Kumamotoken",
    "gn:adm2_name":"Asogun'Ichinomiyamachi",
    "gn:name":"Teno",
    "iso:country":"JP",
    "wof:name":"869-2601",
    "wof:placetype":"postalcode"
},
  "geometry": {"coordinates":[131.12620000000001,32.9817],"type":"Point"}
}