{
  "type": "Feature",
  "properties": {
    "gn:adm1_name":"Chibaken",
    "gn:adm2_name":"Isumigun'Ootakimachi",
    "gn:name":"Kugahara",
    "iso:country":"JP",
    "wof:name":"298-0251",
    "wof:placetype":"postalcode"
},
  "geometry": {"coordinates":[140.25540000000001,35.2456],"type":"Point"}
}