{
  "type": "Feature",
  "properties": {
    "gn:adm1_name":"Kyoutofu",
    "gn:adm2_name":"Amatagunmiwachou",
    "gn:name":"Kusayama",
    "iso:country":"JP",
    "wof:name":"620-1435",
    "wof:placetype":"postalcode"
},
  "geometry": {"coordinates":[135.20419999999999,35.2114],"type":"Point"}
}