{
  "type": "Feature",
  "properties": {
    "gn:adm1_name":"Wakayamaken",
    "gn:adm2_name":"Wakayamashi",
    "gn:name":"Wakauranishi",
    "iso:country":"JP",
    "wof:name":"641-0024",
    "wof:placetype":"postalcode"
},
  "geometry": {"coordinates":[135.1678,34.1952],"type":"Point"}
}