{
  "type": "Feature",
  "properties": {
    "gn:adm1_name":"Saitamaken",
    "gn:adm2_name":"Satteshi",
    "gn:name":"Yoshino",
    "iso:country":"JP",
    "wof:name":"340-0153",
    "wof:placetype":"postalcode"
},
  "geometry": {"coordinates":[139.7259,36.0559],"type":"Point"}
}