{
  "type": "Feature",
  "properties": {
    "gn:adm1_name":"Ibarakiken",
    "gn:adm2_name":"Yuukishi",
    "gn:name":"Higashimoro",
    "iso:country":"JP",
    "wof:name":"307-0037",
    "wof:placetype":"postalcode"
},
  "geometry": {"coordinates":[139.8407,36.2247],"type":"Point"}
}