{
  "type": "Feature",
  "properties": {
    "gn:adm1_name":"Toyamaken",
    "gn:adm2_name":"Toyamashi",
    "gn:name":"Kamishoumachi",
    "iso:country":"JP",
    "wof:name":"930-0826",
    "wof:placetype":"postalcode"
},
  "geometry": {"coordinates":[137.2525,36.7066],"type":"Point"}
}