{
  "type": "Feature",
  "properties": {
    "gn:adm1_name":"Miyagiken",
    "gn:adm2_name":"Motoyoshigun'Utatsuchou",
    "gn:name":"Ishizumi",
    "iso:country":"JP",
    "wof:name":"988-0471",
    "wof:placetype":"postalcode"
},
  "geometry": {"coordinates":[141.50059999999999,38.7415],"type":"Point"}
}