{
  "type": "Feature",
  "properties": {
    "gn:adm1_name":"Saitamaken",
    "gn:adm2_name":"Tokorozawashi",
    "gn:name":"Wakamatsuchou",
    "iso:country":"JP",
    "wof:name":"359-0032",
    "wof:placetype":"postalcode"
},
  "geometry": {"coordinates":[139.48390000000001,35.8018],"type":"Point"}
}