{
  "type": "Feature",
  "properties": {
    "gn:adm1_name":"Kyoutofu",
    "gn:adm2_name":"Kyoutoshikitaku",
    "gn:name":"Kamigamonakaoojichou",
    "iso:country":"JP",
    "wof:name":"603-8075",
    "wof:placetype":"postalcode"
},
  "geometry": {"coordinates":[135.75489999999999,35.0565],"type":"Point"}
}