{
  "type": "Feature",
  "properties": {
    "gn:adm1_name":"Shizuokaken",
    "gn:adm2_name":"Shizuokashi",
    "gn:name":"Sena",
    "iso:country":"JP",
    "wof:name":"420-0911",
    "wof:placetype":"postalcode"
},
  "geometry": {"coordinates":[138.42189999999999,35.022],"type":"Point"}
}