{
  "type": "Feature",
  "properties": {
    "gn:adm1_name":"Kyoutofu",
    "gn:adm2_name":"Kyoutoshihigashiyamaku",
    "gn:name":"Sennyuujisuzumegamorichou",
    "iso:country":"JP",
    "wof:name":"605-0975",
    "wof:placetype":"postalcode"
},
  "geometry": {"coordinates":[135.77340000000001,34.9821],"type":"Point"}
}