{
  "type": "Feature",
  "properties": {
    "gn:adm1_name":"Toyamaken",
    "gn:adm2_name":"Higashitonamiguntairamura",
    "gn:name":"Kurusu",
    "iso:country":"JP",
    "wof:name":"939-1925",
    "wof:placetype":"postalcode"
},
  "geometry": {"coordinates":[136.94130000000001,36.4332],"type":"Point"}
}