{
  "type": "Feature",
  "properties": {
    "gn:adm1_name":"Aichiken",
    "gn:adm2_name":"Ichinomiyashi",
    "gn:name":"Azaichoumaeno",
    "iso:country":"JP",
    "wof:name":"491-0103",
    "wof:placetype":"postalcode"
},
  "geometry": {"coordinates":[136.8295,35.3441],"type":"Point"}
}