{
  "type": "Feature",
  "properties": {
    "gn:adm1_name":"Miyagiken",
    "gn:adm2_name":"Kuriharagun'Ichihasamachou",
    "gn:name":"Takahashi",
    "iso:country":"JP",
    "wof:name":"987-2332",
    "wof:placetype":"postalcode"
},
  "geometry": {"coordinates":[140.91569999999999,38.7443],"type":"Point"}
}