{
  "type": "Feature",
  "properties": {
    "gn:adm1_name":"Kyoutofu",
    "gn:adm2_name":"Kyoutoshifushimiku",
    "gn:name":"Nousoshimono",
    "iso:country":"JP",
    "wof:name":"612-8267",
    "wof:placetype":"postalcode"
},
  "geometry": {"coordinates":[135.72479999999999,34.9103],"type":"Point"}
}