{
  "type": "Feature",
  "properties": {
    "gn:adm1_name":"Hyougoken",
    "gn:adm2_name":"Izushigun'Izushichou",
    "gn:name":"Nakamura",
    "iso:country":"JP",
    "wof:name":"668-0254",
    "wof:placetype":"postalcode"
},
  "geometry": {"coordinates":[134.86250000000001,35.4535],"type":"Point"}
}