{
  "type": "Feature",
  "properties": {
    "gn:adm1_name":"Ibarakiken",
    "gn:adm2_name":"Tsukubashi",
    "gn:name":"Myoujin",
    "iso:country":"JP",
    "wof:name":"300-1257",
    "wof:placetype":"postalcode"
},
  "geometry": {"coordinates":[140.13480000000001,35.9873],"type":"Point"}
}