{
  "type": "Feature",
  "properties": {
    "gn:adm1_name":"Shigaken",
    "gn:adm2_name":"Ootsushi",
    "gn:name":"Katsuragawamachiichou",
    "iso:country":"JP",
    "wof:name":"520-0474",
    "wof:placetype":"postalcode"
},
  "geometry": {"coordinates":[135.86869999999999,35.2551],"type":"Point"}
}