{
  "type": "Feature",
  "properties": {
    "gn:adm1_name":"Toyamaken",
    "gn:adm2_name":"Tonamishi",
    "gn:name":"Nishinaka",
    "iso:country":"JP",
    "wof:name":"939-1336",
    "wof:placetype":"postalcode"
},
  "geometry": {"coordinates":[136.91970000000001,36.6466],"type":"Point"}
}