{
  "type": "Feature",
  "properties": {
    "gn:adm1_name":"Shimaneken",
    "gn:adm2_name":"Nakagunyasakamura",
    "gn:name":"Osaka",
    "iso:country":"JP",
    "wof:name":"697-1202",
    "wof:placetype":"postalcode"
},
  "geometry": {"coordinates":[132.1251,34.811],"type":"Point"}
}