{
  "type": "Feature",
  "properties": {
    "gn:adm1_name":"Fukuiken",
    "gn:adm2_name":"Sakaigunmikunichou",
    "gn:name":"Shinbo",
    "iso:country":"JP",
    "wof:name":"913-0031",
    "wof:placetype":"postalcode"
},
  "geometry": {"coordinates":[136.14150000000001,36.2062],"type":"Point"}
}