{
  "type": "Feature",
  "properties": {
    "gn:adm1_name":"Hiroshimaken",
    "gn:adm2_name":"Miyoshishi",
    "gn:name":"Tookaichinishi",
    "iso:country":"JP",
    "wof:name":"728-0011",
    "wof:placetype":"postalcode"
},
  "geometry": {"coordinates":[132.84559999999999,34.8007],"type":"Point"}
}