{
  "type": "Feature",
  "properties": {
    "gn:adm1_name":"Ooitaken",
    "gn:adm2_name":"Tsukumishi",
    "gn:name":"Ootomomachi",
    "iso:country":"JP",
    "wof:name":"879-2431",
    "wof:placetype":"postalcode"
},
  "geometry": {"coordinates":[131.8647,33.0708],"type":"Point"}
}