{
  "type": "Feature",
  "properties": {
    "gn:adm1_name":"Wakayamaken",
    "gn:adm2_name":"Shinguushi",
    "gn:name":"Isadachou",
    "iso:country":"JP",
    "wof:name":"647-0012",
    "wof:placetype":"postalcode"
},
  "geometry": {"coordinates":[135.9939,33.7278],"type":"Point"}
}