{
  "type": "Feature",
  "properties": {
    "gn:adm1_name":"Ibarakiken",
    "gn:adm2_name":"Tsukubashi",
    "gn:name":"Kitanakajima",
    "iso:country":"JP",
    "wof:name":"305-0072",
    "wof:placetype":"postalcode"
},
  "geometry": {"coordinates":[140.1395,36.0257],"type":"Point"}
}