{
  "type": "Feature",
  "properties": {
    "gn:adm1_name":"Wakayamaken",
    "gn:adm2_name":"Itogunkatsuragichou",
    "gn:name":"Taira",
    "iso:country":"JP",
    "wof:name":"649-7104",
    "wof:placetype":"postalcode"
},
  "geometry": {"coordinates":[135.4753,34.3406],"type":"Point"}
}