{
  "type": "Feature",
  "properties": {
    "gn:adm1_name":"Tottoriken",
    "gn:adm2_name":"Saihakugun'Aimichou",
    "gn:name":"Misaki",
    "iso:country":"JP",
    "wof:name":"683-0203",
    "wof:placetype":"postalcode"
},
  "geometry": {"coordinates":[133.35409999999999,35.3727],"type":"Point"}
}