{
  "type": "Feature",
  "properties": {
    "gn:adm1_name":"Fukuokaken",
    "gn:adm2_name":"Kitakyuushuushimojiku",
    "gn:name":"Shinkai",
    "iso:country":"JP",
    "wof:name":"801-0885",
    "wof:placetype":"postalcode"
},
  "geometry": {"coordinates":[130.9853,33.9566],"type":"Point"}
}