{
  "type": "Feature",
  "properties": {
    "gn:adm1_name":"Nagasakiken",
    "gn:adm2_name":"Nagasakishi",
    "gn:name":"Minamigaokamachi",
    "iso:country":"JP",
    "wof:name":"850-0943",
    "wof:placetype":"postalcode"
},
  "geometry": {"coordinates":[129.8854,32.7283],"type":"Point"}
}