{
  "type": "Feature",
  "properties": {
    "gn:adm1_name":"Ishikawaken",
    "gn:adm2_name":"Kashimagunnakajimamachi",
    "gn:name":"Besshiyo",
    "iso:country":"JP",
    "wof:name":"929-2202",
    "wof:placetype":"postalcode"
},
  "geometry": {"coordinates":[136.8398,37.1646],"type":"Point"}
}