{
  "type": "Feature",
  "properties": {
    "gn:adm1_name":"Miyazakiken",
    "gn:adm2_name":"Miyazakishi",
    "gn:name":"Ootsukadainishi",
    "iso:country":"JP",
    "wof:name":"880-2105",
    "wof:placetype":"postalcode"
},
  "geometry": {"coordinates":[131.38290000000001,31.9153],"type":"Point"}
}