{
  "type": "Feature",
  "properties": {
    "gn:adm1_name":"Fukuokaken",
    "gn:adm2_name":"Kasuyagun'Umimachi",
    "gn:name":"Umi",
    "iso:country":"JP",
    "wof:name":"811-2101",
    "wof:placetype":"postalcode"
},
  "geometry": {"coordinates":[130.5171,33.5684],"type":"Point"}
}