{
  "type": "Feature",
  "properties": {
    "gn:adm1_name":"Kyoutofu",
    "gn:adm2_name":"Kameokashi",
    "gn:name":"Higashibetsuinchoutouge",
    "iso:country":"JP",
    "wof:name":"621-0103",
    "wof:placetype":"postalcode"
},
  "geometry": {"coordinates":[135.54859999999999,34.9488],"type":"Point"}
}