{
  "type": "Feature",
  "properties": {
    "gn:adm1_name":"Ishikawaken",
    "gn:adm2_name":"Ishikawaguntorigoemura",
    "gn:name":"Kamino",
    "iso:country":"JP",
    "wof:name":"920-2375",
    "wof:placetype":"postalcode"
},
  "geometry": {"coordinates":[136.60470000000001,36.3727],"type":"Point"}
}