{
  "type": "Feature",
  "properties": {
    "gn:adm1_name":"Hyougoken",
    "gn:adm2_name":"Hikamigunkasugachou",
    "gn:name":"Tada",
    "iso:country":"JP",
    "wof:name":"669-4125",
    "wof:placetype":"postalcode"
},
  "geometry": {"coordinates":[135.11660000000001,35.1782],"type":"Point"}
}