{
  "type": "Feature",
  "properties": {
    "gn:adm1_name":"Fukuokaken",
    "gn:adm2_name":"Kasugashi",
    "gn:name":"Momijigaokahigashi",
    "iso:country":"JP",
    "wof:name":"816-0833",
    "wof:placetype":"postalcode"
},
  "geometry": {"coordinates":[130.45939999999999,33.5184],"type":"Point"}
}