{
  "type": "Feature",
  "properties": {
    "gn:adm1_name":"Tottoriken",
    "gn:adm2_name":"Iwamigunkokufuchou",
    "gn:name":"Kihara",
    "iso:country":"JP",
    "wof:name":"680-0208",
    "wof:placetype":"postalcode"
},
  "geometry": {"coordinates":[134.37039999999999,35.4804],"type":"Point"}
}