{
  "type": "Feature",
  "properties": {
    "gn:adm1_name":"Toyamaken",
    "gn:adm2_name":"Kurobeshi",
    "gn:name":"Kanaya",
    "iso:country":"JP",
    "wof:name":"938-0022",
    "wof:placetype":"postalcode"
},
  "geometry": {"coordinates":[137.44210000000001,36.8866],"type":"Point"}
}