{
  "type": "Feature",
  "properties": {
    "gn:adm1_name":"Naraken",
    "gn:adm2_name":"Narashi",
    "gn:name":"Kawanokamichou",
    "iso:country":"JP",
    "wof:name":"630-8313",
    "wof:placetype":"postalcode"
},
  "geometry": {"coordinates":[135.8321,34.675],"type":"Point"}
}