{
  "type": "Feature",
  "properties": {
    "gn:adm1_name":"Mieken",
    "gn:adm2_name":"Agegunkawagechou",
    "gn:name":"Kageshige",
    "iso:country":"JP",
    "wof:name":"510-0307",
    "wof:placetype":"postalcode"
},
  "geometry": {"coordinates":[136.53980000000001,34.7773],"type":"Point"}
}