{
  "type": "Feature",
  "properties": {
    "gn:adm1_name":"Aichiken",
    "gn:adm2_name":"Kounanshi",
    "gn:name":"Gomyouchoudaizen",
    "iso:country":"JP",
    "wof:name":"483-8245",
    "wof:placetype":"postalcode"
},
  "geometry": {"coordinates":[136.8596,35.3155],"type":"Point"}
}