{
  "type": "Feature",
  "properties": {
    "gn:adm1_name":"Aichiken",
    "gn:adm2_name":"Nishikamogun'Obaramura",
    "gn:name":"Kitasasadaira",
    "iso:country":"JP",
    "wof:name":"470-0543",
    "wof:placetype":"postalcode"
},
  "geometry": {"coordinates":[137.26079999999999,35.2254],"type":"Point"}
}