{
  "type": "Feature",
  "properties": {
    "gn:adm1_name":"Toukyouto",
    "gn:adm2_name":"Hachioujishi",
    "gn:name":"Kamiyugi",
    "iso:country":"JP",
    "wof:name":"192-0373",
    "wof:placetype":"postalcode"
},
  "geometry": {"coordinates":[139.37029999999999,35.6208],"type":"Point"}
}