{
  "type": "Feature",
  "properties": {
    "gn:adm1_name":"Kyoutofu",
    "gn:adm2_name":"Maidurushi",
    "gn:name":"Nakayama",
    "iso:country":"JP",
    "wof:name":"624-0966",
    "wof:placetype":"postalcode"
},
  "geometry": {"coordinates":[135.28219999999999,35.4708],"type":"Point"}
}