{
  "type": "Feature",
  "properties": {
    "gn:adm1_name":"Mieken",
    "gn:adm2_name":"Agegun'Anouchou",
    "gn:name":"Araki",
    "iso:country":"JP",
    "wof:name":"514-2301",
    "wof:placetype":"postalcode"
},
  "geometry": {"coordinates":[136.44659999999999,34.7795],"type":"Point"}
}