{
  "type": "Feature",
  "properties": {
    "gn:adm1_name":"Mieken",
    "gn:adm2_name":"Wataraiguntamakichou",
    "gn:name":"Miyako",
    "iso:country":"JP",
    "wof:name":"519-0427",
    "wof:placetype":"postalcode"
},
  "geometry": {"coordinates":[136.63140000000001,34.4713],"type":"Point"}
}