{
  "type": "Feature",
  "properties": {
    "gn:adm1_name":"Niigataken",
    "gn:adm2_name":"Sadogunhamochimachi",
    "gn:name":"Sanse",
    "iso:country":"JP",
    "wof:name":"952-0505",
    "wof:placetype":"postalcode"
},
  "geometry": {"coordinates":[138.34139999999999,37.8287],"type":"Point"}
}