{
  "type": "Feature",
  "properties": {
    "gn:adm1_name":"Hiroshimaken",
    "gn:adm2_name":"Kureshi",
    "gn:name":"Hiroryoutani",
    "iso:country":"JP",
    "wof:name":"737-0123",
    "wof:placetype":"postalcode"
},
  "geometry": {"coordinates":[132.6327,34.2341],"type":"Point"}
}