{
  "type": "Feature",
  "properties": {
    "gn:adm1_name":"Niigataken",
    "gn:adm2_name":"Jouetsushi",
    "gn:name":"Nakamanago",
    "iso:country":"JP",
    "wof:name":"942-0037",
    "wof:placetype":"postalcode"
},
  "geometry": {"coordinates":[138.2972,37.1538],"type":"Point"}
}