{
  "type": "Feature",
  "properties": {
    "gn:adm1_name":"Okayamaken",
    "gn:adm2_name":"Bizenshi",
    "gn:name":"Kagatonishi",
    "iso:country":"JP",
    "wof:name":"705-0011",
    "wof:placetype":"postalcode"
},
  "geometry": {"coordinates":[134.11709999999999,34.7308],"type":"Point"}
}