{
  "type": "Feature",
  "properties": {
    "gn:adm1_name":"Toyamaken",
    "gn:adm2_name":"Neigunfuchuumachi",
    "gn:name":"Shimosakakura",
    "iso:country":"JP",
    "wof:name":"939-2715",
    "wof:placetype":"postalcode"
},
  "geometry": {"coordinates":[137.1686,36.6646],"type":"Point"}
}