{
  "type": "Feature",
  "properties": {
    "gn:adm1_name":"Tottoriken",
    "gn:adm2_name":"Touhakugunmisasachou",
    "gn:name":"Nishio",
    "iso:country":"JP",
    "wof:name":"682-0145",
    "wof:placetype":"postalcode"
},
  "geometry": {"coordinates":[133.9118,35.3915],"type":"Point"}
}