{
  "type": "Feature",
  "properties": {
    "gn:adm1_name":"Toyamaken",
    "gn:adm2_name":"Toyamashi",
    "gn:name":"Sannokuma",
    "iso:country":"JP",
    "wof:name":"930-0155",
    "wof:placetype":"postalcode"
},
  "geometry": {"coordinates":[137.10759999999999,36.6675],"type":"Point"}
}