{
  "type": "Feature",
  "properties": {
    "gn:adm1_name":"Gunmaken",
    "gn:adm2_name":"Maebashishi",
    "gn:name":"Kamiaonashimachi",
    "iso:country":"JP",
    "wof:name":"370-3572",
    "wof:placetype":"postalcode"
},
  "geometry": {"coordinates":[139.0163,36.4218],"type":"Point"}
}