{
  "type": "Feature",
  "properties": {
    "gn:adm1_name":"Nagasakiken",
    "gn:adm2_name":"Nagasakishi",
    "gn:name":"Okamachi",
    "iso:country":"JP",
    "wof:name":"852-8115",
    "wof:placetype":"postalcode"
},
  "geometry": {"coordinates":[129.86259999999999,32.7773],"type":"Point"}
}