{
  "type": "Feature",
  "properties": {
    "gn:adm1_name":"Hiroshimaken",
    "gn:adm2_name":"Hiroshimashiasakitaku",
    "gn:name":"Shirakichoushiji",
    "iso:country":"JP",
    "wof:name":"739-1303",
    "wof:placetype":"postalcode"
},
  "geometry": {"coordinates":[132.5745,34.5607],"type":"Point"}
}