{
  "type": "Feature",
  "properties": {
    "gn:adm1_name":"Miyagiken",
    "gn:adm2_name":"Kuriharaguntakashimizumachi",
    "gn:name":"Shitamachi",
    "iso:country":"JP",
    "wof:name":"987-2189",
    "wof:placetype":"postalcode"
},
  "geometry": {"coordinates":[141.0104,38.6519],"type":"Point"}
}