{
  "type": "Feature",
  "properties": {
    "gn:adm1_name":"Ooitaken",
    "gn:adm2_name":"Ooitashi",
    "gn:name":"Katsuragi",
    "iso:country":"JP",
    "wof:name":"870-0133",
    "wof:placetype":"postalcode"
},
  "geometry": {"coordinates":[131.6721,33.224],"type":"Point"}
}