{
  "type": "Feature",
  "properties": {
    "gn:adm1_name":"Shimaneken",
    "gn:adm2_name":"Kanoashigunmuikaichichou",
    "gn:name":"Nukutsuki",
    "iso:country":"JP",
    "wof:name":"699-5525",
    "wof:placetype":"postalcode"
},
  "geometry": {"coordinates":[131.86869999999999,34.3869],"type":"Point"}
}