{
  "type": "Feature",
  "properties": {
    "gn:adm1_name":"Kouchiken",
    "gn:adm2_name":"Akishi",
    "gn:name":"Kotobukichou",
    "iso:country":"JP",
    "wof:name":"784-0007",
    "wof:placetype":"postalcode"
},
  "geometry": {"coordinates":[133.90299999999999,33.4988],"type":"Point"}
}