{
  "type": "Feature",
  "properties": {
    "gn:adm1_name":"Tochigiken",
    "gn:adm2_name":"Kawachigunkaminokawamachi",
    "gn:name":"Yana",
    "iso:country":"JP",
    "wof:name":"329-0523",
    "wof:placetype":"postalcode"
},
  "geometry": {"coordinates":[139.886,36.4286],"type":"Point"}
}