{
  "type": "Feature",
  "properties": {
    "gn:adm1_name":"Hyougoken",
    "gn:adm2_name":"Sasayamashi",
    "gn:name":"Okuharayama",
    "iso:country":"JP",
    "wof:name":"669-2501",
    "wof:placetype":"postalcode"
},
  "geometry": {"coordinates":[135.39789999999999,35.0884],"type":"Point"}
}