{
  "type": "Feature",
  "properties": {
    "gn:adm1_name":"Kyoutofu",
    "gn:adm2_name":"Kyoutoshinakagyouku",
    "gn:name":"Kikusuihokochou",
    "iso:country":"JP",
    "wof:name":"604-8154",
    "wof:placetype":"postalcode"
},
  "geometry": {"coordinates":[135.75819999999999,35.0044],"type":"Point"}
}