{
  "type": "Feature",
  "properties": {
    "gn:adm1_name":"Toyamaken",
    "gn:adm2_name":"Nakaniikawagunkamiichimachi",
    "gn:name":"Shinmeimachi",
    "iso:country":"JP",
    "wof:name":"930-0342",
    "wof:placetype":"postalcode"
},
  "geometry": {"coordinates":[137.36680000000001,36.7049],"type":"Point"}
}