{
  "type": "Feature",
  "properties": {
    "gn:adm1_name":"Aichiken",
    "gn:adm2_name":"Tokonameshi",
    "gn:name":"Takasaka",
    "iso:country":"JP",
    "wof:name":"479-0016",
    "wof:placetype":"postalcode"
},
  "geometry": {"coordinates":[136.86840000000001,34.8931],"type":"Point"}
}