{
  "type": "Feature",
  "properties": {
    "gn:adm1_name":"Fukuokaken",
    "gn:adm2_name":"Kitakyuushuushikokuraminamiku",
    "gn:name":"Horigoshi",
    "iso:country":"JP",
    "wof:name":"802-0835",
    "wof:placetype":"postalcode"
},
  "geometry": {"coordinates":[130.8861,33.8125],"type":"Point"}
}