{
  "type": "Feature",
  "properties": {
    "gn:adm1_name":"Saitamaken",
    "gn:adm2_name":"Saitamashinishiku",
    "gn:name":"Sajikawa",
    "iso:country":"JP",
    "wof:name":"331-0064",
    "wof:placetype":"postalcode"
},
  "geometry": {"coordinates":[139.5838,35.903],"type":"Point"}
}