{
  "type": "Feature",
  "properties": {
    "gn:adm1_name":"Yamagataken",
    "gn:adm2_name":"Nishiokitamagun'Ogunimachi",
    "gn:name":"Kaname",
    "iso:country":"JP",
    "wof:name":"999-1301",
    "wof:placetype":"postalcode"
},
  "geometry": {"coordinates":[139.8065,38.0956],"type":"Point"}
}