{
  "type": "Feature",
  "properties": {
    "gn:adm1_name":"Fukuokaken",
    "gn:adm2_name":"Itoshimagunnijoumachi",
    "gn:name":"Shikaka",
    "iso:country":"JP",
    "wof:name":"819-1642",
    "wof:placetype":"postalcode"
},
  "geometry": {"coordinates":[130.05119999999999,33.4856],"type":"Point"}
}