{
  "type": "Feature",
  "properties": {
    "gn:adm1_name":"Hyougoken",
    "gn:adm2_name":"Sasayamashi",
    "gn:name":"Saikujo",
    "iso:country":"JP",
    "wof:name":"669-2542",
    "wof:placetype":"postalcode"
},
  "geometry": {"coordinates":[135.3151,35.09],"type":"Point"}
}