{
  "type": "Feature",
  "properties": {
    "gn:adm1_name":"Kanagawaken",
    "gn:adm2_name":"Yokohamashikanagawaku",
    "gn:name":"Nishiterao",
    "iso:country":"JP",
    "wof:name":"221-0001",
    "wof:placetype":"postalcode"
},
  "geometry": {"coordinates":[139.64869999999999,35.499],"type":"Point"}
}