{
  "type": "Feature",
  "properties": {
    "gn:adm1_name":"Aichiken",
    "gn:adm2_name":"Chitashi",
    "gn:name":"Nishitatsumigaoka",
    "iso:country":"JP",
    "wof:name":"478-0014",
    "wof:placetype":"postalcode"
},
  "geometry": {"coordinates":[136.9068,34.9623],"type":"Point"}
}