{
  "type": "Feature",
  "properties": {
    "gn:adm1_name":"Yamanashiken",
    "gn:adm2_name":"Koufushi",
    "gn:name":"Wadomachi",
    "iso:country":"JP",
    "wof:name":"400-0812",
    "wof:placetype":"postalcode"
},
  "geometry": {"coordinates":[138.61619999999999,35.6529],"type":"Point"}
}