{
  "type": "Feature",
  "properties": {
    "gn:adm1_name":"Ishikawaken",
    "gn:adm2_name":"Kanazawashi",
    "gn:name":"Takaramachi",
    "iso:country":"JP",
    "wof:name":"920-0934",
    "wof:placetype":"postalcode"
},
  "geometry": {"coordinates":[136.67140000000001,36.5585],"type":"Point"}
}