{
  "type": "Feature",
  "properties": {
    "gn:adm1_name":"Fukushimaken",
    "gn:adm2_name":"Nishishirakawagunnishigoumura",
    "gn:name":"Kashiwano",
    "iso:country":"JP",
    "wof:name":"961-8011",
    "wof:placetype":"postalcode"
},
  "geometry": {"coordinates":[140.1799,37.156],"type":"Point"}
}