{
  "type": "Feature",
  "properties": {
    "gn:adm1_name":"Ishikawaken",
    "gn:adm2_name":"Nomiguntatsunokuchimachi",
    "gn:name":"Miyatake",
    "iso:country":"JP",
    "wof:name":"923-1205",
    "wof:placetype":"postalcode"
},
  "geometry": {"coordinates":[136.58789999999999,36.4531],"type":"Point"}
}