{
  "type": "Feature",
  "properties": {
    "gn:adm1_name":"Niigataken",
    "gn:adm2_name":"Kitakanbaragunsasakamimura",
    "gn:name":"Kamisekiguchi",
    "iso:country":"JP",
    "wof:name":"959-1962",
    "wof:placetype":"postalcode"
},
  "geometry": {"coordinates":[139.2603,37.8657],"type":"Point"}
}