{
  "type": "Feature",
  "properties": {
    "gn:adm1_name":"Saitamaken",
    "gn:adm2_name":"Kitakatsushikagunkurihashimachi",
    "gn:name":"Nakazato",
    "iso:country":"JP",
    "wof:name":"349-1112",
    "wof:placetype":"postalcode"
},
  "geometry": {"coordinates":[139.7176,36.1059],"type":"Point"}
}