{
  "type": "Feature",
  "properties": {
    "gn:adm1_name":"Niigataken",
    "gn:adm2_name":"Kitakanbaragunnakajoumachi",
    "gn:name":"Tomioka",
    "iso:country":"JP",
    "wof:name":"959-2608",
    "wof:placetype":"postalcode"
},
  "geometry": {"coordinates":[139.3794,38.1018],"type":"Point"}
}