{
  "type": "Feature",
  "properties": {
    "gn:adm1_name":"Ibarakiken",
    "gn:adm2_name":"Kashimagunhokotamachi",
    "gn:name":"Ootake",
    "iso:country":"JP",
    "wof:name":"311-1513",
    "wof:placetype":"postalcode"
},
  "geometry": {"coordinates":[140.5692,36.1539],"type":"Point"}
}