{
  "type": "Feature",
  "properties": {
    "gn:adm1_name":"Hyougoken",
    "gn:adm2_name":"Sandashi",
    "gn:name":"Umawatari",
    "iso:country":"JP",
    "wof:name":"669-1336",
    "wof:placetype":"postalcode"
},
  "geometry": {"coordinates":[135.1611,34.8976],"type":"Point"}
}