{
  "type": "Feature",
  "properties": {
    "gn:adm1_name":"Ehimeken",
    "gn:adm2_name":"Matsuyamashi",
    "gn:name":"Hataderamachi",
    "iso:country":"JP",
    "wof:name":"790-0912",
    "wof:placetype":"postalcode"
},
  "geometry": {"coordinates":[132.80459999999999,33.8358],"type":"Point"}
}