{
  "type": "Feature",
  "properties": {
    "gn:adm1_name":"Okinawaken",
    "gn:adm2_name":"Ishigakishi",
    "gn:name":"Hirae",
    "iso:country":"JP",
    "wof:name":"907-0003",
    "wof:placetype":"postalcode"
},
  "geometry": {"coordinates":[124.17610000000001,24.3425],"type":"Point"}
}