{
  "type": "Feature",
  "properties": {
    "gn:adm1_name":"Shizuokaken",
    "gn:adm2_name":"Haibaragunnakakawanechou",
    "gn:name":"Mizukawa",
    "iso:country":"JP",
    "wof:name":"428-0312",
    "wof:placetype":"postalcode"
},
  "geometry": {"coordinates":[138.07130000000001,35.0762],"type":"Point"}
}