{
  "type": "Feature",
  "properties": {
    "gn:adm1_name":"Saitamaken",
    "gn:adm2_name":"Kodamagunkamisatomachi",
    "gn:name":"Oshibo",
    "iso:country":"JP",
    "wof:name":"369-0303",
    "wof:placetype":"postalcode"
},
  "geometry": {"coordinates":[139.1507,36.2673],"type":"Point"}
}