{
  "type": "Feature",
  "properties": {
    "gn:adm1_name":"Hyougoken",
    "gn:adm2_name":"Mikatagunmuraokachou",
    "gn:name":"Tsukuriyama",
    "iso:country":"JP",
    "wof:name":"667-1331",
    "wof:placetype":"postalcode"
},
  "geometry": {"coordinates":[134.6251,35.4207],"type":"Point"}
}