{
  "type": "Feature",
  "properties": {
    "gn:adm1_name":"Gunmaken",
    "gn:adm2_name":"Setagun'Oogomachi",
    "gn:name":"Yokozawa",
    "iso:country":"JP",
    "wof:name":"371-0233",
    "wof:placetype":"postalcode"
},
  "geometry": {"coordinates":[139.13730000000001,36.4255],"type":"Point"}
}