{
  "type": "Feature",
  "properties": {
    "gn:adm1_name":"Niigataken",
    "gn:adm2_name":"Kariwagun'Ogunimachi",
    "gn:name":"Mioke",
    "iso:country":"JP",
    "wof:name":"949-5345",
    "wof:placetype":"postalcode"
},
  "geometry": {"coordinates":[138.70760000000001,37.2434],"type":"Point"}
}