{
  "type": "Feature",
  "properties": {
    "gn:adm1_name":"Toukyouto",
    "gn:adm2_name":"Fuchuushi",
    "gn:name":"Nikkouchou",
    "iso:country":"JP",
    "wof:name":"183-0044",
    "wof:placetype":"postalcode"
},
  "geometry": {"coordinates":[139.47110000000001,35.6755],"type":"Point"}
}