{
  "type": "Feature",
  "properties": {
    "gn:adm1_name":"Hyougoken",
    "gn:adm2_name":"Koubeshisumaku",
    "gn:name":"Minamimachi",
    "iso:country":"JP",
    "wof:name":"654-0036",
    "wof:placetype":"postalcode"
},
  "geometry": {"coordinates":[135.12520000000001,34.6496],"type":"Point"}
}