{
  "type": "Feature",
  "properties": {
    "gn:adm1_name":"Chibaken",
    "gn:adm2_name":"Sousagunnosakamachi",
    "gn:name":"Kayada",
    "iso:country":"JP",
    "wof:name":"289-3184",
    "wof:placetype":"postalcode"
},
  "geometry": {"coordinates":[140.55410000000001,35.6419],"type":"Point"}
}