{
  "type": "Feature",
  "properties": {
    "gn:adm1_name":"Toyamaken",
    "gn:adm2_name":"Toyamashi",
    "gn:name":"Toyokawachou",
    "iso:country":"JP",
    "wof:name":"930-0049",
    "wof:placetype":"postalcode"
},
  "geometry": {"coordinates":[137.22,36.6911],"type":"Point"}
}