{
  "type": "Feature",
  "properties": {
    "gn:adm1_name":"Aichiken",
    "gn:adm2_name":"Toukaishi",
    "gn:name":"Fukinodai",
    "iso:country":"JP",
    "wof:name":"476-0014",
    "wof:placetype":"postalcode"
},
  "geometry": {"coordinates":[136.90369999999999,35.0312],"type":"Point"}
}