{
  "type": "Feature",
  "properties": {
    "gn:adm1_name":"Yamagataken",
    "gn:adm2_name":"Sakatashi",
    "gn:name":"Mizuho",
    "iso:country":"JP",
    "wof:name":"998-0853",
    "wof:placetype":"postalcode"
},
  "geometry": {"coordinates":[139.85159999999999,38.904],"type":"Point"}
}