{
  "type": "Feature",
  "properties": {
    "gn:adm1_name":"Shimaneken",
    "gn:adm2_name":"Hamadashi",
    "gn:name":"Ushironochou",
    "iso:country":"JP",
    "wof:name":"697-0011",
    "wof:placetype":"postalcode"
},
  "geometry": {"coordinates":[132.1343,34.893],"type":"Point"}
}