{
  "type": "Feature",
  "properties": {
    "gn:adm1_name":"Hyougoken",
    "gn:adm2_name":"Koubeshinishiku",
    "gn:name":"Oshibedanichoukidu",
    "iso:country":"JP",
    "wof:name":"651-2222",
    "wof:placetype":"postalcode"
},
  "geometry": {"coordinates":[135.0814,34.7473],"type":"Point"}
}