{
  "type": "Feature",
  "properties": {
    "gn:adm1_name":"Tokushimaken",
    "gn:adm2_name":"Narutoshi",
    "gn:name":"Setochoukoshimada",
    "iso:country":"JP",
    "wof:name":"771-0365",
    "wof:placetype":"postalcode"
},
  "geometry": {"coordinates":[134.59370000000001,34.2273],"type":"Point"}
}