{
  "type": "Feature",
  "properties": {
    "gn:adm1_name":"Kouchiken",
    "gn:adm2_name":"Susakishi",
    "gn:name":"Oonogouotsu",
    "iso:country":"JP",
    "wof:name":"785-0054",
    "wof:placetype":"postalcode"
},
  "geometry": {"coordinates":[133.3032,33.3924],"type":"Point"}
}