{
  "type": "Feature",
  "properties": {
    "gn:adm1_name":"Fukuokaken",
    "gn:adm2_name":"Kasugashi",
    "gn:name":"Wakabadaihigashi",
    "iso:country":"JP",
    "wof:name":"816-0821",
    "wof:placetype":"postalcode"
},
  "geometry": {"coordinates":[130.46289999999999,33.5264],"type":"Point"}
}