{
  "type": "Feature",
  "properties": {
    "gn:adm1_name":"Toukyouto",
    "gn:adm2_name":"Adachiku",
    "gn:name":"Senjunakachou",
    "iso:country":"JP",
    "wof:name":"120-0036",
    "wof:placetype":"postalcode"
},
  "geometry": {"coordinates":[139.80099999999999,35.7454],"type":"Point"}
}