{
  "type": "Feature",
  "properties": {
    "gn:adm1_name":"Toyamaken",
    "gn:adm2_name":"Kaminiikawagun'Oosawanomachi",
    "gn:name":"Shitabayashi",
    "iso:country":"JP",
    "wof:name":"939-2226",
    "wof:placetype":"postalcode"
},
  "geometry": {"coordinates":[137.20699999999999,36.5674],"type":"Point"}
}