{
  "type": "Feature",
  "properties": {
    "gn:adm1_name":"Kyoutofu",
    "gn:adm2_name":"Kyoutoshifushimiku",
    "gn:name":"Sugimotochou",
    "iso:country":"JP",
    "wof:name":"612-8231",
    "wof:placetype":"postalcode"
},
  "geometry": {"coordinates":[135.75470000000001,34.9312],"type":"Point"}
}