{
  "type": "Feature",
  "properties": {
    "gn:adm1_name":"Niigataken",
    "gn:adm2_name":"Iwafunegunsekikawamura",
    "gn:name":"Shimoseki",
    "iso:country":"JP",
    "wof:name":"959-3265",
    "wof:placetype":"postalcode"
},
  "geometry": {"coordinates":[139.56,38.0916],"type":"Point"}
}