{
  "type": "Feature",
  "properties": {
    "gn:adm1_name":"Fukuokaken",
    "gn:adm2_name":"Tagawagun'Itodamachi",
    "gn:name":"Miyatokodanchi",
    "iso:country":"JP",
    "wof:name":"822-1305",
    "wof:placetype":"postalcode"
},
  "geometry": {"coordinates":[130.78630000000001,33.6526],"type":"Point"}
}