{
  "type": "Feature",
  "properties": {
    "gn:adm1_name":"Niigataken",
    "gn:adm2_name":"Minamiuonumagunshiozawamachi",
    "gn:name":"Yoshiyamashinden",
    "iso:country":"JP",
    "wof:name":"949-6417",
    "wof:placetype":"postalcode"
},
  "geometry": {"coordinates":[138.86109999999999,37.0065],"type":"Point"}
}