{
  "type": "Feature",
  "properties": {
    "gn:adm1_name":"Fukushimaken",
    "gn:adm2_name":"Fukushimashi",
    "gn:name":"Kamata",
    "iso:country":"JP",
    "wof:name":"960-0102",
    "wof:placetype":"postalcode"
},
  "geometry": {"coordinates":[140.48699999999999,37.7947],"type":"Point"}
}