{
  "type": "Feature",
  "properties": {
    "gn:adm1_name":"Okayamaken",
    "gn:adm2_name":"Okayamashi",
    "gn:name":"Chikkouhikarimachi",
    "iso:country":"JP",
    "wof:name":"702-8054",
    "wof:placetype":"postalcode"
},
  "geometry": {"coordinates":[133.93889999999999,34.6007],"type":"Point"}
}