{
  "type": "Feature",
  "properties": {
    "gn:adm1_name":"Shizuokaken",
    "gn:adm2_name":"Shizuokashi",
    "gn:name":"Hanma",
    "iso:country":"JP",
    "wof:name":"421-1224",
    "wof:placetype":"postalcode"
},
  "geometry": {"coordinates":[138.30289999999999,34.9803],"type":"Point"}
}