{
  "type": "Feature",
  "properties": {
    "gn:adm1_name":"Miyagiken",
    "gn:adm2_name":"Kamigunkamimachi",
    "gn:name":"Hara",
    "iso:country":"JP",
    "wof:name":"981-4371",
    "wof:placetype":"postalcode"
},
  "geometry": {"coordinates":[140.7192,38.6263],"type":"Point"}
}