{
  "type": "Feature",
  "properties": {
    "gn:adm1_name":"Fukushimaken",
    "gn:adm2_name":"Aiduwakamatsushi",
    "gn:name":"Sakaemachi",
    "iso:country":"JP",
    "wof:name":"965-0871",
    "wof:placetype":"postalcode"
},
  "geometry": {"coordinates":[139.9307,37.496],"type":"Point"}
}