{
  "type": "Feature",
  "properties": {
    "gn:adm1_name":"Tochigiken",
    "gn:adm2_name":"Oyamashi",
    "gn:name":"Tenjinchou",
    "iso:country":"JP",
    "wof:name":"323-0032",
    "wof:placetype":"postalcode"
},
  "geometry": {"coordinates":[139.80029999999999,36.3071],"type":"Point"}
}