{
  "type": "Feature",
  "properties": {
    "gn:adm1_name":"Hyougoken",
    "gn:adm2_name":"Takaradukashi",
    "gn:name":"Umenochou",
    "iso:country":"JP",
    "wof:name":"665-0004",
    "wof:placetype":"postalcode"
},
  "geometry": {"coordinates":[135.34379999999999,34.8048],"type":"Point"}
}