{
  "type": "Feature",
  "properties": {
    "gn:adm1_name":"Yamaguchiken",
    "gn:adm2_name":"Yamaguchishi",
    "gn:name":"Ootemachi",
    "iso:country":"JP",
    "wof:name":"753-0072",
    "wof:placetype":"postalcode"
},
  "geometry": {"coordinates":[131.47409999999999,34.1834],"type":"Point"}
}