{
  "type": "Feature",
  "properties": {
    "gn:adm1_name":"Oosakafu",
    "gn:adm2_name":"Sennangunkumatorichou",
    "gn:name":"Shinnoda",
    "iso:country":"JP",
    "wof:name":"590-0454",
    "wof:placetype":"postalcode"
},
  "geometry": {"coordinates":[135.35509999999999,34.407],"type":"Point"}
}