{
  "type": "Feature",
  "properties": {
    "gn:adm1_name":"Oosakafu",
    "gn:adm2_name":"Suitashi",
    "gn:name":"Minamiseiwaenchou",
    "iso:country":"JP",
    "wof:name":"564-0038",
    "wof:placetype":"postalcode"
},
  "geometry": {"coordinates":[135.51580000000001,34.7543],"type":"Point"}
}