{
  "type": "Feature",
  "properties": {
    "gn:adm1_name":"Tochigiken",
    "gn:adm2_name":"Mookashi",
    "gn:name":"Iigai",
    "iso:country":"JP",
    "wof:name":"321-4405",
    "wof:placetype":"postalcode"
},
  "geometry": {"coordinates":[140.03100000000001,36.4768],"type":"Point"}
}