{
  "type": "Feature",
  "properties": {
    "gn:adm1_name":"Kyoutofu",
    "gn:adm2_name":"Ujishi",
    "gn:name":"Ookubochou",
    "iso:country":"JP",
    "wof:name":"611-0033",
    "wof:placetype":"postalcode"
},
  "geometry": {"coordinates":[135.7713,34.8714],"type":"Point"}
}