{
  "type": "Feature",
  "properties": {
    "gn:adm1_name":"Gifuken",
    "gn:adm2_name":"Gifushi",
    "gn:name":"Nishikaidenkawamukai",
    "iso:country":"JP",
    "wof:name":"501-1161",
    "wof:placetype":"postalcode"
},
  "geometry": {"coordinates":[136.70500000000001,35.4494],"type":"Point"}
}