{
  "type": "Feature",
  "properties": {
    "gn:adm1_name":"Okayamaken",
    "gn:adm2_name":"Kurashikishi",
    "gn:name":"Inarimachi",
    "iso:country":"JP",
    "wof:name":"710-0822",
    "wof:placetype":"postalcode"
},
  "geometry": {"coordinates":[133.76570000000001,34.5951],"type":"Point"}
}