{
  "type": "Feature",
  "properties": {
    "gn:adm1_name":"Mieken",
    "gn:adm2_name":"Tsushi",
    "gn:name":"Sakuradachou",
    "iso:country":"JP",
    "wof:name":"514-0047",
    "wof:placetype":"postalcode"
},
  "geometry": {"coordinates":[136.48939999999999,34.7174],"type":"Point"}
}