{
  "type": "Feature",
  "properties": {
    "gn:adm1_name":"Niigataken",
    "gn:adm2_name":"Nagaokashi",
    "gn:name":"Gotandamachi",
    "iso:country":"JP",
    "wof:name":"940-2036",
    "wof:placetype":"postalcode"
},
  "geometry": {"coordinates":[138.77369999999999,37.4578],"type":"Point"}
}