{
  "type": "Feature",
  "properties": {
    "gn:adm1_name":"Okinawaken",
    "gn:adm2_name":"Shimajirigunkitadaitouson",
    "gn:name":"Minami",
    "iso:country":"JP",
    "wof:name":"901-3901",
    "wof:placetype":"postalcode"
},
  "geometry": {"coordinates":[131.31209999999999,25.9386],"type":"Point"}
}