{
  "type": "Feature",
  "properties": {
    "gn:adm1_name":"Wakayamaken",
    "gn:adm2_name":"Hidakagunhidakachou",
    "gn:name":"Ikeda",
    "iso:country":"JP",
    "wof:name":"649-1203",
    "wof:placetype":"postalcode"
},
  "geometry": {"coordinates":[135.1343,33.9419],"type":"Point"}
}