{
  "type": "Feature",
  "properties": {
    "gn:adm1_name":"Oosakafu",
    "gn:adm2_name":"Daitoushi",
    "gn:name":"Shinden'Asahimachi",
    "iso:country":"JP",
    "wof:name":"574-0053",
    "wof:placetype":"postalcode"
},
  "geometry": {"coordinates":[135.6069,34.7101],"type":"Point"}
}