{
  "type": "Feature",
  "properties": {
    "gn:adm1_name":"Saitamaken",
    "gn:adm2_name":"Kumagayashi",
    "gn:name":"Isechou",
    "iso:country":"JP",
    "wof:name":"360-0821",
    "wof:placetype":"postalcode"
},
  "geometry": {"coordinates":[139.3751,36.1438],"type":"Point"}
}