{
  "type": "Feature",
  "properties": {
    "gn:adm1_name":"Aichiken",
    "gn:adm2_name":"Inazawashi",
    "gn:name":"Okudashimokawachou",
    "iso:country":"JP",
    "wof:name":"492-8244",
    "wof:placetype":"postalcode"
},
  "geometry": {"coordinates":[136.81720000000001,35.2243],"type":"Point"}
}