{
  "type": "Feature",
  "properties": {
    "gn:adm1_name":"Aichiken",
    "gn:adm2_name":"Tsushimashi",
    "gn:name":"Hirumachou",
    "iso:country":"JP",
    "wof:name":"496-0004",
    "wof:placetype":"postalcode"
},
  "geometry": {"coordinates":[136.76840000000001,35.1884],"type":"Point"}
}