{
  "type": "Feature",
  "properties": {
    "gn:adm1_name":"Hiroshimaken",
    "gn:adm2_name":"Ootakeshi",
    "gn:name":"Misono",
    "iso:country":"JP",
    "wof:name":"739-0624",
    "wof:placetype":"postalcode"
},
  "geometry": {"coordinates":[132.2158,34.2349],"type":"Point"}
}