{
  "type": "Feature",
  "properties": {
    "gn:adm1_name":"Hiroshimaken",
    "gn:adm2_name":"Takeharashi",
    "gn:name":"Tadanoumitokonoura",
    "iso:country":"JP",
    "wof:name":"729-2314",
    "wof:placetype":"postalcode"
},
  "geometry": {"coordinates":[132.98339999999999,34.3357],"type":"Point"}
}