{
  "type": "Feature",
  "properties": {
    "gn:adm1_name":"Fukushimaken",
    "gn:adm2_name":"Dategunyanagawamachi",
    "gn:name":"Nakamachi",
    "iso:country":"JP",
    "wof:name":"960-0782",
    "wof:placetype":"postalcode"
},
  "geometry": {"coordinates":[140.6061,37.8543],"type":"Point"}
}