{
  "type": "Feature",
  "properties": {
    "gn:adm1_name":"Tochigiken",
    "gn:adm2_name":"Mookashi",
    "gn:name":"Ooyashinmachi",
    "iso:country":"JP",
    "wof:name":"321-4332",
    "wof:placetype":"postalcode"
},
  "geometry": {"coordinates":[139.99950000000001,36.4332],"type":"Point"}
}