{
  "type": "Feature",
  "properties": {
    "gn:adm1_name":"Gunmaken",
    "gn:adm2_name":"Maebashishi",
    "gn:name":"Toribamachi",
    "iso:country":"JP",
    "wof:name":"371-0845",
    "wof:placetype":"postalcode"
},
  "geometry": {"coordinates":[139.0317,36.3771],"type":"Point"}
}