{
  "type": "Feature",
  "properties": {
    "gn:adm1_name":"Toukyouto",
    "gn:adm2_name":"Shibuyaku",
    "gn:name":"Daikanyamachou",
    "iso:country":"JP",
    "wof:name":"150-0034",
    "wof:placetype":"postalcode"
},
  "geometry": {"coordinates":[139.70410000000001,35.6506],"type":"Point"}
}