{
  "type": "Feature",
  "properties": {
    "gn:adm1_name":"Fukuokaken",
    "gn:adm2_name":"Maebarushi",
    "gn:name":"Maebaruminami",
    "iso:country":"JP",
    "wof:name":"819-1139",
    "wof:placetype":"postalcode"
},
  "geometry": {"coordinates":[130.2089,33.5568],"type":"Point"}
}