{
  "type": "Feature",
  "properties": {
    "gn:adm1_name":"Saitamaken",
    "gn:adm2_name":"Asakashi",
    "gn:name":"Mihara",
    "iso:country":"JP",
    "wof:name":"351-0025",
    "wof:placetype":"postalcode"
},
  "geometry": {"coordinates":[139.57839999999999,35.8143],"type":"Point"}
}