{
  "type": "Feature",
  "properties": {
    "gn:adm1_name":"Aichiken",
    "gn:adm2_name":"Nishikasugaigunnishibiwajimachou",
    "gn:name":"Shimosuiri",
    "iso:country":"JP",
    "wof:name":"452-0017",
    "wof:placetype":"postalcode"
},
  "geometry": {"coordinates":[136.86670000000001,35.1959],"type":"Point"}
}