{
  "type": "Feature",
  "properties": {
    "gn:adm1_name":"Hiroshimaken",
    "gn:adm2_name":"Kamogunkouchichou",
    "gn:name":"Kamikouchi",
    "iso:country":"JP",
    "wof:name":"729-1103",
    "wof:placetype":"postalcode"
},
  "geometry": {"coordinates":[132.8648,34.4785],"type":"Point"}
}