{
  "type": "Feature",
  "properties": {
    "gn:adm1_name":"Ishikawaken",
    "gn:adm2_name":"Hakuigunshikamachi",
    "gn:name":"Shimizuimae",
    "iso:country":"JP",
    "wof:name":"925-0153",
    "wof:placetype":"postalcode"
},
  "geometry": {"coordinates":[136.78749999999999,37.0189],"type":"Point"}
}