{
  "type": "Feature",
  "properties": {
    "gn:adm1_name":"Kagawaken",
    "gn:adm2_name":"Sakaideshi",
    "gn:name":"Tanimachi",
    "iso:country":"JP",
    "wof:name":"762-0033",
    "wof:placetype":"postalcode"
},
  "geometry": {"coordinates":[133.86340000000001,34.3119],"type":"Point"}
}