{
  "type": "Feature",
  "properties": {
    "gn:adm1_name":"Gifuken",
    "gn:adm2_name":"Enagun'Akechichou",
    "gn:name":"Ichibachou",
    "iso:country":"JP",
    "wof:name":"509-7703",
    "wof:placetype":"postalcode"
},
  "geometry": {"coordinates":[137.39009999999999,35.3084],"type":"Point"}
}