{
  "type": "Feature",
  "properties": {
    "gn:adm1_name":"Shimaneken",
    "gn:adm2_name":"Kanoashiguntsuwanochou",
    "gn:name":"Terada",
    "iso:country":"JP",
    "wof:name":"699-5606",
    "wof:placetype":"postalcode"
},
  "geometry": {"coordinates":[131.77449999999999,34.487],"type":"Point"}
}