{
  "type": "Feature",
  "properties": {
    "gn:adm1_name":"Toukyouto",
    "gn:adm2_name":"Katsushikaku",
    "gn:name":"Tateishi",
    "iso:country":"JP",
    "wof:name":"124-0012",
    "wof:placetype":"postalcode"
},
  "geometry": {"coordinates":[139.84829999999999,35.7402],"type":"Point"}
}