{
  "type": "Feature",
  "properties": {
    "gn:adm1_name":"Fukuokaken",
    "gn:adm2_name":"Asakuragunmiwamachi",
    "gn:name":"Shinmachi",
    "iso:country":"JP",
    "wof:name":"838-0816",
    "wof:placetype":"postalcode"
},
  "geometry": {"coordinates":[130.63820000000001,33.4339],"type":"Point"}
}