{
  "type": "Feature",
  "properties": {
    "gn:adm1_name":"Miyagiken",
    "gn:adm2_name":"Igugunmarumorimachi",
    "gn:name":"Sengariba",
    "iso:country":"JP",
    "wof:name":"981-2151",
    "wof:placetype":"postalcode"
},
  "geometry": {"coordinates":[140.76910000000001,37.9136],"type":"Point"}
}