{
  "type": "Feature",
  "properties": {
    "gn:adm1_name":"Ehimeken",
    "gn:adm2_name":"Saijoushi",
    "gn:name":"Higashimachi",
    "iso:country":"JP",
    "wof:name":"793-0026",
    "wof:placetype":"postalcode"
},
  "geometry": {"coordinates":[133.18450000000001,33.9196],"type":"Point"}
}