{
  "type": "Feature",
  "properties": {
    "gn:adm1_name":"Hyougoken",
    "gn:adm2_name":"Nishiwakishi",
    "gn:name":"Hinochou",
    "iso:country":"JP",
    "wof:name":"677-0013",
    "wof:placetype":"postalcode"
},
  "geometry": {"coordinates":[134.96459999999999,35.0075],"type":"Point"}
}