{
  "type": "Feature",
  "properties": {
    "gn:adm1_name":"Hyougoken",
    "gn:adm2_name":"Himejishi",
    "gn:name":"Hayashidachoukuchisami",
    "iso:country":"JP",
    "wof:name":"679-4222",
    "wof:placetype":"postalcode"
},
  "geometry": {"coordinates":[134.58770000000001,34.9105],"type":"Point"}
}