{
  "type": "Feature",
  "properties": {
    "gn:adm1_name":"Ooitaken",
    "gn:adm2_name":"Taketashi",
    "gn:name":"Kubo(Sonota)",
    "iso:country":"JP",
    "wof:name":"878-0156",
    "wof:placetype":"postalcode"
},
  "geometry": {"coordinates":[131.28270000000001,32.9773],"type":"Point"}
}