{
  "type": "Feature",
  "properties": {
    "gn:adm1_name":"Chibaken",
    "gn:adm2_name":"Kashiwashi",
    "gn:name":"Imayaminamichou",
    "iso:country":"JP",
    "wof:name":"277-0073",
    "wof:placetype":"postalcode"
},
  "geometry": {"coordinates":[139.95740000000001,35.8365],"type":"Point"}
}