{
  "type": "Feature",
  "properties": {
    "gn:adm1_name":"Ishikawaken",
    "gn:adm2_name":"Komatsushi",
    "gn:name":"Obishimachi",
    "iso:country":"JP",
    "wof:name":"923-0314",
    "wof:placetype":"postalcode"
},
  "geometry": {"coordinates":[136.4479,36.3387],"type":"Point"}
}