{
  "type": "Feature",
  "properties": {
    "gn:adm1_name":"Hiroshimaken",
    "gn:adm2_name":"Akigunkaitachou",
    "gn:name":"Tsukimimachi",
    "iso:country":"JP",
    "wof:name":"736-0034",
    "wof:placetype":"postalcode"
},
  "geometry": {"coordinates":[132.5367,34.3607],"type":"Point"}
}