{
  "type": "Feature",
  "properties": {
    "gn:adm1_name":"Miyazakiken",
    "gn:adm2_name":"Koyugunshintomichou",
    "gn:name":"Kamitonda",
    "iso:country":"JP",
    "wof:name":"889-1403",
    "wof:placetype":"postalcode"
},
  "geometry": {"coordinates":[131.48079999999999,32.063],"type":"Point"}
}