{
  "type": "Feature",
  "properties": {
    "gn:adm1_name":"Saitamaken",
    "gn:adm2_name":"Kawagoeshi",
    "gn:name":"Motomachi",
    "iso:country":"JP",
    "wof:name":"350-0062",
    "wof:placetype":"postalcode"
},
  "geometry": {"coordinates":[139.48339999999999,35.925],"type":"Point"}
}