{
  "type": "Feature",
  "properties": {
    "gn:adm1_name":"Wakayamaken",
    "gn:adm2_name":"Itogunkudoyamachou",
    "gn:name":"Shiide",
    "iso:country":"JP",
    "wof:name":"648-0141",
    "wof:placetype":"postalcode"
},
  "geometry": {"coordinates":[135.56610000000001,34.2711],"type":"Point"}
}