{
  "type": "Feature",
  "properties": {
    "gn:adm1_name":"Hyougoken",
    "gn:adm2_name":"Sayougunsayouchou",
    "gn:name":"Kuchinagatani",
    "iso:country":"JP",
    "wof:name":"679-5343",
    "wof:placetype":"postalcode"
},
  "geometry": {"coordinates":[134.3751,35.0348],"type":"Point"}
}