{
  "type": "Feature",
  "properties": {
    "gn:adm1_name":"Oosakafu",
    "gn:adm2_name":"Izumishi",
    "gn:name":"Kuwabarachou",
    "iso:country":"JP",
    "wof:name":"594-0066",
    "wof:placetype":"postalcode"
},
  "geometry": {"coordinates":[135.43270000000001,34.4807],"type":"Point"}
}