{
  "type": "Feature",
  "properties": {
    "gn:adm1_name":"Shizuokaken",
    "gn:adm2_name":"Yaidushi",
    "gn:name":"Honnakane",
    "iso:country":"JP",
    "wof:name":"425-0063",
    "wof:placetype":"postalcode"
},
  "geometry": {"coordinates":[138.2938,34.8277],"type":"Point"}
}