{
  "type": "Feature",
  "properties": {
    "gn:adm1_name":"Chibaken",
    "gn:adm2_name":"Nodashi",
    "gn:name":"Sekiyadomachi",
    "iso:country":"JP",
    "wof:name":"270-0206",
    "wof:placetype":"postalcode"
},
  "geometry": {"coordinates":[139.78280000000001,36.0927],"type":"Point"}
}