{
  "type": "Feature",
  "properties": {
    "gn:adm1_name":"Aichiken",
    "gn:adm2_name":"Chitashi",
    "gn:name":"Hirano",
    "iso:country":"JP",
    "wof:name":"478-0002",
    "wof:placetype":"postalcode"
},
  "geometry": {"coordinates":[136.88220000000001,34.9974],"type":"Point"}
}