{
  "type": "Feature",
  "properties": {
    "gn:adm1_name":"Shimaneken",
    "gn:adm2_name":"Iishigunkakeyamachi",
    "gn:name":"Tane",
    "iso:country":"JP",
    "wof:name":"690-2706",
    "wof:placetype":"postalcode"
},
  "geometry": {"coordinates":[132.81219999999999,35.2368],"type":"Point"}
}