{
  "type": "Feature",
  "properties": {
    "gn:adm1_name":"Tochigiken",
    "gn:adm2_name":"Shimotsugagunfujiokamachi",
    "gn:name":"Nakane",
    "iso:country":"JP",
    "wof:name":"329-0319",
    "wof:placetype":"postalcode"
},
  "geometry": {"coordinates":[139.6866,36.2822],"type":"Point"}
}