{
  "type": "Feature",
  "properties": {
    "gn:adm1_name":"Kumamotoken",
    "gn:adm2_name":"Yatsushiroshi",
    "gn:name":"Yokotemachi",
    "iso:country":"JP",
    "wof:name":"866-0873",
    "wof:placetype":"postalcode"
},
  "geometry": {"coordinates":[130.60599999999999,32.5162],"type":"Point"}
}