{
  "type": "Feature",
  "properties": {
    "gn:adm1_name":"Shizuokaken",
    "gn:adm2_name":"Kakegawashi",
    "gn:name":"Kouyamachi",
    "iso:country":"JP",
    "wof:name":"436-0055",
    "wof:placetype":"postalcode"
},
  "geometry": {"coordinates":[138.0145,34.7719],"type":"Point"}
}