{
  "type": "Feature",
  "properties": {
    "gn:adm1_name":"Ooitaken",
    "gn:adm2_name":"Ooitashi",
    "gn:name":"Nakao",
    "iso:country":"JP",
    "wof:name":"870-0862",
    "wof:placetype":"postalcode"
},
  "geometry": {"coordinates":[131.54740000000001,33.1977],"type":"Point"}
}