{
  "type": "Feature",
  "properties": {
    "gn:adm1_name":"Yamagataken",
    "gn:adm2_name":"Sakatashi",
    "gn:name":"Wakahamachou",
    "iso:country":"JP",
    "wof:name":"998-0857",
    "wof:placetype":"postalcode"
},
  "geometry": {"coordinates":[139.84960000000001,38.913],"type":"Point"}
}