{
  "type": "Feature",
  "properties": {
    "gn:adm1_name":"Naganoken",
    "gn:adm2_name":"Matsumotoshi",
    "gn:name":"Idegawamachi",
    "iso:country":"JP",
    "wof:name":"390-0826",
    "wof:placetype":"postalcode"
},
  "geometry": {"coordinates":[137.9717,36.2103],"type":"Point"}
}