{
  "type": "Feature",
  "properties": {
    "gn:adm1_name":"Hyougoken",
    "gn:adm2_name":"Nishinomiyashi",
    "gn:name":"Ochayashochou",
    "iso:country":"JP",
    "wof:name":"662-0961",
    "wof:placetype":"postalcode"
},
  "geometry": {"coordinates":[135.32679999999999,34.7378],"type":"Point"}
}