{
  "type": "Feature",
  "properties": {
    "gn:adm1_name":"Shizuokaken",
    "gn:adm2_name":"Haibaragunkawanechou",
    "gn:name":"Nukuri",
    "iso:country":"JP",
    "wof:name":"428-0106",
    "wof:placetype":"postalcode"
},
  "geometry": {"coordinates":[138.08189999999999,34.953],"type":"Point"}
}