{
  "type": "Feature",
  "properties": {
    "gn:adm1_name":"Kumamotoken",
    "gn:adm2_name":"Yatsushiroshi",
    "gn:name":"Gunchiku8banchou",
    "iso:country":"JP",
    "wof:name":"866-0005",
    "wof:placetype":"postalcode"
},
  "geometry": {"coordinates":[130.57759999999999,32.5397],"type":"Point"}
}