{
  "type": "Feature",
  "properties": {
    "gn:adm1_name":"Shimaneken",
    "gn:adm2_name":"Kanoashiguntsuwanochou",
    "gn:name":"Kouda",
    "iso:country":"JP",
    "wof:name":"699-5607",
    "wof:placetype":"postalcode"
},
  "geometry": {"coordinates":[131.7946,34.4803],"type":"Point"}
}