{
  "type": "Feature",
  "properties": {
    "gn:adm1_name":"Okayamaken",
    "gn:adm2_name":"Okayamashi",
    "gn:name":"Masunochou",
    "iso:country":"JP",
    "wof:name":"704-8175",
    "wof:placetype":"postalcode"
},
  "geometry": {"coordinates":[133.99760000000001,34.6565],"type":"Point"}
}