{
  "type": "Feature",
  "properties": {
    "gn:adm1_name":"Oosakafu",
    "gn:adm2_name":"Minooshi",
    "gn:name":"Nyoidani",
    "iso:country":"JP",
    "wof:name":"562-0011",
    "wof:placetype":"postalcode"
},
  "geometry": {"coordinates":[135.48159999999999,34.8367],"type":"Point"}
}