{
  "type": "Feature",
  "properties": {
    "gn:adm1_name":"Kagawaken",
    "gn:adm2_name":"Takamatsushi",
    "gn:name":"Muromachi",
    "iso:country":"JP",
    "wof:name":"761-8061",
    "wof:placetype":"postalcode"
},
  "geometry": {"coordinates":[134.0428,34.3255],"type":"Point"}
}