{
  "type": "Feature",
  "properties": {
    "gn:adm1_name":"Tottoriken",
    "gn:adm2_name":"Yonagoshi",
    "gn:name":"Oozaki",
    "iso:country":"JP",
    "wof:name":"683-0104",
    "wof:placetype":"postalcode"
},
  "geometry": {"coordinates":[133.26349999999999,35.4708],"type":"Point"}
}