{
  "type": "Feature",
  "properties": {
    "gn:adm1_name":"Chibaken",
    "gn:adm2_name":"Funabashishi",
    "gn:name":"Matsugaoka",
    "iso:country":"JP",
    "wof:name":"274-0064",
    "wof:placetype":"postalcode"
},
  "geometry": {"coordinates":[140.04679999999999,35.7352],"type":"Point"}
}