{
  "type": "Feature",
  "properties": {
    "gn:adm1_name":"Aichiken",
    "gn:adm2_name":"Amagunmiwachou",
    "gn:name":"Tanba",
    "iso:country":"JP",
    "wof:name":"490-1224",
    "wof:placetype":"postalcode"
},
  "geometry": {"coordinates":[136.77340000000001,35.2001],"type":"Point"}
}