{
  "type": "Feature",
  "properties": {
    "gn:adm1_name":"Mieken",
    "gn:adm2_name":"Minamimurogunmihamachou",
    "gn:name":"Ikanikeisaiganaibaai",
    "iso:country":"JP",
    "wof:name":"519-5200",
    "wof:placetype":"postalcode"
},
  "geometry": {"coordinates":[136.03970000000001,33.8681],"type":"Point"}
}