{
  "type": "Feature",
  "properties": {
    "gn:adm1_name":"Fukushimaken",
    "gn:adm2_name":"Kawanumagun'Aidubangemachi",
    "gn:name":"Katsuoo",
    "iso:country":"JP",
    "wof:name":"969-6575",
    "wof:placetype":"postalcode"
},
  "geometry": {"coordinates":[139.7971,37.5377],"type":"Point"}
}