{
  "type": "Feature",
  "properties": {
    "gn:adm1_name":"Gunmaken",
    "gn:adm2_name":"Takasakishi",
    "gn:name":"Nakaooruimachi",
    "iso:country":"JP",
    "wof:name":"370-0033",
    "wof:placetype":"postalcode"
},
  "geometry": {"coordinates":[139.05950000000001,36.3246],"type":"Point"}
}