{
  "type": "Feature",
  "properties": {
    "gn:adm1_name":"Yamagataken",
    "gn:adm2_name":"Nishiokitamagun'Ogunimachi",
    "gn:name":"Hinosawa",
    "iso:country":"JP",
    "wof:name":"999-1433",
    "wof:placetype":"postalcode"
},
  "geometry": {"coordinates":[139.7381,38.1576],"type":"Point"}
}