{
  "type": "Feature",
  "properties": {
    "gn:adm1_name":"Kouchiken",
    "gn:adm2_name":"Tosaguntosachou",
    "gn:name":"Shimokawa",
    "iso:country":"JP",
    "wof:name":"781-3525",
    "wof:placetype":"postalcode"
},
  "geometry": {"coordinates":[133.5129,33.806],"type":"Point"}
}