{
  "type": "Feature",
  "properties": {
    "gn:adm1_name":"Hyougoken",
    "gn:adm2_name":"Kanzakigunkanzakichou",
    "gn:name":"Ooyama",
    "iso:country":"JP",
    "wof:name":"679-2432",
    "wof:placetype":"postalcode"
},
  "geometry": {"coordinates":[134.78489999999999,35.1122],"type":"Point"}
}