{
  "type": "Feature",
  "properties": {
    "gn:adm1_name":"Ooitaken",
    "gn:adm2_name":"Beppushi",
    "gn:name":"Yuyama",
    "iso:country":"JP",
    "wof:name":"874-0004",
    "wof:placetype":"postalcode"
},
  "geometry": {"coordinates":[131.45320000000001,33.3235],"type":"Point"}
}