{
  "type": "Feature",
  "properties": {
    "gn:adm1_name":"Kagoshimaken",
    "gn:adm2_name":"Sendaishi",
    "gn:name":"Kokurachou",
    "iso:country":"JP",
    "wof:name":"899-1922",
    "wof:placetype":"postalcode"
},
  "geometry": {"coordinates":[130.2612,31.8463],"type":"Point"}
}