{
  "type": "Feature",
  "properties": {
    "gn:adm1_name":"Miyagiken",
    "gn:adm2_name":"Kakudashi",
    "gn:name":"Fujita",
    "iso:country":"JP",
    "wof:name":"981-1501",
    "wof:placetype":"postalcode"
},
  "geometry": {"coordinates":[140.82470000000001,37.9805],"type":"Point"}
}