{
  "type": "Feature",
  "properties": {
    "gn:adm1_name":"Kanagawaken",
    "gn:adm2_name":"Hiratsukashi",
    "gn:name":"Nakaharakamijuku",
    "iso:country":"JP",
    "wof:name":"254-0071",
    "wof:placetype":"postalcode"
},
  "geometry": {"coordinates":[139.33410000000001,35.3472],"type":"Point"}
}