{
  "type": "Feature",
  "properties": {
    "gn:adm1_name":"Toyamaken",
    "gn:adm2_name":"Shimoniikawagunnyuuzenmachi",
    "gn:name":"Tanomata",
    "iso:country":"JP",
    "wof:name":"939-0613",
    "wof:placetype":"postalcode"
},
  "geometry": {"coordinates":[137.52099999999999,36.9477],"type":"Point"}
}