{
  "type": "Feature",
  "properties": {
    "gn:adm1_name":"Oosakafu",
    "gn:adm2_name":"Hirakatashi",
    "gn:name":"Oominehigashimachi",
    "iso:country":"JP",
    "wof:name":"573-0142",
    "wof:placetype":"postalcode"
},
  "geometry": {"coordinates":[135.6918,34.8124],"type":"Point"}
}