{
  "type": "Feature",
  "properties": {
    "gn:adm1_name":"Miyazakiken",
    "gn:adm2_name":"Koyugunnishimerason",
    "gn:name":"Takewara",
    "iso:country":"JP",
    "wof:name":"881-1414",
    "wof:placetype":"postalcode"
},
  "geometry": {"coordinates":[131.15270000000001,32.2445],"type":"Point"}
}