{
  "type": "Feature",
  "properties": {
    "gn:adm1_name":"Fukuiken",
    "gn:adm2_name":"Fukuishi",
    "gn:name":"Imaichichou",
    "iso:country":"JP",
    "wof:name":"918-8152",
    "wof:placetype":"postalcode"
},
  "geometry": {"coordinates":[136.20599999999999,36.0157],"type":"Point"}
}