{
  "type": "Feature",
  "properties": {
    "gn:adm1_name":"Kyoutofu",
    "gn:adm2_name":"Maidurushi",
    "gn:name":"Mizoshirinakamachi",
    "iso:country":"JP",
    "wof:name":"625-0041",
    "wof:placetype":"postalcode"
},
  "geometry": {"coordinates":[135.40459999999999,35.4701],"type":"Point"}
}