{
  "type": "Feature",
  "properties": {
    "gn:adm1_name":"Toyamaken",
    "gn:adm2_name":"Neigunfuchuumachi",
    "gn:name":"Konagasawa",
    "iso:country":"JP",
    "wof:name":"939-2601",
    "wof:placetype":"postalcode"
},
  "geometry": {"coordinates":[137.1319,36.6644],"type":"Point"}
}