{
  "type": "Feature",
  "properties": {
    "gn:adm1_name":"Tochigiken",
    "gn:adm2_name":"Kuroisoshi",
    "gn:name":"Shimonakano",
    "iso:country":"JP",
    "wof:name":"329-3146",
    "wof:placetype":"postalcode"
},
  "geometry": {"coordinates":[140.01570000000001,36.9128],"type":"Point"}
}