{
  "type": "Feature",
  "properties": {
    "gn:adm1_name":"Hyougoken",
    "gn:adm2_name":"Koubeshinishiku",
    "gn:name":"Oshibedanichoukinkou",
    "iso:country":"JP",
    "wof:name":"651-2203",
    "wof:placetype":"postalcode"
},
  "geometry": {"coordinates":[135.03790000000001,34.7463],"type":"Point"}
}