{
  "type": "Feature",
  "properties": {
    "gn:adm1_name":"Fukuokaken",
    "gn:adm2_name":"Asakuragun'Asakuramachi",
    "gn:name":"Tadare",
    "iso:country":"JP",
    "wof:name":"838-1311",
    "wof:placetype":"postalcode"
},
  "geometry": {"coordinates":[130.721,33.3791],"type":"Point"}
}