{
  "type": "Feature",
  "properties": {
    "gn:adm1_name":"Kyoutofu",
    "gn:adm2_name":"Kyoutoshishimogyouku",
    "gn:name":"Shinkaichou",
    "iso:country":"JP",
    "wof:name":"600-8084",
    "wof:placetype":"postalcode"
},
  "geometry": {"coordinates":[135.76259999999999,35.0009],"type":"Point"}
}