{
  "type": "Feature",
  "properties": {
    "gn:adm1_name":"Hyougoken",
    "gn:adm2_name":"Yabugun'Ooyachou",
    "gn:name":"Wakasu",
    "iso:country":"JP",
    "wof:name":"667-0323",
    "wof:placetype":"postalcode"
},
  "geometry": {"coordinates":[134.5966,35.2932],"type":"Point"}
}