{
  "type": "Feature",
  "properties": {
    "gn:adm1_name":"Chibaken",
    "gn:adm2_name":"Naritashi",
    "gn:name":"Nanbu",
    "iso:country":"JP",
    "wof:name":"286-0806",
    "wof:placetype":"postalcode"
},
  "geometry": {"coordinates":[140.2961,35.8447],"type":"Point"}
}