{
  "type": "Feature",
  "properties": {
    "gn:adm1_name":"Toyamaken",
    "gn:adm2_name":"Neigunfuchuumachi",
    "gn:name":"Haneshin",
    "iso:country":"JP",
    "wof:name":"939-2704",
    "wof:placetype":"postalcode"
},
  "geometry": {"coordinates":[137.18190000000001,36.6753],"type":"Point"}
}