{
  "type": "Feature",
  "properties": {
    "gn:adm1_name":"Kumamotoken",
    "gn:adm2_name":"Asogun'Ogunimachi",
    "gn:name":"Ikanikeisaiganaibaai",
    "iso:country":"JP",
    "wof:name":"869-2500",
    "wof:placetype":"postalcode"
},
  "geometry": {"coordinates":[131.06700000000001,33.1336],"type":"Point"}
}