{
  "type": "Feature",
  "properties": {
    "gn:adm1_name":"Hiroshimaken",
    "gn:adm2_name":"Fuchuushi",
    "gn:name":"Morokechou",
    "iso:country":"JP",
    "wof:name":"722-0431",
    "wof:placetype":"postalcode"
},
  "geometry": {"coordinates":[133.1765,34.5742],"type":"Point"}
}