{
  "type": "Feature",
  "properties": {
    "gn:adm1_name":"Toyamaken",
    "gn:adm2_name":"Nishitonamigunfukumitsumachi",
    "gn:name":"Hirotani",
    "iso:country":"JP",
    "wof:name":"939-1672",
    "wof:placetype":"postalcode"
},
  "geometry": {"coordinates":[136.84,36.5264],"type":"Point"}
}