{
  "type": "Feature",
  "properties": {
    "gn:adm1_name":"Tottoriken",
    "gn:adm2_name":"Yazugunkoogechou",
    "gn:name":"Ikeda",
    "iso:country":"JP",
    "wof:name":"680-0452",
    "wof:placetype":"postalcode"
},
  "geometry": {"coordinates":[134.24010000000001,35.4101],"type":"Point"}
}