{
  "type": "Feature",
  "properties": {
    "gn:adm1_name":"Kyoutofu",
    "gn:adm2_name":"Kyoutoshinakagyouku",
    "gn:name":"Ebisuchou",
    "iso:country":"JP",
    "wof:name":"604-8005",
    "wof:placetype":"postalcode"
},
  "geometry": {"coordinates":[135.76949999999999,35.0094],"type":"Point"}
}