{
  "type": "Feature",
  "properties": {
    "gn:adm1_name":"Niigataken",
    "gn:adm2_name":"Higashikubikigunmatsunoyamamachi",
    "gn:name":"Kurokura",
    "iso:country":"JP",
    "wof:name":"942-1341",
    "wof:placetype":"postalcode"
},
  "geometry": {"coordinates":[138.5812,37.0908],"type":"Point"}
}