{
  "type": "Feature",
  "properties": {
    "gn:adm1_name":"Kanagawaken",
    "gn:adm2_name":"Hiratsukashi",
    "gn:name":"Minamitoyoda",
    "iso:country":"JP",
    "wof:name":"254-0084",
    "wof:placetype":"postalcode"
},
  "geometry": {"coordinates":[139.3278,35.3562],"type":"Point"}
}