{
  "type": "Feature",
  "properties": {
    "gn:adm1_name":"Aichiken",
    "gn:adm2_name":"Toyotashi",
    "gn:name":"Nichinanchou",
    "iso:country":"JP",
    "wof:name":"471-0032",
    "wof:placetype":"postalcode"
},
  "geometry": {"coordinates":[137.14850000000001,35.0937],"type":"Point"}
}