{
  "type": "Feature",
  "properties": {
    "gn:adm1_name":"Saitamaken",
    "gn:adm2_name":"Kitamotoshi",
    "gn:name":"Kitamotojuku",
    "iso:country":"JP",
    "wof:name":"364-0021",
    "wof:placetype":"postalcode"
},
  "geometry": {"coordinates":[139.53960000000001,36.021],"type":"Point"}
}