{
  "type": "Feature",
  "properties": {
    "gn:adm1_name":"Fukushimaken",
    "gn:adm2_name":"Minamiaiduguntadamimachi",
    "gn:name":"Tagokura",
    "iso:country":"JP",
    "wof:name":"968-0423",
    "wof:placetype":"postalcode"
},
  "geometry": {"coordinates":[139.2825,37.3029],"type":"Point"}
}