{
  "type": "Feature",
  "properties": {
    "gn:adm1_name":"Niigataken",
    "gn:adm2_name":"Niigatashi",
    "gn:name":"Teraokami",
    "iso:country":"JP",
    "wof:name":"950-2055",
    "wof:placetype":"postalcode"
},
  "geometry": {"coordinates":[138.96860000000001,37.876],"type":"Point"}
}