{
  "type": "Feature",
  "properties": {
    "gn:adm1_name":"Niigataken",
    "gn:adm2_name":"Jouetsushi",
    "gn:name":"Fukuhashi",
    "iso:country":"JP",
    "wof:name":"942-0033",
    "wof:placetype":"postalcode"
},
  "geometry": {"coordinates":[138.28139999999999,37.1724],"type":"Point"}
}