{
  "type": "Feature",
  "properties": {
    "gn:adm1_name":"Mieken",
    "gn:adm2_name":"Yokkaichishi",
    "gn:name":"Shimosazaraichou",
    "iso:country":"JP",
    "wof:name":"510-8033",
    "wof:placetype":"postalcode"
},
  "geometry": {"coordinates":[136.6429,35.0196],"type":"Point"}
}