{
  "type": "Feature",
  "properties": {
    "gn:adm1_name":"Fukuiken",
    "gn:adm2_name":"Mikatagunmikatachou",
    "gn:name":"Shakushi",
    "iso:country":"JP",
    "wof:name":"919-1455",
    "wof:placetype":"postalcode"
},
  "geometry": {"coordinates":[135.85810000000001,35.589],"type":"Point"}
}