{
  "type": "Feature",
  "properties": {
    "gn:adm1_name":"Miyazakiken",
    "gn:adm2_name":"Nobeokashi",
    "gn:name":"Ozakimachi",
    "iso:country":"JP",
    "wof:name":"882-0006",
    "wof:placetype":"postalcode"
},
  "geometry": {"coordinates":[131.66220000000001,32.6076],"type":"Point"}
}