{
  "type": "Feature",
  "properties": {
    "gn:adm1_name":"Gifuken",
    "gn:adm2_name":"Sekishi",
    "gn:name":"Nishikakenoshita",
    "iso:country":"JP",
    "wof:name":"501-3906",
    "wof:placetype":"postalcode"
},
  "geometry": {"coordinates":[136.9188,35.4782],"type":"Point"}
}