{
  "type": "Feature",
  "properties": {
    "gn:adm1_name":"Shizuokaken",
    "gn:adm2_name":"Shimodashi",
    "gn:name":"Oogamo",
    "iso:country":"JP",
    "wof:name":"415-0038",
    "wof:placetype":"postalcode"
},
  "geometry": {"coordinates":[138.90799999999999,34.6778],"type":"Point"}
}