{
  "type": "Feature",
  "properties": {
    "gn:adm1_name":"Niigataken",
    "gn:adm2_name":"Nakakubikigun'Itakuramachi",
    "gn:name":"Aoba",
    "iso:country":"JP",
    "wof:name":"944-0150",
    "wof:placetype":"postalcode"
},
  "geometry": {"coordinates":[138.28829999999999,37.0738],"type":"Point"}
}