{
  "type": "Feature",
  "properties": {
    "gn:adm1_name":"Nagasakiken",
    "gn:adm2_name":"Ikigungounourachou",
    "gn:name":"Harashima",
    "iso:country":"JP",
    "wof:name":"811-5163",
    "wof:placetype":"postalcode"
},
  "geometry": {"coordinates":[129.64859999999999,33.7232],"type":"Point"}
}