{
  "type": "Feature",
  "properties": {
    "gn:adm1_name":"Fukuokaken",
    "gn:adm2_name":"Kitakyuushuushikokuraminamiku",
    "gn:name":"Tashiro",
    "iso:country":"JP",
    "wof:name":"803-0262",
    "wof:placetype":"postalcode"
},
  "geometry": {"coordinates":[130.81010000000001,33.8092],"type":"Point"}
}