{
  "type": "Feature",
  "properties": {
    "gn:adm1_name":"Kagawaken",
    "gn:adm2_name":"Takamatsushi",
    "gn:name":"Kamimachi",
    "iso:country":"JP",
    "wof:name":"761-8055",
    "wof:placetype":"postalcode"
},
  "geometry": {"coordinates":[134.03450000000001,34.3171],"type":"Point"}
}