{
  "type": "Feature",
  "properties": {
    "gn:adm1_name":"Shigaken",
    "gn:adm2_name":"Gamougunhinochou",
    "gn:name":"Satoguchi",
    "iso:country":"JP",
    "wof:name":"529-1643",
    "wof:placetype":"postalcode"
},
  "geometry": {"coordinates":[136.227,35.0149],"type":"Point"}
}