{
  "type": "Feature",
  "properties": {
    "gn:adm1_name":"Toukyouto",
    "gn:adm2_name":"Oumeshi",
    "gn:name":"Shiobune",
    "iso:country":"JP",
    "wof:name":"198-0011",
    "wof:placetype":"postalcode"
},
  "geometry": {"coordinates":[139.28380000000001,35.8027],"type":"Point"}
}