{
  "type": "Feature",
  "properties": {
    "gn:adm1_name":"Mieken",
    "gn:adm2_name":"Inabeshi",
    "gn:name":"Hokuseichoukitanakatsuhara",
    "iso:country":"JP",
    "wof:name":"511-0422",
    "wof:placetype":"postalcode"
},
  "geometry": {"coordinates":[136.55170000000001,35.1606],"type":"Point"}
}