{
  "type": "Feature",
  "properties": {
    "gn:adm1_name":"Shimaneken",
    "gn:adm2_name":"Hiratashi",
    "gn:name":"Kawashimochou",
    "iso:country":"JP",
    "wof:name":"691-0025",
    "wof:placetype":"postalcode"
},
  "geometry": {"coordinates":[132.74639999999999,35.4426],"type":"Point"}
}