{
  "type": "Feature",
  "properties": {
    "gn:adm1_name":"Okayamaken",
    "gn:adm2_name":"Tamanoshi",
    "gn:name":"Wada",
    "iso:country":"JP",
    "wof:name":"706-0021",
    "wof:placetype":"postalcode"
},
  "geometry": {"coordinates":[133.923,34.4686],"type":"Point"}
}