{
  "type": "Feature",
  "properties": {
    "gn:adm1_name":"Niigataken",
    "gn:adm2_name":"Minamiuonumagunshiozawamachi",
    "gn:name":"Minamitanaka",
    "iso:country":"JP",
    "wof:name":"949-6362",
    "wof:placetype":"postalcode"
},
  "geometry": {"coordinates":[138.8306,37.0189],"type":"Point"}
}