{
  "type": "Feature",
  "properties": {
    "gn:adm1_name":"Mieken",
    "gn:adm2_name":"Wataraigunwataraichou",
    "gn:name":"Taguchi",
    "iso:country":"JP",
    "wof:name":"516-2118",
    "wof:placetype":"postalcode"
},
  "geometry": {"coordinates":[136.5393,34.4346],"type":"Point"}
}