{
  "type": "Feature",
  "properties": {
    "gn:adm1_name":"Niigataken",
    "gn:adm2_name":"Nishikanbaragunmakimachi",
    "gn:name":"Takenomachi",
    "iso:country":"JP",
    "wof:name":"953-0023",
    "wof:placetype":"postalcode"
},
  "geometry": {"coordinates":[138.86940000000001,37.7668],"type":"Point"}
}