{
  "type": "Feature",
  "properties": {
    "gn:adm1_name":"Saitamaken",
    "gn:adm2_name":"Wakoushi",
    "gn:name":"Shirako",
    "iso:country":"JP",
    "wof:name":"351-0101",
    "wof:placetype":"postalcode"
},
  "geometry": {"coordinates":[139.625,35.7795],"type":"Point"}
}