{
  "type": "Feature",
  "properties": {
    "gn:adm1_name":"Hyougoken",
    "gn:adm2_name":"Koubeshitarumiku",
    "gn:name":"Seigenchou",
    "iso:country":"JP",
    "wof:name":"655-0865",
    "wof:placetype":"postalcode"
},
  "geometry": {"coordinates":[135.09229999999999,34.6532],"type":"Point"}
}