{
  "type": "Feature",
  "properties": {
    "gn:adm1_name":"Gifuken",
    "gn:adm2_name":"Oonogunnyuukawamura",
    "gn:name":"Kashihara",
    "iso:country":"JP",
    "wof:name":"506-2106",
    "wof:placetype":"postalcode"
},
  "geometry": {"coordinates":[137.29169999999999,36.205],"type":"Point"}
}