{
  "type": "Feature",
  "properties": {
    "gn:adm1_name":"Kyoutofu",
    "gn:adm2_name":"Kyoutoshikitaku",
    "gn:name":"Nishigamohimurochou",
    "iso:country":"JP",
    "wof:name":"603-8855",
    "wof:placetype":"postalcode"
},
  "geometry": {"coordinates":[135.72300000000001,35.0848],"type":"Point"}
}