{
  "type": "Feature",
  "properties": {
    "gn:adm1_name":"Gifuken",
    "gn:adm2_name":"Tajimishi",
    "gn:name":"Kamimachi",
    "iso:country":"JP",
    "wof:name":"507-0806",
    "wof:placetype":"postalcode"
},
  "geometry": {"coordinates":[137.13560000000001,35.3363],"type":"Point"}
}