{
  "type": "Feature",
  "properties": {
    "gn:adm1_name":"Naganoken",
    "gn:adm2_name":"Kamiinaguntatsunomachi",
    "gn:name":"Higuchi",
    "iso:country":"JP",
    "wof:name":"399-0425",
    "wof:placetype":"postalcode"
},
  "geometry": {"coordinates":[137.99299999999999,35.9611],"type":"Point"}
}