{
  "type": "Feature",
  "properties": {
    "gn:adm1_name":"Toyamaken",
    "gn:adm2_name":"Himishi",
    "gn:name":"Awara",
    "iso:country":"JP",
    "wof:name":"935-0054",
    "wof:placetype":"postalcode"
},
  "geometry": {"coordinates":[136.93889999999999,36.8282],"type":"Point"}
}