{
  "type": "Feature",
  "properties": {
    "gn:adm1_name":"Tottoriken",
    "gn:adm2_name":"Yazugunfunaokachou",
    "gn:name":"Ooe",
    "iso:country":"JP",
    "wof:name":"680-0416",
    "wof:placetype":"postalcode"
},
  "geometry": {"coordinates":[134.27770000000001,35.3274],"type":"Point"}
}