{
  "type": "Feature",
  "properties": {
    "gn:adm1_name":"Wakayamaken",
    "gn:adm2_name":"Hidakagunyurachou",
    "gn:name":"Enokoma",
    "iso:country":"JP",
    "wof:name":"649-1104",
    "wof:placetype":"postalcode"
},
  "geometry": {"coordinates":[135.11439999999999,33.9648],"type":"Point"}
}