{
  "type": "Feature",
  "properties": {
    "gn:adm1_name":"Fukuiken",
    "gn:adm2_name":"Oonoshi",
    "gn:name":"Ariakechou",
    "iso:country":"JP",
    "wof:name":"912-0035",
    "wof:placetype":"postalcode"
},
  "geometry": {"coordinates":[136.50040000000001,35.9824],"type":"Point"}
}