{
  "type": "Feature",
  "properties": {
    "gn:adm1_name":"Ooitaken",
    "gn:adm2_name":"Saikishi",
    "gn:name":"Arajiroura",
    "iso:country":"JP",
    "wof:name":"876-0004",
    "wof:placetype":"postalcode"
},
  "geometry": {"coordinates":[131.93709999999999,32.9934],"type":"Point"}
}