{
  "type": "Feature",
  "properties": {
    "gn:adm1_name":"Niigataken",
    "gn:adm2_name":"Murakamishi",
    "gn:name":"Senamikanmachi",
    "iso:country":"JP",
    "wof:name":"958-0023",
    "wof:placetype":"postalcode"
},
  "geometry": {"coordinates":[139.45660000000001,38.231],"type":"Point"}
}