{
  "type": "Feature",
  "properties": {
    "gn:adm1_name":"Hiroshimaken",
    "gn:adm2_name":"Miharashi",
    "gn:name":"Nutahigashichoushippou",
    "iso:country":"JP",
    "wof:name":"723-0148",
    "wof:placetype":"postalcode"
},
  "geometry": {"coordinates":[133.0316,34.3917],"type":"Point"}
}