{
  "type": "Feature",
  "properties": {
    "gn:adm1_name":"Shizuokaken",
    "gn:adm2_name":"Shizuokashi",
    "gn:name":"Kagiana",
    "iso:country":"JP",
    "wof:name":"421-1302",
    "wof:placetype":"postalcode"
},
  "geometry": {"coordinates":[138.24700000000001,35.0465],"type":"Point"}
}