{
  "type": "Feature",
  "properties": {
    "gn:adm1_name":"Fukuiken",
    "gn:adm2_name":"Oonoshi",
    "gn:name":"Higashiyama",
    "iso:country":"JP",
    "wof:name":"912-0413",
    "wof:placetype":"postalcode"
},
  "geometry": {"coordinates":[136.53700000000001,35.9548],"type":"Point"}
}