{
  "type": "Feature",
  "properties": {
    "gn:adm1_name":"Ishikawaken",
    "gn:adm2_name":"Hakuiguntogimachi",
    "gn:name":"Toboshi",
    "iso:country":"JP",
    "wof:name":"925-0425",
    "wof:placetype":"postalcode"
},
  "geometry": {"coordinates":[136.79400000000001,37.1809],"type":"Point"}
}