{
  "type": "Feature",
  "properties": {
    "gn:adm1_name":"Miyagiken",
    "gn:adm2_name":"Kesennumashi",
    "gn:name":"Nagaisoakagai",
    "iso:country":"JP",
    "wof:name":"988-0237",
    "wof:placetype":"postalcode"
},
  "geometry": {"coordinates":[141.56800000000001,38.8383],"type":"Point"}
}