{
  "type": "Feature",
  "properties": {
    "gn:adm1_name":"Fukushimaken",
    "gn:adm2_name":"Dategunyanagawamachi",
    "gn:name":"Hosoya",
    "iso:country":"JP",
    "wof:name":"960-0766",
    "wof:placetype":"postalcode"
},
  "geometry": {"coordinates":[140.59469999999999,37.8277],"type":"Point"}
}