{
  "type": "Feature",
  "properties": {
    "gn:adm1_name":"Aichiken",
    "gn:adm2_name":"Owariasahishi",
    "gn:name":"Hirakochounagaikekami",
    "iso:country":"JP",
    "wof:name":"488-0872",
    "wof:placetype":"postalcode"
},
  "geometry": {"coordinates":[137.0248,35.2243],"type":"Point"}
}