{
  "type": "Feature",
  "properties": {
    "gn:adm1_name":"Tottoriken",
    "gn:adm2_name":"Tottorishi",
    "gn:name":"Uemachi",
    "iso:country":"JP",
    "wof:name":"680-0015",
    "wof:placetype":"postalcode"
},
  "geometry": {"coordinates":[134.24119999999999,35.4977],"type":"Point"}
}