{
  "type": "Feature",
  "properties": {
    "gn:adm1_name":"Hyougoken",
    "gn:adm2_name":"Sasayamashi",
    "gn:name":"Izumi",
    "iso:country":"JP",
    "wof:name":"669-2406",
    "wof:placetype":"postalcode"
},
  "geometry": {"coordinates":[135.2756,35.075],"type":"Point"}
}