{
  "type": "Feature",
  "properties": {
    "gn:adm1_name":"Kouchiken",
    "gn:adm2_name":"Sukumoshi",
    "gn:name":"Kodukushichouiyono",
    "iso:country":"JP",
    "wof:name":"788-0267",
    "wof:placetype":"postalcode"
},
  "geometry": {"coordinates":[132.72579999999999,32.888],"type":"Point"}
}