{
  "type": "Feature",
  "properties": {
    "gn:adm1_name":"Tottoriken",
    "gn:adm2_name":"Touhakugunsekiganechou",
    "gn:name":"Yonedome",
    "iso:country":"JP",
    "wof:name":"682-0431",
    "wof:placetype":"postalcode"
},
  "geometry": {"coordinates":[133.65610000000001,35.3685],"type":"Point"}
}