{
  "type": "Feature",
  "properties": {
    "gn:adm1_name":"Okinawaken",
    "gn:adm2_name":"Miyakogun'Uenoson",
    "gn:name":"Nobaru",
    "iso:country":"JP",
    "wof:name":"906-0201",
    "wof:placetype":"postalcode"
},
  "geometry": {"coordinates":[125.3245,24.7541],"type":"Point"}
}