{
  "type": "Feature",
  "properties": {
    "gn:adm1_name":"Niigataken",
    "gn:adm2_name":"Minamiuonumagunshiozawamachi",
    "gn:name":"Nagasaki",
    "iso:country":"JP",
    "wof:name":"949-6545",
    "wof:placetype":"postalcode"
},
  "geometry": {"coordinates":[138.89920000000001,37.0096],"type":"Point"}
}