{
  "type": "Feature",
  "properties": {
    "gn:adm1_name":"Nagasakiken",
    "gn:adm2_name":"Shimoagatagun'Iduharamachi",
    "gn:name":"Kunehama",
    "iso:country":"JP",
    "wof:name":"817-0244",
    "wof:placetype":"postalcode"
},
  "geometry": {"coordinates":[129.1788,34.1668],"type":"Point"}
}