{
  "type": "Feature",
  "properties": {
    "gn:adm1_name":"Aichiken",
    "gn:adm2_name":"Niwagunfusouchou",
    "gn:name":"Takagi",
    "iso:country":"JP",
    "wof:name":"480-0107",
    "wof:placetype":"postalcode"
},
  "geometry": {"coordinates":[136.91040000000001,35.3585],"type":"Point"}
}