{
  "type": "Feature",
  "properties": {
    "gn:adm1_name":"Kyoutofu",
    "gn:adm2_name":"Kyoutoshikitaku",
    "gn:name":"Kinugasaaramichou",
    "iso:country":"JP",
    "wof:name":"603-8315",
    "wof:placetype":"postalcode"
},
  "geometry": {"coordinates":[135.7355,35.0371],"type":"Point"}
}