{
  "type": "Feature",
  "properties": {
    "gn:adm1_name":"Ehimeken",
    "gn:adm2_name":"Kamiukenagunmikawamura",
    "gn:name":"Sawatari",
    "iso:country":"JP",
    "wof:name":"791-1514",
    "wof:placetype":"postalcode"
},
  "geometry": {"coordinates":[132.9896,33.6101],"type":"Point"}
}