{
  "type": "Feature",
  "properties": {
    "gn:adm1_name":"Tokushimaken",
    "gn:adm2_name":"Narutoshi",
    "gn:name":"Ooasachounishiumadume",
    "iso:country":"JP",
    "wof:name":"779-0314",
    "wof:placetype":"postalcode"
},
  "geometry": {"coordinates":[134.53960000000001,34.142],"type":"Point"}
}