{
  "type": "Feature",
  "properties": {
    "gn:adm1_name":"Miyagiken",
    "gn:adm2_name":"Kamigunkamimachi",
    "gn:name":"Hakkokushita",
    "iso:country":"JP",
    "wof:name":"981-4352",
    "wof:placetype":"postalcode"
},
  "geometry": {"coordinates":[140.76900000000001,38.5752],"type":"Point"}
}