{
  "type": "Feature",
  "properties": {
    "gn:adm1_name":"Saitamaken",
    "gn:adm2_name":"Saitamashiminamiku",
    "gn:name":"Buzou",
    "iso:country":"JP",
    "wof:name":"336-0025",
    "wof:placetype":"postalcode"
},
  "geometry": {"coordinates":[139.67140000000001,35.84],"type":"Point"}
}