{
  "type": "Feature",
  "properties": {
    "gn:adm1_name":"Fukuiken",
    "gn:adm2_name":"Oonoshi",
    "gn:name":"Nakaho",
    "iso:country":"JP",
    "wof:name":"912-0014",
    "wof:placetype":"postalcode"
},
  "geometry": {"coordinates":[136.51079999999999,35.9883],"type":"Point"}
}