{
  "type": "Feature",
  "properties": {
    "gn:adm1_name":"Naraken",
    "gn:adm2_name":"Kitakatsuragigunkawaichou",
    "gn:name":"Kawai",
    "iso:country":"JP",
    "wof:name":"636-0051",
    "wof:placetype":"postalcode"
},
  "geometry": {"coordinates":[135.74529999999999,34.5876],"type":"Point"}
}