{
  "type": "Feature",
  "properties": {
    "gn:adm1_name":"Fukuokaken",
    "gn:adm2_name":"Fukuokashihigashiku",
    "gn:name":"Natadanchi",
    "iso:country":"JP",
    "wof:name":"811-0205",
    "wof:placetype":"postalcode"
},
  "geometry": {"coordinates":[130.41399999999999,33.6859],"type":"Point"}
}