{
  "type": "Feature",
  "properties": {
    "gn:adm1_name":"Toyamaken",
    "gn:adm2_name":"Namerikawashi",
    "gn:name":"Tanakashinmachi",
    "iso:country":"JP",
    "wof:name":"936-0056",
    "wof:placetype":"postalcode"
},
  "geometry": {"coordinates":[137.34030000000001,36.7608],"type":"Point"}
}