{
  "type": "Feature",
  "properties": {
    "gn:adm1_name":"Aichiken",
    "gn:adm2_name":"Nagoyashitenpakuku",
    "gn:name":"Oonechou",
    "iso:country":"JP",
    "wof:name":"468-0024",
    "wof:placetype":"postalcode"
},
  "geometry": {"coordinates":[136.99010000000001,35.1137],"type":"Point"}
}