{
  "type": "Feature",
  "properties": {
    "gn:adm1_name":"Niigataken",
    "gn:adm2_name":"Tookamachishi",
    "gn:name":"Chiyodachou",
    "iso:country":"JP",
    "wof:name":"948-0078",
    "wof:placetype":"postalcode"
},
  "geometry": {"coordinates":[138.7525,37.1357],"type":"Point"}
}