{
  "type": "Feature",
  "properties": {
    "gn:adm1_name":"Niigataken",
    "gn:adm2_name":"Tsubameshi",
    "gn:name":"Chuuoudoori",
    "iso:country":"JP",
    "wof:name":"959-1244",
    "wof:placetype":"postalcode"
},
  "geometry": {"coordinates":[138.93270000000001,37.6704],"type":"Point"}
}