{
  "type": "Feature",
  "properties": {
    "gn:adm1_name":"Hiroshimaken",
    "gn:adm2_name":"Yamagatagungeihokuchou",
    "gn:name":"Takano",
    "iso:country":"JP",
    "wof:name":"731-2201",
    "wof:placetype":"postalcode"
},
  "geometry": {"coordinates":[132.37450000000001,34.7569],"type":"Point"}
}