{
  "type": "Feature",
  "properties": {
    "gn:adm1_name":"Ehimeken",
    "gn:adm2_name":"Ochigunyoshiumichou",
    "gn:name":"Myou",
    "iso:country":"JP",
    "wof:name":"794-2114",
    "wof:placetype":"postalcode"
},
  "geometry": {"coordinates":[133.0361,34.1309],"type":"Point"}
}