{
  "type": "Feature",
  "properties": {
    "gn:adm1_name":"Kagoshimaken",
    "gn:adm2_name":"Makurazakishi",
    "gn:name":"Hinokamimisakichou",
    "iso:country":"JP",
    "wof:name":"898-0049",
    "wof:placetype":"postalcode"
},
  "geometry": {"coordinates":[130.273,31.2543],"type":"Point"}
}