{
  "type": "Feature",
  "properties": {
    "gn:adm1_name":"Ehimeken",
    "gn:adm2_name":"Nishiuwagun'Ikatachou",
    "gn:name":"Kawanagata",
    "iso:country":"JP",
    "wof:name":"796-0312",
    "wof:placetype":"postalcode"
},
  "geometry": {"coordinates":[132.33930000000001,33.4846],"type":"Point"}
}