{
  "type": "Feature",
  "properties": {
    "gn:adm1_name":"Aichiken",
    "gn:adm2_name":"Inazawashi",
    "gn:name":"Akaikeyamanakachou",
    "iso:country":"JP",
    "wof:name":"492-8007",
    "wof:placetype":"postalcode"
},
  "geometry": {"coordinates":[136.8202,35.274],"type":"Point"}
}