{
  "type": "Feature",
  "properties": {
    "gn:adm1_name":"Gifuken",
    "gn:adm2_name":"Gifushi",
    "gn:name":"Kamikidaijinaka",
    "iso:country":"JP",
    "wof:name":"502-0862",
    "wof:placetype":"postalcode"
},
  "geometry": {"coordinates":[136.7449,35.4717],"type":"Point"}
}