{
  "type": "Feature",
  "properties": {
    "gn:adm1_name":"Kyoutofu",
    "gn:adm2_name":"Miyadushi",
    "gn:name":"Nakamura",
    "iso:country":"JP",
    "wof:name":"626-0076",
    "wof:placetype":"postalcode"
},
  "geometry": {"coordinates":[135.2405,35.5373],"type":"Point"}
}