{
  "type": "Feature",
  "properties": {
    "gn:adm1_name":"Okayamaken",
    "gn:adm2_name":"Maniwagun'Ochiaichou",
    "gn:name":"Maitaka",
    "iso:country":"JP",
    "wof:name":"719-3135",
    "wof:placetype":"postalcode"
},
  "geometry": {"coordinates":[133.78129999999999,34.9971],"type":"Point"}
}