{
  "type": "Feature",
  "properties": {
    "gn:adm1_name":"Aichiken",
    "gn:adm2_name":"Inazawashi",
    "gn:name":"Inajimahoujoujichou",
    "iso:country":"JP",
    "wof:name":"492-8206",
    "wof:placetype":"postalcode"
},
  "geometry": {"coordinates":[136.7989,35.2587],"type":"Point"}
}