{
  "type": "Feature",
  "properties": {
    "gn:adm1_name":"Gifuken",
    "gn:adm2_name":"Kanishi",
    "gn:name":"Shimoedo",
    "iso:country":"JP",
    "wof:name":"509-0203",
    "wof:placetype":"postalcode"
},
  "geometry": {"coordinates":[137.05019999999999,35.4233],"type":"Point"}
}