{
  "type": "Feature",
  "properties": {
    "gn:adm1_name":"Fukuokaken",
    "gn:adm2_name":"Yukuhashishi",
    "gn:name":"Jindenmachi",
    "iso:country":"JP",
    "wof:name":"824-0007",
    "wof:placetype":"postalcode"
},
  "geometry": {"coordinates":[130.9734,33.7251],"type":"Point"}
}