{
  "type": "Feature",
  "properties": {
    "gn:adm1_name":"Gunmaken",
    "gn:adm2_name":"Ouragun'Itakuramachi",
    "gn:name":"Nishiokashinden",
    "iso:country":"JP",
    "wof:name":"374-0106",
    "wof:placetype":"postalcode"
},
  "geometry": {"coordinates":[139.6087,36.2629],"type":"Point"}
}