{
  "type": "Feature",
  "properties": {
    "gn:adm1_name":"Yamagataken",
    "gn:adm2_name":"Higashiokitamagunkawanishimachi",
    "gn:name":"Kamiokuda",
    "iso:country":"JP",
    "wof:name":"999-0152",
    "wof:placetype":"postalcode"
},
  "geometry": {"coordinates":[140.02680000000001,37.9636],"type":"Point"}
}