{
  "type": "Feature",
  "properties": {
    "gn:adm1_name":"Sagaken",
    "gn:adm2_name":"Higashimatsuuragungenkaichou",
    "gn:name":"Moroura",
    "iso:country":"JP",
    "wof:name":"847-1421",
    "wof:placetype":"postalcode"
},
  "geometry": {"coordinates":[129.8734,33.4722],"type":"Point"}
}