{
  "type": "Feature",
  "properties": {
    "gn:adm1_name":"Saitamaken",
    "gn:adm2_name":"Koshigayashi",
    "gn:name":"Onma",
    "iso:country":"JP",
    "wof:name":"343-0033",
    "wof:placetype":"postalcode"
},
  "geometry": {"coordinates":[139.77010000000001,35.9259],"type":"Point"}
}