{
  "type": "Feature",
  "properties": {
    "gn:adm1_name":"Hiroshimaken",
    "gn:adm2_name":"Hiroshimashiminamiku",
    "gn:name":"Ninoshimachou",
    "iso:country":"JP",
    "wof:name":"734-0017",
    "wof:placetype":"postalcode"
},
  "geometry": {"coordinates":[132.43450000000001,34.3112],"type":"Point"}
}