{
  "type": "Feature",
  "properties": {
    "gn:adm1_name":"Miyagiken",
    "gn:adm2_name":"Motoyoshigunshidugawachou",
    "gn:name":"Gozenshita",
    "iso:country":"JP",
    "wof:name":"986-0768",
    "wof:placetype":"postalcode"
},
  "geometry": {"coordinates":[141.4391,38.687],"type":"Point"}
}