{
  "type": "Feature",
  "properties": {
    "gn:adm1_name":"Shizuokaken",
    "gn:adm2_name":"Shimodashi",
    "gn:name":"Ochiai",
    "iso:country":"JP",
    "wof:name":"413-0701",
    "wof:placetype":"postalcode"
},
  "geometry": {"coordinates":[138.95009999999999,34.7208],"type":"Point"}
}