{
  "type": "Feature",
  "properties": {
    "gn:adm1_name":"Kouchiken",
    "gn:adm2_name":"Agawagun'Agawamura",
    "gn:name":"Kitagawa",
    "iso:country":"JP",
    "wof:name":"781-1746",
    "wof:placetype":"postalcode"
},
  "geometry": {"coordinates":[133.11150000000001,33.5911],"type":"Point"}
}