{
  "type": "Feature",
  "properties": {
    "gn:adm1_name":"Fukushimaken",
    "gn:adm2_name":"Shirakawashi",
    "gn:name":"Juumonji",
    "iso:country":"JP",
    "wof:name":"961-0027",
    "wof:placetype":"postalcode"
},
  "geometry": {"coordinates":[140.2252,37.0992],"type":"Point"}
}