{
  "type": "Feature",
  "properties": {
    "gn:adm1_name":"Toukyouto",
    "gn:adm2_name":"Kokubunjishi",
    "gn:name":"Fujimoto",
    "iso:country":"JP",
    "wof:name":"185-0031",
    "wof:placetype":"postalcode"
},
  "geometry": {"coordinates":[139.44880000000001,35.7064],"type":"Point"}
}