{
  "type": "Feature",
  "properties": {
    "gn:adm1_name":"Gifuken",
    "gn:adm2_name":"Gifushi",
    "gn:name":"Rokujouminami",
    "iso:country":"JP",
    "wof:name":"500-8358",
    "wof:placetype":"postalcode"
},
  "geometry": {"coordinates":[136.74029999999999,35.3973],"type":"Point"}
}