{
  "type": "Feature",
  "properties": {
    "gn:adm1_name":"Niigataken",
    "gn:adm2_name":"Iwafunegun'Arakawamachi",
    "gn:name":"Nakakura",
    "iso:country":"JP",
    "wof:name":"959-3123",
    "wof:placetype":"postalcode"
},
  "geometry": {"coordinates":[139.4299,38.1254],"type":"Point"}
}