{
  "type": "Feature",
  "properties": {
    "gn:adm1_name":"Naganoken",
    "gn:adm2_name":"Chiisagatagunnagatomachi",
    "gn:name":"Daimon",
    "iso:country":"JP",
    "wof:name":"386-0601",
    "wof:placetype":"postalcode"
},
  "geometry": {"coordinates":[138.2405,36.1672],"type":"Point"}
}