{
  "type": "Feature",
  "properties": {
    "gn:adm1_name":"Gifuken",
    "gn:adm2_name":"Gifushi",
    "gn:name":"Minamisemi",
    "iso:country":"JP",
    "wof:name":"502-0852",
    "wof:placetype":"postalcode"
},
  "geometry": {"coordinates":[136.76159999999999,35.4467],"type":"Point"}
}