{
  "type": "Feature",
  "properties": {
    "gn:adm1_name":"Ehimeken",
    "gn:adm2_name":"Onsengunshigenobuchou",
    "gn:name":"Noda",
    "iso:country":"JP",
    "wof:name":"791-0216",
    "wof:placetype":"postalcode"
},
  "geometry": {"coordinates":[132.8381,33.795],"type":"Point"}
}