{
  "type": "Feature",
  "properties": {
    "gn:adm1_name":"Shizuokaken",
    "gn:adm2_name":"Shizuokashi",
    "gn:name":"Higashichiyoda",
    "iso:country":"JP",
    "wof:name":"420-0801",
    "wof:placetype":"postalcode"
},
  "geometry": {"coordinates":[138.40889999999999,35.0018],"type":"Point"}
}