{
  "type": "Feature",
  "properties": {
    "gn:adm1_name":"Ibarakiken",
    "gn:adm2_name":"Hitachiootashi",
    "gn:name":"Mayumichou",
    "iso:country":"JP",
    "wof:name":"313-0022",
    "wof:placetype":"postalcode"
},
  "geometry": {"coordinates":[140.57839999999999,36.5307],"type":"Point"}
}