{
  "type": "Feature",
  "properties": {
    "gn:adm1_name":"Oosakafu",
    "gn:adm2_name":"Takatsukishi",
    "gn:name":"Nasaharamotomachi",
    "iso:country":"JP",
    "wof:name":"569-1043",
    "wof:placetype":"postalcode"
},
  "geometry": {"coordinates":[135.5847,34.863],"type":"Point"}
}