{
  "type": "Feature",
  "properties": {
    "gn:adm1_name":"Shizuokaken",
    "gn:adm2_name":"Iwatagunryuuyouchou",
    "gn:name":"Kawabukuro",
    "iso:country":"JP",
    "wof:name":"438-0232",
    "wof:placetype":"postalcode"
},
  "geometry": {"coordinates":[137.80189999999999,34.6782],"type":"Point"}
}