{
  "type": "Feature",
  "properties": {
    "gn:adm1_name":"Oosakafu",
    "gn:adm2_name":"Oosakashisumiyoshiku",
    "gn:name":"Abikonishi",
    "iso:country":"JP",
    "wof:name":"558-0015",
    "wof:placetype":"postalcode"
},
  "geometry": {"coordinates":[135.50630000000001,34.6034],"type":"Point"}
}