{
  "type": "Feature",
  "properties": {
    "gn:adm1_name":"Niigataken",
    "gn:adm2_name":"Kariwagunkariwamura",
    "gn:name":"Shoumyouji",
    "iso:country":"JP",
    "wof:name":"945-0317",
    "wof:placetype":"postalcode"
},
  "geometry": {"coordinates":[138.6003,37.4047],"type":"Point"}
}