{
  "type": "Feature",
  "properties": {
    "gn:adm1_name":"Nagasakiken",
    "gn:adm2_name":"Shimoagatagunmitsushimachou",
    "gn:name":"Yoshigaura",
    "iso:country":"JP",
    "wof:name":"817-1102",
    "wof:placetype":"postalcode"
},
  "geometry": {"coordinates":[129.37260000000001,34.3475],"type":"Point"}
}