{
  "type": "Feature",
  "properties": {
    "gn:adm1_name":"Mieken",
    "gn:adm2_name":"Kuwanagunkisosakichou",
    "gn:name":"Sakae",
    "iso:country":"JP",
    "wof:name":"498-0811",
    "wof:placetype":"postalcode"
},
  "geometry": {"coordinates":[136.73910000000001,35.0715],"type":"Point"}
}