{
  "type": "Feature",
  "properties": {
    "gn:adm1_name":"Toyamaken",
    "gn:adm2_name":"Nishitonamigunfukumitsumachi",
    "gn:name":"Sodani",
    "iso:country":"JP",
    "wof:name":"939-1675",
    "wof:placetype":"postalcode"
},
  "geometry": {"coordinates":[136.84809999999999,36.5369],"type":"Point"}
}