{
  "type": "Feature",
  "properties": {
    "gn:adm1_name":"Gifuken",
    "gn:adm2_name":"Kaidugunkaiduchou",
    "gn:name":"Tanaka",
    "iso:country":"JP",
    "wof:name":"503-0606",
    "wof:placetype":"postalcode"
},
  "geometry": {"coordinates":[136.66290000000001,35.2306],"type":"Point"}
}