{
  "type": "Feature",
  "properties": {
    "gn:adm1_name":"Mieken",
    "gn:adm2_name":"Yokkaichishi",
    "gn:name":"Nakamachi",
    "iso:country":"JP",
    "wof:name":"510-0096",
    "wof:placetype":"postalcode"
},
  "geometry": {"coordinates":[136.62989999999999,34.969],"type":"Point"}
}