{
  "type": "Feature",
  "properties": {
    "gn:adm1_name":"Yamanashiken",
    "gn:adm2_name":"Nishiyatsushirogun'Ichikawadaimonchou",
    "gn:name":"Ichikawadaimonchounotsuginibanchigakurubaai",
    "iso:country":"JP",
    "wof:name":"409-3601",
    "wof:placetype":"postalcode"
},
  "geometry": {"coordinates":[138.50309999999999,35.5243],"type":"Point"}
}