{
  "type": "Feature",
  "properties": {
    "gn:adm1_name":"Kumamotoken",
    "gn:adm2_name":"Kumamotoshi",
    "gn:name":"Suigen",
    "iso:country":"JP",
    "wof:name":"862-0907",
    "wof:placetype":"postalcode"
},
  "geometry": {"coordinates":[130.75630000000001,32.7753],"type":"Point"}
}