{
  "type": "Feature",
  "properties": {
    "gn:adm1_name":"Okayamaken",
    "gn:adm2_name":"Tomatagunkagaminochou",
    "gn:name":"Yoshihara",
    "iso:country":"JP",
    "wof:name":"708-0332",
    "wof:placetype":"postalcode"
},
  "geometry": {"coordinates":[133.9358,35.0688],"type":"Point"}
}