{
  "type": "Feature",
  "properties": {
    "gn:adm1_name":"Kyoutofu",
    "gn:adm2_name":"Fukuchiyamashi",
    "gn:name":"Oono",
    "iso:country":"JP",
    "wof:name":"620-0858",
    "wof:placetype":"postalcode"
},
  "geometry": {"coordinates":[135.17089999999999,35.2866],"type":"Point"}
}