{
  "type": "Feature",
  "properties": {
    "gn:adm1_name":"Toyamaken",
    "gn:adm2_name":"Nakaniikawagunkamiichimachi",
    "gn:name":"Higashiegami",
    "iso:country":"JP",
    "wof:name":"930-0312",
    "wof:placetype":"postalcode"
},
  "geometry": {"coordinates":[137.34790000000001,36.7217],"type":"Point"}
}