{
  "type": "Feature",
  "properties": {
    "gn:adm1_name":"Fukushimaken",
    "gn:adm2_name":"Kitakatashi",
    "gn:name":"Minamimachi",
    "iso:country":"JP",
    "wof:name":"966-0074",
    "wof:placetype":"postalcode"
},
  "geometry": {"coordinates":[139.8802,37.6545],"type":"Point"}
}