{
  "type": "Feature",
  "properties": {
    "gn:adm1_name":"Kanagawaken",
    "gn:adm2_name":"Yokohamashiminamiku",
    "gn:name":"Sanya",
    "iso:country":"JP",
    "wof:name":"232-0036",
    "wof:placetype":"postalcode"
},
  "geometry": {"coordinates":[139.62629999999999,35.4298],"type":"Point"}
}