{
  "type": "Feature",
  "properties": {
    "gn:adm1_name":"Tottoriken",
    "gn:adm2_name":"Iwamigun'Iwamichou",
    "gn:name":"Aiyama",
    "iso:country":"JP",
    "wof:name":"681-0036",
    "wof:placetype":"postalcode"
},
  "geometry": {"coordinates":[134.3766,35.5383],"type":"Point"}
}