{
  "type": "Feature",
  "properties": {
    "gn:adm1_name":"Fukuokaken",
    "gn:adm2_name":"Chikushigunnakagawamachi",
    "gn:name":"Nishiguma",
    "iso:country":"JP",
    "wof:name":"811-1242",
    "wof:placetype":"postalcode"
},
  "geometry": {"coordinates":[130.42019999999999,33.4995],"type":"Point"}
}