{
  "type": "Feature",
  "properties": {
    "gn:adm1_name":"Shizuokaken",
    "gn:adm2_name":"Fujishi",
    "gn:name":"Nagatakitachou",
    "iso:country":"JP",
    "wof:name":"417-0058",
    "wof:placetype":"postalcode"
},
  "geometry": {"coordinates":[138.67760000000001,35.1637],"type":"Point"}
}