{
  "type": "Feature",
  "properties": {
    "gn:adm1_name":"Okayamaken",
    "gn:adm2_name":"Okayamashi",
    "gn:name":"Fukushima",
    "iso:country":"JP",
    "wof:name":"702-8044",
    "wof:placetype":"postalcode"
},
  "geometry": {"coordinates":[133.95429999999999,34.6152],"type":"Point"}
}