{
  "type": "Feature",
  "properties": {
    "gn:adm1_name":"Oosakafu",
    "gn:adm2_name":"Ibarakishi",
    "gn:name":"Shimootowa",
    "iso:country":"JP",
    "wof:name":"568-0082",
    "wof:placetype":"postalcode"
},
  "geometry": {"coordinates":[135.54060000000001,34.9054],"type":"Point"}
}