{
  "type": "Feature",
  "properties": {
    "gn:adm1_name":"Miyazakiken",
    "gn:adm2_name":"Nichinanshi",
    "gn:name":"Umegahama",
    "iso:country":"JP",
    "wof:name":"887-0017",
    "wof:placetype":"postalcode"
},
  "geometry": {"coordinates":[131.40780000000001,31.5861],"type":"Point"}
}