{
  "type": "Feature",
  "properties": {
    "gn:adm1_name":"Kyoutofu",
    "gn:adm2_name":"Kyoutoshiyamashinaku",
    "gn:name":"Kawatakakenoue",
    "iso:country":"JP",
    "wof:name":"607-8334",
    "wof:placetype":"postalcode"
},
  "geometry": {"coordinates":[135.79920000000001,34.9794],"type":"Point"}
}