{
  "type": "Feature",
  "properties": {
    "gn:adm1_name":"Miyagiken",
    "gn:adm2_name":"Shibatagunshibatamachi",
    "gn:name":"Funaokahigashi",
    "iso:country":"JP",
    "wof:name":"989-1604",
    "wof:placetype":"postalcode"
},
  "geometry": {"coordinates":[140.77529999999999,38.0567],"type":"Point"}
}