{
  "type": "Feature",
  "properties": {
    "gn:adm1_name":"Kanagawaken",
    "gn:adm2_name":"Yamatoshi",
    "gn:name":"Souyagi",
    "iso:country":"JP",
    "wof:name":"242-0026",
    "wof:placetype":"postalcode"
},
  "geometry": {"coordinates":[139.45679999999999,35.4626],"type":"Point"}
}