{
  "type": "Feature",
  "properties": {
    "gn:adm1_name":"Kanagawaken",
    "gn:adm2_name":"Atsugishi",
    "gn:name":"Tomuro",
    "iso:country":"JP",
    "wof:name":"243-0031",
    "wof:placetype":"postalcode"
},
  "geometry": {"coordinates":[139.35040000000001,35.4487],"type":"Point"}
}