{
  "type": "Feature",
  "properties": {
    "gn:adm1_name":"Miyazakiken",
    "gn:adm2_name":"Nichinanshi",
    "gn:name":"Kamikata",
    "iso:country":"JP",
    "wof:name":"889-3151",
    "wof:placetype":"postalcode"
},
  "geometry": {"coordinates":[131.3561,31.564],"type":"Point"}
}