{
  "type": "Feature",
  "properties": {
    "gn:adm1_name":"Yamagataken",
    "gn:adm2_name":"Murayamashi",
    "gn:name":"Tateokaaramachi",
    "iso:country":"JP",
    "wof:name":"995-0032",
    "wof:placetype":"postalcode"
},
  "geometry": {"coordinates":[140.39240000000001,38.4772],"type":"Point"}
}