{
  "type": "Feature",
  "properties": {
    "gn:adm1_name":"Ibarakiken",
    "gn:adm2_name":"Tsukubashi",
    "gn:name":"Suginoki",
    "iso:country":"JP",
    "wof:name":"300-4217",
    "wof:placetype":"postalcode"
},
  "geometry": {"coordinates":[140.07900000000001,36.1869],"type":"Point"}
}