{
  "type": "Feature",
  "properties": {
    "gn:adm1_name":"Naganoken",
    "gn:adm2_name":"Kamiminochigunshinanomachi",
    "gn:name":"Kashiwabara",
    "iso:country":"JP",
    "wof:name":"389-1305",
    "wof:placetype":"postalcode"
},
  "geometry": {"coordinates":[138.19370000000001,36.8075],"type":"Point"}
}