{
  "type": "Feature",
  "properties": {
    "gn:adm1_name":"Kanagawaken",
    "gn:adm2_name":"Atsugishi",
    "gn:name":"Izumichou",
    "iso:country":"JP",
    "wof:name":"243-0013",
    "wof:placetype":"postalcode"
},
  "geometry": {"coordinates":[139.36600000000001,35.4397],"type":"Point"}
}