{
  "type": "Feature",
  "properties": {
    "gn:adm1_name":"Hiroshimaken",
    "gn:adm2_name":"Jinsekigunjinsekichou",
    "gn:name":"Tandou",
    "iso:country":"JP",
    "wof:name":"729-3514",
    "wof:placetype":"postalcode"
},
  "geometry": {"coordinates":[133.17619999999999,34.734],"type":"Point"}
}