{
  "type": "Feature",
  "properties": {
    "gn:adm1_name":"Niigataken",
    "gn:adm2_name":"Kashiwazakishi",
    "gn:name":"Yamadani",
    "iso:country":"JP",
    "wof:name":"949-3726",
    "wof:placetype":"postalcode"
},
  "geometry": {"coordinates":[138.65129999999999,37.363],"type":"Point"}
}