{
  "type": "Feature",
  "properties": {
    "gn:adm1_name":"Fukushimaken",
    "gn:adm2_name":"Nishishirakawagunyabukimachi",
    "gn:name":"Joushikimen",
    "iso:country":"JP",
    "wof:name":"969-0266",
    "wof:placetype":"postalcode"
},
  "geometry": {"coordinates":[140.34030000000001,37.1581],"type":"Point"}
}