{
  "type": "Feature",
  "properties": {
    "gn:adm1_name":"Aichiken",
    "gn:adm2_name":"Toyohashishi",
    "gn:name":"Ooiwachou(Minamimotoyashiki)",
    "iso:country":"JP",
    "wof:name":"441-3144",
    "wof:placetype":"postalcode"
},
  "geometry": {"coordinates":[137.43989999999999,34.7259],"type":"Point"}
}