{
  "type": "Feature",
  "properties": {
    "gn:adm1_name":"Oosakafu",
    "gn:adm2_name":"Takatsukishi",
    "gn:name":"Tsutsumichou",
    "iso:country":"JP",
    "wof:name":"569-0047",
    "wof:placetype":"postalcode"
},
  "geometry": {"coordinates":[135.61850000000001,34.8268],"type":"Point"}
}