{
  "type": "Feature",
  "properties": {
    "gn:adm1_name":"Aichiken",
    "gn:adm2_name":"Setoshi",
    "gn:name":"Nishioiwakechou",
    "iso:country":"JP",
    "wof:name":"489-0065",
    "wof:placetype":"postalcode"
},
  "geometry": {"coordinates":[137.0822,35.2251],"type":"Point"}
}