{
  "type": "Feature",
  "properties": {
    "gn:adm1_name":"Okayamaken",
    "gn:adm2_name":"Takahashishi",
    "gn:name":"Kougachou",
    "iso:country":"JP",
    "wof:name":"716-0026",
    "wof:placetype":"postalcode"
},
  "geometry": {"coordinates":[133.61670000000001,34.7941],"type":"Point"}
}