{
  "type": "Feature",
  "properties": {
    "gn:adm1_name":"Tottoriken",
    "gn:adm2_name":"Touhakugunmisasachou",
    "gn:name":"Yutani",
    "iso:country":"JP",
    "wof:name":"682-0171",
    "wof:placetype":"postalcode"
},
  "geometry": {"coordinates":[133.8603,35.3906],"type":"Point"}
}