{
  "type": "Feature",
  "properties": {
    "gn:adm1_name":"Aichiken",
    "gn:adm2_name":"Tsushimashi",
    "gn:name":"Shironokoshichou",
    "iso:country":"JP",
    "wof:name":"496-0821",
    "wof:placetype":"postalcode"
},
  "geometry": {"coordinates":[136.72300000000001,35.1811],"type":"Point"}
}