{
  "type": "Feature",
  "properties": {
    "gn:adm1_name":"Ibarakiken",
    "gn:adm2_name":"Makabegunkyouwamachi",
    "gn:name":"Ooshima",
    "iso:country":"JP",
    "wof:name":"309-1125",
    "wof:placetype":"postalcode"
},
  "geometry": {"coordinates":[140.04820000000001,36.3039],"type":"Point"}
}