{
  "type": "Feature",
  "properties": {
    "gn:adm1_name":"Okayamaken",
    "gn:adm2_name":"Okugun'Osafunechou",
    "gn:name":"Nishisue",
    "iso:country":"JP",
    "wof:name":"701-4263",
    "wof:placetype":"postalcode"
},
  "geometry": {"coordinates":[134.13120000000001,34.6774],"type":"Point"}
}