{
  "type": "Feature",
  "properties": {
    "gn:adm1_name":"Ehimeken",
    "gn:adm2_name":"Imabarishi",
    "gn:name":"Chikamichou",
    "iso:country":"JP",
    "wof:name":"794-0007",
    "wof:placetype":"postalcode"
},
  "geometry": {"coordinates":[132.98349999999999,34.0889],"type":"Point"}
}