{
  "type": "Feature",
  "properties": {
    "gn:adm1_name":"Hyougoken",
    "gn:adm2_name":"Hikamigunhikamichou",
    "gn:name":"Oosaki",
    "iso:country":"JP",
    "wof:name":"669-3462",
    "wof:placetype":"postalcode"
},
  "geometry": {"coordinates":[135.0616,35.1602],"type":"Point"}
}