{
  "type": "Feature",
  "properties": {
    "gn:adm1_name":"Toukyouto",
    "gn:adm2_name":"Shinjukuku",
    "gn:name":"Ichigayafunagawaramachi",
    "iso:country":"JP",
    "wof:name":"162-0826",
    "wof:placetype":"postalcode"
},
  "geometry": {"coordinates":[139.73990000000001,35.6978],"type":"Point"}
}