{
  "type": "Feature",
  "properties": {
    "gn:adm1_name":"Mieken",
    "gn:adm2_name":"Inabeshi",
    "gn:name":"Fujiwarachouoogaito",
    "iso:country":"JP",
    "wof:name":"511-0517",
    "wof:placetype":"postalcode"
},
  "geometry": {"coordinates":[136.4795,35.1707],"type":"Point"}
}