{
  "type": "Feature",
  "properties": {
    "gn:adm1_name":"Saitamaken",
    "gn:adm2_name":"Wakoushi",
    "gn:name":"Minami",
    "iso:country":"JP",
    "wof:name":"351-0104",
    "wof:placetype":"postalcode"
},
  "geometry": {"coordinates":[139.61080000000001,35.7719],"type":"Point"}
}