{
  "type": "Feature",
  "properties": {
    "gn:adm1_name":"Okinawaken",
    "gn:adm2_name":"Nagoshi",
    "gn:name":"Oonaka",
    "iso:country":"JP",
    "wof:name":"905-0017",
    "wof:placetype":"postalcode"
},
  "geometry": {"coordinates":[127.9867,26.5938],"type":"Point"}
}