{
  "type": "Feature",
  "properties": {
    "gn:adm1_name":"Shizuokaken",
    "gn:adm2_name":"Shizuokashi",
    "gn:name":"Maruyamachou",
    "iso:country":"JP",
    "wof:name":"420-0861",
    "wof:placetype":"postalcode"
},
  "geometry": {"coordinates":[138.3768,34.9857],"type":"Point"}
}