{
  "type": "Feature",
  "properties": {
    "gn:adm1_name":"Saitamaken",
    "gn:adm2_name":"Kasukabeshi",
    "gn:name":"Akanuma",
    "iso:country":"JP",
    "wof:name":"344-0015",
    "wof:placetype":"postalcode"
},
  "geometry": {"coordinates":[139.80009999999999,35.9517],"type":"Point"}
}