{
  "type": "Feature",
  "properties": {
    "gn:adm1_name":"Naraken",
    "gn:adm2_name":"Yoshinogunshimoichichou",
    "gn:name":"Haradani",
    "iso:country":"JP",
    "wof:name":"638-0032",
    "wof:placetype":"postalcode"
},
  "geometry": {"coordinates":[135.80000000000001,34.3444],"type":"Point"}
}