{
  "type": "Feature",
  "properties": {
    "gn:adm1_name":"Fukuokaken",
    "gn:adm2_name":"Kitakyuushuushimojiku",
    "gn:name":"Shiranoe",
    "iso:country":"JP",
    "wof:name":"801-0802",
    "wof:placetype":"postalcode"
},
  "geometry": {"coordinates":[131.00819999999999,33.9415],"type":"Point"}
}