{
  "type": "Feature",
  "properties": {
    "gn:adm1_name":"Ibarakiken",
    "gn:adm2_name":"Namegatagun'Asoumachi",
    "gn:name":"Amagake",
    "iso:country":"JP",
    "wof:name":"311-3814",
    "wof:placetype":"postalcode"
},
  "geometry": {"coordinates":[140.548,36.0483],"type":"Point"}
}