{
  "type": "Feature",
  "properties": {
    "gn:adm1_name":"Chibaken",
    "gn:adm2_name":"Touganeshi",
    "gn:name":"Taki",
    "iso:country":"JP",
    "wof:name":"283-0825",
    "wof:placetype":"postalcode"
},
  "geometry": {"coordinates":[140.3236,35.5824],"type":"Point"}
}