{
  "type": "Feature",
  "properties": {
    "gn:adm1_name":"Niigataken",
    "gn:adm2_name":"Nakauonumagunkawanishimachi",
    "gn:name":"Aramachishinden",
    "iso:country":"JP",
    "wof:name":"948-0121",
    "wof:placetype":"postalcode"
},
  "geometry": {"coordinates":[138.7482,37.1922],"type":"Point"}
}