{
  "type": "Feature",
  "properties": {
    "gn:adm1_name":"Mieken",
    "gn:adm2_name":"Nabarishi",
    "gn:name":"Umegaokakita5banchou",
    "iso:country":"JP",
    "wof:name":"518-0740",
    "wof:placetype":"postalcode"
},
  "geometry": {"coordinates":[136.08699999999999,34.6409],"type":"Point"}
}