{
  "type": "Feature",
  "properties": {
    "gn:adm1_name":"Kagoshimaken",
    "gn:adm2_name":"Satsumagunsatsumachou",
    "gn:name":"Gumyou",
    "iso:country":"JP",
    "wof:name":"895-2201",
    "wof:placetype":"postalcode"
},
  "geometry": {"coordinates":[130.53790000000001,31.9423],"type":"Point"}
}