{
  "type": "Feature",
  "properties": {
    "gn:adm1_name":"Tochigiken",
    "gn:adm2_name":"Ootawarashi",
    "gn:name":"Motomachi",
    "iso:country":"JP",
    "wof:name":"324-0053",
    "wof:placetype":"postalcode"
},
  "geometry": {"coordinates":[140.03280000000001,36.8615],"type":"Point"}
}