{
  "type": "Feature",
  "properties": {
    "gn:adm1_name":"Sagaken",
    "gn:adm2_name":"Sagashi",
    "gn:name":"Kitakawasoemachishingou",
    "iso:country":"JP",
    "wof:name":"840-0013",
    "wof:placetype":"postalcode"
},
  "geometry": {"coordinates":[130.31450000000001,33.2339],"type":"Point"}
}