{
  "type": "Feature",
  "properties": {
    "gn:adm1_name":"Yamagataken",
    "gn:adm2_name":"Higashitagawagunhaguromachi",
    "gn:name":"Uwanoshinden",
    "iso:country":"JP",
    "wof:name":"997-0142",
    "wof:placetype":"postalcode"
},
  "geometry": {"coordinates":[139.90770000000001,38.6789],"type":"Point"}
}