{
  "type": "Feature",
  "properties": {
    "gn:adm1_name":"Niigataken",
    "gn:adm2_name":"Ryoutsushi",
    "gn:name":"Mitate",
    "iso:country":"JP",
    "wof:name":"952-3206",
    "wof:placetype":"postalcode"
},
  "geometry": {"coordinates":[138.50739999999999,38.2889],"type":"Point"}
}