{
  "type": "Feature",
  "properties": {
    "gn:adm1_name":"Toyamaken",
    "gn:adm2_name":"Neigunyatsuomachi",
    "gn:name":"Higashinunotani",
    "iso:country":"JP",
    "wof:name":"939-2412",
    "wof:placetype":"postalcode"
},
  "geometry": {"coordinates":[137.119,36.5235],"type":"Point"}
}