{
  "type": "Feature",
  "properties": {
    "gn:adm1_name":"Niigataken",
    "gn:adm2_name":"Tookamachishi",
    "gn:name":"Kitaabuzaka",
    "iso:country":"JP",
    "wof:name":"948-0105",
    "wof:placetype":"postalcode"
},
  "geometry": {"coordinates":[138.7216,37.1323],"type":"Point"}
}