{
  "type": "Feature",
  "properties": {
    "gn:adm1_name":"Chibaken",
    "gn:adm2_name":"Sakurashi",
    "gn:name":"Kamidai",
    "iso:country":"JP",
    "wof:name":"285-0044",
    "wof:placetype":"postalcode"
},
  "geometry": {"coordinates":[140.25210000000001,35.7138],"type":"Point"}
}