{
  "type": "Feature",
  "properties": {
    "gn:adm1_name":"Ibarakiken",
    "gn:adm2_name":"Tsukubashi",
    "gn:name":"Sakae",
    "iso:country":"JP",
    "wof:name":"305-0013",
    "wof:placetype":"postalcode"
},
  "geometry": {"coordinates":[140.142,36.1068],"type":"Point"}
}