{
  "type": "Feature",
  "properties": {
    "gn:adm1_name":"Kanagawaken",
    "gn:adm2_name":"Yokohamashikanazawaku",
    "gn:name":"Horiguchi",
    "iso:country":"JP",
    "wof:name":"236-0054",
    "wof:placetype":"postalcode"
},
  "geometry": {"coordinates":[139.63040000000001,35.3591],"type":"Point"}
}