{
  "type": "Feature",
  "properties": {
    "gn:adm1_name":"Miyagiken",
    "gn:adm2_name":"Kattagunshichikashukumachi",
    "gn:name":"Sakanoue",
    "iso:country":"JP",
    "wof:name":"989-0661",
    "wof:placetype":"postalcode"
},
  "geometry": {"coordinates":[140.31479999999999,38.0171],"type":"Point"}
}