{
  "type": "Feature",
  "properties": {
    "gn:adm1_name":"Kyoutofu",
    "gn:adm2_name":"Kyoutoshiukyouku",
    "gn:name":"Uzumasayasuimitodenchou",
    "iso:country":"JP",
    "wof:name":"616-8073",
    "wof:placetype":"postalcode"
},
  "geometry": {"coordinates":[135.7234,35.0126],"type":"Point"}
}