{
  "type": "Feature",
  "properties": {
    "gn:adm1_name":"Sagaken",
    "gn:adm2_name":"Karatsushi",
    "gn:name":"Kouda",
    "iso:country":"JP",
    "wof:name":"847-0824",
    "wof:placetype":"postalcode"
},
  "geometry": {"coordinates":[129.9562,33.4387],"type":"Point"}
}