{
  "type": "Feature",
  "properties": {
    "gn:adm1_name":"Gunmaken",
    "gn:adm2_name":"Takasakishi",
    "gn:name":"Machiyamachi",
    "iso:country":"JP",
    "wof:name":"370-0881",
    "wof:placetype":"postalcode"
},
  "geometry": {"coordinates":[138.9494,36.3533],"type":"Point"}
}