{
  "type": "Feature",
  "properties": {
    "gn:adm1_name":"Fukuiken",
    "gn:adm2_name":"Fukuishi",
    "gn:name":"Arakichou",
    "iso:country":"JP",
    "wof:name":"910-2171",
    "wof:placetype":"postalcode"
},
  "geometry": {"coordinates":[136.2672,36.039],"type":"Point"}
}