{
  "type": "Feature",
  "properties": {
    "gn:adm1_name":"Chibaken",
    "gn:adm2_name":"Katoriguntounoshoumachi",
    "gn:name":"Ooma",
    "iso:country":"JP",
    "wof:name":"289-0615",
    "wof:placetype":"postalcode"
},
  "geometry": {"coordinates":[140.67599999999999,35.8086],"type":"Point"}
}