{
  "type": "Feature",
  "properties": {
    "gn:adm1_name":"Hyougoken",
    "gn:adm2_name":"Koubeshisumaku",
    "gn:name":"Ootechou",
    "iso:country":"JP",
    "wof:name":"654-0013",
    "wof:placetype":"postalcode"
},
  "geometry": {"coordinates":[135.1283,34.6584],"type":"Point"}
}