{
  "type": "Feature",
  "properties": {
    "gn:adm1_name":"Kanagawaken",
    "gn:adm2_name":"Yokohamashinakaku",
    "gn:name":"Tateno",
    "iso:country":"JP",
    "wof:name":"231-0845",
    "wof:placetype":"postalcode"
},
  "geometry": {"coordinates":[139.64789999999999,35.4287],"type":"Point"}
}