{
  "type": "Feature",
  "properties": {
    "gn:adm1_name":"Fukuokaken",
    "gn:adm2_name":"Kitakyuushuushiyahatahigashiku",
    "gn:name":"Nishimaruyamamachi",
    "iso:country":"JP",
    "wof:name":"805-0052",
    "wof:placetype":"postalcode"
},
  "geometry": {"coordinates":[130.80959999999999,33.861],"type":"Point"}
}