{
  "type": "Feature",
  "properties": {
    "gn:adm1_name":"Gifuken",
    "gn:adm2_name":"Gujougunyamatochou",
    "gn:name":"Ochibe",
    "iso:country":"JP",
    "wof:name":"501-4619",
    "wof:placetype":"postalcode"
},
  "geometry": {"coordinates":[136.88509999999999,35.8081],"type":"Point"}
}