{
  "type": "Feature",
  "properties": {
    "gn:adm1_name":"Aichiken",
    "gn:adm2_name":"Higashikamogun'Inabuchou",
    "gn:name":"Noiri",
    "iso:country":"JP",
    "wof:name":"441-2512",
    "wof:placetype":"postalcode"
},
  "geometry": {"coordinates":[137.54089999999999,35.2284],"type":"Point"}
}