{
  "type": "Feature",
  "properties": {
    "gn:adm1_name":"Ishikawaken",
    "gn:adm2_name":"Kanazawashi",
    "gn:name":"Jinguuji",
    "iso:country":"JP",
    "wof:name":"920-0806",
    "wof:placetype":"postalcode"
},
  "geometry": {"coordinates":[136.6677,36.5853],"type":"Point"}
}