{
  "type": "Feature",
  "properties": {
    "gn:adm1_name":"Fukushimaken",
    "gn:adm2_name":"Nihonmatsushi",
    "gn:name":"Matsubayashi",
    "iso:country":"JP",
    "wof:name":"964-0947",
    "wof:placetype":"postalcode"
},
  "geometry": {"coordinates":[140.48259999999999,37.5697],"type":"Point"}
}