{
  "type": "Feature",
  "properties": {
    "gn:adm1_name":"Saitamaken",
    "gn:adm2_name":"Gyoudashi",
    "gn:name":"Saijou",
    "iso:country":"JP",
    "wof:name":"361-0005",
    "wof:placetype":"postalcode"
},
  "geometry": {"coordinates":[139.46090000000001,36.1696],"type":"Point"}
}