{
  "type": "Feature",
  "properties": {
    "gn:adm1_name":"Aichiken",
    "gn:adm2_name":"Inuyamashi",
    "gn:name":"Shimoenokijima",
    "iso:country":"JP",
    "wof:name":"484-0965",
    "wof:placetype":"postalcode"
},
  "geometry": {"coordinates":[136.94139999999999,35.3271],"type":"Point"}
}