{
  "type": "Feature",
  "properties": {
    "gn:adm1_name":"Nagasakiken",
    "gn:adm2_name":"Fukueshi",
    "gn:name":"Nagatechou",
    "iso:country":"JP",
    "wof:name":"853-0012",
    "wof:placetype":"postalcode"
},
  "geometry": {"coordinates":[128.87370000000001,32.6751],"type":"Point"}
}