{
  "type": "Feature",
  "properties": {
    "gn:adm1_name":"Mieken",
    "gn:adm2_name":"Kumanoshi",
    "gn:name":"Asukachousawatari",
    "iso:country":"JP",
    "wof:name":"519-4564",
    "wof:placetype":"postalcode"
},
  "geometry": {"coordinates":[136.0814,33.9411],"type":"Point"}
}