{
  "type": "Feature",
  "properties": {
    "gn:adm1_name":"Kouchiken",
    "gn:adm2_name":"Nakamurashi",
    "gn:name":"Warabiokaotsu",
    "iso:country":"JP",
    "wof:name":"787-1443",
    "wof:placetype":"postalcode"
},
  "geometry": {"coordinates":[132.93440000000001,33.0572],"type":"Point"}
}