{
  "type": "Feature",
  "properties": {
    "gn:adm1_name":"Fukuokaken",
    "gn:adm2_name":"Oomutashi",
    "gn:name":"Higashimiyauramachi",
    "iso:country":"JP",
    "wof:name":"836-0827",
    "wof:placetype":"postalcode"
},
  "geometry": {"coordinates":[130.4554,33.0372],"type":"Point"}
}