{
  "type": "Feature",
  "properties": {
    "gn:adm1_name":"Niigataken",
    "gn:adm2_name":"Minamikanbaragunnakanoshimamachi",
    "gn:name":"Suginomori",
    "iso:country":"JP",
    "wof:name":"954-0151",
    "wof:placetype":"postalcode"
},
  "geometry": {"coordinates":[138.8674,37.541],"type":"Point"}
}