{
  "type": "Feature",
  "properties": {
    "gn:adm1_name":"Mieken",
    "gn:adm2_name":"Inabeshi",
    "gn:name":"Hokuseichouhigashikaino",
    "iso:country":"JP",
    "wof:name":"511-0415",
    "wof:placetype":"postalcode"
},
  "geometry": {"coordinates":[136.5368,35.1735],"type":"Point"}
}