{
  "type": "Feature",
  "properties": {
    "gn:adm1_name":"Ibarakiken",
    "gn:adm2_name":"Yuukishi",
    "gn:name":"Takei",
    "iso:country":"JP",
    "wof:name":"307-0043",
    "wof:placetype":"postalcode"
},
  "geometry": {"coordinates":[139.83170000000001,36.2459],"type":"Point"}
}