{
  "type": "Feature",
  "properties": {
    "gn:adm1_name":"Saitamaken",
    "gn:adm2_name":"Gyoudashi",
    "gn:name":"Fujimichou",
    "iso:country":"JP",
    "wof:name":"361-0021",
    "wof:placetype":"postalcode"
},
  "geometry": {"coordinates":[139.47550000000001,36.1487],"type":"Point"}
}