{
  "type": "Feature",
  "properties": {
    "gn:adm1_name":"Kouchiken",
    "gn:adm2_name":"Tosagunhongawamura",
    "gn:name":"Nagasawa",
    "iso:country":"JP",
    "wof:name":"781-2601",
    "wof:placetype":"postalcode"
},
  "geometry": {"coordinates":[133.30420000000001,33.7266],"type":"Point"}
}