{
  "type": "Feature",
  "properties": {
    "gn:adm1_name":"Aichiken",
    "gn:adm2_name":"Inazawashi",
    "gn:name":"Jiromarunakamachi",
    "iso:country":"JP",
    "wof:name":"492-8128",
    "wof:placetype":"postalcode"
},
  "geometry": {"coordinates":[136.8083,35.2619],"type":"Point"}
}