{
  "type": "Feature",
  "properties": {
    "gn:adm1_name":"Saitamaken",
    "gn:adm2_name":"Chichibugunnagatoromachi",
    "gn:name":"Ikanikeisaiganaibaai",
    "iso:country":"JP",
    "wof:name":"369-1300",
    "wof:placetype":"postalcode"
},
  "geometry": {"coordinates":[139.11770000000001,36.1139],"type":"Point"}
}