{
  "type": "Feature",
  "properties": {
    "gn:adm1_name":"Chibaken",
    "gn:adm2_name":"Tomisatoshi",
    "gn:name":"Hiyoshidai",
    "iso:country":"JP",
    "wof:name":"286-0201",
    "wof:placetype":"postalcode"
},
  "geometry": {"coordinates":[140.31960000000001,35.7661],"type":"Point"}
}