{
  "type": "Feature",
  "properties": {
    "gn:adm1_name":"Hyougoken",
    "gn:adm2_name":"Ibogun'Ibogawachou",
    "gn:name":"Fukurojiri",
    "iso:country":"JP",
    "wof:name":"671-1661",
    "wof:placetype":"postalcode"
},
  "geometry": {"coordinates":[134.53890000000001,34.8071],"type":"Point"}
}