{
  "type": "Feature",
  "properties": {
    "gn:adm1_name":"Toyamaken",
    "gn:adm2_name":"Takaokashi",
    "gn:name":"Joutou",
    "iso:country":"JP",
    "wof:name":"933-0041",
    "wof:placetype":"postalcode"
},
  "geometry": {"coordinates":[137.0307,36.7456],"type":"Point"}
}