{
  "type": "Feature",
  "properties": {
    "gn:adm1_name":"Toyamaken",
    "gn:adm2_name":"Takaokashi",
    "gn:name":"Nakagawamachi",
    "iso:country":"JP",
    "wof:name":"933-0031",
    "wof:placetype":"postalcode"
},
  "geometry": {"coordinates":[137.0214,36.7443],"type":"Point"}
}