{
  "type": "Feature",
  "properties": {
    "gn:adm1_name":"Hiroshimaken",
    "gn:adm2_name":"Miyoshishi",
    "gn:name":"Tookaichiminami",
    "iso:country":"JP",
    "wof:name":"728-0014",
    "wof:placetype":"postalcode"
},
  "geometry": {"coordinates":[132.857,34.8004],"type":"Point"}
}