{
  "type": "Feature",
  "properties": {
    "gn:adm1_name":"Shizuokaken",
    "gn:adm2_name":"Hamamatsushi",
    "gn:name":"Uriuchichou",
    "iso:country":"JP",
    "wof:name":"430-0854",
    "wof:placetype":"postalcode"
},
  "geometry": {"coordinates":[137.7347,34.6883],"type":"Point"}
}