{
  "type": "Feature",
  "properties": {
    "gn:adm1_name":"Kumamotoken",
    "gn:adm2_name":"Hitoyoshishi",
    "gn:name":"Akaikemizunashimachi",
    "iso:country":"JP",
    "wof:name":"868-0824",
    "wof:placetype":"postalcode"
},
  "geometry": {"coordinates":[130.77959999999999,32.1865],"type":"Point"}
}