{
  "type": "Feature",
  "properties": {
    "gn:adm1_name":"Ibarakiken",
    "gn:adm2_name":"Niiharigunyasatomachi",
    "gn:name":"Negoya",
    "iso:country":"JP",
    "wof:name":"315-0132",
    "wof:placetype":"postalcode"
},
  "geometry": {"coordinates":[140.2199,36.2166],"type":"Point"}
}