{
  "type": "Feature",
  "properties": {
    "gn:adm1_name":"Hyougoken",
    "gn:adm2_name":"Shisougunhagachou",
    "gn:name":"Onzui",
    "iso:country":"JP",
    "wof:name":"671-4211",
    "wof:placetype":"postalcode"
},
  "geometry": {"coordinates":[134.52420000000001,35.2293],"type":"Point"}
}