{
  "type": "Feature",
  "properties": {
    "gn:adm1_name":"Shizuokaken",
    "gn:adm2_name":"Suntougunnagaizumichou",
    "gn:name":"Kaminagakubo",
    "iso:country":"JP",
    "wof:name":"411-0935",
    "wof:placetype":"postalcode"
},
  "geometry": {"coordinates":[138.87700000000001,35.1511],"type":"Point"}
}