{
  "type": "Feature",
  "properties": {
    "gn:adm1_name":"Gunmaken",
    "gn:adm2_name":"Usuigunmatsuidamachi",
    "gn:name":"Yashiro",
    "iso:country":"JP",
    "wof:name":"379-0225",
    "wof:placetype":"postalcode"
},
  "geometry": {"coordinates":[138.79830000000001,36.3066],"type":"Point"}
}