{
  "type": "Feature",
  "properties": {
    "gn:adm1_name":"Fukuiken",
    "gn:adm2_name":"Ooiguntakahamachou",
    "gn:name":"Takano",
    "iso:country":"JP",
    "wof:name":"919-2374",
    "wof:placetype":"postalcode"
},
  "geometry": {"coordinates":[135.4872,35.4925],"type":"Point"}
}