{
  "type": "Feature",
  "properties": {
    "gn:adm1_name":"Okayamaken",
    "gn:adm2_name":"Akaiwagunsetochou",
    "gn:name":"Koumyoutani",
    "iso:country":"JP",
    "wof:name":"709-0876",
    "wof:placetype":"postalcode"
},
  "geometry": {"coordinates":[134.04320000000001,34.739],"type":"Point"}
}