{
  "type": "Feature",
  "properties": {
    "gn:adm1_name":"Shizuokaken",
    "gn:adm2_name":"Shimodashi",
    "gn:name":"Udogane",
    "iso:country":"JP",
    "wof:name":"413-0715",
    "wof:placetype":"postalcode"
},
  "geometry": {"coordinates":[138.92660000000001,34.7306],"type":"Point"}
}