{
  "type": "Feature",
  "properties": {
    "gn:adm1_name":"Aichiken",
    "gn:adm2_name":"Kounanshi",
    "gn:name":"Takayachounishisato",
    "iso:country":"JP",
    "wof:name":"483-8085",
    "wof:placetype":"postalcode"
},
  "geometry": {"coordinates":[136.87450000000001,35.3525],"type":"Point"}
}