{
  "type": "Feature",
  "properties": {
    "gn:adm1_name":"Wakayamaken",
    "gn:adm2_name":"Higashimurogunkozachou",
    "gn:name":"Tsuga",
    "iso:country":"JP",
    "wof:name":"649-4113",
    "wof:placetype":"postalcode"
},
  "geometry": {"coordinates":[135.8409,33.5188],"type":"Point"}
}