{
  "type": "Feature",
  "properties": {
    "gn:adm1_name":"Tokushimaken",
    "gn:adm2_name":"Myouzaigun'Ishiichou",
    "gn:name":"Ishii(Ishii)",
    "iso:country":"JP",
    "wof:name":"779-3233",
    "wof:placetype":"postalcode"
},
  "geometry": {"coordinates":[134.44550000000001,34.0666],"type":"Point"}
}