{
  "type": "Feature",
  "properties": {
    "gn:adm1_name":"Kyoutofu",
    "gn:adm2_name":"Kyoutoshisakyouku",
    "gn:name":"Matsugasakishoudenchou",
    "iso:country":"JP",
    "wof:name":"606-0966",
    "wof:placetype":"postalcode"
},
  "geometry": {"coordinates":[135.78299999999999,35.0486],"type":"Point"}
}