{
  "type": "Feature",
  "properties": {
    "gn:adm1_name":"Yamagataken",
    "gn:adm2_name":"Akumigunyuzamachi",
    "gn:name":"Yuzamachi",
    "iso:country":"JP",
    "wof:name":"999-8301",
    "wof:placetype":"postalcode"
},
  "geometry": {"coordinates":[139.9093,39.0164],"type":"Point"}
}