{
  "type": "Feature",
  "properties": {
    "gn:adm1_name":"Aichiken",
    "gn:adm2_name":"Inazawashi",
    "gn:name":"Okudaoosawachou",
    "iso:country":"JP",
    "wof:name":"492-8224",
    "wof:placetype":"postalcode"
},
  "geometry": {"coordinates":[136.81710000000001,35.2347],"type":"Point"}
}