{
  "type": "Feature",
  "properties": {
    "gn:adm1_name":"Naraken",
    "gn:adm2_name":"Narashi",
    "gn:name":"Oobochou",
    "iso:country":"JP",
    "wof:name":"630-1236",
    "wof:placetype":"postalcode"
},
  "geometry": {"coordinates":[135.9512,34.702],"type":"Point"}
}