{
  "type": "Feature",
  "properties": {
    "gn:adm1_name":"Toukyouto",
    "gn:adm2_name":"Machidashi",
    "gn:name":"Ogawa",
    "iso:country":"JP",
    "wof:name":"194-0003",
    "wof:placetype":"postalcode"
},
  "geometry": {"coordinates":[139.47280000000001,35.5263],"type":"Point"}
}