{
  "type": "Feature",
  "properties": {
    "gn:adm1_name":"Saitamaken",
    "gn:adm2_name":"Asakashi",
    "gn:name":"Oka",
    "iso:country":"JP",
    "wof:name":"351-0007",
    "wof:placetype":"postalcode"
},
  "geometry": {"coordinates":[139.60040000000001,35.8089],"type":"Point"}
}