{
  "type": "Feature",
  "properties": {
    "gn:adm1_name":"Saitamaken",
    "gn:adm2_name":"Higashimatsuyamashi",
    "gn:name":"Ishibashi",
    "iso:country":"JP",
    "wof:name":"355-0072",
    "wof:placetype":"postalcode"
},
  "geometry": {"coordinates":[139.37799999999999,36.0318],"type":"Point"}
}