{
  "type": "Feature",
  "properties": {
    "gn:adm1_name":"Nagasakiken",
    "gn:adm2_name":"Higashisonogigunhasamichou",
    "gn:name":"Takebetagou",
    "iso:country":"JP",
    "wof:name":"859-3722",
    "wof:placetype":"postalcode"
},
  "geometry": {"coordinates":[129.875,33.1109],"type":"Point"}
}