{
  "type": "Feature",
  "properties": {
    "gn:adm1_name":"Aichiken",
    "gn:adm2_name":"Ichinomiyashi",
    "gn:name":"Yamatochouujinaga",
    "iso:country":"JP",
    "wof:name":"491-0923",
    "wof:placetype":"postalcode"
},
  "geometry": {"coordinates":[136.80289999999999,35.2755],"type":"Point"}
}