{
  "type": "Feature",
  "properties": {
    "gn:adm1_name":"Ehimeken",
    "gn:adm2_name":"Kitagunnagahamachou",
    "gn:name":"Konboukou",
    "iso:country":"JP",
    "wof:name":"799-3411",
    "wof:placetype":"postalcode"
},
  "geometry": {"coordinates":[132.52250000000001,33.631],"type":"Point"}
}