{
  "type": "Feature",
  "properties": {
    "gn:adm1_name":"Yamaguchiken",
    "gn:adm2_name":"Nagatoshi",
    "gn:name":"Nishifukawa",
    "iso:country":"JP",
    "wof:name":"759-4102",
    "wof:placetype":"postalcode"
},
  "geometry": {"coordinates":[131.16820000000001,34.3636],"type":"Point"}
}