{
  "type": "Feature",
  "properties": {
    "gn:adm1_name":"Chibaken",
    "gn:adm2_name":"Sanbugunhasunumamura",
    "gn:name":"I",
    "iso:country":"JP",
    "wof:name":"289-1801",
    "wof:placetype":"postalcode"
},
  "geometry": {"coordinates":[140.50370000000001,35.6098],"type":"Point"}
}