{
  "type": "Feature",
  "properties": {
    "gn:adm1_name":"Kanagawaken",
    "gn:adm2_name":"Yokohamashikanagawaku",
    "gn:name":"Mitsuzawashimomachi",
    "iso:country":"JP",
    "wof:name":"221-0852",
    "wof:placetype":"postalcode"
},
  "geometry": {"coordinates":[139.61449999999999,35.478],"type":"Point"}
}