{
  "type": "Feature",
  "properties": {
    "gn:adm1_name":"Gifuken",
    "gn:adm2_name":"Oogakishi",
    "gn:name":"Higashimaechou",
    "iso:country":"JP",
    "wof:name":"503-0849",
    "wof:placetype":"postalcode"
},
  "geometry": {"coordinates":[136.63849999999999,35.3467],"type":"Point"}
}