{
  "type": "Feature",
  "properties": {
    "gn:adm1_name":"Naganoken",
    "gn:adm2_name":"Naganoshi",
    "gn:name":"Matsushiroonsen",
    "iso:country":"JP",
    "wof:name":"381-1226",
    "wof:placetype":"postalcode"
},
  "geometry": {"coordinates":[138.21029999999999,36.574],"type":"Point"}
}