{
  "type": "Feature",
  "properties": {
    "gn:adm1_name":"Hyougoken",
    "gn:adm2_name":"Koubeshinishiku",
    "gn:name":"Ikawadanichoubefu",
    "iso:country":"JP",
    "wof:name":"651-2115",
    "wof:placetype":"postalcode"
},
  "geometry": {"coordinates":[135.01179999999999,34.6683],"type":"Point"}
}