{
  "type": "Feature",
  "properties": {
    "gn:adm1_name":"Kyoutofu",
    "gn:adm2_name":"Kyoutoshifushimiku",
    "gn:name":"Fukakusakawaramachi",
    "iso:country":"JP",
    "wof:name":"612-0873",
    "wof:placetype":"postalcode"
},
  "geometry": {"coordinates":[135.77780000000001,34.9574],"type":"Point"}
}