{
  "type": "Feature",
  "properties": {
    "gn:adm1_name":"Niigataken",
    "gn:adm2_name":"Kitakanbaragunnakajoumachi",
    "gn:name":"Ooide",
    "iso:country":"JP",
    "wof:name":"959-2604",
    "wof:placetype":"postalcode"
},
  "geometry": {"coordinates":[139.3922,38.1064],"type":"Point"}
}