{
  "type": "Feature",
  "properties": {
    "gn:adm1_name":"Miyagiken",
    "gn:adm2_name":"Miyagigunshichigahamamachi",
    "gn:name":"Sakaiyama",
    "iso:country":"JP",
    "wof:name":"985-0824",
    "wof:placetype":"postalcode"
},
  "geometry": {"coordinates":[141.04320000000001,38.3006],"type":"Point"}
}