{
  "type": "Feature",
  "properties": {
    "gn:adm1_name":"Aichiken",
    "gn:adm2_name":"Toyohashishi",
    "gn:name":"Wakamatsuchou",
    "iso:country":"JP",
    "wof:name":"441-8123",
    "wof:placetype":"postalcode"
},
  "geometry": {"coordinates":[137.3939,34.6902],"type":"Point"}
}