{
  "type": "Feature",
  "properties": {
    "gn:adm1_name":"Kouchiken",
    "gn:adm2_name":"Kouchishi",
    "gn:name":"Izumichou",
    "iso:country":"JP",
    "wof:name":"780-0064",
    "wof:placetype":"postalcode"
},
  "geometry": {"coordinates":[133.54150000000001,33.5714],"type":"Point"}
}