{
  "type": "Feature",
  "properties": {
    "gn:adm1_name":"Okinawaken",
    "gn:adm2_name":"Shimajirigun'Iheyason",
    "gn:name":"Noho",
    "iso:country":"JP",
    "wof:name":"905-0705",
    "wof:placetype":"postalcode"
},
  "geometry": {"coordinates":[127.925,26.9964],"type":"Point"}
}