{
  "type": "Feature",
  "properties": {
    "gn:adm1_name":"Saitamaken",
    "gn:adm2_name":"Hikigunkawajimamachi",
    "gn:name":"Shoujiki",
    "iso:country":"JP",
    "wof:name":"350-0162",
    "wof:placetype":"postalcode"
},
  "geometry": {"coordinates":[139.44370000000001,36.0023],"type":"Point"}
}