{
  "type": "Feature",
  "properties": {
    "gn:adm1_name":"Naraken",
    "gn:adm2_name":"Narashi",
    "gn:name":"Nakanokawachou(106-306,405-3)",
    "iso:country":"JP",
    "wof:name":"630-1124",
    "wof:placetype":"postalcode"
},
  "geometry": {"coordinates":[135.86779999999999,34.7071],"type":"Point"}
}