{
  "type": "Feature",
  "properties": {
    "gn:adm1_name":"Kagawaken",
    "gn:adm2_name":"Mitoyogunniochou",
    "gn:name":"Nioshin",
    "iso:country":"JP",
    "wof:name":"769-1406",
    "wof:placetype":"postalcode"
},
  "geometry": {"coordinates":[133.6439,34.1975],"type":"Point"}
}