{
  "type": "Feature",
  "properties": {
    "gn:adm1_name":"Kyoutofu",
    "gn:adm2_name":"Kyoutoshiukyouku",
    "gn:name":"Umegahatashimizuchou",
    "iso:country":"JP",
    "wof:name":"616-8276",
    "wof:placetype":"postalcode"
},
  "geometry": {"coordinates":[135.68620000000001,35.0423],"type":"Point"}
}