{
  "type": "Feature",
  "properties": {
    "gn:adm1_name":"Ehimeken",
    "gn:adm2_name":"Imabarishi",
    "gn:name":"Karakodaihigashi",
    "iso:country":"JP",
    "wof:name":"799-1531",
    "wof:placetype":"postalcode"
},
  "geometry": {"coordinates":[133.029,34.031],"type":"Point"}
}