{
  "type": "Feature",
  "properties": {
    "gn:adm1_name":"Ehimeken",
    "gn:adm2_name":"Touyoshi",
    "gn:name":"Nyuugawa",
    "iso:country":"JP",
    "wof:name":"799-1341",
    "wof:placetype":"postalcode"
},
  "geometry": {"coordinates":[133.08330000000001,33.9373],"type":"Point"}
}