{
  "type": "Feature",
  "properties": {
    "gn:adm1_name":"Aichiken",
    "gn:adm2_name":"Taharashi",
    "gn:name":"Yoshigochou",
    "iso:country":"JP",
    "wof:name":"441-3402",
    "wof:placetype":"postalcode"
},
  "geometry": {"coordinates":[137.2799,34.684],"type":"Point"}
}