{
  "type": "Feature",
  "properties": {
    "gn:adm1_name":"Kanagawaken",
    "gn:adm2_name":"Yokohamashimidoriku",
    "gn:name":"Niiharuchou",
    "iso:country":"JP",
    "wof:name":"226-0017",
    "wof:placetype":"postalcode"
},
  "geometry": {"coordinates":[139.52340000000001,35.5201],"type":"Point"}
}