{
  "type": "Feature",
  "properties": {
    "gn:adm1_name":"Kouchiken",
    "gn:adm2_name":"Nankokushi",
    "gn:name":"Maehama",
    "iso:country":"JP",
    "wof:name":"783-0094",
    "wof:placetype":"postalcode"
},
  "geometry": {"coordinates":[133.66300000000001,33.5379],"type":"Point"}
}