{
  "type": "Feature",
  "properties": {
    "gn:adm1_name":"Hiroshimaken",
    "gn:adm2_name":"Hibagunhiwachou",
    "gn:name":"Hiwa",
    "iso:country":"JP",
    "wof:name":"727-0301",
    "wof:placetype":"postalcode"
},
  "geometry": {"coordinates":[132.9888,34.9875],"type":"Point"}
}