{
  "type": "Feature",
  "properties": {
    "gn:adm1_name":"Kyoutofu",
    "gn:adm2_name":"Kyoutoshikamigyouku",
    "gn:name":"Shiratakechou",
    "iso:country":"JP",
    "wof:name":"602-8348",
    "wof:placetype":"postalcode"
},
  "geometry": {"coordinates":[135.74000000000001,35.0238],"type":"Point"}
}