{
  "type": "Feature",
  "properties": {
    "gn:adm1_name":"Ibarakiken",
    "gn:adm2_name":"Tsukubashi",
    "gn:name":"Tennoudai",
    "iso:country":"JP",
    "wof:name":"305-0006",
    "wof:placetype":"postalcode"
},
  "geometry": {"coordinates":[140.10300000000001,36.111],"type":"Point"}
}