{
  "type": "Feature",
  "properties": {
    "gn:adm1_name":"Ooitaken",
    "gn:adm2_name":"Usagun'Ajimumachi",
    "gn:name":"Furuichi",
    "iso:country":"JP",
    "wof:name":"872-0512",
    "wof:placetype":"postalcode"
},
  "geometry": {"coordinates":[131.35329999999999,33.4281],"type":"Point"}
}