{
  "type": "Feature",
  "properties": {
    "gn:adm1_name":"Hyougoken",
    "gn:adm2_name":"Shisougun'Ichinomiyachou",
    "gn:name":"Mikatamachi",
    "iso:country":"JP",
    "wof:name":"671-4113",
    "wof:placetype":"postalcode"
},
  "geometry": {"coordinates":[134.624,35.1828],"type":"Point"}
}