{
  "type": "Feature",
  "properties": {
    "gn:adm1_name":"Gunmaken",
    "gn:adm2_name":"Tonegunniiharumura",
    "gn:name":"Sukawa",
    "iso:country":"JP",
    "wof:name":"379-1418",
    "wof:placetype":"postalcode"
},
  "geometry": {"coordinates":[138.9025,36.7014],"type":"Point"}
}