{
  "type": "Feature",
  "properties": {
    "gn:adm1_name":"Niigataken",
    "gn:adm2_name":"Jouetsushi",
    "gn:name":"Kitashirochou",
    "iso:country":"JP",
    "wof:name":"943-0824",
    "wof:placetype":"postalcode"
},
  "geometry": {"coordinates":[138.2577,37.1172],"type":"Point"}
}