{
  "type": "Feature",
  "properties": {
    "gn:adm1_name":"Shigaken",
    "gn:adm2_name":"Ootsushi",
    "gn:name":"Kitaooji",
    "iso:country":"JP",
    "wof:name":"520-0843",
    "wof:placetype":"postalcode"
},
  "geometry": {"coordinates":[135.89060000000001,34.9735],"type":"Point"}
}