{
  "type": "Feature",
  "properties": {
    "gn:adm1_name":"Fukuokaken",
    "gn:adm2_name":"Kasuyagunshimemachi",
    "gn:name":"Shimechuuou",
    "iso:country":"JP",
    "wof:name":"811-2244",
    "wof:placetype":"postalcode"
},
  "geometry": {"coordinates":[130.48070000000001,33.5892],"type":"Point"}
}