{
  "type": "Feature",
  "properties": {
    "gn:adm1_name":"Tochigiken",
    "gn:adm2_name":"Hagagunninomiyamachi",
    "gn:name":"Oki",
    "iso:country":"JP",
    "wof:name":"321-4505",
    "wof:placetype":"postalcode"
},
  "geometry": {"coordinates":[139.9864,36.3944],"type":"Point"}
}