{
  "type": "Feature",
  "properties": {
    "gn:adm1_name":"Miyagiken",
    "gn:adm2_name":"Shiroishishi",
    "gn:name":"Doubamae",
    "iso:country":"JP",
    "wof:name":"989-0207",
    "wof:placetype":"postalcode"
},
  "geometry": {"coordinates":[140.62799999999999,38.0051],"type":"Point"}
}