{
  "type": "Feature",
  "properties": {
    "gn:adm1_name":"Ishikawaken",
    "gn:adm2_name":"Suzugun'Uchiuramachi",
    "gn:name":"Nunoura",
    "iso:country":"JP",
    "wof:name":"927-0603",
    "wof:placetype":"postalcode"
},
  "geometry": {"coordinates":[137.25579999999999,37.3497],"type":"Point"}
}