{
  "type": "Feature",
  "properties": {
    "gn:adm1_name":"Ehimeken",
    "gn:adm2_name":"Ochigun'Oomishimachou",
    "gn:name":"Oomi",
    "iso:country":"JP",
    "wof:name":"794-1302",
    "wof:placetype":"postalcode"
},
  "geometry": {"coordinates":[132.99420000000001,34.2596],"type":"Point"}
}