{
  "type": "Feature",
  "properties": {
    "gn:adm1_name":"Tochigiken",
    "gn:adm2_name":"Hagagunmashikomachi",
    "gn:name":"Kamiooba",
    "iso:country":"JP",
    "wof:name":"321-4212",
    "wof:placetype":"postalcode"
},
  "geometry": {"coordinates":[140.13200000000001,36.4495],"type":"Point"}
}