{
  "type": "Feature",
  "properties": {
    "gn:adm1_name":"Miyazakiken",
    "gn:adm2_name":"Nichinanshi",
    "gn:name":"Tsukadaotsu",
    "iso:country":"JP",
    "wof:name":"889-3155",
    "wof:placetype":"postalcode"
},
  "geometry": {"coordinates":[131.3252,31.5751],"type":"Point"}
}