{
  "type": "Feature",
  "properties": {
    "gn:adm1_name":"Niigataken",
    "gn:adm2_name":"Jouetsushi",
    "gn:name":"Shimoyotsuya",
    "iso:country":"JP",
    "wof:name":"943-0135",
    "wof:placetype":"postalcode"
},
  "geometry": {"coordinates":[138.30719999999999,37.0781],"type":"Point"}
}