{
  "type": "Feature",
  "properties": {
    "gn:adm1_name":"Gifuken",
    "gn:adm2_name":"Gujougunhachimanchou",
    "gn:name":"Shokuninmachi",
    "iso:country":"JP",
    "wof:name":"501-4212",
    "wof:placetype":"postalcode"
},
  "geometry": {"coordinates":[136.95599999999999,35.7531],"type":"Point"}
}