{
  "type": "Feature",
  "properties": {
    "gn:adm1_name":"Kanagawaken",
    "gn:adm2_name":"Miurashi",
    "gn:name":"Misakimachikoajiro",
    "iso:country":"JP",
    "wof:name":"238-0225",
    "wof:placetype":"postalcode"
},
  "geometry": {"coordinates":[139.62780000000001,35.1596],"type":"Point"}
}