{
  "type": "Feature",
  "properties": {
    "gn:adm1_name":"Hyougoken",
    "gn:adm2_name":"Takasagoshi",
    "gn:name":"Araichoushinhama",
    "iso:country":"JP",
    "wof:name":"676-0008",
    "wof:placetype":"postalcode"
},
  "geometry": {"coordinates":[134.7878,34.7555],"type":"Point"}
}