{
  "type": "Feature",
  "properties": {
    "gn:adm1_name":"Ibarakiken",
    "gn:adm2_name":"Tsukubashi",
    "gn:name":"Karima",
    "iso:country":"JP",
    "wof:name":"305-0822",
    "wof:placetype":"postalcode"
},
  "geometry": {"coordinates":[140.0985,36.0796],"type":"Point"}
}