{
  "type": "Feature",
  "properties": {
    "gn:adm1_name":"Kanagawaken",
    "gn:adm2_name":"Fujisawashi",
    "gn:name":"Tsujidouhigashikaigan",
    "iso:country":"JP",
    "wof:name":"251-0045",
    "wof:placetype":"postalcode"
},
  "geometry": {"coordinates":[139.45740000000001,35.324],"type":"Point"}
}