{
  "type": "Feature",
  "properties": {
    "gn:adm1_name":"Naganoken",
    "gn:adm2_name":"Kamiinagun'Iijimamachi",
    "gn:name":"Tagiri",
    "iso:country":"JP",
    "wof:name":"399-3701",
    "wof:placetype":"postalcode"
},
  "geometry": {"coordinates":[137.93379999999999,35.6949],"type":"Point"}
}