{
  "type": "Feature",
  "properties": {
    "gn:adm1_name":"Naraken",
    "gn:adm2_name":"Gojoushi",
    "gn:name":"Sakaaibeshindenchou",
    "iso:country":"JP",
    "wof:name":"637-0065",
    "wof:placetype":"postalcode"
},
  "geometry": {"coordinates":[135.68620000000001,34.3017],"type":"Point"}
}