{
  "type": "Feature",
  "properties": {
    "gn:adm1_name":"Naganoken",
    "gn:adm2_name":"Naganoshi",
    "gn:name":"Amori",
    "iso:country":"JP",
    "wof:name":"380-0941",
    "wof:placetype":"postalcode"
},
  "geometry": {"coordinates":[138.16800000000001,36.6343],"type":"Point"}
}