{
  "type": "Feature",
  "properties": {
    "gn:adm1_name":"Mieken",
    "gn:adm2_name":"Uenoshi",
    "gn:name":"Araki",
    "iso:country":"JP",
    "wof:name":"518-0818",
    "wof:placetype":"postalcode"
},
  "geometry": {"coordinates":[136.16309999999999,34.7695],"type":"Point"}
}