{
  "type": "Feature",
  "properties": {
    "gn:adm1_name":"Toyamaken",
    "gn:adm2_name":"Namerikawashi",
    "gn:name":"Shikenchou",
    "iso:country":"JP",
    "wof:name":"936-0035",
    "wof:placetype":"postalcode"
},
  "geometry": {"coordinates":[137.34039999999999,36.7662],"type":"Point"}
}