{
  "type": "Feature",
  "properties": {
    "gn:adm1_name":"Chibaken",
    "gn:adm2_name":"Ichiharashi",
    "gn:name":"Azu",
    "iso:country":"JP",
    "wof:name":"290-0253",
    "wof:placetype":"postalcode"
},
  "geometry": {"coordinates":[140.1156,35.4554],"type":"Point"}
}