{
  "type": "Feature",
  "properties": {
    "gn:adm1_name":"Aichiken",
    "gn:adm2_name":"Toukaishi",
    "gn:name":"Nakanoike",
    "iso:country":"JP",
    "wof:name":"477-0033",
    "wof:placetype":"postalcode"
},
  "geometry": {"coordinates":[136.89709999999999,35.0002],"type":"Point"}
}