{
  "type": "Feature",
  "properties": {
    "gn:adm1_name":"Kagawaken",
    "gn:adm2_name":"Marugameshi",
    "gn:name":"Honjimachoutomari",
    "iso:country":"JP",
    "wof:name":"763-0223",
    "wof:placetype":"postalcode"
},
  "geometry": {"coordinates":[133.78049999999999,34.3841],"type":"Point"}
}