{
  "type": "Feature",
  "properties": {
    "gn:adm1_name":"Shigaken",
    "gn:adm2_name":"Koukaguntsuchiyamachou",
    "gn:name":"Senooto",
    "iso:country":"JP",
    "wof:name":"528-0223",
    "wof:placetype":"postalcode"
},
  "geometry": {"coordinates":[136.2826,34.9589],"type":"Point"}
}