{
  "type": "Feature",
  "properties": {
    "gn:adm1_name":"Oosakafu",
    "gn:adm2_name":"Higashioosakashi",
    "gn:name":"Kamikosaka",
    "iso:country":"JP",
    "wof:name":"577-0806",
    "wof:placetype":"postalcode"
},
  "geometry": {"coordinates":[135.58459999999999,34.6546],"type":"Point"}
}