{
  "type": "Feature",
  "properties": {
    "gn:adm1_name":"Naganoken",
    "gn:adm2_name":"Iidashi",
    "gn:name":"Motomachi",
    "iso:country":"JP",
    "wof:name":"395-0052",
    "wof:placetype":"postalcode"
},
  "geometry": {"coordinates":[137.81950000000001,35.5185],"type":"Point"}
}