{
  "type": "Feature",
  "properties": {
    "gn:adm1_name":"Miyazakiken",
    "gn:adm2_name":"Saitoshi",
    "gn:name":"Kiyomizu",
    "iso:country":"JP",
    "wof:name":"881-0004",
    "wof:placetype":"postalcode"
},
  "geometry": {"coordinates":[131.3869,32.0957],"type":"Point"}
}