{
  "type": "Feature",
  "properties": {
    "gn:adm1_name":"Ibarakiken",
    "gn:adm2_name":"Kashimagunhasakimachi",
    "gn:name":"Wakamatsuchuuou",
    "iso:country":"JP",
    "wof:name":"314-0256",
    "wof:placetype":"postalcode"
},
  "geometry": {"coordinates":[140.7373,35.8349],"type":"Point"}
}