{
  "type": "Feature",
  "properties": {
    "gn:adm1_name":"Wakayamaken",
    "gn:adm2_name":"Wakayamashi",
    "gn:name":"Mikimachiminaminochou",
    "iso:country":"JP",
    "wof:name":"640-8105",
    "wof:placetype":"postalcode"
},
  "geometry": {"coordinates":[135.17869999999999,34.2301],"type":"Point"}
}