{
  "type": "Feature",
  "properties": {
    "gn:adm1_name":"Shizuokaken",
    "gn:adm2_name":"Hamamatsushi",
    "gn:name":"Washizawachou",
    "iso:country":"JP",
    "wof:name":"431-2104",
    "wof:placetype":"postalcode"
},
  "geometry": {"coordinates":[137.71360000000001,34.8465],"type":"Point"}
}