{
  "type": "Feature",
  "properties": {
    "gn:adm1_name":"Kyoutofu",
    "gn:adm2_name":"Miyadushi",
    "gn:name":"Kokubun",
    "iso:country":"JP",
    "wof:name":"629-2234",
    "wof:placetype":"postalcode"
},
  "geometry": {"coordinates":[135.17959999999999,35.5781],"type":"Point"}
}