{
  "type": "Feature",
  "properties": {
    "gn:adm1_name":"Gifuken",
    "gn:adm2_name":"Gifushi",
    "gn:name":"Iwatakinishi",
    "iso:country":"JP",
    "wof:name":"501-3152",
    "wof:placetype":"postalcode"
},
  "geometry": {"coordinates":[136.84520000000001,35.431],"type":"Point"}
}