{
  "type": "Feature",
  "properties": {
    "gn:adm1_name":"Kyoutofu",
    "gn:adm2_name":"Kyoutoshihigashiyamaku",
    "gn:name":"Gionmachiminamigawa",
    "iso:country":"JP",
    "wof:name":"605-0074",
    "wof:placetype":"postalcode"
},
  "geometry": {"coordinates":[135.7756,35.0027],"type":"Point"}
}