{
  "type": "Feature",
  "properties": {
    "gn:adm1_name":"Mieken",
    "gn:adm2_name":"Iinangun'Iitakachou",
    "gn:name":"Sougano",
    "iso:country":"JP",
    "wof:name":"515-1727",
    "wof:placetype":"postalcode"
},
  "geometry": {"coordinates":[136.12280000000001,34.4308],"type":"Point"}
}