{
  "type": "Feature",
  "properties": {
    "gn:adm1_name":"Kyoutofu",
    "gn:adm2_name":"Kyoutoshiminamiku",
    "gn:name":"Kuzekamikuzechou",
    "iso:country":"JP",
    "wof:name":"601-8212",
    "wof:placetype":"postalcode"
},
  "geometry": {"coordinates":[135.71530000000001,34.9653],"type":"Point"}
}