{
  "type": "Feature",
  "properties": {
    "gn:adm1_name":"Sagaken",
    "gn:adm2_name":"Karatsushi",
    "gn:name":"Minamifujimichou",
    "iso:country":"JP",
    "wof:name":"847-0876",
    "wof:placetype":"postalcode"
},
  "geometry": {"coordinates":[129.96299999999999,33.4561],"type":"Point"}
}