{
  "type": "Feature",
  "properties": {
    "gn:adm1_name":"Miyagiken",
    "gn:adm2_name":"Motoyoshigun'Utatsuchou",
    "gn:name":"Kudanohama",
    "iso:country":"JP",
    "wof:name":"988-0451",
    "wof:placetype":"postalcode"
},
  "geometry": {"coordinates":[141.52780000000001,38.7169],"type":"Point"}
}