{
  "type": "Feature",
  "properties": {
    "gn:adm1_name":"Nagasakiken",
    "gn:adm2_name":"Kitamatsuuraguntabirachou",
    "gn:name":"Yokoshimamen",
    "iso:country":"JP",
    "wof:name":"859-4827",
    "wof:placetype":"postalcode"
},
  "geometry": {"coordinates":[129.4973,33.316],"type":"Point"}
}