{
  "type": "Feature",
  "properties": {
    "gn:adm1_name":"Naganoken",
    "gn:adm2_name":"Iiyamashi",
    "gn:name":"Ooike",
    "iso:country":"JP",
    "wof:name":"389-2415",
    "wof:placetype":"postalcode"
},
  "geometry": {"coordinates":[138.37139999999999,36.878],"type":"Point"}
}