{
  "type": "Feature",
  "properties": {
    "gn:adm1_name":"Toukyouto",
    "gn:adm2_name":"Machidashi",
    "gn:name":"Shinkoujimachi",
    "iso:country":"JP",
    "wof:name":"195-0051",
    "wof:placetype":"postalcode"
},
  "geometry": {"coordinates":[139.46090000000001,35.602],"type":"Point"}
}