{
  "type": "Feature",
  "properties": {
    "gn:adm1_name":"Shizuokaken",
    "gn:adm2_name":"Tagatagunkannamichou",
    "gn:name":"Hirai",
    "iso:country":"JP",
    "wof:name":"419-0107",
    "wof:placetype":"postalcode"
},
  "geometry": {"coordinates":[138.96629999999999,35.0937],"type":"Point"}
}