{
  "type": "Feature",
  "properties": {
    "gn:adm1_name":"Okinawaken",
    "gn:adm2_name":"Urasoeshi",
    "gn:name":"Uchima",
    "iso:country":"JP",
    "wof:name":"901-2121",
    "wof:placetype":"postalcode"
},
  "geometry": {"coordinates":[127.7034,26.2386],"type":"Point"}
}