{
  "type": "Feature",
  "properties": {
    "gn:adm1_name":"Miyagiken",
    "gn:adm2_name":"Sendaishiwakabayashiku",
    "gn:name":"Minamizaimokuchou",
    "iso:country":"JP",
    "wof:name":"984-0805",
    "wof:placetype":"postalcode"
},
  "geometry": {"coordinates":[140.8888,38.2425],"type":"Point"}
}