{
  "type": "Feature",
  "properties": {
    "gn:adm1_name":"Okinawaken",
    "gn:adm2_name":"Kunigamigun'Ieson",
    "gn:name":"Higashieue",
    "iso:country":"JP",
    "wof:name":"905-0501",
    "wof:placetype":"postalcode"
},
  "geometry": {"coordinates":[127.8073,26.7188],"type":"Point"}
}