{
  "type": "Feature",
  "properties": {
    "gn:adm1_name":"Toyamaken",
    "gn:adm2_name":"Higashitonamigunfukunomachi",
    "gn:name":"Kawayokeshin",
    "iso:country":"JP",
    "wof:name":"939-1504",
    "wof:placetype":"postalcode"
},
  "geometry": {"coordinates":[136.9391,36.6049],"type":"Point"}
}