{
  "type": "Feature",
  "properties": {
    "gn:adm1_name":"Yamagataken",
    "gn:adm2_name":"Sagaeshi",
    "gn:name":"Shima",
    "iso:country":"JP",
    "wof:name":"991-0043",
    "wof:placetype":"postalcode"
},
  "geometry": {"coordinates":[140.27780000000001,38.353],"type":"Point"}
}