{
  "type": "Feature",
  "properties": {
    "gn:adm1_name":"Toyamaken",
    "gn:adm2_name":"Shimoniikawagun'Asahimachi",
    "gn:name":"Tonomachi",
    "iso:country":"JP",
    "wof:name":"938-0161",
    "wof:placetype":"postalcode"
},
  "geometry": {"coordinates":[137.56729999999999,36.9219],"type":"Point"}
}