{
  "type": "Feature",
  "properties": {
    "gn:adm1_name":"Ibarakiken",
    "gn:adm2_name":"Higashiibarakigun'Ibarakimachi",
    "gn:name":"Kamiamagai",
    "iso:country":"JP",
    "wof:name":"311-3145",
    "wof:placetype":"postalcode"
},
  "geometry": {"coordinates":[140.39269999999999,36.242],"type":"Point"}
}