{
  "type": "Feature",
  "properties": {
    "gn:adm1_name":"Toyamaken",
    "gn:adm2_name":"Toyamashi",
    "gn:name":"Tabata",
    "iso:country":"JP",
    "wof:name":"931-8403",
    "wof:placetype":"postalcode"
},
  "geometry": {"coordinates":[137.25749999999999,36.7564],"type":"Point"}
}