{
  "type": "Feature",
  "properties": {
    "gn:adm1_name":"Aichiken",
    "gn:adm2_name":"Nagoyashiminatoku",
    "gn:name":"Minami11banchou",
    "iso:country":"JP",
    "wof:name":"455-0006",
    "wof:placetype":"postalcode"
},
  "geometry": {"coordinates":[136.88,35.1158],"type":"Point"}
}