{
  "type": "Feature",
  "properties": {
    "gn:adm1_name":"Oosakafu",
    "gn:adm2_name":"Neyagawashi",
    "gn:name":"Takamiyasakaemachi",
    "iso:country":"JP",
    "wof:name":"572-0846",
    "wof:placetype":"postalcode"
},
  "geometry": {"coordinates":[135.62880000000001,34.7579],"type":"Point"}
}