{
  "type": "Feature",
  "properties": {
    "gn:adm1_name":"Kyoutofu",
    "gn:adm2_name":"Kyoutoshiyamashinaku",
    "gn:name":"Shinomiyataishougunchou",
    "iso:country":"JP",
    "wof:name":"607-8029",
    "wof:placetype":"postalcode"
},
  "geometry": {"coordinates":[135.82470000000001,34.991],"type":"Point"}
}