{
  "type": "Feature",
  "properties": {
    "gn:adm1_name":"Niigataken",
    "gn:adm2_name":"Higashikubikigunmatsudaimachi",
    "gn:name":"Kiriyama",
    "iso:country":"JP",
    "wof:name":"942-1541",
    "wof:placetype":"postalcode"
},
  "geometry": {"coordinates":[138.6481,37.1743],"type":"Point"}
}