{
  "type": "Feature",
  "properties": {
    "gn:adm1_name":"Ishikawaken",
    "gn:adm2_name":"Mattoushi",
    "gn:name":"Yasutamachi",
    "iso:country":"JP",
    "wof:name":"924-0862",
    "wof:placetype":"postalcode"
},
  "geometry": {"coordinates":[136.56209999999999,36.5228],"type":"Point"}
}