{
  "type": "Feature",
  "properties": {
    "gn:adm1_name":"Kouchiken",
    "gn:adm2_name":"Takaokagun'Ochichou",
    "gn:name":"Yokobatakekita",
    "iso:country":"JP",
    "wof:name":"781-1315",
    "wof:placetype":"postalcode"
},
  "geometry": {"coordinates":[133.21729999999999,33.5732],"type":"Point"}
}