{
  "type": "Feature",
  "properties": {
    "gn:adm1_name":"Wakayamaken",
    "gn:adm2_name":"Higashimurogunhonguuchou",
    "gn:name":"Nodake",
    "iso:country":"JP",
    "wof:name":"647-1724",
    "wof:placetype":"postalcode"
},
  "geometry": {"coordinates":[135.7157,33.7648],"type":"Point"}
}