{
  "type": "Feature",
  "properties": {
    "gn:adm1_name":"Gunmaken",
    "gn:adm2_name":"Maebashishi",
    "gn:name":"Takahanadai",
    "iso:country":"JP",
    "wof:name":"371-0123",
    "wof:placetype":"postalcode"
},
  "geometry": {"coordinates":[139.10669999999999,36.428],"type":"Point"}
}