{
  "type": "Feature",
  "properties": {
    "gn:adm1_name":"Miyagiken",
    "gn:adm2_name":"Ishinomakishi",
    "gn:name":"Izumichou",
    "iso:country":"JP",
    "wof:name":"986-0832",
    "wof:placetype":"postalcode"
},
  "geometry": {"coordinates":[141.2989,38.4281],"type":"Point"}
}