{
  "type": "Feature",
  "properties": {
    "gn:adm1_name":"Toukyouto",
    "gn:adm2_name":"Koganeishi",
    "gn:name":"Sakurachou",
    "iso:country":"JP",
    "wof:name":"184-0005",
    "wof:placetype":"postalcode"
},
  "geometry": {"coordinates":[139.50899999999999,35.7114],"type":"Point"}
}