{
  "type": "Feature",
  "properties": {
    "gn:adm1_name":"Gunmaken",
    "gn:adm2_name":"Fujiokashi",
    "gn:name":"Kanai",
    "iso:country":"JP",
    "wof:name":"375-0045",
    "wof:placetype":"postalcode"
},
  "geometry": {"coordinates":[139.02709999999999,36.2146],"type":"Point"}
}