{
  "type": "Feature",
  "properties": {
    "gn:adm1_name":"Ehimeken",
    "gn:adm2_name":"Onsengunnakajimachou",
    "gn:name":"Ooura",
    "iso:country":"JP",
    "wof:name":"791-4501",
    "wof:placetype":"postalcode"
},
  "geometry": {"coordinates":[132.6283,33.976],"type":"Point"}
}