{
  "type": "Feature",
  "properties": {
    "gn:adm1_name":"Toyamaken",
    "gn:adm2_name":"Nishitonamigunfukumitsumachi",
    "gn:name":"Kurahara",
    "iso:country":"JP",
    "wof:name":"939-1614",
    "wof:placetype":"postalcode"
},
  "geometry": {"coordinates":[136.8287,36.5871],"type":"Point"}
}