{
  "type": "Feature",
  "properties": {
    "gn:adm1_name":"Yamanashiken",
    "gn:adm2_name":"Higashiyatsushirogunmisakachou",
    "gn:name":"Kanegawabara",
    "iso:country":"JP",
    "wof:name":"406-0802",
    "wof:placetype":"postalcode"
},
  "geometry": {"coordinates":[138.6738,35.632],"type":"Point"}
}