{
  "type": "Feature",
  "properties": {
    "gn:adm1_name":"Toukyouto",
    "gn:adm2_name":"Adachiku",
    "gn:name":"Tatsunuma",
    "iso:country":"JP",
    "wof:name":"121-0054",
    "wof:placetype":"postalcode"
},
  "geometry": {"coordinates":[139.8349,35.7883],"type":"Point"}
}