{
  "type": "Feature",
  "properties": {
    "gn:adm1_name":"Saitamaken",
    "gn:adm2_name":"Gyoudashi",
    "gn:name":"Watariyanagi",
    "iso:country":"JP",
    "wof:name":"361-0033",
    "wof:placetype":"postalcode"
},
  "geometry": {"coordinates":[139.4803,36.1168],"type":"Point"}
}