{
  "type": "Feature",
  "properties": {
    "gn:adm1_name":"Kyoutofu",
    "gn:adm2_name":"Yawatashi",
    "gn:name":"Iwatamatsubara",
    "iso:country":"JP",
    "wof:name":"614-8262",
    "wof:placetype":"postalcode"
},
  "geometry": {"coordinates":[135.7467,34.854],"type":"Point"}
}