{
  "type": "Feature",
  "properties": {
    "gn:adm1_name":"Gifuken",
    "gn:adm2_name":"Kakamigaharashi",
    "gn:name":"Soharakichishinchou",
    "iso:country":"JP",
    "wof:name":"504-0844",
    "wof:placetype":"postalcode"
},
  "geometry": {"coordinates":[136.85810000000001,35.4084],"type":"Point"}
}