{
  "type": "Feature",
  "properties": {
    "gn:adm1_name":"Shizuokaken",
    "gn:adm2_name":"Shizuokashi",
    "gn:name":"Togiyachou",
    "iso:country":"JP",
    "wof:name":"420-0029",
    "wof:placetype":"postalcode"
},
  "geometry": {"coordinates":[138.3768,34.9759],"type":"Point"}
}