{
  "type": "Feature",
  "properties": {
    "gn:adm1_name":"Hyougoken",
    "gn:adm2_name":"Yabugunsekinomiyachou",
    "gn:name":"Deai",
    "iso:country":"JP",
    "wof:name":"667-1112",
    "wof:placetype":"postalcode"
},
  "geometry": {"coordinates":[134.5933,35.3623],"type":"Point"}
}