{
  "type": "Feature",
  "properties": {
    "gn:adm1_name":"Oosakafu",
    "gn:adm2_name":"Takatsukishi",
    "gn:name":"Daigakumachi",
    "iso:country":"JP",
    "wof:name":"569-0801",
    "wof:placetype":"postalcode"
},
  "geometry": {"coordinates":[135.62530000000001,34.8519],"type":"Point"}
}