{
  "type": "Feature",
  "properties": {
    "gn:adm1_name":"Yamanashiken",
    "gn:adm2_name":"Nirasakishi",
    "gn:name":"Anayamamachi",
    "iso:country":"JP",
    "wof:name":"407-0263",
    "wof:placetype":"postalcode"
},
  "geometry": {"coordinates":[138.41800000000001,35.7543],"type":"Point"}
}