{
  "type": "Feature",
  "properties": {
    "gn:adm1_name":"Fukuokaken",
    "gn:adm2_name":"Miyakogunkandamachi",
    "gn:name":"Inamitsu",
    "iso:country":"JP",
    "wof:name":"800-0337",
    "wof:placetype":"postalcode"
},
  "geometry": {"coordinates":[130.94,33.7524],"type":"Point"}
}