{
  "type": "Feature",
  "properties": {
    "gn:adm1_name":"Gifuken",
    "gn:adm2_name":"Sekishi",
    "gn:name":"Azakuradai",
    "iso:country":"JP",
    "wof:name":"501-3808",
    "wof:placetype":"postalcode"
},
  "geometry": {"coordinates":[136.9134,35.492],"type":"Point"}
}