{
  "type": "Feature",
  "properties": {
    "gn:adm1_name":"Fukuokaken",
    "gn:adm2_name":"Yukuhashishi",
    "gn:name":"Bunkyuu",
    "iso:country":"JP",
    "wof:name":"824-0012",
    "wof:placetype":"postalcode"
},
  "geometry": {"coordinates":[131.0067,33.7393],"type":"Point"}
}