{
  "type": "Feature",
  "properties": {
    "gn:adm1_name":"Nagasakiken",
    "gn:adm2_name":"Kitamatsuuragunsazachou",
    "gn:name":"Hiranomen",
    "iso:country":"JP",
    "wof:name":"857-0342",
    "wof:placetype":"postalcode"
},
  "geometry": {"coordinates":[129.65940000000001,33.2359],"type":"Point"}
}