{
  "type": "Feature",
  "properties": {
    "gn:adm1_name":"Oosakafu",
    "gn:adm2_name":"Oosakashinishiyodogawaku",
    "gn:name":"Dekishima",
    "iso:country":"JP",
    "wof:name":"555-0031",
    "wof:placetype":"postalcode"
},
  "geometry": {"coordinates":[135.4374,34.7062],"type":"Point"}
}