{
  "type": "Feature",
  "properties": {
    "gn:adm1_name":"Gunmaken",
    "gn:adm2_name":"Maebashishi",
    "gn:name":"Higashizenmachi",
    "iso:country":"JP",
    "wof:name":"379-2132",
    "wof:placetype":"postalcode"
},
  "geometry": {"coordinates":[139.1293,36.3439],"type":"Point"}
}