{
  "type": "Feature",
  "properties": {
    "gn:adm1_name":"Gifuken",
    "gn:adm2_name":"Gifushi",
    "gn:name":"Akanabeoono",
    "iso:country":"JP",
    "wof:name":"500-8261",
    "wof:placetype":"postalcode"
},
  "geometry": {"coordinates":[136.75219999999999,35.3958],"type":"Point"}
}