{
  "type": "Feature",
  "properties": {
    "gn:adm1_name":"Miyagiken",
    "gn:adm2_name":"Monougunmonouchou",
    "gn:name":"Oota",
    "iso:country":"JP",
    "wof:name":"986-0311",
    "wof:placetype":"postalcode"
},
  "geometry": {"coordinates":[141.273,38.5484],"type":"Point"}
}