{
  "type": "Feature",
  "properties": {
    "gn:adm1_name":"Ehimeken",
    "gn:adm2_name":"Kitauwagunyoshidachou",
    "gn:name":"Uotana",
    "iso:country":"JP",
    "wof:name":"799-3704",
    "wof:placetype":"postalcode"
},
  "geometry": {"coordinates":[132.54130000000001,33.2739],"type":"Point"}
}