{
  "type": "Feature",
  "properties": {
    "gn:adm1_name":"Ibarakiken",
    "gn:adm2_name":"Tsukubashi",
    "gn:name":"Yokomachi",
    "iso:country":"JP",
    "wof:name":"305-0017",
    "wof:placetype":"postalcode"
},
  "geometry": {"coordinates":[140.1414,36.1052],"type":"Point"}
}