{
  "type": "Feature",
  "properties": {
    "gn:adm1_name":"Saitamaken",
    "gn:adm2_name":"Todashi",
    "gn:name":"Niizo",
    "iso:country":"JP",
    "wof:name":"335-0021",
    "wof:placetype":"postalcode"
},
  "geometry": {"coordinates":[139.66499999999999,35.8172],"type":"Point"}
}