{
  "type": "Feature",
  "properties": {
    "gn:adm1_name":"Saitamaken",
    "gn:adm2_name":"Chichibugunyoshidamachi",
    "gn:name":"Shimoyoshida",
    "iso:country":"JP",
    "wof:name":"369-1503",
    "wof:placetype":"postalcode"
},
  "geometry": {"coordinates":[139.0299,36.0388],"type":"Point"}
}