{
  "type": "Feature",
  "properties": {
    "gn:adm1_name":"Okayamaken",
    "gn:adm2_name":"Takahashishi",
    "gn:name":"Igamachi",
    "iso:country":"JP",
    "wof:name":"716-0018",
    "wof:placetype":"postalcode"
},
  "geometry": {"coordinates":[133.62180000000001,34.7968],"type":"Point"}
}