{
  "type": "Feature",
  "properties": {
    "gn:adm1_name":"Yamaguchiken",
    "gn:adm2_name":"Yamaguchishi",
    "gn:name":"Dounomaechou",
    "iso:country":"JP",
    "wof:name":"753-0032",
    "wof:placetype":"postalcode"
},
  "geometry": {"coordinates":[131.48140000000001,34.1799],"type":"Point"}
}