{
  "type": "Feature",
  "properties": {
    "gn:adm1_name":"Aichiken",
    "gn:adm2_name":"Kounanshi",
    "gn:name":"Nobakuchouhigashisenmaru",
    "iso:country":"JP",
    "wof:name":"483-8204",
    "wof:placetype":"postalcode"
},
  "geometry": {"coordinates":[136.874,35.3424],"type":"Point"}
}