{
  "type": "Feature",
  "properties": {
    "gn:adm1_name":"Hyougoken",
    "gn:adm2_name":"Itamishi",
    "gn:name":"Minamino",
    "iso:country":"JP",
    "wof:name":"664-0865",
    "wof:placetype":"postalcode"
},
  "geometry": {"coordinates":[135.404,34.7674],"type":"Point"}
}