{
  "type": "Feature",
  "properties": {
    "gn:adm1_name":"Yamanashiken",
    "gn:adm2_name":"Higashiyatsushirogun'Ichinomiyachou",
    "gn:name":"Kaneta",
    "iso:country":"JP",
    "wof:name":"405-0079",
    "wof:placetype":"postalcode"
},
  "geometry": {"coordinates":[138.6808,35.651],"type":"Point"}
}