{
  "type": "Feature",
  "properties": {
    "gn:adm1_name":"Mieken",
    "gn:adm2_name":"Owaseshi",
    "gn:name":"Kitaurachou",
    "iso:country":"JP",
    "wof:name":"519-3606",
    "wof:placetype":"postalcode"
},
  "geometry": {"coordinates":[136.19820000000001,34.0775],"type":"Point"}
}