{
  "type": "Feature",
  "properties": {
    "gn:adm1_name":"Okayamaken",
    "gn:adm2_name":"Tomatagun'Okutsuchou",
    "gn:name":"Izaka",
    "iso:country":"JP",
    "wof:name":"708-0421",
    "wof:placetype":"postalcode"
},
  "geometry": {"coordinates":[133.90870000000001,35.185],"type":"Point"}
}