{
  "type": "Feature",
  "properties": {
    "gn:adm1_name":"Ehimeken",
    "gn:adm2_name":"Niihamashi",
    "gn:name":"Izumiikechou",
    "iso:country":"JP",
    "wof:name":"792-0013",
    "wof:placetype":"postalcode"
},
  "geometry": {"coordinates":[133.27520000000001,33.9658],"type":"Point"}
}