{
  "type": "Feature",
  "properties": {
    "gn:adm1_name":"Hiroshimaken",
    "gn:adm2_name":"Miyoshishi",
    "gn:name":"Kamishiwachimachi",
    "iso:country":"JP",
    "wof:name":"729-6332",
    "wof:placetype":"postalcode"
},
  "geometry": {"coordinates":[132.798,34.7362],"type":"Point"}
}