{
  "type": "Feature",
  "properties": {
    "gn:adm1_name":"Saitamaken",
    "gn:adm2_name":"Saitamashimidoriku",
    "gn:name":"Kaminoda",
    "iso:country":"JP",
    "wof:name":"336-0977",
    "wof:placetype":"postalcode"
},
  "geometry": {"coordinates":[139.69919999999999,35.9078],"type":"Point"}
}