{
  "type": "Feature",
  "properties": {
    "gn:adm1_name":"Naraken",
    "gn:adm2_name":"Yoshinogun'Ooyodochou",
    "gn:name":"Ooiwa",
    "iso:country":"JP",
    "wof:name":"638-0842",
    "wof:placetype":"postalcode"
},
  "geometry": {"coordinates":[135.7646,34.4164],"type":"Point"}
}