{
  "type": "Feature",
  "properties": {
    "gn:adm1_name":"Nagasakiken",
    "gn:adm2_name":"Nagasakishi",
    "gn:name":"Nakagawa",
    "iso:country":"JP",
    "wof:name":"850-0013",
    "wof:placetype":"postalcode"
},
  "geometry": {"coordinates":[129.89279999999999,32.7519],"type":"Point"}
}