{
  "type": "Feature",
  "properties": {
    "gn:adm1_name":"Tochigiken",
    "gn:adm2_name":"Hagagunninomiyamachi",
    "gn:name":"Sorimachi",
    "iso:country":"JP",
    "wof:name":"321-4515",
    "wof:placetype":"postalcode"
},
  "geometry": {"coordinates":[140.01990000000001,36.3837],"type":"Point"}
}