{
  "type": "Feature",
  "properties": {
    "gn:adm1_name":"Ishikawaken",
    "gn:adm2_name":"Ishikawagunmikawamachi",
    "gn:name":"Chouyamachi",
    "iso:country":"JP",
    "wof:name":"929-0214",
    "wof:placetype":"postalcode"
},
  "geometry": {"coordinates":[136.4967,36.4853],"type":"Point"}
}