{
  "type": "Feature",
  "properties": {
    "gn:adm1_name":"Fukuiken",
    "gn:adm2_name":"Katsuyamashi",
    "gn:name":"Kitadanichoukougo",
    "iso:country":"JP",
    "wof:name":"911-0003",
    "wof:placetype":"postalcode"
},
  "geometry": {"coordinates":[136.5616,36.1073],"type":"Point"}
}