{
  "type": "Feature",
  "properties": {
    "gn:adm1_name":"Aichiken",
    "gn:adm2_name":"Higashikamogunshimoyamamura",
    "gn:name":"Hirase",
    "iso:country":"JP",
    "wof:name":"444-3251",
    "wof:placetype":"postalcode"
},
  "geometry": {"coordinates":[137.3416,35.0539],"type":"Point"}
}