{
  "type": "Feature",
  "properties": {
    "gn:adm1_name":"Gifuken",
    "gn:adm2_name":"Ibigun'Ikedachou",
    "gn:name":"Miyaji",
    "iso:country":"JP",
    "wof:name":"503-2406",
    "wof:placetype":"postalcode"
},
  "geometry": {"coordinates":[136.55199999999999,35.4563],"type":"Point"}
}