{
  "type": "Feature",
  "properties": {
    "gn:adm1_name":"Hyougoken",
    "gn:adm2_name":"Sumotoshi",
    "gn:name":"Aigachounakata",
    "iso:country":"JP",
    "wof:name":"656-2122",
    "wof:placetype":"postalcode"
},
  "geometry": {"coordinates":[134.87180000000001,34.3893],"type":"Point"}
}