{
  "type": "Feature",
  "properties": {
    "gn:adm1_name":"Sagaken",
    "gn:adm2_name":"Sagagunmorodomichou",
    "gn:name":"Tameshige",
    "iso:country":"JP",
    "wof:name":"840-2102",
    "wof:placetype":"postalcode"
},
  "geometry": {"coordinates":[130.35230000000001,33.2167],"type":"Point"}
}