{
  "type": "Feature",
  "properties": {
    "gn:adm1_name":"Nagasakiken",
    "gn:adm2_name":"Minamitakakigun'Obamachou",
    "gn:name":"Minamihonmachi",
    "iso:country":"JP",
    "wof:name":"854-0513",
    "wof:placetype":"postalcode"
},
  "geometry": {"coordinates":[130.22370000000001,32.7239],"type":"Point"}
}