{
  "type": "Feature",
  "properties": {
    "gn:adm1_name":"Chibaken",
    "gn:adm2_name":"Kisaradushi",
    "gn:name":"Sone",
    "iso:country":"JP",
    "wof:name":"292-0027",
    "wof:placetype":"postalcode"
},
  "geometry": {"coordinates":[139.96960000000001,35.4125],"type":"Point"}
}