{
  "type": "Feature",
  "properties": {
    "gn:adm1_name":"Yamaguchiken",
    "gn:adm2_name":"Shuunanshi",
    "gn:name":"Hara",
    "iso:country":"JP",
    "wof:name":"745-0621",
    "wof:placetype":"postalcode"
},
  "geometry": {"coordinates":[131.96850000000001,34.0581],"type":"Point"}
}