{
  "type": "Feature",
  "properties": {
    "gn:adm1_name":"Fukushimaken",
    "gn:adm2_name":"Kooriyamashi",
    "gn:name":"Konanmachitate",
    "iso:country":"JP",
    "wof:name":"963-1412",
    "wof:placetype":"postalcode"
},
  "geometry": {"coordinates":[140.1377,37.4145],"type":"Point"}
}