{
  "type": "Feature",
  "properties": {
    "gn:adm1_name":"Nagasakiken",
    "gn:adm2_name":"Shimabarashi",
    "gn:name":"Uwajinchou",
    "iso:country":"JP",
    "wof:name":"855-0067",
    "wof:placetype":"postalcode"
},
  "geometry": {"coordinates":[130.3605,32.7896],"type":"Point"}
}