{
  "type": "Feature",
  "properties": {
    "gn:adm1_name":"Fukuiken",
    "gn:adm2_name":"Fukuishi",
    "gn:name":"Kawashirichou",
    "iso:country":"JP",
    "wof:name":"910-3136",
    "wof:placetype":"postalcode"
},
  "geometry": {"coordinates":[136.0975,36.1456],"type":"Point"}
}