{
  "type": "Feature",
  "properties": {
    "gn:adm1_name":"Miyagiken",
    "gn:adm2_name":"Kesennumashi",
    "gn:name":"Akaiwakamihada",
    "iso:country":"JP",
    "wof:name":"988-0166",
    "wof:placetype":"postalcode"
},
  "geometry": {"coordinates":[141.50319999999999,38.8579],"type":"Point"}
}