{
  "type": "Feature",
  "properties": {
    "gn:adm1_name":"Tottoriken",
    "gn:adm2_name":"Saihakugunnawachou",
    "gn:name":"Kodake",
    "iso:country":"JP",
    "wof:name":"689-3203",
    "wof:placetype":"postalcode"
},
  "geometry": {"coordinates":[133.5274,35.4999],"type":"Point"}
}