{
  "type": "Feature",
  "properties": {
    "gn:adm1_name":"Yamagataken",
    "gn:adm2_name":"Nishimurayamagun'Asahimachi",
    "gn:name":"Tokiwa",
    "iso:country":"JP",
    "wof:name":"990-1552",
    "wof:placetype":"postalcode"
},
  "geometry": {"coordinates":[140.12360000000001,38.2907],"type":"Point"}
}