{
  "type": "Feature",
  "properties": {
    "gn:adm1_name":"Okinawaken",
    "gn:adm2_name":"Shimajirigunkumejimachou",
    "gn:name":"Uezu",
    "iso:country":"JP",
    "wof:name":"901-3138",
    "wof:placetype":"postalcode"
},
  "geometry": {"coordinates":[126.747,26.3569],"type":"Point"}
}