{
  "type": "Feature",
  "properties": {
    "gn:adm1_name":"Ooitaken",
    "gn:adm2_name":"Naoirigun'Ogimachi",
    "gn:name":"Shindou",
    "iso:country":"JP",
    "wof:name":"879-6103",
    "wof:placetype":"postalcode"
},
  "geometry": {"coordinates":[131.29400000000001,32.9387],"type":"Point"}
}