{
  "type": "Feature",
  "properties": {
    "gn:adm1_name":"Yamagataken",
    "gn:adm2_name":"Nishiokitamagun'Ogunimachi",
    "gn:name":"Shirakozawa",
    "iso:country":"JP",
    "wof:name":"999-1202",
    "wof:placetype":"postalcode"
},
  "geometry": {"coordinates":[139.86099999999999,38.0112],"type":"Point"}
}