{
  "type": "Feature",
  "properties": {
    "gn:adm1_name":"Tottoriken",
    "gn:adm2_name":"Touhakuguntougouchou",
    "gn:name":"Nagouta",
    "iso:country":"JP",
    "wof:name":"689-0732",
    "wof:placetype":"postalcode"
},
  "geometry": {"coordinates":[133.88069999999999,35.4623],"type":"Point"}
}