{
  "type": "Feature",
  "properties": {
    "gn:adm1_name":"Miyagiken",
    "gn:adm2_name":"Toodagunkogotachou",
    "gn:name":"Kandou",
    "iso:country":"JP",
    "wof:name":"987-0065",
    "wof:placetype":"postalcode"
},
  "geometry": {"coordinates":[141.0898,38.5301],"type":"Point"}
}