{
  "type": "Feature",
  "properties": {
    "gn:adm1_name":"Toukyouto",
    "gn:adm2_name":"Shinagawaku",
    "gn:name":"Higashiyashio",
    "iso:country":"JP",
    "wof:name":"135-0092",
    "wof:placetype":"postalcode"
},
  "geometry": {"coordinates":[139.77099999999999,35.6212],"type":"Point"}
}