{
  "type": "Feature",
  "properties": {
    "gn:adm1_name":"Tokushimaken",
    "gn:adm2_name":"Miyoshigunmikamochou",
    "gn:name":"Keta(Sonota)",
    "iso:country":"JP",
    "wof:name":"779-4705",
    "wof:placetype":"postalcode"
},
  "geometry": {"coordinates":[133.99039999999999,34.0175],"type":"Point"}
}