{
  "type": "Feature",
  "properties": {
    "gn:adm1_name":"Miyagiken",
    "gn:adm2_name":"Kesennumashi",
    "gn:name":"Kiridooshi",
    "iso:country":"JP",
    "wof:name":"988-0822",
    "wof:placetype":"postalcode"
},
  "geometry": {"coordinates":[141.53980000000001,38.9125],"type":"Point"}
}