{
  "type": "Feature",
  "properties": {
    "gn:adm1_name":"Ehimeken",
    "gn:adm2_name":"Niihamashi",
    "gn:name":"Tanoue",
    "iso:country":"JP",
    "wof:name":"792-0888",
    "wof:placetype":"postalcode"
},
  "geometry": {"coordinates":[133.31639999999999,33.9724],"type":"Point"}
}