{
  "type": "Feature",
  "properties": {
    "gn:adm1_name":"Kyoutofu",
    "gn:adm2_name":"Kyoutoshikitaku",
    "gn:name":"Takagaminefujibayashichou",
    "iso:country":"JP",
    "wof:name":"603-8445",
    "wof:placetype":"postalcode"
},
  "geometry": {"coordinates":[135.7364,35.0491],"type":"Point"}
}