{
  "type": "Feature",
  "properties": {
    "gn:adm1_name":"Tochigiken",
    "gn:adm2_name":"Oyamashi",
    "gn:name":"Shibui",
    "iso:country":"JP",
    "wof:name":"323-0005",
    "wof:placetype":"postalcode"
},
  "geometry": {"coordinates":[139.7928,36.3318],"type":"Point"}
}