{
  "type": "Feature",
  "properties": {
    "gn:adm1_name":"Nagasakiken",
    "gn:adm2_name":"Kamiagatagunminechou",
    "gn:name":"Kasa",
    "iso:country":"JP",
    "wof:name":"817-1307",
    "wof:placetype":"postalcode"
},
  "geometry": {"coordinates":[129.30240000000001,34.4482],"type":"Point"}
}