{
  "type": "Feature",
  "properties": {
    "gn:adm1_name":"Hyougoken",
    "gn:adm2_name":"Himejishi",
    "gn:name":"Katsuharakuyoro",
    "iso:country":"JP",
    "wof:name":"671-1203",
    "wof:placetype":"postalcode"
},
  "geometry": {"coordinates":[134.5993,34.8182],"type":"Point"}
}