{
  "type": "Feature",
  "properties": {
    "gn:adm1_name":"Yamaguchiken",
    "gn:adm2_name":"Kudamatsushi",
    "gn:name":"Hokutochou",
    "iso:country":"JP",
    "wof:name":"744-0012",
    "wof:placetype":"postalcode"
},
  "geometry": {"coordinates":[131.86930000000001,34.01],"type":"Point"}
}