{
  "type": "Feature",
  "properties": {
    "gn:adm1_name":"Tochigiken",
    "gn:adm2_name":"Utsunomiyashi",
    "gn:name":"Wakakusa",
    "iso:country":"JP",
    "wof:name":"320-0072",
    "wof:placetype":"postalcode"
},
  "geometry": {"coordinates":[139.86009999999999,36.5872],"type":"Point"}
}