{
  "type": "Feature",
  "properties": {
    "gn:adm1_name":"Naganoken",
    "gn:adm2_name":"Suwashi",
    "gn:name":"Toyoda",
    "iso:country":"JP",
    "wof:name":"392-0016",
    "wof:placetype":"postalcode"
},
  "geometry": {"coordinates":[138.0924,36.0233],"type":"Point"}
}