{
  "type": "Feature",
  "properties": {
    "gn:adm1_name":"Ooitaken",
    "gn:adm2_name":"Ooitashi",
    "gn:name":"Nihoudanchi",
    "iso:country":"JP",
    "wof:name":"870-1167",
    "wof:placetype":"postalcode"
},
  "geometry": {"coordinates":[131.57579999999999,33.1941],"type":"Point"}
}