{
  "type": "Feature",
  "properties": {
    "gn:adm1_name":"Ehimeken",
    "gn:adm2_name":"Kitagunnagahamachou",
    "gn:name":"Hodumiotsu",
    "iso:country":"JP",
    "wof:name":"799-3443",
    "wof:placetype":"postalcode"
},
  "geometry": {"coordinates":[132.47710000000001,33.5761],"type":"Point"}
}