{
  "type": "Feature",
  "properties": {
    "gn:adm1_name":"Gifuken",
    "gn:adm2_name":"Kamoguntomikachou",
    "gn:name":"Ooyama",
    "iso:country":"JP",
    "wof:name":"501-3306",
    "wof:placetype":"postalcode"
},
  "geometry": {"coordinates":[136.96960000000001,35.4956],"type":"Point"}
}