{
  "type": "Feature",
  "properties": {
    "gn:adm1_name":"Hyougoken",
    "gn:adm2_name":"Koubeshinagataku",
    "gn:name":"Ootanichou",
    "iso:country":"JP",
    "wof:name":"653-0838",
    "wof:placetype":"postalcode"
},
  "geometry": {"coordinates":[135.13990000000001,34.6653],"type":"Point"}
}