{
  "type": "Feature",
  "properties": {
    "gn:adm1_name":"Fukuokaken",
    "gn:adm2_name":"Kurumeshi",
    "gn:name":"Yamamotomachitoyota",
    "iso:country":"JP",
    "wof:name":"839-0827",
    "wof:placetype":"postalcode"
},
  "geometry": {"coordinates":[130.58690000000001,33.3107],"type":"Point"}
}