{
  "type": "Feature",
  "properties": {
    "gn:adm1_name":"Ishikawaken",
    "gn:adm2_name":"Komatsushi",
    "gn:name":"Nishiaratanimachi",
    "iso:country":"JP",
    "wof:name":"923-0323",
    "wof:placetype":"postalcode"
},
  "geometry": {"coordinates":[136.45760000000001,36.3211],"type":"Point"}
}