{
  "type": "Feature",
  "properties": {
    "gn:adm1_name":"Fukushimaken",
    "gn:adm2_name":"Fukushimashi",
    "gn:name":"Sugitsumachou",
    "iso:country":"JP",
    "wof:name":"960-8065",
    "wof:placetype":"postalcode"
},
  "geometry": {"coordinates":[140.46799999999999,37.7506],"type":"Point"}
}