{
  "type": "Feature",
  "properties": {
    "gn:adm1_name":"Gifuken",
    "gn:adm2_name":"Gujougunyamatochou",
    "gn:name":"Manba",
    "iso:country":"JP",
    "wof:name":"501-4611",
    "wof:placetype":"postalcode"
},
  "geometry": {"coordinates":[136.87970000000001,35.8383],"type":"Point"}
}