{
  "type": "Feature",
  "properties": {
    "gn:adm1_name":"Kyoutofu",
    "gn:adm2_name":"Kyoutoshifushimiku",
    "gn:name":"Daigouenoyamachou",
    "iso:country":"JP",
    "wof:name":"601-1371",
    "wof:placetype":"postalcode"
},
  "geometry": {"coordinates":[135.81469999999999,34.9573],"type":"Point"}
}