{
  "type": "Feature",
  "properties": {
    "gn:adm1_name":"Saitamaken",
    "gn:adm2_name":"Kasukabeshi",
    "gn:name":"Yutakachou",
    "iso:country":"JP",
    "wof:name":"344-0066",
    "wof:placetype":"postalcode"
},
  "geometry": {"coordinates":[139.73920000000001,35.9687],"type":"Point"}
}