{
  "type": "Feature",
  "properties": {
    "gn:adm1_name":"Ehimeken",
    "gn:adm2_name":"Niihamashi",
    "gn:name":"Kitauchichou",
    "iso:country":"JP",
    "wof:name":"792-0842",
    "wof:placetype":"postalcode"
},
  "geometry": {"coordinates":[133.30850000000001,33.9309],"type":"Point"}
}