{
  "type": "Feature",
  "properties": {
    "gn:adm1_name":"Ooitaken",
    "gn:adm2_name":"Saikishi",
    "gn:name":"Katagamiura",
    "iso:country":"JP",
    "wof:name":"876-0008",
    "wof:placetype":"postalcode"
},
  "geometry": {"coordinates":[131.9272,33.0002],"type":"Point"}
}