{
  "type": "Feature",
  "properties": {
    "gn:adm1_name":"Gifuken",
    "gn:adm2_name":"Gifushi",
    "gn:name":"Kisaragichou",
    "iso:country":"JP",
    "wof:name":"500-8327",
    "wof:placetype":"postalcode"
},
  "geometry": {"coordinates":[136.7406,35.4131],"type":"Point"}
}