{
  "type": "Feature",
  "properties": {
    "gn:adm1_name":"Niigataken",
    "gn:adm2_name":"Nishikanbaraguntsukigatamura",
    "gn:name":"Shimomagari",
    "iso:country":"JP",
    "wof:name":"950-1301",
    "wof:placetype":"postalcode"
},
  "geometry": {"coordinates":[139.00800000000001,37.7482],"type":"Point"}
}