{
  "type": "Feature",
  "properties": {
    "gn:adm1_name":"Tochigiken",
    "gn:adm2_name":"Nasugunkarasuyamamachi",
    "gn:name":"Taki",
    "iso:country":"JP",
    "wof:name":"321-0633",
    "wof:placetype":"postalcode"
},
  "geometry": {"coordinates":[140.13820000000001,36.6451],"type":"Point"}
}