{
  "type": "Feature",
  "properties": {
    "gn:adm1_name":"Hyougoken",
    "gn:adm2_name":"Himejishi",
    "gn:name":"Shikamakuhigashibori",
    "iso:country":"JP",
    "wof:name":"672-8054",
    "wof:placetype":"postalcode"
},
  "geometry": {"coordinates":[134.67269999999999,34.7961],"type":"Point"}
}