{
  "type": "Feature",
  "properties": {
    "gn:adm1_name":"Ehimeken",
    "gn:adm2_name":"Nishiuwagun'Ikatachou",
    "gn:name":"Minatoura",
    "iso:country":"JP",
    "wof:name":"796-0301",
    "wof:placetype":"postalcode"
},
  "geometry": {"coordinates":[132.35509999999999,33.4898],"type":"Point"}
}