{
  "type": "Feature",
  "properties": {
    "gn:adm1_name":"Fukuokaken",
    "gn:adm2_name":"Asakuragunyasumachi",
    "gn:name":"Shimotakaba",
    "iso:country":"JP",
    "wof:name":"838-0211",
    "wof:placetype":"postalcode"
},
  "geometry": {"coordinates":[130.60640000000001,33.4435],"type":"Point"}
}