{
  "type": "Feature",
  "properties": {
    "gn:adm1_name":"Shizuokaken",
    "gn:adm2_name":"Gotenbashi",
    "gn:name":"Muikaichiba",
    "iso:country":"JP",
    "wof:name":"412-0016",
    "wof:placetype":"postalcode"
},
  "geometry": {"coordinates":[138.9408,35.3315],"type":"Point"}
}