{
  "type": "Feature",
  "properties": {
    "gn:adm1_name":"Saitamaken",
    "gn:adm2_name":"Hikigunyoshimimachi",
    "gn:name":"Shimohosoya",
    "iso:country":"JP",
    "wof:name":"355-0118",
    "wof:placetype":"postalcode"
},
  "geometry": {"coordinates":[139.45150000000001,36.041],"type":"Point"}
}