{
  "type": "Feature",
  "properties": {
    "gn:adm1_name":"Ibarakiken",
    "gn:adm2_name":"Kashimashi",
    "gn:name":"Hikari",
    "iso:country":"JP",
    "wof:name":"314-0014",
    "wof:placetype":"postalcode"
},
  "geometry": {"coordinates":[140.6695,35.9395],"type":"Point"}
}