{
  "type": "Feature",
  "properties": {
    "gn:adm1_name":"Chibaken",
    "gn:adm2_name":"Choushishi",
    "gn:name":"Suehirochou",
    "iso:country":"JP",
    "wof:name":"288-0042",
    "wof:placetype":"postalcode"
},
  "geometry": {"coordinates":[140.8314,35.732],"type":"Point"}
}