{
  "type": "Feature",
  "properties": {
    "gn:adm1_name":"Okayamaken",
    "gn:adm2_name":"Kibigunmabichou",
    "gn:name":"Tsujita",
    "iso:country":"JP",
    "wof:name":"710-1312",
    "wof:placetype":"postalcode"
},
  "geometry": {"coordinates":[133.71510000000001,34.6471],"type":"Point"}
}