{
  "type": "Feature",
  "properties": {
    "gn:adm1_name":"Shigaken",
    "gn:adm2_name":"Nagahamashi",
    "gn:name":"Tobakamichou",
    "iso:country":"JP",
    "wof:name":"526-0822",
    "wof:placetype":"postalcode"
},
  "geometry": {"coordinates":[136.32849999999999,35.3732],"type":"Point"}
}