{
  "type": "Feature",
  "properties": {
    "gn:adm1_name":"Aichiken",
    "gn:adm2_name":"Iwakurashi",
    "gn:name":"Saichichou",
    "iso:country":"JP",
    "wof:name":"482-0036",
    "wof:placetype":"postalcode"
},
  "geometry": {"coordinates":[136.86410000000001,35.2816],"type":"Point"}
}