{
  "type": "Feature",
  "properties": {
    "gn:adm1_name":"Kyoutofu",
    "gn:adm2_name":"Kameokashi",
    "gn:name":"Nishitsutsujigaokamiyamadai",
    "iso:country":"JP",
    "wof:name":"621-0845",
    "wof:placetype":"postalcode"
},
  "geometry": {"coordinates":[135.58439999999999,34.9968],"type":"Point"}
}