{
  "type": "Feature",
  "properties": {
    "gn:adm1_name":"Ehimeken",
    "gn:adm2_name":"Kawanoeshi",
    "gn:name":"Kawatakichoushimoyama",
    "iso:country":"JP",
    "wof:name":"799-0127",
    "wof:placetype":"postalcode"
},
  "geometry": {"coordinates":[133.6456,33.9929],"type":"Point"}
}