{
  "type": "Feature",
  "properties": {
    "gn:adm1_name":"Naraken",
    "gn:adm2_name":"Goseshi",
    "gn:name":"Heisaka",
    "iso:country":"JP",
    "wof:name":"639-2266",
    "wof:placetype":"postalcode"
},
  "geometry": {"coordinates":[135.7313,34.395],"type":"Point"}
}