{
  "type": "Feature",
  "properties": {
    "gn:adm1_name":"Naganoken",
    "gn:adm2_name":"Komaganeshi",
    "gn:name":"Uwabukita",
    "iso:country":"JP",
    "wof:name":"399-4116",
    "wof:placetype":"postalcode"
},
  "geometry": {"coordinates":[137.9331,35.7413],"type":"Point"}
}