{
  "type": "Feature",
  "properties": {
    "gn:adm1_name":"Kyoutofu",
    "gn:adm2_name":"Kumanogunkumihamachou",
    "gn:name":"Endonji",
    "iso:country":"JP",
    "wof:name":"629-3555",
    "wof:placetype":"postalcode"
},
  "geometry": {"coordinates":[134.9845,35.5887],"type":"Point"}
}