{
  "type": "Feature",
  "properties": {
    "gn:adm1_name":"Fukuokaken",
    "gn:adm2_name":"Kitakyuushuushiyahatanishiku",
    "gn:name":"Asakawagakuendai",
    "iso:country":"JP",
    "wof:name":"807-0871",
    "wof:placetype":"postalcode"
},
  "geometry": {"coordinates":[130.70670000000001,33.8839],"type":"Point"}
}