{
  "type": "Feature",
  "properties": {
    "gn:adm1_name":"Gunmaken",
    "gn:adm2_name":"Takasakishi",
    "gn:name":"Kaminamiemachi",
    "iso:country":"JP",
    "wof:name":"370-0801",
    "wof:placetype":"postalcode"
},
  "geometry": {"coordinates":[138.9879,36.3428],"type":"Point"}
}