{
  "type": "Feature",
  "properties": {
    "gn:adm1_name":"Aichiken",
    "gn:adm2_name":"Inazawashi",
    "gn:name":"Akaikechou",
    "iso:country":"JP",
    "wof:name":"492-8008",
    "wof:placetype":"postalcode"
},
  "geometry": {"coordinates":[136.81790000000001,35.2738],"type":"Point"}
}