{
  "type": "Feature",
  "properties": {
    "gn:adm1_name":"Fukushimaken",
    "gn:adm2_name":"Ishikawagun'Ishikawamachi",
    "gn:name":"Kitayamagata",
    "iso:country":"JP",
    "wof:name":"963-7811",
    "wof:placetype":"postalcode"
},
  "geometry": {"coordinates":[140.47479999999999,37.1321],"type":"Point"}
}