{
  "type": "Feature",
  "properties": {
    "gn:adm1_name":"Hyougoken",
    "gn:adm2_name":"Nishinomiyashi",
    "gn:name":"Uegahara1banchou",
    "iso:country":"JP",
    "wof:name":"662-0891",
    "wof:placetype":"postalcode"
},
  "geometry": {"coordinates":[135.3468,34.7683],"type":"Point"}
}