{
  "type": "Feature",
  "properties": {
    "gn:adm1_name":"Kagawaken",
    "gn:adm2_name":"Takamatsushi",
    "gn:name":"Kamihayashichou",
    "iso:country":"JP",
    "wof:name":"761-0302",
    "wof:placetype":"postalcode"
},
  "geometry": {"coordinates":[134.06649999999999,34.2893],"type":"Point"}
}