{
  "type": "Feature",
  "properties": {
    "gn:adm1_name":"Aichiken",
    "gn:adm2_name":"Nagoyashinakagawaku",
    "gn:name":"Souenchou",
    "iso:country":"JP",
    "wof:name":"454-0821",
    "wof:placetype":"postalcode"
},
  "geometry": {"coordinates":[136.8682,35.1458],"type":"Point"}
}