{
  "type": "Feature",
  "properties": {
    "gn:adm1_name":"Chibaken",
    "gn:adm2_name":"Sakurashi",
    "gn:name":"Oosakidai",
    "iso:country":"JP",
    "wof:name":"285-0817",
    "wof:placetype":"postalcode"
},
  "geometry": {"coordinates":[140.22219999999999,35.7059],"type":"Point"}
}