{
  "type": "Feature",
  "properties": {
    "gn:adm1_name":"Hiroshimaken",
    "gn:adm2_name":"Hiroshimashiminamiku",
    "gn:name":"Nihookimachi",
    "iso:country":"JP",
    "wof:name":"734-0057",
    "wof:placetype":"postalcode"
},
  "geometry": {"coordinates":[132.48429999999999,34.3617],"type":"Point"}
}