{
  "type": "Feature",
  "properties": {
    "gn:adm1_name":"Niigataken",
    "gn:adm2_name":"Kitakanbaragunshiunjimachi",
    "gn:name":"Tomijima",
    "iso:country":"JP",
    "wof:name":"957-0207",
    "wof:placetype":"postalcode"
},
  "geometry": {"coordinates":[139.33099999999999,38.0227],"type":"Point"}
}