{
  "type": "Feature",
  "properties": {
    "gn:adm1_name":"Ishikawaken",
    "gn:adm2_name":"Suzushi",
    "gn:name":"Nonoemachi",
    "iso:country":"JP",
    "wof:name":"927-1213",
    "wof:placetype":"postalcode"
},
  "geometry": {"coordinates":[137.27430000000001,37.4423],"type":"Point"}
}