{
  "type": "Feature",
  "properties": {
    "gn:adm1_name":"Tottoriken",
    "gn:adm2_name":"Iwamigunfukubeson",
    "gn:name":"Amou",
    "iso:country":"JP",
    "wof:name":"689-0106",
    "wof:placetype":"postalcode"
},
  "geometry": {"coordinates":[134.27340000000001,35.5475],"type":"Point"}
}