{
  "type": "Feature",
  "properties": {
    "gn:adm1_name":"Fukuokaken",
    "gn:adm2_name":"Miyakogunsaigawamachi",
    "gn:name":"Yamaga",
    "iso:country":"JP",
    "wof:name":"824-0221",
    "wof:placetype":"postalcode"
},
  "geometry": {"coordinates":[130.93270000000001,33.6492],"type":"Point"}
}