{
  "type": "Feature",
  "properties": {
    "gn:adm1_name":"Niigataken",
    "gn:adm2_name":"Nakakanbaragunkosudomachi",
    "gn:name":"Yokogawahama",
    "iso:country":"JP",
    "wof:name":"956-0121",
    "wof:placetype":"postalcode"
},
  "geometry": {"coordinates":[139.0728,37.7485],"type":"Point"}
}