{
  "type": "Feature",
  "properties": {
    "gn:adm1_name":"Saitamaken",
    "gn:adm2_name":"Fukayashi",
    "gn:name":"Nishijima",
    "iso:country":"JP",
    "wof:name":"366-0824",
    "wof:placetype":"postalcode"
},
  "geometry": {"coordinates":[139.28229999999999,36.193],"type":"Point"}
}