{
  "type": "Feature",
  "properties": {
    "gn:adm1_name":"Ehimeken",
    "gn:adm2_name":"Imabarishi",
    "gn:name":"Sakaemachi",
    "iso:country":"JP",
    "wof:name":"794-0023",
    "wof:placetype":"postalcode"
},
  "geometry": {"coordinates":[132.99979999999999,34.0694],"type":"Point"}
}