{
  "type": "Feature",
  "properties": {
    "gn:adm1_name":"Gifuken",
    "gn:adm2_name":"Tokishi",
    "gn:name":"Hidaasanoyaochichou",
    "iso:country":"JP",
    "wof:name":"509-5116",
    "wof:placetype":"postalcode"
},
  "geometry": {"coordinates":[137.19409999999999,35.3597],"type":"Point"}
}