{
  "type": "Feature",
  "properties": {
    "gn:adm1_name":"Saitamaken",
    "gn:adm2_name":"Kawaguchishi",
    "gn:name":"Saiwaichou",
    "iso:country":"JP",
    "wof:name":"332-0016",
    "wof:placetype":"postalcode"
},
  "geometry": {"coordinates":[139.71950000000001,35.8064],"type":"Point"}
}