{
  "type": "Feature",
  "properties": {
    "gn:adm1_name":"Hyougoken",
    "gn:adm2_name":"Koubeshitarumiku",
    "gn:name":"Mizugaoka",
    "iso:country":"JP",
    "wof:name":"655-0025",
    "wof:placetype":"postalcode"
},
  "geometry": {"coordinates":[135.05629999999999,34.6338],"type":"Point"}
}