{
  "type": "Feature",
  "properties": {
    "gn:adm1_name":"Shizuokaken",
    "gn:adm2_name":"Shizuokashi",
    "gn:name":"Kamiashiarai",
    "iso:country":"JP",
    "wof:name":"420-0841",
    "wof:placetype":"postalcode"
},
  "geometry": {"coordinates":[138.39410000000001,34.993],"type":"Point"}
}