{
  "type": "Feature",
  "properties": {
    "gn:adm1_name":"Hyougoken",
    "gn:adm2_name":"Himejishi",
    "gn:name":"Tougouchou",
    "iso:country":"JP",
    "wof:name":"670-0821",
    "wof:placetype":"postalcode"
},
  "geometry": {"coordinates":[134.71539999999999,34.8308],"type":"Point"}
}