{
  "type": "Feature",
  "properties": {
    "gn:adm1_name":"Fukushimaken",
    "gn:adm2_name":"Shirakawashi",
    "gn:name":"Dobuduka",
    "iso:country":"JP",
    "wof:name":"961-0046",
    "wof:placetype":"postalcode"
},
  "geometry": {"coordinates":[140.2243,37.1091],"type":"Point"}
}