{
  "type": "Feature",
  "properties": {
    "gn:adm1_name":"Ibarakiken",
    "gn:adm2_name":"Hitachinakashi",
    "gn:name":"Karasugadai",
    "iso:country":"JP",
    "wof:name":"311-1207",
    "wof:placetype":"postalcode"
},
  "geometry": {"coordinates":[140.60220000000001,36.3661],"type":"Point"}
}