{
  "type": "Feature",
  "properties": {
    "gn:adm1_name":"Toukyouto",
    "gn:adm2_name":"Suginamiku",
    "gn:name":"Kamitakaido",
    "iso:country":"JP",
    "wof:name":"168-0074",
    "wof:placetype":"postalcode"
},
  "geometry": {"coordinates":[139.61269999999999,35.674],"type":"Point"}
}