{
  "type": "Feature",
  "properties": {
    "gn:adm1_name":"Naraken",
    "gn:adm2_name":"Shikiguntawaramotochou",
    "gn:name":"Yao",
    "iso:country":"JP",
    "wof:name":"636-0311",
    "wof:placetype":"postalcode"
},
  "geometry": {"coordinates":[135.79140000000001,34.5628],"type":"Point"}
}