{
  "type": "Feature",
  "properties": {
    "gn:adm1_name":"Naganoken",
    "gn:adm2_name":"Iidashi",
    "gn:name":"Kanaeshimoyama",
    "iso:country":"JP",
    "wof:name":"395-0803",
    "wof:placetype":"postalcode"
},
  "geometry": {"coordinates":[137.8338,35.5056],"type":"Point"}
}