{
  "type": "Feature",
  "properties": {
    "gn:adm1_name":"Wakayamaken",
    "gn:adm2_name":"Higashimurogunkozagawachou",
    "gn:name":"Uruno",
    "iso:country":"JP",
    "wof:name":"649-4225",
    "wof:placetype":"postalcode"
},
  "geometry": {"coordinates":[135.76560000000001,33.5365],"type":"Point"}
}