{
  "type": "Feature",
  "properties": {
    "gn:adm1_name":"Toukyouto",
    "gn:adm2_name":"Koutouku",
    "gn:name":"Kameido",
    "iso:country":"JP",
    "wof:name":"136-0071",
    "wof:placetype":"postalcode"
},
  "geometry": {"coordinates":[139.82820000000001,35.699],"type":"Point"}
}