{
  "type": "Feature",
  "properties": {
    "gn:adm1_name":"Oosakafu",
    "gn:adm2_name":"Kaidukashi",
    "gn:name":"Mitsumatsu(Sonota)",
    "iso:country":"JP",
    "wof:name":"597-0105",
    "wof:placetype":"postalcode"
},
  "geometry": {"coordinates":[135.3817,34.4082],"type":"Point"}
}