{
  "type": "Feature",
  "properties": {
    "gn:adm1_name":"Miyagiken",
    "gn:adm2_name":"Sendaishiaobaku",
    "gn:name":"Akasaka",
    "iso:country":"JP",
    "wof:name":"989-3211",
    "wof:placetype":"postalcode"
},
  "geometry": {"coordinates":[140.74610000000001,38.2931],"type":"Point"}
}