{
  "type": "Feature",
  "properties": {
    "gn:adm1_name":"Naraken",
    "gn:adm2_name":"Kashiharashi",
    "gn:name":"Toriyachou",
    "iso:country":"JP",
    "wof:name":"634-0822",
    "wof:placetype":"postalcode"
},
  "geometry": {"coordinates":[135.7817,34.4793],"type":"Point"}
}