{
  "type": "Feature",
  "properties": {
    "gn:adm1_name":"Shigaken",
    "gn:adm2_name":"Oumihachimanshi",
    "gn:name":"Sakuramiyachou",
    "iso:country":"JP",
    "wof:name":"523-0893",
    "wof:placetype":"postalcode"
},
  "geometry": {"coordinates":[136.09710000000001,35.1283],"type":"Point"}
}