{
  "type": "Feature",
  "properties": {
    "gn:adm1_name":"Hyougoken",
    "gn:adm2_name":"Himejishi",
    "gn:name":"Aboshikukaichihigashimachi",
    "iso:country":"JP",
    "wof:name":"671-1252",
    "wof:placetype":"postalcode"
},
  "geometry": {"coordinates":[134.59039999999999,34.79],"type":"Point"}
}