{
  "type": "Feature",
  "properties": {
    "gn:adm1_name":"Nagasakiken",
    "gn:adm2_name":"Minamimatsuuraguntamanourachou",
    "gn:name":"Tachiyagou",
    "iso:country":"JP",
    "wof:name":"853-0412",
    "wof:placetype":"postalcode"
},
  "geometry": {"coordinates":[128.64070000000001,32.6079],"type":"Point"}
}