{
  "type": "Feature",
  "properties": {
    "gn:adm1_name":"Okayamaken",
    "gn:adm2_name":"Katsutagunshoubokuchou",
    "gn:name":"Shimonoda",
    "iso:country":"JP",
    "wof:name":"708-1213",
    "wof:placetype":"postalcode"
},
  "geometry": {"coordinates":[134.0994,35.0759],"type":"Point"}
}