{
  "type": "Feature",
  "properties": {
    "gn:adm1_name":"Aichiken",
    "gn:adm2_name":"Nagoyashiatsutaku",
    "gn:name":"Nakadechou",
    "iso:country":"JP",
    "wof:name":"456-0067",
    "wof:placetype":"postalcode"
},
  "geometry": {"coordinates":[136.89019999999999,35.1321],"type":"Point"}
}