{
  "type": "Feature",
  "properties": {
    "gn:adm1_name":"Ooitaken",
    "gn:adm2_name":"Hitashi",
    "gn:name":"Takedashinmachi",
    "iso:country":"JP",
    "wof:name":"877-0041",
    "wof:placetype":"postalcode"
},
  "geometry": {"coordinates":[130.93729999999999,33.311],"type":"Point"}
}