{
  "type": "Feature",
  "properties": {
    "gn:adm1_name":"Mieken",
    "gn:adm2_name":"Yokkaichishi",
    "gn:name":"Miyukigaoka",
    "iso:country":"JP",
    "wof:name":"510-0811",
    "wof:placetype":"postalcode"
},
  "geometry": {"coordinates":[136.61699999999999,34.9946],"type":"Point"}
}