{
  "type": "Feature",
  "properties": {
    "gn:adm1_name":"Naraken",
    "gn:adm2_name":"Tenrishi",
    "gn:name":"Nikaidoukitasugatachou",
    "iso:country":"JP",
    "wof:name":"632-0088",
    "wof:placetype":"postalcode"
},
  "geometry": {"coordinates":[135.79409999999999,34.5988],"type":"Point"}
}