{
  "type": "Feature",
  "properties": {
    "gn:adm1_name":"Okayamaken",
    "gn:adm2_name":"Maniwagun'Ochiaichou",
    "gn:name":"Yoshi",
    "iso:country":"JP",
    "wof:name":"719-3136",
    "wof:placetype":"postalcode"
},
  "geometry": {"coordinates":[133.79130000000001,34.9648],"type":"Point"}
}