{
  "type": "Feature",
  "properties": {
    "gn:adm1_name":"Okayamaken",
    "gn:adm2_name":"Tamanoshi",
    "gn:name":"Nishitaiji",
    "iso:country":"JP",
    "wof:name":"706-0313",
    "wof:placetype":"postalcode"
},
  "geometry": {"coordinates":[133.9922,34.5519],"type":"Point"}
}