{
  "type": "Feature",
  "properties": {
    "gn:adm1_name":"Chibaken",
    "gn:adm2_name":"Matsudoshi",
    "gn:name":"Kazusauchi",
    "iso:country":"JP",
    "wof:name":"270-0018",
    "wof:placetype":"postalcode"
},
  "geometry": {"coordinates":[139.9307,35.8277],"type":"Point"}
}