{
  "type": "Feature",
  "properties": {
    "gn:adm1_name":"Gunmaken",
    "gn:adm2_name":"Tonegunniiharumura",
    "gn:name":"Aimata",
    "iso:country":"JP",
    "wof:name":"379-1404",
    "wof:placetype":"postalcode"
},
  "geometry": {"coordinates":[138.89859999999999,36.7252],"type":"Point"}
}