{
  "type": "Feature",
  "properties": {
    "gn:adm1_name":"Toukyouto",
    "gn:adm2_name":"Machidashi",
    "gn:name":"Kisomachi",
    "iso:country":"JP",
    "wof:name":"194-0033",
    "wof:placetype":"postalcode"
},
  "geometry": {"coordinates":[139.42410000000001,35.5642],"type":"Point"}
}