{
  "type": "Feature",
  "properties": {
    "gn:adm1_name":"Gifuken",
    "gn:adm2_name":"Mashitagunkanayamachou",
    "gn:name":"Sugatasasahora",
    "iso:country":"JP",
    "wof:name":"509-1624",
    "wof:placetype":"postalcode"
},
  "geometry": {"coordinates":[137.10720000000001,35.6419],"type":"Point"}
}