{
  "type": "Feature",
  "properties": {
    "gn:adm1_name":"Oosakafu",
    "gn:adm2_name":"Minamikawachiguntaishichou",
    "gn:name":"Hamuro",
    "iso:country":"JP",
    "wof:name":"583-0994",
    "wof:placetype":"postalcode"
},
  "geometry": {"coordinates":[135.64070000000001,34.5116],"type":"Point"}
}