{
  "type": "Feature",
  "properties": {
    "gn:adm1_name":"Kyoutofu",
    "gn:adm2_name":"Takenoguntangochou",
    "gn:name":"Ueyama",
    "iso:country":"JP",
    "wof:name":"627-0247",
    "wof:placetype":"postalcode"
},
  "geometry": {"coordinates":[135.19059999999999,35.7368],"type":"Point"}
}