{
  "type": "Feature",
  "properties": {
    "gn:adm1_name":"Kouchiken",
    "gn:adm2_name":"Kouchishi",
    "gn:name":"Yorikimachi",
    "iso:country":"JP",
    "wof:name":"780-0863",
    "wof:placetype":"postalcode"
},
  "geometry": {"coordinates":[133.53870000000001,33.5571],"type":"Point"}
}