{
  "type": "Feature",
  "properties": {
    "gn:adm1_name":"Tochigiken",
    "gn:adm2_name":"Ashikagashi",
    "gn:name":"Igusachou",
    "iso:country":"JP",
    "wof:name":"326-0811",
    "wof:placetype":"postalcode"
},
  "geometry": {"coordinates":[139.45060000000001,36.3362],"type":"Point"}
}