{
  "type": "Feature",
  "properties": {
    "gn:adm1_name":"Oosakafu",
    "gn:adm2_name":"Oosakashisumiyoshiku",
    "gn:name":"Yamanouchi",
    "iso:country":"JP",
    "wof:name":"558-0023",
    "wof:placetype":"postalcode"
},
  "geometry": {"coordinates":[135.5017,34.5956],"type":"Point"}
}