{
  "type": "Feature",
  "properties": {
    "gn:adm1_name":"Fukushimaken",
    "gn:adm2_name":"Dategunkoorimachi",
    "gn:name":"Shinmachi",
    "iso:country":"JP",
    "wof:name":"969-1628",
    "wof:placetype":"postalcode"
},
  "geometry": {"coordinates":[140.51390000000001,37.8431],"type":"Point"}
}