{
  "type": "Feature",
  "properties": {
    "gn:adm1_name":"Hyougoken",
    "gn:adm2_name":"Himejishi",
    "gn:name":"Hirohatakushimizuchou",
    "iso:country":"JP",
    "wof:name":"671-1113",
    "wof:placetype":"postalcode"
},
  "geometry": {"coordinates":[134.63319999999999,34.8038],"type":"Point"}
}