{
  "type": "Feature",
  "properties": {
    "gn:adm1_name":"Toyamaken",
    "gn:adm2_name":"Higashitonamigunjouhanamachi",
    "gn:name":"Yoshimatsu",
    "iso:country":"JP",
    "wof:name":"939-1806",
    "wof:placetype":"postalcode"
},
  "geometry": {"coordinates":[136.91820000000001,36.5245],"type":"Point"}
}