{
  "type": "Feature",
  "properties": {
    "gn:adm1_name":"Kouchiken",
    "gn:adm2_name":"Susakishi",
    "gn:name":"Uranouchitachimesurugi",
    "iso:country":"JP",
    "wof:name":"785-0164",
    "wof:placetype":"postalcode"
},
  "geometry": {"coordinates":[133.38319999999999,33.4334],"type":"Point"}
}