{
  "type": "Feature",
  "properties": {
    "gn:adm1_name":"Oosakafu",
    "gn:adm2_name":"Hirakatashi",
    "gn:name":"Higashifunahashi",
    "iso:country":"JP",
    "wof:name":"573-1115",
    "wof:placetype":"postalcode"
},
  "geometry": {"coordinates":[135.68520000000001,34.8526],"type":"Point"}
}