{
  "type": "Feature",
  "properties": {
    "gn:adm1_name":"Shizuokaken",
    "gn:adm2_name":"Shizuokashi",
    "gn:name":"Yamazaki",
    "iso:country":"JP",
    "wof:name":"421-1213",
    "wof:placetype":"postalcode"
},
  "geometry": {"coordinates":[138.35329999999999,34.9778],"type":"Point"}
}