{
  "type": "Feature",
  "properties": {
    "gn:adm1_name":"Nagasakiken",
    "gn:adm2_name":"Kitamatsuuragun'Odikachou",
    "gn:name":"Nakamuragou",
    "iso:country":"JP",
    "wof:name":"857-4703",
    "wof:placetype":"postalcode"
},
  "geometry": {"coordinates":[129.0643,33.199],"type":"Point"}
}