{
  "type": "Feature",
  "properties": {
    "gn:adm1_name":"Shizuokaken",
    "gn:adm2_name":"Mishimashi",
    "gn:name":"Wakamatsuchou",
    "iso:country":"JP",
    "wof:name":"411-0024",
    "wof:placetype":"postalcode"
},
  "geometry": {"coordinates":[138.92570000000001,35.1312],"type":"Point"}
}