{
  "type": "Feature",
  "properties": {
    "gn:adm1_name":"Toukyouto",
    "gn:adm2_name":"Fuchuushi",
    "gn:name":"Sakaechou",
    "iso:country":"JP",
    "wof:name":"183-0051",
    "wof:placetype":"postalcode"
},
  "geometry": {"coordinates":[139.4786,35.6887],"type":"Point"}
}