{
  "type": "Feature",
  "properties": {
    "gn:adm1_name":"Chibaken",
    "gn:adm2_name":"Sodegaurashi",
    "gn:name":"Eichi",
    "iso:country":"JP",
    "wof:name":"299-0232",
    "wof:placetype":"postalcode"
},
  "geometry": {"coordinates":[140.0316,35.4054],"type":"Point"}
}