{
  "type": "Feature",
  "properties": {
    "gn:adm1_name":"Yamaguchiken",
    "gn:adm2_name":"Shimonosekishi",
    "gn:name":"Takura",
    "iso:country":"JP",
    "wof:name":"751-0883",
    "wof:placetype":"postalcode"
},
  "geometry": {"coordinates":[130.9693,34.015],"type":"Point"}
}