{
  "type": "Feature",
  "properties": {
    "gn:adm1_name":"Tochigiken",
    "gn:adm2_name":"Ootawarashi",
    "gn:name":"Shintomichou",
    "iso:country":"JP",
    "wof:name":"324-0055",
    "wof:placetype":"postalcode"
},
  "geometry": {"coordinates":[140.02600000000001,36.8636],"type":"Point"}
}