{
  "type": "Feature",
  "properties": {
    "gn:adm1_name":"Toyamaken",
    "gn:adm2_name":"Toyamashi",
    "gn:name":"Aidenmachi",
    "iso:country":"JP",
    "wof:name":"930-0845",
    "wof:placetype":"postalcode"
},
  "geometry": {"coordinates":[137.23589999999999,36.6997],"type":"Point"}
}