{
  "type": "Feature",
  "properties": {
    "gn:adm1_name":"Miyagiken",
    "gn:adm2_name":"Sendaishiaobaku",
    "gn:name":"Toorichou",
    "iso:country":"JP",
    "wof:name":"981-0915",
    "wof:placetype":"postalcode"
},
  "geometry": {"coordinates":[140.8657,38.2791],"type":"Point"}
}