{
  "type": "Feature",
  "properties": {
    "gn:adm1_name":"Saitamaken",
    "gn:adm2_name":"Saitamashioomiyaku",
    "gn:name":"Sakuragichou",
    "iso:country":"JP",
    "wof:name":"330-0854",
    "wof:placetype":"postalcode"
},
  "geometry": {"coordinates":[139.61949999999999,35.9052],"type":"Point"}
}