{
  "type": "Feature",
  "properties": {
    "gn:adm1_name":"Ooitaken",
    "gn:adm2_name":"Kusugunkusumachi",
    "gn:name":"Iwamuro",
    "iso:country":"JP",
    "wof:name":"879-4405",
    "wof:placetype":"postalcode"
},
  "geometry": {"coordinates":[131.178,33.2856],"type":"Point"}
}