{
  "type": "Feature",
  "properties": {
    "gn:adm1_name":"Naganoken",
    "gn:adm2_name":"Shimoinagun'Ananchou",
    "gn:name":"Kitajou",
    "iso:country":"JP",
    "wof:name":"399-1501",
    "wof:placetype":"postalcode"
},
  "geometry": {"coordinates":[137.8321,35.3363],"type":"Point"}
}