{
  "type": "Feature",
  "properties": {
    "gn:adm1_name":"Kouchiken",
    "gn:adm2_name":"Agawagun'Inochou",
    "gn:name":"Kono",
    "iso:country":"JP",
    "wof:name":"781-2135",
    "wof:placetype":"postalcode"
},
  "geometry": {"coordinates":[133.3931,33.5725],"type":"Point"}
}