{
  "type": "Feature",
  "properties": {
    "gn:adm1_name":"Kyoutofu",
    "gn:adm2_name":"Maidurushi",
    "gn:name":"Asashiro",
    "iso:country":"JP",
    "wof:name":"624-0842",
    "wof:placetype":"postalcode"
},
  "geometry": {"coordinates":[135.3244,35.4445],"type":"Point"}
}