{
  "type": "Feature",
  "properties": {
    "gn:adm1_name":"Kyoutofu",
    "gn:adm2_name":"Kyoutoshisakyouku",
    "gn:name":"Shishigatanikamimiyanomaechou",
    "iso:country":"JP",
    "wof:name":"606-8447",
    "wof:placetype":"postalcode"
},
  "geometry": {"coordinates":[135.79300000000001,35.019],"type":"Point"}
}