{
  "type": "Feature",
  "properties": {
    "gn:adm1_name":"Naganoken",
    "gn:adm2_name":"Kamiinagunhasemura",
    "gn:name":"Ura",
    "iso:country":"JP",
    "wof:name":"396-0407",
    "wof:placetype":"postalcode"
},
  "geometry": {"coordinates":[137.96690000000001,35.8373],"type":"Point"}
}