{
  "type": "Feature",
  "properties": {
    "gn:adm1_name":"Aichiken",
    "gn:adm2_name":"Higashikamogun'Asukechou",
    "gn:name":"Kochou",
    "iso:country":"JP",
    "wof:name":"444-2521",
    "wof:placetype":"postalcode"
},
  "geometry": {"coordinates":[137.33109999999999,35.1892],"type":"Point"}
}