{
  "type": "Feature",
  "properties": {
    "gn:adm1_name":"Ibarakiken",
    "gn:adm2_name":"Kujigundaigomachi",
    "gn:name":"Hanawa",
    "iso:country":"JP",
    "wof:name":"319-3537",
    "wof:placetype":"postalcode"
},
  "geometry": {"coordinates":[140.30629999999999,36.7857],"type":"Point"}
}