{
  "type": "Feature",
  "properties": {
    "gn:adm1_name":"Yamanashiken",
    "gn:adm2_name":"Kitakomagunhakushuumachi",
    "gn:name":"Daibou",
    "iso:country":"JP",
    "wof:name":"408-0314",
    "wof:placetype":"postalcode"
},
  "geometry": {"coordinates":[138.31739999999999,35.7765],"type":"Point"}
}