{
  "type": "Feature",
  "properties": {
    "gn:adm1_name":"Okayamaken",
    "gn:adm2_name":"Kumegunchuuouchou",
    "gn:name":"Sakai",
    "iso:country":"JP",
    "wof:name":"709-3723",
    "wof:placetype":"postalcode"
},
  "geometry": {"coordinates":[133.91319999999999,34.9561],"type":"Point"}
}