{
  "type": "Feature",
  "properties": {
    "gn:adm1_name":"Tochigiken",
    "gn:adm2_name":"Asogunkuzuumachi",
    "gn:name":"Kakidaira",
    "iso:country":"JP",
    "wof:name":"327-0515",
    "wof:placetype":"postalcode"
},
  "geometry": {"coordinates":[139.55670000000001,36.4652],"type":"Point"}
}