{
  "type": "Feature",
  "properties": {
    "gn:adm1_name":"Saitamaken",
    "gn:adm2_name":"Kawagoeshi",
    "gn:name":"Fukuda",
    "iso:country":"JP",
    "wof:name":"350-0821",
    "wof:placetype":"postalcode"
},
  "geometry": {"coordinates":[139.4725,35.9522],"type":"Point"}
}