{
  "type": "Feature",
  "properties": {
    "gn:adm1_name":"Hiroshimaken",
    "gn:adm2_name":"Onomichishi",
    "gn:name":"Hirahara",
    "iso:country":"JP",
    "wof:name":"722-0018",
    "wof:placetype":"postalcode"
},
  "geometry": {"coordinates":[133.17679999999999,34.4121],"type":"Point"}
}