{
  "type": "Feature",
  "properties": {
    "gn:adm1_name":"Niigataken",
    "gn:adm2_name":"Sadogun'Aikawamachi",
    "gn:name":"Shimoyamanokamimachi",
    "iso:country":"JP",
    "wof:name":"952-1504",
    "wof:placetype":"postalcode"
},
  "geometry": {"coordinates":[138.24160000000001,38.0388],"type":"Point"}
}