{
  "type": "Feature",
  "properties": {
    "gn:adm1_name":"Hiroshimaken",
    "gn:adm2_name":"Kounugunjougechou",
    "gn:name":"Jouge",
    "iso:country":"JP",
    "wof:name":"729-3431",
    "wof:placetype":"postalcode"
},
  "geometry": {"coordinates":[133.12119999999999,34.6968],"type":"Point"}
}