{
  "type": "Feature",
  "properties": {
    "gn:adm1_name":"Kagoshimaken",
    "gn:adm2_name":"Kushikinoshi",
    "gn:name":"Nagasakichou",
    "iso:country":"JP",
    "wof:name":"896-0033",
    "wof:placetype":"postalcode"
},
  "geometry": {"coordinates":[130.26779999999999,31.7087],"type":"Point"}
}