{
  "type": "Feature",
  "properties": {
    "gn:adm1_name":"Nagasakiken",
    "gn:adm2_name":"Kitatakakigunmoriyamachou",
    "gn:name":"Moriyamasugitanimyou",
    "iso:country":"JP",
    "wof:name":"854-0205",
    "wof:placetype":"postalcode"
},
  "geometry": {"coordinates":[130.14099999999999,32.8168],"type":"Point"}
}