{
  "type": "Feature",
  "properties": {
    "gn:adm1_name":"Mieken",
    "gn:adm2_name":"Tsushi",
    "gn:name":"Oozatokonodachou",
    "iso:country":"JP",
    "wof:name":"514-0123",
    "wof:placetype":"postalcode"
},
  "geometry": {"coordinates":[136.49029999999999,34.7778],"type":"Point"}
}