{
  "type": "Feature",
  "properties": {
    "gn:adm1_name":"Nagasakiken",
    "gn:adm2_name":"Minamimatsuuraguntomiechou",
    "gn:name":"Yamashitagou",
    "iso:country":"JP",
    "wof:name":"853-0212",
    "wof:placetype":"postalcode"
},
  "geometry": {"coordinates":[128.75640000000001,32.5891],"type":"Point"}
}