{
  "type": "Feature",
  "properties": {
    "gn:adm1_name":"Shimaneken",
    "gn:adm2_name":"Ooharagunkisukichou",
    "gn:name":"Nishihinobori",
    "iso:country":"JP",
    "wof:name":"699-1324",
    "wof:placetype":"postalcode"
},
  "geometry": {"coordinates":[132.90549999999999,35.2659],"type":"Point"}
}