{
  "type": "Feature",
  "properties": {
    "gn:adm1_name":"Aichiken",
    "gn:adm2_name":"Ichinomiyashi",
    "gn:name":"Tanyouchoudosaki",
    "iso:country":"JP",
    "wof:name":"491-0825",
    "wof:placetype":"postalcode"
},
  "geometry": {"coordinates":[136.82759999999999,35.2791],"type":"Point"}
}