{
  "type": "Feature",
  "properties": {
    "gn:adm1_name":"Chibaken",
    "gn:adm2_name":"Chibashimidoriku",
    "gn:name":"Takatsudochou",
    "iso:country":"JP",
    "wof:name":"267-0053",
    "wof:placetype":"postalcode"
},
  "geometry": {"coordinates":[140.26140000000001,35.5388],"type":"Point"}
}