{
  "type": "Feature",
  "properties": {
    "gn:adm1_name":"Hiroshimaken",
    "gn:adm2_name":"Akigunkaitachou",
    "gn:name":"Terasako",
    "iso:country":"JP",
    "wof:name":"736-0011",
    "wof:placetype":"postalcode"
},
  "geometry": {"coordinates":[132.55170000000001,34.3727],"type":"Point"}
}