{
  "type": "Feature",
  "properties": {
    "gn:adm1_name":"Hiroshimaken",
    "gn:adm2_name":"Yamagatagungeihokuchou",
    "gn:name":"Kawakoda",
    "iso:country":"JP",
    "wof:name":"731-2323",
    "wof:placetype":"postalcode"
},
  "geometry": {"coordinates":[132.2818,34.7298],"type":"Point"}
}