{
  "type": "Feature",
  "properties": {
    "gn:adm1_name":"Chibaken",
    "gn:adm2_name":"Awagunkyonanmachi",
    "gn:name":"Okuzure",
    "iso:country":"JP",
    "wof:name":"299-2111",
    "wof:placetype":"postalcode"
},
  "geometry": {"coordinates":[139.9109,35.1338],"type":"Point"}
}