{
  "type": "Feature",
  "properties": {
    "gn:adm1_name":"Hyougoken",
    "gn:adm2_name":"Kanzakigunkouderachou",
    "gn:name":"Tano",
    "iso:country":"JP",
    "wof:name":"679-2153",
    "wof:placetype":"postalcode"
},
  "geometry": {"coordinates":[134.72810000000001,34.9089],"type":"Point"}
}