{
  "type": "Feature",
  "properties": {
    "gn:adm1_name":"Mieken",
    "gn:adm2_name":"Uenoshi",
    "gn:name":"Midorigaokahonmachi",
    "iso:country":"JP",
    "wof:name":"518-0836",
    "wof:placetype":"postalcode"
},
  "geometry": {"coordinates":[136.14109999999999,34.7614],"type":"Point"}
}