{
  "type": "Feature",
  "properties": {
    "gn:adm1_name":"Ehimeken",
    "gn:adm2_name":"Kitagunnagahamachou",
    "gn:name":"Izumikou",
    "iso:country":"JP",
    "wof:name":"799-3455",
    "wof:placetype":"postalcode"
},
  "geometry": {"coordinates":[132.43430000000001,33.5594],"type":"Point"}
}