{
  "type": "Feature",
  "properties": {
    "gn:adm1_name":"Okayamaken",
    "gn:adm2_name":"Okayamashi",
    "gn:name":"Iwai",
    "iso:country":"JP",
    "wof:name":"700-0046",
    "wof:placetype":"postalcode"
},
  "geometry": {"coordinates":[133.89670000000001,34.6716],"type":"Point"}
}