{
  "type": "Feature",
  "properties": {
    "gn:adm1_name":"Niigataken",
    "gn:adm2_name":"Odiyashi",
    "gn:name":"Funaoka",
    "iso:country":"JP",
    "wof:name":"947-0024",
    "wof:placetype":"postalcode"
},
  "geometry": {"coordinates":[138.79640000000001,37.3028],"type":"Point"}
}