{
  "type": "Feature",
  "properties": {
    "gn:adm1_name":"Aichiken",
    "gn:adm2_name":"Atsumigun'Atsumichou",
    "gn:name":"Takaki",
    "iso:country":"JP",
    "wof:name":"441-3612",
    "wof:placetype":"postalcode"
},
  "geometry": {"coordinates":[137.1207,34.6319],"type":"Point"}
}