{
  "type": "Feature",
  "properties": {
    "gn:adm1_name":"Ibarakiken",
    "gn:adm2_name":"Niiharigunkasumigauramachi",
    "gn:name":"Tabuse",
    "iso:country":"JP",
    "wof:name":"300-0202",
    "wof:placetype":"postalcode"
},
  "geometry": {"coordinates":[140.3792,36.087],"type":"Point"}
}