{
  "type": "Feature",
  "properties": {
    "gn:adm1_name":"Toyamaken",
    "gn:adm2_name":"Oyabeshi",
    "gn:name":"Wasawa",
    "iso:country":"JP",
    "wof:name":"932-0822",
    "wof:placetype":"postalcode"
},
  "geometry": {"coordinates":[136.88339999999999,36.6536],"type":"Point"}
}