{
  "type": "Feature",
  "properties": {
    "gn:adm1_name":"Yamanashiken",
    "gn:adm2_name":"Tsurushi",
    "gn:name":"Tookaichiba",
    "iso:country":"JP",
    "wof:name":"402-0031",
    "wof:placetype":"postalcode"
},
  "geometry": {"coordinates":[138.88560000000001,35.5402],"type":"Point"}
}