{
  "type": "Feature",
  "properties": {
    "gn:adm1_name":"Niigataken",
    "gn:adm2_name":"Nishikanbaragunkatahigashimura",
    "gn:name":"Uhachirouuke",
    "iso:country":"JP",
    "wof:name":"959-0507",
    "wof:placetype":"postalcode"
},
  "geometry": {"coordinates":[138.95519999999999,37.7831],"type":"Point"}
}