{
  "type": "Feature",
  "properties": {
    "gn:adm1_name":"Niigataken",
    "gn:adm2_name":"Shibatashi",
    "gn:name":"Iijimaotsu",
    "iso:country":"JP",
    "wof:name":"957-0085",
    "wof:placetype":"postalcode"
},
  "geometry": {"coordinates":[139.28059999999999,37.9387],"type":"Point"}
}