{
  "type": "Feature",
  "properties": {
    "gn:adm1_name":"Shigaken",
    "gn:adm2_name":"Ikaguntakatsukichou",
    "gn:name":"Higashimonobe",
    "iso:country":"JP",
    "wof:name":"529-0261",
    "wof:placetype":"postalcode"
},
  "geometry": {"coordinates":[136.22450000000001,35.4796],"type":"Point"}
}