{
  "type": "Feature",
  "properties": {
    "gn:adm1_name":"Ibarakiken",
    "gn:adm2_name":"Tsuchiurashi",
    "gn:name":"Amakawa",
    "iso:country":"JP",
    "wof:name":"300-0818",
    "wof:placetype":"postalcode"
},
  "geometry": {"coordinates":[140.1738,36.0679],"type":"Point"}
}