{
  "type": "Feature",
  "properties": {
    "gn:adm1_name":"Ooitaken",
    "gn:adm2_name":"Saikishi",
    "gn:name":"Higashinada",
    "iso:country":"JP",
    "wof:name":"876-0021",
    "wof:placetype":"postalcode"
},
  "geometry": {"coordinates":[131.92850000000001,32.9549],"type":"Point"}
}