{
  "type": "Feature",
  "properties": {
    "gn:adm1_name":"Kanagawaken",
    "gn:adm2_name":"Yokohamashikanagawaku",
    "gn:name":"Kougaya",
    "iso:country":"JP",
    "wof:name":"221-0051",
    "wof:placetype":"postalcode"
},
  "geometry": {"coordinates":[139.63030000000001,35.473],"type":"Point"}
}