{
  "type": "Feature",
  "properties": {
    "gn:adm1_name":"Gifuken",
    "gn:adm2_name":"Oogakishi",
    "gn:name":"Hiruichou",
    "iso:country":"JP",
    "wof:name":"503-2216",
    "wof:placetype":"postalcode"
},
  "geometry": {"coordinates":[136.57069999999999,35.3864],"type":"Point"}
}