{
  "type": "Feature",
  "properties": {
    "gn:adm1_name":"Toukyouto",
    "gn:adm2_name":"Edogawaku",
    "gn:name":"Kitashinozaki",
    "iso:country":"JP",
    "wof:name":"133-0053",
    "wof:placetype":"postalcode"
},
  "geometry": {"coordinates":[139.89570000000001,35.7184],"type":"Point"}
}