{
  "type": "Feature",
  "properties": {
    "gn:adm1_name":"Hyougoken",
    "gn:adm2_name":"Kawanishishi",
    "gn:name":"Minamihanayashiki",
    "iso:country":"JP",
    "wof:name":"666-0026",
    "wof:placetype":"postalcode"
},
  "geometry": {"coordinates":[135.4042,34.8223],"type":"Point"}
}