{
  "type": "Feature",
  "properties": {
    "gn:adm1_name":"Kyoutofu",
    "gn:adm2_name":"Nagaokakyoushi",
    "gn:name":"Koufuudai",
    "iso:country":"JP",
    "wof:name":"617-0851",
    "wof:placetype":"postalcode"
},
  "geometry": {"coordinates":[135.6781,34.9301],"type":"Point"}
}