{
  "type": "Feature",
  "properties": {
    "gn:adm1_name":"Fukuiken",
    "gn:adm2_name":"Nanjougun'Imajouchou",
    "gn:name":"Imajou",
    "iso:country":"JP",
    "wof:name":"919-0131",
    "wof:placetype":"postalcode"
},
  "geometry": {"coordinates":[136.1977,35.7729],"type":"Point"}
}