{
  "type": "Feature",
  "properties": {
    "gn:adm1_name":"Chibaken",
    "gn:adm2_name":"Chibashihanamigawaku",
    "gn:name":"Yokododai",
    "iso:country":"JP",
    "wof:name":"262-0006",
    "wof:placetype":"postalcode"
},
  "geometry": {"coordinates":[140.11340000000001,35.6981],"type":"Point"}
}