{
  "type": "Feature",
  "properties": {
    "gn:adm1_name":"Aichiken",
    "gn:adm2_name":"Nagoyashinakamuraku",
    "gn:name":"Kasumorichou",
    "iso:country":"JP",
    "wof:name":"453-0855",
    "wof:placetype":"postalcode"
},
  "geometry": {"coordinates":[136.85810000000001,35.1537],"type":"Point"}
}