{
  "type": "Feature",
  "properties": {
    "gn:adm1_name":"Shimaneken",
    "gn:adm2_name":"Oodashi",
    "gn:name":"Isotakechou",
    "iso:country":"JP",
    "wof:name":"694-0035",
    "wof:placetype":"postalcode"
},
  "geometry": {"coordinates":[132.42959999999999,35.1861],"type":"Point"}
}