{
  "type": "Feature",
  "properties": {
    "gn:adm1_name":"Kyoutofu",
    "gn:adm2_name":"Kyoutoshiukyouku",
    "gn:name":"Sagamizuoooiwa",
    "iso:country":"JP",
    "wof:name":"616-8467",
    "wof:placetype":"postalcode"
},
  "geometry": {"coordinates":[135.70439999999999,35.0219],"type":"Point"}
}