{
  "type": "Feature",
  "properties": {
    "gn:adm1_name":"Naraken",
    "gn:adm2_name":"Narashi",
    "gn:name":"Narukawachou",
    "iso:country":"JP",
    "wof:name":"630-8335",
    "wof:placetype":"postalcode"
},
  "geometry": {"coordinates":[135.8289,34.6761],"type":"Point"}
}