{
  "type": "Feature",
  "properties": {
    "gn:adm1_name":"Ooitaken",
    "gn:adm2_name":"Naoirigun'Ogimachi",
    "gn:name":"Baba",
    "iso:country":"JP",
    "wof:name":"879-6115",
    "wof:placetype":"postalcode"
},
  "geometry": {"coordinates":[131.2972,32.9273],"type":"Point"}
}