{
  "type": "Feature",
  "properties": {
    "gn:adm1_name":"Ishikawaken",
    "gn:adm2_name":"Kanazawashi",
    "gn:name":"Yuwakumachi",
    "iso:country":"JP",
    "wof:name":"920-1123",
    "wof:placetype":"postalcode"
},
  "geometry": {"coordinates":[136.75710000000001,36.4861],"type":"Point"}
}