{
  "type": "Feature",
  "properties": {
    "gn:adm1_name":"Saitamaken",
    "gn:adm2_name":"Kodamagunkamikawamachi",
    "gn:name":"Nakaniisato",
    "iso:country":"JP",
    "wof:name":"367-0231",
    "wof:placetype":"postalcode"
},
  "geometry": {"coordinates":[139.0958,36.2093],"type":"Point"}
}