{
  "type": "Feature",
  "properties": {
    "gn:adm1_name":"Shizuokaken",
    "gn:adm2_name":"Kamogunkawaduchou",
    "gn:name":"Shimosagano",
    "iso:country":"JP",
    "wof:name":"413-0506",
    "wof:placetype":"postalcode"
},
  "geometry": {"coordinates":[138.96010000000001,34.7733],"type":"Point"}
}