{
  "type": "Feature",
  "properties": {
    "gn:adm1_name":"Hiroshimaken",
    "gn:adm2_name":"Kamoguntoyosakachou",
    "gn:name":"Befu",
    "iso:country":"JP",
    "wof:name":"724-0302",
    "wof:placetype":"postalcode"
},
  "geometry": {"coordinates":[132.79900000000001,34.578],"type":"Point"}
}