{
  "type": "Feature",
  "properties": {
    "gn:adm1_name":"Saitamaken",
    "gn:adm2_name":"Satteshi",
    "gn:name":"Higashi",
    "iso:country":"JP",
    "wof:name":"340-0114",
    "wof:placetype":"postalcode"
},
  "geometry": {"coordinates":[139.72569999999999,36.0751],"type":"Point"}
}