{
  "type": "Feature",
  "properties": {
    "gn:adm1_name":"Fukushimaken",
    "gn:adm2_name":"Iwakishi",
    "gn:name":"Tabitomachitabiuto(Mizunomiba)",
    "iso:country":"JP",
    "wof:name":"974-0252",
    "wof:placetype":"postalcode"
},
  "geometry": {"coordinates":[140.5966,36.9514],"type":"Point"}
}