{
  "type": "Feature",
  "properties": {
    "gn:adm1_name":"Wakayamaken",
    "gn:adm2_name":"Hidakagunyurachou",
    "gn:name":"Naka",
    "iso:country":"JP",
    "wof:name":"649-1102",
    "wof:placetype":"postalcode"
},
  "geometry": {"coordinates":[135.1386,33.9748],"type":"Point"}
}