{
  "type": "Feature",
  "properties": {
    "gn:adm1_name":"Miyazakiken",
    "gn:adm2_name":"Nobeokashi",
    "gn:name":"Hagimachi",
    "iso:country":"JP",
    "wof:name":"882-0052",
    "wof:placetype":"postalcode"
},
  "geometry": {"coordinates":[131.67160000000001,32.5917],"type":"Point"}
}