{
  "type": "Feature",
  "properties": {
    "gn:adm1_name":"Naraken",
    "gn:adm2_name":"Narashi",
    "gn:name":"Kainotsukachou",
    "iso:country":"JP",
    "wof:name":"630-8142",
    "wof:placetype":"postalcode"
},
  "geometry": {"coordinates":[135.8305,34.6697],"type":"Point"}
}