{
  "type": "Feature",
  "properties": {
    "gn:adm1_name":"Ibarakiken",
    "gn:adm2_name":"Inashikigunsakuragawamura",
    "gn:name":"Shimomawatashi",
    "iso:country":"JP",
    "wof:name":"300-0642",
    "wof:placetype":"postalcode"
},
  "geometry": {"coordinates":[140.40539999999999,35.9735],"type":"Point"}
}