{
  "type": "Feature",
  "properties": {
    "gn:adm1_name":"Fukushimaken",
    "gn:adm2_name":"Dategundatemachi",
    "gn:name":"Shiwadamae",
    "iso:country":"JP",
    "wof:name":"960-0454",
    "wof:placetype":"postalcode"
},
  "geometry": {"coordinates":[140.4907,37.8161],"type":"Point"}
}