{
  "type": "Feature",
  "properties": {
    "gn:adm1_name":"Niigataken",
    "gn:adm2_name":"Minamiuonumagunshiozawamachi",
    "gn:name":"Edayoshi",
    "iso:country":"JP",
    "wof:name":"949-6544",
    "wof:placetype":"postalcode"
},
  "geometry": {"coordinates":[138.8794,37.0269],"type":"Point"}
}