{
  "type": "Feature",
  "properties": {
    "gn:adm1_name":"Fukuiken",
    "gn:adm2_name":"Obamashi",
    "gn:name":"Obamatatsuta",
    "iso:country":"JP",
    "wof:name":"917-0064",
    "wof:placetype":"postalcode"
},
  "geometry": {"coordinates":[135.7422,35.4941],"type":"Point"}
}