{
  "type": "Feature",
  "properties": {
    "gn:adm1_name":"Oosakafu",
    "gn:adm2_name":"Ibarakishi",
    "gn:name":"Fujinosato",
    "iso:country":"JP",
    "wof:name":"567-0054",
    "wof:placetype":"postalcode"
},
  "geometry": {"coordinates":[135.54169999999999,34.8381],"type":"Point"}
}