{
  "type": "Feature",
  "properties": {
    "gn:adm1_name":"Niigataken",
    "gn:adm2_name":"Kashiwazakishi",
    "gn:name":"Satougaikeshinden",
    "iso:country":"JP",
    "wof:name":"945-1354",
    "wof:placetype":"postalcode"
},
  "geometry": {"coordinates":[138.59280000000001,37.3495],"type":"Point"}
}