{
  "type": "Feature",
  "properties": {
    "gn:adm1_name":"Tochigiken",
    "gn:adm2_name":"Yaitashi",
    "gn:name":"Kataoka",
    "iso:country":"JP",
    "wof:name":"329-1571",
    "wof:placetype":"postalcode"
},
  "geometry": {"coordinates":[139.9442,36.7635],"type":"Point"}
}