{
  "type": "Feature",
  "properties": {
    "gn:adm1_name":"Tokushimaken",
    "gn:adm2_name":"Nakagunkitouson",
    "gn:name":"Suke",
    "iso:country":"JP",
    "wof:name":"771-6401",
    "wof:placetype":"postalcode"
},
  "geometry": {"coordinates":[134.22319999999999,33.7959],"type":"Point"}
}