{
  "type": "Feature",
  "properties": {
    "gn:adm1_name":"Yamaguchiken",
    "gn:adm2_name":"Yanaishi",
    "gn:name":"Yota",
    "iso:country":"JP",
    "wof:name":"742-0034",
    "wof:placetype":"postalcode"
},
  "geometry": {"coordinates":[132.0703,33.9705],"type":"Point"}
}