{
  "type": "Feature",
  "properties": {
    "gn:adm1_name":"Shizuokaken",
    "gn:adm2_name":"Ogasagun'Ogasachou",
    "gn:name":"Motsuki",
    "iso:country":"JP",
    "wof:name":"437-1511",
    "wof:placetype":"postalcode"
},
  "geometry": {"coordinates":[138.1129,34.7111],"type":"Point"}
}