{
  "type": "Feature",
  "properties": {
    "gn:adm1_name":"Aichiken",
    "gn:adm2_name":"Setoshi",
    "gn:name":"Hazamachou",
    "iso:country":"JP",
    "wof:name":"489-0852",
    "wof:placetype":"postalcode"
},
  "geometry": {"coordinates":[137.13290000000001,35.2187],"type":"Point"}
}