{
  "type": "Feature",
  "properties": {
    "gn:adm1_name":"Kyoutofu",
    "gn:adm2_name":"Kyoutoshisakyouku",
    "gn:name":"Tanakaminamiookubochou",
    "iso:country":"JP",
    "wof:name":"606-8214",
    "wof:placetype":"postalcode"
},
  "geometry": {"coordinates":[135.77979999999999,35.0349],"type":"Point"}
}