{
  "type": "Feature",
  "properties": {
    "gn:adm1_name":"Fukushimaken",
    "gn:adm2_name":"Nihonmatsushi",
    "gn:name":"Harasesekishita",
    "iso:country":"JP",
    "wof:name":"964-0034",
    "wof:placetype":"postalcode"
},
  "geometry": {"coordinates":[140.38810000000001,37.59],"type":"Point"}
}