{
  "type": "Feature",
  "properties": {
    "gn:adm1_name":"Ibarakiken",
    "gn:adm2_name":"Torideshi",
    "gn:name":"Nonoi",
    "iso:country":"JP",
    "wof:name":"302-0032",
    "wof:placetype":"postalcode"
},
  "geometry": {"coordinates":[140.03479999999999,35.9186],"type":"Point"}
}