{
  "type": "Feature",
  "properties": {
    "gn:adm1_name":"Fukuiken",
    "gn:adm2_name":"Oonoshi",
    "gn:name":"Hashidume",
    "iso:country":"JP",
    "wof:name":"912-0141",
    "wof:placetype":"postalcode"
},
  "geometry": {"coordinates":[136.58349999999999,35.9979],"type":"Point"}
}