{
  "type": "Feature",
  "properties": {
    "gn:adm1_name":"Fukuokaken",
    "gn:adm2_name":"Kitakyuushuushikokurakitaku",
    "gn:name":"Tokiwamachi",
    "iso:country":"JP",
    "wof:name":"802-0035",
    "wof:placetype":"postalcode"
},
  "geometry": {"coordinates":[130.90639999999999,33.8803],"type":"Point"}
}