{
  "type": "Feature",
  "properties": {
    "gn:adm1_name":"Hiroshimaken",
    "gn:adm2_name":"Hiroshimashihigashiku",
    "gn:name":"Kaminukushina",
    "iso:country":"JP",
    "wof:name":"732-0032",
    "wof:placetype":"postalcode"
},
  "geometry": {"coordinates":[132.51570000000001,34.4249],"type":"Point"}
}