{
  "type": "Feature",
  "properties": {
    "gn:adm1_name":"Kyoutofu",
    "gn:adm2_name":"Nakagunmineyamachou",
    "gn:name":"Konishi",
    "iso:country":"JP",
    "wof:name":"627-0044",
    "wof:placetype":"postalcode"
},
  "geometry": {"coordinates":[135.03149999999999,35.6142],"type":"Point"}
}