{
  "type": "Feature",
  "properties": {
    "gn:adm1_name":"Hyougoken",
    "gn:adm2_name":"Kinosakiguntakenochou",
    "gn:name":"Takuhi",
    "iso:country":"JP",
    "wof:name":"669-6203",
    "wof:placetype":"postalcode"
},
  "geometry": {"coordinates":[134.79470000000001,35.6656],"type":"Point"}
}