{
  "type": "Feature",
  "properties": {
    "gn:adm1_name":"Kyoutofu",
    "gn:adm2_name":"Kyoutoshifushimiku",
    "gn:name":"Daigoshinmachiuramachi",
    "iso:country":"JP",
    "wof:name":"601-1326",
    "wof:placetype":"postalcode"
},
  "geometry": {"coordinates":[135.81649999999999,34.9564],"type":"Point"}
}