{
  "type": "Feature",
  "properties": {
    "gn:adm1_name":"Okinawaken",
    "gn:adm2_name":"Kunigamigunnakijinson",
    "gn:name":"Kamiunten",
    "iso:country":"JP",
    "wof:name":"905-0404",
    "wof:placetype":"postalcode"
},
  "geometry": {"coordinates":[127.996,26.6812],"type":"Point"}
}