{
  "type": "Feature",
  "properties": {
    "gn:adm1_name":"Miyazakiken",
    "gn:adm2_name":"Hyuugashi",
    "gn:name":"Shinseichou",
    "iso:country":"JP",
    "wof:name":"883-0013",
    "wof:placetype":"postalcode"
},
  "geometry": {"coordinates":[131.63390000000001,32.4205],"type":"Point"}
}