{
  "type": "Feature",
  "properties": {
    "gn:adm1_name":"Niigataken",
    "gn:adm2_name":"Kashiwazakishi",
    "gn:name":"Taya",
    "iso:country":"JP",
    "wof:name":"945-1248",
    "wof:placetype":"postalcode"
},
  "geometry": {"coordinates":[138.5514,37.28],"type":"Point"}
}