{
  "type": "Feature",
  "properties": {
    "gn:adm1_name":"Shimaneken",
    "gn:adm2_name":"Nakagunkanagichou",
    "gn:name":"Haza",
    "iso:country":"JP",
    "wof:name":"697-0211",
    "wof:placetype":"postalcode"
},
  "geometry": {"coordinates":[132.17869999999999,34.7612],"type":"Point"}
}