{
  "type": "Feature",
  "properties": {
    "gn:adm1_name":"Ooitaken",
    "gn:adm2_name":"Usashi",
    "gn:name":"Imani",
    "iso:country":"JP",
    "wof:name":"879-0234",
    "wof:placetype":"postalcode"
},
  "geometry": {"coordinates":[131.2705,33.5338],"type":"Point"}
}