{
  "type": "Feature",
  "properties": {
    "gn:adm1_name":"Shigaken",
    "gn:adm2_name":"Ootsushi",
    "gn:name":"Inadu",
    "iso:country":"JP",
    "wof:name":"520-2271",
    "wof:placetype":"postalcode"
},
  "geometry": {"coordinates":[135.9161,34.9466],"type":"Point"}
}