{
  "type": "Feature",
  "properties": {
    "gn:adm1_name":"Yamaguchiken",
    "gn:adm2_name":"Onodashi",
    "gn:name":"Kitamatsuchigou",
    "iso:country":"JP",
    "wof:name":"756-0007",
    "wof:placetype":"postalcode"
},
  "geometry": {"coordinates":[131.2174,34.0236],"type":"Point"}
}