{
  "type": "Feature",
  "properties": {
    "gn:adm1_name":"Naraken",
    "gn:adm2_name":"Takaichiguntakatorichou",
    "gn:name":"Shimizutani",
    "iso:country":"JP",
    "wof:name":"635-0103",
    "wof:placetype":"postalcode"
},
  "geometry": {"coordinates":[135.7998,34.4381],"type":"Point"}
}