{
  "type": "Feature",
  "properties": {
    "gn:adm1_name":"Ibarakiken",
    "gn:adm2_name":"Nakagun'Ogawamura",
    "gn:name":"Ooiwa",
    "iso:country":"JP",
    "wof:name":"319-2418",
    "wof:placetype":"postalcode"
},
  "geometry": {"coordinates":[140.2544,36.6323],"type":"Point"}
}