{
  "type": "Feature",
  "properties": {
    "gn:adm1_name":"Gunmaken",
    "gn:adm2_name":"Nittagun'Ojimamachi",
    "gn:name":"Ootachi",
    "iso:country":"JP",
    "wof:name":"370-0423",
    "wof:placetype":"postalcode"
},
  "geometry": {"coordinates":[139.29939999999999,36.2522],"type":"Point"}
}