{
  "type": "Feature",
  "properties": {
    "gn:adm1_name":"Miyagiken",
    "gn:adm2_name":"Motoyoshigun'Utatsuchou",
    "gn:name":"Hiratana",
    "iso:country":"JP",
    "wof:name":"988-0421",
    "wof:placetype":"postalcode"
},
  "geometry": {"coordinates":[141.5608,38.7371],"type":"Point"}
}