{
  "type": "Feature",
  "properties": {
    "gn:adm1_name":"Naganoken",
    "gn:adm2_name":"Nakanoshi",
    "gn:name":"Higashiyama",
    "iso:country":"JP",
    "wof:name":"383-0024",
    "wof:placetype":"postalcode"
},
  "geometry": {"coordinates":[138.37950000000001,36.745],"type":"Point"}
}