{
  "type": "Feature",
  "properties": {
    "gn:adm1_name":"Fukuiken",
    "gn:adm2_name":"Katsuyamashi",
    "gn:name":"Yoshinochou",
    "iso:country":"JP",
    "wof:name":"911-0032",
    "wof:placetype":"postalcode"
},
  "geometry": {"coordinates":[136.50139999999999,36.0668],"type":"Point"}
}