{
  "type": "Feature",
  "properties": {
    "gn:adm1_name":"Kanagawaken",
    "gn:adm2_name":"Kamakurashi",
    "gn:name":"Nishikamakura",
    "iso:country":"JP",
    "wof:name":"248-0035",
    "wof:placetype":"postalcode"
},
  "geometry": {"coordinates":[139.50139999999999,35.3215],"type":"Point"}
}