{
  "type": "Feature",
  "properties": {
    "gn:adm1_name":"Wakayamaken",
    "gn:adm2_name":"Nagagun'Iwadechou",
    "gn:name":"Sakaidani",
    "iso:country":"JP",
    "wof:name":"649-6251",
    "wof:placetype":"postalcode"
},
  "geometry": {"coordinates":[135.2783,34.3077],"type":"Point"}
}