{
  "type": "Feature",
  "properties": {
    "gn:adm1_name":"Toyamaken",
    "gn:adm2_name":"Neigunyatsuomachi",
    "gn:name":"Nishimachi",
    "iso:country":"JP",
    "wof:name":"939-2355",
    "wof:placetype":"postalcode"
},
  "geometry": {"coordinates":[137.136,36.5784],"type":"Point"}
}