{
  "type": "Feature",
  "properties": {
    "gn:adm1_name":"Shizuokaken",
    "gn:adm2_name":"Shizuokashi",
    "gn:name":"Shimizumiho",
    "iso:country":"JP",
    "wof:name":"424-0901",
    "wof:placetype":"postalcode"
},
  "geometry": {"coordinates":[138.5188,35.0038],"type":"Point"}
}