{
  "type": "Feature",
  "properties": {
    "gn:adm1_name":"Sagaken",
    "gn:adm2_name":"Sagagunyamatochou",
    "gn:name":"Kawakami",
    "iso:country":"JP",
    "wof:name":"840-0214",
    "wof:placetype":"postalcode"
},
  "geometry": {"coordinates":[130.2586,33.3164],"type":"Point"}
}