{
  "type": "Feature",
  "properties": {
    "gn:adm1_name":"Hyougoken",
    "gn:adm2_name":"Koubeshinishiku",
    "gn:name":"Oshibedanichoukobata",
    "iso:country":"JP",
    "wof:name":"651-2221",
    "wof:placetype":"postalcode"
},
  "geometry": {"coordinates":[135.06819999999999,34.7484],"type":"Point"}
}