{
  "type": "Feature",
  "properties": {
    "gn:adm1_name":"Gifuken",
    "gn:adm2_name":"Oogakishi",
    "gn:name":"Kasanuichou",
    "iso:country":"JP",
    "wof:name":"503-0027",
    "wof:placetype":"postalcode"
},
  "geometry": {"coordinates":[136.6046,35.3763],"type":"Point"}
}