{
  "type": "Feature",
  "properties": {
    "gn:adm1_name":"Toukyouto",
    "gn:adm2_name":"Itabashiku",
    "gn:name":"Wakagi",
    "iso:country":"JP",
    "wof:name":"174-0065",
    "wof:placetype":"postalcode"
},
  "geometry": {"coordinates":[139.67339999999999,35.77],"type":"Point"}
}