{
  "type": "Feature",
  "properties": {
    "gn:adm1_name":"Kyoutofu",
    "gn:adm2_name":"Kyoutoshiyamashinaku",
    "gn:name":"Nishinoyamakakenouechou",
    "iso:country":"JP",
    "wof:name":"607-8302",
    "wof:placetype":"postalcode"
},
  "geometry": {"coordinates":[135.8014,34.9755],"type":"Point"}
}