{
  "type": "Feature",
  "properties": {
    "gn:adm1_name":"Ibarakiken",
    "gn:adm2_name":"Hitachiootashi",
    "gn:name":"Sawamechou",
    "iso:country":"JP",
    "wof:name":"313-0032",
    "wof:placetype":"postalcode"
},
  "geometry": {"coordinates":[140.55160000000001,36.5149],"type":"Point"}
}