{
  "type": "Feature",
  "properties": {
    "gn:adm1_name":"Kumamotoken",
    "gn:adm2_name":"Yatsushirogunryuuhokumachi",
    "gn:name":"Kawahara",
    "iso:country":"JP",
    "wof:name":"869-4806",
    "wof:placetype":"postalcode"
},
  "geometry": {"coordinates":[130.68620000000001,32.5567],"type":"Point"}
}