{
  "type": "Feature",
  "properties": {
    "gn:adm1_name":"Mieken",
    "gn:adm2_name":"Tsushi",
    "gn:name":"Handa",
    "iso:country":"JP",
    "wof:name":"514-0823",
    "wof:placetype":"postalcode"
},
  "geometry": {"coordinates":[136.49600000000001,34.705],"type":"Point"}
}