{
  "type": "Feature",
  "properties": {
    "gn:adm1_name":"Kagoshimaken",
    "gn:adm2_name":"Akuneshi",
    "gn:name":"Wakimoto",
    "iso:country":"JP",
    "wof:name":"899-1131",
    "wof:placetype":"postalcode"
},
  "geometry": {"coordinates":[130.19990000000001,32.0876],"type":"Point"}
}