{
  "type": "Feature",
  "properties": {
    "gn:adm1_name":"Ehimeken",
    "gn:adm2_name":"Kitauwaguntsushimachou",
    "gn:name":"Naru",
    "iso:country":"JP",
    "wof:name":"798-3333",
    "wof:placetype":"postalcode"
},
  "geometry": {"coordinates":[132.4273,33.0563],"type":"Point"}
}