{
  "type": "Feature",
  "properties": {
    "gn:adm1_name":"Fukuiken",
    "gn:adm2_name":"Sakaigunkanaduchou",
    "gn:name":"Furuyaishiduka",
    "iso:country":"JP",
    "wof:name":"919-0613",
    "wof:placetype":"postalcode"
},
  "geometry": {"coordinates":[136.2587,36.1847],"type":"Point"}
}