{
  "type": "Feature",
  "properties": {
    "gn:adm1_name":"Okayamaken",
    "gn:adm2_name":"Odagunyakagechou",
    "gn:name":"Obayashi",
    "iso:country":"JP",
    "wof:name":"714-1202",
    "wof:placetype":"postalcode"
},
  "geometry": {"coordinates":[133.58199999999999,34.6301],"type":"Point"}
}