{
  "type": "Feature",
  "properties": {
    "gn:adm1_name":"Aichiken",
    "gn:adm2_name":"Higashikamogun'Asukechou",
    "gn:name":"Hosoda",
    "iso:country":"JP",
    "wof:name":"444-2503",
    "wof:placetype":"postalcode"
},
  "geometry": {"coordinates":[137.3665,35.169],"type":"Point"}
}