{
  "type": "Feature",
  "properties": {
    "gn:adm1_name":"Miyagiken",
    "gn:adm2_name":"Kamigunkamimachi",
    "gn:name":"Ipponyanagi",
    "iso:country":"JP",
    "wof:name":"981-4274",
    "wof:placetype":"postalcode"
},
  "geometry": {"coordinates":[140.85050000000001,38.5732],"type":"Point"}
}