{
  "type": "Feature",
  "properties": {
    "gn:adm1_name":"Kanagawaken",
    "gn:adm2_name":"Odawarashi",
    "gn:name":"Yanagishinden",
    "iso:country":"JP",
    "wof:name":"250-0857",
    "wof:placetype":"postalcode"
},
  "geometry": {"coordinates":[139.1405,35.2966],"type":"Point"}
}