{
  "type": "Feature",
  "properties": {
    "gn:adm1_name":"Shimaneken",
    "gn:adm2_name":"Iishigunkakeyamachi",
    "gn:name":"Anami",
    "iso:country":"JP",
    "wof:name":"690-2704",
    "wof:placetype":"postalcode"
},
  "geometry": {"coordinates":[132.76390000000001,35.173],"type":"Point"}
}