{
  "type": "Feature",
  "properties": {
    "gn:adm1_name":"Ishikawaken",
    "gn:adm2_name":"Kahokuguntakamatsumachi",
    "gn:name":"Setomachi",
    "iso:country":"JP",
    "wof:name":"929-1208",
    "wof:placetype":"postalcode"
},
  "geometry": {"coordinates":[136.75309999999999,36.779],"type":"Point"}
}