{
  "type": "Feature",
  "properties": {
    "gn:adm1_name":"Ishikawaken",
    "gn:adm2_name":"Fugeshigunnotomachi",
    "gn:name":"Ukawa",
    "iso:country":"JP",
    "wof:name":"927-0302",
    "wof:placetype":"postalcode"
},
  "geometry": {"coordinates":[137.08439999999999,37.2546],"type":"Point"}
}