{
  "type": "Feature",
  "properties": {
    "gn:adm1_name":"Oosakafu",
    "gn:adm2_name":"Higashioosakashi",
    "gn:name":"Tamakushichounishi",
    "iso:country":"JP",
    "wof:name":"578-0934",
    "wof:placetype":"postalcode"
},
  "geometry": {"coordinates":[135.61529999999999,34.6541],"type":"Point"}
}