{
  "type": "Feature",
  "properties": {
    "gn:adm1_name":"Gunmaken",
    "gn:adm2_name":"Maebashishi",
    "gn:name":"Izumisawamachi",
    "iso:country":"JP",
    "wof:name":"379-2101",
    "wof:placetype":"postalcode"
},
  "geometry": {"coordinates":[139.16290000000001,36.3968],"type":"Point"}
}