{
  "type": "Feature",
  "properties": {
    "gn:adm1_name":"Shimaneken",
    "gn:adm2_name":"Hikawagunhikawachou",
    "gn:name":"Nakanosu",
    "iso:country":"JP",
    "wof:name":"699-0552",
    "wof:placetype":"postalcode"
},
  "geometry": {"coordinates":[132.8485,35.4063],"type":"Point"}
}