{
  "type": "Feature",
  "properties": {
    "gn:adm1_name":"Aichiken",
    "gn:adm2_name":"Toyohashishi",
    "gn:name":"Umeyabuchou",
    "iso:country":"JP",
    "wof:name":"441-0155",
    "wof:placetype":"postalcode"
},
  "geometry": {"coordinates":[137.327,34.7907],"type":"Point"}
}