{
  "type": "Feature",
  "properties": {
    "gn:adm1_name":"Fukushimaken",
    "gn:adm2_name":"Nihonmatsushi",
    "gn:name":"Kakurezato",
    "iso:country":"JP",
    "wof:name":"964-0842",
    "wof:placetype":"postalcode"
},
  "geometry": {"coordinates":[140.41560000000001,37.5474],"type":"Point"}
}