{
  "type": "Feature",
  "properties": {
    "gn:adm1_name":"Hyougoken",
    "gn:adm2_name":"Nishinomiyashi",
    "gn:name":"Tsutoootsukachou",
    "iso:country":"JP",
    "wof:name":"663-8241",
    "wof:placetype":"postalcode"
},
  "geometry": {"coordinates":[135.3537,34.7376],"type":"Point"}
}