{
  "type": "Feature",
  "properties": {
    "gn:adm1_name":"Kumamotoken",
    "gn:adm2_name":"Tamanaguntensuimachi",
    "gn:name":"Ota",
    "iso:country":"JP",
    "wof:name":"861-5406",
    "wof:placetype":"postalcode"
},
  "geometry": {"coordinates":[130.59899999999999,32.8831],"type":"Point"}
}