{
  "type": "Feature",
  "properties": {
    "gn:adm1_name":"Oosakafu",
    "gn:adm2_name":"Hirakatashi",
    "gn:name":"Indachou",
    "iso:country":"JP",
    "wof:name":"573-0017",
    "wof:placetype":"postalcode"
},
  "geometry": {"coordinates":[135.66560000000001,34.8049],"type":"Point"}
}