{
  "type": "Feature",
  "properties": {
    "gn:adm1_name":"Shigaken",
    "gn:adm2_name":"Ikagunyogochou",
    "gn:name":"Nakanogou",
    "iso:country":"JP",
    "wof:name":"529-0515",
    "wof:placetype":"postalcode"
},
  "geometry": {"coordinates":[136.2073,35.5435],"type":"Point"}
}