{
  "type": "Feature",
  "properties": {
    "gn:adm1_name":"Kanagawaken",
    "gn:adm2_name":"Fujisawashi",
    "gn:name":"Hatori",
    "iso:country":"JP",
    "wof:name":"251-0056",
    "wof:placetype":"postalcode"
},
  "geometry": {"coordinates":[139.45779999999999,35.3443],"type":"Point"}
}