{
  "type": "Feature",
  "properties": {
    "gn:adm1_name":"Fukuokaken",
    "gn:adm2_name":"Kitakyuushuushiwakamatsuku",
    "gn:name":"Youjakumachi",
    "iso:country":"JP",
    "wof:name":"808-0077",
    "wof:placetype":"postalcode"
},
  "geometry": {"coordinates":[130.77000000000001,33.8933],"type":"Point"}
}