{
  "type": "Feature",
  "properties": {
    "gn:adm1_name":"Toukyouto",
    "gn:adm2_name":"Hachioujishi",
    "gn:name":"Teramachi",
    "iso:country":"JP",
    "wof:name":"192-0073",
    "wof:placetype":"postalcode"
},
  "geometry": {"coordinates":[139.3331,35.6566],"type":"Point"}
}