{
  "type": "Feature",
  "properties": {
    "gn:adm1_name":"Miyazakiken",
    "gn:adm2_name":"Koyuguntakanabechou",
    "gn:name":"Uwae",
    "iso:country":"JP",
    "wof:name":"884-0006",
    "wof:placetype":"postalcode"
},
  "geometry": {"coordinates":[131.4939,32.1385],"type":"Point"}
}