{
  "type": "Feature",
  "properties": {
    "gn:adm1_name":"Aichiken",
    "gn:adm2_name":"Inazawashi",
    "gn:name":"Kouwasumiyoshichou",
    "iso:country":"JP",
    "wof:name":"492-8107",
    "wof:placetype":"postalcode"
},
  "geometry": {"coordinates":[136.80510000000001,35.2706],"type":"Point"}
}