{
  "type": "Feature",
  "properties": {
    "gn:adm1_name":"Naganoken",
    "gn:adm2_name":"Uedashi",
    "gn:name":"Uedahara",
    "iso:country":"JP",
    "wof:name":"386-1102",
    "wof:placetype":"postalcode"
},
  "geometry": {"coordinates":[138.22309999999999,36.3899],"type":"Point"}
}