{
  "type": "Feature",
  "properties": {
    "gn:adm1_name":"Fukuiken",
    "gn:adm2_name":"Mikatagunmikatachou",
    "gn:name":"Ueno",
    "iso:country":"JP",
    "wof:name":"919-1321",
    "wof:placetype":"postalcode"
},
  "geometry": {"coordinates":[135.90260000000001,35.5074],"type":"Point"}
}