{
  "type": "Feature",
  "properties": {
    "gn:adm1_name":"Saitamaken",
    "gn:adm2_name":"Kawagoeshi",
    "gn:name":"Hiratsuka",
    "iso:country":"JP",
    "wof:name":"350-0814",
    "wof:placetype":"postalcode"
},
  "geometry": {"coordinates":[139.46440000000001,35.9448],"type":"Point"}
}