{
  "type": "Feature",
  "properties": {
    "gn:adm1_name":"Aichiken",
    "gn:adm2_name":"Kariyashi",
    "gn:name":"Kumanochou",
    "iso:country":"JP",
    "wof:name":"448-0831",
    "wof:placetype":"postalcode"
},
  "geometry": {"coordinates":[136.9889,34.9958],"type":"Point"}
}