{
  "type": "Feature",
  "properties": {
    "gn:adm1_name":"Miyagiken",
    "gn:adm2_name":"Motoyoshigunkarakuwachou",
    "gn:name":"Kosaba",
    "iso:country":"JP",
    "wof:name":"988-0561",
    "wof:placetype":"postalcode"
},
  "geometry": {"coordinates":[141.64760000000001,38.886],"type":"Point"}
}