{
  "type": "Feature",
  "properties": {
    "gn:adm1_name":"Ibarakiken",
    "gn:adm2_name":"Kashimashi",
    "gn:name":"Shizaki",
    "iso:country":"JP",
    "wof:name":"311-2207",
    "wof:placetype":"postalcode"
},
  "geometry": {"coordinates":[140.58160000000001,36.0659],"type":"Point"}
}