{
  "type": "Feature",
  "properties": {
    "gn:adm1_name":"Kyoutofu",
    "gn:adm2_name":"Ayabeshi",
    "gn:name":"Honguuchou",
    "iso:country":"JP",
    "wof:name":"623-0036",
    "wof:placetype":"postalcode"
},
  "geometry": {"coordinates":[135.26140000000001,35.295],"type":"Point"}
}