{
  "type": "Feature",
  "properties": {
    "gn:adm1_name":"Toukyouto",
    "gn:adm2_name":"Adachiku",
    "gn:name":"Senjukawarachou",
    "iso:country":"JP",
    "wof:name":"120-0037",
    "wof:placetype":"postalcode"
},
  "geometry": {"coordinates":[139.79900000000001,35.7428],"type":"Point"}
}