{
  "type": "Feature",
  "properties": {
    "gn:adm1_name":"Tottoriken",
    "gn:adm2_name":"Yazugunhattouchou",
    "gn:name":"Kaihara",
    "iso:country":"JP",
    "wof:name":"680-0533",
    "wof:placetype":"postalcode"
},
  "geometry": {"coordinates":[134.3416,35.3556],"type":"Point"}
}