{
  "type": "Feature",
  "properties": {
    "gn:adm1_name":"Fukushimaken",
    "gn:adm2_name":"Ishikawagun'Ishikawamachi",
    "gn:name":"Shimonouchi",
    "iso:country":"JP",
    "wof:name":"963-7828",
    "wof:placetype":"postalcode"
},
  "geometry": {"coordinates":[140.41149999999999,37.1681],"type":"Point"}
}