{
  "type": "Feature",
  "properties": {
    "gn:adm1_name":"Aichiken",
    "gn:adm2_name":"Toyotashi",
    "gn:name":"Miwachou",
    "iso:country":"JP",
    "wof:name":"471-0007",
    "wof:placetype":"postalcode"
},
  "geometry": {"coordinates":[137.19319999999999,35.1007],"type":"Point"}
}