{
  "type": "Feature",
  "properties": {
    "gn:adm1_name":"Hyougoken",
    "gn:adm2_name":"Nishinomiyashi",
    "gn:name":"Okuhata",
    "iso:country":"JP",
    "wof:name":"662-0022",
    "wof:placetype":"postalcode"
},
  "geometry": {"coordinates":[135.33619999999999,34.7528],"type":"Point"}
}