{
  "type": "Feature",
  "properties": {
    "gn:adm1_name":"Kagawaken",
    "gn:adm2_name":"Takamatsushi",
    "gn:name":"Chuuouchou",
    "iso:country":"JP",
    "wof:name":"760-0007",
    "wof:placetype":"postalcode"
},
  "geometry": {"coordinates":[134.04499999999999,34.3364],"type":"Point"}
}