{
  "type": "Feature",
  "properties": {
    "gn:adm1_name":"Hiroshimaken",
    "gn:adm2_name":"Toyotagunyutakamachi",
    "gn:name":"Oochou",
    "iso:country":"JP",
    "wof:name":"734-0301",
    "wof:placetype":"postalcode"
},
  "geometry": {"coordinates":[132.8553,34.1823],"type":"Point"}
}