{
  "type": "Feature",
  "properties": {
    "gn:adm1_name":"Chibaken",
    "gn:adm2_name":"Mobarashi",
    "gn:name":"Yoshiishimo",
    "iso:country":"JP",
    "wof:name":"299-4121",
    "wof:placetype":"postalcode"
},
  "geometry": {"coordinates":[140.29150000000001,35.4854],"type":"Point"}
}