{
  "type": "Feature",
  "properties": {
    "gn:adm1_name":"Aichiken",
    "gn:adm2_name":"Inazawashi",
    "gn:name":"Nakanokawabatachou",
    "iso:country":"JP",
    "wof:name":"492-8391",
    "wof:placetype":"postalcode"
},
  "geometry": {"coordinates":[136.75839999999999,35.2513],"type":"Point"}
}