{
  "type": "Feature",
  "properties": {
    "gn:adm1_name":"Chibaken",
    "gn:adm2_name":"Ichiharashi",
    "gn:name":"Shiroganechou",
    "iso:country":"JP",
    "wof:name":"290-0059",
    "wof:placetype":"postalcode"
},
  "geometry": {"coordinates":[140.10220000000001,35.5271],"type":"Point"}
}