{
  "type": "Feature",
  "properties": {
    "gn:adm1_name":"Kyoutofu",
    "gn:adm2_name":"Kyoutoshisakyouku",
    "gn:name":"Iwakuraminamioosagichou",
    "iso:country":"JP",
    "wof:name":"606-0003",
    "wof:placetype":"postalcode"
},
  "geometry": {"coordinates":[135.7861,35.0626],"type":"Point"}
}