{
  "type": "Feature",
  "properties": {
    "gn:adm1_name":"Gifuken",
    "gn:adm2_name":"Tajimishi",
    "gn:name":"Himechou",
    "iso:country":"JP",
    "wof:name":"507-0061",
    "wof:placetype":"postalcode"
},
  "geometry": {"coordinates":[137.06800000000001,35.39],"type":"Point"}
}