{
  "type": "Feature",
  "properties": {
    "gn:adm1_name":"Chibaken",
    "gn:adm2_name":"Chouseigunchounanmachi",
    "gn:name":"Fukasawa",
    "iso:country":"JP",
    "wof:name":"297-0124",
    "wof:placetype":"postalcode"
},
  "geometry": {"coordinates":[140.20930000000001,35.3969],"type":"Point"}
}