{
  "type": "Feature",
  "properties": {
    "gn:adm1_name":"Niigataken",
    "gn:adm2_name":"Tochioshi",
    "gn:name":"Yamadachou",
    "iso:country":"JP",
    "wof:name":"940-0213",
    "wof:placetype":"postalcode"
},
  "geometry": {"coordinates":[138.98699999999999,37.4822],"type":"Point"}
}