{
  "type": "Feature",
  "properties": {
    "gn:adm1_name":"Tochigiken",
    "gn:adm2_name":"Mookashi",
    "gn:name":"Daimachi",
    "iso:country":"JP",
    "wof:name":"321-4306",
    "wof:placetype":"postalcode"
},
  "geometry": {"coordinates":[140.00450000000001,36.4401],"type":"Point"}
}