{
  "type": "Feature",
  "properties": {
    "gn:adm1_name":"Ooitaken",
    "gn:adm2_name":"Usagun'Innaimachi",
    "gn:name":"Kuriyama",
    "iso:country":"JP",
    "wof:name":"872-0456",
    "wof:placetype":"postalcode"
},
  "geometry": {"coordinates":[131.3039,33.3706],"type":"Point"}
}