{
  "type": "Feature",
  "properties": {
    "gn:adm1_name":"Hyougoken",
    "gn:adm2_name":"Koubeshihyougoku",
    "gn:name":"Minamisakasegawachou",
    "iso:country":"JP",
    "wof:name":"652-0893",
    "wof:placetype":"postalcode"
},
  "geometry": {"coordinates":[135.17099999999999,34.6667],"type":"Point"}
}