{
  "type": "Feature",
  "properties": {
    "gn:adm1_name":"Fukuokaken",
    "gn:adm2_name":"Ookawashi",
    "gn:name":"Kuami",
    "iso:country":"JP",
    "wof:name":"831-0042",
    "wof:placetype":"postalcode"
},
  "geometry": {"coordinates":[130.3639,33.1981],"type":"Point"}
}