{
  "type": "Feature",
  "properties": {
    "gn:adm1_name":"Toukyouto",
    "gn:adm2_name":"Shinjukuku",
    "gn:name":"Shinanomachi",
    "iso:country":"JP",
    "wof:name":"160-0016",
    "wof:placetype":"postalcode"
},
  "geometry": {"coordinates":[139.71979999999999,35.6824],"type":"Point"}
}