{
  "type": "Feature",
  "properties": {
    "gn:adm1_name":"Wakayamaken",
    "gn:adm2_name":"Wakayamashi",
    "gn:name":"Tsuhada",
    "iso:country":"JP",
    "wof:name":"640-8315",
    "wof:placetype":"postalcode"
},
  "geometry": {"coordinates":[135.20500000000001,34.2209],"type":"Point"}
}