{
  "type": "Feature",
  "properties": {
    "gn:adm1_name":"Shizuokaken",
    "gn:adm2_name":"Iwataguntatsuyamamura",
    "gn:name":"Tokura",
    "iso:country":"JP",
    "wof:name":"431-3803",
    "wof:placetype":"postalcode"
},
  "geometry": {"coordinates":[137.83430000000001,34.9721],"type":"Point"}
}