{
  "type": "Feature",
  "properties": {
    "gn:adm1_name":"Chibaken",
    "gn:adm2_name":"Ichiharashi",
    "gn:name":"Chigusa",
    "iso:country":"JP",
    "wof:name":"299-0109",
    "wof:placetype":"postalcode"
},
  "geometry": {"coordinates":[140.0523,35.4964],"type":"Point"}
}