{
  "type": "Feature",
  "properties": {
    "gn:adm1_name":"Nagasakiken",
    "gn:adm2_name":"Kitamatsuuraguntabirachou",
    "gn:name":"Nodamen",
    "iso:country":"JP",
    "wof:name":"859-4826",
    "wof:placetype":"postalcode"
},
  "geometry": {"coordinates":[129.57239999999999,33.3744],"type":"Point"}
}