{
  "type": "Feature",
  "properties": {
    "gn:adm1_name":"Shizuokaken",
    "gn:adm2_name":"Kosaishi",
    "gn:name":"Oochiba",
    "iso:country":"JP",
    "wof:name":"431-0403",
    "wof:placetype":"postalcode"
},
  "geometry": {"coordinates":[137.5061,34.7601],"type":"Point"}
}