{
  "type": "Feature",
  "properties": {
    "gn:adm1_name":"Aichiken",
    "gn:adm2_name":"Nakashimagunheiwachou",
    "gn:name":"Yokoike",
    "iso:country":"JP",
    "wof:name":"490-1313",
    "wof:placetype":"postalcode"
},
  "geometry": {"coordinates":[136.73759999999999,35.2147],"type":"Point"}
}