{
  "type": "Feature",
  "properties": {
    "gn:adm1_name":"Aichiken",
    "gn:adm2_name":"Iwakurashi",
    "gn:name":"Nakanochou",
    "iso:country":"JP",
    "wof:name":"482-0046",
    "wof:placetype":"postalcode"
},
  "geometry": {"coordinates":[136.87090000000001,35.2883],"type":"Point"}
}