{
  "type": "Feature",
  "properties": {
    "gn:adm1_name":"Toyamaken",
    "gn:adm2_name":"Uodushi",
    "gn:name":"Daikaijino",
    "iso:country":"JP",
    "wof:name":"937-0816",
    "wof:placetype":"postalcode"
},
  "geometry": {"coordinates":[137.42230000000001,36.8092],"type":"Point"}
}