{
  "type": "Feature",
  "properties": {
    "gn:adm1_name":"Chibaken",
    "gn:adm2_name":"Kimitsushi",
    "gn:name":"Ogisaku",
    "iso:country":"JP",
    "wof:name":"292-1156",
    "wof:placetype":"postalcode"
},
  "geometry": {"coordinates":[139.96700000000001,35.2844],"type":"Point"}
}