{
  "type": "Feature",
  "properties": {
    "gn:adm1_name":"Gunmaken",
    "gn:adm2_name":"Ootashi",
    "gn:name":"Sugashiochou",
    "iso:country":"JP",
    "wof:name":"373-0002",
    "wof:placetype":"postalcode"
},
  "geometry": {"coordinates":[139.33770000000001,36.3432],"type":"Point"}
}