{
  "type": "Feature",
  "properties": {
    "gn:adm1_name":"Toyamaken",
    "gn:adm2_name":"Takaokashi",
    "gn:name":"Toideichinose",
    "iso:country":"JP",
    "wof:name":"939-1101",
    "wof:placetype":"postalcode"
},
  "geometry": {"coordinates":[136.983,36.697],"type":"Point"}
}