{
  "type": "Feature",
  "properties": {
    "gn:adm1_name":"Hyougoken",
    "gn:adm2_name":"Sasayamashi",
    "gn:name":"Inoue",
    "iso:country":"JP",
    "wof:name":"669-2416",
    "wof:placetype":"postalcode"
},
  "geometry": {"coordinates":[135.29300000000001,35.0705],"type":"Point"}
}