{
  "type": "Feature",
  "properties": {
    "gn:adm1_name":"Kanagawaken",
    "gn:adm2_name":"Yokohamashiasahiku",
    "gn:name":"Imagawachou",
    "iso:country":"JP",
    "wof:name":"241-0033",
    "wof:placetype":"postalcode"
},
  "geometry": {"coordinates":[139.53649999999999,35.4756],"type":"Point"}
}