{
  "type": "Feature",
  "properties": {
    "gn:adm1_name":"Ooitaken",
    "gn:adm2_name":"Nishikunisakigunmatamamachi",
    "gn:name":"Usuno",
    "iso:country":"JP",
    "wof:name":"872-1107",
    "wof:placetype":"postalcode"
},
  "geometry": {"coordinates":[131.4905,33.6272],"type":"Point"}
}