{
  "type": "Feature",
  "properties": {
    "gn:adm1_name":"Shimaneken",
    "gn:adm2_name":"Masudashi",
    "gn:name":"Nakazuchou",
    "iso:country":"JP",
    "wof:name":"698-0044",
    "wof:placetype":"postalcode"
},
  "geometry": {"coordinates":[131.83529999999999,34.6979],"type":"Point"}
}