{
  "type": "Feature",
  "properties": {
    "gn:adm1_name":"Okayamaken",
    "gn:adm2_name":"Aidagunmimasakachou",
    "gn:name":"Shimokayama",
    "iso:country":"JP",
    "wof:name":"707-0016",
    "wof:placetype":"postalcode"
},
  "geometry": {"coordinates":[134.1635,35.0422],"type":"Point"}
}