{
  "type": "Feature",
  "properties": {
    "gn:adm1_name":"Chibaken",
    "gn:adm2_name":"Narashinoshi",
    "gn:name":"Hanasaki",
    "iso:country":"JP",
    "wof:name":"275-0013",
    "wof:placetype":"postalcode"
},
  "geometry": {"coordinates":[140.04669999999999,35.6797],"type":"Point"}
}