{
  "type": "Feature",
  "properties": {
    "gn:adm1_name":"Gunmaken",
    "gn:adm2_name":"Tomiokashi",
    "gn:name":"Nanjai",
    "iso:country":"JP",
    "wof:name":"370-2464",
    "wof:placetype":"postalcode"
},
  "geometry": {"coordinates":[138.8092,36.2349],"type":"Point"}
}