{
  "type": "Feature",
  "properties": {
    "gn:adm1_name":"Aichiken",
    "gn:adm2_name":"Nagoyashishouwaku",
    "gn:name":"Touhatachou",
    "iso:country":"JP",
    "wof:name":"466-0014",
    "wof:placetype":"postalcode"
},
  "geometry": {"coordinates":[136.92959999999999,35.1505],"type":"Point"}
}