{
  "type": "Feature",
  "properties": {
    "gn:adm1_name":"Saitamaken",
    "gn:adm2_name":"Yoshikawashi",
    "gn:name":"Komatsugawa",
    "iso:country":"JP",
    "wof:name":"342-0043",
    "wof:placetype":"postalcode"
},
  "geometry": {"coordinates":[139.86330000000001,35.8838],"type":"Point"}
}