{
  "type": "Feature",
  "properties": {
    "gn:adm1_name":"Tochigiken",
    "gn:adm2_name":"Ashikagashi",
    "gn:name":"Yukiwachou",
    "iso:country":"JP",
    "wof:name":"326-0804",
    "wof:placetype":"postalcode"
},
  "geometry": {"coordinates":[139.4485,36.3378],"type":"Point"}
}