{
  "type": "Feature",
  "properties": {
    "gn:adm1_name":"Niigataken",
    "gn:adm2_name":"Nagaokashi",
    "gn:name":"Kaminozokimachi",
    "iso:country":"JP",
    "wof:name":"940-2033",
    "wof:placetype":"postalcode"
},
  "geometry": {"coordinates":[138.7852,37.4503],"type":"Point"}
}