{
  "type": "Feature",
  "properties": {
    "gn:adm1_name":"Kyoutofu",
    "gn:adm2_name":"Fukuchiyamashi",
    "gn:name":"Shimooochi",
    "iso:country":"JP",
    "wof:name":"620-0912",
    "wof:placetype":"postalcode"
},
  "geometry": {"coordinates":[135.08170000000001,35.3377],"type":"Point"}
}