{
  "type": "Feature",
  "properties": {
    "gn:adm1_name":"Hyougoken",
    "gn:adm2_name":"Nishinomiyashi",
    "gn:name":"Najiosakuradai",
    "iso:country":"JP",
    "wof:name":"669-1146",
    "wof:placetype":"postalcode"
},
  "geometry": {"coordinates":[135.27809999999999,34.8375],"type":"Point"}
}