{
  "type": "Feature",
  "properties": {
    "gn:adm1_name":"Kanagawaken",
    "gn:adm2_name":"Yokohamashiisogoku",
    "gn:name":"Kaminakazatochou",
    "iso:country":"JP",
    "wof:name":"235-0042",
    "wof:placetype":"postalcode"
},
  "geometry": {"coordinates":[139.61150000000001,35.3709],"type":"Point"}
}