{
  "type": "Feature",
  "properties": {
    "gn:adm1_name":"Ehimeken",
    "gn:adm2_name":"Touyoshi",
    "gn:name":"Kawanouchi",
    "iso:country":"JP",
    "wof:name":"799-1314",
    "wof:placetype":"postalcode"
},
  "geometry": {"coordinates":[133.02359999999999,33.934],"type":"Point"}
}