{
  "type": "Feature",
  "properties": {
    "gn:adm1_name":"Toyamaken",
    "gn:adm2_name":"Nakaniikawagunkamiichimachi",
    "gn:name":"Shimokyouden",
    "iso:country":"JP",
    "wof:name":"930-0373",
    "wof:placetype":"postalcode"
},
  "geometry": {"coordinates":[137.3382,36.7044],"type":"Point"}
}