{
  "type": "Feature",
  "properties": {
    "gn:adm1_name":"Fukuokaken",
    "gn:adm2_name":"Oomutashi",
    "gn:name":"Kuranaga",
    "iso:country":"JP",
    "wof:name":"837-0906",
    "wof:placetype":"postalcode"
},
  "geometry": {"coordinates":[130.4597,33.0796],"type":"Point"}
}