{
  "type": "Feature",
  "properties": {
    "gn:adm1_name":"Aichiken",
    "gn:adm2_name":"Nagoyashimeitouku",
    "gn:name":"Fujimakichou",
    "iso:country":"JP",
    "wof:name":"465-0075",
    "wof:placetype":"postalcode"
},
  "geometry": {"coordinates":[136.9881,35.151],"type":"Point"}
}