{
  "type": "Feature",
  "properties": {
    "gn:adm1_name":"Niigataken",
    "gn:adm2_name":"Nakauonumaguntsunanmachi",
    "gn:name":"Akinari",
    "iso:country":"JP",
    "wof:name":"949-8313",
    "wof:placetype":"postalcode"
},
  "geometry": {"coordinates":[138.66929999999999,36.9681],"type":"Point"}
}