{
  "type": "Feature",
  "properties": {
    "gn:adm1_name":"Kumamotoken",
    "gn:adm2_name":"Yatsushirogunmiyaharamachi",
    "gn:name":"Kakoi",
    "iso:country":"JP",
    "wof:name":"869-4607",
    "wof:placetype":"postalcode"
},
  "geometry": {"coordinates":[130.67670000000001,32.5409],"type":"Point"}
}