{
  "type": "Feature",
  "properties": {
    "gn:adm1_name":"Shigaken",
    "gn:adm2_name":"Nagahamashi",
    "gn:name":"Shimosakahamachou",
    "iso:country":"JP",
    "wof:name":"526-0047",
    "wof:placetype":"postalcode"
},
  "geometry": {"coordinates":[136.27500000000001,35.367],"type":"Point"}
}