{
  "type": "Feature",
  "properties": {
    "gn:adm1_name":"Niigataken",
    "gn:adm2_name":"Minamikanbaragunshitadamura",
    "gn:name":"Nagasawa",
    "iso:country":"JP",
    "wof:name":"955-0157",
    "wof:placetype":"postalcode"
},
  "geometry": {"coordinates":[139.01679999999999,37.5556],"type":"Point"}
}