{
  "type": "Feature",
  "properties": {
    "gn:adm1_name":"Toyamaken",
    "gn:adm2_name":"Toyamashi",
    "gn:name":"Eirakuchou",
    "iso:country":"JP",
    "wof:name":"930-0853",
    "wof:placetype":"postalcode"
},
  "geometry": {"coordinates":[137.22190000000001,36.7042],"type":"Point"}
}