{
  "type": "Feature",
  "properties": {
    "gn:adm1_name":"Niigataken",
    "gn:adm2_name":"Kariwagun'Ogunimachi",
    "gn:name":"Houzaka",
    "iso:country":"JP",
    "wof:name":"949-5213",
    "wof:placetype":"postalcode"
},
  "geometry": {"coordinates":[138.71029999999999,37.3035],"type":"Point"}
}