{
  "type": "Feature",
  "properties": {
    "gn:adm1_name":"Miyazakiken",
    "gn:adm2_name":"Ebinoshi",
    "gn:name":"Okamatsu",
    "iso:country":"JP",
    "wof:name":"889-4161",
    "wof:placetype":"postalcode"
},
  "geometry": {"coordinates":[130.75120000000001,32.0477],"type":"Point"}
}