{
  "type": "Feature",
  "properties": {
    "gn:adm1_name":"Oosakafu",
    "gn:adm2_name":"Hirakatashi",
    "gn:name":"Kuzuhanoda",
    "iso:country":"JP",
    "wof:name":"573-1103",
    "wof:placetype":"postalcode"
},
  "geometry": {"coordinates":[135.68539999999999,34.8671],"type":"Point"}
}