{
  "type": "Feature",
  "properties": {
    "gn:adm1_name":"Oosakafu",
    "gn:adm2_name":"Daitoushi",
    "gn:name":"Shinmachi",
    "iso:country":"JP",
    "wof:name":"574-0037",
    "wof:placetype":"postalcode"
},
  "geometry": {"coordinates":[135.6232,34.7046],"type":"Point"}
}