{
  "type": "Feature",
  "properties": {
    "gn:adm1_name":"Aichiken",
    "gn:adm2_name":"Setoshi",
    "gn:name":"Sakaemachi",
    "iso:country":"JP",
    "wof:name":"489-0044",
    "wof:placetype":"postalcode"
},
  "geometry": {"coordinates":[137.09960000000001,35.226],"type":"Point"}
}