{
  "type": "Feature",
  "properties": {
    "gn:adm1_name":"Shigaken",
    "gn:adm2_name":"Koukagunkoukachou",
    "gn:name":"Jinbo",
    "iso:country":"JP",
    "wof:name":"520-3404",
    "wof:placetype":"postalcode"
},
  "geometry": {"coordinates":[136.20959999999999,34.9305],"type":"Point"}
}