{
  "type": "Feature",
  "properties": {
    "gn:adm1_name":"Fukuokaken",
    "gn:adm2_name":"Oomutashi",
    "gn:name":"Shinchimachi",
    "iso:country":"JP",
    "wof:name":"836-0032",
    "wof:placetype":"postalcode"
},
  "geometry": {"coordinates":[130.43690000000001,33.0334],"type":"Point"}
}