{
  "type": "Feature",
  "properties": {
    "gn:adm1_name":"Niigataken",
    "gn:adm2_name":"Kashiwazakishi",
    "gn:name":"Nakahama",
    "iso:country":"JP",
    "wof:name":"945-0852",
    "wof:placetype":"postalcode"
},
  "geometry": {"coordinates":[138.5412,37.364],"type":"Point"}
}