{
  "type": "Feature",
  "properties": {
    "gn:adm1_name":"Hyougoken",
    "gn:adm2_name":"Mikatagunhamasakachou",
    "gn:name":"Mio",
    "iso:country":"JP",
    "wof:name":"669-6715",
    "wof:placetype":"postalcode"
},
  "geometry": {"coordinates":[134.51070000000001,35.6537],"type":"Point"}
}