{
  "type": "Feature",
  "properties": {
    "gn:adm1_name":"Ibarakiken",
    "gn:adm2_name":"Higashiibarakigun'Ibarakimachi",
    "gn:name":"Sobahara",
    "iso:country":"JP",
    "wof:name":"311-3105",
    "wof:placetype":"postalcode"
},
  "geometry": {"coordinates":[140.3989,36.2998],"type":"Point"}
}