{
  "type": "Feature",
  "properties": {
    "gn:adm1_name":"Nagasakiken",
    "gn:adm2_name":"Nagasakishi",
    "gn:name":"Chikugomachi",
    "iso:country":"JP",
    "wof:name":"850-0052",
    "wof:placetype":"postalcode"
},
  "geometry": {"coordinates":[129.87469999999999,32.7528],"type":"Point"}
}