{
  "type": "Feature",
  "properties": {
    "gn:adm1_name":"Shigaken",
    "gn:adm2_name":"Kanzakigun'Eigenjichou",
    "gn:name":"Kimigahata",
    "iso:country":"JP",
    "wof:name":"527-0202",
    "wof:placetype":"postalcode"
},
  "geometry": {"coordinates":[136.38560000000001,35.1379],"type":"Point"}
}