{
  "type": "Feature",
  "properties": {
    "gn:adm1_name":"Hyougoken",
    "gn:adm2_name":"Sandashi",
    "gn:name":"Aioichou",
    "iso:country":"JP",
    "wof:name":"669-1526",
    "wof:placetype":"postalcode"
},
  "geometry": {"coordinates":[135.22810000000001,34.8827],"type":"Point"}
}