{
  "type": "Feature",
  "properties": {
    "gn:adm1_name":"Shimaneken",
    "gn:adm2_name":"Oochigun'Oochichou",
    "gn:name":"Kasubuchi",
    "iso:country":"JP",
    "wof:name":"699-4621",
    "wof:placetype":"postalcode"
},
  "geometry": {"coordinates":[132.59119999999999,35.0764],"type":"Point"}
}