{
  "type": "Feature",
  "properties": {
    "gn:adm1_name":"Saitamaken",
    "gn:adm2_name":"Kumagayashi",
    "gn:name":"Miyachou",
    "iso:country":"JP",
    "wof:name":"360-0041",
    "wof:placetype":"postalcode"
},
  "geometry": {"coordinates":[139.3871,36.1466],"type":"Point"}
}