{
  "type": "Feature",
  "properties": {
    "gn:adm1_name":"Aichiken",
    "gn:adm2_name":"Toyotashi",
    "gn:name":"Koshidochou",
    "iso:country":"JP",
    "wof:name":"470-0332",
    "wof:placetype":"postalcode"
},
  "geometry": {"coordinates":[137.18279999999999,35.1077],"type":"Point"}
}