{
  "type": "Feature",
  "properties": {
    "gn:adm1_name":"Yamaguchiken",
    "gn:adm2_name":"Abugunfukueson",
    "gn:name":"Fukuikami",
    "iso:country":"JP",
    "wof:name":"758-0211",
    "wof:placetype":"postalcode"
},
  "geometry": {"coordinates":[131.5215,34.4104],"type":"Point"}
}