{
  "type": "Feature",
  "properties": {
    "gn:adm1_name":"Shigaken",
    "gn:adm2_name":"Higashiazaigunkohokuchou",
    "gn:name":"Gujou",
    "iso:country":"JP",
    "wof:name":"529-0312",
    "wof:placetype":"postalcode"
},
  "geometry": {"coordinates":[136.26589999999999,35.4525],"type":"Point"}
}