{
  "type": "Feature",
  "properties": {
    "gn:adm1_name":"Kumamotoken",
    "gn:adm2_name":"Yatsushirogunmiyaharamachi",
    "gn:name":"Ikanikeisaiganaibaai",
    "iso:country":"JP",
    "wof:name":"869-4600",
    "wof:placetype":"postalcode"
},
  "geometry": {"coordinates":[130.67910000000001,32.5688],"type":"Point"}
}