{
  "type": "Feature",
  "properties": {
    "gn:adm1_name":"Gunmaken",
    "gn:adm2_name":"Nittagunnittamachi",
    "gn:name":"Kokin",
    "iso:country":"JP",
    "wof:name":"370-0302",
    "wof:placetype":"postalcode"
},
  "geometry": {"coordinates":[139.32210000000001,36.3337],"type":"Point"}
}