{
  "type": "Feature",
  "properties": {
    "gn:adm1_name":"Fukuokaken",
    "gn:adm2_name":"Kurategunkotakemachi",
    "gn:name":"Naradu",
    "iso:country":"JP",
    "wof:name":"820-1106",
    "wof:placetype":"postalcode"
},
  "geometry": {"coordinates":[130.7037,33.7197],"type":"Point"}
}