{
  "type": "Feature",
  "properties": {
    "gn:adm1_name":"Yamaguchiken",
    "gn:adm2_name":"Houfushi",
    "gn:name":"Kamimigita",
    "iso:country":"JP",
    "wof:name":"747-0062",
    "wof:placetype":"postalcode"
},
  "geometry": {"coordinates":[131.5735,34.0846],"type":"Point"}
}