{
  "type": "Feature",
  "properties": {
    "gn:adm1_name":"Fukuokaken",
    "gn:adm2_name":"Ukihagunyoshiimachi",
    "gn:name":"Ikuha",
    "iso:country":"JP",
    "wof:name":"839-1342",
    "wof:placetype":"postalcode"
},
  "geometry": {"coordinates":[130.73570000000001,33.348],"type":"Point"}
}