{
  "type": "Feature",
  "properties": {
    "gn:adm1_name":"Hyougoken",
    "gn:adm2_name":"Toyookashi",
    "gn:name":"Miyajima",
    "iso:country":"JP",
    "wof:name":"668-0016",
    "wof:placetype":"postalcode"
},
  "geometry": {"coordinates":[134.8186,35.5568],"type":"Point"}
}