{
  "type": "Feature",
  "properties": {
    "gn:adm1_name":"Yamagataken",
    "gn:adm2_name":"Nanyoushi",
    "gn:name":"Kawatoi",
    "iso:country":"JP",
    "wof:name":"999-2204",
    "wof:placetype":"postalcode"
},
  "geometry": {"coordinates":[140.1884,38.088],"type":"Point"}
}