{
  "type": "Feature",
  "properties": {
    "gn:adm1_name":"Okinawaken",
    "gn:adm2_name":"Urasoeshi",
    "gn:name":"Maeda",
    "iso:country":"JP",
    "wof:name":"901-2102",
    "wof:placetype":"postalcode"
},
  "geometry": {"coordinates":[127.73609999999999,26.2414],"type":"Point"}
}