{
  "type": "Feature",
  "properties": {
    "gn:adm1_name":"Tokushimaken",
    "gn:adm2_name":"Nakagunkisawason",
    "gn:name":"Adue",
    "iso:country":"JP",
    "wof:name":"771-6101",
    "wof:placetype":"postalcode"
},
  "geometry": {"coordinates":[134.29509999999999,33.8487],"type":"Point"}
}