{
  "type": "Feature",
  "properties": {
    "gn:adm1_name":"Oosakafu",
    "gn:adm2_name":"Oosakashihigashisumiyoshiku",
    "gn:name":"Tanabe",
    "iso:country":"JP",
    "wof:name":"546-0031",
    "wof:placetype":"postalcode"
},
  "geometry": {"coordinates":[135.5264,34.6256],"type":"Point"}
}