{
  "type": "Feature",
  "properties": {
    "gn:adm1_name":"Hiroshimaken",
    "gn:adm2_name":"Akigunfuchuuchou",
    "gn:name":"Shinchi",
    "iso:country":"JP",
    "wof:name":"735-0028",
    "wof:placetype":"postalcode"
},
  "geometry": {"coordinates":[132.50110000000001,34.3832],"type":"Point"}
}