{
  "type": "Feature",
  "properties": {
    "gn:adm1_name":"Ehimeken",
    "gn:adm2_name":"Iyoguntobechou",
    "gn:name":"Takouda(Sonota)",
    "iso:country":"JP",
    "wof:name":"791-2101",
    "wof:placetype":"postalcode"
},
  "geometry": {"coordinates":[132.7945,33.7807],"type":"Point"}
}