{
  "type": "Feature",
  "properties": {
    "gn:adm1_name":"Oosakafu",
    "gn:adm2_name":"Moriguchishi",
    "gn:name":"Raikouchou",
    "iso:country":"JP",
    "wof:name":"570-0029",
    "wof:placetype":"postalcode"
},
  "geometry": {"coordinates":[135.56659999999999,34.7382],"type":"Point"}
}