{
  "type": "Feature",
  "properties": {
    "gn:adm1_name":"Okayamaken",
    "gn:adm2_name":"Okayamashi",
    "gn:name":"Nagatoshi",
    "iso:country":"JP",
    "wof:name":"703-8223",
    "wof:placetype":"postalcode"
},
  "geometry": {"coordinates":[133.99780000000001,34.675],"type":"Point"}
}