{
  "type": "Feature",
  "properties": {
    "gn:adm1_name":"Yamanashiken",
    "gn:adm2_name":"Koufushi",
    "gn:name":"Choushoujichou",
    "iso:country":"JP",
    "wof:name":"400-0067",
    "wof:placetype":"postalcode"
},
  "geometry": {"coordinates":[138.54089999999999,35.6671],"type":"Point"}
}