{
  "type": "Feature",
  "properties": {
    "gn:adm1_name":"Chibaken",
    "gn:adm2_name":"Kashiwashi",
    "gn:name":"Higashinakashinjuku",
    "iso:country":"JP",
    "wof:name":"277-0061",
    "wof:placetype":"postalcode"
},
  "geometry": {"coordinates":[139.96190000000001,35.8316],"type":"Point"}
}