{
  "type": "Feature",
  "properties": {
    "gn:adm1_name":"Kyoutofu",
    "gn:adm2_name":"Kyoutoshinakagyouku",
    "gn:name":"Kamikorikichou",
    "iso:country":"JP",
    "wof:name":"604-0923",
    "wof:placetype":"postalcode"
},
  "geometry": {"coordinates":[135.77090000000001,35.0118],"type":"Point"}
}