{
  "type": "Feature",
  "properties": {
    "gn:adm1_name":"Shizuokaken",
    "gn:adm2_name":"Iwatagunryuuyouchou",
    "gn:name":"Matsumoto",
    "iso:country":"JP",
    "wof:name":"438-0206",
    "wof:placetype":"postalcode"
},
  "geometry": {"coordinates":[137.80549999999999,34.6942],"type":"Point"}
}