{
  "type": "Feature",
  "properties": {
    "gn:adm1_name":"Toyamaken",
    "gn:adm2_name":"Takaokashi",
    "gn:name":"Honbo",
    "iso:country":"JP",
    "wof:name":"933-0333",
    "wof:placetype":"postalcode"
},
  "geometry": {"coordinates":[136.97219999999999,36.7103],"type":"Point"}
}