{
  "type": "Feature",
  "properties": {
    "gn:adm1_name":"Aichiken",
    "gn:adm2_name":"Toyotashi",
    "gn:name":"Takahashichou",
    "iso:country":"JP",
    "wof:name":"471-0019",
    "wof:placetype":"postalcode"
},
  "geometry": {"coordinates":[137.1797,35.094],"type":"Point"}
}