{
  "type": "Feature",
  "properties": {
    "gn:adm1_name":"Shizuokaken",
    "gn:adm2_name":"Fujiedashi",
    "gn:name":"Shimonogou",
    "iso:country":"JP",
    "wof:name":"426-0203",
    "wof:placetype":"postalcode"
},
  "geometry": {"coordinates":[138.24459999999999,34.8964],"type":"Point"}
}