{
  "type": "Feature",
  "properties": {
    "gn:adm1_name":"Fukuokaken",
    "gn:adm2_name":"Kitakyuushuushikokurakitaku",
    "gn:name":"Akasakakaigan",
    "iso:country":"JP",
    "wof:name":"802-0031",
    "wof:placetype":"postalcode"
},
  "geometry": {"coordinates":[130.91130000000001,33.8941],"type":"Point"}
}