{
  "type": "Feature",
  "properties": {
    "gn:adm1_name":"Miyagiken",
    "gn:adm2_name":"Ishinomakishi",
    "gn:name":"Hachimanchou",
    "iso:country":"JP",
    "wof:name":"986-0016",
    "wof:placetype":"postalcode"
},
  "geometry": {"coordinates":[141.31370000000001,38.4307],"type":"Point"}
}