{
  "type": "Feature",
  "properties": {
    "gn:adm1_name":"Kumamotoken",
    "gn:adm2_name":"Kumamotoshi",
    "gn:name":"Tarouzakomachi",
    "iso:country":"JP",
    "wof:name":"861-5532",
    "wof:placetype":"postalcode"
},
  "geometry": {"coordinates":[130.6755,32.8612],"type":"Point"}
}