{
  "type": "Feature",
  "properties": {
    "gn:adm1_name":"Shizuokaken",
    "gn:adm2_name":"Hamamatsushi",
    "gn:name":"Joukouchou",
    "iso:country":"JP",
    "wof:name":"431-3103",
    "wof:placetype":"postalcode"
},
  "geometry": {"coordinates":[137.80260000000001,34.7526],"type":"Point"}
}