{
  "type": "Feature",
  "properties": {
    "gn:adm1_name":"Yamanashiken",
    "gn:adm2_name":"Nakakomagunshikishimamachi",
    "gn:name":"Kamezawa(Sonota)",
    "iso:country":"JP",
    "wof:name":"400-1113",
    "wof:placetype":"postalcode"
},
  "geometry": {"coordinates":[138.52590000000001,35.7246],"type":"Point"}
}