{
  "type": "Feature",
  "properties": {
    "gn:adm1_name":"Naganoken",
    "gn:adm2_name":"Matsumotoshi",
    "gn:name":"Hara",
    "iso:country":"JP",
    "wof:name":"390-0316",
    "wof:placetype":"postalcode"
},
  "geometry": {"coordinates":[137.9829,36.2679],"type":"Point"}
}