{
  "type": "Feature",
  "properties": {
    "gn:adm1_name":"Naganoken",
    "gn:adm2_name":"Komaganeshi",
    "gn:name":"Chuuou",
    "iso:country":"JP",
    "wof:name":"399-4112",
    "wof:placetype":"postalcode"
},
  "geometry": {"coordinates":[137.93520000000001,35.7356],"type":"Point"}
}