{
  "type": "Feature",
  "properties": {
    "gn:adm1_name":"Tokushimaken",
    "gn:adm2_name":"Nakagunkisawason",
    "gn:name":"Takano",
    "iso:country":"JP",
    "wof:name":"771-6112",
    "wof:placetype":"postalcode"
},
  "geometry": {"coordinates":[134.30189999999999,33.8597],"type":"Point"}
}