{
  "type": "Feature",
  "properties": {
    "gn:adm1_name":"Miyagiken",
    "gn:adm2_name":"Kuriharagunkannarichou",
    "gn:name":"Nakamachinishiura",
    "iso:country":"JP",
    "wof:name":"989-5145",
    "wof:placetype":"postalcode"
},
  "geometry": {"coordinates":[141.07310000000001,38.8124],"type":"Point"}
}