{
  "type": "Feature",
  "properties": {
    "gn:adm1_name":"Sagaken",
    "gn:adm2_name":"Higashimatsuuragunchinzeichou",
    "gn:name":"Nakano",
    "iso:country":"JP",
    "wof:name":"847-0316",
    "wof:placetype":"postalcode"
},
  "geometry": {"coordinates":[129.90379999999999,33.5304],"type":"Point"}
}