{
  "type": "Feature",
  "properties": {
    "gn:adm1_name":"Ishikawaken",
    "gn:adm2_name":"Kanazawashi",
    "gn:name":"Shimooshiharamachi",
    "iso:country":"JP",
    "wof:name":"920-1323",
    "wof:placetype":"postalcode"
},
  "geometry": {"coordinates":[136.71619999999999,36.4902],"type":"Point"}
}