{
  "type": "Feature",
  "properties": {
    "gn:adm1_name":"Ibarakiken",
    "gn:adm2_name":"Sashimagunsakaimachi",
    "gn:name":"Yamazaki",
    "iso:country":"JP",
    "wof:name":"306-0413",
    "wof:placetype":"postalcode"
},
  "geometry": {"coordinates":[139.8312,36.1225],"type":"Point"}
}