{
  "type": "Feature",
  "properties": {
    "gn:adm1_name":"Naraken",
    "gn:adm2_name":"Tenrishi",
    "gn:name":"Higaichou",
    "iso:country":"JP",
    "wof:name":"632-0054",
    "wof:placetype":"postalcode"
},
  "geometry": {"coordinates":[135.828,34.5563],"type":"Point"}
}