{
  "type": "Feature",
  "properties": {
    "gn:adm1_name":"Gifuken",
    "gn:adm2_name":"Anpachigungoudochou",
    "gn:name":"Shinyashiki",
    "iso:country":"JP",
    "wof:name":"503-2313",
    "wof:placetype":"postalcode"
},
  "geometry": {"coordinates":[136.62389999999999,35.4131],"type":"Point"}
}