{
  "type": "Feature",
  "properties": {
    "gn:adm1_name":"Niigataken",
    "gn:adm2_name":"Santougun'Izumozakimachi",
    "gn:name":"Sawada",
    "iso:country":"JP",
    "wof:name":"949-4351",
    "wof:placetype":"postalcode"
},
  "geometry": {"coordinates":[138.72389999999999,37.545],"type":"Point"}
}