{
  "type": "Feature",
  "properties": {
    "gn:adm1_name":"Aichiken",
    "gn:adm2_name":"Toyohashishi",
    "gn:name":"Hanada2banchou",
    "iso:country":"JP",
    "wof:name":"441-8014",
    "wof:placetype":"postalcode"
},
  "geometry": {"coordinates":[137.37559999999999,34.7623],"type":"Point"}
}