{
  "type": "Feature",
  "properties": {
    "gn:adm1_name":"Shizuokaken",
    "gn:adm2_name":"Numadushi",
    "gn:name":"Senbonminatomachi",
    "iso:country":"JP",
    "wof:name":"410-0845",
    "wof:placetype":"postalcode"
},
  "geometry": {"coordinates":[138.85759999999999,35.0836],"type":"Point"}
}