{
  "type": "Feature",
  "properties": {
    "gn:adm1_name":"Aichiken",
    "gn:adm2_name":"Toyotashi",
    "gn:name":"Naraichou",
    "iso:country":"JP",
    "wof:name":"470-0317",
    "wof:placetype":"postalcode"
},
  "geometry": {"coordinates":[137.23070000000001,35.1283],"type":"Point"}
}