{
  "type": "Feature",
  "properties": {
    "gn:adm1_name":"Naraken",
    "gn:adm2_name":"Ikomagunhegurichou",
    "gn:name":"Ichihara",
    "iso:country":"JP",
    "wof:name":"636-0944",
    "wof:placetype":"postalcode"
},
  "geometry": {"coordinates":[135.69130000000001,34.6475],"type":"Point"}
}