{
  "type": "Feature",
  "properties": {
    "gn:adm1_name":"Kanagawaken",
    "gn:adm2_name":"Zushishi",
    "gn:name":"Shinjuku",
    "iso:country":"JP",
    "wof:name":"249-0007",
    "wof:placetype":"postalcode"
},
  "geometry": {"coordinates":[139.5702,35.2961],"type":"Point"}
}