{
  "type": "Feature",
  "properties": {
    "gn:adm1_name":"Toyamaken",
    "gn:adm2_name":"Uodushi",
    "gn:name":"Kitayama",
    "iso:country":"JP",
    "wof:name":"937-0826",
    "wof:placetype":"postalcode"
},
  "geometry": {"coordinates":[137.44560000000001,36.7753],"type":"Point"}
}