{
  "type": "Feature",
  "properties": {
    "gn:adm1_name":"Shizuokaken",
    "gn:adm2_name":"Haibaragunhonkawanechou",
    "gn:name":"Umeji",
    "iso:country":"JP",
    "wof:name":"428-0401",
    "wof:placetype":"postalcode"
},
  "geometry": {"coordinates":[138.2106,35.1803],"type":"Point"}
}