{
  "type": "Feature",
  "properties": {
    "gn:adm1_name":"Yamanashiken",
    "gn:adm2_name":"Koufushi",
    "gn:name":"Horinouchimachi",
    "iso:country":"JP",
    "wof:name":"400-0056",
    "wof:placetype":"postalcode"
},
  "geometry": {"coordinates":[138.56270000000001,35.6121],"type":"Point"}
}