{
  "type": "Feature",
  "properties": {
    "gn:adm1_name":"Niigataken",
    "gn:adm2_name":"Kashiwazakishi",
    "gn:name":"Onadani",
    "iso:country":"JP",
    "wof:name":"945-1252",
    "wof:placetype":"postalcode"
},
  "geometry": {"coordinates":[138.54820000000001,37.2437],"type":"Point"}
}