{
  "type": "Feature",
  "properties": {
    "gn:adm1_name":"Oosakafu",
    "gn:adm2_name":"Oosakashiyodogawaku",
    "gn:name":"Kikawanishi",
    "iso:country":"JP",
    "wof:name":"532-0013",
    "wof:placetype":"postalcode"
},
  "geometry": {"coordinates":[135.48869999999999,34.724],"type":"Point"}
}