{
  "type": "Feature",
  "properties": {
    "gn:adm1_name":"Kagoshimaken",
    "gn:adm2_name":"Nishinoomoteshi",
    "gn:name":"Higashimachi",
    "iso:country":"JP",
    "wof:name":"891-3113",
    "wof:placetype":"postalcode"
},
  "geometry": {"coordinates":[130.99549999999999,30.7312],"type":"Point"}
}