{
  "type": "Feature",
  "properties": {
    "gn:adm1_name":"Ibarakiken",
    "gn:adm2_name":"Mitoshi",
    "gn:name":"Suifuchou",
    "iso:country":"JP",
    "wof:name":"310-0005",
    "wof:placetype":"postalcode"
},
  "geometry": {"coordinates":[140.4872,36.3796],"type":"Point"}
}