{
  "type": "Feature",
  "properties": {
    "gn:adm1_name":"Ibarakiken",
    "gn:adm2_name":"Sashimagunsashimamachi",
    "gn:name":"Yama",
    "iso:country":"JP",
    "wof:name":"306-0502",
    "wof:placetype":"postalcode"
},
  "geometry": {"coordinates":[139.87620000000001,36.1263],"type":"Point"}
}