{
  "type": "Feature",
  "properties": {
    "gn:adm1_name":"Miyazakiken",
    "gn:adm2_name":"Kushimashi",
    "gn:name":"Akiyama",
    "iso:country":"JP",
    "wof:name":"888-0006",
    "wof:placetype":"postalcode"
},
  "geometry": {"coordinates":[131.27090000000001,31.5064],"type":"Point"}
}