{
  "type": "Feature",
  "properties": {
    "gn:adm1_name":"Niigataken",
    "gn:adm2_name":"Nakakubikigunkakizakimachi",
    "gn:name":"Shimoono",
    "iso:country":"JP",
    "wof:name":"949-3232",
    "wof:placetype":"postalcode"
},
  "geometry": {"coordinates":[138.40889999999999,37.2544],"type":"Point"}
}