{
  "type": "Feature",
  "properties": {
    "gn:adm1_name":"Kyoutofu",
    "gn:adm2_name":"Kyoutoshinishikyouku",
    "gn:name":"Katsurakawadachou",
    "iso:country":"JP",
    "wof:name":"615-8017",
    "wof:placetype":"postalcode"
},
  "geometry": {"coordinates":[135.7062,34.9882],"type":"Point"}
}