{
  "type": "Feature",
  "properties": {
    "gn:adm1_name":"Gunmaken",
    "gn:adm2_name":"Tomiokashi",
    "gn:name":"Kanohara",
    "iso:country":"JP",
    "wof:name":"370-2455",
    "wof:placetype":"postalcode"
},
  "geometry": {"coordinates":[138.8467,36.2428],"type":"Point"}
}