{
  "type": "Feature",
  "properties": {
    "gn:adm1_name":"Chibaken",
    "gn:adm2_name":"Abikoshi",
    "gn:name":"Hibiri",
    "iso:country":"JP",
    "wof:name":"270-1123",
    "wof:placetype":"postalcode"
},
  "geometry": {"coordinates":[140.08959999999999,35.8642],"type":"Point"}
}