{
  "type": "Feature",
  "properties": {
    "gn:adm1_name":"Yamaguchiken",
    "gn:adm2_name":"Mineshi",
    "gn:name":"Toyotamaechoudake",
    "iso:country":"JP",
    "wof:name":"750-0606",
    "wof:placetype":"postalcode"
},
  "geometry": {"coordinates":[131.0959,34.1537],"type":"Point"}
}