{
  "type": "Feature",
  "properties": {
    "gn:adm1_name":"Hiroshimaken",
    "gn:adm2_name":"Shoubarashi",
    "gn:name":"Miyauchichou",
    "iso:country":"JP",
    "wof:name":"727-0007",
    "wof:placetype":"postalcode"
},
  "geometry": {"coordinates":[133.0403,34.8617],"type":"Point"}
}