{
  "type": "Feature",
  "properties": {
    "gn:adm1_name":"Shizuokaken",
    "gn:adm2_name":"Kakegawashi",
    "gn:name":"Higashiyama",
    "iso:country":"JP",
    "wof:name":"436-0001",
    "wof:placetype":"postalcode"
},
  "geometry": {"coordinates":[138.0789,34.8336],"type":"Point"}
}