{
  "type": "Feature",
  "properties": {
    "gn:adm1_name":"Kyoutofu",
    "gn:adm2_name":"Fukuchiyamashi",
    "gn:name":"Okunobe",
    "iso:country":"JP",
    "wof:name":"620-0928",
    "wof:placetype":"postalcode"
},
  "geometry": {"coordinates":[135.09700000000001,35.3099],"type":"Point"}
}