{
  "type": "Feature",
  "properties": {
    "gn:adm1_name":"Yamaguchiken",
    "gn:adm2_name":"Shuunanshi",
    "gn:name":"Yoyogidoori",
    "iso:country":"JP",
    "wof:name":"745-0073",
    "wof:placetype":"postalcode"
},
  "geometry": {"coordinates":[131.8038,34.0551],"type":"Point"}
}