{
  "type": "Feature",
  "properties": {
    "gn:adm1_name":"Aichiken",
    "gn:adm2_name":"Nagoyashiminatoku",
    "gn:name":"Higashichaya",
    "iso:country":"JP",
    "wof:name":"455-0851",
    "wof:placetype":"postalcode"
},
  "geometry": {"coordinates":[136.83160000000001,35.1081],"type":"Point"}
}