{
  "type": "Feature",
  "properties": {
    "gn:adm1_name":"Shigaken",
    "gn:adm2_name":"Gamougunryuuouchou",
    "gn:name":"Tanaka",
    "iso:country":"JP",
    "wof:name":"520-2523",
    "wof:placetype":"postalcode"
},
  "geometry": {"coordinates":[136.13050000000001,35.0575],"type":"Point"}
}