{
  "type": "Feature",
  "properties": {
    "gn:adm1_name":"Tochigiken",
    "gn:adm2_name":"Nasugunnishinasunomachi",
    "gn:name":"Higashimishima",
    "iso:country":"JP",
    "wof:name":"329-2751",
    "wof:placetype":"postalcode"
},
  "geometry": {"coordinates":[139.9778,36.8998],"type":"Point"}
}