{
  "type": "Feature",
  "properties": {
    "gn:adm1_name":"Ishikawaken",
    "gn:adm2_name":"Kagashi",
    "gn:name":"Oosuganamimachi",
    "iso:country":"JP",
    "wof:name":"922-0425",
    "wof:placetype":"postalcode"
},
  "geometry": {"coordinates":[136.3374,36.3188],"type":"Point"}
}