{
  "type": "Feature",
  "properties": {
    "gn:adm1_name":"Hyougoken",
    "gn:adm2_name":"Aioishi",
    "gn:name":"Ooshimachou",
    "iso:country":"JP",
    "wof:name":"678-0052",
    "wof:placetype":"postalcode"
},
  "geometry": {"coordinates":[134.46889999999999,34.8078],"type":"Point"}
}