{
  "type": "Feature",
  "properties": {
    "gn:adm1_name":"Aichiken",
    "gn:adm2_name":"Nagoyashinakaku",
    "gn:name":"Shinsakaemachi",
    "iso:country":"JP",
    "wof:name":"460-0004",
    "wof:placetype":"postalcode"
},
  "geometry": {"coordinates":[136.9109,35.1695],"type":"Point"}
}