{
  "type": "Feature",
  "properties": {
    "gn:adm1_name":"Toyamaken",
    "gn:adm2_name":"Himishi",
    "gn:name":"Minamioomachi",
    "iso:country":"JP",
    "wof:name":"935-0013",
    "wof:placetype":"postalcode"
},
  "geometry": {"coordinates":[136.98920000000001,36.8536],"type":"Point"}
}