{
  "type": "Feature",
  "properties": {
    "gn:adm1_name":"Fukushimaken",
    "gn:adm2_name":"Nihonmatsushi",
    "gn:name":"Ooishigasaku",
    "iso:country":"JP",
    "wof:name":"964-0057",
    "wof:placetype":"postalcode"
},
  "geometry": {"coordinates":[140.36969999999999,37.576],"type":"Point"}
}