{
  "type": "Feature",
  "properties": {
    "gn:adm1_name":"Kyoutofu",
    "gn:adm2_name":"Miyadushi",
    "gn:name":"Kamiseya",
    "iso:country":"JP",
    "wof:name":"626-0227",
    "wof:placetype":"postalcode"
},
  "geometry": {"coordinates":[135.18799999999999,35.6393],"type":"Point"}
}