{
  "type": "Feature",
  "properties": {
    "gn:adm1_name":"Hiroshimaken",
    "gn:adm2_name":"Kamogunkurosechou",
    "gn:name":"Kanesawa",
    "iso:country":"JP",
    "wof:name":"724-0731",
    "wof:placetype":"postalcode"
},
  "geometry": {"coordinates":[132.65020000000001,34.3172],"type":"Point"}
}