{
  "type": "Feature",
  "properties": {
    "gn:adm1_name":"Miyagiken",
    "gn:adm2_name":"Kamigunkamimachi",
    "gn:name":"Torishima",
    "iso:country":"JP",
    "wof:name":"981-4412",
    "wof:placetype":"postalcode"
},
  "geometry": {"coordinates":[140.7989,38.5962],"type":"Point"}
}