{
  "type": "Feature",
  "properties": {
    "gn:adm1_name":"Kanagawaken",
    "gn:adm2_name":"Yokohamashihodogayaku",
    "gn:name":"Fujidukachou",
    "iso:country":"JP",
    "wof:name":"240-0031",
    "wof:placetype":"postalcode"
},
  "geometry": {"coordinates":[139.57470000000001,35.4497],"type":"Point"}
}