{
  "type": "Feature",
  "properties": {
    "gn:adm1_name":"Toyamaken",
    "gn:adm2_name":"Toyamashi",
    "gn:name":"Chuugenjima",
    "iso:country":"JP",
    "wof:name":"930-0921",
    "wof:placetype":"postalcode"
},
  "geometry": {"coordinates":[137.26759999999999,36.6915],"type":"Point"}
}