{
  "type": "Feature",
  "properties": {
    "gn:adm1_name":"Kyoutofu",
    "gn:adm2_name":"Kyoutoshifushimiku",
    "gn:name":"Yokooojimaegawachou",
    "iso:country":"JP",
    "wof:name":"612-8256",
    "wof:placetype":"postalcode"
},
  "geometry": {"coordinates":[135.7637,34.9406],"type":"Point"}
}