{
  "type": "Feature",
  "properties": {
    "gn:adm1_name":"Fukuokaken",
    "gn:adm2_name":"Nakamashi",
    "gn:name":"Asagiri",
    "iso:country":"JP",
    "wof:name":"809-0021",
    "wof:placetype":"postalcode"
},
  "geometry": {"coordinates":[130.7295,33.8179],"type":"Point"}
}