{
  "type": "Feature",
  "properties": {
    "gn:adm1_name":"Kagoshimaken",
    "gn:adm2_name":"Ooshimagun'Ukenson",
    "gn:name":"Yuwan",
    "iso:country":"JP",
    "wof:name":"894-3301",
    "wof:placetype":"postalcode"
},
  "geometry": {"coordinates":[129.30099999999999,28.2773],"type":"Point"}
}