{
  "type": "Feature",
  "properties": {
    "gn:adm1_name":"Saitamaken",
    "gn:adm2_name":"Kitakatsushikagunkurihashimachi",
    "gn:name":"Chuuou",
    "iso:country":"JP",
    "wof:name":"349-1102",
    "wof:placetype":"postalcode"
},
  "geometry": {"coordinates":[139.69890000000001,36.1376],"type":"Point"}
}