{
  "type": "Feature",
  "properties": {
    "gn:adm1_name":"Hyougoken",
    "gn:adm2_name":"Kinosakigunhidakachou",
    "gn:name":"Inotsume",
    "iso:country":"JP",
    "wof:name":"669-5338",
    "wof:placetype":"postalcode"
},
  "geometry": {"coordinates":[134.75710000000001,35.4959],"type":"Point"}
}