{
  "type": "Feature",
  "properties": {
    "gn:adm1_name":"Niigataken",
    "gn:adm2_name":"Kitakanbaragunkurokawamura",
    "gn:name":"Shimoarasawa",
    "iso:country":"JP",
    "wof:name":"959-2816",
    "wof:placetype":"postalcode"
},
  "geometry": {"coordinates":[139.56469999999999,37.9291],"type":"Point"}
}