{
  "type": "Feature",
  "properties": {
    "gn:adm1_name":"Kyoutofu",
    "gn:adm2_name":"Kyoutoshiminamiku",
    "gn:name":"Higashikujounishigoryouchou",
    "iso:country":"JP",
    "wof:name":"601-8042",
    "wof:placetype":"postalcode"
},
  "geometry": {"coordinates":[135.76130000000001,34.9782],"type":"Point"}
}