{
  "type": "Feature",
  "properties": {
    "gn:adm1_name":"Gifuken",
    "gn:adm2_name":"Kakamigaharashi",
    "gn:name":"Nakamaenochou",
    "iso:country":"JP",
    "wof:name":"504-0026",
    "wof:placetype":"postalcode"
},
  "geometry": {"coordinates":[136.83519999999999,35.4086],"type":"Point"}
}