{
  "type": "Feature",
  "properties": {
    "gn:adm1_name":"Miyagiken",
    "gn:adm2_name":"Kesennumashi",
    "gn:name":"Kameyama",
    "iso:country":"JP",
    "wof:name":"988-0607",
    "wof:placetype":"postalcode"
},
  "geometry": {"coordinates":[141.61490000000001,38.8765],"type":"Point"}
}