{
  "type": "Feature",
  "properties": {
    "gn:adm1_name":"Kanagawaken",
    "gn:adm2_name":"Yokohamashitsurumiku",
    "gn:name":"Ushiodachou",
    "iso:country":"JP",
    "wof:name":"230-0041",
    "wof:placetype":"postalcode"
},
  "geometry": {"coordinates":[139.68719999999999,35.5036],"type":"Point"}
}