{
  "type": "Feature",
  "properties": {
    "gn:adm1_name":"Niigataken",
    "gn:adm2_name":"Higashikubikigunyasudukamachi",
    "gn:name":"Yukuno",
    "iso:country":"JP",
    "wof:name":"942-0521",
    "wof:placetype":"postalcode"
},
  "geometry": {"coordinates":[138.48099999999999,37.1099],"type":"Point"}
}