{
  "type": "Feature",
  "properties": {
    "gn:adm1_name":"Fukuokaken",
    "gn:adm2_name":"Fukuokashisawaraku",
    "gn:name":"Hara",
    "iso:country":"JP",
    "wof:name":"814-0022",
    "wof:placetype":"postalcode"
},
  "geometry": {"coordinates":[130.3433,33.5659],"type":"Point"}
}