{
  "type": "Feature",
  "properties": {
    "gn:adm1_name":"Ibarakiken",
    "gn:adm2_name":"Shimotsumashi",
    "gn:name":"Akasu",
    "iso:country":"JP",
    "wof:name":"304-0074",
    "wof:placetype":"postalcode"
},
  "geometry": {"coordinates":[139.935,36.207],"type":"Point"}
}