{
  "type": "Feature",
  "properties": {
    "gn:adm1_name":"Aichiken",
    "gn:adm2_name":"Chitaguntaketoyochou",
    "gn:name":"Ikeda",
    "iso:country":"JP",
    "wof:name":"470-2329",
    "wof:placetype":"postalcode"
},
  "geometry": {"coordinates":[136.9151,34.861],"type":"Point"}
}