{
  "type": "Feature",
  "properties": {
    "gn:adm1_name":"Naraken",
    "gn:adm2_name":"Yoshinogunnishiyoshinomura",
    "gn:name":"Oomine",
    "iso:country":"JP",
    "wof:name":"637-0234",
    "wof:placetype":"postalcode"
},
  "geometry": {"coordinates":[135.78319999999999,34.2742],"type":"Point"}
}