{
  "type": "Feature",
  "properties": {
    "gn:adm1_name":"Kagawaken",
    "gn:adm2_name":"Mitoyogunminochou",
    "gn:name":"Shimotakase",
    "iso:country":"JP",
    "wof:name":"767-0032",
    "wof:placetype":"postalcode"
},
  "geometry": {"coordinates":[133.70509999999999,34.2032],"type":"Point"}
}