{
  "type": "Feature",
  "properties": {
    "gn:adm1_name":"Sagaken",
    "gn:adm2_name":"Higashimatsuuragunchinzeichou",
    "gn:name":"Maruda",
    "iso:country":"JP",
    "wof:name":"847-0311",
    "wof:placetype":"postalcode"
},
  "geometry": {"coordinates":[129.9057,33.5379],"type":"Point"}
}