{
  "type": "Feature",
  "properties": {
    "gn:adm1_name":"Kyoutofu",
    "gn:adm2_name":"Takenoguntangochou",
    "gn:name":"Hata",
    "iso:country":"JP",
    "wof:name":"627-0236",
    "wof:placetype":"postalcode"
},
  "geometry": {"coordinates":[135.1694,35.7357],"type":"Point"}
}