{
  "type": "Feature",
  "properties": {
    "gn:adm1_name":"Fukushimaken",
    "gn:adm2_name":"Adachigunmotomiyamachi",
    "gn:name":"Takagi",
    "iso:country":"JP",
    "wof:name":"969-1101",
    "wof:placetype":"postalcode"
},
  "geometry": {"coordinates":[140.41470000000001,37.5154],"type":"Point"}
}