{
  "type": "Feature",
  "properties": {
    "gn:adm1_name":"Fukuokaken",
    "gn:adm2_name":"Miyakogunsaigawamachi",
    "gn:name":"Inumaru",
    "iso:country":"JP",
    "wof:name":"824-0242",
    "wof:placetype":"postalcode"
},
  "geometry": {"coordinates":[130.96969999999999,33.6329],"type":"Point"}
}