{
  "type": "Feature",
  "properties": {
    "gn:adm1_name":"Oosakafu",
    "gn:adm2_name":"Matsubarashi",
    "gn:name":"Amamihigashi",
    "iso:country":"JP",
    "wof:name":"580-0032",
    "wof:placetype":"postalcode"
},
  "geometry": {"coordinates":[135.53579999999999,34.5889],"type":"Point"}
}