{
  "type": "Feature",
  "properties": {
    "gn:adm1_name":"Yamaguchiken",
    "gn:adm2_name":"Ooshimagun'Ooshimachou",
    "gn:name":"Himi",
    "iso:country":"JP",
    "wof:name":"742-2716",
    "wof:placetype":"postalcode"
},
  "geometry": {"coordinates":[132.1825,33.9027],"type":"Point"}
}