{
  "type": "Feature",
  "properties": {
    "gn:adm1_name":"Hyougoken",
    "gn:adm2_name":"Nishinomiyashi",
    "gn:name":"Nishinomiyahama",
    "iso:country":"JP",
    "wof:name":"662-0934",
    "wof:placetype":"postalcode"
},
  "geometry": {"coordinates":[135.333,34.7152],"type":"Point"}
}