{
  "type": "Feature",
  "properties": {
    "gn:adm1_name":"Oosakafu",
    "gn:adm2_name":"Oosakashiabenoku",
    "gn:name":"Hashimotochou",
    "iso:country":"JP",
    "wof:name":"545-0031",
    "wof:placetype":"postalcode"
},
  "geometry": {"coordinates":[135.5026,34.633],"type":"Point"}
}