{
  "type": "Feature",
  "properties": {
    "gn:adm1_name":"Ishikawaken",
    "gn:adm2_name":"Ishikawaguntsurugimachi",
    "gn:name":"Kamihigashimachi",
    "iso:country":"JP",
    "wof:name":"920-2127",
    "wof:placetype":"postalcode"
},
  "geometry": {"coordinates":[136.62860000000001,36.4474],"type":"Point"}
}