{
  "type": "Feature",
  "properties": {
    "gn:adm1_name":"Aichiken",
    "gn:adm2_name":"Nagoyashichikusaku",
    "gn:name":"Kanarebashi",
    "iso:country":"JP",
    "wof:name":"464-0002",
    "wof:placetype":"postalcode"
},
  "geometry": {"coordinates":[136.98230000000001,35.1903],"type":"Point"}
}