{
  "type": "Feature",
  "properties": {
    "gn:adm1_name":"Aichiken",
    "gn:adm2_name":"Nagoyashiminatoku",
    "gn:name":"Sunamichou",
    "iso:country":"JP",
    "wof:name":"455-0056",
    "wof:placetype":"postalcode"
},
  "geometry": {"coordinates":[136.8682,35.1033],"type":"Point"}
}