{
  "type": "Feature",
  "properties": {
    "gn:adm1_name":"Hyougoken",
    "gn:adm2_name":"Takasagoshi",
    "gn:name":"Yonedadanchi",
    "iso:country":"JP",
    "wof:name":"676-0809",
    "wof:placetype":"postalcode"
},
  "geometry": {"coordinates":[134.8075,34.7821],"type":"Point"}
}