{
  "type": "Feature",
  "properties": {
    "gn:adm1_name":"Shizuokaken",
    "gn:adm2_name":"Suntougunnagaizumichou",
    "gn:name":"Sakuradutsumi",
    "iso:country":"JP",
    "wof:name":"411-0951",
    "wof:placetype":"postalcode"
},
  "geometry": {"coordinates":[138.9058,35.1442],"type":"Point"}
}