{
  "type": "Feature",
  "properties": {
    "gn:adm1_name":"Toukyouto",
    "gn:adm2_name":"Katsushikaku",
    "gn:name":"Kameari",
    "iso:country":"JP",
    "wof:name":"125-0061",
    "wof:placetype":"postalcode"
},
  "geometry": {"coordinates":[139.84790000000001,35.764],"type":"Point"}
}