{
  "type": "Feature",
  "properties": {
    "gn:adm1_name":"Fukuiken",
    "gn:adm2_name":"Onyuugunkaminakachou",
    "gn:name":"Mishouno",
    "iso:country":"JP",
    "wof:name":"919-1511",
    "wof:placetype":"postalcode"
},
  "geometry": {"coordinates":[135.86670000000001,35.5255],"type":"Point"}
}