{
  "type": "Feature",
  "properties": {
    "gn:adm1_name":"Aichiken",
    "gn:adm2_name":"Owariasahishi",
    "gn:name":"Inbamotochoukitajima",
    "iso:country":"JP",
    "wof:name":"488-0842",
    "wof:placetype":"postalcode"
},
  "geometry": {"coordinates":[137.01390000000001,35.2098],"type":"Point"}
}