{
  "type": "Feature",
  "properties": {
    "gn:adm1_name":"Shimaneken",
    "gn:adm2_name":"Oochigundaiwamura",
    "gn:name":"Kamino",
    "iso:country":"JP",
    "wof:name":"696-0702",
    "wof:placetype":"postalcode"
},
  "geometry": {"coordinates":[132.64699999999999,34.9402],"type":"Point"}
}