{
  "type": "Feature",
  "properties": {
    "gn:adm1_name":"Shigaken",
    "gn:adm2_name":"Moriyamashi",
    "gn:name":"Umedachou",
    "iso:country":"JP",
    "wof:name":"524-0037",
    "wof:placetype":"postalcode"
},
  "geometry": {"coordinates":[135.9949,35.0523],"type":"Point"}
}