{
  "type": "Feature",
  "properties": {
    "gn:adm1_name":"Miyagiken",
    "gn:adm2_name":"Kakudashi",
    "gn:name":"Kakuda",
    "iso:country":"JP",
    "wof:name":"981-1505",
    "wof:placetype":"postalcode"
},
  "geometry": {"coordinates":[140.78190000000001,37.974],"type":"Point"}
}