{
  "type": "Feature",
  "properties": {
    "gn:adm1_name":"Hyougoken",
    "gn:adm2_name":"Shisougunyamasakichou",
    "gn:name":"Shimouwara",
    "iso:country":"JP",
    "wof:name":"671-2536",
    "wof:placetype":"postalcode"
},
  "geometry": {"coordinates":[134.55109999999999,34.9567],"type":"Point"}
}