{
  "type": "Feature",
  "properties": {
    "gn:adm1_name":"Tochigiken",
    "gn:adm2_name":"Hagagunmotegimachi",
    "gn:name":"Fukasawa",
    "iso:country":"JP",
    "wof:name":"321-3628",
    "wof:placetype":"postalcode"
},
  "geometry": {"coordinates":[140.16569999999999,36.4419],"type":"Point"}
}