{
  "type": "Feature",
  "properties": {
    "gn:adm1_name":"Fukushimaken",
    "gn:adm2_name":"Nishishirakawagun'Omotegoumura",
    "gn:name":"Nakano",
    "iso:country":"JP",
    "wof:name":"961-0401",
    "wof:placetype":"postalcode"
},
  "geometry": {"coordinates":[140.1831,37.1139],"type":"Point"}
}