{
  "type": "Feature",
  "properties": {
    "gn:adm1_name":"Shigaken",
    "gn:adm2_name":"Takashimagunshin'Asahichou",
    "gn:name":"Kitabata",
    "iso:country":"JP",
    "wof:name":"520-1521",
    "wof:placetype":"postalcode"
},
  "geometry": {"coordinates":[136.03720000000001,35.3503],"type":"Point"}
}