{
  "type": "Feature",
  "properties": {
    "gn:adm1_name":"Sagaken",
    "gn:adm2_name":"Higashimatsuuragunkyuuragimachi",
    "gn:name":"Amagawa",
    "iso:country":"JP",
    "wof:name":"849-3101",
    "wof:placetype":"postalcode"
},
  "geometry": {"coordinates":[130.13409999999999,33.3569],"type":"Point"}
}