{
  "type": "Feature",
  "properties": {
    "gn:adm1_name":"Nagasakiken",
    "gn:adm2_name":"Nagasakishi",
    "gn:name":"Umegasakimachi",
    "iso:country":"JP",
    "wof:name":"850-0909",
    "wof:placetype":"postalcode"
},
  "geometry": {"coordinates":[129.8751,32.74],"type":"Point"}
}