{
  "type": "Feature",
  "properties": {
    "gn:adm1_name":"Ooitaken",
    "gn:adm2_name":"Oonogunmiemachi",
    "gn:name":"Nakaduru",
    "iso:country":"JP",
    "wof:name":"879-7263",
    "wof:placetype":"postalcode"
},
  "geometry": {"coordinates":[131.54390000000001,32.8988],"type":"Point"}
}