{
  "type": "Feature",
  "properties": {
    "gn:adm1_name":"Aichiken",
    "gn:adm2_name":"Amagunsayachou",
    "gn:name":"Hiki",
    "iso:country":"JP",
    "wof:name":"496-0906",
    "wof:placetype":"postalcode"
},
  "geometry": {"coordinates":[136.73099999999999,35.1623],"type":"Point"}
}