{
  "type": "Feature",
  "properties": {
    "gn:adm1_name":"Fukushimaken",
    "gn:adm2_name":"Nihonmatsushi",
    "gn:name":"Takenouchi",
    "iso:country":"JP",
    "wof:name":"964-0958",
    "wof:placetype":"postalcode"
},
  "geometry": {"coordinates":[140.47720000000001,37.5799],"type":"Point"}
}