{
  "type": "Feature",
  "properties": {
    "gn:adm1_name":"Yamagataken",
    "gn:adm2_name":"Kitamurayamagun'Ooishidamachi",
    "gn:name":"Komagome",
    "iso:country":"JP",
    "wof:name":"999-4132",
    "wof:placetype":"postalcode"
},
  "geometry": {"coordinates":[140.3417,38.6265],"type":"Point"}
}