{
  "type": "Feature",
  "properties": {
    "gn:adm1_name":"Sagaken",
    "gn:adm2_name":"Kishimagunshiroishichou",
    "gn:name":"Higashigou",
    "iso:country":"JP",
    "wof:name":"849-1111",
    "wof:placetype":"postalcode"
},
  "geometry": {"coordinates":[130.13679999999999,33.1929],"type":"Point"}
}