{
  "type": "Feature",
  "properties": {
    "gn:adm1_name":"Kagoshimaken",
    "gn:adm2_name":"Satsumagunmiyanojouchou",
    "gn:name":"Tabaru",
    "iso:country":"JP",
    "wof:name":"895-1802",
    "wof:placetype":"postalcode"
},
  "geometry": {"coordinates":[130.4787,31.9142],"type":"Point"}
}