{
  "type": "Feature",
  "properties": {
    "gn:adm1_name":"Niigataken",
    "gn:adm2_name":"Tookamachishi",
    "gn:name":"Kotobukichou",
    "iso:country":"JP",
    "wof:name":"948-0051",
    "wof:placetype":"postalcode"
},
  "geometry": {"coordinates":[138.75380000000001,37.128],"type":"Point"}
}