{
  "type": "Feature",
  "properties": {
    "gn:adm1_name":"Niigataken",
    "gn:adm2_name":"Nakakubikigunkakizakimachi",
    "gn:name":"Asahidaira",
    "iso:country":"JP",
    "wof:name":"949-3363",
    "wof:placetype":"postalcode"
},
  "geometry": {"coordinates":[138.48750000000001,37.2288],"type":"Point"}
}