{
  "type": "Feature",
  "properties": {
    "gn:adm1_name":"Ehimeken",
    "gn:adm2_name":"Yawatahamashi",
    "gn:name":"Katayamachou",
    "iso:country":"JP",
    "wof:name":"796-0065",
    "wof:placetype":"postalcode"
},
  "geometry": {"coordinates":[132.4237,33.459],"type":"Point"}
}