{
  "type": "Feature",
  "properties": {
    "gn:adm1_name":"Okayamaken",
    "gn:adm2_name":"Maniwagunkatsuyamachou",
    "gn:name":"Seitani",
    "iso:country":"JP",
    "wof:name":"717-0737",
    "wof:placetype":"postalcode"
},
  "geometry": {"coordinates":[133.58860000000001,35.091],"type":"Point"}
}