{
  "type": "Feature",
  "properties": {
    "gn:adm1_name":"Fukushimaken",
    "gn:adm2_name":"Ishikawagun'Ishikawamachi",
    "gn:name":"Yanomeda",
    "iso:country":"JP",
    "wof:name":"963-7861",
    "wof:placetype":"postalcode"
},
  "geometry": {"coordinates":[140.45070000000001,37.1483],"type":"Point"}
}