{
  "type": "Feature",
  "properties": {
    "gn:adm1_name":"Niigataken",
    "gn:adm2_name":"Sadogunsawatamachi",
    "gn:name":"Kawaharadasuwamachi",
    "iso:country":"JP",
    "wof:name":"952-1315",
    "wof:placetype":"postalcode"
},
  "geometry": {"coordinates":[138.31559999999999,38.0028],"type":"Point"}
}