{
  "type": "Feature",
  "properties": {
    "gn:adm1_name":"Yamanashiken",
    "gn:adm2_name":"Minamikomagunhayakawachou",
    "gn:name":"Shionoue",
    "iso:country":"JP",
    "wof:name":"409-2721",
    "wof:placetype":"postalcode"
},
  "geometry": {"coordinates":[138.37,35.4329],"type":"Point"}
}