{
  "type": "Feature",
  "properties": {
    "gn:adm1_name":"Shizuokaken",
    "gn:adm2_name":"Yaidushi",
    "gn:name":"Nakashinden",
    "iso:country":"JP",
    "wof:name":"425-0068",
    "wof:placetype":"postalcode"
},
  "geometry": {"coordinates":[138.2877,34.8392],"type":"Point"}
}