{
  "type": "Feature",
  "properties": {
    "gn:adm1_name":"Yamaguchiken",
    "gn:adm2_name":"Yanaishi",
    "gn:name":"Shintenchi",
    "iso:country":"JP",
    "wof:name":"742-0006",
    "wof:placetype":"postalcode"
},
  "geometry": {"coordinates":[132.1146,33.9674],"type":"Point"}
}