{
  "type": "Feature",
  "properties": {
    "gn:adm1_name":"Kagoshimaken",
    "gn:adm2_name":"Ooshimagunsetouchichou",
    "gn:name":"Koniya(Matsue)",
    "iso:country":"JP",
    "wof:name":"894-1505",
    "wof:placetype":"postalcode"
},
  "geometry": {"coordinates":[129.31229999999999,28.1475],"type":"Point"}
}