{
  "type": "Feature",
  "properties": {
    "gn:adm1_name":"Kumamotoken",
    "gn:adm2_name":"Amakusagunmatsushimamachi",
    "gn:name":"Imaizumi",
    "iso:country":"JP",
    "wof:name":"861-6103",
    "wof:placetype":"postalcode"
},
  "geometry": {"coordinates":[130.40969999999999,32.4932],"type":"Point"}
}