{
  "type": "Feature",
  "properties": {
    "gn:adm1_name":"Fukuokaken",
    "gn:adm2_name":"Ukihagunyoshiimachi",
    "gn:name":"Takatori",
    "iso:country":"JP",
    "wof:name":"839-1343",
    "wof:placetype":"postalcode"
},
  "geometry": {"coordinates":[130.7287,33.3396],"type":"Point"}
}