{
  "type": "Feature",
  "properties": {
    "gn:adm1_name":"Naganoken",
    "gn:adm2_name":"Chiisagataguntoubumachi",
    "gn:name":"Shiokawa",
    "iso:country":"JP",
    "wof:name":"389-0519",
    "wof:placetype":"postalcode"
},
  "geometry": {"coordinates":[138.3075,36.3619],"type":"Point"}
}