{
  "type": "Feature",
  "properties": {
    "gn:adm1_name":"Niigataken",
    "gn:adm2_name":"Higashikubikigunmakimura",
    "gn:name":"Ochida",
    "iso:country":"JP",
    "wof:name":"943-0646",
    "wof:placetype":"postalcode"
},
  "geometry": {"coordinates":[138.3783,37.0822],"type":"Point"}
}