{
  "type": "Feature",
  "properties": {
    "gn:adm1_name":"Kyoutofu",
    "gn:adm2_name":"Kyoutoshishimogyouku",
    "gn:name":"Higashitamamizuchou",
    "iso:country":"JP",
    "wof:name":"600-8190",
    "wof:placetype":"postalcode"
},
  "geometry": {"coordinates":[135.7628,34.9912],"type":"Point"}
}