{
  "type": "Feature",
  "properties": {
    "gn:adm1_name":"Kanagawaken",
    "gn:adm2_name":"Zamashi",
    "gn:name":"Kuriharachuuou",
    "iso:country":"JP",
    "wof:name":"228-0014",
    "wof:placetype":"postalcode"
},
  "geometry": {"coordinates":[139.41589999999999,35.4826],"type":"Point"}
}