{
  "type": "Feature",
  "properties": {
    "gn:adm1_name":"Kouchiken",
    "gn:adm2_name":"Kouchishi",
    "gn:name":"Asakuraki",
    "iso:country":"JP",
    "wof:name":"780-8066",
    "wof:placetype":"postalcode"
},
  "geometry": {"coordinates":[133.48679999999999,33.534],"type":"Point"}
}