{
  "type": "Feature",
  "properties": {
    "gn:adm1_name":"Naraken",
    "gn:adm2_name":"Narashi",
    "gn:name":"Shijouoojiminamimachi",
    "iso:country":"JP",
    "wof:name":"630-8015",
    "wof:placetype":"postalcode"
},
  "geometry": {"coordinates":[135.80340000000001,34.6749],"type":"Point"}
}