{
  "type": "Feature",
  "properties": {
    "gn:adm1_name":"Shizuokaken",
    "gn:adm2_name":"Shuuchigunharunochou",
    "gn:name":"Keta",
    "iso:country":"JP",
    "wof:name":"437-0605",
    "wof:placetype":"postalcode"
},
  "geometry": {"coordinates":[137.9067,35.006],"type":"Point"}
}