{
  "type": "Feature",
  "properties": {
    "gn:adm1_name":"Toukyouto",
    "gn:adm2_name":"Choufushi",
    "gn:name":"Wakabachou",
    "iso:country":"JP",
    "wof:name":"182-0003",
    "wof:placetype":"postalcode"
},
  "geometry": {"coordinates":[139.58439999999999,35.6573],"type":"Point"}
}