{
  "type": "Feature",
  "properties": {
    "gn:adm1_name":"Kyoutofu",
    "gn:adm2_name":"Kyoutoshinakagyouku",
    "gn:name":"Mibuhigashihinokichou",
    "iso:country":"JP",
    "wof:name":"604-8843",
    "wof:placetype":"postalcode"
},
  "geometry": {"coordinates":[135.73589999999999,34.9999],"type":"Point"}
}