{
  "type": "Feature",
  "properties": {
    "gn:adm1_name":"Hyougoken",
    "gn:adm2_name":"Hikamigunsannanchou",
    "gn:name":"Minaminaka",
    "iso:country":"JP",
    "wof:name":"669-3146",
    "wof:placetype":"postalcode"
},
  "geometry": {"coordinates":[134.99889999999999,35.0929],"type":"Point"}
}