{
  "type": "Feature",
  "properties": {
    "gn:adm1_name":"Kanagawaken",
    "gn:adm2_name":"Yokohamashikanagawaku",
    "gn:name":"Takarachou",
    "iso:country":"JP",
    "wof:name":"221-0023",
    "wof:placetype":"postalcode"
},
  "geometry": {"coordinates":[139.66380000000001,35.4817],"type":"Point"}
}