{
  "type": "Feature",
  "properties": {
    "gn:adm1_name":"Ehimeken",
    "gn:adm2_name":"Ochigunyugechou",
    "gn:name":"Shimoyuge",
    "iso:country":"JP",
    "wof:name":"794-2506",
    "wof:placetype":"postalcode"
},
  "geometry": {"coordinates":[133.2056,34.2574],"type":"Point"}
}