{
  "type": "Feature",
  "properties": {
    "gn:adm1_name":"Chibaken",
    "gn:adm2_name":"Isumigun'Ootakimachi",
    "gn:name":"Yakiyou",
    "iso:country":"JP",
    "wof:name":"298-0245",
    "wof:placetype":"postalcode"
},
  "geometry": {"coordinates":[140.22319999999999,35.2493],"type":"Point"}
}