{
  "type": "Feature",
  "properties": {
    "gn:adm1_name":"Toyamaken",
    "gn:adm2_name":"Himishi",
    "gn:name":"Okubo",
    "iso:country":"JP",
    "wof:name":"935-0257",
    "wof:placetype":"postalcode"
},
  "geometry": {"coordinates":[136.90790000000001,36.8578],"type":"Point"}
}