{
  "type": "Feature",
  "properties": {
    "gn:adm1_name":"Naraken",
    "gn:adm2_name":"Tenrishi",
    "gn:name":"Besshiyochou",
    "iso:country":"JP",
    "wof:name":"632-0018",
    "wof:placetype":"postalcode"
},
  "geometry": {"coordinates":[135.83510000000001,34.6084],"type":"Point"}
}