{
  "type": "Feature",
  "properties": {
    "gn:adm1_name":"Kanagawaken",
    "gn:adm2_name":"Kawasakishiasaoku",
    "gn:name":"Kamiasao",
    "iso:country":"JP",
    "wof:name":"215-0021",
    "wof:placetype":"postalcode"
},
  "geometry": {"coordinates":[139.5042,35.5935],"type":"Point"}
}