{
  "type": "Feature",
  "properties": {
    "gn:adm1_name":"Sagaken",
    "gn:adm2_name":"Higashimatsuuragunhizenchou",
    "gn:name":"Umezaki",
    "iso:country":"JP",
    "wof:name":"847-1512",
    "wof:placetype":"postalcode"
},
  "geometry": {"coordinates":[129.8381,33.4413],"type":"Point"}
}