{
  "type": "Feature",
  "properties": {
    "gn:adm1_name":"Fukuiken",
    "gn:adm2_name":"Oonogun'Izumimura",
    "gn:name":"Shimooono",
    "iso:country":"JP",
    "wof:name":"912-0215",
    "wof:placetype":"postalcode"
},
  "geometry": {"coordinates":[136.62610000000001,35.873],"type":"Point"}
}