{
  "type": "Feature",
  "properties": {
    "gn:adm1_name":"Aichiken",
    "gn:adm2_name":"Nagoyashimoriyamaku",
    "gn:name":"Midorigaoka",
    "iso:country":"JP",
    "wof:name":"463-0009",
    "wof:placetype":"postalcode"
},
  "geometry": {"coordinates":[136.98230000000001,35.212],"type":"Point"}
}