{
  "type": "Feature",
  "properties": {
    "gn:adm1_name":"Aichiken",
    "gn:adm2_name":"Nagoyashinakagawaku",
    "gn:name":"Kamitakabata",
    "iso:country":"JP",
    "wof:name":"454-0873",
    "wof:placetype":"postalcode"
},
  "geometry": {"coordinates":[136.85659999999999,35.1447],"type":"Point"}
}