{
  "type": "Feature",
  "properties": {
    "gn:adm1_name":"Kyoutofu",
    "gn:adm2_name":"Kumanogunkumihamachou",
    "gn:name":"Maruyama",
    "iso:country":"JP",
    "wof:name":"629-3558",
    "wof:placetype":"postalcode"
},
  "geometry": {"coordinates":[134.95509999999999,35.5922],"type":"Point"}
}