{
  "type": "Feature",
  "properties": {
    "gn:adm1_name":"Niigataken",
    "gn:adm2_name":"Iwafunegunsekikawamura",
    "gn:name":"Takada",
    "iso:country":"JP",
    "wof:name":"959-3252",
    "wof:placetype":"postalcode"
},
  "geometry": {"coordinates":[139.52809999999999,38.1075],"type":"Point"}
}