{
  "type": "Feature",
  "properties": {
    "gn:adm1_name":"Ibarakiken",
    "gn:adm2_name":"Nakagun'Ogawamura",
    "gn:name":"Matsunokusa",
    "iso:country":"JP",
    "wof:name":"319-2413",
    "wof:placetype":"postalcode"
},
  "geometry": {"coordinates":[140.28469999999999,36.607],"type":"Point"}
}