{
  "type": "Feature",
  "properties": {
    "gn:adm1_name":"Shigaken",
    "gn:adm2_name":"Oumihachimanshi",
    "gn:name":"Yakushichou",
    "iso:country":"JP",
    "wof:name":"523-0826",
    "wof:placetype":"postalcode"
},
  "geometry": {"coordinates":[136.0926,35.142],"type":"Point"}
}