{
  "type": "Feature",
  "properties": {
    "gn:adm1_name":"Aichiken",
    "gn:adm2_name":"Komakishi",
    "gn:name":"Tagatachou",
    "iso:country":"JP",
    "wof:name":"485-0004",
    "wof:placetype":"postalcode"
},
  "geometry": {"coordinates":[136.9417,35.3159],"type":"Point"}
}