{
  "type": "Feature",
  "properties": {
    "gn:adm1_name":"Kyoutofu",
    "gn:adm2_name":"Maidurushi",
    "gn:name":"Oouchi",
    "iso:country":"JP",
    "wof:name":"624-0852",
    "wof:placetype":"postalcode"
},
  "geometry": {"coordinates":[135.3348,35.4451],"type":"Point"}
}