{
  "type": "Feature",
  "properties": {
    "gn:adm1_name":"Niigataken",
    "gn:adm2_name":"Minamikanbaraguntagamimachi",
    "gn:name":"Ikanikeisaiganaibaai",
    "iso:country":"JP",
    "wof:name":"959-1500",
    "wof:placetype":"postalcode"
},
  "geometry": {"coordinates":[139.0763,37.7004],"type":"Point"}
}