{
  "type": "Feature",
  "properties": {
    "gn:adm1_name":"Shizuokaken",
    "gn:adm2_name":"Kakegawashi",
    "gn:name":"Minami",
    "iso:country":"JP",
    "wof:name":"436-0029",
    "wof:placetype":"postalcode"
},
  "geometry": {"coordinates":[138.017,34.7684],"type":"Point"}
}