{
  "type": "Feature",
  "properties": {
    "gn:adm1_name":"Niigataken",
    "gn:adm2_name":"Tsubameshi",
    "gn:name":"Todoroki",
    "iso:country":"JP",
    "wof:name":"959-1283",
    "wof:placetype":"postalcode"
},
  "geometry": {"coordinates":[138.91380000000001,37.6706],"type":"Point"}
}