{
  "type": "Feature",
  "properties": {
    "gn:adm1_name":"Gifuken",
    "gn:adm2_name":"Kaidugunnannouchou",
    "gn:name":"Niwada",
    "iso:country":"JP",
    "wof:name":"503-0408",
    "wof:placetype":"postalcode"
},
  "geometry": {"coordinates":[136.58369999999999,35.2292],"type":"Point"}
}