{
  "type": "Feature",
  "properties": {
    "gn:adm1_name":"Fukushimaken",
    "gn:adm2_name":"Soumashi",
    "gn:name":"Niida",
    "iso:country":"JP",
    "wof:name":"976-0033",
    "wof:placetype":"postalcode"
},
  "geometry": {"coordinates":[140.95609999999999,37.7881],"type":"Point"}
}