{
  "type": "Feature",
  "properties": {
    "gn:adm1_name":"Gifuken",
    "gn:adm2_name":"Yoshikigunkokufuchou",
    "gn:name":"Utsue",
    "iso:country":"JP",
    "wof:name":"509-4121",
    "wof:placetype":"postalcode"
},
  "geometry": {"coordinates":[137.18860000000001,36.2081],"type":"Point"}
}