{
  "type": "Feature",
  "properties": {
    "gn:adm1_name":"Ishikawaken",
    "gn:adm2_name":"Ishikawaguntsurugimachi",
    "gn:name":"Sodanimachi",
    "iso:country":"JP",
    "wof:name":"920-2101",
    "wof:placetype":"postalcode"
},
  "geometry": {"coordinates":[136.6173,36.4901],"type":"Point"}
}