{
  "type": "Feature",
  "properties": {
    "gn:adm1_name":"Aichiken",
    "gn:adm2_name":"Nagoyashinakagawaku",
    "gn:name":"Juubanchou",
    "iso:country":"JP",
    "wof:name":"454-0055",
    "wof:placetype":"postalcode"
},
  "geometry": {"coordinates":[136.88239999999999,35.123],"type":"Point"}
}