{
  "type": "Feature",
  "properties": {
    "gn:adm1_name":"Hyougoken",
    "gn:adm2_name":"Sasayamashi",
    "gn:name":"Ochikata",
    "iso:country":"JP",
    "wof:name":"669-2704",
    "wof:placetype":"postalcode"
},
  "geometry": {"coordinates":[135.27260000000001,35.1686],"type":"Point"}
}