{
  "type": "Feature",
  "properties": {
    "gn:adm1_name":"Ishikawaken",
    "gn:adm2_name":"Kanazawashi",
    "gn:name":"Futsukaichimachi",
    "iso:country":"JP",
    "wof:name":"920-0107",
    "wof:placetype":"postalcode"
},
  "geometry": {"coordinates":[136.71100000000001,36.6351],"type":"Point"}
}