{
  "type": "Feature",
  "properties": {
    "gn:adm1_name":"Niigataken",
    "gn:adm2_name":"Nagaokashi",
    "gn:name":"Sumonzakimachi",
    "iso:country":"JP",
    "wof:name":"940-2462",
    "wof:placetype":"postalcode"
},
  "geometry": {"coordinates":[138.83580000000001,37.5224],"type":"Point"}
}