{
  "type": "Feature",
  "properties": {
    "gn:adm1_name":"Ehimeken",
    "gn:adm2_name":"Kitauwagunhiromichou",
    "gn:name":"Kitagawa",
    "iso:country":"JP",
    "wof:name":"798-1354",
    "wof:placetype":"postalcode"
},
  "geometry": {"coordinates":[132.62799999999999,33.2482],"type":"Point"}
}