{
  "type": "Feature",
  "properties": {
    "gn:adm1_name":"Kagoshimaken",
    "gn:adm2_name":"Airagunkamouchou",
    "gn:name":"Kamigyuutoku",
    "iso:country":"JP",
    "wof:name":"899-5302",
    "wof:placetype":"postalcode"
},
  "geometry": {"coordinates":[130.57419999999999,31.7631],"type":"Point"}
}