{
  "type": "Feature",
  "properties": {
    "gn:adm1_name":"Fukuiken",
    "gn:adm2_name":"Fukuishi",
    "gn:name":"Mionochou",
    "iso:country":"JP",
    "wof:name":"918-8188",
    "wof:placetype":"postalcode"
},
  "geometry": {"coordinates":[136.17439999999999,36.0155],"type":"Point"}
}