{
  "type": "Feature",
  "properties": {
    "gn:adm1_name":"Hyougoken",
    "gn:adm2_name":"Akoushi",
    "gn:name":"Uneyokoo",
    "iso:country":"JP",
    "wof:name":"678-1184",
    "wof:placetype":"postalcode"
},
  "geometry": {"coordinates":[134.39449999999999,34.8278],"type":"Point"}
}