{
  "type": "Feature",
  "properties": {
    "gn:adm1_name":"Ooitaken",
    "gn:adm2_name":"Saikishi",
    "gn:name":"Takamatsuura",
    "iso:country":"JP",
    "wof:name":"876-0001",
    "wof:placetype":"postalcode"
},
  "geometry": {"coordinates":[131.9265,33.0122],"type":"Point"}
}