{
  "type": "Feature",
  "properties": {
    "gn:adm1_name":"Oosakafu",
    "gn:adm2_name":"Oosakashikitaku",
    "gn:name":"Kamiyamachou",
    "iso:country":"JP",
    "wof:name":"530-0026",
    "wof:placetype":"postalcode"
},
  "geometry": {"coordinates":[135.50569999999999,34.7031],"type":"Point"}
}