{
  "type": "Feature",
  "properties": {
    "gn:adm1_name":"Tottoriken",
    "gn:adm2_name":"Tottorishi",
    "gn:name":"Yoshinariminamimachi",
    "iso:country":"JP",
    "wof:name":"680-0871",
    "wof:placetype":"postalcode"
},
  "geometry": {"coordinates":[134.2174,35.4817],"type":"Point"}
}