{
  "type": "Feature",
  "properties": {
    "gn:adm1_name":"Fukushimaken",
    "gn:adm2_name":"Dategunyanagawamachi",
    "gn:name":"Kamigawara",
    "iso:country":"JP",
    "wof:name":"960-0753",
    "wof:placetype":"postalcode"
},
  "geometry": {"coordinates":[140.61080000000001,37.8515],"type":"Point"}
}