{
  "type": "Feature",
  "properties": {
    "gn:adm1_name":"Okayamaken",
    "gn:adm2_name":"Asakuchigunfunaochou",
    "gn:name":"Mizue",
    "iso:country":"JP",
    "wof:name":"710-0262",
    "wof:placetype":"postalcode"
},
  "geometry": {"coordinates":[133.71979999999999,34.6023],"type":"Point"}
}