{
  "type": "Feature",
  "properties": {
    "gn:adm1_name":"Tokushimaken",
    "gn:adm2_name":"Tokushimashi",
    "gn:name":"Kokufuchouhigai",
    "iso:country":"JP",
    "wof:name":"779-3117",
    "wof:placetype":"postalcode"
},
  "geometry": {"coordinates":[134.47620000000001,34.0816],"type":"Point"}
}