{
  "type": "Feature",
  "properties": {
    "gn:adm1_name":"Fukushimaken",
    "gn:adm2_name":"Iwakishi",
    "gn:name":"Ishidukamachi",
    "iso:country":"JP",
    "wof:name":"974-8213",
    "wof:placetype":"postalcode"
},
  "geometry": {"coordinates":[140.80009999999999,36.9284],"type":"Point"}
}