{
  "type": "Feature",
  "properties": {
    "gn:adm1_name":"Ishikawaken",
    "gn:adm2_name":"Nanaoshi",
    "gn:name":"Yamazakimachi",
    "iso:country":"JP",
    "wof:name":"926-0385",
    "wof:placetype":"postalcode"
},
  "geometry": {"coordinates":[137.02969999999999,36.9791],"type":"Point"}
}