{
  "type": "Feature",
  "properties": {
    "gn:adm1_name":"Saitamaken",
    "gn:adm2_name":"Satteshi",
    "gn:name":"Nakakawasaki",
    "iso:country":"JP",
    "wof:name":"340-0163",
    "wof:placetype":"postalcode"
},
  "geometry": {"coordinates":[139.6995,36.0803],"type":"Point"}
}