{
  "type": "Feature",
  "properties": {
    "gn:adm1_name":"Kouchiken",
    "gn:adm2_name":"Susakishi",
    "gn:name":"Nishizakimachi",
    "iso:country":"JP",
    "wof:name":"785-0041",
    "wof:placetype":"postalcode"
},
  "geometry": {"coordinates":[133.2921,33.4117],"type":"Point"}
}