{
  "type": "Feature",
  "properties": {
    "gn:adm1_name":"Aichiken",
    "gn:adm2_name":"Setoshi",
    "gn:name":"Odadumachou",
    "iso:country":"JP",
    "wof:name":"489-0067",
    "wof:placetype":"postalcode"
},
  "geometry": {"coordinates":[137.0735,35.244],"type":"Point"}
}