{
  "type": "Feature",
  "properties": {
    "gn:adm1_name":"Chibaken",
    "gn:adm2_name":"Kimitsushi",
    "gn:name":"Terazawa",
    "iso:country":"JP",
    "wof:name":"292-0443",
    "wof:placetype":"postalcode"
},
  "geometry": {"coordinates":[140.0557,35.3053],"type":"Point"}
}