{
  "type": "Feature",
  "properties": {
    "gn:adm1_name":"Kanagawaken",
    "gn:adm2_name":"Yokohamashinakaku",
    "gn:name":"Yaguchidai",
    "iso:country":"JP",
    "wof:name":"231-0831",
    "wof:placetype":"postalcode"
},
  "geometry": {"coordinates":[139.64779999999999,35.4243],"type":"Point"}
}