{
  "type": "Feature",
  "properties": {
    "gn:adm1_name":"Kouchiken",
    "gn:adm2_name":"Akigunkitagawamura",
    "gn:name":"Futamata",
    "iso:country":"JP",
    "wof:name":"781-6453",
    "wof:placetype":"postalcode"
},
  "geometry": {"coordinates":[134.13499999999999,33.524],"type":"Point"}
}