{
  "type": "Feature",
  "properties": {
    "gn:adm1_name":"Fukuokaken",
    "gn:adm2_name":"Yanagawashi",
    "gn:name":"Nanatsue",
    "iso:country":"JP",
    "wof:name":"832-0087",
    "wof:placetype":"postalcode"
},
  "geometry": {"coordinates":[130.37049999999999,33.167],"type":"Point"}
}