{
  "type": "Feature",
  "properties": {
    "gn:adm1_name":"Fukuiken",
    "gn:adm2_name":"Fukuishi",
    "gn:name":"Asouzusangachou",
    "iso:country":"JP",
    "wof:name":"918-8183",
    "wof:placetype":"postalcode"
},
  "geometry": {"coordinates":[136.19890000000001,36.0014],"type":"Point"}
}