{
  "type": "Feature",
  "properties": {
    "gn:adm1_name":"Ehimeken",
    "gn:adm2_name":"Kawanoeshi",
    "gn:name":"Kawanoechou",
    "iso:country":"JP",
    "wof:name":"799-0101",
    "wof:placetype":"postalcode"
},
  "geometry": {"coordinates":[133.5735,34.0116],"type":"Point"}
}