{
  "type": "Feature",
  "properties": {
    "gn:adm1_name":"Miyagiken",
    "gn:adm2_name":"Shiogamashi",
    "gn:name":"Ashigurochou",
    "iso:country":"JP",
    "wof:name":"985-0012",
    "wof:placetype":"postalcode"
},
  "geometry": {"coordinates":[141.0326,38.3045],"type":"Point"}
}