{
  "type": "Feature",
  "properties": {
    "gn:adm1_name":"Gifuken",
    "gn:adm2_name":"Sekishi",
    "gn:name":"Adumachou",
    "iso:country":"JP",
    "wof:name":"501-3845",
    "wof:placetype":"postalcode"
},
  "geometry": {"coordinates":[136.92160000000001,35.4843],"type":"Point"}
}