{
  "type": "Feature",
  "properties": {
    "gn:adm1_name":"Wakayamaken",
    "gn:adm2_name":"Nagagunkishigawachou",
    "gn:name":"Kishiono",
    "iso:country":"JP",
    "wof:name":"640-0422",
    "wof:placetype":"postalcode"
},
  "geometry": {"coordinates":[135.33500000000001,34.2037],"type":"Point"}
}