{
  "type": "Feature",
  "properties": {
    "gn:adm1_name":"Fukuokaken",
    "gn:adm2_name":"Itoshimagunnijoumachi",
    "gn:name":"Take",
    "iso:country":"JP",
    "wof:name":"819-1616",
    "wof:placetype":"postalcode"
},
  "geometry": {"coordinates":[130.16900000000001,33.5286],"type":"Point"}
}