{
  "type": "Feature",
  "properties": {
    "gn:adm1_name":"Hiroshimaken",
    "gn:adm2_name":"Shoubarashi",
    "gn:name":"Heiwachou",
    "iso:country":"JP",
    "wof:name":"729-6144",
    "wof:placetype":"postalcode"
},
  "geometry": {"coordinates":[132.93629999999999,34.8243],"type":"Point"}
}