{
  "type": "Feature",
  "properties": {
    "gn:adm1_name":"Yamagataken",
    "gn:adm2_name":"Shinjoushi",
    "gn:name":"Motoaikai",
    "iso:country":"JP",
    "wof:name":"996-0112",
    "wof:placetype":"postalcode"
},
  "geometry": {"coordinates":[140.23560000000001,38.7319],"type":"Point"}
}