{
  "type": "Feature",
  "properties": {
    "gn:adm1_name":"Naraken",
    "gn:adm2_name":"Yoshinogunhigashiyoshinomura",
    "gn:name":"Ogawa",
    "iso:country":"JP",
    "wof:name":"633-2421",
    "wof:placetype":"postalcode"
},
  "geometry": {"coordinates":[135.9718,34.4059],"type":"Point"}
}