{
  "type": "Feature",
  "properties": {
    "gn:adm1_name":"Ibarakiken",
    "gn:adm2_name":"Shimodateshi",
    "gn:name":"Kuchido",
    "iso:country":"JP",
    "wof:name":"308-0071",
    "wof:placetype":"postalcode"
},
  "geometry": {"coordinates":[139.9658,36.3533],"type":"Point"}
}