{
  "type": "Feature",
  "properties": {
    "gn:adm1_name":"Shigaken",
    "gn:adm2_name":"Koukaguntsuchiyamachou",
    "gn:name":"Yamanaka",
    "iso:country":"JP",
    "wof:name":"528-0206",
    "wof:placetype":"postalcode"
},
  "geometry": {"coordinates":[136.3272,34.9078],"type":"Point"}
}