{
  "type": "Feature",
  "properties": {
    "gn:adm1_name":"Hyougoken",
    "gn:adm2_name":"Koubeshinishiku",
    "gn:name":"Tennouzan",
    "iso:country":"JP",
    "wof:name":"651-2123",
    "wof:placetype":"postalcode"
},
  "geometry": {"coordinates":[135.0085,34.677],"type":"Point"}
}