{
  "type": "Feature",
  "properties": {
    "gn:adm1_name":"Toyamaken",
    "gn:adm2_name":"Nishitonamigunfukuokamachi",
    "gn:name":"Oono",
    "iso:country":"JP",
    "wof:name":"939-0118",
    "wof:placetype":"postalcode"
},
  "geometry": {"coordinates":[137.02520000000001,36.7386],"type":"Point"}
}