{
  "type": "Feature",
  "properties": {
    "gn:adm1_name":"Hyougoken",
    "gn:adm2_name":"Katouguntoujouchou",
    "gn:name":"Iwaya",
    "iso:country":"JP",
    "wof:name":"673-1321",
    "wof:placetype":"postalcode"
},
  "geometry": {"coordinates":[135.05350000000001,34.9006],"type":"Point"}
}