{
  "type": "Feature",
  "properties": {
    "gn:adm1_name":"Okinawaken",
    "gn:adm2_name":"Nakagamigunkatsurenchou",
    "gn:name":"Heshikiya",
    "iso:country":"JP",
    "wof:name":"904-2314",
    "wof:placetype":"postalcode"
},
  "geometry": {"coordinates":[127.9139,26.3079],"type":"Point"}
}