{
  "type": "Feature",
  "properties": {
    "gn:adm1_name":"Naraken",
    "gn:adm2_name":"Yoshinogunyoshinochou",
    "gn:name":"Yaji",
    "iso:country":"JP",
    "wof:name":"639-3441",
    "wof:placetype":"postalcode"
},
  "geometry": {"coordinates":[135.90989999999999,34.3808],"type":"Point"}
}