{
  "type": "Feature",
  "properties": {
    "gn:adm1_name":"Niigataken",
    "gn:adm2_name":"Niigatashi",
    "gn:name":"Hamachou",
    "iso:country":"JP",
    "wof:name":"950-0046",
    "wof:placetype":"postalcode"
},
  "geometry": {"coordinates":[139.07050000000001,37.9419],"type":"Point"}
}