{
  "type": "Feature",
  "properties": {
    "gn:adm1_name":"Hiroshimaken",
    "gn:adm2_name":"Hiroshimashinishiku",
    "gn:name":"Koihonmachi",
    "iso:country":"JP",
    "wof:name":"733-0812",
    "wof:placetype":"postalcode"
},
  "geometry": {"coordinates":[132.4272,34.3958],"type":"Point"}
}