{
  "type": "Feature",
  "properties": {
    "gn:adm1_name":"Hyougoken",
    "gn:adm2_name":"Akougunkamigoorichou",
    "gn:name":"Nashigahara",
    "iso:country":"JP",
    "wof:name":"678-1244",
    "wof:placetype":"postalcode"
},
  "geometry": {"coordinates":[134.3082,34.8323],"type":"Point"}
}