{
  "type": "Feature",
  "properties": {
    "gn:adm1_name":"Aichiken",
    "gn:adm2_name":"Amagunshippouchou",
    "gn:name":"Akitake",
    "iso:country":"JP",
    "wof:name":"497-0003",
    "wof:placetype":"postalcode"
},
  "geometry": {"coordinates":[136.80420000000001,35.1742],"type":"Point"}
}