{
  "type": "Feature",
  "properties": {
    "gn:adm1_name":"Niigataken",
    "gn:adm2_name":"Kashiwazakishi",
    "gn:name":"Kasashima",
    "iso:country":"JP",
    "wof:name":"949-3662",
    "wof:placetype":"postalcode"
},
  "geometry": {"coordinates":[138.46860000000001,37.336],"type":"Point"}
}