{
  "type": "Feature",
  "properties": {
    "gn:adm1_name":"Kanagawaken",
    "gn:adm2_name":"Kawasakishitamaku",
    "gn:name":"Kuriya",
    "iso:country":"JP",
    "wof:name":"214-0039",
    "wof:placetype":"postalcode"
},
  "geometry": {"coordinates":[139.53569999999999,35.6116],"type":"Point"}
}