{
  "type": "Feature",
  "properties": {
    "gn:adm1_name":"Shimaneken",
    "gn:adm2_name":"Oodashi",
    "gn:name":"Yamaguchichouyamaguchi",
    "iso:country":"JP",
    "wof:name":"694-0002",
    "wof:placetype":"postalcode"
},
  "geometry": {"coordinates":[132.63419999999999,35.1703],"type":"Point"}
}