{
  "type": "Feature",
  "properties": {
    "gn:adm1_name":"Niigataken",
    "gn:adm2_name":"Niigatashi",
    "gn:name":"Eguchi",
    "iso:country":"JP",
    "wof:name":"950-0101",
    "wof:placetype":"postalcode"
},
  "geometry": {"coordinates":[139.14279999999999,37.9043],"type":"Point"}
}