{
  "type": "Feature",
  "properties": {
    "gn:adm1_name":"Toyamaken",
    "gn:adm2_name":"Nakaniikawagunkamiichimachi",
    "gn:name":"Takehana",
    "iso:country":"JP",
    "wof:name":"930-0301",
    "wof:placetype":"postalcode"
},
  "geometry": {"coordinates":[137.34229999999999,36.7354],"type":"Point"}
}