{
  "type": "Feature",
  "properties": {
    "gn:adm1_name":"Fukushimaken",
    "gn:adm2_name":"Shirakawashi",
    "gn:name":"Kurabeishi",
    "iso:country":"JP",
    "wof:name":"961-0017",
    "wof:placetype":"postalcode"
},
  "geometry": {"coordinates":[140.2578,37.1116],"type":"Point"}
}