{
  "type": "Feature",
  "properties": {
    "gn:adm1_name":"Miyagiken",
    "gn:adm2_name":"Sendaishiizumiku",
    "gn:name":"Nenoshiroishi",
    "iso:country":"JP",
    "wof:name":"981-3221",
    "wof:placetype":"postalcode"
},
  "geometry": {"coordinates":[140.79849999999999,38.3441],"type":"Point"}
}