{
  "type": "Feature",
  "properties": {
    "gn:adm1_name":"Kanagawaken",
    "gn:adm2_name":"Sagamiharashi",
    "gn:name":"Kyouwa",
    "iso:country":"JP",
    "wof:name":"229-0034",
    "wof:placetype":"postalcode"
},
  "geometry": {"coordinates":[139.39959999999999,35.5635],"type":"Point"}
}