{
  "type": "Feature",
  "properties": {
    "gn:adm1_name":"Yamagataken",
    "gn:adm2_name":"Tsuruokashi",
    "gn:name":"Nakadate",
    "iso:country":"JP",
    "wof:name":"997-1135",
    "wof:placetype":"postalcode"
},
  "geometry": {"coordinates":[139.74639999999999,38.7184],"type":"Point"}
}