{
  "type": "Feature",
  "properties": {
    "gn:adm1_name":"Toukyouto",
    "gn:adm2_name":"Machidashi",
    "gn:name":"Minaminaruse",
    "iso:country":"JP",
    "wof:name":"194-0045",
    "wof:placetype":"postalcode"
},
  "geometry": {"coordinates":[139.47450000000001,35.5369],"type":"Point"}
}