{
  "type": "Feature",
  "properties": {
    "gn:adm1_name":"Chibaken",
    "gn:adm2_name":"Chibashiwakabaku",
    "gn:name":"Chishirodaikita",
    "iso:country":"JP",
    "wof:name":"264-0005",
    "wof:placetype":"postalcode"
},
  "geometry": {"coordinates":[140.1874,35.6258],"type":"Point"}
}