{
  "type": "Feature",
  "properties": {
    "gn:adm1_name":"Kyoutofu",
    "gn:adm2_name":"Yawatashi",
    "gn:name":"Hashimotonakanochou",
    "iso:country":"JP",
    "wof:name":"614-8341",
    "wof:placetype":"postalcode"
},
  "geometry": {"coordinates":[135.68360000000001,34.8821],"type":"Point"}
}