{
  "type": "Feature",
  "properties": {
    "gn:adm1_name":"Ehimeken",
    "gn:adm2_name":"Higashiuwagun'Akehamachou",
    "gn:name":"Tawaradu",
    "iso:country":"JP",
    "wof:name":"797-0111",
    "wof:placetype":"postalcode"
},
  "geometry": {"coordinates":[132.49090000000001,33.326],"type":"Point"}
}