{
  "type": "Feature",
  "properties": {
    "gn:adm1_name":"Fukuokaken",
    "gn:adm2_name":"Kitakyuushuushiyahatahigashiku",
    "gn:name":"Matsuomachi",
    "iso:country":"JP",
    "wof:name":"805-0032",
    "wof:placetype":"postalcode"
},
  "geometry": {"coordinates":[130.8426,33.8626],"type":"Point"}
}