{
  "type": "Feature",
  "properties": {
    "gn:adm1_name":"Kagawaken",
    "gn:adm2_name":"Marugameshi",
    "gn:name":"Dokichouhigashi",
    "iso:country":"JP",
    "wof:name":"763-0082",
    "wof:placetype":"postalcode"
},
  "geometry": {"coordinates":[133.81370000000001,34.2945],"type":"Point"}
}