{
  "type": "Feature",
  "properties": {
    "gn:adm1_name":"Yamanashiken",
    "gn:adm2_name":"Minamikomagunkajikazawachou",
    "gn:name":"Ekimaedoori",
    "iso:country":"JP",
    "wof:name":"400-0602",
    "wof:placetype":"postalcode"
},
  "geometry": {"coordinates":[138.4658,35.54],"type":"Point"}
}