{
  "type": "Feature",
  "properties": {
    "gn:adm1_name":"Hyougoken",
    "gn:adm2_name":"Himejishi",
    "gn:name":"Hirohatakukamada",
    "iso:country":"JP",
    "wof:name":"671-1102",
    "wof:placetype":"postalcode"
},
  "geometry": {"coordinates":[134.64349999999999,34.83],"type":"Point"}
}