{
  "type": "Feature",
  "properties": {
    "gn:adm1_name":"Naganoken",
    "gn:adm2_name":"Suzakashi",
    "gn:name":"Shinmachi",
    "iso:country":"JP",
    "wof:name":"382-0014",
    "wof:placetype":"postalcode"
},
  "geometry": {"coordinates":[138.3158,36.6559],"type":"Point"}
}