{
  "type": "Feature",
  "properties": {
    "gn:adm1_name":"Saitamaken",
    "gn:adm2_name":"Koshigayashi",
    "gn:name":"Kitakawasaki",
    "iso:country":"JP",
    "wof:name":"343-0006",
    "wof:placetype":"postalcode"
},
  "geometry": {"coordinates":[139.80709999999999,35.9305],"type":"Point"}
}