{
  "type": "Feature",
  "properties": {
    "gn:adm1_name":"Tochigiken",
    "gn:adm2_name":"Kuroisoshi",
    "gn:name":"Yayoichou",
    "iso:country":"JP",
    "wof:name":"325-0044",
    "wof:placetype":"postalcode"
},
  "geometry": {"coordinates":[140.05539999999999,36.9746],"type":"Point"}
}