{
  "type": "Feature",
  "properties": {
    "gn:adm1_name":"Niigataken",
    "gn:adm2_name":"Kitakanbaragunsasakamimura",
    "gn:name":"Katsuya",
    "iso:country":"JP",
    "wof:name":"959-1923",
    "wof:placetype":"postalcode"
},
  "geometry": {"coordinates":[139.30119999999999,37.8323],"type":"Point"}
}