{
  "type": "Feature",
  "properties": {
    "gn:adm1_name":"Nagasakiken",
    "gn:adm2_name":"Nagasakishi",
    "gn:name":"Hamaguchimachi",
    "iso:country":"JP",
    "wof:name":"852-8107",
    "wof:placetype":"postalcode"
},
  "geometry": {"coordinates":[129.86539999999999,32.769],"type":"Point"}
}