{
  "type": "Feature",
  "properties": {
    "gn:adm1_name":"Kyoutofu",
    "gn:adm2_name":"Kyoutoshisakyouku",
    "gn:name":"Kamitakanokitatachou",
    "iso:country":"JP",
    "wof:name":"606-0036",
    "wof:placetype":"postalcode"
},
  "geometry": {"coordinates":[135.79409999999999,35.0663],"type":"Point"}
}