{
  "type": "Feature",
  "properties": {
    "gn:adm1_name":"Gunmaken",
    "gn:adm2_name":"Fujiokashi",
    "gn:name":"Okanogou",
    "iso:country":"JP",
    "wof:name":"375-0011",
    "wof:placetype":"postalcode"
},
  "geometry": {"coordinates":[139.0986,36.2679],"type":"Point"}
}