{
  "type": "Feature",
  "properties": {
    "gn:adm1_name":"Chibaken",
    "gn:adm2_name":"Abikoshi",
    "gn:name":"Nedo",
    "iso:country":"JP",
    "wof:name":"270-1168",
    "wof:placetype":"postalcode"
},
  "geometry": {"coordinates":[139.9973,35.8785],"type":"Point"}
}