{
  "type": "Feature",
  "properties": {
    "gn:adm1_name":"Nagasakiken",
    "gn:adm2_name":"Higashisonogigunkawatanachou",
    "gn:name":"Ishikigou",
    "iso:country":"JP",
    "wof:name":"859-3604",
    "wof:placetype":"postalcode"
},
  "geometry": {"coordinates":[129.87479999999999,33.0833],"type":"Point"}
}