{
  "type": "Feature",
  "properties": {
    "gn:adm1_name":"Niigataken",
    "gn:adm2_name":"Shironeshi",
    "gn:name":"Oodoorinishi",
    "iso:country":"JP",
    "wof:name":"950-1204",
    "wof:placetype":"postalcode"
},
  "geometry": {"coordinates":[139.0179,37.8354],"type":"Point"}
}