{
  "type": "Feature",
  "properties": {
    "gn:adm1_name":"Oosakafu",
    "gn:adm2_name":"Neyagawashi",
    "gn:name":"Hachimandai",
    "iso:country":"JP",
    "wof:name":"572-0014",
    "wof:placetype":"postalcode"
},
  "geometry": {"coordinates":[135.6379,34.7686],"type":"Point"}
}