{
  "type": "Feature",
  "properties": {
    "gn:adm1_name":"Hyougoken",
    "gn:adm2_name":"Shisougunyamasakichou",
    "gn:name":"Yokosu",
    "iso:country":"JP",
    "wof:name":"671-2518",
    "wof:placetype":"postalcode"
},
  "geometry": {"coordinates":[134.53790000000001,35.018],"type":"Point"}
}