{
  "type": "Feature",
  "properties": {
    "gn:adm1_name":"Hyougoken",
    "gn:adm2_name":"Yabugun'Ooyachou",
    "gn:name":"Yamaji",
    "iso:country":"JP",
    "wof:name":"667-0312",
    "wof:placetype":"postalcode"
},
  "geometry": {"coordinates":[134.66399999999999,35.3323],"type":"Point"}
}