{
  "type": "Feature",
  "properties": {
    "gn:adm1_name":"Kyoutofu",
    "gn:adm2_name":"Miyadushi",
    "gn:name":"Yawara",
    "iso:country":"JP",
    "wof:name":"626-0067",
    "wof:placetype":"postalcode"
},
  "geometry": {"coordinates":[135.22739999999999,35.5696],"type":"Point"}
}