{
  "type": "Feature",
  "properties": {
    "gn:adm1_name":"Naganoken",
    "gn:adm2_name":"Kamiinaguntakatoomachi",
    "gn:name":"Yamamuro",
    "iso:country":"JP",
    "wof:name":"396-0304",
    "wof:placetype":"postalcode"
},
  "geometry": {"coordinates":[138.09960000000001,35.845],"type":"Point"}
}