{
  "type": "Feature",
  "properties": {
    "gn:adm1_name":"Oosakafu",
    "gn:adm2_name":"Oosakashitennoujiku",
    "gn:name":"Karasugatsuji",
    "iso:country":"JP",
    "wof:name":"543-0042",
    "wof:placetype":"postalcode"
},
  "geometry": {"coordinates":[135.52590000000001,34.6572],"type":"Point"}
}