{
  "type": "Feature",
  "properties": {
    "gn:adm1_name":"Ishikawaken",
    "gn:adm2_name":"Suzushi",
    "gn:name":"Misakimachifushimi",
    "iso:country":"JP",
    "wof:name":"927-1461",
    "wof:placetype":"postalcode"
},
  "geometry": {"coordinates":[137.35509999999999,37.4583],"type":"Point"}
}