{
  "type": "Feature",
  "properties": {
    "gn:adm1_name":"Aichiken",
    "gn:adm2_name":"Inuyamashi",
    "gn:name":"Nonaka",
    "iso:country":"JP",
    "wof:name":"484-0025",
    "wof:placetype":"postalcode"
},
  "geometry": {"coordinates":[136.9922,35.3324],"type":"Point"}
}