{
  "type": "Feature",
  "properties": {
    "gn:adm1_name":"Yamagataken",
    "gn:adm2_name":"Nishiokitamagunshiratakamachi",
    "gn:name":"Kurofuji",
    "iso:country":"JP",
    "wof:name":"992-0841",
    "wof:placetype":"postalcode"
},
  "geometry": {"coordinates":[140.0908,38.1635],"type":"Point"}
}