{
  "type": "Feature",
  "properties": {
    "gn:adm1_name":"Hyougoken",
    "gn:adm2_name":"Toyookashi",
    "gn:name":"Ootemachi",
    "iso:country":"JP",
    "wof:name":"668-0031",
    "wof:placetype":"postalcode"
},
  "geometry": {"coordinates":[134.81469999999999,35.5448],"type":"Point"}
}