{
  "type": "Feature",
  "properties": {
    "gn:adm1_name":"Gunmaken",
    "gn:adm2_name":"Sawagun'Akaborimachi",
    "gn:name":"Magarisawa",
    "iso:country":"JP",
    "wof:name":"379-2203",
    "wof:placetype":"postalcode"
},
  "geometry": {"coordinates":[139.24789999999999,36.3766],"type":"Point"}
}