{
  "type": "Feature",
  "properties": {
    "gn:adm1_name":"Ibarakiken",
    "gn:adm2_name":"Hitachishi",
    "gn:name":"Aidachou",
    "iso:country":"JP",
    "wof:name":"319-1415",
    "wof:placetype":"postalcode"
},
  "geometry": {"coordinates":[140.68559999999999,36.6281],"type":"Point"}
}