{
  "type": "Feature",
  "properties": {
    "gn:adm1_name":"Ishikawaken",
    "gn:adm2_name":"Ishikawagunnonoichimachi",
    "gn:name":"Yanagimachi",
    "iso:country":"JP",
    "wof:name":"921-8848",
    "wof:placetype":"postalcode"
},
  "geometry": {"coordinates":[136.58340000000001,36.5274],"type":"Point"}
}