{
  "type": "Feature",
  "properties": {
    "gn:adm1_name":"Toyamaken",
    "gn:adm2_name":"Higashitonamigun'Inokuchimura",
    "gn:name":"Inokuchi",
    "iso:country":"JP",
    "wof:name":"939-1877",
    "wof:placetype":"postalcode"
},
  "geometry": {"coordinates":[136.9265,36.5373],"type":"Point"}
}