{
  "type": "Feature",
  "properties": {
    "gn:adm1_name":"Aichiken",
    "gn:adm2_name":"Niwagun'Ooguchichou",
    "gn:name":"Toyota",
    "iso:country":"JP",
    "wof:name":"480-0134",
    "wof:placetype":"postalcode"
},
  "geometry": {"coordinates":[136.89019999999999,35.3093],"type":"Point"}
}