{
  "type": "Feature",
  "properties": {
    "gn:adm1_name":"Tochigiken",
    "gn:adm2_name":"Nasugunkurobanemachi",
    "gn:name":"Kurobanetamachi",
    "iso:country":"JP",
    "wof:name":"324-0233",
    "wof:placetype":"postalcode"
},
  "geometry": {"coordinates":[140.13120000000001,36.8599],"type":"Point"}
}