{
  "type": "Feature",
  "properties": {
    "gn:adm1_name":"Ibarakiken",
    "gn:adm2_name":"Tsukubashi",
    "gn:name":"Yoshinuma",
    "iso:country":"JP",
    "wof:name":"300-2617",
    "wof:placetype":"postalcode"
},
  "geometry": {"coordinates":[140.0128,36.1445],"type":"Point"}
}