{
  "type": "Feature",
  "properties": {
    "gn:adm1_name":"Kyoutofu",
    "gn:adm2_name":"Kyoutoshinakagyouku",
    "gn:name":"Yamamotochou",
    "iso:country":"JP",
    "wof:name":"604-0933",
    "wof:placetype":"postalcode"
},
  "geometry": {"coordinates":[135.76660000000001,35.013],"type":"Point"}
}