{
  "type": "Feature",
  "properties": {
    "gn:adm1_name":"Fukushimaken",
    "gn:adm2_name":"Oonumagunmishimamachi",
    "gn:name":"Nishikata",
    "iso:country":"JP",
    "wof:name":"969-7401",
    "wof:placetype":"postalcode"
},
  "geometry": {"coordinates":[139.66120000000001,37.4916],"type":"Point"}
}