{
  "type": "Feature",
  "properties": {
    "gn:adm1_name":"Mieken",
    "gn:adm2_name":"Tsushi",
    "gn:name":"Ishindentoyono",
    "iso:country":"JP",
    "wof:name":"514-0115",
    "wof:placetype":"postalcode"
},
  "geometry": {"coordinates":[136.51259999999999,34.7685],"type":"Point"}
}