{
  "type": "Feature",
  "properties": {
    "gn:adm1_name":"Kagoshimaken",
    "gn:adm2_name":"Kagoshimashi",
    "gn:name":"Higashisakamoto",
    "iso:country":"JP",
    "wof:name":"892-0861",
    "wof:placetype":"postalcode"
},
  "geometry": {"coordinates":[130.55940000000001,31.6216],"type":"Point"}
}