{
  "type": "Feature",
  "properties": {
    "gn:adm1_name":"Hyougoken",
    "gn:adm2_name":"Koubeshitarumiku",
    "gn:name":"Miyamotochou",
    "iso:country":"JP",
    "wof:name":"655-0028",
    "wof:placetype":"postalcode"
},
  "geometry": {"coordinates":[135.053,34.6285],"type":"Point"}
}