{
  "type": "Feature",
  "properties": {
    "gn:adm1_name":"Kouchiken",
    "gn:adm2_name":"Nakamurashi",
    "gn:name":"Fukaki",
    "iso:country":"JP",
    "wof:name":"787-0159",
    "wof:placetype":"postalcode"
},
  "geometry": {"coordinates":[132.95750000000001,32.9461],"type":"Point"}
}