{
  "type": "Feature",
  "properties": {
    "gn:adm1_name":"Naraken",
    "gn:adm2_name":"Kashiharashi",
    "gn:name":"Tooichichou",
    "iso:country":"JP",
    "wof:name":"634-0008",
    "wof:placetype":"postalcode"
},
  "geometry": {"coordinates":[135.8013,34.5318],"type":"Point"}
}