{
  "type": "Feature",
  "properties": {
    "gn:adm1_name":"Toyamaken",
    "gn:adm2_name":"Shimoniikawagunnyuuzenmachi",
    "gn:name":"Kimijima",
    "iso:country":"JP",
    "wof:name":"939-0614",
    "wof:placetype":"postalcode"
},
  "geometry": {"coordinates":[137.50790000000001,36.9462],"type":"Point"}
}