{
  "type": "Feature",
  "properties": {
    "gn:adm1_name":"Niigataken",
    "gn:adm2_name":"Shibatashi",
    "gn:name":"Nakakura",
    "iso:country":"JP",
    "wof:name":"959-2525",
    "wof:placetype":"postalcode"
},
  "geometry": {"coordinates":[139.38630000000001,37.9539],"type":"Point"}
}