{
  "type": "Feature",
  "properties": {
    "gn:adm1_name":"Shizuokaken",
    "gn:adm2_name":"Haibaragunkanayachou",
    "gn:name":"Oojiro",
    "iso:country":"JP",
    "wof:name":"428-0009",
    "wof:placetype":"postalcode"
},
  "geometry": {"coordinates":[138.0898,34.8529],"type":"Point"}
}