{
  "type": "Feature",
  "properties": {
    "gn:adm1_name":"Shizuokaken",
    "gn:adm2_name":"Haibaragunyoshidachou",
    "gn:name":"Sumiyoshi",
    "iso:country":"JP",
    "wof:name":"421-0301",
    "wof:placetype":"postalcode"
},
  "geometry": {"coordinates":[138.2543,34.7573],"type":"Point"}
}