{
  "type": "Feature",
  "properties": {
    "gn:adm1_name":"Shimaneken",
    "gn:adm2_name":"Yasugishi",
    "gn:name":"Kunouchou",
    "iso:country":"JP",
    "wof:name":"692-0032",
    "wof:placetype":"postalcode"
},
  "geometry": {"coordinates":[133.2595,35.403],"type":"Point"}
}