{
  "type": "Feature",
  "properties": {
    "gn:adm1_name":"Hyougoken",
    "gn:adm2_name":"Himejishi",
    "gn:name":"Fukumotomachi",
    "iso:country":"JP",
    "wof:name":"670-0004",
    "wof:placetype":"postalcode"
},
  "geometry": {"coordinates":[134.70079999999999,34.8423],"type":"Point"}
}