{
  "type": "Feature",
  "properties": {
    "gn:adm1_name":"Fukuokaken",
    "gn:adm2_name":"Munakatagunfukumamachi",
    "gn:name":"Tebika",
    "iso:country":"JP",
    "wof:name":"811-3224",
    "wof:placetype":"postalcode"
},
  "geometry": {"coordinates":[130.4982,33.7747],"type":"Point"}
}