{
  "type": "Feature",
  "properties": {
    "gn:adm1_name":"Chibaken",
    "gn:adm2_name":"Shiroishi",
    "gn:name":"Toyoichi",
    "iso:country":"JP",
    "wof:name":"270-1411",
    "wof:placetype":"postalcode"
},
  "geometry": {"coordinates":[140.09389999999999,35.8093],"type":"Point"}
}