{
  "type": "Feature",
  "properties": {
    "gn:adm1_name":"Fukushimaken",
    "gn:adm2_name":"Nihonmatsushi",
    "gn:name":"Motomachi",
    "iso:country":"JP",
    "wof:name":"964-0917",
    "wof:placetype":"postalcode"
},
  "geometry": {"coordinates":[140.43639999999999,37.5913],"type":"Point"}
}