{
  "type": "Feature",
  "properties": {
    "gn:adm1_name":"Niigataken",
    "gn:adm2_name":"Niigatashi",
    "gn:name":"Nakaoohatachou",
    "iso:country":"JP",
    "wof:name":"951-8108",
    "wof:placetype":"postalcode"
},
  "geometry": {"coordinates":[139.04140000000001,37.9255],"type":"Point"}
}