{
  "type": "Feature",
  "properties": {
    "gn:adm1_name":"Toyamaken",
    "gn:adm2_name":"Namerikawashi",
    "gn:name":"Shimizuchou",
    "iso:country":"JP",
    "wof:name":"936-0052",
    "wof:placetype":"postalcode"
},
  "geometry": {"coordinates":[137.346,36.7638],"type":"Point"}
}