{
  "type": "Feature",
  "properties": {
    "gn:adm1_name":"Miyagiken",
    "gn:adm2_name":"Kuriharaguntsukidatechou",
    "gn:name":"Akasaka",
    "iso:country":"JP",
    "wof:name":"987-2231",
    "wof:placetype":"postalcode"
},
  "geometry": {"coordinates":[141.0188,38.7212],"type":"Point"}
}