{
  "type": "Feature",
  "properties": {
    "gn:adm1_name":"Kyoutofu",
    "gn:adm2_name":"Yawatashi",
    "gn:name":"Otokoyamamatsusato",
    "iso:country":"JP",
    "wof:name":"614-8364",
    "wof:placetype":"postalcode"
},
  "geometry": {"coordinates":[135.69970000000001,34.8558],"type":"Point"}
}