{
  "type": "Feature",
  "properties": {
    "gn:adm1_name":"Aichiken",
    "gn:adm2_name":"Komakishi",
    "gn:name":"Shimoobarinakashima",
    "iso:country":"JP",
    "wof:name":"485-0051",
    "wof:placetype":"postalcode"
},
  "geometry": {"coordinates":[136.90350000000001,35.2708],"type":"Point"}
}