{
  "type": "Feature",
  "properties": {
    "gn:adm1_name":"Gifuken",
    "gn:adm2_name":"Motosugunkitagatachou",
    "gn:name":"Heisei",
    "iso:country":"JP",
    "wof:name":"501-0438",
    "wof:placetype":"postalcode"
},
  "geometry": {"coordinates":[136.68109999999999,35.4318],"type":"Point"}
}