{
  "type": "Feature",
  "properties": {
    "gn:adm1_name":"Kagawaken",
    "gn:adm2_name":"Takamatsushi",
    "gn:name":"Nishikimachi",
    "iso:country":"JP",
    "wof:name":"760-0020",
    "wof:placetype":"postalcode"
},
  "geometry": {"coordinates":[134.04339999999999,34.3472],"type":"Point"}
}