{
  "type": "Feature",
  "properties": {
    "gn:adm1_name":"Okayamaken",
    "gn:adm2_name":"Takahashishi",
    "gn:name":"Danchou",
    "iso:country":"JP",
    "wof:name":"716-0047",
    "wof:placetype":"postalcode"
},
  "geometry": {"coordinates":[133.60480000000001,34.7804],"type":"Point"}
}