{
  "type": "Feature",
  "properties": {
    "gn:adm1_name":"Shizuokaken",
    "gn:adm2_name":"Haibaragunsagarachou",
    "gn:name":"Wada",
    "iso:country":"JP",
    "wof:name":"421-0507",
    "wof:placetype":"postalcode"
},
  "geometry": {"coordinates":[138.1671,34.7212],"type":"Point"}
}