{
  "type": "Feature",
  "properties": {
    "gn:adm1_name":"Niigataken",
    "gn:adm2_name":"Shibatashi",
    "gn:name":"Kamisankou",
    "iso:country":"JP",
    "wof:name":"957-0331",
    "wof:placetype":"postalcode"
},
  "geometry": {"coordinates":[139.41470000000001,37.942],"type":"Point"}
}