{
  "type": "Feature",
  "properties": {
    "gn:adm1_name":"Fukuiken",
    "gn:adm2_name":"Nanjougun'Imajouchou",
    "gn:name":"Futatsuya",
    "iso:country":"JP",
    "wof:name":"919-0135",
    "wof:placetype":"postalcode"
},
  "geometry": {"coordinates":[136.1601,35.7508],"type":"Point"}
}