{
  "type": "Feature",
  "properties": {
    "gn:adm1_name":"Okinawaken",
    "gn:adm2_name":"Gushikawashi",
    "gn:name":"Miyazato",
    "iso:country":"JP",
    "wof:name":"904-2243",
    "wof:placetype":"postalcode"
},
  "geometry": {"coordinates":[127.8355,26.352],"type":"Point"}
}