{
  "type": "Feature",
  "properties": {
    "gn:adm1_name":"Toukyouto",
    "gn:adm2_name":"Fuchuushi",
    "gn:name":"Kitayamachou",
    "iso:country":"JP",
    "wof:name":"183-0041",
    "wof:placetype":"postalcode"
},
  "geometry": {"coordinates":[139.45660000000001,35.6879],"type":"Point"}
}