{
  "type": "Feature",
  "properties": {
    "gn:adm1_name":"Kyoutofu",
    "gn:adm2_name":"Kyoutoshisakyouku",
    "gn:name":"Shimogamonishibayashichou",
    "iso:country":"JP",
    "wof:name":"606-0817",
    "wof:placetype":"postalcode"
},
  "geometry": {"coordinates":[135.77080000000001,35.0389],"type":"Point"}
}