{
  "type": "Feature",
  "properties": {
    "gn:adm1_name":"Gifuken",
    "gn:adm2_name":"Mizunamishi",
    "gn:name":"Ikanikeisaiganaibaai",
    "iso:country":"JP",
    "wof:name":"509-6100",
    "wof:placetype":"postalcode"
},
  "geometry": {"coordinates":[137.2371,35.3749],"type":"Point"}
}