{
  "type": "Feature",
  "properties": {
    "gn:adm1_name":"Tochigiken",
    "gn:adm2_name":"Nasugunshiobaramachi",
    "gn:name":"Yumotoshiobara",
    "iso:country":"JP",
    "wof:name":"329-2922",
    "wof:placetype":"postalcode"
},
  "geometry": {"coordinates":[139.77340000000001,36.9559],"type":"Point"}
}