{
  "type": "Feature",
  "properties": {
    "gn:adm1_name":"Miyazakiken",
    "gn:adm2_name":"Kitamorokatagunmimatachou",
    "gn:name":"Gohonmatsu",
    "iso:country":"JP",
    "wof:name":"889-1902",
    "wof:placetype":"postalcode"
},
  "geometry": {"coordinates":[131.1225,31.7303],"type":"Point"}
}