{
  "type": "Feature",
  "properties": {
    "gn:adm1_name":"Gifuken",
    "gn:adm2_name":"Gifushi",
    "gn:name":"Kayabakitamachi",
    "iso:country":"JP",
    "wof:name":"502-0938",
    "wof:placetype":"postalcode"
},
  "geometry": {"coordinates":[136.73089999999999,35.4389],"type":"Point"}
}