{
  "type": "Feature",
  "properties": {
    "gn:adm1_name":"Fukuiken",
    "gn:adm2_name":"Sabaeshi",
    "gn:name":"Fujimachou",
    "iso:country":"JP",
    "wof:name":"916-0072",
    "wof:placetype":"postalcode"
},
  "geometry": {"coordinates":[136.149,35.9541],"type":"Point"}
}