{
  "type": "Feature",
  "properties": {
    "gn:adm1_name":"Miyagiken",
    "gn:adm2_name":"Iwanumashi",
    "gn:name":"Nagaoka",
    "iso:country":"JP",
    "wof:name":"989-2461",
    "wof:placetype":"postalcode"
},
  "geometry": {"coordinates":[140.84899999999999,38.1264],"type":"Point"}
}