{
  "type": "Feature",
  "properties": {
    "gn:adm1_name":"Chibaken",
    "gn:adm2_name":"Sakurashi",
    "gn:name":"Nagakuma",
    "iso:country":"JP",
    "wof:name":"285-0051",
    "wof:placetype":"postalcode"
},
  "geometry": {"coordinates":[140.2559,35.7097],"type":"Point"}
}