{
  "type": "Feature",
  "properties": {
    "gn:adm1_name":"Yamaguchiken",
    "gn:adm2_name":"Hikarishi",
    "gn:name":"Murodumijinden",
    "iso:country":"JP",
    "wof:name":"743-0006",
    "wof:placetype":"postalcode"
},
  "geometry": {"coordinates":[131.977,33.932],"type":"Point"}
}