{
  "type": "Feature",
  "properties": {
    "gn:adm1_name":"Ibarakiken",
    "gn:adm2_name":"Kasamashi",
    "gn:name":"Kurusu",
    "iso:country":"JP",
    "wof:name":"309-1625",
    "wof:placetype":"postalcode"
},
  "geometry": {"coordinates":[140.23750000000001,36.3726],"type":"Point"}
}