{
  "type": "Feature",
  "properties": {
    "gn:adm1_name":"Hyougoken",
    "gn:adm2_name":"Mikatagun'Onsenchou",
    "gn:name":"Imaoka",
    "iso:country":"JP",
    "wof:name":"669-6803",
    "wof:placetype":"postalcode"
},
  "geometry": {"coordinates":[134.4906,35.5858],"type":"Point"}
}