{
  "type": "Feature",
  "properties": {
    "gn:adm1_name":"Toyamaken",
    "gn:adm2_name":"Toyamashi",
    "gn:name":"Kitadaifujigaoka",
    "iso:country":"JP",
    "wof:name":"930-0105",
    "wof:placetype":"postalcode"
},
  "geometry": {"coordinates":[137.179,36.7158],"type":"Point"}
}