{
  "type": "Feature",
  "properties": {
    "gn:adm1_name":"Oosakafu",
    "gn:adm2_name":"Toyonakashi",
    "gn:name":"Higashitoyonakachou",
    "iso:country":"JP",
    "wof:name":"560-0003",
    "wof:placetype":"postalcode"
},
  "geometry": {"coordinates":[135.48259999999999,34.7987],"type":"Point"}
}