{
  "type": "Feature",
  "properties": {
    "gn:adm1_name":"Shigaken",
    "gn:adm2_name":"Kusatsushi",
    "gn:name":"Shinanakachou",
    "iso:country":"JP",
    "wof:name":"525-0006",
    "wof:placetype":"postalcode"
},
  "geometry": {"coordinates":[135.94130000000001,35.0523],"type":"Point"}
}