{
  "type": "Feature",
  "properties": {
    "gn:adm1_name":"Kagoshimaken",
    "gn:adm2_name":"Soogunkihokuchou",
    "gn:name":"Suwabara",
    "iso:country":"JP",
    "wof:name":"899-8512",
    "wof:placetype":"postalcode"
},
  "geometry": {"coordinates":[130.88570000000001,31.5866],"type":"Point"}
}