{
  "type": "Feature",
  "properties": {
    "gn:adm1_name":"Yamaguchiken",
    "gn:adm2_name":"Houfushi",
    "gn:name":"Minamimatsuzakichou",
    "iso:country":"JP",
    "wof:name":"747-0027",
    "wof:placetype":"postalcode"
},
  "geometry": {"coordinates":[131.578,34.0575],"type":"Point"}
}