{
  "type": "Feature",
  "properties": {
    "gn:adm1_name":"Miyagiken",
    "gn:adm2_name":"Tomeguntoyosatochou",
    "gn:name":"Kamiyachi",
    "iso:country":"JP",
    "wof:name":"987-0382",
    "wof:placetype":"postalcode"
},
  "geometry": {"coordinates":[141.2004,38.5817],"type":"Point"}
}