{
  "type": "Feature",
  "properties": {
    "gn:adm1_name":"Kyoutofu",
    "gn:adm2_name":"Kyoutoshikamigyouku",
    "gn:name":"Kodenmachou",
    "iso:country":"JP",
    "wof:name":"602-8133",
    "wof:placetype":"postalcode"
},
  "geometry": {"coordinates":[135.74969999999999,35.0181],"type":"Point"}
}