{
  "type": "Feature",
  "properties": {
    "gn:adm1_name":"Kagoshimaken",
    "gn:adm2_name":"Sooguntakarabechou",
    "gn:name":"Kitamata",
    "iso:country":"JP",
    "wof:name":"899-4102",
    "wof:placetype":"postalcode"
},
  "geometry": {"coordinates":[130.97370000000001,31.7326],"type":"Point"}
}