{
  "type": "Feature",
  "properties": {
    "gn:adm1_name":"Ehimeken",
    "gn:adm2_name":"Matsuyamashi",
    "gn:name":"Haritamachi",
    "iso:country":"JP",
    "wof:name":"790-0055",
    "wof:placetype":"postalcode"
},
  "geometry": {"coordinates":[132.7364,33.8224],"type":"Point"}
}