{
  "type": "Feature",
  "properties": {
    "gn:adm1_name":"Naganoken",
    "gn:adm2_name":"Shiojirishi",
    "gn:name":"Hirookatakaide",
    "iso:country":"JP",
    "wof:name":"399-0703",
    "wof:placetype":"postalcode"
},
  "geometry": {"coordinates":[137.95920000000001,36.1273],"type":"Point"}
}