{
  "type": "Feature",
  "properties": {
    "gn:adm1_name":"Nagasakiken",
    "gn:adm2_name":"Saseboshi",
    "gn:name":"Takebechou",
    "iso:country":"JP",
    "wof:name":"858-0911",
    "wof:placetype":"postalcode"
},
  "geometry": {"coordinates":[129.6756,33.1978],"type":"Point"}
}