{
  "type": "Feature",
  "properties": {
    "gn:adm1_name":"Fukuokaken",
    "gn:adm2_name":"Chikushinoshi",
    "gn:name":"Futsukaichinishi",
    "iso:country":"JP",
    "wof:name":"818-0071",
    "wof:placetype":"postalcode"
},
  "geometry": {"coordinates":[130.51499999999999,33.4949],"type":"Point"}
}