{
  "type": "Feature",
  "properties": {
    "gn:adm1_name":"Gifuken",
    "gn:adm2_name":"Takayamashi",
    "gn:name":"Kamikawaharamachi",
    "iso:country":"JP",
    "wof:name":"506-0024",
    "wof:placetype":"postalcode"
},
  "geometry": {"coordinates":[137.25710000000001,36.1356],"type":"Point"}
}