{
  "type": "Feature",
  "properties": {
    "gn:adm1_name":"Yamagataken",
    "gn:adm2_name":"Nishiokitamagun'Ogunimachi",
    "gn:name":"Ashimizunakazato",
    "iso:country":"JP",
    "wof:name":"999-1504",
    "wof:placetype":"postalcode"
},
  "geometry": {"coordinates":[139.7225,38.0086],"type":"Point"}
}