{
  "type": "Feature",
  "properties": {
    "gn:adm1_name":"Miyagiken",
    "gn:adm2_name":"Kattagunshichikashukumachi",
    "gn:name":"Mogazawa",
    "iso:country":"JP",
    "wof:name":"989-0601",
    "wof:placetype":"postalcode"
},
  "geometry": {"coordinates":[140.3689,38.0177],"type":"Point"}
}