{
  "type": "Feature",
  "properties": {
    "gn:adm1_name":"Miyagiken",
    "gn:adm2_name":"Oshikagun'Oshikachou",
    "gn:name":"Ooharahama",
    "iso:country":"JP",
    "wof:name":"986-2412",
    "wof:placetype":"postalcode"
},
  "geometry": {"coordinates":[141.47499999999999,38.3347],"type":"Point"}
}