{
  "type": "Feature",
  "properties": {
    "gn:adm1_name":"Okayamaken",
    "gn:adm2_name":"Kawakamigunnariwachou",
    "gn:name":"Aisaka",
    "iso:country":"JP",
    "wof:name":"716-0333",
    "wof:placetype":"postalcode"
},
  "geometry": {"coordinates":[133.47210000000001,34.7948],"type":"Point"}
}