{
  "type": "Feature",
  "properties": {
    "gn:adm1_name":"Yamagataken",
    "gn:adm2_name":"Tsuruokashi",
    "gn:name":"Nishinuma",
    "iso:country":"JP",
    "wof:name":"997-1112",
    "wof:placetype":"postalcode"
},
  "geometry": {"coordinates":[139.8115,38.7961],"type":"Point"}
}