{
  "type": "Feature",
  "properties": {
    "gn:adm1_name":"Shigaken",
    "gn:adm2_name":"Yasugunchuuzuchou",
    "gn:name":"Rokujou",
    "iso:country":"JP",
    "wof:name":"520-2412",
    "wof:placetype":"postalcode"
},
  "geometry": {"coordinates":[136.00800000000001,35.1093],"type":"Point"}
}