{
  "type": "Feature",
  "properties": {
    "gn:adm1_name":"Ehimeken",
    "gn:adm2_name":"Kitauwagunyoshidachou",
    "gn:name":"Shiroura",
    "iso:country":"JP",
    "wof:name":"799-3741",
    "wof:placetype":"postalcode"
},
  "geometry": {"coordinates":[132.52070000000001,33.303],"type":"Point"}
}