{
  "type": "Feature",
  "properties": {
    "gn:adm1_name":"Ooitaken",
    "gn:adm2_name":"Oonogunmiemachi",
    "gn:name":"Hisada",
    "iso:country":"JP",
    "wof:name":"879-7143",
    "wof:placetype":"postalcode"
},
  "geometry": {"coordinates":[131.54900000000001,32.9647],"type":"Point"}
}