{
  "type": "Feature",
  "properties": {
    "gn:adm1_name":"Mieken",
    "gn:adm2_name":"Agegun'Anouchou",
    "gn:name":"Kondoku",
    "iso:country":"JP",
    "wof:name":"514-2313",
    "wof:placetype":"postalcode"
},
  "geometry": {"coordinates":[136.44329999999999,34.7465],"type":"Point"}
}