{
  "type": "Feature",
  "properties": {
    "gn:adm1_name":"Yamanashiken",
    "gn:adm2_name":"Nakakomagunshouwachou",
    "gn:name":"Kamisukiawara",
    "iso:country":"JP",
    "wof:name":"409-3861",
    "wof:placetype":"postalcode"
},
  "geometry": {"coordinates":[138.54509999999999,35.6217],"type":"Point"}
}