{
  "type": "Feature",
  "properties": {
    "gn:adm1_name":"Niigataken",
    "gn:adm2_name":"Minamiuonumagunshiozawamachi",
    "gn:name":"Tokudashinden",
    "iso:country":"JP",
    "wof:name":"949-6422",
    "wof:placetype":"postalcode"
},
  "geometry": {"coordinates":[138.84440000000001,37.0109],"type":"Point"}
}