{
  "type": "Feature",
  "properties": {
    "gn:adm1_name":"Ibarakiken",
    "gn:adm2_name":"Moriyashi",
    "gn:name":"Ooyamashinden",
    "iso:country":"JP",
    "wof:name":"302-0103",
    "wof:placetype":"postalcode"
},
  "geometry": {"coordinates":[139.96510000000001,35.9739],"type":"Point"}
}