{
  "type": "Feature",
  "properties": {
    "gn:adm1_name":"Chibaken",
    "gn:adm2_name":"Nagareyamashi",
    "gn:name":"Edogawadaihigashi",
    "iso:country":"JP",
    "wof:name":"270-0111",
    "wof:placetype":"postalcode"
},
  "geometry": {"coordinates":[139.91220000000001,35.9006],"type":"Point"}
}