{
  "type": "Feature",
  "properties": {
    "gn:adm1_name":"Niigataken",
    "gn:adm2_name":"Sadogunkanaimachi",
    "gn:name":"Yoshiihongou",
    "iso:country":"JP",
    "wof:name":"952-1202",
    "wof:placetype":"postalcode"
},
  "geometry": {"coordinates":[138.3903,38.0502],"type":"Point"}
}