{
  "type": "Feature",
  "properties": {
    "gn:adm1_name":"Wakayamaken",
    "gn:adm2_name":"Nagagun'Iwadechou",
    "gn:name":"Souya",
    "iso:country":"JP",
    "wof:name":"649-6236",
    "wof:placetype":"postalcode"
},
  "geometry": {"coordinates":[135.30189999999999,34.2679],"type":"Point"}
}