{
  "type": "Feature",
  "properties": {
    "gn:adm1_name":"Oosakafu",
    "gn:adm2_name":"Toyonakashi",
    "gn:name":"Hounanchounishi",
    "iso:country":"JP",
    "wof:name":"561-0816",
    "wof:placetype":"postalcode"
},
  "geometry": {"coordinates":[135.48099999999999,34.75],"type":"Point"}
}