{
  "type": "Feature",
  "properties": {
    "gn:adm1_name":"Tochigiken",
    "gn:adm2_name":"Kanumashi",
    "gn:name":"Fudokorochou",
    "iso:country":"JP",
    "wof:name":"322-0033",
    "wof:placetype":"postalcode"
},
  "geometry": {"coordinates":[139.7587,36.5666],"type":"Point"}
}