{
  "type": "Feature",
  "properties": {
    "gn:adm1_name":"Aichiken",
    "gn:adm2_name":"Hoigunkozakaichou",
    "gn:name":"Ikanikeisaiganaibaai",
    "iso:country":"JP",
    "wof:name":"441-0100",
    "wof:placetype":"postalcode"
},
  "geometry": {"coordinates":[137.3586,34.806],"type":"Point"}
}