{
  "type": "Feature",
  "properties": {
    "gn:adm1_name":"Fukushimaken",
    "gn:adm2_name":"Nishishirakawagunhigashimura",
    "gn:name":"Tochimoto",
    "iso:country":"JP",
    "wof:name":"961-0307",
    "wof:placetype":"postalcode"
},
  "geometry": {"coordinates":[140.20670000000001,37.1137],"type":"Point"}
}