{
  "type": "Feature",
  "properties": {
    "gn:adm1_name":"Tottoriken",
    "gn:adm2_name":"Yazugunchiduchou",
    "gn:name":"Keijo",
    "iso:country":"JP",
    "wof:name":"689-1441",
    "wof:placetype":"postalcode"
},
  "geometry": {"coordinates":[134.22450000000001,35.222],"type":"Point"}
}