{
  "type": "Feature",
  "properties": {
    "gn:adm1_name":"Mieken",
    "gn:adm2_name":"Uenoshi",
    "gn:name":"Iyomachi",
    "iso:country":"JP",
    "wof:name":"518-0852",
    "wof:placetype":"postalcode"
},
  "geometry": {"coordinates":[136.13550000000001,34.7644],"type":"Point"}
}