{
  "type": "Feature",
  "properties": {
    "gn:adm1_name":"Fukuokaken",
    "gn:adm2_name":"Ookawashi",
    "gn:name":"Hitotsuki",
    "iso:country":"JP",
    "wof:name":"831-0034",
    "wof:placetype":"postalcode"
},
  "geometry": {"coordinates":[130.36840000000001,33.1916],"type":"Point"}
}