{
  "type": "Feature",
  "properties": {
    "gn:adm1_name":"Ishikawaken",
    "gn:adm2_name":"Wajimashi",
    "gn:name":"Machinomachiokedo",
    "iso:country":"JP",
    "wof:name":"928-0216",
    "wof:placetype":"postalcode"
},
  "geometry": {"coordinates":[137.09229999999999,37.4168],"type":"Point"}
}