{
  "type": "Feature",
  "properties": {
    "gn:adm1_name":"Aichiken",
    "gn:adm2_name":"Amagunmiwachou",
    "gn:name":"Kobashikata",
    "iso:country":"JP",
    "wof:name":"490-1212",
    "wof:placetype":"postalcode"
},
  "geometry": {"coordinates":[136.7851,35.1807],"type":"Point"}
}