{
  "type": "Feature",
  "properties": {
    "gn:adm1_name":"Aichiken",
    "gn:adm2_name":"Handashi",
    "gn:name":"Otsukawakitagawachou",
    "iso:country":"JP",
    "wof:name":"475-0047",
    "wof:placetype":"postalcode"
},
  "geometry": {"coordinates":[136.9443,34.9096],"type":"Point"}
}