{
  "type": "Feature",
  "properties": {
    "gn:adm1_name":"Kagawaken",
    "gn:adm2_name":"Ayautagun'Utaduchou",
    "gn:name":"Yoshida",
    "iso:country":"JP",
    "wof:name":"769-0221",
    "wof:placetype":"postalcode"
},
  "geometry": {"coordinates":[133.82480000000001,34.3279],"type":"Point"}
}