{
  "type": "Feature",
  "properties": {
    "gn:adm1_name":"Fukushimaken",
    "gn:adm2_name":"Shirakawashi",
    "gn:name":"Fujisawa",
    "iso:country":"JP",
    "wof:name":"961-0043",
    "wof:placetype":"postalcode"
},
  "geometry": {"coordinates":[140.2312,37.1164],"type":"Point"}
}