{
  "type": "Feature",
  "properties": {
    "gn:adm1_name":"Kyoutofu",
    "gn:adm2_name":"Fukuchiyamashi",
    "gn:name":"Marutagaoka",
    "iso:country":"JP",
    "wof:name":"620-0894",
    "wof:placetype":"postalcode"
},
  "geometry": {"coordinates":[135.124,35.2853],"type":"Point"}
}