{
  "type": "Feature",
  "properties": {
    "gn:adm1_name":"Gunmaken",
    "gn:adm2_name":"Isesakishi",
    "gn:name":"Daishoujichou",
    "iso:country":"JP",
    "wof:name":"372-0841",
    "wof:placetype":"postalcode"
},
  "geometry": {"coordinates":[139.19990000000001,36.2824],"type":"Point"}
}