{
  "type": "Feature",
  "properties": {
    "gn:adm1_name":"Mieken",
    "gn:adm2_name":"Ichishigunmikumochou",
    "gn:name":"Onoe",
    "iso:country":"JP",
    "wof:name":"515-2109",
    "wof:placetype":"postalcode"
},
  "geometry": {"coordinates":[136.51499999999999,34.6433],"type":"Point"}
}