{
  "type": "Feature",
  "properties": {
    "gn:adm1_name":"Niigataken",
    "gn:adm2_name":"Sadogun'Ogimachi",
    "gn:name":"Itsubo",
    "iso:country":"JP",
    "wof:name":"952-0626",
    "wof:placetype":"postalcode"
},
  "geometry": {"coordinates":[138.2526,37.839],"type":"Point"}
}