{
  "type": "Feature",
  "properties": {
    "gn:adm1_name":"Gunmaken",
    "gn:adm2_name":"Gunmagungunmamachi",
    "gn:name":"Ikanikeisaiganaibaai",
    "iso:country":"JP",
    "wof:name":"370-3500",
    "wof:placetype":"postalcode"
},
  "geometry": {"coordinates":[138.9539,36.4584],"type":"Point"}
}