{
  "type": "Feature",
  "properties": {
    "gn:adm1_name":"Gifuken",
    "gn:adm2_name":"Anpachigun'Anpachichou",
    "gn:name":"Moribe",
    "iso:country":"JP",
    "wof:name":"503-0114",
    "wof:placetype":"postalcode"
},
  "geometry": {"coordinates":[136.68039999999999,35.3379],"type":"Point"}
}