{
  "type": "Feature",
  "properties": {
    "gn:adm1_name":"Saitamaken",
    "gn:adm2_name":"Kawaguchishi",
    "gn:name":"Iiharachou",
    "iso:country":"JP",
    "wof:name":"332-0024",
    "wof:placetype":"postalcode"
},
  "geometry": {"coordinates":[139.70699999999999,35.7981],"type":"Point"}
}