{
  "type": "Feature",
  "properties": {
    "gn:adm1_name":"Kagawaken",
    "gn:adm2_name":"Takamatsushi",
    "gn:name":"Ootakamimachi",
    "iso:country":"JP",
    "wof:name":"761-8074",
    "wof:placetype":"postalcode"
},
  "geometry": {"coordinates":[134.04329999999999,34.2986],"type":"Point"}
}