{
  "type": "Feature",
  "properties": {
    "gn:adm1_name":"Kumamotoken",
    "gn:adm2_name":"Yatsushiroshi",
    "gn:name":"Hinaguhigashimachi",
    "iso:country":"JP",
    "wof:name":"869-5136",
    "wof:placetype":"postalcode"
},
  "geometry": {"coordinates":[130.57679999999999,32.4337],"type":"Point"}
}