{
  "type": "Feature",
  "properties": {
    "gn:adm1_name":"Okayamaken",
    "gn:adm2_name":"Maniwagunkawakamison",
    "gn:name":"Yubune",
    "iso:country":"JP",
    "wof:name":"717-0601",
    "wof:placetype":"postalcode"
},
  "geometry": {"coordinates":[133.63910000000001,35.2971],"type":"Point"}
}