{
  "type": "Feature",
  "properties": {
    "gn:adm1_name":"Wakayamaken",
    "gn:adm2_name":"Shinguushi",
    "gn:name":"Bettouyashikichou",
    "iso:country":"JP",
    "wof:name":"647-0007",
    "wof:placetype":"postalcode"
},
  "geometry": {"coordinates":[135.98560000000001,33.7287],"type":"Point"}
}