{
  "type": "Feature",
  "properties": {
    "gn:adm1_name":"Kumamotoken",
    "gn:adm2_name":"Amakusagun'Ooyanomachi",
    "gn:name":"Ikanikeisaiganaibaai",
    "iso:country":"JP",
    "wof:name":"869-3600",
    "wof:placetype":"postalcode"
},
  "geometry": {"coordinates":[130.4117,32.3953],"type":"Point"}
}