{
  "type": "Feature",
  "properties": {
    "gn:adm1_name":"Okayamaken",
    "gn:adm2_name":"Odagunbiseichou",
    "gn:name":"Utou",
    "iso:country":"JP",
    "wof:name":"714-1404",
    "wof:placetype":"postalcode"
},
  "geometry": {"coordinates":[133.5795,34.6955],"type":"Point"}
}