{
  "type": "Feature",
  "properties": {
    "gn:adm1_name":"Fukuiken",
    "gn:adm2_name":"Imadategun'Ikedachou",
    "gn:name":"Inari",
    "iso:country":"JP",
    "wof:name":"910-2512",
    "wof:placetype":"postalcode"
},
  "geometry": {"coordinates":[136.34370000000001,35.8888],"type":"Point"}
}