{
  "type": "Feature",
  "properties": {
    "gn:adm1_name":"Niigataken",
    "gn:adm2_name":"Niigatashi",
    "gn:name":"Koshinnishi",
    "iso:country":"JP",
    "wof:name":"950-2024",
    "wof:placetype":"postalcode"
},
  "geometry": {"coordinates":[138.99250000000001,37.8757],"type":"Point"}
}