{
  "type": "Feature",
  "properties": {
    "gn:adm1_name":"Niigataken",
    "gn:adm2_name":"Gosenshi",
    "gn:name":"Ogisone",
    "iso:country":"JP",
    "wof:name":"959-1852",
    "wof:placetype":"postalcode"
},
  "geometry": {"coordinates":[139.16460000000001,37.7406],"type":"Point"}
}