{
  "type": "Feature",
  "properties": {
    "gn:adm1_name":"Fukuokaken",
    "gn:adm2_name":"Fukuokashihigashiku",
    "gn:name":"Najima",
    "iso:country":"JP",
    "wof:name":"813-0043",
    "wof:placetype":"postalcode"
},
  "geometry": {"coordinates":[130.43090000000001,33.6427],"type":"Point"}
}