{
  "type": "Feature",
  "properties": {
    "gn:adm1_name":"Mieken",
    "gn:adm2_name":"Yokkaichishi",
    "gn:name":"Nishimachi",
    "iso:country":"JP",
    "wof:name":"510-0089",
    "wof:placetype":"postalcode"
},
  "geometry": {"coordinates":[136.62270000000001,34.9721],"type":"Point"}
}