{
  "type": "Feature",
  "properties": {
    "gn:adm1_name":"Ishikawaken",
    "gn:adm2_name":"Kanazawashi",
    "gn:name":"Fukuhisahigashi",
    "iso:country":"JP",
    "wof:name":"920-3123",
    "wof:placetype":"postalcode"
},
  "geometry": {"coordinates":[136.68270000000001,36.6159],"type":"Point"}
}