{
  "type": "Feature",
  "properties": {
    "gn:adm1_name":"Fukushimaken",
    "gn:adm2_name":"Higashishirakawagunhanawamachi",
    "gn:name":"Katakai",
    "iso:country":"JP",
    "wof:name":"963-5522",
    "wof:placetype":"postalcode"
},
  "geometry": {"coordinates":[140.52170000000001,36.8824],"type":"Point"}
}