{
  "type": "Feature",
  "properties": {
    "gn:adm1_name":"Shizuokaken",
    "gn:adm2_name":"Shizuokashi",
    "gn:name":"Shimizutakahashichou",
    "iso:country":"JP",
    "wof:name":"424-0048",
    "wof:placetype":"postalcode"
},
  "geometry": {"coordinates":[138.46789999999999,35.0244],"type":"Point"}
}