{
  "type": "Feature",
  "properties": {
    "gn:adm1_name":"Sagaken",
    "gn:adm2_name":"Sagashi",
    "gn:name":"Gofukumotomachi",
    "iso:country":"JP",
    "wof:name":"840-0824",
    "wof:placetype":"postalcode"
},
  "geometry": {"coordinates":[130.304,33.2544],"type":"Point"}
}