{
  "type": "Feature",
  "properties": {
    "gn:adm1_name":"Fukushimaken",
    "gn:adm2_name":"Soumagun'Iitatemura",
    "gn:name":"Fukaya",
    "iso:country":"JP",
    "wof:name":"960-1802",
    "wof:placetype":"postalcode"
},
  "geometry": {"coordinates":[140.73330000000001,37.6989],"type":"Point"}
}