{
  "type": "Feature",
  "properties": {
    "gn:adm1_name":"Niigataken",
    "gn:adm2_name":"Nishikanbaragun'Iwamuromura",
    "gn:name":"Katagami",
    "iso:country":"JP",
    "wof:name":"953-0114",
    "wof:placetype":"postalcode"
},
  "geometry": {"coordinates":[138.8621,37.7313],"type":"Point"}
}