{
  "type": "Feature",
  "properties": {
    "gn:adm1_name":"Hiroshimaken",
    "gn:adm2_name":"Hiroshimashisaekiku",
    "gn:name":"Rakurakuen",
    "iso:country":"JP",
    "wof:name":"731-5136",
    "wof:placetype":"postalcode"
},
  "geometry": {"coordinates":[132.3535,34.3624],"type":"Point"}
}