{
  "type": "Feature",
  "properties": {
    "gn:adm1_name":"Oosakafu",
    "gn:adm2_name":"Hirakatashi",
    "gn:name":"Sugiyamate",
    "iso:country":"JP",
    "wof:name":"573-0118",
    "wof:placetype":"postalcode"
},
  "geometry": {"coordinates":[135.7218,34.816],"type":"Point"}
}