{
  "type": "Feature",
  "properties": {
    "gn:adm1_name":"Shizuokaken",
    "gn:adm2_name":"Iwatagun'Asabachou",
    "gn:name":"Niibori",
    "iso:country":"JP",
    "wof:name":"437-1104",
    "wof:placetype":"postalcode"
},
  "geometry": {"coordinates":[137.934,34.6965],"type":"Point"}
}