{
  "type": "Feature",
  "properties": {
    "gn:adm1_name":"Niigataken",
    "gn:adm2_name":"Kitakanbaragunkyougasemura",
    "gn:name":"Iimorisugi",
    "iso:country":"JP",
    "wof:name":"959-2122",
    "wof:placetype":"postalcode"
},
  "geometry": {"coordinates":[139.1902,37.8382],"type":"Point"}
}