{
  "type": "Feature",
  "properties": {
    "gn:adm1_name":"Ibarakiken",
    "gn:adm2_name":"Sashimagunsouwamachi",
    "gn:name":"Komahane",
    "iso:country":"JP",
    "wof:name":"306-0221",
    "wof:placetype":"postalcode"
},
  "geometry": {"coordinates":[139.7576,36.1667],"type":"Point"}
}