{
  "type": "Feature",
  "properties": {
    "gn:adm1_name":"Kumamotoken",
    "gn:adm2_name":"Kamimashikigunkashimamachi",
    "gn:name":"Shimonakama",
    "iso:country":"JP",
    "wof:name":"861-3108",
    "wof:placetype":"postalcode"
},
  "geometry": {"coordinates":[130.71809999999999,32.7402],"type":"Point"}
}