{
  "type": "Feature",
  "properties": {
    "gn:adm1_name":"Shizuokaken",
    "gn:adm2_name":"Hamamatsushi",
    "gn:name":"Toyookachou",
    "iso:country":"JP",
    "wof:name":"433-8103",
    "wof:placetype":"postalcode"
},
  "geometry": {"coordinates":[137.72730000000001,34.7895],"type":"Point"}
}