{
  "type": "Feature",
  "properties": {
    "gn:adm1_name":"Hyougoken",
    "gn:adm2_name":"Yabugunyoukachou",
    "gn:name":"Asakura",
    "iso:country":"JP",
    "wof:name":"667-0024",
    "wof:placetype":"postalcode"
},
  "geometry": {"coordinates":[134.76310000000001,35.3954],"type":"Point"}
}