{
  "type": "Feature",
  "properties": {
    "gn:adm1_name":"Shizuokaken",
    "gn:adm2_name":"Hamakitashi",
    "gn:name":"Uchino",
    "iso:country":"JP",
    "wof:name":"434-0044",
    "wof:placetype":"postalcode"
},
  "geometry": {"coordinates":[137.75710000000001,34.7828],"type":"Point"}
}