{
  "type": "Feature",
  "properties": {
    "gn:adm1_name":"Ooitaken",
    "gn:adm2_name":"Oonogun'Oonomachi",
    "gn:name":"Tanaka",
    "iso:country":"JP",
    "wof:name":"879-6441",
    "wof:placetype":"postalcode"
},
  "geometry": {"coordinates":[131.50069999999999,33.0411],"type":"Point"}
}