{
  "type": "Feature",
  "properties": {
    "gn:adm1_name":"Kanagawaken",
    "gn:adm2_name":"Atsugishi",
    "gn:name":"Okata",
    "iso:country":"JP",
    "wof:name":"243-0021",
    "wof:placetype":"postalcode"
},
  "geometry": {"coordinates":[139.36410000000001,35.4254],"type":"Point"}
}