{
  "type": "Feature",
  "properties": {
    "gn:adm1_name":"Fukushimaken",
    "gn:adm2_name":"Aiduwakamatsushi",
    "gn:name":"Higashinengu",
    "iso:country":"JP",
    "wof:name":"965-0839",
    "wof:placetype":"postalcode"
},
  "geometry": {"coordinates":[139.92760000000001,37.4741],"type":"Point"}
}