{
  "type": "Feature",
  "properties": {
    "gn:adm1_name":"Kumamotoken",
    "gn:adm2_name":"Ashikitagun'Ashikitamachi",
    "gn:name":"Sashiki",
    "iso:country":"JP",
    "wof:name":"869-5441",
    "wof:placetype":"postalcode"
},
  "geometry": {"coordinates":[130.50530000000001,32.3026],"type":"Point"}
}