{
  "type": "Feature",
  "properties": {
    "gn:adm1_name":"Fukushimaken",
    "gn:adm2_name":"Dategunkawamatamachi",
    "gn:name":"Miyanowaki",
    "iso:country":"JP",
    "wof:name":"960-1464",
    "wof:placetype":"postalcode"
},
  "geometry": {"coordinates":[140.59739999999999,37.6681],"type":"Point"}
}