{
  "type": "Feature",
  "properties": {
    "gn:adm1_name":"Toyamaken",
    "gn:adm2_name":"Toyamashi",
    "gn:name":"Hongoushin",
    "iso:country":"JP",
    "wof:name":"939-8046",
    "wof:placetype":"postalcode"
},
  "geometry": {"coordinates":[137.2302,36.6694],"type":"Point"}
}