{
  "type": "Feature",
  "properties": {
    "gn:adm1_name":"Wakayamaken",
    "gn:adm2_name":"Hidakagunkawabechou",
    "gn:name":"Nakatsukawa",
    "iso:country":"JP",
    "wof:name":"649-1325",
    "wof:placetype":"postalcode"
},
  "geometry": {"coordinates":[135.2004,33.943],"type":"Point"}
}