{
  "type": "Feature",
  "properties": {
    "gn:adm1_name":"Okayamaken",
    "gn:adm2_name":"Tsuyamashi",
    "gn:name":"Kawasaki",
    "iso:country":"JP",
    "wof:name":"708-0841",
    "wof:placetype":"postalcode"
},
  "geometry": {"coordinates":[134.02940000000001,35.0614],"type":"Point"}
}