{
  "type": "Feature",
  "properties": {
    "gn:adm1_name":"Tochigiken",
    "gn:adm2_name":"Utsunomiyashi",
    "gn:name":"Yaitamachi",
    "iso:country":"JP",
    "wof:name":"321-0112",
    "wof:placetype":"postalcode"
},
  "geometry": {"coordinates":[139.89830000000001,36.5137],"type":"Point"}
}