{
  "type": "Feature",
  "properties": {
    "gn:adm1_name":"Shigaken",
    "gn:adm2_name":"Hikoneshi",
    "gn:name":"Shimoinabachou",
    "iso:country":"JP",
    "wof:name":"521-1132",
    "wof:placetype":"postalcode"
},
  "geometry": {"coordinates":[136.17910000000001,35.2004],"type":"Point"}
}