{
  "type": "Feature",
  "properties": {
    "gn:adm1_name":"Miyagiken",
    "gn:adm2_name":"Motoyoshigunshidugawachou",
    "gn:name":"Fukada",
    "iso:country":"JP",
    "wof:name":"986-0715",
    "wof:placetype":"postalcode"
},
  "geometry": {"coordinates":[141.47409999999999,38.687],"type":"Point"}
}