{
  "type": "Feature",
  "properties": {
    "gn:adm1_name":"Ishikawaken",
    "gn:adm2_name":"Suzushi",
    "gn:name":"Houryuumachiukai",
    "iso:country":"JP",
    "wof:name":"927-1222",
    "wof:placetype":"postalcode"
},
  "geometry": {"coordinates":[137.24039999999999,37.4021],"type":"Point"}
}