{
  "type": "Feature",
  "properties": {
    "gn:adm1_name":"Fukuiken",
    "gn:adm2_name":"Oonoshi",
    "gn:name":"Shoubayashi",
    "iso:country":"JP",
    "wof:name":"912-0006",
    "wof:placetype":"postalcode"
},
  "geometry": {"coordinates":[136.49090000000001,36.0025],"type":"Point"}
}