{
  "type": "Feature",
  "properties": {
    "gn:adm1_name":"Oosakafu",
    "gn:adm2_name":"Takatsukishi",
    "gn:name":"Karasakikita",
    "iso:country":"JP",
    "wof:name":"569-0831",
    "wof:placetype":"postalcode"
},
  "geometry": {"coordinates":[135.61320000000001,34.8187],"type":"Point"}
}