{
  "type": "Feature",
  "properties": {
    "gn:adm1_name":"Hyougoken",
    "gn:adm2_name":"Nishinomiyashi",
    "gn:name":"Jingikanchou",
    "iso:country":"JP",
    "wof:name":"662-0843",
    "wof:placetype":"postalcode"
},
  "geometry": {"coordinates":[135.3528,34.7398],"type":"Point"}
}