{
  "type": "Feature",
  "properties": {
    "gn:adm1_name":"Miyagiken",
    "gn:adm2_name":"Kesennumashi",
    "gn:name":"Akaiwatateshita",
    "iso:country":"JP",
    "wof:name":"988-0101",
    "wof:placetype":"postalcode"
},
  "geometry": {"coordinates":[141.57159999999999,38.8889],"type":"Point"}
}