{
  "type": "Feature",
  "properties": {
    "gn:adm1_name":"Ibarakiken",
    "gn:adm2_name":"Inashikigunmihomura",
    "gn:name":"Okitsu",
    "iso:country":"JP",
    "wof:name":"300-0425",
    "wof:placetype":"postalcode"
},
  "geometry": {"coordinates":[140.30179999999999,35.9964],"type":"Point"}
}