{
  "type": "Feature",
  "properties": {
    "gn:adm1_name":"Toukyouto",
    "gn:adm2_name":"Taitouku",
    "gn:name":"Kitaueno",
    "iso:country":"JP",
    "wof:name":"110-0014",
    "wof:placetype":"postalcode"
},
  "geometry": {"coordinates":[139.78380000000001,35.7172],"type":"Point"}
}