{
  "type": "Feature",
  "properties": {
    "gn:adm1_name":"Yamanashiken",
    "gn:adm2_name":"Kitakomagunmukawamura",
    "gn:name":"Mifuki",
    "iso:country":"JP",
    "wof:name":"408-0301",
    "wof:placetype":"postalcode"
},
  "geometry": {"coordinates":[138.37200000000001,35.7909],"type":"Point"}
}