{
  "type": "Feature",
  "properties": {
    "gn:adm1_name":"Tochigiken",
    "gn:adm2_name":"Yaitashi",
    "gn:name":"Honchou",
    "iso:country":"JP",
    "wof:name":"329-2164",
    "wof:placetype":"postalcode"
},
  "geometry": {"coordinates":[139.9263,36.8084],"type":"Point"}
}