{
  "type": "Feature",
  "properties": {
    "gn:adm1_name":"Niigataken",
    "gn:adm2_name":"Nishikanbaragunnakanokuchimura",
    "gn:name":"Kouma",
    "iso:country":"JP",
    "wof:name":"950-1342",
    "wof:placetype":"postalcode"
},
  "geometry": {"coordinates":[138.9648,37.7272],"type":"Point"}
}