{
  "type": "Feature",
  "properties": {
    "gn:adm1_name":"Shizuokaken",
    "gn:adm2_name":"Mishimashi",
    "gn:name":"Nishihonchou",
    "iso:country":"JP",
    "wof:name":"411-0847",
    "wof:placetype":"postalcode"
},
  "geometry": {"coordinates":[138.90870000000001,35.1177],"type":"Point"}
}