{
  "type": "Feature",
  "properties": {
    "gn:adm1_name":"Yamanashiken",
    "gn:adm2_name":"Enzanshi",
    "gn:name":"Kamiozo",
    "iso:country":"JP",
    "wof:name":"404-0042",
    "wof:placetype":"postalcode"
},
  "geometry": {"coordinates":[138.72640000000001,35.7079],"type":"Point"}
}