{
  "type": "Feature",
  "properties": {
    "gn:adm1_name":"Shizuokaken",
    "gn:adm2_name":"Fujiedashi",
    "gn:name":"Seinanchou",
    "iso:country":"JP",
    "wof:name":"426-0063",
    "wof:placetype":"postalcode"
},
  "geometry": {"coordinates":[138.23660000000001,34.8357],"type":"Point"}
}