{
  "type": "Feature",
  "properties": {
    "gn:adm1_name":"Okayamaken",
    "gn:adm2_name":"Tsuyamashi",
    "gn:name":"Minamimachi",
    "iso:country":"JP",
    "wof:name":"708-0881",
    "wof:placetype":"postalcode"
},
  "geometry": {"coordinates":[134.0025,35.0556],"type":"Point"}
}