{
  "type": "Feature",
  "properties": {
    "gn:adm1_name":"Shizuokaken",
    "gn:adm2_name":"Haibaragunkanayachou",
    "gn:name":"Shima",
    "iso:country":"JP",
    "wof:name":"428-0007",
    "wof:placetype":"postalcode"
},
  "geometry": {"coordinates":[138.1268,34.8408],"type":"Point"}
}