{
  "type": "Feature",
  "properties": {
    "gn:adm1_name":"Hyougoken",
    "gn:adm2_name":"Takaradukashi",
    "gn:name":"Nakanochou",
    "iso:country":"JP",
    "wof:name":"665-0056",
    "wof:placetype":"postalcode"
},
  "geometry": {"coordinates":[135.35560000000001,34.7867],"type":"Point"}
}