{
  "type": "Feature",
  "properties": {
    "gn:adm1_name":"Hiroshimaken",
    "gn:adm2_name":"Seragunserachou",
    "gn:name":"Nakabara",
    "iso:country":"JP",
    "wof:name":"722-1623",
    "wof:placetype":"postalcode"
},
  "geometry": {"coordinates":[133.0155,34.5828],"type":"Point"}
}