{
  "type": "Feature",
  "properties": {
    "gn:adm1_name":"Mieken",
    "gn:adm2_name":"Yokkaichishi",
    "gn:name":"Minaminayachou",
    "iso:country":"JP",
    "wof:name":"510-0043",
    "wof:placetype":"postalcode"
},
  "geometry": {"coordinates":[136.6335,34.9624],"type":"Point"}
}