{
  "type": "Feature",
  "properties": {
    "gn:adm1_name":"Aichiken",
    "gn:adm2_name":"Nagoyashimoriyamaku",
    "gn:name":"Obatakita",
    "iso:country":"JP",
    "wof:name":"463-0008",
    "wof:placetype":"postalcode"
},
  "geometry": {"coordinates":[136.98650000000001,35.2145],"type":"Point"}
}