{
  "type": "Feature",
  "properties": {
    "gn:adm1_name":"Shimaneken",
    "gn:adm2_name":"Iishigun'Akagichou",
    "gn:name":"Kamikijima",
    "iso:country":"JP",
    "wof:name":"690-3405",
    "wof:placetype":"postalcode"
},
  "geometry": {"coordinates":[132.7345,35.0215],"type":"Point"}
}