{
  "type": "Feature",
  "properties": {
    "gn:adm1_name":"Toukyouto",
    "gn:adm2_name":"Hamurashi",
    "gn:name":"Hanekami",
    "iso:country":"JP",
    "wof:name":"205-0016",
    "wof:placetype":"postalcode"
},
  "geometry": {"coordinates":[139.3032,35.7664],"type":"Point"}
}