{
  "type": "Feature",
  "properties": {
    "gn:adm1_name":"Okayamaken",
    "gn:adm2_name":"Takahashishi",
    "gn:name":"Matsubarachouooduyori",
    "iso:country":"JP",
    "wof:name":"716-0065",
    "wof:placetype":"postalcode"
},
  "geometry": {"coordinates":[133.5608,34.8135],"type":"Point"}
}