{
  "type": "Feature",
  "properties": {
    "gn:adm1_name":"Chibaken",
    "gn:adm2_name":"Ichiharashi",
    "gn:name":"Gosho",
    "iso:country":"JP",
    "wof:name":"290-0066",
    "wof:placetype":"postalcode"
},
  "geometry": {"coordinates":[140.11160000000001,35.5305],"type":"Point"}
}