{
  "type": "Feature",
  "properties": {
    "gn:adm1_name":"Gifuken",
    "gn:adm2_name":"Oogakishi",
    "gn:name":"Yonokidochou",
    "iso:country":"JP",
    "wof:name":"503-2222",
    "wof:placetype":"postalcode"
},
  "geometry": {"coordinates":[136.56129999999999,35.3787],"type":"Point"}
}