{
  "type": "Feature",
  "properties": {
    "gn:adm1_name":"Okayamaken",
    "gn:adm2_name":"Wakegunwakechou",
    "gn:name":"Shakuso",
    "iso:country":"JP",
    "wof:name":"709-0422",
    "wof:placetype":"postalcode"
},
  "geometry": {"coordinates":[134.15880000000001,34.8014],"type":"Point"}
}