{
  "type": "Feature",
  "properties": {
    "gn:adm1_name":"Aichiken",
    "gn:adm2_name":"Kounanshi",
    "gn:name":"Akadoujichouminamino",
    "iso:country":"JP",
    "wof:name":"483-8167",
    "wof:placetype":"postalcode"
},
  "geometry": {"coordinates":[136.8733,35.3336],"type":"Point"}
}