{
  "type": "Feature",
  "properties": {
    "gn:adm1_name":"Yamagataken",
    "gn:adm2_name":"Shinjoushi",
    "gn:name":"Senmonchou",
    "iso:country":"JP",
    "wof:name":"996-0079",
    "wof:placetype":"postalcode"
},
  "geometry": {"coordinates":[140.28700000000001,38.7614],"type":"Point"}
}