{
  "type": "Feature",
  "properties": {
    "gn:adm1_name":"Kagoshimaken",
    "gn:adm2_name":"Kanoyashi",
    "gn:name":"Kotobuki",
    "iso:country":"JP",
    "wof:name":"893-0014",
    "wof:placetype":"postalcode"
},
  "geometry": {"coordinates":[130.86850000000001,31.3863],"type":"Point"}
}