{
  "type": "Feature",
  "properties": {
    "gn:adm1_name":"Fukuokaken",
    "gn:adm2_name":"Kogashi",
    "gn:name":"Kadurugaoka",
    "iso:country":"JP",
    "wof:name":"811-3104",
    "wof:placetype":"postalcode"
},
  "geometry": {"coordinates":[130.46709999999999,33.7255],"type":"Point"}
}