{
  "type": "Feature",
  "properties": {
    "gn:adm1_name":"Yamaguchiken",
    "gn:adm2_name":"Ooshimagun'Ooshimachou",
    "gn:name":"Nishimigama",
    "iso:country":"JP",
    "wof:name":"742-2101",
    "wof:placetype":"postalcode"
},
  "geometry": {"coordinates":[132.2098,33.9441],"type":"Point"}
}