{
  "type": "Feature",
  "properties": {
    "gn:adm1_name":"Toukyouto",
    "gn:adm2_name":"Choufushi",
    "gn:name":"Jindaijikitamachi",
    "iso:country":"JP",
    "wof:name":"182-0011",
    "wof:placetype":"postalcode"
},
  "geometry": {"coordinates":[139.54859999999999,35.6774],"type":"Point"}
}