{
  "type": "Feature",
  "properties": {
    "gn:adm1_name":"Tokushimaken",
    "gn:adm2_name":"Tokushimashi",
    "gn:name":"Hachimanchou(Ootsubo)",
    "iso:country":"JP",
    "wof:name":"770-8079",
    "wof:placetype":"postalcode"
},
  "geometry": {"coordinates":[134.52789999999999,34.0452],"type":"Point"}
}