{
  "type": "Feature",
  "properties": {
    "gn:adm1_name":"Ooitaken",
    "gn:adm2_name":"Nakatsushi",
    "gn:name":"Shinbori",
    "iso:country":"JP",
    "wof:name":"871-0069",
    "wof:placetype":"postalcode"
},
  "geometry": {"coordinates":[131.1925,33.6059],"type":"Point"}
}