{
  "type": "Feature",
  "properties": {
    "gn:adm1_name":"Aichiken",
    "gn:adm2_name":"Nagoyashimizuhoku",
    "gn:name":"Katasakachou",
    "iso:country":"JP",
    "wof:name":"467-0052",
    "wof:placetype":"postalcode"
},
  "geometry": {"coordinates":[136.9453,35.1165],"type":"Point"}
}