{
  "type": "Feature",
  "properties": {
    "gn:adm1_name":"Hyougoken",
    "gn:adm2_name":"Takasagoshi",
    "gn:name":"Takasagochoumatsunamichou",
    "iso:country":"JP",
    "wof:name":"676-0023",
    "wof:placetype":"postalcode"
},
  "geometry": {"coordinates":[134.79650000000001,34.7527],"type":"Point"}
}