{
  "type": "Feature",
  "properties": {
    "gn:adm1_name":"Sagaken",
    "gn:adm2_name":"Miyakigunkitashigeyasuchou",
    "gn:name":"Higashio",
    "iso:country":"JP",
    "wof:name":"849-0113",
    "wof:placetype":"postalcode"
},
  "geometry": {"coordinates":[130.45519999999999,33.3273],"type":"Point"}
}