{
  "type": "Feature",
  "properties": {
    "gn:adm1_name":"Chibaken",
    "gn:adm2_name":"Inbagunsakaemachi",
    "gn:name":"Nishi",
    "iso:country":"JP",
    "wof:name":"270-1534",
    "wof:placetype":"postalcode"
},
  "geometry": {"coordinates":[140.1798,35.8441],"type":"Point"}
}