{
  "type": "Feature",
  "properties": {
    "gn:adm1_name":"Chibaken",
    "gn:adm2_name":"Naritashi",
    "gn:name":"Kinone(Sonota)",
    "iso:country":"JP",
    "wof:name":"286-0105",
    "wof:placetype":"postalcode"
},
  "geometry": {"coordinates":[140.39169999999999,35.764],"type":"Point"}
}