{
  "type": "Feature",
  "properties": {
    "gn:adm1_name":"Toukyouto",
    "gn:adm2_name":"Hinoshi",
    "gn:name":"Takahata",
    "iso:country":"JP",
    "wof:name":"191-0031",
    "wof:placetype":"postalcode"
},
  "geometry": {"coordinates":[139.41290000000001,35.662],"type":"Point"}
}