{
  "type": "Feature",
  "properties": {
    "gn:adm1_name":"Fukuokaken",
    "gn:adm2_name":"Chikushigunnakagawamachi",
    "gn:name":"Eko",
    "iso:country":"JP",
    "wof:name":"811-1255",
    "wof:placetype":"postalcode"
},
  "geometry": {"coordinates":[130.41650000000001,33.5136],"type":"Point"}
}