{
  "type": "Feature",
  "properties": {
    "gn:adm1_name":"Aichiken",
    "gn:adm2_name":"Okazakishi",
    "gn:name":"Idaminamimachi",
    "iso:country":"JP",
    "wof:name":"444-0068",
    "wof:placetype":"postalcode"
},
  "geometry": {"coordinates":[137.16139999999999,34.9749],"type":"Point"}
}