{
  "type": "Feature",
  "properties": {
    "gn:adm1_name":"Hyougoken",
    "gn:adm2_name":"Izushigun'Izushichou",
    "gn:name":"Hinobe",
    "iso:country":"JP",
    "wof:name":"668-0246",
    "wof:placetype":"postalcode"
},
  "geometry": {"coordinates":[134.88290000000001,35.4509],"type":"Point"}
}