{
  "type": "Feature",
  "properties": {
    "gn:adm1_name":"Oosakafu",
    "gn:adm2_name":"Sennangunmisakichou",
    "gn:name":"Ikanikeisaiganaibaai",
    "iso:country":"JP",
    "wof:name":"599-0300",
    "wof:placetype":"postalcode"
},
  "geometry": {"coordinates":[135.154,34.3211],"type":"Point"}
}