{
  "type": "Feature",
  "properties": {
    "gn:adm1_name":"Hyougoken",
    "gn:adm2_name":"Tsunagunhokudanchou",
    "gn:name":"Tonouchi",
    "iso:country":"JP",
    "wof:name":"656-1743",
    "wof:placetype":"postalcode"
},
  "geometry": {"coordinates":[134.9091,34.5303],"type":"Point"}
}