{
  "type": "Feature",
  "properties": {
    "gn:adm1_name":"Fukushimaken",
    "gn:adm2_name":"Soumagun'Iitatemura",
    "gn:name":"Ookura",
    "iso:country":"JP",
    "wof:name":"960-1814",
    "wof:placetype":"postalcode"
},
  "geometry": {"coordinates":[140.80369999999999,37.7332],"type":"Point"}
}