{
  "type": "Feature",
  "properties": {
    "gn:adm1_name":"Ishikawaken",
    "gn:adm2_name":"Komatsushi",
    "gn:name":"Akebonomachi",
    "iso:country":"JP",
    "wof:name":"923-0035",
    "wof:placetype":"postalcode"
},
  "geometry": {"coordinates":[136.47640000000001,36.4255],"type":"Point"}
}