{
  "type": "Feature",
  "properties": {
    "gn:adm1_name":"Kagawaken",
    "gn:adm2_name":"Takamatsushi",
    "gn:name":"Furujinmachi",
    "iso:country":"JP",
    "wof:name":"760-0025",
    "wof:placetype":"postalcode"
},
  "geometry": {"coordinates":[134.04820000000001,34.3457],"type":"Point"}
}