{
  "type": "Feature",
  "properties": {
    "gn:adm1_name":"Miyazakiken",
    "gn:adm2_name":"Nobeokashi",
    "gn:name":"Atagoyama",
    "iso:country":"JP",
    "wof:name":"882-0871",
    "wof:placetype":"postalcode"
},
  "geometry": {"coordinates":[131.65309999999999,32.5603],"type":"Point"}
}