{
  "type": "Feature",
  "properties": {
    "gn:adm1_name":"Toyamaken",
    "gn:adm2_name":"Nakaniikawagunfunahashimura",
    "gn:name":"Busshouji",
    "iso:country":"JP",
    "wof:name":"930-0282",
    "wof:placetype":"postalcode"
},
  "geometry": {"coordinates":[137.30699999999999,36.7019],"type":"Point"}
}