{
  "type": "Feature",
  "properties": {
    "gn:adm1_name":"Okayamaken",
    "gn:adm2_name":"Okayamashi",
    "gn:name":"Imamura",
    "iso:country":"JP",
    "wof:name":"700-0974",
    "wof:placetype":"postalcode"
},
  "geometry": {"coordinates":[133.8963,34.6398],"type":"Point"}
}