{
  "type": "Feature",
  "properties": {
    "gn:adm1_name":"Hyougoken",
    "gn:adm2_name":"Himejishi",
    "gn:name":"Katsuharakukatsuyamachou",
    "iso:country":"JP",
    "wof:name":"671-1202",
    "wof:placetype":"postalcode"
},
  "geometry": {"coordinates":[134.60470000000001,34.8173],"type":"Point"}
}