{
  "type": "Feature",
  "properties": {
    "gn:adm1_name":"Tochigiken",
    "gn:adm2_name":"Nasugunnasumachi",
    "gn:name":"Numanoi",
    "iso:country":"JP",
    "wof:name":"329-3446",
    "wof:placetype":"postalcode"
},
  "geometry": {"coordinates":[140.13460000000001,36.9542],"type":"Point"}
}