{
  "type": "Feature",
  "properties": {
    "gn:adm1_name":"Hyougoken",
    "gn:adm2_name":"Miharagunseidanchou",
    "gn:name":"Shichitatara",
    "iso:country":"JP",
    "wof:name":"656-0322",
    "wof:placetype":"postalcode"
},
  "geometry": {"coordinates":[134.74189999999999,34.3006],"type":"Point"}
}