{
  "type": "Feature",
  "properties": {
    "gn:adm1_name":"Tottoriken",
    "gn:adm2_name":"Yazugunhattouchou",
    "gn:name":"Shigeeda",
    "iso:country":"JP",
    "wof:name":"680-0606",
    "wof:placetype":"postalcode"
},
  "geometry": {"coordinates":[134.34870000000001,35.3632],"type":"Point"}
}