{
  "type": "Feature",
  "properties": {
    "gn:adm1_name":"Niigataken",
    "gn:adm2_name":"Mitsukeshi",
    "gn:name":"Kuzumaki",
    "iso:country":"JP",
    "wof:name":"954-0058",
    "wof:placetype":"postalcode"
},
  "geometry": {"coordinates":[138.9127,37.5261],"type":"Point"}
}