{
  "type": "Feature",
  "properties": {
    "gn:adm1_name":"Aichiken",
    "gn:adm2_name":"Komakishi",
    "gn:name":"Mama",
    "iso:country":"JP",
    "wof:name":"485-0015",
    "wof:placetype":"postalcode"
},
  "geometry": {"coordinates":[136.91079999999999,35.2976],"type":"Point"}
}