{
  "type": "Feature",
  "properties": {
    "gn:adm1_name":"Chibaken",
    "gn:adm2_name":"Chouseigunnagaramachi",
    "gn:name":"Nagadomi",
    "iso:country":"JP",
    "wof:name":"297-0214",
    "wof:placetype":"postalcode"
},
  "geometry": {"coordinates":[140.22980000000001,35.4293],"type":"Point"}
}