{
  "type": "Feature",
  "properties": {
    "gn:adm1_name":"Niigataken",
    "gn:adm2_name":"Ryoutsushi",
    "gn:name":"Kujikawachi",
    "iso:country":"JP",
    "wof:name":"952-3423",
    "wof:placetype":"postalcode"
},
  "geometry": {"coordinates":[138.46879999999999,38.044],"type":"Point"}
}