{
  "type": "Feature",
  "properties": {
    "gn:adm1_name":"Hyougoken",
    "gn:adm2_name":"Himejishi",
    "gn:name":"Shikamakutamachi",
    "iso:country":"JP",
    "wof:name":"672-8052",
    "wof:placetype":"postalcode"
},
  "geometry": {"coordinates":[134.6764,34.7996],"type":"Point"}
}