{
  "type": "Feature",
  "properties": {
    "gn:adm1_name":"Kagoshimaken",
    "gn:adm2_name":"Kumagegunyakuchou",
    "gn:name":"Hirauchi",
    "iso:country":"JP",
    "wof:name":"891-4406",
    "wof:placetype":"postalcode"
},
  "geometry": {"coordinates":[130.50309999999999,30.2365],"type":"Point"}
}