{
  "type": "Feature",
  "properties": {
    "gn:adm1_name":"Ishikawaken",
    "gn:adm2_name":"Hakuishi",
    "gn:name":"Shibagakimachi",
    "iso:country":"JP",
    "wof:name":"925-0001",
    "wof:placetype":"postalcode"
},
  "geometry": {"coordinates":[136.76519999999999,36.9492],"type":"Point"}
}