{
  "type": "Feature",
  "properties": {
    "gn:adm1_name":"Shigaken",
    "gn:adm2_name":"Nagahamashi",
    "gn:name":"Hachijouchou",
    "iso:country":"JP",
    "wof:name":"526-0815",
    "wof:placetype":"postalcode"
},
  "geometry": {"coordinates":[136.3142,35.3808],"type":"Point"}
}