{
  "type": "Feature",
  "properties": {
    "gn:adm1_name":"Tokushimaken",
    "gn:adm2_name":"Ananshi",
    "gn:name":"Yokomichou",
    "iso:country":"JP",
    "wof:name":"774-0042",
    "wof:placetype":"postalcode"
},
  "geometry": {"coordinates":[134.65860000000001,33.9288],"type":"Point"}
}