{
  "type": "Feature",
  "properties": {
    "gn:adm1_name":"Kagawaken",
    "gn:adm2_name":"Mitoyogunminochou",
    "gn:name":"Yoshidu",
    "iso:country":"JP",
    "wof:name":"767-0033",
    "wof:placetype":"postalcode"
},
  "geometry": {"coordinates":[133.68620000000001,34.1989],"type":"Point"}
}