{
  "type": "Feature",
  "properties": {
    "gn:adm1_name":"Kouchiken",
    "gn:adm2_name":"Kamiguntosayamadachou",
    "gn:name":"Sakaemachi",
    "iso:country":"JP",
    "wof:name":"782-0039",
    "wof:placetype":"postalcode"
},
  "geometry": {"coordinates":[133.67660000000001,33.6023],"type":"Point"}
}