{
  "type": "Feature",
  "properties": {
    "gn:adm1_name":"Shizuokaken",
    "gn:adm2_name":"Ogasagundaitouchou",
    "gn:name":"Kamihijikata",
    "iso:country":"JP",
    "wof:name":"437-1433",
    "wof:placetype":"postalcode"
},
  "geometry": {"coordinates":[138.04050000000001,34.7073],"type":"Point"}
}