{
  "type": "Feature",
  "properties": {
    "gn:adm1_name":"Hiroshimaken",
    "gn:adm2_name":"Hiroshimashiasaminamiku",
    "gn:name":"Furuichi",
    "iso:country":"JP",
    "wof:name":"731-0123",
    "wof:placetype":"postalcode"
},
  "geometry": {"coordinates":[132.47120000000001,34.4533],"type":"Point"}
}