{
  "type": "Feature",
  "properties": {
    "gn:adm1_name":"Okayamaken",
    "gn:adm2_name":"Soujashi",
    "gn:name":"Kitamizote",
    "iso:country":"JP",
    "wof:name":"719-1117",
    "wof:placetype":"postalcode"
},
  "geometry": {"coordinates":[133.7748,34.6896],"type":"Point"}
}