{
  "type": "Feature",
  "properties": {
    "gn:adm1_name":"Ooitaken",
    "gn:adm2_name":"Tsukumishi",
    "gn:name":"Monzenmachi",
    "iso:country":"JP",
    "wof:name":"879-2456",
    "wof:placetype":"postalcode"
},
  "geometry": {"coordinates":[131.84909999999999,33.0765],"type":"Point"}
}