{
  "type": "Feature",
  "properties": {
    "gn:adm1_name":"Niigataken",
    "gn:adm2_name":"Niigatashi",
    "gn:name":"Furukawachou",
    "iso:country":"JP",
    "wof:name":"950-0056",
    "wof:placetype":"postalcode"
},
  "geometry": {"coordinates":[139.0736,37.9373],"type":"Point"}
}