{
  "type": "Feature",
  "properties": {
    "gn:adm1_name":"Niigataken",
    "gn:adm2_name":"Minamiuonumagunmuikamachi",
    "gn:name":"Iwasaki",
    "iso:country":"JP",
    "wof:name":"949-6765",
    "wof:placetype":"postalcode"
},
  "geometry": {"coordinates":[138.91849999999999,37.0677],"type":"Point"}
}