{
  "type": "Feature",
  "properties": {
    "gn:adm1_name":"Fukuokaken",
    "gn:adm2_name":"Kasuyagunkasuyamachi",
    "gn:name":"Choujabaru",
    "iso:country":"JP",
    "wof:name":"811-2311",
    "wof:placetype":"postalcode"
},
  "geometry": {"coordinates":[130.4752,33.617],"type":"Point"}
}