{
  "type": "Feature",
  "properties": {
    "gn:adm1_name":"Toukyouto",
    "gn:adm2_name":"Suginamiku",
    "gn:name":"Takaidohigashi",
    "iso:country":"JP",
    "wof:name":"168-0072",
    "wof:placetype":"postalcode"
},
  "geometry": {"coordinates":[139.61949999999999,35.684],"type":"Point"}
}