{
  "type": "Feature",
  "properties": {
    "gn:adm1_name":"Kanagawaken",
    "gn:adm2_name":"Miurashi",
    "gn:name":"Ogamichou",
    "iso:country":"JP",
    "wof:name":"238-0246",
    "wof:placetype":"postalcode"
},
  "geometry": {"coordinates":[139.6182,35.15],"type":"Point"}
}