{
  "type": "Feature",
  "properties": {
    "gn:adm1_name":"Shizuokaken",
    "gn:adm2_name":"Shizuokashi",
    "gn:name":"Suwa",
    "iso:country":"JP",
    "wof:name":"420-0902",
    "wof:placetype":"postalcode"
},
  "geometry": {"coordinates":[138.40809999999999,35.0239],"type":"Point"}
}