{
  "type": "Feature",
  "properties": {
    "gn:adm1_name":"Kagoshimaken",
    "gn:adm2_name":"Ooshimagunsetouchichou",
    "gn:name":"Ikanikeisaiganaibaai",
    "iso:country":"JP",
    "wof:name":"894-1500",
    "wof:placetype":"postalcode"
},
  "geometry": {"coordinates":[129.3107,28.1468],"type":"Point"}
}