{
  "type": "Feature",
  "properties": {
    "gn:adm1_name":"Shigaken",
    "gn:adm2_name":"Oumihachimanshi",
    "gn:name":"Takakaichoukita",
    "iso:country":"JP",
    "wof:name":"523-0896",
    "wof:placetype":"postalcode"
},
  "geometry": {"coordinates":[136.1052,35.1288],"type":"Point"}
}