{
  "type": "Feature",
  "properties": {
    "gn:adm1_name":"Chibaken",
    "gn:adm2_name":"Kamagayashi",
    "gn:name":"Higashinakazawa",
    "iso:country":"JP",
    "wof:name":"273-0112",
    "wof:placetype":"postalcode"
},
  "geometry": {"coordinates":[139.99029999999999,35.7699],"type":"Point"}
}