{
  "type": "Feature",
  "properties": {
    "gn:adm1_name":"Okayamaken",
    "gn:adm2_name":"Joubougunkayouchou",
    "gn:name":"Kamitake",
    "iso:country":"JP",
    "wof:name":"716-1131",
    "wof:placetype":"postalcode"
},
  "geometry": {"coordinates":[133.67269999999999,34.8443],"type":"Point"}
}