{
  "type": "Feature",
  "properties": {
    "gn:adm1_name":"Hyougoken",
    "gn:adm2_name":"Nishinomiyashi",
    "gn:name":"Najiotoukubo",
    "iso:country":"JP",
    "wof:name":"669-1148",
    "wof:placetype":"postalcode"
},
  "geometry": {"coordinates":[135.27440000000001,34.8336],"type":"Point"}
}