{
  "type": "Feature",
  "properties": {
    "gn:adm1_name":"Aichiken",
    "gn:adm2_name":"Setoshi",
    "gn:name":"Shingouchou",
    "iso:country":"JP",
    "wof:name":"489-0873",
    "wof:placetype":"postalcode"
},
  "geometry": {"coordinates":[137.08359999999999,35.2133],"type":"Point"}
}