{
  "type": "Feature",
  "properties": {
    "gn:adm1_name":"Tokushimaken",
    "gn:adm2_name":"Tokushimashi",
    "gn:name":"Kawauchichou(Okinoshima)",
    "iso:country":"JP",
    "wof:name":"771-0142",
    "wof:placetype":"postalcode"
},
  "geometry": {"coordinates":[134.572,34.1057],"type":"Point"}
}