{
  "type": "Feature",
  "properties": {
    "gn:adm1_name":"Okayamaken",
    "gn:adm2_name":"Akaiwagunsetochou",
    "gn:name":"Teraji",
    "iso:country":"JP",
    "wof:name":"709-0875",
    "wof:placetype":"postalcode"
},
  "geometry": {"coordinates":[134.04910000000001,34.7428],"type":"Point"}
}