{
  "type": "Feature",
  "properties": {
    "gn:adm1_name":"Mieken",
    "gn:adm2_name":"Suzukashi",
    "gn:name":"Nomachiminami",
    "iso:country":"JP",
    "wof:name":"510-0219",
    "wof:placetype":"postalcode"
},
  "geometry": {"coordinates":[136.56129999999999,34.8504],"type":"Point"}
}