{
  "type": "Feature",
  "properties": {
    "gn:adm1_name":"Kanagawaken",
    "gn:adm2_name":"Kawasakishitamaku",
    "gn:name":"Teraodai",
    "iso:country":"JP",
    "wof:name":"214-0005",
    "wof:placetype":"postalcode"
},
  "geometry": {"coordinates":[139.53469999999999,35.6197],"type":"Point"}
}