{
  "type": "Feature",
  "properties": {
    "gn:adm1_name":"Tottoriken",
    "gn:adm2_name":"Touhakuguntouhakuchou",
    "gn:name":"Miyaba",
    "iso:country":"JP",
    "wof:name":"689-2323",
    "wof:placetype":"postalcode"
},
  "geometry": {"coordinates":[133.68260000000001,35.4337],"type":"Point"}
}