{
  "type": "Feature",
  "properties": {
    "gn:adm1_name":"Mieken",
    "gn:adm2_name":"Agegungeinouchou",
    "gn:name":"Nakanawa",
    "iso:country":"JP",
    "wof:name":"514-2203",
    "wof:placetype":"postalcode"
},
  "geometry": {"coordinates":[136.416,34.8167],"type":"Point"}
}