{
  "type": "Feature",
  "properties": {
    "gn:adm1_name":"Tochigiken",
    "gn:adm2_name":"Hagagunninomiyamachi",
    "gn:name":"Kugetanishi",
    "iso:country":"JP",
    "wof:name":"321-4522",
    "wof:placetype":"postalcode"
},
  "geometry": {"coordinates":[139.96539999999999,36.3771],"type":"Point"}
}