{
  "type": "Feature",
  "properties": {
    "gn:adm1_name":"Aichiken",
    "gn:adm2_name":"Nagoyashikitaku",
    "gn:name":"Kinjou",
    "iso:country":"JP",
    "wof:name":"462-0847",
    "wof:placetype":"postalcode"
},
  "geometry": {"coordinates":[136.90360000000001,35.1953],"type":"Point"}
}