{
  "type": "Feature",
  "properties": {
    "gn:adm1_name":"Chibaken",
    "gn:adm2_name":"Ichiharashi",
    "gn:name":"Katamatagi",
    "iso:country":"JP",
    "wof:name":"299-0113",
    "wof:placetype":"postalcode"
},
  "geometry": {"coordinates":[140.0609,35.4623],"type":"Point"}
}