{
  "type": "Feature",
  "properties": {
    "gn:adm1_name":"Okayamaken",
    "gn:adm2_name":"Bizenshi",
    "gn:name":"Irinaka",
    "iso:country":"JP",
    "wof:name":"705-0023",
    "wof:placetype":"postalcode"
},
  "geometry": {"coordinates":[134.2191,34.7579],"type":"Point"}
}