{
  "type": "Feature",
  "properties": {
    "gn:adm1_name":"Toyamaken",
    "gn:adm2_name":"Shimoniikawagun'Asahimachi",
    "gn:name":"Kanayama",
    "iso:country":"JP",
    "wof:name":"939-0727",
    "wof:placetype":"postalcode"
},
  "geometry": {"coordinates":[137.53870000000001,36.925],"type":"Point"}
}