{
  "type": "Feature",
  "properties": {
    "gn:adm1_name":"Ibarakiken",
    "gn:adm2_name":"Shimotsumashi",
    "gn:name":"Shitte",
    "iso:country":"JP",
    "wof:name":"304-0071",
    "wof:placetype":"postalcode"
},
  "geometry": {"coordinates":[139.9187,36.2149],"type":"Point"}
}