{
  "type": "Feature",
  "properties": {
    "gn:adm1_name":"Fukushimaken",
    "gn:adm2_name":"Shirakawashi",
    "gn:name":"Natsunashi",
    "iso:country":"JP",
    "wof:name":"961-0025",
    "wof:placetype":"postalcode"
},
  "geometry": {"coordinates":[140.2321,37.0975],"type":"Point"}
}