{
  "type": "Feature",
  "properties": {
    "gn:adm1_name":"Hyougoken",
    "gn:adm2_name":"Koubeshinagataku",
    "gn:name":"Takatorisanchou",
    "iso:country":"JP",
    "wof:name":"653-0856",
    "wof:placetype":"postalcode"
},
  "geometry": {"coordinates":[135.1344,34.6708],"type":"Point"}
}