{
  "type": "Feature",
  "properties": {
    "gn:adm1_name":"Saitamaken",
    "gn:adm2_name":"Hanyuushi",
    "gn:name":"Kita",
    "iso:country":"JP",
    "wof:name":"348-0057",
    "wof:placetype":"postalcode"
},
  "geometry": {"coordinates":[139.53460000000001,36.1769],"type":"Point"}
}