{
  "type": "Feature",
  "properties": {
    "gn:adm1_name":"Hyougoken",
    "gn:adm2_name":"Ashiyashi",
    "gn:name":"Tsukiwakachou",
    "iso:country":"JP",
    "wof:name":"659-0084",
    "wof:placetype":"postalcode"
},
  "geometry": {"coordinates":[135.3004,34.7345],"type":"Point"}
}