{
  "type": "Feature",
  "properties": {
    "gn:adm1_name":"Kagoshimaken",
    "gn:adm2_name":"Kimotsukigun'Oonejimechou",
    "gn:name":"Kamikawa",
    "iso:country":"JP",
    "wof:name":"893-2301",
    "wof:placetype":"postalcode"
},
  "geometry": {"coordinates":[130.80690000000001,31.2742],"type":"Point"}
}