{
  "type": "Feature",
  "properties": {
    "gn:adm1_name":"Tochigiken",
    "gn:adm2_name":"Utsunomiyashi",
    "gn:name":"Mitanagashimachou",
    "iso:country":"JP",
    "wof:name":"321-0125",
    "wof:placetype":"postalcode"
},
  "geometry": {"coordinates":[139.88759999999999,36.4776],"type":"Point"}
}