{
  "type": "Feature",
  "properties": {
    "gn:adm1_name":"Hiroshimaken",
    "gn:adm2_name":"Kureshi",
    "gn:name":"Yoshiuramatsubachou",
    "iso:country":"JP",
    "wof:name":"737-0866",
    "wof:placetype":"postalcode"
},
  "geometry": {"coordinates":[132.52950000000001,34.2654],"type":"Point"}
}