{
  "type": "Feature",
  "properties": {
    "gn:adm1_name":"Yamaguchiken",
    "gn:adm2_name":"Shimonosekishi",
    "gn:name":"Futaoijima",
    "iso:country":"JP",
    "wof:name":"759-6542",
    "wof:placetype":"postalcode"
},
  "geometry": {"coordinates":[130.7868,34.1006],"type":"Point"}
}