{
  "type": "Feature",
  "properties": {
    "gn:adm1_name":"Kagawaken",
    "gn:adm2_name":"Shouzuguntonoshouchou",
    "gn:name":"Oe",
    "iso:country":"JP",
    "wof:name":"761-4132",
    "wof:placetype":"postalcode"
},
  "geometry": {"coordinates":[134.1669,34.5182],"type":"Point"}
}