{
  "type": "Feature",
  "properties": {
    "gn:adm1_name":"Okayamaken",
    "gn:adm2_name":"Kasaokashi",
    "gn:name":"Yoshihama",
    "iso:country":"JP",
    "wof:name":"714-0074",
    "wof:placetype":"postalcode"
},
  "geometry": {"coordinates":[133.48179999999999,34.5176],"type":"Point"}
}