{
  "type": "Feature",
  "properties": {
    "gn:adm1_name":"Niigataken",
    "gn:adm2_name":"Sadogun'Aikawamachi",
    "gn:name":"Zaimokumachi",
    "iso:country":"JP",
    "wof:name":"952-1518",
    "wof:placetype":"postalcode"
},
  "geometry": {"coordinates":[138.2381,38.0348],"type":"Point"}
}