{
  "type": "Feature",
  "properties": {
    "gn:adm1_name":"Toukyouto",
    "gn:adm2_name":"Akirunoshi",
    "gn:name":"Ogawa",
    "iso:country":"JP",
    "wof:name":"197-0821",
    "wof:placetype":"postalcode"
},
  "geometry": {"coordinates":[139.3158,35.7202],"type":"Point"}
}