{
  "type": "Feature",
  "properties": {
    "gn:adm1_name":"Fukushimaken",
    "gn:adm2_name":"Nihonmatsushi",
    "gn:name":"Yawako",
    "iso:country":"JP",
    "wof:name":"964-0925",
    "wof:placetype":"postalcode"
},
  "geometry": {"coordinates":[140.48949999999999,37.5836],"type":"Point"}
}