{
  "type": "Feature",
  "properties": {
    "gn:adm1_name":"Yamagataken",
    "gn:adm2_name":"Higashimurayamagunnakayamamachi",
    "gn:name":"Nagasaki",
    "iso:country":"JP",
    "wof:name":"990-0401",
    "wof:placetype":"postalcode"
},
  "geometry": {"coordinates":[140.28360000000001,38.3352],"type":"Point"}
}