{
  "type": "Feature",
  "properties": {
    "gn:adm1_name":"Sagaken",
    "gn:adm2_name":"Sagashi",
    "gn:name":"Hasuikemachikomatsu",
    "iso:country":"JP",
    "wof:name":"840-0004",
    "wof:placetype":"postalcode"
},
  "geometry": {"coordinates":[130.36709999999999,33.2467],"type":"Point"}
}