{
  "type": "Feature",
  "properties": {
    "gn:adm1_name":"Chibaken",
    "gn:adm2_name":"Abikoshi",
    "gn:name":"Nakazatoshinden",
    "iso:country":"JP",
    "wof:name":"270-1126",
    "wof:placetype":"postalcode"
},
  "geometry": {"coordinates":[140.0821,35.8588],"type":"Point"}
}