{
  "type": "Feature",
  "properties": {
    "gn:adm1_name":"Aichiken",
    "gn:adm2_name":"Kounanshi",
    "gn:name":"Hoteichounishi",
    "iso:country":"JP",
    "wof:name":"483-8237",
    "wof:placetype":"postalcode"
},
  "geometry": {"coordinates":[136.86879999999999,35.3208],"type":"Point"}
}