{
  "type": "Feature",
  "properties": {
    "gn:adm1_name":"Shizuokaken",
    "gn:adm2_name":"Numadushi",
    "gn:name":"Shinjukuchou",
    "iso:country":"JP",
    "wof:name":"410-0048",
    "wof:placetype":"postalcode"
},
  "geometry": {"coordinates":[138.8597,35.1075],"type":"Point"}
}