{
  "type": "Feature",
  "properties": {
    "gn:adm1_name":"Miyazakiken",
    "gn:adm2_name":"Miyazakigunkiyotakechou",
    "gn:name":"Asahi",
    "iso:country":"JP",
    "wof:name":"889-1609",
    "wof:placetype":"postalcode"
},
  "geometry": {"coordinates":[131.40809999999999,31.8803],"type":"Point"}
}