{
  "type": "Feature",
  "properties": {
    "gn:adm1_name":"Yamagataken",
    "gn:adm2_name":"Yamagatashi",
    "gn:name":"Imaduka",
    "iso:country":"JP",
    "wof:name":"990-0817",
    "wof:placetype":"postalcode"
},
  "geometry": {"coordinates":[140.32320000000001,38.2918],"type":"Point"}
}