{
  "type": "Feature",
  "properties": {
    "gn:adm1_name":"Miyagiken",
    "gn:adm2_name":"Kuriharagunshiwahimechou",
    "gn:name":"Karishiki",
    "iso:country":"JP",
    "wof:name":"989-5601",
    "wof:placetype":"postalcode"
},
  "geometry": {"coordinates":[141.0652,38.7739],"type":"Point"}
}