{
  "type": "Feature",
  "properties": {
    "gn:adm1_name":"Ooitaken",
    "gn:adm2_name":"Usukishi",
    "gn:name":"Tajiri",
    "iso:country":"JP",
    "wof:name":"875-0021",
    "wof:placetype":"postalcode"
},
  "geometry": {"coordinates":[131.7373,33.1421],"type":"Point"}
}