{
  "type": "Feature",
  "properties": {
    "gn:adm1_name":"Tottoriken",
    "gn:adm2_name":"Yazugunmochigasechou",
    "gn:name":"Kawanaka",
    "iso:country":"JP",
    "wof:name":"689-1226",
    "wof:placetype":"postalcode"
},
  "geometry": {"coordinates":[134.20670000000001,35.3025],"type":"Point"}
}