{
  "type": "Feature",
  "properties": {
    "gn:adm1_name":"Oosakafu",
    "gn:adm2_name":"Suitashi",
    "gn:name":"Tarumichou",
    "iso:country":"JP",
    "wof:name":"564-0062",
    "wof:placetype":"postalcode"
},
  "geometry": {"coordinates":[135.50370000000001,34.7629],"type":"Point"}
}