{
  "type": "Feature",
  "properties": {
    "gn:adm1_name":"Kanagawaken",
    "gn:adm2_name":"Yokohamashiisogoku",
    "gn:name":"Sugitatsubonomi",
    "iso:country":"JP",
    "wof:name":"235-0034",
    "wof:placetype":"postalcode"
},
  "geometry": {"coordinates":[139.61420000000001,35.3774],"type":"Point"}
}