{
  "type": "Feature",
  "properties": {
    "gn:adm1_name":"Hiroshimaken",
    "gn:adm2_name":"Akigunfuchuuchou",
    "gn:name":"Hamadahonmachi",
    "iso:country":"JP",
    "wof:name":"735-0023",
    "wof:placetype":"postalcode"
},
  "geometry": {"coordinates":[132.5087,34.3894],"type":"Point"}
}