{
  "type": "Feature",
  "properties": {
    "gn:adm1_name":"Kyoutofu",
    "gn:adm2_name":"Kyoutoshishimogyouku",
    "gn:name":"Kaminakanochou",
    "iso:country":"JP",
    "wof:name":"600-8248",
    "wof:placetype":"postalcode"
},
  "geometry": {"coordinates":[135.74930000000001,34.9874],"type":"Point"}
}