{
  "type": "Feature",
  "properties": {
    "gn:adm1_name":"Fukushimaken",
    "gn:adm2_name":"Tamuragunmiharumachi",
    "gn:name":"Sakuragaoka",
    "iso:country":"JP",
    "wof:name":"963-7711",
    "wof:placetype":"postalcode"
},
  "geometry": {"coordinates":[140.49969999999999,37.4348],"type":"Point"}
}