{
  "type": "Feature",
  "properties": {
    "gn:adm1_name":"Kagoshimaken",
    "gn:adm2_name":"Ooshimaguntokunoshimachou",
    "gn:name":"Tete",
    "iso:country":"JP",
    "wof:name":"891-7421",
    "wof:placetype":"postalcode"
},
  "geometry": {"coordinates":[128.9341,27.8879],"type":"Point"}
}