{
  "type": "Feature",
  "properties": {
    "gn:adm1_name":"Gifuken",
    "gn:adm2_name":"Gifushi",
    "gn:name":"Ukawachou",
    "iso:country":"JP",
    "wof:name":"502-0837",
    "wof:placetype":"postalcode"
},
  "geometry": {"coordinates":[136.7704,35.4425],"type":"Point"}
}