{
  "type": "Feature",
  "properties": {
    "gn:adm1_name":"Naganoken",
    "gn:adm2_name":"Shimoinagun'Ananchou",
    "gn:name":"Higashijou",
    "iso:country":"JP",
    "wof:name":"399-1502",
    "wof:placetype":"postalcode"
},
  "geometry": {"coordinates":[137.8203,35.3246],"type":"Point"}
}