{
  "type": "Feature",
  "properties": {
    "gn:adm1_name":"Kanagawaken",
    "gn:adm2_name":"Fujisawashi",
    "gn:name":"Kotsuka",
    "iso:country":"JP",
    "wof:name":"251-0013",
    "wof:placetype":"postalcode"
},
  "geometry": {"coordinates":[139.50659999999999,35.3407],"type":"Point"}
}