{
  "type": "Feature",
  "properties": {
    "gn:adm1_name":"Miyazakiken",
    "gn:adm2_name":"Miyazakishi",
    "gn:name":"Chuuoudoori",
    "iso:country":"JP",
    "wof:name":"880-0002",
    "wof:placetype":"postalcode"
},
  "geometry": {"coordinates":[131.4211,31.9146],"type":"Point"}
}