{
  "type": "Feature",
  "properties": {
    "gn:adm1_name":"Toyamaken",
    "gn:adm2_name":"Takaokashi",
    "gn:name":"Taki",
    "iso:country":"JP",
    "wof:name":"939-1255",
    "wof:placetype":"postalcode"
},
  "geometry": {"coordinates":[137.02979999999999,36.6806],"type":"Point"}
}