{
  "type": "Feature",
  "properties": {
    "gn:adm1_name":"Hiroshimaken",
    "gn:adm2_name":"Saekigun'Oonochou",
    "gn:name":"Takami",
    "iso:country":"JP",
    "wof:name":"739-0476",
    "wof:placetype":"postalcode"
},
  "geometry": {"coordinates":[132.28110000000001,34.3137],"type":"Point"}
}