{
  "type": "Feature",
  "properties": {
    "gn:adm1_name":"Aichiken",
    "gn:adm2_name":"Toyotashi",
    "gn:name":"Ugasechou",
    "iso:country":"JP",
    "wof:name":"444-2204",
    "wof:placetype":"postalcode"
},
  "geometry": {"coordinates":[137.21809999999999,35.0619],"type":"Point"}
}