{
  "type": "Feature",
  "properties": {
    "gn:adm1_name":"Miyagiken",
    "gn:adm2_name":"Kesennumashi",
    "gn:name":"Hajikamisuginoshita",
    "iso:country":"JP",
    "wof:name":"988-0245",
    "wof:placetype":"postalcode"
},
  "geometry": {"coordinates":[141.5872,38.827],"type":"Point"}
}