{
  "type": "Feature",
  "properties": {
    "gn:adm1_name":"Shimaneken",
    "gn:adm2_name":"Oochigunkawamotomachi",
    "gn:name":"Tando",
    "iso:country":"JP",
    "wof:name":"696-0005",
    "wof:placetype":"postalcode"
},
  "geometry": {"coordinates":[132.48400000000001,34.9973],"type":"Point"}
}