{
  "type": "Feature",
  "properties": {
    "gn:adm1_name":"Chibaken",
    "gn:adm2_name":"Yachiyoshi",
    "gn:name":"Oowada",
    "iso:country":"JP",
    "wof:name":"276-0045",
    "wof:placetype":"postalcode"
},
  "geometry": {"coordinates":[140.1054,35.715],"type":"Point"}
}