{
  "type": "Feature",
  "properties": {
    "gn:adm1_name":"Wakayamaken",
    "gn:adm2_name":"Kaisougunshimotsuchou",
    "gn:name":"Shimo",
    "iso:country":"JP",
    "wof:name":"649-0133",
    "wof:placetype":"postalcode"
},
  "geometry": {"coordinates":[135.16489999999999,34.1281],"type":"Point"}
}