{
  "type": "Feature",
  "properties": {
    "gn:adm1_name":"Gunmaken",
    "gn:adm2_name":"Takasakishi",
    "gn:name":"Yoriaichou",
    "iso:country":"JP",
    "wof:name":"370-0822",
    "wof:placetype":"postalcode"
},
  "geometry": {"coordinates":[139.00540000000001,36.3278],"type":"Point"}
}