{
  "type": "Feature",
  "properties": {
    "gn:adm1_name":"Kagoshimaken",
    "gn:adm2_name":"Makurazakishi",
    "gn:name":"Sakuragichou",
    "iso:country":"JP",
    "wof:name":"898-0018",
    "wof:placetype":"postalcode"
},
  "geometry": {"coordinates":[130.29140000000001,31.2741],"type":"Point"}
}