{
  "type": "Feature",
  "properties": {
    "gn:adm1_name":"Aichiken",
    "gn:adm2_name":"Toyotashi",
    "gn:name":"Tsutsumihonmachi",
    "iso:country":"JP",
    "wof:name":"473-0939",
    "wof:placetype":"postalcode"
},
  "geometry": {"coordinates":[137.07830000000001,35.0526],"type":"Point"}
}