{
  "type": "Feature",
  "properties": {
    "gn:adm1_name":"Gifuken",
    "gn:adm2_name":"Oonogunnyuukawamura",
    "gn:name":"Kono",
    "iso:country":"JP",
    "wof:name":"506-2115",
    "wof:placetype":"postalcode"
},
  "geometry": {"coordinates":[137.3759,36.1749],"type":"Point"}
}