{
  "type": "Feature",
  "properties": {
    "gn:adm1_name":"Toyamaken",
    "gn:adm2_name":"Himishi",
    "gn:name":"Kurumi",
    "iso:country":"JP",
    "wof:name":"935-0335",
    "wof:placetype":"postalcode"
},
  "geometry": {"coordinates":[136.93690000000001,36.9271],"type":"Point"}
}