{
  "type": "Feature",
  "properties": {
    "gn:adm1_name":"Nagasakiken",
    "gn:adm2_name":"Minamitakakigunminamikushiyamachou",
    "gn:name":"Otsu(Onoborimyou)",
    "iso:country":"JP",
    "wof:name":"854-0702",
    "wof:placetype":"postalcode"
},
  "geometry": {"coordinates":[130.1635,32.6747],"type":"Point"}
}