{
  "type": "Feature",
  "properties": {
    "gn:adm1_name":"Naganoken",
    "gn:adm2_name":"Iidashi",
    "gn:name":"Toorimachi",
    "iso:country":"JP",
    "wof:name":"395-0043",
    "wof:placetype":"postalcode"
},
  "geometry": {"coordinates":[137.82320000000001,35.5167],"type":"Point"}
}