{
  "type": "Feature",
  "properties": {
    "gn:adm1_name":"Toyamaken",
    "gn:adm2_name":"Toyamashi",
    "gn:name":"Iwaseminatomachi",
    "iso:country":"JP",
    "wof:name":"931-8364",
    "wof:placetype":"postalcode"
},
  "geometry": {"coordinates":[137.22900000000001,36.759],"type":"Point"}
}