{
  "type": "Feature",
  "properties": {
    "gn:adm1_name":"Mieken",
    "gn:adm2_name":"Iseshi",
    "gn:name":"Iwabuchichou",
    "iso:country":"JP",
    "wof:name":"516-0038",
    "wof:placetype":"postalcode"
},
  "geometry": {"coordinates":[136.71940000000001,34.485],"type":"Point"}
}