{
  "type": "Feature",
  "properties": {
    "gn:adm1_name":"Okayamaken",
    "gn:adm2_name":"Kurashikishi",
    "gn:name":"Mizushimanishikotobukichou",
    "iso:country":"JP",
    "wof:name":"712-8038",
    "wof:placetype":"postalcode"
},
  "geometry": {"coordinates":[133.74629999999999,34.5463],"type":"Point"}
}