{
  "type": "Feature",
  "properties": {
    "gn:adm1_name":"Ibarakiken",
    "gn:adm2_name":"Tsuchiurashi",
    "gn:name":"Ootsuno",
    "iso:country":"JP",
    "wof:name":"300-0028",
    "wof:placetype":"postalcode"
},
  "geometry": {"coordinates":[140.25409999999999,36.0858],"type":"Point"}
}