{
  "type": "Feature",
  "properties": {
    "gn:adm1_name":"Yamaguchiken",
    "gn:adm2_name":"Shimonosekishi",
    "gn:name":"Hosoeshinmachi",
    "iso:country":"JP",
    "wof:name":"750-0017",
    "wof:placetype":"postalcode"
},
  "geometry": {"coordinates":[130.92920000000001,33.949],"type":"Point"}
}