{
  "type": "Feature",
  "properties": {
    "gn:adm1_name":"Niigataken",
    "gn:adm2_name":"Nishikanbaraguntsukigatamura",
    "gn:name":"Tsuriyoseshin",
    "iso:country":"JP",
    "wof:name":"950-1312",
    "wof:placetype":"postalcode"
},
  "geometry": {"coordinates":[138.98060000000001,37.7413],"type":"Point"}
}