{
  "type": "Feature",
  "properties": {
    "gn:adm1_name":"Aichiken",
    "gn:adm2_name":"Higashikamogun'Asahichou",
    "gn:name":"Kobata",
    "iso:country":"JP",
    "wof:name":"444-2805",
    "wof:placetype":"postalcode"
},
  "geometry": {"coordinates":[137.40219999999999,35.1882],"type":"Point"}
}