{
  "type": "Feature",
  "properties": {
    "gn:adm1_name":"Saitamaken",
    "gn:adm2_name":"Yashioshi",
    "gn:name":"Kizone",
    "iso:country":"JP",
    "wof:name":"340-0813",
    "wof:placetype":"postalcode"
},
  "geometry": {"coordinates":[139.85310000000001,35.818],"type":"Point"}
}