{
  "type": "Feature",
  "properties": {
    "gn:adm1_name":"Miyagiken",
    "gn:adm2_name":"Kuriharaguntakashimizumachi",
    "gn:name":"Higashitate",
    "iso:country":"JP",
    "wof:name":"987-2132",
    "wof:placetype":"postalcode"
},
  "geometry": {"coordinates":[141.01499999999999,38.6545],"type":"Point"}
}