{
  "type": "Feature",
  "properties": {
    "gn:adm1_name":"Shimaneken",
    "gn:adm2_name":"Nimagunyunotsumachi",
    "gn:name":"Fukunamiimaura",
    "iso:country":"JP",
    "wof:name":"699-2515",
    "wof:placetype":"postalcode"
},
  "geometry": {"coordinates":[132.32660000000001,35.0677],"type":"Point"}
}