{
  "type": "Feature",
  "properties": {
    "gn:adm1_name":"Mieken",
    "gn:adm2_name":"Ayamagun'Igachou",
    "gn:name":"Tsugemachi",
    "iso:country":"JP",
    "wof:name":"519-1402",
    "wof:placetype":"postalcode"
},
  "geometry": {"coordinates":[136.2474,34.8412],"type":"Point"}
}