{
  "type": "Feature",
  "properties": {
    "gn:adm1_name":"Kanagawaken",
    "gn:adm2_name":"Odawarashi",
    "gn:name":"Shimoshinden",
    "iso:country":"JP",
    "wof:name":"250-0878",
    "wof:placetype":"postalcode"
},
  "geometry": {"coordinates":[139.17590000000001,35.2761],"type":"Point"}
}