{
  "type": "Feature",
  "properties": {
    "gn:adm1_name":"Gifuken",
    "gn:adm2_name":"Hashimashi",
    "gn:name":"Hottsuchouyokote",
    "iso:country":"JP",
    "wof:name":"501-6331",
    "wof:placetype":"postalcode"
},
  "geometry": {"coordinates":[136.67250000000001,35.3116],"type":"Point"}
}