{
  "type": "Feature",
  "properties": {
    "gn:adm1_name":"Yamaguchiken",
    "gn:adm2_name":"Minegunmitouchou",
    "gn:name":"Edou",
    "iso:country":"JP",
    "wof:name":"754-0301",
    "wof:placetype":"postalcode"
},
  "geometry": {"coordinates":[131.36199999999999,34.2769],"type":"Point"}
}