{
  "type": "Feature",
  "properties": {
    "gn:adm1_name":"Ehimeken",
    "gn:adm2_name":"Minamiuwagunnishiumichou",
    "gn:name":"Nakadomari",
    "iso:country":"JP",
    "wof:name":"798-4207",
    "wof:placetype":"postalcode"
},
  "geometry": {"coordinates":[132.482,32.9377],"type":"Point"}
}