{
  "type": "Feature",
  "properties": {
    "gn:adm1_name":"Ehimeken",
    "gn:adm2_name":"Houjoushi",
    "gn:name":"Kamonoike",
    "iso:country":"JP",
    "wof:name":"799-2466",
    "wof:placetype":"postalcode"
},
  "geometry": {"coordinates":[132.7696,33.9313],"type":"Point"}
}