{
  "type": "Feature",
  "properties": {
    "gn:adm1_name":"Sagaken",
    "gn:adm2_name":"Sagashi",
    "gn:name":"Kounohigashi",
    "iso:country":"JP",
    "wof:name":"840-0804",
    "wof:placetype":"postalcode"
},
  "geometry": {"coordinates":[130.29589999999999,33.2669],"type":"Point"}
}