{
  "type": "Feature",
  "properties": {
    "gn:adm1_name":"Kagawaken",
    "gn:adm2_name":"Kagawagunkounanchou",
    "gn:name":"Ikenouchi",
    "iso:country":"JP",
    "wof:name":"761-1405",
    "wof:placetype":"postalcode"
},
  "geometry": {"coordinates":[133.99979999999999,34.2498],"type":"Point"}
}