{
  "type": "Feature",
  "properties": {
    "gn:adm1_name":"Shimaneken",
    "gn:adm2_name":"Okigunsaigouchou",
    "gn:name":"Iida",
    "iso:country":"JP",
    "wof:name":"685-0004",
    "wof:placetype":"postalcode"
},
  "geometry": {"coordinates":[133.34989999999999,36.2183],"type":"Point"}
}