{
  "type": "Feature",
  "properties": {
    "gn:adm1_name":"Fukuokaken",
    "gn:adm2_name":"Itoshimagunnijoumachi",
    "gn:name":"Nagaishi",
    "iso:country":"JP",
    "wof:name":"819-1625",
    "wof:placetype":"postalcode"
},
  "geometry": {"coordinates":[130.1677,33.5093],"type":"Point"}
}