{
  "type": "Feature",
  "properties": {
    "gn:adm1_name":"Fukushimaken",
    "gn:adm2_name":"Iwakishi",
    "gn:name":"Tairatoyoma",
    "iso:country":"JP",
    "wof:name":"970-0224",
    "wof:placetype":"postalcode"
},
  "geometry": {"coordinates":[140.96809999999999,36.9883],"type":"Point"}
}