{
  "type": "Feature",
  "properties": {
    "gn:adm1_name":"Kouchiken",
    "gn:adm2_name":"Takaokagunhayamamura",
    "gn:name":"Suginokawaotsu",
    "iso:country":"JP",
    "wof:name":"785-0215",
    "wof:placetype":"postalcode"
},
  "geometry": {"coordinates":[133.16470000000001,33.4379],"type":"Point"}
}