{
  "type": "Feature",
  "properties": {
    "gn:adm1_name":"Yamanashiken",
    "gn:adm2_name":"Minamitsurugunfujikawaguchikomachi",
    "gn:name":"Asagawa",
    "iso:country":"JP",
    "wof:name":"401-0303",
    "wof:placetype":"postalcode"
},
  "geometry": {"coordinates":[138.77449999999999,35.5097],"type":"Point"}
}