{
  "type": "Feature",
  "properties": {
    "gn:adm1_name":"Okayamaken",
    "gn:adm2_name":"Okayamashi",
    "gn:name":"Akasakadai",
    "iso:country":"JP",
    "wof:name":"703-8287",
    "wof:placetype":"postalcode"
},
  "geometry": {"coordinates":[133.9384,34.6492],"type":"Point"}
}