{
  "type": "Feature",
  "properties": {
    "gn:adm1_name":"Fukuokaken",
    "gn:adm2_name":"Oomutashi",
    "gn:name":"Shimoshirakawamachi",
    "iso:country":"JP",
    "wof:name":"837-0928",
    "wof:placetype":"postalcode"
},
  "geometry": {"coordinates":[130.45529999999999,33.0448],"type":"Point"}
}