{
  "type": "Feature",
  "properties": {
    "gn:adm1_name":"Kyoutofu",
    "gn:adm2_name":"Nagaokakyoushi",
    "gn:name":"Takadai",
    "iso:country":"JP",
    "wof:name":"617-0847",
    "wof:placetype":"postalcode"
},
  "geometry": {"coordinates":[135.67590000000001,34.9174],"type":"Point"}
}