{
  "type": "Feature",
  "properties": {
    "gn:adm1_name":"Saitamaken",
    "gn:adm2_name":"Hannoushi",
    "gn:name":"Haramachi",
    "iso:country":"JP",
    "wof:name":"357-0005",
    "wof:placetype":"postalcode"
},
  "geometry": {"coordinates":[139.31999999999999,35.8595],"type":"Point"}
}