{
  "type": "Feature",
  "properties": {
    "gn:adm1_name":"Fukushimaken",
    "gn:adm2_name":"Oonumagun'Aiduhongoumachi",
    "gn:name":"Omoiborimukai",
    "iso:country":"JP",
    "wof:name":"969-6102",
    "wof:placetype":"postalcode"
},
  "geometry": {"coordinates":[139.8931,37.4564],"type":"Point"}
}