{
  "type": "Feature",
  "properties": {
    "gn:adm1_name":"Miyagiken",
    "gn:adm2_name":"Motoyoshigun'Utatsuchou",
    "gn:name":"Makita",
    "iso:country":"JP",
    "wof:name":"988-0404",
    "wof:placetype":"postalcode"
},
  "geometry": {"coordinates":[141.5378,38.7296],"type":"Point"}
}