{
  "type": "Feature",
  "properties": {
    "gn:adm1_name":"Aichiken",
    "gn:adm2_name":"Nagoyashimeitouku",
    "gn:name":"Takabari",
    "iso:country":"JP",
    "wof:name":"465-0061",
    "wof:placetype":"postalcode"
},
  "geometry": {"coordinates":[137.0094,35.1569],"type":"Point"}
}