{
  "type": "Feature",
  "properties": {
    "gn:adm1_name":"Fukushimaken",
    "gn:adm2_name":"Yamagunyamatomachi",
    "gn:name":"Nakaishiuchiba",
    "iso:country":"JP",
    "wof:name":"969-4161",
    "wof:placetype":"postalcode"
},
  "geometry": {"coordinates":[139.76390000000001,37.641],"type":"Point"}
}