{
  "type": "Feature",
  "properties": {
    "gn:adm1_name":"Hyougoken",
    "gn:adm2_name":"Himejishi",
    "gn:name":"Hayashidachoumukudani",
    "iso:country":"JP",
    "wof:name":"679-4211",
    "wof:placetype":"postalcode"
},
  "geometry": {"coordinates":[134.58090000000001,34.9146],"type":"Point"}
}