{
  "type": "Feature",
  "properties": {
    "gn:adm1_name":"Naraken",
    "gn:adm2_name":"Kitakatsuragigunkouryouchou",
    "gn:name":"Misasagidai",
    "iso:country":"JP",
    "wof:name":"635-0835",
    "wof:placetype":"postalcode"
},
  "geometry": {"coordinates":[135.73240000000001,34.5324],"type":"Point"}
}