{
  "type": "Feature",
  "properties": {
    "gn:adm1_name":"Niigataken",
    "gn:adm2_name":"Niitsushi",
    "gn:name":"Higashichou",
    "iso:country":"JP",
    "wof:name":"956-0816",
    "wof:placetype":"postalcode"
},
  "geometry": {"coordinates":[139.13990000000001,37.8029],"type":"Point"}
}