{
  "type": "Feature",
  "properties": {
    "gn:adm1_name":"Naganoken",
    "gn:adm2_name":"Kamiinagun'Iijimamachi",
    "gn:name":"Ikanikeisaiganaibaai",
    "iso:country":"JP",
    "wof:name":"399-3700",
    "wof:placetype":"postalcode"
},
  "geometry": {"coordinates":[137.92230000000001,35.6735],"type":"Point"}
}