{
  "type": "Feature",
  "properties": {
    "gn:adm1_name":"Kagoshimaken",
    "gn:adm2_name":"Kushikinoshi",
    "gn:name":"Kozechou",
    "iso:country":"JP",
    "wof:name":"896-0034",
    "wof:placetype":"postalcode"
},
  "geometry": {"coordinates":[130.26429999999999,31.7094],"type":"Point"}
}