{
  "type": "Feature",
  "properties": {
    "gn:adm1_name":"Oosakafu",
    "gn:adm2_name":"Neyagawashi",
    "gn:name":"Hiraikechou",
    "iso:country":"JP",
    "wof:name":"572-0839",
    "wof:placetype":"postalcode"
},
  "geometry": {"coordinates":[135.62370000000001,34.7697],"type":"Point"}
}