{
  "type": "Feature",
  "properties": {
    "gn:adm1_name":"Okayamaken",
    "gn:adm2_name":"Takahashishi",
    "gn:name":"Asahimachi",
    "iso:country":"JP",
    "wof:name":"716-0039",
    "wof:placetype":"postalcode"
},
  "geometry": {"coordinates":[133.61539999999999,34.7886],"type":"Point"}
}