{
  "type": "Feature",
  "properties": {
    "gn:adm1_name":"Nagasakiken",
    "gn:adm2_name":"Nagasakishi",
    "gn:name":"Yayoimachi",
    "iso:country":"JP",
    "wof:name":"850-0823",
    "wof:placetype":"postalcode"
},
  "geometry": {"coordinates":[129.8938,32.7302],"type":"Point"}
}