{
  "type": "Feature",
  "properties": {
    "gn:adm1_name":"Niigataken",
    "gn:adm2_name":"Nagaokashi",
    "gn:name":"Aramachi",
    "iso:country":"JP",
    "wof:name":"940-0023",
    "wof:placetype":"postalcode"
},
  "geometry": {"coordinates":[138.85720000000001,37.4629],"type":"Point"}
}