{
  "type": "Feature",
  "properties": {
    "gn:adm1_name":"Aichiken",
    "gn:adm2_name":"Toyokawashi",
    "gn:name":"Yayoichou",
    "iso:country":"JP",
    "wof:name":"442-0831",
    "wof:placetype":"postalcode"
},
  "geometry": {"coordinates":[137.37469999999999,34.8101],"type":"Point"}
}