{
  "type": "Feature",
  "properties": {
    "gn:adm1_name":"Toyamaken",
    "gn:adm2_name":"Neigunyamadamura",
    "gn:name":"Kaminakanose",
    "iso:country":"JP",
    "wof:name":"930-2108",
    "wof:placetype":"postalcode"
},
  "geometry": {"coordinates":[137.08330000000001,36.5873],"type":"Point"}
}