{
  "type": "Feature",
  "properties": {
    "gn:adm1_name":"Aichiken",
    "gn:adm2_name":"Setoshi",
    "gn:name":"Nishiterayamachou",
    "iso:country":"JP",
    "wof:name":"489-0925",
    "wof:placetype":"postalcode"
},
  "geometry": {"coordinates":[137.06899999999999,35.2151],"type":"Point"}
}