{
  "type": "Feature",
  "properties": {
    "gn:adm1_name":"Kagoshimaken",
    "gn:adm2_name":"Kumagegunnakatanechou",
    "gn:name":"Tashima",
    "iso:country":"JP",
    "wof:name":"891-3607",
    "wof:placetype":"postalcode"
},
  "geometry": {"coordinates":[130.9306,30.4959],"type":"Point"}
}