{
  "type": "Feature",
  "properties": {
    "gn:adm1_name":"Ishikawaken",
    "gn:adm2_name":"Komatsushi",
    "gn:name":"Wakasugimachi",
    "iso:country":"JP",
    "wof:name":"923-0832",
    "wof:placetype":"postalcode"
},
  "geometry": {"coordinates":[136.48249999999999,36.3966],"type":"Point"}
}