{
  "type": "Feature",
  "properties": {
    "gn:adm1_name":"Aichiken",
    "gn:adm2_name":"Kounanshi",
    "gn:name":"Ogouchougodairiki",
    "iso:country":"JP",
    "wof:name":"483-8143",
    "wof:placetype":"postalcode"
},
  "geometry": {"coordinates":[136.8681,35.3139],"type":"Point"}
}