{
  "type": "Feature",
  "properties": {
    "gn:adm1_name":"Okayamaken",
    "gn:adm2_name":"Okayamashi",
    "gn:name":"Koube",
    "iso:country":"JP",
    "wof:name":"701-1201",
    "wof:placetype":"postalcode"
},
  "geometry": {"coordinates":[133.8965,34.6853],"type":"Point"}
}