{
  "type": "Feature",
  "properties": {
    "gn:adm1_name":"Ibarakiken",
    "gn:adm2_name":"Kitaibarakishi",
    "gn:name":"Sekinamichoukamiokashimo",
    "iso:country":"JP",
    "wof:name":"319-1715",
    "wof:placetype":"postalcode"
},
  "geometry": {"coordinates":[140.7679,36.8334],"type":"Point"}
}