{
  "type": "Feature",
  "properties": {
    "gn:adm1_name":"Ooitaken",
    "gn:adm2_name":"Ooitashi",
    "gn:name":"Ookubo",
    "iso:country":"JP",
    "wof:name":"870-0806",
    "wof:placetype":"postalcode"
},
  "geometry": {"coordinates":[131.5754,33.2442],"type":"Point"}
}