{
  "type": "Feature",
  "properties": {
    "gn:adm1_name":"Miyagiken",
    "gn:adm2_name":"Kuriharaguntsukidatechou",
    "gn:name":"Koedate",
    "iso:country":"JP",
    "wof:name":"987-2273",
    "wof:placetype":"postalcode"
},
  "geometry": {"coordinates":[141.00389999999999,38.7369],"type":"Point"}
}