{
  "type": "Feature",
  "properties": {
    "gn:adm1_name":"Gunmaken",
    "gn:adm2_name":"Ouragun'Itakuramachi",
    "gn:name":"Ikanikeisaiganaibaai",
    "iso:country":"JP",
    "wof:name":"374-0100",
    "wof:placetype":"postalcode"
},
  "geometry": {"coordinates":[139.59030000000001,36.235],"type":"Point"}
}