{
  "type": "Feature",
  "properties": {
    "gn:adm1_name":"Tochigiken",
    "gn:adm2_name":"Ootawarashi",
    "gn:name":"Wakamatsuchou",
    "iso:country":"JP",
    "wof:name":"324-0054",
    "wof:placetype":"postalcode"
},
  "geometry": {"coordinates":[140.0264,36.8593],"type":"Point"}
}