{
  "type": "Feature",
  "properties": {
    "gn:adm1_name":"Ibarakiken",
    "gn:adm2_name":"Tsuchiurashi",
    "gn:name":"Fujisaki",
    "iso:country":"JP",
    "wof:name":"300-0813",
    "wof:placetype":"postalcode"
},
  "geometry": {"coordinates":[140.19909999999999,36.0723],"type":"Point"}
}