{
  "type": "Feature",
  "properties": {
    "gn:adm1_name":"Naraken",
    "gn:adm2_name":"Kitakatsuragigunkouryouchou",
    "gn:name":"Hirose",
    "iso:country":"JP",
    "wof:name":"635-0812",
    "wof:placetype":"postalcode"
},
  "geometry": {"coordinates":[135.75899999999999,34.5577],"type":"Point"}
}