{
  "type": "Feature",
  "properties": {
    "gn:adm1_name":"Niigataken",
    "gn:adm2_name":"Odiyashi",
    "gn:name":"Ikenakashinden",
    "iso:country":"JP",
    "wof:name":"949-8727",
    "wof:placetype":"postalcode"
},
  "geometry": {"coordinates":[138.7978,37.261],"type":"Point"}
}