{
  "type": "Feature",
  "properties": {
    "gn:adm1_name":"Miyagiken",
    "gn:adm2_name":"Tomegunhasamachou",
    "gn:name":"Nitsuta",
    "iso:country":"JP",
    "wof:name":"989-4601",
    "wof:placetype":"postalcode"
},
  "geometry": {"coordinates":[141.1097,38.6965],"type":"Point"}
}