{
  "type": "Feature",
  "properties": {
    "gn:adm1_name":"Kagawaken",
    "gn:adm2_name":"Ayautagun'Ayautachou",
    "gn:name":"Kurikumahigashi",
    "iso:country":"JP",
    "wof:name":"761-2406",
    "wof:placetype":"postalcode"
},
  "geometry": {"coordinates":[133.88749999999999,34.2346],"type":"Point"}
}