{
  "type": "Feature",
  "properties": {
    "gn:adm1_name":"Sagaken",
    "gn:adm2_name":"Imarishi",
    "gn:name":"Ootsubochouhei",
    "iso:country":"JP",
    "wof:name":"848-0023",
    "wof:placetype":"postalcode"
},
  "geometry": {"coordinates":[129.89189999999999,33.2699],"type":"Point"}
}