{
  "type": "Feature",
  "properties": {
    "gn:adm1_name":"Fukuiken",
    "gn:adm2_name":"Fukuishi",
    "gn:name":"Shinbirakichou",
    "iso:country":"JP",
    "wof:name":"919-0328",
    "wof:placetype":"postalcode"
},
  "geometry": {"coordinates":[136.22020000000001,36.0142],"type":"Point"}
}