{
  "type": "Feature",
  "properties": {
    "gn:adm1_name":"Naraken",
    "gn:adm2_name":"Yoshinogunnishiyoshinomura",
    "gn:name":"Kawamata",
    "iso:country":"JP",
    "wof:name":"637-0225",
    "wof:placetype":"postalcode"
},
  "geometry": {"coordinates":[135.79169999999999,34.2471],"type":"Point"}
}