{
  "type": "Feature",
  "properties": {
    "gn:adm1_name":"Nagasakiken",
    "gn:adm2_name":"Kitamatsuuragunsazachou",
    "gn:name":"Shikatamen",
    "iso:country":"JP",
    "wof:name":"857-0315",
    "wof:placetype":"postalcode"
},
  "geometry": {"coordinates":[129.6369,33.2389],"type":"Point"}
}