{
  "type": "Feature",
  "properties": {
    "gn:adm1_name":"Ibarakiken",
    "gn:adm2_name":"Tsuchiurashi",
    "gn:name":"Komatsu",
    "iso:country":"JP",
    "wof:name":"300-0823",
    "wof:placetype":"postalcode"
},
  "geometry": {"coordinates":[140.20419999999999,36.0679],"type":"Point"}
}