{
  "type": "Feature",
  "properties": {
    "gn:adm1_name":"Naganoken",
    "gn:adm2_name":"Uedashi",
    "gn:name":"Urano",
    "iso:country":"JP",
    "wof:name":"386-1546",
    "wof:placetype":"postalcode"
},
  "geometry": {"coordinates":[138.16,36.3778],"type":"Point"}
}