{
  "type": "Feature",
  "properties": {
    "gn:adm1_name":"Aichiken",
    "gn:adm2_name":"Nagoyashikitaku",
    "gn:name":"Joutouchou",
    "iso:country":"JP",
    "wof:name":"462-0831",
    "wof:placetype":"postalcode"
},
  "geometry": {"coordinates":[136.9195,35.1946],"type":"Point"}
}