{
  "type": "Feature",
  "properties": {
    "gn:adm1_name":"Ehimeken",
    "gn:adm2_name":"Matsuyamashi",
    "gn:name":"Edamatsu",
    "iso:country":"JP",
    "wof:name":"790-0962",
    "wof:placetype":"postalcode"
},
  "geometry": {"coordinates":[132.785,33.8308],"type":"Point"}
}