{
  "type": "Feature",
  "properties": {
    "gn:adm1_name":"Kanagawaken",
    "gn:adm2_name":"Yokohamashinakaku",
    "gn:name":"Kashiwaba",
    "iso:country":"JP",
    "wof:name":"231-0866",
    "wof:placetype":"postalcode"
},
  "geometry": {"coordinates":[139.643,35.4326],"type":"Point"}
}