{
  "type": "Feature",
  "properties": {
    "gn:adm1_name":"Fukushimaken",
    "gn:adm2_name":"Ishikawagun'Ishikawamachi",
    "gn:name":"Kitayama",
    "iso:country":"JP",
    "wof:name":"963-7802",
    "wof:placetype":"postalcode"
},
  "geometry": {"coordinates":[140.48310000000001,37.1646],"type":"Point"}
}