{
  "type": "Feature",
  "properties": {
    "gn:adm1_name":"Chibaken",
    "gn:adm2_name":"Katsuurashi",
    "gn:name":"Hamakatsuura",
    "iso:country":"JP",
    "wof:name":"299-5233",
    "wof:placetype":"postalcode"
},
  "geometry": {"coordinates":[140.31440000000001,35.1458],"type":"Point"}
}