{
  "type": "Feature",
  "properties": {
    "gn:adm1_name":"Ishikawaken",
    "gn:adm2_name":"Kanazawashi",
    "gn:name":"Moroemachi(Kamichou)",
    "iso:country":"JP",
    "wof:name":"920-0015",
    "wof:placetype":"postalcode"
},
  "geometry": {"coordinates":[136.64519999999999,36.5919],"type":"Point"}
}