{
  "type": "Feature",
  "properties": {
    "gn:adm1_name":"Oosakafu",
    "gn:adm2_name":"Tondabayashishi",
    "gn:name":"Tondabayashichou",
    "iso:country":"JP",
    "wof:name":"584-0033",
    "wof:placetype":"postalcode"
},
  "geometry": {"coordinates":[135.6028,34.5004],"type":"Point"}
}