{
  "type": "Feature",
  "properties": {
    "gn:adm1_name":"Gifuken",
    "gn:adm2_name":"Kamoguntomikachou",
    "gn:name":"Kajita",
    "iso:country":"JP",
    "wof:name":"501-3301",
    "wof:placetype":"postalcode"
},
  "geometry": {"coordinates":[136.9914,35.4944],"type":"Point"}
}