{
  "type": "Feature",
  "properties": {
    "gn:adm1_name":"Shizuokaken",
    "gn:adm2_name":"Iwatagunfukudechou",
    "gn:name":"Nakajima",
    "iso:country":"JP",
    "wof:name":"437-1204",
    "wof:placetype":"postalcode"
},
  "geometry": {"coordinates":[137.87180000000001,34.6771],"type":"Point"}
}