{
  "type": "Feature",
  "properties": {
    "gn:adm1_name":"Oosakafu",
    "gn:adm2_name":"Takatsukishi",
    "gn:name":"Nariai",
    "iso:country":"JP",
    "wof:name":"569-1012",
    "wof:placetype":"postalcode"
},
  "geometry": {"coordinates":[135.62729999999999,34.8795],"type":"Point"}
}