{
  "type": "Feature",
  "properties": {
    "gn:adm1_name":"Kyoutofu",
    "gn:adm2_name":"Kyoutoshifushimiku",
    "gn:name":"Hiranochou",
    "iso:country":"JP",
    "wof:name":"612-8057",
    "wof:placetype":"postalcode"
},
  "geometry": {"coordinates":[135.76060000000001,34.9324],"type":"Point"}
}