{
  "type": "Feature",
  "properties": {
    "gn:adm1_name":"Fukuokaken",
    "gn:adm2_name":"Miigunkitanomachi",
    "gn:name":"Inakazu",
    "iso:country":"JP",
    "wof:name":"830-1126",
    "wof:placetype":"postalcode"
},
  "geometry": {"coordinates":[130.60550000000001,33.3546],"type":"Point"}
}