{
  "type": "Feature",
  "properties": {
    "gn:adm1_name":"Shizuokaken",
    "gn:adm2_name":"Inasagun'Inasachou",
    "gn:name":"Iinoya",
    "iso:country":"JP",
    "wof:name":"431-2212",
    "wof:placetype":"postalcode"
},
  "geometry": {"coordinates":[137.6721,34.8316],"type":"Point"}
}