{
  "type": "Feature",
  "properties": {
    "gn:adm1_name":"Okayamaken",
    "gn:adm2_name":"Kasaokashi",
    "gn:name":"Nishimobira",
    "iso:country":"JP",
    "wof:name":"714-0064",
    "wof:placetype":"postalcode"
},
  "geometry": {"coordinates":[133.4513,34.487],"type":"Point"}
}