{
  "type": "Feature",
  "properties": {
    "gn:adm1_name":"Wakayamaken",
    "gn:adm2_name":"Nagagun'Iwadechou",
    "gn:name":"Takase",
    "iso:country":"JP",
    "wof:name":"649-6234",
    "wof:placetype":"postalcode"
},
  "geometry": {"coordinates":[135.31319999999999,34.2566],"type":"Point"}
}