{
  "type": "Feature",
  "properties": {
    "gn:adm1_name":"Aichiken",
    "gn:adm2_name":"Higashikamogunshimoyamamura",
    "gn:name":"Kaburaki",
    "iso:country":"JP",
    "wof:name":"444-3223",
    "wof:placetype":"postalcode"
},
  "geometry": {"coordinates":[137.2869,35.0218],"type":"Point"}
}