{
  "type": "Feature",
  "properties": {
    "gn:adm1_name":"Oosakafu",
    "gn:adm2_name":"Izumishi",
    "gn:name":"Shimonomiyachou",
    "iso:country":"JP",
    "wof:name":"594-1121",
    "wof:placetype":"postalcode"
},
  "geometry": {"coordinates":[135.49109999999999,34.4303],"type":"Point"}
}