{
  "type": "Feature",
  "properties": {
    "gn:adm1_name":"Hiroshimaken",
    "gn:adm2_name":"Yamagatagungeihokuchou",
    "gn:name":"Koujinbara",
    "iso:country":"JP",
    "wof:name":"731-2431",
    "wof:placetype":"postalcode"
},
  "geometry": {"coordinates":[132.24160000000001,34.7328],"type":"Point"}
}