{
  "type": "Feature",
  "properties": {
    "gn:adm1_name":"Aichiken",
    "gn:adm2_name":"Tsushimashi",
    "gn:name":"Matsubarachou",
    "iso:country":"JP",
    "wof:name":"496-0818",
    "wof:placetype":"postalcode"
},
  "geometry": {"coordinates":[136.72409999999999,35.1832],"type":"Point"}
}