{
  "type": "Feature",
  "properties": {
    "gn:adm1_name":"Fukuokaken",
    "gn:adm2_name":"Fukuokashihigashiku",
    "gn:name":"Shiohama",
    "iso:country":"JP",
    "wof:name":"811-0203",
    "wof:placetype":"postalcode"
},
  "geometry": {"coordinates":[130.42009999999999,33.6928],"type":"Point"}
}