{
  "type": "Feature",
  "properties": {
    "gn:adm1_name":"Sagaken",
    "gn:adm2_name":"Takushi",
    "gn:name":"Kitatakumachimeipurutaun",
    "iso:country":"JP",
    "wof:name":"846-0007",
    "wof:placetype":"postalcode"
},
  "geometry": {"coordinates":[130.1217,33.2899],"type":"Point"}
}