{
  "type": "Feature",
  "properties": {
    "gn:adm1_name":"Ibarakiken",
    "gn:adm2_name":"Nakagun'Oomiyamachi",
    "gn:name":"Iwazaki",
    "iso:country":"JP",
    "wof:name":"319-2211",
    "wof:placetype":"postalcode"
},
  "geometry": {"coordinates":[140.4109,36.5953],"type":"Point"}
}