{
  "type": "Feature",
  "properties": {
    "gn:adm1_name":"Hiroshimaken",
    "gn:adm2_name":"Miharashi",
    "gn:name":"Yorikane",
    "iso:country":"JP",
    "wof:name":"723-0054",
    "wof:placetype":"postalcode"
},
  "geometry": {"coordinates":[133.05799999999999,34.3992],"type":"Point"}
}