{
  "type": "Feature",
  "properties": {
    "gn:adm1_name":"Hiroshimaken",
    "gn:adm2_name":"Ootakeshi",
    "gn:name":"Higashisakae",
    "iso:country":"JP",
    "wof:name":"739-0601",
    "wof:placetype":"postalcode"
},
  "geometry": {"coordinates":[132.2313,34.2193],"type":"Point"}
}