{
  "type": "Feature",
  "properties": {
    "gn:adm1_name":"Aichiken",
    "gn:adm2_name":"Nagoyashinakamuraku",
    "gn:name":"Yasukunichou",
    "iso:country":"JP",
    "wof:name":"453-0065",
    "wof:placetype":"postalcode"
},
  "geometry": {"coordinates":[136.84999999999999,35.1696],"type":"Point"}
}