{
  "type": "Feature",
  "properties": {
    "gn:adm1_name":"Fukushimaken",
    "gn:adm2_name":"Dategunhobaramachi",
    "gn:name":"Yahatamachi",
    "iso:country":"JP",
    "wof:name":"960-0656",
    "wof:placetype":"postalcode"
},
  "geometry": {"coordinates":[140.5438,37.8308],"type":"Point"}
}