{
  "type": "Feature",
  "properties": {
    "gn:adm1_name":"Yamaguchiken",
    "gn:adm2_name":"Onodashi",
    "gn:name":"Midorigaoka",
    "iso:country":"JP",
    "wof:name":"756-0034",
    "wof:placetype":"postalcode"
},
  "geometry": {"coordinates":[131.1722,34.016],"type":"Point"}
}