{
  "type": "Feature",
  "properties": {
    "gn:adm1_name":"Aichiken",
    "gn:adm2_name":"Inazawashi",
    "gn:name":"Kugatahakusanchou",
    "iso:country":"JP",
    "wof:name":"492-8037",
    "wof:placetype":"postalcode"
},
  "geometry": {"coordinates":[136.8143,35.271],"type":"Point"}
}