{
  "type": "Feature",
  "properties": {
    "gn:adm1_name":"Okayamaken",
    "gn:adm2_name":"Okayamashi",
    "gn:name":"Megurochou",
    "iso:country":"JP",
    "wof:name":"704-8171",
    "wof:placetype":"postalcode"
},
  "geometry": {"coordinates":[134.00239999999999,34.6696],"type":"Point"}
}