{
  "type": "Feature",
  "properties": {
    "gn:adm1_name":"Hyougoken",
    "gn:adm2_name":"Koubeshitarumiku",
    "gn:name":"Tsutsujigaoka",
    "iso:country":"JP",
    "wof:name":"655-0853",
    "wof:placetype":"postalcode"
},
  "geometry": {"coordinates":[135.0772,34.6612],"type":"Point"}
}