{
  "type": "Feature",
  "properties": {
    "gn:adm1_name":"Hyougoken",
    "gn:adm2_name":"Onoshi",
    "gn:name":"Furukawachou",
    "iso:country":"JP",
    "wof:name":"675-1363",
    "wof:placetype":"postalcode"
},
  "geometry": {"coordinates":[134.9462,34.8801],"type":"Point"}
}