{
  "type": "Feature",
  "properties": {
    "gn:adm1_name":"Aichiken",
    "gn:adm2_name":"Higashikamogunshimoyamamura",
    "gn:name":"Azou",
    "iso:country":"JP",
    "wof:name":"444-3202",
    "wof:placetype":"postalcode"
},
  "geometry": {"coordinates":[137.41640000000001,35.0786],"type":"Point"}
}