{
  "type": "Feature",
  "properties": {
    "gn:adm1_name":"Kyoutofu",
    "gn:adm2_name":"Kyoutoshifushimiku",
    "gn:name":"Daigokawakubochou",
    "iso:country":"JP",
    "wof:name":"601-1378",
    "wof:placetype":"postalcode"
},
  "geometry": {"coordinates":[135.81180000000001,34.9548],"type":"Point"}
}