{
  "type": "Feature",
  "properties": {
    "gn:adm1_name":"Wakayamaken",
    "gn:adm2_name":"Wakayamashi",
    "gn:name":"Tanakamachi",
    "iso:country":"JP",
    "wof:name":"640-8329",
    "wof:placetype":"postalcode"
},
  "geometry": {"coordinates":[135.1884,34.2283],"type":"Point"}
}