{
  "type": "Feature",
  "properties": {
    "gn:adm1_name":"Saitamaken",
    "gn:adm2_name":"Hikigun'Ogawamachi",
    "gn:name":"Nakatsume",
    "iso:country":"JP",
    "wof:name":"355-0314",
    "wof:placetype":"postalcode"
},
  "geometry": {"coordinates":[139.29939999999999,36.0643],"type":"Point"}
}