{
  "type": "Feature",
  "properties": {
    "gn:adm1_name":"Miyagiken",
    "gn:adm2_name":"Shibatagunmuratamachi",
    "gn:name":"Ikanikeisaiganaibaai",
    "iso:country":"JP",
    "wof:name":"989-1300",
    "wof:placetype":"postalcode"
},
  "geometry": {"coordinates":[140.7242,38.0963],"type":"Point"}
}