{
  "type": "Feature",
  "properties": {
    "gn:adm1_name":"Wakayamaken",
    "gn:adm2_name":"Nagagunkokawachou",
    "gn:name":"Kamitomobuchi",
    "iso:country":"JP",
    "wof:name":"649-6571",
    "wof:placetype":"postalcode"
},
  "geometry": {"coordinates":[135.47399999999999,34.2328],"type":"Point"}
}