{
  "type": "Feature",
  "properties": {
    "gn:adm1_name":"Gifuken",
    "gn:adm2_name":"Sekishi",
    "gn:name":"Higashimachi",
    "iso:country":"JP",
    "wof:name":"501-3815",
    "wof:placetype":"postalcode"
},
  "geometry": {"coordinates":[136.93620000000001,35.4879],"type":"Point"}
}