{
  "type": "Feature",
  "properties": {
    "gn:adm1_name":"Miyagiken",
    "gn:adm2_name":"Toodagunkogotachou",
    "gn:name":"Sakuragichou",
    "iso:country":"JP",
    "wof:name":"987-0011",
    "wof:placetype":"postalcode"
},
  "geometry": {"coordinates":[141.06,38.5379],"type":"Point"}
}