{
  "type": "Feature",
  "properties": {
    "gn:adm1_name":"Naraken",
    "gn:adm2_name":"Yoshinoguntotsukawamura",
    "gn:name":"Oono",
    "iso:country":"JP",
    "wof:name":"637-1331",
    "wof:placetype":"postalcode"
},
  "geometry": {"coordinates":[135.83529999999999,33.9922],"type":"Point"}
}