{
  "type": "Feature",
  "properties": {
    "gn:adm1_name":"Shimaneken",
    "gn:adm2_name":"Iishigunmitoyachou",
    "gn:name":"Tonogouchi",
    "iso:country":"JP",
    "wof:name":"690-2633",
    "wof:placetype":"postalcode"
},
  "geometry": {"coordinates":[132.85249999999999,35.2778],"type":"Point"}
}