{
  "type": "Feature",
  "properties": {
    "gn:adm1_name":"Kumamotoken",
    "gn:adm2_name":"Yatsushiroshi",
    "gn:name":"Kitaheiwamachi",
    "iso:country":"JP",
    "wof:name":"869-5166",
    "wof:placetype":"postalcode"
},
  "geometry": {"coordinates":[130.55430000000001,32.4942],"type":"Point"}
}