{
  "type": "Feature",
  "properties": {
    "gn:adm1_name":"Aichiken",
    "gn:adm2_name":"Kariyashi",
    "gn:name":"Tennouchou",
    "iso:country":"JP",
    "wof:name":"448-0824",
    "wof:placetype":"postalcode"
},
  "geometry": {"coordinates":[136.99029999999999,34.9779],"type":"Point"}
}