{
  "type": "Feature",
  "properties": {
    "gn:adm1_name":"Okayamaken",
    "gn:adm2_name":"Shitsukigunyoshiichou",
    "gn:name":"Shimoshigi",
    "iso:country":"JP",
    "wof:name":"714-2231",
    "wof:placetype":"postalcode"
},
  "geometry": {"coordinates":[133.40690000000001,34.6836],"type":"Point"}
}