{
  "type": "Feature",
  "properties": {
    "gn:adm1_name":"Wakayamaken",
    "gn:adm2_name":"Hidakagunhidakachou",
    "gn:name":"Katakui",
    "iso:country":"JP",
    "wof:name":"649-1225",
    "wof:placetype":"postalcode"
},
  "geometry": {"coordinates":[135.0873,33.9393],"type":"Point"}
}