{
  "type": "Feature",
  "properties": {
    "gn:adm1_name":"Naraken",
    "gn:adm2_name":"Tenrishi",
    "gn:name":"Inabachou",
    "iso:country":"JP",
    "wof:name":"632-0083",
    "wof:placetype":"postalcode"
},
  "geometry": {"coordinates":[135.80340000000001,34.5941],"type":"Point"}
}