{
  "type": "Feature",
  "properties": {
    "gn:adm1_name":"Ooitaken",
    "gn:adm2_name":"Nakatsushi",
    "gn:name":"Emitakemachi",
    "iso:country":"JP",
    "wof:name":"871-0044",
    "wof:placetype":"postalcode"
},
  "geometry": {"coordinates":[131.18520000000001,33.6007],"type":"Point"}
}