{
  "type": "Feature",
  "properties": {
    "gn:adm1_name":"Ehimeken",
    "gn:adm2_name":"Houjoushi",
    "gn:name":"Aijima",
    "iso:country":"JP",
    "wof:name":"799-2433",
    "wof:placetype":"postalcode"
},
  "geometry": {"coordinates":[132.7063,34.0695],"type":"Point"}
}