{
  "type": "Feature",
  "properties": {
    "gn:adm1_name":"Chibaken",
    "gn:adm2_name":"Yotsukaidoushi",
    "gn:name":"Kamezaki",
    "iso:country":"JP",
    "wof:name":"284-0011",
    "wof:placetype":"postalcode"
},
  "geometry": {"coordinates":[140.1987,35.6991],"type":"Point"}
}