{
  "type": "Feature",
  "properties": {
    "gn:adm1_name":"Okinawaken",
    "gn:adm2_name":"Ishigakishi",
    "gn:name":"Tonoshiro",
    "iso:country":"JP",
    "wof:name":"907-0004",
    "wof:placetype":"postalcode"
},
  "geometry": {"coordinates":[124.1653,24.3402],"type":"Point"}
}