{
  "type": "Feature",
  "properties": {
    "gn:adm1_name":"Okayamaken",
    "gn:adm2_name":"Okayamashi",
    "gn:name":"Shimoashimori",
    "iso:country":"JP",
    "wof:name":"701-1464",
    "wof:placetype":"postalcode"
},
  "geometry": {"coordinates":[133.80549999999999,34.7179],"type":"Point"}
}