{
  "type": "Feature",
  "properties": {
    "gn:adm1_name":"Niigataken",
    "gn:adm2_name":"Nishikubikigunnoumachi",
    "gn:name":"Sakae",
    "iso:country":"JP",
    "wof:name":"949-1353",
    "wof:placetype":"postalcode"
},
  "geometry": {"coordinates":[137.9854,37.0996],"type":"Point"}
}