{
  "type": "Feature",
  "properties": {
    "gn:adm1_name":"Wakayamaken",
    "gn:adm2_name":"Higashimurogunnachikatsuurachou",
    "gn:name":"Minamihirano",
    "iso:country":"JP",
    "wof:name":"649-5453",
    "wof:placetype":"postalcode"
},
  "geometry": {"coordinates":[135.8826,33.6458],"type":"Point"}
}