{
  "type": "Feature",
  "properties": {
    "gn:adm1_name":"Kagoshimaken",
    "gn:adm2_name":"Ibusukigunyamagawachou",
    "gn:name":"Shin'Eichou",
    "iso:country":"JP",
    "wof:name":"891-0501",
    "wof:placetype":"postalcode"
},
  "geometry": {"coordinates":[130.64320000000001,31.2042],"type":"Point"}
}