{
  "type": "Feature",
  "properties": {
    "gn:adm1_name":"Yamanashiken",
    "gn:adm2_name":"Fujiyoshidashi",
    "gn:name":"Araya",
    "iso:country":"JP",
    "wof:name":"403-0006",
    "wof:placetype":"postalcode"
},
  "geometry": {"coordinates":[138.79910000000001,35.4671],"type":"Point"}
}