{
  "type": "Feature",
  "properties": {
    "gn:adm1_name":"Oosakafu",
    "gn:adm2_name":"Izumishi",
    "gn:name":"Fuchuuchou",
    "iso:country":"JP",
    "wof:name":"594-0071",
    "wof:placetype":"postalcode"
},
  "geometry": {"coordinates":[135.4271,34.4866],"type":"Point"}
}