{
  "type": "Feature",
  "properties": {
    "gn:adm1_name":"Yamagataken",
    "gn:adm2_name":"Tsuruokashi",
    "gn:name":"Takada",
    "iso:country":"JP",
    "wof:name":"997-0054",
    "wof:placetype":"postalcode"
},
  "geometry": {"coordinates":[139.8117,38.7483],"type":"Point"}
}