{
  "type": "Feature",
  "properties": {
    "gn:adm1_name":"Toukyouto",
    "gn:adm2_name":"Kokubunjishi",
    "gn:name":"Higashikoigakubo",
    "iso:country":"JP",
    "wof:name":"185-0014",
    "wof:placetype":"postalcode"
},
  "geometry": {"coordinates":[139.47139999999999,35.7096],"type":"Point"}
}