{
  "type": "Feature",
  "properties": {
    "gn:adm1_name":"Aichiken",
    "gn:adm2_name":"Nagoyashinakamuraku",
    "gn:name":"Higashijukuchou",
    "iso:country":"JP",
    "wof:name":"453-0063",
    "wof:placetype":"postalcode"
},
  "geometry": {"coordinates":[136.85069999999999,35.1743],"type":"Point"}
}