{
  "type": "Feature",
  "properties": {
    "gn:adm1_name":"Aichiken",
    "gn:adm2_name":"Komakishi",
    "gn:name":"Kasuganji",
    "iso:country":"JP",
    "wof:name":"485-0025",
    "wof:placetype":"postalcode"
},
  "geometry": {"coordinates":[136.93180000000001,35.2605],"type":"Point"}
}