{
  "type": "Feature",
  "properties": {
    "gn:adm1_name":"Shimaneken",
    "gn:adm2_name":"Goutsushi",
    "gn:name":"Matsukawachoukandui",
    "iso:country":"JP",
    "wof:name":"699-2835",
    "wof:placetype":"postalcode"
},
  "geometry": {"coordinates":[132.3177,35.0043],"type":"Point"}
}