{
  "type": "Feature",
  "properties": {
    "gn:adm1_name":"Kyoutofu",
    "gn:adm2_name":"Maidurushi",
    "gn:name":"Sakaidani",
    "iso:country":"JP",
    "wof:name":"624-0815",
    "wof:placetype":"postalcode"
},
  "geometry": {"coordinates":[135.3356,35.4354],"type":"Point"}
}