{
  "type": "Feature",
  "properties": {
    "gn:adm1_name":"Okayamaken",
    "gn:adm2_name":"Mitsugunkamogawachou",
    "gn:name":"Toyookashimo",
    "iso:country":"JP",
    "wof:name":"709-2661",
    "wof:placetype":"postalcode"
},
  "geometry": {"coordinates":[133.78129999999999,34.9172],"type":"Point"}
}