{
  "type": "Feature",
  "properties": {
    "gn:adm1_name":"Miyagiken",
    "gn:adm2_name":"Ishinomakishi",
    "gn:name":"Nishikichou",
    "iso:country":"JP",
    "wof:name":"986-0877",
    "wof:placetype":"postalcode"
},
  "geometry": {"coordinates":[141.28960000000001,38.4363],"type":"Point"}
}