{
  "type": "Feature",
  "properties": {
    "gn:adm1_name":"Aichiken",
    "gn:adm2_name":"Nishikamogun'Obaramura",
    "gn:name":"Ookusa",
    "iso:country":"JP",
    "wof:name":"470-0531",
    "wof:placetype":"postalcode"
},
  "geometry": {"coordinates":[137.2861,35.2319],"type":"Point"}
}