{
  "type": "Feature",
  "properties": {
    "gn:adm1_name":"Tokushimaken",
    "gn:adm2_name":"Itanogun'Aizumichou",
    "gn:name":"Higashinakatomi(Kitahouji)",
    "iso:country":"JP",
    "wof:name":"771-1222",
    "wof:placetype":"postalcode"
},
  "geometry": {"coordinates":[134.4803,34.1341],"type":"Point"}
}