{
  "type": "Feature",
  "properties": {
    "gn:adm1_name":"Shigaken",
    "gn:adm2_name":"Koukagun'Ishibechou",
    "gn:name":"Ishibenishi",
    "iso:country":"JP",
    "wof:name":"520-3105",
    "wof:placetype":"postalcode"
},
  "geometry": {"coordinates":[136.05279999999999,35.0136],"type":"Point"}
}