{
  "type": "Feature",
  "properties": {
    "gn:adm1_name":"Niigataken",
    "gn:adm2_name":"Tookamachishi",
    "gn:name":"Izumichou",
    "iso:country":"JP",
    "wof:name":"948-0062",
    "wof:placetype":"postalcode"
},
  "geometry": {"coordinates":[138.75649999999999,37.1328],"type":"Point"}
}