{
  "type": "Feature",
  "properties": {
    "gn:adm1_name":"Chibaken",
    "gn:adm2_name":"Ichikawashi",
    "gn:name":"Honshio",
    "iso:country":"JP",
    "wof:name":"272-0104",
    "wof:placetype":"postalcode"
},
  "geometry": {"coordinates":[139.9205,35.6911],"type":"Point"}
}