{
  "type": "Feature",
  "properties": {
    "gn:adm1_name":"Okinawaken",
    "gn:adm2_name":"Kunigamigunmotobuchou",
    "gn:name":"Inoha",
    "iso:country":"JP",
    "wof:name":"905-0228",
    "wof:placetype":"postalcode"
},
  "geometry": {"coordinates":[127.9091,26.6598],"type":"Point"}
}