{
  "type": "Feature",
  "properties": {
    "gn:adm1_name":"Kyoutofu",
    "gn:adm2_name":"Kyoutoshisakyouku",
    "gn:name":"Tanakanishiurachou",
    "iso:country":"JP",
    "wof:name":"606-8217",
    "wof:placetype":"postalcode"
},
  "geometry": {"coordinates":[135.77940000000001,35.0365],"type":"Point"}
}