{
  "type": "Feature",
  "properties": {
    "gn:adm1_name":"Miyagiken",
    "gn:adm2_name":"Kamigunkamimachi",
    "gn:name":"Itabashi",
    "iso:country":"JP",
    "wof:name":"981-4311",
    "wof:placetype":"postalcode"
},
  "geometry": {"coordinates":[140.80350000000001,38.5762],"type":"Point"}
}