{
  "type": "Feature",
  "properties": {
    "gn:adm1_name":"Niigataken",
    "gn:adm2_name":"Niigatashi",
    "gn:name":"Oogatahonchou",
    "iso:country":"JP",
    "wof:name":"950-0813",
    "wof:placetype":"postalcode"
},
  "geometry": {"coordinates":[139.12020000000001,37.9235],"type":"Point"}
}