{
  "type": "Feature",
  "properties": {
    "gn:adm1_name":"Toyamaken",
    "gn:adm2_name":"Takaokashi",
    "gn:name":"Kamiaso",
    "iso:country":"JP",
    "wof:name":"939-1274",
    "wof:placetype":"postalcode"
},
  "geometry": {"coordinates":[137.01070000000001,36.6836],"type":"Point"}
}