{
  "type": "Feature",
  "properties": {
    "gn:adm1_name":"Mieken",
    "gn:adm2_name":"Iseshi",
    "gn:name":"Seitachou",
    "iso:country":"JP",
    "wof:name":"516-0035",
    "wof:placetype":"postalcode"
},
  "geometry": {"coordinates":[136.7124,34.4775],"type":"Point"}
}