{
  "type": "Feature",
  "properties": {
    "gn:adm1_name":"Tottoriken",
    "gn:adm2_name":"Kurayoshishi",
    "gn:name":"Wada",
    "iso:country":"JP",
    "wof:name":"682-0912",
    "wof:placetype":"postalcode"
},
  "geometry": {"coordinates":[133.81020000000001,35.4443],"type":"Point"}
}