{
  "type": "Feature",
  "properties": {
    "gn:adm1_name":"Tokushimaken",
    "gn:adm2_name":"Nakagun'Aioichou",
    "gn:name":"Enokidani",
    "iso:country":"JP",
    "wof:name":"771-5320",
    "wof:placetype":"postalcode"
},
  "geometry": {"coordinates":[134.453,33.8457],"type":"Point"}
}