{
  "type": "Feature",
  "properties": {
    "gn:adm1_name":"Ibarakiken",
    "gn:adm2_name":"Nakagun'Ogawamura",
    "gn:name":"Kamiose",
    "iso:country":"JP",
    "wof:name":"319-2401",
    "wof:placetype":"postalcode"
},
  "geometry": {"coordinates":[140.3212,36.6069],"type":"Point"}
}