{
  "type": "Feature",
  "properties": {
    "gn:adm1_name":"Chibaken",
    "gn:adm2_name":"Matsudoshi",
    "gn:name":"Takadukashinden",
    "iso:country":"JP",
    "wof:name":"270-2222",
    "wof:placetype":"postalcode"
},
  "geometry": {"coordinates":[139.93770000000001,35.757],"type":"Point"}
}