{
  "type": "Feature",
  "properties": {
    "gn:adm1_name":"Shigaken",
    "gn:adm2_name":"Takashimagunmakinochou",
    "gn:name":"Makino",
    "iso:country":"JP",
    "wof:name":"520-1836",
    "wof:placetype":"postalcode"
},
  "geometry": {"coordinates":[136.03550000000001,35.4897],"type":"Point"}
}