{
  "type": "Feature",
  "properties": {
    "gn:adm1_name":"Kyoutofu",
    "gn:adm2_name":"Kyoutoshiyamashinaku",
    "gn:name":"Kanshuujikomatsubarachou",
    "iso:country":"JP",
    "wof:name":"607-8236",
    "wof:placetype":"postalcode"
},
  "geometry": {"coordinates":[135.80099999999999,34.9599],"type":"Point"}
}