{
  "type": "Feature",
  "properties": {
    "gn:adm1_name":"Aichiken",
    "gn:adm2_name":"Toyohashishi",
    "gn:name":"Sugiyamachou",
    "iso:country":"JP",
    "wof:name":"441-3302",
    "wof:placetype":"postalcode"
},
  "geometry": {"coordinates":[137.32310000000001,34.6794],"type":"Point"}
}