{
  "type": "Feature",
  "properties": {
    "gn:adm1_name":"Kagoshimaken",
    "gn:adm2_name":"Isagunhishikarichou",
    "gn:name":"Ikanikeisaiganaibaai",
    "iso:country":"JP",
    "wof:name":"895-2700",
    "wof:placetype":"postalcode"
},
  "geometry": {"coordinates":[130.63829999999999,32.0499],"type":"Point"}
}