{
  "type": "Feature",
  "properties": {
    "gn:adm1_name":"Saitamaken",
    "gn:adm2_name":"Satteshi",
    "gn:name":"Naka",
    "iso:country":"JP",
    "wof:name":"340-0115",
    "wof:placetype":"postalcode"
},
  "geometry": {"coordinates":[139.71690000000001,36.0768],"type":"Point"}
}