{
  "type": "Feature",
  "properties": {
    "gn:adm1_name":"Aichiken",
    "gn:adm2_name":"Kasugaishi",
    "gn:name":"Akechichou",
    "iso:country":"JP",
    "wof:name":"480-0303",
    "wof:placetype":"postalcode"
},
  "geometry": {"coordinates":[137.03360000000001,35.311],"type":"Point"}
}