{
  "type": "Feature",
  "properties": {
    "gn:adm1_name":"Ibarakiken",
    "gn:adm2_name":"Shimodateshi",
    "gn:name":"Kanamaru",
    "iso:country":"JP",
    "wof:name":"308-0804",
    "wof:placetype":"postalcode"
},
  "geometry": {"coordinates":[139.99959999999999,36.3114],"type":"Point"}
}