{
  "type": "Feature",
  "properties": {
    "gn:adm1_name":"Aichiken",
    "gn:adm2_name":"Nagoyashichikusaku",
    "gn:name":"Hagiokachou",
    "iso:country":"JP",
    "wof:name":"464-0805",
    "wof:placetype":"postalcode"
},
  "geometry": {"coordinates":[136.97059999999999,35.1481],"type":"Point"}
}