{
  "type": "Feature",
  "properties": {
    "gn:adm1_name":"Oosakafu",
    "gn:adm2_name":"Senbokuguntadaokachou",
    "gn:name":"Kitaide",
    "iso:country":"JP",
    "wof:name":"595-0803",
    "wof:placetype":"postalcode"
},
  "geometry": {"coordinates":[135.4076,34.4816],"type":"Point"}
}