{
  "type": "Feature",
  "properties": {
    "gn:adm1_name":"Shizuokaken",
    "gn:adm2_name":"Fujinomiyashi",
    "gn:name":"Yodohirachou",
    "iso:country":"JP",
    "wof:name":"418-0052",
    "wof:placetype":"postalcode"
},
  "geometry": {"coordinates":[138.60740000000001,35.2367],"type":"Point"}
}