{
  "type": "Feature",
  "properties": {
    "gn:adm1_name":"Niigataken",
    "gn:adm2_name":"Shibatashi",
    "gn:name":"Furutera",
    "iso:country":"JP",
    "wof:name":"957-0022",
    "wof:placetype":"postalcode"
},
  "geometry": {"coordinates":[139.36070000000001,37.9228],"type":"Point"}
}