{
  "type": "Feature",
  "properties": {
    "gn:adm1_name":"Okayamaken",
    "gn:adm2_name":"Kasaokashi",
    "gn:name":"Asahigaoka",
    "iso:country":"JP",
    "wof:name":"714-0056",
    "wof:placetype":"postalcode"
},
  "geometry": {"coordinates":[133.4819,34.5115],"type":"Point"}
}