{
  "type": "Feature",
  "properties": {
    "gn:adm1_name":"Naraken",
    "gn:adm2_name":"Yamatokooriyamashi",
    "gn:name":"Tangonoshouchou",
    "iso:country":"JP",
    "wof:name":"639-1122",
    "wof:placetype":"postalcode"
},
  "geometry": {"coordinates":[135.78569999999999,34.6277],"type":"Point"}
}