{
  "type": "Feature",
  "properties": {
    "gn:adm1_name":"Aichiken",
    "gn:adm2_name":"Nagoyashimoriyamaku",
    "gn:name":"Seko(Ooaza)",
    "iso:country":"JP",
    "wof:name":"463-0078",
    "wof:placetype":"postalcode"
},
  "geometry": {"coordinates":[136.93799999999999,35.2108],"type":"Point"}
}