{
  "type": "Feature",
  "properties": {
    "gn:adm1_name":"Toyamaken",
    "gn:adm2_name":"Toyamashi",
    "gn:name":"Aramachi",
    "iso:country":"JP",
    "wof:name":"930-0028",
    "wof:placetype":"postalcode"
},
  "geometry": {"coordinates":[137.2158,36.6909],"type":"Point"}
}