{
  "type": "Feature",
  "properties": {
    "gn:adm1_name":"Gifuken",
    "gn:adm2_name":"Oonogunnyuukawamura",
    "gn:name":"Machikata",
    "iso:country":"JP",
    "wof:name":"506-2123",
    "wof:placetype":"postalcode"
},
  "geometry": {"coordinates":[137.30619999999999,36.1694],"type":"Point"}
}