{
  "type": "Feature",
  "properties": {
    "gn:adm1_name":"Tochigiken",
    "gn:adm2_name":"Hagagunninomiyamachi",
    "gn:name":"Horigome",
    "iso:country":"JP",
    "wof:name":"321-4544",
    "wof:placetype":"postalcode"
},
  "geometry": {"coordinates":[139.93000000000001,36.3728],"type":"Point"}
}