{
  "type": "Feature",
  "properties": {
    "gn:adm1_name":"Naraken",
    "gn:adm2_name":"Yoshinogun'Ooyodochou",
    "gn:name":"Shimobuchi",
    "iso:country":"JP",
    "wof:name":"638-0821",
    "wof:placetype":"postalcode"
},
  "geometry": {"coordinates":[135.7861,34.3853],"type":"Point"}
}