{
  "type": "Feature",
  "properties": {
    "gn:adm1_name":"Fukuokaken",
    "gn:adm2_name":"Kitakyuushuushiyahatanishiku",
    "gn:name":"Jinnoharu",
    "iso:country":"JP",
    "wof:name":"807-0821",
    "wof:placetype":"postalcode"
},
  "geometry": {"coordinates":[130.73920000000001,33.8665],"type":"Point"}
}