{
  "type": "Feature",
  "properties": {
    "gn:adm1_name":"Niigataken",
    "gn:adm2_name":"Minamikanbaragunshitadamura",
    "gn:name":"Baba",
    "iso:country":"JP",
    "wof:name":"955-0167",
    "wof:placetype":"postalcode"
},
  "geometry": {"coordinates":[139.00569999999999,37.5898],"type":"Point"}
}