{
  "type": "Feature",
  "properties": {
    "gn:adm1_name":"Nagasakiken",
    "gn:adm2_name":"Nagasakishi",
    "gn:name":"Tadewaramachi",
    "iso:country":"JP",
    "wof:name":"851-0252",
    "wof:placetype":"postalcode"
},
  "geometry": {"coordinates":[129.9059,32.7415],"type":"Point"}
}