{
  "type": "Feature",
  "properties": {
    "gn:adm1_name":"Shizuokaken",
    "gn:adm2_name":"Hamakitashi",
    "gn:name":"Aburaishiki",
    "iso:country":"JP",
    "wof:name":"434-0027",
    "wof:placetype":"postalcode"
},
  "geometry": {"coordinates":[137.80709999999999,34.8025],"type":"Point"}
}