{
  "type": "Feature",
  "properties": {
    "gn:adm1_name":"Kyoutofu",
    "gn:adm2_name":"Ayabeshi",
    "gn:name":"Uwanobuchou",
    "iso:country":"JP",
    "wof:name":"623-0043",
    "wof:placetype":"postalcode"
},
  "geometry": {"coordinates":[135.23500000000001,35.2982],"type":"Point"}
}