{
  "type": "Feature",
  "properties": {
    "gn:adm1_name":"Gunmaken",
    "gn:adm2_name":"Isesakishi",
    "gn:name":"Higashikaminomiyamachi",
    "iso:country":"JP",
    "wof:name":"372-0815",
    "wof:placetype":"postalcode"
},
  "geometry": {"coordinates":[139.1533,36.3112],"type":"Point"}
}