{
  "type": "Feature",
  "properties": {
    "gn:adm1_name":"Chibaken",
    "gn:adm2_name":"Inbagunmotonomura",
    "gn:name":"Monoki",
    "iso:country":"JP",
    "wof:name":"270-2321",
    "wof:placetype":"postalcode"
},
  "geometry": {"coordinates":[140.19110000000001,35.8205],"type":"Point"}
}