{
  "type": "Feature",
  "properties": {
    "gn:adm1_name":"Kyoutofu",
    "gn:adm2_name":"Kyoutoshiyamashinaku",
    "gn:name":"Hinookatsutsumidanichou",
    "iso:country":"JP",
    "wof:name":"607-8494",
    "wof:placetype":"postalcode"
},
  "geometry": {"coordinates":[135.80009999999999,34.9979],"type":"Point"}
}