{
  "type": "Feature",
  "properties": {
    "gn:adm1_name":"Aichiken",
    "gn:adm2_name":"Nagoyashimeitouku",
    "gn:name":"Fujimorinishimachi",
    "iso:country":"JP",
    "wof:name":"465-0022",
    "wof:placetype":"postalcode"
},
  "geometry": {"coordinates":[137.01060000000001,35.188],"type":"Point"}
}