{
  "type": "Feature",
  "properties": {
    "gn:adm1_name":"Saitamaken",
    "gn:adm2_name":"Fukayashi",
    "gn:name":"Numajiri",
    "iso:country":"JP",
    "wof:name":"366-0017",
    "wof:placetype":"postalcode"
},
  "geometry": {"coordinates":[139.3109,36.2261],"type":"Point"}
}