{
  "type": "Feature",
  "properties": {
    "gn:adm1_name":"Mieken",
    "gn:adm2_name":"Yokkaichishi",
    "gn:name":"Shoueichou",
    "iso:country":"JP",
    "wof:name":"510-0057",
    "wof:placetype":"postalcode"
},
  "geometry": {"coordinates":[136.62739999999999,34.9581],"type":"Point"}
}