{
  "type": "Feature",
  "properties": {
    "gn:adm1_name":"Saitamaken",
    "gn:adm2_name":"Sakadoshi",
    "gn:name":"Kouya",
    "iso:country":"JP",
    "wof:name":"350-0204",
    "wof:placetype":"postalcode"
},
  "geometry": {"coordinates":[139.44839999999999,35.9577],"type":"Point"}
}