{
  "type": "Feature",
  "properties": {
    "gn:adm1_name":"Kouchiken",
    "gn:adm2_name":"Kouchishi",
    "gn:name":"Saenbachou",
    "iso:country":"JP",
    "wof:name":"780-0823",
    "wof:placetype":"postalcode"
},
  "geometry": {"coordinates":[133.54839999999999,33.5595],"type":"Point"}
}