{
  "type": "Feature",
  "properties": {
    "gn:adm1_name":"Fukuokaken",
    "gn:adm2_name":"Kitakyuushuushiyahatanishiku",
    "gn:name":"Sangamori",
    "iso:country":"JP",
    "wof:name":"807-0843",
    "wof:placetype":"postalcode"
},
  "geometry": {"coordinates":[130.73679999999999,33.8339],"type":"Point"}
}