{
  "type": "Feature",
  "properties": {
    "gn:adm1_name":"Saitamaken",
    "gn:adm2_name":"Ageoshi",
    "gn:name":"Haraichinaka",
    "iso:country":"JP",
    "wof:name":"362-0023",
    "wof:placetype":"postalcode"
},
  "geometry": {"coordinates":[139.62370000000001,35.9632],"type":"Point"}
}