{
  "type": "Feature",
  "properties": {
    "gn:adm1_name":"Kyoutofu",
    "gn:adm2_name":"Kyoutoshinakagyouku",
    "gn:name":"Tamakurachou",
    "iso:country":"JP",
    "wof:name":"604-8211",
    "wof:placetype":"postalcode"
},
  "geometry": {"coordinates":[135.75729999999999,35.0074],"type":"Point"}
}