{
  "type": "Feature",
  "properties": {
    "gn:adm1_name":"Saitamaken",
    "gn:adm2_name":"Hanyuushi",
    "gn:name":"Sunayama",
    "iso:country":"JP",
    "wof:name":"348-0036",
    "wof:placetype":"postalcode"
},
  "geometry": {"coordinates":[139.53120000000001,36.148],"type":"Point"}
}