{
  "type": "Feature",
  "properties": {
    "gn:adm1_name":"Fukushimaken",
    "gn:adm2_name":"Fukushimashi",
    "gn:name":"Minamimachi",
    "iso:country":"JP",
    "wof:name":"960-8162",
    "wof:placetype":"postalcode"
},
  "geometry": {"coordinates":[140.46270000000001,37.742],"type":"Point"}
}