{
  "type": "Feature",
  "properties": {
    "gn:adm1_name":"Okayamaken",
    "gn:adm2_name":"Tomatagunkamochou",
    "gn:name":"Kurogi",
    "iso:country":"JP",
    "wof:name":"709-3902",
    "wof:placetype":"postalcode"
},
  "geometry": {"coordinates":[134.04079999999999,35.2177],"type":"Point"}
}