{
  "type": "Feature",
  "properties": {
    "gn:adm1_name":"Gifuken",
    "gn:adm2_name":"Gifushi",
    "gn:name":"Minamihonjou3joudoori",
    "iso:country":"JP",
    "wof:name":"500-8342",
    "wof:placetype":"postalcode"
},
  "geometry": {"coordinates":[136.7465,35.4099],"type":"Point"}
}