{
  "type": "Feature",
  "properties": {
    "gn:adm1_name":"Oosakafu",
    "gn:adm2_name":"Yaoshi",
    "gn:name":"Tennoujiya",
    "iso:country":"JP",
    "wof:name":"581-0025",
    "wof:placetype":"postalcode"
},
  "geometry": {"coordinates":[135.6139,34.6041],"type":"Point"}
}