{
  "type": "Feature",
  "properties": {
    "gn:adm1_name":"Toukyouto",
    "gn:adm2_name":"Katsushikaku",
    "gn:name":"Shinkoiwa",
    "iso:country":"JP",
    "wof:name":"124-0024",
    "wof:placetype":"postalcode"
},
  "geometry": {"coordinates":[139.86199999999999,35.7163],"type":"Point"}
}