{
  "type": "Feature",
  "properties": {
    "gn:adm1_name":"Kouchiken",
    "gn:adm2_name":"Nagaokagunmotoyamachou",
    "gn:name":"Yoshinobu",
    "iso:country":"JP",
    "wof:name":"781-3603",
    "wof:placetype":"postalcode"
},
  "geometry": {"coordinates":[133.60579999999999,33.7413],"type":"Point"}
}