{
  "type": "Feature",
  "properties": {
    "gn:adm1_name":"Miyazakiken",
    "gn:adm2_name":"Nichinanshi",
    "gn:name":"Nakahirano",
    "iso:country":"JP",
    "wof:name":"887-0016",
    "wof:placetype":"postalcode"
},
  "geometry": {"coordinates":[131.3912,31.592],"type":"Point"}
}