{
  "type": "Feature",
  "properties": {
    "gn:adm1_name":"Fukuokaken",
    "gn:adm2_name":"Kurumeshi",
    "gn:name":"Honmachi",
    "iso:country":"JP",
    "wof:name":"830-0044",
    "wof:placetype":"postalcode"
},
  "geometry": {"coordinates":[130.5077,33.3119],"type":"Point"}
}