{
  "type": "Feature",
  "properties": {
    "gn:adm1_name":"Kanagawaken",
    "gn:adm2_name":"Zamashi",
    "gn:name":"Minamikurihara",
    "iso:country":"JP",
    "wof:name":"228-0015",
    "wof:placetype":"postalcode"
},
  "geometry": {"coordinates":[139.4178,35.4735],"type":"Point"}
}