{
  "type": "Feature",
  "properties": {
    "gn:adm1_name":"Kanagawaken",
    "gn:adm2_name":"Yokosukashi",
    "gn:name":"Akiya",
    "iso:country":"JP",
    "wof:name":"240-0105",
    "wof:placetype":"postalcode"
},
  "geometry": {"coordinates":[139.59999999999999,35.2413],"type":"Point"}
}