{
  "type": "Feature",
  "properties": {
    "gn:adm1_name":"Shizuokaken",
    "gn:adm2_name":"Fujishi",
    "gn:name":"Matsuoka",
    "iso:country":"JP",
    "wof:name":"416-0909",
    "wof:placetype":"postalcode"
},
  "geometry": {"coordinates":[138.63720000000001,35.1612],"type":"Point"}
}