{
  "type": "Feature",
  "properties": {
    "gn:adm1_name":"Shimaneken",
    "gn:adm2_name":"Masudashi",
    "gn:name":"Asakachou",
    "iso:country":"JP",
    "wof:name":"698-2253",
    "wof:placetype":"postalcode"
},
  "geometry": {"coordinates":[131.74700000000001,34.5757],"type":"Point"}
}