{
  "type": "Feature",
  "properties": {
    "gn:adm1_name":"Niigataken",
    "gn:adm2_name":"Nakakubikigunyoshikawamachi",
    "gn:name":"Ishidani",
    "iso:country":"JP",
    "wof:name":"949-3554",
    "wof:placetype":"postalcode"
},
  "geometry": {"coordinates":[138.50470000000001,37.1966],"type":"Point"}
}