{
  "type": "Feature",
  "properties": {
    "gn:adm1_name":"Shigaken",
    "gn:adm2_name":"Ikaguntakatsukichou",
    "gn:name":"Yokoyama",
    "iso:country":"JP",
    "wof:name":"529-0201",
    "wof:placetype":"postalcode"
},
  "geometry": {"coordinates":[136.22370000000001,35.4849],"type":"Point"}
}