{
  "type": "Feature",
  "properties": {
    "gn:adm1_name":"Ibarakiken",
    "gn:adm2_name":"Mitoshi",
    "gn:name":"Honchou",
    "iso:country":"JP",
    "wof:name":"310-0815",
    "wof:placetype":"postalcode"
},
  "geometry": {"coordinates":[140.49289999999999,36.365],"type":"Point"}
}