{
  "type": "Feature",
  "properties": {
    "gn:adm1_name":"Fukuokaken",
    "gn:adm2_name":"Ukihagunyoshiimachi",
    "gn:name":"Yawata",
    "iso:country":"JP",
    "wof:name":"839-1308",
    "wof:placetype":"postalcode"
},
  "geometry": {"coordinates":[130.74639999999999,33.3581],"type":"Point"}
}