{
  "type": "Feature",
  "properties": {
    "gn:adm1_name":"Saitamaken",
    "gn:adm2_name":"Fukayashi",
    "gn:name":"Ootsukajima",
    "iso:country":"JP",
    "wof:name":"366-0838",
    "wof:placetype":"postalcode"
},
  "geometry": {"coordinates":[139.26609999999999,36.2138],"type":"Point"}
}