{
  "type": "Feature",
  "properties": {
    "gn:adm1_name":"Kyoutofu",
    "gn:adm2_name":"Kyoutoshinakagyouku",
    "gn:name":"Nishinokyouminamikamiaichou",
    "iso:country":"JP",
    "wof:name":"604-8483",
    "wof:placetype":"postalcode"
},
  "geometry": {"coordinates":[135.73150000000001,35.0144],"type":"Point"}
}