{
  "type": "Feature",
  "properties": {
    "gn:adm1_name":"Wakayamaken",
    "gn:adm2_name":"Wakayamashi",
    "gn:name":"Nishitakamatsu",
    "iso:country":"JP",
    "wof:name":"641-0051",
    "wof:placetype":"postalcode"
},
  "geometry": {"coordinates":[135.17009999999999,34.2075],"type":"Point"}
}