{
  "type": "Feature",
  "properties": {
    "gn:adm1_name":"Ehimeken",
    "gn:adm2_name":"Kitauwagunyoshidachou",
    "gn:name":"Higashikouji",
    "iso:country":"JP",
    "wof:name":"799-3703",
    "wof:placetype":"postalcode"
},
  "geometry": {"coordinates":[132.54069999999999,33.2805],"type":"Point"}
}