{
  "type": "Feature",
  "properties": {
    "gn:adm1_name":"Naraken",
    "gn:adm2_name":"Takaichigun'Asukamura",
    "gn:name":"Jougo",
    "iso:country":"JP",
    "wof:name":"634-0113",
    "wof:placetype":"postalcode"
},
  "geometry": {"coordinates":[135.83019999999999,34.466],"type":"Point"}
}