{
  "type": "Feature",
  "properties": {
    "gn:adm1_name":"Naganoken",
    "gn:adm2_name":"Nakanoshi",
    "gn:name":"Nanguu",
    "iso:country":"JP",
    "wof:name":"383-0031",
    "wof:placetype":"postalcode"
},
  "geometry": {"coordinates":[138.37090000000001,36.7384],"type":"Point"}
}