{
  "type": "Feature",
  "properties": {
    "gn:adm1_name":"Ibarakiken",
    "gn:adm2_name":"Makabegunsekijoumachi",
    "gn:name":"Funadama",
    "iso:country":"JP",
    "wof:name":"308-0121",
    "wof:placetype":"postalcode"
},
  "geometry": {"coordinates":[139.91050000000001,36.2743],"type":"Point"}
}