{
  "type": "Feature",
  "properties": {
    "gn:adm1_name":"Ehimeken",
    "gn:adm2_name":"Matsuyamashi",
    "gn:name":"Izumimachi",
    "iso:country":"JP",
    "wof:name":"790-0025",
    "wof:placetype":"postalcode"
},
  "geometry": {"coordinates":[132.7671,33.8327],"type":"Point"}
}