{
  "type": "Feature",
  "properties": {
    "gn:adm1_name":"Kyoutofu",
    "gn:adm2_name":"Maidurushi",
    "gn:name":"Shidaka",
    "iso:country":"JP",
    "wof:name":"624-0102",
    "wof:placetype":"postalcode"
},
  "geometry": {"coordinates":[135.24879999999999,35.4331],"type":"Point"}
}