{
  "type": "Feature",
  "properties": {
    "gn:adm1_name":"Nagasakiken",
    "gn:adm2_name":"Nishisonogigunnagayochou",
    "gn:name":"Marutagou",
    "iso:country":"JP",
    "wof:name":"851-2124",
    "wof:placetype":"postalcode"
},
  "geometry": {"coordinates":[129.8817,32.8269],"type":"Point"}
}