{
  "type": "Feature",
  "properties": {
    "gn:adm1_name":"Kyoutofu",
    "gn:adm2_name":"Kyoutoshihigashiyamaku",
    "gn:name":"Fukuinetakaharachou",
    "iso:country":"JP",
    "wof:name":"605-0984",
    "wof:placetype":"postalcode"
},
  "geometry": {"coordinates":[135.7671,34.9748],"type":"Point"}
}