{
  "type": "Feature",
  "properties": {
    "gn:adm1_name":"Ibarakiken",
    "gn:adm2_name":"Mitoshi",
    "gn:name":"Nakaoono",
    "iso:country":"JP",
    "wof:name":"310-0821",
    "wof:placetype":"postalcode"
},
  "geometry": {"coordinates":[140.5438,36.3593],"type":"Point"}
}