{
  "type": "Feature",
  "properties": {
    "gn:adm1_name":"Yamanashiken",
    "gn:adm2_name":"Minamikomagunmasuhochou",
    "gn:name":"Kobayashi",
    "iso:country":"JP",
    "wof:name":"400-0504",
    "wof:placetype":"postalcode"
},
  "geometry": {"coordinates":[138.45490000000001,35.5744],"type":"Point"}
}