{
  "type": "Feature",
  "properties": {
    "gn:adm1_name":"Niigataken",
    "gn:adm2_name":"Santougunkoshijimachi",
    "gn:name":"Kamagashima(Sonota)",
    "iso:country":"JP",
    "wof:name":"949-5404",
    "wof:placetype":"postalcode"
},
  "geometry": {"coordinates":[138.80670000000001,37.3799],"type":"Point"}
}