{
  "type": "Feature",
  "properties": {
    "gn:adm1_name":"Niigataken",
    "gn:adm2_name":"Iwafunegun'Arakawamachi",
    "gn:name":"Yamaguchi",
    "iso:country":"JP",
    "wof:name":"959-3133",
    "wof:placetype":"postalcode"
},
  "geometry": {"coordinates":[139.44370000000001,38.123],"type":"Point"}
}