{
  "type": "Feature",
  "properties": {
    "gn:adm1_name":"Fukushimaken",
    "gn:adm2_name":"Tamuragunmiharumachi",
    "gn:name":"Tsurumakita",
    "iso:country":"JP",
    "wof:name":"963-7742",
    "wof:placetype":"postalcode"
},
  "geometry": {"coordinates":[140.482,37.4411],"type":"Point"}
}