{
  "type": "Feature",
  "properties": {
    "gn:adm1_name":"Tochigiken",
    "gn:adm2_name":"Utsunomiyashi",
    "gn:name":"Suzumenomiya",
    "iso:country":"JP",
    "wof:name":"321-0132",
    "wof:placetype":"postalcode"
},
  "geometry": {"coordinates":[139.8707,36.4933],"type":"Point"}
}