{
  "type": "Feature",
  "properties": {
    "gn:adm1_name":"Fukushimaken",
    "gn:adm2_name":"Shirakawashi",
    "gn:name":"Ootemachi",
    "iso:country":"JP",
    "wof:name":"961-0908",
    "wof:placetype":"postalcode"
},
  "geometry": {"coordinates":[140.21440000000001,37.1284],"type":"Point"}
}