{
  "type": "Feature",
  "properties": {
    "gn:adm1_name":"Shigaken",
    "gn:adm2_name":"Oumihachimanshi",
    "gn:name":"Nagaharachoukami",
    "iso:country":"JP",
    "wof:name":"523-0849",
    "wof:placetype":"postalcode"
},
  "geometry": {"coordinates":[136.0943,35.1377],"type":"Point"}
}