{
  "type": "Feature",
  "properties": {
    "gn:adm1_name":"Naganoken",
    "gn:adm2_name":"Matsumotoshi",
    "gn:name":"Kotobukinaka",
    "iso:country":"JP",
    "wof:name":"399-0026",
    "wof:placetype":"postalcode"
},
  "geometry": {"coordinates":[137.9701,36.184],"type":"Point"}
}