{
  "type": "Feature",
  "properties": {
    "gn:adm1_name":"Yamagataken",
    "gn:adm2_name":"Higashiokitamaguntakahatamachi",
    "gn:name":"Takahata",
    "iso:country":"JP",
    "wof:name":"992-0351",
    "wof:placetype":"postalcode"
},
  "geometry": {"coordinates":[140.19710000000001,38.0037],"type":"Point"}
}