{
  "type": "Feature",
  "properties": {
    "gn:adm1_name":"Kyoutofu",
    "gn:adm2_name":"Kyoutoshiyamashinaku",
    "gn:name":"Nishinoyamanakatomichou",
    "iso:country":"JP",
    "wof:name":"607-8305",
    "wof:placetype":"postalcode"
},
  "geometry": {"coordinates":[135.8039,34.9709],"type":"Point"}
}