{
  "type": "Feature",
  "properties": {
    "gn:adm1_name":"Toyamaken",
    "gn:adm2_name":"Toyamashi",
    "gn:name":"Hamakurosaki",
    "iso:country":"JP",
    "wof:name":"931-8414",
    "wof:placetype":"postalcode"
},
  "geometry": {"coordinates":[137.27850000000001,36.7553],"type":"Point"}
}