{
  "type": "Feature",
  "properties": {
    "gn:adm1_name":"Niigataken",
    "gn:adm2_name":"Sadogun'Aikawamachi",
    "gn:name":"Kitatatsushima",
    "iso:country":"JP",
    "wof:name":"952-2221",
    "wof:placetype":"postalcode"
},
  "geometry": {"coordinates":[138.3184,38.1793],"type":"Point"}
}