{
  "type": "Feature",
  "properties": {
    "gn:adm1_name":"Fukushimaken",
    "gn:adm2_name":"Iwakishi",
    "gn:name":"Ogawamachifukuoka",
    "iso:country":"JP",
    "wof:name":"979-3125",
    "wof:placetype":"postalcode"
},
  "geometry": {"coordinates":[140.84829999999999,37.1435],"type":"Point"}
}