{
  "type": "Feature",
  "properties": {
    "gn:adm1_name":"Naganoken",
    "gn:adm2_name":"Uedashi",
    "gn:name":"Juunin",
    "iso:country":"JP",
    "wof:name":"386-1435",
    "wof:placetype":"postalcode"
},
  "geometry": {"coordinates":[138.1953,36.3551],"type":"Point"}
}