{
  "type": "Feature",
  "properties": {
    "gn:adm1_name":"Ishikawaken",
    "gn:adm2_name":"Hakuigunshikamachi",
    "gn:name":"Taniya",
    "iso:country":"JP",
    "wof:name":"925-0206",
    "wof:placetype":"postalcode"
},
  "geometry": {"coordinates":[136.80289999999999,37.063],"type":"Point"}
}