{
  "type": "Feature",
  "properties": {
    "gn:adm1_name":"Tokushimaken",
    "gn:adm2_name":"Komatsushimashi",
    "gn:name":"Wadajimachou(Sonota)",
    "iso:country":"JP",
    "wof:name":"773-0025",
    "wof:placetype":"postalcode"
},
  "geometry": {"coordinates":[134.6371,33.9987],"type":"Point"}
}