{
  "type": "Feature",
  "properties": {
    "gn:adm1_name":"Aichiken",
    "gn:adm2_name":"Inazawashi",
    "gn:name":"Inokuchikitabatachou",
    "iso:country":"JP",
    "wof:name":"492-8151",
    "wof:placetype":"postalcode"
},
  "geometry": {"coordinates":[136.8229,35.2455],"type":"Point"}
}