{
  "type": "Feature",
  "properties": {
    "gn:adm1_name":"Chibaken",
    "gn:adm2_name":"Matsudoshi",
    "gn:name":"Oohashi",
    "iso:country":"JP",
    "wof:name":"270-2224",
    "wof:placetype":"postalcode"
},
  "geometry": {"coordinates":[139.9169,35.7675],"type":"Point"}
}