{
  "type": "Feature",
  "properties": {
    "gn:adm1_name":"Mieken",
    "gn:adm2_name":"Tsushi",
    "gn:name":"Koubechou",
    "iso:country":"JP",
    "wof:name":"514-0065",
    "wof:placetype":"postalcode"
},
  "geometry": {"coordinates":[136.48070000000001,34.7458],"type":"Point"}
}