{
  "type": "Feature",
  "properties": {
    "gn:adm1_name":"Fukuokaken",
    "gn:adm2_name":"Miyakogunsaigawamachi",
    "gn:name":"Yatsumizo",
    "iso:country":"JP",
    "wof:name":"824-0206",
    "wof:placetype":"postalcode"
},
  "geometry": {"coordinates":[130.9434,33.655],"type":"Point"}
}