{
  "type": "Feature",
  "properties": {
    "gn:adm1_name":"Hyougoken",
    "gn:adm2_name":"Akoushi",
    "gn:name":"Nakahiro",
    "iso:country":"JP",
    "wof:name":"678-0232",
    "wof:placetype":"postalcode"
},
  "geometry": {"coordinates":[134.39320000000001,34.7466],"type":"Point"}
}