{
  "type": "Feature",
  "properties": {
    "gn:adm1_name":"Naraken",
    "gn:adm2_name":"Gojoushi",
    "gn:name":"Kurunochou",
    "iso:country":"JP",
    "wof:name":"637-0018",
    "wof:placetype":"postalcode"
},
  "geometry": {"coordinates":[135.6942,34.3844],"type":"Point"}
}