{
  "type": "Feature",
  "properties": {
    "gn:adm1_name":"Yamagataken",
    "gn:adm2_name":"Kaminoyamashi",
    "gn:name":"Misakichou",
    "iso:country":"JP",
    "wof:name":"999-3123",
    "wof:placetype":"postalcode"
},
  "geometry": {"coordinates":[140.28129999999999,38.153],"type":"Point"}
}