{
  "type": "Feature",
  "properties": {
    "gn:adm1_name":"Aichiken",
    "gn:adm2_name":"Owariasahishi",
    "gn:name":"Asahigaokachounigoriike",
    "iso:country":"JP",
    "wof:name":"488-0085",
    "wof:placetype":"postalcode"
},
  "geometry": {"coordinates":[137.04069999999999,35.2271],"type":"Point"}
}