{
  "type": "Feature",
  "properties": {
    "gn:adm1_name":"Hyougoken",
    "gn:adm2_name":"Kawabegun'Inagawachou",
    "gn:name":"Minamitahara",
    "iso:country":"JP",
    "wof:name":"666-0235",
    "wof:placetype":"postalcode"
},
  "geometry": {"coordinates":[135.36590000000001,34.9086],"type":"Point"}
}