{
  "type": "Feature",
  "properties": {
    "gn:adm1_name":"Wakayamaken",
    "gn:adm2_name":"Goboushi",
    "gn:name":"Shioyachouminamishioya",
    "iso:country":"JP",
    "wof:name":"644-0024",
    "wof:placetype":"postalcode"
},
  "geometry": {"coordinates":[135.16319999999999,33.8642],"type":"Point"}
}