{
  "type": "Feature",
  "properties": {
    "gn:adm1_name":"Toyamaken",
    "gn:adm2_name":"Higashitonamigun'Inamimachi",
    "gn:name":"Shikanji",
    "iso:country":"JP",
    "wof:name":"932-0243",
    "wof:placetype":"postalcode"
},
  "geometry": {"coordinates":[136.97139999999999,36.5551],"type":"Point"}
}