{
  "type": "Feature",
  "properties": {
    "gn:adm1_name":"Shizuokaken",
    "gn:adm2_name":"Yaidushi",
    "gn:name":"Ooshimashinden",
    "iso:country":"JP",
    "wof:name":"425-0069",
    "wof:placetype":"postalcode"
},
  "geometry": {"coordinates":[138.3073,34.8149],"type":"Point"}
}