{
  "type": "Feature",
  "properties": {
    "gn:adm1_name":"Shimaneken",
    "gn:adm2_name":"Hamadashi",
    "gn:name":"Setomichou",
    "iso:country":"JP",
    "wof:name":"697-0057",
    "wof:placetype":"postalcode"
},
  "geometry": {"coordinates":[132.072,34.8923],"type":"Point"}
}