{
  "type": "Feature",
  "properties": {
    "gn:adm1_name":"Hyougoken",
    "gn:adm2_name":"Koubeshihyougoku",
    "gn:name":"Gonomiyachou",
    "iso:country":"JP",
    "wof:name":"652-0007",
    "wof:placetype":"postalcode"
},
  "geometry": {"coordinates":[135.1695,34.6921],"type":"Point"}
}