{
  "type": "Feature",
  "properties": {
    "gn:adm1_name":"Ibarakiken",
    "gn:adm2_name":"Makabegun'Akenomachi",
    "gn:name":"Akahama",
    "iso:country":"JP",
    "wof:name":"300-4523",
    "wof:placetype":"postalcode"
},
  "geometry": {"coordinates":[140.02109999999999,36.2157],"type":"Point"}
}