{
  "type": "Feature",
  "properties": {
    "gn:adm1_name":"Gifuken",
    "gn:adm2_name":"Anpachigunwanouchichou",
    "gn:name":"Shiobami",
    "iso:country":"JP",
    "wof:name":"503-0236",
    "wof:placetype":"postalcode"
},
  "geometry": {"coordinates":[136.61580000000001,35.2847],"type":"Point"}
}