{
  "type": "Feature",
  "properties": {
    "gn:adm1_name":"Nagasakiken",
    "gn:adm2_name":"Minamitakakigunminamikushiyamachou",
    "gn:name":"Hei(Kyoudomarimyou)",
    "iso:country":"JP",
    "wof:name":"854-0703",
    "wof:placetype":"postalcode"
},
  "geometry": {"coordinates":[130.14359999999999,32.6703],"type":"Point"}
}