{
  "type": "Feature",
  "properties": {
    "gn:adm1_name":"Fukuokaken",
    "gn:adm2_name":"Chikushigunnakagawamachi",
    "gn:name":"Ichinose",
    "iso:country":"JP",
    "wof:name":"811-1233",
    "wof:placetype":"postalcode"
},
  "geometry": {"coordinates":[130.43090000000001,33.4498],"type":"Point"}
}