{
  "type": "Feature",
  "properties": {
    "gn:adm1_name":"Miyazakiken",
    "gn:adm2_name":"Koyugunkawaminamichou",
    "gn:name":"Heida",
    "iso:country":"JP",
    "wof:name":"889-1302",
    "wof:placetype":"postalcode"
},
  "geometry": {"coordinates":[131.5394,32.1863],"type":"Point"}
}