{
  "type": "Feature",
  "properties": {
    "gn:adm1_name":"Yamagataken",
    "gn:adm2_name":"Nishiokitamagun'Ogunimachi",
    "gn:name":"Kaishou",
    "iso:country":"JP",
    "wof:name":"999-1311",
    "wof:placetype":"postalcode"
},
  "geometry": {"coordinates":[139.75729999999999,38.0971],"type":"Point"}
}