{
  "type": "Feature",
  "properties": {
    "gn:adm1_name":"Shigaken",
    "gn:adm2_name":"Koukaguntsuchiyamachou",
    "gn:name":"Akebihara",
    "iso:country":"JP",
    "wof:name":"528-0204",
    "wof:placetype":"postalcode"
},
  "geometry": {"coordinates":[136.35140000000001,34.9178],"type":"Point"}
}