{
  "type": "Feature",
  "properties": {
    "gn:adm1_name":"Hyougoken",
    "gn:adm2_name":"Koubeshinagataku",
    "gn:name":"Tozakidoori",
    "iso:country":"JP",
    "wof:name":"653-0845",
    "wof:placetype":"postalcode"
},
  "geometry": {"coordinates":[135.13820000000001,34.6609],"type":"Point"}
}