{
  "type": "Feature",
  "properties": {
    "gn:adm1_name":"Hiroshimaken",
    "gn:adm2_name":"Shoubarashi",
    "gn:name":"Nanatsukachou",
    "iso:country":"JP",
    "wof:name":"727-0023",
    "wof:placetype":"postalcode"
},
  "geometry": {"coordinates":[132.977,34.8367],"type":"Point"}
}