{
  "type": "Feature",
  "properties": {
    "gn:adm1_name":"Fukushimaken",
    "gn:adm2_name":"Nihonmatsushi",
    "gn:name":"Oodan",
    "iso:country":"JP",
    "wof:name":"964-0891",
    "wof:placetype":"postalcode"
},
  "geometry": {"coordinates":[140.42400000000001,37.5866],"type":"Point"}
}