{
  "type": "Feature",
  "properties": {
    "gn:adm1_name":"Ishikawaken",
    "gn:adm2_name":"Kanazawashi",
    "gn:name":"Ougimachi",
    "iso:country":"JP",
    "wof:name":"920-0927",
    "wof:placetype":"postalcode"
},
  "geometry": {"coordinates":[136.6694,36.5621],"type":"Point"}
}