{
  "type": "Feature",
  "properties": {
    "gn:adm1_name":"Kagoshimaken",
    "gn:adm2_name":"Makurazakishi",
    "gn:name":"Sakurayamahigashimachi",
    "iso:country":"JP",
    "wof:name":"898-0065",
    "wof:placetype":"postalcode"
},
  "geometry": {"coordinates":[130.30600000000001,31.2979],"type":"Point"}
}