{
  "type": "Feature",
  "properties": {
    "gn:adm1_name":"Chibaken",
    "gn:adm2_name":"Funabashishi",
    "gn:name":"Takidaichou",
    "iso:country":"JP",
    "wof:name":"274-0075",
    "wof:placetype":"postalcode"
},
  "geometry": {"coordinates":[140.0361,35.7103],"type":"Point"}
}