{
  "type": "Feature",
  "properties": {
    "gn:adm1_name":"Okayamaken",
    "gn:adm2_name":"Mitsugunkamogawachou",
    "gn:name":"Takatomi",
    "iso:country":"JP",
    "wof:name":"709-2402",
    "wof:placetype":"postalcode"
},
  "geometry": {"coordinates":[133.82300000000001,34.9218],"type":"Point"}
}