{
  "type": "Feature",
  "properties": {
    "gn:adm1_name":"Okinawaken",
    "gn:adm2_name":"Nahashi",
    "gn:name":"Nakaima",
    "iso:country":"JP",
    "wof:name":"902-0074",
    "wof:placetype":"postalcode"
},
  "geometry": {"coordinates":[127.7073,26.1961],"type":"Point"}
}