{
  "type": "Feature",
  "properties": {
    "gn:adm1_name":"Fukushimaken",
    "gn:adm2_name":"Kawanumagun'Aidubangemachi",
    "gn:name":"Ichinakashinchoukou",
    "iso:country":"JP",
    "wof:name":"969-6563",
    "wof:placetype":"postalcode"
},
  "geometry": {"coordinates":[139.81540000000001,37.5633],"type":"Point"}
}