{
  "type": "Feature",
  "properties": {
    "gn:adm1_name":"Ooitaken",
    "gn:adm2_name":"Usagun'Innaimachi",
    "gn:name":"Kamifunagi",
    "iso:country":"JP",
    "wof:name":"872-0326",
    "wof:placetype":"postalcode"
},
  "geometry": {"coordinates":[131.29140000000001,33.4434],"type":"Point"}
}