{
  "type": "Feature",
  "properties": {
    "gn:adm1_name":"Niigataken",
    "gn:adm2_name":"Nakakubikigunkakizakimachi",
    "gn:name":"Higashiyachi",
    "iso:country":"JP",
    "wof:name":"949-3224",
    "wof:placetype":"postalcode"
},
  "geometry": {"coordinates":[138.4151,37.2827],"type":"Point"}
}