{
  "type": "Feature",
  "properties": {
    "gn:adm1_name":"Hyougoken",
    "gn:adm2_name":"Koubeshinadaku",
    "gn:name":"Nadakitadoori",
    "iso:country":"JP",
    "wof:name":"657-0835",
    "wof:placetype":"postalcode"
},
  "geometry": {"coordinates":[135.22389999999999,34.7092],"type":"Point"}
}