{
  "type": "Feature",
  "properties": {
    "gn:adm1_name":"Aichiken",
    "gn:adm2_name":"Amagunyatomichou",
    "gn:name":"Inamoto",
    "iso:country":"JP",
    "wof:name":"498-0045",
    "wof:placetype":"postalcode"
},
  "geometry": {"coordinates":[136.76730000000001,35.0792],"type":"Point"}
}