{
  "type": "Feature",
  "properties": {
    "gn:adm1_name":"Niigataken",
    "gn:adm2_name":"Sadogun'Aikawamachi",
    "gn:name":"Nichoumeshinhamamachi",
    "iso:country":"JP",
    "wof:name":"952-1554",
    "wof:placetype":"postalcode"
},
  "geometry": {"coordinates":[138.36259999999999,38.0094],"type":"Point"}
}