{
  "type": "Feature",
  "properties": {
    "gn:adm1_name":"Kanagawaken",
    "gn:adm2_name":"Kawasakishikawasakiku",
    "gn:name":"Chidorichou",
    "iso:country":"JP",
    "wof:name":"210-0865",
    "wof:placetype":"postalcode"
},
  "geometry": {"coordinates":[139.75470000000001,35.5171],"type":"Point"}
}