{
  "type": "Feature",
  "properties": {
    "gn:adm1_name":"Fukushimaken",
    "gn:adm2_name":"Kitakatashi",
    "gn:name":"Oshimizuminami",
    "iso:country":"JP",
    "wof:name":"966-0825",
    "wof:placetype":"postalcode"
},
  "geometry": {"coordinates":[139.87280000000001,37.6478],"type":"Point"}
}