{
  "type": "Feature",
  "properties": {
    "gn:adm1_name":"Gunmaken",
    "gn:adm2_name":"Numatashi",
    "gn:name":"Higashiharashinmachi",
    "iso:country":"JP",
    "wof:name":"378-0053",
    "wof:placetype":"postalcode"
},
  "geometry": {"coordinates":[139.0573,36.6476],"type":"Point"}
}