{
  "type": "Feature",
  "properties": {
    "gn:adm1_name":"Ooitaken",
    "gn:adm2_name":"Nakatsushi",
    "gn:name":"Noyori",
    "iso:country":"JP",
    "wof:name":"879-0104",
    "wof:placetype":"postalcode"
},
  "geometry": {"coordinates":[131.2604,33.5562],"type":"Point"}
}