{
  "type": "Feature",
  "properties": {
    "gn:adm1_name":"Mieken",
    "gn:adm2_name":"Takigunmeiwachou",
    "gn:name":"Ikemura",
    "iso:country":"JP",
    "wof:name":"515-0317",
    "wof:placetype":"postalcode"
},
  "geometry": {"coordinates":[136.60550000000001,34.5176],"type":"Point"}
}