{
  "type": "Feature",
  "properties": {
    "gn:adm1_name":"Shimaneken",
    "gn:adm2_name":"Matsueshi",
    "gn:name":"Nishitanichou",
    "iso:country":"JP",
    "wof:name":"690-0142",
    "wof:placetype":"postalcode"
},
  "geometry": {"coordinates":[133.00229999999999,35.4907],"type":"Point"}
}