{
  "type": "Feature",
  "properties": {
    "gn:adm1_name":"Mieken",
    "gn:adm2_name":"Owaseshi",
    "gn:name":"Yanohamaoomichi",
    "iso:country":"JP",
    "wof:name":"519-3673",
    "wof:placetype":"postalcode"
},
  "geometry": {"coordinates":[136.20189999999999,34.0547],"type":"Point"}
}