{
  "type": "Feature",
  "properties": {
    "gn:adm1_name":"Hiroshimaken",
    "gn:adm2_name":"Saekigun'Oonochou",
    "gn:name":"Ikanatsu",
    "iso:country":"JP",
    "wof:name":"739-0478",
    "wof:placetype":"postalcode"
},
  "geometry": {"coordinates":[132.27619999999999,34.2979],"type":"Point"}
}