{
  "type": "Feature",
  "properties": {
    "gn:adm1_name":"Hyougoken",
    "gn:adm2_name":"Iboguntaishichou",
    "gn:name":"Ikanikeisaiganaibaai",
    "iso:country":"JP",
    "wof:name":"671-1500",
    "wof:placetype":"postalcode"
},
  "geometry": {"coordinates":[134.58170000000001,34.8335],"type":"Point"}
}