{
  "type": "Feature",
  "properties": {
    "gn:adm1_name":"Shizuokaken",
    "gn:adm2_name":"Shimodashi",
    "gn:name":"Naka",
    "iso:country":"JP",
    "wof:name":"415-0016",
    "wof:placetype":"postalcode"
},
  "geometry": {"coordinates":[138.94890000000001,34.6839],"type":"Point"}
}