{
  "type": "Feature",
  "properties": {
    "gn:adm1_name":"Wakayamaken",
    "gn:adm2_name":"Wakayamashi",
    "gn:name":"Matsue",
    "iso:country":"JP",
    "wof:name":"640-8421",
    "wof:placetype":"postalcode"
},
  "geometry": {"coordinates":[135.14269999999999,34.2466],"type":"Point"}
}