{
  "type": "Feature",
  "properties": {
    "gn:adm1_name":"Kyoutofu",
    "gn:adm2_name":"Ayabeshi",
    "gn:name":"Oyogichou",
    "iso:country":"JP",
    "wof:name":"623-0101",
    "wof:placetype":"postalcode"
},
  "geometry": {"coordinates":[135.34469999999999,35.3774],"type":"Point"}
}