{
  "type": "Feature",
  "properties": {
    "gn:adm1_name":"Okayamaken",
    "gn:adm2_name":"Tsuyamashi",
    "gn:name":"Yayoichou",
    "iso:country":"JP",
    "wof:name":"708-0823",
    "wof:placetype":"postalcode"
},
  "geometry": {"coordinates":[134.01499999999999,35.0743],"type":"Point"}
}