{
  "type": "Feature",
  "properties": {
    "gn:adm1_name":"Toyamaken",
    "gn:adm2_name":"Higashitonamigunfukunomachi",
    "gn:name":"Hiroyasu",
    "iso:country":"JP",
    "wof:name":"939-1534",
    "wof:placetype":"postalcode"
},
  "geometry": {"coordinates":[136.9151,36.5728],"type":"Point"}
}