{
  "type": "Feature",
  "properties": {
    "gn:adm1_name":"Tottoriken",
    "gn:adm2_name":"Ketakagun'Aoyachou",
    "gn:name":"Kurauchi",
    "iso:country":"JP",
    "wof:name":"689-0513",
    "wof:placetype":"postalcode"
},
  "geometry": {"coordinates":[134.02000000000001,35.4902],"type":"Point"}
}