{
  "type": "Feature",
  "properties": {
    "gn:adm1_name":"Toyamaken",
    "gn:adm2_name":"Higashitonamiguntairamura",
    "gn:name":"Takasourei",
    "iso:country":"JP",
    "wof:name":"939-1906",
    "wof:placetype":"postalcode"
},
  "geometry": {"coordinates":[136.9768,36.4408],"type":"Point"}
}