{
  "type": "Feature",
  "properties": {
    "gn:adm1_name":"Tochigiken",
    "gn:adm2_name":"Kamitsugagun'Ashiomachi",
    "gn:name":"Fukasawa",
    "iso:country":"JP",
    "wof:name":"321-1503",
    "wof:placetype":"postalcode"
},
  "geometry": {"coordinates":[139.4479,36.6629],"type":"Point"}
}