{
  "type": "Feature",
  "properties": {
    "gn:adm1_name":"Fukushimaken",
    "gn:adm2_name":"Nishishirakawagun'Izumizakimura",
    "gn:name":"Sekiwagu(Yakumojinja)",
    "iso:country":"JP",
    "wof:name":"969-0106",
    "wof:placetype":"postalcode"
},
  "geometry": {"coordinates":[140.32089999999999,37.1423],"type":"Point"}
}