{
  "type": "Feature",
  "properties": {
    "gn:adm1_name":"Gifuken",
    "gn:adm2_name":"Oonogunshoukawamura",
    "gn:name":"Ushimaru",
    "iso:country":"JP",
    "wof:name":"501-5422",
    "wof:placetype":"postalcode"
},
  "geometry": {"coordinates":[136.9425,36.0532],"type":"Point"}
}