{
  "type": "Feature",
  "properties": {
    "gn:adm1_name":"Niigataken",
    "gn:adm2_name":"Sadogun'Aikawamachi",
    "gn:name":"Nigorikawamachi",
    "iso:country":"JP",
    "wof:name":"952-1513",
    "wof:placetype":"postalcode"
},
  "geometry": {"coordinates":[138.238,38.037],"type":"Point"}
}