{
  "type": "Feature",
  "properties": {
    "gn:adm1_name":"Yamagataken",
    "gn:adm2_name":"Kaminoyamashi",
    "gn:name":"Keyakinomori",
    "iso:country":"JP",
    "wof:name":"999-3241",
    "wof:placetype":"postalcode"
},
  "geometry": {"coordinates":[140.27180000000001,38.1466],"type":"Point"}
}