{
  "type": "Feature",
  "properties": {
    "gn:adm1_name":"Tottoriken",
    "gn:adm2_name":"Tottorishi",
    "gn:name":"Kouro",
    "iso:country":"JP",
    "wof:name":"680-1177",
    "wof:placetype":"postalcode"
},
  "geometry": {"coordinates":[134.1549,35.4351],"type":"Point"}
}