{
  "type": "Feature",
  "properties": {
    "gn:adm1_name":"Oosakafu",
    "gn:adm2_name":"Oosakashitennoujiku",
    "gn:name":"Hiden'Inchou",
    "iso:country":"JP",
    "wof:name":"543-0055",
    "wof:placetype":"postalcode"
},
  "geometry": {"coordinates":[135.5147,34.6477],"type":"Point"}
}