{
  "type": "Feature",
  "properties": {
    "gn:adm1_name":"Hyougoken",
    "gn:adm2_name":"Kakogawashi",
    "gn:name":"Kakogawachoukimura",
    "iso:country":"JP",
    "wof:name":"675-0038",
    "wof:placetype":"postalcode"
},
  "geometry": {"coordinates":[134.8271,34.7642],"type":"Point"}
}