{
  "type": "Feature",
  "properties": {
    "gn:adm1_name":"Aichiken",
    "gn:adm2_name":"Higashikamogun'Asukechou",
    "gn:name":"Kuwaharada",
    "iso:country":"JP",
    "wof:name":"444-2325",
    "wof:placetype":"postalcode"
},
  "geometry": {"coordinates":[137.28700000000001,35.088],"type":"Point"}
}