{
  "type": "Feature",
  "properties": {
    "gn:adm1_name":"Kumamotoken",
    "gn:adm2_name":"Shimomashikigunjounanmachi",
    "gn:name":"Shimada",
    "iso:country":"JP",
    "wof:name":"861-4236",
    "wof:placetype":"postalcode"
},
  "geometry": {"coordinates":[130.70949999999999,32.7155],"type":"Point"}
}