{
  "type": "Feature",
  "properties": {
    "gn:adm1_name":"Oosakafu",
    "gn:adm2_name":"Oosakasayamashi",
    "gn:name":"Ikejirikita",
    "iso:country":"JP",
    "wof:name":"589-0009",
    "wof:placetype":"postalcode"
},
  "geometry": {"coordinates":[135.55179999999999,34.5145],"type":"Point"}
}