{
  "type": "Feature",
  "properties": {
    "gn:adm1_name":"Miyagiken",
    "gn:adm2_name":"Motoyoshigunkarakuwachou",
    "gn:name":"Deyama",
    "iso:country":"JP",
    "wof:name":"988-0506",
    "wof:placetype":"postalcode"
},
  "geometry": {"coordinates":[141.63460000000001,38.9597],"type":"Point"}
}