{
  "type": "Feature",
  "properties": {
    "gn:adm1_name":"Fukushimaken",
    "gn:adm2_name":"Adachigunmotomiyamachi",
    "gn:name":"Arai",
    "iso:country":"JP",
    "wof:name":"969-1104",
    "wof:placetype":"postalcode"
},
  "geometry": {"coordinates":[140.38040000000001,37.4867],"type":"Point"}
}