{
  "type": "Feature",
  "properties": {
    "gn:adm1_name":"Toyamaken",
    "gn:adm2_name":"Himishi",
    "gn:name":"Kosugi",
    "iso:country":"JP",
    "wof:name":"935-0424",
    "wof:placetype":"postalcode"
},
  "geometry": {"coordinates":[137.00540000000001,36.8954],"type":"Point"}
}