{
  "type": "Feature",
  "properties": {
    "gn:adm1_name":"Okinawaken",
    "gn:adm2_name":"Kunigamigunnakijinson",
    "gn:name":"Nakasone",
    "iso:country":"JP",
    "wof:name":"905-0401",
    "wof:placetype":"postalcode"
},
  "geometry": {"coordinates":[127.97629999999999,26.6834],"type":"Point"}
}