{
  "type": "Feature",
  "properties": {
    "gn:adm1_name":"Toyamaken",
    "gn:adm2_name":"Toyamashi",
    "gn:name":"Akigashima",
    "iso:country":"JP",
    "wof:name":"939-8252",
    "wof:placetype":"postalcode"
},
  "geometry": {"coordinates":[137.1917,36.6446],"type":"Point"}
}