{
  "type": "Feature",
  "properties": {
    "gn:adm1_name":"Shizuokaken",
    "gn:adm2_name":"Shizuokashi",
    "gn:name":"Kojima",
    "iso:country":"JP",
    "wof:name":"421-1301",
    "wof:placetype":"postalcode"
},
  "geometry": {"coordinates":[138.23769999999999,35.0571],"type":"Point"}
}