{
  "type": "Feature",
  "properties": {
    "gn:adm1_name":"Niigataken",
    "gn:adm2_name":"Minamiuonumagunshiozawamachi",
    "gn:name":"Oozato",
    "iso:country":"JP",
    "wof:name":"949-6412",
    "wof:placetype":"postalcode"
},
  "geometry": {"coordinates":[138.8655,37.0278],"type":"Point"}
}