{
  "type": "Feature",
  "properties": {
    "gn:adm1_name":"Shigaken",
    "gn:adm2_name":"Youkaichishi",
    "gn:name":"Shimofutamatachou",
    "iso:country":"JP",
    "wof:name":"527-0065",
    "wof:placetype":"postalcode"
},
  "geometry": {"coordinates":[136.21100000000001,35.0889],"type":"Point"}
}