{
  "type": "Feature",
  "properties": {
    "gn:adm1_name":"Shizuokaken",
    "gn:adm2_name":"Shimadashi",
    "gn:name":"Ita",
    "iso:country":"JP",
    "wof:name":"427-0034",
    "wof:placetype":"postalcode"
},
  "geometry": {"coordinates":[138.15020000000001,34.8506],"type":"Point"}
}