{
  "type": "Feature",
  "properties": {
    "gn:adm1_name":"Kumamotoken",
    "gn:adm2_name":"Kumamotoshi",
    "gn:name":"Aidomimachi",
    "iso:country":"JP",
    "wof:name":"861-4121",
    "wof:placetype":"postalcode"
},
  "geometry": {"coordinates":[130.65520000000001,32.7528],"type":"Point"}
}