{
  "type": "Feature",
  "properties": {
    "gn:adm1_name":"Oosakafu",
    "gn:adm2_name":"Takatsukishi",
    "gn:name":"Nishioohichou",
    "iso:country":"JP",
    "wof:name":"569-0045",
    "wof:placetype":"postalcode"
},
  "geometry": {"coordinates":[135.61869999999999,34.8209],"type":"Point"}
}