{
  "type": "Feature",
  "properties": {
    "gn:adm1_name":"Hiroshimaken",
    "gn:adm2_name":"Kureshi",
    "gn:name":"Nigataminamimachi",
    "iso:country":"JP",
    "wof:name":"737-0156",
    "wof:placetype":"postalcode"
},
  "geometry": {"coordinates":[132.65700000000001,34.2138],"type":"Point"}
}