{
  "type": "Feature",
  "properties": {
    "gn:adm1_name":"Mieken",
    "gn:adm2_name":"Kuwanagunnagashimachou",
    "gn:name":"Komae",
    "iso:country":"JP",
    "wof:name":"511-1144",
    "wof:placetype":"postalcode"
},
  "geometry": {"coordinates":[136.7046,35.0828],"type":"Point"}
}