{
  "type": "Feature",
  "properties": {
    "gn:adm1_name":"Niigataken",
    "gn:adm2_name":"Nagaokashi",
    "gn:name":"Shimogejou",
    "iso:country":"JP",
    "wof:name":"940-0012",
    "wof:placetype":"postalcode"
},
  "geometry": {"coordinates":[138.86250000000001,37.4851],"type":"Point"}
}