{
  "type": "Feature",
  "properties": {
    "gn:adm1_name":"Ishikawaken",
    "gn:adm2_name":"Kagashi",
    "gn:name":"Katayamadukojoumachi",
    "iso:country":"JP",
    "wof:name":"922-0413",
    "wof:placetype":"postalcode"
},
  "geometry": {"coordinates":[136.36060000000001,36.3375],"type":"Point"}
}