{
  "type": "Feature",
  "properties": {
    "gn:adm1_name":"Toukyouto",
    "gn:adm2_name":"Higashiyamatoshi",
    "gn:name":"Zoushiki",
    "iso:country":"JP",
    "wof:name":"207-0032",
    "wof:placetype":"postalcode"
},
  "geometry": {"coordinates":[139.4195,35.7518],"type":"Point"}
}