{
  "type": "Feature",
  "properties": {
    "gn:adm1_name":"Miyagiken",
    "gn:adm2_name":"Kurokawaguntaiwachou",
    "gn:name":"Ochiaimaino",
    "iso:country":"JP",
    "wof:name":"981-3405",
    "wof:placetype":"postalcode"
},
  "geometry": {"coordinates":[140.90770000000001,38.4353],"type":"Point"}
}