{
  "type": "Feature",
  "properties": {
    "gn:adm1_name":"Niigataken",
    "gn:adm2_name":"Santougunkoshijimachi",
    "gn:name":"Iiduka",
    "iso:country":"JP",
    "wof:name":"949-5414",
    "wof:placetype":"postalcode"
},
  "geometry": {"coordinates":[138.75380000000001,37.3878],"type":"Point"}
}