{
  "type": "Feature",
  "properties": {
    "gn:adm1_name":"Hyougoken",
    "gn:adm2_name":"Kanzakigunkouderachou",
    "gn:name":"Tsuneya",
    "iso:country":"JP",
    "wof:name":"679-2165",
    "wof:placetype":"postalcode"
},
  "geometry": {"coordinates":[134.72030000000001,34.9393],"type":"Point"}
}