{
  "type": "Feature",
  "properties": {
    "gn:adm1_name":"Aichiken",
    "gn:adm2_name":"Tokonameshi",
    "gn:name":"Koiehonmachi",
    "iso:country":"JP",
    "wof:name":"479-0838",
    "wof:placetype":"postalcode"
},
  "geometry": {"coordinates":[136.83349999999999,34.8913],"type":"Point"}
}