{
  "type": "Feature",
  "properties": {
    "gn:adm1_name":"Mieken",
    "gn:adm2_name":"Kameyamashi",
    "gn:name":"Nakayashikichou",
    "iso:country":"JP",
    "wof:name":"519-0127",
    "wof:placetype":"postalcode"
},
  "geometry": {"coordinates":[136.4538,34.8579],"type":"Point"}
}