{
  "type": "Feature",
  "properties": {
    "gn:adm1_name":"Gifuken",
    "gn:adm2_name":"Oogakishi",
    "gn:name":"Shinmachi",
    "iso:country":"JP",
    "wof:name":"503-0872",
    "wof:placetype":"postalcode"
},
  "geometry": {"coordinates":[136.6207,35.3587],"type":"Point"}
}