{
  "type": "Feature",
  "properties": {
    "gn:adm1_name":"Hiroshimaken",
    "gn:adm2_name":"Kamogunkurosechou",
    "gn:name":"Kamibouda",
    "iso:country":"JP",
    "wof:name":"724-0625",
    "wof:placetype":"postalcode"
},
  "geometry": {"coordinates":[132.66810000000001,34.3198],"type":"Point"}
}