{
  "type": "Feature",
  "properties": {
    "gn:adm1_name":"Okayamaken",
    "gn:adm2_name":"Okayamashi",
    "gn:name":"Onarichou",
    "iso:country":"JP",
    "wof:name":"703-8277",
    "wof:placetype":"postalcode"
},
  "geometry": {"coordinates":[133.94499999999999,34.6579],"type":"Point"}
}