{
  "type": "Feature",
  "properties": {
    "gn:adm1_name":"Ibarakiken",
    "gn:adm2_name":"Higashiibarakigunkatsuramura",
    "gn:name":"Takaku",
    "iso:country":"JP",
    "wof:name":"311-4324",
    "wof:placetype":"postalcode"
},
  "geometry": {"coordinates":[140.35380000000001,36.4952],"type":"Point"}
}