{
  "type": "Feature",
  "properties": {
    "gn:adm1_name":"Wakayamaken",
    "gn:adm2_name":"Wakayamashi",
    "gn:name":"Futasujime",
    "iso:country":"JP",
    "wof:name":"640-8068",
    "wof:placetype":"postalcode"
},
  "geometry": {"coordinates":[135.17019999999999,34.238],"type":"Point"}
}