{
  "type": "Feature",
  "properties": {
    "gn:adm1_name":"Yamagataken",
    "gn:adm2_name":"Yonezawashi",
    "gn:name":"Minamiharashinmachi",
    "iso:country":"JP",
    "wof:name":"992-1454",
    "wof:placetype":"postalcode"
},
  "geometry": {"coordinates":[140.10830000000001,37.8693],"type":"Point"}
}