{
  "type": "Feature",
  "properties": {
    "gn:adm1_name":"Toyamaken",
    "gn:adm2_name":"Oyabeshi",
    "gn:name":"Chou",
    "iso:country":"JP",
    "wof:name":"932-0842",
    "wof:placetype":"postalcode"
},
  "geometry": {"coordinates":[136.8553,36.647],"type":"Point"}
}