{
  "type": "Feature",
  "properties": {
    "gn:adm1_name":"Tochigiken",
    "gn:adm2_name":"Ashikagashi",
    "gn:name":"Oomaechou",
    "iso:country":"JP",
    "wof:name":"326-0845",
    "wof:placetype":"postalcode"
},
  "geometry": {"coordinates":[139.39930000000001,36.3581],"type":"Point"}
}