{
  "type": "Feature",
  "properties": {
    "gn:adm1_name":"Chibaken",
    "gn:adm2_name":"Choushishi",
    "gn:name":"Minamichou",
    "iso:country":"JP",
    "wof:name":"288-0038",
    "wof:placetype":"postalcode"
},
  "geometry": {"coordinates":[140.83920000000001,35.7295],"type":"Point"}
}