{
  "type": "Feature",
  "properties": {
    "gn:adm1_name":"Nagasakiken",
    "gn:adm2_name":"Higashisonogigunhasamichou",
    "gn:name":"Hiekobagou",
    "iso:country":"JP",
    "wof:name":"859-3726",
    "wof:placetype":"postalcode"
},
  "geometry": {"coordinates":[129.8741,33.1343],"type":"Point"}
}