{
  "type": "Feature",
  "properties": {
    "gn:adm1_name":"Chibaken",
    "gn:adm2_name":"Chouseigunchouseimura",
    "gn:name":"Iwanumatobichi",
    "iso:country":"JP",
    "wof:name":"299-4343",
    "wof:placetype":"postalcode"
},
  "geometry": {"coordinates":[140.34129999999999,35.4197],"type":"Point"}
}