{
  "type": "Feature",
  "properties": {
    "gn:adm1_name":"Aichiken",
    "gn:adm2_name":"Toyotashi",
    "gn:name":"Ichigichou",
    "iso:country":"JP",
    "wof:name":"471-0006",
    "wof:placetype":"postalcode"
},
  "geometry": {"coordinates":[137.1943,35.0966],"type":"Point"}
}