{
  "type": "Feature",
  "properties": {
    "gn:adm1_name":"Yamagataken",
    "gn:adm2_name":"Mogamigun'Ookuramura",
    "gn:name":"Shimizu",
    "iso:country":"JP",
    "wof:name":"996-0212",
    "wof:placetype":"postalcode"
},
  "geometry": {"coordinates":[140.22790000000001,38.6966],"type":"Point"}
}