{
  "type": "Feature",
  "properties": {
    "gn:adm1_name":"Wakayamaken",
    "gn:adm2_name":"Itogunkatsuragichou",
    "gn:name":"Anii",
    "iso:country":"JP",
    "wof:name":"649-7137",
    "wof:placetype":"postalcode"
},
  "geometry": {"coordinates":[135.50550000000001,34.2886],"type":"Point"}
}