{
  "type": "Feature",
  "properties": {
    "gn:adm1_name":"Gifuken",
    "gn:adm2_name":"Takayamashi",
    "gn:name":"Shimo2nomachi",
    "iso:country":"JP",
    "wof:name":"506-0842",
    "wof:placetype":"postalcode"
},
  "geometry": {"coordinates":[137.25919999999999,36.1447],"type":"Point"}
}