{
  "type": "Feature",
  "properties": {
    "gn:adm1_name":"Ishikawaken",
    "gn:adm2_name":"Kanazawashi",
    "gn:name":"Oritanimachi",
    "iso:country":"JP",
    "wof:name":"920-1112",
    "wof:placetype":"postalcode"
},
  "geometry": {"coordinates":[136.76310000000001,36.5105],"type":"Point"}
}