{
  "type": "Feature",
  "properties": {
    "gn:adm1_name":"Saitamaken",
    "gn:adm2_name":"Ageoshi",
    "gn:name":"Nishikichou",
    "iso:country":"JP",
    "wof:name":"362-0006",
    "wof:placetype":"postalcode"
},
  "geometry": {"coordinates":[139.58840000000001,35.9886],"type":"Point"}
}