{
  "type": "Feature",
  "properties": {
    "gn:adm1_name":"Fukuiken",
    "gn:adm2_name":"Obamashi",
    "gn:name":"Horiyashiki",
    "iso:country":"JP",
    "wof:name":"917-0097",
    "wof:placetype":"postalcode"
},
  "geometry": {"coordinates":[135.7484,35.5095],"type":"Point"}
}