{
  "type": "Feature",
  "properties": {
    "gn:adm1_name":"Shimaneken",
    "gn:adm2_name":"Ooharagunkamomachi",
    "gn:name":"Inoo",
    "iso:country":"JP",
    "wof:name":"699-1114",
    "wof:placetype":"postalcode"
},
  "geometry": {"coordinates":[132.90180000000001,35.3621],"type":"Point"}
}