{
  "type": "Feature",
  "properties": {
    "gn:adm1_name":"Shizuokaken",
    "gn:adm2_name":"Hamakitashi",
    "gn:name":"Numa",
    "iso:country":"JP",
    "wof:name":"434-0037",
    "wof:placetype":"postalcode"
},
  "geometry": {"coordinates":[137.78630000000001,34.7922],"type":"Point"}
}