{
  "type": "Feature",
  "properties": {
    "gn:adm1_name":"Fukuokaken",
    "gn:adm2_name":"Kitakyuushuushikokurakitaku",
    "gn:name":"Saenba",
    "iso:country":"JP",
    "wof:name":"803-0823",
    "wof:placetype":"postalcode"
},
  "geometry": {"coordinates":[130.86279999999999,33.8836],"type":"Point"}
}