{
  "type": "Feature",
  "properties": {
    "gn:adm1_name":"Mieken",
    "gn:adm2_name":"Owaseshi",
    "gn:name":"Nojimachi",
    "iso:country":"JP",
    "wof:name":"519-3617",
    "wof:placetype":"postalcode"
},
  "geometry": {"coordinates":[136.1918,34.0759],"type":"Point"}
}