{
  "type": "Feature",
  "properties": {
    "gn:adm1_name":"Ibarakiken",
    "gn:adm2_name":"Inashikigun'Azumamachi",
    "gn:name":"Yotsuya",
    "iso:country":"JP",
    "wof:name":"300-0742",
    "wof:placetype":"postalcode"
},
  "geometry": {"coordinates":[140.42769999999999,35.9123],"type":"Point"}
}