{
  "type": "Feature",
  "properties": {
    "gn:adm1_name":"Niigataken",
    "gn:adm2_name":"Jouetsushi",
    "gn:name":"Yoshiura",
    "iso:country":"JP",
    "wof:name":"949-1705",
    "wof:placetype":"postalcode"
},
  "geometry": {"coordinates":[138.1259,37.1639],"type":"Point"}
}