{
  "type": "Feature",
  "properties": {
    "gn:adm1_name":"Toyamaken",
    "gn:adm2_name":"Kurobeshi",
    "gn:name":"Amaike",
    "iso:country":"JP",
    "wof:name":"938-0032",
    "wof:placetype":"postalcode"
},
  "geometry": {"coordinates":[137.45150000000001,36.8671],"type":"Point"}
}