{
  "type": "Feature",
  "properties": {
    "gn:adm1_name":"Shizuokaken",
    "gn:adm2_name":"Iwatagunsakumachou",
    "gn:name":"Toguchi",
    "iso:country":"JP",
    "wof:name":"431-3904",
    "wof:placetype":"postalcode"
},
  "geometry": {"coordinates":[137.83760000000001,35.0757],"type":"Point"}
}