{
  "type": "Feature",
  "properties": {
    "gn:adm1_name":"Chibaken",
    "gn:adm2_name":"Ichiharashi",
    "gn:name":"Chiharadaiminami",
    "iso:country":"JP",
    "wof:name":"290-0142",
    "wof:placetype":"postalcode"
},
  "geometry": {"coordinates":[140.1849,35.5287],"type":"Point"}
}