{
  "type": "Feature",
  "properties": {
    "gn:adm1_name":"Ishikawaken",
    "gn:adm2_name":"Wajimashi",
    "gn:name":"Miimachimizuho",
    "iso:country":"JP",
    "wof:name":"929-2371",
    "wof:placetype":"postalcode"
},
  "geometry": {"coordinates":[136.96029999999999,37.2998],"type":"Point"}
}