{
  "type": "Feature",
  "properties": {
    "gn:adm1_name":"Shizuokaken",
    "gn:adm2_name":"Fujiedashi",
    "gn:name":"Otowachou",
    "iso:country":"JP",
    "wof:name":"426-0087",
    "wof:placetype":"postalcode"
},
  "geometry": {"coordinates":[138.2389,34.8736],"type":"Point"}
}