{
  "type": "Feature",
  "properties": {
    "gn:adm1_name":"Aichiken",
    "gn:adm2_name":"Ichinomiyashi",
    "gn:name":"Matsufuridoori",
    "iso:country":"JP",
    "wof:name":"491-0078",
    "wof:placetype":"postalcode"
},
  "geometry": {"coordinates":[136.8082,35.3155],"type":"Point"}
}