{
  "type": "Feature",
  "properties": {
    "gn:adm1_name":"Kagoshimaken",
    "gn:adm2_name":"Sendaishi",
    "gn:name":"Takaechou",
    "iso:country":"JP",
    "wof:name":"895-0131",
    "wof:placetype":"postalcode"
},
  "geometry": {"coordinates":[130.25299999999999,31.8226],"type":"Point"}
}