{
  "type": "Feature",
  "properties": {
    "gn:adm1_name":"Kouchiken",
    "gn:adm2_name":"Tosashi",
    "gn:name":"Kanbara",
    "iso:country":"JP",
    "wof:name":"781-1113",
    "wof:placetype":"postalcode"
},
  "geometry": {"coordinates":[133.3689,33.4856],"type":"Point"}
}