{
  "type": "Feature",
  "properties": {
    "gn:adm1_name":"Okayamaken",
    "gn:adm2_name":"Okayamashi",
    "gn:name":"Shikatahonmachi",
    "iso:country":"JP",
    "wof:name":"700-0915",
    "wof:placetype":"postalcode"
},
  "geometry": {"coordinates":[133.91650000000001,34.6517],"type":"Point"}
}