{
  "type": "Feature",
  "properties": {
    "gn:adm1_name":"Tochigiken",
    "gn:adm2_name":"Oyamashi",
    "gn:name":"Hongouchou",
    "iso:country":"JP",
    "wof:name":"323-0026",
    "wof:placetype":"postalcode"
},
  "geometry": {"coordinates":[139.80430000000001,36.3192],"type":"Point"}
}