{
  "type": "Feature",
  "properties": {
    "gn:adm1_name":"Tottoriken",
    "gn:adm2_name":"Saihakugunnawachou",
    "gn:name":"Komidou",
    "iso:country":"JP",
    "wof:name":"689-3222",
    "wof:placetype":"postalcode"
},
  "geometry": {"coordinates":[133.4803,35.4926],"type":"Point"}
}