{
  "type": "Feature",
  "properties": {
    "gn:adm1_name":"Wakayamaken",
    "gn:adm2_name":"Hidakagunyurachou",
    "gn:name":"Ena",
    "iso:country":"JP",
    "wof:name":"649-1132",
    "wof:placetype":"postalcode"
},
  "geometry": {"coordinates":[135.10759999999999,33.9882],"type":"Point"}
}