{
  "type": "Feature",
  "properties": {
    "gn:adm1_name":"Aichiken",
    "gn:adm2_name":"Handashi",
    "gn:name":"Oodakachou",
    "iso:country":"JP",
    "wof:name":"475-0015",
    "wof:placetype":"postalcode"
},
  "geometry": {"coordinates":[136.9478,34.9236],"type":"Point"}
}