{
  "type": "Feature",
  "properties": {
    "gn:adm1_name":"Aichiken",
    "gn:adm2_name":"Nagoyashiminamiku",
    "gn:name":"Motoshibatanishimachi",
    "iso:country":"JP",
    "wof:name":"457-0817",
    "wof:placetype":"postalcode"
},
  "geometry": {"coordinates":[136.90469999999999,35.0723],"type":"Point"}
}