{
  "type": "Feature",
  "properties": {
    "gn:adm1_name":"Fukuokaken",
    "gn:adm2_name":"Oomutashi",
    "gn:name":"Ukyoumachi",
    "iso:country":"JP",
    "wof:name":"836-0846",
    "wof:placetype":"postalcode"
},
  "geometry": {"coordinates":[130.43950000000001,33.0182],"type":"Point"}
}