{
  "type": "Feature",
  "properties": {
    "gn:adm1_name":"Mieken",
    "gn:adm2_name":"Suzukashi",
    "gn:name":"Hiratanakamachi",
    "iso:country":"JP",
    "wof:name":"513-0846",
    "wof:placetype":"postalcode"
},
  "geometry": {"coordinates":[136.53639999999999,34.8727],"type":"Point"}
}