{
  "type": "Feature",
  "properties": {
    "gn:adm1_name":"Gifuken",
    "gn:adm2_name":"Yoshikigunfurukawachou",
    "gn:name":"Kifunechou",
    "iso:country":"JP",
    "wof:name":"509-4243",
    "wof:placetype":"postalcode"
},
  "geometry": {"coordinates":[137.19130000000001,36.2297],"type":"Point"}
}