{
  "type": "Feature",
  "properties": {
    "gn:adm1_name":"Fukuiken",
    "gn:adm2_name":"Obamashi",
    "gn:name":"Shitsumi",
    "iso:country":"JP",
    "wof:name":"917-0103",
    "wof:placetype":"postalcode"
},
  "geometry": {"coordinates":[135.79900000000001,35.5242],"type":"Point"}
}