{
  "type": "Feature",
  "properties": {
    "gn:adm1_name":"Gifuken",
    "gn:adm2_name":"Minoshi",
    "gn:name":"Kuchinono",
    "iso:country":"JP",
    "wof:name":"501-3712",
    "wof:placetype":"postalcode"
},
  "geometry": {"coordinates":[136.92910000000001,35.5443],"type":"Point"}
}