{
  "type": "Feature",
  "properties": {
    "gn:adm1_name":"Aichiken",
    "gn:adm2_name":"Iwakurashi",
    "gn:name":"Higashishinmachi",
    "iso:country":"JP",
    "wof:name":"482-0001",
    "wof:placetype":"postalcode"
},
  "geometry": {"coordinates":[136.88380000000001,35.2809],"type":"Point"}
}