{
  "type": "Feature",
  "properties": {
    "gn:adm1_name":"Hyougoken",
    "gn:adm2_name":"Koubeshihyougoku",
    "gn:name":"Kikusuichou",
    "iso:country":"JP",
    "wof:name":"652-0058",
    "wof:placetype":"postalcode"
},
  "geometry": {"coordinates":[135.15790000000001,34.6834],"type":"Point"}
}