{
  "type": "Feature",
  "properties": {
    "gn:adm1_name":"Aichiken",
    "gn:adm2_name":"Toyotashi",
    "gn:name":"Shimizuchou",
    "iso:country":"JP",
    "wof:name":"471-0843",
    "wof:placetype":"postalcode"
},
  "geometry": {"coordinates":[137.11959999999999,35.0579],"type":"Point"}
}