{
  "type": "Feature",
  "properties": {
    "gn:adm1_name":"Yamaguchiken",
    "gn:adm2_name":"Kugagunshuutouchou",
    "gn:name":"Kamisudoori",
    "iso:country":"JP",
    "wof:name":"742-0426",
    "wof:placetype":"postalcode"
},
  "geometry": {"coordinates":[131.99100000000001,34.101],"type":"Point"}
}