{
  "type": "Feature",
  "properties": {
    "gn:adm1_name":"Gifuken",
    "gn:adm2_name":"Sekishi",
    "gn:name":"Magorokuchou",
    "iso:country":"JP",
    "wof:name":"501-3884",
    "wof:placetype":"postalcode"
},
  "geometry": {"coordinates":[136.91589999999999,35.487],"type":"Point"}
}