{
  "type": "Feature",
  "properties": {
    "gn:adm1_name":"Kyoutofu",
    "gn:adm2_name":"Kyoutoshinakagyouku",
    "gn:name":"Nishikihorikawachou",
    "iso:country":"JP",
    "wof:name":"604-8235",
    "wof:placetype":"postalcode"
},
  "geometry": {"coordinates":[135.75200000000001,35.0043],"type":"Point"}
}