{
  "type": "Feature",
  "properties": {
    "gn:adm1_name":"Saitamaken",
    "gn:adm2_name":"Saitamashiurawaku",
    "gn:name":"Kouzanchou",
    "iso:country":"JP",
    "wof:name":"330-0045",
    "wof:placetype":"postalcode"
},
  "geometry": {"coordinates":[139.65379999999999,35.8858],"type":"Point"}
}