{
  "type": "Feature",
  "properties": {
    "gn:adm1_name":"Oosakafu",
    "gn:adm2_name":"Takatsukishi",
    "gn:name":"Jounanchou",
    "iso:country":"JP",
    "wof:name":"569-0056",
    "wof:placetype":"postalcode"
},
  "geometry": {"coordinates":[135.62309999999999,34.838],"type":"Point"}
}