{
  "type": "Feature",
  "properties": {
    "gn:adm1_name":"Niigataken",
    "gn:adm2_name":"Jouetsushi",
    "gn:name":"Takasumi",
    "iso:country":"JP",
    "wof:name":"949-1716",
    "wof:placetype":"postalcode"
},
  "geometry": {"coordinates":[138.14680000000001,37.1454],"type":"Point"}
}