{
  "type": "Feature",
  "properties": {
    "gn:adm1_name":"Aichiken",
    "gn:adm2_name":"Nagoyashiminamiku",
    "gn:name":"Naruhamachou",
    "iso:country":"JP",
    "wof:name":"457-0806",
    "wof:placetype":"postalcode"
},
  "geometry": {"coordinates":[136.91460000000001,35.0741],"type":"Point"}
}