{
  "type": "Feature",
  "properties": {
    "gn:adm1_name":"Hiroshimaken",
    "gn:adm2_name":"Higashihiroshimashi",
    "gn:name":"Saijouasahimachi",
    "iso:country":"JP",
    "wof:name":"739-0012",
    "wof:placetype":"postalcode"
},
  "geometry": {"coordinates":[132.7457,34.4273],"type":"Point"}
}