{
  "type": "Feature",
  "properties": {
    "gn:adm1_name":"Hyougoken",
    "gn:adm2_name":"Akashishi",
    "gn:name":"Fujigaoka",
    "iso:country":"JP",
    "wof:name":"673-0046",
    "wof:placetype":"postalcode"
},
  "geometry": {"coordinates":[134.947,34.6665],"type":"Point"}
}