{
  "type": "Feature",
  "properties": {
    "gn:adm1_name":"Nagasakiken",
    "gn:adm2_name":"Shimabarashi",
    "gn:name":"Sugiyamamachi",
    "iso:country":"JP",
    "wof:name":"855-0068",
    "wof:placetype":"postalcode"
},
  "geometry": {"coordinates":[130.35339999999999,32.7965],"type":"Point"}
}