{
  "type": "Feature",
  "properties": {
    "gn:adm1_name":"Hyougoken",
    "gn:adm2_name":"Onoshi",
    "gn:name":"Kurokawachou",
    "iso:country":"JP",
    "wof:name":"675-1371",
    "wof:placetype":"postalcode"
},
  "geometry": {"coordinates":[134.94220000000001,34.8511],"type":"Point"}
}