{
  "type": "Feature",
  "properties": {
    "gn:adm1_name":"Shigaken",
    "gn:adm2_name":"Higashiazaiguntorahimechou",
    "gn:name":"Su",
    "iso:country":"JP",
    "wof:name":"529-0122",
    "wof:placetype":"postalcode"
},
  "geometry": {"coordinates":[136.2544,35.4167],"type":"Point"}
}