{
  "type": "Feature",
  "properties": {
    "gn:adm1_name":"Nagasakiken",
    "gn:adm2_name":"Hiradoshi",
    "gn:name":"Kihikidachou",
    "iso:country":"JP",
    "wof:name":"859-5113",
    "wof:placetype":"postalcode"
},
  "geometry": {"coordinates":[129.55199999999999,33.3673],"type":"Point"}
}