{
  "type": "Feature",
  "properties": {
    "gn:adm1_name":"Hiroshimaken",
    "gn:adm2_name":"Hatsukaichishi",
    "gn:name":"Ajinadainishi",
    "iso:country":"JP",
    "wof:name":"738-0055",
    "wof:placetype":"postalcode"
},
  "geometry": {"coordinates":[132.3032,34.3247],"type":"Point"}
}