{
  "type": "Feature",
  "properties": {
    "gn:adm1_name":"Kumamotoken",
    "gn:adm2_name":"Kumamotoshi",
    "gn:name":"Kawachimachitake",
    "iso:country":"JP",
    "wof:name":"861-5344",
    "wof:placetype":"postalcode"
},
  "geometry": {"coordinates":[130.64609999999999,32.826],"type":"Point"}
}