{
  "type": "Feature",
  "properties": {
    "gn:adm1_name":"Fukushimaken",
    "gn:adm2_name":"Soumashi",
    "gn:name":"Ootsubo",
    "iso:country":"JP",
    "wof:name":"976-0007",
    "wof:placetype":"postalcode"
},
  "geometry": {"coordinates":[140.89410000000001,37.8272],"type":"Point"}
}