{
  "type": "Feature",
  "properties": {
    "gn:adm1_name":"Niigataken",
    "gn:adm2_name":"Nakakanbaragunmuramatsumachi",
    "gn:name":"Hei",
    "iso:country":"JP",
    "wof:name":"959-1706",
    "wof:placetype":"postalcode"
},
  "geometry": {"coordinates":[139.13489999999999,37.6866],"type":"Point"}
}