{
  "type": "Feature",
  "properties": {
    "gn:adm1_name":"Aichiken",
    "gn:adm2_name":"Komakishi",
    "gn:name":"Nishijimachou",
    "iso:country":"JP",
    "wof:name":"485-0078",
    "wof:placetype":"postalcode"
},
  "geometry": {"coordinates":[136.90000000000001,35.2955],"type":"Point"}
}