{
  "type": "Feature",
  "properties": {
    "gn:adm1_name":"Saitamaken",
    "gn:adm2_name":"Kawagoeshi",
    "gn:name":"Yamashiro",
    "iso:country":"JP",
    "wof:name":"350-1169",
    "wof:placetype":"postalcode"
},
  "geometry": {"coordinates":[139.44329999999999,35.891],"type":"Point"}
}