{
  "type": "Feature",
  "properties": {
    "gn:adm1_name":"Aichiken",
    "gn:adm2_name":"Inazawashi",
    "gn:name":"Okudanagarechou",
    "iso:country":"JP",
    "wof:name":"492-8231",
    "wof:placetype":"postalcode"
},
  "geometry": {"coordinates":[136.81389999999999,35.2322],"type":"Point"}
}