{
  "type": "Feature",
  "properties": {
    "gn:adm1_name":"Mieken",
    "gn:adm2_name":"Inabeshi",
    "gn:name":"Daianchouishigureminami",
    "iso:country":"JP",
    "wof:name":"511-0266",
    "wof:placetype":"postalcode"
},
  "geometry": {"coordinates":[136.4982,35.1045],"type":"Point"}
}