{
  "type": "Feature",
  "properties": {
    "gn:adm1_name":"Shimaneken",
    "gn:adm2_name":"Matsueshi",
    "gn:name":"Uchinakabarachou",
    "iso:country":"JP",
    "wof:name":"690-0873",
    "wof:placetype":"postalcode"
},
  "geometry": {"coordinates":[133.04750000000001,35.4734],"type":"Point"}
}