{
  "type": "Feature",
  "properties": {
    "gn:adm1_name":"Yamaguchiken",
    "gn:adm2_name":"Yamaguchishi",
    "gn:name":"Chuuou",
    "iso:country":"JP",
    "wof:name":"753-0074",
    "wof:placetype":"postalcode"
},
  "geometry": {"coordinates":[131.4718,34.1741],"type":"Point"}
}