{
  "type": "Feature",
  "properties": {
    "gn:adm1_name":"Aichiken",
    "gn:adm2_name":"Toyokawashi",
    "gn:name":"Goyuchou(Hourokudo)",
    "iso:country":"JP",
    "wof:name":"441-0215",
    "wof:placetype":"postalcode"
},
  "geometry": {"coordinates":[137.3203,34.8494],"type":"Point"}
}