{
  "type": "Feature",
  "properties": {
    "gn:adm1_name":"Aichiken",
    "gn:adm2_name":"Hazugun'Isshikichou",
    "gn:name":"Tsuigome",
    "iso:country":"JP",
    "wof:name":"444-0406",
    "wof:placetype":"postalcode"
},
  "geometry": {"coordinates":[137.0341,34.8071],"type":"Point"}
}