{
  "type": "Feature",
  "properties": {
    "gn:adm1_name":"Ibarakiken",
    "gn:adm2_name":"Tsukubashi",
    "gn:name":"Midorigaoka",
    "iso:country":"JP",
    "wof:name":"305-0863",
    "wof:placetype":"postalcode"
},
  "geometry": {"coordinates":[140.0866,36.0079],"type":"Point"}
}