{
  "type": "Feature",
  "properties": {
    "gn:adm1_name":"Okayamaken",
    "gn:adm2_name":"Okayamashi",
    "gn:name":"Fujiwarahikarimachi",
    "iso:country":"JP",
    "wof:name":"703-8246",
    "wof:placetype":"postalcode"
},
  "geometry": {"coordinates":[133.95429999999999,34.6789],"type":"Point"}
}