{
  "type": "Feature",
  "properties": {
    "gn:adm1_name":"Ehimeken",
    "gn:adm2_name":"Shuusouguntanbarachou",
    "gn:name":"Nagano",
    "iso:country":"JP",
    "wof:name":"791-0521",
    "wof:placetype":"postalcode"
},
  "geometry": {"coordinates":[133.04329999999999,33.8756],"type":"Point"}
}