{
  "type": "Feature",
  "properties": {
    "gn:adm1_name":"Niigataken",
    "gn:adm2_name":"Shibatashi",
    "gn:name":"Honmashinden",
    "iso:country":"JP",
    "wof:name":"957-0342",
    "wof:placetype":"postalcode"
},
  "geometry": {"coordinates":[139.41,37.9197],"type":"Point"}
}