{
  "type": "Feature",
  "properties": {
    "gn:adm1_name":"Chibaken",
    "gn:adm2_name":"Sanbugunnarutoumachi",
    "gn:name":"Himeshima",
    "iso:country":"JP",
    "wof:name":"289-1327",
    "wof:placetype":"postalcode"
},
  "geometry": {"coordinates":[140.41480000000001,35.5954],"type":"Point"}
}