{
  "type": "Feature",
  "properties": {
    "gn:adm1_name":"Kouchiken",
    "gn:adm2_name":"Kamiguntosayamadachou",
    "gn:name":"Miyamaechou",
    "iso:country":"JP",
    "wof:name":"782-0037",
    "wof:placetype":"postalcode"
},
  "geometry": {"coordinates":[133.68629999999999,33.6082],"type":"Point"}
}