{
  "type": "Feature",
  "properties": {
    "gn:adm1_name":"Kouchiken",
    "gn:adm2_name":"Kamigunkahokuchou",
    "gn:name":"Shirakawa",
    "iso:country":"JP",
    "wof:name":"781-4221",
    "wof:placetype":"postalcode"
},
  "geometry": {"coordinates":[133.74700000000001,33.6457],"type":"Point"}
}