{
  "type": "Feature",
  "properties": {
    "gn:adm1_name":"Oosakafu",
    "gn:adm2_name":"Minooshi",
    "gn:name":"Aogein",
    "iso:country":"JP",
    "wof:name":"562-0025",
    "wof:placetype":"postalcode"
},
  "geometry": {"coordinates":[135.50579999999999,34.8402],"type":"Point"}
}