{
  "type": "Feature",
  "properties": {
    "gn:adm1_name":"Kumamotoken",
    "gn:adm2_name":"Amakusagunhimedomachi",
    "gn:name":"Futamado",
    "iso:country":"JP",
    "wof:name":"866-0102",
    "wof:placetype":"postalcode"
},
  "geometry": {"coordinates":[130.40010000000001,32.4266],"type":"Point"}
}