{
  "type": "Feature",
  "properties": {
    "gn:adm1_name":"Naganoken",
    "gn:adm2_name":"Okayashi",
    "gn:name":"Higashiginza",
    "iso:country":"JP",
    "wof:name":"394-0023",
    "wof:placetype":"postalcode"
},
  "geometry": {"coordinates":[138.0582,36.0698],"type":"Point"}
}