{
  "type": "Feature",
  "properties": {
    "gn:adm1_name":"Fukuokaken",
    "gn:adm2_name":"Chikushinoshi",
    "gn:name":"Hagiwara",
    "iso:country":"JP",
    "wof:name":"818-0044",
    "wof:placetype":"postalcode"
},
  "geometry": {"coordinates":[130.51939999999999,33.4647],"type":"Point"}
}