{
  "type": "Feature",
  "properties": {
    "gn:adm1_name":"Kagoshimaken",
    "gn:adm2_name":"Airagunkamouchou",
    "gn:name":"Urushi",
    "iso:country":"JP",
    "wof:name":"899-5301",
    "wof:placetype":"postalcode"
},
  "geometry": {"coordinates":[130.55680000000001,31.8288],"type":"Point"}
}