{
  "type": "Feature",
  "properties": {
    "gn:adm1_name":"Tochigiken",
    "gn:adm2_name":"Utsunomiyashi",
    "gn:name":"Takaragichou",
    "iso:country":"JP",
    "wof:name":"320-0061",
    "wof:placetype":"postalcode"
},
  "geometry": {"coordinates":[139.84829999999999,36.5843],"type":"Point"}
}