{
  "type": "Feature",
  "properties": {
    "gn:adm1_name":"Tochigiken",
    "gn:adm2_name":"Utsunomiyashi",
    "gn:name":"Zaimokuchou",
    "iso:country":"JP",
    "wof:name":"320-0042",
    "wof:placetype":"postalcode"
},
  "geometry": {"coordinates":[139.87379999999999,36.5615],"type":"Point"}
}