{
  "type": "Feature",
  "properties": {
    "gn:adm1_name":"Hyougoken",
    "gn:adm2_name":"Sumotoshi",
    "gn:name":"Takenokuchi",
    "iso:country":"JP",
    "wof:name":"656-0011",
    "wof:placetype":"postalcode"
},
  "geometry": {"coordinates":[134.8922,34.3513],"type":"Point"}
}