{
  "type": "Feature",
  "properties": {
    "gn:adm1_name":"Aichiken",
    "gn:adm2_name":"Tsushimashi",
    "gn:name":"Shimogirichou",
    "iso:country":"JP",
    "wof:name":"496-0029",
    "wof:placetype":"postalcode"
},
  "geometry": {"coordinates":[136.75790000000001,35.1781],"type":"Point"}
}