{
  "type": "Feature",
  "properties": {
    "gn:adm1_name":"Aichiken",
    "gn:adm2_name":"Chiryuushi",
    "gn:name":"Uchisaiwaichou",
    "iso:country":"JP",
    "wof:name":"472-0042",
    "wof:placetype":"postalcode"
},
  "geometry": {"coordinates":[137.04589999999999,35.0041],"type":"Point"}
}