{
  "type": "Feature",
  "properties": {
    "gn:adm1_name":"Kyoutofu",
    "gn:adm2_name":"Maidurushi",
    "gn:name":"Kichisaka",
    "iso:country":"JP",
    "wof:name":"625-0011",
    "wof:placetype":"postalcode"
},
  "geometry": {"coordinates":[135.44909999999999,35.4863],"type":"Point"}
}