{
  "type": "Feature",
  "properties": {
    "gn:adm1_name":"Saitamaken",
    "gn:adm2_name":"Minamisaitamagunshiraokamachi",
    "gn:name":"Shinodu",
    "iso:country":"JP",
    "wof:name":"349-0204",
    "wof:placetype":"postalcode"
},
  "geometry": {"coordinates":[139.65629999999999,36.0306],"type":"Point"}
}