{
  "type": "Feature",
  "properties": {
    "gn:adm1_name":"Toukyouto",
    "gn:adm2_name":"Shinjukuku",
    "gn:name":"Nijutsukimachi",
    "iso:country":"JP",
    "wof:name":"162-0855",
    "wof:placetype":"postalcode"
},
  "geometry": {"coordinates":[139.73099999999999,35.6983],"type":"Point"}
}