{
  "type": "Feature",
  "properties": {
    "gn:adm1_name":"Shizuokaken",
    "gn:adm2_name":"Shizuokashi",
    "gn:name":"Oohara",
    "iso:country":"JP",
    "wof:name":"421-1314",
    "wof:placetype":"postalcode"
},
  "geometry": {"coordinates":[138.28039999999999,35.0101],"type":"Point"}
}