{
  "type": "Feature",
  "properties": {
    "gn:adm1_name":"Ishikawaken",
    "gn:adm2_name":"Fugeshigunnotomachi",
    "gn:name":"Ushitsushinminato",
    "iso:country":"JP",
    "wof:name":"927-0435",
    "wof:placetype":"postalcode"
},
  "geometry": {"coordinates":[137.14660000000001,37.2994],"type":"Point"}
}