{
  "type": "Feature",
  "properties": {
    "gn:adm1_name":"Saitamaken",
    "gn:adm2_name":"Kawagoeshi",
    "gn:name":"Kamioibukuro",
    "iso:country":"JP",
    "wof:name":"350-0845",
    "wof:placetype":"postalcode"
},
  "geometry": {"coordinates":[139.5275,35.9461],"type":"Point"}
}