{
  "type": "Feature",
  "properties": {
    "gn:adm1_name":"Okayamaken",
    "gn:adm2_name":"Akaiwagunkumayamachou",
    "gn:name":"Shakurenji",
    "iso:country":"JP",
    "wof:name":"709-0731",
    "wof:placetype":"postalcode"
},
  "geometry": {"coordinates":[134.05330000000001,34.8063],"type":"Point"}
}