{
  "type": "Feature",
  "properties": {
    "gn:adm1_name":"Ishikawaken",
    "gn:adm2_name":"Hakuigunshikamachi",
    "gn:name":"Nashitanikoyama",
    "iso:country":"JP",
    "wof:name":"925-0151",
    "wof:placetype":"postalcode"
},
  "geometry": {"coordinates":[136.7919,37.0345],"type":"Point"}
}