{
  "type": "Feature",
  "properties": {
    "gn:adm1_name":"Aichiken",
    "gn:adm2_name":"Nishioshi",
    "gn:name":"Ibunchou",
    "iso:country":"JP",
    "wof:name":"445-0822",
    "wof:placetype":"postalcode"
},
  "geometry": {"coordinates":[137.05629999999999,34.8695],"type":"Point"}
}