{
  "type": "Feature",
  "properties": {
    "gn:adm1_name":"Saitamaken",
    "gn:adm2_name":"Shikishi",
    "gn:name":"Saiwaichou",
    "iso:country":"JP",
    "wof:name":"353-0005",
    "wof:placetype":"postalcode"
},
  "geometry": {"coordinates":[139.5642,35.8233],"type":"Point"}
}