{
  "type": "Feature",
  "properties": {
    "gn:adm1_name":"Tottoriken",
    "gn:adm2_name":"Touhakuguntouhakuchou",
    "gn:name":"Sanbonsugi",
    "iso:country":"JP",
    "wof:name":"689-2334",
    "wof:placetype":"postalcode"
},
  "geometry": {"coordinates":[133.64410000000001,35.4092],"type":"Point"}
}