{
  "type": "Feature",
  "properties": {
    "gn:adm1_name":"Fukuokaken",
    "gn:adm2_name":"Yukuhashishi",
    "gn:name":"Takarayama",
    "iso:country":"JP",
    "wof:name":"824-0048",
    "wof:placetype":"postalcode"
},
  "geometry": {"coordinates":[130.95519999999999,33.7051],"type":"Point"}
}