{
  "type": "Feature",
  "properties": {
    "gn:adm1_name":"Gifuken",
    "gn:adm2_name":"Anpachigun'Anpachichou",
    "gn:name":"Ikanikeisaiganaibaai",
    "iso:country":"JP",
    "wof:name":"503-0100",
    "wof:placetype":"postalcode"
},
  "geometry": {"coordinates":[136.6627,35.3705],"type":"Point"}
}