{
  "type": "Feature",
  "properties": {
    "gn:adm1_name":"Fukuiken",
    "gn:adm2_name":"Nyuugun'Asahichou",
    "gn:name":"Tanaka",
    "iso:country":"JP",
    "wof:name":"916-0132",
    "wof:placetype":"postalcode"
},
  "geometry": {"coordinates":[136.14510000000001,35.9842],"type":"Point"}
}