{
  "type": "Feature",
  "properties": {
    "gn:adm1_name":"Tokushimaken",
    "gn:adm2_name":"Katsuuragunkamikatsuchou",
    "gn:name":"Ikanikeisaiganaibaai",
    "iso:country":"JP",
    "wof:name":"771-4500",
    "wof:placetype":"postalcode"
},
  "geometry": {"coordinates":[134.40559999999999,33.884],"type":"Point"}
}