{
  "type": "Feature",
  "properties": {
    "gn:adm1_name":"Kanagawaken",
    "gn:adm2_name":"Yokosukashi",
    "gn:name":"Uchikawa",
    "iso:country":"JP",
    "wof:name":"239-0836",
    "wof:placetype":"postalcode"
},
  "geometry": {"coordinates":[139.6919,35.2392],"type":"Point"}
}