{
  "type": "Feature",
  "properties": {
    "gn:adm1_name":"Yamaguchiken",
    "gn:adm2_name":"Onodashi",
    "gn:name":"Higashimachi",
    "iso:country":"JP",
    "wof:name":"756-0018",
    "wof:placetype":"postalcode"
},
  "geometry": {"coordinates":[131.21129999999999,34.0203],"type":"Point"}
}