{
  "type": "Feature",
  "properties": {
    "gn:adm1_name":"Fukuiken",
    "gn:adm2_name":"Nyuugun'Otachou",
    "gn:name":"Misaki",
    "iso:country":"JP",
    "wof:name":"916-0221",
    "wof:placetype":"postalcode"
},
  "geometry": {"coordinates":[136.04429999999999,35.9609],"type":"Point"}
}