{
  "type": "Feature",
  "properties": {
    "gn:adm1_name":"Okayamaken",
    "gn:adm2_name":"Shitsukigunyoshiichou",
    "gn:name":"Yanase",
    "iso:country":"JP",
    "wof:name":"714-2112",
    "wof:placetype":"postalcode"
},
  "geometry": {"coordinates":[133.43510000000001,34.62],"type":"Point"}
}