{
  "type": "Feature",
  "properties": {
    "gn:adm1_name":"Tochigiken",
    "gn:adm2_name":"Oyamashi",
    "gn:name":"Samukawa",
    "iso:country":"JP",
    "wof:name":"329-0226",
    "wof:placetype":"postalcode"
},
  "geometry": {"coordinates":[139.73079999999999,36.2838],"type":"Point"}
}