{
  "type": "Feature",
  "properties": {
    "gn:adm1_name":"Toyamaken",
    "gn:adm2_name":"Kurobeshi",
    "gn:name":"Ikujishinku",
    "iso:country":"JP",
    "wof:name":"938-0061",
    "wof:placetype":"postalcode"
},
  "geometry": {"coordinates":[137.4221,36.8865],"type":"Point"}
}