{
  "type": "Feature",
  "properties": {
    "gn:adm1_name":"Kyoutofu",
    "gn:adm2_name":"Kyoutoshiukyouku",
    "gn:name":"Nishikyougokunishimukougawarachou",
    "iso:country":"JP",
    "wof:name":"615-0837",
    "wof:placetype":"postalcode"
},
  "geometry": {"coordinates":[135.71520000000001,34.9851],"type":"Point"}
}