{
  "type": "Feature",
  "properties": {
    "gn:adm1_name":"Fukuokaken",
    "gn:adm2_name":"Kitakyuushuushiyahatahigashiku",
    "gn:name":"Shirakawamachi",
    "iso:country":"JP",
    "wof:name":"805-0007",
    "wof:placetype":"postalcode"
},
  "geometry": {"coordinates":[130.81909999999999,33.8735],"type":"Point"}
}