{
  "type": "Feature",
  "properties": {
    "gn:adm1_name":"Gunmaken",
    "gn:adm2_name":"Kanragunshimonitamachi",
    "gn:name":"Ookuwahara",
    "iso:country":"JP",
    "wof:name":"370-2613",
    "wof:placetype":"postalcode"
},
  "geometry": {"coordinates":[138.7671,36.2028],"type":"Point"}
}