{
  "type": "Feature",
  "properties": {
    "gn:adm1_name":"Toukyouto",
    "gn:adm2_name":"Choufushi",
    "gn:name":"Jindaijimotomachi",
    "iso:country":"JP",
    "wof:name":"182-0017",
    "wof:placetype":"postalcode"
},
  "geometry": {"coordinates":[139.54589999999999,35.6663],"type":"Point"}
}