{
  "type": "Feature",
  "properties": {
    "gn:adm1_name":"Oosakafu",
    "gn:adm2_name":"Mishimagunshimamotochou",
    "gn:name":"Takahama",
    "iso:country":"JP",
    "wof:name":"618-0012",
    "wof:placetype":"postalcode"
},
  "geometry": {"coordinates":[135.66749999999999,34.874],"type":"Point"}
}