{
  "type": "Feature",
  "properties": {
    "gn:adm1_name":"Hyougoken",
    "gn:adm2_name":"Himejishi",
    "gn:name":"Shikamakushimizu",
    "iso:country":"JP",
    "wof:name":"672-8051",
    "wof:placetype":"postalcode"
},
  "geometry": {"coordinates":[134.67670000000001,34.8019],"type":"Point"}
}