{
  "type": "Feature",
  "properties": {
    "gn:adm1_name":"Fukuokaken",
    "gn:adm2_name":"Asakuragunmiwamachi",
    "gn:name":"Yorii",
    "iso:country":"JP",
    "wof:name":"838-0813",
    "wof:placetype":"postalcode"
},
  "geometry": {"coordinates":[130.6429,33.4301],"type":"Point"}
}