{
  "type": "Feature",
  "properties": {
    "gn:adm1_name":"Aichiken",
    "gn:adm2_name":"Komakishi",
    "gn:name":"Muranaka",
    "iso:country":"JP",
    "wof:name":"485-0082",
    "wof:placetype":"postalcode"
},
  "geometry": {"coordinates":[136.9074,35.3022],"type":"Point"}
}