{
  "type": "Feature",
  "properties": {
    "gn:adm1_name":"Kyoutofu",
    "gn:adm2_name":"Kyoutoshisakyouku",
    "gn:name":"Matsugasakikumojichou",
    "iso:country":"JP",
    "wof:name":"606-0955",
    "wof:placetype":"postalcode"
},
  "geometry": {"coordinates":[135.78370000000001,35.0518],"type":"Point"}
}