{
  "type": "Feature",
  "properties": {
    "gn:adm1_name":"Ehimeken",
    "gn:adm2_name":"Matsuyamashi",
    "gn:name":"Nakamura",
    "iso:country":"JP",
    "wof:name":"790-0964",
    "wof:placetype":"postalcode"
},
  "geometry": {"coordinates":[132.77680000000001,33.8296],"type":"Point"}
}