{
  "type": "Feature",
  "properties": {
    "gn:adm1_name":"Ishikawaken",
    "gn:adm2_name":"Kanazawashi",
    "gn:name":"Utatsumachi",
    "iso:country":"JP",
    "wof:name":"920-0832",
    "wof:placetype":"postalcode"
},
  "geometry": {"coordinates":[136.67310000000001,36.5733],"type":"Point"}
}