{
  "type": "Feature",
  "properties": {
    "gn:adm1_name":"Aichiken",
    "gn:adm2_name":"Inuyamashi",
    "gn:name":"Tomiokashinmachi",
    "iso:country":"JP",
    "wof:name":"484-0099",
    "wof:placetype":"postalcode"
},
  "geometry": {"coordinates":[136.95590000000001,35.3804],"type":"Point"}
}