{
  "type": "Feature",
  "properties": {
    "gn:adm1_name":"Mieken",
    "gn:adm2_name":"Kameyamashi",
    "gn:name":"Ichigasakachou",
    "iso:country":"JP",
    "wof:name":"519-0158",
    "wof:placetype":"postalcode"
},
  "geometry": {"coordinates":[136.4469,34.8563],"type":"Point"}
}