{
  "type": "Feature",
  "properties": {
    "gn:adm1_name":"Hyougoken",
    "gn:adm2_name":"Izushiguntantouchou",
    "gn:name":"Hirata",
    "iso:country":"JP",
    "wof:name":"668-0362",
    "wof:placetype":"postalcode"
},
  "geometry": {"coordinates":[134.9863,35.4512],"type":"Point"}
}