{
  "type": "Feature",
  "properties": {
    "gn:adm1_name":"Fukushimaken",
    "gn:adm2_name":"Iwakishi",
    "gn:name":"Tairamakunouchi",
    "iso:country":"JP",
    "wof:name":"970-8014",
    "wof:placetype":"postalcode"
},
  "geometry": {"coordinates":[140.8999,37.0671],"type":"Point"}
}