{
  "type": "Feature",
  "properties": {
    "gn:adm1_name":"Oosakafu",
    "gn:adm2_name":"Higashioosakashi",
    "gn:name":"Inadauemachi",
    "iso:country":"JP",
    "wof:name":"577-0002",
    "wof:placetype":"postalcode"
},
  "geometry": {"coordinates":[135.584,34.6925],"type":"Point"}
}