{
  "type": "Feature",
  "properties": {
    "gn:adm1_name":"Ehimeken",
    "gn:adm2_name":"Ochigunyoshiumichou",
    "gn:name":"Tomari",
    "iso:country":"JP",
    "wof:name":"794-2102",
    "wof:placetype":"postalcode"
},
  "geometry": {"coordinates":[133.0351,34.1715],"type":"Point"}
}