{
  "type": "Feature",
  "properties": {
    "gn:adm1_name":"Hyougoken",
    "gn:adm2_name":"Sayougunsayouchou",
    "gn:name":"Yodo",
    "iso:country":"JP",
    "wof:name":"679-5315",
    "wof:placetype":"postalcode"
},
  "geometry": {"coordinates":[134.32499999999999,35.0499],"type":"Point"}
}