{
  "type": "Feature",
  "properties": {
    "gn:adm1_name":"Kyoutofu",
    "gn:adm2_name":"Fukuchiyamashi",
    "gn:name":"Kisaichi",
    "iso:country":"JP",
    "wof:name":"620-0003",
    "wof:placetype":"postalcode"
},
  "geometry": {"coordinates":[135.18389999999999,35.3169],"type":"Point"}
}