{
  "type": "Feature",
  "properties": {
    "gn:adm1_name":"Hiroshimaken",
    "gn:adm2_name":"Kamoguntoyosakachou",
    "gn:name":"Nomi",
    "iso:country":"JP",
    "wof:name":"724-0301",
    "wof:placetype":"postalcode"
},
  "geometry": {"coordinates":[132.81059999999999,34.5638],"type":"Point"}
}