{
  "type": "Feature",
  "properties": {
    "gn:adm1_name":"Nagasakiken",
    "gn:adm2_name":"Minamimatsuuragunnaraochou",
    "gn:name":"Naraogou",
    "iso:country":"JP",
    "wof:name":"853-3101",
    "wof:placetype":"postalcode"
},
  "geometry": {"coordinates":[129.0598,32.8436],"type":"Point"}
}