{
  "type": "Feature",
  "properties": {
    "gn:adm1_name":"Okayamaken",
    "gn:adm2_name":"Okayamashi",
    "gn:name":"Kurata",
    "iso:country":"JP",
    "wof:name":"703-8265",
    "wof:placetype":"postalcode"
},
  "geometry": {"coordinates":[133.95920000000001,34.6353],"type":"Point"}
}