{
  "type": "Feature",
  "properties": {
    "gn:adm1_name":"Fukuiken",
    "gn:adm2_name":"Sabaeshi",
    "gn:name":"Shinmeichou",
    "iso:country":"JP",
    "wof:name":"916-0017",
    "wof:placetype":"postalcode"
},
  "geometry": {"coordinates":[136.1842,35.9755],"type":"Point"}
}