{
  "type": "Feature",
  "properties": {
    "gn:adm1_name":"Saitamaken",
    "gn:adm2_name":"Kitakatsushikagunkurihashimachi",
    "gn:name":"Takayanagi",
    "iso:country":"JP",
    "wof:name":"349-1125",
    "wof:placetype":"postalcode"
},
  "geometry": {"coordinates":[139.67500000000001,36.1154],"type":"Point"}
}