{
  "type": "Feature",
  "properties": {
    "gn:adm1_name":"Miyagiken",
    "gn:adm2_name":"Motoyoshigun'Utatsuchou",
    "gn:name":"Nagasawa",
    "iso:country":"JP",
    "wof:name":"988-0414",
    "wof:placetype":"postalcode"
},
  "geometry": {"coordinates":[141.54349999999999,38.7256],"type":"Point"}
}