{
  "type": "Feature",
  "properties": {
    "gn:adm1_name":"Ooitaken",
    "gn:adm2_name":"Oonogunchitosemura",
    "gn:name":"Niidono",
    "iso:country":"JP",
    "wof:name":"879-7401",
    "wof:placetype":"postalcode"
},
  "geometry": {"coordinates":[131.59690000000001,33.042],"type":"Point"}
}