{
  "type": "Feature",
  "properties": {
    "gn:adm1_name":"Ibarakiken",
    "gn:adm2_name":"Kitaibarakishi",
    "gn:name":"Hanakawachoukamikotsuda",
    "iso:country":"JP",
    "wof:name":"319-1532",
    "wof:placetype":"postalcode"
},
  "geometry": {"coordinates":[140.71019999999999,36.8313],"type":"Point"}
}