{
  "type": "Feature",
  "properties": {
    "gn:adm1_name":"Naganoken",
    "gn:adm2_name":"Shimotakaigunyamanouchimachi",
    "gn:name":"Hirao",
    "iso:country":"JP",
    "wof:name":"381-0401",
    "wof:placetype":"postalcode"
},
  "geometry": {"coordinates":[138.4229,36.7391],"type":"Point"}
}