{
  "type": "Feature",
  "properties": {
    "gn:adm1_name":"Fukuokaken",
    "gn:adm2_name":"Miigunkitanomachi",
    "gn:name":"Torisu",
    "iso:country":"JP",
    "wof:name":"830-1115",
    "wof:placetype":"postalcode"
},
  "geometry": {"coordinates":[130.58109999999999,33.3337],"type":"Point"}
}