{
  "type": "Feature",
  "properties": {
    "gn:adm1_name":"Ishikawaken",
    "gn:adm2_name":"Kashimagunkashimamachi",
    "gn:name":"Nishi",
    "iso:country":"JP",
    "wof:name":"929-1803",
    "wof:placetype":"postalcode"
},
  "geometry": {"coordinates":[136.91829999999999,36.9965],"type":"Point"}
}