{
  "type": "Feature",
  "properties": {
    "gn:adm1_name":"Kyoutofu",
    "gn:adm2_name":"Kyoutoshihigashiyamaku",
    "gn:name":"Hiyoshichou",
    "iso:country":"JP",
    "wof:name":"605-0993",
    "wof:placetype":"postalcode"
},
  "geometry": {"coordinates":[135.76859999999999,34.989],"type":"Point"}
}