{
  "type": "Feature",
  "properties": {
    "gn:adm1_name":"Fukuokaken",
    "gn:adm2_name":"Nakamashi",
    "gn:name":"Iwase",
    "iso:country":"JP",
    "wof:name":"809-0011",
    "wof:placetype":"postalcode"
},
  "geometry": {"coordinates":[130.71209999999999,33.8319],"type":"Point"}
}