{
  "type": "Feature",
  "properties": {
    "gn:adm1_name":"Fukuiken",
    "gn:adm2_name":"Tsurugashi",
    "gn:name":"Ikenokouchi",
    "iso:country":"JP",
    "wof:name":"914-0004",
    "wof:placetype":"postalcode"
},
  "geometry": {"coordinates":[136.13919999999999,35.6524],"type":"Point"}
}