{
  "type": "Feature",
  "properties": {
    "gn:adm1_name":"Ehimeken",
    "gn:adm2_name":"Onsengunkawauchichou",
    "gn:name":"Yoshihisa",
    "iso:country":"JP",
    "wof:name":"791-0302",
    "wof:placetype":"postalcode"
},
  "geometry": {"coordinates":[132.88999999999999,33.7888],"type":"Point"}
}