{
  "type": "Feature",
  "properties": {
    "gn:adm1_name":"Toyamaken",
    "gn:adm2_name":"Toyamashi",
    "gn:name":"Higashiiwasemachi",
    "iso:country":"JP",
    "wof:name":"931-8358",
    "wof:placetype":"postalcode"
},
  "geometry": {"coordinates":[137.22839999999999,36.7544],"type":"Point"}
}