{
  "type": "Feature",
  "properties": {
    "gn:adm1_name":"Ehimeken",
    "gn:adm2_name":"Iyoguntobechou",
    "gn:name":"Kamiharamachi",
    "iso:country":"JP",
    "wof:name":"791-2117",
    "wof:placetype":"postalcode"
},
  "geometry": {"coordinates":[132.78960000000001,33.7664],"type":"Point"}
}