{
  "type": "Feature",
  "properties": {
    "gn:adm1_name":"Hiroshimaken",
    "gn:adm2_name":"Hiroshimashiminamiku",
    "gn:name":"Dejima",
    "iso:country":"JP",
    "wof:name":"734-0013",
    "wof:placetype":"postalcode"
},
  "geometry": {"coordinates":[132.4502,34.3557],"type":"Point"}
}