{
  "type": "Feature",
  "properties": {
    "gn:adm1_name":"Toukyouto",
    "gn:adm2_name":"Tamashi",
    "gn:name":"Ichinomiya",
    "iso:country":"JP",
    "wof:name":"206-0002",
    "wof:placetype":"postalcode"
},
  "geometry": {"coordinates":[139.44200000000001,35.6518],"type":"Point"}
}