{
  "type": "Feature",
  "properties": {
    "gn:adm1_name":"Hyougoken",
    "gn:adm2_name":"Koubeshinishiku",
    "gn:name":"Sakuragaokahigashimachi",
    "iso:country":"JP",
    "wof:name":"651-2225",
    "wof:placetype":"postalcode"
},
  "geometry": {"coordinates":[135.06219999999999,34.7451],"type":"Point"}
}