{
  "type": "Feature",
  "properties": {
    "gn:adm1_name":"Gunmaken",
    "gn:adm2_name":"Maebashishi",
    "gn:name":"Shouwamachi",
    "iso:country":"JP",
    "wof:name":"371-0034",
    "wof:placetype":"postalcode"
},
  "geometry": {"coordinates":[139.06319999999999,36.4033],"type":"Point"}
}