{
  "type": "Feature",
  "properties": {
    "gn:adm1_name":"Yamaguchiken",
    "gn:adm2_name":"Ubeshi",
    "gn:name":"Saiwaimachi",
    "iso:country":"JP",
    "wof:name":"755-0012",
    "wof:placetype":"postalcode"
},
  "geometry": {"coordinates":[131.25409999999999,33.939],"type":"Point"}
}