{
  "type": "Feature",
  "properties": {
    "gn:adm1_name":"Hyougoken",
    "gn:adm2_name":"Amagasakishi",
    "gn:name":"Minaminanamatsuchou",
    "iso:country":"JP",
    "wof:name":"660-0053",
    "wof:placetype":"postalcode"
},
  "geometry": {"coordinates":[135.4007,34.7316],"type":"Point"}
}