{
  "type": "Feature",
  "properties": {
    "gn:adm1_name":"Shizuokaken",
    "gn:adm2_name":"Tagatagunnakaizuchou",
    "gn:name":"Kisoubou",
    "iso:country":"JP",
    "wof:name":"410-2517",
    "wof:placetype":"postalcode"
},
  "geometry": {"coordinates":[138.98310000000001,34.9185],"type":"Point"}
}