{
  "type": "Feature",
  "properties": {
    "gn:adm1_name":"Aichiken",
    "gn:adm2_name":"Inazawashi",
    "gn:name":"Shimakoharachou",
    "iso:country":"JP",
    "wof:name":"492-8203",
    "wof:placetype":"postalcode"
},
  "geometry": {"coordinates":[136.80590000000001,35.2677],"type":"Point"}
}