{
  "type": "Feature",
  "properties": {
    "gn:adm1_name":"Hyougoken",
    "gn:adm2_name":"Itamishi",
    "gn:name":"Aramakiminami",
    "iso:country":"JP",
    "wof:name":"664-0008",
    "wof:placetype":"postalcode"
},
  "geometry": {"coordinates":[135.38339999999999,34.8067],"type":"Point"}
}