{
  "type": "Feature",
  "properties": {
    "gn:adm1_name":"Fukuokaken",
    "gn:adm2_name":"Fukuokashihakataku",
    "gn:name":"Takeokachou",
    "iso:country":"JP",
    "wof:name":"816-0078",
    "wof:placetype":"postalcode"
},
  "geometry": {"coordinates":[130.46459999999999,33.5439],"type":"Point"}
}