{
  "type": "Feature",
  "properties": {
    "gn:adm1_name":"Kyoutofu",
    "gn:adm2_name":"Kyoutoshinakagyouku",
    "gn:name":"Kamihachimonjichou",
    "iso:country":"JP",
    "wof:name":"604-8323",
    "wof:placetype":"postalcode"
},
  "geometry": {"coordinates":[135.751,35.0091],"type":"Point"}
}