{
  "type": "Feature",
  "properties": {
    "gn:adm1_name":"Fukushimaken",
    "gn:adm2_name":"Dategun'Iinomachi",
    "gn:name":"Aoki",
    "iso:country":"JP",
    "wof:name":"960-1303",
    "wof:placetype":"postalcode"
},
  "geometry": {"coordinates":[140.53360000000001,37.679],"type":"Point"}
}