{
  "type": "Feature",
  "properties": {
    "gn:adm1_name":"Gunmaken",
    "gn:adm2_name":"Annakashi",
    "gn:name":"Shimoakima",
    "iso:country":"JP",
    "wof:name":"379-0104",
    "wof:placetype":"postalcode"
},
  "geometry": {"coordinates":[138.88669999999999,36.3472],"type":"Point"}
}