{
  "type": "Feature",
  "properties": {
    "gn:adm1_name":"Shimaneken",
    "gn:adm2_name":"Matsueshi",
    "gn:name":"Okamotochou",
    "iso:country":"JP",
    "wof:name":"690-0262",
    "wof:placetype":"postalcode"
},
  "geometry": {"coordinates":[132.94669999999999,35.484],"type":"Point"}
}