{
  "type": "Feature",
  "properties": {
    "gn:adm1_name":"Saitamaken",
    "gn:adm2_name":"Minamisaitamagunmiyashiromachi",
    "gn:name":"Kanehara",
    "iso:country":"JP",
    "wof:name":"345-0816",
    "wof:placetype":"postalcode"
},
  "geometry": {"coordinates":[139.71549999999999,36.0084],"type":"Point"}
}