{
  "type": "Feature",
  "properties": {
    "gn:adm1_name":"Kouchiken",
    "gn:adm2_name":"Kamiguntosayamadachou",
    "gn:name":"Sue",
    "iso:country":"JP",
    "wof:name":"782-0055",
    "wof:placetype":"postalcode"
},
  "geometry": {"coordinates":[133.67439999999999,33.618],"type":"Point"}
}