{
  "type": "Feature",
  "properties": {
    "gn:adm1_name":"Gifuken",
    "gn:adm2_name":"Oogakishi",
    "gn:name":"Tsurumichou",
    "iso:country":"JP",
    "wof:name":"503-0805",
    "wof:placetype":"postalcode"
},
  "geometry": {"coordinates":[136.63829999999999,35.3607],"type":"Point"}
}