{
  "type": "Feature",
  "properties": {
    "gn:adm1_name":"Hyougoken",
    "gn:adm2_name":"Itamishi",
    "gn:name":"Kuchisakai",
    "iso:country":"JP",
    "wof:name":"664-0844",
    "wof:placetype":"postalcode"
},
  "geometry": {"coordinates":[135.43520000000001,34.774],"type":"Point"}
}