{
  "type": "Feature",
  "properties": {
    "gn:adm1_name":"Niigataken",
    "gn:adm2_name":"Itoigawashi",
    "gn:name":"Ookubo",
    "iso:country":"JP",
    "wof:name":"949-0545",
    "wof:placetype":"postalcode"
},
  "geometry": {"coordinates":[137.91820000000001,36.9248],"type":"Point"}
}