{
  "type": "Feature",
  "properties": {
    "gn:adm1_name":"Mieken",
    "gn:adm2_name":"Kumanoshi",
    "gn:name":"Ikuseichoukodokoro",
    "iso:country":"JP",
    "wof:name":"519-4445",
    "wof:placetype":"postalcode"
},
  "geometry": {"coordinates":[135.99719999999999,33.9253],"type":"Point"}
}