{
  "type": "Feature",
  "properties": {
    "gn:adm1_name":"Nagasakiken",
    "gn:adm2_name":"Isahayashi",
    "gn:name":"Wakabachou",
    "iso:country":"JP",
    "wof:name":"854-0064",
    "wof:placetype":"postalcode"
},
  "geometry": {"coordinates":[130.0068,32.8278],"type":"Point"}
}