{
  "type": "Feature",
  "properties": {
    "gn:adm1_name":"Oosakafu",
    "gn:adm2_name":"Takatsukishi",
    "gn:name":"Tamagawashinmachi",
    "iso:country":"JP",
    "wof:name":"569-0856",
    "wof:placetype":"postalcode"
},
  "geometry": {"coordinates":[135.60509999999999,34.816],"type":"Point"}
}