{
  "type": "Feature",
  "properties": {
    "gn:adm1_name":"Oosakafu",
    "gn:adm2_name":"Neyagawashi",
    "gn:name":"Miyukihigashimachi",
    "iso:country":"JP",
    "wof:name":"572-0055",
    "wof:placetype":"postalcode"
},
  "geometry": {"coordinates":[135.60749999999999,34.7516],"type":"Point"}
}