{
  "type": "Feature",
  "properties": {
    "gn:adm1_name":"Hyougoken",
    "gn:adm2_name":"Sasayamashi",
    "gn:name":"Taniyama",
    "iso:country":"JP",
    "wof:name":"669-2453",
    "wof:placetype":"postalcode"
},
  "geometry": {"coordinates":[135.2132,35.0625],"type":"Point"}
}