{
  "type": "Feature",
  "properties": {
    "gn:adm1_name":"Naganoken",
    "gn:adm2_name":"Uedashi",
    "gn:name":"Tokiiri",
    "iso:country":"JP",
    "wof:name":"386-0015",
    "wof:placetype":"postalcode"
},
  "geometry": {"coordinates":[138.26840000000001,36.3905],"type":"Point"}
}