{
  "type": "Feature",
  "properties": {
    "gn:adm1_name":"Tochigiken",
    "gn:adm2_name":"Ootawarashi",
    "gn:name":"Yamanote",
    "iso:country":"JP",
    "wof:name":"324-0051",
    "wof:placetype":"postalcode"
},
  "geometry": {"coordinates":[140.0282,36.8698],"type":"Point"}
}