{
  "type": "Feature",
  "properties": {
    "gn:adm1_name":"Toukyouto",
    "gn:adm2_name":"Koganeishi",
    "gn:name":"Higashichou",
    "iso:country":"JP",
    "wof:name":"184-0011",
    "wof:placetype":"postalcode"
},
  "geometry": {"coordinates":[139.5265,35.6959],"type":"Point"}
}