{
  "type": "Feature",
  "properties": {
    "gn:adm1_name":"Niigataken",
    "gn:adm2_name":"Iwafunegun'Asahimura",
    "gn:name":"Ueno",
    "iso:country":"JP",
    "wof:name":"958-0262",
    "wof:placetype":"postalcode"
},
  "geometry": {"coordinates":[139.51390000000001,38.2765],"type":"Point"}
}