{
  "type": "Feature",
  "properties": {
    "gn:adm1_name":"Ooitaken",
    "gn:adm2_name":"Usashi",
    "gn:name":"Matsusaki",
    "iso:country":"JP",
    "wof:name":"872-0015",
    "wof:placetype":"postalcode"
},
  "geometry": {"coordinates":[131.40049999999999,33.5579],"type":"Point"}
}