{
  "type": "Feature",
  "properties": {
    "gn:adm1_name":"Aichiken",
    "gn:adm2_name":"Setoshi",
    "gn:name":"Azumachou",
    "iso:country":"JP",
    "wof:name":"489-0847",
    "wof:placetype":"postalcode"
},
  "geometry": {"coordinates":[137.11590000000001,35.2222],"type":"Point"}
}