{
  "type": "Feature",
  "properties": {
    "gn:adm1_name":"Tochigiken",
    "gn:adm2_name":"Utsunomiyashi",
    "gn:name":"Iidamachi",
    "iso:country":"JP",
    "wof:name":"321-0347",
    "wof:placetype":"postalcode"
},
  "geometry": {"coordinates":[139.80969999999999,36.5677],"type":"Point"}
}