{
  "type": "Feature",
  "properties": {
    "gn:adm1_name":"Aichiken",
    "gn:adm2_name":"Nagoyashinakagawaku",
    "gn:name":"Fukuzumichou",
    "iso:country":"JP",
    "wof:name":"454-0802",
    "wof:placetype":"postalcode"
},
  "geometry": {"coordinates":[136.88040000000001,35.1574],"type":"Point"}
}