{
  "type": "Feature",
  "properties": {
    "gn:adm1_name":"Gunmaken",
    "gn:adm2_name":"Tonegunshirasawamura",
    "gn:name":"Hiraide",
    "iso:country":"JP",
    "wof:name":"378-0125",
    "wof:placetype":"postalcode"
},
  "geometry": {"coordinates":[139.12710000000001,36.6581],"type":"Point"}
}