{
  "type": "Feature",
  "properties": {
    "gn:adm1_name":"Chibaken",
    "gn:adm2_name":"Tateyamashi",
    "gn:name":"Hamada",
    "iso:country":"JP",
    "wof:name":"294-0303",
    "wof:placetype":"postalcode"
},
  "geometry": {"coordinates":[139.8056,34.9743],"type":"Point"}
}