{
  "type": "Feature",
  "properties": {
    "gn:adm1_name":"Ehimeken",
    "gn:adm2_name":"Yawatahamashi",
    "gn:name":"Anai",
    "iso:country":"JP",
    "wof:name":"796-8054",
    "wof:placetype":"postalcode"
},
  "geometry": {"coordinates":[132.39750000000001,33.3985],"type":"Point"}
}