{
  "type": "Feature",
  "properties": {
    "gn:adm1_name":"Ishikawaken",
    "gn:adm2_name":"Hakuiguntogimachi",
    "gn:name":"Kyuubun",
    "iso:country":"JP",
    "wof:name":"925-0457",
    "wof:placetype":"postalcode"
},
  "geometry": {"coordinates":[136.73099999999999,37.1654],"type":"Point"}
}