{
  "type": "Feature",
  "properties": {
    "gn:adm1_name":"Saitamaken",
    "gn:adm2_name":"Fukayashi",
    "gn:name":"Ooya",
    "iso:country":"JP",
    "wof:name":"366-0814",
    "wof:placetype":"postalcode"
},
  "geometry": {"coordinates":[139.2458,36.1574],"type":"Point"}
}