{
  "type": "Feature",
  "properties": {
    "gn:adm1_name":"Okayamaken",
    "gn:adm2_name":"Tamanoshi",
    "gn:name":"Hachihamachoumiishi",
    "iso:country":"JP",
    "wof:name":"706-0222",
    "wof:placetype":"postalcode"
},
  "geometry": {"coordinates":[133.946,34.5654],"type":"Point"}
}