{
  "type": "Feature",
  "properties": {
    "gn:adm1_name":"Oosakafu",
    "gn:adm2_name":"Hirakatashi",
    "gn:name":"Isoshimamotomachi",
    "iso:country":"JP",
    "wof:name":"573-1187",
    "wof:placetype":"postalcode"
},
  "geometry": {"coordinates":[135.64680000000001,34.8233],"type":"Point"}
}