{
  "type": "Feature",
  "properties": {
    "gn:adm1_name":"Fukuokaken",
    "gn:adm2_name":"Kitakyuushuushikokuraminamiku",
    "gn:name":"Fujimi",
    "iso:country":"JP",
    "wof:name":"802-0801",
    "wof:placetype":"postalcode"
},
  "geometry": {"coordinates":[130.8817,33.8581],"type":"Point"}
}