{
  "type": "Feature",
  "properties": {
    "gn:adm1_name":"Saitamaken",
    "gn:adm2_name":"Kawagoeshi",
    "gn:name":"Izumichou",
    "iso:country":"JP",
    "wof:name":"350-0026",
    "wof:placetype":"postalcode"
},
  "geometry": {"coordinates":[139.51300000000001,35.9052],"type":"Point"}
}