{
  "type": "Feature",
  "properties": {
    "gn:adm1_name":"Tottoriken",
    "gn:adm2_name":"Ketakagunketakachou",
    "gn:name":"Tono",
    "iso:country":"JP",
    "wof:name":"689-0342",
    "wof:placetype":"postalcode"
},
  "geometry": {"coordinates":[134.03700000000001,35.4593],"type":"Point"}
}