{
  "type": "Feature",
  "properties": {
    "gn:adm1_name":"Ooitaken",
    "gn:adm2_name":"Shimogegunhonyabakeimachi",
    "gn:name":"Hida",
    "iso:country":"JP",
    "wof:name":"871-0201",
    "wof:placetype":"postalcode"
},
  "geometry": {"coordinates":[131.1737,33.5043],"type":"Point"}
}