{
  "type": "Feature",
  "properties": {
    "gn:adm1_name":"Miyagiken",
    "gn:adm2_name":"Sendaishitaihakuku",
    "gn:name":"Nakada",
    "iso:country":"JP",
    "wof:name":"981-1104",
    "wof:placetype":"postalcode"
},
  "geometry": {"coordinates":[140.8871,38.1978],"type":"Point"}
}