{
  "type": "Feature",
  "properties": {
    "gn:adm1_name":"Kagoshimaken",
    "gn:adm2_name":"Kimotsukigun'Uchinourachou",
    "gn:name":"Kitakata",
    "iso:country":"JP",
    "wof:name":"893-1401",
    "wof:placetype":"postalcode"
},
  "geometry": {"coordinates":[131.06360000000001,31.2858],"type":"Point"}
}