{
  "type": "Feature",
  "properties": {
    "gn:adm1_name":"Mieken",
    "gn:adm2_name":"Ayamagun'Ooyamadamura",
    "gn:name":"Shimoawa",
    "iso:country":"JP",
    "wof:name":"518-1416",
    "wof:placetype":"postalcode"
},
  "geometry": {"coordinates":[136.2636,34.7581],"type":"Point"}
}