{
  "type": "Feature",
  "properties": {
    "gn:adm1_name":"Gunmaken",
    "gn:adm2_name":"Ouragun'Ouramachi",
    "gn:name":"Fujikawa",
    "iso:country":"JP",
    "wof:name":"370-0605",
    "wof:placetype":"postalcode"
},
  "geometry": {"coordinates":[139.4521,36.276],"type":"Point"}
}