{
  "type": "Feature",
  "properties": {
    "gn:adm1_name":"Ibarakiken",
    "gn:adm2_name":"Niiharigunkasumigauramachi",
    "gn:name":"Ogami",
    "iso:country":"JP",
    "wof:name":"300-0132",
    "wof:placetype":"postalcode"
},
  "geometry": {"coordinates":[140.33959999999999,36.0843],"type":"Point"}
}