{
  "type": "Feature",
  "properties": {
    "gn:adm1_name":"Toyamaken",
    "gn:adm2_name":"Toyamashi",
    "gn:name":"Nishifutamata",
    "iso:country":"JP",
    "wof:name":"930-0177",
    "wof:placetype":"postalcode"
},
  "geometry": {"coordinates":[137.1309,36.7189],"type":"Point"}
}