{
  "type": "Feature",
  "properties": {
    "gn:adm1_name":"Ehimeken",
    "gn:adm2_name":"Saijoushi",
    "gn:name":"Tamatsu",
    "iso:country":"JP",
    "wof:name":"793-0001",
    "wof:placetype":"postalcode"
},
  "geometry": {"coordinates":[133.1994,33.9272],"type":"Point"}
}