{
  "type": "Feature",
  "properties": {
    "gn:adm1_name":"Hyougoken",
    "gn:adm2_name":"Koubeshichuuouku",
    "gn:name":"Nakaochou",
    "iso:country":"JP",
    "wof:name":"651-0057",
    "wof:placetype":"postalcode"
},
  "geometry": {"coordinates":[135.20310000000001,34.7103],"type":"Point"}
}