{
  "type": "Feature",
  "properties": {
    "gn:adm1_name":"Hyougoken",
    "gn:adm2_name":"Onoshi",
    "gn:name":"Ooshimachou",
    "iso:country":"JP",
    "wof:name":"675-1334",
    "wof:placetype":"postalcode"
},
  "geometry": {"coordinates":[134.9289,34.8359],"type":"Point"}
}