{
  "type": "Feature",
  "properties": {
    "gn:adm1_name":"Fukushimaken",
    "gn:adm2_name":"Nishishirakawagunyabukimachi",
    "gn:name":"Nejuku",
    "iso:country":"JP",
    "wof:name":"969-0263",
    "wof:placetype":"postalcode"
},
  "geometry": {"coordinates":[140.3467,37.1746],"type":"Point"}
}