{
  "type": "Feature",
  "properties": {
    "gn:adm1_name":"Ishikawaken",
    "gn:adm2_name":"Fugeshigunmonzenmachi",
    "gn:name":"Kuresaka",
    "iso:country":"JP",
    "wof:name":"927-2273",
    "wof:placetype":"postalcode"
},
  "geometry": {"coordinates":[136.7782,37.3505],"type":"Point"}
}