{
  "type": "Feature",
  "properties": {
    "gn:adm1_name":"Aichiken",
    "gn:adm2_name":"Kounanshi",
    "gn:name":"Wadachoukawahigashi",
    "iso:country":"JP",
    "wof:name":"483-8014",
    "wof:placetype":"postalcode"
},
  "geometry": {"coordinates":[136.8921,35.3625],"type":"Point"}
}