{
  "type": "Feature",
  "properties": {
    "gn:adm1_name":"Ibarakiken",
    "gn:adm2_name":"Tsuchiurashi",
    "gn:name":"Mariyamashinden",
    "iso:country":"JP",
    "wof:name":"300-0838",
    "wof:placetype":"postalcode"
},
  "geometry": {"coordinates":[140.17779999999999,36.0397],"type":"Point"}
}