{
  "type": "Feature",
  "properties": {
    "gn:adm1_name":"Tochigiken",
    "gn:adm2_name":"Nasugunbatoumachi",
    "gn:name":"Moriizumi",
    "iso:country":"JP",
    "wof:name":"324-0604",
    "wof:placetype":"postalcode"
},
  "geometry": {"coordinates":[140.24359999999999,36.7663],"type":"Point"}
}