{
  "type": "Feature",
  "properties": {
    "gn:adm1_name":"Nagasakiken",
    "gn:adm2_name":"Ikigun'Ashibechou",
    "gn:name":"Hakozakitaniefure",
    "iso:country":"JP",
    "wof:name":"811-5464",
    "wof:placetype":"postalcode"
},
  "geometry": {"coordinates":[129.7295,33.8219],"type":"Point"}
}