{
  "type": "Feature",
  "properties": {
    "gn:adm1_name":"Shigaken",
    "gn:adm2_name":"Oumihachimanshi",
    "gn:name":"Nodachou",
    "iso:country":"JP",
    "wof:name":"523-0002",
    "wof:placetype":"postalcode"
},
  "geometry": {"coordinates":[136.12389999999999,35.1198],"type":"Point"}
}