{
  "type": "Feature",
  "properties": {
    "gn:adm1_name":"Yamagataken",
    "gn:adm2_name":"Nishimurayamagun'Ooemachi",
    "gn:name":"Tomizawa",
    "iso:country":"JP",
    "wof:name":"990-1114",
    "wof:placetype":"postalcode"
},
  "geometry": {"coordinates":[140.20320000000001,38.3569],"type":"Point"}
}