{
  "type": "Feature",
  "properties": {
    "gn:adm1_name":"Gifuken",
    "gn:adm2_name":"Oogakishi",
    "gn:name":"Aratachou",
    "iso:country":"JP",
    "wof:name":"503-0856",
    "wof:placetype":"postalcode"
},
  "geometry": {"coordinates":[136.62180000000001,35.345],"type":"Point"}
}