{
  "type": "Feature",
  "properties": {
    "gn:adm1_name":"Chibaken",
    "gn:adm2_name":"Chibashihanamigawaku",
    "gn:name":"Uchiyamachou",
    "iso:country":"JP",
    "wof:name":"262-0002",
    "wof:placetype":"postalcode"
},
  "geometry": {"coordinates":[140.1294,35.6938],"type":"Point"}
}