{
  "type": "Feature",
  "properties": {
    "gn:adm1_name":"Miyagiken",
    "gn:adm2_name":"Shibatagun'Oogawaramachi",
    "gn:name":"Ootatsu",
    "iso:country":"JP",
    "wof:name":"989-1204",
    "wof:placetype":"postalcode"
},
  "geometry": {"coordinates":[140.7345,38.0344],"type":"Point"}
}