{
  "type": "Feature",
  "properties": {
    "gn:adm1_name":"Hyougoken",
    "gn:adm2_name":"Kawabegun'Inagawachou",
    "gn:name":"Kidu",
    "iso:country":"JP",
    "wof:name":"666-0225",
    "wof:placetype":"postalcode"
},
  "geometry": {"coordinates":[135.3425,34.9333],"type":"Point"}
}