{
  "type": "Feature",
  "properties": {
    "gn:adm1_name":"Chibaken",
    "gn:adm2_name":"Isumigun'Ootakimachi",
    "gn:name":"Sanjou",
    "iso:country":"JP",
    "wof:name":"298-0273",
    "wof:placetype":"postalcode"
},
  "geometry": {"coordinates":[140.21080000000001,35.2466],"type":"Point"}
}