{
  "type": "Feature",
  "properties": {
    "gn:adm1_name":"Shigaken",
    "gn:adm2_name":"Takashimagunmakinochou",
    "gn:name":"Kamikaide",
    "iso:country":"JP",
    "wof:name":"520-1831",
    "wof:placetype":"postalcode"
},
  "geometry": {"coordinates":[136.047,35.4803],"type":"Point"}
}