{
  "type": "Feature",
  "properties": {
    "gn:adm1_name":"Kagoshimaken",
    "gn:adm2_name":"Kawanabegunkawanabechou",
    "gn:name":"Kiyomizu",
    "iso:country":"JP",
    "wof:name":"897-0202",
    "wof:placetype":"postalcode"
},
  "geometry": {"coordinates":[130.43950000000001,31.4222],"type":"Point"}
}