{
  "type": "Feature",
  "properties": {
    "gn:adm1_name":"Fukuokaken",
    "gn:adm2_name":"Asakuragunyasumachi",
    "gn:name":"Futa",
    "iso:country":"JP",
    "wof:name":"838-0228",
    "wof:placetype":"postalcode"
},
  "geometry": {"coordinates":[130.5643,33.4738],"type":"Point"}
}