{
  "type": "Feature",
  "properties": {
    "gn:adm1_name":"Kanagawaken",
    "gn:adm2_name":"Kawasakishikawasakiku",
    "gn:name":"Shimonamiki",
    "iso:country":"JP",
    "wof:name":"210-0025",
    "wof:placetype":"postalcode"
},
  "geometry": {"coordinates":[139.6901,35.5231],"type":"Point"}
}