{
  "type": "Feature",
  "properties": {
    "gn:adm1_name":"Ooitaken",
    "gn:adm2_name":"Hitashi",
    "gn:name":"Nakaomachi",
    "iso:country":"JP",
    "wof:name":"877-1363",
    "wof:placetype":"postalcode"
},
  "geometry": {"coordinates":[130.9588,33.3338],"type":"Point"}
}