{
  "type": "Feature",
  "properties": {
    "gn:adm1_name":"Kyoutofu",
    "gn:adm2_name":"Kyoutoshifushimiku",
    "gn:name":"Tangochou",
    "iso:country":"JP",
    "wof:name":"612-8044",
    "wof:placetype":"postalcode"
},
  "geometry": {"coordinates":[135.76259999999999,34.9299],"type":"Point"}
}