{
  "type": "Feature",
  "properties": {
    "gn:adm1_name":"Ishikawaken",
    "gn:adm2_name":"Fugeshigunnotomachi",
    "gn:name":"Kakio",
    "iso:country":"JP",
    "wof:name":"927-0304",
    "wof:placetype":"postalcode"
},
  "geometry": {"coordinates":[137.0557,37.2683],"type":"Point"}
}