{
  "type": "Feature",
  "properties": {
    "gn:adm1_name":"Kyoutofu",
    "gn:adm2_name":"Kyoutoshishimogyouku",
    "gn:name":"Hirayachou",
    "iso:country":"JP",
    "wof:name":"600-8109",
    "wof:placetype":"postalcode"
},
  "geometry": {"coordinates":[135.75470000000001,34.9966],"type":"Point"}
}