{
  "type": "Feature",
  "properties": {
    "gn:adm1_name":"Fukushimaken",
    "gn:adm2_name":"Ishikawagun'Ishikawamachi",
    "gn:name":"Wagu",
    "iso:country":"JP",
    "wof:name":"963-7886",
    "wof:placetype":"postalcode"
},
  "geometry": {"coordinates":[140.41730000000001,37.1614],"type":"Point"}
}