{
  "type": "Feature",
  "properties": {
    "gn:adm1_name":"Gunmaken",
    "gn:adm2_name":"Sawagunsakaimachi",
    "gn:name":"Nishiimai",
    "iso:country":"JP",
    "wof:name":"370-0112",
    "wof:placetype":"postalcode"
},
  "geometry": {"coordinates":[139.26490000000001,36.2814],"type":"Point"}
}