{
  "type": "Feature",
  "properties": {
    "gn:adm1_name":"Yamanashiken",
    "gn:adm2_name":"Tsurushi",
    "gn:name":"Yonawa",
    "iso:country":"JP",
    "wof:name":"402-0012",
    "wof:placetype":"postalcode"
},
  "geometry": {"coordinates":[138.94380000000001,35.5618],"type":"Point"}
}