{
  "type": "Feature",
  "properties": {
    "gn:adm1_name":"Nagasakiken",
    "gn:adm2_name":"Minamimatsuuragunwakamatsuchou",
    "gn:name":"Kounouragou",
    "iso:country":"JP",
    "wof:name":"853-2305",
    "wof:placetype":"postalcode"
},
  "geometry": {"coordinates":[129.00989999999999,32.9129],"type":"Point"}
}