{
  "type": "Feature",
  "properties": {
    "gn:adm1_name":"Tochigiken",
    "gn:adm2_name":"Oyamashi",
    "gn:name":"Shimokouduka",
    "iso:country":"JP",
    "wof:name":"323-0065",
    "wof:placetype":"postalcode"
},
  "geometry": {"coordinates":[139.76580000000001,36.3145],"type":"Point"}
}