{
  "type": "Feature",
  "properties": {
    "gn:adm1_name":"Shimaneken",
    "gn:adm2_name":"Oochigundaiwamura",
    "gn:name":"Tsugayuki",
    "iso:country":"JP",
    "wof:name":"696-0705",
    "wof:placetype":"postalcode"
},
  "geometry": {"coordinates":[132.61179999999999,34.9849],"type":"Point"}
}