{
  "type": "Feature",
  "properties": {
    "gn:adm1_name":"Shizuokaken",
    "gn:adm2_name":"Kosaishi",
    "gn:name":"Kazenomori",
    "iso:country":"JP",
    "wof:name":"431-0432",
    "wof:placetype":"postalcode"
},
  "geometry": {"coordinates":[137.54900000000001,34.7203],"type":"Point"}
}