{
  "type": "Feature",
  "properties": {
    "gn:adm1_name":"Tokushimaken",
    "gn:adm2_name":"Tokushimashi",
    "gn:name":"Seimichou",
    "iso:country":"JP",
    "wof:name":"770-0927",
    "wof:placetype":"postalcode"
},
  "geometry": {"coordinates":[134.54499999999999,34.0607],"type":"Point"}
}