{
  "type": "Feature",
  "properties": {
    "gn:adm1_name":"Kyoutofu",
    "gn:adm2_name":"Kyoutoshifushimiku",
    "gn:name":"Daigominamisatochou",
    "iso:country":"JP",
    "wof:name":"601-1352",
    "wof:placetype":"postalcode"
},
  "geometry": {"coordinates":[135.81530000000001,34.9463],"type":"Point"}
}