{
  "type": "Feature",
  "properties": {
    "gn:adm1_name":"Miyagiken",
    "gn:adm2_name":"Kuriharaguntsukidatechou",
    "gn:name":"Takada",
    "iso:country":"JP",
    "wof:name":"987-2215",
    "wof:placetype":"postalcode"
},
  "geometry": {"coordinates":[141.02350000000001,38.7267],"type":"Point"}
}