{
  "type": "Feature",
  "properties": {
    "gn:adm1_name":"Kyoutofu",
    "gn:adm2_name":"Yawatashi",
    "gn:name":"Iwatatakeduna",
    "iso:country":"JP",
    "wof:name":"614-8255",
    "wof:placetype":"postalcode"
},
  "geometry": {"coordinates":[135.7441,34.8554],"type":"Point"}
}