{
  "type": "Feature",
  "properties": {
    "gn:adm1_name":"Ehimeken",
    "gn:adm2_name":"Higashiuwagunnomurachou",
    "gn:name":"Kamanta",
    "iso:country":"JP",
    "wof:name":"797-1326",
    "wof:placetype":"postalcode"
},
  "geometry": {"coordinates":[132.68559999999999,33.4038],"type":"Point"}
}