{
  "type": "Feature",
  "properties": {
    "gn:adm1_name":"Kagoshimaken",
    "gn:adm2_name":"Ooshimagun'Ukenson",
    "gn:name":"Uken",
    "iso:country":"JP",
    "wof:name":"894-3411",
    "wof:placetype":"postalcode"
},
  "geometry": {"coordinates":[129.22839999999999,28.2958],"type":"Point"}
}