{
  "type": "Feature",
  "properties": {
    "gn:adm1_name":"Kyoutofu",
    "gn:adm2_name":"Yawatashi",
    "gn:name":"Shimonarakamisandoko",
    "iso:country":"JP",
    "wof:name":"614-8141",
    "wof:placetype":"postalcode"
},
  "geometry": {"coordinates":[135.72319999999999,34.8715],"type":"Point"}
}