{
  "type": "Feature",
  "properties": {
    "gn:adm1_name":"Gifuken",
    "gn:adm2_name":"Oogakishi",
    "gn:name":"Kirigasakichou",
    "iso:country":"JP",
    "wof:name":"503-0904",
    "wof:placetype":"postalcode"
},
  "geometry": {"coordinates":[136.61490000000001,35.3646],"type":"Point"}
}