{
  "type": "Feature",
  "properties": {
    "gn:adm1_name":"Miyazakiken",
    "gn:adm2_name":"Miyazakishi",
    "gn:name":"Minamitakamatsuchou",
    "iso:country":"JP",
    "wof:name":"880-0005",
    "wof:placetype":"postalcode"
},
  "geometry": {"coordinates":[131.4152,31.9148],"type":"Point"}
}