{
  "type": "Feature",
  "properties": {
    "gn:adm1_name":"Niigataken",
    "gn:adm2_name":"Kashiwazakishi",
    "gn:name":"Hisumi",
    "iso:country":"JP",
    "wof:name":"945-0047",
    "wof:placetype":"postalcode"
},
  "geometry": {"coordinates":[138.5693,37.3734],"type":"Point"}
}