{
  "type": "Feature",
  "properties": {
    "gn:adm1_name":"Aichiken",
    "gn:adm2_name":"Okazakishi",
    "gn:name":"Ooyanagichou",
    "iso:country":"JP",
    "wof:name":"444-3161",
    "wof:placetype":"postalcode"
},
  "geometry": {"coordinates":[137.25729999999999,35.0143],"type":"Point"}
}