{
  "type": "Feature",
  "properties": {
    "gn:adm1_name":"Oosakafu",
    "gn:adm2_name":"Takatsukishi",
    "gn:name":"Besshiyoshinmachi",
    "iso:country":"JP",
    "wof:name":"569-1114",
    "wof:placetype":"postalcode"
},
  "geometry": {"coordinates":[135.6266,34.8576],"type":"Point"}
}