{
  "type": "Feature",
  "properties": {
    "gn:adm1_name":"Niigataken",
    "gn:adm2_name":"Minamikanbaragunshitadamura",
    "gn:name":"Hirote",
    "iso:country":"JP",
    "wof:name":"955-0155",
    "wof:placetype":"postalcode"
},
  "geometry": {"coordinates":[138.9888,37.5443],"type":"Point"}
}