{
  "type": "Feature",
  "properties": {
    "gn:adm1_name":"Naganoken",
    "gn:adm2_name":"Chiisagatagun'Aokimura",
    "gn:name":"Ikanikeisaiganaibaai",
    "iso:country":"JP",
    "wof:name":"386-1600",
    "wof:placetype":"postalcode"
},
  "geometry": {"coordinates":[138.1317,36.3717],"type":"Point"}
}