{
  "type": "Feature",
  "properties": {
    "gn:adm1_name":"Ishikawaken",
    "gn:adm2_name":"Kahokuguntsubatamachi",
    "gn:name":"Shimoyata",
    "iso:country":"JP",
    "wof:name":"929-0315",
    "wof:placetype":"postalcode"
},
  "geometry": {"coordinates":[136.74340000000001,36.7043],"type":"Point"}
}