{
  "type": "Feature",
  "properties": {
    "gn:adm1_name":"Toyamaken",
    "gn:adm2_name":"Kurobeshi",
    "gn:name":"Miyano",
    "iso:country":"JP",
    "wof:name":"938-0804",
    "wof:placetype":"postalcode"
},
  "geometry": {"coordinates":[137.4752,36.8667],"type":"Point"}
}