{
  "type": "Feature",
  "properties": {
    "gn:adm1_name":"Kouchiken",
    "gn:adm2_name":"Sukumoshi",
    "gn:name":"Nishimachi",
    "iso:country":"JP",
    "wof:name":"788-0025",
    "wof:placetype":"postalcode"
},
  "geometry": {"coordinates":[132.6866,32.9289],"type":"Point"}
}