{
  "type": "Feature",
  "properties": {
    "gn:adm1_name":"Tottoriken",
    "gn:adm2_name":"Hinogunnichinanchou",
    "gn:name":"Yukawa",
    "iso:country":"JP",
    "wof:name":"689-5226",
    "wof:placetype":"postalcode"
},
  "geometry": {"coordinates":[133.20439999999999,35.1158],"type":"Point"}
}