{
  "type": "Feature",
  "properties": {
    "gn:adm1_name":"Kyoutofu",
    "gn:adm2_name":"Ayabeshi",
    "gn:name":"Mutsuyorichou",
    "iso:country":"JP",
    "wof:name":"623-1131",
    "wof:placetype":"postalcode"
},
  "geometry": {"coordinates":[135.44390000000001,35.3705],"type":"Point"}
}