{
  "type": "Feature",
  "properties": {
    "gn:adm1_name":"Okayamaken",
    "gn:adm2_name":"Okayamashi",
    "gn:name":"Shimoishii",
    "iso:country":"JP",
    "wof:name":"700-0907",
    "wof:placetype":"postalcode"
},
  "geometry": {"coordinates":[133.91810000000001,34.6606],"type":"Point"}
}