{
  "type": "Feature",
  "properties": {
    "gn:adm1_name":"Ishikawaken",
    "gn:adm2_name":"Hakuigun'Oshimizumachi",
    "gn:name":"Sougou",
    "iso:country":"JP",
    "wof:name":"939-0171",
    "wof:placetype":"postalcode"
},
  "geometry": {"coordinates":[136.84960000000001,36.7709],"type":"Point"}
}