{
  "type": "Feature",
  "properties": {
    "gn:adm1_name":"Miyagiken",
    "gn:adm2_name":"Toodagunnangouchou",
    "gn:name":"Ooyanagi",
    "iso:country":"JP",
    "wof:name":"989-4204",
    "wof:placetype":"postalcode"
},
  "geometry": {"coordinates":[141.1223,38.5011],"type":"Point"}
}