{
  "type": "Feature",
  "properties": {
    "gn:adm1_name":"Oosakafu",
    "gn:adm2_name":"Oosakashichuuouku",
    "gn:name":"Tokuichou",
    "iso:country":"JP",
    "wof:name":"540-0025",
    "wof:placetype":"postalcode"
},
  "geometry": {"coordinates":[135.51410000000001,34.6841],"type":"Point"}
}