{
  "type": "Feature",
  "properties": {
    "gn:adm1_name":"Okinawaken",
    "gn:adm2_name":"Nakagamigunnakagusukuson",
    "gn:name":"Asato",
    "iso:country":"JP",
    "wof:name":"901-2407",
    "wof:placetype":"postalcode"
},
  "geometry": {"coordinates":[127.7886,26.2593],"type":"Point"}
}