{
  "type": "Feature",
  "properties": {
    "gn:adm1_name":"Shimaneken",
    "gn:adm2_name":"Hamadashi",
    "gn:name":"Tonourachou",
    "iso:country":"JP",
    "wof:name":"697-0001",
    "wof:placetype":"postalcode"
},
  "geometry": {"coordinates":[132.0778,34.9114],"type":"Point"}
}