{
  "type": "Feature",
  "properties": {
    "gn:adm1_name":"Yamanashiken",
    "gn:adm2_name":"Nishiyatsushirogunshimobechou",
    "gn:name":"Kurumada",
    "iso:country":"JP",
    "wof:name":"409-3116",
    "wof:placetype":"postalcode"
},
  "geometry": {"coordinates":[138.4871,35.4817],"type":"Point"}
}