{
  "type": "Feature",
  "properties": {
    "gn:adm1_name":"Kouchiken",
    "gn:adm2_name":"Takaokagunsakawachou",
    "gn:name":"Nishiyamakou",
    "iso:country":"JP",
    "wof:name":"789-1223",
    "wof:placetype":"postalcode"
},
  "geometry": {"coordinates":[133.25980000000001,33.4777],"type":"Point"}
}