{
  "type": "Feature",
  "properties": {
    "gn:adm1_name":"Fukushimaken",
    "gn:adm2_name":"Nihonmatsushi",
    "gn:name":"Tooyama",
    "iso:country":"JP",
    "wof:name":"964-0945",
    "wof:placetype":"postalcode"
},
  "geometry": {"coordinates":[140.48400000000001,37.5627],"type":"Point"}
}