{
  "type": "Feature",
  "properties": {
    "gn:adm1_name":"Kagoshimaken",
    "gn:adm2_name":"Ooshimagunkikaichou",
    "gn:name":"Shimanaka",
    "iso:country":"JP",
    "wof:name":"891-6222",
    "wof:placetype":"postalcode"
},
  "geometry": {"coordinates":[129.96690000000001,28.3262],"type":"Point"}
}