{
  "type": "Feature",
  "properties": {
    "gn:adm1_name":"Tokushimaken",
    "gn:adm2_name":"Tokushimashi",
    "gn:name":"Hachimanchou(Shimofukuman)",
    "iso:country":"JP",
    "wof:name":"770-8074",
    "wof:placetype":"postalcode"
},
  "geometry": {"coordinates":[134.5325,34.0513],"type":"Point"}
}