{
  "type": "Feature",
  "properties": {
    "gn:adm1_name":"Fukuokaken",
    "gn:adm2_name":"Ukihagunyoshiimachi",
    "gn:name":"Wakamiya",
    "iso:country":"JP",
    "wof:name":"839-1311",
    "wof:placetype":"postalcode"
},
  "geometry": {"coordinates":[130.76509999999999,33.343],"type":"Point"}
}