{
  "type": "Feature",
  "properties": {
    "gn:adm1_name":"Ooitaken",
    "gn:adm2_name":"Shimogegunyamakunimachi",
    "gn:name":"Hiraono",
    "iso:country":"JP",
    "wof:name":"871-0711",
    "wof:placetype":"postalcode"
},
  "geometry": {"coordinates":[131.03,33.411],"type":"Point"}
}