{
  "type": "Feature",
  "properties": {
    "gn:adm1_name":"Yamagataken",
    "gn:adm2_name":"Higashitagawagunmikawamachi",
    "gn:name":"Doguchi",
    "iso:country":"JP",
    "wof:name":"997-1322",
    "wof:placetype":"postalcode"
},
  "geometry": {"coordinates":[139.869,38.8081],"type":"Point"}
}