{
  "type": "Feature",
  "properties": {
    "gn:adm1_name":"Kagoshimaken",
    "gn:adm2_name":"Kimotsukigunkouyamachou",
    "gn:name":"Hami",
    "iso:country":"JP",
    "wof:name":"893-1202",
    "wof:placetype":"postalcode"
},
  "geometry": {"coordinates":[131.0206,31.349],"type":"Point"}
}