{
  "type": "Feature",
  "properties": {
    "gn:adm1_name":"Shizuokaken",
    "gn:adm2_name":"Numadushi",
    "gn:name":"Senbontokiwachou",
    "iso:country":"JP",
    "wof:name":"410-0854",
    "wof:placetype":"postalcode"
},
  "geometry": {"coordinates":[138.85230000000001,35.0892],"type":"Point"}
}