{
  "type": "Feature",
  "properties": {
    "gn:adm1_name":"Mieken",
    "gn:adm2_name":"Wataraigunnanseichou",
    "gn:name":"Naize",
    "iso:country":"JP",
    "wof:name":"516-0111",
    "wof:placetype":"postalcode"
},
  "geometry": {"coordinates":[136.65950000000001,34.3494],"type":"Point"}
}