{
  "type": "Feature",
  "properties": {
    "gn:adm1_name":"Toyamaken",
    "gn:adm2_name":"Toyamashi",
    "gn:name":"Yamagishi",
    "iso:country":"JP",
    "wof:name":"930-2215",
    "wof:placetype":"postalcode"
},
  "geometry": {"coordinates":[137.20310000000001,36.7197],"type":"Point"}
}