{
  "type": "Feature",
  "properties": {
    "gn:adm1_name":"Kagoshimaken",
    "gn:adm2_name":"Hiokigunkooriyamachou",
    "gn:name":"Ariyada",
    "iso:country":"JP",
    "wof:name":"891-1107",
    "wof:placetype":"postalcode"
},
  "geometry": {"coordinates":[130.44890000000001,31.6664],"type":"Point"}
}