{
  "type": "Feature",
  "properties": {
    "gn:adm1_name":"Ooitaken",
    "gn:adm2_name":"Ooitashi",
    "gn:name":"Akenokita",
    "iso:country":"JP",
    "wof:name":"870-0165",
    "wof:placetype":"postalcode"
},
  "geometry": {"coordinates":[131.65360000000001,33.228],"type":"Point"}
}