{
  "type": "Feature",
  "properties": {
    "gn:adm1_name":"Gifuken",
    "gn:adm2_name":"Gifushi",
    "gn:name":"Kanounagaichou",
    "iso:country":"JP",
    "wof:name":"500-8454",
    "wof:placetype":"postalcode"
},
  "geometry": {"coordinates":[136.75550000000001,35.4034],"type":"Point"}
}