{
  "type": "Feature",
  "properties": {
    "gn:adm1_name":"Fukuiken",
    "gn:adm2_name":"Tsurugashi",
    "gn:name":"Myoujinchou",
    "iso:country":"JP",
    "wof:name":"914-0842",
    "wof:placetype":"postalcode"
},
  "geometry": {"coordinates":[136.0206,35.752],"type":"Point"}
}