{
  "type": "Feature",
  "properties": {
    "gn:adm1_name":"Naganoken",
    "gn:adm2_name":"Kisogun'Ookuwamura",
    "gn:name":"Nagano",
    "iso:country":"JP",
    "wof:name":"399-5503",
    "wof:placetype":"postalcode"
},
  "geometry": {"coordinates":[137.67449999999999,35.6832],"type":"Point"}
}