{
  "type": "Feature",
  "properties": {
    "gn:adm1_name":"Mieken",
    "gn:adm2_name":"Uenoshi",
    "gn:name":"Yuyadani",
    "iso:country":"JP",
    "wof:name":"518-1146",
    "wof:placetype":"postalcode"
},
  "geometry": {"coordinates":[136.10579999999999,34.694],"type":"Point"}
}