{
  "type": "Feature",
  "properties": {
    "gn:adm1_name":"Miyazakiken",
    "gn:adm2_name":"Saitoshi",
    "gn:name":"Seiryouchou",
    "iso:country":"JP",
    "wof:name":"881-0015",
    "wof:placetype":"postalcode"
},
  "geometry": {"coordinates":[131.40129999999999,32.1093],"type":"Point"}
}