{
  "type": "Feature",
  "properties": {
    "gn:adm1_name":"Toukyouto",
    "gn:adm2_name":"Tachikawashi",
    "gn:name":"Hagoromochou",
    "iso:country":"JP",
    "wof:name":"190-0021",
    "wof:placetype":"postalcode"
},
  "geometry": {"coordinates":[139.42699999999999,35.6939],"type":"Point"}
}