{
  "type": "Feature",
  "properties": {
    "gn:adm1_name":"Miyagiken",
    "gn:adm2_name":"Sendaishitaihakuku",
    "gn:name":"Sahoyama",
    "iso:country":"JP",
    "wof:name":"982-0211",
    "wof:placetype":"postalcode"
},
  "geometry": {"coordinates":[140.82159999999999,38.2351],"type":"Point"}
}