{
  "type": "Feature",
  "properties": {
    "gn:adm1_name":"Kyoutofu",
    "gn:adm2_name":"Kyoutoshisakyouku",
    "gn:name":"Okazakisaishoujichou",
    "iso:country":"JP",
    "wof:name":"606-8342",
    "wof:placetype":"postalcode"
},
  "geometry": {"coordinates":[135.78020000000001,35.0143],"type":"Point"}
}