{
  "type": "Feature",
  "properties": {
    "gn:adm1_name":"Toukyouto",
    "gn:adm2_name":"Toshimaku",
    "gn:name":"Higashiikebukurosanshain60(4kai)",
    "iso:country":"JP",
    "wof:name":"170-6004",
    "wof:placetype":"postalcode"
},
  "geometry": {"coordinates":[139.72030000000001,35.7275],"type":"Point"}
}