{
  "type": "Feature",
  "properties": {
    "gn:adm1_name":"Mieken",
    "gn:adm2_name":"Shimagunhamajimachou",
    "gn:name":"Hazako",
    "iso:country":"JP",
    "wof:name":"517-0403",
    "wof:placetype":"postalcode"
},
  "geometry": {"coordinates":[136.78360000000001,34.3115],"type":"Point"}
}