{
  "type": "Feature",
  "properties": {
    "gn:adm1_name":"Niigataken",
    "gn:adm2_name":"Jouetsushi",
    "gn:name":"Iiduka",
    "iso:country":"JP",
    "wof:name":"942-0039",
    "wof:placetype":"postalcode"
},
  "geometry": {"coordinates":[138.30350000000001,37.1503],"type":"Point"}
}