{
  "type": "Feature",
  "properties": {
    "gn:adm1_name":"Kanagawaken",
    "gn:adm2_name":"Yokohamashitsurumiku",
    "gn:name":"Komaoka",
    "iso:country":"JP",
    "wof:name":"230-0071",
    "wof:placetype":"postalcode"
},
  "geometry": {"coordinates":[139.65379999999999,35.5304],"type":"Point"}
}