{
  "type": "Feature",
  "properties": {
    "gn:adm1_name":"Ibarakiken",
    "gn:adm2_name":"Kujigundaigomachi",
    "gn:name":"Morigane",
    "iso:country":"JP",
    "wof:name":"319-3364",
    "wof:placetype":"postalcode"
},
  "geometry": {"coordinates":[140.39940000000001,36.6877],"type":"Point"}
}