{
  "type": "Feature",
  "properties": {
    "gn:adm1_name":"Niigataken",
    "gn:adm2_name":"Kariwagunnishiyamamachi",
    "gn:name":"Onouchi",
    "iso:country":"JP",
    "wof:name":"949-4112",
    "wof:placetype":"postalcode"
},
  "geometry": {"coordinates":[138.68279999999999,37.4759],"type":"Point"}
}