{
  "type": "Feature",
  "properties": {
    "gn:adm1_name":"Tochigiken",
    "gn:adm2_name":"Hagagun'Ichikaimachi",
    "gn:name":"Shioda",
    "iso:country":"JP",
    "wof:name":"321-3406",
    "wof:placetype":"postalcode"
},
  "geometry": {"coordinates":[140.1104,36.6128],"type":"Point"}
}