{
  "type": "Feature",
  "properties": {
    "gn:adm1_name":"Shizuokaken",
    "gn:adm2_name":"Hamamatsushi",
    "gn:name":"Ooharachou",
    "iso:country":"JP",
    "wof:name":"433-8102",
    "wof:placetype":"postalcode"
},
  "geometry": {"coordinates":[137.73570000000001,34.7991],"type":"Point"}
}