{
  "type": "Feature",
  "properties": {
    "gn:adm1_name":"Kanagawaken",
    "gn:adm2_name":"Kawasakishitamaku",
    "gn:name":"Sugeinadadutsumi",
    "iso:country":"JP",
    "wof:name":"214-0003",
    "wof:placetype":"postalcode"
},
  "geometry": {"coordinates":[139.5384,35.6347],"type":"Point"}
}