{
  "type": "Feature",
  "properties": {
    "gn:adm1_name":"Kagawaken",
    "gn:adm2_name":"Takamatsushi",
    "gn:name":"Kanotsunochou",
    "iso:country":"JP",
    "wof:name":"761-8082",
    "wof:placetype":"postalcode"
},
  "geometry": {"coordinates":[134.0324,34.3002],"type":"Point"}
}