{
  "type": "Feature",
  "properties": {
    "gn:adm1_name":"Ishikawaken",
    "gn:adm2_name":"Mattoushi",
    "gn:name":"Chiyonominami",
    "iso:country":"JP",
    "wof:name":"924-0074",
    "wof:placetype":"postalcode"
},
  "geometry": {"coordinates":[136.53960000000001,36.5191],"type":"Point"}
}