{
  "type": "Feature",
  "properties": {
    "gn:adm1_name":"Aichiken",
    "gn:adm2_name":"Nagoyashinakagawaku",
    "gn:name":"Daitourou",
    "iso:country":"JP",
    "wof:name":"454-0943",
    "wof:placetype":"postalcode"
},
  "geometry": {"coordinates":[136.83369999999999,35.1312],"type":"Point"}
}