{
  "type": "Feature",
  "properties": {
    "gn:adm1_name":"Niigataken",
    "gn:adm2_name":"Tookamachishi",
    "gn:name":"Wakamiyachou",
    "iso:country":"JP",
    "wof:name":"948-0027",
    "wof:placetype":"postalcode"
},
  "geometry": {"coordinates":[138.76220000000001,37.1332],"type":"Point"}
}