{
  "type": "Feature",
  "properties": {
    "gn:adm1_name":"Oosakafu",
    "gn:adm2_name":"Izumishi",
    "gn:name":"Ibukino",
    "iso:country":"JP",
    "wof:name":"594-0041",
    "wof:placetype":"postalcode"
},
  "geometry": {"coordinates":[135.4522,34.4647],"type":"Point"}
}