{
  "type": "Feature",
  "properties": {
    "gn:adm1_name":"Yamanashiken",
    "gn:adm2_name":"Tsurushi",
    "gn:name":"Ogatayama",
    "iso:country":"JP",
    "wof:name":"402-0006",
    "wof:placetype":"postalcode"
},
  "geometry": {"coordinates":[138.92840000000001,35.5864],"type":"Point"}
}