{
  "type": "Feature",
  "properties": {
    "gn:adm1_name":"Ehimeken",
    "gn:adm2_name":"Saijoushi",
    "gn:name":"Nishiizumikou",
    "iso:country":"JP",
    "wof:name":"793-0063",
    "wof:placetype":"postalcode"
},
  "geometry": {"coordinates":[133.1508,33.9055],"type":"Point"}
}