{
  "type": "Feature",
  "properties": {
    "gn:adm1_name":"Gunmaken",
    "gn:adm2_name":"Usuigunmatsuidamachi",
    "gn:name":"Arai",
    "iso:country":"JP",
    "wof:name":"379-0216",
    "wof:placetype":"postalcode"
},
  "geometry": {"coordinates":[138.78790000000001,36.3358],"type":"Point"}
}