{
  "type": "Feature",
  "properties": {
    "gn:adm1_name":"Gifuken",
    "gn:adm2_name":"Mashitagungerochou",
    "gn:name":"Yakeishi",
    "iso:country":"JP",
    "wof:name":"509-2134",
    "wof:placetype":"postalcode"
},
  "geometry": {"coordinates":[137.19900000000001,35.7277],"type":"Point"}
}