{
  "type": "Feature",
  "properties": {
    "gn:adm1_name":"Fukushimaken",
    "gn:adm2_name":"Iwakishi",
    "gn:name":"Tairafujima",
    "iso:country":"JP",
    "wof:name":"970-0103",
    "wof:placetype":"postalcode"
},
  "geometry": {"coordinates":[140.965,37.041],"type":"Point"}
}