{
  "type": "Feature",
  "properties": {
    "gn:adm1_name":"Toyamaken",
    "gn:adm2_name":"Takaokashi",
    "gn:name":"Toidetokuichi",
    "iso:country":"JP",
    "wof:name":"939-1111",
    "wof:placetype":"postalcode"
},
  "geometry": {"coordinates":[137.00290000000001,36.6971],"type":"Point"}
}