{
  "type": "Feature",
  "properties": {
    "gn:adm1_name":"Ehimeken",
    "gn:adm2_name":"Saijoushi",
    "gn:name":"Tonoyama",
    "iso:country":"JP",
    "wof:name":"793-0213",
    "wof:placetype":"postalcode"
},
  "geometry": {"coordinates":[133.16120000000001,33.8748],"type":"Point"}
}