{
  "type": "Feature",
  "properties": {
    "gn:adm1_name":"Shimaneken",
    "gn:adm2_name":"Okigunchibumura",
    "gn:name":"Ooe",
    "iso:country":"JP",
    "wof:name":"684-0101",
    "wof:placetype":"postalcode"
},
  "geometry": {"coordinates":[133.0401,36.0118],"type":"Point"}
}