{
  "type": "Feature",
  "properties": {
    "gn:adm1_name":"Yamanashiken",
    "gn:adm2_name":"Higashiyatsushirogun'Isawachou",
    "gn:name":"Higashiaburakawa",
    "iso:country":"JP",
    "wof:name":"406-0046",
    "wof:placetype":"postalcode"
},
  "geometry": {"coordinates":[138.601,35.6232],"type":"Point"}
}