{
  "type": "Feature",
  "properties": {
    "gn:adm1_name":"Fukushimaken",
    "gn:adm2_name":"Aiduwakamatsushi",
    "gn:name":"Yanagiwaramachi",
    "iso:country":"JP",
    "wof:name":"965-0857",
    "wof:placetype":"postalcode"
},
  "geometry": {"coordinates":[139.9057,37.4938],"type":"Point"}
}