{
  "type": "Feature",
  "properties": {
    "gn:adm1_name":"Shigaken",
    "gn:adm2_name":"Takashimagunmakinochou",
    "gn:name":"Shimokaide",
    "iso:country":"JP",
    "wof:name":"520-1832",
    "wof:placetype":"postalcode"
},
  "geometry": {"coordinates":[136.0523,35.4745],"type":"Point"}
}