{
  "type": "Feature",
  "properties": {
    "gn:adm1_name":"Ooitaken",
    "gn:adm2_name":"Shimogegunyamakunimachi",
    "gn:name":"Uso",
    "iso:country":"JP",
    "wof:name":"871-0715",
    "wof:placetype":"postalcode"
},
  "geometry": {"coordinates":[131.04949999999999,33.4059],"type":"Point"}
}