{
  "type": "Feature",
  "properties": {
    "gn:adm1_name":"Kanagawaken",
    "gn:adm2_name":"Ashigarakamigunmatsudamachi",
    "gn:name":"Kouyama",
    "iso:country":"JP",
    "wof:name":"258-0002",
    "wof:placetype":"postalcode"
},
  "geometry": {"coordinates":[139.15180000000001,35.3479],"type":"Point"}
}