{
  "type": "Feature",
  "properties": {
    "gn:adm1_name":"Ibarakiken",
    "gn:adm2_name":"Kitasoumagunfujishiromachi",
    "gn:name":"Haimatsu",
    "iso:country":"JP",
    "wof:name":"300-1541",
    "wof:placetype":"postalcode"
},
  "geometry": {"coordinates":[140.07259999999999,35.9401],"type":"Point"}
}