{
  "type": "Feature",
  "properties": {
    "gn:adm1_name":"Kanagawaken",
    "gn:adm2_name":"Yokosukashi",
    "gn:name":"Yoshikurachou",
    "iso:country":"JP",
    "wof:name":"238-0047",
    "wof:placetype":"postalcode"
},
  "geometry": {"coordinates":[139.64670000000001,35.2862],"type":"Point"}
}