{
  "type": "Feature",
  "properties": {
    "gn:adm1_name":"Ibarakiken",
    "gn:adm2_name":"Nakagunnakamachi",
    "gn:name":"Kamigachichou",
    "iso:country":"JP",
    "wof:name":"311-0116",
    "wof:placetype":"postalcode"
},
  "geometry": {"coordinates":[140.48339999999999,36.463],"type":"Point"}
}