{
  "type": "Feature",
  "properties": {
    "gn:adm1_name":"Ishikawaken",
    "gn:adm2_name":"Hakuigunshikamachi",
    "gn:name":"Wakabadai",
    "iso:country":"JP",
    "wof:name":"925-0375",
    "wof:placetype":"postalcode"
},
  "geometry": {"coordinates":[136.75540000000001,37.0753],"type":"Point"}
}