{
  "type": "Feature",
  "properties": {
    "gn:adm1_name":"Nagasakiken",
    "gn:adm2_name":"Nagasakishi",
    "gn:name":"Shouwa",
    "iso:country":"JP",
    "wof:name":"852-8145",
    "wof:placetype":"postalcode"
},
  "geometry": {"coordinates":[129.87029999999999,32.793],"type":"Point"}
}