{
  "type": "Feature",
  "properties": {
    "gn:adm1_name":"Ibarakiken",
    "gn:adm2_name":"Hitachinakashi",
    "gn:name":"Mineushiro",
    "iso:country":"JP",
    "wof:name":"311-1234",
    "wof:placetype":"postalcode"
},
  "geometry": {"coordinates":[140.57849999999999,36.3485],"type":"Point"}
}