{
  "type": "Feature",
  "properties": {
    "gn:adm1_name":"Tokushimaken",
    "gn:adm2_name":"Oegunkawashimachou",
    "gn:name":"Miyanoshima",
    "iso:country":"JP",
    "wof:name":"779-3304",
    "wof:placetype":"postalcode"
},
  "geometry": {"coordinates":[134.316,34.0611],"type":"Point"}
}