{
  "type": "Feature",
  "properties": {
    "gn:adm1_name":"Aichiken",
    "gn:adm2_name":"Nagoyashimoriyamaku",
    "gn:name":"Nakashin",
    "iso:country":"JP",
    "wof:name":"463-0057",
    "wof:placetype":"postalcode"
},
  "geometry": {"coordinates":[136.9716,35.1973],"type":"Point"}
}