{
  "type": "Feature",
  "properties": {
    "gn:adm1_name":"Miyagiken",
    "gn:adm2_name":"Ishinomakishi",
    "gn:name":"Taremizuchou",
    "iso:country":"JP",
    "wof:name":"986-2104",
    "wof:placetype":"postalcode"
},
  "geometry": {"coordinates":[141.3698,38.4279],"type":"Point"}
}