{
  "type": "Feature",
  "properties": {
    "gn:adm1_name":"Kyoutofu",
    "gn:adm2_name":"Kyoutoshikamigyouku",
    "gn:name":"Takashimachou",
    "iso:country":"JP",
    "wof:name":"602-0878",
    "wof:placetype":"postalcode"
},
  "geometry": {"coordinates":[135.76859999999999,35.0176],"type":"Point"}
}