{
  "type": "Feature",
  "properties": {
    "gn:adm1_name":"Okayamaken",
    "gn:adm2_name":"Wakegunwakechou",
    "gn:name":"Hon",
    "iso:country":"JP",
    "wof:name":"709-0462",
    "wof:placetype":"postalcode"
},
  "geometry": {"coordinates":[134.1198,34.7995],"type":"Point"}
}