{
  "type": "Feature",
  "properties": {
    "gn:adm1_name":"Fukushimaken",
    "gn:adm2_name":"Iwakishi",
    "gn:name":"Ogawamachiuwadaira",
    "iso:country":"JP",
    "wof:name":"979-3112",
    "wof:placetype":"postalcode"
},
  "geometry": {"coordinates":[140.86420000000001,37.1309],"type":"Point"}
}