{
  "type": "Feature",
  "properties": {
    "gn:adm1_name":"Miyazakiken",
    "gn:adm2_name":"Nobeokashi",
    "gn:name":"Kushitsumachi",
    "iso:country":"JP",
    "wof:name":"889-0514",
    "wof:placetype":"postalcode"
},
  "geometry": {"coordinates":[131.6771,32.5046],"type":"Point"}
}