{
  "type": "Feature",
  "properties": {
    "gn:adm1_name":"Hiroshimaken",
    "gn:adm2_name":"Saekigun'Oonochou",
    "gn:name":"Doi",
    "iso:country":"JP",
    "wof:name":"739-0474",
    "wof:placetype":"postalcode"
},
  "geometry": {"coordinates":[132.28039999999999,34.3048],"type":"Point"}
}