{
  "type": "Feature",
  "properties": {
    "gn:adm1_name":"Gunmaken",
    "gn:adm2_name":"Tatebayashishi",
    "gn:name":"Ooshimachou",
    "iso:country":"JP",
    "wof:name":"374-0001",
    "wof:placetype":"postalcode"
},
  "geometry": {"coordinates":[139.58150000000001,36.2625],"type":"Point"}
}