{
  "type": "Feature",
  "properties": {
    "gn:adm1_name":"Oosakafu",
    "gn:adm2_name":"Oosakashikitaku",
    "gn:name":"Yamazakichou",
    "iso:country":"JP",
    "wof:name":"530-0024",
    "wof:placetype":"postalcode"
},
  "geometry": {"coordinates":[135.50899999999999,34.706],"type":"Point"}
}