{
  "type": "Feature",
  "properties": {
    "gn:adm1_name":"Tottoriken",
    "gn:adm2_name":"Kurayoshishi",
    "gn:name":"Nishimachi",
    "iso:country":"JP",
    "wof:name":"682-0862",
    "wof:placetype":"postalcode"
},
  "geometry": {"coordinates":[133.82060000000001,35.432],"type":"Point"}
}