{
  "type": "Feature",
  "properties": {
    "gn:adm1_name":"Aichiken",
    "gn:adm2_name":"Nagoyashikitaku",
    "gn:name":"Kisouji",
    "iso:country":"JP",
    "wof:name":"462-0065",
    "wof:placetype":"postalcode"
},
  "geometry": {"coordinates":[136.90539999999999,35.2345],"type":"Point"}
}