{
  "type": "Feature",
  "properties": {
    "gn:adm1_name":"Fukuokaken",
    "gn:adm2_name":"Kitakyuushuushiyahatahigashiku",
    "gn:name":"Gionbaramachi",
    "iso:country":"JP",
    "wof:name":"805-0066",
    "wof:placetype":"postalcode"
},
  "geometry": {"coordinates":[130.78700000000001,33.8583],"type":"Point"}
}