{
  "type": "Feature",
  "properties": {
    "gn:adm1_name":"Hyougoken",
    "gn:adm2_name":"Akougunkamigoorichou",
    "gn:name":"Nishinoyama",
    "iso:country":"JP",
    "wof:name":"678-1222",
    "wof:placetype":"postalcode"
},
  "geometry": {"coordinates":[134.38499999999999,34.8552],"type":"Point"}
}