{
  "type": "Feature",
  "properties": {
    "gn:adm1_name":"Hiroshimaken",
    "gn:adm2_name":"Shoubarashi",
    "gn:name":"Tonogouchichou",
    "iso:country":"JP",
    "wof:name":"729-6133",
    "wof:placetype":"postalcode"
},
  "geometry": {"coordinates":[132.9615,34.8382],"type":"Point"}
}