{
  "type": "Feature",
  "properties": {
    "gn:adm1_name":"Tochigiken",
    "gn:adm2_name":"Hagagunmashikomachi",
    "gn:name":"Maezawa",
    "iso:country":"JP",
    "wof:name":"321-4214",
    "wof:placetype":"postalcode"
},
  "geometry": {"coordinates":[140.09209999999999,36.4355],"type":"Point"}
}