{
  "type": "Feature",
  "properties": {
    "gn:adm1_name":"Kyoutofu",
    "gn:adm2_name":"Kyoutoshihigashiyamaku",
    "gn:name":"Fukurochou",
    "iso:country":"JP",
    "wof:name":"605-0911",
    "wof:placetype":"postalcode"
},
  "geometry": {"coordinates":[135.77099999999999,34.9946],"type":"Point"}
}