{
  "type": "Feature",
  "properties": {
    "gn:adm1_name":"Chibaken",
    "gn:adm2_name":"Mobarashi",
    "gn:name":"Kitaduka",
    "iso:country":"JP",
    "wof:name":"297-0009",
    "wof:placetype":"postalcode"
},
  "geometry": {"coordinates":[140.30539999999999,35.4647],"type":"Point"}
}