{
  "type": "Feature",
  "properties": {
    "gn:adm1_name":"Chibaken",
    "gn:adm2_name":"Touganeshi",
    "gn:name":"Futamata",
    "iso:country":"JP",
    "wof:name":"283-0004",
    "wof:placetype":"postalcode"
},
  "geometry": {"coordinates":[140.39340000000001,35.5694],"type":"Point"}
}