{
  "type": "Feature",
  "properties": {
    "gn:adm1_name":"Shigaken",
    "gn:adm2_name":"Gamougunhinochou",
    "gn:name":"Ookubo",
    "iso:country":"JP",
    "wof:name":"529-1603",
    "wof:placetype":"postalcode"
},
  "geometry": {"coordinates":[136.2482,35.0125],"type":"Point"}
}