{
  "type": "Feature",
  "properties": {
    "gn:adm1_name":"Shigaken",
    "gn:adm2_name":"Takashimagun'Adogawachou",
    "gn:name":"Aoyagi",
    "iso:country":"JP",
    "wof:name":"520-1221",
    "wof:placetype":"postalcode"
},
  "geometry": {"coordinates":[136.03389999999999,35.3297],"type":"Point"}
}