{
  "type": "Feature",
  "properties": {
    "gn:adm1_name":"Fukuiken",
    "gn:adm2_name":"Nyuugun'Asahichou",
    "gn:name":"Asahi",
    "iso:country":"JP",
    "wof:name":"916-0146",
    "wof:placetype":"postalcode"
},
  "geometry": {"coordinates":[136.12569999999999,35.9709],"type":"Point"}
}