{
  "type": "Feature",
  "properties": {
    "gn:adm1_name":"Toukyouto",
    "gn:adm2_name":"Komaeshi",
    "gn:name":"Inogata",
    "iso:country":"JP",
    "wof:name":"201-0015",
    "wof:placetype":"postalcode"
},
  "geometry": {"coordinates":[139.5796,35.6259],"type":"Point"}
}