{
  "type": "Feature",
  "properties": {
    "gn:adm1_name":"Hyougoken",
    "gn:adm2_name":"Akougunkamigoorichou",
    "gn:name":"Oeda",
    "iso:country":"JP",
    "wof:name":"678-1275",
    "wof:placetype":"postalcode"
},
  "geometry": {"coordinates":[134.35650000000001,34.8865],"type":"Point"}
}