{
  "type": "Feature",
  "properties": {
    "gn:adm1_name":"Ehimeken",
    "gn:adm2_name":"Matsuyamashi",
    "gn:name":"Kamigawaramachi",
    "iso:country":"JP",
    "wof:name":"791-1124",
    "wof:placetype":"postalcode"
},
  "geometry": {"coordinates":[132.81190000000001,33.7791],"type":"Point"}
}