{
  "type": "Feature",
  "properties": {
    "gn:adm1_name":"Kyoutofu",
    "gn:adm2_name":"Kyoutoshikamigyouku",
    "gn:name":"Nakahashidumechou",
    "iso:country":"JP",
    "wof:name":"602-8051",
    "wof:placetype":"postalcode"
},
  "geometry": {"coordinates":[135.7543,35.0233],"type":"Point"}
}