{
  "type": "Feature",
  "properties": {
    "gn:adm1_name":"Kagoshimaken",
    "gn:adm2_name":"Airagun'Airachou",
    "gn:name":"Nishiaira",
    "iso:country":"JP",
    "wof:name":"899-5656",
    "wof:placetype":"postalcode"
},
  "geometry": {"coordinates":[130.6019,31.7315],"type":"Point"}
}