{
  "type": "Feature",
  "properties": {
    "gn:adm1_name":"Chibaken",
    "gn:adm2_name":"Ichiharashi",
    "gn:name":"Uehara",
    "iso:country":"JP",
    "wof:name":"290-0222",
    "wof:placetype":"postalcode"
},
  "geometry": {"coordinates":[140.1234,35.4212],"type":"Point"}
}