{
  "type": "Feature",
  "properties": {
    "gn:adm1_name":"Ibarakiken",
    "gn:adm2_name":"Kashimagunkamisumachi",
    "gn:name":"Oonohara",
    "iso:country":"JP",
    "wof:name":"314-0144",
    "wof:placetype":"postalcode"
},
  "geometry": {"coordinates":[140.64590000000001,35.8925],"type":"Point"}
}