{
  "type": "Feature",
  "properties": {
    "gn:adm1_name":"Toyamaken",
    "gn:adm2_name":"Toyamashi",
    "gn:name":"Sakaemachi",
    "iso:country":"JP",
    "wof:name":"930-0032",
    "wof:placetype":"postalcode"
},
  "geometry": {"coordinates":[137.232,36.6918],"type":"Point"}
}