{
  "type": "Feature",
  "properties": {
    "gn:adm1_name":"Hyougoken",
    "gn:adm2_name":"Koubeshihigashinadaku",
    "gn:name":"Mikagenakamachi",
    "iso:country":"JP",
    "wof:name":"658-0054",
    "wof:placetype":"postalcode"
},
  "geometry": {"coordinates":[135.255,34.7169],"type":"Point"}
}