{
  "type": "Feature",
  "properties": {
    "gn:adm1_name":"Hiroshimaken",
    "gn:adm2_name":"Kureshi",
    "gn:name":"Tennoushioyachou",
    "iso:country":"JP",
    "wof:name":"737-0881",
    "wof:placetype":"postalcode"
},
  "geometry": {"coordinates":[132.52019999999999,34.2828],"type":"Point"}
}