{
  "type": "Feature",
  "properties": {
    "gn:adm1_name":"Saitamaken",
    "gn:adm2_name":"Oosatogunyoriimachi",
    "gn:name":"Murei",
    "iso:country":"JP",
    "wof:name":"369-1215",
    "wof:placetype":"postalcode"
},
  "geometry": {"coordinates":[139.2533,36.1019],"type":"Point"}
}