{
  "type": "Feature",
  "properties": {
    "gn:adm1_name":"Aichiken",
    "gn:adm2_name":"Nagoyashiminamiku",
    "gn:name":"Doutokushinmachi",
    "iso:country":"JP",
    "wof:name":"457-0847",
    "wof:placetype":"postalcode"
},
  "geometry": {"coordinates":[136.9067,35.1034],"type":"Point"}
}