{
  "type": "Feature",
  "properties": {
    "gn:adm1_name":"Kyoutofu",
    "gn:adm2_name":"Kyoutoshiminamiku",
    "gn:name":"Kuzetakadachou",
    "iso:country":"JP",
    "wof:name":"601-8211",
    "wof:placetype":"postalcode"
},
  "geometry": {"coordinates":[135.7063,34.9647],"type":"Point"}
}