{
  "type": "Feature",
  "properties": {
    "gn:adm1_name":"Gifuken",
    "gn:adm2_name":"Yoshikigunkamiokachou",
    "gn:name":"Maki",
    "iso:country":"JP",
    "wof:name":"506-1214",
    "wof:placetype":"postalcode"
},
  "geometry": {"coordinates":[137.29519999999999,36.4018],"type":"Point"}
}