{
  "type": "Feature",
  "properties": {
    "gn:adm1_name":"Naganoken",
    "gn:adm2_name":"Suzakashi",
    "gn:name":"Natsubatachou",
    "iso:country":"JP",
    "wof:name":"382-0032",
    "wof:placetype":"postalcode"
},
  "geometry": {"coordinates":[138.3339,36.6224],"type":"Point"}
}