{
  "type": "Feature",
  "properties": {
    "gn:adm1_name":"Aichiken",
    "gn:adm2_name":"Nagoyashinakagawaku",
    "gn:name":"Todanishi",
    "iso:country":"JP",
    "wof:name":"454-0967",
    "wof:placetype":"postalcode"
},
  "geometry": {"coordinates":[136.80240000000001,35.1377],"type":"Point"}
}