{
  "type": "Feature",
  "properties": {
    "gn:adm1_name":"Niigataken",
    "gn:adm2_name":"Nagaokashi",
    "gn:name":"Imai",
    "iso:country":"JP",
    "wof:name":"940-1166",
    "wof:placetype":"postalcode"
},
  "geometry": {"coordinates":[138.8295,37.4252],"type":"Point"}
}