{
  "type": "Feature",
  "properties": {
    "gn:adm1_name":"Gunmaken",
    "gn:adm2_name":"Ouragunchiyodamachi",
    "gn:name":"Nabeya",
    "iso:country":"JP",
    "wof:name":"370-0502",
    "wof:placetype":"postalcode"
},
  "geometry": {"coordinates":[139.4529,36.2158],"type":"Point"}
}