{
  "type": "Feature",
  "properties": {
    "gn:adm1_name":"Kanagawaken",
    "gn:adm2_name":"Sagamiharashi",
    "gn:name":"Sagamihara",
    "iso:country":"JP",
    "wof:name":"229-0031",
    "wof:placetype":"postalcode"
},
  "geometry": {"coordinates":[139.37139999999999,35.5781],"type":"Point"}
}