{
  "type": "Feature",
  "properties": {
    "gn:adm1_name":"Gifuken",
    "gn:adm2_name":"Hashimagunginanchou",
    "gn:name":"Miyamachi",
    "iso:country":"JP",
    "wof:name":"501-6019",
    "wof:placetype":"postalcode"
},
  "geometry": {"coordinates":[136.77350000000001,35.3927],"type":"Point"}
}