{
  "type": "Feature",
  "properties": {
    "gn:adm1_name":"Hiroshimaken",
    "gn:adm2_name":"Mitsugigunmitsugichou",
    "gn:name":"Suge",
    "iso:country":"JP",
    "wof:name":"722-0334",
    "wof:placetype":"postalcode"
},
  "geometry": {"coordinates":[133.18530000000001,34.5146],"type":"Point"}
}