{
  "type": "Feature",
  "properties": {
    "gn:adm1_name":"Aichiken",
    "gn:adm2_name":"Nagoyashimeitouku",
    "gn:name":"Itsusha",
    "iso:country":"JP",
    "wof:name":"465-0093",
    "wof:placetype":"postalcode"
},
  "geometry": {"coordinates":[136.99950000000001,35.1673],"type":"Point"}
}