{
  "type": "Feature",
  "properties": {
    "gn:adm1_name":"Miyagiken",
    "gn:adm2_name":"Sendaishitaihakuku",
    "gn:name":"Hatatate",
    "iso:country":"JP",
    "wof:name":"982-0215",
    "wof:placetype":"postalcode"
},
  "geometry": {"coordinates":[140.81209999999999,38.2258],"type":"Point"}
}