{
  "type": "Feature",
  "properties": {
    "gn:adm1_name":"Saitamaken",
    "gn:adm2_name":"Kukishi",
    "gn:name":"Kamikiyoku",
    "iso:country":"JP",
    "wof:name":"346-0038",
    "wof:placetype":"postalcode"
},
  "geometry": {"coordinates":[139.64689999999999,36.0802],"type":"Point"}
}