{
  "type": "Feature",
  "properties": {
    "gn:adm1_name":"Ishikawaken",
    "gn:adm2_name":"Kahokugunnanatsukamachi",
    "gn:name":"Matsuhama",
    "iso:country":"JP",
    "wof:name":"929-1172",
    "wof:placetype":"postalcode"
},
  "geometry": {"coordinates":[136.70429999999999,36.7436],"type":"Point"}
}