{
  "type": "Feature",
  "properties": {
    "gn:adm1_name":"Ishikawaken",
    "gn:adm2_name":"Fugeshigun'Anamizumachi",
    "gn:name":"Takeda",
    "iso:country":"JP",
    "wof:name":"927-0201",
    "wof:placetype":"postalcode"
},
  "geometry": {"coordinates":[137.0744,37.2488],"type":"Point"}
}