{
  "type": "Feature",
  "properties": {
    "gn:adm1_name":"Hyougoken",
    "gn:adm2_name":"Asagogunwadayamachou",
    "gn:name":"Hirano",
    "iso:country":"JP",
    "wof:name":"669-5211",
    "wof:placetype":"postalcode"
},
  "geometry": {"coordinates":[134.84309999999999,35.3419],"type":"Point"}
}