{
  "type": "Feature",
  "properties": {
    "gn:adm1_name":"Ibarakiken",
    "gn:adm2_name":"Sashimagunsouwamachi",
    "gn:name":"Kazurou",
    "iso:country":"JP",
    "wof:name":"306-0211",
    "wof:placetype":"postalcode"
},
  "geometry": {"coordinates":[139.78739999999999,36.1632],"type":"Point"}
}