{
  "type": "Feature",
  "properties": {
    "gn:adm1_name":"Kumamotoken",
    "gn:adm2_name":"Amakusagunreihokumachi",
    "gn:name":"Toshikara",
    "iso:country":"JP",
    "wof:name":"863-2504",
    "wof:placetype":"postalcode"
},
  "geometry": {"coordinates":[130.04900000000001,32.4853],"type":"Point"}
}