{
  "type": "Feature",
  "properties": {
    "gn:adm1_name":"Shigaken",
    "gn:adm2_name":"Ikagunkinomotochou",
    "gn:name":"Tabe",
    "iso:country":"JP",
    "wof:name":"529-0422",
    "wof:placetype":"postalcode"
},
  "geometry": {"coordinates":[136.2319,35.5008],"type":"Point"}
}