{
  "type": "Feature",
  "properties": {
    "gn:adm1_name":"Fukushimaken",
    "gn:adm2_name":"Kooriyamashi",
    "gn:name":"Ousemachikouzu",
    "iso:country":"JP",
    "wof:name":"963-0212",
    "wof:placetype":"postalcode"
},
  "geometry": {"coordinates":[140.27699999999999,37.4193],"type":"Point"}
}