{
  "type": "Feature",
  "properties": {
    "gn:adm1_name":"Aichiken",
    "gn:adm2_name":"Toyokawashi",
    "gn:name":"Toukouchou",
    "iso:country":"JP",
    "wof:name":"442-0022",
    "wof:placetype":"postalcode"
},
  "geometry": {"coordinates":[137.39529999999999,34.8304],"type":"Point"}
}