{
  "type": "Feature",
  "properties": {
    "gn:adm1_name":"Fukushimaken",
    "gn:adm2_name":"Sukagawashi",
    "gn:name":"Oroshimachi",
    "iso:country":"JP",
    "wof:name":"962-0053",
    "wof:placetype":"postalcode"
},
  "geometry": {"coordinates":[140.35769999999999,37.2933],"type":"Point"}
}