{
  "type": "Feature",
  "properties": {
    "gn:adm1_name":"Tochigiken",
    "gn:adm2_name":"Hagagunmotegimachi",
    "gn:name":"Oume",
    "iso:country":"JP",
    "wof:name":"321-3534",
    "wof:placetype":"postalcode"
},
  "geometry": {"coordinates":[140.2336,36.5179],"type":"Point"}
}