{
  "type": "Feature",
  "properties": {
    "gn:adm1_name":"Kyoutofu",
    "gn:adm2_name":"Kyoutoshikamigyouku",
    "gn:name":"Higashiuoyachou",
    "iso:country":"JP",
    "wof:name":"602-8038",
    "wof:placetype":"postalcode"
},
  "geometry": {"coordinates":[135.7542,35.0187],"type":"Point"}
}