{
  "type": "Feature",
  "properties": {
    "gn:adm1_name":"Fukuokaken",
    "gn:adm2_name":"Yukuhashishi",
    "gn:name":"Kitaizumi",
    "iso:country":"JP",
    "wof:name":"824-0033",
    "wof:placetype":"postalcode"
},
  "geometry": {"coordinates":[130.98599999999999,33.717],"type":"Point"}
}