{
  "type": "Feature",
  "properties": {
    "gn:adm1_name":"Fukushimaken",
    "gn:adm2_name":"Sukagawashi",
    "gn:name":"Ookanbara",
    "iso:country":"JP",
    "wof:name":"962-0056",
    "wof:placetype":"postalcode"
},
  "geometry": {"coordinates":[140.31710000000001,37.2959],"type":"Point"}
}