{
  "type": "Feature",
  "properties": {
    "gn:adm1_name":"Aichiken",
    "gn:adm2_name":"Toyotashi",
    "gn:name":"Chidorichou",
    "iso:country":"JP",
    "wof:name":"470-0316",
    "wof:placetype":"postalcode"
},
  "geometry": {"coordinates":[137.24199999999999,35.1269],"type":"Point"}
}