{
  "type": "Feature",
  "properties": {
    "gn:adm1_name":"Aichiken",
    "gn:adm2_name":"Kounanshi",
    "gn:name":"Kochinochoutakase",
    "iso:country":"JP",
    "wof:name":"483-8331",
    "wof:placetype":"postalcode"
},
  "geometry": {"coordinates":[136.86779999999999,35.3442],"type":"Point"}
}