{
  "type": "Feature",
  "properties": {
    "gn:adm1_name":"Fukuiken",
    "gn:adm2_name":"Katsuyamashi",
    "gn:name":"Sakaemachi",
    "iso:country":"JP",
    "wof:name":"911-0033",
    "wof:placetype":"postalcode"
},
  "geometry": {"coordinates":[136.4967,36.0643],"type":"Point"}
}