{
  "type": "Feature",
  "properties": {
    "gn:adm1_name":"Kyoutofu",
    "gn:adm2_name":"Kyoutoshiukyouku",
    "gn:name":"Sagashakadoumonzen'Urayanagichou",
    "iso:country":"JP",
    "wof:name":"616-8423",
    "wof:placetype":"postalcode"
},
  "geometry": {"coordinates":[135.67449999999999,35.0204],"type":"Point"}
}