{
  "type": "Feature",
  "properties": {
    "gn:adm1_name":"Shimaneken",
    "gn:adm2_name":"Izumoshi",
    "gn:name":"Imaichichouminamihonmachi",
    "iso:country":"JP",
    "wof:name":"693-0003",
    "wof:placetype":"postalcode"
},
  "geometry": {"coordinates":[132.75919999999999,35.3582],"type":"Point"}
}