{
  "type": "Feature",
  "properties": {
    "gn:adm1_name":"Aichiken",
    "gn:adm2_name":"Aichiguntougouchou",
    "gn:name":"Wagou",
    "iso:country":"JP",
    "wof:name":"470-0153",
    "wof:placetype":"postalcode"
},
  "geometry": {"coordinates":[137.04929999999999,35.1042],"type":"Point"}
}