{
  "type": "Feature",
  "properties": {
    "gn:adm1_name":"Aichiken",
    "gn:adm2_name":"Toyotashi",
    "gn:name":"Sachihodai",
    "iso:country":"JP",
    "wof:name":"444-2226",
    "wof:placetype":"postalcode"
},
  "geometry": {"coordinates":[137.22989999999999,35.0835],"type":"Point"}
}