{
  "type": "Feature",
  "properties": {
    "gn:adm1_name":"Kagoshimaken",
    "gn:adm2_name":"Kagoshimashi",
    "gn:name":"Jiyuugaoka",
    "iso:country":"JP",
    "wof:name":"891-0106",
    "wof:placetype":"postalcode"
},
  "geometry": {"coordinates":[130.512,31.5415],"type":"Point"}
}