{
  "type": "Feature",
  "properties": {
    "gn:adm1_name":"Fukushimaken",
    "gn:adm2_name":"Nishishirakawagun'Omotegoumura",
    "gn:name":"Yashiroda",
    "iso:country":"JP",
    "wof:name":"961-0404",
    "wof:placetype":"postalcode"
},
  "geometry": {"coordinates":[140.28319999999999,37.0725],"type":"Point"}
}