{
  "type": "Feature",
  "properties": {
    "gn:adm1_name":"Aichiken",
    "gn:adm2_name":"Tsushimashi",
    "gn:name":"Yokomachi",
    "iso:country":"JP",
    "wof:name":"496-0841",
    "wof:placetype":"postalcode"
},
  "geometry": {"coordinates":[136.7242,35.1768],"type":"Point"}
}