{
  "type": "Feature",
  "properties": {
    "gn:adm1_name":"Chibaken",
    "gn:adm2_name":"Chibashimidoriku",
    "gn:name":"Kamioowadachou",
    "iso:country":"JP",
    "wof:name":"267-0051",
    "wof:placetype":"postalcode"
},
  "geometry": {"coordinates":[140.279,35.5529],"type":"Point"}
}