{
  "type": "Feature",
  "properties": {
    "gn:adm1_name":"Hiroshimaken",
    "gn:adm2_name":"Hiroshimashiminamiku",
    "gn:name":"Minamikaniya",
    "iso:country":"JP",
    "wof:name":"732-0803",
    "wof:placetype":"postalcode"
},
  "geometry": {"coordinates":[132.48509999999999,34.3898],"type":"Point"}
}