{
  "type": "Feature",
  "properties": {
    "gn:adm1_name":"Kagoshimaken",
    "gn:adm2_name":"Kimotsukigunhigashikushirachou",
    "gn:name":"Ikanikeisaiganaibaai",
    "iso:country":"JP",
    "wof:name":"893-1600",
    "wof:placetype":"postalcode"
},
  "geometry": {"coordinates":[130.98419999999999,31.3842],"type":"Point"}
}