{
  "type": "Feature",
  "properties": {
    "gn:adm1_name":"Kagawaken",
    "gn:adm2_name":"Ayautagun'Utaduchou",
    "gn:name":"Hama4banchou",
    "iso:country":"JP",
    "wof:name":"769-0204",
    "wof:placetype":"postalcode"
},
  "geometry": {"coordinates":[133.81569999999999,34.3117],"type":"Point"}
}