{
  "type": "Feature",
  "properties": {
    "gn:adm1_name":"Shimaneken",
    "gn:adm2_name":"Kanoashigunmuikaichichou",
    "gn:name":"Sawada",
    "iso:country":"JP",
    "wof:name":"699-5516",
    "wof:placetype":"postalcode"
},
  "geometry": {"coordinates":[131.92179999999999,34.3463],"type":"Point"}
}