{
  "type": "Feature",
  "properties": {
    "gn:adm1_name":"Fukushimaken",
    "gn:adm2_name":"Tamuragunmiharumachi",
    "gn:name":"Fukadawa",
    "iso:country":"JP",
    "wof:name":"963-7773",
    "wof:placetype":"postalcode"
},
  "geometry": {"coordinates":[140.48560000000001,37.4555],"type":"Point"}
}