{
  "type": "Feature",
  "properties": {
    "gn:adm1_name":"Miyagiken",
    "gn:adm2_name":"Shiogamashi",
    "gn:name":"Shinhamachou",
    "iso:country":"JP",
    "wof:name":"985-0001",
    "wof:placetype":"postalcode"
},
  "geometry": {"coordinates":[141.0428,38.3292],"type":"Point"}
}