{
  "type": "Feature",
  "properties": {
    "gn:adm1_name":"Hyougoken",
    "gn:adm2_name":"Koubeshihyougoku",
    "gn:name":"Shimagamichou",
    "iso:country":"JP",
    "wof:name":"652-0833",
    "wof:placetype":"postalcode"
},
  "geometry": {"coordinates":[135.17609999999999,34.6688],"type":"Point"}
}