{
  "type": "Feature",
  "properties": {
    "gn:adm1_name":"Hiroshimaken",
    "gn:adm2_name":"Kureshi",
    "gn:name":"Hiroishiuchi",
    "iso:country":"JP",
    "wof:name":"737-0101",
    "wof:placetype":"postalcode"
},
  "geometry": {"coordinates":[132.63290000000001,34.2668],"type":"Point"}
}