{
  "type": "Feature",
  "properties": {
    "gn:adm1_name":"Niigataken",
    "gn:adm2_name":"Sanjoushi",
    "gn:name":"Yoshida",
    "iso:country":"JP",
    "wof:name":"955-0805",
    "wof:placetype":"postalcode"
},
  "geometry": {"coordinates":[138.96780000000001,37.599],"type":"Point"}
}