{
  "type": "Feature",
  "properties": {
    "gn:adm1_name":"Ibarakiken",
    "gn:adm2_name":"Tsukubashi",
    "gn:name":"Nishihara",
    "iso:country":"JP",
    "wof:name":"305-0815",
    "wof:placetype":"postalcode"
},
  "geometry": {"coordinates":[140.07990000000001,36.1034],"type":"Point"}
}