{
  "type": "Feature",
  "properties": {
    "gn:adm1_name":"Hyougoken",
    "gn:adm2_name":"Amagasakishi",
    "gn:name":"Kitatakeyachou",
    "iso:country":"JP",
    "wof:name":"660-0878",
    "wof:placetype":"postalcode"
},
  "geometry": {"coordinates":[135.40520000000001,34.7206],"type":"Point"}
}