{
  "type": "Feature",
  "properties": {
    "gn:adm1_name":"Ishikawaken",
    "gn:adm2_name":"Komatsushi",
    "gn:name":"Shindaikuchou",
    "iso:country":"JP",
    "wof:name":"923-0906",
    "wof:placetype":"postalcode"
},
  "geometry": {"coordinates":[136.44630000000001,36.4068],"type":"Point"}
}