{
  "type": "Feature",
  "properties": {
    "gn:adm1_name":"Tokushimaken",
    "gn:adm2_name":"Tokushimashi",
    "gn:name":"Sakaemachi",
    "iso:country":"JP",
    "wof:name":"770-0921",
    "wof:placetype":"postalcode"
},
  "geometry": {"coordinates":[134.5487,34.0646],"type":"Point"}
}