{
  "type": "Feature",
  "properties": {
    "gn:adm1_name":"Hyougoken",
    "gn:adm2_name":"Koubeshihigashinadaku",
    "gn:name":"Ougi",
    "iso:country":"JP",
    "wof:name":"658-0027",
    "wof:placetype":"postalcode"
},
  "geometry": {"coordinates":[135.2833,34.7167],"type":"Point"}
}