{
  "type": "Feature",
  "properties": {
    "gn:adm1_name":"Hyougoken",
    "gn:adm2_name":"Himejishi",
    "gn:name":"Aboshikutsuichiba",
    "iso:country":"JP",
    "wof:name":"671-1224",
    "wof:placetype":"postalcode"
},
  "geometry": {"coordinates":[134.58250000000001,34.7975],"type":"Point"}
}