{
  "type": "Feature",
  "properties": {
    "gn:adm1_name":"Miyazakiken",
    "gn:adm2_name":"Kitamorokataguntakajouchou",
    "gn:name":"Shika",
    "iso:country":"JP",
    "wof:name":"885-1312",
    "wof:placetype":"postalcode"
},
  "geometry": {"coordinates":[131.1867,31.9208],"type":"Point"}
}