{
  "type": "Feature",
  "properties": {
    "gn:adm1_name":"Oosakafu",
    "gn:adm2_name":"Oosakashisuminoeku",
    "gn:name":"Higashikagaya",
    "iso:country":"JP",
    "wof:name":"559-0012",
    "wof:placetype":"postalcode"
},
  "geometry": {"coordinates":[135.48330000000001,34.6168],"type":"Point"}
}