{
  "type": "Feature",
  "properties": {
    "gn:adm1_name":"Kyoutofu",
    "gn:adm2_name":"Kyoutoshikamigyouku",
    "gn:name":"Nishisenbonchou",
    "iso:country":"JP",
    "wof:name":"602-8404",
    "wof:placetype":"postalcode"
},
  "geometry": {"coordinates":[135.7467,35.0346],"type":"Point"}
}