{
  "type": "Feature",
  "properties": {
    "gn:adm1_name":"Aichiken",
    "gn:adm2_name":"Kounanshi",
    "gn:name":"Higashinochoukomeno",
    "iso:country":"JP",
    "wof:name":"483-8418",
    "wof:placetype":"postalcode"
},
  "geometry": {"coordinates":[136.85740000000001,35.3359],"type":"Point"}
}