{
  "type": "Feature",
  "properties": {
    "gn:adm1_name":"Oosakafu",
    "gn:adm2_name":"Higashioosakashi",
    "gn:name":"Kashitahigashimachi",
    "iso:country":"JP",
    "wof:name":"577-0833",
    "wof:placetype":"postalcode"
},
  "geometry": {"coordinates":[135.57380000000001,34.6471],"type":"Point"}
}