{
  "type": "Feature",
  "properties": {
    "gn:adm1_name":"Niigataken",
    "gn:adm2_name":"Niigatashi",
    "gn:name":"Hiraga",
    "iso:country":"JP",
    "wof:name":"950-0329",
    "wof:placetype":"postalcode"
},
  "geometry": {"coordinates":[139.0395,37.8447],"type":"Point"}
}