{
  "type": "Feature",
  "properties": {
    "gn:adm1_name":"Ishikawaken",
    "gn:adm2_name":"Fugeshigunmonzenmachi",
    "gn:name":"Ohae",
    "iso:country":"JP",
    "wof:name":"927-2163",
    "wof:placetype":"postalcode"
},
  "geometry": {"coordinates":[136.7533,37.2725],"type":"Point"}
}