{
  "type": "Feature",
  "properties": {
    "gn:adm1_name":"Tottoriken",
    "gn:adm2_name":"Kurayoshishi",
    "gn:name":"Kazuwa",
    "iso:country":"JP",
    "wof:name":"682-0902",
    "wof:placetype":"postalcode"
},
  "geometry": {"coordinates":[133.79669999999999,35.4566],"type":"Point"}
}