{
  "type": "Feature",
  "properties": {
    "gn:adm1_name":"Ibarakiken",
    "gn:adm2_name":"Shimodateshi",
    "gn:name":"Shimonodono",
    "iso:country":"JP",
    "wof:name":"308-0844",
    "wof:placetype":"postalcode"
},
  "geometry": {"coordinates":[139.97190000000001,36.2696],"type":"Point"}
}