{
  "type": "Feature",
  "properties": {
    "gn:adm1_name":"Kyoutofu",
    "gn:adm2_name":"Kyoutoshisakyouku",
    "gn:name":"Hanaseharachichou",
    "iso:country":"JP",
    "wof:name":"601-1102",
    "wof:placetype":"postalcode"
},
  "geometry": {"coordinates":[135.7801,35.2352],"type":"Point"}
}