{
  "type": "Feature",
  "properties": {
    "gn:adm1_name":"Tottoriken",
    "gn:adm2_name":"Yazugunchiduchou",
    "gn:name":"Shinozaka",
    "iso:country":"JP",
    "wof:name":"689-1417",
    "wof:placetype":"postalcode"
},
  "geometry": {"coordinates":[134.25550000000001,35.2609],"type":"Point"}
}