{
  "type": "Feature",
  "properties": {
    "gn:adm1_name":"Shimaneken",
    "gn:adm2_name":"Hamadashi",
    "gn:name":"Sanochou",
    "iso:country":"JP",
    "wof:name":"697-0311",
    "wof:placetype":"postalcode"
},
  "geometry": {"coordinates":[132.1626,34.888],"type":"Point"}
}