{
  "type": "Feature",
  "properties": {
    "gn:adm1_name":"Saitamaken",
    "gn:adm2_name":"Kitasaitamagunkitakawabemachi",
    "gn:name":"Youkoudai",
    "iso:country":"JP",
    "wof:name":"349-1204",
    "wof:placetype":"postalcode"
},
  "geometry": {"coordinates":[139.68350000000001,36.1917],"type":"Point"}
}