{
  "type": "Feature",
  "properties": {
    "gn:adm1_name":"Okinawaken",
    "gn:adm2_name":"Nagoshi",
    "gn:name":"Miyazato",
    "iso:country":"JP",
    "wof:name":"905-0011",
    "wof:placetype":"postalcode"
},
  "geometry": {"coordinates":[127.9729,26.5987],"type":"Point"}
}