{
  "type": "Feature",
  "properties": {
    "gn:adm1_name":"Aichiken",
    "gn:adm2_name":"Chitashi",
    "gn:name":"Midorimachi",
    "iso:country":"JP",
    "wof:name":"478-0047",
    "wof:placetype":"postalcode"
},
  "geometry": {"coordinates":[136.8639,34.9957],"type":"Point"}
}