{
  "type": "Feature",
  "properties": {
    "gn:adm1_name":"Aichiken",
    "gn:adm2_name":"Nagoyashikitaku",
    "gn:name":"Yadachou",
    "iso:country":"JP",
    "wof:name":"462-0812",
    "wof:placetype":"postalcode"
},
  "geometry": {"coordinates":[136.94139999999999,35.2006],"type":"Point"}
}