{
  "type": "Feature",
  "properties": {
    "gn:adm1_name":"Toyamaken",
    "gn:adm2_name":"Toyamashi",
    "gn:name":"Awajimamachi",
    "iso:country":"JP",
    "wof:name":"931-8314",
    "wof:placetype":"postalcode"
},
  "geometry": {"coordinates":[137.22829999999999,36.7221],"type":"Point"}
}