{
  "type": "Feature",
  "properties": {
    "gn:adm1_name":"Kyoutofu",
    "gn:adm2_name":"Kyoutoshifushimiku",
    "gn:name":"Ogurisukosakachou",
    "iso:country":"JP",
    "wof:name":"601-1455",
    "wof:placetype":"postalcode"
},
  "geometry": {"coordinates":[135.80080000000001,34.9469],"type":"Point"}
}