{
  "type": "Feature",
  "properties": {
    "gn:adm1_name":"Okinawaken",
    "gn:adm2_name":"Shimajirigunsashikichou",
    "gn:name":"Fusozaki",
    "iso:country":"JP",
    "wof:name":"901-1404",
    "wof:placetype":"postalcode"
},
  "geometry": {"coordinates":[127.794,26.1764],"type":"Point"}
}