{
  "type": "Feature",
  "properties": {
    "gn:adm1_name":"Toukyouto",
    "gn:adm2_name":"Meguroku",
    "gn:name":"Haramachi",
    "iso:country":"JP",
    "wof:name":"152-0011",
    "wof:placetype":"postalcode"
},
  "geometry": {"coordinates":[139.69470000000001,35.6163],"type":"Point"}
}