{
  "type": "Feature",
  "properties": {
    "gn:adm1_name":"Fukuokaken",
    "gn:adm2_name":"Yanagawashi",
    "gn:name":"Motofunatsumachi",
    "iso:country":"JP",
    "wof:name":"832-0018",
    "wof:placetype":"postalcode"
},
  "geometry": {"coordinates":[130.4059,33.1717],"type":"Point"}
}