{
  "type": "Feature",
  "properties": {
    "gn:adm1_name":"Tokushimaken",
    "gn:adm2_name":"Kaifugunshishikuichou",
    "gn:name":"Kuo",
    "iso:country":"JP",
    "wof:name":"775-0511",
    "wof:placetype":"postalcode"
},
  "geometry": {"coordinates":[134.215,33.5955],"type":"Point"}
}