{
  "type": "Feature",
  "properties": {
    "gn:adm1_name":"Oosakafu",
    "gn:adm2_name":"Fujiiderashi",
    "gn:name":"Houjouchou",
    "iso:country":"JP",
    "wof:name":"583-0002",
    "wof:placetype":"postalcode"
},
  "geometry": {"coordinates":[135.61869999999999,34.579],"type":"Point"}
}