{
  "type": "Feature",
  "properties": {
    "gn:adm1_name":"Aichiken",
    "gn:adm2_name":"Nagoyashimoriyamaku",
    "gn:name":"Kitayama",
    "iso:country":"JP",
    "wof:name":"463-0017",
    "wof:placetype":"postalcode"
},
  "geometry": {"coordinates":[136.98939999999999,35.2061],"type":"Point"}
}