{
  "type": "Feature",
  "properties": {
    "gn:adm1_name":"Kyoutofu",
    "gn:adm2_name":"Kyoutoshifushimiku",
    "gn:name":"Daigokarasubashichou",
    "iso:country":"JP",
    "wof:name":"601-1315",
    "wof:placetype":"postalcode"
},
  "geometry": {"coordinates":[135.81960000000001,34.9566],"type":"Point"}
}