{
  "type": "Feature",
  "properties": {
    "gn:adm1_name":"Hyougoken",
    "gn:adm2_name":"Sayougunsayouchou",
    "gn:name":"Nobuyoshi",
    "iso:country":"JP",
    "wof:name":"679-5332",
    "wof:placetype":"postalcode"
},
  "geometry": {"coordinates":[134.3648,35.0582],"type":"Point"}
}