{
  "type": "Feature",
  "properties": {
    "gn:adm1_name":"Naganoken",
    "gn:adm2_name":"Kitasakuguntateshinamachi",
    "gn:name":"Motai(Sonota)",
    "iso:country":"JP",
    "wof:name":"384-2211",
    "wof:placetype":"postalcode"
},
  "geometry": {"coordinates":[138.33199999999999,36.2704],"type":"Point"}
}