{
  "type": "Feature",
  "properties": {
    "gn:adm1_name":"Naganoken",
    "gn:adm2_name":"Iiyamashi",
    "gn:name":"Mizuho",
    "iso:country":"JP",
    "wof:name":"389-2322",
    "wof:placetype":"postalcode"
},
  "geometry": {"coordinates":[138.41560000000001,36.8877],"type":"Point"}
}