{
  "type": "Feature",
  "properties": {
    "gn:adm1_name":"Fukushimaken",
    "gn:adm2_name":"Kooriyamashi",
    "gn:name":"Arayashiki",
    "iso:country":"JP",
    "wof:name":"963-8045",
    "wof:placetype":"postalcode"
},
  "geometry": {"coordinates":[140.3563,37.4182],"type":"Point"}
}