{
  "type": "Feature",
  "properties": {
    "gn:adm1_name":"Fukuokaken",
    "gn:adm2_name":"Fukuokashihigashiku",
    "gn:name":"Tanotsu",
    "iso:country":"JP",
    "wof:name":"813-0034",
    "wof:placetype":"postalcode"
},
  "geometry": {"coordinates":[130.44890000000001,33.6249],"type":"Point"}
}