{
  "type": "Feature",
  "properties": {
    "gn:adm1_name":"Hyougoken",
    "gn:adm2_name":"Himejishi",
    "gn:name":"Besshochoukobayashi",
    "iso:country":"JP",
    "wof:name":"671-0222",
    "wof:placetype":"postalcode"
},
  "geometry": {"coordinates":[134.76060000000001,34.7993],"type":"Point"}
}