{
  "type": "Feature",
  "properties": {
    "gn:adm1_name":"Yamaguchiken",
    "gn:adm2_name":"Abugun'Atouchou",
    "gn:name":"Shinome",
    "iso:country":"JP",
    "wof:name":"759-1232",
    "wof:placetype":"postalcode"
},
  "geometry": {"coordinates":[131.55629999999999,34.2811],"type":"Point"}
}