{
  "type": "Feature",
  "properties": {
    "gn:adm1_name":"Fukuokaken",
    "gn:adm2_name":"Munakatashi",
    "gn:name":"Jougatani",
    "iso:country":"JP",
    "wof:name":"811-4182",
    "wof:placetype":"postalcode"
},
  "geometry": {"coordinates":[130.5532,33.8072],"type":"Point"}
}