{
  "type": "Feature",
  "properties": {
    "gn:adm1_name":"Yamaguchiken",
    "gn:adm2_name":"Shimonosekishi",
    "gn:name":"Matsuya",
    "iso:country":"JP",
    "wof:name":"750-1121",
    "wof:placetype":"postalcode"
},
  "geometry": {"coordinates":[131.078,34.0639],"type":"Point"}
}