{
  "type": "Feature",
  "properties": {
    "gn:adm1_name":"Nagasakiken",
    "gn:adm2_name":"Ikigungounourachou",
    "gn:name":"Higashifure",
    "iso:country":"JP",
    "wof:name":"811-5132",
    "wof:placetype":"postalcode"
},
  "geometry": {"coordinates":[129.70009999999999,33.7549],"type":"Point"}
}