{
  "type": "Feature",
  "properties": {
    "gn:adm1_name":"Ishikawaken",
    "gn:adm2_name":"Komatsushi",
    "gn:name":"Tenjinmachi",
    "iso:country":"JP",
    "wof:name":"923-0025",
    "wof:placetype":"postalcode"
},
  "geometry": {"coordinates":[136.4504,36.4175],"type":"Point"}
}