{
  "type": "Feature",
  "properties": {
    "gn:adm1_name":"Ibarakiken",
    "gn:adm2_name":"Tsukubashi",
    "gn:name":"Teshirogi",
    "iso:country":"JP",
    "wof:name":"305-0834",
    "wof:placetype":"postalcode"
},
  "geometry": {"coordinates":[140.1001,36.0602],"type":"Point"}
}