{
  "type": "Feature",
  "properties": {
    "gn:adm1_name":"Mieken",
    "gn:adm2_name":"Kuwanashi",
    "gn:name":"Tsukushi",
    "iso:country":"JP",
    "wof:name":"511-0945",
    "wof:placetype":"postalcode"
},
  "geometry": {"coordinates":[136.61170000000001,35.072],"type":"Point"}
}