{
  "type": "Feature",
  "properties": {
    "gn:adm1_name":"Hyougoken",
    "gn:adm2_name":"Sasayamashi",
    "gn:name":"Kuwabara",
    "iso:country":"JP",
    "wof:name":"669-2703",
    "wof:placetype":"postalcode"
},
  "geometry": {"coordinates":[135.25020000000001,35.1698],"type":"Point"}
}