{
  "type": "Feature",
  "properties": {
    "gn:adm1_name":"Sagaken",
    "gn:adm2_name":"Kanzakigunkanzakimachi",
    "gn:name":"Motoorimuta",
    "iso:country":"JP",
    "wof:name":"842-0013",
    "wof:placetype":"postalcode"
},
  "geometry": {"coordinates":[130.36429999999999,33.2979],"type":"Point"}
}