{
  "type": "Feature",
  "properties": {
    "gn:adm1_name":"Fukushimaken",
    "gn:adm2_name":"Kooriyamashi",
    "gn:name":"Tamuramachiyadagawa",
    "iso:country":"JP",
    "wof:name":"963-1246",
    "wof:placetype":"postalcode"
},
  "geometry": {"coordinates":[140.44470000000001,37.3147],"type":"Point"}
}