{
  "type": "Feature",
  "properties": {
    "gn:adm1_name":"Kyoutofu",
    "gn:adm2_name":"Yawatashi",
    "gn:name":"Yawatanagori",
    "iso:country":"JP",
    "wof:name":"614-8023",
    "wof:placetype":"postalcode"
},
  "geometry": {"coordinates":[135.71119999999999,34.8802],"type":"Point"}
}