{
  "type": "Feature",
  "properties": {
    "gn:adm1_name":"Toukyouto",
    "gn:adm2_name":"Ootaku",
    "gn:name":"Toukai",
    "iso:country":"JP",
    "wof:name":"143-0001",
    "wof:placetype":"postalcode"
},
  "geometry": {"coordinates":[139.76300000000001,35.5832],"type":"Point"}
}