{
  "type": "Feature",
  "properties": {
    "gn:adm1_name":"Aichiken",
    "gn:adm2_name":"Higashikamogun'Asukechou",
    "gn:name":"Asuke",
    "iso:country":"JP",
    "wof:name":"444-2424",
    "wof:placetype":"postalcode"
},
  "geometry": {"coordinates":[137.31790000000001,35.1361],"type":"Point"}
}