{
  "type": "Feature",
  "properties": {
    "gn:adm1_name":"Yamaguchiken",
    "gn:adm2_name":"Abugun'Atouchou",
    "gn:name":"Jifukukami",
    "iso:country":"JP",
    "wof:name":"759-1421",
    "wof:placetype":"postalcode"
},
  "geometry": {"coordinates":[131.6722,34.3644],"type":"Point"}
}