{
  "type": "Feature",
  "properties": {
    "gn:adm1_name":"Kanagawaken",
    "gn:adm2_name":"Yokohamashiaobaku",
    "gn:name":"Midoriyama",
    "iso:country":"JP",
    "wof:name":"227-0037",
    "wof:placetype":"postalcode"
},
  "geometry": {"coordinates":[139.4836,35.5683],"type":"Point"}
}