{
  "type": "Feature",
  "properties": {
    "gn:adm1_name":"Toukyouto",
    "gn:adm2_name":"Fussashi",
    "gn:name":"Higashichou",
    "iso:country":"JP",
    "wof:name":"197-0021",
    "wof:placetype":"postalcode"
},
  "geometry": {"coordinates":[139.3279,35.7435],"type":"Point"}
}