{
  "type": "Feature",
  "properties": {
    "gn:adm1_name":"Shizuokaken",
    "gn:adm2_name":"Shizuokashi",
    "gn:name":"Shimizuaioichou",
    "iso:country":"JP",
    "wof:name":"424-0821",
    "wof:placetype":"postalcode"
},
  "geometry": {"coordinates":[138.48840000000001,35.0164],"type":"Point"}
}