{
  "type": "Feature",
  "properties": {
    "gn:adm1_name":"Naganoken",
    "gn:adm2_name":"Iidashi",
    "gn:name":"Touwachou",
    "iso:country":"JP",
    "wof:name":"395-0086",
    "wof:placetype":"postalcode"
},
  "geometry": {"coordinates":[137.8237,35.5196],"type":"Point"}
}