{
  "type": "Feature",
  "properties": {
    "gn:adm1_name":"Ishikawaken",
    "gn:adm2_name":"Mattoushi",
    "gn:name":"Uchikatashinbomachi",
    "iso:country":"JP",
    "wof:name":"924-0847",
    "wof:placetype":"postalcode"
},
  "geometry": {"coordinates":[136.55670000000001,36.4876],"type":"Point"}
}