{
  "type": "Feature",
  "properties": {
    "gn:adm1_name":"Saitamaken",
    "gn:adm2_name":"Chichibushi",
    "gn:name":"Obashira",
    "iso:country":"JP",
    "wof:name":"368-0061",
    "wof:placetype":"postalcode"
},
  "geometry": {"coordinates":[139.08799999999999,36.0614],"type":"Point"}
}