{
  "type": "Feature",
  "properties": {
    "gn:adm1_name":"Kagoshimaken",
    "gn:adm2_name":"Kagoshimashi",
    "gn:name":"Jounanchou",
    "iso:country":"JP",
    "wof:name":"892-0835",
    "wof:placetype":"postalcode"
},
  "geometry": {"coordinates":[130.5642,31.5825],"type":"Point"}
}