{
  "type": "Feature",
  "properties": {
    "gn:adm1_name":"Hyougoken",
    "gn:adm2_name":"Akashishi",
    "gn:name":"Uozumichoukamoike",
    "iso:country":"JP",
    "wof:name":"674-0073",
    "wof:placetype":"postalcode"
},
  "geometry": {"coordinates":[134.90880000000001,34.6987],"type":"Point"}
}