{
  "type": "Feature",
  "properties": {
    "gn:adm1_name":"Tokushimaken",
    "gn:adm2_name":"Itanogun'Aizumichou",
    "gn:name":"Kasagi(Higashino)",
    "iso:country":"JP",
    "wof:name":"771-1261",
    "wof:placetype":"postalcode"
},
  "geometry": {"coordinates":[134.5086,34.1359],"type":"Point"}
}