{
  "type": "Feature",
  "properties": {
    "gn:adm1_name":"Ooitaken",
    "gn:adm2_name":"Nakatsushi",
    "gn:name":"Korenori",
    "iso:country":"JP",
    "wof:name":"871-0003",
    "wof:placetype":"postalcode"
},
  "geometry": {"coordinates":[131.23509999999999,33.5865],"type":"Point"}
}