{
  "type": "Feature",
  "properties": {
    "gn:adm1_name":"Kyoutofu",
    "gn:adm2_name":"Kyoutoshihigashiyamaku",
    "gn:name":"Tatsumichou",
    "iso:country":"JP",
    "wof:name":"605-0018",
    "wof:placetype":"postalcode"
},
  "geometry": {"coordinates":[135.77610000000001,35.0078],"type":"Point"}
}