{
  "type": "Feature",
  "properties": {
    "gn:adm1_name":"Ibarakiken",
    "gn:adm2_name":"Namegatagunkitauramachi",
    "gn:name":"Obata",
    "iso:country":"JP",
    "wof:name":"311-1715",
    "wof:placetype":"postalcode"
},
  "geometry": {"coordinates":[140.47790000000001,36.0756],"type":"Point"}
}