{
  "type": "Feature",
  "properties": {
    "gn:adm1_name":"Niigataken",
    "gn:adm2_name":"Jouetsushi",
    "gn:name":"Takatsu",
    "iso:country":"JP",
    "wof:name":"943-0423",
    "wof:placetype":"postalcode"
},
  "geometry": {"coordinates":[138.33070000000001,37.0942],"type":"Point"}
}