{
  "type": "Feature",
  "properties": {
    "gn:adm1_name":"Kagoshimaken",
    "gn:adm2_name":"Hiokigun'Ijuuinchou",
    "gn:name":"Oota(Kukinonoishiduka)",
    "iso:country":"JP",
    "wof:name":"899-3121",
    "wof:placetype":"postalcode"
},
  "geometry": {"coordinates":[130.3811,31.6296],"type":"Point"}
}