{
  "type": "Feature",
  "properties": {
    "gn:adm1_name":"Shizuokaken",
    "gn:adm2_name":"Shimadashi",
    "gn:name":"Kanza",
    "iso:country":"JP",
    "wof:name":"427-0032",
    "wof:placetype":"postalcode"
},
  "geometry": {"coordinates":[138.11429999999999,34.8721],"type":"Point"}
}