{
  "type": "Feature",
  "properties": {
    "gn:adm1_name":"Niigataken",
    "gn:adm2_name":"Shibatashi",
    "gn:name":"Hiwatashi",
    "iso:country":"JP",
    "wof:name":"957-0072",
    "wof:placetype":"postalcode"
},
  "geometry": {"coordinates":[139.2868,37.951],"type":"Point"}
}