{
  "type": "Feature",
  "properties": {
    "gn:adm1_name":"Gunmaken",
    "gn:adm2_name":"Isesakishi",
    "gn:name":"Tsunatorimachi",
    "iso:country":"JP",
    "wof:name":"372-0812",
    "wof:placetype":"postalcode"
},
  "geometry": {"coordinates":[139.1773,36.3171],"type":"Point"}
}