{
  "type": "Feature",
  "properties": {
    "gn:adm1_name":"Fukuokaken",
    "gn:adm2_name":"Chikushigunnakagawamachi",
    "gn:name":"Nakabaru",
    "iso:country":"JP",
    "wof:name":"811-1213",
    "wof:placetype":"postalcode"
},
  "geometry": {"coordinates":[130.43549999999999,33.5155],"type":"Point"}
}