{
  "type": "Feature",
  "properties": {
    "gn:adm1_name":"Saitamaken",
    "gn:adm2_name":"Satteshi",
    "gn:name":"Toshima",
    "iso:country":"JP",
    "wof:name":"340-0144",
    "wof:placetype":"postalcode"
},
  "geometry": {"coordinates":[139.74000000000001,36.0503],"type":"Point"}
}