{
  "type": "Feature",
  "properties": {
    "gn:adm1_name":"Naraken",
    "gn:adm2_name":"Yoshinogunkurotakimura",
    "gn:name":"Nakato",
    "iso:country":"JP",
    "wof:name":"638-0221",
    "wof:placetype":"postalcode"
},
  "geometry": {"coordinates":[135.86150000000001,34.3056],"type":"Point"}
}