{
  "type": "Feature",
  "properties": {
    "gn:adm1_name":"Naraken",
    "gn:adm2_name":"Takaichiguntakatorichou",
    "gn:name":"Hyougo",
    "iso:country":"JP",
    "wof:name":"635-0136",
    "wof:placetype":"postalcode"
},
  "geometry": {"coordinates":[135.774,34.4488],"type":"Point"}
}