{
  "type": "Feature",
  "properties": {
    "gn:adm1_name":"Naganoken",
    "gn:adm2_name":"Suzakashi",
    "gn:name":"Nakamachi",
    "iso:country":"JP",
    "wof:name":"382-0082",
    "wof:placetype":"postalcode"
},
  "geometry": {"coordinates":[138.31319999999999,36.6559],"type":"Point"}
}