{
  "type": "Feature",
  "properties": {
    "gn:adm1_name":"Niigataken",
    "gn:adm2_name":"Iwafunegunkamihayashimura",
    "gn:name":"Makinome",
    "iso:country":"JP",
    "wof:name":"959-3424",
    "wof:placetype":"postalcode"
},
  "geometry": {"coordinates":[139.4485,38.1759],"type":"Point"}
}