{
  "type": "Feature",
  "properties": {
    "gn:adm1_name":"Oosakafu",
    "gn:adm2_name":"Higashioosakashi",
    "gn:name":"Oohasuminami",
    "iso:country":"JP",
    "wof:name":"577-0825",
    "wof:placetype":"postalcode"
},
  "geometry": {"coordinates":[135.57730000000001,34.6347],"type":"Point"}
}