{
  "type": "Feature",
  "properties": {
    "gn:adm1_name":"Ishikawaken",
    "gn:adm2_name":"Kanazawashi",
    "gn:name":"Habamachi",
    "iso:country":"JP",
    "wof:name":"920-1128",
    "wof:placetype":"postalcode"
},
  "geometry": {"coordinates":[136.74950000000001,36.4896],"type":"Point"}
}