{
  "type": "Feature",
  "properties": {
    "gn:adm1_name":"Tochigiken",
    "gn:adm2_name":"Nasugunkurobanemachi",
    "gn:name":"Kawada",
    "iso:country":"JP",
    "wof:name":"324-0208",
    "wof:placetype":"postalcode"
},
  "geometry": {"coordinates":[140.1352,36.9198],"type":"Point"}
}