{
  "type": "Feature",
  "properties": {
    "gn:adm1_name":"Naganoken",
    "gn:adm2_name":"Minamisakugun'Usudamachi",
    "gn:name":"Tokiwa",
    "iso:country":"JP",
    "wof:name":"384-0411",
    "wof:placetype":"postalcode"
},
  "geometry": {"coordinates":[138.50110000000001,36.2087],"type":"Point"}
}