{
  "type": "Feature",
  "properties": {
    "gn:adm1_name":"Hiroshimaken",
    "gn:adm2_name":"Hiroshimashiasakitaku",
    "gn:name":"Kamezaki",
    "iso:country":"JP",
    "wof:name":"739-1742",
    "wof:placetype":"postalcode"
},
  "geometry": {"coordinates":[132.52379999999999,34.4821],"type":"Point"}
}