{
  "type": "Feature",
  "properties": {
    "gn:adm1_name":"Niigataken",
    "gn:adm2_name":"Sanjoushi",
    "gn:name":"Magarifuchi",
    "iso:country":"JP",
    "wof:name":"955-0864",
    "wof:placetype":"postalcode"
},
  "geometry": {"coordinates":[138.9709,37.6203],"type":"Point"}
}