{
  "type": "Feature",
  "properties": {
    "gn:adm1_name":"Aichiken",
    "gn:adm2_name":"Hekinanshi",
    "gn:name":"Misakimachi",
    "iso:country":"JP",
    "wof:name":"447-0832",
    "wof:placetype":"postalcode"
},
  "geometry": {"coordinates":[136.97309999999999,34.8574],"type":"Point"}
}