{
  "type": "Feature",
  "properties": {
    "gn:adm1_name":"Mieken",
    "gn:adm2_name":"Iinangun'Iitakachou",
    "gn:name":"Mori",
    "iso:country":"JP",
    "wof:name":"515-1615",
    "wof:placetype":"postalcode"
},
  "geometry": {"coordinates":[136.2182,34.3885],"type":"Point"}
}