{
  "type": "Feature",
  "properties": {
    "gn:adm1_name":"Tochigiken",
    "gn:adm2_name":"Nasugun'Ogawamachi",
    "gn:name":"Yoshii",
    "iso:country":"JP",
    "wof:name":"324-0505",
    "wof:placetype":"postalcode"
},
  "geometry": {"coordinates":[140.0635,36.7803],"type":"Point"}
}