{
  "type": "Feature",
  "properties": {
    "gn:adm1_name":"Naraken",
    "gn:adm2_name":"Narashi",
    "gn:name":"Koinokubohigashimachi",
    "iso:country":"JP",
    "wof:name":"630-8137",
    "wof:placetype":"postalcode"
},
  "geometry": {"coordinates":[135.81,34.6732],"type":"Point"}
}