{
  "type": "Feature",
  "properties": {
    "gn:adm1_name":"Kanagawaken",
    "gn:adm2_name":"Yokohamashisakaeku",
    "gn:name":"Noshichiri",
    "iso:country":"JP",
    "wof:name":"247-0024",
    "wof:placetype":"postalcode"
},
  "geometry": {"coordinates":[139.57910000000001,35.3475],"type":"Point"}
}