{
  "type": "Feature",
  "properties": {
    "gn:adm1_name":"Aichiken",
    "gn:adm2_name":"Toyohashishi",
    "gn:name":"Minowachou",
    "iso:country":"JP",
    "wof:name":"440-0838",
    "wof:placetype":"postalcode"
},
  "geometry": {"coordinates":[137.41159999999999,34.7526],"type":"Point"}
}