{
  "type": "Feature",
  "properties": {
    "gn:adm1_name":"Hyougoken",
    "gn:adm2_name":"Takagunkamichou",
    "gn:name":"Todoroki",
    "iso:country":"JP",
    "wof:name":"679-1324",
    "wof:placetype":"postalcode"
},
  "geometry": {"coordinates":[134.9213,35.1566],"type":"Point"}
}