{
  "type": "Feature",
  "properties": {
    "gn:adm1_name":"Shigaken",
    "gn:adm2_name":"Echigun'Aitouchou",
    "gn:name":"Kamigishimoto",
    "iso:country":"JP",
    "wof:name":"527-0173",
    "wof:placetype":"postalcode"
},
  "geometry": {"coordinates":[136.23249999999999,35.1138],"type":"Point"}
}