{
  "type": "Feature",
  "properties": {
    "gn:adm1_name":"Fukuokaken",
    "gn:adm2_name":"Kitakyuushuushiyahatanishiku",
    "gn:name":"Tetsuou",
    "iso:country":"JP",
    "wof:name":"806-0057",
    "wof:placetype":"postalcode"
},
  "geometry": {"coordinates":[130.75450000000001,33.8497],"type":"Point"}
}