{
  "type": "Feature",
  "properties": {
    "gn:adm1_name":"Kouchiken",
    "gn:adm2_name":"Nagaokagun'Ootoyochou",
    "gn:name":"Funato",
    "iso:country":"JP",
    "wof:name":"789-0235",
    "wof:placetype":"postalcode"
},
  "geometry": {"coordinates":[133.72309999999999,33.7858],"type":"Point"}
}