{
  "type": "Feature",
  "properties": {
    "gn:adm1_name":"Okinawaken",
    "gn:adm2_name":"Nakagamigunnakagusukuson",
    "gn:name":"Ishadou",
    "iso:country":"JP",
    "wof:name":"901-2403",
    "wof:placetype":"postalcode"
},
  "geometry": {"coordinates":[127.80119999999999,26.2754],"type":"Point"}
}