{
  "type": "Feature",
  "properties": {
    "gn:adm1_name":"Tochigiken",
    "gn:adm2_name":"Shimotsugagun'Iwafunemachi",
    "gn:name":"Miya",
    "iso:country":"JP",
    "wof:name":"329-4315",
    "wof:placetype":"postalcode"
},
  "geometry": {"coordinates":[139.64019999999999,36.3431],"type":"Point"}
}