{
  "type": "Feature",
  "properties": {
    "gn:adm1_name":"Naraken",
    "gn:adm2_name":"Kashiharashi",
    "gn:name":"Oogaruchou",
    "iso:country":"JP",
    "wof:name":"634-0044",
    "wof:placetype":"postalcode"
},
  "geometry": {"coordinates":[135.798,34.479],"type":"Point"}
}