{
  "type": "Feature",
  "properties": {
    "gn:adm1_name":"Fukushimaken",
    "gn:adm2_name":"Sukagawashi",
    "gn:name":"Tsutsumi",
    "iso:country":"JP",
    "wof:name":"962-0802",
    "wof:placetype":"postalcode"
},
  "geometry": {"coordinates":[140.4075,37.3063],"type":"Point"}
}