{
  "type": "Feature",
  "properties": {
    "gn:adm1_name":"Yamaguchiken",
    "gn:adm2_name":"Kumageguntabusechou",
    "gn:name":"Chuuouminami",
    "iso:country":"JP",
    "wof:name":"742-1517",
    "wof:placetype":"postalcode"
},
  "geometry": {"coordinates":[132.04429999999999,33.9516],"type":"Point"}
}