{
  "type": "Feature",
  "properties": {
    "gn:adm1_name":"Hiroshimaken",
    "gn:adm2_name":"Ootakeshi",
    "gn:name":"Kuritanichoutaniwa",
    "iso:country":"JP",
    "wof:name":"739-0643",
    "wof:placetype":"postalcode"
},
  "geometry": {"coordinates":[132.18029999999999,34.2695],"type":"Point"}
}