{
  "type": "Feature",
  "properties": {
    "gn:adm1_name":"Kumamotoken",
    "gn:adm2_name":"Tamanashi",
    "gn:name":"Yamada",
    "iso:country":"JP",
    "wof:name":"865-0066",
    "wof:placetype":"postalcode"
},
  "geometry": {"coordinates":[130.54089999999999,32.9405],"type":"Point"}
}