{
  "type": "Feature",
  "properties": {
    "gn:adm1_name":"Sagaken",
    "gn:adm2_name":"Imarishi",
    "gn:name":"Hatatsuchoumategata",
    "iso:country":"JP",
    "wof:name":"848-0105",
    "wof:placetype":"postalcode"
},
  "geometry": {"coordinates":[129.8621,33.3661],"type":"Point"}
}