{
  "type": "Feature",
  "properties": {
    "gn:adm1_name":"Naraken",
    "gn:adm2_name":"Narashi",
    "gn:name":"Saidaijishindenchou",
    "iso:country":"JP",
    "wof:name":"631-0832",
    "wof:placetype":"postalcode"
},
  "geometry": {"coordinates":[135.77770000000001,34.6944],"type":"Point"}
}