{
  "type": "Feature",
  "properties": {
    "gn:adm1_name":"Hyougoken",
    "gn:adm2_name":"Koubeshinagataku",
    "gn:name":"Umegakachou",
    "iso:country":"JP",
    "wof:name":"653-0021",
    "wof:placetype":"postalcode"
},
  "geometry": {"coordinates":[135.15799999999999,34.6625],"type":"Point"}
}