{
  "type": "Feature",
  "properties": {
    "gn:adm1_name":"Yamaguchiken",
    "gn:adm2_name":"Shimonosekishi",
    "gn:name":"Nishiootsubochou",
    "iso:country":"JP",
    "wof:name":"750-0054",
    "wof:placetype":"postalcode"
},
  "geometry": {"coordinates":[130.9169,33.9625],"type":"Point"}
}