{
  "type": "Feature",
  "properties": {
    "gn:adm1_name":"Kagoshimaken",
    "gn:adm2_name":"Ooshimagunsetouchichou",
    "gn:name":"Akitoku",
    "iso:country":"JP",
    "wof:name":"894-2234",
    "wof:placetype":"postalcode"
},
  "geometry": {"coordinates":[129.28389999999999,28.0839],"type":"Point"}
}