{
  "type": "Feature",
  "properties": {
    "gn:adm1_name":"Fukuokaken",
    "gn:adm2_name":"Fukuokashiminamiku",
    "gn:name":"Gojitsukawa",
    "iso:country":"JP",
    "wof:name":"815-0001",
    "wof:placetype":"postalcode"
},
  "geometry": {"coordinates":[130.43870000000001,33.5607],"type":"Point"}
}