{
  "type": "Feature",
  "properties": {
    "gn:adm1_name":"Niigataken",
    "gn:adm2_name":"Shibatashi",
    "gn:name":"Okayashiki",
    "iso:country":"JP",
    "wof:name":"959-2333",
    "wof:placetype":"postalcode"
},
  "geometry": {"coordinates":[139.30160000000001,37.8893],"type":"Point"}
}