{
  "type": "Feature",
  "properties": {
    "gn:adm1_name":"Shigaken",
    "gn:adm2_name":"Hikoneshi",
    "gn:name":"Kouzakichou",
    "iso:country":"JP",
    "wof:name":"521-1141",
    "wof:placetype":"postalcode"
},
  "geometry": {"coordinates":[136.1711,35.2267],"type":"Point"}
}