{
  "type": "Feature",
  "properties": {
    "gn:adm1_name":"Oosakafu",
    "gn:adm2_name":"Kadomashi",
    "gn:name":"Matsuochou",
    "iso:country":"JP",
    "wof:name":"571-0044",
    "wof:placetype":"postalcode"
},
  "geometry": {"coordinates":[135.58459999999999,34.7285],"type":"Point"}
}