{
  "type": "Feature",
  "properties": {
    "gn:adm1_name":"Aichiken",
    "gn:adm2_name":"Tokonameshi",
    "gn:name":"Kanayama",
    "iso:country":"JP",
    "wof:name":"479-0003",
    "wof:placetype":"postalcode"
},
  "geometry": {"coordinates":[136.84270000000001,34.9227],"type":"Point"}
}