{
  "type": "Feature",
  "properties": {
    "gn:adm1_name":"Aichiken",
    "gn:adm2_name":"Toyohashishi",
    "gn:name":"Murosuijinchou",
    "iso:country":"JP",
    "wof:name":"441-8091",
    "wof:placetype":"postalcode"
},
  "geometry": {"coordinates":[137.35730000000001,34.7578],"type":"Point"}
}