{
  "type": "Feature",
  "properties": {
    "gn:adm1_name":"Naganoken",
    "gn:adm2_name":"Kitasakugunmochidukimachi",
    "gn:name":"Kasuga",
    "iso:country":"JP",
    "wof:name":"384-2205",
    "wof:placetype":"postalcode"
},
  "geometry": {"coordinates":[138.35329999999999,36.2167],"type":"Point"}
}