{
  "type": "Feature",
  "properties": {
    "gn:adm1_name":"Hyougoken",
    "gn:adm2_name":"Koubeshisumaku",
    "gn:name":"Myouhouji",
    "iso:country":"JP",
    "wof:name":"654-0121",
    "wof:placetype":"postalcode"
},
  "geometry": {"coordinates":[135.11850000000001,34.6768],"type":"Point"}
}