{
  "type": "Feature",
  "properties": {
    "gn:adm1_name":"Kagoshimaken",
    "gn:adm2_name":"Kagoshimashi",
    "gn:name":"Soumuta",
    "iso:country":"JP",
    "wof:name":"890-0014",
    "wof:placetype":"postalcode"
},
  "geometry": {"coordinates":[130.54060000000001,31.6037],"type":"Point"}
}