{
  "type": "Feature",
  "properties": {
    "gn:adm1_name":"Fukushimaken",
    "gn:adm2_name":"Kooriyamashi",
    "gn:name":"Furuyashiki",
    "iso:country":"JP",
    "wof:name":"963-8805",
    "wof:placetype":"postalcode"
},
  "geometry": {"coordinates":[140.40379999999999,37.3961],"type":"Point"}
}