{
  "type": "Feature",
  "properties": {
    "gn:adm1_name":"Kyoutofu",
    "gn:adm2_name":"Kyoutoshinakagyouku",
    "gn:name":"Nishisanbouhorikawachou",
    "iso:country":"JP",
    "wof:name":"604-8265",
    "wof:placetype":"postalcode"
},
  "geometry": {"coordinates":[135.7516,35.0104],"type":"Point"}
}