{
  "type": "Feature",
  "properties": {
    "gn:adm1_name":"Okayamaken",
    "gn:adm2_name":"Okayamashi",
    "gn:name":"Nakaune",
    "iso:country":"JP",
    "wof:name":"701-0213",
    "wof:placetype":"postalcode"
},
  "geometry": {"coordinates":[133.85470000000001,34.5851],"type":"Point"}
}