{
  "type": "Feature",
  "properties": {
    "gn:adm1_name":"Fukuokaken",
    "gn:adm2_name":"Kitakyuushuushikokurakitaku",
    "gn:name":"Uomachi",
    "iso:country":"JP",
    "wof:name":"802-0006",
    "wof:placetype":"postalcode"
},
  "geometry": {"coordinates":[130.8801,33.8834],"type":"Point"}
}