{
  "type": "Feature",
  "properties": {
    "gn:adm1_name":"Shigaken",
    "gn:adm2_name":"Takashimagun'Imaduchou",
    "gn:name":"Sanami",
    "iso:country":"JP",
    "wof:name":"520-1651",
    "wof:placetype":"postalcode"
},
  "geometry": {"coordinates":[136.01140000000001,35.4322],"type":"Point"}
}