{
  "type": "Feature",
  "properties": {
    "gn:adm1_name":"Yamagataken",
    "gn:adm2_name":"Tsuruokashi",
    "gn:name":"Imaizumi",
    "iso:country":"JP",
    "wof:name":"997-1206",
    "wof:placetype":"postalcode"
},
  "geometry": {"coordinates":[139.72489999999999,38.7597],"type":"Point"}
}