{
  "type": "Feature",
  "properties": {
    "gn:adm1_name":"Kyoutofu",
    "gn:adm2_name":"Yosagun'Inechou",
    "gn:name":"Honzaka",
    "iso:country":"JP",
    "wof:name":"626-0432",
    "wof:placetype":"postalcode"
},
  "geometry": {"coordinates":[135.23769999999999,35.7111],"type":"Point"}
}