{
  "type": "Feature",
  "properties": {
    "gn:adm1_name":"Hiroshimaken",
    "gn:adm2_name":"Hibagunsaijouchou",
    "gn:name":"Irie",
    "iso:country":"JP",
    "wof:name":"729-5733",
    "wof:placetype":"postalcode"
},
  "geometry": {"coordinates":[133.10929999999999,34.9337],"type":"Point"}
}