{
  "type": "Feature",
  "properties": {
    "gn:adm1_name":"Fukuiken",
    "gn:adm2_name":"Oonoshi",
    "gn:name":"Honmachi",
    "iso:country":"JP",
    "wof:name":"912-0025",
    "wof:placetype":"postalcode"
},
  "geometry": {"coordinates":[136.48929999999999,35.9876],"type":"Point"}
}