{
  "type": "Feature",
  "properties": {
    "gn:adm1_name":"Shizuokaken",
    "gn:adm2_name":"Fujishi",
    "gn:name":"Denbou",
    "iso:country":"JP",
    "wof:name":"417-0061",
    "wof:placetype":"postalcode"
},
  "geometry": {"coordinates":[138.67060000000001,35.1749],"type":"Point"}
}