{
  "type": "Feature",
  "properties": {
    "gn:adm1_name":"Ehimeken",
    "gn:adm2_name":"Matsuyamashi",
    "gn:name":"Eidaimachi",
    "iso:country":"JP",
    "wof:name":"790-0022",
    "wof:placetype":"postalcode"
},
  "geometry": {"coordinates":[132.7612,33.8346],"type":"Point"}
}