{
  "type": "Feature",
  "properties": {
    "gn:adm1_name":"Hyougoken",
    "gn:adm2_name":"Tatsunoshi",
    "gn:name":"Tatsunochoukamikajou",
    "iso:country":"JP",
    "wof:name":"679-4179",
    "wof:placetype":"postalcode"
},
  "geometry": {"coordinates":[134.54390000000001,34.8669],"type":"Point"}
}