{
  "type": "Feature",
  "properties": {
    "gn:adm1_name":"Hyougoken",
    "gn:adm2_name":"Yabugun'Ooyachou",
    "gn:name":"Kasadani",
    "iso:country":"JP",
    "wof:name":"667-0313",
    "wof:placetype":"postalcode"
},
  "geometry": {"coordinates":[134.6618,35.3314],"type":"Point"}
}