{
  "type": "Feature",
  "properties": {
    "gn:adm1_name":"Okayamaken",
    "gn:adm2_name":"Okayamashi",
    "gn:name":"Banzanchou",
    "iso:country":"JP",
    "wof:name":"700-0818",
    "wof:placetype":"postalcode"
},
  "geometry": {"coordinates":[133.92689999999999,34.6669],"type":"Point"}
}