{
  "type": "Feature",
  "properties": {
    "gn:adm1_name":"Kyoutofu",
    "gn:adm2_name":"Funaiguntanbachou",
    "gn:name":"Mori",
    "iso:country":"JP",
    "wof:name":"622-0233",
    "wof:placetype":"postalcode"
},
  "geometry": {"coordinates":[135.405,35.1558],"type":"Point"}
}