{
  "type": "Feature",
  "properties": {
    "gn:adm1_name":"Hiroshimaken",
    "gn:adm2_name":"Yamagataguntogouchichou",
    "gn:name":"Kawate",
    "iso:country":"JP",
    "wof:name":"731-3831",
    "wof:placetype":"postalcode"
},
  "geometry": {"coordinates":[132.21629999999999,34.6055],"type":"Point"}
}