{
  "type": "Feature",
  "properties": {
    "gn:adm1_name":"Toyamaken",
    "gn:adm2_name":"Kaminiikawagun'Ooyamamachi",
    "gn:name":"Higashikuromaki(Ueno)",
    "iso:country":"JP",
    "wof:name":"930-1263",
    "wof:placetype":"postalcode"
},
  "geometry": {"coordinates":[137.27279999999999,36.6012],"type":"Point"}
}