{
  "type": "Feature",
  "properties": {
    "gn:adm1_name":"Yamagataken",
    "gn:adm2_name":"Nishimurayamagun'Ooemachi",
    "gn:name":"Kosei",
    "iso:country":"JP",
    "wof:name":"990-1273",
    "wof:placetype":"postalcode"
},
  "geometry": {"coordinates":[140.0926,38.3572],"type":"Point"}
}