{
  "type": "Feature",
  "properties": {
    "gn:adm1_name":"Kanagawaken",
    "gn:adm2_name":"Yokohamashiminamiku",
    "gn:name":"Nagatadai",
    "iso:country":"JP",
    "wof:name":"232-0076",
    "wof:placetype":"postalcode"
},
  "geometry": {"coordinates":[139.58410000000001,35.4334],"type":"Point"}
}