{
  "type": "Feature",
  "properties": {
    "gn:adm1_name":"Toukyouto",
    "gn:adm2_name":"Meguroku",
    "gn:name":"Nakameguro",
    "iso:country":"JP",
    "wof:name":"153-0061",
    "wof:placetype":"postalcode"
},
  "geometry": {"coordinates":[139.7012,35.6391],"type":"Point"}
}