{
  "type": "Feature",
  "properties": {
    "gn:adm1_name":"Hyougoken",
    "gn:adm2_name":"Kanzakigun'Ichikawachou",
    "gn:name":"Yakata",
    "iso:country":"JP",
    "wof:name":"679-2337",
    "wof:placetype":"postalcode"
},
  "geometry": {"coordinates":[134.76159999999999,35.0255],"type":"Point"}
}