{
  "type": "Feature",
  "properties": {
    "gn:adm1_name":"Hyougoken",
    "gn:adm2_name":"Akoushi",
    "gn:name":"Ootsu",
    "iso:country":"JP",
    "wof:name":"678-0252",
    "wof:placetype":"postalcode"
},
  "geometry": {"coordinates":[134.36510000000001,34.775],"type":"Point"}
}