{
  "type": "Feature",
  "properties": {
    "gn:adm1_name":"Sagaken",
    "gn:adm2_name":"Takushi",
    "gn:name":"Minamitakumachi",
    "iso:country":"JP",
    "wof:name":"846-0021",
    "wof:placetype":"postalcode"
},
  "geometry": {"coordinates":[130.0898,33.2653],"type":"Point"}
}