{
  "type": "Feature",
  "properties": {
    "gn:adm1_name":"Gifuken",
    "gn:adm2_name":"Takayamashi",
    "gn:name":"Honobumachi",
    "iso:country":"JP",
    "wof:name":"506-0003",
    "wof:placetype":"postalcode"
},
  "geometry": {"coordinates":[137.2484,36.1619],"type":"Point"}
}