{
  "type": "Feature",
  "properties": {
    "gn:adm1_name":"Aichiken",
    "gn:adm2_name":"Nagoyashimidoriku",
    "gn:name":"Koubutsume",
    "iso:country":"JP",
    "wof:name":"458-0023",
    "wof:placetype":"postalcode"
},
  "geometry": {"coordinates":[136.9802,35.0812],"type":"Point"}
}