{
  "type": "Feature",
  "properties": {
    "gn:adm1_name":"Fukuokaken",
    "gn:adm2_name":"Mizumagun'Ookimachi",
    "gn:name":"Ooyabu",
    "iso:country":"JP",
    "wof:name":"830-0423",
    "wof:placetype":"postalcode"
},
  "geometry": {"coordinates":[130.44640000000001,33.1923],"type":"Point"}
}