{
  "type": "Feature",
  "properties": {
    "gn:adm1_name":"Saitamaken",
    "gn:adm2_name":"Todashi",
    "gn:name":"Todakouen",
    "iso:country":"JP",
    "wof:name":"335-0024",
    "wof:placetype":"postalcode"
},
  "geometry": {"coordinates":[139.67580000000001,35.8021],"type":"Point"}
}