{
  "type": "Feature",
  "properties": {
    "gn:adm1_name":"Naraken",
    "gn:adm2_name":"Yoshinogunyoshinochou",
    "gn:name":"Iigai",
    "iso:country":"JP",
    "wof:name":"639-3113",
    "wof:placetype":"postalcode"
},
  "geometry": {"coordinates":[135.85980000000001,34.3913],"type":"Point"}
}