{
  "type": "Feature",
  "properties": {
    "gn:adm1_name":"Ooitaken",
    "gn:adm2_name":"Usagun'Ajimumachi",
    "gn:name":"Sobe",
    "iso:country":"JP",
    "wof:name":"872-0863",
    "wof:placetype":"postalcode"
},
  "geometry": {"coordinates":[131.32740000000001,33.3748],"type":"Point"}
}