{
  "type": "Feature",
  "properties": {
    "gn:adm1_name":"Hyougoken",
    "gn:adm2_name":"Ashiyashi",
    "gn:name":"Okuyama",
    "iso:country":"JP",
    "wof:name":"659-0002",
    "wof:placetype":"postalcode"
},
  "geometry": {"coordinates":[135.28909999999999,34.7502],"type":"Point"}
}