{
  "type": "Feature",
  "properties": {
    "gn:adm1_name":"Kyoutofu",
    "gn:adm2_name":"Kyoutoshinishikyouku",
    "gn:name":"Katagiharahiratachou",
    "iso:country":"JP",
    "wof:name":"615-8141",
    "wof:placetype":"postalcode"
},
  "geometry": {"coordinates":[135.6936,34.973],"type":"Point"}
}