{
  "type": "Feature",
  "properties": {
    "gn:adm1_name":"Chibaken",
    "gn:adm2_name":"Chibashiinageku",
    "gn:name":"Inage",
    "iso:country":"JP",
    "wof:name":"263-0034",
    "wof:placetype":"postalcode"
},
  "geometry": {"coordinates":[140.0831,35.6374],"type":"Point"}
}