{
  "type": "Feature",
  "properties": {
    "gn:adm1_name":"Ibarakiken",
    "gn:adm2_name":"Tsukubashi",
    "gn:name":"Kamigou",
    "iso:country":"JP",
    "wof:name":"300-2645",
    "wof:placetype":"postalcode"
},
  "geometry": {"coordinates":[140.0136,36.0987],"type":"Point"}
}