{
  "type": "Feature",
  "properties": {
    "gn:adm1_name":"Wakayamaken",
    "gn:adm2_name":"Kainanshi",
    "gn:name":"Takadu",
    "iso:country":"JP",
    "wof:name":"640-0451",
    "wof:placetype":"postalcode"
},
  "geometry": {"coordinates":[135.2944,34.1979],"type":"Point"}
}