{
  "type": "Feature",
  "properties": {
    "gn:adm1_name":"Kyoutofu",
    "gn:adm2_name":"Kyoutoshifushimiku",
    "gn:name":"Echizenchou",
    "iso:country":"JP",
    "wof:name":"612-8321",
    "wof:placetype":"postalcode"
},
  "geometry": {"coordinates":[135.7602,34.944],"type":"Point"}
}