{
  "type": "Feature",
  "properties": {
    "gn:adm1_name":"Kanagawaken",
    "gn:adm2_name":"Sagamiharashi",
    "gn:name":"Tana",
    "iso:country":"JP",
    "wof:name":"229-1124",
    "wof:placetype":"postalcode"
},
  "geometry": {"coordinates":[139.33799999999999,35.5521],"type":"Point"}
}