{
  "type": "Feature",
  "properties": {
    "gn:adm1_name":"Fukuiken",
    "gn:adm2_name":"Obamashi",
    "gn:name":"Itayachou",
    "iso:country":"JP",
    "wof:name":"917-0005",
    "wof:placetype":"postalcode"
},
  "geometry": {"coordinates":[135.75030000000001,35.5111],"type":"Point"}
}