{
  "type": "Feature",
  "properties": {
    "gn:adm1_name":"Okayamaken",
    "gn:adm2_name":"Tamanoshi",
    "gn:name":"Koshimaji",
    "iso:country":"JP",
    "wof:name":"706-0144",
    "wof:placetype":"postalcode"
},
  "geometry": {"coordinates":[133.87819999999999,34.5141],"type":"Point"}
}