{
  "type": "Feature",
  "properties": {
    "gn:adm1_name":"Mieken",
    "gn:adm2_name":"Minamimurogunkiwachou",
    "gn:name":"Kogawaguchi",
    "iso:country":"JP",
    "wof:name":"519-5417",
    "wof:placetype":"postalcode"
},
  "geometry": {"coordinates":[135.90299999999999,33.8823],"type":"Point"}
}