{
  "type": "Feature",
  "properties": {
    "gn:adm1_name":"Kanagawaken",
    "gn:adm2_name":"Yokohamashihodogayaku",
    "gn:name":"Minezawachou",
    "iso:country":"JP",
    "wof:name":"240-0061",
    "wof:placetype":"postalcode"
},
  "geometry": {"coordinates":[139.5975,35.4785],"type":"Point"}
}