{
  "type": "Feature",
  "properties": {
    "gn:adm1_name":"Saitamaken",
    "gn:adm2_name":"Gyoudashi",
    "gn:name":"Miyamoto",
    "iso:country":"JP",
    "wof:name":"361-0072",
    "wof:placetype":"postalcode"
},
  "geometry": {"coordinates":[139.46199999999999,36.1432],"type":"Point"}
}