{
  "type": "Feature",
  "properties": {
    "gn:adm1_name":"Fukushimaken",
    "gn:adm2_name":"Sukagawashi",
    "gn:name":"Takakudazakai",
    "iso:country":"JP",
    "wof:name":"962-0837",
    "wof:placetype":"postalcode"
},
  "geometry": {"coordinates":[140.36619999999999,37.2734],"type":"Point"}
}