{
  "type": "Feature",
  "properties": {
    "gn:adm1_name":"Niigataken",
    "gn:adm2_name":"Tookamachishi",
    "gn:name":"Sarukura",
    "iso:country":"JP",
    "wof:name":"948-0015",
    "wof:placetype":"postalcode"
},
  "geometry": {"coordinates":[138.78399999999999,37.1308],"type":"Point"}
}