{
  "type": "Feature",
  "properties": {
    "gn:adm1_name":"Miyazakiken",
    "gn:adm2_name":"Nishiusukigunhinokagechou",
    "gn:name":"Iwaikawa(Sakaino)",
    "iso:country":"JP",
    "wof:name":"882-0302",
    "wof:placetype":"postalcode"
},
  "geometry": {"coordinates":[131.36840000000001,32.6493],"type":"Point"}
}