{
  "type": "Feature",
  "properties": {
    "gn:adm1_name":"Fukushimaken",
    "gn:adm2_name":"Fukushimashi",
    "gn:name":"Gorouuchimachi",
    "iso:country":"JP",
    "wof:name":"960-8111",
    "wof:placetype":"postalcode"
},
  "geometry": {"coordinates":[140.4743,37.7604],"type":"Point"}
}