{
  "type": "Feature",
  "properties": {
    "gn:adm1_name":"Yamaguchiken",
    "gn:adm2_name":"Kudamatsushi",
    "gn:name":"Aoyagi",
    "iso:country":"JP",
    "wof:name":"744-0004",
    "wof:placetype":"postalcode"
},
  "geometry": {"coordinates":[131.8716,34.0052],"type":"Point"}
}