{
  "type": "Feature",
  "properties": {
    "gn:adm1_name":"Tochigiken",
    "gn:adm2_name":"Kamitsugagunnishikatamachi",
    "gn:name":"Kanai",
    "iso:country":"JP",
    "wof:name":"322-0602",
    "wof:placetype":"postalcode"
},
  "geometry": {"coordinates":[139.74959999999999,36.4503],"type":"Point"}
}