{
  "type": "Feature",
  "properties": {
    "gn:adm1_name":"Miyagiken",
    "gn:adm2_name":"Kattagunshichikashukumachi",
    "gn:name":"Tougetaatagoshita",
    "iso:country":"JP",
    "wof:name":"989-0625",
    "wof:placetype":"postalcode"
},
  "geometry": {"coordinates":[140.3553,38.0045],"type":"Point"}
}