{
  "type": "Feature",
  "properties": {
    "gn:adm1_name":"Yamaguchiken",
    "gn:adm2_name":"Nagatoshi",
    "gn:name":"Tawarayama",
    "iso:country":"JP",
    "wof:name":"759-4211",
    "wof:placetype":"postalcode"
},
  "geometry": {"coordinates":[131.11189999999999,34.2939],"type":"Point"}
}