{
  "type": "Feature",
  "properties": {
    "gn:adm1_name":"Kyoutofu",
    "gn:adm2_name":"Kasagun'Ooechou",
    "gn:name":"Kewara",
    "iso:country":"JP",
    "wof:name":"620-0322",
    "wof:placetype":"postalcode"
},
  "geometry": {"coordinates":[135.16120000000001,35.4468],"type":"Point"}
}