{
  "type": "Feature",
  "properties": {
    "gn:adm1_name":"Kumamotoken",
    "gn:adm2_name":"Yatsushiroshi",
    "gn:name":"Uyanagimotomachi",
    "iso:country":"JP",
    "wof:name":"866-0085",
    "wof:placetype":"postalcode"
},
  "geometry": {"coordinates":[130.5985,32.4896],"type":"Point"}
}