{
  "type": "Feature",
  "properties": {
    "gn:adm1_name":"Niigataken",
    "gn:adm2_name":"Niigatashi",
    "gn:name":"Oono",
    "iso:country":"JP",
    "wof:name":"950-2037",
    "wof:placetype":"postalcode"
},
  "geometry": {"coordinates":[138.95169999999999,37.8644],"type":"Point"}
}