{
  "type": "Feature",
  "properties": {
    "gn:adm1_name":"Kumamotoken",
    "gn:adm2_name":"Kamotogunkikukamachi",
    "gn:name":"Shimonagano",
    "iso:country":"JP",
    "wof:name":"861-0405",
    "wof:placetype":"postalcode"
},
  "geometry": {"coordinates":[130.7732,33.0274],"type":"Point"}
}