{
  "type": "Feature",
  "properties": {
    "gn:adm1_name":"Hyougoken",
    "gn:adm2_name":"Ibogunshinguuchou",
    "gn:name":"Yoshima",
    "iso:country":"JP",
    "wof:name":"679-4305",
    "wof:placetype":"postalcode"
},
  "geometry": {"coordinates":[134.5498,34.9372],"type":"Point"}
}