{
  "type": "Feature",
  "properties": {
    "gn:adm1_name":"Yamagataken",
    "gn:adm2_name":"Sakatashi",
    "gn:name":"Yoshida",
    "iso:country":"JP",
    "wof:name":"999-8161",
    "wof:placetype":"postalcode"
},
  "geometry": {"coordinates":[139.87549999999999,38.9474],"type":"Point"}
}