{
  "type": "Feature",
  "properties": {
    "gn:adm1_name":"Ehimeken",
    "gn:adm2_name":"Houjoushi",
    "gn:name":"Kubo",
    "iso:country":"JP",
    "wof:name":"799-2462",
    "wof:placetype":"postalcode"
},
  "geometry": {"coordinates":[132.76910000000001,33.9385],"type":"Point"}
}