{
  "type": "Feature",
  "properties": {
    "gn:adm1_name":"Shigaken",
    "gn:adm2_name":"Koukagunkouseichou",
    "gn:name":"Takamatsuchou",
    "iso:country":"JP",
    "wof:name":"520-3211",
    "wof:placetype":"postalcode"
},
  "geometry": {"coordinates":[136.13159999999999,35.0153],"type":"Point"}
}