{
  "type": "Feature",
  "properties": {
    "gn:adm1_name":"Kagawaken",
    "gn:adm2_name":"Zentsuujishi",
    "gn:name":"Oosachou",
    "iso:country":"JP",
    "wof:name":"765-0052",
    "wof:placetype":"postalcode"
},
  "geometry": {"coordinates":[133.80430000000001,34.2066],"type":"Point"}
}