{
  "type": "Feature",
  "properties": {
    "gn:adm1_name":"Chibaken",
    "gn:adm2_name":"Isumigun'Ooharamachi",
    "gn:name":"Wakayama",
    "iso:country":"JP",
    "wof:name":"298-0001",
    "wof:placetype":"postalcode"
},
  "geometry": {"coordinates":[140.38630000000001,35.2646],"type":"Point"}
}