{
  "type": "Feature",
  "properties": {
    "gn:adm1_name":"Ibarakiken",
    "gn:adm2_name":"Inashikigunmihomura",
    "gn:name":"Funako",
    "iso:country":"JP",
    "wof:name":"300-0428",
    "wof:placetype":"postalcode"
},
  "geometry": {"coordinates":[140.279,36.027],"type":"Point"}
}