{
  "type": "Feature",
  "properties": {
    "gn:adm1_name":"Toyamaken",
    "gn:adm2_name":"Himishi",
    "gn:name":"Nakanami",
    "iso:country":"JP",
    "wof:name":"935-0402",
    "wof:placetype":"postalcode"
},
  "geometry": {"coordinates":[137.03909999999999,36.9521],"type":"Point"}
}