{
  "type": "Feature",
  "properties": {
    "gn:adm1_name":"Gunmaken",
    "gn:adm2_name":"Maebashishi",
    "gn:name":"Kozakashimachi",
    "iso:country":"JP",
    "wof:name":"371-0122",
    "wof:placetype":"postalcode"
},
  "geometry": {"coordinates":[139.119,36.4305],"type":"Point"}
}