{
  "type": "Feature",
  "properties": {
    "gn:adm1_name":"Aichiken",
    "gn:adm2_name":"Minamishitaraguntsukudemura",
    "gn:name":"Kamogaya",
    "iso:country":"JP",
    "wof:name":"441-1412",
    "wof:placetype":"postalcode"
},
  "geometry": {"coordinates":[137.4357,34.9725],"type":"Point"}
}