{
  "type": "Feature",
  "properties": {
    "gn:adm1_name":"Hyougoken",
    "gn:adm2_name":"Nishinomiyashi",
    "gn:name":"Nagatachou",
    "iso:country":"JP",
    "wof:name":"663-8034",
    "wof:placetype":"postalcode"
},
  "geometry": {"coordinates":[135.3613,34.7477],"type":"Point"}
}