{
  "type": "Feature",
  "properties": {
    "gn:adm1_name":"Niigataken",
    "gn:adm2_name":"Niigatashi",
    "gn:name":"Toumei",
    "iso:country":"JP",
    "wof:name":"950-0853",
    "wof:placetype":"postalcode"
},
  "geometry": {"coordinates":[139.08629999999999,37.8997],"type":"Point"}
}