{
  "type": "Feature",
  "properties": {
    "gn:adm1_name":"Kyoutofu",
    "gn:adm2_name":"Kyoutoshihigashiyamaku",
    "gn:name":"Kanayachou",
    "iso:country":"JP",
    "wof:name":"605-0834",
    "wof:placetype":"postalcode"
},
  "geometry": {"coordinates":[135.7704,34.9961],"type":"Point"}
}