{
  "type": "Feature",
  "properties": {
    "gn:adm1_name":"Aichiken",
    "gn:adm2_name":"Nagoyashimizuhoku",
    "gn:name":"Nishinowarichou",
    "iso:country":"JP",
    "wof:name":"467-0813",
    "wof:placetype":"postalcode"
},
  "geometry": {"coordinates":[136.9306,35.1299],"type":"Point"}
}