{
  "type": "Feature",
  "properties": {
    "gn:adm1_name":"Aichiken",
    "gn:adm2_name":"Kasugaishi",
    "gn:name":"Kouzoujichou",
    "iso:country":"JP",
    "wof:name":"487-0013",
    "wof:placetype":"postalcode"
},
  "geometry": {"coordinates":[137.0428,35.2627],"type":"Point"}
}