{
  "type": "Feature",
  "properties": {
    "gn:adm1_name":"Tottoriken",
    "gn:adm2_name":"Touhakugun'Akasakichou",
    "gn:name":"Matsudani",
    "iso:country":"JP",
    "wof:name":"689-2503",
    "wof:placetype":"postalcode"
},
  "geometry": {"coordinates":[133.64609999999999,35.5024],"type":"Point"}
}