{
  "type": "Feature",
  "properties": {
    "gn:adm1_name":"Tottoriken",
    "gn:adm2_name":"Hinogunkoufuchou",
    "gn:name":"Koebi",
    "iso:country":"JP",
    "wof:name":"689-4402",
    "wof:placetype":"postalcode"
},
  "geometry": {"coordinates":[133.4873,35.2899],"type":"Point"}
}