{
  "type": "Feature",
  "properties": {
    "gn:adm1_name":"Okayamaken",
    "gn:adm2_name":"Kibigunmabichou",
    "gn:name":"Osaki",
    "iso:country":"JP",
    "wof:name":"710-1304",
    "wof:placetype":"postalcode"
},
  "geometry": {"coordinates":[133.66990000000001,34.6288],"type":"Point"}
}