{
  "type": "Feature",
  "properties": {
    "gn:adm1_name":"Aichiken",
    "gn:adm2_name":"Nagoyashinakagawaku",
    "gn:name":"Hirosumichou",
    "iso:country":"JP",
    "wof:name":"454-0007",
    "wof:placetype":"postalcode"
},
  "geometry": {"coordinates":[136.8845,35.1558],"type":"Point"}
}