{
  "type": "Feature",
  "properties": {
    "gn:adm1_name":"Toukyouto",
    "gn:adm2_name":"Kitaku",
    "gn:name":"Shimo",
    "iso:country":"JP",
    "wof:name":"115-0042",
    "wof:placetype":"postalcode"
},
  "geometry": {"coordinates":[139.7304,35.7799],"type":"Point"}
}