{
  "type": "Feature",
  "properties": {
    "gn:adm1_name":"Saitamaken",
    "gn:adm2_name":"Iwatsukishi",
    "gn:name":"Magome",
    "iso:country":"JP",
    "wof:name":"339-0077",
    "wof:placetype":"postalcode"
},
  "geometry": {"coordinates":[139.6651,35.9696],"type":"Point"}
}