{
  "type": "Feature",
  "properties": {
    "gn:adm1_name":"Hyougoken",
    "gn:adm2_name":"Asagogun'Asagochou",
    "gn:name":"Mononobe",
    "iso:country":"JP",
    "wof:name":"679-3401",
    "wof:placetype":"postalcode"
},
  "geometry": {"coordinates":[134.8142,35.2713],"type":"Point"}
}