{
  "type": "Feature",
  "properties": {
    "gn:adm1_name":"Ehimeken",
    "gn:adm2_name":"Iyogunmasakichou",
    "gn:name":"Oomizo",
    "iso:country":"JP",
    "wof:name":"791-3153",
    "wof:placetype":"postalcode"
},
  "geometry": {"coordinates":[132.72319999999999,33.7826],"type":"Point"}
}