{
  "type": "Feature",
  "properties": {
    "gn:adm1_name":"Aichiken",
    "gn:adm2_name":"Inazawashi",
    "gn:name":"Jiromaruhigashimachi",
    "iso:country":"JP",
    "wof:name":"492-8115",
    "wof:placetype":"postalcode"
},
  "geometry": {"coordinates":[136.80869999999999,35.2636],"type":"Point"}
}