{
  "type": "Feature",
  "properties": {
    "gn:adm1_name":"Nagasakiken",
    "gn:adm2_name":"Oomurashi",
    "gn:name":"Miyashouji",
    "iso:country":"JP",
    "wof:name":"856-0807",
    "wof:placetype":"postalcode"
},
  "geometry": {"coordinates":[129.94380000000001,32.9506],"type":"Point"}
}