{
  "type": "Feature",
  "properties": {
    "gn:adm1_name":"Kouchiken",
    "gn:adm2_name":"Kouchishi",
    "gn:name":"Yokohamanishimachi",
    "iso:country":"JP",
    "wof:name":"781-0242",
    "wof:placetype":"postalcode"
},
  "geometry": {"coordinates":[133.5419,33.5185],"type":"Point"}
}