{
  "type": "Feature",
  "properties": {
    "gn:adm1_name":"Hiroshimaken",
    "gn:adm2_name":"Hiroshimashinakaku",
    "gn:name":"Ebaminami",
    "iso:country":"JP",
    "wof:name":"730-0835",
    "wof:placetype":"postalcode"
},
  "geometry": {"coordinates":[132.4348,34.3647],"type":"Point"}
}