{
  "type": "Feature",
  "properties": {
    "gn:adm1_name":"Yamagataken",
    "gn:adm2_name":"Higashimurayamagunyamanobemachi",
    "gn:name":"Yamanobe",
    "iso:country":"JP",
    "wof:name":"990-0301",
    "wof:placetype":"postalcode"
},
  "geometry": {"coordinates":[140.26679999999999,38.2948],"type":"Point"}
}