{
  "type": "Feature",
  "properties": {
    "gn:adm1_name":"Hiroshimaken",
    "gn:adm2_name":"Hiroshimashiasaminamiku",
    "gn:name":"Takatorikita",
    "iso:country":"JP",
    "wof:name":"731-0144",
    "wof:placetype":"postalcode"
},
  "geometry": {"coordinates":[132.43610000000001,34.4777],"type":"Point"}
}