{
  "type": "Feature",
  "properties": {
    "gn:adm1_name":"Kanagawaken",
    "gn:adm2_name":"Odawarashi",
    "gn:name":"Kamishinden",
    "iso:country":"JP",
    "wof:name":"250-0877",
    "wof:placetype":"postalcode"
},
  "geometry": {"coordinates":[139.172,35.2759],"type":"Point"}
}