{
  "type": "Feature",
  "properties": {
    "gn:adm1_name":"Fukushimaken",
    "gn:adm2_name":"Dategunkoorimachi",
    "gn:name":"Ikanikeisaiganaibaai",
    "iso:country":"JP",
    "wof:name":"969-1600",
    "wof:placetype":"postalcode"
},
  "geometry": {"coordinates":[140.5189,37.8553],"type":"Point"}
}