{
  "type": "Feature",
  "properties": {
    "gn:adm1_name":"Okinawaken",
    "gn:adm2_name":"Kunigamigunmotobuchou",
    "gn:name":"Urasaki",
    "iso:country":"JP",
    "wof:name":"905-0217",
    "wof:placetype":"postalcode"
},
  "geometry": {"coordinates":[127.8922,26.6775],"type":"Point"}
}