{
  "type": "Feature",
  "properties": {
    "gn:adm1_name":"Ehimeken",
    "gn:adm2_name":"Ochigunnamikatachou",
    "gn:name":"Miyazaki",
    "iso:country":"JP",
    "wof:name":"799-2104",
    "wof:placetype":"postalcode"
},
  "geometry": {"coordinates":[132.90649999999999,34.1149],"type":"Point"}
}