{
  "type": "Feature",
  "properties": {
    "gn:adm1_name":"Kagoshimaken",
    "gn:adm2_name":"Ibusukishi",
    "gn:name":"Shinnishikata",
    "iso:country":"JP",
    "wof:name":"891-0313",
    "wof:placetype":"postalcode"
},
  "geometry": {"coordinates":[130.59350000000001,31.2772],"type":"Point"}
}