{
  "type": "Feature",
  "properties": {
    "gn:adm1_name":"Shigaken",
    "gn:adm2_name":"Higashiazaigunkohokuchou",
    "gn:name":"Youkaichi",
    "iso:country":"JP",
    "wof:name":"529-0331",
    "wof:placetype":"postalcode"
},
  "geometry": {"coordinates":[136.24010000000001,35.4563],"type":"Point"}
}