{
  "type": "Feature",
  "properties": {
    "gn:adm1_name":"Tochigiken",
    "gn:adm2_name":"Utsunomiyashi",
    "gn:name":"Nakatomatsuri",
    "iso:country":"JP",
    "wof:name":"320-0057",
    "wof:placetype":"postalcode"
},
  "geometry": {"coordinates":[139.86840000000001,36.5788],"type":"Point"}
}