{
  "type": "Feature",
  "properties": {
    "gn:adm1_name":"Kagawaken",
    "gn:adm2_name":"Kan'Onjishi",
    "gn:name":"Nakadaichou",
    "iso:country":"JP",
    "wof:name":"768-0024",
    "wof:placetype":"postalcode"
},
  "geometry": {"coordinates":[133.70599999999999,34.1232],"type":"Point"}
}