{
  "type": "Feature",
  "properties": {
    "gn:adm1_name":"Hyougoken",
    "gn:adm2_name":"Nishiwakishi",
    "gn:name":"Hiechou",
    "iso:country":"JP",
    "wof:name":"677-0037",
    "wof:placetype":"postalcode"
},
  "geometry": {"coordinates":[135.00049999999999,34.9949],"type":"Point"}
}