{
  "type": "Feature",
  "properties": {
    "gn:adm1_name":"Gifuken",
    "gn:adm2_name":"Kaidugunkaiduchou",
    "gn:name":"Numashinden",
    "iso:country":"JP",
    "wof:name":"503-0634",
    "wof:placetype":"postalcode"
},
  "geometry": {"coordinates":[136.6421,35.1848],"type":"Point"}
}