{
  "type": "Feature",
  "properties": {
    "gn:adm1_name":"Kumamotoken",
    "gn:adm2_name":"Araoshi",
    "gn:name":"Midorigaoka",
    "iso:country":"JP",
    "wof:name":"864-0033",
    "wof:placetype":"postalcode"
},
  "geometry": {"coordinates":[130.47399999999999,32.9851],"type":"Point"}
}