{
  "type": "Feature",
  "properties": {
    "gn:adm1_name":"Oosakafu",
    "gn:adm2_name":"Senbokuguntadaokachou",
    "gn:name":"Tadaokakita",
    "iso:country":"JP",
    "wof:name":"595-0811",
    "wof:placetype":"postalcode"
},
  "geometry": {"coordinates":[135.39359999999999,34.4951],"type":"Point"}
}