{
  "type": "Feature",
  "properties": {
    "gn:adm1_name":"Kumamotoken",
    "gn:adm2_name":"Shimomashikigun'Ogawamachi",
    "gn:name":"Ogawa",
    "iso:country":"JP",
    "wof:name":"869-0621",
    "wof:placetype":"postalcode"
},
  "geometry": {"coordinates":[130.70679999999999,32.5857],"type":"Point"}
}