{
  "type": "Feature",
  "properties": {
    "gn:adm1_name":"Fukushimaken",
    "gn:adm2_name":"Shirakawashi",
    "gn:name":"Iizawayama",
    "iso:country":"JP",
    "wof:name":"961-0081",
    "wof:placetype":"postalcode"
},
  "geometry": {"coordinates":[140.2122,37.1427],"type":"Point"}
}