{
  "type": "Feature",
  "properties": {
    "gn:adm1_name":"Tochigiken",
    "gn:adm2_name":"Asoguntanumamachi",
    "gn:name":"Tomuro",
    "iso:country":"JP",
    "wof:name":"327-0306",
    "wof:placetype":"postalcode"
},
  "geometry": {"coordinates":[139.57409999999999,36.3842],"type":"Point"}
}