{
  "type": "Feature",
  "properties": {
    "gn:adm1_name":"Naraken",
    "gn:adm2_name":"Udagunhaibarachou",
    "gn:name":"Akabane",
    "iso:country":"JP",
    "wof:name":"633-0213",
    "wof:placetype":"postalcode"
},
  "geometry": {"coordinates":[136.0052,34.5103],"type":"Point"}
}