{
  "type": "Feature",
  "properties": {
    "gn:adm1_name":"Miyagiken",
    "gn:adm2_name":"Motoyoshigunmotoyoshichou",
    "gn:name":"Sugenosawa",
    "iso:country":"JP",
    "wof:name":"988-0328",
    "wof:placetype":"postalcode"
},
  "geometry": {"coordinates":[141.5128,38.7619],"type":"Point"}
}