{
  "type": "Feature",
  "properties": {
    "gn:adm1_name":"Chibaken",
    "gn:adm2_name":"Kashiwashi",
    "gn:name":"Akebono",
    "iso:country":"JP",
    "wof:name":"277-0841",
    "wof:placetype":"postalcode"
},
  "geometry": {"coordinates":[139.97130000000001,35.8678],"type":"Point"}
}