{
  "type": "Feature",
  "properties": {
    "gn:adm1_name":"Gunmaken",
    "gn:adm2_name":"Takasakishi",
    "gn:name":"Shimotoyookamachi",
    "iso:country":"JP",
    "wof:name":"370-0873",
    "wof:placetype":"postalcode"
},
  "geometry": {"coordinates":[138.98259999999999,36.3332],"type":"Point"}
}