{
  "type": "Feature",
  "properties": {
    "gn:adm1_name":"Ehimeken",
    "gn:adm2_name":"Iyoshi",
    "gn:name":"Unosaki",
    "iso:country":"JP",
    "wof:name":"799-3136",
    "wof:placetype":"postalcode"
},
  "geometry": {"coordinates":[132.7612,33.7127],"type":"Point"}
}