{
  "type": "Feature",
  "properties": {
    "gn:adm1_name":"Niigataken",
    "gn:adm2_name":"Niitsushi",
    "gn:name":"Nishifurutsu",
    "iso:country":"JP",
    "wof:name":"956-0037",
    "wof:placetype":"postalcode"
},
  "geometry": {"coordinates":[139.1131,37.7738],"type":"Point"}
}