{
  "type": "Feature",
  "properties": {
    "gn:adm1_name":"Toukyouto",
    "gn:adm2_name":"Akishimashi",
    "gn:name":"Tsutsujigaoka",
    "iso:country":"JP",
    "wof:name":"196-0012",
    "wof:placetype":"postalcode"
},
  "geometry": {"coordinates":[139.3681,35.7131],"type":"Point"}
}