{
  "type": "Feature",
  "properties": {
    "gn:adm1_name":"Ibarakiken",
    "gn:adm2_name":"Makabegun'Akenomachi",
    "gn:name":"Ebie",
    "iso:country":"JP",
    "wof:name":"300-4538",
    "wof:placetype":"postalcode"
},
  "geometry": {"coordinates":[140.00749999999999,36.2505],"type":"Point"}
}