{
  "type": "Feature",
  "properties": {
    "gn:adm1_name":"Kumamotoken",
    "gn:adm2_name":"Yatsushiroshi",
    "gn:name":"Gunchiku4banchou",
    "iso:country":"JP",
    "wof:name":"866-0021",
    "wof:placetype":"postalcode"
},
  "geometry": {"coordinates":[130.56790000000001,32.5285],"type":"Point"}
}