{
  "type": "Feature",
  "properties": {
    "gn:adm1_name":"Fukuokaken",
    "gn:adm2_name":"Kitakyuushuushikokuraminamiku",
    "gn:name":"Yokoshiro",
    "iso:country":"JP",
    "wof:name":"802-0824",
    "wof:placetype":"postalcode"
},
  "geometry": {"coordinates":[130.8991,33.8207],"type":"Point"}
}