{
  "type": "Feature",
  "properties": {
    "gn:adm1_name":"Niigataken",
    "gn:adm2_name":"Gosenshi",
    "gn:name":"Oosugou",
    "iso:country":"JP",
    "wof:name":"959-1633",
    "wof:placetype":"postalcode"
},
  "geometry": {"coordinates":[139.2353,37.7189],"type":"Point"}
}