{
  "type": "Feature",
  "properties": {
    "gn:adm1_name":"Niigataken",
    "gn:adm2_name":"Sadogun'Aikawamachi",
    "gn:name":"Ookura",
    "iso:country":"JP",
    "wof:name":"952-2205",
    "wof:placetype":"postalcode"
},
  "geometry": {"coordinates":[138.39080000000001,38.2335],"type":"Point"}
}