{
  "type": "Feature",
  "properties": {
    "gn:adm1_name":"Okayamaken",
    "gn:adm2_name":"Okugun'Okuchou",
    "gn:name":"Toyoyasu",
    "iso:country":"JP",
    "wof:name":"701-4222",
    "wof:placetype":"postalcode"
},
  "geometry": {"coordinates":[134.09229999999999,34.6596],"type":"Point"}
}