{
  "type": "Feature",
  "properties": {
    "gn:adm1_name":"Kumamotoken",
    "gn:adm2_name":"Kamotogunkamotomachi",
    "gn:name":"Takahashi",
    "iso:country":"JP",
    "wof:name":"861-0303",
    "wof:placetype":"postalcode"
},
  "geometry": {"coordinates":[130.75210000000001,33.0067],"type":"Point"}
}