{
  "type": "Feature",
  "properties": {
    "gn:adm1_name":"Kanagawaken",
    "gn:adm2_name":"Yokohamashinakaku",
    "gn:name":"Nogemachi",
    "iso:country":"JP",
    "wof:name":"231-0064",
    "wof:placetype":"postalcode"
},
  "geometry": {"coordinates":[139.62960000000001,35.448],"type":"Point"}
}