{
  "type": "Feature",
  "properties": {
    "gn:adm1_name":"Fukushimaken",
    "gn:adm2_name":"Shirakawashi",
    "gn:name":"Enmyouji",
    "iso:country":"JP",
    "wof:name":"961-0921",
    "wof:placetype":"postalcode"
},
  "geometry": {"coordinates":[140.2166,37.1228],"type":"Point"}
}