{
  "type": "Feature",
  "properties": {
    "gn:adm1_name":"Kouchiken",
    "gn:adm2_name":"Kouchishi",
    "gn:name":"Hinodechou",
    "iso:country":"JP",
    "wof:name":"780-0804",
    "wof:placetype":"postalcode"
},
  "geometry": {"coordinates":[133.5582,33.5604],"type":"Point"}
}