{
  "type": "Feature",
  "properties": {
    "gn:adm1_name":"Chibaken",
    "gn:adm2_name":"Chibashiwakabaku",
    "gn:name":"Yatouchou",
    "iso:country":"JP",
    "wof:name":"265-0072",
    "wof:placetype":"postalcode"
},
  "geometry": {"coordinates":[140.21260000000001,35.6402],"type":"Point"}
}