{
  "type": "Feature",
  "properties": {
    "gn:adm1_name":"Wakayamaken",
    "gn:adm2_name":"Wakayamashi",
    "gn:name":"Kitashinmotokanayachou",
    "iso:country":"JP",
    "wof:name":"640-8011",
    "wof:placetype":"postalcode"
},
  "geometry": {"coordinates":[135.1798,34.2386],"type":"Point"}
}