{
  "type": "Feature",
  "properties": {
    "gn:adm1_name":"Toukyouto",
    "gn:adm2_name":"Akishimashi",
    "gn:name":"Miyazawachou",
    "iso:country":"JP",
    "wof:name":"196-0024",
    "wof:placetype":"postalcode"
},
  "geometry": {"coordinates":[139.36500000000001,35.7032],"type":"Point"}
}