{
  "type": "Feature",
  "properties": {
    "gn:adm1_name":"Nagasakiken",
    "gn:adm2_name":"Nishisonogiguntaramichou",
    "gn:name":"Ichinunomyou",
    "iso:country":"JP",
    "wof:name":"859-0403",
    "wof:placetype":"postalcode"
},
  "geometry": {"coordinates":[129.9649,32.8181],"type":"Point"}
}