{
  "type": "Feature",
  "properties": {
    "gn:adm1_name":"Ibarakiken",
    "gn:adm2_name":"Kogashi",
    "gn:name":"Hase",
    "iso:country":"JP",
    "wof:name":"306-0035",
    "wof:placetype":"postalcode"
},
  "geometry": {"coordinates":[139.70230000000001,36.1859],"type":"Point"}
}