{
  "type": "Feature",
  "properties": {
    "gn:adm1_name":"Tottoriken",
    "gn:adm2_name":"Yonagoshi",
    "gn:name":"Oodanichou",
    "iso:country":"JP",
    "wof:name":"683-0045",
    "wof:placetype":"postalcode"
},
  "geometry": {"coordinates":[133.33369999999999,35.4173],"type":"Point"}
}