{
  "type": "Feature",
  "properties": {
    "gn:adm1_name":"Shigaken",
    "gn:adm2_name":"Sakatagun'Ibukichou",
    "gn:name":"Fujikawa",
    "iso:country":"JP",
    "wof:name":"521-0325",
    "wof:placetype":"postalcode"
},
  "geometry": {"coordinates":[136.42590000000001,35.381],"type":"Point"}
}