{
  "type": "Feature",
  "properties": {
    "gn:adm1_name":"Fukuiken",
    "gn:adm2_name":"Nyuugun'Asahichou",
    "gn:name":"Uchikoori",
    "iso:country":"JP",
    "wof:name":"916-0147",
    "wof:placetype":"postalcode"
},
  "geometry": {"coordinates":[136.12790000000001,35.9741],"type":"Point"}
}