{
  "type": "Feature",
  "properties": {
    "gn:adm1_name":"Yamagataken",
    "gn:adm2_name":"Higashiokitamaguntakahatamachi",
    "gn:name":"Tsuyufuji",
    "iso:country":"JP",
    "wof:name":"992-0323",
    "wof:placetype":"postalcode"
},
  "geometry": {"coordinates":[140.16069999999999,37.9698],"type":"Point"}
}