{
  "type": "Feature",
  "properties": {
    "gn:adm1_name":"Ooitaken",
    "gn:adm2_name":"Beppushi",
    "gn:name":"Souen",
    "iso:country":"JP",
    "wof:name":"874-0838",
    "wof:placetype":"postalcode"
},
  "geometry": {"coordinates":[131.4802,33.2936],"type":"Point"}
}