{
  "type": "Feature",
  "properties": {
    "gn:adm1_name":"Aichiken",
    "gn:adm2_name":"Hazugunkirachou",
    "gn:name":"Ogiwara",
    "iso:country":"JP",
    "wof:name":"444-0524",
    "wof:placetype":"postalcode"
},
  "geometry": {"coordinates":[137.06389999999999,34.8069],"type":"Point"}
}