{
  "type": "Feature",
  "properties": {
    "gn:adm1_name":"Miyagiken",
    "gn:adm2_name":"Shibatagun'Oogawaramachi",
    "gn:name":"Nittera",
    "iso:country":"JP",
    "wof:name":"989-1257",
    "wof:placetype":"postalcode"
},
  "geometry": {"coordinates":[140.7039,38.061],"type":"Point"}
}