{
  "type": "Feature",
  "properties": {
    "gn:adm1_name":"Oosakafu",
    "gn:adm2_name":"Kawachinaganoshi",
    "gn:name":"Nagaretani",
    "iso:country":"JP",
    "wof:name":"586-0063",
    "wof:placetype":"postalcode"
},
  "geometry": {"coordinates":[135.5797,34.3926],"type":"Point"}
}