{
  "type": "Feature",
  "properties": {
    "gn:adm1_name":"Gifuken",
    "gn:adm2_name":"Tajimishi",
    "gn:name":"Hikarigaoka",
    "iso:country":"JP",
    "wof:name":"507-0052",
    "wof:placetype":"postalcode"
},
  "geometry": {"coordinates":[137.10990000000001,35.346],"type":"Point"}
}