{
  "type": "Feature",
  "properties": {
    "gn:adm1_name":"Kyoutofu",
    "gn:adm2_name":"Maidurushi",
    "gn:name":"Oonyuu",
    "iso:country":"JP",
    "wof:name":"625-0136",
    "wof:placetype":"postalcode"
},
  "geometry": {"coordinates":[135.3501,35.5208],"type":"Point"}
}