{
  "type": "Feature",
  "properties": {
    "gn:adm1_name":"Gifuken",
    "gn:adm2_name":"Minoshi",
    "gn:name":"Matsukuradai",
    "iso:country":"JP",
    "wof:name":"501-3751",
    "wof:placetype":"postalcode"
},
  "geometry": {"coordinates":[136.91220000000001,35.5333],"type":"Point"}
}