{
  "type": "Feature",
  "properties": {
    "gn:adm1_name":"Yamaguchiken",
    "gn:adm2_name":"Shuunanshi",
    "gn:name":"Kanonaka",
    "iso:country":"JP",
    "wof:name":"745-0303",
    "wof:placetype":"postalcode"
},
  "geometry": {"coordinates":[131.8039,34.2263],"type":"Point"}
}