{
  "type": "Feature",
  "properties": {
    "gn:adm1_name":"Aichiken",
    "gn:adm2_name":"Toyotashi",
    "gn:name":"Yanamichou",
    "iso:country":"JP",
    "wof:name":"471-0002",
    "wof:placetype":"postalcode"
},
  "geometry": {"coordinates":[137.22790000000001,35.0961],"type":"Point"}
}