{
  "type": "Feature",
  "properties": {
    "gn:adm1_name":"Hiroshimaken",
    "gn:adm2_name":"Hiroshimashihigashiku",
    "gn:name":"Nakayamakami",
    "iso:country":"JP",
    "wof:name":"732-0027",
    "wof:placetype":"postalcode"
},
  "geometry": {"coordinates":[132.49930000000001,34.4185],"type":"Point"}
}