{
  "type": "Feature",
  "properties": {
    "gn:adm1_name":"Shigaken",
    "gn:adm2_name":"Ikaguntakatsukichou",
    "gn:name":"Nishiatsuji",
    "iso:country":"JP",
    "wof:name":"529-0253",
    "wof:placetype":"postalcode"
},
  "geometry": {"coordinates":[136.2149,35.4526],"type":"Point"}
}