{
  "type": "Feature",
  "properties": {
    "gn:adm1_name":"Hyougoken",
    "gn:adm2_name":"Shikamagunyumesakichou",
    "gn:name":"Miyaoki",
    "iso:country":"JP",
    "wof:name":"671-2121",
    "wof:placetype":"postalcode"
},
  "geometry": {"coordinates":[134.6755,34.9127],"type":"Point"}
}