{
  "type": "Feature",
  "properties": {
    "gn:adm1_name":"Yamagataken",
    "gn:adm2_name":"Tsuruokashi",
    "gn:name":"Hinode",
    "iso:country":"JP",
    "wof:name":"997-0025",
    "wof:placetype":"postalcode"
},
  "geometry": {"coordinates":[139.84630000000001,38.7233],"type":"Point"}
}