{
  "type": "Feature",
  "properties": {
    "gn:adm1_name":"Chibaken",
    "gn:adm2_name":"Chibashichuuouku",
    "gn:name":"Sogachou",
    "iso:country":"JP",
    "wof:name":"260-0822",
    "wof:placetype":"postalcode"
},
  "geometry": {"coordinates":[140.1318,35.5709],"type":"Point"}
}