{
  "type": "Feature",
  "properties": {
    "gn:adm1_name":"Niigataken",
    "gn:adm2_name":"Shibatashi",
    "gn:name":"Shimokomatsu",
    "iso:country":"JP",
    "wof:name":"959-2456",
    "wof:placetype":"postalcode"
},
  "geometry": {"coordinates":[139.35329999999999,37.9658],"type":"Point"}
}