{
  "type": "Feature",
  "properties": {
    "gn:adm1_name":"Saitamaken",
    "gn:adm2_name":"Kawaguchishi",
    "gn:name":"Namiki",
    "iso:country":"JP",
    "wof:name":"332-0034",
    "wof:placetype":"postalcode"
},
  "geometry": {"coordinates":[139.70820000000001,35.8163],"type":"Point"}
}