{
  "type": "Feature",
  "properties": {
    "gn:adm1_name":"Niigataken",
    "gn:adm2_name":"Araishi",
    "gn:name":"Yoshikishinden",
    "iso:country":"JP",
    "wof:name":"944-0024",
    "wof:placetype":"postalcode"
},
  "geometry": {"coordinates":[138.26740000000001,37.0171],"type":"Point"}
}