{
  "type": "Feature",
  "properties": {
    "gn:adm1_name":"Ibarakiken",
    "gn:adm2_name":"Kujigundaigomachi",
    "gn:name":"Machitsuki",
    "iso:country":"JP",
    "wof:name":"319-3702",
    "wof:placetype":"postalcode"
},
  "geometry": {"coordinates":[140.35769999999999,36.8401],"type":"Point"}
}