{
  "type": "Feature",
  "properties": {
    "gn:adm1_name":"Tokushimaken",
    "gn:adm2_name":"Oegunkamojimachou",
    "gn:name":"Uchibara",
    "iso:country":"JP",
    "wof:name":"776-0003",
    "wof:placetype":"postalcode"
},
  "geometry": {"coordinates":[134.36930000000001,34.0698],"type":"Point"}
}