{
  "type": "Feature",
  "properties": {
    "gn:adm1_name":"Niigataken",
    "gn:adm2_name":"Nakakanbaragunkamedamachi",
    "gn:name":"Azumachou",
    "iso:country":"JP",
    "wof:name":"950-0124",
    "wof:placetype":"postalcode"
},
  "geometry": {"coordinates":[139.11439999999999,37.8685],"type":"Point"}
}