{
  "type": "Feature",
  "properties": {
    "gn:adm1_name":"Niigataken",
    "gn:adm2_name":"Nagaokashi",
    "gn:name":"Takamimachi",
    "iso:country":"JP",
    "wof:name":"940-0004",
    "wof:placetype":"postalcode"
},
  "geometry": {"coordinates":[138.86099999999999,37.5025],"type":"Point"}
}