{
  "type": "Feature",
  "properties": {
    "gn:adm1_name":"Toyamaken",
    "gn:adm2_name":"Neigunfuchuumachi",
    "gn:name":"Araya",
    "iso:country":"JP",
    "wof:name":"939-2734",
    "wof:placetype":"postalcode"
},
  "geometry": {"coordinates":[137.17490000000001,36.6273],"type":"Point"}
}