{
  "type": "Feature",
  "properties": {
    "gn:adm1_name":"Shizuokaken",
    "gn:adm2_name":"Hamamatsushi",
    "gn:name":"Kasaikamimachi",
    "iso:country":"JP",
    "wof:name":"431-3106",
    "wof:placetype":"postalcode"
},
  "geometry": {"coordinates":[137.79810000000001,34.7761],"type":"Point"}
}