{
  "type": "Feature",
  "properties": {
    "gn:adm1_name":"Wakayamaken",
    "gn:adm2_name":"Aridashi",
    "gn:name":"Miyaharachousugai",
    "iso:country":"JP",
    "wof:name":"649-0433",
    "wof:placetype":"postalcode"
},
  "geometry": {"coordinates":[135.18770000000001,34.0742],"type":"Point"}
}