{
  "type": "Feature",
  "properties": {
    "gn:adm1_name":"Okinawaken",
    "gn:adm2_name":"Kunigamigunginozason",
    "gn:name":"Ikanikeisaiganaibaai",
    "iso:country":"JP",
    "wof:name":"904-1300",
    "wof:placetype":"postalcode"
},
  "geometry": {"coordinates":[127.9933,26.4917],"type":"Point"}
}