{
  "type": "Feature",
  "properties": {
    "gn:adm1_name":"Saitamaken",
    "gn:adm2_name":"Kitakatsushikagunkurihashimachi",
    "gn:name":"Kitahiroshima",
    "iso:country":"JP",
    "wof:name":"349-1111",
    "wof:placetype":"postalcode"
},
  "geometry": {"coordinates":[139.7022,36.1167],"type":"Point"}
}