{
  "type": "Feature",
  "properties": {
    "gn:adm1_name":"Fukushimaken",
    "gn:adm2_name":"Nishishirakawagunyabukimachi",
    "gn:name":"Marunouchi",
    "iso:country":"JP",
    "wof:name":"969-0235",
    "wof:placetype":"postalcode"
},
  "geometry": {"coordinates":[140.3545,37.2069],"type":"Point"}
}