{
  "type": "Feature",
  "properties": {
    "gn:adm1_name":"Ehimeken",
    "gn:adm2_name":"Uwajimashi",
    "gn:name":"Wareichou",
    "iso:country":"JP",
    "wof:name":"798-0012",
    "wof:placetype":"postalcode"
},
  "geometry": {"coordinates":[132.5676,33.2315],"type":"Point"}
}