{
  "type": "Feature",
  "properties": {
    "gn:adm1_name":"Naraken",
    "gn:adm2_name":"Narashi",
    "gn:name":"Kitakoujichou",
    "iso:country":"JP",
    "wof:name":"630-8252",
    "wof:placetype":"postalcode"
},
  "geometry": {"coordinates":[135.8261,34.6876],"type":"Point"}
}