{
  "type": "Feature",
  "properties": {
    "gn:adm1_name":"Wakayamaken",
    "gn:adm2_name":"Tanabeshi",
    "gn:name":"Higashiyama",
    "iso:country":"JP",
    "wof:name":"646-0022",
    "wof:placetype":"postalcode"
},
  "geometry": {"coordinates":[135.39259999999999,33.726],"type":"Point"}
}