{
  "type": "Feature",
  "properties": {
    "gn:adm1_name":"Okayamaken",
    "gn:adm2_name":"Asakuchigunkamogatachou",
    "gn:name":"Rokujouinnaka",
    "iso:country":"JP",
    "wof:name":"719-0252",
    "wof:placetype":"postalcode"
},
  "geometry": {"coordinates":[133.58860000000001,34.5231],"type":"Point"}
}