{
  "type": "Feature",
  "properties": {
    "gn:adm1_name":"Aichiken",
    "gn:adm2_name":"Inuyamashi",
    "gn:name":"Imai",
    "iso:country":"JP",
    "wof:name":"484-0005",
    "wof:placetype":"postalcode"
},
  "geometry": {"coordinates":[137.00129999999999,35.3669],"type":"Point"}
}