{
  "type": "Feature",
  "properties": {
    "gn:adm1_name":"Shimaneken",
    "gn:adm2_name":"Iishigunmitoyachou",
    "gn:name":"Kamikumatani",
    "iso:country":"JP",
    "wof:name":"690-2511",
    "wof:placetype":"postalcode"
},
  "geometry": {"coordinates":[132.89089999999999,35.2609],"type":"Point"}
}