{
  "type": "Feature",
  "properties": {
    "gn:adm1_name":"Nagasakiken",
    "gn:adm2_name":"Ikigun'Ashibechou",
    "gn:name":"Moroyoshihonmurafure",
    "iso:country":"JP",
    "wof:name":"811-5311",
    "wof:placetype":"postalcode"
},
  "geometry": {"coordinates":[129.78479999999999,33.7867],"type":"Point"}
}