{
  "type": "Feature",
  "properties": {
    "gn:adm1_name":"Tochigiken",
    "gn:adm2_name":"Nasugunminaminasumachi",
    "gn:name":"Takase",
    "iso:country":"JP",
    "wof:name":"321-0512",
    "wof:placetype":"postalcode"
},
  "geometry": {"coordinates":[140.10929999999999,36.6506],"type":"Point"}
}