{
  "type": "Feature",
  "properties": {
    "gn:adm1_name":"Toyamaken",
    "gn:adm2_name":"Toyamashi",
    "gn:name":"Hikatae",
    "iso:country":"JP",
    "wof:name":"931-8416",
    "wof:placetype":"postalcode"
},
  "geometry": {"coordinates":[137.26220000000001,36.7585],"type":"Point"}
}