{
  "type": "Feature",
  "properties": {
    "gn:adm1_name":"Hyougoken",
    "gn:adm2_name":"Shisougunyamasakichou",
    "gn:name":"Monzen",
    "iso:country":"JP",
    "wof:name":"671-2579",
    "wof:placetype":"postalcode"
},
  "geometry": {"coordinates":[134.53440000000001,35.0061],"type":"Point"}
}