{
  "type": "Feature",
  "properties": {
    "gn:adm1_name":"Sagaken",
    "gn:adm2_name":"Karatsushi",
    "gn:name":"Chouda",
    "iso:country":"JP",
    "wof:name":"847-0821",
    "wof:placetype":"postalcode"
},
  "geometry": {"coordinates":[129.9692,33.4414],"type":"Point"}
}