{
  "type": "Feature",
  "properties": {
    "gn:adm1_name":"Saitamaken",
    "gn:adm2_name":"Kounosushi",
    "gn:name":"Kasahara",
    "iso:country":"JP",
    "wof:name":"365-0023",
    "wof:placetype":"postalcode"
},
  "geometry": {"coordinates":[139.5504,36.0662],"type":"Point"}
}