{
  "type": "Feature",
  "properties": {
    "gn:adm1_name":"Oosakafu",
    "gn:adm2_name":"Kishiwadashi",
    "gn:name":"Makamichou",
    "iso:country":"JP",
    "wof:name":"596-0842",
    "wof:placetype":"postalcode"
},
  "geometry": {"coordinates":[135.40379999999999,34.4314],"type":"Point"}
}