{
  "type": "Feature",
  "properties": {
    "gn:adm1_name":"Mieken",
    "gn:adm2_name":"Wataraiguntamakichou",
    "gn:name":"Kamitanui",
    "iso:country":"JP",
    "wof:name":"519-0417",
    "wof:placetype":"postalcode"
},
  "geometry": {"coordinates":[136.6131,34.4963],"type":"Point"}
}