{
  "type": "Feature",
  "properties": {
    "gn:adm1_name":"Toukyouto",
    "gn:adm2_name":"Edogawaku",
    "gn:name":"Matsushima",
    "iso:country":"JP",
    "wof:name":"132-0031",
    "wof:placetype":"postalcode"
},
  "geometry": {"coordinates":[139.86170000000001,35.7091],"type":"Point"}
}