{
  "type": "Feature",
  "properties": {
    "gn:adm1_name":"Toukyouto",
    "gn:adm2_name":"Shinjukuku",
    "gn:name":"Nishishinjukushinjukusenta^Biru(8kai)",
    "iso:country":"JP",
    "wof:name":"163-0608",
    "wof:placetype":"postalcode"
},
  "geometry": {"coordinates":[139.6927,35.6956],"type":"Point"}
}