{
  "type": "Feature",
  "properties": {
    "gn:adm1_name":"Sagaken",
    "gn:adm2_name":"Miyakigunkiyamachou",
    "gn:name":"Sonobe",
    "iso:country":"JP",
    "wof:name":"841-0203",
    "wof:placetype":"postalcode"
},
  "geometry": {"coordinates":[130.50909999999999,33.4182],"type":"Point"}
}