{
  "type": "Feature",
  "properties": {
    "gn:adm1_name":"Mieken",
    "gn:adm2_name":"Agegun'Anouchou",
    "gn:name":"Minamikoyama",
    "iso:country":"JP",
    "wof:name":"514-2316",
    "wof:placetype":"postalcode"
},
  "geometry": {"coordinates":[136.43049999999999,34.7473],"type":"Point"}
}