{
  "type": "Feature",
  "properties": {
    "gn:adm1_name":"Kanagawaken",
    "gn:adm2_name":"Kawasakishikawasakiku",
    "gn:name":"Oiwakechou",
    "iso:country":"JP",
    "wof:name":"210-0835",
    "wof:placetype":"postalcode"
},
  "geometry": {"coordinates":[139.71469999999999,35.5195],"type":"Point"}
}