{
  "type": "Feature",
  "properties": {
    "gn:adm1_name":"Sagaken",
    "gn:adm2_name":"Kanzakigunkanzakimachi",
    "gn:name":"Anegawa",
    "iso:country":"JP",
    "wof:name":"842-0014",
    "wof:placetype":"postalcode"
},
  "geometry": {"coordinates":[130.346,33.2892],"type":"Point"}
}