{
  "type": "Feature",
  "properties": {
    "gn:adm1_name":"Saitamaken",
    "gn:adm2_name":"Sayamashi",
    "gn:name":"Kashiwabara",
    "iso:country":"JP",
    "wof:name":"350-1335",
    "wof:placetype":"postalcode"
},
  "geometry": {"coordinates":[139.4032,35.8773],"type":"Point"}
}