{
  "type": "Feature",
  "properties": {
    "gn:adm1_name":"Kanagawaken",
    "gn:adm2_name":"Zamashi",
    "gn:name":"Midorigaoka",
    "iso:country":"JP",
    "wof:name":"228-0021",
    "wof:placetype":"postalcode"
},
  "geometry": {"coordinates":[139.4085,35.4927],"type":"Point"}
}