{
  "type": "Feature",
  "properties": {
    "gn:adm1_name":"Fukushimaken",
    "gn:adm2_name":"Dategundatemachi",
    "gn:name":"Sawada",
    "iso:country":"JP",
    "wof:name":"960-0473",
    "wof:placetype":"postalcode"
},
  "geometry": {"coordinates":[139.86429999999999,37.238],"type":"Point"}
}