{
  "type": "Feature",
  "properties": {
    "gn:adm1_name":"Ishikawaken",
    "gn:adm2_name":"Hakuigunshikamachi",
    "gn:name":"Akasumi",
    "iso:country":"JP",
    "wof:name":"925-0161",
    "wof:placetype":"postalcode"
},
  "geometry": {"coordinates":[136.73849999999999,37.0508],"type":"Point"}
}