{
  "type": "Feature",
  "properties": {
    "gn:adm1_name":"Kagoshimaken",
    "gn:adm2_name":"Soogun'Oosumichou",
    "gn:name":"Sudaki",
    "iso:country":"JP",
    "wof:name":"899-8423",
    "wof:placetype":"postalcode"
},
  "geometry": {"coordinates":[130.8732,31.6142],"type":"Point"}
}