{
  "type": "Feature",
  "properties": {
    "gn:adm1_name":"Aichiken",
    "gn:adm2_name":"Nagoyashiminamiku",
    "gn:name":"Hoshizonochou",
    "iso:country":"JP",
    "wof:name":"457-0069",
    "wof:placetype":"postalcode"
},
  "geometry": {"coordinates":[136.93430000000001,35.0862],"type":"Point"}
}