{
  "type": "Feature",
  "properties": {
    "gn:adm1_name":"Kagawaken",
    "gn:adm2_name":"Sakaideshi",
    "gn:name":"Komadomechou",
    "iso:country":"JP",
    "wof:name":"762-0032",
    "wof:placetype":"postalcode"
},
  "geometry": {"coordinates":[133.8569,34.3109],"type":"Point"}
}