{
  "type": "Feature",
  "properties": {
    "gn:adm1_name":"Mieken",
    "gn:adm2_name":"Suzukashi",
    "gn:name":"Kitanagochou",
    "iso:country":"JP",
    "wof:name":"513-0049",
    "wof:placetype":"postalcode"
},
  "geometry": {"coordinates":[136.63030000000001,34.8985],"type":"Point"}
}