{
  "type": "Feature",
  "properties": {
    "gn:adm1_name":"Aichiken",
    "gn:adm2_name":"Nagoyashiminatoku",
    "gn:name":"Sakurachou",
    "iso:country":"JP",
    "wof:name":"455-0012",
    "wof:placetype":"postalcode"
},
  "geometry": {"coordinates":[136.8912,35.1024],"type":"Point"}
}