{
  "type": "Feature",
  "properties": {
    "gn:adm1_name":"Ishikawaken",
    "gn:adm2_name":"Kanazawashi",
    "gn:name":"Tomuroshinbo",
    "iso:country":"JP",
    "wof:name":"920-1105",
    "wof:placetype":"postalcode"
},
  "geometry": {"coordinates":[136.7338,36.5392],"type":"Point"}
}