{
  "type": "Feature",
  "properties": {
    "gn:adm1_name":"Toyamaken",
    "gn:adm2_name":"Oyabeshi",
    "gn:name":"Shimoyashiki",
    "iso:country":"JP",
    "wof:name":"932-0005",
    "wof:placetype":"postalcode"
},
  "geometry": {"coordinates":[136.85310000000001,36.7214],"type":"Point"}
}