{
  "type": "Feature",
  "properties": {
    "gn:adm1_name":"Kouchiken",
    "gn:adm2_name":"Nakamurashi",
    "gn:name":"Sakamoto",
    "iso:country":"JP",
    "wof:name":"787-0156",
    "wof:placetype":"postalcode"
},
  "geometry": {"coordinates":[132.93530000000001,32.9734],"type":"Point"}
}