{
  "type": "Feature",
  "properties": {
    "gn:adm1_name":"Yamaguchiken",
    "gn:adm2_name":"Shimonosekishi",
    "gn:name":"Mutsurejima",
    "iso:country":"JP",
    "wof:name":"750-0095",
    "wof:placetype":"postalcode"
},
  "geometry": {"coordinates":[130.86529999999999,33.9753],"type":"Point"}
}