{
  "type": "Feature",
  "properties": {
    "gn:adm1_name":"Ibarakiken",
    "gn:adm2_name":"Kashimaguntaiyoumura",
    "gn:name":"Kamizawa",
    "iso:country":"JP",
    "wof:name":"311-2111",
    "wof:placetype":"postalcode"
},
  "geometry": {"coordinates":[140.59270000000001,36.1045],"type":"Point"}
}