{
  "type": "Feature",
  "properties": {
    "gn:adm1_name":"Tottoriken",
    "gn:adm2_name":"Yonagoshi",
    "gn:name":"Furuichi",
    "iso:country":"JP",
    "wof:name":"683-0025",
    "wof:placetype":"postalcode"
},
  "geometry": {"coordinates":[133.3366,35.3917],"type":"Point"}
}