{
  "type": "Feature",
  "properties": {
    "gn:adm1_name":"Sagaken",
    "gn:adm2_name":"Sagagunfujichou",
    "gn:name":"Kamikumakawa",
    "iso:country":"JP",
    "wof:name":"840-0512",
    "wof:placetype":"postalcode"
},
  "geometry": {"coordinates":[130.23570000000001,33.3609],"type":"Point"}
}