{
  "type": "Feature",
  "properties": {
    "gn:adm1_name":"Oosakafu",
    "gn:adm2_name":"Minamikawachigunkananchou",
    "gn:name":"Hamuro",
    "iso:country":"JP",
    "wof:name":"585-0006",
    "wof:placetype":"postalcode"
},
  "geometry": {"coordinates":[135.63589999999999,34.4881],"type":"Point"}
}