{
  "type": "Feature",
  "properties": {
    "gn:adm1_name":"Kyoutofu",
    "gn:adm2_name":"Kyoutoshisakyouku",
    "gn:name":"Kamitakanonakamachi",
    "iso:country":"JP",
    "wof:name":"606-0044",
    "wof:placetype":"postalcode"
},
  "geometry": {"coordinates":[135.79079999999999,35.0629],"type":"Point"}
}