{
  "type": "Feature",
  "properties": {
    "gn:adm1_name":"Shizuokaken",
    "gn:adm2_name":"Ogasagundaitouchou",
    "gn:name":"Kikuhama",
    "iso:country":"JP",
    "wof:name":"437-1415",
    "wof:placetype":"postalcode"
},
  "geometry": {"coordinates":[138.06010000000001,34.6624],"type":"Point"}
}