{
  "type": "Feature",
  "properties": {
    "gn:adm1_name":"Ishikawaken",
    "gn:adm2_name":"Fugeshigunmonzenmachi",
    "gn:name":"Watase",
    "iso:country":"JP",
    "wof:name":"927-2331",
    "wof:placetype":"postalcode"
},
  "geometry": {"coordinates":[136.72909999999999,37.2321],"type":"Point"}
}