{
  "type": "Feature",
  "properties": {
    "gn:adm1_name":"Kyoutofu",
    "gn:adm2_name":"Kyoutoshikitaku",
    "gn:name":"Kamigamookamotochou",
    "iso:country":"JP",
    "wof:name":"603-8081",
    "wof:placetype":"postalcode"
},
  "geometry": {"coordinates":[135.7603,35.0588],"type":"Point"}
}