{
  "type": "Feature",
  "properties": {
    "gn:adm1_name":"Sagaken",
    "gn:adm2_name":"Kanzakigunchiyodachou",
    "gn:name":"Yanagishima",
    "iso:country":"JP",
    "wof:name":"842-0062",
    "wof:placetype":"postalcode"
},
  "geometry": {"coordinates":[130.40860000000001,33.2695],"type":"Point"}
}