{
  "type": "Feature",
  "properties": {
    "gn:adm1_name":"Yamagataken",
    "gn:adm2_name":"Yamagatashi",
    "gn:name":"Saiwaichou",
    "iso:country":"JP",
    "wof:name":"990-0038",
    "wof:placetype":"postalcode"
},
  "geometry": {"coordinates":[140.32759999999999,38.2454],"type":"Point"}
}