{
  "type": "Feature",
  "properties": {
    "gn:adm1_name":"Saitamaken",
    "gn:adm2_name":"Gyoudashi",
    "gn:name":"Kamiikemori",
    "iso:country":"JP",
    "wof:name":"361-0066",
    "wof:placetype":"postalcode"
},
  "geometry": {"coordinates":[139.43600000000001,36.1574],"type":"Point"}
}