{
  "type": "Feature",
  "properties": {
    "gn:adm1_name":"Miyagiken",
    "gn:adm2_name":"Shibatagunkawasakimachi",
    "gn:name":"Hasekuradai",
    "iso:country":"JP",
    "wof:name":"989-1506",
    "wof:placetype":"postalcode"
},
  "geometry": {"coordinates":[140.73699999999999,38.2007],"type":"Point"}
}