{
  "type": "Feature",
  "properties": {
    "gn:adm1_name":"Chibaken",
    "gn:adm2_name":"Futtsushi",
    "gn:name":"Kokubo",
    "iso:country":"JP",
    "wof:name":"293-0042",
    "wof:placetype":"postalcode"
},
  "geometry": {"coordinates":[139.86009999999999,35.2766],"type":"Point"}
}