{
  "type": "Feature",
  "properties": {
    "gn:adm1_name":"Kyoutofu",
    "gn:adm2_name":"Kyoutoshishimogyouku",
    "gn:name":"Monzenchou",
    "iso:country":"JP",
    "wof:name":"600-8358",
    "wof:placetype":"postalcode"
},
  "geometry": {"coordinates":[135.7516,34.9924],"type":"Point"}
}