{
  "type": "Feature",
  "properties": {
    "gn:adm1_name":"Kagoshimaken",
    "gn:adm2_name":"Kimotsukigunkushirachou",
    "gn:name":"Arisato",
    "iso:country":"JP",
    "wof:name":"893-1602",
    "wof:placetype":"postalcode"
},
  "geometry": {"coordinates":[130.93299999999999,31.4132],"type":"Point"}
}