{
  "type": "Feature",
  "properties": {
    "gn:adm1_name":"Aichiken",
    "gn:adm2_name":"Setoshi",
    "gn:name":"Sonochou",
    "iso:country":"JP",
    "wof:name":"489-0008",
    "wof:placetype":"postalcode"
},
  "geometry": {"coordinates":[137.0975,35.2571],"type":"Point"}
}