{
  "type": "Feature",
  "properties": {
    "gn:adm1_name":"Hyougoken",
    "gn:adm2_name":"Aioishi",
    "gn:name":"Ooishichou",
    "iso:country":"JP",
    "wof:name":"678-0005",
    "wof:placetype":"postalcode"
},
  "geometry": {"coordinates":[134.4769,34.8164],"type":"Point"}
}