{
  "type": "Feature",
  "properties": {
    "gn:adm1_name":"Niigataken",
    "gn:adm2_name":"Niigatashi",
    "gn:name":"Hashikekawagishichou",
    "iso:country":"JP",
    "wof:name":"951-8017",
    "wof:placetype":"postalcode"
},
  "geometry": {"coordinates":[139.05340000000001,37.9327],"type":"Point"}
}