{
  "type": "Feature",
  "properties": {
    "gn:adm1_name":"Hiroshimaken",
    "gn:adm2_name":"Ootakeshi",
    "gn:name":"Kurokawa",
    "iso:country":"JP",
    "wof:name":"739-0653",
    "wof:placetype":"postalcode"
},
  "geometry": {"coordinates":[132.22139999999999,34.2474],"type":"Point"}
}