{
  "type": "Feature",
  "properties": {
    "gn:adm1_name":"Saitamaken",
    "gn:adm2_name":"Kitasaitamagun'Ootonemachi",
    "gn:name":"Kitashimoarai",
    "iso:country":"JP",
    "wof:name":"349-1134",
    "wof:placetype":"postalcode"
},
  "geometry": {"coordinates":[139.67269999999999,36.1379],"type":"Point"}
}