{
  "type": "Feature",
  "properties": {
    "gn:adm1_name":"Ooitaken",
    "gn:adm2_name":"Tsukumishi",
    "gn:name":"Chinu",
    "iso:country":"JP",
    "wof:name":"879-2401",
    "wof:placetype":"postalcode"
},
  "geometry": {"coordinates":[131.8869,33.0715],"type":"Point"}
}