{
  "type": "Feature",
  "properties": {
    "gn:adm1_name":"Chibaken",
    "gn:adm2_name":"Ichiharashi",
    "gn:name":"Yata",
    "iso:country":"JP",
    "wof:name":"290-0517",
    "wof:placetype":"postalcode"
},
  "geometry": {"coordinates":[140.16120000000001,35.382],"type":"Point"}
}