{
  "type": "Feature",
  "properties": {
    "gn:adm1_name":"Yamaguchiken",
    "gn:adm2_name":"Mineshi",
    "gn:name":"Toyotamaechoufurueboshi",
    "iso:country":"JP",
    "wof:name":"750-0605",
    "wof:placetype":"postalcode"
},
  "geometry": {"coordinates":[131.0993,34.1482],"type":"Point"}
}