{
  "type": "Feature",
  "properties": {
    "gn:adm1_name":"Niigataken",
    "gn:adm2_name":"Kitakanbaragunsasakamimura",
    "gn:name":"Kumadou",
    "iso:country":"JP",
    "wof:name":"959-1907",
    "wof:placetype":"postalcode"
},
  "geometry": {"coordinates":[139.27420000000001,37.8625],"type":"Point"}
}