{
  "type": "Feature",
  "properties": {
    "gn:adm1_name":"Ibarakiken",
    "gn:adm2_name":"Tsuchiurashi",
    "gn:name":"Nakaarakawaokimachi",
    "iso:country":"JP",
    "wof:name":"300-0875",
    "wof:placetype":"postalcode"
},
  "geometry": {"coordinates":[140.16630000000001,36.0334],"type":"Point"}
}