{
  "type": "Feature",
  "properties": {
    "gn:adm1_name":"Yamagataken",
    "gn:adm2_name":"Obanazawashi",
    "gn:name":"Ichinono",
    "iso:country":"JP",
    "wof:name":"999-4208",
    "wof:placetype":"postalcode"
},
  "geometry": {"coordinates":[140.49760000000001,38.6572],"type":"Point"}
}