{
  "type": "Feature",
  "properties": {
    "gn:adm1_name":"Kyoutofu",
    "gn:adm2_name":"Ayabeshi",
    "gn:name":"Nishizakachou",
    "iso:country":"JP",
    "wof:name":"623-0364",
    "wof:placetype":"postalcode"
},
  "geometry": {"coordinates":[135.19669999999999,35.366],"type":"Point"}
}