{
  "type": "Feature",
  "properties": {
    "gn:adm1_name":"Chibaken",
    "gn:adm2_name":"Kaijougun'Iiokamachi",
    "gn:name":"Hiramatsu",
    "iso:country":"JP",
    "wof:name":"289-2708",
    "wof:placetype":"postalcode"
},
  "geometry": {"coordinates":[140.71879999999999,35.7032],"type":"Point"}
}