{
  "type": "Feature",
  "properties": {
    "gn:adm1_name":"Hyougoken",
    "gn:adm2_name":"Kasaishi",
    "gn:name":"Sakaechou",
    "iso:country":"JP",
    "wof:name":"675-2112",
    "wof:placetype":"postalcode"
},
  "geometry": {"coordinates":[134.88800000000001,34.8682],"type":"Point"}
}