{
  "type": "Feature",
  "properties": {
    "gn:adm1_name":"Shigaken",
    "gn:adm2_name":"Koukagunminakuchichou",
    "gn:name":"Nasaka",
    "iso:country":"JP",
    "wof:name":"528-0035",
    "wof:placetype":"postalcode"
},
  "geometry": {"coordinates":[136.16730000000001,34.9805],"type":"Point"}
}