{
  "type": "Feature",
  "properties": {
    "gn:adm1_name":"Yamagataken",
    "gn:adm2_name":"Mogamigunkaneyamamachi",
    "gn:name":"Ariya",
    "iso:country":"JP",
    "wof:name":"999-5401",
    "wof:placetype":"postalcode"
},
  "geometry": {"coordinates":[140.38310000000001,38.9047],"type":"Point"}
}