{
  "type": "Feature",
  "properties": {
    "gn:adm1_name":"Aichiken",
    "gn:adm2_name":"Atsumigun'Atsumichou",
    "gn:name":"Ishigami",
    "iso:country":"JP",
    "wof:name":"441-3611",
    "wof:placetype":"postalcode"
},
  "geometry": {"coordinates":[137.13890000000001,34.6385],"type":"Point"}
}