{
  "type": "Feature",
  "properties": {
    "gn:adm1_name":"Ishikawaken",
    "gn:adm2_name":"Hakuishi",
    "gn:name":"Ookawamachi",
    "iso:country":"JP",
    "wof:name":"925-0015",
    "wof:placetype":"postalcode"
},
  "geometry": {"coordinates":[136.77619999999999,36.9035],"type":"Point"}
}