{
  "type": "Feature",
  "properties": {
    "gn:adm1_name":"Kouchiken",
    "gn:adm2_name":"Agawagun'Agawamura",
    "gn:name":"Mineiwado",
    "iso:country":"JP",
    "wof:name":"781-1513",
    "wof:placetype":"postalcode"
},
  "geometry": {"coordinates":[133.2003,33.5914],"type":"Point"}
}