{
  "type": "Feature",
  "properties": {
    "gn:adm1_name":"Aichiken",
    "gn:adm2_name":"Toyokawashi",
    "gn:name":"Koukichou",
    "iso:country":"JP",
    "wof:name":"442-0882",
    "wof:placetype":"postalcode"
},
  "geometry": {"coordinates":[137.37739999999999,34.814],"type":"Point"}
}