{
  "type": "Feature",
  "properties": {
    "gn:adm1_name":"Tochigiken",
    "gn:adm2_name":"Utsunomiyashi",
    "gn:name":"Tokamichou",
    "iso:country":"JP",
    "wof:name":"320-0856",
    "wof:placetype":"postalcode"
},
  "geometry": {"coordinates":[139.8417,36.5515],"type":"Point"}
}