{
  "type": "Feature",
  "properties": {
    "gn:adm1_name":"Kagoshimaken",
    "gn:adm2_name":"Izumiguntakaonochou",
    "gn:name":"Shimozuru",
    "iso:country":"JP",
    "wof:name":"899-0405",
    "wof:placetype":"postalcode"
},
  "geometry": {"coordinates":[130.29519999999999,32.0907],"type":"Point"}
}