{
  "type": "Feature",
  "properties": {
    "gn:adm1_name":"Chibaken",
    "gn:adm2_name":"Futtsushi",
    "gn:name":"Sasage",
    "iso:country":"JP",
    "wof:name":"293-0055",
    "wof:placetype":"postalcode"
},
  "geometry": {"coordinates":[139.874,35.2424],"type":"Point"}
}