{
  "type": "Feature",
  "properties": {
    "gn:adm1_name":"Okinawaken",
    "gn:adm2_name":"Nakagamigunyonashirochou",
    "gn:name":"Nohen",
    "iso:country":"JP",
    "wof:name":"904-2307",
    "wof:placetype":"postalcode"
},
  "geometry": {"coordinates":[127.9096,26.313],"type":"Point"}
}