{
  "type": "Feature",
  "properties": {
    "gn:adm1_name":"Miyazakiken",
    "gn:adm2_name":"Nichinanshi",
    "gn:name":"Yoshinokata",
    "iso:country":"JP",
    "wof:name":"889-2513",
    "wof:placetype":"postalcode"
},
  "geometry": {"coordinates":[131.3288,31.6322],"type":"Point"}
}