{
  "type": "Feature",
  "properties": {
    "gn:adm1_name":"Kouchiken",
    "gn:adm2_name":"Takaokagunhidakamura",
    "gn:name":"Hongou",
    "iso:country":"JP",
    "wof:name":"781-2153",
    "wof:placetype":"postalcode"
},
  "geometry": {"coordinates":[133.36170000000001,33.5327],"type":"Point"}
}