{
  "type": "Feature",
  "properties": {
    "gn:adm1_name":"Toukyouto",
    "gn:adm2_name":"Bunkyouku",
    "gn:name":"Ootsuka",
    "iso:country":"JP",
    "wof:name":"112-0012",
    "wof:placetype":"postalcode"
},
  "geometry": {"coordinates":[139.73150000000001,35.7225],"type":"Point"}
}