{
  "type": "Feature",
  "properties": {
    "gn:adm1_name":"Aichiken",
    "gn:adm2_name":"Kounanshi",
    "gn:name":"Hoteishimoyamachouhigashi",
    "iso:country":"JP",
    "wof:name":"483-8142",
    "wof:placetype":"postalcode"
},
  "geometry": {"coordinates":[136.8717,35.3165],"type":"Point"}
}