{
  "type": "Feature",
  "properties": {
    "gn:adm1_name":"Oosakafu",
    "gn:adm2_name":"Sakaishi",
    "gn:name":"Chikkouhamaderanishimachi",
    "iso:country":"JP",
    "wof:name":"592-8352",
    "wof:placetype":"postalcode"
},
  "geometry": {"coordinates":[135.4119,34.5471],"type":"Point"}
}