{
  "type": "Feature",
  "properties": {
    "gn:adm1_name":"Saitamaken",
    "gn:adm2_name":"Sayamashi",
    "gn:name":"Inariyama",
    "iso:country":"JP",
    "wof:name":"350-1324",
    "wof:placetype":"postalcode"
},
  "geometry": {"coordinates":[139.39599999999999,35.8432],"type":"Point"}
}