{
  "type": "Feature",
  "properties": {
    "gn:adm1_name":"Toyamaken",
    "gn:adm2_name":"Himishi",
    "gn:name":"Waki",
    "iso:country":"JP",
    "wof:name":"935-0401",
    "wof:placetype":"postalcode"
},
  "geometry": {"coordinates":[137.0472,36.9575],"type":"Point"}
}