{
  "type": "Feature",
  "properties": {
    "gn:adm1_name":"Aichiken",
    "gn:adm2_name":"Toyohashishi",
    "gn:name":"Higashinananechou",
    "iso:country":"JP",
    "wof:name":"441-3201",
    "wof:placetype":"postalcode"
},
  "geometry": {"coordinates":[137.4203,34.6856],"type":"Point"}
}