{
  "type": "Feature",
  "properties": {
    "gn:adm1_name":"Aichiken",
    "gn:adm2_name":"Nagoyashichikusaku",
    "gn:name":"Furouchou",
    "iso:country":"JP",
    "wof:name":"464-0814",
    "wof:placetype":"postalcode"
},
  "geometry": {"coordinates":[136.96780000000001,35.1551],"type":"Point"}
}