{
  "type": "Feature",
  "properties": {
    "gn:adm1_name":"Shigaken",
    "gn:adm2_name":"Koukagunminakuchichou",
    "gn:name":"Rokushin",
    "iso:country":"JP",
    "wof:name":"528-0014",
    "wof:placetype":"postalcode"
},
  "geometry": {"coordinates":[136.172,34.9691],"type":"Point"}
}