{
  "type": "Feature",
  "properties": {
    "gn:adm1_name":"Aichiken",
    "gn:adm2_name":"Okazakishi",
    "gn:name":"Yonagouchichou",
    "iso:country":"JP",
    "wof:name":"444-3167",
    "wof:placetype":"postalcode"
},
  "geometry": {"coordinates":[137.22239999999999,34.9932],"type":"Point"}
}