{
  "type": "Feature",
  "properties": {
    "gn:adm1_name":"Yamagataken",
    "gn:adm2_name":"Higashitagawagunhaguromachi",
    "gn:name":"Ishinoshinden",
    "iso:country":"JP",
    "wof:name":"997-0155",
    "wof:placetype":"postalcode"
},
  "geometry": {"coordinates":[139.8638,38.7053],"type":"Point"}
}