{
  "type": "Feature",
  "properties": {
    "gn:adm1_name":"Miyagiken",
    "gn:adm2_name":"Sendaishiizumiku",
    "gn:name":"Houzawa",
    "iso:country":"JP",
    "wof:name":"981-3226",
    "wof:placetype":"postalcode"
},
  "geometry": {"coordinates":[140.78919999999999,38.3685],"type":"Point"}
}