{
  "type": "Feature",
  "properties": {
    "gn:adm1_name":"Naganoken",
    "gn:adm2_name":"Kisogunmitakemura",
    "gn:name":"Mitakemuraichien",
    "iso:country":"JP",
    "wof:name":"397-0101",
    "wof:placetype":"postalcode"
},
  "geometry": {"coordinates":[137.62129999999999,35.8515],"type":"Point"}
}