{
  "type": "Feature",
  "properties": {
    "gn:adm1_name":"Kyoutofu",
    "gn:adm2_name":"Kyoutoshifushimiku",
    "gn:name":"Ishidaooukechou",
    "iso:country":"JP",
    "wof:name":"601-1431",
    "wof:placetype":"postalcode"
},
  "geometry": {"coordinates":[135.8073,34.9422],"type":"Point"}
}