{
  "type": "Feature",
  "properties": {
    "gn:adm1_name":"Fukushimaken",
    "gn:adm2_name":"Oonumagun'Aiduhongoumachi",
    "gn:name":"Michinishikou",
    "iso:country":"JP",
    "wof:name":"969-6129",
    "wof:placetype":"postalcode"
},
  "geometry": {"coordinates":[139.8888,37.4497],"type":"Point"}
}