{
  "type": "Feature",
  "properties": {
    "gn:adm1_name":"Shigaken",
    "gn:adm2_name":"Kanzakigungokashouchou",
    "gn:name":"Kondou",
    "iso:country":"JP",
    "wof:name":"529-1405",
    "wof:placetype":"postalcode"
},
  "geometry": {"coordinates":[136.1799,35.1547],"type":"Point"}
}