{
  "type": "Feature",
  "properties": {
    "gn:adm1_name":"Naganoken",
    "gn:adm2_name":"Kisogunnarakawamura",
    "gn:name":"Hirasawa",
    "iso:country":"JP",
    "wof:name":"399-6302",
    "wof:placetype":"postalcode"
},
  "geometry": {"coordinates":[137.8312,35.9802],"type":"Point"}
}