{
  "type": "Feature",
  "properties": {
    "gn:adm1_name":"Wakayamaken",
    "gn:adm2_name":"Wakayamashi",
    "gn:name":"Honmachi",
    "iso:country":"JP",
    "wof:name":"640-8033",
    "wof:placetype":"postalcode"
},
  "geometry": {"coordinates":[135.17449999999999,34.2366],"type":"Point"}
}