{
  "type": "Feature",
  "properties": {
    "gn:adm1_name":"Gunmaken",
    "gn:adm2_name":"Ootashi",
    "gn:name":"Takahayashikotobukichou",
    "iso:country":"JP",
    "wof:name":"373-0824",
    "wof:placetype":"postalcode"
},
  "geometry": {"coordinates":[139.37549999999999,36.2627],"type":"Point"}
}