{
  "type": "Feature",
  "properties": {
    "gn:adm1_name":"Tottoriken",
    "gn:adm2_name":"Yazugunkoogechou",
    "gn:name":"Kunouji",
    "iso:country":"JP",
    "wof:name":"680-0451",
    "wof:placetype":"postalcode"
},
  "geometry": {"coordinates":[134.24680000000001,35.4024],"type":"Point"}
}