{
  "type": "Feature",
  "properties": {
    "gn:adm1_name":"Chibaken",
    "gn:adm2_name":"Matsudoshi",
    "gn:name":"Shichiuemonshinden",
    "iso:country":"JP",
    "wof:name":"271-0041",
    "wof:placetype":"postalcode"
},
  "geometry": {"coordinates":[139.89449999999999,35.8268],"type":"Point"}
}