{
  "type": "Feature",
  "properties": {
    "gn:adm1_name":"Tochigiken",
    "gn:adm2_name":"Shimotsugagunnogimachi",
    "gn:name":"Nakaya",
    "iso:country":"JP",
    "wof:name":"329-0113",
    "wof:placetype":"postalcode"
},
  "geometry": {"coordinates":[139.73670000000001,36.2151],"type":"Point"}
}