{
  "type": "Feature",
  "properties": {
    "gn:adm1_name":"Niigataken",
    "gn:adm2_name":"Jouetsushi",
    "gn:name":"Sanden",
    "iso:country":"JP",
    "wof:name":"949-1714",
    "wof:placetype":"postalcode"
},
  "geometry": {"coordinates":[138.2313,37.1446],"type":"Point"}
}