{
  "type": "Feature",
  "properties": {
    "gn:adm1_name":"Ibarakiken",
    "gn:adm2_name":"Kitasoumaguntonemachi",
    "gn:name":"Shimozone",
    "iso:country":"JP",
    "wof:name":"300-1632",
    "wof:placetype":"postalcode"
},
  "geometry": {"coordinates":[140.14670000000001,35.8715],"type":"Point"}
}