{
  "type": "Feature",
  "properties": {
    "gn:adm1_name":"Toukyouto",
    "gn:adm2_name":"Hamurashi",
    "gn:name":"Hane",
    "iso:country":"JP",
    "wof:name":"205-0012",
    "wof:placetype":"postalcode"
},
  "geometry": {"coordinates":[139.32259999999999,35.7635],"type":"Point"}
}