{
  "type": "Feature",
  "properties": {
    "gn:adm1_name":"Toyamaken",
    "gn:adm2_name":"Nishitonamigunfukumitsumachi",
    "gn:name":"Kaihotsu",
    "iso:country":"JP",
    "wof:name":"939-1667",
    "wof:placetype":"postalcode"
},
  "geometry": {"coordinates":[136.85990000000001,36.5554],"type":"Point"}
}