{
  "type": "Feature",
  "properties": {
    "gn:adm1_name":"Fukushimaken",
    "gn:adm2_name":"Kawanumagunyanaidumachi",
    "gn:name":"Karuizawa",
    "iso:country":"JP",
    "wof:name":"969-7203",
    "wof:placetype":"postalcode"
},
  "geometry": {"coordinates":[139.74799999999999,37.4805],"type":"Point"}
}