{
  "type": "Feature",
  "properties": {
    "gn:adm1_name":"Okinawaken",
    "gn:adm2_name":"Shimajiriguntokashikison",
    "gn:name":"Ikanikeisaiganaibaai",
    "iso:country":"JP",
    "wof:name":"901-3500",
    "wof:placetype":"postalcode"
},
  "geometry": {"coordinates":[127.3582,26.1886],"type":"Point"}
}