{
  "type": "Feature",
  "properties": {
    "gn:adm1_name":"Wakayamaken",
    "gn:adm2_name":"Higashimurogunnachikatsuurachou",
    "gn:name":"Shimosato",
    "iso:country":"JP",
    "wof:name":"649-5142",
    "wof:placetype":"postalcode"
},
  "geometry": {"coordinates":[135.92439999999999,33.5799],"type":"Point"}
}