{
  "type": "Feature",
  "properties": {
    "gn:adm1_name":"Ibarakiken",
    "gn:adm2_name":"Ryuugasakishi",
    "gn:name":"Kawasakimachi",
    "iso:country":"JP",
    "wof:name":"301-0048",
    "wof:placetype":"postalcode"
},
  "geometry": {"coordinates":[140.1464,35.927],"type":"Point"}
}