{
  "type": "Feature",
  "properties": {
    "gn:adm1_name":"Gifuken",
    "gn:adm2_name":"Mizunamishi",
    "gn:name":"Myougadai",
    "iso:country":"JP",
    "wof:name":"509-6105",
    "wof:placetype":"postalcode"
},
  "geometry": {"coordinates":[137.24539999999999,35.3435],"type":"Point"}
}