{
  "type": "Feature",
  "properties": {
    "gn:adm1_name":"Shimaneken",
    "gn:adm2_name":"Iishigun'Akagichou",
    "gn:name":"Maki",
    "iso:country":"JP",
    "wof:name":"690-3404",
    "wof:placetype":"postalcode"
},
  "geometry": {"coordinates":[132.7483,35.0019],"type":"Point"}
}