{
  "type": "Feature",
  "properties": {
    "gn:adm1_name":"Nagasakiken",
    "gn:adm2_name":"Shimoagatagunmitsushimachou",
    "gn:name":"Shimayama",
    "iso:country":"JP",
    "wof:name":"817-0514",
    "wof:placetype":"postalcode"
},
  "geometry": {"coordinates":[129.31720000000001,34.3189],"type":"Point"}
}