{
  "type": "Feature",
  "properties": {
    "gn:adm1_name":"Niigataken",
    "gn:adm2_name":"Iwafunegun'Asahimura",
    "gn:name":"Sekiguchi",
    "iso:country":"JP",
    "wof:name":"958-0225",
    "wof:placetype":"postalcode"
},
  "geometry": {"coordinates":[139.5538,38.3049],"type":"Point"}
}