{
  "type": "Feature",
  "properties": {
    "gn:adm1_name":"Chibaken",
    "gn:adm2_name":"Shiroishi",
    "gn:name":"Kawarago",
    "iso:country":"JP",
    "wof:name":"270-1403",
    "wof:placetype":"postalcode"
},
  "geometry": {"coordinates":[140.06190000000001,35.8183],"type":"Point"}
}