{
  "type": "Feature",
  "properties": {
    "gn:adm1_name":"Tochigiken",
    "gn:adm2_name":"Sanoshi",
    "gn:name":"Tajimachou",
    "iso:country":"JP",
    "wof:name":"327-0031",
    "wof:placetype":"postalcode"
},
  "geometry": {"coordinates":[139.56540000000001,36.2953],"type":"Point"}
}