{
  "type": "Feature",
  "properties": {
    "gn:adm1_name":"Aichiken",
    "gn:adm2_name":"Kitashitaraguntoyonemura",
    "gn:name":"Komadate",
    "iso:country":"JP",
    "wof:name":"449-0402",
    "wof:placetype":"postalcode"
},
  "geometry": {"coordinates":[137.75,35.1508],"type":"Point"}
}