{
  "type": "Feature",
  "properties": {
    "gn:adm1_name":"Kagoshimaken",
    "gn:adm2_name":"Ooshimaguntokunoshimachou",
    "gn:name":"Asahigaoka",
    "iso:country":"JP",
    "wof:name":"891-7116",
    "wof:placetype":"postalcode"
},
  "geometry": {"coordinates":[129.0018,27.7672],"type":"Point"}
}