{
  "type": "Feature",
  "properties": {
    "gn:adm1_name":"Gifuken",
    "gn:adm2_name":"Oogakishi",
    "gn:name":"Oomura",
    "iso:country":"JP",
    "wof:name":"503-0814",
    "wof:placetype":"postalcode"
},
  "geometry": {"coordinates":[136.65289999999999,35.3529],"type":"Point"}
}