{
  "type": "Feature",
  "properties": {
    "gn:adm1_name":"Kouchiken",
    "gn:adm2_name":"Agawagun'Agawamura",
    "gn:name":"Oohira",
    "iso:country":"JP",
    "wof:name":"781-1744",
    "wof:placetype":"postalcode"
},
  "geometry": {"coordinates":[133.14320000000001,33.5625],"type":"Point"}
}