{
  "type": "Feature",
  "properties": {
    "gn:adm1_name":"Tottoriken",
    "gn:adm2_name":"Saihakugundaisenchou",
    "gn:name":"Kuninobu",
    "iso:country":"JP",
    "wof:name":"689-3309",
    "wof:placetype":"postalcode"
},
  "geometry": {"coordinates":[133.45249999999999,35.4863],"type":"Point"}
}