{
  "type": "Feature",
  "properties": {
    "gn:adm1_name":"Tottoriken",
    "gn:adm2_name":"Saihakugundaisenchou",
    "gn:name":"Tomioka",
    "iso:country":"JP",
    "wof:name":"689-3325",
    "wof:placetype":"postalcode"
},
  "geometry": {"coordinates":[133.4453,35.4689],"type":"Point"}
}