{
  "type": "Feature",
  "properties": {
    "gn:adm1_name":"Kyoutofu",
    "gn:adm2_name":"Kyoutoshishimogyouku",
    "gn:name":"Yabushitachou",
    "iso:country":"JP",
    "wof:name":"600-8448",
    "wof:placetype":"postalcode"
},
  "geometry": {"coordinates":[135.7559,34.9989],"type":"Point"}
}