{
  "type": "Feature",
  "properties": {
    "gn:adm1_name":"Ibarakiken",
    "gn:adm2_name":"Tsukubashi",
    "gn:name":"Koyama",
    "iso:country":"JP",
    "wof:name":"300-1276",
    "wof:placetype":"postalcode"
},
  "geometry": {"coordinates":[140.09020000000001,35.9916],"type":"Point"}
}