{
  "type": "Feature",
  "properties": {
    "gn:adm1_name":"Chibaken",
    "gn:adm2_name":"Higashikatsushikagunshounanmachi",
    "gn:name":"Minowa",
    "iso:country":"JP",
    "wof:name":"277-0912",
    "wof:placetype":"postalcode"
},
  "geometry": {"coordinates":[140.0223,35.8519],"type":"Point"}
}