{
  "type": "Feature",
  "properties": {
    "gn:adm1_name":"Miyagiken",
    "gn:adm2_name":"Kurokawaguntaiwachou",
    "gn:name":"Tsurusuoodaira",
    "iso:country":"JP",
    "wof:name":"981-3411",
    "wof:placetype":"postalcode"
},
  "geometry": {"coordinates":[140.96100000000001,38.42],"type":"Point"}
}