{
  "type": "Feature",
  "properties": {
    "gn:adm1_name":"Hyougoken",
    "gn:adm2_name":"Nishinomiyashi",
    "gn:name":"Tsutooogochou",
    "iso:country":"JP",
    "wof:name":"663-8243",
    "wof:placetype":"postalcode"
},
  "geometry": {"coordinates":[135.35679999999999,34.7353],"type":"Point"}
}