{
  "type": "Feature",
  "properties": {
    "gn:adm1_name":"Ibarakiken",
    "gn:adm2_name":"Moriyashi",
    "gn:name":"Misono",
    "iso:country":"JP",
    "wof:name":"302-0124",
    "wof:placetype":"postalcode"
},
  "geometry": {"coordinates":[140.001,35.9247],"type":"Point"}
}