{
  "type": "Feature",
  "properties": {
    "gn:adm1_name":"Okayamaken",
    "gn:adm2_name":"Mitsugunkamogawachou",
    "gn:name":"Ooki",
    "iso:country":"JP",
    "wof:name":"709-2663",
    "wof:placetype":"postalcode"
},
  "geometry": {"coordinates":[133.77869999999999,34.9093],"type":"Point"}
}