{
  "type": "Feature",
  "properties": {
    "gn:adm1_name":"Hiroshimaken",
    "gn:adm2_name":"Kureshi",
    "gn:name":"Higashikatayamachou",
    "iso:country":"JP",
    "wof:name":"737-0805",
    "wof:placetype":"postalcode"
},
  "geometry": {"coordinates":[132.56639999999999,34.2534],"type":"Point"}
}