{
  "type": "Feature",
  "properties": {
    "gn:adm1_name":"Shizuokaken",
    "gn:adm2_name":"Shimadashi",
    "gn:name":"Matsubachou",
    "iso:country":"JP",
    "wof:name":"427-0052",
    "wof:placetype":"postalcode"
},
  "geometry": {"coordinates":[138.1908,34.8405],"type":"Point"}
}