{
  "type": "Feature",
  "properties": {
    "gn:adm1_name":"Oosakafu",
    "gn:adm2_name":"Higashioosakashi",
    "gn:name":"Higashikounoikechou",
    "iso:country":"JP",
    "wof:name":"578-0973",
    "wof:placetype":"postalcode"
},
  "geometry": {"coordinates":[135.6122,34.6946],"type":"Point"}
}