{
  "type": "Feature",
  "properties": {
    "gn:adm1_name":"Shizuokaken",
    "gn:adm2_name":"Numadushi",
    "gn:name":"Matsushita",
    "iso:country":"JP",
    "wof:name":"410-0864",
    "wof:placetype":"postalcode"
},
  "geometry": {"coordinates":[138.84729999999999,35.0988],"type":"Point"}
}