{
  "type": "Feature",
  "properties": {
    "gn:adm1_name":"Fukushimaken",
    "gn:adm2_name":"Tamuragunmiharumachi",
    "gn:name":"Yamada",
    "iso:country":"JP",
    "wof:name":"963-7733",
    "wof:placetype":"postalcode"
},
  "geometry": {"coordinates":[140.4528,37.4282],"type":"Point"}
}