{
  "type": "Feature",
  "properties": {
    "gn:adm1_name":"Nagasakiken",
    "gn:adm2_name":"Saseboshi",
    "gn:name":"Kamiainourachou",
    "iso:country":"JP",
    "wof:name":"858-0915",
    "wof:placetype":"postalcode"
},
  "geometry": {"coordinates":[129.6687,33.1943],"type":"Point"}
}