{
  "type": "Feature",
  "properties": {
    "gn:adm1_name":"Aichiken",
    "gn:adm2_name":"Chitaguntaketoyochou",
    "gn:name":"Asamizu",
    "iso:country":"JP",
    "wof:name":"470-2314",
    "wof:placetype":"postalcode"
},
  "geometry": {"coordinates":[136.91980000000001,34.864],"type":"Point"}
}