{
  "type": "Feature",
  "properties": {
    "gn:adm1_name":"Gunmaken",
    "gn:adm2_name":"Gunmagunmisatomachi",
    "gn:name":"Shirakawa",
    "iso:country":"JP",
    "wof:name":"370-3117",
    "wof:placetype":"postalcode"
},
  "geometry": {"coordinates":[138.95169999999999,36.3704],"type":"Point"}
}