{
  "type": "Feature",
  "properties": {
    "gn:adm1_name":"Toukyouto",
    "gn:adm2_name":"Machidashi",
    "gn:name":"Tamagawagakuen",
    "iso:country":"JP",
    "wof:name":"194-0041",
    "wof:placetype":"postalcode"
},
  "geometry": {"coordinates":[139.46019999999999,35.5628],"type":"Point"}
}