{
  "type": "Feature",
  "properties": {
    "gn:adm1_name":"Tochigiken",
    "gn:adm2_name":"Nasugun'Ogawamachi",
    "gn:name":"Ogawa",
    "iso:country":"JP",
    "wof:name":"324-0501",
    "wof:placetype":"postalcode"
},
  "geometry": {"coordinates":[140.1224,36.771],"type":"Point"}
}