{
  "type": "Feature",
  "properties": {
    "gn:adm1_name":"Shizuokaken",
    "gn:adm2_name":"Shimadashi",
    "gn:name":"Nakamizochou",
    "iso:country":"JP",
    "wof:name":"427-0047",
    "wof:placetype":"postalcode"
},
  "geometry": {"coordinates":[138.16540000000001,34.84],"type":"Point"}
}