{
  "type": "Feature",
  "properties": {
    "gn:adm1_name":"Kagawaken",
    "gn:adm2_name":"Takamatsushi",
    "gn:name":"Kamedaminamimachi",
    "iso:country":"JP",
    "wof:name":"761-0432",
    "wof:placetype":"postalcode"
},
  "geometry": {"coordinates":[134.11150000000001,34.279],"type":"Point"}
}