{
  "type": "Feature",
  "properties": {
    "gn:adm1_name":"Kyoutofu",
    "gn:adm2_name":"Kyoutoshinishikyouku",
    "gn:name":"Katagiharabonyama",
    "iso:country":"JP",
    "wof:name":"615-8165",
    "wof:placetype":"postalcode"
},
  "geometry": {"coordinates":[135.68690000000001,34.9744],"type":"Point"}
}