{
  "type": "Feature",
  "properties": {
    "gn:adm1_name":"Saitamaken",
    "gn:adm2_name":"Satteshi",
    "gn:name":"Ikanikeisaiganaibaai",
    "iso:country":"JP",
    "wof:name":"340-0100",
    "wof:placetype":"postalcode"
},
  "geometry": {"coordinates":[139.7132,36.0705],"type":"Point"}
}