{
  "type": "Feature",
  "properties": {
    "gn:adm1_name":"Fukuiken",
    "gn:adm2_name":"Fukuishi",
    "gn:name":"Sunagosakachou",
    "iso:country":"JP",
    "wof:name":"910-3143",
    "wof:placetype":"postalcode"
},
  "geometry": {"coordinates":[136.1482,36.145],"type":"Point"}
}