{
  "type": "Feature",
  "properties": {
    "gn:adm1_name":"Sagaken",
    "gn:adm2_name":"Fujitsuguntarachou",
    "gn:name":"Ikanikeisaiganaibaai",
    "iso:country":"JP",
    "wof:name":"849-1600",
    "wof:placetype":"postalcode"
},
  "geometry": {"coordinates":[130.2236,32.9587],"type":"Point"}
}