{
  "type": "Feature",
  "properties": {
    "gn:adm1_name":"Okayamaken",
    "gn:adm2_name":"Kurashikishi",
    "gn:name":"Horinan",
    "iso:country":"JP",
    "wof:name":"710-0841",
    "wof:placetype":"postalcode"
},
  "geometry": {"coordinates":[133.75800000000001,34.5726],"type":"Point"}
}