{
  "type": "Feature",
  "properties": {
    "gn:adm1_name":"Gunmaken",
    "gn:adm2_name":"Takasakishi",
    "gn:name":"Katamachi",
    "iso:country":"JP",
    "wof:name":"370-0814",
    "wof:placetype":"postalcode"
},
  "geometry": {"coordinates":[139.00370000000001,36.3298],"type":"Point"}
}