{
  "type": "Feature",
  "properties": {
    "gn:adm1_name":"Yamagataken",
    "gn:adm2_name":"Higashineshi",
    "gn:name":"Jinmachichuuou",
    "iso:country":"JP",
    "wof:name":"999-3763",
    "wof:placetype":"postalcode"
},
  "geometry": {"coordinates":[140.3794,38.4076],"type":"Point"}
}