{
  "type": "Feature",
  "properties": {
    "gn:adm1_name":"Toyamaken",
    "gn:adm2_name":"Higashitonamigunfukunomachi",
    "gn:name":"Shimoyoshie",
    "iso:country":"JP",
    "wof:name":"939-1543",
    "wof:placetype":"postalcode"
},
  "geometry": {"coordinates":[136.89760000000001,36.5754],"type":"Point"}
}