{
  "type": "Feature",
  "properties": {
    "gn:adm1_name":"Aichiken",
    "gn:adm2_name":"Toyotashi",
    "gn:name":"Hondachou",
    "iso:country":"JP",
    "wof:name":"473-0938",
    "wof:placetype":"postalcode"
},
  "geometry": {"coordinates":[137.0711,35.0489],"type":"Point"}
}