{
  "type": "Feature",
  "properties": {
    "gn:adm1_name":"Tochigiken",
    "gn:adm2_name":"Ootawarashi",
    "gn:name":"Handa",
    "iso:country":"JP",
    "wof:name":"324-0002",
    "wof:placetype":"postalcode"
},
  "geometry": {"coordinates":[140.08760000000001,36.9131],"type":"Point"}
}