{
  "type": "Feature",
  "properties": {
    "gn:adm1_name":"Ibarakiken",
    "gn:adm2_name":"Mitoshi",
    "gn:name":"Tayachou",
    "iso:country":"JP",
    "wof:name":"311-4204",
    "wof:placetype":"postalcode"
},
  "geometry": {"coordinates":[140.44720000000001,36.4265],"type":"Point"}
}