{
  "type": "Feature",
  "properties": {
    "gn:adm1_name":"Aichiken",
    "gn:adm2_name":"Chitashi",
    "gn:name":"Minamikasuyashinkai",
    "iso:country":"JP",
    "wof:name":"478-0026",
    "wof:placetype":"postalcode"
},
  "geometry": {"coordinates":[136.8372,34.9384],"type":"Point"}
}