{
  "type": "Feature",
  "properties": {
    "gn:adm1_name":"Miyagiken",
    "gn:adm2_name":"Toodagunwakuyachou",
    "gn:name":"Narisawa",
    "iso:country":"JP",
    "wof:name":"987-0286",
    "wof:placetype":"postalcode"
},
  "geometry": {"coordinates":[141.15600000000001,38.5668],"type":"Point"}
}