{
  "type": "Feature",
  "properties": {
    "gn:adm1_name":"Kyoutofu",
    "gn:adm2_name":"Kyoutoshiyamashinaku",
    "gn:name":"Otowaisejukuchou",
    "iso:country":"JP",
    "wof:name":"607-8072",
    "wof:placetype":"postalcode"
},
  "geometry": {"coordinates":[135.82130000000001,34.984],"type":"Point"}
}