{
  "type": "Feature",
  "properties": {
    "gn:adm1_name":"Aichiken",
    "gn:adm2_name":"Handashi",
    "gn:name":"Yokomatsukamichou",
    "iso:country":"JP",
    "wof:name":"475-0076",
    "wof:placetype":"postalcode"
},
  "geometry": {"coordinates":[136.9348,34.9157],"type":"Point"}
}