{
  "type": "Feature",
  "properties": {
    "gn:adm1_name":"Niigataken",
    "gn:adm2_name":"Nakakubikigunkiyosatomura",
    "gn:name":"Higashifukushima",
    "iso:country":"JP",
    "wof:name":"943-0505",
    "wof:placetype":"postalcode"
},
  "geometry": {"coordinates":[138.3287,37.0645],"type":"Point"}
}