{
  "type": "Feature",
  "properties": {
    "gn:adm1_name":"Miyagiken",
    "gn:adm2_name":"Watarigunwatarichou",
    "gn:name":"Ookumakamigoori",
    "iso:country":"JP",
    "wof:name":"989-2381",
    "wof:placetype":"postalcode"
},
  "geometry": {"coordinates":[140.85120000000001,38.0573],"type":"Point"}
}