{
  "type": "Feature",
  "properties": {
    "gn:adm1_name":"Ishikawaken",
    "gn:adm2_name":"Nomigunneagarimachi",
    "gn:name":"Akaimachi",
    "iso:country":"JP",
    "wof:name":"929-0101",
    "wof:placetype":"postalcode"
},
  "geometry": {"coordinates":[136.48439999999999,36.4558],"type":"Point"}
}