{
  "type": "Feature",
  "properties": {
    "gn:adm1_name":"Hyougoken",
    "gn:adm2_name":"Akashishi",
    "gn:name":"Daidouchou",
    "iso:country":"JP",
    "wof:name":"673-0029",
    "wof:placetype":"postalcode"
},
  "geometry": {"coordinates":[134.97839999999999,34.6559],"type":"Point"}
}