{
  "type": "Feature",
  "properties": {
    "gn:adm1_name":"Hyougoken",
    "gn:adm2_name":"Shisougunyasutomichou",
    "gn:name":"Sebato",
    "iso:country":"JP",
    "wof:name":"671-2423",
    "wof:placetype":"postalcode"
},
  "geometry": {"coordinates":[134.5822,34.958],"type":"Point"}
}