{
  "type": "Feature",
  "properties": {
    "gn:adm1_name":"Kanagawaken",
    "gn:adm2_name":"Yokohamashitsudukiku",
    "gn:name":"Edaminamichou",
    "iso:country":"JP",
    "wof:name":"224-0008",
    "wof:placetype":"postalcode"
},
  "geometry": {"coordinates":[139.56379999999999,35.5556],"type":"Point"}
}