{
  "type": "Feature",
  "properties": {
    "gn:adm1_name":"Tottoriken",
    "gn:adm2_name":"Hinogunnichinanchou",
    "gn:name":"Shouyama",
    "iso:country":"JP",
    "wof:name":"689-5211",
    "wof:placetype":"postalcode"
},
  "geometry": {"coordinates":[133.31960000000001,35.1694],"type":"Point"}
}