{
  "type": "Feature",
  "properties": {
    "gn:adm1_name":"Chibaken",
    "gn:adm2_name":"Naritashi",
    "gn:name":"Nanpeidai",
    "iso:country":"JP",
    "wof:name":"286-0042",
    "wof:placetype":"postalcode"
},
  "geometry": {"coordinates":[140.3057,35.7707],"type":"Point"}
}