{
  "type": "Feature",
  "properties": {
    "gn:adm1_name":"Ibarakiken",
    "gn:adm2_name":"Hitachishi",
    "gn:name":"Saiwaichou",
    "iso:country":"JP",
    "wof:name":"317-0073",
    "wof:placetype":"postalcode"
},
  "geometry": {"coordinates":[140.6584,36.59],"type":"Point"}
}