{
  "type": "Feature",
  "properties": {
    "gn:adm1_name":"Oosakafu",
    "gn:adm2_name":"Kishiwadashi",
    "gn:name":"Harukiizumichou",
    "iso:country":"JP",
    "wof:name":"596-0035",
    "wof:placetype":"postalcode"
},
  "geometry": {"coordinates":[135.38059999999999,34.4762],"type":"Point"}
}