{
  "type": "Feature",
  "properties": {
    "gn:adm1_name":"Oosakafu",
    "gn:adm2_name":"Yaoshi",
    "gn:name":"Yamamotochouminami",
    "iso:country":"JP",
    "wof:name":"581-0013",
    "wof:placetype":"postalcode"
},
  "geometry": {"coordinates":[135.61949999999999,34.6241],"type":"Point"}
}