{
  "type": "Feature",
  "properties": {
    "gn:adm1_name":"Aichiken",
    "gn:adm2_name":"Kitashitaragunshitarachou",
    "gn:name":"Kada",
    "iso:country":"JP",
    "wof:name":"441-2315",
    "wof:placetype":"postalcode"
},
  "geometry": {"coordinates":[137.61660000000001,35.0717],"type":"Point"}
}