{
  "type": "Feature",
  "properties": {
    "gn:adm1_name":"Fukuokaken",
    "gn:adm2_name":"Fukuokashiminamiku",
    "gn:name":"Osa",
    "iso:country":"JP",
    "wof:name":"811-1313",
    "wof:placetype":"postalcode"
},
  "geometry": {"coordinates":[130.4367,33.5382],"type":"Point"}
}