{
  "type": "Feature",
  "properties": {
    "gn:adm1_name":"Toyamaken",
    "gn:adm2_name":"Himishi",
    "gn:name":"Moridera",
    "iso:country":"JP",
    "wof:name":"935-0332",
    "wof:placetype":"postalcode"
},
  "geometry": {"coordinates":[136.96719999999999,36.8975],"type":"Point"}
}