{
  "type": "Feature",
  "properties": {
    "gn:adm1_name":"Wakayamaken",
    "gn:adm2_name":"Wakayamashi",
    "gn:name":"Mukai",
    "iso:country":"JP",
    "wof:name":"640-8431",
    "wof:placetype":"postalcode"
},
  "geometry": {"coordinates":[135.14680000000001,34.2576],"type":"Point"}
}