{
  "type": "Feature",
  "properties": {
    "gn:adm1_name":"Toyamaken",
    "gn:adm2_name":"Neigunyatsuomachi",
    "gn:name":"Kagamimachi",
    "iso:country":"JP",
    "wof:name":"939-2341",
    "wof:placetype":"postalcode"
},
  "geometry": {"coordinates":[137.1328,36.5777],"type":"Point"}
}