{
  "type": "Feature",
  "properties": {
    "gn:adm1_name":"Kyoutofu",
    "gn:adm2_name":"Kyoutoshishimogyouku",
    "gn:name":"Higashinochou",
    "iso:country":"JP",
    "wof:name":"600-8204",
    "wof:placetype":"postalcode"
},
  "geometry": {"coordinates":[135.7654,34.9849],"type":"Point"}
}