{
  "type": "Feature",
  "properties": {
    "gn:adm1_name":"Fukushimaken",
    "gn:adm2_name":"Shirakawashi",
    "gn:name":"Funada",
    "iso:country":"JP",
    "wof:name":"961-0013",
    "wof:placetype":"postalcode"
},
  "geometry": {"coordinates":[140.279,37.1221],"type":"Point"}
}