{
  "type": "Feature",
  "properties": {
    "gn:adm1_name":"Niigataken",
    "gn:adm2_name":"Higashikubikigunmatsudaimachi",
    "gn:name":"Touge",
    "iso:country":"JP",
    "wof:name":"942-1351",
    "wof:placetype":"postalcode"
},
  "geometry": {"coordinates":[138.53319999999999,37.1224],"type":"Point"}
}