{
  "type": "Feature",
  "properties": {
    "gn:adm1_name":"Fukuokaken",
    "gn:adm2_name":"Chikushinoshi",
    "gn:name":"Hondouji",
    "iso:country":"JP",
    "wof:name":"818-0007",
    "wof:placetype":"postalcode"
},
  "geometry": {"coordinates":[130.57929999999999,33.5252],"type":"Point"}
}