{
  "type": "Feature",
  "properties": {
    "gn:adm1_name":"Oosakafu",
    "gn:adm2_name":"Neyagawashi",
    "gn:name":"Nansuienchou",
    "iso:country":"JP",
    "wof:name":"572-0826",
    "wof:placetype":"postalcode"
},
  "geometry": {"coordinates":[135.61410000000001,34.7449],"type":"Point"}
}