{
  "type": "Feature",
  "properties": {
    "gn:adm1_name":"Toukyouto",
    "gn:adm2_name":"Kitaku",
    "gn:name":"Tabata",
    "iso:country":"JP",
    "wof:name":"114-0014",
    "wof:placetype":"postalcode"
},
  "geometry": {"coordinates":[139.75720000000001,35.7361],"type":"Point"}
}