{
  "type": "Feature",
  "properties": {
    "gn:adm1_name":"Kagawaken",
    "gn:adm2_name":"Marugameshi",
    "gn:name":"Imaduchou",
    "iso:country":"JP",
    "wof:name":"763-0051",
    "wof:placetype":"postalcode"
},
  "geometry": {"coordinates":[133.78299999999999,34.28],"type":"Point"}
}