{
  "type": "Feature",
  "properties": {
    "gn:adm1_name":"Fukuiken",
    "gn:adm2_name":"Sabaeshi",
    "gn:name":"Funatsuchou",
    "iso:country":"JP",
    "wof:name":"916-0054",
    "wof:placetype":"postalcode"
},
  "geometry": {"coordinates":[136.1816,35.9352],"type":"Point"}
}