{
  "type": "Feature",
  "properties": {
    "gn:adm1_name":"Kanagawaken",
    "gn:adm2_name":"Yokohamashiaobaku",
    "gn:name":"Umegaoka",
    "iso:country":"JP",
    "wof:name":"227-0052",
    "wof:placetype":"postalcode"
},
  "geometry": {"coordinates":[139.52590000000001,35.5356],"type":"Point"}
}