{
  "type": "Feature",
  "properties": {
    "gn:adm1_name":"Kumamotoken",
    "gn:adm2_name":"Utogunmisumimachi",
    "gn:name":"Teba",
    "iso:country":"JP",
    "wof:name":"869-3412",
    "wof:placetype":"postalcode"
},
  "geometry": {"coordinates":[130.5658,32.6308],"type":"Point"}
}