{
  "type": "Feature",
  "properties": {
    "gn:adm1_name":"Chibaken",
    "gn:adm2_name":"Funabashishi",
    "gn:name":"Shiomichou",
    "iso:country":"JP",
    "wof:name":"273-0016",
    "wof:placetype":"postalcode"
},
  "geometry": {"coordinates":[139.96950000000001,35.6767],"type":"Point"}
}