{
  "type": "Feature",
  "properties": {
    "gn:adm1_name":"Shizuokaken",
    "gn:adm2_name":"Inasagunmikkabichou",
    "gn:name":"Mikkabi",
    "iso:country":"JP",
    "wof:name":"431-1414",
    "wof:placetype":"postalcode"
},
  "geometry": {"coordinates":[137.55189999999999,34.8059],"type":"Point"}
}