{
  "type": "Feature",
  "properties": {
    "gn:adm1_name":"Fukushimaken",
    "gn:adm2_name":"Shirakawashi",
    "gn:name":"Kubanchou",
    "iso:country":"JP",
    "wof:name":"961-0875",
    "wof:placetype":"postalcode"
},
  "geometry": {"coordinates":[140.2054,37.1196],"type":"Point"}
}