{
  "type": "Feature",
  "properties": {
    "gn:adm1_name":"Fukuiken",
    "gn:adm2_name":"Sabaeshi",
    "gn:name":"Jimyoujichou",
    "iso:country":"JP",
    "wof:name":"916-0071",
    "wof:placetype":"postalcode"
},
  "geometry": {"coordinates":[136.14599999999999,35.9622],"type":"Point"}
}