{
  "type": "Feature",
  "properties": {
    "gn:adm1_name":"Fukuokaken",
    "gn:adm2_name":"Ukihaguntanushimarumachi",
    "gn:name":"Tanushimaru",
    "iso:country":"JP",
    "wof:name":"839-1233",
    "wof:placetype":"postalcode"
},
  "geometry": {"coordinates":[130.69229999999999,33.3431],"type":"Point"}
}