{
  "type": "Feature",
  "properties": {
    "gn:adm1_name":"Yamanashiken",
    "gn:adm2_name":"Minamikomagunmasuhochou",
    "gn:name":"Tenjinnakajou",
    "iso:country":"JP",
    "wof:name":"400-0503",
    "wof:placetype":"postalcode"
},
  "geometry": {"coordinates":[138.4589,35.5646],"type":"Point"}
}