{
  "type": "Feature",
  "properties": {
    "gn:adm1_name":"Hyougoken",
    "gn:adm2_name":"Kinosakigunkasumichou",
    "gn:name":"Nakano",
    "iso:country":"JP",
    "wof:name":"669-6556",
    "wof:placetype":"postalcode"
},
  "geometry": {"coordinates":[134.6123,35.5884],"type":"Point"}
}