{
  "type": "Feature",
  "properties": {
    "gn:adm1_name":"Aichiken",
    "gn:adm2_name":"Nagoyashimizuhoku",
    "gn:name":"Naeshirochou",
    "iso:country":"JP",
    "wof:name":"467-0841",
    "wof:placetype":"postalcode"
},
  "geometry": {"coordinates":[136.9237,35.1181],"type":"Point"}
}