{
  "type": "Feature",
  "properties": {
    "gn:adm1_name":"Hiroshimaken",
    "gn:adm2_name":"Kureshi",
    "gn:name":"Yayoichou",
    "iso:country":"JP",
    "wof:name":"737-0877",
    "wof:placetype":"postalcode"
},
  "geometry": {"coordinates":[132.5222,34.2794],"type":"Point"}
}