{
  "type": "Feature",
  "properties": {
    "gn:adm1_name":"Fukushimaken",
    "gn:adm2_name":"Nihonmatsushi",
    "gn:name":"Saiwaichou",
    "iso:country":"JP",
    "wof:name":"964-0893",
    "wof:placetype":"postalcode"
},
  "geometry": {"coordinates":[140.44980000000001,37.6285],"type":"Point"}
}