{
  "type": "Feature",
  "properties": {
    "gn:adm1_name":"Niigataken",
    "gn:adm2_name":"Sadogunhamochimachi",
    "gn:name":"Murayama",
    "iso:country":"JP",
    "wof:name":"952-0513",
    "wof:placetype":"postalcode"
},
  "geometry": {"coordinates":[138.30090000000001,37.8578],"type":"Point"}
}