{
  "type": "Feature",
  "properties": {
    "gn:adm1_name":"Toukyouto",
    "gn:adm2_name":"Kiyoseshi",
    "gn:name":"Nakazato",
    "iso:country":"JP",
    "wof:name":"204-0003",
    "wof:placetype":"postalcode"
},
  "geometry": {"coordinates":[139.51920000000001,35.7844],"type":"Point"}
}