{
  "type": "Feature",
  "properties": {
    "gn:adm1_name":"Yamagataken",
    "gn:adm2_name":"Kaminoyamashi",
    "gn:name":"Shoubu",
    "iso:country":"JP",
    "wof:name":"999-3217",
    "wof:placetype":"postalcode"
},
  "geometry": {"coordinates":[140.339,38.0996],"type":"Point"}
}