{
  "type": "Feature",
  "properties": {
    "gn:adm1_name":"Aichiken",
    "gn:adm2_name":"Toyoakeshi",
    "gn:name":"Kutsukakechou(Chokushi)",
    "iso:country":"JP",
    "wof:name":"470-1102",
    "wof:placetype":"postalcode"
},
  "geometry": {"coordinates":[137.01730000000001,35.0826],"type":"Point"}
}