{
  "type": "Feature",
  "properties": {
    "gn:adm1_name":"Kumamotoken",
    "gn:adm2_name":"Asogunsoyoumachi",
    "gn:name":"Shiobaru",
    "iso:country":"JP",
    "wof:name":"861-3916",
    "wof:placetype":"postalcode"
},
  "geometry": {"coordinates":[131.13030000000001,32.7055],"type":"Point"}
}