{
  "type": "Feature",
  "properties": {
    "gn:adm1_name":"Niigataken",
    "gn:adm2_name":"Nishikanbaragunnakanokuchimura",
    "gn:name":"Nagaba",
    "iso:country":"JP",
    "wof:name":"950-1332",
    "wof:placetype":"postalcode"
},
  "geometry": {"coordinates":[138.9811,37.6979],"type":"Point"}
}