{
  "type": "Feature",
  "properties": {
    "gn:adm1_name":"Chibaken",
    "gn:adm2_name":"Nodashi",
    "gn:name":"Kirigasaku",
    "iso:country":"JP",
    "wof:name":"270-0213",
    "wof:placetype":"postalcode"
},
  "geometry": {"coordinates":[139.81059999999999,36.0538],"type":"Point"}
}