{
  "type": "Feature",
  "properties": {
    "gn:adm1_name":"Hiroshimaken",
    "gn:adm2_name":"Hiroshimashiasakitaku",
    "gn:name":"Ochiai",
    "iso:country":"JP",
    "wof:name":"739-1731",
    "wof:placetype":"postalcode"
},
  "geometry": {"coordinates":[132.512,34.4771],"type":"Point"}
}