{
  "type": "Feature",
  "properties": {
    "gn:adm1_name":"Shizuokaken",
    "gn:adm2_name":"Hamamatsushi",
    "gn:name":"Namedachou",
    "iso:country":"JP",
    "wof:name":"432-8031",
    "wof:placetype":"postalcode"
},
  "geometry": {"coordinates":[137.72970000000001,34.7025],"type":"Point"}
}