{
  "type": "Feature",
  "properties": {
    "gn:adm1_name":"Kyoutofu",
    "gn:adm2_name":"Yosagun'Inechou",
    "gn:name":"Tsumo",
    "iso:country":"JP",
    "wof:name":"626-0412",
    "wof:placetype":"postalcode"
},
  "geometry": {"coordinates":[135.28620000000001,35.7127],"type":"Point"}
}