{
  "type": "Feature",
  "properties": {
    "gn:adm1_name":"Gunmaken",
    "gn:adm2_name":"Numatashi",
    "gn:name":"Sasaochou",
    "iso:country":"JP",
    "wof:name":"378-0023",
    "wof:placetype":"postalcode"
},
  "geometry": {"coordinates":[139.0772,36.6567],"type":"Point"}
}