{
  "type": "Feature",
  "properties": {
    "gn:adm1_name":"Oosakafu",
    "gn:adm2_name":"Tondabayashishi",
    "gn:name":"Ebitani",
    "iso:country":"JP",
    "wof:name":"584-0095",
    "wof:placetype":"postalcode"
},
  "geometry": {"coordinates":[135.5925,34.505],"type":"Point"}
}