{
  "type": "Feature",
  "properties": {
    "gn:adm1_name":"Chibaken",
    "gn:adm2_name":"Kamagayashi",
    "gn:name":"Michinobehonchou",
    "iso:country":"JP",
    "wof:name":"273-0137",
    "wof:placetype":"postalcode"
},
  "geometry": {"coordinates":[139.99879999999999,35.7627],"type":"Point"}
}