{
  "type": "Feature",
  "properties": {
    "gn:adm1_name":"Ehimeken",
    "gn:adm2_name":"Touyoshi",
    "gn:name":"Kawaradushinden",
    "iso:country":"JP",
    "wof:name":"799-1304",
    "wof:placetype":"postalcode"
},
  "geometry": {"coordinates":[133.07650000000001,33.9612],"type":"Point"}
}