{
  "type": "Feature",
  "properties": {
    "gn:adm1_name":"Naraken",
    "gn:adm2_name":"Ikomashi",
    "gn:name":"Shin'Asahigaoka",
    "iso:country":"JP",
    "wof:name":"630-0253",
    "wof:placetype":"postalcode"
},
  "geometry": {"coordinates":[135.7039,34.6856],"type":"Point"}
}