{
  "type": "Feature",
  "properties": {
    "gn:adm1_name":"Fukushimaken",
    "gn:adm2_name":"Nihonmatsushi",
    "gn:name":"Eguchi",
    "iso:country":"JP",
    "wof:name":"964-0997",
    "wof:placetype":"postalcode"
},
  "geometry": {"coordinates":[140.4426,37.5574],"type":"Point"}
}