{
  "type": "Feature",
  "properties": {
    "gn:adm1_name":"Oosakafu",
    "gn:adm2_name":"Kishiwadashi",
    "gn:name":"Harukimotomachi",
    "iso:country":"JP",
    "wof:name":"596-0032",
    "wof:placetype":"postalcode"
},
  "geometry": {"coordinates":[135.38489999999999,34.48],"type":"Point"}
}