{
  "type": "Feature",
  "properties": {
    "gn:adm1_name":"Tochigiken",
    "gn:adm2_name":"Utsunomiyashi",
    "gn:name":"Shouwa",
    "iso:country":"JP",
    "wof:name":"320-0032",
    "wof:placetype":"postalcode"
},
  "geometry": {"coordinates":[139.88059999999999,36.5665],"type":"Point"}
}