{
  "type": "Feature",
  "properties": {
    "gn:adm1_name":"Tochigiken",
    "gn:adm2_name":"Kanumashi",
    "gn:name":"Nojiri",
    "iso:country":"JP",
    "wof:name":"322-0251",
    "wof:placetype":"postalcode"
},
  "geometry": {"coordinates":[139.71019999999999,36.5482],"type":"Point"}
}