{
  "type": "Feature",
  "properties": {
    "gn:adm1_name":"Mieken",
    "gn:adm2_name":"Owaseshi",
    "gn:name":"Miyanouechou",
    "iso:country":"JP",
    "wof:name":"519-3663",
    "wof:placetype":"postalcode"
},
  "geometry": {"coordinates":[136.19390000000001,34.0793],"type":"Point"}
}