{
  "type": "Feature",
  "properties": {
    "gn:adm1_name":"Yamagataken",
    "gn:adm2_name":"Sagaeshi",
    "gn:name":"Nanokamachi",
    "iso:country":"JP",
    "wof:name":"991-0022",
    "wof:placetype":"postalcode"
},
  "geometry": {"coordinates":[140.28100000000001,38.38],"type":"Point"}
}