{
  "type": "Feature",
  "properties": {
    "gn:adm1_name":"Kyoutofu",
    "gn:adm2_name":"Funaiguntanbachou",
    "gn:name":"Toyota",
    "iso:country":"JP",
    "wof:name":"622-0231",
    "wof:placetype":"postalcode"
},
  "geometry": {"coordinates":[135.40219999999999,35.1757],"type":"Point"}
}