{
  "type": "Feature",
  "properties": {
    "gn:adm1_name":"Shimaneken",
    "gn:adm2_name":"Nogigunhakutachou",
    "gn:name":"Kamijuunenbata",
    "iso:country":"JP",
    "wof:name":"692-0325",
    "wof:placetype":"postalcode"
},
  "geometry": {"coordinates":[133.23849999999999,35.2726],"type":"Point"}
}