{
  "type": "Feature",
  "properties": {
    "gn:adm1_name":"Fukushimaken",
    "gn:adm2_name":"Iwakishi",
    "gn:name":"Tabitomachikaidomari",
    "iso:country":"JP",
    "wof:name":"974-0242",
    "wof:placetype":"postalcode"
},
  "geometry": {"coordinates":[140.61689999999999,36.9988],"type":"Point"}
}