{
  "type": "Feature",
  "properties": {
    "gn:adm1_name":"Toyamaken",
    "gn:adm2_name":"Shimoniikawagun'Asahimachi",
    "gn:name":"Yokomizu",
    "iso:country":"JP",
    "wof:name":"939-0724",
    "wof:placetype":"postalcode"
},
  "geometry": {"coordinates":[137.5538,36.9185],"type":"Point"}
}