{
  "type": "Feature",
  "properties": {
    "gn:adm1_name":"Yamagataken",
    "gn:adm2_name":"Higashitagawaguntachikawamachi",
    "gn:name":"Senbonsugi",
    "iso:country":"JP",
    "wof:name":"999-6604",
    "wof:placetype":"postalcode"
},
  "geometry": {"coordinates":[139.9419,38.7784],"type":"Point"}
}