{
  "type": "Feature",
  "properties": {
    "gn:adm1_name":"Ibarakiken",
    "gn:adm2_name":"Kitaibarakishi",
    "gn:name":"Ikanikeisaiganaibaai",
    "iso:country":"JP",
    "wof:name":"319-1500",
    "wof:placetype":"postalcode"
},
  "geometry": {"coordinates":[140.7312,36.7527],"type":"Point"}
}