{
  "type": "Feature",
  "properties": {
    "gn:adm1_name":"Kyoutofu",
    "gn:adm2_name":"Kyoutoshihigashiyamaku",
    "gn:name":"Kitakinomotochou",
    "iso:country":"JP",
    "wof:name":"605-0014",
    "wof:placetype":"postalcode"
},
  "geometry": {"coordinates":[135.77780000000001,35.0087],"type":"Point"}
}