{
  "type": "Feature",
  "properties": {
    "gn:adm1_name":"Kouchiken",
    "gn:adm2_name":"Kamiguntosayamadachou",
    "gn:name":"Yamadajima",
    "iso:country":"JP",
    "wof:name":"782-0011",
    "wof:placetype":"postalcode"
},
  "geometry": {"coordinates":[133.71889999999999,33.6124],"type":"Point"}
}