{
  "type": "Feature",
  "properties": {
    "gn:adm1_name":"Fukushimaken",
    "gn:adm2_name":"Kooriyamashi",
    "gn:name":"Shima",
    "iso:country":"JP",
    "wof:name":"963-8034",
    "wof:placetype":"postalcode"
},
  "geometry": {"coordinates":[140.34630000000001,37.3979],"type":"Point"}
}