{
  "type": "Feature",
  "properties": {
    "gn:adm1_name":"Niigataken",
    "gn:adm2_name":"Minamiuonumagunmuikamachi",
    "gn:name":"Nakamachi",
    "iso:country":"JP",
    "wof:name":"949-6622",
    "wof:placetype":"postalcode"
},
  "geometry": {"coordinates":[138.87950000000001,37.0646],"type":"Point"}
}