{
  "type": "Feature",
  "properties": {
    "gn:adm1_name":"Kagoshimaken",
    "gn:adm2_name":"Ooshimaguntokunoshimachou",
    "gn:name":"Inokawa",
    "iso:country":"JP",
    "wof:name":"891-7114",
    "wof:placetype":"postalcode"
},
  "geometry": {"coordinates":[129.0204,27.7763],"type":"Point"}
}