{
  "type": "Feature",
  "properties": {
    "gn:adm1_name":"Wakayamaken",
    "gn:adm2_name":"Tanabeshi",
    "gn:name":"Minato",
    "iso:country":"JP",
    "wof:name":"646-0031",
    "wof:placetype":"postalcode"
},
  "geometry": {"coordinates":[135.38249999999999,33.7333],"type":"Point"}
}