{
  "type": "Feature",
  "properties": {
    "gn:adm1_name":"Gifuken",
    "gn:adm2_name":"Tajimishi",
    "gn:name":"Asahigaoka",
    "iso:country":"JP",
    "wof:name":"507-0071",
    "wof:placetype":"postalcode"
},
  "geometry": {"coordinates":[137.10140000000001,35.3674],"type":"Point"}
}