{
  "type": "Feature",
  "properties": {
    "gn:adm1_name":"Tottoriken",
    "gn:adm2_name":"Yazugunkawaharachou",
    "gn:name":"Ogura",
    "iso:country":"JP",
    "wof:name":"680-1245",
    "wof:placetype":"postalcode"
},
  "geometry": {"coordinates":[134.17840000000001,35.3578],"type":"Point"}
}