{
  "type": "Feature",
  "properties": {
    "gn:adm1_name":"Yamaguchiken",
    "gn:adm2_name":"Shimonosekishi",
    "gn:name":"Hiedanishimachi",
    "iso:country":"JP",
    "wof:name":"751-0855",
    "wof:placetype":"postalcode"
},
  "geometry": {"coordinates":[130.92670000000001,33.9987],"type":"Point"}
}