{
  "type": "Feature",
  "properties": {
    "gn:adm1_name":"Gunmaken",
    "gn:adm2_name":"Tomiokashi",
    "gn:name":"Ainota",
    "iso:country":"JP",
    "wof:name":"370-2306",
    "wof:placetype":"postalcode"
},
  "geometry": {"coordinates":[138.92689999999999,36.2836],"type":"Point"}
}