{
  "type": "Feature",
  "properties": {
    "gn:adm1_name":"Ishikawaken",
    "gn:adm2_name":"Hakuiguntogimachi",
    "gn:name":"Yachiyo",
    "iso:country":"JP",
    "wof:name":"925-0438",
    "wof:placetype":"postalcode"
},
  "geometry": {"coordinates":[136.77289999999999,37.1672],"type":"Point"}
}