{
  "type": "Feature",
  "properties": {
    "gn:adm1_name":"Mieken",
    "gn:adm2_name":"Wataraigunwataraichou",
    "gn:name":"Tama",
    "iso:country":"JP",
    "wof:name":"516-2113",
    "wof:placetype":"postalcode"
},
  "geometry": {"coordinates":[136.60310000000001,34.4364],"type":"Point"}
}