{
  "type": "Feature",
  "properties": {
    "gn:adm1_name":"Shizuokaken",
    "gn:adm2_name":"Hamamatsushi",
    "gn:name":"Zaimokuchou",
    "iso:country":"JP",
    "wof:name":"435-0021",
    "wof:placetype":"postalcode"
},
  "geometry": {"coordinates":[137.79060000000001,34.7176],"type":"Point"}
}