{
  "type": "Feature",
  "properties": {
    "gn:adm1_name":"Aichiken",
    "gn:adm2_name":"Nagoyashimizuhoku",
    "gn:name":"Satsumachou",
    "iso:country":"JP",
    "wof:name":"467-0812",
    "wof:placetype":"postalcode"
},
  "geometry": {"coordinates":[136.92920000000001,35.1306],"type":"Point"}
}