{
  "type": "Feature",
  "properties": {
    "gn:adm1_name":"Shimaneken",
    "gn:adm2_name":"Goutsushi",
    "gn:name":"Kawahirachouhirata",
    "iso:country":"JP",
    "wof:name":"695-0014",
    "wof:placetype":"postalcode"
},
  "geometry": {"coordinates":[132.27379999999999,34.9748],"type":"Point"}
}