{
  "type": "Feature",
  "properties": {
    "gn:adm1_name":"Nagasakiken",
    "gn:adm2_name":"Nishisonogigunnagayochou",
    "gn:name":"Koudagou",
    "iso:country":"JP",
    "wof:name":"851-2127",
    "wof:placetype":"postalcode"
},
  "geometry": {"coordinates":[129.8614,32.8124],"type":"Point"}
}