{
  "type": "Feature",
  "properties": {
    "gn:adm1_name":"Ehimeken",
    "gn:adm2_name":"Higashiuwagun'Uwachou",
    "gn:name":"Gounai",
    "iso:country":"JP",
    "wof:name":"797-0025",
    "wof:placetype":"postalcode"
},
  "geometry": {"coordinates":[132.45869999999999,33.39],"type":"Point"}
}