{
  "type": "Feature",
  "properties": {
    "gn:adm1_name":"Fukuiken",
    "gn:adm2_name":"Nyuugun'Asahichou",
    "gn:name":"Tenpou",
    "iso:country":"JP",
    "wof:name":"916-0123",
    "wof:placetype":"postalcode"
},
  "geometry": {"coordinates":[136.12700000000001,35.9819],"type":"Point"}
}