{
  "type": "Feature",
  "properties": {
    "gn:adm1_name":"Ibarakiken",
    "gn:adm2_name":"Shimodateshi",
    "gn:name":"Nishonou",
    "iso:country":"JP",
    "wof:name":"308-0832",
    "wof:placetype":"postalcode"
},
  "geometry": {"coordinates":[139.98400000000001,36.2934],"type":"Point"}
}