{
  "type": "Feature",
  "properties": {
    "gn:adm1_name":"Toukyouto",
    "gn:adm2_name":"Suginamiku",
    "gn:name":"Asagayaminami",
    "iso:country":"JP",
    "wof:name":"166-0004",
    "wof:placetype":"postalcode"
},
  "geometry": {"coordinates":[139.63679999999999,35.7023],"type":"Point"}
}