{
  "type": "Feature",
  "properties": {
    "gn:adm1_name":"Tottoriken",
    "gn:adm2_name":"Touhakugun'Akasakichou",
    "gn:name":"Sazaki",
    "iso:country":"JP",
    "wof:name":"689-2531",
    "wof:placetype":"postalcode"
},
  "geometry": {"coordinates":[133.62690000000001,35.4943],"type":"Point"}
}