{
  "type": "Feature",
  "properties": {
    "gn:adm1_name":"Aichiken",
    "gn:adm2_name":"Minamishitaragunhouraichou",
    "gn:name":"Furi",
    "iso:country":"JP",
    "wof:name":"441-1955",
    "wof:placetype":"postalcode"
},
  "geometry": {"coordinates":[137.5222,34.9858],"type":"Point"}
}