{
  "type": "Feature",
  "properties": {
    "gn:adm1_name":"Hyougoken",
    "gn:adm2_name":"Akoushi",
    "gn:name":"Itayachou",
    "iso:country":"JP",
    "wof:name":"678-0248",
    "wof:placetype":"postalcode"
},
  "geometry": {"coordinates":[134.37909999999999,34.7564],"type":"Point"}
}