{
  "type": "Feature",
  "properties": {
    "gn:adm1_name":"Niigataken",
    "gn:adm2_name":"Nakauonumaguntsunanmachi",
    "gn:name":"Yachi",
    "iso:country":"JP",
    "wof:name":"949-8204",
    "wof:placetype":"postalcode"
},
  "geometry": {"coordinates":[138.62450000000001,36.9779],"type":"Point"}
}