{
  "type": "Feature",
  "properties": {
    "gn:adm1_name":"Tottoriken",
    "gn:adm2_name":"Sakaiminatoshi",
    "gn:name":"Hasuikechou",
    "iso:country":"JP",
    "wof:name":"684-0062",
    "wof:placetype":"postalcode"
},
  "geometry": {"coordinates":[133.22399999999999,35.5403],"type":"Point"}
}