{
  "type": "Feature",
  "properties": {
    "gn:adm1_name":"Hiroshimaken",
    "gn:adm2_name":"Kureshi",
    "gn:name":"Boujichou",
    "iso:country":"JP",
    "wof:name":"737-0065",
    "wof:placetype":"postalcode"
},
  "geometry": {"coordinates":[132.58070000000001,34.2579],"type":"Point"}
}