{
  "type": "Feature",
  "properties": {
    "gn:adm1_name":"Kanagawaken",
    "gn:adm2_name":"Yokosukashi",
    "gn:name":"Maborikaigan",
    "iso:country":"JP",
    "wof:name":"239-0801",
    "wof:placetype":"postalcode"
},
  "geometry": {"coordinates":[139.70519999999999,35.2621],"type":"Point"}
}