{
  "type": "Feature",
  "properties": {
    "gn:adm1_name":"Gifuken",
    "gn:adm2_name":"Gifushi",
    "gn:name":"Houraichou",
    "iso:country":"JP",
    "wof:name":"500-8124",
    "wof:placetype":"postalcode"
},
  "geometry": {"coordinates":[136.7834,35.4211],"type":"Point"}
}