{
  "type": "Feature",
  "properties": {
    "gn:adm1_name":"Ibarakiken",
    "gn:adm2_name":"Ishiokashi",
    "gn:name":"Namiki",
    "iso:country":"JP",
    "wof:name":"315-0006",
    "wof:placetype":"postalcode"
},
  "geometry": {"coordinates":[140.24959999999999,36.211],"type":"Point"}
}