{
  "type": "Feature",
  "properties": {
    "gn:adm1_name":"Kumamotoken",
    "gn:adm2_name":"Kikuchigunshichijoumachi",
    "gn:name":"Setoguchi",
    "iso:country":"JP",
    "wof:name":"861-1366",
    "wof:placetype":"postalcode"
},
  "geometry": {"coordinates":[130.76419999999999,32.991],"type":"Point"}
}