{
  "type": "Feature",
  "properties": {
    "gn:adm1_name":"Gunmaken",
    "gn:adm2_name":"Takasakishi",
    "gn:name":"Yotsuyamachi",
    "iso:country":"JP",
    "wof:name":"370-0819",
    "wof:placetype":"postalcode"
},
  "geometry": {"coordinates":[139.0009,36.3313],"type":"Point"}
}