{
  "type": "Feature",
  "properties": {
    "gn:adm1_name":"Ibarakiken",
    "gn:adm2_name":"Yuukigunyachiyomachi",
    "gn:name":"Shiomoto",
    "iso:country":"JP",
    "wof:name":"300-3501",
    "wof:placetype":"postalcode"
},
  "geometry": {"coordinates":[139.8597,36.2123],"type":"Point"}
}