{
  "type": "Feature",
  "properties": {
    "gn:adm1_name":"Oosakafu",
    "gn:adm2_name":"Yaoshi",
    "gn:name":"Yuugechouminami",
    "iso:country":"JP",
    "wof:name":"581-0034",
    "wof:placetype":"postalcode"
},
  "geometry": {"coordinates":[135.61179999999999,34.5952],"type":"Point"}
}