{
  "type": "Feature",
  "properties": {
    "gn:adm1_name":"Naganoken",
    "gn:adm2_name":"Kamitakaigun'Obusemachi",
    "gn:name":"Yoshijima",
    "iso:country":"JP",
    "wof:name":"381-0212",
    "wof:placetype":"postalcode"
},
  "geometry": {"coordinates":[138.29230000000001,36.713],"type":"Point"}
}