{
  "type": "Feature",
  "properties": {
    "gn:adm1_name":"Wakayamaken",
    "gn:adm2_name":"Aridashi",
    "gn:name":"Itogachounakaban",
    "iso:country":"JP",
    "wof:name":"649-0421",
    "wof:placetype":"postalcode"
},
  "geometry": {"coordinates":[135.17789999999999,34.0675],"type":"Point"}
}