{
  "type": "Feature",
  "properties": {
    "gn:adm1_name":"Hyougoken",
    "gn:adm2_name":"Koubeshinadaku",
    "gn:name":"Shougundoori",
    "iso:country":"JP",
    "wof:name":"657-0058",
    "wof:placetype":"postalcode"
},
  "geometry": {"coordinates":[135.22970000000001,34.7152],"type":"Point"}
}