{
  "type": "Feature",
  "properties": {
    "gn:adm1_name":"Fukushimaken",
    "gn:adm2_name":"Kawanumagun'Aidubangemachi",
    "gn:name":"Habayashi",
    "iso:country":"JP",
    "wof:name":"969-6572",
    "wof:placetype":"postalcode"
},
  "geometry": {"coordinates":[139.82990000000001,37.5539],"type":"Point"}
}