{
  "type": "Feature",
  "properties": {
    "gn:adm1_name":"Kyoutofu",
    "gn:adm2_name":"Kyoutoshisakyouku",
    "gn:name":"Kurodanichou",
    "iso:country":"JP",
    "wof:name":"606-8331",
    "wof:placetype":"postalcode"
},
  "geometry": {"coordinates":[135.78800000000001,35.0189],"type":"Point"}
}