{
  "type": "Feature",
  "properties": {
    "gn:adm1_name":"Hiroshimaken",
    "gn:adm2_name":"Hiroshimashisaekiku",
    "gn:name":"Tousuien",
    "iso:country":"JP",
    "wof:name":"731-5131",
    "wof:placetype":"postalcode"
},
  "geometry": {"coordinates":[132.3733,34.3648],"type":"Point"}
}