{
  "type": "Feature",
  "properties": {
    "gn:adm1_name":"Hyougoken",
    "gn:adm2_name":"Koubeshihigashinadaku",
    "gn:name":"Motoyamanakamachi",
    "iso:country":"JP",
    "wof:name":"658-0016",
    "wof:placetype":"postalcode"
},
  "geometry": {"coordinates":[135.28280000000001,34.7266],"type":"Point"}
}