{
  "type": "Feature",
  "properties": {
    "gn:adm1_name":"Gunmaken",
    "gn:adm2_name":"Setagunfujimimura",
    "gn:name":"Komeno",
    "iso:country":"JP",
    "wof:name":"371-0111",
    "wof:placetype":"postalcode"
},
  "geometry": {"coordinates":[139.05969999999999,36.4646],"type":"Point"}
}