{
  "type": "Feature",
  "properties": {
    "gn:adm1_name":"Naraken",
    "gn:adm2_name":"Shikiguntawaramotochou",
    "gn:name":"Ebisudoori",
    "iso:country":"JP",
    "wof:name":"636-0314",
    "wof:placetype":"postalcode"
},
  "geometry": {"coordinates":[135.791,34.5533],"type":"Point"}
}