{
  "type": "Feature",
  "properties": {
    "gn:adm1_name":"Ehimeken",
    "gn:adm2_name":"Iyoguntobechou",
    "gn:name":"Kitakawage",
    "iso:country":"JP",
    "wof:name":"791-2131",
    "wof:placetype":"postalcode"
},
  "geometry": {"coordinates":[132.78870000000001,33.7434],"type":"Point"}
}