{
  "type": "Feature",
  "properties": {
    "gn:adm1_name":"Niigataken",
    "gn:adm2_name":"Niigatashi",
    "gn:name":"Amigawara",
    "iso:country":"JP",
    "wof:name":"950-0964",
    "wof:placetype":"postalcode"
},
  "geometry": {"coordinates":[139.02160000000001,37.8936],"type":"Point"}
}