{
  "type": "Feature",
  "properties": {
    "gn:adm1_name":"Okayamaken",
    "gn:adm2_name":"Katsutagunshoubokuchou",
    "gn:name":"Nishinaka",
    "iso:country":"JP",
    "wof:name":"708-1222",
    "wof:placetype":"postalcode"
},
  "geometry": {"coordinates":[134.10769999999999,35.1124],"type":"Point"}
}