{
  "type": "Feature",
  "properties": {
    "gn:adm1_name":"Chibaken",
    "gn:adm2_name":"Abikoshi",
    "gn:name":"Fusa",
    "iso:country":"JP",
    "wof:name":"270-1101",
    "wof:placetype":"postalcode"
},
  "geometry": {"coordinates":[140.1301,35.8533],"type":"Point"}
}