{
  "type": "Feature",
  "properties": {
    "gn:adm1_name":"Toukyouto",
    "gn:adm2_name":"Tamashi",
    "gn:name":"Nakazawa",
    "iso:country":"JP",
    "wof:name":"206-0036",
    "wof:placetype":"postalcode"
},
  "geometry": {"coordinates":[139.4134,35.6214],"type":"Point"}
}