{
  "type": "Feature",
  "properties": {
    "gn:adm1_name":"Ibarakiken",
    "gn:adm2_name":"Iwaishi",
    "gn:name":"Kansukeshinden",
    "iso:country":"JP",
    "wof:name":"306-0603",
    "wof:placetype":"postalcode"
},
  "geometry": {"coordinates":[139.92599999999999,36.0668],"type":"Point"}
}