{
  "type": "Feature",
  "properties": {
    "gn:adm1_name":"Nagasakiken",
    "gn:adm2_name":"Ikigun'Ashibechou",
    "gn:name":"Hakozakiesumifure",
    "iso:country":"JP",
    "wof:name":"811-5467",
    "wof:placetype":"postalcode"
},
  "geometry": {"coordinates":[129.7338,33.8419],"type":"Point"}
}