{
  "type": "Feature",
  "properties": {
    "gn:adm1_name":"Naganoken",
    "gn:adm2_name":"Matsumotoshi",
    "gn:name":"Shimizu",
    "iso:country":"JP",
    "wof:name":"390-0805",
    "wof:placetype":"postalcode"
},
  "geometry": {"coordinates":[137.9821,36.2368],"type":"Point"}
}