{
  "type": "Feature",
  "properties": {
    "gn:adm1_name":"Chibaken",
    "gn:adm2_name":"Katsuurashi",
    "gn:name":"Nakazato",
    "iso:country":"JP",
    "wof:name":"299-5262",
    "wof:placetype":"postalcode"
},
  "geometry": {"coordinates":[140.24520000000001,35.1586],"type":"Point"}
}