{
  "type": "Feature",
  "properties": {
    "gn:adm1_name":"Miyazakiken",
    "gn:adm2_name":"Miyazakishi",
    "gn:name":"Komatsudaihigashi",
    "iso:country":"JP",
    "wof:name":"880-0953",
    "wof:placetype":"postalcode"
},
  "geometry": {"coordinates":[131.39500000000001,31.9299],"type":"Point"}
}