{
  "type": "Feature",
  "properties": {
    "gn:adm1_name":"Chibaken",
    "gn:adm2_name":"Futtsushi",
    "gn:name":"Kawana",
    "iso:country":"JP",
    "wof:name":"293-0023",
    "wof:placetype":"postalcode"
},
  "geometry": {"coordinates":[139.83359999999999,35.3072],"type":"Point"}
}