{
  "type": "Feature",
  "properties": {
    "gn:adm1_name":"Gunmaken",
    "gn:adm2_name":"Takasakishi",
    "gn:name":"Tsubakichou",
    "iso:country":"JP",
    "wof:name":"370-0059",
    "wof:placetype":"postalcode"
},
  "geometry": {"coordinates":[139.00710000000001,36.3308],"type":"Point"}
}