{
  "type": "Feature",
  "properties": {
    "gn:adm1_name":"Yamaguchiken",
    "gn:adm2_name":"Hikarishi",
    "gn:name":"Wadachou",
    "iso:country":"JP",
    "wof:name":"743-0044",
    "wof:placetype":"postalcode"
},
  "geometry": {"coordinates":[131.92740000000001,33.9838],"type":"Point"}
}