{
  "type": "Feature",
  "properties": {
    "gn:adm1_name":"Chibaken",
    "gn:adm2_name":"Matsudoshi",
    "gn:name":"Wanagaya",
    "iso:country":"JP",
    "wof:name":"270-2232",
    "wof:placetype":"postalcode"
},
  "geometry": {"coordinates":[139.92410000000001,35.7774],"type":"Point"}
}