{
  "type": "Feature",
  "properties": {
    "gn:adm1_name":"Hiroshimaken",
    "gn:adm2_name":"Fukuyamashi",
    "gn:name":"Sendachouyaburo",
    "iso:country":"JP",
    "wof:name":"720-0014",
    "wof:placetype":"postalcode"
},
  "geometry": {"coordinates":[133.3648,34.5136],"type":"Point"}
}