{
  "type": "Feature",
  "properties": {
    "gn:adm1_name":"Yamagataken",
    "gn:adm2_name":"Yamagatashi",
    "gn:name":"Yoshiharaminami",
    "iso:country":"JP",
    "wof:name":"990-2455",
    "wof:placetype":"postalcode"
},
  "geometry": {"coordinates":[140.3115,38.2226],"type":"Point"}
}