{
  "type": "Feature",
  "properties": {
    "gn:adm1_name":"Miyazakiken",
    "gn:adm2_name":"Hyuugashi",
    "gn:name":"Hamamachi",
    "iso:country":"JP",
    "wof:name":"883-0004",
    "wof:placetype":"postalcode"
},
  "geometry": {"coordinates":[131.6473,32.4173],"type":"Point"}
}