{
  "type": "Feature",
  "properties": {
    "gn:adm1_name":"Hyougoken",
    "gn:adm2_name":"Koubeshihyougoku",
    "gn:name":"Susanodoori",
    "iso:country":"JP",
    "wof:name":"652-0896",
    "wof:placetype":"postalcode"
},
  "geometry": {"coordinates":[135.1678,34.665],"type":"Point"}
}