{
  "type": "Feature",
  "properties": {
    "gn:adm1_name":"Oosakafu",
    "gn:adm2_name":"Minamikawachigunkananchou",
    "gn:name":"Mochio",
    "iso:country":"JP",
    "wof:name":"585-0021",
    "wof:placetype":"postalcode"
},
  "geometry": {"coordinates":[135.65780000000001,34.4852],"type":"Point"}
}