{
  "type": "Feature",
  "properties": {
    "gn:adm1_name":"Saitamaken",
    "gn:adm2_name":"Gyoudashi",
    "gn:name":"Sekine",
    "iso:country":"JP",
    "wof:name":"361-0015",
    "wof:placetype":"postalcode"
},
  "geometry": {"coordinates":[139.5266,36.1216],"type":"Point"}
}