{
  "type": "Feature",
  "properties": {
    "gn:adm1_name":"Fukuokaken",
    "gn:adm2_name":"Fukuokashijounanku",
    "gn:name":"Arae",
    "iso:country":"JP",
    "wof:name":"814-0101",
    "wof:placetype":"postalcode"
},
  "geometry": {"coordinates":[130.35849999999999,33.5721],"type":"Point"}
}