{
  "type": "Feature",
  "properties": {
    "gn:adm1_name":"Toyamaken",
    "gn:adm2_name":"Higashitonamigunjouhanamachi",
    "gn:name":"Uwami",
    "iso:country":"JP",
    "wof:name":"939-1833",
    "wof:placetype":"postalcode"
},
  "geometry": {"coordinates":[136.88409999999999,36.4968],"type":"Point"}
}