{
  "type": "Feature",
  "properties": {
    "gn:adm1_name":"Hyougoken",
    "gn:adm2_name":"Takasagoshi",
    "gn:name":"Takasagochouebisumachi",
    "iso:country":"JP",
    "wof:name":"676-0045",
    "wof:placetype":"postalcode"
},
  "geometry": {"coordinates":[134.8021,34.7431],"type":"Point"}
}