{
  "type": "Feature",
  "properties": {
    "gn:adm1_name":"Fukuokaken",
    "gn:adm2_name":"Kitakyuushuushiyahatanishiku",
    "gn:name":"Nishioriomachi",
    "iso:country":"JP",
    "wof:name":"807-0862",
    "wof:placetype":"postalcode"
},
  "geometry": {"coordinates":[130.70859999999999,33.8582],"type":"Point"}
}