{
  "type": "Feature",
  "properties": {
    "gn:adm1_name":"Shizuokaken",
    "gn:adm2_name":"Kakegawashi",
    "gn:name":"Hatakama",
    "iso:country":"JP",
    "wof:name":"436-0117",
    "wof:placetype":"postalcode"
},
  "geometry": {"coordinates":[137.95140000000001,34.8161],"type":"Point"}
}