{
  "type": "Feature",
  "properties": {
    "gn:adm1_name":"Yamagataken",
    "gn:adm2_name":"Sagaeshi",
    "gn:name":"Sakaechou",
    "iso:country":"JP",
    "wof:name":"991-0034",
    "wof:placetype":"postalcode"
},
  "geometry": {"coordinates":[140.27950000000001,38.3689],"type":"Point"}
}