{
  "type": "Feature",
  "properties": {
    "gn:adm1_name":"Oosakafu",
    "gn:adm2_name":"Fujiiderashi",
    "gn:name":"Fujigaoka",
    "iso:country":"JP",
    "wof:name":"583-0017",
    "wof:placetype":"postalcode"
},
  "geometry": {"coordinates":[135.6001,34.5636],"type":"Point"}
}