{
  "type": "Feature",
  "properties": {
    "gn:adm1_name":"Miyagiken",
    "gn:adm2_name":"Sendaishiaobaku",
    "gn:name":"Futabagaoka",
    "iso:country":"JP",
    "wof:name":"981-0924",
    "wof:placetype":"postalcode"
},
  "geometry": {"coordinates":[140.87430000000001,38.3026],"type":"Point"}
}