{
  "type": "Feature",
  "properties": {
    "gn:adm1_name":"Fukuokaken",
    "gn:adm2_name":"Kitakyuushuushiyahatanishiku",
    "gn:name":"Kurosaki",
    "iso:country":"JP",
    "wof:name":"806-0021",
    "wof:placetype":"postalcode"
},
  "geometry": {"coordinates":[130.76679999999999,33.8652],"type":"Point"}
}