{
  "type": "Feature",
  "properties": {
    "gn:adm1_name":"Toukyouto",
    "gn:adm2_name":"Chuuouku",
    "gn:name":"Kyoubashi",
    "iso:country":"JP",
    "wof:name":"104-0031",
    "wof:placetype":"postalcode"
},
  "geometry": {"coordinates":[139.77099999999999,35.6769],"type":"Point"}
}