{
  "type": "Feature",
  "properties": {
    "gn:adm1_name":"Naganoken",
    "gn:adm2_name":"Shiojirishi",
    "gn:name":"Horinouchi",
    "iso:country":"JP",
    "wof:name":"399-0714",
    "wof:placetype":"postalcode"
},
  "geometry": {"coordinates":[137.96899999999999,36.1088],"type":"Point"}
}