{
  "type": "Feature",
  "properties": {
    "gn:adm1_name":"Ehimeken",
    "gn:adm2_name":"Imabarishi",
    "gn:name":"Miyagazaki",
    "iso:country":"JP",
    "wof:name":"799-1537",
    "wof:placetype":"postalcode"
},
  "geometry": {"coordinates":[133.00999999999999,34.0152],"type":"Point"}
}