{
  "type": "Feature",
  "properties": {
    "gn:adm1_name":"Okinawaken",
    "gn:adm2_name":"Shimajirigunkumejimachou",
    "gn:name":"Yamagusuku",
    "iso:country":"JP",
    "wof:name":"901-3111",
    "wof:placetype":"postalcode"
},
  "geometry": {"coordinates":[126.78579999999999,26.3339],"type":"Point"}
}