{
  "type": "Feature",
  "properties": {
    "gn:adm1_name":"Ishikawaken",
    "gn:adm2_name":"Hakuigun'Oshimizumachi",
    "gn:name":"Takono",
    "iso:country":"JP",
    "wof:name":"929-1305",
    "wof:placetype":"postalcode"
},
  "geometry": {"coordinates":[136.76900000000001,36.8337],"type":"Point"}
}