{
  "type": "Feature",
  "properties": {
    "gn:adm1_name":"Tochigiken",
    "gn:adm2_name":"Nasugunminaminasumachi",
    "gn:name":"Minamioowagu",
    "iso:country":"JP",
    "wof:name":"321-0533",
    "wof:placetype":"postalcode"
},
  "geometry": {"coordinates":[140.10470000000001,36.6678],"type":"Point"}
}