{
  "type": "Feature",
  "properties": {
    "gn:adm1_name":"Aichiken",
    "gn:adm2_name":"Atsumigun'Atsumichou",
    "gn:name":"Nakayama",
    "iso:country":"JP",
    "wof:name":"441-3615",
    "wof:placetype":"postalcode"
},
  "geometry": {"coordinates":[137.0813,34.6323],"type":"Point"}
}