{
  "type": "Feature",
  "properties": {
    "gn:adm1_name":"Fukuiken",
    "gn:adm2_name":"Sabaeshi",
    "gn:name":"Katayamachou",
    "iso:country":"JP",
    "wof:name":"916-1223",
    "wof:placetype":"postalcode"
},
  "geometry": {"coordinates":[136.2758,35.9505],"type":"Point"}
}