{
  "type": "Feature",
  "properties": {
    "gn:adm1_name":"Kanagawaken",
    "gn:adm2_name":"Atsugishi",
    "gn:name":"Shimoogino",
    "iso:country":"JP",
    "wof:name":"243-0203",
    "wof:placetype":"postalcode"
},
  "geometry": {"coordinates":[139.3398,35.4808],"type":"Point"}
}