{
  "type": "Feature",
  "properties": {
    "gn:adm1_name":"Kumamotoken",
    "gn:adm2_name":"Utoshi",
    "gn:name":"Ishikoujimachi",
    "iso:country":"JP",
    "wof:name":"869-0441",
    "wof:placetype":"postalcode"
},
  "geometry": {"coordinates":[130.6628,32.6886],"type":"Point"}
}