{
  "type": "Feature",
  "properties": {
    "gn:adm1_name":"Aichiken",
    "gn:adm2_name":"Nagoyashiminatoku",
    "gn:name":"Nishikanita",
    "iso:country":"JP",
    "wof:name":"455-0872",
    "wof:placetype":"postalcode"
},
  "geometry": {"coordinates":[136.8152,35.1204],"type":"Point"}
}