{
  "type": "Feature",
  "properties": {
    "gn:adm1_name":"Aichiken",
    "gn:adm2_name":"Shinshiroshi",
    "gn:name":"Hiyoshi",
    "iso:country":"JP",
    "wof:name":"441-1322",
    "wof:placetype":"postalcode"
},
  "geometry": {"coordinates":[137.52590000000001,34.9016],"type":"Point"}
}