{
  "type": "Feature",
  "properties": {
    "gn:adm1_name":"Yamagataken",
    "gn:adm2_name":"Sagaeshi",
    "gn:name":"Tashiro",
    "iso:country":"JP",
    "wof:name":"990-0503",
    "wof:placetype":"postalcode"
},
  "geometry": {"coordinates":[140.23269999999999,38.4501],"type":"Point"}
}