{
  "type": "Feature",
  "properties": {
    "gn:adm1_name":"Tochigiken",
    "gn:adm2_name":"Nasugunnishinasunomachi",
    "gn:name":"Mutsumi",
    "iso:country":"JP",
    "wof:name":"329-2706",
    "wof:placetype":"postalcode"
},
  "geometry": {"coordinates":[139.9855,36.897],"type":"Point"}
}