{
  "type": "Feature",
  "properties": {
    "gn:adm1_name":"Aichiken",
    "gn:adm2_name":"Nagoyashiatsutaku",
    "gn:name":"Oosekochou",
    "iso:country":"JP",
    "wof:name":"456-0045",
    "wof:placetype":"postalcode"
},
  "geometry": {"coordinates":[136.90479999999999,35.1204],"type":"Point"}
}