{
  "type": "Feature",
  "properties": {
    "gn:adm1_name":"Hyougoken",
    "gn:adm2_name":"Nishinomiyashi",
    "gn:name":"Danjouchou",
    "iso:country":"JP",
    "wof:name":"663-8006",
    "wof:placetype":"postalcode"
},
  "geometry": {"coordinates":[135.36519999999999,34.771],"type":"Point"}
}