{
  "type": "Feature",
  "properties": {
    "gn:adm1_name":"Nagasakiken",
    "gn:adm2_name":"Saseboshi",
    "gn:name":"Hiramachi",
    "iso:country":"JP",
    "wof:name":"857-0040",
    "wof:placetype":"postalcode"
},
  "geometry": {"coordinates":[129.71250000000001,33.1783],"type":"Point"}
}