{
  "type": "Feature",
  "properties": {
    "gn:adm1_name":"Saitamaken",
    "gn:adm2_name":"Saitamashisakuraku",
    "gn:name":"Machiya",
    "iso:country":"JP",
    "wof:name":"338-0836",
    "wof:placetype":"postalcode"
},
  "geometry": {"coordinates":[139.62,35.8574],"type":"Point"}
}