{
  "type": "Feature",
  "properties": {
    "gn:adm1_name":"Niigataken",
    "gn:adm2_name":"Niigatashi",
    "gn:name":"Nishikobaridai",
    "iso:country":"JP",
    "wof:name":"950-2015",
    "wof:placetype":"postalcode"
},
  "geometry": {"coordinates":[138.97999999999999,37.8854],"type":"Point"}
}