{
  "type": "Feature",
  "properties": {
    "gn:adm1_name":"Kyoutofu",
    "gn:adm2_name":"Kyoutoshikitaku",
    "gn:name":"Nishigamofuneyama",
    "iso:country":"JP",
    "wof:name":"603-8848",
    "wof:placetype":"postalcode"
},
  "geometry": {"coordinates":[135.7362,35.065],"type":"Point"}
}