{
  "type": "Feature",
  "properties": {
    "gn:adm1_name":"Aichiken",
    "gn:adm2_name":"Toyohashishi",
    "gn:name":"Susechou",
    "iso:country":"JP",
    "wof:name":"441-1111",
    "wof:placetype":"postalcode"
},
  "geometry": {"coordinates":[137.4692,34.8011],"type":"Point"}
}