{
  "type": "Feature",
  "properties": {
    "gn:adm1_name":"Kanagawaken",
    "gn:adm2_name":"Zushishi",
    "gn:name":"Zushi",
    "iso:country":"JP",
    "wof:name":"249-0006",
    "wof:placetype":"postalcode"
},
  "geometry": {"coordinates":[139.57919999999999,35.2953],"type":"Point"}
}