{
  "type": "Feature",
  "properties": {
    "gn:adm1_name":"Fukuiken",
    "gn:adm2_name":"Tsurugashi",
    "gn:name":"Daguchi",
    "iso:country":"JP",
    "wof:name":"914-0305",
    "wof:placetype":"postalcode"
},
  "geometry": {"coordinates":[136.1001,35.5732],"type":"Point"}
}