{
  "type": "Feature",
  "properties": {
    "gn:adm1_name":"Ooitaken",
    "gn:adm2_name":"Saikishi",
    "gn:name":"Higashimachi",
    "iso:country":"JP",
    "wof:name":"876-0814",
    "wof:placetype":"postalcode"
},
  "geometry": {"coordinates":[131.9074,32.966],"type":"Point"}
}