{
  "type": "Feature",
  "properties": {
    "gn:adm1_name":"Aichiken",
    "gn:adm2_name":"Tsushimashi",
    "gn:name":"Koshiduchou",
    "iso:country":"JP",
    "wof:name":"496-0022",
    "wof:placetype":"postalcode"
},
  "geometry": {"coordinates":[136.76509999999999,35.1744],"type":"Point"}
}