{
  "type": "Feature",
  "properties": {
    "gn:adm1_name":"Chibaken",
    "gn:adm2_name":"Touganeshi",
    "gn:name":"Gumyou",
    "iso:country":"JP",
    "wof:name":"283-0002",
    "wof:placetype":"postalcode"
},
  "geometry": {"coordinates":[140.3989,35.5814],"type":"Point"}
}