{
  "type": "Feature",
  "properties": {
    "gn:adm1_name":"Niigataken",
    "gn:adm2_name":"Murakamishi",
    "gn:name":"Iwafunemikkaichi",
    "iso:country":"JP",
    "wof:name":"958-0041",
    "wof:placetype":"postalcode"
},
  "geometry": {"coordinates":[139.43190000000001,38.1972],"type":"Point"}
}