{
  "type": "Feature",
  "properties": {
    "gn:adm1_name":"Sagaken",
    "gn:adm2_name":"Imarishi",
    "gn:name":"Kisuchou",
    "iso:country":"JP",
    "wof:name":"848-0044",
    "wof:placetype":"postalcode"
},
  "geometry": {"coordinates":[129.864,33.29],"type":"Point"}
}