{
  "type": "Feature",
  "properties": {
    "gn:adm1_name":"Aichiken",
    "gn:adm2_name":"Setoshi",
    "gn:name":"Ishidachou",
    "iso:country":"JP",
    "wof:name":"489-0951",
    "wof:placetype":"postalcode"
},
  "geometry": {"coordinates":[137.09030000000001,35.1993],"type":"Point"}
}