{
  "type": "Feature",
  "properties": {
    "gn:adm1_name":"Gunmaken",
    "gn:adm2_name":"Tanogunyoshiimachi",
    "gn:name":"Shiogawa",
    "iso:country":"JP",
    "wof:name":"370-2134",
    "wof:placetype":"postalcode"
},
  "geometry": {"coordinates":[138.9812,36.2587],"type":"Point"}
}