{
  "type": "Feature",
  "properties": {
    "gn:adm1_name":"Okayamaken",
    "gn:adm2_name":"Maniwagunkusechou",
    "gn:name":"Tominoo",
    "iso:country":"JP",
    "wof:name":"719-3203",
    "wof:placetype":"postalcode"
},
  "geometry": {"coordinates":[133.75,35.0649],"type":"Point"}
}