{
  "type": "Feature",
  "properties": {
    "gn:adm1_name":"Naraken",
    "gn:adm2_name":"Narashi",
    "gn:name":"Nishinoshinyachou",
    "iso:country":"JP",
    "wof:name":"630-8334",
    "wof:placetype":"postalcode"
},
  "geometry": {"coordinates":[135.82980000000001,34.6767],"type":"Point"}
}