{
  "type": "Feature",
  "properties": {
    "gn:adm1_name":"Fukuiken",
    "gn:adm2_name":"Sakaigunkanaduchou",
    "gn:name":"Ikanikeisaiganaibaai",
    "iso:country":"JP",
    "wof:name":"919-0600",
    "wof:placetype":"postalcode"
},
  "geometry": {"coordinates":[136.19159999999999,36.2309],"type":"Point"}
}