{
  "type": "Feature",
  "properties": {
    "gn:adm1_name":"Ehimeken",
    "gn:adm2_name":"Houjoushi",
    "gn:name":"Sainohara",
    "iso:country":"JP",
    "wof:name":"799-2417",
    "wof:placetype":"postalcode"
},
  "geometry": {"coordinates":[132.8237,33.9729],"type":"Point"}
}