{
  "type": "Feature",
  "properties": {
    "gn:adm1_name":"Kyoutofu",
    "gn:adm2_name":"Kyoutoshisakyouku",
    "gn:name":"Ichijoujinishisuginomiyachou",
    "iso:country":"JP",
    "wof:name":"606-8112",
    "wof:placetype":"postalcode"
},
  "geometry": {"coordinates":[135.7861,35.0464],"type":"Point"}
}