{
  "type": "Feature",
  "properties": {
    "gn:adm1_name":"Okinawaken",
    "gn:adm2_name":"Nagoshi",
    "gn:name":"Isagawa",
    "iso:country":"JP",
    "wof:name":"905-1152",
    "wof:placetype":"postalcode"
},
  "geometry": {"coordinates":[128.00389999999999,26.6114],"type":"Point"}
}