{
  "type": "Feature",
  "properties": {
    "gn:adm1_name":"Gifuken",
    "gn:adm2_name":"Gifushi",
    "gn:name":"Nishikaidenkomeno",
    "iso:country":"JP",
    "wof:name":"501-1163",
    "wof:placetype":"postalcode"
},
  "geometry": {"coordinates":[136.70769999999999,35.4465],"type":"Point"}
}