{
  "type": "Feature",
  "properties": {
    "gn:adm1_name":"Kyoutofu",
    "gn:adm2_name":"Yawatashi",
    "gn:name":"Otokoyamashigetsu",
    "iso:country":"JP",
    "wof:name":"614-8361",
    "wof:placetype":"postalcode"
},
  "geometry": {"coordinates":[135.69749999999999,34.8701],"type":"Point"}
}