{
  "type": "Feature",
  "properties": {
    "gn:adm1_name":"Hyougoken",
    "gn:adm2_name":"Nishinomiyashi",
    "gn:name":"Manchidanichou",
    "iso:country":"JP",
    "wof:name":"662-0031",
    "wof:placetype":"postalcode"
},
  "geometry": {"coordinates":[135.33459999999999,34.7472],"type":"Point"}
}