{
  "type": "Feature",
  "properties": {
    "gn:adm1_name":"Chibaken",
    "gn:adm2_name":"Kimitsushi",
    "gn:name":"Ooyamano",
    "iso:country":"JP",
    "wof:name":"299-1123",
    "wof:placetype":"postalcode"
},
  "geometry": {"coordinates":[139.92779999999999,35.2862],"type":"Point"}
}