{
  "type": "Feature",
  "properties": {
    "gn:adm1_name":"Aichiken",
    "gn:adm2_name":"Kounanshi",
    "gn:name":"Imaichibachoumiyamae",
    "iso:country":"JP",
    "wof:name":"483-8182",
    "wof:placetype":"postalcode"
},
  "geometry": {"coordinates":[136.88839999999999,35.3273],"type":"Point"}
}