{
  "type": "Feature",
  "properties": {
    "gn:adm1_name":"Fukushimaken",
    "gn:adm2_name":"Futabagunhironomachi",
    "gn:name":"Shimoasamigawa",
    "iso:country":"JP",
    "wof:name":"979-0403",
    "wof:placetype":"postalcode"
},
  "geometry": {"coordinates":[140.9982,37.2102],"type":"Point"}
}