{
  "type": "Feature",
  "properties": {
    "gn:adm1_name":"Miyagiken",
    "gn:adm2_name":"Shibatagunmuratamachi",
    "gn:name":"Ashitate(Kitamuki)",
    "iso:country":"JP",
    "wof:name":"989-1511",
    "wof:placetype":"postalcode"
},
  "geometry": {"coordinates":[140.6568,38.1676],"type":"Point"}
}