{
  "type": "Feature",
  "properties": {
    "gn:adm1_name":"Fukuokaken",
    "gn:adm2_name":"Munakatashi",
    "gn:name":"Kouryoudai",
    "iso:country":"JP",
    "wof:name":"811-4165",
    "wof:placetype":"postalcode"
},
  "geometry": {"coordinates":[130.59800000000001,33.7919],"type":"Point"}
}