{
  "type": "Feature",
  "properties": {
    "gn:adm1_name":"Tochigiken",
    "gn:adm2_name":"Shioyaguntakanezawamachi",
    "gn:name":"Terawatado",
    "iso:country":"JP",
    "wof:name":"329-1222",
    "wof:placetype":"postalcode"
},
  "geometry": {"coordinates":[140.02289999999999,36.6223],"type":"Point"}
}