{
  "type": "Feature",
  "properties": {
    "gn:adm1_name":"Fukushimaken",
    "gn:adm2_name":"Ishikawagun'Asakawamachi",
    "gn:name":"Fukizaku",
    "iso:country":"JP",
    "wof:name":"963-6201",
    "wof:placetype":"postalcode"
},
  "geometry": {"coordinates":[140.42150000000001,37.1153],"type":"Point"}
}