{
  "type": "Feature",
  "properties": {
    "gn:adm1_name":"Okayamaken",
    "gn:adm2_name":"Katsutagunshououchou",
    "gn:name":"Kurosaka",
    "iso:country":"JP",
    "wof:name":"709-4323",
    "wof:placetype":"postalcode"
},
  "geometry": {"coordinates":[134.09180000000001,35.0409],"type":"Point"}
}