{
  "type": "Feature",
  "properties": {
    "gn:adm1_name":"Toukyouto",
    "gn:adm2_name":"Hinoshi",
    "gn:name":"Tamadaira",
    "iso:country":"JP",
    "wof:name":"191-0062",
    "wof:placetype":"postalcode"
},
  "geometry": {"coordinates":[139.38040000000001,35.6667],"type":"Point"}
}