{
  "type": "Feature",
  "properties": {
    "gn:adm1_name":"Hyougoken",
    "gn:adm2_name":"Nishinomiyashi",
    "gn:name":"Oohatachou",
    "iso:country":"JP",
    "wof:name":"662-0836",
    "wof:placetype":"postalcode"
},
  "geometry": {"coordinates":[135.34999999999999,34.7486],"type":"Point"}
}