{
  "type": "Feature",
  "properties": {
    "gn:adm1_name":"Chibaken",
    "gn:adm2_name":"Kisaradushi",
    "gn:name":"Sakuramachi",
    "iso:country":"JP",
    "wof:name":"292-0821",
    "wof:placetype":"postalcode"
},
  "geometry": {"coordinates":[139.92740000000001,35.37],"type":"Point"}
}