{
  "type": "Feature",
  "properties": {
    "gn:adm1_name":"Ibarakiken",
    "gn:adm2_name":"Mitoshi",
    "gn:name":"Fujiichou",
    "iso:country":"JP",
    "wof:name":"311-4201",
    "wof:placetype":"postalcode"
},
  "geometry": {"coordinates":[140.40360000000001,36.446],"type":"Point"}
}