{
  "type": "Feature",
  "properties": {
    "gn:adm1_name":"Okayamaken",
    "gn:adm2_name":"Kurashikishi",
    "gn:name":"Nakase",
    "iso:country":"JP",
    "wof:name":"712-8051",
    "wof:placetype":"postalcode"
},
  "geometry": {"coordinates":[133.74889999999999,34.5293],"type":"Point"}
}