{
  "type": "Feature",
  "properties": {
    "gn:adm1_name":"Naraken",
    "gn:adm2_name":"Kashiharashi",
    "gn:name":"Ootanichou",
    "iso:country":"JP",
    "wof:name":"634-0815",
    "wof:placetype":"postalcode"
},
  "geometry": {"coordinates":[135.77889999999999,34.4925],"type":"Point"}
}