{
  "type": "Feature",
  "properties": {
    "gn:adm1_name":"Kyoutofu",
    "gn:adm2_name":"Kyoutanabeshi",
    "gn:name":"Kannabidai",
    "iso:country":"JP",
    "wof:name":"610-0333",
    "wof:placetype":"postalcode"
},
  "geometry": {"coordinates":[135.7482,34.8045],"type":"Point"}
}