{
  "type": "Feature",
  "properties": {
    "gn:adm1_name":"Tottoriken",
    "gn:adm2_name":"Tottorishi",
    "gn:name":"Nishiimazaike",
    "iso:country":"JP",
    "wof:name":"680-1173",
    "wof:placetype":"postalcode"
},
  "geometry": {"coordinates":[134.18199999999999,35.4706],"type":"Point"}
}