{
  "type": "Feature",
  "properties": {
    "gn:adm1_name":"Ishikawaken",
    "gn:adm2_name":"Fugeshigunmonzenmachi",
    "gn:name":"Minaduki",
    "iso:country":"JP",
    "wof:name":"927-2271",
    "wof:placetype":"postalcode"
},
  "geometry": {"coordinates":[136.75739999999999,37.3512],"type":"Point"}
}