{
  "type": "Feature",
  "properties": {
    "gn:adm1_name":"Hiroshimaken",
    "gn:adm2_name":"Hiroshimashinishiku",
    "gn:name":"Yamadachou",
    "iso:country":"JP",
    "wof:name":"733-0854",
    "wof:placetype":"postalcode"
},
  "geometry": {"coordinates":[132.39179999999999,34.4036],"type":"Point"}
}