{
  "type": "Feature",
  "properties": {
    "gn:adm1_name":"Ooitaken",
    "gn:adm2_name":"Nakatsushi",
    "gn:name":"Shimoshouji",
    "iso:country":"JP",
    "wof:name":"871-0097",
    "wof:placetype":"postalcode"
},
  "geometry": {"coordinates":[131.19210000000001,33.6107],"type":"Point"}
}