{
  "type": "Feature",
  "properties": {
    "gn:adm1_name":"Miyagiken",
    "gn:adm2_name":"Natorishi",
    "gn:name":"Ootemachi",
    "iso:country":"JP",
    "wof:name":"981-1232",
    "wof:placetype":"postalcode"
},
  "geometry": {"coordinates":[140.8793,38.1684],"type":"Point"}
}