{
  "type": "Feature",
  "properties": {
    "gn:adm1_name":"Ibarakiken",
    "gn:adm2_name":"Makabegunsekijoumachi",
    "gn:name":"Sekimotoshimo",
    "iso:country":"JP",
    "wof:name":"308-0127",
    "wof:placetype":"postalcode"
},
  "geometry": {"coordinates":[139.91999999999999,36.2476],"type":"Point"}
}