{
  "type": "Feature",
  "properties": {
    "gn:adm1_name":"Ehimeken",
    "gn:adm2_name":"Niihamashi",
    "gn:name":"Takata",
    "iso:country":"JP",
    "wof:name":"792-0887",
    "wof:placetype":"postalcode"
},
  "geometry": {"coordinates":[133.31020000000001,33.9687],"type":"Point"}
}