{
  "type": "Feature",
  "properties": {
    "gn:adm1_name":"Aichiken",
    "gn:adm2_name":"Niwagun'Ooguchichou",
    "gn:name":"Gogosho",
    "iso:country":"JP",
    "wof:name":"480-0135",
    "wof:placetype":"postalcode"
},
  "geometry": {"coordinates":[136.8871,35.3163],"type":"Point"}
}