{
  "type": "Feature",
  "properties": {
    "gn:adm1_name":"Miyagiken",
    "gn:adm2_name":"Sendaishiaobaku",
    "gn:name":"Nishikichou",
    "iso:country":"JP",
    "wof:name":"980-0012",
    "wof:placetype":"postalcode"
},
  "geometry": {"coordinates":[140.87799999999999,38.2689],"type":"Point"}
}