{
  "type": "Feature",
  "properties": {
    "gn:adm1_name":"Fukushimaken",
    "gn:adm2_name":"Shirakawashi",
    "gn:name":"Motomachi",
    "iso:country":"JP",
    "wof:name":"961-0905",
    "wof:placetype":"postalcode"
},
  "geometry": {"coordinates":[140.2166,37.1264],"type":"Point"}
}