{
  "type": "Feature",
  "properties": {
    "gn:adm1_name":"Shigaken",
    "gn:adm2_name":"Koukagunshigarakichou",
    "gn:name":"Tarao",
    "iso:country":"JP",
    "wof:name":"529-1821",
    "wof:placetype":"postalcode"
},
  "geometry": {"coordinates":[136.03989999999999,34.8136],"type":"Point"}
}