{
  "type": "Feature",
  "properties": {
    "gn:adm1_name":"Kouchiken",
    "gn:adm2_name":"Takaokagunsakawachou",
    "gn:name":"Higashigumi",
    "iso:country":"JP",
    "wof:name":"789-1232",
    "wof:placetype":"postalcode"
},
  "geometry": {"coordinates":[133.2912,33.4795],"type":"Point"}
}