{
  "type": "Feature",
  "properties": {
    "gn:adm1_name":"Ooitaken",
    "gn:adm2_name":"Nakatsushi",
    "gn:name":"Takase",
    "iso:country":"JP",
    "wof:name":"871-0026",
    "wof:placetype":"postalcode"
},
  "geometry": {"coordinates":[131.1797,33.5808],"type":"Point"}
}