{
  "type": "Feature",
  "properties": {
    "gn:adm1_name":"Shizuokaken",
    "gn:adm2_name":"Shizuokashi",
    "gn:name":"Karase",
    "iso:country":"JP",
    "wof:name":"420-0937",
    "wof:placetype":"postalcode"
},
  "geometry": {"coordinates":[138.38679999999999,35.0111],"type":"Point"}
}