{
  "type": "Feature",
  "properties": {
    "gn:adm1_name":"Gifuken",
    "gn:adm2_name":"Kaidugunnannouchou",
    "gn:name":"Komanoshinden",
    "iso:country":"JP",
    "wof:name":"503-0405",
    "wof:placetype":"postalcode"
},
  "geometry": {"coordinates":[136.59950000000001,35.232],"type":"Point"}
}