{
  "type": "Feature",
  "properties": {
    "gn:adm1_name":"Toukyouto",
    "gn:adm2_name":"Kodairashi",
    "gn:name":"Jousuiminamichou",
    "iso:country":"JP",
    "wof:name":"187-0021",
    "wof:placetype":"postalcode"
},
  "geometry": {"coordinates":[139.48689999999999,35.7126],"type":"Point"}
}