{
  "type": "Feature",
  "properties": {
    "gn:adm1_name":"Kyoutofu",
    "gn:adm2_name":"Kyoutoshiukyouku",
    "gn:name":"Uzumasahachiokachou",
    "iso:country":"JP",
    "wof:name":"616-8162",
    "wof:placetype":"postalcode"
},
  "geometry": {"coordinates":[135.7072,35.0158],"type":"Point"}
}