{
  "type": "Feature",
  "properties": {
    "gn:adm1_name":"Toyamaken",
    "gn:adm2_name":"Toyamashi",
    "gn:name":"Ooshima",
    "iso:country":"JP",
    "wof:name":"939-8025",
    "wof:placetype":"postalcode"
},
  "geometry": {"coordinates":[137.27209999999999,36.6742],"type":"Point"}
}