{
  "type": "Feature",
  "properties": {
    "gn:adm1_name":"Miyagiken",
    "gn:adm2_name":"Kuriharagunkannarichou",
    "gn:name":"Kamimachi",
    "iso:country":"JP",
    "wof:name":"989-5154",
    "wof:placetype":"postalcode"
},
  "geometry": {"coordinates":[141.07380000000001,38.8085],"type":"Point"}
}