{
  "type": "Feature",
  "properties": {
    "gn:adm1_name":"Saitamaken",
    "gn:adm2_name":"Asakashi",
    "gn:name":"Tajima",
    "iso:country":"JP",
    "wof:name":"351-0032",
    "wof:placetype":"postalcode"
},
  "geometry": {"coordinates":[139.60650000000001,35.8143],"type":"Point"}
}