{
  "type": "Feature",
  "properties": {
    "gn:adm1_name":"Kanagawaken",
    "gn:adm2_name":"Fujisawashi",
    "gn:name":"Tsujidou",
    "iso:country":"JP",
    "wof:name":"251-0047",
    "wof:placetype":"postalcode"
},
  "geometry": {"coordinates":[139.4468,35.3315],"type":"Point"}
}