{
  "type": "Feature",
  "properties": {
    "gn:adm1_name":"Aichiken",
    "gn:adm2_name":"Toyotashi",
    "gn:name":"Izumichou",
    "iso:country":"JP",
    "wof:name":"471-0803",
    "wof:placetype":"postalcode"
},
  "geometry": {"coordinates":[137.19159999999999,35.0717],"type":"Point"}
}