{
  "type": "Feature",
  "properties": {
    "gn:adm1_name":"Ibarakiken",
    "gn:adm2_name":"Kitaibarakishi",
    "gn:name":"Ootsuchoukitachou",
    "iso:country":"JP",
    "wof:name":"319-1704",
    "wof:placetype":"postalcode"
},
  "geometry": {"coordinates":[140.78229999999999,36.8451],"type":"Point"}
}