{
  "type": "Feature",
  "properties": {
    "gn:adm1_name":"Hyougoken",
    "gn:adm2_name":"Akoushi",
    "gn:name":"Kouno",
    "iso:country":"JP",
    "wof:name":"678-0171",
    "wof:placetype":"postalcode"
},
  "geometry": {"coordinates":[134.42740000000001,34.7818],"type":"Point"}
}