{
  "type": "Feature",
  "properties": {
    "gn:adm1_name":"Ibarakiken",
    "gn:adm2_name":"Shimodateshi",
    "gn:name":"Morisoejima",
    "iso:country":"JP",
    "wof:name":"308-0861",
    "wof:placetype":"postalcode"
},
  "geometry": {"coordinates":[139.94300000000001,36.3428],"type":"Point"}
}