{
  "type": "Feature",
  "properties": {
    "gn:adm1_name":"Fukuokaken",
    "gn:adm2_name":"Ukihagunyoshiimachi",
    "gn:name":"Tachibanada",
    "iso:country":"JP",
    "wof:name":"839-1307",
    "wof:placetype":"postalcode"
},
  "geometry": {"coordinates":[130.76050000000001,33.3565],"type":"Point"}
}