{
  "type": "Feature",
  "properties": {
    "gn:adm1_name":"Shigaken",
    "gn:adm2_name":"Ootsushi",
    "gn:name":"Seiwachou",
    "iso:country":"JP",
    "wof:name":"520-0227",
    "wof:placetype":"postalcode"
},
  "geometry": {"coordinates":[135.90639999999999,35.1451],"type":"Point"}
}