{
  "type": "Feature",
  "properties": {
    "gn:adm1_name":"Tottoriken",
    "gn:adm2_name":"Iwamigunfukubeson",
    "gn:name":"Hosogawa",
    "iso:country":"JP",
    "wof:name":"689-0102",
    "wof:placetype":"postalcode"
},
  "geometry": {"coordinates":[134.28100000000001,35.5532],"type":"Point"}
}