{
  "type": "Feature",
  "properties": {
    "gn:adm1_name":"Toyamaken",
    "gn:adm2_name":"Toyamashi",
    "gn:name":"Sugise",
    "iso:country":"JP",
    "wof:name":"939-8165",
    "wof:placetype":"postalcode"
},
  "geometry": {"coordinates":[137.22649999999999,36.6155],"type":"Point"}
}