{
  "type": "Feature",
  "properties": {
    "gn:adm1_name":"Ishikawaken",
    "gn:adm2_name":"Kashimagunkashimamachi",
    "gn:name":"Takebe",
    "iso:country":"JP",
    "wof:name":"929-1802",
    "wof:placetype":"postalcode"
},
  "geometry": {"coordinates":[136.92910000000001,36.9858],"type":"Point"}
}