{
  "type": "Feature",
  "properties": {
    "gn:adm1_name":"Aichiken",
    "gn:adm2_name":"Owariasahishi",
    "gn:name":"Inbamotochoukitayama",
    "iso:country":"JP",
    "wof:name":"488-0841",
    "wof:placetype":"postalcode"
},
  "geometry": {"coordinates":[137.0111,35.2109],"type":"Point"}
}