{
  "type": "Feature",
  "properties": {
    "gn:adm1_name":"Hyougoken",
    "gn:adm2_name":"Koubeshinadaku",
    "gn:name":"Minookadoori",
    "iso:country":"JP",
    "wof:name":"657-0812",
    "wof:placetype":"postalcode"
},
  "geometry": {"coordinates":[135.21899999999999,34.7217],"type":"Point"}
}