{
  "type": "Feature",
  "properties": {
    "gn:adm1_name":"Fukushimaken",
    "gn:adm2_name":"Shirakawashi",
    "gn:name":"Ichibanchou",
    "iso:country":"JP",
    "wof:name":"961-0947",
    "wof:placetype":"postalcode"
},
  "geometry": {"coordinates":[140.20500000000001,37.1268],"type":"Point"}
}