{
  "type": "Feature",
  "properties": {
    "gn:adm1_name":"Wakayamaken",
    "gn:adm2_name":"Hashimotoshi",
    "gn:name":"Hosokawa",
    "iso:country":"JP",
    "wof:name":"648-0051",
    "wof:placetype":"postalcode"
},
  "geometry": {"coordinates":[135.62010000000001,34.3506],"type":"Point"}
}