{
  "type": "Feature",
  "properties": {
    "gn:adm1_name":"Ibarakiken",
    "gn:adm2_name":"Tsukubashi",
    "gn:name":"Komagome",
    "iso:country":"JP",
    "wof:name":"300-1277",
    "wof:placetype":"postalcode"
},
  "geometry": {"coordinates":[140.09030000000001,35.998],"type":"Point"}
}