{
  "type": "Feature",
  "properties": {
    "gn:adm1_name":"Hyougoken",
    "gn:adm2_name":"Koubeshinishiku",
    "gn:name":"Ikawadanichoukamiwaki",
    "iso:country":"JP",
    "wof:name":"651-2105",
    "wof:placetype":"postalcode"
},
  "geometry": {"coordinates":[135.02969999999999,34.6807],"type":"Point"}
}