{
  "type": "Feature",
  "properties": {
    "gn:adm1_name":"Toyamaken",
    "gn:adm2_name":"Takaokashi",
    "gn:name":"Hakka",
    "iso:country":"JP",
    "wof:name":"933-0982",
    "wof:placetype":"postalcode"
},
  "geometry": {"coordinates":[137.023,36.7719],"type":"Point"}
}