{
  "type": "Feature",
  "properties": {
    "gn:adm1_name":"Aichiken",
    "gn:adm2_name":"Gamagoorishi",
    "gn:name":"Araichou",
    "iso:country":"JP",
    "wof:name":"443-0052",
    "wof:placetype":"postalcode"
},
  "geometry": {"coordinates":[137.23330000000001,34.8287],"type":"Point"}
}