{
  "type": "Feature",
  "properties": {
    "gn:adm1_name":"Toukyouto",
    "gn:adm2_name":"Fuchuushi",
    "gn:name":"Momijigaoka",
    "iso:country":"JP",
    "wof:name":"183-0004",
    "wof:placetype":"postalcode"
},
  "geometry": {"coordinates":[139.5129,35.6756],"type":"Point"}
}