{
  "type": "Feature",
  "properties": {
    "gn:adm1_name":"Okinawaken",
    "gn:adm2_name":"Gushikawashi",
    "gn:name":"Suzaki",
    "iso:country":"JP",
    "wof:name":"904-2234",
    "wof:placetype":"postalcode"
},
  "geometry": {"coordinates":[127.85209999999999,26.3337],"type":"Point"}
}