{
  "type": "Feature",
  "properties": {
    "gn:adm1_name":"Aichiken",
    "gn:adm2_name":"Nagoyashichikusaku",
    "gn:name":"Tashirochou(Kanokoden)",
    "iso:country":"JP",
    "wof:name":"464-0023",
    "wof:placetype":"postalcode"
},
  "geometry": {"coordinates":[136.9709,35.1658],"type":"Point"}
}