{
  "type": "Feature",
  "properties": {
    "gn:adm1_name":"Kagoshimaken",
    "gn:adm2_name":"Ooshimagunyoronchou",
    "gn:name":"Gusuku",
    "iso:country":"JP",
    "wof:name":"891-9303",
    "wof:placetype":"postalcode"
},
  "geometry": {"coordinates":[128.42769999999999,27.0429],"type":"Point"}
}