{
  "type": "Feature",
  "properties": {
    "gn:adm1_name":"Fukuokaken",
    "gn:adm2_name":"Ongagun'Okagakimachi",
    "gn:name":"Higashiyamada",
    "iso:country":"JP",
    "wof:name":"811-4220",
    "wof:placetype":"postalcode"
},
  "geometry": {"coordinates":[130.6277,33.8482],"type":"Point"}
}