{
  "type": "Feature",
  "properties": {
    "gn:adm1_name":"Miyagiken",
    "gn:adm2_name":"Kesennumashi",
    "gn:name":"Ochiai",
    "iso:country":"JP",
    "wof:name":"988-0843",
    "wof:placetype":"postalcode"
},
  "geometry": {"coordinates":[141.49629999999999,38.9054],"type":"Point"}
}