{
  "type": "Feature",
  "properties": {
    "gn:adm1_name":"Miyazakiken",
    "gn:adm2_name":"Higashimorokataguntakaokachou",
    "gn:name":"Oyamada",
    "iso:country":"JP",
    "wof:name":"880-2214",
    "wof:placetype":"postalcode"
},
  "geometry": {"coordinates":[131.32239999999999,31.9352],"type":"Point"}
}