{
  "type": "Feature",
  "properties": {
    "gn:adm1_name":"Nagasakiken",
    "gn:adm2_name":"Kitamatsuuragun'Ikitsukichou",
    "gn:name":"Yamadamen",
    "iso:country":"JP",
    "wof:name":"859-5704",
    "wof:placetype":"postalcode"
},
  "geometry": {"coordinates":[129.42310000000001,33.3708],"type":"Point"}
}