{
  "type": "Feature",
  "properties": {
    "gn:adm1_name":"Toyamaken",
    "gn:adm2_name":"Takaokashi",
    "gn:name":"Nibanmachi",
    "iso:country":"JP",
    "wof:name":"933-0931",
    "wof:placetype":"postalcode"
},
  "geometry": {"coordinates":[137.00829999999999,36.7449],"type":"Point"}
}