{
  "type": "Feature",
  "properties": {
    "gn:adm1_name":"Saitamaken",
    "gn:adm2_name":"Kawaguchishi",
    "gn:name":"Funatochou",
    "iso:country":"JP",
    "wof:name":"332-0013",
    "wof:placetype":"postalcode"
},
  "geometry": {"coordinates":[139.7242,35.7932],"type":"Point"}
}