{
  "type": "Feature",
  "properties": {
    "gn:adm1_name":"Ehimeken",
    "gn:adm2_name":"Houjoushi",
    "gn:name":"Oonishidani",
    "iso:country":"JP",
    "wof:name":"799-2458",
    "wof:placetype":"postalcode"
},
  "geometry": {"coordinates":[132.7852,33.9132],"type":"Point"}
}