{
  "type": "Feature",
  "properties": {
    "gn:adm1_name":"Chibaken",
    "gn:adm2_name":"Chibashichuuouku",
    "gn:name":"Miyazakichou",
    "iso:country":"JP",
    "wof:name":"260-0805",
    "wof:placetype":"postalcode"
},
  "geometry": {"coordinates":[140.14349999999999,35.5851],"type":"Point"}
}