{
  "type": "Feature",
  "properties": {
    "gn:adm1_name":"Kumamotoken",
    "gn:adm2_name":"Kumamotoshi",
    "gn:name":"Furukyoumachi",
    "iso:country":"JP",
    "wof:name":"860-0007",
    "wof:placetype":"postalcode"
},
  "geometry": {"coordinates":[130.70089999999999,32.809],"type":"Point"}
}