{
  "type": "Feature",
  "properties": {
    "gn:adm1_name":"Toukyouto",
    "gn:adm2_name":"Arakawaku",
    "gn:name":"Nishinippori",
    "iso:country":"JP",
    "wof:name":"116-0013",
    "wof:placetype":"postalcode"
},
  "geometry": {"coordinates":[139.77029999999999,35.7332],"type":"Point"}
}