{
  "type": "Feature",
  "properties": {
    "gn:adm1_name":"Hyougoken",
    "gn:adm2_name":"Akashishi",
    "gn:name":"Tateishi",
    "iso:country":"JP",
    "wof:name":"673-0032",
    "wof:placetype":"postalcode"
},
  "geometry": {"coordinates":[134.97229999999999,34.6518],"type":"Point"}
}