{
  "type": "Feature",
  "properties": {
    "gn:adm1_name":"Tottoriken",
    "gn:adm2_name":"Saihakugunyodoechou",
    "gn:name":"Honguu",
    "iso:country":"JP",
    "wof:name":"689-3413",
    "wof:placetype":"postalcode"
},
  "geometry": {"coordinates":[133.45590000000001,35.423],"type":"Point"}
}