{
  "type": "Feature",
  "properties": {
    "gn:adm1_name":"Fukuiken",
    "gn:adm2_name":"Sakaigunharuechou",
    "gn:name":"Edomekamichuuou",
    "iso:country":"JP",
    "wof:name":"919-0453",
    "wof:placetype":"postalcode"
},
  "geometry": {"coordinates":[136.22640000000001,36.1239],"type":"Point"}
}