{
  "type": "Feature",
  "properties": {
    "gn:adm1_name":"Aichiken",
    "gn:adm2_name":"Shinshiroshi",
    "gn:name":"Minamibata",
    "iso:country":"JP",
    "wof:name":"441-1386",
    "wof:placetype":"postalcode"
},
  "geometry": {"coordinates":[137.4897,34.897],"type":"Point"}
}