{
  "type": "Feature",
  "properties": {
    "gn:adm1_name":"Ooitaken",
    "gn:adm2_name":"Usukishi",
    "gn:name":"Emuta",
    "iso:country":"JP",
    "wof:name":"875-0023",
    "wof:placetype":"postalcode"
},
  "geometry": {"coordinates":[131.78559999999999,33.1268],"type":"Point"}
}