{
  "type": "Feature",
  "properties": {
    "gn:adm1_name":"Oosakafu",
    "gn:adm2_name":"Kishiwadashi",
    "gn:name":"Nakagitachou",
    "iso:country":"JP",
    "wof:name":"596-0062",
    "wof:placetype":"postalcode"
},
  "geometry": {"coordinates":[135.36840000000001,34.4639],"type":"Point"}
}