{
  "type": "Feature",
  "properties": {
    "gn:adm1_name":"Aichiken",
    "gn:adm2_name":"Nagoyashinakagawaku",
    "gn:name":"Shoumeichou",
    "iso:country":"JP",
    "wof:name":"454-0855",
    "wof:placetype":"postalcode"
},
  "geometry": {"coordinates":[136.87100000000001,35.1223],"type":"Point"}
}