{
  "type": "Feature",
  "properties": {
    "gn:adm1_name":"Kouchiken",
    "gn:adm2_name":"Hatagun'Ootsukichou",
    "gn:name":"Hiromi",
    "iso:country":"JP",
    "wof:name":"788-0302",
    "wof:placetype":"postalcode"
},
  "geometry": {"coordinates":[132.70760000000001,32.8451],"type":"Point"}
}