{
  "type": "Feature",
  "properties": {
    "gn:adm1_name":"Ehimeken",
    "gn:adm2_name":"Matsuyamashi",
    "gn:name":"Dougoyunomachi",
    "iso:country":"JP",
    "wof:name":"790-0842",
    "wof:placetype":"postalcode"
},
  "geometry": {"coordinates":[132.78530000000001,33.8514],"type":"Point"}
}