{
  "type": "Feature",
  "properties": {
    "gn:adm1_name":"Yamagataken",
    "gn:adm2_name":"Nanyoushi",
    "gn:name":"Kotaki",
    "iso:country":"JP",
    "wof:name":"992-0581",
    "wof:placetype":"postalcode"
},
  "geometry": {"coordinates":[140.18690000000001,38.1857],"type":"Point"}
}