{
  "type": "Feature",
  "properties": {
    "gn:adm1_name":"Kyoutofu",
    "gn:adm2_name":"Kasagun'Ooechou",
    "gn:name":"Hitou",
    "iso:country":"JP",
    "wof:name":"620-0313",
    "wof:placetype":"postalcode"
},
  "geometry": {"coordinates":[135.1164,35.3663],"type":"Point"}
}