{
  "type": "Feature",
  "properties": {
    "gn:adm1_name":"Miyagiken",
    "gn:adm2_name":"Shibatagun'Oogawaramachi",
    "gn:name":"Shin'Aokawa",
    "iso:country":"JP",
    "wof:name":"989-1264",
    "wof:placetype":"postalcode"
},
  "geometry": {"coordinates":[140.73910000000001,38.0627],"type":"Point"}
}