{
  "type": "Feature",
  "properties": {
    "gn:adm1_name":"Fukushimaken",
    "gn:adm2_name":"Iwakishi",
    "gn:name":"Tabitomachinichibu",
    "iso:country":"JP",
    "wof:name":"974-0241",
    "wof:placetype":"postalcode"
},
  "geometry": {"coordinates":[140.66050000000001,36.9685],"type":"Point"}
}