{
  "type": "Feature",
  "properties": {
    "gn:adm1_name":"Nagasakiken",
    "gn:adm2_name":"Matsuurashi",
    "gn:name":"Shisachoukayanokimen",
    "iso:country":"JP",
    "wof:name":"859-4504",
    "wof:placetype":"postalcode"
},
  "geometry": {"coordinates":[129.7072,33.3222],"type":"Point"}
}