{
  "type": "Feature",
  "properties": {
    "gn:adm1_name":"Saitamaken",
    "gn:adm2_name":"Yoshikawashi",
    "gn:name":"Saranuma",
    "iso:country":"JP",
    "wof:name":"342-0023",
    "wof:placetype":"postalcode"
},
  "geometry": {"coordinates":[139.8707,35.8868],"type":"Point"}
}