{
  "type": "Feature",
  "properties": {
    "gn:adm1_name":"Fukuokaken",
    "gn:adm2_name":"Miyakoguntoyotsumachi",
    "gn:name":"Kamisaka",
    "iso:country":"JP",
    "wof:name":"824-0111",
    "wof:placetype":"postalcode"
},
  "geometry": {"coordinates":[130.90690000000001,33.6554],"type":"Point"}
}