{
  "type": "Feature",
  "properties": {
    "gn:adm1_name":"Toyamaken",
    "gn:adm2_name":"Tonamishi",
    "gn:name":"Tsubonouchi",
    "iso:country":"JP",
    "wof:name":"939-1384",
    "wof:placetype":"postalcode"
},
  "geometry": {"coordinates":[136.9692,36.6336],"type":"Point"}
}