{
  "type": "Feature",
  "properties": {
    "gn:adm1_name":"Yamaguchiken",
    "gn:adm2_name":"Shimonosekishi",
    "gn:name":"Choufutoyorachou",
    "iso:country":"JP",
    "wof:name":"752-0945",
    "wof:placetype":"postalcode"
},
  "geometry": {"coordinates":[130.98920000000001,34.0097],"type":"Point"}
}