{
  "type": "Feature",
  "properties": {
    "gn:adm1_name":"Shizuokaken",
    "gn:adm2_name":"Fukuroishi",
    "gn:name":"Mutsumichou",
    "iso:country":"JP",
    "wof:name":"437-0041",
    "wof:placetype":"postalcode"
},
  "geometry": {"coordinates":[137.91919999999999,34.7421],"type":"Point"}
}