{
  "type": "Feature",
  "properties": {
    "gn:adm1_name":"Okayamaken",
    "gn:adm2_name":"Okayamashi",
    "gn:name":"Musa",
    "iso:country":"JP",
    "wof:name":"701-2141",
    "wof:placetype":"postalcode"
},
  "geometry": {"coordinates":[133.97900000000001,34.7258],"type":"Point"}
}