{
  "type": "Feature",
  "properties": {
    "gn:adm1_name":"Tochigiken",
    "gn:adm2_name":"Nikkoushi",
    "gn:name":"Ikanikeisaiganaibaai",
    "iso:country":"JP",
    "wof:name":"321-1400",
    "wof:placetype":"postalcode"
},
  "geometry": {"coordinates":[139.62280000000001,36.7456],"type":"Point"}
}