{
  "type": "Feature",
  "properties": {
    "gn:adm1_name":"Shigaken",
    "gn:adm2_name":"Ikagunyogochou",
    "gn:name":"Ootani",
    "iso:country":"JP",
    "wof:name":"529-0534",
    "wof:placetype":"postalcode"
},
  "geometry": {"coordinates":[136.1934,35.5739],"type":"Point"}
}