{
  "type": "Feature",
  "properties": {
    "gn:adm1_name":"Miyagiken",
    "gn:adm2_name":"Igugunmarumorimachi",
    "gn:name":"Nozokiminami",
    "iso:country":"JP",
    "wof:name":"981-2161",
    "wof:placetype":"postalcode"
},
  "geometry": {"coordinates":[140.76669999999999,37.9139],"type":"Point"}
}