{
  "type": "Feature",
  "properties": {
    "gn:adm1_name":"Okayamaken",
    "gn:adm2_name":"Tsuyamashi",
    "gn:name":"Honmachi",
    "iso:country":"JP",
    "wof:name":"708-0073",
    "wof:placetype":"postalcode"
},
  "geometry": {"coordinates":[133.999,35.0601],"type":"Point"}
}