{
  "type": "Feature",
  "properties": {
    "gn:adm1_name":"Tottoriken",
    "gn:adm2_name":"Kurayoshishi",
    "gn:name":"Kitamo",
    "iso:country":"JP",
    "wof:name":"682-0903",
    "wof:placetype":"postalcode"
},
  "geometry": {"coordinates":[133.7835,35.4552],"type":"Point"}
}