{
  "type": "Feature",
  "properties": {
    "gn:adm1_name":"Ishikawaken",
    "gn:adm2_name":"Kagashi",
    "gn:name":"Yamashiroonsen",
    "iso:country":"JP",
    "wof:name":"922-0242",
    "wof:placetype":"postalcode"
},
  "geometry": {"coordinates":[136.36019999999999,36.2901],"type":"Point"}
}