{
  "type": "Feature",
  "properties": {
    "gn:adm1_name":"Tochigiken",
    "gn:adm2_name":"Mookashi",
    "gn:name":"Sugama",
    "iso:country":"JP",
    "wof:name":"321-4313",
    "wof:placetype":"postalcode"
},
  "geometry": {"coordinates":[140.05369999999999,36.4211],"type":"Point"}
}