{
  "type": "Feature",
  "properties": {
    "gn:adm1_name":"Mieken",
    "gn:adm2_name":"Suzukashi",
    "gn:name":"Shiroko",
    "iso:country":"JP",
    "wof:name":"510-0243",
    "wof:placetype":"postalcode"
},
  "geometry": {"coordinates":[136.58619999999999,34.8298],"type":"Point"}
}