{
  "type": "Feature",
  "properties": {
    "gn:adm1_name":"Wakayamaken",
    "gn:adm2_name":"Nishimurogunnakahechichou",
    "gn:name":"Nishidani",
    "iso:country":"JP",
    "wof:name":"646-1414",
    "wof:placetype":"postalcode"
},
  "geometry": {"coordinates":[135.4837,33.7685],"type":"Point"}
}