{
  "type": "Feature",
  "properties": {
    "gn:adm1_name":"Gunmaken",
    "gn:adm2_name":"Agatsumagunnaganoharamachi",
    "gn:name":"Yokiya",
    "iso:country":"JP",
    "wof:name":"377-1305",
    "wof:placetype":"postalcode"
},
  "geometry": {"coordinates":[138.62450000000001,36.5452],"type":"Point"}
}