{
  "type": "Feature",
  "properties": {
    "gn:adm1_name":"Gunmaken",
    "gn:adm2_name":"Agatsumagun'Agatsumamachi",
    "gn:name":"Ikanikeisaiganaibaai",
    "iso:country":"JP",
    "wof:name":"377-0800",
    "wof:placetype":"postalcode"
},
  "geometry": {"coordinates":[138.83750000000001,36.5715],"type":"Point"}
}