{
  "type": "Feature",
  "properties": {
    "gn:adm1_name":"Fukushimaken",
    "gn:adm2_name":"Yamagunkitashiobaramura",
    "gn:name":"Shimoyoshi",
    "iso:country":"JP",
    "wof:name":"966-0405",
    "wof:placetype":"postalcode"
},
  "geometry": {"coordinates":[139.91909999999999,37.6584],"type":"Point"}
}