{
  "type": "Feature",
  "properties": {
    "gn:adm1_name":"Yamagataken",
    "gn:adm2_name":"Shinjoushi",
    "gn:name":"Tokihamachi",
    "iso:country":"JP",
    "wof:name":"996-0021",
    "wof:placetype":"postalcode"
},
  "geometry": {"coordinates":[140.30359999999999,38.7701],"type":"Point"}
}