{
  "type": "Feature",
  "properties": {
    "gn:adm1_name":"Toyamaken",
    "gn:adm2_name":"Takaokashi",
    "gn:name":"Fushikiyatashinmachi",
    "iso:country":"JP",
    "wof:name":"933-0121",
    "wof:placetype":"postalcode"
},
  "geometry": {"coordinates":[137.04230000000001,36.789],"type":"Point"}
}