{
  "type": "Feature",
  "properties": {
    "gn:adm1_name":"Ehimeken",
    "gn:adm2_name":"Higashiuwagun'Uwachou",
    "gn:name":"Kubo",
    "iso:country":"JP",
    "wof:name":"797-0036",
    "wof:placetype":"postalcode"
},
  "geometry": {"coordinates":[132.5189,33.4435],"type":"Point"}
}