{
  "type": "Feature",
  "properties": {
    "gn:adm1_name":"Yamagataken",
    "gn:adm2_name":"Murayamashi",
    "gn:name":"Yukinokannongou",
    "iso:country":"JP",
    "wof:name":"995-0207",
    "wof:placetype":"postalcode"
},
  "geometry": {"coordinates":[140.36850000000001,38.4921],"type":"Point"}
}