{
  "type": "Feature",
  "properties": {
    "gn:adm1_name":"Niigataken",
    "gn:adm2_name":"Shibatashi",
    "gn:name":"Honchou",
    "iso:country":"JP",
    "wof:name":"957-0054",
    "wof:placetype":"postalcode"
},
  "geometry": {"coordinates":[139.33430000000001,37.949],"type":"Point"}
}