{
  "type": "Feature",
  "properties": {
    "gn:adm1_name":"Hyougoken",
    "gn:adm2_name":"Koubeshihigashinadaku",
    "gn:name":"Mikagechouishiya",
    "iso:country":"JP",
    "wof:name":"658-0055",
    "wof:placetype":"postalcode"
},
  "geometry": {"coordinates":[135.24889999999999,34.7202],"type":"Point"}
}