{
  "type": "Feature",
  "properties": {
    "gn:adm1_name":"Nagasakiken",
    "gn:adm2_name":"Isahayashi",
    "gn:name":"Ukimachi",
    "iso:country":"JP",
    "wof:name":"854-0121",
    "wof:placetype":"postalcode"
},
  "geometry": {"coordinates":[130.083,32.795],"type":"Point"}
}