{
  "type": "Feature",
  "properties": {
    "gn:adm1_name":"Kyoutofu",
    "gn:adm2_name":"Kyoutoshiukyouku",
    "gn:name":"Tokiwakandachou",
    "iso:country":"JP",
    "wof:name":"616-8219",
    "wof:placetype":"postalcode"
},
  "geometry": {"coordinates":[135.70930000000001,35.0227],"type":"Point"}
}