{
  "type": "Feature",
  "properties": {
    "gn:adm1_name":"Fukuiken",
    "gn:adm2_name":"Katsuyamashi",
    "gn:name":"Shikadanichoushida",
    "iso:country":"JP",
    "wof:name":"911-0842",
    "wof:placetype":"postalcode"
},
  "geometry": {"coordinates":[136.46289999999999,36.065],"type":"Point"}
}