{
  "type": "Feature",
  "properties": {
    "gn:adm1_name":"Okayamaken",
    "gn:adm2_name":"Mitsugunkamogawachou",
    "gn:name":"Sugitani",
    "iso:country":"JP",
    "wof:name":"709-2671",
    "wof:placetype":"postalcode"
},
  "geometry": {"coordinates":[133.7526,34.9412],"type":"Point"}
}