{
  "type": "Feature",
  "properties": {
    "gn:adm1_name":"Ehimeken",
    "gn:adm2_name":"Matsuyamashi",
    "gn:name":"Ikushimachi",
    "iso:country":"JP",
    "wof:name":"790-0051",
    "wof:placetype":"postalcode"
},
  "geometry": {"coordinates":[132.7424,33.8327],"type":"Point"}
}