{
  "type": "Feature",
  "properties": {
    "gn:adm1_name":"Shigaken",
    "gn:adm2_name":"Ikagunnishiazaichou",
    "gn:name":"Yamakado",
    "iso:country":"JP",
    "wof:name":"529-0724",
    "wof:placetype":"postalcode"
},
  "geometry": {"coordinates":[136.1234,35.522],"type":"Point"}
}