{
  "type": "Feature",
  "properties": {
    "gn:adm1_name":"Hyougoken",
    "gn:adm2_name":"Kawanishishi",
    "gn:name":"Sakane",
    "iso:country":"JP",
    "wof:name":"666-0021",
    "wof:placetype":"postalcode"
},
  "geometry": {"coordinates":[135.41220000000001,34.823],"type":"Point"}
}