{
  "type": "Feature",
  "properties": {
    "gn:adm1_name":"Niigataken",
    "gn:adm2_name":"Kamoshi",
    "gn:name":"Gotanda",
    "iso:country":"JP",
    "wof:name":"959-1302",
    "wof:placetype":"postalcode"
},
  "geometry": {"coordinates":[139.024,37.6929],"type":"Point"}
}