{
  "type": "Feature",
  "properties": {
    "gn:adm1_name":"Chibaken",
    "gn:adm2_name":"Chouseigunmutsuzawamachi",
    "gn:name":"Kawashima",
    "iso:country":"JP",
    "wof:name":"299-4402",
    "wof:placetype":"postalcode"
},
  "geometry": {"coordinates":[140.33750000000001,35.3841],"type":"Point"}
}