{
  "type": "Feature",
  "properties": {
    "gn:adm1_name":"Okinawaken",
    "gn:adm2_name":"Nahashi",
    "gn:name":"Kohagura",
    "iso:country":"JP",
    "wof:name":"900-0024",
    "wof:placetype":"postalcode"
},
  "geometry": {"coordinates":[127.68729999999999,26.1994],"type":"Point"}
}