{
  "type": "Feature",
  "properties": {
    "gn:adm1_name":"Shizuokaken",
    "gn:adm2_name":"Kamogunkawaduchou",
    "gn:name":"Sasahara",
    "iso:country":"JP",
    "wof:name":"413-0512",
    "wof:placetype":"postalcode"
},
  "geometry": {"coordinates":[138.9931,34.7492],"type":"Point"}
}