{
  "type": "Feature",
  "properties": {
    "gn:adm1_name":"Shizuokaken",
    "gn:adm2_name":"Tagatagunkannamichou",
    "gn:name":"Shinden",
    "iso:country":"JP",
    "wof:name":"419-0115",
    "wof:placetype":"postalcode"
},
  "geometry": {"coordinates":[138.94229999999999,35.0691],"type":"Point"}
}