{
  "type": "Feature",
  "properties": {
    "gn:adm1_name":"Fukushimaken",
    "gn:adm2_name":"Dategundatemachi",
    "gn:name":"Ubagawa",
    "iso:country":"JP",
    "wof:name":"960-0425",
    "wof:placetype":"postalcode"
},
  "geometry": {"coordinates":[140.49959999999999,37.8148],"type":"Point"}
}