{
  "type": "Feature",
  "properties": {
    "gn:adm1_name":"Oosakafu",
    "gn:adm2_name":"Sennangunkumatorichou",
    "gn:name":"Shichiyamahigashi",
    "iso:country":"JP",
    "wof:name":"590-0425",
    "wof:placetype":"postalcode"
},
  "geometry": {"coordinates":[135.3623,34.4123],"type":"Point"}
}