{
  "type": "Feature",
  "properties": {
    "gn:adm1_name":"Toukyouto",
    "gn:adm2_name":"Chiyodaku",
    "gn:name":"Kandahigashikonyachou",
    "iso:country":"JP",
    "wof:name":"101-0034",
    "wof:placetype":"postalcode"
},
  "geometry": {"coordinates":[139.77459999999999,35.6931],"type":"Point"}
}