{
  "type": "Feature",
  "properties": {
    "gn:adm1_name":"Ooitaken",
    "gn:adm2_name":"Hitashi",
    "gn:name":"Suzuremachi",
    "iso:country":"JP",
    "wof:name":"877-1243",
    "wof:placetype":"postalcode"
},
  "geometry": {"coordinates":[130.941,33.3924],"type":"Point"}
}