{
  "type": "Feature",
  "properties": {
    "gn:adm1_name":"Fukushimaken",
    "gn:adm2_name":"Nishishirakawagunnishigoumura",
    "gn:name":"Mabune",
    "iso:country":"JP",
    "wof:name":"961-8071",
    "wof:placetype":"postalcode"
},
  "geometry": {"coordinates":[140.11189999999999,37.1504],"type":"Point"}
}