{
  "type": "Feature",
  "properties": {
    "gn:adm1_name":"Kyoutofu",
    "gn:adm2_name":"Kyoutoshihigashiyamaku",
    "gn:name":"Makitachou",
    "iso:country":"JP",
    "wof:name":"605-0942",
    "wof:placetype":"postalcode"
},
  "geometry": {"coordinates":[135.77070000000001,34.9867],"type":"Point"}
}