{
  "type": "Feature",
  "properties": {
    "gn:adm1_name":"Tochigiken",
    "gn:adm2_name":"Hagagun'Ichikaimachi",
    "gn:name":"Ishioroshi",
    "iso:country":"JP",
    "wof:name":"321-3422",
    "wof:placetype":"postalcode"
},
  "geometry": {"coordinates":[140.12569999999999,36.5265],"type":"Point"}
}