{
  "type": "Feature",
  "properties": {
    "gn:adm1_name":"Shigaken",
    "gn:adm2_name":"Sakatagunsantouchou",
    "gn:name":"Nishiyama",
    "iso:country":"JP",
    "wof:name":"521-0241",
    "wof:placetype":"postalcode"
},
  "geometry": {"coordinates":[136.36779999999999,35.3698],"type":"Point"}
}