{
  "type": "Feature",
  "properties": {
    "gn:adm1_name":"Naganoken",
    "gn:adm2_name":"Kisogun'Agematsumachi",
    "gn:name":"Ikanikeisaiganaibaai",
    "iso:country":"JP",
    "wof:name":"399-5600",
    "wof:placetype":"postalcode"
},
  "geometry": {"coordinates":[137.69550000000001,35.7846],"type":"Point"}
}