{
  "type": "Feature",
  "properties": {
    "gn:adm1_name":"Shizuokaken",
    "gn:adm2_name":"Shizuokashi",
    "gn:name":"Shimizuobane",
    "iso:country":"JP",
    "wof:name":"424-0103",
    "wof:placetype":"postalcode"
},
  "geometry": {"coordinates":[138.4897,35.0454],"type":"Point"}
}