{
  "type": "Feature",
  "properties": {
    "gn:adm1_name":"Shizuokaken",
    "gn:adm2_name":"Shizuokashi",
    "gn:name":"Shimizuyokosunahonchou",
    "iso:country":"JP",
    "wof:name":"424-0033",
    "wof:placetype":"postalcode"
},
  "geometry": {"coordinates":[138.50049999999999,35.0435],"type":"Point"}
}