{
  "type": "Feature",
  "properties": {
    "gn:adm1_name":"Fukuiken",
    "gn:adm2_name":"Mikatagunmihamachou",
    "gn:name":"Kanayama",
    "iso:country":"JP",
    "wof:name":"919-1145",
    "wof:placetype":"postalcode"
},
  "geometry": {"coordinates":[135.9247,35.5989],"type":"Point"}
}