{
  "type": "Feature",
  "properties": {
    "gn:adm1_name":"Hyougoken",
    "gn:adm2_name":"Sasayamashi",
    "gn:name":"Kawauchidai",
    "iso:country":"JP",
    "wof:name":"669-2722",
    "wof:placetype":"postalcode"
},
  "geometry": {"coordinates":[135.17850000000001,35.0912],"type":"Point"}
}