{
  "type": "Feature",
  "properties": {
    "gn:adm1_name":"Wakayamaken",
    "gn:adm2_name":"Aridagunhirogawachou",
    "gn:name":"Yanase",
    "iso:country":"JP",
    "wof:name":"643-0061",
    "wof:placetype":"postalcode"
},
  "geometry": {"coordinates":[135.19,34.0185],"type":"Point"}
}