{
  "type": "Feature",
  "properties": {
    "gn:adm1_name":"Okayamaken",
    "gn:adm2_name":"Ibarashi",
    "gn:name":"Mondenchou",
    "iso:country":"JP",
    "wof:name":"715-0005",
    "wof:placetype":"postalcode"
},
  "geometry": {"coordinates":[133.49100000000001,34.57],"type":"Point"}
}