{
  "type": "Feature",
  "properties": {
    "gn:adm1_name":"Nagasakiken",
    "gn:adm2_name":"Nagasakishi",
    "gn:name":"Iwasedoumachi",
    "iso:country":"JP",
    "wof:name":"850-0072",
    "wof:placetype":"postalcode"
},
  "geometry": {"coordinates":[129.8544,32.7384],"type":"Point"}
}