{
  "type": "Feature",
  "properties": {
    "gn:adm1_name":"Kouchiken",
    "gn:adm2_name":"Kouchishi",
    "gn:name":"Yoshidachou",
    "iso:country":"JP",
    "wof:name":"780-0048",
    "wof:placetype":"postalcode"
},
  "geometry": {"coordinates":[133.5343,33.5717],"type":"Point"}
}