{
  "type": "Feature",
  "properties": {
    "gn:adm1_name":"Fukushimaken",
    "gn:adm2_name":"Kitaaidugunkitaaidumura",
    "gn:name":"Sagibayashi",
    "iso:country":"JP",
    "wof:name":"965-0126",
    "wof:placetype":"postalcode"
},
  "geometry": {"coordinates":[139.8579,37.4947],"type":"Point"}
}