{
  "type": "Feature",
  "properties": {
    "gn:adm1_name":"Miyazakiken",
    "gn:adm2_name":"Nishiusukiguntakachihochou",
    "gn:name":"Oshikata",
    "iso:country":"JP",
    "wof:name":"882-1102",
    "wof:placetype":"postalcode"
},
  "geometry": {"coordinates":[131.27680000000001,32.7082],"type":"Point"}
}