{
  "type": "Feature",
  "properties": {
    "gn:adm1_name":"Shizuokaken",
    "gn:adm2_name":"Yaidushi",
    "gn:name":"Echigoshima",
    "iso:country":"JP",
    "wof:name":"425-0092",
    "wof:placetype":"postalcode"
},
  "geometry": {"coordinates":[138.29810000000001,34.8847],"type":"Point"}
}