{
  "type": "Feature",
  "properties": {
    "gn:adm1_name":"Naganoken",
    "gn:adm2_name":"Minamiadumigun'Adumimura",
    "gn:name":"Bandokoro",
    "iso:country":"JP",
    "wof:name":"390-1506",
    "wof:placetype":"postalcode"
},
  "geometry": {"coordinates":[137.65369999999999,36.1249],"type":"Point"}
}