{
  "type": "Feature",
  "properties": {
    "gn:adm1_name":"Tochigiken",
    "gn:adm2_name":"Nasugunbatoumachi",
    "gn:name":"Tomiyama",
    "iso:country":"JP",
    "wof:name":"324-0616",
    "wof:placetype":"postalcode"
},
  "geometry": {"coordinates":[140.19710000000001,36.6898],"type":"Point"}
}