{
  "type": "Feature",
  "properties": {
    "gn:adm1_name":"Kanagawaken",
    "gn:adm2_name":"Yokohamashinakaku",
    "gn:name":"Uchikoshi",
    "iso:country":"JP",
    "wof:name":"231-0867",
    "wof:placetype":"postalcode"
},
  "geometry": {"coordinates":[139.6379,35.4344],"type":"Point"}
}