{
  "type": "Feature",
  "properties": {
    "gn:adm1_name":"Oosakafu",
    "gn:adm2_name":"Habikinoshi",
    "gn:name":"Tsuboi",
    "iso:country":"JP",
    "wof:name":"583-0844",
    "wof:placetype":"postalcode"
},
  "geometry": {"coordinates":[135.6225,34.5302],"type":"Point"}
}