{
  "type": "Feature",
  "properties": {
    "gn:adm1_name":"Aichiken",
    "gn:adm2_name":"Handashi",
    "gn:name":"Doiyamachou",
    "iso:country":"JP",
    "wof:name":"475-0914",
    "wof:placetype":"postalcode"
},
  "geometry": {"coordinates":[136.90719999999999,34.8979],"type":"Point"}
}