{
  "type": "Feature",
  "properties": {
    "gn:adm1_name":"Oosakafu",
    "gn:adm2_name":"Toyonakashi",
    "gn:name":"Tachibanachou",
    "iso:country":"JP",
    "wof:name":"560-0025",
    "wof:placetype":"postalcode"
},
  "geometry": {"coordinates":[135.45689999999999,34.784],"type":"Point"}
}