{
  "type": "Feature",
  "properties": {
    "gn:adm1_name":"Ehimeken",
    "gn:adm2_name":"Minamiuwagunnishiumichou",
    "gn:name":"Sotodomari",
    "iso:country":"JP",
    "wof:name":"798-4208",
    "wof:placetype":"postalcode"
},
  "geometry": {"coordinates":[132.4776,32.9364],"type":"Point"}
}