{
  "type": "Feature",
  "properties": {
    "gn:adm1_name":"Miyagiken",
    "gn:adm2_name":"Motoyoshigunkarakuwachou",
    "gn:name":"Arayamae",
    "iso:country":"JP",
    "wof:name":"988-0503",
    "wof:placetype":"postalcode"
},
  "geometry": {"coordinates":[141.6292,38.9588],"type":"Point"}
}