{
  "type": "Feature",
  "properties": {
    "gn:adm1_name":"Shigaken",
    "gn:adm2_name":"Gamougunhinochou",
    "gn:name":"Ootani",
    "iso:country":"JP",
    "wof:name":"529-1608",
    "wof:placetype":"postalcode"
},
  "geometry": {"coordinates":[136.23750000000001,35.0257],"type":"Point"}
}