{
  "type": "Feature",
  "properties": {
    "gn:adm1_name":"Oosakafu",
    "gn:adm2_name":"Oosakashikonohanaku",
    "gn:name":"Shikanjima",
    "iso:country":"JP",
    "wof:name":"554-0014",
    "wof:placetype":"postalcode"
},
  "geometry": {"coordinates":[135.45519999999999,34.6849],"type":"Point"}
}