{
  "type": "Feature",
  "properties": {
    "gn:adm1_name":"Ibarakiken",
    "gn:adm2_name":"Shimotsumashi",
    "gn:name":"Kazusu",
    "iso:country":"JP",
    "wof:name":"304-0016",
    "wof:placetype":"postalcode"
},
  "geometry": {"coordinates":[139.98929999999999,36.2156],"type":"Point"}
}