{
  "type": "Feature",
  "properties": {
    "gn:adm1_name":"Aichiken",
    "gn:adm2_name":"Nagoyashinakagawaku",
    "gn:name":"Houzouchou",
    "iso:country":"JP",
    "wof:name":"454-0859",
    "wof:placetype":"postalcode"
},
  "geometry": {"coordinates":[136.86609999999999,35.1239],"type":"Point"}
}