{
  "type": "Feature",
  "properties": {
    "gn:adm1_name":"Miyazakiken",
    "gn:adm2_name":"Higashimorokataguntakaokachou",
    "gn:name":"Iida",
    "iso:country":"JP",
    "wof:name":"880-2224",
    "wof:placetype":"postalcode"
},
  "geometry": {"coordinates":[131.2953,31.9658],"type":"Point"}
}