{
  "type": "Feature",
  "properties": {
    "gn:adm1_name":"Hiroshimaken",
    "gn:adm2_name":"Hibaguntoujouchou",
    "gn:name":"Ogushi",
    "iso:country":"JP",
    "wof:name":"729-5504",
    "wof:placetype":"postalcode"
},
  "geometry": {"coordinates":[133.30520000000001,34.992],"type":"Point"}
}