{
  "type": "Feature",
  "properties": {
    "gn:adm1_name":"Shimaneken",
    "gn:adm2_name":"Izumoshi",
    "gn:name":"Otsutachichou",
    "iso:country":"JP",
    "wof:name":"693-0216",
    "wof:placetype":"postalcode"
},
  "geometry": {"coordinates":[132.7252,35.2821],"type":"Point"}
}