{
  "type": "Feature",
  "properties": {
    "gn:adm1_name":"Ehimeken",
    "gn:adm2_name":"Imabarishi",
    "gn:name":"Kitahouraichou",
    "iso:country":"JP",
    "wof:name":"794-0028",
    "wof:placetype":"postalcode"
},
  "geometry": {"coordinates":[132.99379999999999,34.0656],"type":"Point"}
}