{
  "type": "Feature",
  "properties": {
    "gn:adm1_name":"Chibaken",
    "gn:adm2_name":"Tateyamashi",
    "gn:name":"Houjoumasaki",
    "iso:country":"JP",
    "wof:name":"294-0053",
    "wof:placetype":"postalcode"
},
  "geometry": {"coordinates":[139.87559999999999,35.0106],"type":"Point"}
}