{
  "type": "Feature",
  "properties": {
    "gn:adm1_name":"Miyazakiken",
    "gn:adm2_name":"Nobeokashi",
    "gn:name":"Shinmachi",
    "iso:country":"JP",
    "wof:name":"882-0827",
    "wof:placetype":"postalcode"
},
  "geometry": {"coordinates":[131.67019999999999,32.581],"type":"Point"}
}