{
  "type": "Feature",
  "properties": {
    "gn:adm1_name":"Kagawaken",
    "gn:adm2_name":"Sanukishi",
    "gn:name":"Shouwa",
    "iso:country":"JP",
    "wof:name":"769-2304",
    "wof:placetype":"postalcode"
},
  "geometry": {"coordinates":[134.16560000000001,34.2682],"type":"Point"}
}