{
  "type": "Feature",
  "properties": {
    "gn:adm1_name":"Aichiken",
    "gn:adm2_name":"Ichinomiyashi",
    "gn:name":"Jousuiji",
    "iso:country":"JP",
    "wof:name":"491-0004",
    "wof:placetype":"postalcode"
},
  "geometry": {"coordinates":[136.84039999999999,35.3129],"type":"Point"}
}