{
  "type": "Feature",
  "properties": {
    "gn:adm1_name":"Aichiken",
    "gn:adm2_name":"Toyotashi",
    "gn:name":"Shiomichou",
    "iso:country":"JP",
    "wof:name":"471-0041",
    "wof:placetype":"postalcode"
},
  "geometry": {"coordinates":[137.12200000000001,35.0961],"type":"Point"}
}