{
  "type": "Feature",
  "properties": {
    "gn:adm1_name":"Gifuken",
    "gn:adm2_name":"Gifushi",
    "gn:name":"Masuyachou",
    "iso:country":"JP",
    "wof:name":"500-8019",
    "wof:placetype":"postalcode"
},
  "geometry": {"coordinates":[136.77080000000001,35.433],"type":"Point"}
}