{
  "type": "Feature",
  "properties": {
    "gn:adm1_name":"Mieken",
    "gn:adm2_name":"Nabarishi",
    "gn:name":"Shinden",
    "iso:country":"JP",
    "wof:name":"518-0611",
    "wof:placetype":"postalcode"
},
  "geometry": {"coordinates":[136.13210000000001,34.6648],"type":"Point"}
}