{
  "type": "Feature",
  "properties": {
    "gn:adm1_name":"Okayamaken",
    "gn:adm2_name":"Kurashikishi",
    "gn:name":"Bakurochou",
    "iso:country":"JP",
    "wof:name":"710-0824",
    "wof:placetype":"postalcode"
},
  "geometry": {"coordinates":[133.7664,34.5888],"type":"Point"}
}