{
  "type": "Feature",
  "properties": {
    "gn:adm1_name":"Shigaken",
    "gn:adm2_name":"Kusatsushi",
    "gn:name":"Nojihigashi",
    "iso:country":"JP",
    "wof:name":"525-0058",
    "wof:placetype":"postalcode"
},
  "geometry": {"coordinates":[135.95840000000001,34.9868],"type":"Point"}
}