{
  "type": "Feature",
  "properties": {
    "gn:adm1_name":"Niigataken",
    "gn:adm2_name":"Nishikanbaragun'Iwamuromura",
    "gn:name":"Takahashi",
    "iso:country":"JP",
    "wof:name":"953-0121",
    "wof:placetype":"postalcode"
},
  "geometry": {"coordinates":[138.8897,37.7292],"type":"Point"}
}