{
  "type": "Feature",
  "properties": {
    "gn:adm1_name":"Gifuken",
    "gn:adm2_name":"Takayamashi",
    "gn:name":"Ishiuramachi",
    "iso:country":"JP",
    "wof:name":"506-0825",
    "wof:placetype":"postalcode"
},
  "geometry": {"coordinates":[137.26249999999999,36.1167],"type":"Point"}
}