{
  "type": "Feature",
  "properties": {
    "gn:adm1_name":"Tottoriken",
    "gn:adm2_name":"Iwamigunkokufuchou",
    "gn:name":"Waji",
    "iso:country":"JP",
    "wof:name":"680-0212",
    "wof:placetype":"postalcode"
},
  "geometry": {"coordinates":[134.3777,35.4505],"type":"Point"}
}