{
  "type": "Feature",
  "properties": {
    "gn:adm1_name":"Tottoriken",
    "gn:adm2_name":"Hinogunnichinanchou",
    "gn:name":"Kadonokami",
    "iso:country":"JP",
    "wof:name":"689-5662",
    "wof:placetype":"postalcode"
},
  "geometry": {"coordinates":[133.3827,35.128],"type":"Point"}
}