{
  "type": "Feature",
  "properties": {
    "gn:adm1_name":"Kagoshimaken",
    "gn:adm2_name":"Kagoshimashi",
    "gn:name":"Arimurachou",
    "iso:country":"JP",
    "wof:name":"891-1545",
    "wof:placetype":"postalcode"
},
  "geometry": {"coordinates":[130.66589999999999,31.5548],"type":"Point"}
}