{
  "type": "Feature",
  "properties": {
    "gn:adm1_name":"Kyoutofu",
    "gn:adm2_name":"Kyoutoshiminamiku",
    "gn:name":"Kisshouin'Inabachou",
    "iso:country":"JP",
    "wof:name":"601-8343",
    "wof:placetype":"postalcode"
},
  "geometry": {"coordinates":[135.7389,34.9685],"type":"Point"}
}