{
  "type": "Feature",
  "properties": {
    "gn:adm1_name":"Yamanashiken",
    "gn:adm2_name":"Nakakomagunshouwachou",
    "gn:name":"Shimizuarai",
    "iso:country":"JP",
    "wof:name":"409-3867",
    "wof:placetype":"postalcode"
},
  "geometry": {"coordinates":[138.5471,35.6465],"type":"Point"}
}