{
  "type": "Feature",
  "properties": {
    "gn:adm1_name":"Tottoriken",
    "gn:adm2_name":"Tottorishi",
    "gn:name":"Ebisumachi",
    "iso:country":"JP",
    "wof:name":"680-0055",
    "wof:placetype":"postalcode"
},
  "geometry": {"coordinates":[134.23179999999999,35.4985],"type":"Point"}
}