{
  "type": "Feature",
  "properties": {
    "gn:adm1_name":"Kyoutofu",
    "gn:adm2_name":"Kyoutoshikitaku",
    "gn:name":"Nishigamokitaimaharachou",
    "iso:country":"JP",
    "wof:name":"603-8841",
    "wof:placetype":"postalcode"
},
  "geometry": {"coordinates":[135.7398,35.0657],"type":"Point"}
}