{
  "type": "Feature",
  "properties": {
    "gn:adm1_name":"Aichiken",
    "gn:adm2_name":"Inazawashi",
    "gn:name":"Inokuchiootsubochou",
    "iso:country":"JP",
    "wof:name":"492-8164",
    "wof:placetype":"postalcode"
},
  "geometry": {"coordinates":[136.81729999999999,35.2374],"type":"Point"}
}