{
  "type": "Feature",
  "properties": {
    "gn:adm1_name":"Mieken",
    "gn:adm2_name":"Tobashi",
    "gn:name":"Funatsuchou",
    "iso:country":"JP",
    "wof:name":"517-0045",
    "wof:placetype":"postalcode"
},
  "geometry": {"coordinates":[136.8416,34.4604],"type":"Point"}
}