{
  "type": "Feature",
  "properties": {
    "gn:adm1_name":"Niigataken",
    "gn:adm2_name":"Nakakubikigunsanwamura",
    "gn:name":"Kanda",
    "iso:country":"JP",
    "wof:name":"942-0265",
    "wof:placetype":"postalcode"
},
  "geometry": {"coordinates":[138.35900000000001,37.1463],"type":"Point"}
}