{
  "type": "Feature",
  "properties": {
    "gn:adm1_name":"Tokushimaken",
    "gn:adm2_name":"Tokushimashi",
    "gn:name":"Nakayoshinochou",
    "iso:country":"JP",
    "wof:name":"770-0804",
    "wof:placetype":"postalcode"
},
  "geometry": {"coordinates":[134.5548,34.0851],"type":"Point"}
}