{
  "type": "Feature",
  "properties": {
    "gn:adm1_name":"Ibarakiken",
    "gn:adm2_name":"Sashimagunsanwamachi",
    "gn:name":"Higashiyamata",
    "iso:country":"JP",
    "wof:name":"306-0112",
    "wof:placetype":"postalcode"
},
  "geometry": {"coordinates":[139.82159999999999,36.1608],"type":"Point"}
}