{
  "type": "Feature",
  "properties": {
    "gn:adm1_name":"Chibaken",
    "gn:adm2_name":"Futtsushi",
    "gn:name":"Isshiki",
    "iso:country":"JP",
    "wof:name":"293-0033",
    "wof:placetype":"postalcode"
},
  "geometry": {"coordinates":[139.89930000000001,35.2944],"type":"Point"}
}