{
  "type": "Feature",
  "properties": {
    "gn:adm1_name":"Shizuokaken",
    "gn:adm2_name":"Fukuroishi",
    "gn:name":"Kasuinomori",
    "iso:country":"JP",
    "wof:name":"437-0127",
    "wof:placetype":"postalcode"
},
  "geometry": {"coordinates":[137.9162,34.7764],"type":"Point"}
}