{
  "type": "Feature",
  "properties": {
    "gn:adm1_name":"Tochigiken",
    "gn:adm2_name":"Kuroisoshi",
    "gn:name":"Kitayaroku",
    "iso:country":"JP",
    "wof:name":"329-3132",
    "wof:placetype":"postalcode"
},
  "geometry": {"coordinates":[140.01329999999999,36.947],"type":"Point"}
}