{
  "type": "Feature",
  "properties": {
    "gn:adm1_name":"Tochigiken",
    "gn:adm2_name":"Ashikagashi",
    "gn:name":"Sukedoshinyamachou",
    "iso:country":"JP",
    "wof:name":"326-0041",
    "wof:placetype":"postalcode"
},
  "geometry": {"coordinates":[139.47200000000001,36.3442],"type":"Point"}
}