{
  "type": "Feature",
  "properties": {
    "gn:adm1_name":"Hyougoken",
    "gn:adm2_name":"Takagunkamichou",
    "gn:name":"Terauchi",
    "iso:country":"JP",
    "wof:name":"679-1211",
    "wof:placetype":"postalcode"
},
  "geometry": {"coordinates":[134.86529999999999,35.0822],"type":"Point"}
}