{
  "type": "Feature",
  "properties": {
    "gn:adm1_name":"Chibaken",
    "gn:adm2_name":"Sakurashi",
    "gn:name":"Tsuboyamashinden",
    "iso:country":"JP",
    "wof:name":"285-0056",
    "wof:placetype":"postalcode"
},
  "geometry": {"coordinates":[140.27690000000001,35.6831],"type":"Point"}
}