{
  "type": "Feature",
  "properties": {
    "gn:adm1_name":"Saitamaken",
    "gn:adm2_name":"Chichibushi",
    "gn:name":"Kanamuromachi",
    "iso:country":"JP",
    "wof:name":"368-0014",
    "wof:placetype":"postalcode"
},
  "geometry": {"coordinates":[139.0806,36.0079],"type":"Point"}
}