{
  "type": "Feature",
  "properties": {
    "gn:adm1_name":"Naraken",
    "gn:adm2_name":"Kitakatsuragiguntaimachou",
    "gn:name":"Nagao",
    "iso:country":"JP",
    "wof:name":"639-2164",
    "wof:placetype":"postalcode"
},
  "geometry": {"coordinates":[135.7099,34.5098],"type":"Point"}
}