{
  "type": "Feature",
  "properties": {
    "gn:adm1_name":"Wakayamaken",
    "gn:adm2_name":"Hidakagunnakatsumura",
    "gn:name":"Takatsuogawa",
    "iso:country":"JP",
    "wof:name":"644-1123",
    "wof:placetype":"postalcode"
},
  "geometry": {"coordinates":[135.29730000000001,33.9931],"type":"Point"}
}