{
  "type": "Feature",
  "properties": {
    "gn:adm1_name":"Niigataken",
    "gn:adm2_name":"Tochioshi",
    "gn:name":"Hara",
    "iso:country":"JP",
    "wof:name":"940-0132",
    "wof:placetype":"postalcode"
},
  "geometry": {"coordinates":[139.001,37.4818],"type":"Point"}
}