{
  "type": "Feature",
  "properties": {
    "gn:adm1_name":"Tokushimaken",
    "gn:adm2_name":"Mimagun'Anabukichou",
    "gn:name":"Kuchiyama",
    "iso:country":"JP",
    "wof:name":"777-0006",
    "wof:placetype":"postalcode"
},
  "geometry": {"coordinates":[134.1465,34.0206],"type":"Point"}
}