{
  "type": "Feature",
  "properties": {
    "gn:adm1_name":"Naraken",
    "gn:adm2_name":"Takaichiguntakatorichou",
    "gn:name":"Terasaki",
    "iso:country":"JP",
    "wof:name":"635-0142",
    "wof:placetype":"postalcode"
},
  "geometry": {"coordinates":[135.77269999999999,34.4647],"type":"Point"}
}