{
  "type": "Feature",
  "properties": {
    "gn:adm1_name":"Oosakafu",
    "gn:adm2_name":"Higashioosakashi",
    "gn:name":"Motomachi",
    "iso:country":"JP",
    "wof:name":"579-8005",
    "wof:placetype":"postalcode"
},
  "geometry": {"coordinates":[135.6354,34.6964],"type":"Point"}
}