{
  "type": "Feature",
  "properties": {
    "gn:adm1_name":"Yamanashiken",
    "gn:adm2_name":"Ootsukishi",
    "gn:name":"Tomihamamachimiyatani",
    "iso:country":"JP",
    "wof:name":"409-0501",
    "wof:placetype":"postalcode"
},
  "geometry": {"coordinates":[138.98779999999999,35.622],"type":"Point"}
}