{
  "type": "Feature",
  "properties": {
    "gn:adm1_name":"Saitamaken",
    "gn:adm2_name":"Honjoushi",
    "gn:name":"Hotta",
    "iso:country":"JP",
    "wof:name":"367-0014",
    "wof:placetype":"postalcode"
},
  "geometry": {"coordinates":[139.23410000000001,36.229],"type":"Point"}
}