{
  "type": "Feature",
  "properties": {
    "gn:adm1_name":"Ibarakiken",
    "gn:adm2_name":"Kujigundaigomachi",
    "gn:name":"Korofuji",
    "iso:country":"JP",
    "wof:name":"319-3361",
    "wof:placetype":"postalcode"
},
  "geometry": {"coordinates":[140.38319999999999,36.7199],"type":"Point"}
}