{
  "type": "Feature",
  "properties": {
    "gn:adm1_name":"Fukuokaken",
    "gn:adm2_name":"Iidukashi",
    "gn:name":"Komodahigashi",
    "iso:country":"JP",
    "wof:name":"820-0016",
    "wof:placetype":"postalcode"
},
  "geometry": {"coordinates":[130.6917,33.6302],"type":"Point"}
}