{
  "type": "Feature",
  "properties": {
    "gn:adm1_name":"Mieken",
    "gn:adm2_name":"Takiguntakichou",
    "gn:name":"Kouda",
    "iso:country":"JP",
    "wof:name":"519-2153",
    "wof:placetype":"postalcode"
},
  "geometry": {"coordinates":[136.5821,34.519],"type":"Point"}
}