{
  "type": "Feature",
  "properties": {
    "gn:adm1_name":"Sagaken",
    "gn:adm2_name":"Ogigun'Ashikarichou",
    "gn:name":"Ashimizo",
    "iso:country":"JP",
    "wof:name":"849-0311",
    "wof:placetype":"postalcode"
},
  "geometry": {"coordinates":[130.2133,33.2397],"type":"Point"}
}