{
  "type": "Feature",
  "properties": {
    "gn:adm1_name":"Ehimeken",
    "gn:adm2_name":"Ochigunkikumachou",
    "gn:name":"Nakanokawa",
    "iso:country":"JP",
    "wof:name":"799-2308",
    "wof:placetype":"postalcode"
},
  "geometry": {"coordinates":[132.8536,34.007],"type":"Point"}
}