{
  "type": "Feature",
  "properties": {
    "gn:adm1_name":"Kyoutofu",
    "gn:adm2_name":"Ayabeshi",
    "gn:name":"Shimobarachou",
    "iso:country":"JP",
    "wof:name":"629-1273",
    "wof:placetype":"postalcode"
},
  "geometry": {"coordinates":[135.30439999999999,35.2885],"type":"Point"}
}