{
  "type": "Feature",
  "properties": {
    "gn:adm1_name":"Gifuken",
    "gn:adm2_name":"Mizuhoshi",
    "gn:name":"Mori",
    "iso:country":"JP",
    "wof:name":"501-0303",
    "wof:placetype":"postalcode"
},
  "geometry": {"coordinates":[136.65119999999999,35.4197],"type":"Point"}
}