{
  "type": "Feature",
  "properties": {
    "gn:adm1_name":"Aichiken",
    "gn:adm2_name":"Toukaishi",
    "gn:name":"Araomachimizubuka",
    "iso:country":"JP",
    "wof:name":"476-0004",
    "wof:placetype":"postalcode"
},
  "geometry": {"coordinates":[136.91239999999999,35.025],"type":"Point"}
}