{
  "type": "Feature",
  "properties": {
    "gn:adm1_name":"Ooitaken",
    "gn:adm2_name":"Nakatsushi",
    "gn:name":"Kanaya(Uenochou,Nakanochou,Nishinochou,Nishihoribata,Higashihoribata,Furukanaya,Honmachi,Minaminochou,",
    "iso:country":"JP",
    "wof:name":"871-0046",
    "wof:placetype":"postalcode"
},
  "geometry": {"coordinates":[131.18299999999999,33.609],"type":"Point"}
}