{
  "type": "Feature",
  "properties": {
    "gn:adm1_name":"Naganoken",
    "gn:adm2_name":"Kitaadumigunyasakamura",
    "gn:name":"Shoubu",
    "iso:country":"JP",
    "wof:name":"399-7302",
    "wof:placetype":"postalcode"
},
  "geometry": {"coordinates":[137.91589999999999,36.4785],"type":"Point"}
}