{
  "type": "Feature",
  "properties": {
    "gn:adm1_name":"Fukuiken",
    "gn:adm2_name":"Nyuugun'Asahichou",
    "gn:name":"Sakaino",
    "iso:country":"JP",
    "wof:name":"916-0154",
    "wof:placetype":"postalcode"
},
  "geometry": {"coordinates":[136.0908,35.961],"type":"Point"}
}