{
  "type": "Feature",
  "properties": {
    "gn:adm1_name":"Aichiken",
    "gn:adm2_name":"Higashikamogun'Asukechou",
    "gn:name":"Iwaya",
    "iso:country":"JP",
    "wof:name":"444-2331",
    "wof:placetype":"postalcode"
},
  "geometry": {"coordinates":[137.30109999999999,35.0806],"type":"Point"}
}