{
  "type": "Feature",
  "properties": {
    "gn:adm1_name":"Yamagataken",
    "gn:adm2_name":"Yonezawashi",
    "gn:name":"Itaya",
    "iso:country":"JP",
    "wof:name":"992-1331",
    "wof:placetype":"postalcode"
},
  "geometry": {"coordinates":[140.27430000000001,37.8142],"type":"Point"}
}