{
  "type": "Feature",
  "properties": {
    "gn:adm1_name":"Kumamotoken",
    "gn:adm2_name":"Kamotogunkahokumachi",
    "gn:name":"Taku",
    "iso:country":"JP",
    "wof:name":"861-0605",
    "wof:placetype":"postalcode"
},
  "geometry": {"coordinates":[130.7473,33.1069],"type":"Point"}
}