{
  "type": "Feature",
  "properties": {
    "gn:adm1_name":"Aichiken",
    "gn:adm2_name":"Nagoyashikitaku",
    "gn:name":"Chuumaruchou",
    "iso:country":"JP",
    "wof:name":"462-0056",
    "wof:placetype":"postalcode"
},
  "geometry": {"coordinates":[136.90299999999999,35.2055],"type":"Point"}
}