{
  "type": "Feature",
  "properties": {
    "gn:adm1_name":"Saitamaken",
    "gn:adm2_name":"Koshigayashi",
    "gn:name":"Noboritochou",
    "iso:country":"JP",
    "wof:name":"343-0846",
    "wof:placetype":"postalcode"
},
  "geometry": {"coordinates":[139.79839999999999,35.8731],"type":"Point"}
}