{
  "type": "Feature",
  "properties": {
    "gn:adm1_name":"Kyoutofu",
    "gn:adm2_name":"Kyoutoshinakagyouku",
    "gn:name":"Echigochou",
    "iso:country":"JP",
    "wof:name":"604-8256",
    "wof:placetype":"postalcode"
},
  "geometry": {"coordinates":[135.75280000000001,35.0074],"type":"Point"}
}