{
  "type": "Feature",
  "properties": {
    "gn:adm1_name":"Saitamaken",
    "gn:adm2_name":"Yashioshi",
    "gn:name":"Ukiduka",
    "iso:country":"JP",
    "wof:name":"340-0835",
    "wof:placetype":"postalcode"
},
  "geometry": {"coordinates":[139.828,35.7976],"type":"Point"}
}