{
  "type": "Feature",
  "properties": {
    "gn:adm1_name":"Ehimeken",
    "gn:adm2_name":"Saijoushi",
    "gn:name":"Nakanootsu",
    "iso:country":"JP",
    "wof:name":"793-0055",
    "wof:placetype":"postalcode"
},
  "geometry": {"coordinates":[133.1857,33.8868],"type":"Point"}
}