{
  "type": "Feature",
  "properties": {
    "gn:adm1_name":"Hyougoken",
    "gn:adm2_name":"Himejishi",
    "gn:name":"Hirohatakunagamachi",
    "iso:country":"JP",
    "wof:name":"671-1125",
    "wof:placetype":"postalcode"
},
  "geometry": {"coordinates":[134.63329999999999,34.7966],"type":"Point"}
}