{
  "type": "Feature",
  "properties": {
    "gn:adm1_name":"Ooitaken",
    "gn:adm2_name":"Shimogegunsankoumura",
    "gn:name":"Kamifukouzu",
    "iso:country":"JP",
    "wof:name":"879-0225",
    "wof:placetype":"postalcode"
},
  "geometry": {"coordinates":[131.25960000000001,33.4954],"type":"Point"}
}