{
  "type": "Feature",
  "properties": {
    "gn:adm1_name":"Fukushimaken",
    "gn:adm2_name":"Soumashi",
    "gn:name":"Tsukanobe",
    "iso:country":"JP",
    "wof:name":"976-0003",
    "wof:placetype":"postalcode"
},
  "geometry": {"coordinates":[140.9153,37.835],"type":"Point"}
}