{
  "type": "Feature",
  "properties": {
    "gn:adm1_name":"Gifuken",
    "gn:adm2_name":"Oonogunnyuukawamura",
    "gn:name":"Hiyomo",
    "iso:country":"JP",
    "wof:name":"506-2256",
    "wof:placetype":"postalcode"
},
  "geometry": {"coordinates":[137.42140000000001,36.1778],"type":"Point"}
}