{
  "type": "Feature",
  "properties": {
    "gn:adm1_name":"Kanagawaken",
    "gn:adm2_name":"Yokohamashikounanku",
    "gn:name":"Saido",
    "iso:country":"JP",
    "wof:name":"233-0008",
    "wof:placetype":"postalcode"
},
  "geometry": {"coordinates":[139.5943,35.4134],"type":"Point"}
}