{
  "type": "Feature",
  "properties": {
    "gn:adm1_name":"Kyoutofu",
    "gn:adm2_name":"Kyoutoshiyamashinaku",
    "gn:name":"Kanshuujinishikitadechou",
    "iso:country":"JP",
    "wof:name":"607-8225",
    "wof:placetype":"postalcode"
},
  "geometry": {"coordinates":[135.80770000000001,34.9639],"type":"Point"}
}