{
  "type": "Feature",
  "properties": {
    "gn:adm1_name":"Niigataken",
    "gn:adm2_name":"Shibatashi",
    "gn:name":"Nakanomeshinden",
    "iso:country":"JP",
    "wof:name":"959-2329",
    "wof:placetype":"postalcode"
},
  "geometry": {"coordinates":[139.2799,37.9176],"type":"Point"}
}