{
  "type": "Feature",
  "properties": {
    "gn:adm1_name":"Kouchiken",
    "gn:adm2_name":"Nakamurashi",
    "gn:name":"Kamikoshoumachi",
    "iso:country":"JP",
    "wof:name":"787-0030",
    "wof:placetype":"postalcode"
},
  "geometry": {"coordinates":[132.93129999999999,32.9946],"type":"Point"}
}