{
  "type": "Feature",
  "properties": {
    "gn:adm1_name":"Ishikawaken",
    "gn:adm2_name":"Fugeshigunmonzenmachi",
    "gn:name":"Futamata",
    "iso:country":"JP",
    "wof:name":"927-2301",
    "wof:placetype":"postalcode"
},
  "geometry": {"coordinates":[136.76410000000001,37.2415],"type":"Point"}
}