{
  "type": "Feature",
  "properties": {
    "gn:adm1_name":"Kagoshimaken",
    "gn:adm2_name":"Ooshimagunkikaichou",
    "gn:name":"Yamada",
    "iso:country":"JP",
    "wof:name":"891-6225",
    "wof:placetype":"postalcode"
},
  "geometry": {"coordinates":[129.95949999999999,28.3094],"type":"Point"}
}