{
  "type": "Feature",
  "properties": {
    "gn:adm1_name":"Tokushimaken",
    "gn:adm2_name":"Oegunkamojimachou",
    "gn:name":"Kamojimakou",
    "iso:country":"JP",
    "wof:name":"776-0011",
    "wof:placetype":"postalcode"
},
  "geometry": {"coordinates":[134.3535,34.0755],"type":"Point"}
}