{
  "type": "Feature",
  "properties": {
    "gn:adm1_name":"Ibarakiken",
    "gn:adm2_name":"Tsuchiurashi",
    "gn:name":"Higashimanabemachi",
    "iso:country":"JP",
    "wof:name":"300-0052",
    "wof:placetype":"postalcode"
},
  "geometry": {"coordinates":[140.20650000000001,36.0936],"type":"Point"}
}