{
  "type": "Feature",
  "properties": {
    "gn:adm1_name":"Hyougoken",
    "gn:adm2_name":"Takaradukashi",
    "gn:name":"Fujigaoka",
    "iso:country":"JP",
    "wof:name":"665-0806",
    "wof:placetype":"postalcode"
},
  "geometry": {"coordinates":[135.38910000000001,34.8369],"type":"Point"}
}