{
  "type": "Feature",
  "properties": {
    "gn:adm1_name":"Niigataken",
    "gn:adm2_name":"Kashiwazakishi",
    "gn:name":"Sanwachou(8,9ban)",
    "iso:country":"JP",
    "wof:name":"945-1342",
    "wof:placetype":"postalcode"
},
  "geometry": {"coordinates":[138.58099999999999,37.3642],"type":"Point"}
}