{
  "type": "Feature",
  "properties": {
    "gn:adm1_name":"Tottoriken",
    "gn:adm2_name":"Yonagoshi",
    "gn:name":"Kawasaki",
    "iso:country":"JP",
    "wof:name":"683-0852",
    "wof:placetype":"postalcode"
},
  "geometry": {"coordinates":[133.3066,35.4574],"type":"Point"}
}