{
  "type": "Feature",
  "properties": {
    "gn:adm1_name":"Niigataken",
    "gn:adm2_name":"Minamikanbaragunnakanoshimamachi",
    "gn:name":"Nishitakayamashinden",
    "iso:country":"JP",
    "wof:name":"954-0205",
    "wof:placetype":"postalcode"
},
  "geometry": {"coordinates":[138.8716,37.5734],"type":"Point"}
}