{
  "type": "Feature",
  "properties": {
    "gn:adm1_name":"Shizuokaken",
    "gn:adm2_name":"Hamamatsushi",
    "gn:name":"Kanzanjichou",
    "iso:country":"JP",
    "wof:name":"431-1209",
    "wof:placetype":"postalcode"
},
  "geometry": {"coordinates":[137.6157,34.7615],"type":"Point"}
}