{
  "type": "Feature",
  "properties": {
    "gn:adm1_name":"Miyagiken",
    "gn:adm2_name":"Kesennumashi",
    "gn:name":"Matsuzakishimokanetori",
    "iso:country":"JP",
    "wof:name":"988-0156",
    "wof:placetype":"postalcode"
},
  "geometry": {"coordinates":[141.53550000000001,38.8597],"type":"Point"}
}