{
  "type": "Feature",
  "properties": {
    "gn:adm1_name":"Kouchiken",
    "gn:adm2_name":"Nagaokagunmotoyamachou",
    "gn:name":"Kinoudu",
    "iso:country":"JP",
    "wof:name":"781-3608",
    "wof:placetype":"postalcode"
},
  "geometry": {"coordinates":[133.62020000000001,33.7557],"type":"Point"}
}