{
  "type": "Feature",
  "properties": {
    "gn:adm1_name":"Nagasakiken",
    "gn:adm2_name":"Matsuurashi",
    "gn:name":"Mikuriyachounishikobamen",
    "iso:country":"JP",
    "wof:name":"859-4769",
    "wof:placetype":"postalcode"
},
  "geometry": {"coordinates":[129.64019999999999,33.3592],"type":"Point"}
}