{
  "type": "Feature",
  "properties": {
    "gn:adm1_name":"Fukushimaken",
    "gn:adm2_name":"Iwakishi",
    "gn:name":"Tairanakashio",
    "iso:country":"JP",
    "wof:name":"970-8016",
    "wof:placetype":"postalcode"
},
  "geometry": {"coordinates":[140.89609999999999,37.0716],"type":"Point"}
}