{
  "type": "Feature",
  "properties": {
    "gn:adm1_name":"Hiroshimaken",
    "gn:adm2_name":"Hibagunkuchiwachou",
    "gn:name":"Kinde",
    "iso:country":"JP",
    "wof:name":"727-0112",
    "wof:placetype":"postalcode"
},
  "geometry": {"coordinates":[132.9049,34.8626],"type":"Point"}
}