{
  "type": "Feature",
  "properties": {
    "gn:adm1_name":"Toyamaken",
    "gn:adm2_name":"Oyabeshi",
    "gn:name":"Higashifukumachi",
    "iso:country":"JP",
    "wof:name":"932-0041",
    "wof:placetype":"postalcode"
},
  "geometry": {"coordinates":[136.88409999999999,36.6795],"type":"Point"}
}