{
  "type": "Feature",
  "properties": {
    "gn:adm1_name":"Saitamaken",
    "gn:adm2_name":"Yoshikawashi",
    "gn:name":"Nakano",
    "iso:country":"JP",
    "wof:name":"342-0042",
    "wof:placetype":"postalcode"
},
  "geometry": {"coordinates":[139.85810000000001,35.8828],"type":"Point"}
}