{
  "type": "Feature",
  "properties": {
    "gn:adm1_name":"Miyazakiken",
    "gn:adm2_name":"Miyazakishi",
    "gn:name":"Miyatachou",
    "iso:country":"JP",
    "wof:name":"880-0804",
    "wof:placetype":"postalcode"
},
  "geometry": {"coordinates":[131.42599999999999,31.9115],"type":"Point"}
}