{
  "type": "Feature",
  "properties": {
    "gn:adm1_name":"Gunmaken",
    "gn:adm2_name":"Setagunfujimimura",
    "gn:name":"Tokizawa",
    "iso:country":"JP",
    "wof:name":"371-0104",
    "wof:placetype":"postalcode"
},
  "geometry": {"coordinates":[139.08690000000001,36.436],"type":"Point"}
}