{
  "type": "Feature",
  "properties": {
    "gn:adm1_name":"Chibaken",
    "gn:adm2_name":"Kisaradushi",
    "gn:name":"Hatazawa",
    "iso:country":"JP",
    "wof:name":"292-0825",
    "wof:placetype":"postalcode"
},
  "geometry": {"coordinates":[139.9076,35.3466],"type":"Point"}
}