{
  "type": "Feature",
  "properties": {
    "gn:adm1_name":"Shizuokaken",
    "gn:adm2_name":"Shizuokashi",
    "gn:name":"Shimizumachi",
    "iso:country":"JP",
    "wof:name":"424-0947",
    "wof:placetype":"postalcode"
},
  "geometry": {"coordinates":[138.4898,35.0065],"type":"Point"}
}