{
  "type": "Feature",
  "properties": {
    "gn:adm1_name":"Niigataken",
    "gn:adm2_name":"Shironeshi",
    "gn:name":"Negishi",
    "iso:country":"JP",
    "wof:name":"950-1234",
    "wof:placetype":"postalcode"
},
  "geometry": {"coordinates":[139.01769999999999,37.792],"type":"Point"}
}