{
  "type": "Feature",
  "properties": {
    "gn:adm1_name":"Saitamaken",
    "gn:adm2_name":"Fukayashi",
    "gn:name":"Orinokuchi",
    "iso:country":"JP",
    "wof:name":"366-0812",
    "wof:placetype":"postalcode"
},
  "geometry": {"coordinates":[139.2842,36.1621],"type":"Point"}
}