{
  "type": "Feature",
  "properties": {
    "gn:adm1_name":"Fukuokaken",
    "gn:adm2_name":"Dazaifushi",
    "gn:name":"Uchiyama",
    "iso:country":"JP",
    "wof:name":"818-0115",
    "wof:placetype":"postalcode"
},
  "geometry": {"coordinates":[130.54939999999999,33.5282],"type":"Point"}
}