{
  "type": "Feature",
  "properties": {
    "gn:adm1_name":"Hyougoken",
    "gn:adm2_name":"Koubeshisumaku",
    "gn:name":"Tainohata",
    "iso:country":"JP",
    "wof:name":"654-0133",
    "wof:placetype":"postalcode"
},
  "geometry": {"coordinates":[135.09639999999999,34.6618],"type":"Point"}
}