{
  "type": "Feature",
  "properties": {
    "gn:adm1_name":"Wakayamaken",
    "gn:adm2_name":"Nishimurogunnakahechichou",
    "gn:name":"Fukusada",
    "iso:country":"JP",
    "wof:name":"646-1432",
    "wof:placetype":"postalcode"
},
  "geometry": {"coordinates":[135.56270000000001,33.8203],"type":"Point"}
}