{
  "type": "Feature",
  "properties": {
    "gn:adm1_name":"Shizuokaken",
    "gn:adm2_name":"Fukuroishi",
    "gn:name":"Oyama",
    "iso:country":"JP",
    "wof:name":"437-0056",
    "wof:placetype":"postalcode"
},
  "geometry": {"coordinates":[137.8938,34.7532],"type":"Point"}
}