{
  "type": "Feature",
  "properties": {
    "gn:adm1_name":"Naraken",
    "gn:adm2_name":"Sakuraishi",
    "gn:name":"Tobi",
    "iso:country":"JP",
    "wof:name":"633-0007",
    "wof:placetype":"postalcode"
},
  "geometry": {"coordinates":[135.85820000000001,34.5136],"type":"Point"}
}