{
  "type": "Feature",
  "properties": {
    "gn:adm1_name":"Ibarakiken",
    "gn:adm2_name":"Mitoshi",
    "gn:name":"Ishikawa",
    "iso:country":"JP",
    "wof:name":"310-0905",
    "wof:placetype":"postalcode"
},
  "geometry": {"coordinates":[140.42670000000001,36.3889],"type":"Point"}
}