{
  "type": "Feature",
  "properties": {
    "gn:adm1_name":"Kagoshimaken",
    "gn:adm2_name":"Ooshimagunsetouchichou",
    "gn:name":"Kiji",
    "iso:country":"JP",
    "wof:name":"894-2417",
    "wof:placetype":"postalcode"
},
  "geometry": {"coordinates":[129.22149999999999,28.1577],"type":"Point"}
}