{
  "type": "Feature",
  "properties": {
    "gn:adm1_name":"Fukuokaken",
    "gn:adm2_name":"Fukuokashihigashiku",
    "gn:name":"Katsuma",
    "iso:country":"JP",
    "wof:name":"811-0325",
    "wof:placetype":"postalcode"
},
  "geometry": {"coordinates":[130.29750000000001,33.6833],"type":"Point"}
}