{
  "type": "Feature",
  "properties": {
    "gn:adm1_name":"Aichiken",
    "gn:adm2_name":"Anjoushi",
    "gn:name":"Daitouchou",
    "iso:country":"JP",
    "wof:name":"446-0065",
    "wof:placetype":"postalcode"
},
  "geometry": {"coordinates":[137.08369999999999,34.9652],"type":"Point"}
}