{
  "type": "Feature",
  "properties": {
    "gn:adm1_name":"Niigataken",
    "gn:adm2_name":"Tookamachishi",
    "gn:name":"Minamiabuzaka",
    "iso:country":"JP",
    "wof:name":"948-0106",
    "wof:placetype":"postalcode"
},
  "geometry": {"coordinates":[138.72059999999999,37.1265],"type":"Point"}
}