{
  "type": "Feature",
  "properties": {
    "gn:adm1_name":"Kyoutofu",
    "gn:adm2_name":"Kyoutoshikitaku",
    "gn:name":"Oomiyaminamihakonoichou",
    "iso:country":"JP",
    "wof:name":"603-8476",
    "wof:placetype":"postalcode"
},
  "geometry": {"coordinates":[135.74039999999999,35.0529],"type":"Point"}
}