{
  "type": "Feature",
  "properties": {
    "gn:adm1_name":"Shimaneken",
    "gn:adm2_name":"Iishigun'Akagichou",
    "gn:name":"Shimoakana",
    "iso:country":"JP",
    "wof:name":"690-3513",
    "wof:placetype":"postalcode"
},
  "geometry": {"coordinates":[132.71619999999999,35.0076],"type":"Point"}
}