{
  "type": "Feature",
  "properties": {
    "gn:adm1_name":"Ibarakiken",
    "gn:adm2_name":"Mitoshi",
    "gn:name":"Shimadachou",
    "iso:country":"JP",
    "wof:name":"311-1121",
    "wof:placetype":"postalcode"
},
  "geometry": {"coordinates":[140.55340000000001,36.3195],"type":"Point"}
}