{
  "type": "Feature",
  "properties": {
    "gn:adm1_name":"Mieken",
    "gn:adm2_name":"Ayamagun'Ooyamadamura",
    "gn:name":"Hirata",
    "iso:country":"JP",
    "wof:name":"518-1422",
    "wof:placetype":"postalcode"
},
  "geometry": {"coordinates":[136.21449999999999,34.7651],"type":"Point"}
}