{
  "type": "Feature",
  "properties": {
    "gn:adm1_name":"Hyougoken",
    "gn:adm2_name":"Nishinomiyashi",
    "gn:name":"Ichigayachou",
    "iso:country":"JP",
    "wof:name":"662-0873",
    "wof:placetype":"postalcode"
},
  "geometry": {"coordinates":[135.34059999999999,34.7573],"type":"Point"}
}