{
  "type": "Feature",
  "properties": {
    "gn:adm1_name":"Ehimeken",
    "gn:adm2_name":"Matsuyamashi",
    "gn:name":"Misakemachi",
    "iso:country":"JP",
    "wof:name":"790-0814",
    "wof:placetype":"postalcode"
},
  "geometry": {"coordinates":[132.75569999999999,33.844],"type":"Point"}
}