{
  "type": "Feature",
  "properties": {
    "gn:adm1_name":"Hyougoken",
    "gn:adm2_name":"Yabugunyabuchou",
    "gn:name":"Takinoya",
    "iso:country":"JP",
    "wof:name":"667-0142",
    "wof:placetype":"postalcode"
},
  "geometry": {"coordinates":[134.74379999999999,35.3005],"type":"Point"}
}