{
  "type": "Feature",
  "properties": {
    "gn:adm1_name":"Yamaguchiken",
    "gn:adm2_name":"Iwakunishi",
    "gn:name":"Houki",
    "iso:country":"JP",
    "wof:name":"740-0313",
    "wof:placetype":"postalcode"
},
  "geometry": {"coordinates":[132.1087,34.166],"type":"Point"}
}