{
  "type": "Feature",
  "properties": {
    "gn:adm1_name":"Niigataken",
    "gn:adm2_name":"Kitakanbaragunsasakamimura",
    "gn:name":"Shimofukuoka",
    "iso:country":"JP",
    "wof:name":"959-1951",
    "wof:placetype":"postalcode"
},
  "geometry": {"coordinates":[139.2516,37.8504],"type":"Point"}
}