{
  "type": "Feature",
  "properties": {
    "gn:adm1_name":"Oosakafu",
    "gn:adm2_name":"Oosakashikitaku",
    "gn:name":"Tsurunochou",
    "iso:country":"JP",
    "wof:name":"530-0014",
    "wof:placetype":"postalcode"
},
  "geometry": {"coordinates":[135.50120000000001,34.708],"type":"Point"}
}