{
  "type": "Feature",
  "properties": {
    "gn:adm1_name":"Ooitaken",
    "gn:adm2_name":"Beppushi",
    "gn:name":"Shouhaenmachi",
    "iso:country":"JP",
    "wof:name":"874-0031",
    "wof:placetype":"postalcode"
},
  "geometry": {"coordinates":[131.49610000000001,33.3183],"type":"Point"}
}