{
  "type": "Feature",
  "properties": {
    "gn:adm1_name":"Okayamaken",
    "gn:adm2_name":"Shitsukigunyoshiichou",
    "gn:name":"Yoi",
    "iso:country":"JP",
    "wof:name":"714-2102",
    "wof:placetype":"postalcode"
},
  "geometry": {"coordinates":[133.4376,34.6266],"type":"Point"}
}