{
  "type": "Feature",
  "properties": {
    "gn:adm1_name":"Kouchiken",
    "gn:adm2_name":"Takaokagunhayamamura",
    "gn:name":"Oono",
    "iso:country":"JP",
    "wof:name":"785-0218",
    "wof:placetype":"postalcode"
},
  "geometry": {"coordinates":[133.1696,33.4418],"type":"Point"}
}