{
  "type": "Feature",
  "properties": {
    "gn:adm1_name":"Oosakafu",
    "gn:adm2_name":"Sakaishi",
    "gn:name":"Miyazonochou",
    "iso:country":"JP",
    "wof:name":"599-8274",
    "wof:placetype":"postalcode"
},
  "geometry": {"coordinates":[135.49170000000001,34.5269],"type":"Point"}
}