{
  "type": "Feature",
  "properties": {
    "gn:adm1_name":"Ishikawaken",
    "gn:adm2_name":"Komatsushi",
    "gn:name":"Kojimamachi",
    "iso:country":"JP",
    "wof:name":"923-0002",
    "wof:placetype":"postalcode"
},
  "geometry": {"coordinates":[136.4357,36.4214],"type":"Point"}
}