{
  "type": "Feature",
  "properties": {
    "gn:adm1_name":"Kumamotoken",
    "gn:adm2_name":"Kumamotoshi",
    "gn:name":"Togawaramachi",
    "iso:country":"JP",
    "wof:name":"861-5252",
    "wof:placetype":"postalcode"
},
  "geometry": {"coordinates":[130.66739999999999,32.7684],"type":"Point"}
}