{
  "type": "Feature",
  "properties": {
    "gn:adm1_name":"Ibarakiken",
    "gn:adm2_name":"Ryuugasakishi",
    "gn:name":"Sanumamachi",
    "iso:country":"JP",
    "wof:name":"301-0812",
    "wof:placetype":"postalcode"
},
  "geometry": {"coordinates":[140.2022,35.8887],"type":"Point"}
}