{
  "type": "Feature",
  "properties": {
    "gn:adm1_name":"Hyougoken",
    "gn:adm2_name":"Sasayamashi",
    "gn:name":"Kondachoushimotachikui",
    "iso:country":"JP",
    "wof:name":"669-2141",
    "wof:placetype":"postalcode"
},
  "geometry": {"coordinates":[135.1277,34.9742],"type":"Point"}
}