{
  "type": "Feature",
  "properties": {
    "gn:adm1_name":"Niigataken",
    "gn:adm2_name":"Minamiuonumagunyamatomachi",
    "gn:name":"Imamachishinden",
    "iso:country":"JP",
    "wof:name":"949-7254",
    "wof:placetype":"postalcode"
},
  "geometry": {"coordinates":[138.92760000000001,37.1341],"type":"Point"}
}