{
  "type": "Feature",
  "properties": {
    "gn:adm1_name":"Toukyouto",
    "gn:adm2_name":"Hachioujishi",
    "gn:name":"Motoyokoyamachou",
    "iso:country":"JP",
    "wof:name":"192-0063",
    "wof:placetype":"postalcode"
},
  "geometry": {"coordinates":[139.33699999999999,35.6635],"type":"Point"}
}