{
  "type": "Feature",
  "properties": {
    "gn:adm1_name":"Niigataken",
    "gn:adm2_name":"Kashiwazakishi",
    "gn:name":"Yata",
    "iso:country":"JP",
    "wof:name":"945-0215",
    "wof:placetype":"postalcode"
},
  "geometry": {"coordinates":[138.63319999999999,37.3855],"type":"Point"}
}