{
  "type": "Feature",
  "properties": {
    "gn:adm1_name":"Ibarakiken",
    "gn:adm2_name":"Tsukubashi",
    "gn:name":"Isobe",
    "iso:country":"JP",
    "wof:name":"300-4248",
    "wof:placetype":"postalcode"
},
  "geometry": {"coordinates":[140.05879999999999,36.1891],"type":"Point"}
}