{
  "type": "Feature",
  "properties": {
    "gn:adm1_name":"Aichiken",
    "gn:adm2_name":"Higashikamogun'Asahichou",
    "gn:name":"Ichidaira",
    "iso:country":"JP",
    "wof:name":"444-2825",
    "wof:placetype":"postalcode"
},
  "geometry": {"coordinates":[137.31960000000001,35.2081],"type":"Point"}
}