{
  "type": "Feature",
  "properties": {
    "gn:adm1_name":"Okayamaken",
    "gn:adm2_name":"Tsuyamashi",
    "gn:name":"Tanokuma",
    "iso:country":"JP",
    "wof:name":"708-1113",
    "wof:placetype":"postalcode"
},
  "geometry": {"coordinates":[134.09030000000001,35.0707],"type":"Point"}
}