{
  "type": "Feature",
  "properties": {
    "gn:adm1_name":"Ooitaken",
    "gn:adm2_name":"Beppushi",
    "gn:name":"Uchinari",
    "iso:country":"JP",
    "wof:name":"879-5551",
    "wof:placetype":"postalcode"
},
  "geometry": {"coordinates":[131.48410000000001,33.2361],"type":"Point"}
}