{
  "type": "Feature",
  "properties": {
    "gn:adm1_name":"Wakayamaken",
    "gn:adm2_name":"Higashimurogunkumanogawachou",
    "gn:name":"Miyai",
    "iso:country":"JP",
    "wof:name":"647-1235",
    "wof:placetype":"postalcode"
},
  "geometry": {"coordinates":[135.8492,33.8282],"type":"Point"}
}