{
  "type": "Feature",
  "properties": {
    "gn:adm1_name":"Naraken",
    "gn:adm2_name":"Yoshinoguntenkawamura",
    "gn:name":"Iosumi",
    "iso:country":"JP",
    "wof:name":"638-0552",
    "wof:placetype":"postalcode"
},
  "geometry": {"coordinates":[135.8013,34.1939],"type":"Point"}
}