{
  "type": "Feature",
  "properties": {
    "gn:adm1_name":"Fukushimaken",
    "gn:adm2_name":"Tamuragun'Onomachi",
    "gn:name":"Iitoyo",
    "iso:country":"JP",
    "wof:name":"963-3521",
    "wof:placetype":"postalcode"
},
  "geometry": {"coordinates":[140.61600000000001,37.3127],"type":"Point"}
}