{
  "type": "Feature",
  "properties": {
    "gn:adm1_name":"Aichiken",
    "gn:adm2_name":"Kitashitaragunshitarachou",
    "gn:name":"Toyokuni",
    "iso:country":"JP",
    "wof:name":"441-2224",
    "wof:placetype":"postalcode"
},
  "geometry": {"coordinates":[137.46690000000001,35.0748],"type":"Point"}
}