{
  "type": "Feature",
  "properties": {
    "gn:adm1_name":"Aichiken",
    "gn:adm2_name":"Shinshiroshi",
    "gn:name":"Matoba",
    "iso:country":"JP",
    "wof:name":"441-1375",
    "wof:placetype":"postalcode"
},
  "geometry": {"coordinates":[137.49629999999999,34.9026],"type":"Point"}
}