{
  "type": "Feature",
  "properties": {
    "gn:adm1_name":"Hyougoken",
    "gn:adm2_name":"Miharagunnandanchou",
    "gn:name":"Nada",
    "iso:country":"JP",
    "wof:name":"656-0551",
    "wof:placetype":"postalcode"
},
  "geometry": {"coordinates":[134.75450000000001,34.2852],"type":"Point"}
}