{
  "type": "Feature",
  "properties": {
    "gn:adm1_name":"Aichiken",
    "gn:adm2_name":"Iwakurashi",
    "gn:name":"Honmachi",
    "iso:country":"JP",
    "wof:name":"482-0043",
    "wof:placetype":"postalcode"
},
  "geometry": {"coordinates":[136.87260000000001,35.2817],"type":"Point"}
}