{
  "type": "Feature",
  "properties": {
    "gn:adm1_name":"Niigataken",
    "gn:adm2_name":"Iwafunegunsekikawamura",
    "gn:name":"Fukazawa",
    "iso:country":"JP",
    "wof:name":"959-3215",
    "wof:placetype":"postalcode"
},
  "geometry": {"coordinates":[139.54150000000001,38.1236],"type":"Point"}
}