{
  "type": "Feature",
  "properties": {
    "gn:adm1_name":"Miyazakiken",
    "gn:adm2_name":"Higashiusukigunnangouson",
    "gn:name":"Kijino",
    "iso:country":"JP",
    "wof:name":"883-0304",
    "wof:placetype":"postalcode"
},
  "geometry": {"coordinates":[131.3015,32.3909],"type":"Point"}
}