{
  "type": "Feature",
  "properties": {
    "gn:adm1_name":"Mieken",
    "gn:adm2_name":"Ichishigun'Ichishichou",
    "gn:name":"Sonokura",
    "iso:country":"JP",
    "wof:name":"515-2526",
    "wof:placetype":"postalcode"
},
  "geometry": {"coordinates":[136.41460000000001,34.667],"type":"Point"}
}