{
  "type": "Feature",
  "properties": {
    "gn:adm1_name":"Miyazakiken",
    "gn:adm2_name":"Minaminakagunnangouchou",
    "gn:name":"Nakamurakou",
    "iso:country":"JP",
    "wof:name":"889-3202",
    "wof:placetype":"postalcode"
},
  "geometry": {"coordinates":[131.3664,31.5454],"type":"Point"}
}