{
  "type": "Feature",
  "properties": {
    "gn:adm1_name":"Shizuokaken",
    "gn:adm2_name":"Shizuokashi",
    "gn:name":"Kakishima",
    "iso:country":"JP",
    "wof:name":"421-2214",
    "wof:placetype":"postalcode"
},
  "geometry": {"coordinates":[138.32810000000001,35.1508],"type":"Point"}
}