{
  "type": "Feature",
  "properties": {
    "gn:adm1_name":"Aichiken",
    "gn:adm2_name":"Nagoyashimeitouku",
    "gn:name":"Kamisato",
    "iso:country":"JP",
    "wof:name":"465-0082",
    "wof:placetype":"postalcode"
},
  "geometry": {"coordinates":[137.00290000000001,35.157],"type":"Point"}
}