{
  "type": "Feature",
  "properties": {
    "gn:adm1_name":"Ooitaken",
    "gn:adm2_name":"Taketashi",
    "gn:name":"Tsugikura",
    "iso:country":"JP",
    "wof:name":"878-0571",
    "wof:placetype":"postalcode"
},
  "geometry": {"coordinates":[131.33500000000001,32.9013],"type":"Point"}
}