{
  "type": "Feature",
  "properties": {
    "gn:adm1_name":"Hyougoken",
    "gn:adm2_name":"Koubeshichuuouku",
    "gn:name":"Asahidoori",
    "iso:country":"JP",
    "wof:name":"651-0095",
    "wof:placetype":"postalcode"
},
  "geometry": {"coordinates":[135.19900000000001,34.6972],"type":"Point"}
}