{
  "type": "Feature",
  "properties": {
    "gn:adm1_name":"Kumamotoken",
    "gn:adm2_name":"Araoshi",
    "gn:name":"Kuramitsu",
    "iso:country":"JP",
    "wof:name":"864-0027",
    "wof:placetype":"postalcode"
},
  "geometry": {"coordinates":[130.44139999999999,32.961],"type":"Point"}
}