{
  "type": "Feature",
  "properties": {
    "gn:adm1_name":"Shigaken",
    "gn:adm2_name":"Rittoushi",
    "gn:name":"Kasagawa",
    "iso:country":"JP",
    "wof:name":"520-3033",
    "wof:placetype":"postalcode"
},
  "geometry": {"coordinates":[135.97200000000001,35.0333],"type":"Point"}
}