{
  "type": "Feature",
  "properties": {
    "gn:adm1_name":"Kanagawaken",
    "gn:adm2_name":"Kawasakishimiyamaeku",
    "gn:name":"Shiboku",
    "iso:country":"JP",
    "wof:name":"216-0032",
    "wof:placetype":"postalcode"
},
  "geometry": {"coordinates":[139.5821,35.5943],"type":"Point"}
}