{
  "type": "Feature",
  "properties": {
    "gn:adm1_name":"Ooitaken",
    "gn:adm2_name":"Nakatsushi",
    "gn:name":"Oosada",
    "iso:country":"JP",
    "wof:name":"871-0153",
    "wof:placetype":"postalcode"
},
  "geometry": {"coordinates":[131.21610000000001,33.5675],"type":"Point"}
}