{
  "type": "Feature",
  "properties": {
    "gn:adm1_name":"Tochigiken",
    "gn:adm2_name":"Shioyagunshioyamachi",
    "gn:name":"Kazamiyamada",
    "iso:country":"JP",
    "wof:name":"329-2338",
    "wof:placetype":"postalcode"
},
  "geometry": {"coordinates":[139.8571,36.7413],"type":"Point"}
}