{
  "type": "Feature",
  "properties": {
    "gn:adm1_name":"Kagoshimaken",
    "gn:adm2_name":"Makurazakishi",
    "gn:name":"Shioyaminamimachi",
    "iso:country":"JP",
    "wof:name":"898-0042",
    "wof:placetype":"postalcode"
},
  "geometry": {"coordinates":[130.27940000000001,31.2617],"type":"Point"}
}