{
  "type": "Feature",
  "properties": {
    "gn:adm1_name":"Mieken",
    "gn:adm2_name":"Owaseshi",
    "gn:name":"Uenochou",
    "iso:country":"JP",
    "wof:name":"519-3653",
    "wof:placetype":"postalcode"
},
  "geometry": {"coordinates":[136.18889999999999,34.0695],"type":"Point"}
}