{
  "type": "Feature",
  "properties": {
    "gn:adm1_name":"Kagoshimaken",
    "gn:adm2_name":"Izumigunnodachou",
    "gn:name":"Shimomyou",
    "iso:country":"JP",
    "wof:name":"899-0502",
    "wof:placetype":"postalcode"
},
  "geometry": {"coordinates":[130.26259999999999,32.0688],"type":"Point"}
}