{
  "type": "Feature",
  "properties": {
    "gn:adm1_name":"Okayamaken",
    "gn:adm2_name":"Aidagunsakutouchou",
    "gn:name":"Iwanabe",
    "iso:country":"JP",
    "wof:name":"709-4222",
    "wof:placetype":"postalcode"
},
  "geometry": {"coordinates":[134.25,35.0423],"type":"Point"}
}