{
  "type": "Feature",
  "properties": {
    "gn:adm1_name":"Fukushimaken",
    "gn:adm2_name":"Kooriyamashi",
    "gn:name":"Atamimachitakatama",
    "iso:country":"JP",
    "wof:name":"963-1302",
    "wof:placetype":"postalcode"
},
  "geometry": {"coordinates":[140.27809999999999,37.4983],"type":"Point"}
}