{
  "type": "Feature",
  "properties": {
    "gn:adm1_name":"Saitamaken",
    "gn:adm2_name":"Hannoushi",
    "gn:name":"Nakamachi",
    "iso:country":"JP",
    "wof:name":"357-0038",
    "wof:placetype":"postalcode"
},
  "geometry": {"coordinates":[139.3176,35.853],"type":"Point"}
}