{
  "type": "Feature",
  "properties": {
    "gn:adm1_name":"Ehimeken",
    "gn:adm2_name":"Oozushi",
    "gn:name":"Hiranochounoda",
    "iso:country":"JP",
    "wof:name":"795-0021",
    "wof:placetype":"postalcode"
},
  "geometry": {"coordinates":[132.5119,33.4863],"type":"Point"}
}