{
  "type": "Feature",
  "properties": {
    "gn:adm1_name":"Niigataken",
    "gn:adm2_name":"Niigatashi",
    "gn:name":"Koushi",
    "iso:country":"JP",
    "wof:name":"950-0926",
    "wof:placetype":"postalcode"
},
  "geometry": {"coordinates":[139.07560000000001,37.8966],"type":"Point"}
}