{
  "type": "Feature",
  "properties": {
    "gn:adm1_name":"Kyoutofu",
    "gn:adm2_name":"Kyoutoshifushimiku",
    "gn:name":"Nabeshimachou",
    "iso:country":"JP",
    "wof:name":"612-8038",
    "wof:placetype":"postalcode"
},
  "geometry": {"coordinates":[135.76820000000001,34.9323],"type":"Point"}
}