{
  "type": "Feature",
  "properties": {
    "gn:adm1_name":"Wakayamaken",
    "gn:adm2_name":"Wakayamashi",
    "gn:name":"Kyuuemonchou",
    "iso:country":"JP",
    "wof:name":"640-8244",
    "wof:placetype":"postalcode"
},
  "geometry": {"coordinates":[135.16589999999999,34.2255],"type":"Point"}
}