{
  "type": "Feature",
  "properties": {
    "gn:adm1_name":"Niigataken",
    "gn:adm2_name":"Jouetsushi",
    "gn:name":"Chuuou",
    "iso:country":"JP",
    "wof:name":"942-0001",
    "wof:placetype":"postalcode"
},
  "geometry": {"coordinates":[138.24299999999999,37.1763],"type":"Point"}
}