{
  "type": "Feature",
  "properties": {
    "gn:adm1_name":"Kyoutofu",
    "gn:adm2_name":"Kyoutoshifushimiku",
    "gn:name":"Ishidaooyamachou",
    "iso:country":"JP",
    "wof:name":"601-1433",
    "wof:placetype":"postalcode"
},
  "geometry": {"coordinates":[135.80779999999999,34.9379],"type":"Point"}
}