{
  "type": "Feature",
  "properties": {
    "gn:adm1_name":"Tochigiken",
    "gn:adm2_name":"Kuroisoshi",
    "gn:name":"Sumiyoshichou",
    "iso:country":"JP",
    "wof:name":"325-0062",
    "wof:placetype":"postalcode"
},
  "geometry": {"coordinates":[140.0504,36.9664],"type":"Point"}
}