{
  "type": "Feature",
  "properties": {
    "gn:adm1_name":"Yamagataken",
    "gn:adm2_name":"Mogamigun'Ookuramura",
    "gn:name":"Aikai",
    "iso:country":"JP",
    "wof:name":"996-0211",
    "wof:placetype":"postalcode"
},
  "geometry": {"coordinates":[140.2319,38.711],"type":"Point"}
}