{
  "type": "Feature",
  "properties": {
    "gn:adm1_name":"Fukuokaken",
    "gn:adm2_name":"Kasuyagunsasagurimachi",
    "gn:name":"Takata",
    "iso:country":"JP",
    "wof:name":"811-2401",
    "wof:placetype":"postalcode"
},
  "geometry": {"coordinates":[130.52809999999999,33.6283],"type":"Point"}
}