{
  "type": "Feature",
  "properties": {
    "gn:adm1_name":"Shizuokaken",
    "gn:adm2_name":"Shizuokashi",
    "gn:name":"Morokozawa",
    "iso:country":"JP",
    "wof:name":"421-1402",
    "wof:placetype":"postalcode"
},
  "geometry": {"coordinates":[138.24520000000001,35.1091],"type":"Point"}
}