{
  "type": "Feature",
  "properties": {
    "gn:adm1_name":"Aichiken",
    "gn:adm2_name":"Handashi",
    "gn:name":"Kamihamachou",
    "iso:country":"JP",
    "wof:name":"475-0804",
    "wof:placetype":"postalcode"
},
  "geometry": {"coordinates":[136.93780000000001,34.899],"type":"Point"}
}