{
  "type": "Feature",
  "properties": {
    "gn:adm1_name":"Hyougoken",
    "gn:adm2_name":"Akougunkamigoorichou",
    "gn:name":"Yoishin",
    "iso:country":"JP",
    "wof:name":"678-1224",
    "wof:placetype":"postalcode"
},
  "geometry": {"coordinates":[134.3767,34.8557],"type":"Point"}
}