{
  "type": "Feature",
  "properties": {
    "gn:adm1_name":"Tochigiken",
    "gn:adm2_name":"Utsunomiyashi",
    "gn:name":"Minamioodoori",
    "iso:country":"JP",
    "wof:name":"321-0963",
    "wof:placetype":"postalcode"
},
  "geometry": {"coordinates":[139.89429999999999,36.5556],"type":"Point"}
}