{
  "type": "Feature",
  "properties": {
    "gn:adm1_name":"Fukuokaken",
    "gn:adm2_name":"Oomutashi",
    "gn:name":"Miyasakamachi",
    "iso:country":"JP",
    "wof:name":"836-0856",
    "wof:placetype":"postalcode"
},
  "geometry": {"coordinates":[130.45230000000001,33.0267],"type":"Point"}
}