{
  "type": "Feature",
  "properties": {
    "gn:adm1_name":"Hyougoken",
    "gn:adm2_name":"Mikatagun'Onsenchou",
    "gn:name":"Uchiyama",
    "iso:country":"JP",
    "wof:name":"669-6945",
    "wof:placetype":"postalcode"
},
  "geometry": {"coordinates":[134.4401,35.5188],"type":"Point"}
}