{
  "type": "Feature",
  "properties": {
    "gn:adm1_name":"Toyamaken",
    "gn:adm2_name":"Takaokashi",
    "gn:name":"Shimokuroda",
    "iso:country":"JP",
    "wof:name":"933-0852",
    "wof:placetype":"postalcode"
},
  "geometry": {"coordinates":[137.0061,36.7275],"type":"Point"}
}