{
  "type": "Feature",
  "properties": {
    "gn:adm1_name":"Gifuken",
    "gn:adm2_name":"Kakamigaharashi",
    "gn:name":"Unumakakamigaharachou",
    "iso:country":"JP",
    "wof:name":"509-0141",
    "wof:placetype":"postalcode"
},
  "geometry": {"coordinates":[136.9051,35.4005],"type":"Point"}
}