{
  "type": "Feature",
  "properties": {
    "gn:adm1_name":"Ibarakiken",
    "gn:adm2_name":"Moriyashi",
    "gn:name":"Kubogaoka",
    "iso:country":"JP",
    "wof:name":"302-0104",
    "wof:placetype":"postalcode"
},
  "geometry": {"coordinates":[139.97370000000001,35.969],"type":"Point"}
}