{
  "type": "Feature",
  "properties": {
    "gn:adm1_name":"Naraken",
    "gn:adm2_name":"Narashi",
    "gn:name":"Sanjousoegawachou",
    "iso:country":"JP",
    "wof:name":"630-8127",
    "wof:placetype":"postalcode"
},
  "geometry": {"coordinates":[135.8124,34.681],"type":"Point"}
}