{
  "type": "Feature",
  "properties": {
    "gn:adm1_name":"Kyoutofu",
    "gn:adm2_name":"Kyoutoshifushimiku",
    "gn:name":"Nousooono",
    "iso:country":"JP",
    "wof:name":"612-8268",
    "wof:placetype":"postalcode"
},
  "geometry": {"coordinates":[135.7259,34.9147],"type":"Point"}
}