{
  "type": "Feature",
  "properties": {
    "gn:adm1_name":"Kyoutofu",
    "gn:adm2_name":"Kyoutoshisakyouku",
    "gn:name":"Okazakitokuseichou",
    "iso:country":"JP",
    "wof:name":"606-8351",
    "wof:placetype":"postalcode"
},
  "geometry": {"coordinates":[135.7782,35.0148],"type":"Point"}
}