{
  "type": "Feature",
  "properties": {
    "gn:adm1_name":"Toyamaken",
    "gn:adm2_name":"Toyamashi",
    "gn:name":"Fujikoshihonmachi",
    "iso:country":"JP",
    "wof:name":"930-0965",
    "wof:placetype":"postalcode"
},
  "geometry": {"coordinates":[137.23560000000001,36.684],"type":"Point"}
}