{
  "type": "Feature",
  "properties": {
    "gn:adm1_name":"Shigaken",
    "gn:adm2_name":"Gamougun'Aduchichou",
    "gn:name":"Ishidera",
    "iso:country":"JP",
    "wof:name":"521-1331",
    "wof:placetype":"postalcode"
},
  "geometry": {"coordinates":[136.16460000000001,35.1377],"type":"Point"}
}