{
  "type": "Feature",
  "properties": {
    "gn:adm1_name":"Hyougoken",
    "gn:adm2_name":"Himejishi",
    "gn:name":"Tenjinmachi",
    "iso:country":"JP",
    "wof:name":"670-0846",
    "wof:placetype":"postalcode"
},
  "geometry": {"coordinates":[134.67529999999999,34.8315],"type":"Point"}
}