{
  "type": "Feature",
  "properties": {
    "gn:adm1_name":"Sagaken",
    "gn:adm2_name":"Tosushi",
    "gn:name":"Imamachi",
    "iso:country":"JP",
    "wof:name":"841-0001",
    "wof:placetype":"postalcode"
},
  "geometry": {"coordinates":[130.52760000000001,33.4064],"type":"Point"}
}