{
  "type": "Feature",
  "properties": {
    "gn:adm1_name":"Ishikawaken",
    "gn:adm2_name":"Fugeshigunmonzenmachi",
    "gn:name":"Tarumi",
    "iso:country":"JP",
    "wof:name":"927-2272",
    "wof:placetype":"postalcode"
},
  "geometry": {"coordinates":[136.7775,37.3615],"type":"Point"}
}