{
  "type": "Feature",
  "properties": {
    "gn:adm1_name":"Kouchiken",
    "gn:adm2_name":"Kouchishi",
    "gn:name":"Nishitsukanohara",
    "iso:country":"JP",
    "wof:name":"780-0951",
    "wof:placetype":"postalcode"
},
  "geometry": {"coordinates":[133.49199999999999,33.5649],"type":"Point"}
}