{
  "type": "Feature",
  "properties": {
    "gn:adm1_name":"Kagawaken",
    "gn:adm2_name":"Higashikagawashi",
    "gn:name":"Kawahigashi",
    "iso:country":"JP",
    "wof:name":"769-2602",
    "wof:placetype":"postalcode"
},
  "geometry": {"coordinates":[134.33019999999999,34.2434],"type":"Point"}
}