{
  "type": "Feature",
  "properties": {
    "gn:adm1_name":"Aichiken",
    "gn:adm2_name":"Okazakishi",
    "gn:name":"Shinpukujichou",
    "iso:country":"JP",
    "wof:name":"444-2106",
    "wof:placetype":"postalcode"
},
  "geometry": {"coordinates":[137.18799999999999,35.0035],"type":"Point"}
}