{
  "type": "Feature",
  "properties": {
    "gn:adm1_name":"Fukushimaken",
    "gn:adm2_name":"Sukagawashi",
    "gn:name":"Shounindan",
    "iso:country":"JP",
    "wof:name":"962-0002",
    "wof:placetype":"postalcode"
},
  "geometry": {"coordinates":[140.374,37.3031],"type":"Point"}
}