{
  "type": "Feature",
  "properties": {
    "gn:adm1_name":"Niigataken",
    "gn:adm2_name":"Shironeshi",
    "gn:name":"Sakanamachi",
    "iso:country":"JP",
    "wof:name":"950-1218",
    "wof:placetype":"postalcode"
},
  "geometry": {"coordinates":[139.01410000000001,37.7656],"type":"Point"}
}