{
  "type": "Feature",
  "properties": {
    "gn:adm1_name":"Aichiken",
    "gn:adm2_name":"Komakishi",
    "gn:name":"Obari",
    "iso:country":"JP",
    "wof:name":"485-0037",
    "wof:placetype":"postalcode"
},
  "geometry": {"coordinates":[136.91370000000001,35.2742],"type":"Point"}
}