{
  "type": "Feature",
  "properties": {
    "gn:adm1_name":"Hiroshimaken",
    "gn:adm2_name":"Hiroshimashiasaminamiku",
    "gn:name":"Nakasuji",
    "iso:country":"JP",
    "wof:name":"731-0122",
    "wof:placetype":"postalcode"
},
  "geometry": {"coordinates":[132.47810000000001,34.4521],"type":"Point"}
}