{
  "type": "Feature",
  "properties": {
    "gn:adm1_name":"Wakayamaken",
    "gn:adm2_name":"Goboushi",
    "gn:name":"Iya",
    "iso:country":"JP",
    "wof:name":"644-0033",
    "wof:placetype":"postalcode"
},
  "geometry": {"coordinates":[135.18190000000001,33.8884],"type":"Point"}
}