{
  "type": "Feature",
  "properties": {
    "gn:adm1_name":"Saitamaken",
    "gn:adm2_name":"Saitamashinishiku",
    "gn:name":"Puraza",
    "iso:country":"JP",
    "wof:name":"331-0063",
    "wof:placetype":"postalcode"
},
  "geometry": {"coordinates":[139.57839999999999,35.9073],"type":"Point"}
}