{
  "type": "Feature",
  "properties": {
    "gn:adm1_name":"Tochigiken",
    "gn:adm2_name":"Ashikagashi",
    "gn:name":"Sukedonakachou",
    "iso:country":"JP",
    "wof:name":"326-0043",
    "wof:placetype":"postalcode"
},
  "geometry": {"coordinates":[139.46680000000001,36.332],"type":"Point"}
}