{
  "type": "Feature",
  "properties": {
    "gn:adm1_name":"Kyoutofu",
    "gn:adm2_name":"Kumanogunkumihamachou",
    "gn:name":"Shinmachi",
    "iso:country":"JP",
    "wof:name":"629-3408",
    "wof:placetype":"postalcode"
},
  "geometry": {"coordinates":[134.89680000000001,35.6048],"type":"Point"}
}