{
  "type": "Feature",
  "properties": {
    "gn:adm1_name":"Hyougoken",
    "gn:adm2_name":"Minougunyokawachou",
    "gn:name":"Minagidai",
    "iso:country":"JP",
    "wof:name":"673-1117",
    "wof:placetype":"postalcode"
},
  "geometry": {"coordinates":[135.1087,34.8716],"type":"Point"}
}