{
  "type": "Feature",
  "properties": {
    "gn:adm1_name":"Gifuken",
    "gn:adm2_name":"Mashitagungerochou",
    "gn:name":"Mitsubuchi",
    "iso:country":"JP",
    "wof:name":"509-2135",
    "wof:placetype":"postalcode"
},
  "geometry": {"coordinates":[137.19229999999999,35.7153],"type":"Point"}
}