{
  "type": "Feature",
  "properties": {
    "gn:adm1_name":"Ehimeken",
    "gn:adm2_name":"Onsengunshigenobuchou",
    "gn:name":"Ushibuchi",
    "iso:country":"JP",
    "wof:name":"791-0213",
    "wof:placetype":"postalcode"
},
  "geometry": {"coordinates":[132.84970000000001,33.7938],"type":"Point"}
}