{
  "type": "Feature",
  "properties": {
    "gn:adm1_name":"Sagaken",
    "gn:adm2_name":"Sagashi",
    "gn:name":"Shoueimachi",
    "iso:country":"JP",
    "wof:name":"840-0855",
    "wof:placetype":"postalcode"
},
  "geometry": {"coordinates":[130.27889999999999,33.2505],"type":"Point"}
}