{
  "type": "Feature",
  "properties": {
    "gn:adm1_name":"Hiroshimaken",
    "gn:adm2_name":"Takeharashi",
    "gn:name":"Takasakichou",
    "iso:country":"JP",
    "wof:name":"729-2313",
    "wof:placetype":"postalcode"
},
  "geometry": {"coordinates":[132.93950000000001,34.3352],"type":"Point"}
}