{
  "type": "Feature",
  "properties": {
    "gn:adm1_name":"Saitamaken",
    "gn:adm2_name":"Irumashi",
    "gn:name":"Miyadera",
    "iso:country":"JP",
    "wof:name":"358-0014",
    "wof:placetype":"postalcode"
},
  "geometry": {"coordinates":[139.37610000000001,35.7974],"type":"Point"}
}