{
  "type": "Feature",
  "properties": {
    "gn:adm1_name":"Ibarakiken",
    "gn:adm2_name":"Shimotsumashi",
    "gn:name":"Sanumashinden",
    "iso:country":"JP",
    "wof:name":"304-0055",
    "wof:placetype":"postalcode"
},
  "geometry": {"coordinates":[139.9547,36.1815],"type":"Point"}
}