{
  "type": "Feature",
  "properties": {
    "gn:adm1_name":"Niigataken",
    "gn:adm2_name":"Murakamishi",
    "gn:name":"Iwafuneminatomachi",
    "iso:country":"JP",
    "wof:name":"958-0058",
    "wof:placetype":"postalcode"
},
  "geometry": {"coordinates":[139.43260000000001,38.1885],"type":"Point"}
}