{
  "type": "Feature",
  "properties": {
    "gn:adm1_name":"Hiroshimaken",
    "gn:adm2_name":"Yamagataguntogouchichou",
    "gn:name":"Itagatani",
    "iso:country":"JP",
    "wof:name":"731-3833",
    "wof:placetype":"postalcode"
},
  "geometry": {"coordinates":[132.23079999999999,34.628],"type":"Point"}
}