{
  "type": "Feature",
  "properties": {
    "gn:adm1_name":"Aichiken",
    "gn:adm2_name":"Kasugaishi",
    "gn:name":"Nishihonmachi",
    "iso:country":"JP",
    "wof:name":"486-0958",
    "wof:placetype":"postalcode"
},
  "geometry": {"coordinates":[136.93289999999999,35.2365],"type":"Point"}
}