{
  "type": "Feature",
  "properties": {
    "gn:adm1_name":"Kouchiken",
    "gn:adm2_name":"Tosashi",
    "gn:name":"Usachoufukushima",
    "iso:country":"JP",
    "wof:name":"781-1163",
    "wof:placetype":"postalcode"
},
  "geometry": {"coordinates":[133.43549999999999,33.4411],"type":"Point"}
}