{
  "type": "Feature",
  "properties": {
    "gn:adm1_name":"Mieken",
    "gn:adm2_name":"Nagagun'Aoyamachou",
    "gn:name":"Kashio",
    "iso:country":"JP",
    "wof:name":"518-0224",
    "wof:placetype":"postalcode"
},
  "geometry": {"coordinates":[136.1944,34.6688],"type":"Point"}
}