{
  "type": "Feature",
  "properties": {
    "gn:adm1_name":"Hyougoken",
    "gn:adm2_name":"Sasayamashi",
    "gn:name":"Otada",
    "iso:country":"JP",
    "wof:name":"669-2435",
    "wof:placetype":"postalcode"
},
  "geometry": {"coordinates":[135.23509999999999,35.0542],"type":"Point"}
}