{
  "type": "Feature",
  "properties": {
    "gn:adm1_name":"Yamaguchiken",
    "gn:adm2_name":"Minegunshuuhouchou",
    "gn:name":"Beppu",
    "iso:country":"JP",
    "wof:name":"754-0603",
    "wof:placetype":"postalcode"
},
  "geometry": {"coordinates":[131.251,34.2441],"type":"Point"}
}