{
  "type": "Feature",
  "properties": {
    "gn:adm1_name":"Kyoutofu",
    "gn:adm2_name":"Kyoutoshinishikyouku",
    "gn:name":"Katagiharaishibatachou",
    "iso:country":"JP",
    "wof:name":"615-8181",
    "wof:placetype":"postalcode"
},
  "geometry": {"coordinates":[135.696,34.9752],"type":"Point"}
}