{
  "type": "Feature",
  "properties": {
    "gn:adm1_name":"Oosakafu",
    "gn:adm2_name":"Takatsukishi",
    "gn:name":"Saimeminami",
    "iso:country":"JP",
    "wof:name":"569-0847",
    "wof:placetype":"postalcode"
},
  "geometry": {"coordinates":[135.6011,34.8011],"type":"Point"}
}