{
  "type": "Feature",
  "properties": {
    "gn:adm1_name":"Naraken",
    "gn:adm2_name":"Yamatokooriyamashi",
    "gn:name":"Toufumachi",
    "iso:country":"JP",
    "wof:name":"639-1149",
    "wof:placetype":"postalcode"
},
  "geometry": {"coordinates":[135.7852,34.6484],"type":"Point"}
}