{
  "type": "Feature",
  "properties": {
    "gn:adm1_name":"Okayamaken",
    "gn:adm2_name":"Okayamashi",
    "gn:name":"Hirosechou",
    "iso:country":"JP",
    "wof:name":"700-0806",
    "wof:placetype":"postalcode"
},
  "geometry": {"coordinates":[133.92869999999999,34.6762],"type":"Point"}
}