{
  "type": "Feature",
  "properties": {
    "gn:adm1_name":"Miyagiken",
    "gn:adm2_name":"Shibatagunshibatamachi",
    "gn:name":"Funaokaminami",
    "iso:country":"JP",
    "wof:name":"989-1605",
    "wof:placetype":"postalcode"
},
  "geometry": {"coordinates":[140.76830000000001,38.0523],"type":"Point"}
}