{
  "type": "Feature",
  "properties": {
    "gn:adm1_name":"Chibaken",
    "gn:adm2_name":"Katorigunhikatamachi",
    "gn:name":"Sakuradai",
    "iso:country":"JP",
    "wof:name":"289-0506",
    "wof:placetype":"postalcode"
},
  "geometry": {"coordinates":[140.64070000000001,35.7775],"type":"Point"}
}