{
  "type": "Feature",
  "properties": {
    "gn:adm1_name":"Tochigiken",
    "gn:adm2_name":"Shimotsugagunmibumachi",
    "gn:name":"Omotemachi",
    "iso:country":"JP",
    "wof:name":"321-0224",
    "wof:placetype":"postalcode"
},
  "geometry": {"coordinates":[139.80160000000001,36.4164],"type":"Point"}
}