{
  "type": "Feature",
  "properties": {
    "gn:adm1_name":"Hiroshimaken",
    "gn:adm2_name":"Futamigunkisachou",
    "gn:name":"Kamiyasuda",
    "iso:country":"JP",
    "wof:name":"729-4202",
    "wof:placetype":"postalcode"
},
  "geometry": {"coordinates":[133.0455,34.7446],"type":"Point"}
}