{
  "type": "Feature",
  "properties": {
    "gn:adm1_name":"Ooitaken",
    "gn:adm2_name":"Ooitashi",
    "gn:name":"Kichoubaru",
    "iso:country":"JP",
    "wof:name":"870-0809",
    "wof:placetype":"postalcode"
},
  "geometry": {"coordinates":[131.5438,33.23],"type":"Point"}
}