{
  "type": "Feature",
  "properties": {
    "gn:adm1_name":"Ishikawaken",
    "gn:adm2_name":"Fugeshigunmonzenmachi",
    "gn:name":"Monzen",
    "iso:country":"JP",
    "wof:name":"927-2156",
    "wof:placetype":"postalcode"
},
  "geometry": {"coordinates":[136.76900000000001,37.2889],"type":"Point"}
}