{
  "type": "Feature",
  "properties": {
    "gn:adm1_name":"Kumamotoken",
    "gn:adm2_name":"Kumagun'Asagirichou",
    "gn:name":"Okaharukita",
    "iso:country":"JP",
    "wof:name":"868-0431",
    "wof:placetype":"postalcode"
},
  "geometry": {"coordinates":[130.93369999999999,32.2411],"type":"Point"}
}