{
  "type": "Feature",
  "properties": {
    "gn:adm1_name":"Fukuiken",
    "gn:adm2_name":"Nyuugunmiyazakimura",
    "gn:name":"Enami",
    "iso:country":"JP",
    "wof:name":"916-0255",
    "wof:placetype":"postalcode"
},
  "geometry": {"coordinates":[136.07320000000001,35.9417],"type":"Point"}
}