{
  "type": "Feature",
  "properties": {
    "gn:adm1_name":"Tochigiken",
    "gn:adm2_name":"Ashikagashi",
    "gn:name":"Kotobukichou",
    "iso:country":"JP",
    "wof:name":"326-0025",
    "wof:placetype":"postalcode"
},
  "geometry": {"coordinates":[139.46709999999999,36.3241],"type":"Point"}
}