{
  "type": "Feature",
  "properties": {
    "gn:adm1_name":"Aichiken",
    "gn:adm2_name":"Inazawashi",
    "gn:name":"Tsukeshimachou",
    "iso:country":"JP",
    "wof:name":"492-8442",
    "wof:placetype":"postalcode"
},
  "geometry": {"coordinates":[136.785,35.2192],"type":"Point"}
}