{
  "type": "Feature",
  "properties": {
    "gn:adm1_name":"Yamagataken",
    "gn:adm2_name":"Yamagatashi",
    "gn:name":"Hanatate",
    "iso:country":"JP",
    "wof:name":"990-0067",
    "wof:placetype":"postalcode"
},
  "geometry": {"coordinates":[140.35079999999999,38.2717],"type":"Point"}
}