{
  "type": "Feature",
  "properties": {
    "gn:adm1_name":"Fukushimaken",
    "gn:adm2_name":"Shirakawashi",
    "gn:name":"Minamihorikiri",
    "iso:country":"JP",
    "wof:name":"961-0857",
    "wof:placetype":"postalcode"
},
  "geometry": {"coordinates":[140.1986,37.1245],"type":"Point"}
}