{
  "type": "Feature",
  "properties": {
    "gn:adm1_name":"Kanagawaken",
    "gn:adm2_name":"Hadanoshi",
    "gn:name":"Hane",
    "iso:country":"JP",
    "wof:name":"259-1301",
    "wof:placetype":"postalcode"
},
  "geometry": {"coordinates":[139.20490000000001,35.3949],"type":"Point"}
}