{
  "type": "Feature",
  "properties": {
    "gn:adm1_name":"Toukyouto",
    "gn:adm2_name":"Higashikurumeshi",
    "gn:name":"Hachimanchou",
    "iso:country":"JP",
    "wof:name":"203-0042",
    "wof:placetype":"postalcode"
},
  "geometry": {"coordinates":[139.5127,35.7536],"type":"Point"}
}