{
  "type": "Feature",
  "properties": {
    "gn:adm1_name":"Hyougoken",
    "gn:adm2_name":"Koubeshinagataku",
    "gn:name":"Yonbanchou",
    "iso:country":"JP",
    "wof:name":"653-0004",
    "wof:placetype":"postalcode"
},
  "geometry": {"coordinates":[135.1533,34.6692],"type":"Point"}
}