{
  "type": "Feature",
  "properties": {
    "gn:adm1_name":"Kanagawaken",
    "gn:adm2_name":"Ashigarakamigun'Ooimachi",
    "gn:name":"Takao",
    "iso:country":"JP",
    "wof:name":"258-0013",
    "wof:placetype":"postalcode"
},
  "geometry": {"coordinates":[139.18700000000001,35.3428],"type":"Point"}
}