{
  "type": "Feature",
  "properties": {
    "gn:adm1_name":"Nagasakiken",
    "gn:adm2_name":"Isahayashi",
    "gn:name":"Onojimamachi",
    "iso:country":"JP",
    "wof:name":"854-0031",
    "wof:placetype":"postalcode"
},
  "geometry": {"coordinates":[130.09350000000001,32.8448],"type":"Point"}
}