{
  "type": "Feature",
  "properties": {
    "gn:adm1_name":"Aichiken",
    "gn:adm2_name":"Inuyamashi",
    "gn:name":"Inuyama",
    "iso:country":"JP",
    "wof:name":"484-0081",
    "wof:placetype":"postalcode"
},
  "geometry": {"coordinates":[136.9417,35.382],"type":"Point"}
}