{
  "type": "Feature",
  "properties": {
    "gn:adm1_name":"Niigataken",
    "gn:adm2_name":"Shibatashi",
    "gn:name":"Kuwanoguchi",
    "iso:country":"JP",
    "wof:name":"957-0003",
    "wof:placetype":"postalcode"
},
  "geometry": {"coordinates":[139.33000000000001,37.9791],"type":"Point"}
}