{
  "type": "Feature",
  "properties": {
    "gn:adm1_name":"Aichiken",
    "gn:adm2_name":"Kitashitaragunshitarachou",
    "gn:name":"Arou",
    "iso:country":"JP",
    "wof:name":"441-2316",
    "wof:placetype":"postalcode"
},
  "geometry": {"coordinates":[137.58709999999999,35.0874],"type":"Point"}
}