{
  "type": "Feature",
  "properties": {
    "gn:adm1_name":"Niigataken",
    "gn:adm2_name":"Minamiuonumagunshiozawamachi",
    "gn:name":"Kamitookamachi",
    "iso:country":"JP",
    "wof:name":"949-6411",
    "wof:placetype":"postalcode"
},
  "geometry": {"coordinates":[138.857,37.0367],"type":"Point"}
}