{
  "type": "Feature",
  "properties": {
    "gn:adm1_name":"Niigataken",
    "gn:adm2_name":"Kitakanbaragunnakajoumachi",
    "gn:name":"Yahikooka",
    "iso:country":"JP",
    "wof:name":"959-2668",
    "wof:placetype":"postalcode"
},
  "geometry": {"coordinates":[139.36179999999999,38.0448],"type":"Point"}
}