{
  "type": "Feature",
  "properties": {
    "gn:adm1_name":"Niigataken",
    "gn:adm2_name":"Nakakubikigunsanwamura",
    "gn:name":"Mimurashinden",
    "iso:country":"JP",
    "wof:name":"943-0315",
    "wof:placetype":"postalcode"
},
  "geometry": {"coordinates":[138.35810000000001,37.1221],"type":"Point"}
}