{
  "type": "Feature",
  "properties": {
    "gn:adm1_name":"Kyoutofu",
    "gn:adm2_name":"Kyoutoshiminamiku",
    "gn:name":"Higashikujouishidachou",
    "iso:country":"JP",
    "wof:name":"601-8032",
    "wof:placetype":"postalcode"
},
  "geometry": {"coordinates":[135.76089999999999,34.9743],"type":"Point"}
}