{
  "type": "Feature",
  "properties": {
    "gn:adm1_name":"Fukuiken",
    "gn:adm2_name":"Oonoshi",
    "gn:name":"Shinmachi",
    "iso:country":"JP",
    "wof:name":"912-0027",
    "wof:placetype":"postalcode"
},
  "geometry": {"coordinates":[136.49029999999999,35.9919],"type":"Point"}
}