{
  "type": "Feature",
  "properties": {
    "gn:adm1_name":"Oosakafu",
    "gn:adm2_name":"Ibarakishi",
    "gn:name":"Mizuo",
    "iso:country":"JP",
    "wof:name":"567-0891",
    "wof:placetype":"postalcode"
},
  "geometry": {"coordinates":[135.5753,34.8065],"type":"Point"}
}