{
  "type": "Feature",
  "properties": {
    "gn:adm1_name":"Kyoutofu",
    "gn:adm2_name":"Kyoutoshinishikyouku",
    "gn:name":"Arashiyamamiyamachi",
    "iso:country":"JP",
    "wof:name":"616-0024",
    "wof:placetype":"postalcode"
},
  "geometry": {"coordinates":[135.685,34.9997],"type":"Point"}
}