{
  "type": "Feature",
  "properties": {
    "gn:adm1_name":"Kagoshimaken",
    "gn:adm2_name":"Kagoshimashi",
    "gn:name":"Shimoarata",
    "iso:country":"JP",
    "wof:name":"890-0056",
    "wof:placetype":"postalcode"
},
  "geometry": {"coordinates":[130.5558,31.5728],"type":"Point"}
}