{
  "type": "Feature",
  "properties": {
    "gn:adm1_name":"Saitamaken",
    "gn:adm2_name":"Chichibugunnagatoromachi",
    "gn:name":"Yanase",
    "iso:country":"JP",
    "wof:name":"369-1301",
    "wof:placetype":"postalcode"
},
  "geometry": {"coordinates":[139.14619999999999,36.1342],"type":"Point"}
}