{
  "type": "Feature",
  "properties": {
    "gn:adm1_name":"Ibarakiken",
    "gn:adm2_name":"Shimodateshi",
    "gn:name":"Shibayama",
    "iso:country":"JP",
    "wof:name":"308-0072",
    "wof:placetype":"postalcode"
},
  "geometry": {"coordinates":[139.9658,36.3471],"type":"Point"}
}