{
  "type": "Feature",
  "properties": {
    "gn:adm1_name":"Kyoutofu",
    "gn:adm2_name":"Kyoutoshiminamiku",
    "gn:name":"Kamitobakamonden",
    "iso:country":"JP",
    "wof:name":"601-8131",
    "wof:placetype":"postalcode"
},
  "geometry": {"coordinates":[135.74590000000001,34.9633],"type":"Point"}
}