{
  "type": "Feature",
  "properties": {
    "gn:adm1_name":"Shizuokaken",
    "gn:adm2_name":"Shidagun'Ooigawachou",
    "gn:name":"Kamishinden",
    "iso:country":"JP",
    "wof:name":"421-0206",
    "wof:placetype":"postalcode"
},
  "geometry": {"coordinates":[138.2698,34.8182],"type":"Point"}
}