{
  "type": "Feature",
  "properties": {
    "gn:adm1_name":"Mieken",
    "gn:adm2_name":"Uenoshi",
    "gn:name":"Ida",
    "iso:country":"JP",
    "wof:name":"518-0123",
    "wof:placetype":"postalcode"
},
  "geometry": {"coordinates":[136.1361,34.7235],"type":"Point"}
}