{
  "type": "Feature",
  "properties": {
    "gn:adm1_name":"Oosakafu",
    "gn:adm2_name":"Sakaishi",
    "gn:name":"Nonoi",
    "iso:country":"JP",
    "wof:name":"590-0155",
    "wof:placetype":"postalcode"
},
  "geometry": {"coordinates":[135.47819999999999,34.4946],"type":"Point"}
}