{
  "type": "Feature",
  "properties": {
    "gn:adm1_name":"Aichiken",
    "gn:adm2_name":"Toyohashishi",
    "gn:name":"Moriokachou",
    "iso:country":"JP",
    "wof:name":"441-1114",
    "wof:placetype":"postalcode"
},
  "geometry": {"coordinates":[137.42760000000001,34.7877],"type":"Point"}
}