{
  "type": "Feature",
  "properties": {
    "gn:adm1_name":"Yamagataken",
    "gn:adm2_name":"Higashitagawagun'Amarumemachi",
    "gn:name":"Amarume",
    "iso:country":"JP",
    "wof:name":"999-7781",
    "wof:placetype":"postalcode"
},
  "geometry": {"coordinates":[139.90430000000001,38.847],"type":"Point"}
}