{
  "type": "Feature",
  "properties": {
    "gn:adm1_name":"Ibarakiken",
    "gn:adm2_name":"Shimodateshi",
    "gn:name":"Soukajima",
    "iso:country":"JP",
    "wof:name":"308-0864",
    "wof:placetype":"postalcode"
},
  "geometry": {"coordinates":[139.952,36.3298],"type":"Point"}
}