{
  "type": "Feature",
  "properties": {
    "gn:adm1_name":"Fukushimaken",
    "gn:adm2_name":"Ishikawagunfurudonomachi",
    "gn:name":"Yamakami",
    "iso:country":"JP",
    "wof:name":"963-8302",
    "wof:placetype":"postalcode"
},
  "geometry": {"coordinates":[140.58150000000001,37.1202],"type":"Point"}
}