{
  "type": "Feature",
  "properties": {
    "gn:adm1_name":"Gifuken",
    "gn:adm2_name":"Yoshikigunmiyagawamura",
    "gn:name":"Todani",
    "iso:country":"JP",
    "wof:name":"509-4544",
    "wof:placetype":"postalcode"
},
  "geometry": {"coordinates":[137.1764,36.3946],"type":"Point"}
}