{
  "type": "Feature",
  "properties": {
    "gn:adm1_name":"Fukushimaken",
    "gn:adm2_name":"Iwakishi",
    "gn:name":"Tairanakahirakubohosodamachi",
    "iso:country":"JP",
    "wof:name":"970-8008",
    "wof:placetype":"postalcode"
},
  "geometry": {"coordinates":[140.87690000000001,37.0847],"type":"Point"}
}