{
  "type": "Feature",
  "properties": {
    "gn:adm1_name":"Tottoriken",
    "gn:adm2_name":"Saihakugundaisenchou",
    "gn:name":"Bouryou",
    "iso:country":"JP",
    "wof:name":"689-3312",
    "wof:placetype":"postalcode"
},
  "geometry": {"coordinates":[133.49350000000001,35.4562],"type":"Point"}
}