{
  "type": "Feature",
  "properties": {
    "gn:adm1_name":"Hyougoken",
    "gn:adm2_name":"Shisougunyamasakichou",
    "gn:name":"Aoki",
    "iso:country":"JP",
    "wof:name":"671-2564",
    "wof:placetype":"postalcode"
},
  "geometry": {"coordinates":[134.49119999999999,35.0303],"type":"Point"}
}