{
  "type": "Feature",
  "properties": {
    "gn:adm1_name":"Aichiken",
    "gn:adm2_name":"Inuyamashi",
    "gn:name":"Wakamiya",
    "iso:country":"JP",
    "wof:name":"484-0861",
    "wof:placetype":"postalcode"
},
  "geometry": {"coordinates":[136.9496,35.3312],"type":"Point"}
}