{
  "type": "Feature",
  "properties": {
    "gn:adm1_name":"Mieken",
    "gn:adm2_name":"Suzukashi",
    "gn:name":"Tsugachou",
    "iso:country":"JP",
    "wof:name":"513-0002",
    "wof:placetype":"postalcode"
},
  "geometry": {"coordinates":[136.5136,34.8898],"type":"Point"}
}