{
  "type": "Feature",
  "properties": {
    "gn:adm1_name":"Okayamaken",
    "gn:adm2_name":"Takahashishi",
    "gn:name":"Tamagawachoumashihara",
    "iso:country":"JP",
    "wof:name":"716-0054",
    "wof:placetype":"postalcode"
},
  "geometry": {"coordinates":[133.57560000000001,34.7307],"type":"Point"}
}