{
  "type": "Feature",
  "properties": {
    "gn:adm1_name":"Miyazakiken",
    "gn:adm2_name":"Hyuugashi",
    "gn:name":"Funabachou",
    "iso:country":"JP",
    "wof:name":"883-0065",
    "wof:placetype":"postalcode"
},
  "geometry": {"coordinates":[131.64869999999999,32.4438],"type":"Point"}
}