{
  "type": "Feature",
  "properties": {
    "gn:adm1_name":"Nagasakiken",
    "gn:adm2_name":"Nagasakishi",
    "gn:name":"Kazagashiramachi",
    "iso:country":"JP",
    "wof:name":"850-0803",
    "wof:placetype":"postalcode"
},
  "geometry": {"coordinates":[129.88849999999999,32.7431],"type":"Point"}
}