{
  "type": "Feature",
  "properties": {
    "gn:adm1_name":"Ishikawaken",
    "gn:adm2_name":"Kanazawashi",
    "gn:name":"Oyamamachi",
    "iso:country":"JP",
    "wof:name":"920-0918",
    "wof:placetype":"postalcode"
},
  "geometry": {"coordinates":[136.6549,36.5675],"type":"Point"}
}