{
  "type": "Feature",
  "properties": {
    "gn:adm1_name":"Fukushimaken",
    "gn:adm2_name":"Tamuragunmiharumachi",
    "gn:name":"Jouroku",
    "iso:country":"JP",
    "wof:name":"963-7743",
    "wof:placetype":"postalcode"
},
  "geometry": {"coordinates":[140.48419999999999,37.4418],"type":"Point"}
}