{
  "type": "Feature",
  "properties": {
    "gn:adm1_name":"Ishikawaken",
    "gn:adm2_name":"Mattoushi",
    "gn:name":"Mukaijimamachi",
    "iso:country":"JP",
    "wof:name":"924-0833",
    "wof:placetype":"postalcode"
},
  "geometry": {"coordinates":[136.57919999999999,36.4807],"type":"Point"}
}