{
  "type": "Feature",
  "properties": {
    "gn:adm1_name":"Fukuokaken",
    "gn:adm2_name":"Kitakyuushuushikokurakitaku",
    "gn:name":"Asano",
    "iso:country":"JP",
    "wof:name":"802-0001",
    "wof:placetype":"postalcode"
},
  "geometry": {"coordinates":[130.88339999999999,33.8882],"type":"Point"}
}