{
  "type": "Feature",
  "properties": {
    "gn:adm1_name":"Naganoken",
    "gn:adm2_name":"Shiojirishi",
    "gn:name":"Hirookayoshida",
    "iso:country":"JP",
    "wof:name":"399-0701",
    "wof:placetype":"postalcode"
},
  "geometry": {"coordinates":[137.9547,36.1625],"type":"Point"}
}