{
  "type": "Feature",
  "properties": {
    "gn:adm1_name":"Chibaken",
    "gn:adm2_name":"Kashiwashi",
    "gn:name":"Chiyoda",
    "iso:country":"JP",
    "wof:name":"277-0025",
    "wof:placetype":"postalcode"
},
  "geometry": {"coordinates":[139.976,35.8548],"type":"Point"}
}