{
  "type": "Feature",
  "properties": {
    "gn:adm1_name":"Okayamaken",
    "gn:adm2_name":"Aidagunsakutouchou",
    "gn:name":"Kajihara",
    "iso:country":"JP",
    "wof:name":"709-4202",
    "wof:placetype":"postalcode"
},
  "geometry": {"coordinates":[134.25790000000001,35.0867],"type":"Point"}
}