{
  "type": "Feature",
  "properties": {
    "gn:adm1_name":"Oosakafu",
    "gn:adm2_name":"Higashioosakashi",
    "gn:name":"Kamishijouchou",
    "iso:country":"JP",
    "wof:name":"579-8052",
    "wof:placetype":"postalcode"
},
  "geometry": {"coordinates":[135.6491,34.6584],"type":"Point"}
}