{
  "type": "Feature",
  "properties": {
    "gn:adm1_name":"Shizuokaken",
    "gn:adm2_name":"Suntougun'Oyamachou",
    "gn:name":"Subashiri",
    "iso:country":"JP",
    "wof:name":"410-1431",
    "wof:placetype":"postalcode"
},
  "geometry": {"coordinates":[138.86869999999999,35.3615],"type":"Point"}
}