{
  "type": "Feature",
  "properties": {
    "gn:adm1_name":"Fukushimaken",
    "gn:adm2_name":"Iwakishi",
    "gn:name":"Tairakinuya",
    "iso:country":"JP",
    "wof:name":"970-0113",
    "wof:placetype":"postalcode"
},
  "geometry": {"coordinates":[140.93340000000001,37.0924],"type":"Point"}
}