{
  "type": "Feature",
  "properties": {
    "gn:adm1_name":"Fukushimaken",
    "gn:adm2_name":"Dategunkoorimachi",
    "gn:name":"Shibatsutsumi",
    "iso:country":"JP",
    "wof:name":"969-1608",
    "wof:placetype":"postalcode"
},
  "geometry": {"coordinates":[140.5154,37.8519],"type":"Point"}
}