{
  "type": "Feature",
  "properties": {
    "gn:adm1_name":"Shizuokaken",
    "gn:adm2_name":"Haibaragunhaibarachou",
    "gn:name":"Sakaguchi",
    "iso:country":"JP",
    "wof:name":"421-0411",
    "wof:placetype":"postalcode"
},
  "geometry": {"coordinates":[138.18729999999999,34.788],"type":"Point"}
}