{
  "type": "Feature",
  "properties": {
    "gn:adm1_name":"Shizuokaken",
    "gn:adm2_name":"Gotenbashi",
    "gn:name":"Komakado",
    "iso:country":"JP",
    "wof:name":"412-0038",
    "wof:placetype":"postalcode"
},
  "geometry": {"coordinates":[138.90960000000001,35.2564],"type":"Point"}
}