{
  "type": "Feature",
  "properties": {
    "gn:adm1_name":"Tokushimaken",
    "gn:adm2_name":"Tokushimashi",
    "gn:name":"Kawauchichou(Komatsukita)",
    "iso:country":"JP",
    "wof:name":"771-0102",
    "wof:placetype":"postalcode"
},
  "geometry": {"coordinates":[134.59520000000001,34.0934],"type":"Point"}
}