{
  "type": "Feature",
  "properties": {
    "gn:adm1_name":"Shigaken",
    "gn:adm2_name":"Oumihachimanshi",
    "gn:name":"Minamihongouchou",
    "iso:country":"JP",
    "wof:name":"523-0814",
    "wof:placetype":"postalcode"
},
  "geometry": {"coordinates":[136.11060000000001,35.1193],"type":"Point"}
}