{
  "type": "Feature",
  "properties": {
    "gn:adm1_name":"Ibarakiken",
    "gn:adm2_name":"Kashimagun'Asahimura",
    "gn:name":"Kamioota",
    "iso:country":"JP",
    "wof:name":"311-1405",
    "wof:placetype":"postalcode"
},
  "geometry": {"coordinates":[140.53039999999999,36.2482],"type":"Point"}
}