{
  "type": "Feature",
  "properties": {
    "gn:adm1_name":"Kumamotoken",
    "gn:adm2_name":"Asogun'Asomachi",
    "gn:name":"Yamada(Sonota)",
    "iso:country":"JP",
    "wof:name":"869-2313",
    "wof:placetype":"postalcode"
},
  "geometry": {"coordinates":[131.09119999999999,32.9876],"type":"Point"}
}