{
  "type": "Feature",
  "properties": {
    "gn:adm1_name":"Tochigiken",
    "gn:adm2_name":"Hagagunmotegimachi",
    "gn:name":"Mashii",
    "iso:country":"JP",
    "wof:name":"321-3564",
    "wof:placetype":"postalcode"
},
  "geometry": {"coordinates":[140.20070000000001,36.5336],"type":"Point"}
}