{
  "type": "Feature",
  "properties": {
    "gn:adm1_name":"Hyougoken",
    "gn:adm2_name":"Koubeshisumaku",
    "gn:name":"Chitosechou",
    "iso:country":"JP",
    "wof:name":"654-0027",
    "wof:placetype":"postalcode"
},
  "geometry": {"coordinates":[135.13839999999999,34.6554],"type":"Point"}
}