{
  "type": "Feature",
  "properties": {
    "gn:adm1_name":"Tochigiken",
    "gn:adm2_name":"Hagagunmashikomachi",
    "gn:name":"Shimoooba",
    "iso:country":"JP",
    "wof:name":"321-4211",
    "wof:placetype":"postalcode"
},
  "geometry": {"coordinates":[140.1336,36.4703],"type":"Point"}
}