{
  "type": "Feature",
  "properties": {
    "gn:adm1_name":"Yamanashiken",
    "gn:adm2_name":"Kitakomagunsutamachou",
    "gn:name":"Wakamikoshinmachi",
    "iso:country":"JP",
    "wof:name":"408-0117",
    "wof:placetype":"postalcode"
},
  "geometry": {"coordinates":[138.40690000000001,35.7745],"type":"Point"}
}