{
  "type": "Feature",
  "properties": {
    "gn:adm1_name":"Hiroshimaken",
    "gn:adm2_name":"Saekigun'Oogakichou",
    "gn:name":"Oobara",
    "iso:country":"JP",
    "wof:name":"737-2213",
    "wof:placetype":"postalcode"
},
  "geometry": {"coordinates":[132.4622,34.1719],"type":"Point"}
}