{
  "type": "Feature",
  "properties": {
    "gn:adm1_name":"Kanagawaken",
    "gn:adm2_name":"Zushishi",
    "gn:name":"Yamanone",
    "iso:country":"JP",
    "wof:name":"249-0002",
    "wof:placetype":"postalcode"
},
  "geometry": {"coordinates":[139.583,35.3003],"type":"Point"}
}