{
  "type": "Feature",
  "properties": {
    "gn:adm1_name":"Shigaken",
    "gn:adm2_name":"Yasugunyasuchou",
    "gn:name":"Tsujimachi",
    "iso:country":"JP",
    "wof:name":"520-2315",
    "wof:placetype":"postalcode"
},
  "geometry": {"coordinates":[136.04419999999999,35.0765],"type":"Point"}
}