{
  "type": "Feature",
  "properties": {
    "gn:adm1_name":"Fukushimaken",
    "gn:adm2_name":"Shirakawashi",
    "gn:name":"Oikuboyama",
    "iso:country":"JP",
    "wof:name":"961-0838",
    "wof:placetype":"postalcode"
},
  "geometry": {"coordinates":[140.19479999999999,37.1107],"type":"Point"}
}