{
  "type": "Feature",
  "properties": {
    "gn:adm1_name":"Kouchiken",
    "gn:adm2_name":"Takaokagunhigashitsunomura",
    "gn:name":"Funato",
    "iso:country":"JP",
    "wof:name":"785-0411",
    "wof:placetype":"postalcode"
},
  "geometry": {"coordinates":[133.0925,33.4201],"type":"Point"}
}