{
  "type": "Feature",
  "properties": {
    "gn:adm1_name":"Ibarakiken",
    "gn:adm2_name":"Yuukigunyachiyomachi",
    "gn:name":"Osaki",
    "iso:country":"JP",
    "wof:name":"300-3554",
    "wof:placetype":"postalcode"
},
  "geometry": {"coordinates":[139.90889999999999,36.1389],"type":"Point"}
}