{
  "type": "Feature",
  "properties": {
    "gn:adm1_name":"Shigaken",
    "gn:adm2_name":"Hikoneshi",
    "gn:name":"Inabechou",
    "iso:country":"JP",
    "wof:name":"521-1113",
    "wof:placetype":"postalcode"
},
  "geometry": {"coordinates":[136.19540000000001,35.207],"type":"Point"}
}