{
  "type": "Feature",
  "properties": {
    "gn:adm1_name":"Miyagiken",
    "gn:adm2_name":"Kamigunkamimachi",
    "gn:name":"Minamiterashuku",
    "iso:country":"JP",
    "wof:name":"981-4332",
    "wof:placetype":"postalcode"
},
  "geometry": {"coordinates":[140.7826,38.576],"type":"Point"}
}