{
  "type": "Feature",
  "properties": {
    "gn:adm1_name":"Tottoriken",
    "gn:adm2_name":"Yazugunchiduchou",
    "gn:name":"Honomi",
    "iso:country":"JP",
    "wof:name":"689-1432",
    "wof:placetype":"postalcode"
},
  "geometry": {"coordinates":[134.2405,35.244],"type":"Point"}
}