{
  "type": "Feature",
  "properties": {
    "gn:adm1_name":"Nagasakiken",
    "gn:adm2_name":"Nagasakishi",
    "gn:name":"Daikokumachi",
    "iso:country":"JP",
    "wof:name":"850-0057",
    "wof:placetype":"postalcode"
},
  "geometry": {"coordinates":[129.87270000000001,32.7522],"type":"Point"}
}