{
  "type": "Feature",
  "properties": {
    "gn:adm1_name":"Yamanashiken",
    "gn:adm2_name":"Nirasakishi",
    "gn:name":"Iwashita",
    "iso:country":"JP",
    "wof:name":"407-0012",
    "wof:placetype":"postalcode"
},
  "geometry": {"coordinates":[138.459,35.7118],"type":"Point"}
}