{
  "type": "Feature",
  "properties": {
    "gn:adm1_name":"Nagasakiken",
    "gn:adm2_name":"Fukueshi",
    "gn:name":"Matsuyamachou",
    "iso:country":"JP",
    "wof:name":"853-0052",
    "wof:placetype":"postalcode"
},
  "geometry": {"coordinates":[128.84129999999999,32.7028],"type":"Point"}
}