{
  "type": "Feature",
  "properties": {
    "gn:adm1_name":"Shigaken",
    "gn:adm2_name":"Youkaichishi",
    "gn:name":"Kamihanedachou",
    "iso:country":"JP",
    "wof:name":"527-0082",
    "wof:placetype":"postalcode"
},
  "geometry": {"coordinates":[136.1557,35.0859],"type":"Point"}
}