{
  "type": "Feature",
  "properties": {
    "gn:adm1_name":"Tochigiken",
    "gn:adm2_name":"Kuroisoshi",
    "gn:name":"Toyosumichou",
    "iso:country":"JP",
    "wof:name":"325-0072",
    "wof:placetype":"postalcode"
},
  "geometry": {"coordinates":[140.04050000000001,36.9757],"type":"Point"}
}