{
  "type": "Feature",
  "properties": {
    "gn:adm1_name":"Shizuokaken",
    "gn:adm2_name":"Hamamatsushi",
    "gn:name":"Hikumachou",
    "iso:country":"JP",
    "wof:name":"430-0902",
    "wof:placetype":"postalcode"
},
  "geometry": {"coordinates":[137.74379999999999,34.7244],"type":"Point"}
}