{
  "type": "Feature",
  "properties": {
    "gn:adm1_name":"Wakayamaken",
    "gn:adm2_name":"Nagagunkishigawachou",
    "gn:name":"Marusu",
    "iso:country":"JP",
    "wof:name":"640-0401",
    "wof:placetype":"postalcode"
},
  "geometry": {"coordinates":[135.3272,34.2367],"type":"Point"}
}