{
  "type": "Feature",
  "properties": {
    "gn:adm1_name":"Okayamaken",
    "gn:adm2_name":"Tsuyamashi",
    "gn:name":"Koujinyama",
    "iso:country":"JP",
    "wof:name":"708-0866",
    "wof:placetype":"postalcode"
},
  "geometry": {"coordinates":[134.0121,35.0291],"type":"Point"}
}