{
  "type": "Feature",
  "properties": {
    "gn:adm1_name":"Mieken",
    "gn:adm2_name":"Yokkaichishi",
    "gn:name":"Oomiyanishimachi",
    "iso:country":"JP",
    "wof:name":"510-0004",
    "wof:placetype":"postalcode"
},
  "geometry": {"coordinates":[136.6283,34.9927],"type":"Point"}
}