{
  "type": "Feature",
  "properties": {
    "gn:adm1_name":"Ishikawaken",
    "gn:adm2_name":"Kanazawashi",
    "gn:name":"Ishibiki",
    "iso:country":"JP",
    "wof:name":"920-0935",
    "wof:placetype":"postalcode"
},
  "geometry": {"coordinates":[136.66999999999999,36.5555],"type":"Point"}
}