{
  "type": "Feature",
  "properties": {
    "gn:adm1_name":"Chibaken",
    "gn:adm2_name":"Tateyamashi",
    "gn:name":"Higashinagata",
    "iso:country":"JP",
    "wof:name":"294-0028",
    "wof:placetype":"postalcode"
},
  "geometry": {"coordinates":[139.88030000000001,34.9678],"type":"Point"}
}