{
  "type": "Feature",
  "properties": {
    "gn:adm1_name":"Okinawaken",
    "gn:adm2_name":"Ginowanshi",
    "gn:name":"Ginowan",
    "iso:country":"JP",
    "wof:name":"901-2211",
    "wof:placetype":"postalcode"
},
  "geometry": {"coordinates":[127.7586,26.2634],"type":"Point"}
}