{
  "type": "Feature",
  "properties": {
    "gn:adm1_name":"Ooitaken",
    "gn:adm2_name":"Beppushi",
    "gn:name":"Chuuoumachi",
    "iso:country":"JP",
    "wof:name":"874-0936",
    "wof:placetype":"postalcode"
},
  "geometry": {"coordinates":[131.5008,33.277],"type":"Point"}
}