{
  "type": "Feature",
  "properties": {
    "gn:adm1_name":"Okayamaken",
    "gn:adm2_name":"Tsuyamashi",
    "gn:name":"Nishiimamachi",
    "iso:country":"JP",
    "wof:name":"708-0046",
    "wof:placetype":"postalcode"
},
  "geometry": {"coordinates":[133.99299999999999,35.0606],"type":"Point"}
}