{
  "type": "Feature",
  "properties": {
    "gn:adm1_name":"Fukuokaken",
    "gn:adm2_name":"Fukuokashichuuouku",
    "gn:name":"Sansoudoori",
    "iso:country":"JP",
    "wof:name":"810-0018",
    "wof:placetype":"postalcode"
},
  "geometry": {"coordinates":[130.3956,33.5732],"type":"Point"}
}