{
  "type": "Feature",
  "properties": {
    "gn:adm1_name":"Kagoshimaken",
    "gn:adm2_name":"Airagunkurinochou",
    "gn:name":"Inabasaki",
    "iso:country":"JP",
    "wof:name":"899-6204",
    "wof:placetype":"postalcode"
},
  "geometry": {"coordinates":[130.68960000000001,31.971],"type":"Point"}
}