{
  "type": "Feature",
  "properties": {
    "gn:adm1_name":"Miyagiken",
    "gn:adm2_name":"Shibatagun'Oogawaramachi",
    "gn:name":"Koushichou",
    "iso:country":"JP",
    "wof:name":"989-1214",
    "wof:placetype":"postalcode"
},
  "geometry": {"coordinates":[140.73679999999999,38.0448],"type":"Point"}
}