{
  "type": "Feature",
  "properties": {
    "gn:adm1_name":"Wakayamaken",
    "gn:adm2_name":"Nagagun'Uchitachou",
    "gn:name":"Tanakababa",
    "iso:country":"JP",
    "wof:name":"649-6421",
    "wof:placetype":"postalcode"
},
  "geometry": {"coordinates":[135.35499999999999,34.2684],"type":"Point"}
}