{
  "type": "Feature",
  "properties": {
    "gn:adm1_name":"Niigataken",
    "gn:adm2_name":"Toyosakashi",
    "gn:name":"Kuzutsuka",
    "iso:country":"JP",
    "wof:name":"950-3321",
    "wof:placetype":"postalcode"
},
  "geometry": {"coordinates":[139.21729999999999,37.9196],"type":"Point"}
}