{
  "type": "Feature",
  "properties": {
    "gn:adm1_name":"Naganoken",
    "gn:adm2_name":"Naganoshi",
    "gn:name":"Aokijimamachitsunashima",
    "iso:country":"JP",
    "wof:name":"381-2206",
    "wof:placetype":"postalcode"
},
  "geometry": {"coordinates":[138.19489999999999,36.615],"type":"Point"}
}