{
  "type": "Feature",
  "properties": {
    "gn:adm1_name":"Fukushimaken",
    "gn:adm2_name":"Tamuraguntokiwamachi",
    "gn:name":"Kobiyama",
    "iso:country":"JP",
    "wof:name":"963-4614",
    "wof:placetype":"postalcode"
},
  "geometry": {"coordinates":[140.6679,37.4166],"type":"Point"}
}