{
  "type": "Feature",
  "properties": {
    "gn:adm1_name":"Ibarakiken",
    "gn:adm2_name":"Tsukubashi",
    "gn:name":"Kaname",
    "iso:country":"JP",
    "wof:name":"300-2622",
    "wof:placetype":"postalcode"
},
  "geometry": {"coordinates":[140.08439999999999,36.1126],"type":"Point"}
}