{
  "type": "Feature",
  "properties": {
    "gn:adm1_name":"Miyazakiken",
    "gn:adm2_name":"Nobeokashi",
    "gn:name":"Ishidamachi",
    "iso:country":"JP",
    "wof:name":"889-0501",
    "wof:placetype":"postalcode"
},
  "geometry": {"coordinates":[131.66630000000001,32.5366],"type":"Point"}
}