{
  "type": "Feature",
  "properties": {
    "gn:adm1_name":"Nagasakiken",
    "gn:adm2_name":"Isahayashi",
    "gn:name":"Azukisakimachi",
    "iso:country":"JP",
    "wof:name":"859-0311",
    "wof:placetype":"postalcode"
},
  "geometry": {"coordinates":[130.06720000000001,32.8566],"type":"Point"}
}