{
  "type": "Feature",
  "properties": {
    "gn:adm1_name":"Gunmaken",
    "gn:adm2_name":"Isesakishi",
    "gn:name":"Hirosechou",
    "iso:country":"JP",
    "wof:name":"372-0039",
    "wof:placetype":"postalcode"
},
  "geometry": {"coordinates":[139.1969,36.3001],"type":"Point"}
}