{
  "type": "Feature",
  "properties": {
    "gn:adm1_name":"Hyougoken",
    "gn:adm2_name":"Koubeshichuuouku",
    "gn:name":"Minatojimaminamimachi",
    "iso:country":"JP",
    "wof:name":"650-0047",
    "wof:placetype":"postalcode"
},
  "geometry": {"coordinates":[135.21549999999999,34.6578],"type":"Point"}
}