{
  "type": "Feature",
  "properties": {
    "gn:adm1_name":"Naganoken",
    "gn:adm2_name":"Sarashinagun'Oookamura",
    "gn:name":"Otsu",
    "iso:country":"JP",
    "wof:name":"381-2703",
    "wof:placetype":"postalcode"
},
  "geometry": {"coordinates":[137.97659999999999,36.5039],"type":"Point"}
}