{
  "type": "Feature",
  "properties": {
    "gn:adm1_name":"Hiroshimaken",
    "gn:adm2_name":"Yamagataguntogouchichou",
    "gn:name":"Shiwagi",
    "iso:country":"JP",
    "wof:name":"731-3813",
    "wof:placetype":"postalcode"
},
  "geometry": {"coordinates":[132.20920000000001,34.5973],"type":"Point"}
}