{
  "type": "Feature",
  "properties": {
    "gn:adm1_name":"Niigataken",
    "gn:adm2_name":"Minamiuonumagunmuikamachi",
    "gn:name":"Futsukamachi",
    "iso:country":"JP",
    "wof:name":"949-6772",
    "wof:placetype":"postalcode"
},
  "geometry": {"coordinates":[138.9007,37.0834],"type":"Point"}
}