{
  "type": "Feature",
  "properties": {
    "gn:adm1_name":"Niigataken",
    "gn:adm2_name":"Minamiuonumagunmuikamachi",
    "gn:name":"Yamaya",
    "iso:country":"JP",
    "wof:name":"949-6763",
    "wof:placetype":"postalcode"
},
  "geometry": {"coordinates":[138.9213,37.0551],"type":"Point"}
}