{
  "type": "Feature",
  "properties": {
    "gn:adm1_name":"Kouchiken",
    "gn:adm2_name":"Akigunkitagawamura",
    "gn:name":"Notomokou",
    "iso:country":"JP",
    "wof:name":"781-6441",
    "wof:placetype":"postalcode"
},
  "geometry": {"coordinates":[134.03890000000001,33.4459],"type":"Point"}
}