{
  "type": "Feature",
  "properties": {
    "gn:adm1_name":"Hiroshimaken",
    "gn:adm2_name":"Innoshimashi",
    "gn:name":"Mitsunoshouchou",
    "iso:country":"JP",
    "wof:name":"722-2322",
    "wof:placetype":"postalcode"
},
  "geometry": {"coordinates":[133.19370000000001,34.2938],"type":"Point"}
}