{
  "type": "Feature",
  "properties": {
    "gn:adm1_name":"Tokushimaken",
    "gn:adm2_name":"Myouzaigun'Ishiichou",
    "gn:name":"Takahara(Higashitakahara)",
    "iso:country":"JP",
    "wof:name":"779-3205",
    "wof:placetype":"postalcode"
},
  "geometry": {"coordinates":[134.42160000000001,34.0803],"type":"Point"}
}