{
  "type": "Feature",
  "properties": {
    "gn:adm1_name":"Chibaken",
    "gn:adm2_name":"Sodegaurashi",
    "gn:name":"Kuranamidai",
    "iso:country":"JP",
    "wof:name":"299-0245",
    "wof:placetype":"postalcode"
},
  "geometry": {"coordinates":[139.9956,35.4414],"type":"Point"}
}