{
  "type": "Feature",
  "properties": {
    "gn:adm1_name":"Gunmaken",
    "gn:adm2_name":"Agatsumagunnakanojoumachi",
    "gn:name":"Ooduka",
    "iso:country":"JP",
    "wof:name":"377-0413",
    "wof:placetype":"postalcode"
},
  "geometry": {"coordinates":[138.88589999999999,36.6149],"type":"Point"}
}