{
  "type": "Feature",
  "properties": {
    "gn:adm1_name":"Oosakafu",
    "gn:adm2_name":"Kawachinaganoshi",
    "gn:name":"Takihata",
    "iso:country":"JP",
    "wof:name":"586-0072",
    "wof:placetype":"postalcode"
},
  "geometry": {"coordinates":[135.52619999999999,34.3874],"type":"Point"}
}