{
  "type": "Feature",
  "properties": {
    "gn:adm1_name":"Tottoriken",
    "gn:adm2_name":"Yazugunkoogechou",
    "gn:name":"Yamanoue",
    "iso:country":"JP",
    "wof:name":"680-0433",
    "wof:placetype":"postalcode"
},
  "geometry": {"coordinates":[134.28909999999999,35.4385],"type":"Point"}
}