{
  "type": "Feature",
  "properties": {
    "gn:adm1_name":"Yamaguchiken",
    "gn:adm2_name":"Kugagunyuuchou",
    "gn:name":"Terazako",
    "iso:country":"JP",
    "wof:name":"740-1401",
    "wof:placetype":"postalcode"
},
  "geometry": {"coordinates":[132.18129999999999,34.0418],"type":"Point"}
}