{
  "type": "Feature",
  "properties": {
    "gn:adm1_name":"Hyougoken",
    "gn:adm2_name":"Takaradukashi",
    "gn:name":"Chigusa",
    "iso:country":"JP",
    "wof:name":"665-0072",
    "wof:placetype":"postalcode"
},
  "geometry": {"coordinates":[135.34829999999999,34.7909],"type":"Point"}
}