{
  "type": "Feature",
  "properties": {
    "gn:adm1_name":"Toukyouto",
    "gn:adm2_name":"Setagayaku",
    "gn:name":"Kamata",
    "iso:country":"JP",
    "wof:name":"157-0077",
    "wof:placetype":"postalcode"
},
  "geometry": {"coordinates":[139.61340000000001,35.6197],"type":"Point"}
}