{
  "type": "Feature",
  "properties": {
    "gn:adm1_name":"Hiroshimaken",
    "gn:adm2_name":"Ootakeshi",
    "gn:name":"Ogata",
    "iso:country":"JP",
    "wof:name":"739-0623",
    "wof:placetype":"postalcode"
},
  "geometry": {"coordinates":[132.2201,34.239],"type":"Point"}
}