{
  "type": "Feature",
  "properties": {
    "gn:adm1_name":"Shimaneken",
    "gn:adm2_name":"Iishigunmitoyachou",
    "gn:name":"Otsukamiya",
    "iso:country":"JP",
    "wof:name":"690-2634",
    "wof:placetype":"postalcode"
},
  "geometry": {"coordinates":[132.83330000000001,35.2655],"type":"Point"}
}