{
  "type": "Feature",
  "properties": {
    "gn:adm1_name":"Kyoutofu",
    "gn:adm2_name":"Kyoutoshisakyouku",
    "gn:name":"Kitashirakawahigashikubotachou",
    "iso:country":"JP",
    "wof:name":"606-8285",
    "wof:placetype":"postalcode"
},
  "geometry": {"coordinates":[135.79220000000001,35.0289],"type":"Point"}
}