{
  "type": "Feature",
  "properties": {
    "gn:adm1_name":"Fukushimaken",
    "gn:adm2_name":"Shirakawashi",
    "gn:name":"Setohara",
    "iso:country":"JP",
    "wof:name":"961-0822",
    "wof:placetype":"postalcode"
},
  "geometry": {"coordinates":[140.2286,37.1017],"type":"Point"}
}