{
  "type": "Feature",
  "properties": {
    "gn:adm1_name":"Oosakafu",
    "gn:adm2_name":"Higashioosakashi",
    "gn:name":"Shibukawachou",
    "iso:country":"JP",
    "wof:name":"577-0836",
    "wof:placetype":"postalcode"
},
  "geometry": {"coordinates":[135.56309999999999,34.6462],"type":"Point"}
}