{
  "type": "Feature",
  "properties": {
    "gn:adm1_name":"Hyougoken",
    "gn:adm2_name":"Nishinomiyashi",
    "gn:name":"Uegahara8banchou",
    "iso:country":"JP",
    "wof:name":"662-0882",
    "wof:placetype":"postalcode"
},
  "geometry": {"coordinates":[135.34350000000001,34.7613],"type":"Point"}
}