{
  "type": "Feature",
  "properties": {
    "gn:adm1_name":"Oosakafu",
    "gn:adm2_name":"Sennangunkumatorichou",
    "gn:name":"Konya",
    "iso:country":"JP",
    "wof:name":"590-0412",
    "wof:placetype":"postalcode"
},
  "geometry": {"coordinates":[135.3494,34.4035],"type":"Point"}
}