{
  "type": "Feature",
  "properties": {
    "gn:adm1_name":"Okinawaken",
    "gn:adm2_name":"Miyakogun'Irabuchou",
    "gn:name":"Sawada",
    "iso:country":"JP",
    "wof:name":"906-0507",
    "wof:placetype":"postalcode"
},
  "geometry": {"coordinates":[125.1584,24.8369],"type":"Point"}
}