{
  "type": "Feature",
  "properties": {
    "gn:adm1_name":"Kanagawaken",
    "gn:adm2_name":"Yokosukashi",
    "gn:name":"Koyasu",
    "iso:country":"JP",
    "wof:name":"240-0106",
    "wof:placetype":"postalcode"
},
  "geometry": {"coordinates":[139.6078,35.2497],"type":"Point"}
}