{
  "type": "Feature",
  "properties": {
    "gn:adm1_name":"Miyagiken",
    "gn:adm2_name":"Shiroishishi",
    "gn:name":"Sumazugaike",
    "iso:country":"JP",
    "wof:name":"989-0271",
    "wof:placetype":"postalcode"
},
  "geometry": {"coordinates":[140.62549999999999,38.0076],"type":"Point"}
}