{
  "type": "Feature",
  "properties": {
    "gn:adm1_name":"Aichiken",
    "gn:adm2_name":"Kitashitaraguntoueichou",
    "gn:name":"Tsuki",
    "iso:country":"JP",
    "wof:name":"449-0212",
    "wof:placetype":"postalcode"
},
  "geometry": {"coordinates":[137.6645,35.077],"type":"Point"}
}