{
  "type": "Feature",
  "properties": {
    "gn:adm1_name":"Hiroshimaken",
    "gn:adm2_name":"Hiroshimashinishiku",
    "gn:name":"Inokuchimyoujin",
    "iso:country":"JP",
    "wof:name":"733-0841",
    "wof:placetype":"postalcode"
},
  "geometry": {"coordinates":[132.38929999999999,34.3716],"type":"Point"}
}