{
  "type": "Feature",
  "properties": {
    "gn:adm1_name":"Hyougoken",
    "gn:adm2_name":"Kakogun'Inamichou",
    "gn:name":"Kunioka",
    "iso:country":"JP",
    "wof:name":"675-1115",
    "wof:placetype":"postalcode"
},
  "geometry": {"coordinates":[134.91220000000001,34.7503],"type":"Point"}
}