{
  "type": "Feature",
  "properties": {
    "gn:adm1_name":"Niigataken",
    "gn:adm2_name":"Kitakanbaragunkurokawamura",
    "gn:name":"Oumishin",
    "iso:country":"JP",
    "wof:name":"959-2801",
    "wof:placetype":"postalcode"
},
  "geometry": {"coordinates":[139.43940000000001,38.0968],"type":"Point"}
}