{
  "type": "Feature",
  "properties": {
    "gn:adm1_name":"Niigataken",
    "gn:adm2_name":"Kitauonumagunsumonmura",
    "gn:name":"Matsukawa",
    "iso:country":"JP",
    "wof:name":"946-0214",
    "wof:placetype":"postalcode"
},
  "geometry": {"coordinates":[139.03299999999999,37.3182],"type":"Point"}
}