{
  "type": "Feature",
  "properties": {
    "gn:adm1_name":"Chibaken",
    "gn:adm2_name":"Abikoshi",
    "gn:name":"Furudo",
    "iso:country":"JP",
    "wof:name":"270-1111",
    "wof:placetype":"postalcode"
},
  "geometry": {"coordinates":[140.09309999999999,35.8697],"type":"Point"}
}