{
  "type": "Feature",
  "properties": {
    "gn:adm1_name":"Yamagataken",
    "gn:adm2_name":"Nishiokitamagun'Ogunimachi",
    "gn:name":"Matsuzaki",
    "iso:country":"JP",
    "wof:name":"999-1411",
    "wof:placetype":"postalcode"
},
  "geometry": {"coordinates":[139.7433,38.1226],"type":"Point"}
}