{
  "type": "Feature",
  "properties": {
    "gn:adm1_name":"Hyougoken",
    "gn:adm2_name":"Amagasakishi",
    "gn:name":"Genbankitanochou",
    "iso:country":"JP",
    "wof:name":"660-0872",
    "wof:placetype":"postalcode"
},
  "geometry": {"coordinates":[135.4084,34.7192],"type":"Point"}
}