{
  "type": "Feature",
  "properties": {
    "gn:adm1_name":"Chibaken",
    "gn:adm2_name":"Katoriguntounoshoumachi",
    "gn:name":"Ookubo",
    "iso:country":"JP",
    "wof:name":"289-0633",
    "wof:placetype":"postalcode"
},
  "geometry": {"coordinates":[140.6515,35.7933],"type":"Point"}
}