{
  "type": "Feature",
  "properties": {
    "gn:adm1_name":"Mieken",
    "gn:adm2_name":"Yokkaichishi",
    "gn:name":"Makinokidai",
    "iso:country":"JP",
    "wof:name":"512-1306",
    "wof:placetype":"postalcode"
},
  "geometry": {"coordinates":[136.56999999999999,35.0383],"type":"Point"}
}