{
  "type": "Feature",
  "properties": {
    "gn:adm1_name":"Shimaneken",
    "gn:adm2_name":"Hamadashi",
    "gn:name":"Nagasawachou",
    "iso:country":"JP",
    "wof:name":"697-0023",
    "wof:placetype":"postalcode"
},
  "geometry": {"coordinates":[132.09950000000001,34.9105],"type":"Point"}
}