{
  "type": "Feature",
  "properties": {
    "gn:adm1_name":"Saitamaken",
    "gn:adm2_name":"Asakashi",
    "gn:name":"Honchou",
    "iso:country":"JP",
    "wof:name":"351-0011",
    "wof:placetype":"postalcode"
},
  "geometry": {"coordinates":[139.59630000000001,35.7991],"type":"Point"}
}