{
  "type": "Feature",
  "properties": {
    "gn:adm1_name":"Niigataken",
    "gn:adm2_name":"Nakakanbaragunkosudomachi",
    "gn:name":"Yashiroda",
    "iso:country":"JP",
    "wof:name":"956-0113",
    "wof:placetype":"postalcode"
},
  "geometry": {"coordinates":[139.09729999999999,37.7473],"type":"Point"}
}