{
  "type": "Feature",
  "properties": {
    "gn:adm1_name":"Aichiken",
    "gn:adm2_name":"Nagoyashiminatoku",
    "gn:name":"Ishinchou",
    "iso:country":"JP",
    "wof:name":"455-0823",
    "wof:placetype":"postalcode"
},
  "geometry": {"coordinates":[136.84399999999999,35.1042],"type":"Point"}
}