{
  "type": "Feature",
  "properties": {
    "gn:adm1_name":"Fukuokaken",
    "gn:adm2_name":"Kasuyagunkasuyamachi",
    "gn:name":"Kamiookuma",
    "iso:country":"JP",
    "wof:name":"811-2301",
    "wof:placetype":"postalcode"
},
  "geometry": {"coordinates":[130.49420000000001,33.6288],"type":"Point"}
}