{
  "type": "Feature",
  "properties": {
    "gn:adm1_name":"Hiroshimaken",
    "gn:adm2_name":"Miharashi",
    "gn:name":"Sunamichou",
    "iso:country":"JP",
    "wof:name":"723-0031",
    "wof:placetype":"postalcode"
},
  "geometry": {"coordinates":[133.08330000000001,34.3683],"type":"Point"}
}