{
  "type": "Feature",
  "properties": {
    "gn:adm1_name":"Kumamotoken",
    "gn:adm2_name":"Asoguntakamorimachi",
    "gn:name":"Kamishikimi",
    "iso:country":"JP",
    "wof:name":"869-1601",
    "wof:placetype":"postalcode"
},
  "geometry": {"coordinates":[131.15430000000001,32.8586],"type":"Point"}
}