{
  "type": "Feature",
  "properties": {
    "gn:adm1_name":"Fukushimaken",
    "gn:adm2_name":"Kitakatashi",
    "gn:name":"Koshimaki",
    "iso:country":"JP",
    "wof:name":"966-0048",
    "wof:placetype":"postalcode"
},
  "geometry": {"coordinates":[139.8836,37.6533],"type":"Point"}
}