{
  "type": "Feature",
  "properties": {
    "gn:adm1_name":"Ehimeken",
    "gn:adm2_name":"Ochigunyugechou",
    "gn:name":"Sawadu",
    "iso:country":"JP",
    "wof:name":"794-2502",
    "wof:placetype":"postalcode"
},
  "geometry": {"coordinates":[133.21600000000001,34.2834],"type":"Point"}
}