{
  "type": "Feature",
  "properties": {
    "gn:adm1_name":"Okinawaken",
    "gn:adm2_name":"Kunigamigunnakijinson",
    "gn:name":"Ikanikeisaiganaibaai",
    "iso:country":"JP",
    "wof:name":"905-0400",
    "wof:placetype":"postalcode"
},
  "geometry": {"coordinates":[127.9571,26.6996],"type":"Point"}
}