{
  "type": "Feature",
  "properties": {
    "gn:adm1_name":"Yamagataken",
    "gn:adm2_name":"Nishiokitamagunshiratakamachi",
    "gn:name":"Shimoyama",
    "iso:country":"JP",
    "wof:name":"992-0862",
    "wof:placetype":"postalcode"
},
  "geometry": {"coordinates":[140.1002,38.2133],"type":"Point"}
}