{
  "type": "Feature",
  "properties": {
    "gn:adm1_name":"Oosakafu",
    "gn:adm2_name":"Takatsukishi",
    "gn:name":"Amakitanochou",
    "iso:country":"JP",
    "wof:name":"569-1108",
    "wof:placetype":"postalcode"
},
  "geometry": {"coordinates":[135.63149999999999,34.8624],"type":"Point"}
}