{
  "type": "Feature",
  "properties": {
    "gn:adm1_name":"Yamaguchiken",
    "gn:adm2_name":"Shimonosekishi",
    "gn:name":"Kamishinchichou",
    "iso:country":"JP",
    "wof:name":"750-0061",
    "wof:placetype":"postalcode"
},
  "geometry": {"coordinates":[130.91890000000001,33.959],"type":"Point"}
}