{
  "type": "Feature",
  "properties": {
    "gn:adm1_name":"Kanagawaken",
    "gn:adm2_name":"Fujisawashi",
    "gn:name":"Osogou",
    "iso:country":"JP",
    "wof:name":"252-0825",
    "wof:placetype":"postalcode"
},
  "geometry": {"coordinates":[139.4066,35.3895],"type":"Point"}
}