{
  "type": "Feature",
  "properties": {
    "gn:adm1_name":"Tochigiken",
    "gn:adm2_name":"Oyamashi",
    "gn:name":"Arai",
    "iso:country":"JP",
    "wof:name":"323-0013",
    "wof:placetype":"postalcode"
},
  "geometry": {"coordinates":[139.83760000000001,36.3539],"type":"Point"}
}