{
  "type": "Feature",
  "properties": {
    "gn:adm1_name":"Tottoriken",
    "gn:adm2_name":"Tottorishi",
    "gn:name":"Yoshinari",
    "iso:country":"JP",
    "wof:name":"680-0864",
    "wof:placetype":"postalcode"
},
  "geometry": {"coordinates":[134.2242,35.4844],"type":"Point"}
}