{
  "type": "Feature",
  "properties": {
    "gn:adm1_name":"Shimaneken",
    "gn:adm2_name":"Nakagunyasakamura",
    "gn:name":"Tochigi",
    "iso:country":"JP",
    "wof:name":"697-1201",
    "wof:placetype":"postalcode"
},
  "geometry": {"coordinates":[132.10040000000001,34.8065],"type":"Point"}
}