{
  "type": "Feature",
  "properties": {
    "gn:adm1_name":"Tottoriken",
    "gn:adm2_name":"Tottorishi",
    "gn:name":"Matsugami",
    "iso:country":"JP",
    "wof:name":"680-1423",
    "wof:placetype":"postalcode"
},
  "geometry": {"coordinates":[134.1327,35.4412],"type":"Point"}
}