{
  "type": "Feature",
  "properties": {
    "gn:adm1_name":"Oosakafu",
    "gn:adm2_name":"Izumisanoshi",
    "gn:name":"Rinkuuouraikita",
    "iso:country":"JP",
    "wof:name":"598-0048",
    "wof:placetype":"postalcode"
},
  "geometry": {"coordinates":[135.30269999999999,34.4128],"type":"Point"}
}