{
  "type": "Feature",
  "properties": {
    "gn:adm1_name":"Fukuokaken",
    "gn:adm2_name":"Fukuokashisawaraku",
    "gn:name":"Kanatake",
    "iso:country":"JP",
    "wof:name":"811-1124",
    "wof:placetype":"postalcode"
},
  "geometry": {"coordinates":[130.34280000000001,33.5517],"type":"Point"}
}