{
  "type": "Feature",
  "properties": {
    "gn:adm1_name":"Hyougoken",
    "gn:adm2_name":"Toyookashi",
    "gn:name":"Dasaka",
    "iso:country":"JP",
    "wof:name":"668-0866",
    "wof:placetype":"postalcode"
},
  "geometry": {"coordinates":[134.84739999999999,35.5182],"type":"Point"}
}