{
  "type": "Feature",
  "properties": {
    "gn:adm1_name":"Shigaken",
    "gn:adm2_name":"Oumihachimanshi",
    "gn:name":"Shiratorichou",
    "iso:country":"JP",
    "wof:name":"523-0032",
    "wof:placetype":"postalcode"
},
  "geometry": {"coordinates":[136.09690000000001,35.121],"type":"Point"}
}