{
  "type": "Feature",
  "properties": {
    "gn:adm1_name":"Okinawaken",
    "gn:adm2_name":"Nakagamigunkitanakagusukuson",
    "gn:name":"Atsuta",
    "iso:country":"JP",
    "wof:name":"901-2313",
    "wof:placetype":"postalcode"
},
  "geometry": {"coordinates":[127.80710000000001,26.2961],"type":"Point"}
}