{
  "type": "Feature",
  "properties": {
    "gn:adm1_name":"Gifuken",
    "gn:adm2_name":"Gujougunhachimanchou",
    "gn:name":"Ikanikeisaiganaibaai",
    "iso:country":"JP",
    "wof:name":"501-4200",
    "wof:placetype":"postalcode"
},
  "geometry": {"coordinates":[136.85769999999999,35.8799],"type":"Point"}
}