{
  "type": "Feature",
  "properties": {
    "gn:adm1_name":"Hiroshimaken",
    "gn:adm2_name":"Miharashi",
    "gn:name":"Kainochou",
    "iso:country":"JP",
    "wof:name":"723-0043",
    "wof:placetype":"postalcode"
},
  "geometry": {"coordinates":[133.08369999999999,34.3833],"type":"Point"}
}