{
  "type": "Feature",
  "properties": {
    "gn:adm1_name":"Kumamotoken",
    "gn:adm2_name":"Shimomashikiguntomochimachi",
    "gn:name":"Kousabira",
    "iso:country":"JP",
    "wof:name":"861-4706",
    "wof:placetype":"postalcode"
},
  "geometry": {"coordinates":[130.88059999999999,32.6463],"type":"Point"}
}