{
  "type": "Feature",
  "properties": {
    "gn:adm1_name":"Saitamaken",
    "gn:adm2_name":"Fujimishi",
    "gn:name":"Nanbatashinden",
    "iso:country":"JP",
    "wof:name":"354-0003",
    "wof:placetype":"postalcode"
},
  "geometry": {"coordinates":[139.57380000000001,35.8635],"type":"Point"}
}