{
  "type": "Feature",
  "properties": {
    "gn:adm1_name":"Mieken",
    "gn:adm2_name":"Owaseshi",
    "gn:name":"Nakaimachi",
    "iso:country":"JP",
    "wof:name":"519-3605",
    "wof:placetype":"postalcode"
},
  "geometry": {"coordinates":[136.19749999999999,34.0753],"type":"Point"}
}