{
  "type": "Feature",
  "properties": {
    "gn:adm1_name":"Gifuken",
    "gn:adm2_name":"Sekishi",
    "gn:name":"Azakurayama",
    "iso:country":"JP",
    "wof:name":"501-3807",
    "wof:placetype":"postalcode"
},
  "geometry": {"coordinates":[136.9161,35.4889],"type":"Point"}
}