{
  "type": "Feature",
  "properties": {
    "gn:adm1_name":"Gifuken",
    "gn:adm2_name":"Enagun'Akechichou",
    "gn:name":"Ooizumi",
    "iso:country":"JP",
    "wof:name":"509-7721",
    "wof:placetype":"postalcode"
},
  "geometry": {"coordinates":[137.37029999999999,35.3149],"type":"Point"}
}