{
  "type": "Feature",
  "properties": {
    "gn:adm1_name":"Ehimeken",
    "gn:adm2_name":"Kawanoeshi",
    "gn:name":"Kanadachoukanagawa",
    "iso:country":"JP",
    "wof:name":"799-0123",
    "wof:placetype":"postalcode"
},
  "geometry": {"coordinates":[133.59649999999999,33.9838],"type":"Point"}
}