{
  "type": "Feature",
  "properties": {
    "gn:adm1_name":"Hyougoken",
    "gn:adm2_name":"Yabugunyoukachou",
    "gn:name":"Shukunami",
    "iso:country":"JP",
    "wof:name":"667-0003",
    "wof:placetype":"postalcode"
},
  "geometry": {"coordinates":[134.77950000000001,35.4377],"type":"Point"}
}