{
  "type": "Feature",
  "properties": {
    "gn:adm1_name":"Hyougoken",
    "gn:adm2_name":"Koubeshihigashinadaku",
    "gn:name":"Mikagetsukamachi",
    "iso:country":"JP",
    "wof:name":"658-0044",
    "wof:placetype":"postalcode"
},
  "geometry": {"coordinates":[135.24760000000001,34.7111],"type":"Point"}
}