{
  "type": "Feature",
  "properties": {
    "gn:adm1_name":"Chibaken",
    "gn:adm2_name":"Ichiharashi",
    "gn:name":"Isogaya",
    "iso:country":"JP",
    "wof:name":"290-0204",
    "wof:placetype":"postalcode"
},
  "geometry": {"coordinates":[140.13589999999999,35.4551],"type":"Point"}
}