{
  "type": "Feature",
  "properties": {
    "gn:adm1_name":"Mieken",
    "gn:adm2_name":"Ichishigun'Ichishichou",
    "gn:name":"Iu",
    "iso:country":"JP",
    "wof:name":"515-2523",
    "wof:placetype":"postalcode"
},
  "geometry": {"coordinates":[136.3845,34.6474],"type":"Point"}
}