{
  "type": "Feature",
  "properties": {
    "gn:adm1_name":"Hyougoken",
    "gn:adm2_name":"Izushiguntantouchou",
    "gn:name":"Hata",
    "iso:country":"JP",
    "wof:name":"668-0303",
    "wof:placetype":"postalcode"
},
  "geometry": {"coordinates":[134.9246,35.4463],"type":"Point"}
}