{
  "type": "Feature",
  "properties": {
    "gn:adm1_name":"Gifuken",
    "gn:adm2_name":"Gifushi",
    "gn:name":"Gyokuseichou",
    "iso:country":"JP",
    "wof:name":"500-8846",
    "wof:placetype":"postalcode"
},
  "geometry": {"coordinates":[136.75489999999999,35.4139],"type":"Point"}
}