{
  "type": "Feature",
  "properties": {
    "gn:adm1_name":"Ooitaken",
    "gn:adm2_name":"Oonogunkiyokawamura",
    "gn:name":"Hiraishi",
    "iso:country":"JP",
    "wof:name":"879-6913",
    "wof:placetype":"postalcode"
},
  "geometry": {"coordinates":[131.4769,32.9162],"type":"Point"}
}