{
  "type": "Feature",
  "properties": {
    "gn:adm1_name":"Fukuokaken",
    "gn:adm2_name":"Munakatashi",
    "gn:name":"Kurieito",
    "iso:country":"JP",
    "wof:name":"811-4184",
    "wof:placetype":"postalcode"
},
  "geometry": {"coordinates":[130.5642,33.8137],"type":"Point"}
}