{
  "type": "Feature",
  "properties": {
    "gn:adm1_name":"Ibarakiken",
    "gn:adm2_name":"Namegataguntamatsukurimachi",
    "gn:name":"Wakaumi",
    "iso:country":"JP",
    "wof:name":"311-3502",
    "wof:placetype":"postalcode"
},
  "geometry": {"coordinates":[140.42789999999999,36.1257],"type":"Point"}
}