{
  "type": "Feature",
  "properties": {
    "gn:adm1_name":"Kyoutofu",
    "gn:adm2_name":"Fukuchiyamashi",
    "gn:name":"Iwasaki",
    "iso:country":"JP",
    "wof:name":"620-0831",
    "wof:placetype":"postalcode"
},
  "geometry": {"coordinates":[135.1891,35.2632],"type":"Point"}
}