{
  "type": "Feature",
  "properties": {
    "gn:adm1_name":"Shigaken",
    "gn:adm2_name":"Kanzakigun'Eigenjichou",
    "gn:name":"Shinde",
    "iso:country":"JP",
    "wof:name":"527-0225",
    "wof:placetype":"postalcode"
},
  "geometry": {"coordinates":[136.2646,35.0666],"type":"Point"}
}