{
  "type": "Feature",
  "properties": {
    "gn:adm1_name":"Okayamaken",
    "gn:adm2_name":"Okayamashi",
    "gn:name":"Naganuma",
    "iso:country":"JP",
    "wof:name":"704-8131",
    "wof:placetype":"postalcode"
},
  "geometry": {"coordinates":[134.06540000000001,34.6413],"type":"Point"}
}