{
  "type": "Feature",
  "properties": {
    "gn:adm1_name":"Shigaken",
    "gn:adm2_name":"Ikagunyogochou",
    "gn:name":"Shimoyogo",
    "iso:country":"JP",
    "wof:name":"529-0521",
    "wof:placetype":"postalcode"
},
  "geometry": {"coordinates":[136.2081,35.5335],"type":"Point"}
}