{
  "type": "Feature",
  "properties": {
    "gn:adm1_name":"Shizuokaken",
    "gn:adm2_name":"Shizuokashi",
    "gn:name":"Shimizuoouchishinden",
    "iso:country":"JP",
    "wof:name":"424-0062",
    "wof:placetype":"postalcode"
},
  "geometry": {"coordinates":[138.45670000000001,35.0264],"type":"Point"}
}