{
  "type": "Feature",
  "properties": {
    "gn:adm1_name":"Hyougoken",
    "gn:adm2_name":"Ibogunshinguuchou",
    "gn:name":"Nakanoshou",
    "iso:country":"JP",
    "wof:name":"679-4327",
    "wof:placetype":"postalcode"
},
  "geometry": {"coordinates":[134.5428,34.9009],"type":"Point"}
}