{
  "type": "Feature",
  "properties": {
    "gn:adm1_name":"Kanagawaken",
    "gn:adm2_name":"Yokohamashitotsukaku",
    "gn:name":"Shimokuratachou",
    "iso:country":"JP",
    "wof:name":"244-0815",
    "wof:placetype":"postalcode"
},
  "geometry": {"coordinates":[139.54079999999999,35.3844],"type":"Point"}
}