{
  "type": "Feature",
  "properties": {
    "gn:adm1_name":"Aichiken",
    "gn:adm2_name":"Handashi",
    "gn:name":"Nakaokudachou",
    "iso:country":"JP",
    "wof:name":"475-0035",
    "wof:placetype":"postalcode"
},
  "geometry": {"coordinates":[136.9546,34.8992],"type":"Point"}
}