{
  "type": "Feature",
  "properties": {
    "gn:adm1_name":"Gunmaken",
    "gn:adm2_name":"Ouragunchiyodamachi",
    "gn:name":"Akaiwa",
    "iso:country":"JP",
    "wof:name":"370-0503",
    "wof:placetype":"postalcode"
},
  "geometry": {"coordinates":[139.44390000000001,36.2151],"type":"Point"}
}