{
  "type": "Feature",
  "properties": {
    "gn:adm1_name":"Okayamaken",
    "gn:adm2_name":"Tomatagun'Okutsuchou",
    "gn:name":"Nagatou",
    "iso:country":"JP",
    "wof:name":"708-0502",
    "wof:placetype":"postalcode"
},
  "geometry": {"coordinates":[133.93029999999999,35.2404],"type":"Point"}
}