{
  "type": "Feature",
  "properties": {
    "gn:adm1_name":"Toyamaken",
    "gn:adm2_name":"Toyamashi",
    "gn:name":"Iwasebunkamachi",
    "iso:country":"JP",
    "wof:name":"931-8353",
    "wof:placetype":"postalcode"
},
  "geometry": {"coordinates":[137.23159999999999,36.7559],"type":"Point"}
}