{
  "type": "Feature",
  "properties": {
    "gn:adm1_name":"Miyagiken",
    "gn:adm2_name":"Kamigunkamimachi",
    "gn:name":"Jou",
    "iso:country":"JP",
    "wof:name":"981-4272",
    "wof:placetype":"postalcode"
},
  "geometry": {"coordinates":[140.85579999999999,38.5809],"type":"Point"}
}