{
  "type": "Feature",
  "properties": {
    "gn:adm1_name":"Ishikawaken",
    "gn:adm2_name":"Kahokuguntsubatamachi",
    "gn:name":"Yamamori",
    "iso:country":"JP",
    "wof:name":"929-0414",
    "wof:placetype":"postalcode"
},
  "geometry": {"coordinates":[136.80529999999999,36.6637],"type":"Point"}
}