{
  "type": "Feature",
  "properties": {
    "gn:adm1_name":"Saitamaken",
    "gn:adm2_name":"Kawaguchishi",
    "gn:name":"Maenoshuku",
    "iso:country":"JP",
    "wof:name":"334-0065",
    "wof:placetype":"postalcode"
},
  "geometry": {"coordinates":[139.75999999999999,35.833],"type":"Point"}
}