{
  "type": "Feature",
  "properties": {
    "gn:adm1_name":"Fukushimaken",
    "gn:adm2_name":"Futabagunnamiemachi",
    "gn:name":"Ikanikeisaiganaibaai",
    "iso:country":"JP",
    "wof:name":"979-1500",
    "wof:placetype":"postalcode"
},
  "geometry": {"coordinates":[140.99420000000001,37.4909],"type":"Point"}
}