{
  "type": "Feature",
  "properties": {
    "gn:adm1_name":"Saitamaken",
    "gn:adm2_name":"Yoshikawashi",
    "gn:name":"Tomishinden",
    "iso:country":"JP",
    "wof:name":"342-0037",
    "wof:placetype":"postalcode"
},
  "geometry": {"coordinates":[139.86199999999999,35.8755],"type":"Point"}
}