{
  "type": "Feature",
  "properties": {
    "gn:adm1_name":"Nagasakiken",
    "gn:adm2_name":"Nishisonogigunkouyagichou",
    "gn:name":"Kouyagichouichien",
    "iso:country":"JP",
    "wof:name":"851-0310",
    "wof:placetype":"postalcode"
},
  "geometry": {"coordinates":[129.81100000000001,32.6897],"type":"Point"}
}