{
  "type": "Feature",
  "properties": {
    "gn:adm1_name":"Kouchiken",
    "gn:adm2_name":"Agawagun'Inochou",
    "gn:name":"Edagawa",
    "iso:country":"JP",
    "wof:name":"781-2120",
    "wof:placetype":"postalcode"
},
  "geometry": {"coordinates":[133.45590000000001,33.5539],"type":"Point"}
}