{
  "type": "Feature",
  "properties": {
    "gn:adm1_name":"Gunmaken",
    "gn:adm2_name":"Kanragunshimonitamachi",
    "gn:name":"Nakaosaka",
    "iso:country":"JP",
    "wof:name":"370-2622",
    "wof:placetype":"postalcode"
},
  "geometry": {"coordinates":[138.7593,36.2367],"type":"Point"}
}