{
  "type": "Feature",
  "properties": {
    "gn:adm1_name":"Chibaken",
    "gn:adm2_name":"Kisaradushi",
    "gn:name":"Nagaisaku",
    "iso:country":"JP",
    "wof:name":"292-0053",
    "wof:placetype":"postalcode"
},
  "geometry": {"coordinates":[139.94499999999999,35.3896],"type":"Point"}
}