{
  "type": "Feature",
  "properties": {
    "gn:adm1_name":"Toukyouto",
    "gn:adm2_name":"Kitaku",
    "gn:name":"Akabanekita",
    "iso:country":"JP",
    "wof:name":"115-0052",
    "wof:placetype":"postalcode"
},
  "geometry": {"coordinates":[139.70910000000001,35.7847],"type":"Point"}
}