{
  "type": "Feature",
  "properties": {
    "gn:adm1_name":"Hiroshimaken",
    "gn:adm2_name":"Ootakeshi",
    "gn:name":"Yubunechou",
    "iso:country":"JP",
    "wof:name":"739-0655",
    "wof:placetype":"postalcode"
},
  "geometry": {"coordinates":[132.21969999999999,34.2521],"type":"Point"}
}