{
  "type": "Feature",
  "properties": {
    "gn:adm1_name":"Kumamotoken",
    "gn:adm2_name":"Yatsushiroshi",
    "gn:name":"Hinaguhamamachi",
    "iso:country":"JP",
    "wof:name":"869-5137",
    "wof:placetype":"postalcode"
},
  "geometry": {"coordinates":[130.5762,32.4345],"type":"Point"}
}