{
  "type": "Feature",
  "properties": {
    "gn:adm1_name":"Fukushimaken",
    "gn:adm2_name":"Aiduwakamatsushi",
    "gn:name":"Ootomachioyahara",
    "iso:country":"JP",
    "wof:name":"969-5143",
    "wof:placetype":"postalcode"
},
  "geometry": {"coordinates":[139.9239,37.3827],"type":"Point"}
}