{
  "type": "Feature",
  "properties": {
    "gn:adm1_name":"Yamanashiken",
    "gn:adm2_name":"Higashiyatsushirogun'Ichinomiyachou",
    "gn:name":"Ichinomiya",
    "iso:country":"JP",
    "wof:name":"405-0056",
    "wof:placetype":"postalcode"
},
  "geometry": {"coordinates":[138.69720000000001,35.6477],"type":"Point"}
}