{
  "type": "Feature",
  "properties": {
    "gn:adm1_name":"Fukuiken",
    "gn:adm2_name":"Tsurugashi",
    "gn:name":"Tone",
    "iso:country":"JP",
    "wof:name":"914-0313",
    "wof:placetype":"postalcode"
},
  "geometry": {"coordinates":[136.1438,35.6046],"type":"Point"}
}