{
  "type": "Feature",
  "properties": {
    "gn:adm1_name":"Fukuokaken",
    "gn:adm2_name":"Kitakyuushuushikokuraminamiku",
    "gn:name":"Tokuyoshiminami",
    "iso:country":"JP",
    "wof:name":"803-0279",
    "wof:placetype":"postalcode"
},
  "geometry": {"coordinates":[130.852,33.8106],"type":"Point"}
}