{
  "type": "Feature",
  "properties": {
    "gn:adm1_name":"Aichiken",
    "gn:adm2_name":"Inazawashi",
    "gn:name":"Oriduaburadenchou",
    "iso:country":"JP",
    "wof:name":"492-8081",
    "wof:placetype":"postalcode"
},
  "geometry": {"coordinates":[136.82820000000001,35.2517],"type":"Point"}
}