{
  "type": "Feature",
  "properties": {
    "gn:adm1_name":"Shimaneken",
    "gn:adm2_name":"Oodashi",
    "gn:name":"Nagahisachounagahisa",
    "iso:country":"JP",
    "wof:name":"694-0041",
    "wof:placetype":"postalcode"
},
  "geometry": {"coordinates":[132.4915,35.2007],"type":"Point"}
}