{
  "type": "Feature",
  "properties": {
    "gn:adm1_name":"Shigaken",
    "gn:adm2_name":"Oumihachimanshi",
    "gn:name":"Takakaichouhigashi",
    "iso:country":"JP",
    "wof:name":"523-0897",
    "wof:placetype":"postalcode"
},
  "geometry": {"coordinates":[136.10640000000001,35.1243],"type":"Point"}
}