{
  "type": "Feature",
  "properties": {
    "gn:adm1_name":"Kagoshimaken",
    "gn:adm2_name":"Kumagegunnakatanechou",
    "gn:name":"Noma",
    "iso:country":"JP",
    "wof:name":"891-3604",
    "wof:placetype":"postalcode"
},
  "geometry": {"coordinates":[130.95939999999999,30.5331],"type":"Point"}
}