{
  "type": "Feature",
  "properties": {
    "gn:adm1_name":"Shigaken",
    "gn:adm2_name":"Ikagunkinomotochou",
    "gn:name":"Ooto",
    "iso:country":"JP",
    "wof:name":"529-0431",
    "wof:placetype":"postalcode"
},
  "geometry": {"coordinates":[136.20089999999999,35.5024],"type":"Point"}
}