{
  "type": "Feature",
  "properties": {
    "gn:adm1_name":"Niigataken",
    "gn:adm2_name":"Shibatashi",
    "gn:name":"Oosaki",
    "iso:country":"JP",
    "wof:name":"957-0043",
    "wof:placetype":"postalcode"
},
  "geometry": {"coordinates":[139.35509999999999,37.9027],"type":"Point"}
}