{
  "type": "Feature",
  "properties": {
    "gn:adm1_name":"Hyougoken",
    "gn:adm2_name":"Kanzakigun'Ichikawachou",
    "gn:name":"Tani",
    "iso:country":"JP",
    "wof:name":"679-2326",
    "wof:placetype":"postalcode"
},
  "geometry": {"coordinates":[134.74969999999999,35.0067],"type":"Point"}
}