{
  "type": "Feature",
  "properties": {
    "gn:adm1_name":"Yamanashiken",
    "gn:adm2_name":"Tsurushi",
    "gn:name":"Asahisoshi",
    "iso:country":"JP",
    "wof:name":"402-0015",
    "wof:placetype":"postalcode"
},
  "geometry": {"coordinates":[138.98519999999999,35.5626],"type":"Point"}
}