{
  "type": "Feature",
  "properties": {
    "gn:adm1_name":"Oosakafu",
    "gn:adm2_name":"Toyonakashi",
    "gn:name":"Hirotachou",
    "iso:country":"JP",
    "wof:name":"561-0863",
    "wof:placetype":"postalcode"
},
  "geometry": {"coordinates":[135.4812,34.7802],"type":"Point"}
}