{
  "type": "Feature",
  "properties": {
    "gn:adm1_name":"Aichiken",
    "gn:adm2_name":"Nagoyashichikusaku",
    "gn:name":"Hanadachou",
    "iso:country":"JP",
    "wof:name":"464-0857",
    "wof:placetype":"postalcode"
},
  "geometry": {"coordinates":[136.95320000000001,35.1706],"type":"Point"}
}