{
  "type": "Feature",
  "properties": {
    "gn:adm1_name":"Saitamaken",
    "gn:adm2_name":"Higashimatsuyamashi",
    "gn:name":"Kamigarako",
    "iso:country":"JP",
    "wof:name":"355-0077",
    "wof:placetype":"postalcode"
},
  "geometry": {"coordinates":[139.3425,36.0352],"type":"Point"}
}