{
  "type": "Feature",
  "properties": {
    "gn:adm1_name":"Sagaken",
    "gn:adm2_name":"Sagagunyamatochou",
    "gn:name":"Ikenoue",
    "iso:country":"JP",
    "wof:name":"840-0212",
    "wof:placetype":"postalcode"
},
  "geometry": {"coordinates":[130.25110000000001,33.2925],"type":"Point"}
}