{
  "type": "Feature",
  "properties": {
    "gn:adm1_name":"Mieken",
    "gn:adm2_name":"Uenoshi",
    "gn:name":"Hane",
    "iso:country":"JP",
    "wof:name":"518-0006",
    "wof:placetype":"postalcode"
},
  "geometry": {"coordinates":[136.14920000000001,34.7782],"type":"Point"}
}