{
  "type": "Feature",
  "properties": {
    "gn:adm1_name":"Gifuken",
    "gn:adm2_name":"Sekishi",
    "gn:name":"Hiragachou",
    "iso:country":"JP",
    "wof:name":"501-3821",
    "wof:placetype":"postalcode"
},
  "geometry": {"coordinates":[136.93770000000001,35.4861],"type":"Point"}
}