{
  "type": "Feature",
  "properties": {
    "gn:adm1_name":"Tochigiken",
    "gn:adm2_name":"Ashikagashi",
    "gn:name":"Toori",
    "iso:country":"JP",
    "wof:name":"326-0814",
    "wof:placetype":"postalcode"
},
  "geometry": {"coordinates":[139.44640000000001,36.336],"type":"Point"}
}