{
  "type": "Feature",
  "properties": {
    "gn:adm1_name":"Ishikawaken",
    "gn:adm2_name":"Kagashi",
    "gn:name":"Tokiwadai",
    "iso:country":"JP",
    "wof:name":"922-0427",
    "wof:placetype":"postalcode"
},
  "geometry": {"coordinates":[136.35720000000001,36.3268],"type":"Point"}
}