{
  "type": "Feature",
  "properties": {
    "gn:adm1_name":"Kanagawaken",
    "gn:adm2_name":"Kawasakishinakaharaku",
    "gn:name":"Kiduki",
    "iso:country":"JP",
    "wof:name":"211-0025",
    "wof:placetype":"postalcode"
},
  "geometry": {"coordinates":[139.65309999999999,35.5631],"type":"Point"}
}