{
  "type": "Feature",
  "properties": {
    "gn:adm1_name":"Fukuiken",
    "gn:adm2_name":"Sakaigunkanaduchou",
    "gn:name":"Aonoki",
    "iso:country":"JP",
    "wof:name":"919-0814",
    "wof:placetype":"postalcode"
},
  "geometry": {"coordinates":[136.25239999999999,36.2335],"type":"Point"}
}