{
  "type": "Feature",
  "properties": {
    "gn:adm1_name":"Miyagiken",
    "gn:adm2_name":"Kuriharagunkannarichou",
    "gn:name":"Fujiwatato",
    "iso:country":"JP",
    "wof:name":"989-4803",
    "wof:placetype":"postalcode"
},
  "geometry": {"coordinates":[141.09119999999999,38.8501],"type":"Point"}
}