{
  "type": "Feature",
  "properties": {
    "gn:adm1_name":"Toyamaken",
    "gn:adm2_name":"Nakaniikawaguntateyamamachi",
    "gn:name":"Fujihashi",
    "iso:country":"JP",
    "wof:name":"930-1404",
    "wof:placetype":"postalcode"
},
  "geometry": {"coordinates":[137.3237,36.6538],"type":"Point"}
}