{
  "type": "Feature",
  "properties": {
    "gn:adm1_name":"Fukuokaken",
    "gn:adm2_name":"Kasuyagun'Umimachi",
    "gn:name":"Shioujizaka",
    "iso:country":"JP",
    "wof:name":"811-2103",
    "wof:placetype":"postalcode"
},
  "geometry": {"coordinates":[130.51929999999999,33.5616],"type":"Point"}
}