{
  "type": "Feature",
  "properties": {
    "gn:adm1_name":"Yamaguchiken",
    "gn:adm2_name":"Shimonosekishi",
    "gn:name":"Ida",
    "iso:country":"JP",
    "wof:name":"751-0881",
    "wof:placetype":"postalcode"
},
  "geometry": {"coordinates":[130.96879999999999,34.0515],"type":"Point"}
}