{
  "type": "Feature",
  "properties": {
    "gn:adm1_name":"Shimaneken",
    "gn:adm2_name":"Hamadashi",
    "gn:name":"Biwamachi",
    "iso:country":"JP",
    "wof:name":"697-0025",
    "wof:placetype":"postalcode"
},
  "geometry": {"coordinates":[132.08709999999999,34.8999],"type":"Point"}
}