{
  "type": "Feature",
  "properties": {
    "gn:adm1_name":"Chibaken",
    "gn:adm2_name":"Isumigun'Onjukumachi",
    "gn:name":"Suka",
    "iso:country":"JP",
    "wof:name":"299-5106",
    "wof:placetype":"postalcode"
},
  "geometry": {"coordinates":[140.3509,35.1863],"type":"Point"}
}