{
  "type": "Feature",
  "properties": {
    "gn:adm1_name":"Fukuokaken",
    "gn:adm2_name":"Kasuyagunshimemachi",
    "gn:name":"Yoshihara",
    "iso:country":"JP",
    "wof:name":"811-2208",
    "wof:placetype":"postalcode"
},
  "geometry": {"coordinates":[130.48650000000001,33.577],"type":"Point"}
}