{
  "type": "Feature",
  "properties": {
    "gn:adm1_name":"Yamagataken",
    "gn:adm2_name":"Tsuruokashi",
    "gn:name":"Barashinden",
    "iso:country":"JP",
    "wof:name":"997-1111",
    "wof:placetype":"postalcode"
},
  "geometry": {"coordinates":[139.8023,38.8041],"type":"Point"}
}