{
  "type": "Feature",
  "properties": {
    "gn:adm1_name":"Shizuokaken",
    "gn:adm2_name":"Hamamatsushi",
    "gn:name":"Ichinochou",
    "iso:country":"JP",
    "wof:name":"435-0051",
    "wof:placetype":"postalcode"
},
  "geometry": {"coordinates":[137.7722,34.7475],"type":"Point"}
}