{
  "type": "Feature",
  "properties": {
    "gn:adm1_name":"Naganoken",
    "gn:adm2_name":"Kamitakaigun'Obusemachi",
    "gn:name":"Sannoujima",
    "iso:country":"JP",
    "wof:name":"381-0205",
    "wof:placetype":"postalcode"
},
  "geometry": {"coordinates":[138.3031,36.7018],"type":"Point"}
}