{
  "type": "Feature",
  "properties": {
    "gn:adm1_name":"Aichiken",
    "gn:adm2_name":"Inuyamashi",
    "gn:name":"Maeharaajika",
    "iso:country":"JP",
    "wof:name":"484-0062",
    "wof:placetype":"postalcode"
},
  "geometry": {"coordinates":[136.9752,35.3573],"type":"Point"}
}