{
  "type": "Feature",
  "properties": {
    "gn:adm1_name":"Okayamaken",
    "gn:adm2_name":"Soujashi",
    "gn:name":"Akahama",
    "iso:country":"JP",
    "wof:name":"719-1121",
    "wof:placetype":"postalcode"
},
  "geometry": {"coordinates":[133.79769999999999,34.6833],"type":"Point"}
}