{
  "type": "Feature",
  "properties": {
    "gn:adm1_name":"Hiroshimaken",
    "gn:adm2_name":"Futamigunfunoson",
    "gn:name":"Kamifuno",
    "iso:country":"JP",
    "wof:name":"728-0201",
    "wof:placetype":"postalcode"
},
  "geometry": {"coordinates":[132.7826,34.8876],"type":"Point"}
}