{
  "type": "Feature",
  "properties": {
    "gn:adm1_name":"Miyagiken",
    "gn:adm2_name":"Sendaishiaobaku",
    "gn:name":"Fujimatsu",
    "iso:country":"JP",
    "wof:name":"981-0921",
    "wof:placetype":"postalcode"
},
  "geometry": {"coordinates":[140.8734,38.2968],"type":"Point"}
}