{
  "type": "Feature",
  "properties": {
    "gn:adm1_name":"Okayamaken",
    "gn:adm2_name":"Tsukubogunyamateson",
    "gn:name":"Shuku",
    "iso:country":"JP",
    "wof:name":"719-1161",
    "wof:placetype":"postalcode"
},
  "geometry": {"coordinates":[133.78389999999999,34.6609],"type":"Point"}
}