{
  "type": "Feature",
  "properties": {
    "gn:adm1_name":"Aichiken",
    "gn:adm2_name":"Nishikasugaigunnishibiwajimachou",
    "gn:name":"Higashirokkenmachi",
    "iso:country":"JP",
    "wof:name":"452-0043",
    "wof:placetype":"postalcode"
},
  "geometry": {"coordinates":[136.8646,35.1936],"type":"Point"}
}