{
  "type": "Feature",
  "properties": {
    "gn:adm1_name":"Oosakafu",
    "gn:adm2_name":"Minooshi",
    "gn:name":"Onoharanishi",
    "iso:country":"JP",
    "wof:name":"562-0032",
    "wof:placetype":"postalcode"
},
  "geometry": {"coordinates":[135.5104,34.8327],"type":"Point"}
}