{
  "type": "Feature",
  "properties": {
    "gn:adm1_name":"Aichiken",
    "gn:adm2_name":"Nakashimagunsobuechou",
    "gn:name":"Nishiunomoto",
    "iso:country":"JP",
    "wof:name":"495-0034",
    "wof:placetype":"postalcode"
},
  "geometry": {"coordinates":[136.6996,35.2402],"type":"Point"}
}