{
  "type": "Feature",
  "properties": {
    "gn:adm1_name":"Kyoutofu",
    "gn:adm2_name":"Kyoutoshifushimiku",
    "gn:name":"Shimotobakoyanagichou",
    "iso:country":"JP",
    "wof:name":"612-8385",
    "wof:placetype":"postalcode"
},
  "geometry": {"coordinates":[135.74870000000001,34.9331],"type":"Point"}
}