{
  "type": "Feature",
  "properties": {
    "gn:adm1_name":"Chibaken",
    "gn:adm2_name":"Choushishi",
    "gn:name":"Yawatachou",
    "iso:country":"JP",
    "wof:name":"288-0803",
    "wof:placetype":"postalcode"
},
  "geometry": {"coordinates":[140.8168,35.7281],"type":"Point"}
}