{
  "type": "Feature",
  "properties": {
    "gn:adm1_name":"Ishikawaken",
    "gn:adm2_name":"Nanaoshi",
    "gn:name":"Iorimachi(Doumimachi)",
    "iso:country":"JP",
    "wof:name":"926-0365",
    "wof:placetype":"postalcode"
},
  "geometry": {"coordinates":[137.0471,37.0411],"type":"Point"}
}