{
  "type": "Feature",
  "properties": {
    "gn:adm1_name":"Shizuokaken",
    "gn:adm2_name":"Hamamatsushi",
    "gn:name":"Nakanomachi",
    "iso:country":"JP",
    "wof:name":"435-0004",
    "wof:placetype":"postalcode"
},
  "geometry": {"coordinates":[137.79660000000001,34.7304],"type":"Point"}
}