{
  "type": "Feature",
  "properties": {
    "gn:adm1_name":"Chibaken",
    "gn:adm2_name":"Tomisatoshi",
    "gn:name":"Nippashi",
    "iso:country":"JP",
    "wof:name":"286-0224",
    "wof:placetype":"postalcode"
},
  "geometry": {"coordinates":[140.30279999999999,35.7246],"type":"Point"}
}