{
  "type": "Feature",
  "properties": {
    "gn:adm1_name":"Hyougoken",
    "gn:adm2_name":"Takaradukashi",
    "gn:name":"Nigawatakamaru",
    "iso:country":"JP",
    "wof:name":"665-0063",
    "wof:placetype":"postalcode"
},
  "geometry": {"coordinates":[135.34520000000001,34.7771],"type":"Point"}
}