{
  "type": "Feature",
  "properties": {
    "gn:adm1_name":"Tokushimaken",
    "gn:adm2_name":"Tokushimashi",
    "gn:name":"Takarachou",
    "iso:country":"JP",
    "wof:name":"771-4264",
    "wof:placetype":"postalcode"
},
  "geometry": {"coordinates":[134.5367,33.9912],"type":"Point"}
}