{
  "type": "Feature",
  "properties": {
    "gn:adm1_name":"Miyagiken",
    "gn:adm2_name":"Kamigunkamimachi",
    "gn:name":"Ishihara",
    "iso:country":"JP",
    "wof:name":"981-4323",
    "wof:placetype":"postalcode"
},
  "geometry": {"coordinates":[140.78989999999999,38.5752],"type":"Point"}
}