{
  "type": "Feature",
  "properties": {
    "gn:adm1_name":"Naraken",
    "gn:adm2_name":"Yamatotakadashi",
    "gn:name":"Kitahonmachi",
    "iso:country":"JP",
    "wof:name":"635-0097",
    "wof:placetype":"postalcode"
},
  "geometry": {"coordinates":[135.7422,34.5179],"type":"Point"}
}