{
  "type": "Feature",
  "properties": {
    "gn:adm1_name":"Gifuken",
    "gn:adm2_name":"Gifushi",
    "gn:name":"Souden'Oodoori",
    "iso:country":"JP",
    "wof:name":"502-0902",
    "wof:placetype":"postalcode"
},
  "geometry": {"coordinates":[136.74879999999999,35.4347],"type":"Point"}
}