{
  "type": "Feature",
  "properties": {
    "gn:adm1_name":"Gifuken",
    "gn:adm2_name":"Enagunkamiyahagichou",
    "gn:name":"Kinomi",
    "iso:country":"JP",
    "wof:name":"509-7501",
    "wof:placetype":"postalcode"
},
  "geometry": {"coordinates":[137.4734,35.3217],"type":"Point"}
}