{
  "type": "Feature",
  "properties": {
    "gn:adm1_name":"Miyagiken",
    "gn:adm2_name":"Shibatagunshibatamachi",
    "gn:name":"Funaokanishi",
    "iso:country":"JP",
    "wof:name":"989-1603",
    "wof:placetype":"postalcode"
},
  "geometry": {"coordinates":[140.76240000000001,38.0542],"type":"Point"}
}