{
  "type": "Feature",
  "properties": {
    "gn:adm1_name":"Niigataken",
    "gn:adm2_name":"Niigatashi",
    "gn:name":"Awayama",
    "iso:country":"JP",
    "wof:name":"950-0843",
    "wof:placetype":"postalcode"
},
  "geometry": {"coordinates":[139.10149999999999,37.8972],"type":"Point"}
}