{
  "type": "Feature",
  "properties": {
    "gn:adm1_name":"Tochigiken",
    "gn:adm2_name":"Sanoshi",
    "gn:name":"Inubushinakachou",
    "iso:country":"JP",
    "wof:name":"327-0805",
    "wof:placetype":"postalcode"
},
  "geometry": {"coordinates":[139.5967,36.3248],"type":"Point"}
}