{
  "type": "Feature",
  "properties": {
    "gn:adm1_name":"Kagoshimaken",
    "gn:adm2_name":"Ooshimagunwadomarichou",
    "gn:name":"Azefu",
    "iso:country":"JP",
    "wof:name":"891-9114",
    "wof:placetype":"postalcode"
},
  "geometry": {"coordinates":[128.63399999999999,27.4053],"type":"Point"}
}