{
  "type": "Feature",
  "properties": {
    "gn:adm1_name":"Gunmaken",
    "gn:adm2_name":"Yamadagun'Oomamamachi",
    "gn:name":"Takatsudo",
    "iso:country":"JP",
    "wof:name":"376-0113",
    "wof:placetype":"postalcode"
},
  "geometry": {"coordinates":[139.2868,36.4351],"type":"Point"}
}