{
  "type": "Feature",
  "properties": {
    "gn:adm1_name":"Tottoriken",
    "gn:adm2_name":"Saihakugunsaihakuchou",
    "gn:name":"Kinuya",
    "iso:country":"JP",
    "wof:name":"683-0364",
    "wof:placetype":"postalcode"
},
  "geometry": {"coordinates":[133.3083,35.3382],"type":"Point"}
}