{
  "type": "Feature",
  "properties": {
    "gn:adm1_name":"Mieken",
    "gn:adm2_name":"Nabarishi",
    "gn:name":"Kikyougaokanishi3banchou",
    "iso:country":"JP",
    "wof:name":"518-0643",
    "wof:placetype":"postalcode"
},
  "geometry": {"coordinates":[136.1121,34.6443],"type":"Point"}
}