{
  "type": "Feature",
  "properties": {
    "gn:adm1_name":"Tokushimaken",
    "gn:adm2_name":"Nakagunkitouson",
    "gn:name":"Oriu",
    "iso:country":"JP",
    "wof:name":"771-6511",
    "wof:placetype":"postalcode"
},
  "geometry": {"coordinates":[134.13579999999999,33.7722],"type":"Point"}
}