{
  "type": "Feature",
  "properties": {
    "gn:adm1_name":"Aichiken",
    "gn:adm2_name":"Nishioshi",
    "gn:name":"Takasagochou",
    "iso:country":"JP",
    "wof:name":"445-0856",
    "wof:placetype":"postalcode"
},
  "geometry": {"coordinates":[137.0548,34.8665],"type":"Point"}
}