{
  "type": "Feature",
  "properties": {
    "gn:adm1_name":"Chibaken",
    "gn:adm2_name":"Chibashiwakabaku",
    "gn:name":"Sakadukichou",
    "iso:country":"JP",
    "wof:name":"264-0012",
    "wof:placetype":"postalcode"
},
  "geometry": {"coordinates":[140.18010000000001,35.6112],"type":"Point"}
}