{
  "type": "Feature",
  "properties": {
    "gn:adm1_name":"Toyamaken",
    "gn:adm2_name":"Toyamashi",
    "gn:name":"Nagaresugi",
    "iso:country":"JP",
    "wof:name":"939-8032",
    "wof:placetype":"postalcode"
},
  "geometry": {"coordinates":[137.2687,36.6647],"type":"Point"}
}