{
  "type": "Feature",
  "properties": {
    "gn:adm1_name":"Fukushimaken",
    "gn:adm2_name":"Dategunhobaramachi",
    "gn:name":"Higashikobuta",
    "iso:country":"JP",
    "wof:name":"960-0648",
    "wof:placetype":"postalcode"
},
  "geometry": {"coordinates":[140.55439999999999,37.8352],"type":"Point"}
}