{
  "type": "Feature",
  "properties": {
    "gn:adm1_name":"Nagasakiken",
    "gn:adm2_name":"Shimabarashi",
    "gn:name":"Shinminato",
    "iso:country":"JP",
    "wof:name":"855-0862",
    "wof:placetype":"postalcode"
},
  "geometry": {"coordinates":[130.36490000000001,32.7626],"type":"Point"}
}