{
  "type": "Feature",
  "properties": {
    "gn:adm1_name":"Kanagawaken",
    "gn:adm2_name":"Chigasakishi",
    "gn:name":"Murota",
    "iso:country":"JP",
    "wof:name":"253-0018",
    "wof:placetype":"postalcode"
},
  "geometry": {"coordinates":[139.4204,35.3433],"type":"Point"}
}