{
  "type": "Feature",
  "properties": {
    "gn:adm1_name":"Niigataken",
    "gn:adm2_name":"Nakakanbaragunkamedamachi",
    "gn:name":"Shinmeichou",
    "iso:country":"JP",
    "wof:name":"950-0125",
    "wof:placetype":"postalcode"
},
  "geometry": {"coordinates":[139.11099999999999,37.8669],"type":"Point"}
}