{
  "type": "Feature",
  "properties": {
    "gn:adm1_name":"Tochigiken",
    "gn:adm2_name":"Kuroisoshi",
    "gn:name":"Nishishinmachi",
    "iso:country":"JP",
    "wof:name":"325-0076",
    "wof:placetype":"postalcode"
},
  "geometry": {"coordinates":[140.0326,36.972],"type":"Point"}
}