{
  "type": "Feature",
  "properties": {
    "gn:adm1_name":"Saitamaken",
    "gn:adm2_name":"Kawagoeshi",
    "gn:name":"Oosenba(Sonota)",
    "iso:country":"JP",
    "wof:name":"350-0032",
    "wof:placetype":"postalcode"
},
  "geometry": {"coordinates":[139.49879999999999,35.9114],"type":"Point"}
}