{
  "type": "Feature",
  "properties": {
    "gn:adm1_name":"Naraken",
    "gn:adm2_name":"Narashi",
    "gn:name":"Tsurumainishimachi",
    "iso:country":"JP",
    "wof:name":"631-0022",
    "wof:placetype":"postalcode"
},
  "geometry": {"coordinates":[135.7491,34.7036],"type":"Point"}
}