{
  "type": "Feature",
  "properties": {
    "gn:adm1_name":"Ibarakiken",
    "gn:adm2_name":"Nakagun'Oomiyamachi",
    "gn:name":"Wakabayashi",
    "iso:country":"JP",
    "wof:name":"319-2222",
    "wof:placetype":"postalcode"
},
  "geometry": {"coordinates":[140.3888,36.5465],"type":"Point"}
}