{
  "type": "Feature",
  "properties": {
    "gn:adm1_name":"Hyougoken",
    "gn:adm2_name":"Aioishi",
    "gn:name":"Hongouchou",
    "iso:country":"JP",
    "wof:name":"678-0006",
    "wof:placetype":"postalcode"
},
  "geometry": {"coordinates":[134.47309999999999,34.8172],"type":"Point"}
}