{
  "type": "Feature",
  "properties": {
    "gn:adm1_name":"Ibarakiken",
    "gn:adm2_name":"Kasamashi",
    "gn:name":"Inada",
    "iso:country":"JP",
    "wof:name":"309-1635",
    "wof:placetype":"postalcode"
},
  "geometry": {"coordinates":[140.20920000000001,36.3696],"type":"Point"}
}