{
  "type": "Feature",
  "properties": {
    "gn:adm1_name":"Naraken",
    "gn:adm2_name":"Udagunsonimura",
    "gn:name":"Yamagasu",
    "iso:country":"JP",
    "wof:name":"633-1216",
    "wof:placetype":"postalcode"
},
  "geometry": {"coordinates":[136.09559999999999,34.489],"type":"Point"}
}