{
  "type": "Feature",
  "properties": {
    "gn:adm1_name":"Nagasakiken",
    "gn:adm2_name":"Saseboshi",
    "gn:name":"Kaizechou",
    "iso:country":"JP",
    "wof:name":"857-0144",
    "wof:placetype":"postalcode"
},
  "geometry": {"coordinates":[129.69880000000001,33.2143],"type":"Point"}
}