{
  "type": "Feature",
  "properties": {
    "gn:adm1_name":"Toukyouto",
    "gn:adm2_name":"Ooshimaooshimamachi",
    "gn:name":"Sashikiji",
    "iso:country":"JP",
    "wof:name":"100-0211",
    "wof:placetype":"postalcode"
},
  "geometry": {"coordinates":[139.42330000000001,34.6849],"type":"Point"}
}