{
  "type": "Feature",
  "properties": {
    "gn:adm1_name":"Toukyouto",
    "gn:adm2_name":"Kodairashi",
    "gn:name":"Meguritachou",
    "iso:country":"JP",
    "wof:name":"187-0013",
    "wof:placetype":"postalcode"
},
  "geometry": {"coordinates":[139.4949,35.7172],"type":"Point"}
}