{
  "type": "Feature",
  "properties": {
    "gn:adm1_name":"Niigataken",
    "gn:adm2_name":"Nishikubikigunnoumachi",
    "gn:name":"Touzaki",
    "iso:country":"JP",
    "wof:name":"949-1305",
    "wof:placetype":"postalcode"
},
  "geometry": {"coordinates":[138.0367,37.1206],"type":"Point"}
}