{
  "type": "Feature",
  "properties": {
    "gn:adm1_name":"Hiroshimaken",
    "gn:adm2_name":"Seragunserachou",
    "gn:name":"Higashikanzaki",
    "iso:country":"JP",
    "wof:name":"722-1114",
    "wof:placetype":"postalcode"
},
  "geometry": {"coordinates":[133.04929999999999,34.5811],"type":"Point"}
}