{
  "type": "Feature",
  "properties": {
    "gn:adm1_name":"Sagaken",
    "gn:adm2_name":"Tosushi",
    "gn:name":"Matsubaramachi",
    "iso:country":"JP",
    "wof:name":"841-0027",
    "wof:placetype":"postalcode"
},
  "geometry": {"coordinates":[130.52199999999999,33.3818],"type":"Point"}
}