{
  "type": "Feature",
  "properties": {
    "gn:adm1_name":"Aichiken",
    "gn:adm2_name":"Nagoyashiatsutaku",
    "gn:name":"Namiyosechou",
    "iso:country":"JP",
    "wof:name":"456-0003",
    "wof:placetype":"postalcode"
},
  "geometry": {"coordinates":[136.9049,35.142],"type":"Point"}
}