{
  "type": "Feature",
  "properties": {
    "gn:adm1_name":"Chibaken",
    "gn:adm2_name":"Kashiwashi",
    "gn:name":"Higashiyama",
    "iso:country":"JP",
    "wof:name":"277-0064",
    "wof:placetype":"postalcode"
},
  "geometry": {"coordinates":[139.95310000000001,35.8254],"type":"Point"}
}