{
  "type": "Feature",
  "properties": {
    "gn:adm1_name":"Kanagawaken",
    "gn:adm2_name":"Yokosukashi",
    "gn:name":"Iwato",
    "iso:country":"JP",
    "wof:name":"239-0844",
    "wof:placetype":"postalcode"
},
  "geometry": {"coordinates":[139.67140000000001,35.2314],"type":"Point"}
}