{
  "type": "Feature",
  "properties": {
    "gn:adm1_name":"Gunmaken",
    "gn:adm2_name":"Annakashi",
    "gn:name":"Annaka",
    "iso:country":"JP",
    "wof:name":"379-0116",
    "wof:placetype":"postalcode"
},
  "geometry": {"coordinates":[138.8946,36.3278],"type":"Point"}
}