{
  "type": "Feature",
  "properties": {
    "gn:adm1_name":"Ibarakiken",
    "gn:adm2_name":"Nakaguntoukaimura",
    "gn:name":"Ishigamitojuku",
    "iso:country":"JP",
    "wof:name":"319-1101",
    "wof:placetype":"postalcode"
},
  "geometry": {"coordinates":[140.566,36.4868],"type":"Point"}
}