{
  "type": "Feature",
  "properties": {
    "gn:adm1_name":"Chibaken",
    "gn:adm2_name":"Katorigun'Omigawamachi",
    "gn:name":"Kaiduka",
    "iso:country":"JP",
    "wof:name":"289-0325",
    "wof:placetype":"postalcode"
},
  "geometry": {"coordinates":[140.60939999999999,35.8513],"type":"Point"}
}