{
  "type": "Feature",
  "properties": {
    "gn:adm1_name":"Fukuokaken",
    "gn:adm2_name":"Ukihaguntanushimarumachi",
    "gn:name":"Takeno",
    "iso:country":"JP",
    "wof:name":"839-1215",
    "wof:placetype":"postalcode"
},
  "geometry": {"coordinates":[130.65950000000001,33.3223],"type":"Point"}
}