{
  "type": "Feature",
  "properties": {
    "gn:adm1_name":"Hyougoken",
    "gn:adm2_name":"Izushigun'Izushichou",
    "gn:name":"Morii",
    "iso:country":"JP",
    "wof:name":"668-0276",
    "wof:placetype":"postalcode"
},
  "geometry": {"coordinates":[134.84780000000001,35.4802],"type":"Point"}
}