{
  "type": "Feature",
  "properties": {
    "gn:adm1_name":"Chibaken",
    "gn:adm2_name":"Funabashishi",
    "gn:name":"Kouyadai",
    "iso:country":"JP",
    "wof:name":"274-0801",
    "wof:placetype":"postalcode"
},
  "geometry": {"coordinates":[140.0282,35.7671],"type":"Point"}
}