{
  "type": "Feature",
  "properties": {
    "gn:adm1_name":"Hiroshimaken",
    "gn:adm2_name":"Akigunsakachou",
    "gn:name":"Yokohamahigashi",
    "iso:country":"JP",
    "wof:name":"731-4322",
    "wof:placetype":"postalcode"
},
  "geometry": {"coordinates":[132.50620000000001,34.3353],"type":"Point"}
}