{
  "type": "Feature",
  "properties": {
    "gn:adm1_name":"Gunmaken",
    "gn:adm2_name":"Sawaguntamamuramachi",
    "gn:name":"Iigura",
    "iso:country":"JP",
    "wof:name":"370-1116",
    "wof:placetype":"postalcode"
},
  "geometry": {"coordinates":[139.1523,36.2858],"type":"Point"}
}