{
  "type": "Feature",
  "properties": {
    "gn:adm1_name":"Oosakafu",
    "gn:adm2_name":"Izumisanoshi",
    "gn:name":"Oomiyachou",
    "iso:country":"JP",
    "wof:name":"598-0053",
    "wof:placetype":"postalcode"
},
  "geometry": {"coordinates":[135.31880000000001,34.4131],"type":"Point"}
}