{
  "type": "Feature",
  "properties": {
    "gn:adm1_name":"Kanagawaken",
    "gn:adm2_name":"Miurashi",
    "gn:name":"Hatsusemachishimomiyata",
    "iso:country":"JP",
    "wof:name":"238-0111",
    "wof:placetype":"postalcode"
},
  "geometry": {"coordinates":[139.63480000000001,35.1801],"type":"Point"}
}