{
  "type": "Feature",
  "properties": {
    "gn:adm1_name":"Aichiken",
    "gn:adm2_name":"Hekinanshi",
    "gn:name":"Nihongimachi",
    "iso:country":"JP",
    "wof:name":"447-0029",
    "wof:placetype":"postalcode"
},
  "geometry": {"coordinates":[137.01329999999999,34.8915],"type":"Point"}
}