{
  "type": "Feature",
  "properties": {
    "gn:adm1_name":"Mieken",
    "gn:adm2_name":"Ayamagun'Igachou",
    "gn:name":"Nakatsuge",
    "iso:country":"JP",
    "wof:name":"519-1404",
    "wof:placetype":"postalcode"
},
  "geometry": {"coordinates":[136.22669999999999,34.8344],"type":"Point"}
}