{
  "type": "Feature",
  "properties": {
    "gn:adm1_name":"Kumamotoken",
    "gn:adm2_name":"Kamotogunkikukamachi",
    "gn:name":"Kino",
    "iso:country":"JP",
    "wof:name":"861-0426",
    "wof:placetype":"postalcode"
},
  "geometry": {"coordinates":[130.77430000000001,33.0077],"type":"Point"}
}