{
  "type": "Feature",
  "properties": {
    "gn:adm1_name":"Niigataken",
    "gn:adm2_name":"Sadogun'Aikawamachi",
    "gn:name":"Kamiyamachi",
    "iso:country":"JP",
    "wof:name":"952-1507",
    "wof:placetype":"postalcode"
},
  "geometry": {"coordinates":[138.23750000000001,38.0377],"type":"Point"}
}