{
  "type": "Feature",
  "properties": {
    "gn:adm1_name":"Fukuokaken",
    "gn:adm2_name":"Kitakyuushuushimojiku",
    "gn:name":"Hata",
    "iso:country":"JP",
    "wof:name":"800-0112",
    "wof:placetype":"postalcode"
},
  "geometry": {"coordinates":[130.97450000000001,33.8809],"type":"Point"}
}