{
  "type": "Feature",
  "properties": {
    "gn:adm1_name":"Chibaken",
    "gn:adm2_name":"Yachimatashi",
    "gn:name":"Izumidai",
    "iso:country":"JP",
    "wof:name":"289-1105",
    "wof:placetype":"postalcode"
},
  "geometry": {"coordinates":[140.29519999999999,35.6812],"type":"Point"}
}