{
  "type": "Feature",
  "properties": {
    "gn:adm1_name":"Shizuokaken",
    "gn:adm2_name":"Tagatagun'Amagiyugashimachou",
    "gn:name":"Kadonohara",
    "iso:country":"JP",
    "wof:name":"410-3209",
    "wof:placetype":"postalcode"
},
  "geometry": {"coordinates":[138.92359999999999,34.9064],"type":"Point"}
}