{
  "type": "Feature",
  "properties": {
    "gn:adm1_name":"Shigaken",
    "gn:adm2_name":"Ikaguntakatsukichou",
    "gn:name":"Ikanikeisaiganaibaai",
    "iso:country":"JP",
    "wof:name":"529-0200",
    "wof:placetype":"postalcode"
},
  "geometry": {"coordinates":[136.22839999999999,35.4855],"type":"Point"}
}