{
  "type": "Feature",
  "properties": {
    "gn:adm1_name":"Fukuokaken",
    "gn:adm2_name":"Oomutashi",
    "gn:name":"Ipponmachi",
    "iso:country":"JP",
    "wof:name":"836-0834",
    "wof:placetype":"postalcode"
},
  "geometry": {"coordinates":[130.45079999999999,33.0332],"type":"Point"}
}