{
  "type": "Feature",
  "properties": {
    "gn:adm1_name":"Kyoutofu",
    "gn:adm2_name":"Kyoutoshifushimiku",
    "gn:name":"Fukakusasoubouyamachou",
    "iso:country":"JP",
    "wof:name":"612-0819",
    "wof:placetype":"postalcode"
},
  "geometry": {"coordinates":[135.78370000000001,34.9629],"type":"Point"}
}