{
  "type": "Feature",
  "properties": {
    "gn:adm1_name":"Shizuokaken",
    "gn:adm2_name":"Shizuokashi",
    "gn:name":"Marikoshinden",
    "iso:country":"JP",
    "wof:name":"421-0111",
    "wof:placetype":"postalcode"
},
  "geometry": {"coordinates":[138.36770000000001,34.9502],"type":"Point"}
}