{
  "type": "Feature",
  "properties": {
    "gn:adm1_name":"Fukuokaken",
    "gn:adm2_name":"Kitakyuushuushimojiku",
    "gn:name":"Higashishinmachi",
    "iso:country":"JP",
    "wof:name":"800-0055",
    "wof:placetype":"postalcode"
},
  "geometry": {"coordinates":[130.92420000000001,33.8922],"type":"Point"}
}