{
  "type": "Feature",
  "properties": {
    "gn:adm1_name":"Ishikawaken",
    "gn:adm2_name":"Kanazawashi",
    "gn:name":"Kiriyamamachi",
    "iso:country":"JP",
    "wof:name":"920-0163",
    "wof:placetype":"postalcode"
},
  "geometry": {"coordinates":[136.73769999999999,36.6042],"type":"Point"}
}