{
  "type": "Feature",
  "properties": {
    "gn:adm1_name":"Fukuokaken",
    "gn:adm2_name":"Chikushigunnakagawamachi",
    "gn:name":"Shimokajiwara",
    "iso:country":"JP",
    "wof:name":"811-1222",
    "wof:placetype":"postalcode"
},
  "geometry": {"coordinates":[130.43539999999999,33.4977],"type":"Point"}
}