{
  "type": "Feature",
  "properties": {
    "gn:adm1_name":"Naraken",
    "gn:adm2_name":"Shikiguntawaramotochou",
    "gn:name":"Chishiro",
    "iso:country":"JP",
    "wof:name":"636-0246",
    "wof:placetype":"postalcode"
},
  "geometry": {"coordinates":[135.8005,34.5437],"type":"Point"}
}