{
  "type": "Feature",
  "properties": {
    "gn:adm1_name":"Toyamaken",
    "gn:adm2_name":"Toyamashi",
    "gn:name":"Kamisenbyoumachi",
    "iso:country":"JP",
    "wof:name":"939-8134",
    "wof:placetype":"postalcode"
},
  "geometry": {"coordinates":[137.24959999999999,36.6234],"type":"Point"}
}