{
  "type": "Feature",
  "properties": {
    "gn:adm1_name":"Mieken",
    "gn:adm2_name":"Wataraigunnanseichou",
    "gn:name":"Izumi",
    "iso:country":"JP",
    "wof:name":"516-0103",
    "wof:placetype":"postalcode"
},
  "geometry": {"coordinates":[136.72900000000001,34.358],"type":"Point"}
}