{
  "type": "Feature",
  "properties": {
    "gn:adm1_name":"Kanagawaken",
    "gn:adm2_name":"Yokohamashikanagawaku",
    "gn:name":"Matsumichou",
    "iso:country":"JP",
    "wof:name":"221-0005",
    "wof:placetype":"postalcode"
},
  "geometry": {"coordinates":[139.64089999999999,35.4996],"type":"Point"}
}