{
  "type": "Feature",
  "properties": {
    "gn:adm1_name":"Miyagiken",
    "gn:adm2_name":"Sendaishiaobaku",
    "gn:name":"Kawauchikameokachou",
    "iso:country":"JP",
    "wof:name":"980-0865",
    "wof:placetype":"postalcode"
},
  "geometry": {"coordinates":[140.84639999999999,38.2613],"type":"Point"}
}