{
  "type": "Feature",
  "properties": {
    "gn:adm1_name":"Miyazakiken",
    "gn:adm2_name":"Miyakonojoushi",
    "gn:name":"Hachimanchou",
    "iso:country":"JP",
    "wof:name":"885-0075",
    "wof:placetype":"postalcode"
},
  "geometry": {"coordinates":[131.0582,31.7202],"type":"Point"}
}