{
  "type": "Feature",
  "properties": {
    "gn:adm1_name":"Okayamaken",
    "gn:adm2_name":"Okayamashi",
    "gn:name":"Kawairi",
    "iso:country":"JP",
    "wof:name":"701-0161",
    "wof:placetype":"postalcode"
},
  "geometry": {"coordinates":[133.84549999999999,34.6567],"type":"Point"}
}