{
  "type": "Feature",
  "properties": {
    "gn:adm1_name":"Hyougoken",
    "gn:adm2_name":"Miharagunmidorichou",
    "gn:name":"Shitoorianjuuji",
    "iso:country":"JP",
    "wof:name":"656-0151",
    "wof:placetype":"postalcode"
},
  "geometry": {"coordinates":[134.8005,34.3478],"type":"Point"}
}