{
  "type": "Feature",
  "properties": {
    "gn:adm1_name":"Yamagataken",
    "gn:adm2_name":"Nishimurayamagun'Asahimachi",
    "gn:name":"Mizumoto",
    "iso:country":"JP",
    "wof:name":"990-1424",
    "wof:placetype":"postalcode"
},
  "geometry": {"coordinates":[140.154,38.2561],"type":"Point"}
}