{
  "type": "Feature",
  "properties": {
    "gn:adm1_name":"Kyoutofu",
    "gn:adm2_name":"Ujishi",
    "gn:name":"Shiragawa",
    "iso:country":"JP",
    "wof:name":"611-0022",
    "wof:placetype":"postalcode"
},
  "geometry": {"coordinates":[135.81229999999999,34.8734],"type":"Point"}
}