{
  "type": "Feature",
  "properties": {
    "gn:adm1_name":"Niigataken",
    "gn:adm2_name":"Tookamachishi",
    "gn:name":"Kawajishimomachi",
    "iso:country":"JP",
    "wof:name":"948-0035",
    "wof:placetype":"postalcode"
},
  "geometry": {"coordinates":[138.7526,37.1199],"type":"Point"}
}