{
  "type": "Feature",
  "properties": {
    "gn:adm1_name":"Mieken",
    "gn:adm2_name":"Kuwanashi",
    "gn:name":"Shigematsushinden",
    "iso:country":"JP",
    "wof:name":"511-0824",
    "wof:placetype":"postalcode"
},
  "geometry": {"coordinates":[136.67269999999999,35.0562],"type":"Point"}
}