{
  "type": "Feature",
  "properties": {
    "gn:adm1_name":"Ishikawaken",
    "gn:adm2_name":"Kanazawashi",
    "gn:name":"Besshomachi",
    "iso:country":"JP",
    "wof:name":"920-1341",
    "wof:placetype":"postalcode"
},
  "geometry": {"coordinates":[136.67519999999999,36.5131],"type":"Point"}
}