{
  "type": "Feature",
  "properties": {
    "gn:adm1_name":"Hiroshimaken",
    "gn:adm2_name":"Hiroshimashiasakitaku",
    "gn:name":"Ikanikeisaiganaibaai",
    "iso:country":"JP",
    "wof:name":"739-1700",
    "wof:placetype":"postalcode"
},
  "geometry": {"coordinates":[132.57300000000001,34.5641],"type":"Point"}
}