{
  "type": "Feature",
  "properties": {
    "gn:adm1_name":"Fukuokaken",
    "gn:adm2_name":"Yukuhashishi",
    "gn:name":"Tokunaga",
    "iso:country":"JP",
    "wof:name":"824-0071",
    "wof:placetype":"postalcode"
},
  "geometry": {"coordinates":[130.92619999999999,33.7427],"type":"Point"}
}