{
  "type": "Feature",
  "properties": {
    "gn:adm1_name":"Saitamaken",
    "gn:adm2_name":"Kazoshi",
    "gn:name":"Kamihiyarikawa",
    "iso:country":"JP",
    "wof:name":"347-0003",
    "wof:placetype":"postalcode"
},
  "geometry": {"coordinates":[139.63489999999999,36.1611],"type":"Point"}
}