{
  "type": "Feature",
  "properties": {
    "gn:adm1_name":"Hyougoken",
    "gn:adm2_name":"Amagasakishi",
    "gn:name":"Nishikawa",
    "iso:country":"JP",
    "wof:name":"661-0966",
    "wof:placetype":"postalcode"
},
  "geometry": {"coordinates":[135.44300000000001,34.7345],"type":"Point"}
}