{
  "type": "Feature",
  "properties": {
    "gn:adm1_name":"Yamagataken",
    "gn:adm2_name":"Yamagatashi",
    "gn:name":"Toyogoshi",
    "iso:country":"JP",
    "wof:name":"990-0815",
    "wof:placetype":"postalcode"
},
  "geometry": {"coordinates":[140.32509999999999,38.2866],"type":"Point"}
}