{
  "type": "Feature",
  "properties": {
    "gn:adm1_name":"Naraken",
    "gn:adm2_name":"Ikomashi",
    "gn:name":"Hikarigaoka",
    "iso:country":"JP",
    "wof:name":"630-0141",
    "wof:placetype":"postalcode"
},
  "geometry": {"coordinates":[135.71510000000001,34.7409],"type":"Point"}
}