{
  "type": "Feature",
  "properties": {
    "gn:adm1_name":"Saitamaken",
    "gn:adm2_name":"Hasudashi",
    "gn:name":"Higashi",
    "iso:country":"JP",
    "wof:name":"349-0111",
    "wof:placetype":"postalcode"
},
  "geometry": {"coordinates":[139.65559999999999,35.9805],"type":"Point"}
}