{
  "type": "Feature",
  "properties": {
    "gn:adm1_name":"Fukushimaken",
    "gn:adm2_name":"Iwakishi",
    "gn:name":"Tairaattame",
    "iso:country":"JP",
    "wof:name":"970-0107",
    "wof:placetype":"postalcode"
},
  "geometry": {"coordinates":[140.9479,37.0556],"type":"Point"}
}