{
  "type": "Feature",
  "properties": {
    "gn:adm1_name":"Okayamaken",
    "gn:adm2_name":"Katsutagunshoubokuchou",
    "gn:name":"Ooyoshi",
    "iso:country":"JP",
    "wof:name":"708-1203",
    "wof:placetype":"postalcode"
},
  "geometry": {"coordinates":[134.13239999999999,35.1322],"type":"Point"}
}