{
  "type": "Feature",
  "properties": {
    "gn:adm1_name":"Kyoutofu",
    "gn:adm2_name":"Amatagunmiwachou",
    "gn:name":"Takasugi",
    "iso:country":"JP",
    "wof:name":"620-1423",
    "wof:placetype":"postalcode"
},
  "geometry": {"coordinates":[135.2647,35.1892],"type":"Point"}
}