{
  "type": "Feature",
  "properties": {
    "gn:adm1_name":"Gunmaken",
    "gn:adm2_name":"Setagun'Oogomachi",
    "gn:name":"Higoshi",
    "iso:country":"JP",
    "wof:name":"371-0221",
    "wof:placetype":"postalcode"
},
  "geometry": {"coordinates":[139.17400000000001,36.415],"type":"Point"}
}