{
  "type": "Feature",
  "properties": {
    "gn:adm1_name":"Fukuokaken",
    "gn:adm2_name":"Ukihaguntanushimarumachi",
    "gn:name":"Nagasu",
    "iso:country":"JP",
    "wof:name":"839-1201",
    "wof:placetype":"postalcode"
},
  "geometry": {"coordinates":[130.726,33.3567],"type":"Point"}
}