{
  "type": "Feature",
  "properties": {
    "gn:adm1_name":"Gunmaken",
    "gn:adm2_name":"Setagunkurohonemura",
    "gn:name":"Yagihara",
    "iso:country":"JP",
    "wof:name":"376-0142",
    "wof:placetype":"postalcode"
},
  "geometry": {"coordinates":[139.279,36.4912],"type":"Point"}
}