{
  "type": "Feature",
  "properties": {
    "gn:adm1_name":"Yamanashiken",
    "gn:adm2_name":"Nishiyatsushirogunrokugouchou",
    "gn:name":"Iwashita",
    "iso:country":"JP",
    "wof:name":"409-3234",
    "wof:placetype":"postalcode"
},
  "geometry": {"coordinates":[138.48609999999999,35.4928],"type":"Point"}
}