{
  "type": "Feature",
  "properties": {
    "gn:adm1_name":"Toukyouto",
    "gn:adm2_name":"Chuuouku",
    "gn:name":"Nihonbashikodenmachou",
    "iso:country":"JP",
    "wof:name":"103-0001",
    "wof:placetype":"postalcode"
},
  "geometry": {"coordinates":[139.779,35.6916],"type":"Point"}
}