{
  "type": "Feature",
  "properties": {
    "gn:adm1_name":"Saitamaken",
    "gn:adm2_name":"Kodamagunmisatomachi",
    "gn:name":"Negi",
    "iso:country":"JP",
    "wof:name":"367-0104",
    "wof:placetype":"postalcode"
},
  "geometry": {"coordinates":[139.1815,36.1933],"type":"Point"}
}