{
  "type": "Feature",
  "properties": {
    "gn:adm1_name":"Kyoutofu",
    "gn:adm2_name":"Funaiguntanbachou",
    "gn:name":"Sone",
    "iso:country":"JP",
    "wof:name":"622-0232",
    "wof:placetype":"postalcode"
},
  "geometry": {"coordinates":[135.41050000000001,35.1629],"type":"Point"}
}