{
  "type": "Feature",
  "properties": {
    "gn:adm1_name":"Oosakafu",
    "gn:adm2_name":"Tondabayashishi",
    "gn:name":"Koganedai",
    "iso:country":"JP",
    "wof:name":"584-0083",
    "wof:placetype":"postalcode"
},
  "geometry": {"coordinates":[135.5821,34.497],"type":"Point"}
}