{
  "type": "Feature",
  "properties": {
    "gn:adm1_name":"Tokushimaken",
    "gn:adm2_name":"Miyoshigun'Ikedachou",
    "gn:name":"Yamada",
    "iso:country":"JP",
    "wof:name":"778-0007",
    "wof:placetype":"postalcode"
},
  "geometry": {"coordinates":[133.82140000000001,34.0263],"type":"Point"}
}