{
  "type": "Feature",
  "properties": {
    "gn:adm1_name":"Shizuokaken",
    "gn:adm2_name":"Mishimashi",
    "gn:name":"Misono",
    "iso:country":"JP",
    "wof:name":"411-0823",
    "wof:placetype":"postalcode"
},
  "geometry": {"coordinates":[138.92169999999999,35.0799],"type":"Point"}
}