{
  "type": "Feature",
  "properties": {
    "gn:adm1_name":"Aichiken",
    "gn:adm2_name":"Tsushimashi",
    "gn:name":"Kamishindenchou",
    "iso:country":"JP",
    "wof:name":"496-0871",
    "wof:placetype":"postalcode"
},
  "geometry": {"coordinates":[136.71369999999999,35.1869],"type":"Point"}
}