{
  "type": "Feature",
  "properties": {
    "gn:adm1_name":"Miyagiken",
    "gn:adm2_name":"Kamigunshikamachou",
    "gn:name":"Koguriyama",
    "iso:country":"JP",
    "wof:name":"981-4151",
    "wof:placetype":"postalcode"
},
  "geometry": {"coordinates":[140.76650000000001,38.526],"type":"Point"}
}