{
  "type": "Feature",
  "properties": {
    "gn:adm1_name":"Shigaken",
    "gn:adm2_name":"Youkaichishi",
    "gn:name":"Hamanochou",
    "iso:country":"JP",
    "wof:name":"527-0011",
    "wof:placetype":"postalcode"
},
  "geometry": {"coordinates":[136.19669999999999,35.1154],"type":"Point"}
}