{
  "type": "Feature",
  "properties": {
    "gn:adm1_name":"Fukushimaken",
    "gn:adm2_name":"Kooriyamashi",
    "gn:name":"Nakatamachiushikubirihongou",
    "iso:country":"JP",
    "wof:name":"963-0834",
    "wof:placetype":"postalcode"
},
  "geometry": {"coordinates":[140.499,37.3771],"type":"Point"}
}