{
  "type": "Feature",
  "properties": {
    "gn:adm1_name":"Tokushimaken",
    "gn:adm2_name":"Ananshi",
    "gn:name":"Kaminakachou",
    "iso:country":"JP",
    "wof:name":"774-0044",
    "wof:placetype":"postalcode"
},
  "geometry": {"coordinates":[134.62100000000001,33.9326],"type":"Point"}
}