{
  "type": "Feature",
  "properties": {
    "gn:adm1_name":"Ishikawaken",
    "gn:adm2_name":"Suzushi",
    "gn:name":"Takayamachi",
    "iso:country":"JP",
    "wof:name":"927-1301",
    "wof:placetype":"postalcode"
},
  "geometry": {"coordinates":[137.23920000000001,37.5181],"type":"Point"}
}