{
  "type": "Feature",
  "properties": {
    "gn:adm1_name":"Toyamaken",
    "gn:adm2_name":"Oyabeshi",
    "gn:name":"Takaki",
    "iso:country":"JP",
    "wof:name":"932-0123",
    "wof:placetype":"postalcode"
},
  "geometry": {"coordinates":[136.8826,36.6267],"type":"Point"}
}