{
  "type": "Feature",
  "properties": {
    "gn:adm1_name":"Aichiken",
    "gn:adm2_name":"Chitaguntaketoyochou",
    "gn:name":"Kamiokoshi",
    "iso:country":"JP",
    "wof:name":"470-2364",
    "wof:placetype":"postalcode"
},
  "geometry": {"coordinates":[136.9041,34.8433],"type":"Point"}
}