{
  "type": "Feature",
  "properties": {
    "gn:adm1_name":"Chibaken",
    "gn:adm2_name":"Isumigun'Ootakimachi",
    "gn:name":"Shinmachi",
    "iso:country":"JP",
    "wof:name":"298-0214",
    "wof:placetype":"postalcode"
},
  "geometry": {"coordinates":[140.2475,35.2825],"type":"Point"}
}