{
  "type": "Feature",
  "properties": {
    "gn:adm1_name":"Niigataken",
    "gn:adm2_name":"Nagaokashi",
    "gn:name":"Nishidumachi",
    "iso:country":"JP",
    "wof:name":"940-2126",
    "wof:placetype":"postalcode"
},
  "geometry": {"coordinates":[138.8065,37.4434],"type":"Point"}
}