{
  "type": "Feature",
  "properties": {
    "gn:adm1_name":"Toukyouto",
    "gn:adm2_name":"Hachioujishi",
    "gn:name":"Nanakuni",
    "iso:country":"JP",
    "wof:name":"192-0919",
    "wof:placetype":"postalcode"
},
  "geometry": {"coordinates":[139.3212,35.6231],"type":"Point"}
}