{
  "type": "Feature",
  "properties": {
    "gn:adm1_name":"Fukushimaken",
    "gn:adm2_name":"Shirakawashi",
    "gn:name":"Sanbonmatsu",
    "iso:country":"JP",
    "wof:name":"961-0872",
    "wof:placetype":"postalcode"
},
  "geometry": {"coordinates":[140.2089,37.1179],"type":"Point"}
}