{
  "type": "Feature",
  "properties": {
    "gn:adm1_name":"Fukushimaken",
    "gn:adm2_name":"Ishikawagun'Ishikawamachi",
    "gn:name":"Sekine",
    "iso:country":"JP",
    "wof:name":"963-7852",
    "wof:placetype":"postalcode"
},
  "geometry": {"coordinates":[140.45910000000001,37.1464],"type":"Point"}
}