{
  "type": "Feature",
  "properties": {
    "gn:adm1_name":"Kagoshimaken",
    "gn:adm2_name":"Ooshimaguntokunoshimachou",
    "gn:name":"Shoda",
    "iso:country":"JP",
    "wof:name":"891-7112",
    "wof:placetype":"postalcode"
},
  "geometry": {"coordinates":[129.02719999999999,27.7645],"type":"Point"}
}