{
  "type": "Feature",
  "properties": {
    "gn:adm1_name":"Shimaneken",
    "gn:adm2_name":"Yatsukaguntamayuchou",
    "gn:name":"Tamatsukuri",
    "iso:country":"JP",
    "wof:name":"699-0201",
    "wof:placetype":"postalcode"
},
  "geometry": {"coordinates":[133.00970000000001,35.4164],"type":"Point"}
}