{
  "type": "Feature",
  "properties": {
    "gn:adm1_name":"Gunmaken",
    "gn:adm2_name":"Sawaguntamamuramachi",
    "gn:name":"Yorokubun",
    "iso:country":"JP",
    "wof:name":"370-1134",
    "wof:placetype":"postalcode"
},
  "geometry": {"coordinates":[139.10409999999999,36.3052],"type":"Point"}
}