{
  "type": "Feature",
  "properties": {
    "gn:adm1_name":"Aichiken",
    "gn:adm2_name":"Nagoyashichikusaku",
    "gn:name":"Shirokichou",
    "iso:country":"JP",
    "wof:name":"464-0846",
    "wof:placetype":"postalcode"
},
  "geometry": {"coordinates":[136.94200000000001,35.1598],"type":"Point"}
}