{
  "type": "Feature",
  "properties": {
    "gn:adm1_name":"Ibarakiken",
    "gn:adm2_name":"Hitachinakashi",
    "gn:name":"Horikawa",
    "iso:country":"JP",
    "wof:name":"311-1233",
    "wof:placetype":"postalcode"
},
  "geometry": {"coordinates":[140.57810000000001,36.3499],"type":"Point"}
}