{
  "type": "Feature",
  "properties": {
    "gn:adm1_name":"Fukuokaken",
    "gn:adm2_name":"Maebarushi",
    "gn:name":"Urashi",
    "iso:country":"JP",
    "wof:name":"819-1112",
    "wof:placetype":"postalcode"
},
  "geometry": {"coordinates":[130.21080000000001,33.5632],"type":"Point"}
}