{
  "type": "Feature",
  "properties": {
    "gn:adm1_name":"Ooitaken",
    "gn:adm2_name":"Saikishi",
    "gn:name":"Wakamiyamachi",
    "iso:country":"JP",
    "wof:name":"876-0013",
    "wof:placetype":"postalcode"
},
  "geometry": {"coordinates":[131.88509999999999,32.9606],"type":"Point"}
}