{
  "type": "Feature",
  "properties": {
    "gn:adm1_name":"Hiroshimaken",
    "gn:adm2_name":"Hiroshimashinakaku",
    "gn:name":"Hakushimanakamachi",
    "iso:country":"JP",
    "wof:name":"730-0002",
    "wof:placetype":"postalcode"
},
  "geometry": {"coordinates":[132.46469999999999,34.4088],"type":"Point"}
}