{
  "type": "Feature",
  "properties": {
    "gn:adm1_name":"Ehimeken",
    "gn:adm2_name":"Matsuyamashi",
    "gn:name":"Fujiwara",
    "iso:country":"JP",
    "wof:name":"790-0035",
    "wof:placetype":"postalcode"
},
  "geometry": {"coordinates":[132.76079999999999,33.8306],"type":"Point"}
}