{
  "type": "Feature",
  "properties": {
    "gn:adm1_name":"Aichiken",
    "gn:adm2_name":"Setoshi",
    "gn:name":"Shindouchou",
    "iso:country":"JP",
    "wof:name":"489-0075",
    "wof:placetype":"postalcode"
},
  "geometry": {"coordinates":[137.10470000000001,35.2271],"type":"Point"}
}