{
  "type": "Feature",
  "properties": {
    "gn:adm1_name":"Kyoutofu",
    "gn:adm2_name":"Kumanogunkumihamachou",
    "gn:name":"Sanbu",
    "iso:country":"JP",
    "wof:name":"629-3433",
    "wof:placetype":"postalcode"
},
  "geometry": {"coordinates":[134.94730000000001,35.6328],"type":"Point"}
}