{
  "type": "Feature",
  "properties": {
    "gn:adm1_name":"Naraken",
    "gn:adm2_name":"Udagunsonimura",
    "gn:name":"Nagano",
    "iso:country":"JP",
    "wof:name":"633-1214",
    "wof:placetype":"postalcode"
},
  "geometry": {"coordinates":[136.1122,34.5059],"type":"Point"}
}