{
  "type": "Feature",
  "properties": {
    "gn:adm1_name":"Miyazakiken",
    "gn:adm2_name":"Kitamorokatagunmimatachou",
    "gn:name":"Nagata",
    "iso:country":"JP",
    "wof:name":"889-1911",
    "wof:placetype":"postalcode"
},
  "geometry": {"coordinates":[131.16640000000001,31.7389],"type":"Point"}
}