{
  "type": "Feature",
  "properties": {
    "gn:adm1_name":"Hiroshimaken",
    "gn:adm2_name":"Akigun'Ondochou",
    "gn:name":"Kitaondo",
    "iso:country":"JP",
    "wof:name":"737-1204",
    "wof:placetype":"postalcode"
},
  "geometry": {"coordinates":[132.5317,34.1912],"type":"Point"}
}