{
  "type": "Feature",
  "properties": {
    "gn:adm1_name":"Naganoken",
    "gn:adm2_name":"Kitasakugunkaruizawamachi",
    "gn:name":"Nakakaruizawa",
    "iso:country":"JP",
    "wof:name":"389-0112",
    "wof:placetype":"postalcode"
},
  "geometry": {"coordinates":[138.59200000000001,36.3491],"type":"Point"}
}