{
  "type": "Feature",
  "properties": {
    "gn:adm1_name":"Naganoken",
    "gn:adm2_name":"Naganoshi",
    "gn:name":"Kuritakitanaka",
    "iso:country":"JP",
    "wof:name":"380-0927",
    "wof:placetype":"postalcode"
},
  "geometry": {"coordinates":[138.1892,36.6411],"type":"Point"}
}