{
  "type": "Feature",
  "properties": {
    "gn:adm1_name":"Miyazakiken",
    "gn:adm2_name":"Ebinoshi",
    "gn:name":"Kurishita",
    "iso:country":"JP",
    "wof:name":"889-4221",
    "wof:placetype":"postalcode"
},
  "geometry": {"coordinates":[130.81440000000001,32.043],"type":"Point"}
}