{
  "type": "Feature",
  "properties": {
    "gn:adm1_name":"Chibaken",
    "gn:adm2_name":"Futtsushi",
    "gn:name":"Futsutsu",
    "iso:country":"JP",
    "wof:name":"293-0021",
    "wof:placetype":"postalcode"
},
  "geometry": {"coordinates":[139.81870000000001,35.3131],"type":"Point"}
}