{
  "type": "Feature",
  "properties": {
    "gn:adm1_name":"Oosakafu",
    "gn:adm2_name":"Mishimagunshimamotochou",
    "gn:name":"Toudaiji",
    "iso:country":"JP",
    "wof:name":"618-0002",
    "wof:placetype":"postalcode"
},
  "geometry": {"coordinates":[135.6679,34.8895],"type":"Point"}
}