{
  "type": "Feature",
  "properties": {
    "gn:adm1_name":"Hiroshimaken",
    "gn:adm2_name":"Kureshi",
    "gn:name":"Hironakasakochou",
    "iso:country":"JP",
    "wof:name":"737-0105",
    "wof:placetype":"postalcode"
},
  "geometry": {"coordinates":[132.63040000000001,34.2481],"type":"Point"}
}