{
  "type": "Feature",
  "properties": {
    "gn:adm1_name":"Chibaken",
    "gn:adm2_name":"Chibashiinageku",
    "gn:name":"Ayamedai",
    "iso:country":"JP",
    "wof:name":"263-0052",
    "wof:placetype":"postalcode"
},
  "geometry": {"coordinates":[140.1138,35.6492],"type":"Point"}
}