{
  "type": "Feature",
  "properties": {
    "gn:adm1_name":"Chibaken",
    "gn:adm2_name":"Yachiyoshi",
    "gn:name":"Imonokubo",
    "iso:country":"JP",
    "wof:name":"276-0008",
    "wof:placetype":"postalcode"
},
  "geometry": {"coordinates":[140.09460000000001,35.7709],"type":"Point"}
}