{
  "type": "Feature",
  "properties": {
    "gn:adm1_name":"Niigataken",
    "gn:adm2_name":"Kitakanbaragunsuibaramachi",
    "gn:name":"Hinodechou",
    "iso:country":"JP",
    "wof:name":"959-2023",
    "wof:placetype":"postalcode"
},
  "geometry": {"coordinates":[139.23589999999999,37.8356],"type":"Point"}
}