{
  "type": "Feature",
  "properties": {
    "gn:adm1_name":"Kouchiken",
    "gn:adm2_name":"Agawagun'Agawamura",
    "gn:name":"Nagasaka",
    "iso:country":"JP",
    "wof:name":"781-1764",
    "wof:placetype":"postalcode"
},
  "geometry": {"coordinates":[133.08330000000001,33.564],"type":"Point"}
}