{
  "type": "Feature",
  "properties": {
    "gn:adm1_name":"Kyoutofu",
    "gn:adm2_name":"Kameokashi",
    "gn:name":"Kosechou",
    "iso:country":"JP",
    "wof:name":"621-0815",
    "wof:placetype":"postalcode"
},
  "geometry": {"coordinates":[135.5847,35.0078],"type":"Point"}
}