{
  "type": "Feature",
  "properties": {
    "gn:adm1_name":"Toyamaken",
    "gn:adm2_name":"Kurobeshi",
    "gn:name":"Makurano",
    "iso:country":"JP",
    "wof:name":"938-0832",
    "wof:placetype":"postalcode"
},
  "geometry": {"coordinates":[137.47479999999999,36.8545],"type":"Point"}
}