{
  "type": "Feature",
  "properties": {
    "gn:adm1_name":"Hyougoken",
    "gn:adm2_name":"Kanzakigun'Ichikawachou",
    "gn:name":"Obata",
    "iso:country":"JP",
    "wof:name":"679-2318",
    "wof:placetype":"postalcode"
},
  "geometry": {"coordinates":[134.78290000000001,35.008],"type":"Point"}
}