{
  "type": "Feature",
  "properties": {
    "gn:adm1_name":"Aichiken",
    "gn:adm2_name":"Inazawashi",
    "gn:name":"Tairaogarichou",
    "iso:country":"JP",
    "wof:name":"492-8332",
    "wof:placetype":"postalcode"
},
  "geometry": {"coordinates":[136.76740000000001,35.2493],"type":"Point"}
}