{
  "type": "Feature",
  "properties": {
    "gn:adm1_name":"Hiroshimaken",
    "gn:adm2_name":"Ootakeshi",
    "gn:name":"Miyukichou",
    "iso:country":"JP",
    "wof:name":"739-0606",
    "wof:placetype":"postalcode"
},
  "geometry": {"coordinates":[132.22300000000001,34.2285],"type":"Point"}
}