{
  "type": "Feature",
  "properties": {
    "gn:adm1_name":"Hiroshimaken",
    "gn:adm2_name":"Akigunkaitachou",
    "gn:name":"Minamimyoujinmachi",
    "iso:country":"JP",
    "wof:name":"736-0055",
    "wof:placetype":"postalcode"
},
  "geometry": {"coordinates":[132.5265,34.3628],"type":"Point"}
}