{
  "type": "Feature",
  "properties": {
    "gn:adm1_name":"Shigaken",
    "gn:adm2_name":"Oumihachimanshi",
    "gn:name":"Kajiyachou",
    "iso:country":"JP",
    "wof:name":"523-0833",
    "wof:placetype":"postalcode"
},
  "geometry": {"coordinates":[136.09370000000001,35.1404],"type":"Point"}
}