{
  "type": "Feature",
  "properties": {
    "gn:adm1_name":"Shigaken",
    "gn:adm2_name":"Oumihachimanshi",
    "gn:name":"Teppouchou",
    "iso:country":"JP",
    "wof:name":"523-0827",
    "wof:placetype":"postalcode"
},
  "geometry": {"coordinates":[136.09270000000001,35.1428],"type":"Point"}
}