{
  "type": "Feature",
  "properties": {
    "gn:adm1_name":"Yamagataken",
    "gn:adm2_name":"Sakatashi",
    "gn:name":"Itado",
    "iso:country":"JP",
    "wof:name":"999-7774",
    "wof:placetype":"postalcode"
},
  "geometry": {"coordinates":[139.86420000000001,38.8625],"type":"Point"}
}