{
  "type": "Feature",
  "properties": {
    "gn:adm1_name":"Toyamaken",
    "gn:adm2_name":"Toyamashi",
    "gn:name":"Sanbanmachi",
    "iso:country":"JP",
    "wof:name":"930-0059",
    "wof:placetype":"postalcode"
},
  "geometry": {"coordinates":[137.2175,36.6881],"type":"Point"}
}