{
  "type": "Feature",
  "properties": {
    "gn:adm1_name":"Kouchiken",
    "gn:adm2_name":"Hatagun'Ootsukichou",
    "gn:name":"Akadomari",
    "iso:country":"JP",
    "wof:name":"788-0332",
    "wof:placetype":"postalcode"
},
  "geometry": {"coordinates":[132.73589999999999,32.785],"type":"Point"}
}