{
  "type": "Feature",
  "properties": {
    "gn:adm1_name":"Yamanashiken",
    "gn:adm2_name":"Minamitsurugunfujikawaguchikomachi",
    "gn:name":"Ooarashi",
    "iso:country":"JP",
    "wof:name":"401-0335",
    "wof:placetype":"postalcode"
},
  "geometry": {"coordinates":[138.7311,35.4953],"type":"Point"}
}