{
  "type": "Feature",
  "properties": {
    "gn:adm1_name":"Miyagiken",
    "gn:adm2_name":"Kurokawaguntaiwachou",
    "gn:name":"Tsurusuoota",
    "iso:country":"JP",
    "wof:name":"981-3414",
    "wof:placetype":"postalcode"
},
  "geometry": {"coordinates":[140.946,38.391],"type":"Point"}
}