{
  "type": "Feature",
  "properties": {
    "gn:adm1_name":"Chibaken",
    "gn:adm2_name":"Yotsukaidoushi",
    "gn:name":"Shikawatashi",
    "iso:country":"JP",
    "wof:name":"284-0003",
    "wof:placetype":"postalcode"
},
  "geometry": {"coordinates":[140.17019999999999,35.6664],"type":"Point"}
}