{
  "type": "Feature",
  "properties": {
    "gn:adm1_name":"Fukuiken",
    "gn:adm2_name":"Fukuishi",
    "gn:name":"Kurimorichouhama",
    "iso:country":"JP",
    "wof:name":"910-0136",
    "wof:placetype":"postalcode"
},
  "geometry": {"coordinates":[136.24100000000001,36.1154],"type":"Point"}
}