{
  "type": "Feature",
  "properties": {
    "gn:adm1_name":"Kyoutofu",
    "gn:adm2_name":"Kameokashi",
    "gn:name":"Miyazakichouinokura",
    "iso:country":"JP",
    "wof:name":"621-0241",
    "wof:placetype":"postalcode"
},
  "geometry": {"coordinates":[135.49459999999999,35.0301],"type":"Point"}
}