{
  "type": "Feature",
  "properties": {
    "gn:adm1_name":"Tochigiken",
    "gn:adm2_name":"Nasugunnasumachi",
    "gn:name":"Terakootsu(Sonota)",
    "iso:country":"JP",
    "wof:name":"329-3215",
    "wof:placetype":"postalcode"
},
  "geometry": {"coordinates":[140.10679999999999,37.0069],"type":"Point"}
}