{
  "type": "Feature",
  "properties": {
    "gn:adm1_name":"Kyoutofu",
    "gn:adm2_name":"Miyadushi",
    "gn:name":"Kagamigaura",
    "iso:country":"JP",
    "wof:name":"626-0055",
    "wof:placetype":"postalcode"
},
  "geometry": {"coordinates":[135.24799999999999,35.5642],"type":"Point"}
}