{
  "type": "Feature",
  "properties": {
    "gn:adm1_name":"Fukushimaken",
    "gn:adm2_name":"Aiduwakamatsushi",
    "gn:name":"Oomachi",
    "iso:country":"JP",
    "wof:name":"965-0042",
    "wof:placetype":"postalcode"
},
  "geometry": {"coordinates":[139.92840000000001,37.5014],"type":"Point"}
}