{
  "type": "Feature",
  "properties": {
    "gn:adm1_name":"Niigataken",
    "gn:adm2_name":"Kashiwazakishi",
    "gn:name":"Orii",
    "iso:country":"JP",
    "wof:name":"945-1253",
    "wof:placetype":"postalcode"
},
  "geometry": {"coordinates":[138.55840000000001,37.2323],"type":"Point"}
}