{
  "type": "Feature",
  "properties": {
    "gn:adm1_name":"Wakayamaken",
    "gn:adm2_name":"Nagagun'Iwadechou",
    "gn:name":"Akagaito",
    "iso:country":"JP",
    "wof:name":"649-6242",
    "wof:placetype":"postalcode"
},
  "geometry": {"coordinates":[135.29689999999999,34.2698],"type":"Point"}
}