{
  "type": "Feature",
  "properties": {
    "gn:adm1_name":"Chibaken",
    "gn:adm2_name":"Chibashichuuouku",
    "gn:name":"Imaichou",
    "iso:country":"JP",
    "wof:name":"260-0815",
    "wof:placetype":"postalcode"
},
  "geometry": {"coordinates":[140.14089999999999,35.5742],"type":"Point"}
}