{
  "type": "Feature",
  "properties": {
    "gn:adm1_name":"Mieken",
    "gn:adm2_name":"Miegunkomonochou",
    "gn:name":"Ikezoko",
    "iso:country":"JP",
    "wof:name":"510-1221",
    "wof:placetype":"postalcode"
},
  "geometry": {"coordinates":[136.52260000000001,35.035],"type":"Point"}
}