{
  "type": "Feature",
  "properties": {
    "gn:adm1_name":"Naraken",
    "gn:adm2_name":"Ikomashi",
    "gn:name":"Shikanodaihigashi",
    "iso:country":"JP",
    "wof:name":"630-0112",
    "wof:placetype":"postalcode"
},
  "geometry": {"coordinates":[135.75319999999999,34.7347],"type":"Point"}
}