{
  "type": "Feature",
  "properties": {
    "gn:adm1_name":"Aichiken",
    "gn:adm2_name":"Chitaguntaketoyochou",
    "gn:name":"Ushiroda",
    "iso:country":"JP",
    "wof:name":"470-2506",
    "wof:placetype":"postalcode"
},
  "geometry": {"coordinates":[136.92009999999999,34.8502],"type":"Point"}
}