{
  "type": "Feature",
  "properties": {
    "gn:adm1_name":"Tottoriken",
    "gn:adm2_name":"Saihakugunhieduson",
    "gn:name":"Ikanikeisaiganaibaai",
    "iso:country":"JP",
    "wof:name":"689-3500",
    "wof:placetype":"postalcode"
},
  "geometry": {"coordinates":[133.38239999999999,35.4317],"type":"Point"}
}