{
  "type": "Feature",
  "properties": {
    "gn:adm1_name":"Tochigiken",
    "gn:adm2_name":"Ashikagashi",
    "gn:name":"Nishinomiyachou",
    "iso:country":"JP",
    "wof:name":"326-0817",
    "wof:placetype":"postalcode"
},
  "geometry": {"coordinates":[139.44210000000001,36.3431],"type":"Point"}
}