{
  "type": "Feature",
  "properties": {
    "gn:adm1_name":"Toyamaken",
    "gn:adm2_name":"Toyamashi",
    "gn:name":"Akaemachi",
    "iso:country":"JP",
    "wof:name":"930-0855",
    "wof:placetype":"postalcode"
},
  "geometry": {"coordinates":[137.21879999999999,36.7009],"type":"Point"}
}