{
  "type": "Feature",
  "properties": {
    "gn:adm1_name":"Niigataken",
    "gn:adm2_name":"Odiyashi",
    "gn:name":"Jounai",
    "iso:country":"JP",
    "wof:name":"947-0028",
    "wof:placetype":"postalcode"
},
  "geometry": {"coordinates":[138.7937,37.313],"type":"Point"}
}