{
  "type": "Feature",
  "properties": {
    "gn:adm1_name":"Aichiken",
    "gn:adm2_name":"Owariasahishi",
    "gn:name":"Kitayamachoukitayama",
    "iso:country":"JP",
    "wof:name":"488-0056",
    "wof:placetype":"postalcode"
},
  "geometry": {"coordinates":[137.04089999999999,35.2108],"type":"Point"}
}