{
  "type": "Feature",
  "properties": {
    "gn:adm1_name":"Kyoutofu",
    "gn:adm2_name":"Kyoutoshifushimiku",
    "gn:name":"Kyoumachikita",
    "iso:country":"JP",
    "wof:name":"612-8086",
    "wof:placetype":"postalcode"
},
  "geometry": {"coordinates":[135.76499999999999,34.9402],"type":"Point"}
}