{
  "type": "Feature",
  "properties": {
    "gn:adm1_name":"Kyoutofu",
    "gn:adm2_name":"Kyoutoshiminamiku",
    "gn:name":"Kisshouintakahatachou",
    "iso:country":"JP",
    "wof:name":"601-8332",
    "wof:placetype":"postalcode"
},
  "geometry": {"coordinates":[135.73660000000001,34.9711],"type":"Point"}
}