{
  "type": "Feature",
  "properties": {
    "gn:adm1_name":"Ishikawaken",
    "gn:adm2_name":"Hakuishi",
    "gn:name":"Chijimachi",
    "iso:country":"JP",
    "wof:name":"925-0012",
    "wof:placetype":"postalcode"
},
  "geometry": {"coordinates":[136.80119999999999,36.9275],"type":"Point"}
}