{
  "type": "Feature",
  "properties": {
    "gn:adm1_name":"Toukyouto",
    "gn:adm2_name":"Ooshimaooshimamachi",
    "gn:name":"Ikanikeisaiganaibaai",
    "iso:country":"JP",
    "wof:name":"100-0100",
    "wof:placetype":"postalcode"
},
  "geometry": {"coordinates":[139.40819999999999,34.6857],"type":"Point"}
}