{
  "type": "Feature",
  "properties": {
    "gn:adm1_name":"Ishikawaken",
    "gn:adm2_name":"Kahokugun'Unokemachi",
    "gn:name":"Karugano",
    "iso:country":"JP",
    "wof:name":"929-1114",
    "wof:placetype":"postalcode"
},
  "geometry": {"coordinates":[136.7132,36.7093],"type":"Point"}
}