{
  "type": "Feature",
  "properties": {
    "gn:adm1_name":"Niigataken",
    "gn:adm2_name":"Nakakanbaragunkamedamachi",
    "gn:name":"Sunaoka",
    "iso:country":"JP",
    "wof:name":"950-0132",
    "wof:placetype":"postalcode"
},
  "geometry": {"coordinates":[139.12299999999999,37.8648],"type":"Point"}
}