{
  "type": "Feature",
  "properties": {
    "gn:adm1_name":"Gifuken",
    "gn:adm2_name":"Motosugunmotosuchou",
    "gn:name":"Hourinji",
    "iso:country":"JP",
    "wof:name":"501-1202",
    "wof:placetype":"postalcode"
},
  "geometry": {"coordinates":[136.6738,35.4981],"type":"Point"}
}