{
  "type": "Feature",
  "properties": {
    "gn:adm1_name":"Fukuokaken",
    "gn:adm2_name":"Fukuokashihakataku",
    "gn:name":"Ooi",
    "iso:country":"JP",
    "wof:name":"812-0001",
    "wof:placetype":"postalcode"
},
  "geometry": {"coordinates":[130.4436,33.6047],"type":"Point"}
}