{
  "type": "Feature",
  "properties": {
    "gn:adm1_name":"Tochigiken",
    "gn:adm2_name":"Nasugunnasumachi",
    "gn:name":"Yanaze",
    "iso:country":"JP",
    "wof:name":"329-3434",
    "wof:placetype":"postalcode"
},
  "geometry": {"coordinates":[140.1507,36.9421],"type":"Point"}
}