{
  "type": "Feature",
  "properties": {
    "gn:adm1_name":"Yamagataken",
    "gn:adm2_name":"Nishimurayamagun'Ooemachi",
    "gn:name":"Kuromori",
    "iso:country":"JP",
    "wof:name":"990-1276",
    "wof:placetype":"postalcode"
},
  "geometry": {"coordinates":[140.08539999999999,38.3826],"type":"Point"}
}