{
  "type": "Feature",
  "properties": {
    "gn:adm1_name":"Niigataken",
    "gn:adm2_name":"Sadogunsawatamachi",
    "gn:name":"Ichinosawa",
    "iso:country":"JP",
    "wof:name":"952-1302",
    "wof:placetype":"postalcode"
},
  "geometry": {"coordinates":[138.33670000000001,38.0131],"type":"Point"}
}