{
  "type": "Feature",
  "properties": {
    "gn:adm1_name":"Niigataken",
    "gn:adm2_name":"Nagaokashi",
    "gn:name":"Omotemachi",
    "iso:country":"JP",
    "wof:name":"940-0071",
    "wof:placetype":"postalcode"
},
  "geometry": {"coordinates":[138.84719999999999,37.4485],"type":"Point"}
}