{
  "type": "Feature",
  "properties": {
    "gn:adm1_name":"Gifuken",
    "gn:adm2_name":"Sekishi",
    "gn:name":"Shirakawachou",
    "iso:country":"JP",
    "wof:name":"501-3868",
    "wof:placetype":"postalcode"
},
  "geometry": {"coordinates":[136.91659999999999,35.4852],"type":"Point"}
}