{
  "type": "Feature",
  "properties": {
    "gn:adm1_name":"Hyougoken",
    "gn:adm2_name":"Onoshi",
    "gn:name":"Yamadachou",
    "iso:country":"JP",
    "wof:name":"675-1321",
    "wof:placetype":"postalcode"
},
  "geometry": {"coordinates":[134.9676,34.8362],"type":"Point"}
}