{
  "type": "Feature",
  "properties": {
    "gn:adm1_name":"Aichiken",
    "gn:adm2_name":"Shinshiroshi",
    "gn:name":"Kuroda",
    "iso:country":"JP",
    "wof:name":"441-1332",
    "wof:placetype":"postalcode"
},
  "geometry": {"coordinates":[137.5128,34.87],"type":"Point"}
}