{
  "type": "Feature",
  "properties": {
    "gn:adm1_name":"Nagasakiken",
    "gn:adm2_name":"Shimabarashi",
    "gn:name":"Urata",
    "iso:country":"JP",
    "wof:name":"855-0817",
    "wof:placetype":"postalcode"
},
  "geometry": {"coordinates":[130.37309999999999,32.7776],"type":"Point"}
}