{
  "type": "Feature",
  "properties": {
    "gn:adm1_name":"Shizuokaken",
    "gn:adm2_name":"Hamakitashi",
    "gn:name":"Nakaze",
    "iso:country":"JP",
    "wof:name":"434-0012",
    "wof:placetype":"postalcode"
},
  "geometry": {"coordinates":[137.81110000000001,34.8248],"type":"Point"}
}