{
  "type": "Feature",
  "properties": {
    "gn:adm1_name":"Shigaken",
    "gn:adm2_name":"Ootsushi",
    "gn:name":"Yanagawa",
    "iso:country":"JP",
    "wof:name":"520-0014",
    "wof:placetype":"postalcode"
},
  "geometry": {"coordinates":[135.85919999999999,35.0321],"type":"Point"}
}