{
  "type": "Feature",
  "properties": {
    "gn:adm1_name":"Ooitaken",
    "gn:adm2_name":"Ooitashi",
    "gn:name":"Yumegaoka",
    "iso:country":"JP",
    "wof:name":"870-0958",
    "wof:placetype":"postalcode"
},
  "geometry": {"coordinates":[131.6437,33.2137],"type":"Point"}
}