{
  "type": "Feature",
  "properties": {
    "gn:adm1_name":"Hyougoken",
    "gn:adm2_name":"Akashishi",
    "gn:name":"Uenomaru",
    "iso:country":"JP",
    "wof:name":"673-0846",
    "wof:placetype":"postalcode"
},
  "geometry": {"coordinates":[134.9975,34.6537],"type":"Point"}
}