{
  "type": "Feature",
  "properties": {
    "gn:adm1_name":"Aichiken",
    "gn:adm2_name":"Toyohashishi",
    "gn:name":"Fukushimachou",
    "iso:country":"JP",
    "wof:name":"441-8005",
    "wof:placetype":"postalcode"
},
  "geometry": {"coordinates":[137.33779999999999,34.7698],"type":"Point"}
}