{
  "type": "Feature",
  "properties": {
    "gn:adm1_name":"Okayamaken",
    "gn:adm2_name":"Bizenshi",
    "gn:name":"Tsurumi",
    "iso:country":"JP",
    "wof:name":"705-0025",
    "wof:placetype":"postalcode"
},
  "geometry": {"coordinates":[134.1952,34.7058],"type":"Point"}
}