{
  "type": "Feature",
  "properties": {
    "gn:adm1_name":"Aichiken",
    "gn:adm2_name":"Okazakishi",
    "gn:name":"Kamodachou",
    "iso:country":"JP",
    "wof:name":"444-2121",
    "wof:placetype":"postalcode"
},
  "geometry": {"coordinates":[137.16829999999999,34.9817],"type":"Point"}
}