{
  "type": "Feature",
  "properties": {
    "gn:adm1_name":"Nagasakiken",
    "gn:adm2_name":"Saseboshi",
    "gn:name":"Kashimaechou",
    "iso:country":"JP",
    "wof:name":"858-0922",
    "wof:placetype":"postalcode"
},
  "geometry": {"coordinates":[129.68340000000001,33.1615],"type":"Point"}
}