{
  "type": "Feature",
  "properties": {
    "gn:adm1_name":"Fukushimaken",
    "gn:adm2_name":"Nihonmatsushi",
    "gn:name":"Shimadera",
    "iso:country":"JP",
    "wof:name":"964-0922",
    "wof:placetype":"postalcode"
},
  "geometry": {"coordinates":[140.5017,37.5916],"type":"Point"}
}