{
  "type": "Feature",
  "properties": {
    "gn:adm1_name":"Aichiken",
    "gn:adm2_name":"Tokonameshi",
    "gn:name":"Tarumichou",
    "iso:country":"JP",
    "wof:name":"479-0826",
    "wof:placetype":"postalcode"
},
  "geometry": {"coordinates":[136.845,34.8744],"type":"Point"}
}