{
  "type": "Feature",
  "properties": {
    "gn:adm1_name":"Kyoutofu",
    "gn:adm2_name":"Kyoutoshiminamiku",
    "gn:name":"Kamitobadaimotsuchou",
    "iso:country":"JP",
    "wof:name":"601-8121",
    "wof:placetype":"postalcode"
},
  "geometry": {"coordinates":[135.75059999999999,34.9683],"type":"Point"}
}