{
  "type": "Feature",
  "properties": {
    "gn:adm1_name":"Oosakafu",
    "gn:adm2_name":"Habikinoshi",
    "gn:name":"Shimaizumi",
    "iso:country":"JP",
    "wof:name":"583-0881",
    "wof:placetype":"postalcode"
},
  "geometry": {"coordinates":[135.58170000000001,34.5766],"type":"Point"}
}