{
  "type": "Feature",
  "properties": {
    "gn:adm1_name":"Fukushimaken",
    "gn:adm2_name":"Yamagunnishiaidumachi",
    "gn:name":"Onomoto",
    "iso:country":"JP",
    "wof:name":"969-4402",
    "wof:placetype":"postalcode"
},
  "geometry": {"coordinates":[139.66139999999999,37.5898],"type":"Point"}
}