{
  "type": "Feature",
  "properties": {
    "gn:adm1_name":"Oosakafu",
    "gn:adm2_name":"Oosakashihigashiyodogawaku",
    "gn:name":"Daidouminami",
    "iso:country":"JP",
    "wof:name":"533-0012",
    "wof:placetype":"postalcode"
},
  "geometry": {"coordinates":[135.54900000000001,34.7428],"type":"Point"}
}