{
  "type": "Feature",
  "properties": {
    "gn:adm1_name":"Ibarakiken",
    "gn:adm2_name":"Makabegunkyouwamachi",
    "gn:name":"Yahata",
    "iso:country":"JP",
    "wof:name":"309-1112",
    "wof:placetype":"postalcode"
},
  "geometry": {"coordinates":[140.05019999999999,36.3198],"type":"Point"}
}