{
  "type": "Feature",
  "properties": {
    "gn:adm1_name":"Wakayamaken",
    "gn:adm2_name":"Higashimurogunnachikatsuurachou",
    "gn:name":"Tagaito",
    "iso:country":"JP",
    "wof:name":"649-5462",
    "wof:placetype":"postalcode"
},
  "geometry": {"coordinates":[135.83920000000001,33.6655],"type":"Point"}
}