{
  "type": "Feature",
  "properties": {
    "gn:adm1_name":"Oosakafu",
    "gn:adm2_name":"Neyagawashi",
    "gn:name":"Kansoudukachou",
    "iso:country":"JP",
    "wof:name":"572-0008",
    "wof:placetype":"postalcode"
},
  "geometry": {"coordinates":[135.64160000000001,34.785],"type":"Point"}
}