{
  "type": "Feature",
  "properties": {
    "gn:adm1_name":"Fukuiken",
    "gn:adm2_name":"Oonoshi",
    "gn:name":"Seiryuu",
    "iso:country":"JP",
    "wof:name":"912-0092",
    "wof:placetype":"postalcode"
},
  "geometry": {"coordinates":[136.48079999999999,35.9818],"type":"Point"}
}