{
  "type": "Feature",
  "properties": {
    "gn:adm1_name":"Nagasakiken",
    "gn:adm2_name":"Matsuurashi",
    "gn:name":"Shisachouyokobetamen",
    "iso:country":"JP",
    "wof:name":"859-4517",
    "wof:placetype":"postalcode"
},
  "geometry": {"coordinates":[129.72999999999999,33.2992],"type":"Point"}
}