{
  "type": "Feature",
  "properties": {
    "gn:adm1_name":"Kagoshimaken",
    "gn:adm2_name":"Izumishi",
    "gn:name":"Rokugatsudamachi",
    "iso:country":"JP",
    "wof:name":"899-0126",
    "wof:placetype":"postalcode"
},
  "geometry": {"coordinates":[130.34219999999999,32.1085],"type":"Point"}
}