{
  "type": "Feature",
  "properties": {
    "gn:adm1_name":"Yamanashiken",
    "gn:adm2_name":"Koufushi",
    "gn:name":"Iwakubochou",
    "iso:country":"JP",
    "wof:name":"400-0013",
    "wof:placetype":"postalcode"
},
  "geometry": {"coordinates":[138.58250000000001,35.6809],"type":"Point"}
}