{
  "type": "Feature",
  "properties": {
    "gn:adm1_name":"Aichiken",
    "gn:adm2_name":"Okazakishi",
    "gn:name":"Nakajimanakamachi",
    "iso:country":"JP",
    "wof:name":"444-0224",
    "wof:placetype":"postalcode"
},
  "geometry": {"coordinates":[137.1223,34.8891],"type":"Point"}
}