{
  "type": "Feature",
  "properties": {
    "gn:adm1_name":"Chibaken",
    "gn:adm2_name":"Katorigunyamadamachi",
    "gn:name":"Shidaka",
    "iso:country":"JP",
    "wof:name":"289-0413",
    "wof:placetype":"postalcode"
},
  "geometry": {"coordinates":[140.61529999999999,35.7859],"type":"Point"}
}