{
  "type": "Feature",
  "properties": {
    "gn:adm1_name":"Toukyouto",
    "gn:adm2_name":"Shinagawaku",
    "gn:name":"Minamishinagawa",
    "iso:country":"JP",
    "wof:name":"140-0004",
    "wof:placetype":"postalcode"
},
  "geometry": {"coordinates":[139.74109999999999,35.6118],"type":"Point"}
}