{
  "type": "Feature",
  "properties": {
    "gn:adm1_name":"Saitamaken",
    "gn:adm2_name":"Sayamashi",
    "gn:name":"Sayamadai",
    "iso:country":"JP",
    "wof:name":"350-1304",
    "wof:placetype":"postalcode"
},
  "geometry": {"coordinates":[139.43369999999999,35.855],"type":"Point"}
}