{
  "type": "Feature",
  "properties": {
    "gn:adm1_name":"Kagoshimaken",
    "gn:adm2_name":"Satsumaguntsurudachou",
    "gn:name":"Koushi",
    "iso:country":"JP",
    "wof:name":"895-2102",
    "wof:placetype":"postalcode"
},
  "geometry": {"coordinates":[130.4813,31.9614],"type":"Point"}
}