{
  "type": "Feature",
  "properties": {
    "gn:adm1_name":"Kanagawaken",
    "gn:adm2_name":"Ashigarakamigun'Ooimachi",
    "gn:name":"Kaneko",
    "iso:country":"JP",
    "wof:name":"258-0019",
    "wof:placetype":"postalcode"
},
  "geometry": {"coordinates":[139.15299999999999,35.3334],"type":"Point"}
}