{
  "type": "Feature",
  "properties": {
    "gn:adm1_name":"Okayamaken",
    "gn:adm2_name":"Okayamashi",
    "gn:name":"Yai",
    "iso:country":"JP",
    "wof:name":"709-0606",
    "wof:placetype":"postalcode"
},
  "geometry": {"coordinates":[134.06039999999999,34.706],"type":"Point"}
}