{
  "type": "Feature",
  "properties": {
    "gn:adm1_name":"Sagaken",
    "gn:adm2_name":"Tosushi",
    "gn:name":"Shukumachi",
    "iso:country":"JP",
    "wof:name":"841-0052",
    "wof:placetype":"postalcode"
},
  "geometry": {"coordinates":[130.50460000000001,33.3774],"type":"Point"}
}