{
  "type": "Feature",
  "properties": {
    "gn:adm1_name":"Miyazakiken",
    "gn:adm2_name":"Miyazakishi",
    "gn:name":"Adumachou",
    "iso:country":"JP",
    "wof:name":"880-0864",
    "wof:placetype":"postalcode"
},
  "geometry": {"coordinates":[131.43260000000001,31.9044],"type":"Point"}
}