{
  "type": "Feature",
  "properties": {
    "gn:adm1_name":"Okayamaken",
    "gn:adm2_name":"Kurashikishi",
    "gn:name":"Tsurajimachounishinoura",
    "iso:country":"JP",
    "wof:name":"712-8001",
    "wof:placetype":"postalcode"
},
  "geometry": {"coordinates":[133.71469999999999,34.5532],"type":"Point"}
}