{
  "type": "Feature",
  "properties": {
    "gn:adm1_name":"Okayamaken",
    "gn:adm2_name":"Okayamashi",
    "gn:name":"Takewara",
    "iso:country":"JP",
    "wof:name":"709-0614",
    "wof:placetype":"postalcode"
},
  "geometry": {"coordinates":[134.05539999999999,34.6892],"type":"Point"}
}