{
  "type": "Feature",
  "properties": {
    "gn:adm1_name":"Fukushimaken",
    "gn:adm2_name":"Iwakishi",
    "gn:name":"Juugaoka",
    "iso:country":"JP",
    "wof:name":"970-8033",
    "wof:placetype":"postalcode"
},
  "geometry": {"coordinates":[140.89240000000001,37.0275],"type":"Point"}
}