{
  "type": "Feature",
  "properties": {
    "gn:adm1_name":"Kyoutofu",
    "gn:adm2_name":"Kyoutoshiukyouku",
    "gn:name":"Narutakishirasuna",
    "iso:country":"JP",
    "wof:name":"616-8257",
    "wof:placetype":"postalcode"
},
  "geometry": {"coordinates":[135.70240000000001,35.0374],"type":"Point"}
}