{
  "type": "Feature",
  "properties": {
    "gn:adm1_name":"Kumamotoken",
    "gn:adm2_name":"Asogunnishiharamura",
    "gn:name":"Miyayama",
    "iso:country":"JP",
    "wof:name":"861-2405",
    "wof:placetype":"postalcode"
},
  "geometry": {"coordinates":[130.91929999999999,32.8236],"type":"Point"}
}