{
  "type": "Feature",
  "properties": {
    "gn:adm1_name":"Tochigiken",
    "gn:adm2_name":"Hagagunmotegimachi",
    "gn:name":"Ikanikeisaiganaibaai",
    "iso:country":"JP",
    "wof:name":"321-3500",
    "wof:placetype":"postalcode"
},
  "geometry": {"coordinates":[140.18729999999999,36.5342],"type":"Point"}
}