{
  "type": "Feature",
  "properties": {
    "gn:adm1_name":"Fukushimaken",
    "gn:adm2_name":"Futabagunfutabamachi",
    "gn:name":"Hosoya",
    "iso:country":"JP",
    "wof:name":"979-1412",
    "wof:placetype":"postalcode"
},
  "geometry": {"coordinates":[141.01519999999999,37.433],"type":"Point"}
}