{
  "type": "Feature",
  "properties": {
    "gn:adm1_name":"Okayamaken",
    "gn:adm2_name":"Joubougunkayouchou",
    "gn:name":"Toyono",
    "iso:country":"JP",
    "wof:name":"716-1101",
    "wof:placetype":"postalcode"
},
  "geometry": {"coordinates":[133.7045,34.8747],"type":"Point"}
}