{
  "type": "Feature",
  "properties": {
    "gn:adm1_name":"Aichiken",
    "gn:adm2_name":"Owariasahishi",
    "gn:name":"Nishiyamachou",
    "iso:country":"JP",
    "wof:name":"488-0824",
    "wof:placetype":"postalcode"
},
  "geometry": {"coordinates":[137.01429999999999,35.1976],"type":"Point"}
}