{
  "type": "Feature",
  "properties": {
    "gn:adm1_name":"Okinawaken",
    "gn:adm2_name":"Shimajirigunhaebaruchou",
    "gn:name":"Arakawa",
    "iso:country":"JP",
    "wof:name":"901-1105",
    "wof:placetype":"postalcode"
},
  "geometry": {"coordinates":[127.72709999999999,26.2061],"type":"Point"}
}