{
  "type": "Feature",
  "properties": {
    "gn:adm1_name":"Miyagiken",
    "gn:adm2_name":"Kuriharagunkannarichou",
    "gn:name":"Inarimae",
    "iso:country":"JP",
    "wof:name":"989-5127",
    "wof:placetype":"postalcode"
},
  "geometry": {"coordinates":[141.0797,38.8249],"type":"Point"}
}