{
  "type": "Feature",
  "properties": {
    "gn:adm1_name":"Tottoriken",
    "gn:adm2_name":"Kurayoshishi",
    "gn:name":"Sugegahara",
    "iso:country":"JP",
    "wof:name":"682-0843",
    "wof:placetype":"postalcode"
},
  "geometry": {"coordinates":[133.8212,35.369],"type":"Point"}
}