{
  "type": "Feature",
  "properties": {
    "gn:adm1_name":"Kanagawaken",
    "gn:adm2_name":"Yokohamashiminamiku",
    "gn:name":"Karasawa",
    "iso:country":"JP",
    "wof:name":"232-0034",
    "wof:placetype":"postalcode"
},
  "geometry": {"coordinates":[139.636,35.4321],"type":"Point"}
}