{
  "type": "Feature",
  "properties": {
    "gn:adm1_name":"Kouchiken",
    "gn:adm2_name":"Takaokagunhayamamura",
    "gn:name":"Shiraishihei",
    "iso:country":"JP",
    "wof:name":"785-0213",
    "wof:placetype":"postalcode"
},
  "geometry": {"coordinates":[133.18539999999999,33.4435],"type":"Point"}
}