{
  "type": "Feature",
  "properties": {
    "gn:adm1_name":"Ehimeken",
    "gn:adm2_name":"Niihamashi",
    "gn:name":"Takatsuchou",
    "iso:country":"JP",
    "wof:name":"792-0867",
    "wof:placetype":"postalcode"
},
  "geometry": {"coordinates":[133.29859999999999,33.9723],"type":"Point"}
}