{
  "type": "Feature",
  "properties": {
    "gn:adm1_name":"Niigataken",
    "gn:adm2_name":"Araishi",
    "gn:name":"Tsuboyama",
    "iso:country":"JP",
    "wof:name":"944-0222",
    "wof:placetype":"postalcode"
},
  "geometry": {"coordinates":[138.30680000000001,36.9868],"type":"Point"}
}