{
  "type": "Feature",
  "properties": {
    "gn:adm1_name":"Fukushimaken",
    "gn:adm2_name":"Nihonmatsushi",
    "gn:name":"Miyamoto",
    "iso:country":"JP",
    "wof:name":"964-0951",
    "wof:placetype":"postalcode"
},
  "geometry": {"coordinates":[140.48439999999999,37.5788],"type":"Point"}
}