{
  "type": "Feature",
  "properties": {
    "gn:adm1_name":"Niigataken",
    "gn:adm2_name":"Niitsushi",
    "gn:name":"Warabisone",
    "iso:country":"JP",
    "wof:name":"956-0056",
    "wof:placetype":"postalcode"
},
  "geometry": {"coordinates":[139.06610000000001,37.7918],"type":"Point"}
}