{
  "type": "Feature",
  "properties": {
    "gn:adm1_name":"Saitamaken",
    "gn:adm2_name":"Hikigunyoshimimachi",
    "gn:name":"Ookushi",
    "iso:country":"JP",
    "wof:name":"355-0134",
    "wof:placetype":"postalcode"
},
  "geometry": {"coordinates":[139.46639999999999,36.0242],"type":"Point"}
}