{
  "type": "Feature",
  "properties": {
    "gn:adm1_name":"Fukuokaken",
    "gn:adm2_name":"Kitakyuushuushiyahatanishiku",
    "gn:name":"Kusubashihigashi",
    "iso:country":"JP",
    "wof:name":"807-1142",
    "wof:placetype":"postalcode"
},
  "geometry": {"coordinates":[130.732,33.791],"type":"Point"}
}