{
  "type": "Feature",
  "properties": {
    "gn:adm1_name":"Tottoriken",
    "gn:adm2_name":"Yazugunwakasachou",
    "gn:name":"Yuwara",
    "iso:country":"JP",
    "wof:name":"680-0725",
    "wof:placetype":"postalcode"
},
  "geometry": {"coordinates":[134.4315,35.3416],"type":"Point"}
}