{
  "type": "Feature",
  "properties": {
    "gn:adm1_name":"Ehimeken",
    "gn:adm2_name":"Uwajimashi",
    "gn:name":"Ooura(Sonota)",
    "iso:country":"JP",
    "wof:name":"798-0002",
    "wof:placetype":"postalcode"
},
  "geometry": {"coordinates":[132.5496,33.2389],"type":"Point"}
}