{
  "type": "Feature",
  "properties": {
    "gn:adm1_name":"Fukushimaken",
    "gn:adm2_name":"Tamuragunfunehikimachi",
    "gn:name":"Ookura",
    "iso:country":"JP",
    "wof:name":"963-4435",
    "wof:placetype":"postalcode"
},
  "geometry": {"coordinates":[140.57310000000001,37.4898],"type":"Point"}
}