{
  "type": "Feature",
  "properties": {
    "gn:adm1_name":"Aichiken",
    "gn:adm2_name":"Toyohashishi",
    "gn:name":"Kamochou",
    "iso:country":"JP",
    "wof:name":"441-1101",
    "wof:placetype":"postalcode"
},
  "geometry": {"coordinates":[137.4358,34.8373],"type":"Point"}
}