{
  "type": "Feature",
  "properties": {
    "gn:adm1_name":"Fukushimaken",
    "gn:adm2_name":"Shirakawashi",
    "gn:name":"Fuujinshita",
    "iso:country":"JP",
    "wof:name":"961-0861",
    "wof:placetype":"postalcode"
},
  "geometry": {"coordinates":[140.20259999999999,37.124],"type":"Point"}
}