{
  "type": "Feature",
  "properties": {
    "gn:adm1_name":"Aichiken",
    "gn:adm2_name":"Kitashitaragunshitarachou",
    "gn:name":"Ikanikeisaiganaibaai",
    "iso:country":"JP",
    "wof:name":"441-2300",
    "wof:placetype":"postalcode"
},
  "geometry": {"coordinates":[137.57050000000001,35.093],"type":"Point"}
}