{
  "type": "Feature",
  "properties": {
    "gn:adm1_name":"Ishikawaken",
    "gn:adm2_name":"Kagashi",
    "gn:name":"Daishoujidaimyoudakemachi",
    "iso:country":"JP",
    "wof:name":"922-0023",
    "wof:placetype":"postalcode"
},
  "geometry": {"coordinates":[136.3175,36.3107],"type":"Point"}
}