{
  "type": "Feature",
  "properties": {
    "gn:adm1_name":"Gunmaken",
    "gn:adm2_name":"Tatebayashishi",
    "gn:name":"Irikayachou",
    "iso:country":"JP",
    "wof:name":"374-0045",
    "wof:placetype":"postalcode"
},
  "geometry": {"coordinates":[139.5027,36.2137],"type":"Point"}
}