{
  "type": "Feature",
  "properties": {
    "gn:adm1_name":"Gifuken",
    "gn:adm2_name":"Kamogunshirakawachou",
    "gn:name":"Katou",
    "iso:country":"JP",
    "wof:name":"509-1107",
    "wof:placetype":"postalcode"
},
  "geometry": {"coordinates":[137.1763,35.6147],"type":"Point"}
}