{
  "type": "Feature",
  "properties": {
    "gn:adm1_name":"Yamagataken",
    "gn:adm2_name":"Sakatashi",
    "gn:name":"Kubota",
    "iso:country":"JP",
    "wof:name":"999-8156",
    "wof:placetype":"postalcode"
},
  "geometry": {"coordinates":[139.90549999999999,38.9267],"type":"Point"}
}