{
  "type": "Feature",
  "properties": {
    "gn:adm1_name":"Toyamaken",
    "gn:adm2_name":"Nakaniikawagunkamiichimachi",
    "gn:name":"Shoinshin",
    "iso:country":"JP",
    "wof:name":"930-0358",
    "wof:placetype":"postalcode"
},
  "geometry": {"coordinates":[137.33869999999999,36.7012],"type":"Point"}
}