{
  "type": "Feature",
  "properties": {
    "gn:adm1_name":"Yamaguchiken",
    "gn:adm2_name":"Minegunshuuhouchou",
    "gn:name":"Akiyoshi",
    "iso:country":"JP",
    "wof:name":"754-0511",
    "wof:placetype":"postalcode"
},
  "geometry": {"coordinates":[131.3006,34.2147],"type":"Point"}
}