{
  "type": "Feature",
  "properties": {
    "gn:adm1_name":"Aichiken",
    "gn:adm2_name":"Toyoakeshi",
    "gn:name":"Kutsukakechou(Shimotakane)",
    "iso:country":"JP",
    "wof:name":"470-1106",
    "wof:placetype":"postalcode"
},
  "geometry": {"coordinates":[137.029,35.0643],"type":"Point"}
}