{
  "type": "Feature",
  "properties": {
    "gn:adm1_name":"Chibaken",
    "gn:adm2_name":"Tateyamashi",
    "gn:name":"Daijinguu",
    "iso:country":"JP",
    "wof:name":"294-0233",
    "wof:placetype":"postalcode"
},
  "geometry": {"coordinates":[139.83600000000001,34.9249],"type":"Point"}
}