{
  "type": "Feature",
  "properties": {
    "gn:adm1_name":"Chibaken",
    "gn:adm2_name":"Futtsushi",
    "gn:name":"Minato",
    "iso:country":"JP",
    "wof:name":"299-1607",
    "wof:placetype":"postalcode"
},
  "geometry": {"coordinates":[139.87270000000001,35.2201],"type":"Point"}
}