{
  "type": "Feature",
  "properties": {
    "gn:adm1_name":"Fukuokaken",
    "gn:adm2_name":"Kitakyuushuushimojiku",
    "gn:name":"Hishakuda",
    "iso:country":"JP",
    "wof:name":"801-0813",
    "wof:placetype":"postalcode"
},
  "geometry": {"coordinates":[130.99289999999999,33.9074],"type":"Point"}
}