{
  "type": "Feature",
  "properties": {
    "gn:adm1_name":"Aichiken",
    "gn:adm2_name":"Toyohashishi",
    "gn:name":"Kitayamachou",
    "iso:country":"JP",
    "wof:name":"441-8105",
    "wof:placetype":"postalcode"
},
  "geometry": {"coordinates":[137.39609999999999,34.7373],"type":"Point"}
}