{
  "type": "Feature",
  "properties": {
    "gn:adm1_name":"Shigaken",
    "gn:adm2_name":"Koukaguntsuchiyamachou",
    "gn:name":"Ayukawa",
    "iso:country":"JP",
    "wof:name":"528-0202",
    "wof:placetype":"postalcode"
},
  "geometry": {"coordinates":[136.33770000000001,34.958],"type":"Point"}
}