{
  "type": "Feature",
  "properties": {
    "gn:adm1_name":"Aichiken",
    "gn:adm2_name":"Nagoyashinakagawaku",
    "gn:name":"Yanagiborichou",
    "iso:country":"JP",
    "wof:name":"454-0006",
    "wof:placetype":"postalcode"
},
  "geometry": {"coordinates":[136.88630000000001,35.1554],"type":"Point"}
}