{
  "type": "Feature",
  "properties": {
    "gn:adm1_name":"Ishikawaken",
    "gn:adm2_name":"Kahokuguntsubatamachi",
    "gn:name":"Bodaiji",
    "iso:country":"JP",
    "wof:name":"929-0308",
    "wof:placetype":"postalcode"
},
  "geometry": {"coordinates":[136.76509999999999,36.7336],"type":"Point"}
}