{
  "type": "Feature",
  "properties": {
    "gn:adm1_name":"Gifuken",
    "gn:adm2_name":"Gujougunshirotorichou",
    "gn:name":"Onji",
    "iso:country":"JP",
    "wof:name":"501-5115",
    "wof:placetype":"postalcode"
},
  "geometry": {"coordinates":[136.88050000000001,35.8846],"type":"Point"}
}