{
  "type": "Feature",
  "properties": {
    "gn:adm1_name":"Hyougoken",
    "gn:adm2_name":"Kanzakigunkanzakichou",
    "gn:name":"Sugi",
    "iso:country":"JP",
    "wof:name":"679-2433",
    "wof:placetype":"postalcode"
},
  "geometry": {"coordinates":[134.78399999999999,35.1012],"type":"Point"}
}