{
  "type": "Feature",
  "properties": {
    "gn:adm1_name":"Ishikawaken",
    "gn:adm2_name":"Komatsushi",
    "gn:name":"Teramachi",
    "iso:country":"JP",
    "wof:name":"923-0932",
    "wof:placetype":"postalcode"
},
  "geometry": {"coordinates":[136.44720000000001,36.4033],"type":"Point"}
}