{
  "type": "Feature",
  "properties": {
    "gn:adm1_name":"Hyougoken",
    "gn:adm2_name":"Nishinomiyashi",
    "gn:name":"Higashiyamadai",
    "iso:country":"JP",
    "wof:name":"669-1133",
    "wof:placetype":"postalcode"
},
  "geometry": {"coordinates":[135.31299999999999,34.8324],"type":"Point"}
}