{
  "type": "Feature",
  "properties": {
    "gn:adm1_name":"Shigaken",
    "gn:adm2_name":"Takashimagunkutsukimura",
    "gn:name":"Furukawa",
    "iso:country":"JP",
    "wof:name":"520-1422",
    "wof:placetype":"postalcode"
},
  "geometry": {"coordinates":[135.9014,35.3337],"type":"Point"}
}