{
  "type": "Feature",
  "properties": {
    "gn:adm1_name":"Ehimeken",
    "gn:adm2_name":"Kitauwagunyoshidachou",
    "gn:name":"Tsuruma(Sonota)",
    "iso:country":"JP",
    "wof:name":"799-3761",
    "wof:placetype":"postalcode"
},
  "geometry": {"coordinates":[132.5291,33.2769],"type":"Point"}
}