{
  "type": "Feature",
  "properties": {
    "gn:adm1_name":"Kanagawaken",
    "gn:adm2_name":"Yokohamashikanagawaku",
    "gn:name":"Matsugaoka",
    "iso:country":"JP",
    "wof:name":"221-0843",
    "wof:placetype":"postalcode"
},
  "geometry": {"coordinates":[139.61879999999999,35.4749],"type":"Point"}
}