{
  "type": "Feature",
  "properties": {
    "gn:adm1_name":"Aichiken",
    "gn:adm2_name":"Hekinanshi",
    "gn:name":"Hamadamachi",
    "iso:country":"JP",
    "wof:name":"447-0842",
    "wof:placetype":"postalcode"
},
  "geometry": {"coordinates":[136.98079999999999,34.8655],"type":"Point"}
}