{
  "type": "Feature",
  "properties": {
    "gn:adm1_name":"Fukuiken",
    "gn:adm2_name":"Fukuishi",
    "gn:name":"Wadahigashi",
    "iso:country":"JP",
    "wof:name":"918-8237",
    "wof:placetype":"postalcode"
},
  "geometry": {"coordinates":[136.2484,36.0516],"type":"Point"}
}