{
  "type": "Feature",
  "properties": {
    "gn:adm1_name":"Nagasakiken",
    "gn:adm2_name":"Matsuurashi",
    "gn:name":"Imafukuchounaberubaemen",
    "iso:country":"JP",
    "wof:name":"859-4523",
    "wof:placetype":"postalcode"
},
  "geometry": {"coordinates":[129.79230000000001,33.3436],"type":"Point"}
}