{
  "type": "Feature",
  "properties": {
    "gn:adm1_name":"Miyazakiken",
    "gn:adm2_name":"Hyuugashi",
    "gn:name":"Sonechou",
    "iso:country":"JP",
    "wof:name":"883-0011",
    "wof:placetype":"postalcode"
},
  "geometry": {"coordinates":[131.6473,32.4224],"type":"Point"}
}