{
  "type": "Feature",
  "properties": {
    "gn:adm1_name":"Ibarakiken",
    "gn:adm2_name":"Kujigunsuifumura",
    "gn:name":"Kamitakakura",
    "iso:country":"JP",
    "wof:name":"313-0353",
    "wof:placetype":"postalcode"
},
  "geometry": {"coordinates":[140.45699999999999,36.7268],"type":"Point"}
}