{
  "type": "Feature",
  "properties": {
    "gn:adm1_name":"Naganoken",
    "gn:adm2_name":"Chiisagatagun'Aokimura",
    "gn:name":"Kutsukake",
    "iso:country":"JP",
    "wof:name":"386-1606",
    "wof:placetype":"postalcode"
},
  "geometry": {"coordinates":[138.11250000000001,36.3456],"type":"Point"}
}