{
  "type": "Feature",
  "properties": {
    "gn:adm1_name":"Mieken",
    "gn:adm2_name":"Hisaishi",
    "gn:name":"Sakuragaokachou",
    "iso:country":"JP",
    "wof:name":"514-1111",
    "wof:placetype":"postalcode"
},
  "geometry": {"coordinates":[136.49019999999999,34.6828],"type":"Point"}
}