{
  "type": "Feature",
  "properties": {
    "gn:adm1_name":"Kanagawaken",
    "gn:adm2_name":"Sagamiharashi",
    "gn:name":"Sagamioono",
    "iso:country":"JP",
    "wof:name":"228-0803",
    "wof:placetype":"postalcode"
},
  "geometry": {"coordinates":[139.43469999999999,35.5314],"type":"Point"}
}