{
  "type": "Feature",
  "properties": {
    "gn:adm1_name":"Ibarakiken",
    "gn:adm2_name":"Kashimashi",
    "gn:name":"Hirai",
    "iso:country":"JP",
    "wof:name":"314-0012",
    "wof:placetype":"postalcode"
},
  "geometry": {"coordinates":[140.66650000000001,35.9617],"type":"Point"}
}