{
  "type": "Feature",
  "properties": {
    "gn:adm1_name":"Fukuokaken",
    "gn:adm2_name":"Kitakyuushuushitobataku",
    "gn:name":"Konpirachou",
    "iso:country":"JP",
    "wof:name":"804-0022",
    "wof:placetype":"postalcode"
},
  "geometry": {"coordinates":[130.84100000000001,33.8797],"type":"Point"}
}