{
  "type": "Feature",
  "properties": {
    "gn:adm1_name":"Naganoken",
    "gn:adm2_name":"Minamiadumiguntoyoshinamachi",
    "gn:name":"Toyoshina",
    "iso:country":"JP",
    "wof:name":"399-8205",
    "wof:placetype":"postalcode"
},
  "geometry": {"coordinates":[137.91030000000001,36.2882],"type":"Point"}
}