{
  "type": "Feature",
  "properties": {
    "gn:adm1_name":"Gifuken",
    "gn:adm2_name":"Gifushi",
    "gn:name":"Kanouhigashimaruchou",
    "iso:country":"JP",
    "wof:name":"500-8483",
    "wof:placetype":"postalcode"
},
  "geometry": {"coordinates":[136.7637,35.4035],"type":"Point"}
}