{
  "type": "Feature",
  "properties": {
    "gn:adm1_name":"Ishikawaken",
    "gn:adm2_name":"Fugeshigunnotomachi",
    "gn:name":"Fujinami",
    "iso:country":"JP",
    "wof:name":"927-0441",
    "wof:placetype":"postalcode"
},
  "geometry": {"coordinates":[137.13810000000001,37.2999],"type":"Point"}
}