{
  "type": "Feature",
  "properties": {
    "gn:adm1_name":"Toukyouto",
    "gn:adm2_name":"Tamashi",
    "gn:name":"Ochiai",
    "iso:country":"JP",
    "wof:name":"206-0033",
    "wof:placetype":"postalcode"
},
  "geometry": {"coordinates":[139.4272,35.6199],"type":"Point"}
}