{
  "type": "Feature",
  "properties": {
    "gn:adm1_name":"Hyougoken",
    "gn:adm2_name":"Ibogunmitsuchou",
    "gn:name":"Kurosaki",
    "iso:country":"JP",
    "wof:name":"671-1301",
    "wof:placetype":"postalcode"
},
  "geometry": {"coordinates":[134.5538,34.7747],"type":"Point"}
}