{
  "type": "Feature",
  "properties": {
    "gn:adm1_name":"Fukuiken",
    "gn:adm2_name":"Oonoshi",
    "gn:name":"Ochiai",
    "iso:country":"JP",
    "wof:name":"912-0146",
    "wof:placetype":"postalcode"
},
  "geometry": {"coordinates":[136.58189999999999,35.9866],"type":"Point"}
}