{
  "type": "Feature",
  "properties": {
    "gn:adm1_name":"Shimaneken",
    "gn:adm2_name":"Masudashi",
    "gn:name":"Iwakurachou",
    "iso:country":"JP",
    "wof:name":"698-0014",
    "wof:placetype":"postalcode"
},
  "geometry": {"coordinates":[131.8937,34.6348],"type":"Point"}
}