{
  "type": "Feature",
  "properties": {
    "gn:adm1_name":"Kumamotoken",
    "gn:adm2_name":"Yatsushiroshi",
    "gn:name":"Yuubachou",
    "iso:country":"JP",
    "wof:name":"866-0833",
    "wof:placetype":"postalcode"
},
  "geometry": {"coordinates":[130.61000000000001,32.5014],"type":"Point"}
}