{
  "type": "Feature",
  "properties": {
    "gn:adm1_name":"Fukuokaken",
    "gn:adm2_name":"Oonojoushi",
    "gn:name":"Ooike",
    "iso:country":"JP",
    "wof:name":"816-0904",
    "wof:placetype":"postalcode"
},
  "geometry": {"coordinates":[130.48779999999999,33.5428],"type":"Point"}
}