{
  "type": "Feature",
  "properties": {
    "gn:adm1_name":"Miyazakiken",
    "gn:adm2_name":"Nobeokashi",
    "gn:name":"Shiohamamachi",
    "iso:country":"JP",
    "wof:name":"882-0864",
    "wof:placetype":"postalcode"
},
  "geometry": {"coordinates":[131.67509999999999,32.5408],"type":"Point"}
}