{
  "type": "Feature",
  "properties": {
    "gn:adm1_name":"Fukuiken",
    "gn:adm2_name":"Sakaigunmikunichou",
    "gn:name":"Chuuou",
    "iso:country":"JP",
    "wof:name":"913-0042",
    "wof:placetype":"postalcode"
},
  "geometry": {"coordinates":[136.15780000000001,36.2185],"type":"Point"}
}