{
  "type": "Feature",
  "properties": {
    "gn:adm1_name":"Gifuken",
    "gn:adm2_name":"Gujougunshirotorichou",
    "gn:name":"Nagataki",
    "iso:country":"JP",
    "wof:name":"501-5104",
    "wof:placetype":"postalcode"
},
  "geometry": {"coordinates":[136.83080000000001,35.9235],"type":"Point"}
}