{
  "type": "Feature",
  "properties": {
    "gn:adm1_name":"Aichiken",
    "gn:adm2_name":"Nagoyashiatsutaku",
    "gn:name":"Tenma",
    "iso:country":"JP",
    "wof:name":"456-0034",
    "wof:placetype":"postalcode"
},
  "geometry": {"coordinates":[136.90989999999999,35.1191],"type":"Point"}
}