{
  "type": "Feature",
  "properties": {
    "gn:adm1_name":"Fukuokaken",
    "gn:adm2_name":"Oomutashi",
    "gn:name":"Hanazonomachi",
    "iso:country":"JP",
    "wof:name":"836-0867",
    "wof:placetype":"postalcode"
},
  "geometry": {"coordinates":[130.45160000000001,33.0219],"type":"Point"}
}