{
  "type": "Feature",
  "properties": {
    "gn:adm1_name":"Miyagiken",
    "gn:adm2_name":"Sendaishimiyaginoku",
    "gn:name":"Odawaraushigoyachou",
    "iso:country":"JP",
    "wof:name":"983-0813",
    "wof:placetype":"postalcode"
},
  "geometry": {"coordinates":[140.89439999999999,38.2639],"type":"Point"}
}