{
  "type": "Feature",
  "properties": {
    "gn:adm1_name":"Toyamaken",
    "gn:adm2_name":"Toyamashi",
    "gn:name":"Makida",
    "iso:country":"JP",
    "wof:name":"939-8161",
    "wof:placetype":"postalcode"
},
  "geometry": {"coordinates":[137.2347,36.6139],"type":"Point"}
}