{
  "type": "Feature",
  "properties": {
    "gn:adm1_name":"Mieken",
    "gn:adm2_name":"Agegun'Anouchou",
    "gn:name":"Toukan'Onji",
    "iso:country":"JP",
    "wof:name":"514-2326",
    "wof:placetype":"postalcode"
},
  "geometry": {"coordinates":[136.44399999999999,34.7615],"type":"Point"}
}