{
  "type": "Feature",
  "properties": {
    "gn:adm1_name":"Hyougoken",
    "gn:adm2_name":"Iboguntaishichou",
    "gn:name":"Iwamikamae",
    "iso:country":"JP",
    "wof:name":"671-1545",
    "wof:placetype":"postalcode"
},
  "geometry": {"coordinates":[134.56309999999999,34.8152],"type":"Point"}
}