{
  "type": "Feature",
  "properties": {
    "gn:adm1_name":"Shigaken",
    "gn:adm2_name":"Hikoneshi",
    "gn:name":"Gokurakujichou",
    "iso:country":"JP",
    "wof:name":"522-0231",
    "wof:placetype":"postalcode"
},
  "geometry": {"coordinates":[136.23490000000001,35.2302],"type":"Point"}
}