{
  "type": "Feature",
  "properties": {
    "gn:adm1_name":"Fukuiken",
    "gn:adm2_name":"Obamashi",
    "gn:name":"Ryuuzen",
    "iso:country":"JP",
    "wof:name":"917-0243",
    "wof:placetype":"postalcode"
},
  "geometry": {"coordinates":[135.77959999999999,35.4702],"type":"Point"}
}