{
  "type": "Feature",
  "properties": {
    "gn:adm1_name":"Shizuokaken",
    "gn:adm2_name":"Hamamatsushi",
    "gn:name":"Tatenochou",
    "iso:country":"JP",
    "wof:name":"430-0827",
    "wof:placetype":"postalcode"
},
  "geometry": {"coordinates":[137.7739,34.6856],"type":"Point"}
}