{
  "type": "Feature",
  "properties": {
    "gn:adm1_name":"Saitamaken",
    "gn:adm2_name":"Chichibugunnagatoromachi",
    "gn:name":"Iwata",
    "iso:country":"JP",
    "wof:name":"369-1311",
    "wof:placetype":"postalcode"
},
  "geometry": {"coordinates":[139.12450000000001,36.1274],"type":"Point"}
}