{
  "type": "Feature",
  "properties": {
    "gn:adm1_name":"Nagasakiken",
    "gn:adm2_name":"Shimabarashi",
    "gn:name":"Hagihara",
    "iso:country":"JP",
    "wof:name":"855-0851",
    "wof:placetype":"postalcode"
},
  "geometry": {"coordinates":[130.36449999999999,32.785],"type":"Point"}
}