{
  "type": "Feature",
  "properties": {
    "gn:adm1_name":"Kumamotoken",
    "gn:adm2_name":"Kamotogunkamotomachi",
    "gn:name":"Ishibuchi",
    "iso:country":"JP",
    "wof:name":"861-0311",
    "wof:placetype":"postalcode"
},
  "geometry": {"coordinates":[130.75999999999999,32.9962],"type":"Point"}
}