{
  "type": "Feature",
  "properties": {
    "gn:adm1_name":"Aichiken",
    "gn:adm2_name":"Nagoyashichikusaku",
    "gn:name":"Nabeyauenochou(Higashiwaki)",
    "iso:country":"JP",
    "wof:name":"464-0097",
    "wof:placetype":"postalcode"
},
  "geometry": {"coordinates":[136.95429999999999,35.1807],"type":"Point"}
}