{
  "type": "Feature",
  "properties": {
    "gn:adm1_name":"Yamaguchiken",
    "gn:adm2_name":"Kumagegunkaminosekichou",
    "gn:name":"Yashima",
    "iso:country":"JP",
    "wof:name":"742-1404",
    "wof:placetype":"postalcode"
},
  "geometry": {"coordinates":[132.14019999999999,33.7284],"type":"Point"}
}