{
  "type": "Feature",
  "properties": {
    "gn:adm1_name":"Miyagiken",
    "gn:adm2_name":"Kattagunshichikashukumachi",
    "gn:name":"Atagoshita",
    "iso:country":"JP",
    "wof:name":"989-0556",
    "wof:placetype":"postalcode"
},
  "geometry": {"coordinates":[140.4016,38.0161],"type":"Point"}
}