{
  "type": "Feature",
  "properties": {
    "gn:adm1_name":"Niigataken",
    "gn:adm2_name":"Mitsukeshi",
    "gn:name":"Urushiyamamachi",
    "iso:country":"JP",
    "wof:name":"954-0063",
    "wof:placetype":"postalcode"
},
  "geometry": {"coordinates":[138.9033,37.513],"type":"Point"}
}