{
  "type": "Feature",
  "properties": {
    "gn:adm1_name":"Mieken",
    "gn:adm2_name":"Ichishigunhakusanchou",
    "gn:name":"Fuji",
    "iso:country":"JP",
    "wof:name":"515-3131",
    "wof:placetype":"postalcode"
},
  "geometry": {"coordinates":[136.31020000000001,34.6313],"type":"Point"}
}