{
  "type": "Feature",
  "properties": {
    "gn:adm1_name":"Oosakafu",
    "gn:adm2_name":"Kishiwadashi",
    "gn:name":"Hachimanchou",
    "iso:country":"JP",
    "wof:name":"596-0023",
    "wof:placetype":"postalcode"
},
  "geometry": {"coordinates":[135.38900000000001,34.4822],"type":"Point"}
}