{
  "type": "Feature",
  "properties": {
    "gn:adm1_name":"Fukuokaken",
    "gn:adm2_name":"Fukuokashiminamiku",
    "gn:name":"Kashiwara",
    "iso:country":"JP",
    "wof:name":"811-1353",
    "wof:placetype":"postalcode"
},
  "geometry": {"coordinates":[130.39850000000001,33.5259],"type":"Point"}
}