{
  "type": "Feature",
  "properties": {
    "gn:adm1_name":"Naraken",
    "gn:adm2_name":"Narashi",
    "gn:name":"Sanjouoomiyachou",
    "iso:country":"JP",
    "wof:name":"630-8123",
    "wof:placetype":"postalcode"
},
  "geometry": {"coordinates":[135.81489999999999,34.6786],"type":"Point"}
}