{
  "type": "Feature",
  "properties": {
    "gn:adm1_name":"Shizuokaken",
    "gn:adm2_name":"Fujishi",
    "gn:name":"Tadehara",
    "iso:country":"JP",
    "wof:name":"416-0931",
    "wof:placetype":"postalcode"
},
  "geometry": {"coordinates":[138.66890000000001,35.1531],"type":"Point"}
}