{
  "type": "Feature",
  "properties": {
    "gn:adm1_name":"Fukuokaken",
    "gn:adm2_name":"Fukuokashijounanku",
    "gn:name":"Umebayashi",
    "iso:country":"JP",
    "wof:name":"814-0144",
    "wof:placetype":"postalcode"
},
  "geometry": {"coordinates":[130.3552,33.5452],"type":"Point"}
}