{
  "type": "Feature",
  "properties": {
    "gn:adm1_name":"Naraken",
    "gn:adm2_name":"Narashi",
    "gn:name":"Karamomochou",
    "iso:country":"JP",
    "wof:name":"630-8454",
    "wof:placetype":"postalcode"
},
  "geometry": {"coordinates":[135.80109999999999,34.6599],"type":"Point"}
}