{
  "type": "Feature",
  "properties": {
    "gn:adm1_name":"Gifuken",
    "gn:adm2_name":"Yoshikigunfurukawachou",
    "gn:name":"Sannomachi",
    "iso:country":"JP",
    "wof:name":"509-4236",
    "wof:placetype":"postalcode"
},
  "geometry": {"coordinates":[137.185,36.2344],"type":"Point"}
}