{
  "type": "Feature",
  "properties": {
    "gn:adm1_name":"Shimaneken",
    "gn:adm2_name":"Oochigunmizuhochou",
    "gn:name":"Fuse",
    "iso:country":"JP",
    "wof:name":"696-0401",
    "wof:placetype":"postalcode"
},
  "geometry": {"coordinates":[132.57380000000001,34.9404],"type":"Point"}
}