{
  "type": "Feature",
  "properties": {
    "gn:adm1_name":"Sagaken",
    "gn:adm2_name":"Sagashi",
    "gn:name":"Nishiyokamachitakatarou",
    "iso:country":"JP",
    "wof:name":"840-0036",
    "wof:placetype":"postalcode"
},
  "geometry": {"coordinates":[130.26949999999999,33.2235],"type":"Point"}
}