{
  "type": "Feature",
  "properties": {
    "gn:adm1_name":"Miyagiken",
    "gn:adm2_name":"Sendaishiwakabayashiku",
    "gn:name":"Higashi9banchou",
    "iso:country":"JP",
    "wof:name":"984-0071",
    "wof:placetype":"postalcode"
},
  "geometry": {"coordinates":[140.8854,38.2507],"type":"Point"}
}