{
  "type": "Feature",
  "properties": {
    "gn:adm1_name":"Chibaken",
    "gn:adm2_name":"Naritashi",
    "gn:name":"Baba",
    "iso:country":"JP",
    "wof:name":"286-0132",
    "wof:placetype":"postalcode"
},
  "geometry": {"coordinates":[140.3409,35.7849],"type":"Point"}
}