{
  "type": "Feature",
  "properties": {
    "gn:adm1_name":"Kanagawaken",
    "gn:adm2_name":"Yokohamashisakaeku",
    "gn:name":"Katsuradainaka",
    "iso:country":"JP",
    "wof:name":"247-0034",
    "wof:placetype":"postalcode"
},
  "geometry": {"coordinates":[139.56630000000001,35.3546],"type":"Point"}
}