{
  "type": "Feature",
  "properties": {
    "gn:adm1_name":"Aichiken",
    "gn:adm2_name":"Kasugaishi",
    "gn:name":"Yayoichou",
    "iso:country":"JP",
    "wof:name":"486-0838",
    "wof:placetype":"postalcode"
},
  "geometry": {"coordinates":[136.9768,35.2406],"type":"Point"}
}