{
  "type": "Feature",
  "properties": {
    "gn:adm1_name":"Aichiken",
    "gn:adm2_name":"Hekinanshi",
    "gn:name":"Susakimachi",
    "iso:country":"JP",
    "wof:name":"447-0086",
    "wof:placetype":"postalcode"
},
  "geometry": {"coordinates":[137.0085,34.908],"type":"Point"}
}