{
  "type": "Feature",
  "properties": {
    "gn:adm1_name":"Nagasakiken",
    "gn:adm2_name":"Nagasakishi",
    "gn:name":"Kosedomachi",
    "iso:country":"JP",
    "wof:name":"850-0077",
    "wof:placetype":"postalcode"
},
  "geometry": {"coordinates":[129.83410000000001,32.7268],"type":"Point"}
}