{
  "type": "Feature",
  "properties": {
    "gn:adm1_name":"Chibaken",
    "gn:adm2_name":"Katoriguntounoshoumachi",
    "gn:name":"Funado",
    "iso:country":"JP",
    "wof:name":"289-0634",
    "wof:placetype":"postalcode"
},
  "geometry": {"coordinates":[140.6481,35.7902],"type":"Point"}
}