{
  "type": "Feature",
  "properties": {
    "gn:adm1_name":"Tokushimaken",
    "gn:adm2_name":"Tokushimashi",
    "gn:name":"Kawauchichou(Suzueminami)",
    "iso:country":"JP",
    "wof:name":"771-0124",
    "wof:placetype":"postalcode"
},
  "geometry": {"coordinates":[134.57149999999999,34.0961],"type":"Point"}
}