{
  "type": "Feature",
  "properties": {
    "gn:adm1_name":"Chibaken",
    "gn:adm2_name":"Naritashi",
    "gn:name":"Kosuge",
    "iso:country":"JP",
    "wof:name":"286-0127",
    "wof:placetype":"postalcode"
},
  "geometry": {"coordinates":[140.35560000000001,35.7777],"type":"Point"}
}