{
  "type": "Feature",
  "properties": {
    "gn:adm1_name":"Shizuokaken",
    "gn:adm2_name":"Shizuokashi",
    "gn:name":"Miroku",
    "iso:country":"JP",
    "wof:name":"420-0053",
    "wof:placetype":"postalcode"
},
  "geometry": {"coordinates":[138.3708,34.9624],"type":"Point"}
}