{
  "type": "Feature",
  "properties": {
    "gn:adm1_name":"Kyoutofu",
    "gn:adm2_name":"Kyoutoshifushimiku",
    "gn:name":"Fukakusakitakagiyachou",
    "iso:country":"JP",
    "wof:name":"612-0041",
    "wof:placetype":"postalcode"
},
  "geometry": {"coordinates":[135.7672,34.9496],"type":"Point"}
}