{
  "type": "Feature",
  "properties": {
    "gn:adm1_name":"Kumamotoken",
    "gn:adm2_name":"Tamanagunnagasumachi",
    "gn:name":"Nagashio",
    "iso:country":"JP",
    "wof:name":"869-0106",
    "wof:placetype":"postalcode"
},
  "geometry": {"coordinates":[130.47200000000001,32.9395],"type":"Point"}
}