{
  "type": "Feature",
  "properties": {
    "gn:adm1_name":"Hyougoken",
    "gn:adm2_name":"Kinosakiguntakenochou",
    "gn:name":"Okusui",
    "iso:country":"JP",
    "wof:name":"669-6218",
    "wof:placetype":"postalcode"
},
  "geometry": {"coordinates":[134.7347,35.6477],"type":"Point"}
}