{
  "type": "Feature",
  "properties": {
    "gn:adm1_name":"Mieken",
    "gn:adm2_name":"Hisaishi",
    "gn:name":"Kotsukurichou",
    "iso:country":"JP",
    "wof:name":"514-1115",
    "wof:placetype":"postalcode"
},
  "geometry": {"coordinates":[136.50559999999999,34.7183],"type":"Point"}
}