{
  "type": "Feature",
  "properties": {
    "gn:adm1_name":"Gunmaken",
    "gn:adm2_name":"Maebashishi",
    "gn:name":"Tonyamachi",
    "iso:country":"JP",
    "wof:name":"371-0855",
    "wof:placetype":"postalcode"
},
  "geometry": {"coordinates":[139.0403,36.3959],"type":"Point"}
}