{
  "type": "Feature",
  "properties": {
    "gn:adm1_name":"Oosakafu",
    "gn:adm2_name":"Takatsukishi",
    "gn:name":"Demaruchou",
    "iso:country":"JP",
    "wof:name":"569-0076",
    "wof:placetype":"postalcode"
},
  "geometry": {"coordinates":[135.61859999999999,34.8421],"type":"Point"}
}