{
  "type": "Feature",
  "properties": {
    "gn:adm1_name":"Kumamotoken",
    "gn:adm2_name":"Shimomashikigunjounanmachi",
    "gn:name":"Izumi",
    "iso:country":"JP",
    "wof:name":"861-4213",
    "wof:placetype":"postalcode"
},
  "geometry": {"coordinates":[130.75460000000001,32.7134],"type":"Point"}
}