{
  "type": "Feature",
  "properties": {
    "gn:adm1_name":"Yamaguchiken",
    "gn:adm2_name":"Sabaguntokudichou",
    "gn:name":"Sabagouchi",
    "iso:country":"JP",
    "wof:name":"747-0611",
    "wof:placetype":"postalcode"
},
  "geometry": {"coordinates":[131.7347,34.1957],"type":"Point"}
}