{
  "type": "Feature",
  "properties": {
    "gn:adm1_name":"Fukushimaken",
    "gn:adm2_name":"Yamagunyamatomachi",
    "gn:name":"Iwabuchi",
    "iso:country":"JP",
    "wof:name":"969-4148",
    "wof:placetype":"postalcode"
},
  "geometry": {"coordinates":[139.76759999999999,37.6412],"type":"Point"}
}