{
  "type": "Feature",
  "properties": {
    "gn:adm1_name":"Ehimeken",
    "gn:adm2_name":"Uwajimashi",
    "gn:name":"Kohama",
    "iso:country":"JP",
    "wof:name":"798-0092",
    "wof:placetype":"postalcode"
},
  "geometry": {"coordinates":[132.50640000000001,33.2045],"type":"Point"}
}