{
  "type": "Feature",
  "properties": {
    "gn:adm1_name":"Yamagataken",
    "gn:adm2_name":"Higashitagawagunhaguromachi",
    "gn:name":"Ushiroda",
    "iso:country":"JP",
    "wof:name":"997-0157",
    "wof:placetype":"postalcode"
},
  "geometry": {"coordinates":[139.875,38.7129],"type":"Point"}
}