{
  "type": "Feature",
  "properties": {
    "gn:adm1_name":"Fukuokaken",
    "gn:adm2_name":"Kitakyuushuushikokuraminamiku",
    "gn:name":"Haruyoshi",
    "iso:country":"JP",
    "wof:name":"803-0265",
    "wof:placetype":"postalcode"
},
  "geometry": {"coordinates":[130.8477,33.79],"type":"Point"}
}