{
  "type": "Feature",
  "properties": {
    "gn:adm1_name":"Fukushimaken",
    "gn:adm2_name":"Iwakishi",
    "gn:name":"Jouban'Osamagomachi",
    "iso:country":"JP",
    "wof:name":"972-8315",
    "wof:placetype":"postalcode"
},
  "geometry": {"coordinates":[140.8546,36.978],"type":"Point"}
}