{
  "type": "Feature",
  "properties": {
    "gn:adm1_name":"Ibarakiken",
    "gn:adm2_name":"Nakagun'Ogawamura",
    "gn:name":"Kuniosa",
    "iso:country":"JP",
    "wof:name":"319-2404",
    "wof:placetype":"postalcode"
},
  "geometry": {"coordinates":[140.2996,36.5814],"type":"Point"}
}