{
  "type": "Feature",
  "properties": {
    "gn:adm1_name":"Gifuken",
    "gn:adm2_name":"Kakamigaharashi",
    "gn:name":"Unumamanagoshichou",
    "iso:country":"JP",
    "wof:name":"509-0134",
    "wof:placetype":"postalcode"
},
  "geometry": {"coordinates":[136.9238,35.3983],"type":"Point"}
}