{
  "type": "Feature",
  "properties": {
    "gn:adm1_name":"Nagasakiken",
    "gn:adm2_name":"Matsuurashi",
    "gn:name":"Imafukuchoukobamen",
    "iso:country":"JP",
    "wof:name":"859-4524",
    "wof:placetype":"postalcode"
},
  "geometry": {"coordinates":[129.76949999999999,33.3289],"type":"Point"}
}