{
  "type": "Feature",
  "properties": {
    "gn:adm1_name":"Naraken",
    "gn:adm2_name":"Kashibashi",
    "gn:name":"Ninji",
    "iso:country":"JP",
    "wof:name":"639-0261",
    "wof:placetype":"postalcode"
},
  "geometry": {"coordinates":[135.69829999999999,34.5721],"type":"Point"}
}