{
  "type": "Feature",
  "properties": {
    "gn:adm1_name":"Fukuiken",
    "gn:adm2_name":"Imadategun'Ikedachou",
    "gn:name":"Shimizutani",
    "iso:country":"JP",
    "wof:name":"910-2507",
    "wof:placetype":"postalcode"
},
  "geometry": {"coordinates":[136.34020000000001,35.9164],"type":"Point"}
}