{
  "type": "Feature",
  "properties": {
    "gn:adm1_name":"Gunmaken",
    "gn:adm2_name":"Isesakishi",
    "gn:name":"Kuruwachou",
    "iso:country":"JP",
    "wof:name":"372-0055",
    "wof:placetype":"postalcode"
},
  "geometry": {"coordinates":[139.1919,36.3243],"type":"Point"}
}