{
  "type": "Feature",
  "properties": {
    "gn:adm1_name":"Nagasakiken",
    "gn:adm2_name":"Matsuurashi",
    "gn:name":"Imafukuchouuramen",
    "iso:country":"JP",
    "wof:name":"859-4528",
    "wof:placetype":"postalcode"
},
  "geometry": {"coordinates":[129.76400000000001,33.3535],"type":"Point"}
}