{
  "type": "Feature",
  "properties": {
    "gn:adm1_name":"Shizuokaken",
    "gn:adm2_name":"Shizuokashi",
    "gn:name":"Utsunoya",
    "iso:country":"JP",
    "wof:name":"421-0105",
    "wof:placetype":"postalcode"
},
  "geometry": {"coordinates":[138.30539999999999,34.9368],"type":"Point"}
}