{
  "type": "Feature",
  "properties": {
    "gn:adm1_name":"Tochigiken",
    "gn:adm2_name":"Kawachigunkaminokawamachi",
    "gn:name":"Sayadou",
    "iso:country":"JP",
    "wof:name":"329-0526",
    "wof:placetype":"postalcode"
},
  "geometry": {"coordinates":[139.86850000000001,36.4583],"type":"Point"}
}