{
  "type": "Feature",
  "properties": {
    "gn:adm1_name":"Miyazakiken",
    "gn:adm2_name":"Saitoshi",
    "gn:name":"Asahi",
    "iso:country":"JP",
    "wof:name":"881-0031",
    "wof:placetype":"postalcode"
},
  "geometry": {"coordinates":[131.41040000000001,32.1105],"type":"Point"}
}