{
  "type": "Feature",
  "properties": {
    "gn:adm1_name":"Hyougoken",
    "gn:adm2_name":"Mikatagunmuraokachou",
    "gn:name":"Nakaootani",
    "iso:country":"JP",
    "wof:name":"667-1343",
    "wof:placetype":"postalcode"
},
  "geometry": {"coordinates":[134.5728,35.402],"type":"Point"}
}