{
  "type": "Feature",
  "properties": {
    "gn:adm1_name":"Hiroshimaken",
    "gn:adm2_name":"Kureshi",
    "gn:name":"Higashishioyachou",
    "iso:country":"JP",
    "wof:name":"737-0837",
    "wof:placetype":"postalcode"
},
  "geometry": {"coordinates":[132.5427,34.2502],"type":"Point"}
}