{
  "type": "Feature",
  "properties": {
    "gn:adm1_name":"Kumamotoken",
    "gn:adm2_name":"Kumamotoshi",
    "gn:name":"Nakamutamachi",
    "iso:country":"JP",
    "wof:name":"861-4116",
    "wof:placetype":"postalcode"
},
  "geometry": {"coordinates":[130.67089999999999,32.735],"type":"Point"}
}