{
  "type": "Feature",
  "properties": {
    "gn:adm1_name":"Mieken",
    "gn:adm2_name":"Miegunkomonochou",
    "gn:name":"Uruda",
    "iso:country":"JP",
    "wof:name":"510-1253",
    "wof:placetype":"postalcode"
},
  "geometry": {"coordinates":[136.51169999999999,35.0235],"type":"Point"}
}