{
  "type": "Feature",
  "properties": {
    "gn:adm1_name":"Saitamaken",
    "gn:adm2_name":"Koshigayashi",
    "gn:name":"Oosugi",
    "iso:country":"JP",
    "wof:name":"343-0005",
    "wof:placetype":"postalcode"
},
  "geometry": {"coordinates":[139.8023,35.9313],"type":"Point"}
}