{
  "type": "Feature",
  "properties": {
    "gn:adm1_name":"Nagasakiken",
    "gn:adm2_name":"Isahayashi",
    "gn:name":"Nakaomachi",
    "iso:country":"JP",
    "wof:name":"854-0073",
    "wof:placetype":"postalcode"
},
  "geometry": {"coordinates":[130.03030000000001,32.8493],"type":"Point"}
}