{
  "type": "Feature",
  "properties": {
    "gn:adm1_name":"Chibaken",
    "gn:adm2_name":"Nodashi",
    "gn:name":"Shimosangao",
    "iso:country":"JP",
    "wof:name":"278-0014",
    "wof:placetype":"postalcode"
},
  "geometry": {"coordinates":[139.92019999999999,35.9235],"type":"Point"}
}