{
  "type": "Feature",
  "properties": {
    "gn:adm1_name":"Saitamaken",
    "gn:adm2_name":"Iwatsukishi",
    "gn:name":"Kake",
    "iso:country":"JP",
    "wof:name":"339-0078",
    "wof:placetype":"postalcode"
},
  "geometry": {"coordinates":[139.68819999999999,35.9716],"type":"Point"}
}