{
  "type": "Feature",
  "properties": {
    "gn:adm1_name":"Hiroshimaken",
    "gn:adm2_name":"Kureshi",
    "gn:name":"Shimokamagarichoushimojima",
    "iso:country":"JP",
    "wof:name":"737-0303",
    "wof:placetype":"postalcode"
},
  "geometry": {"coordinates":[132.6713,34.1898],"type":"Point"}
}