{
  "type": "Feature",
  "properties": {
    "gn:adm1_name":"Niigataken",
    "gn:adm2_name":"Tookamachishi",
    "gn:name":"Kasugachou",
    "iso:country":"JP",
    "wof:name":"948-0057",
    "wof:placetype":"postalcode"
},
  "geometry": {"coordinates":[138.75020000000001,37.1311],"type":"Point"}
}