{
  "type": "Feature",
  "properties": {
    "gn:adm1_name":"Naganoken",
    "gn:adm2_name":"Suwagunharamura",
    "gn:name":"Kashiwagi",
    "iso:country":"JP",
    "wof:name":"391-0105",
    "wof:placetype":"postalcode"
},
  "geometry": {"coordinates":[138.19649999999999,35.9681],"type":"Point"}
}