{
  "type": "Feature",
  "properties": {
    "gn:adm1_name":"Okayamaken",
    "gn:adm2_name":"Mitsuguntakebechou",
    "gn:name":"Wadaminami",
    "iso:country":"JP",
    "wof:name":"709-3102",
    "wof:placetype":"postalcode"
},
  "geometry": {"coordinates":[133.87119999999999,34.932],"type":"Point"}
}