{
  "type": "Feature",
  "properties": {
    "gn:adm1_name":"Gifuken",
    "gn:adm2_name":"Gifushi",
    "gn:name":"Kanouootemachi",
    "iso:country":"JP",
    "wof:name":"500-8482",
    "wof:placetype":"postalcode"
},
  "geometry": {"coordinates":[136.762,35.404],"type":"Point"}
}