{
  "type": "Feature",
  "properties": {
    "gn:adm1_name":"Okayamaken",
    "gn:adm2_name":"Okayamashi",
    "gn:name":"Yokoo",
    "iso:country":"JP",
    "wof:name":"701-1226",
    "wof:placetype":"postalcode"
},
  "geometry": {"coordinates":[133.83090000000001,34.7262],"type":"Point"}
}