{
  "type": "Feature",
  "properties": {
    "gn:adm1_name":"Oosakafu",
    "gn:adm2_name":"Takatsukishi",
    "gn:name":"Kamihamuro",
    "iso:country":"JP",
    "wof:name":"569-1044",
    "wof:placetype":"postalcode"
},
  "geometry": {"coordinates":[135.5796,34.8533],"type":"Point"}
}