{
  "type": "Feature",
  "properties": {
    "gn:adm1_name":"Kumamotoken",
    "gn:adm2_name":"Tamanashi",
    "gn:name":"Akimaru",
    "iso:country":"JP",
    "wof:name":"865-0026",
    "wof:placetype":"postalcode"
},
  "geometry": {"coordinates":[130.56569999999999,32.9312],"type":"Point"}
}