{
  "type": "Feature",
  "properties": {
    "gn:adm1_name":"Kyoutofu",
    "gn:adm2_name":"Kyoutoshinishikyouku",
    "gn:name":"Katsurashimizuchou",
    "iso:country":"JP",
    "wof:name":"615-8013",
    "wof:placetype":"postalcode"
},
  "geometry": {"coordinates":[135.70910000000001,34.9862],"type":"Point"}
}