{
  "type": "Feature",
  "properties": {
    "gn:adm1_name":"Aichiken",
    "gn:adm2_name":"Nagoyashishouwaku",
    "gn:name":"Tsurumai",
    "iso:country":"JP",
    "wof:name":"466-0064",
    "wof:placetype":"postalcode"
},
  "geometry": {"coordinates":[136.91849999999999,35.1516],"type":"Point"}
}