{
  "type": "Feature",
  "properties": {
    "gn:adm1_name":"Toukyouto",
    "gn:adm2_name":"Higashikurumeshi",
    "gn:name":"Yanagikubo",
    "iso:country":"JP",
    "wof:name":"203-0044",
    "wof:placetype":"postalcode"
},
  "geometry": {"coordinates":[139.4932,35.7473],"type":"Point"}
}