{
  "type": "Feature",
  "properties": {
    "gn:adm1_name":"Hyougoken",
    "gn:adm2_name":"Himejishi",
    "gn:name":"Konikaimachi",
    "iso:country":"JP",
    "wof:name":"670-0936",
    "wof:placetype":"postalcode"
},
  "geometry": {"coordinates":[134.69640000000001,34.8307],"type":"Point"}
}