{
  "type": "Feature",
  "properties": {
    "gn:adm1_name":"Kumamotoken",
    "gn:adm2_name":"Hitoyoshishi",
    "gn:name":"Gantsukurimachi",
    "iso:country":"JP",
    "wof:name":"868-0042",
    "wof:placetype":"postalcode"
},
  "geometry": {"coordinates":[130.78039999999999,32.1963],"type":"Point"}
}