{
  "type": "Feature",
  "properties": {
    "gn:adm1_name":"Fukushimaken",
    "gn:adm2_name":"Aiduwakamatsushi",
    "gn:name":"Ootomachiookawa",
    "iso:country":"JP",
    "wof:name":"969-5133",
    "wof:placetype":"postalcode"
},
  "geometry": {"coordinates":[139.91970000000001,37.3698],"type":"Point"}
}