{
  "type": "Feature",
  "properties": {
    "gn:adm1_name":"Fukushimaken",
    "gn:adm2_name":"Kooriyamashi",
    "gn:name":"Konanmachiakatsu",
    "iso:country":"JP",
    "wof:name":"963-1631",
    "wof:placetype":"postalcode"
},
  "geometry": {"coordinates":[140.06950000000001,37.4027],"type":"Point"}
}