{
  "type": "Feature",
  "properties": {
    "gn:adm1_name":"Yamaguchiken",
    "gn:adm2_name":"Shimonosekishi",
    "gn:name":"Yamanotahigashimachi",
    "iso:country":"JP",
    "wof:name":"751-0834",
    "wof:placetype":"postalcode"
},
  "geometry": {"coordinates":[130.92930000000001,33.9864],"type":"Point"}
}