{
  "type": "Feature",
  "properties": {
    "gn:adm1_name":"Shimaneken",
    "gn:adm2_name":"Hamadashi",
    "gn:name":"Ushiichichou",
    "iso:country":"JP",
    "wof:name":"697-0032",
    "wof:placetype":"postalcode"
},
  "geometry": {"coordinates":[132.08410000000001,34.8991],"type":"Point"}
}