{
  "type": "Feature",
  "properties": {
    "gn:adm1_name":"Hyougoken",
    "gn:adm2_name":"Amagasakishi",
    "gn:name":"Shiomachi",
    "iso:country":"JP",
    "wof:name":"660-0866",
    "wof:placetype":"postalcode"
},
  "geometry": {"coordinates":[135.40969999999999,34.7176],"type":"Point"}
}