{
  "type": "Feature",
  "properties": {
    "gn:adm1_name":"Chibaken",
    "gn:adm2_name":"Kamogawashi",
    "gn:name":"Nishichou",
    "iso:country":"JP",
    "wof:name":"296-0043",
    "wof:placetype":"postalcode"
},
  "geometry": {"coordinates":[140.1148,35.1222],"type":"Point"}
}