{
  "type": "Feature",
  "properties": {
    "gn:adm1_name":"Oosakafu",
    "gn:adm2_name":"Yaoshi",
    "gn:name":"Akemichou",
    "iso:country":"JP",
    "wof:name":"581-0087",
    "wof:placetype":"postalcode"
},
  "geometry": {"coordinates":[135.60159999999999,34.6201],"type":"Point"}
}