{
  "type": "Feature",
  "properties": {
    "gn:adm1_name":"Ehimeken",
    "gn:adm2_name":"Oozushi",
    "gn:name":"Nagatani",
    "iso:country":"JP",
    "wof:name":"795-0004",
    "wof:placetype":"postalcode"
},
  "geometry": {"coordinates":[132.5401,33.4531],"type":"Point"}
}