{
  "type": "Feature",
  "properties": {
    "gn:adm1_name":"Toyamaken",
    "gn:adm2_name":"Takaokashi",
    "gn:name":"Gofukumachi",
    "iso:country":"JP",
    "wof:name":"933-0906",
    "wof:placetype":"postalcode"
},
  "geometry": {"coordinates":[137.01439999999999,36.7583],"type":"Point"}
}