{
  "type": "Feature",
  "properties": {
    "gn:adm1_name":"Toukyouto",
    "gn:adm2_name":"Chiyodaku",
    "gn:name":"Kandanishikichou",
    "iso:country":"JP",
    "wof:name":"101-0054",
    "wof:placetype":"postalcode"
},
  "geometry": {"coordinates":[139.76230000000001,35.6925],"type":"Point"}
}