{
  "type": "Feature",
  "properties": {
    "gn:adm1_name":"Hiroshimaken",
    "gn:adm2_name":"Higashihiroshimashi",
    "gn:name":"Saijouchoutaguchi",
    "iso:country":"JP",
    "wof:name":"739-0036",
    "wof:placetype":"postalcode"
},
  "geometry": {"coordinates":[132.72479999999999,34.3886],"type":"Point"}
}