{
  "type": "Feature",
  "properties": {
    "gn:adm1_name":"Shizuokaken",
    "gn:adm2_name":"Suntougunnagaizumichou",
    "gn:name":"Takehara",
    "iso:country":"JP",
    "wof:name":"411-0944",
    "wof:placetype":"postalcode"
},
  "geometry": {"coordinates":[138.898,35.1195],"type":"Point"}
}