{
  "type": "Feature",
  "properties": {
    "gn:adm1_name":"Miyagiken",
    "gn:adm2_name":"Shiogamashi",
    "gn:name":"Komatsuzaki",
    "iso:country":"JP",
    "wof:name":"985-0072",
    "wof:placetype":"postalcode"
},
  "geometry": {"coordinates":[141.01859999999999,38.323],"type":"Point"}
}