{
  "type": "Feature",
  "properties": {
    "gn:adm1_name":"Hyougoken",
    "gn:adm2_name":"Tatsunoshi",
    "gn:name":"Tatsunochouyokka",
    "iso:country":"JP",
    "wof:name":"679-4168",
    "wof:placetype":"postalcode"
},
  "geometry": {"coordinates":[134.5472,34.8507],"type":"Point"}
}