{
  "type": "Feature",
  "properties": {
    "gn:adm1_name":"Shigaken",
    "gn:adm2_name":"Hikoneshi",
    "gn:name":"Kawasebabachou",
    "iso:country":"JP",
    "wof:name":"522-0223",
    "wof:placetype":"postalcode"
},
  "geometry": {"coordinates":[136.22980000000001,35.2261],"type":"Point"}
}