{
  "type": "Feature",
  "properties": {
    "gn:adm1_name":"Toyamaken",
    "gn:adm2_name":"Kaminiikawagun'Ooyamamachi",
    "gn:name":"Nakaooura",
    "iso:country":"JP",
    "wof:name":"930-1334",
    "wof:placetype":"postalcode"
},
  "geometry": {"coordinates":[137.26740000000001,36.6086],"type":"Point"}
}