{
  "type": "Feature",
  "properties": {
    "gn:adm1_name":"Gifuken",
    "gn:adm2_name":"Hashimashi",
    "gn:name":"Kaminakachouishiki",
    "iso:country":"JP",
    "wof:name":"501-6312",
    "wof:placetype":"postalcode"
},
  "geometry": {"coordinates":[136.70949999999999,35.2997],"type":"Point"}
}