{
  "type": "Feature",
  "properties": {
    "gn:adm1_name":"Fukuiken",
    "gn:adm2_name":"Fukuishi",
    "gn:name":"Shimoazoudachou",
    "iso:country":"JP",
    "wof:name":"918-8134",
    "wof:placetype":"postalcode"
},
  "geometry": {"coordinates":[136.2199,36.0278],"type":"Point"}
}