{
  "type": "Feature",
  "properties": {
    "gn:adm1_name":"Naganoken",
    "gn:adm2_name":"Kamiminochigunshinanomachi",
    "gn:name":"Ooi",
    "iso:country":"JP",
    "wof:name":"389-1316",
    "wof:placetype":"postalcode"
},
  "geometry": {"coordinates":[138.1925,36.7703],"type":"Point"}
}