{
  "type": "Feature",
  "properties": {
    "gn:adm1_name":"Gunmaken",
    "gn:adm2_name":"Kanragunmyougimachi",
    "gn:name":"Shimotakata",
    "iso:country":"JP",
    "wof:name":"370-2412",
    "wof:placetype":"postalcode"
},
  "geometry": {"coordinates":[138.8389,36.2734],"type":"Point"}
}