{
  "type": "Feature",
  "properties": {
    "gn:adm1_name":"Ishikawaken",
    "gn:adm2_name":"Fugeshigunnotomachi",
    "gn:name":"Ushitsushin",
    "iso:country":"JP",
    "wof:name":"927-0432",
    "wof:placetype":"postalcode"
},
  "geometry": {"coordinates":[137.14920000000001,37.3077],"type":"Point"}
}