{
  "type": "Feature",
  "properties": {
    "gn:adm1_name":"Hyougoken",
    "gn:adm2_name":"Miharagunnandanchou",
    "gn:name":"Kashuuushiuchi",
    "iso:country":"JP",
    "wof:name":"656-0518",
    "wof:placetype":"postalcode"
},
  "geometry": {"coordinates":[134.7766,34.2606],"type":"Point"}
}