{
  "type": "Feature",
  "properties": {
    "gn:adm1_name":"Chibaken",
    "gn:adm2_name":"Chibashihanamigawaku",
    "gn:name":"Hanashimachou",
    "iso:country":"JP",
    "wof:name":"262-0042",
    "wof:placetype":"postalcode"
},
  "geometry": {"coordinates":[140.0994,35.6842],"type":"Point"}
}