{
  "type": "Feature",
  "properties": {
    "gn:adm1_name":"Yamanashiken",
    "gn:adm2_name":"Koufushi",
    "gn:name":"Hagurochou",
    "iso:country":"JP",
    "wof:name":"400-0071",
    "wof:placetype":"postalcode"
},
  "geometry": {"coordinates":[138.54560000000001,35.6906],"type":"Point"}
}