{
  "type": "Feature",
  "properties": {
    "gn:adm1_name":"Mieken",
    "gn:adm2_name":"Suzukagunsekichou",
    "gn:name":"Kabutokitazaike",
    "iso:country":"JP",
    "wof:name":"519-1128",
    "wof:placetype":"postalcode"
},
  "geometry": {"coordinates":[136.31290000000001,34.8432],"type":"Point"}
}