{
  "type": "Feature",
  "properties": {
    "gn:adm1_name":"Naraken",
    "gn:adm2_name":"Narashi",
    "gn:name":"Aburasakachou",
    "iso:country":"JP",
    "wof:name":"630-8247",
    "wof:placetype":"postalcode"
},
  "geometry": {"coordinates":[135.8227,34.6838],"type":"Point"}
}