{
  "type": "Feature",
  "properties": {
    "gn:adm1_name":"Mieken",
    "gn:adm2_name":"Inabeshi",
    "gn:name":"Inabechoukasadashinden",
    "iso:country":"JP",
    "wof:name":"511-0205",
    "wof:placetype":"postalcode"
},
  "geometry": {"coordinates":[136.5575,35.1175],"type":"Point"}
}