{
  "type": "Feature",
  "properties": {
    "gn:adm1_name":"Ooitaken",
    "gn:adm2_name":"Saikishi",
    "gn:name":"Higashihama",
    "iso:country":"JP",
    "wof:name":"876-0821",
    "wof:placetype":"postalcode"
},
  "geometry": {"coordinates":[131.91999999999999,32.9689],"type":"Point"}
}