{
  "type": "Feature",
  "properties": {
    "gn:adm1_name":"Fukuokaken",
    "gn:adm2_name":"Fukuokashichuuouku",
    "gn:name":"Terukuni",
    "iso:country":"JP",
    "wof:name":"810-0032",
    "wof:placetype":"postalcode"
},
  "geometry": {"coordinates":[130.38159999999999,33.5709],"type":"Point"}
}