{
  "type": "Feature",
  "properties": {
    "gn:adm1_name":"Kanagawaken",
    "gn:adm2_name":"Ashigarashimogunmanatsurumachi",
    "gn:name":"Manatsuru",
    "iso:country":"JP",
    "wof:name":"259-0201",
    "wof:placetype":"postalcode"
},
  "geometry": {"coordinates":[139.13929999999999,35.1543],"type":"Point"}
}