{
  "type": "Feature",
  "properties": {
    "gn:adm1_name":"Kyoutofu",
    "gn:adm2_name":"Kyoutoshiyamashinaku",
    "gn:name":"Nagitsujihiratachou",
    "iso:country":"JP",
    "wof:name":"607-8165",
    "wof:placetype":"postalcode"
},
  "geometry": {"coordinates":[135.81219999999999,34.969],"type":"Point"}
}