{
  "type": "Feature",
  "properties": {
    "gn:adm1_name":"Naraken",
    "gn:adm2_name":"Narashi",
    "gn:name":"Tomiokita",
    "iso:country":"JP",
    "wof:name":"631-0076",
    "wof:placetype":"postalcode"
},
  "geometry": {"coordinates":[135.73560000000001,34.6977],"type":"Point"}
}