{
  "type": "Feature",
  "properties": {
    "gn:adm1_name":"Kyoutofu",
    "gn:adm2_name":"Kyoutoshikamigyouku",
    "gn:name":"Suzuriyachou",
    "iso:country":"JP",
    "wof:name":"602-8439",
    "wof:placetype":"postalcode"
},
  "geometry": {"coordinates":[135.74780000000001,35.0324],"type":"Point"}
}