{
  "type": "Feature",
  "properties": {
    "gn:adm1_name":"Fukuiken",
    "gn:adm2_name":"Sakaigunmikunichou",
    "gn:name":"Yonodu",
    "iso:country":"JP",
    "wof:name":"913-0036",
    "wof:placetype":"postalcode"
},
  "geometry": {"coordinates":[136.12370000000001,36.1711],"type":"Point"}
}