{
  "type": "Feature",
  "properties": {
    "gn:adm1_name":"Kyoutofu",
    "gn:adm2_name":"Kyoutoshinakagyouku",
    "gn:name":"Hishiyachou",
    "iso:country":"JP",
    "wof:name":"604-8131",
    "wof:placetype":"postalcode"
},
  "geometry": {"coordinates":[135.76169999999999,35.0086],"type":"Point"}
}