{
  "type": "Feature",
  "properties": {
    "gn:adm1_name":"Aichiken",
    "gn:adm2_name":"Nagoyashichikusaku",
    "gn:name":"Haruoka",
    "iso:country":"JP",
    "wof:name":"464-0848",
    "wof:placetype":"postalcode"
},
  "geometry": {"coordinates":[136.94309999999999,35.1652],"type":"Point"}
}