{
  "type": "Feature",
  "properties": {
    "gn:adm1_name":"Kanagawaken",
    "gn:adm2_name":"Yokohamashiaobaku",
    "gn:name":"Misuzugaoka",
    "iso:country":"JP",
    "wof:name":"225-0016",
    "wof:placetype":"postalcode"
},
  "geometry": {"coordinates":[139.54050000000001,35.5613],"type":"Point"}
}