{
  "type": "Feature",
  "properties": {
    "gn:adm1_name":"Okayamaken",
    "gn:adm2_name":"Kumegunyanaharachou",
    "gn:name":"Yanahara",
    "iso:country":"JP",
    "wof:name":"708-1527",
    "wof:placetype":"postalcode"
},
  "geometry": {"coordinates":[134.0607,34.9554],"type":"Point"}
}