{
  "type": "Feature",
  "properties": {
    "gn:adm1_name":"Hyougoken",
    "gn:adm2_name":"Mikatagunhamasakachou",
    "gn:name":"Hecchi",
    "iso:country":"JP",
    "wof:name":"669-6724",
    "wof:placetype":"postalcode"
},
  "geometry": {"coordinates":[134.5231,35.6175],"type":"Point"}
}