{
  "type": "Feature",
  "properties": {
    "gn:adm1_name":"Kanagawaken",
    "gn:adm2_name":"Yokohamashikanagawaku",
    "gn:name":"Nishikanagawa",
    "iso:country":"JP",
    "wof:name":"221-0822",
    "wof:placetype":"postalcode"
},
  "geometry": {"coordinates":[139.6301,35.4816],"type":"Point"}
}