{
  "type": "Feature",
  "properties": {
    "gn:adm1_name":"Okinawaken",
    "gn:adm2_name":"Nakagamigunyonashirochou",
    "gn:name":"Yonashiro",
    "iso:country":"JP",
    "wof:name":"904-2303",
    "wof:placetype":"postalcode"
},
  "geometry": {"coordinates":[127.8929,26.327],"type":"Point"}
}