{
  "type": "Feature",
  "properties": {
    "gn:adm1_name":"Kyoutofu",
    "gn:adm2_name":"Kyoutoshinishikyouku",
    "gn:name":"Katsurakamimamedachou",
    "iso:country":"JP",
    "wof:name":"615-8082",
    "wof:placetype":"postalcode"
},
  "geometry": {"coordinates":[135.7037,34.9846],"type":"Point"}
}