{
  "type": "Feature",
  "properties": {
    "gn:adm1_name":"Mieken",
    "gn:adm2_name":"Nabarishi",
    "gn:name":"Akamechoushinkawa",
    "iso:country":"JP",
    "wof:name":"518-0466",
    "wof:placetype":"postalcode"
},
  "geometry": {"coordinates":[136.0779,34.6038],"type":"Point"}
}