{
  "type": "Feature",
  "properties": {
    "gn:adm1_name":"Hiroshimaken",
    "gn:adm2_name":"Higashihiroshimashi",
    "gn:name":"Hachihonmatsuchouyonemitsu",
    "iso:country":"JP",
    "wof:name":"739-0133",
    "wof:placetype":"postalcode"
},
  "geometry": {"coordinates":[132.71889999999999,34.4498],"type":"Point"}
}