{
  "type": "Feature",
  "properties": {
    "gn:adm1_name":"Niigataken",
    "gn:adm2_name":"Kitakanbaragunnakajoumachi",
    "gn:name":"Kitahonchou",
    "iso:country":"JP",
    "wof:name":"959-2647",
    "wof:placetype":"postalcode"
},
  "geometry": {"coordinates":[139.4033,38.0558],"type":"Point"}
}