{
  "type": "Feature",
  "properties": {
    "gn:adm1_name":"Naganoken",
    "gn:adm2_name":"Shimoinaguntakamorimachi",
    "gn:name":"Ikanikeisaiganaibaai",
    "iso:country":"JP",
    "wof:name":"399-3100",
    "wof:placetype":"postalcode"
},
  "geometry": {"coordinates":[137.87,35.5658],"type":"Point"}
}