{
  "type": "Feature",
  "properties": {
    "gn:adm1_name":"Oosakafu",
    "gn:adm2_name":"Higashioosakashi",
    "gn:name":"Kashitanishi",
    "iso:country":"JP",
    "wof:name":"577-0835",
    "wof:placetype":"postalcode"
},
  "geometry": {"coordinates":[135.5677,34.6473],"type":"Point"}
}