{
  "type": "Feature",
  "properties": {
    "gn:adm1_name":"Mieken",
    "gn:adm2_name":"Kuwanashi",
    "gn:name":"Fujigaoka",
    "iso:country":"JP",
    "wof:name":"511-0865",
    "wof:placetype":"postalcode"
},
  "geometry": {"coordinates":[136.6516,35.076],"type":"Point"}
}