{
  "type": "Feature",
  "properties": {
    "gn:adm1_name":"Kanagawaken",
    "gn:adm2_name":"Hiratsukashi",
    "gn:name":"Takarachou",
    "iso:country":"JP",
    "wof:name":"254-0034",
    "wof:placetype":"postalcode"
},
  "geometry": {"coordinates":[139.35140000000001,35.3289],"type":"Point"}
}