{
  "type": "Feature",
  "properties": {
    "gn:adm1_name":"Nagasakiken",
    "gn:adm2_name":"Saseboshi",
    "gn:name":"Seiwadaimachi",
    "iso:country":"JP",
    "wof:name":"858-0924",
    "wof:placetype":"postalcode"
},
  "geometry": {"coordinates":[129.67949999999999,33.1748],"type":"Point"}
}