{
  "type": "Feature",
  "properties": {
    "gn:adm1_name":"Kyoutofu",
    "gn:adm2_name":"Fukuchiyamashi",
    "gn:name":"Tera",
    "iso:country":"JP",
    "wof:name":"620-0021",
    "wof:placetype":"postalcode"
},
  "geometry": {"coordinates":[135.12270000000001,35.3054],"type":"Point"}
}