{
  "type": "Feature",
  "properties": {
    "gn:adm1_name":"Nagasakiken",
    "gn:adm2_name":"Minamimatsuuragunwakamatsuchou",
    "gn:name":"Wakamatsugou",
    "iso:country":"JP",
    "wof:name":"853-2301",
    "wof:placetype":"postalcode"
},
  "geometry": {"coordinates":[129.01949999999999,32.8825],"type":"Point"}
}