{
  "type": "Feature",
  "properties": {
    "gn:adm1_name":"Ibarakiken",
    "gn:adm2_name":"Inashikigunshintonemachi",
    "gn:name":"Kaminemoto",
    "iso:country":"JP",
    "wof:name":"301-0902",
    "wof:placetype":"postalcode"
},
  "geometry": {"coordinates":[140.26179999999999,35.9167],"type":"Point"}
}