{
  "type": "Feature",
  "properties": {
    "gn:adm1_name":"Hiroshimaken",
    "gn:adm2_name":"Hiroshimashihigashiku",
    "gn:name":"Hesakayamasakichou",
    "iso:country":"JP",
    "wof:name":"732-0004",
    "wof:placetype":"postalcode"
},
  "geometry": {"coordinates":[132.48390000000001,34.4353],"type":"Point"}
}