{
  "type": "Feature",
  "properties": {
    "gn:adm1_name":"Tochigiken",
    "gn:adm2_name":"Nasugunnasumachi",
    "gn:name":"Ikanikeisaiganaibaai",
    "iso:country":"JP",
    "wof:name":"329-3200",
    "wof:placetype":"postalcode"
},
  "geometry": {"coordinates":[140.11859999999999,37.022],"type":"Point"}
}