{
  "type": "Feature",
  "properties": {
    "gn:adm1_name":"Miyagiken",
    "gn:adm2_name":"Sendaishiaobaku",
    "gn:name":"Oritate",
    "iso:country":"JP",
    "wof:name":"982-0261",
    "wof:placetype":"postalcode"
},
  "geometry": {"coordinates":[140.80510000000001,38.2705],"type":"Point"}
}