{
  "type": "Feature",
  "properties": {
    "gn:adm1_name":"Tochigiken",
    "gn:adm2_name":"Nikkoushi",
    "gn:name":"Kamihatsuishimachi",
    "iso:country":"JP",
    "wof:name":"321-1401",
    "wof:placetype":"postalcode"
},
  "geometry": {"coordinates":[139.60579999999999,36.7527],"type":"Point"}
}