{
  "type": "Feature",
  "properties": {
    "gn:adm1_name":"Naraken",
    "gn:adm2_name":"Yamatotakadashi",
    "gn:name":"Akebonochou",
    "iso:country":"JP",
    "wof:name":"635-0012",
    "wof:placetype":"postalcode"
},
  "geometry": {"coordinates":[135.75579999999999,34.513],"type":"Point"}
}