{
  "type": "Feature",
  "properties": {
    "gn:adm1_name":"Ibarakiken",
    "gn:adm2_name":"Yuukigunyachiyomachi",
    "gn:name":"Numamori",
    "iso:country":"JP",
    "wof:name":"300-3525",
    "wof:placetype":"postalcode"
},
  "geometry": {"coordinates":[139.91679999999999,36.1854],"type":"Point"}
}