{
  "type": "Feature",
  "properties": {
    "gn:adm1_name":"Aichiken",
    "gn:adm2_name":"Tokonameshi",
    "gn:name":"Kayakariguchi",
    "iso:country":"JP",
    "wof:name":"479-0063",
    "wof:placetype":"postalcode"
},
  "geometry": {"coordinates":[136.84520000000001,34.8966],"type":"Point"}
}