{
  "type": "Feature",
  "properties": {
    "gn:adm1_name":"Ehimeken",
    "gn:adm2_name":"Ochigunnamikatachou",
    "gn:name":"Moriage",
    "iso:country":"JP",
    "wof:name":"799-2106",
    "wof:placetype":"postalcode"
},
  "geometry": {"coordinates":[132.93219999999999,34.1227],"type":"Point"}
}