{
  "type": "Feature",
  "properties": {
    "gn:adm1_name":"Mieken",
    "gn:adm2_name":"Yokkaichishi",
    "gn:name":"Morigayamachou",
    "iso:country":"JP",
    "wof:name":"510-0957",
    "wof:placetype":"postalcode"
},
  "geometry": {"coordinates":[136.5829,34.9314],"type":"Point"}
}