{
  "type": "Feature",
  "properties": {
    "gn:adm1_name":"Okinawaken",
    "gn:adm2_name":"Gushikawashi",
    "gn:name":"Tengan",
    "iso:country":"JP",
    "wof:name":"904-2202",
    "wof:placetype":"postalcode"
},
  "geometry": {"coordinates":[127.8554,26.387],"type":"Point"}
}