{
  "type": "Feature",
  "properties": {
    "gn:adm1_name":"Fukuokaken",
    "gn:adm2_name":"Yukuhashishi",
    "gn:name":"Makomo",
    "iso:country":"JP",
    "wof:name":"824-0017",
    "wof:placetype":"postalcode"
},
  "geometry": {"coordinates":[131.00200000000001,33.7231],"type":"Point"}
}