{
  "type": "Feature",
  "properties": {
    "gn:adm1_name":"Fukushimaken",
    "gn:adm2_name":"Kitakatashi",
    "gn:name":"Seto",
    "iso:country":"JP",
    "wof:name":"966-0033",
    "wof:placetype":"postalcode"
},
  "geometry": {"coordinates":[139.886,37.6579],"type":"Point"}
}