{
  "type": "Feature",
  "properties": {
    "gn:adm1_name":"Kouchiken",
    "gn:adm2_name":"Susakishi",
    "gn:name":"Oonogoukou",
    "iso:country":"JP",
    "wof:name":"785-0030",
    "wof:placetype":"postalcode"
},
  "geometry": {"coordinates":[133.2773,33.4149],"type":"Point"}
}