{
  "type": "Feature",
  "properties": {
    "gn:adm1_name":"Mieken",
    "gn:adm2_name":"Wataraiguntamakichou",
    "gn:name":"Tsumuro",
    "iso:country":"JP",
    "wof:name":"519-0437",
    "wof:placetype":"postalcode"
},
  "geometry": {"coordinates":[136.5976,34.4699],"type":"Point"}
}