{
  "type": "Feature",
  "properties": {
    "gn:adm1_name":"Tottoriken",
    "gn:adm2_name":"Tottorishi",
    "gn:name":"Miyanaga",
    "iso:country":"JP",
    "wof:name":"680-0872",
    "wof:placetype":"postalcode"
},
  "geometry": {"coordinates":[134.22329999999999,35.4766],"type":"Point"}
}