{
  "type": "Feature",
  "properties": {
    "gn:adm1_name":"Hiroshimaken",
    "gn:adm2_name":"Kamogunkurosechou",
    "gn:name":"Ootada",
    "iso:country":"JP",
    "wof:name":"724-0611",
    "wof:placetype":"postalcode"
},
  "geometry": {"coordinates":[132.68190000000001,34.3405],"type":"Point"}
}