{
  "type": "Feature",
  "properties": {
    "gn:adm1_name":"Fukuokaken",
    "gn:adm2_name":"Ukihagunyoshiimachi",
    "gn:name":"Niiharu",
    "iso:country":"JP",
    "wof:name":"839-1306",
    "wof:placetype":"postalcode"
},
  "geometry": {"coordinates":[130.7517,33.3507],"type":"Point"}
}