{
  "type": "Feature",
  "properties": {
    "gn:adm1_name":"Yamagataken",
    "gn:adm2_name":"Sakatashi",
    "gn:name":"Midorichou",
    "iso:country":"JP",
    "wof:name":"998-0858",
    "wof:placetype":"postalcode"
},
  "geometry": {"coordinates":[139.85239999999999,38.9121],"type":"Point"}
}