{
  "type": "Feature",
  "properties": {
    "gn:adm1_name":"Okayamaken",
    "gn:adm2_name":"Atetsuguntetsutachou",
    "gn:name":"Hanagi",
    "iso:country":"JP",
    "wof:name":"718-0302",
    "wof:placetype":"postalcode"
},
  "geometry": {"coordinates":[133.46510000000001,34.9391],"type":"Point"}
}