{
  "type": "Feature",
  "properties": {
    "gn:adm1_name":"Chibaken",
    "gn:adm2_name":"Matsudoshi",
    "gn:name":"Minoridai",
    "iso:country":"JP",
    "wof:name":"270-2231",
    "wof:placetype":"postalcode"
},
  "geometry": {"coordinates":[139.9298,35.7848],"type":"Point"}
}