{
  "type": "Feature",
  "properties": {
    "gn:adm1_name":"Ishikawaken",
    "gn:adm2_name":"Kanazawashi",
    "gn:name":"Araya",
    "iso:country":"JP",
    "wof:name":"920-3124",
    "wof:placetype":"postalcode"
},
  "geometry": {"coordinates":[136.684,36.6153],"type":"Point"}
}