{
  "type": "Feature",
  "properties": {
    "gn:adm1_name":"Saitamaken",
    "gn:adm2_name":"Tokorozawashi",
    "gn:name":"Nakatomiminami",
    "iso:country":"JP",
    "wof:name":"359-0003",
    "wof:placetype":"postalcode"
},
  "geometry": {"coordinates":[139.49590000000001,35.813],"type":"Point"}
}