{
  "type": "Feature",
  "properties": {
    "gn:adm1_name":"Toukyouto",
    "gn:adm2_name":"Shinagawaku",
    "gn:name":"Koyama",
    "iso:country":"JP",
    "wof:name":"142-0062",
    "wof:placetype":"postalcode"
},
  "geometry": {"coordinates":[139.70310000000001,35.6175],"type":"Point"}
}