{
  "type": "Feature",
  "properties": {
    "gn:adm1_name":"Ooitaken",
    "gn:adm2_name":"Ooitashi",
    "gn:name":"Jounannishimachi",
    "iso:country":"JP",
    "wof:name":"870-0826",
    "wof:placetype":"postalcode"
},
  "geometry": {"coordinates":[131.57980000000001,33.2186],"type":"Point"}
}