{
  "type": "Feature",
  "properties": {
    "gn:adm1_name":"Gifuken",
    "gn:adm2_name":"Mashitagunhagiwarachou",
    "gn:name":"Hane",
    "iso:country":"JP",
    "wof:name":"509-2506",
    "wof:placetype":"postalcode"
},
  "geometry": {"coordinates":[137.20320000000001,35.89],"type":"Point"}
}