{
  "type": "Feature",
  "properties": {
    "gn:adm1_name":"Oosakafu",
    "gn:adm2_name":"Kawachinaganoshi",
    "gn:name":"Kagata",
    "iso:country":"JP",
    "wof:name":"586-0071",
    "wof:placetype":"postalcode"
},
  "geometry": {"coordinates":[135.56610000000001,34.4218],"type":"Point"}
}