{
  "type": "Feature",
  "properties": {
    "gn:adm1_name":"Okayamaken",
    "gn:adm2_name":"Tomatagunkagaminochou",
    "gn:name":"Oza",
    "iso:country":"JP",
    "wof:name":"708-0363",
    "wof:placetype":"postalcode"
},
  "geometry": {"coordinates":[133.9238,35.1066],"type":"Point"}
}