{
  "type": "Feature",
  "properties": {
    "gn:adm1_name":"Kyoutofu",
    "gn:adm2_name":"Kyoutoshishimogyouku",
    "gn:name":"Umekoujihigashinakamachi",
    "iso:country":"JP",
    "wof:name":"600-8852",
    "wof:placetype":"postalcode"
},
  "geometry": {"coordinates":[135.73699999999999,34.9849],"type":"Point"}
}