{
  "type": "Feature",
  "properties": {
    "gn:adm1_name":"Aichiken",
    "gn:adm2_name":"Tokonameshi",
    "gn:name":"Jounou",
    "iso:country":"JP",
    "wof:name":"479-0012",
    "wof:placetype":"postalcode"
},
  "geometry": {"coordinates":[136.874,34.8954],"type":"Point"}
}