{
  "type": "Feature",
  "properties": {
    "gn:adm1_name":"Kyoutofu",
    "gn:adm2_name":"Miyadushi",
    "gn:name":"Ogawa",
    "iso:country":"JP",
    "wof:name":"626-0021",
    "wof:placetype":"postalcode"
},
  "geometry": {"coordinates":[135.18969999999999,35.5364],"type":"Point"}
}