{
  "type": "Feature",
  "properties": {
    "gn:adm1_name":"Gunmaken",
    "gn:adm2_name":"Takasakishi",
    "gn:name":"Nakatoyookamachi",
    "iso:country":"JP",
    "wof:name":"370-0874",
    "wof:placetype":"postalcode"
},
  "geometry": {"coordinates":[138.97470000000001,36.3343],"type":"Point"}
}