{
  "type": "Feature",
  "properties": {
    "gn:adm1_name":"Hyougoken",
    "gn:adm2_name":"Koubeshinadaku",
    "gn:name":"Tsuchiyamachou",
    "iso:country":"JP",
    "wof:name":"657-0022",
    "wof:placetype":"postalcode"
},
  "geometry": {"coordinates":[135.2423,34.7282],"type":"Point"}
}