{
  "type": "Feature",
  "properties": {
    "gn:adm1_name":"Kouchiken",
    "gn:adm2_name":"Kouchishi",
    "gn:name":"Okurachou",
    "iso:country":"JP",
    "wof:name":"780-0801",
    "wof:placetype":"postalcode"
},
  "geometry": {"coordinates":[133.56659999999999,33.5589],"type":"Point"}
}