{
  "type": "Feature",
  "properties": {
    "gn:adm1_name":"Kouchiken",
    "gn:adm2_name":"Kamiguntosayamadachou",
    "gn:name":"Nakano",
    "iso:country":"JP",
    "wof:name":"782-0019",
    "wof:placetype":"postalcode"
},
  "geometry": {"coordinates":[133.68020000000001,33.5955],"type":"Point"}
}