{
  "type": "Feature",
  "properties": {
    "gn:adm1_name":"Toukyouto",
    "gn:adm2_name":"Machidashi",
    "gn:name":"Kougasaka",
    "iso:country":"JP",
    "wof:name":"194-0014",
    "wof:placetype":"postalcode"
},
  "geometry": {"coordinates":[139.46029999999999,35.5424],"type":"Point"}
}