{
  "type": "Feature",
  "properties": {
    "gn:adm1_name":"Wakayamaken",
    "gn:adm2_name":"Hidakagunyurachou",
    "gn:name":"Ato",
    "iso:country":"JP",
    "wof:name":"649-1113",
    "wof:placetype":"postalcode"
},
  "geometry": {"coordinates":[135.1147,33.9555],"type":"Point"}
}