{
  "type": "Feature",
  "properties": {
    "gn:adm1_name":"Kagoshimaken",
    "gn:adm2_name":"Makurazakishi",
    "gn:name":"Ootsukaminamimachi",
    "iso:country":"JP",
    "wof:name":"898-0029",
    "wof:placetype":"postalcode"
},
  "geometry": {"coordinates":[130.2749,31.2682],"type":"Point"}
}