{
  "type": "Feature",
  "properties": {
    "gn:adm1_name":"Kyoutofu",
    "gn:adm2_name":"Kyoutoshiyamashinaku",
    "gn:name":"Ooyakeyamada",
    "iso:country":"JP",
    "wof:name":"607-8175",
    "wof:placetype":"postalcode"
},
  "geometry": {"coordinates":[135.82409999999999,34.9681],"type":"Point"}
}