{
  "type": "Feature",
  "properties": {
    "gn:adm1_name":"Ooitaken",
    "gn:adm2_name":"Usagun'Innaimachi",
    "gn:name":"Kobira",
    "iso:country":"JP",
    "wof:name":"872-0455",
    "wof:placetype":"postalcode"
},
  "geometry": {"coordinates":[131.31049999999999,33.3635],"type":"Point"}
}