{
  "type": "Feature",
  "properties": {
    "gn:adm1_name":"Shimaneken",
    "gn:adm2_name":"Iishigunmitoyachou",
    "gn:name":"Igaya",
    "iso:country":"JP",
    "wof:name":"690-2401",
    "wof:placetype":"postalcode"
},
  "geometry": {"coordinates":[132.8801,35.3211],"type":"Point"}
}