{
  "type": "Feature",
  "properties": {
    "gn:adm1_name":"Okinawaken",
    "gn:adm2_name":"Urasoeshi",
    "gn:name":"Minatogawa",
    "iso:country":"JP",
    "wof:name":"901-2134",
    "wof:placetype":"postalcode"
},
  "geometry": {"coordinates":[127.71680000000001,26.2629],"type":"Point"}
}