{
  "type": "Feature",
  "properties": {
    "gn:adm1_name":"Ooitaken",
    "gn:adm2_name":"Kusugunkusumachi",
    "gn:name":"Tobata",
    "iso:country":"JP",
    "wof:name":"879-4331",
    "wof:placetype":"postalcode"
},
  "geometry": {"coordinates":[131.0907,33.2846],"type":"Point"}
}