{
  "type": "Feature",
  "properties": {
    "gn:adm1_name":"Gunmaken",
    "gn:adm2_name":"Setagunkurohonemura",
    "gn:name":"Kamitazawa",
    "iso:country":"JP",
    "wof:name":"376-0145",
    "wof:placetype":"postalcode"
},
  "geometry": {"coordinates":[139.28129999999999,36.5276],"type":"Point"}
}