{
  "type": "Feature",
  "properties": {
    "gn:adm1_name":"Niigataken",
    "gn:adm2_name":"Nakauonumaguntsunanmachi",
    "gn:name":"Maibara",
    "iso:country":"JP",
    "wof:name":"949-8312",
    "wof:placetype":"postalcode"
},
  "geometry": {"coordinates":[138.6902,37.0011],"type":"Point"}
}