{
  "type": "Feature",
  "properties": {
    "gn:adm1_name":"Kumamotoken",
    "gn:adm2_name":"Kamimashikigunmashikimachi",
    "gn:name":"Souryou",
    "iso:country":"JP",
    "wof:name":"861-2233",
    "wof:placetype":"postalcode"
},
  "geometry": {"coordinates":[130.80099999999999,32.7832],"type":"Point"}
}