{
  "type": "Feature",
  "properties": {
    "gn:adm1_name":"Ishikawaken",
    "gn:adm2_name":"Hakuishi",
    "gn:name":"Ishinomachi",
    "iso:country":"JP",
    "wof:name":"925-0026",
    "wof:placetype":"postalcode"
},
  "geometry": {"coordinates":[136.7979,36.895],"type":"Point"}
}