{
  "type": "Feature",
  "properties": {
    "gn:adm1_name":"Fukuokaken",
    "gn:adm2_name":"Chikujougunshinyoshitomimura",
    "gn:name":"Yakata",
    "iso:country":"JP",
    "wof:name":"871-0906",
    "wof:placetype":"postalcode"
},
  "geometry": {"coordinates":[131.1249,33.5688],"type":"Point"}
}