{
  "type": "Feature",
  "properties": {
    "gn:adm1_name":"Fukuokaken",
    "gn:adm2_name":"Miyakogunkatsuyamamachi",
    "gn:name":"Iwaguma",
    "iso:country":"JP",
    "wof:name":"824-0817",
    "wof:placetype":"postalcode"
},
  "geometry": {"coordinates":[130.8922,33.7103],"type":"Point"}
}