{
  "type": "Feature",
  "properties": {
    "gn:adm1_name":"Tochigiken",
    "gn:adm2_name":"Nasugunkarasuyamamachi",
    "gn:name":"Kanaga",
    "iso:country":"JP",
    "wof:name":"321-0632",
    "wof:placetype":"postalcode"
},
  "geometry": {"coordinates":[140.13409999999999,36.6581],"type":"Point"}
}