{
  "type": "Feature",
  "properties": {
    "gn:adm1_name":"Hyougoken",
    "gn:adm2_name":"Koubeshihyougoku",
    "gn:name":"Wadamiyadoori",
    "iso:country":"JP",
    "wof:name":"652-0863",
    "wof:placetype":"postalcode"
},
  "geometry": {"coordinates":[135.1746,34.6567],"type":"Point"}
}