{
  "type": "Feature",
  "properties": {
    "gn:adm1_name":"Hyougoken",
    "gn:adm2_name":"Toyookashi",
    "gn:name":"Koudani",
    "iso:country":"JP",
    "wof:name":"668-0872",
    "wof:placetype":"postalcode"
},
  "geometry": {"coordinates":[134.8486,35.5354],"type":"Point"}
}