{
  "type": "Feature",
  "properties": {
    "gn:adm1_name":"Oosakafu",
    "gn:adm2_name":"Oosakashinishinariku",
    "gn:name":"Nakabiraki",
    "iso:country":"JP",
    "wof:name":"557-0022",
    "wof:placetype":"postalcode"
},
  "geometry": {"coordinates":[135.4915,34.652],"type":"Point"}
}