{
  "type": "Feature",
  "properties": {
    "gn:adm1_name":"Fukuiken",
    "gn:adm2_name":"Obamashi",
    "gn:name":"Ueno",
    "iso:country":"JP",
    "wof:name":"917-0234",
    "wof:placetype":"postalcode"
},
  "geometry": {"coordinates":[135.79429999999999,35.4723],"type":"Point"}
}