{
  "type": "Feature",
  "properties": {
    "gn:adm1_name":"Ehimeken",
    "gn:adm2_name":"Onsengunnakajimachou",
    "gn:name":"Kaminuwa",
    "iso:country":"JP",
    "wof:name":"791-4322",
    "wof:placetype":"postalcode"
},
  "geometry": {"coordinates":[132.55549999999999,33.982],"type":"Point"}
}