{
  "type": "Feature",
  "properties": {
    "gn:adm1_name":"Gifuken",
    "gn:adm2_name":"Gifushi",
    "gn:name":"Sagiyamamidorigaoka",
    "iso:country":"JP",
    "wof:name":"502-0855",
    "wof:placetype":"postalcode"
},
  "geometry": {"coordinates":[136.75219999999999,35.4466],"type":"Point"}
}