{
  "type": "Feature",
  "properties": {
    "gn:adm1_name":"Ishikawaken",
    "gn:adm2_name":"Nomigunkawakitamachi",
    "gn:name":"Tsuchimuro",
    "iso:country":"JP",
    "wof:name":"923-1261",
    "wof:placetype":"postalcode"
},
  "geometry": {"coordinates":[136.55609999999999,36.4739],"type":"Point"}
}