{
  "type": "Feature",
  "properties": {
    "gn:adm1_name":"Fukuiken",
    "gn:adm2_name":"Fukuishi",
    "gn:name":"Tougounikachou",
    "iso:country":"JP",
    "wof:name":"910-2165",
    "wof:placetype":"postalcode"
},
  "geometry": {"coordinates":[136.27099999999999,36.0169],"type":"Point"}
}