{
  "type": "Feature",
  "properties": {
    "gn:adm1_name":"Shigaken",
    "gn:adm2_name":"Kanzakigun'Eigenjichou",
    "gn:name":"Ichiharano",
    "iso:country":"JP",
    "wof:name":"527-0224",
    "wof:placetype":"postalcode"
},
  "geometry": {"coordinates":[136.27090000000001,35.0726],"type":"Point"}
}