{
  "type": "Feature",
  "properties": {
    "gn:adm1_name":"Ehimeken",
    "gn:adm2_name":"Iyogunfutamichou",
    "gn:name":"Kounokawa",
    "iso:country":"JP",
    "wof:name":"799-3201",
    "wof:placetype":"postalcode"
},
  "geometry": {"coordinates":[132.66220000000001,33.7051],"type":"Point"}
}