{
  "type": "Feature",
  "properties": {
    "gn:adm1_name":"Nagasakiken",
    "gn:adm2_name":"Shimabarashi",
    "gn:name":"Kamiorihashimachi",
    "iso:country":"JP",
    "wof:name":"855-0076",
    "wof:placetype":"postalcode"
},
  "geometry": {"coordinates":[130.3383,32.7901],"type":"Point"}
}