{
  "type": "Feature",
  "properties": {
    "gn:adm1_name":"Ooitaken",
    "gn:adm2_name":"Nakatsushi",
    "gn:name":"Zentoku",
    "iso:country":"JP",
    "wof:name":"871-0002",
    "wof:placetype":"postalcode"
},
  "geometry": {"coordinates":[131.22720000000001,33.5884],"type":"Point"}
}