{
  "type": "Feature",
  "properties": {
    "gn:adm1_name":"Shizuokaken",
    "gn:adm2_name":"Hamamatsushi",
    "gn:name":"Terajimachou",
    "iso:country":"JP",
    "wof:name":"430-0925",
    "wof:placetype":"postalcode"
},
  "geometry": {"coordinates":[137.73830000000001,34.6994],"type":"Point"}
}