{
  "type": "Feature",
  "properties": {
    "gn:adm1_name":"Hyougoken",
    "gn:adm2_name":"Koubeshikitaku",
    "gn:name":"Higashiarinodai",
    "iso:country":"JP",
    "wof:name":"651-1322",
    "wof:placetype":"postalcode"
},
  "geometry": {"coordinates":[135.23609999999999,34.8086],"type":"Point"}
}