{
  "type": "Feature",
  "properties": {
    "gn:adm1_name":"Ishikawaken",
    "gn:adm2_name":"Ishikawagunnonoichimachi",
    "gn:name":"Hakusanmachi",
    "iso:country":"JP",
    "wof:name":"921-8821",
    "wof:placetype":"postalcode"
},
  "geometry": {"coordinates":[136.61189999999999,36.528],"type":"Point"}
}