{
  "type": "Feature",
  "properties": {
    "gn:adm1_name":"Okayamaken",
    "gn:adm2_name":"Maniwagunyatsukason",
    "gn:name":"Shimonagata",
    "iso:country":"JP",
    "wof:name":"717-0506",
    "wof:placetype":"postalcode"
},
  "geometry": {"coordinates":[133.7354,35.282],"type":"Point"}
}