{
  "type": "Feature",
  "properties": {
    "gn:adm1_name":"Okinawaken",
    "gn:adm2_name":"Hirarashi",
    "gn:name":"Nishihara",
    "iso:country":"JP",
    "wof:name":"906-0005",
    "wof:placetype":"postalcode"
},
  "geometry": {"coordinates":[125.31059999999999,24.8264],"type":"Point"}
}