{
  "type": "Feature",
  "properties": {
    "gn:adm1_name":"Chibaken",
    "gn:adm2_name":"Youkaichibashi",
    "gn:name":"Jouyanaka",
    "iso:country":"JP",
    "wof:name":"289-2114",
    "wof:placetype":"postalcode"
},
  "geometry": {"coordinates":[140.53049999999999,35.667],"type":"Point"}
}