{
  "type": "Feature",
  "properties": {
    "gn:adm1_name":"Fukuokaken",
    "gn:adm2_name":"Kurumeshi",
    "gn:name":"Shirayamamachi",
    "iso:country":"JP",
    "wof:name":"830-0041",
    "wof:placetype":"postalcode"
},
  "geometry": {"coordinates":[130.50069999999999,33.314],"type":"Point"}
}