{
  "type": "Feature",
  "properties": {
    "gn:adm1_name":"Saitamaken",
    "gn:adm2_name":"Saitamashimidoriku",
    "gn:name":"Harayama",
    "iso:country":"JP",
    "wof:name":"336-0931",
    "wof:placetype":"postalcode"
},
  "geometry": {"coordinates":[139.6721,35.8698],"type":"Point"}
}