{
  "type": "Feature",
  "properties": {
    "gn:adm1_name":"Okayamaken",
    "gn:adm2_name":"Okayamashi",
    "gn:name":"Kouyajiri",
    "iso:country":"JP",
    "wof:name":"701-2152",
    "wof:placetype":"postalcode"
},
  "geometry": {"coordinates":[133.93770000000001,34.7391],"type":"Point"}
}