{
  "type": "Feature",
  "properties": {
    "gn:adm1_name":"Nagasakiken",
    "gn:adm2_name":"Shimoagatagunmitsushimachou",
    "gn:name":"Nobu",
    "iso:country":"JP",
    "wof:name":"817-1104",
    "wof:placetype":"postalcode"
},
  "geometry": {"coordinates":[129.34829999999999,34.3689],"type":"Point"}
}