{
  "type": "Feature",
  "properties": {
    "gn:adm1_name":"Shigaken",
    "gn:adm2_name":"Ootsushi",
    "gn:name":"Saigawa",
    "iso:country":"JP",
    "wof:name":"520-0002",
    "wof:placetype":"postalcode"
},
  "geometry": {"coordinates":[135.86590000000001,35.0415],"type":"Point"}
}