{
  "type": "Feature",
  "properties": {
    "gn:adm1_name":"Tottoriken",
    "gn:adm2_name":"Saihakugunnawachou",
    "gn:name":"Ikanikeisaiganaibaai",
    "iso:country":"JP",
    "wof:name":"689-3200",
    "wof:placetype":"postalcode"
},
  "geometry": {"coordinates":[133.5599,35.5164],"type":"Point"}
}