{
  "type": "Feature",
  "properties": {
    "gn:adm1_name":"Hiroshimaken",
    "gn:adm2_name":"Higashihiroshimashi",
    "gn:name":"Saijouchoumisonou",
    "iso:country":"JP",
    "wof:name":"739-0024",
    "wof:placetype":"postalcode"
},
  "geometry": {"coordinates":[132.749,34.4088],"type":"Point"}
}