{
  "type": "Feature",
  "properties": {
    "gn:adm1_name":"Gifuken",
    "gn:adm2_name":"Gifushi",
    "gn:name":"Kashimachou",
    "iso:country":"JP",
    "wof:name":"500-8323",
    "wof:placetype":"postalcode"
},
  "geometry": {"coordinates":[136.73679999999999,35.4142],"type":"Point"}
}