{
  "type": "Feature",
  "properties": {
    "gn:adm1_name":"Oosakafu",
    "gn:adm2_name":"Izumishi",
    "gn:name":"Tomiakichou",
    "iso:country":"JP",
    "wof:name":"594-0082",
    "wof:placetype":"postalcode"
},
  "geometry": {"coordinates":[135.43510000000001,34.506],"type":"Point"}
}