{
  "type": "Feature",
  "properties": {
    "gn:adm1_name":"Miyagiken",
    "gn:adm2_name":"Monougun'Ogatsuchou",
    "gn:name":"Mizuhama",
    "iso:country":"JP",
    "wof:name":"986-1321",
    "wof:placetype":"postalcode"
},
  "geometry": {"coordinates":[141.48599999999999,38.5024],"type":"Point"}
}