{
  "type": "Feature",
  "properties": {
    "gn:adm1_name":"Ishikawaken",
    "gn:adm2_name":"Kanazawashi",
    "gn:name":"Moriyama",
    "iso:country":"JP",
    "wof:name":"920-0843",
    "wof:placetype":"postalcode"
},
  "geometry": {"coordinates":[136.66759999999999,36.5781],"type":"Point"}
}