{
  "type": "Feature",
  "properties": {
    "gn:adm1_name":"Chibaken",
    "gn:adm2_name":"Kimitsushi",
    "gn:name":"Tawarada",
    "iso:country":"JP",
    "wof:name":"292-0455",
    "wof:placetype":"postalcode"
},
  "geometry": {"coordinates":[140.05770000000001,35.3172],"type":"Point"}
}