{
  "type": "Feature",
  "properties": {
    "gn:adm1_name":"Aichiken",
    "gn:adm2_name":"Nishikasugaigunnishibiwajimachou",
    "gn:name":"Onoda",
    "iso:country":"JP",
    "wof:name":"452-0041",
    "wof:placetype":"postalcode"
},
  "geometry": {"coordinates":[136.86259999999999,35.1942],"type":"Point"}
}