{
  "type": "Feature",
  "properties": {
    "gn:adm1_name":"Aichiken",
    "gn:adm2_name":"Nagoyashichikusaku",
    "gn:name":"Ueno",
    "iso:country":"JP",
    "wof:name":"464-0082",
    "wof:placetype":"postalcode"
},
  "geometry": {"coordinates":[136.95140000000001,35.1793],"type":"Point"}
}