{
  "type": "Feature",
  "properties": {
    "gn:adm1_name":"Kanagawaken",
    "gn:adm2_name":"Yokohamashitsurumiku",
    "gn:name":"Asahichou",
    "iso:country":"JP",
    "wof:name":"230-0033",
    "wof:placetype":"postalcode"
},
  "geometry": {"coordinates":[139.69710000000001,35.5031],"type":"Point"}
}