{
  "type": "Feature",
  "properties": {
    "gn:adm1_name":"Kagoshimaken",
    "gn:adm2_name":"Hiokigunkinpouchou",
    "gn:name":"Hanaze",
    "iso:country":"JP",
    "wof:name":"899-3512",
    "wof:placetype":"postalcode"
},
  "geometry": {"coordinates":[130.34870000000001,31.4251],"type":"Point"}
}