{
  "type": "Feature",
  "properties": {
    "gn:adm1_name":"Kanagawaken",
    "gn:adm2_name":"Miurashi",
    "gn:name":"Misakimachijougashima",
    "iso:country":"JP",
    "wof:name":"238-0237",
    "wof:placetype":"postalcode"
},
  "geometry": {"coordinates":[139.61689999999999,35.1352],"type":"Point"}
}