{
  "type": "Feature",
  "properties": {
    "gn:adm1_name":"Aichiken",
    "gn:adm2_name":"Handashi",
    "gn:name":"Deguchichou",
    "iso:country":"JP",
    "wof:name":"475-0903",
    "wof:placetype":"postalcode"
},
  "geometry": {"coordinates":[136.92240000000001,34.903],"type":"Point"}
}