{
  "type": "Feature",
  "properties": {
    "gn:adm1_name":"Ehimeken",
    "gn:adm2_name":"Imabarishi",
    "gn:name":"Hacchounishi",
    "iso:country":"JP",
    "wof:name":"794-0832",
    "wof:placetype":"postalcode"
},
  "geometry": {"coordinates":[132.99039999999999,34.0452],"type":"Point"}
}