{
  "type": "Feature",
  "properties": {
    "gn:adm1_name":"Chibaken",
    "gn:adm2_name":"Sakurashi",
    "gn:name":"Oujidai",
    "iso:country":"JP",
    "wof:name":"285-0837",
    "wof:placetype":"postalcode"
},
  "geometry": {"coordinates":[140.1814,35.7269],"type":"Point"}
}