{
  "type": "Feature",
  "properties": {
    "gn:adm1_name":"Naganoken",
    "gn:adm2_name":"Kisogun'Agematsumachi",
    "gn:name":"Asahimachi",
    "iso:country":"JP",
    "wof:name":"399-5609",
    "wof:placetype":"postalcode"
},
  "geometry": {"coordinates":[137.69239999999999,35.7875],"type":"Point"}
}