{
  "type": "Feature",
  "properties": {
    "gn:adm1_name":"Niigataken",
    "gn:adm2_name":"Higashikanbaraguntsugawamachi",
    "gn:name":"Misatohei",
    "iso:country":"JP",
    "wof:name":"959-4412",
    "wof:placetype":"postalcode"
},
  "geometry": {"coordinates":[139.50069999999999,37.6592],"type":"Point"}
}