{
  "type": "Feature",
  "properties": {
    "gn:adm1_name":"Gunmaken",
    "gn:adm2_name":"Tanogun'Onishimachi",
    "gn:name":"Yuzurihara",
    "iso:country":"JP",
    "wof:name":"370-1402",
    "wof:placetype":"postalcode"
},
  "geometry": {"coordinates":[139.065,36.2477],"type":"Point"}
}