{
  "type": "Feature",
  "properties": {
    "gn:adm1_name":"Ooitaken",
    "gn:adm2_name":"Ooitashi",
    "gn:name":"Takajouminamimachi",
    "iso:country":"JP",
    "wof:name":"870-0155",
    "wof:placetype":"postalcode"
},
  "geometry": {"coordinates":[131.6576,33.2423],"type":"Point"}
}