{
  "type": "Feature",
  "properties": {
    "gn:adm1_name":"Naraken",
    "gn:adm2_name":"Narashi",
    "gn:name":"Maitanichou",
    "iso:country":"JP",
    "wof:name":"630-8402",
    "wof:placetype":"postalcode"
},
  "geometry": {"coordinates":[135.88120000000001,34.6179],"type":"Point"}
}