{
  "type": "Feature",
  "properties": {
    "gn:adm1_name":"Kyoutofu",
    "gn:adm2_name":"Kyoutoshishimogyouku",
    "gn:name":"Hashidonochou",
    "iso:country":"JP",
    "wof:name":"600-8113",
    "wof:placetype":"postalcode"
},
  "geometry": {"coordinates":[135.76669999999999,34.9934],"type":"Point"}
}