{
  "type": "Feature",
  "properties": {
    "gn:adm1_name":"Kanagawaken",
    "gn:adm2_name":"Yokohamashitsurumiku",
    "gn:name":"Daikokufutou",
    "iso:country":"JP",
    "wof:name":"230-0054",
    "wof:placetype":"postalcode"
},
  "geometry": {"coordinates":[139.68549999999999,35.462],"type":"Point"}
}