{
  "type": "Feature",
  "properties": {
    "gn:adm1_name":"Shimaneken",
    "gn:adm2_name":"Oochigun'Oochichou",
    "gn:name":"Yugakai",
    "iso:country":"JP",
    "wof:name":"699-4633",
    "wof:placetype":"postalcode"
},
  "geometry": {"coordinates":[132.57409999999999,35.0907],"type":"Point"}
}