{
  "type": "Feature",
  "properties": {
    "gn:adm1_name":"Ehimeken",
    "gn:adm2_name":"Nishiuwagunmisakichou",
    "gn:name":"Natori",
    "iso:country":"JP",
    "wof:name":"796-0816",
    "wof:placetype":"postalcode"
},
  "geometry": {"coordinates":[132.15039999999999,33.3841],"type":"Point"}
}