{
  "type": "Feature",
  "properties": {
    "gn:adm1_name":"Tottoriken",
    "gn:adm2_name":"Touhakuguntougouchou",
    "gn:name":"Nagae",
    "iso:country":"JP",
    "wof:name":"689-0737",
    "wof:placetype":"postalcode"
},
  "geometry": {"coordinates":[133.86920000000001,35.4738],"type":"Point"}
}