{
  "type": "Feature",
  "properties": {
    "gn:adm1_name":"Gunmaken",
    "gn:adm2_name":"Annakashi",
    "gn:name":"Goubara",
    "iso:country":"JP",
    "wof:name":"379-0135",
    "wof:placetype":"postalcode"
},
  "geometry": {"coordinates":[138.8382,36.3067],"type":"Point"}
}