{
  "type": "Feature",
  "properties": {
    "gn:adm1_name":"Aichiken",
    "gn:adm2_name":"Nishikasugaigunshinkawachou",
    "gn:name":"Kamigawara",
    "iso:country":"JP",
    "wof:name":"452-0913",
    "wof:placetype":"postalcode"
},
  "geometry": {"coordinates":[136.85339999999999,35.1952],"type":"Point"}
}