{
  "type": "Feature",
  "properties": {
    "gn:adm1_name":"Hyougoken",
    "gn:adm2_name":"Tatsunoshi",
    "gn:name":"Kamiokachoukamiyokouchi",
    "iso:country":"JP",
    "wof:name":"679-4103",
    "wof:placetype":"postalcode"
},
  "geometry": {"coordinates":[134.5754,34.8917],"type":"Point"}
}