{
  "type": "Feature",
  "properties": {
    "gn:adm1_name":"Naraken",
    "gn:adm2_name":"Gojoushi",
    "gn:name":"Yamadachou",
    "iso:country":"JP",
    "wof:name":"637-0029",
    "wof:placetype":"postalcode"
},
  "geometry": {"coordinates":[135.74250000000001,34.3704],"type":"Point"}
}