{
  "type": "Feature",
  "properties": {
    "gn:adm1_name":"Niigataken",
    "gn:adm2_name":"Shibatashi",
    "gn:name":"Mitsukunugi",
    "iso:country":"JP",
    "wof:name":"959-2326",
    "wof:placetype":"postalcode"
},
  "geometry": {"coordinates":[139.2704,37.9079],"type":"Point"}
}