{
  "type": "Feature",
  "properties": {
    "gn:adm1_name":"Mieken",
    "gn:adm2_name":"Kuwanashi",
    "gn:name":"Eba",
    "iso:country":"JP",
    "wof:name":"511-0836",
    "wof:placetype":"postalcode"
},
  "geometry": {"coordinates":[136.68790000000001,35.0524],"type":"Point"}
}