{
  "type": "Feature",
  "properties": {
    "gn:adm1_name":"Aichiken",
    "gn:adm2_name":"Amagunkaniechou",
    "gn:name":"Nishiki",
    "iso:country":"JP",
    "wof:name":"497-0054",
    "wof:placetype":"postalcode"
},
  "geometry": {"coordinates":[136.77930000000001,35.1355],"type":"Point"}
}