{
  "type": "Feature",
  "properties": {
    "gn:adm1_name":"Hyougoken",
    "gn:adm2_name":"Himejishi",
    "gn:name":"Kusunokichou",
    "iso:country":"JP",
    "wof:name":"670-0826",
    "wof:placetype":"postalcode"
},
  "geometry": {"coordinates":[134.7116,34.8344],"type":"Point"}
}