{
  "type": "Feature",
  "properties": {
    "gn:adm1_name":"Shizuokaken",
    "gn:adm2_name":"Shizuokashi",
    "gn:name":"Shimizueirakuchou",
    "iso:country":"JP",
    "wof:name":"424-0043",
    "wof:placetype":"postalcode"
},
  "geometry": {"coordinates":[138.47540000000001,35.0252],"type":"Point"}
}