{
  "type": "Feature",
  "properties": {
    "gn:adm1_name":"Aichiken",
    "gn:adm2_name":"Amagunsayachou",
    "gn:name":"Higashijou",
    "iso:country":"JP",
    "wof:name":"496-0914",
    "wof:placetype":"postalcode"
},
  "geometry": {"coordinates":[136.73220000000001,35.1367],"type":"Point"}
}