{
  "type": "Feature",
  "properties": {
    "gn:adm1_name":"Fukuokaken",
    "gn:adm2_name":"Munakatagunfukumamachi",
    "gn:name":"Hanaminosato",
    "iso:country":"JP",
    "wof:name":"811-3215",
    "wof:placetype":"postalcode"
},
  "geometry": {"coordinates":[130.47479999999999,33.7535],"type":"Point"}
}