{
  "type": "Feature",
  "properties": {
    "gn:adm1_name":"Mieken",
    "gn:adm2_name":"Owaseshi",
    "gn:name":"Kajikachou",
    "iso:country":"JP",
    "wof:name":"519-3923",
    "wof:placetype":"postalcode"
},
  "geometry": {"coordinates":[136.21719999999999,33.9646],"type":"Point"}
}