{
  "type": "Feature",
  "properties": {
    "gn:adm1_name":"Kanagawaken",
    "gn:adm2_name":"Yokohamashitsudukiku",
    "gn:name":"Kuzugaya",
    "iso:country":"JP",
    "wof:name":"224-0062",
    "wof:placetype":"postalcode"
},
  "geometry": {"coordinates":[139.5625,35.5368],"type":"Point"}
}