{
  "type": "Feature",
  "properties": {
    "gn:adm1_name":"Tottoriken",
    "gn:adm2_name":"Kurayoshishi",
    "gn:name":"Ohara",
    "iso:country":"JP",
    "wof:name":"682-0034",
    "wof:placetype":"postalcode"
},
  "geometry": {"coordinates":[133.85509999999999,35.4222],"type":"Point"}
}