{
  "type": "Feature",
  "properties": {
    "gn:adm1_name":"Yamagataken",
    "gn:adm2_name":"Nishimurayamagun'Ooemachi",
    "gn:name":"Juuhatsusaikou",
    "iso:country":"JP",
    "wof:name":"990-1144",
    "wof:placetype":"postalcode"
},
  "geometry": {"coordinates":[140.13390000000001,38.3841],"type":"Point"}
}