{
  "type": "Feature",
  "properties": {
    "gn:adm1_name":"Toyamaken",
    "gn:adm2_name":"Tonamishi",
    "gn:name":"Takandou",
    "iso:country":"JP",
    "wof:name":"939-1383",
    "wof:placetype":"postalcode"
},
  "geometry": {"coordinates":[136.96629999999999,36.6382],"type":"Point"}
}