{
  "type": "Feature",
  "properties": {
    "gn:adm1_name":"Hiroshimaken",
    "gn:adm2_name":"Kounugunsouryouchou",
    "gn:name":"Kamiryouke",
    "iso:country":"JP",
    "wof:name":"729-3712",
    "wof:placetype":"postalcode"
},
  "geometry": {"coordinates":[133.1266,34.8028],"type":"Point"}
}