{
  "type": "Feature",
  "properties": {
    "gn:adm1_name":"Fukuiken",
    "gn:adm2_name":"Ooiguntakahamachou",
    "gn:name":"Miyazaki",
    "iso:country":"JP",
    "wof:name":"919-2225",
    "wof:placetype":"postalcode"
},
  "geometry": {"coordinates":[135.5496,35.4884],"type":"Point"}
}