{
  "type": "Feature",
  "properties": {
    "gn:adm1_name":"Toukyouto",
    "gn:adm2_name":"Higashimurayamashi",
    "gn:name":"Hagiyamachou",
    "iso:country":"JP",
    "wof:name":"189-0012",
    "wof:placetype":"postalcode"
},
  "geometry": {"coordinates":[139.4785,35.7418],"type":"Point"}
}