{
  "type": "Feature",
  "properties": {
    "gn:adm1_name":"Chibaken",
    "gn:adm2_name":"Kisaradushi",
    "gn:name":"Bunkyou",
    "iso:country":"JP",
    "wof:name":"292-0804",
    "wof:placetype":"postalcode"
},
  "geometry": {"coordinates":[139.9299,35.3756],"type":"Point"}
}