{
  "type": "Feature",
  "properties": {
    "gn:adm1_name":"Ishikawaken",
    "gn:adm2_name":"Wajimashi",
    "gn:name":"Futasemachi",
    "iso:country":"JP",
    "wof:name":"928-0031",
    "wof:placetype":"postalcode"
},
  "geometry": {"coordinates":[136.8963,37.3873],"type":"Point"}
}