{
  "type": "Feature",
  "properties": {
    "gn:adm1_name":"Ibarakiken",
    "gn:adm2_name":"Kujigunkanasagoumachi",
    "gn:name":"Kamimiyakawauchi",
    "iso:country":"JP",
    "wof:name":"313-0101",
    "wof:placetype":"postalcode"
},
  "geometry": {"coordinates":[140.43170000000001,36.6386],"type":"Point"}
}