{
  "type": "Feature",
  "properties": {
    "gn:adm1_name":"Aichiken",
    "gn:adm2_name":"Owariasahishi",
    "gn:name":"Toumeinishichou",
    "iso:country":"JP",
    "wof:name":"488-0844",
    "wof:placetype":"postalcode"
},
  "geometry": {"coordinates":[137.0086,35.2069],"type":"Point"}
}