{
  "type": "Feature",
  "properties": {
    "gn:adm1_name":"Okinawaken",
    "gn:adm2_name":"Kunigamigunmotobuchou",
    "gn:name":"Furujima",
    "iso:country":"JP",
    "wof:name":"905-0218",
    "wof:placetype":"postalcode"
},
  "geometry": {"coordinates":[127.9008,26.6792],"type":"Point"}
}