{
  "type": "Feature",
  "properties": {
    "gn:adm1_name":"Yamaguchiken",
    "gn:adm2_name":"Iwakunishi",
    "gn:name":"Mochikuni",
    "iso:country":"JP",
    "wof:name":"741-0085",
    "wof:placetype":"postalcode"
},
  "geometry": {"coordinates":[132.13839999999999,34.1684],"type":"Point"}
}