{
  "type": "Feature",
  "properties": {
    "gn:adm1_name":"Tottoriken",
    "gn:adm2_name":"Tottorishi",
    "gn:name":"Gotandachou",
    "iso:country":"JP",
    "wof:name":"680-0932",
    "wof:placetype":"postalcode"
},
  "geometry": {"coordinates":[134.19759999999999,35.5099],"type":"Point"}
}