{
  "type": "Feature",
  "properties": {
    "gn:adm1_name":"Hiroshimaken",
    "gn:adm2_name":"Kureshi",
    "gn:name":"Nigataootoshichou",
    "iso:country":"JP",
    "wof:name":"737-0153",
    "wof:placetype":"postalcode"
},
  "geometry": {"coordinates":[132.6627,34.222],"type":"Point"}
}