{
  "type": "Feature",
  "properties": {
    "gn:adm1_name":"Wakayamaken",
    "gn:adm2_name":"Wakayamashi",
    "gn:name":"Omatsuchou",
    "iso:country":"JP",
    "wof:name":"640-8124",
    "wof:placetype":"postalcode"
},
  "geometry": {"coordinates":[135.18170000000001,34.2209],"type":"Point"}
}