{
  "type": "Feature",
  "properties": {
    "gn:adm1_name":"Chibaken",
    "gn:adm2_name":"Abikoshi",
    "gn:name":"Nakazato",
    "iso:country":"JP",
    "wof:name":"270-1122",
    "wof:placetype":"postalcode"
},
  "geometry": {"coordinates":[140.0823,35.866],"type":"Point"}
}