{
  "type": "Feature",
  "properties": {
    "gn:adm1_name":"Yamagataken",
    "gn:adm2_name":"Yamagatashi",
    "gn:name":"Miyaura",
    "iso:country":"JP",
    "wof:name":"990-0848",
    "wof:placetype":"postalcode"
},
  "geometry": {"coordinates":[140.2954,38.2597],"type":"Point"}
}