{
  "type": "Feature",
  "properties": {
    "gn:adm1_name":"Okinawaken",
    "gn:adm2_name":"Shimajirigunkumejimachou",
    "gn:name":"Aka",
    "iso:country":"JP",
    "wof:name":"901-3103",
    "wof:placetype":"postalcode"
},
  "geometry": {"coordinates":[126.7937,26.364],"type":"Point"}
}