{
  "type": "Feature",
  "properties": {
    "gn:adm1_name":"Fukuokaken",
    "gn:adm2_name":"Kitakyuushuushikokurakitaku",
    "gn:name":"Shimotomino",
    "iso:country":"JP",
    "wof:name":"802-0023",
    "wof:placetype":"postalcode"
},
  "geometry": {"coordinates":[130.8963,33.8786],"type":"Point"}
}