{
  "type": "Feature",
  "properties": {
    "gn:adm1_name":"Fukushimaken",
    "gn:adm2_name":"Tamuraguntokiwamachi",
    "gn:name":"Hotta",
    "iso:country":"JP",
    "wof:name":"963-4611",
    "wof:placetype":"postalcode"
},
  "geometry": {"coordinates":[140.69560000000001,37.4109],"type":"Point"}
}