{
  "type": "Feature",
  "properties": {
    "gn:adm1_name":"Tokushimaken",
    "gn:adm2_name":"Miyoshigun'Ikedachou",
    "gn:name":"Shima",
    "iso:country":"JP",
    "wof:name":"778-0005",
    "wof:placetype":"postalcode"
},
  "geometry": {"coordinates":[133.8177,34.0276],"type":"Point"}
}