{
  "type": "Feature",
  "properties": {
    "gn:adm1_name":"Kanagawaken",
    "gn:adm2_name":"Yokohamashisakaeku",
    "gn:name":"Koyamadai",
    "iso:country":"JP",
    "wof:name":"247-0002",
    "wof:placetype":"postalcode"
},
  "geometry": {"coordinates":[139.5574,35.3775],"type":"Point"}
}