{
  "type": "Feature",
  "properties": {
    "gn:adm1_name":"Miyagiken",
    "gn:adm2_name":"Kurokawaguntomiyamachi",
    "gn:name":"Tomigaoka",
    "iso:country":"JP",
    "wof:name":"981-3352",
    "wof:placetype":"postalcode"
},
  "geometry": {"coordinates":[140.8663,38.3653],"type":"Point"}
}