{
  "type": "Feature",
  "properties": {
    "gn:adm1_name":"Kyoutofu",
    "gn:adm2_name":"Miyadushi",
    "gn:name":"Tonogaki",
    "iso:country":"JP",
    "wof:name":"626-0205",
    "wof:placetype":"postalcode"
},
  "geometry": {"coordinates":[135.25229999999999,35.662],"type":"Point"}
}