{
  "type": "Feature",
  "properties": {
    "gn:adm1_name":"Okinawaken",
    "gn:adm2_name":"Nahashi",
    "gn:name":"Oomine",
    "iso:country":"JP",
    "wof:name":"901-0148",
    "wof:placetype":"postalcode"
},
  "geometry": {"coordinates":[127.68980000000001,26.2132],"type":"Point"}
}