{
  "type": "Feature",
  "properties": {
    "gn:adm1_name":"Niigataken",
    "gn:adm2_name":"Jouetsushi",
    "gn:name":"Ii",
    "iso:country":"JP",
    "wof:name":"943-0896",
    "wof:placetype":"postalcode"
},
  "geometry": {"coordinates":[138.2302,37.1249],"type":"Point"}
}