{
  "type": "Feature",
  "properties": {
    "gn:adm1_name":"Tochigiken",
    "gn:adm2_name":"Kuroisoshi",
    "gn:name":"Kiwatahata",
    "iso:country":"JP",
    "wof:name":"325-0116",
    "wof:placetype":"postalcode"
},
  "geometry": {"coordinates":[139.93459999999999,36.9937],"type":"Point"}
}