{
  "type": "Feature",
  "properties": {
    "gn:adm1_name":"Hyougoken",
    "gn:adm2_name":"Himejishi",
    "gn:name":"Chounotsubo",
    "iso:country":"JP",
    "wof:name":"670-0984",
    "wof:placetype":"postalcode"
},
  "geometry": {"coordinates":[134.6611,34.8196],"type":"Point"}
}