{
  "type": "Feature",
  "properties": {
    "gn:adm1_name":"Aichiken",
    "gn:adm2_name":"Kounanshi",
    "gn:name":"Hoteichounishiho",
    "iso:country":"JP",
    "wof:name":"483-8141",
    "wof:placetype":"postalcode"
},
  "geometry": {"coordinates":[136.87219999999999,35.3185],"type":"Point"}
}