{
  "type": "Feature",
  "properties": {
    "gn:adm1_name":"Okayamaken",
    "gn:adm2_name":"Okayamashi",
    "gn:name":"Koujita",
    "iso:country":"JP",
    "wof:name":"703-8225",
    "wof:placetype":"postalcode"
},
  "geometry": {"coordinates":[133.98320000000001,34.6765],"type":"Point"}
}