{
  "type": "Feature",
  "properties": {
    "gn:adm1_name":"Nagasakiken",
    "gn:adm2_name":"Nishisonogigunnomozakichou",
    "gn:name":"Takahama",
    "iso:country":"JP",
    "wof:name":"851-0503",
    "wof:placetype":"postalcode"
},
  "geometry": {"coordinates":[129.78649999999999,32.6052],"type":"Point"}
}