{
  "type": "Feature",
  "properties": {
    "gn:adm1_name":"Chibaken",
    "gn:adm2_name":"Kimitsushi",
    "gn:name":"Uchiminowa",
    "iso:country":"JP",
    "wof:name":"299-1176",
    "wof:placetype":"postalcode"
},
  "geometry": {"coordinates":[139.93180000000001,35.3259],"type":"Point"}
}