{
  "type": "Feature",
  "properties": {
    "gn:adm1_name":"Ooitaken",
    "gn:adm2_name":"Beppushi",
    "gn:name":"Minamitateishiniku",
    "iso:country":"JP",
    "wof:name":"874-0827",
    "wof:placetype":"postalcode"
},
  "geometry": {"coordinates":[131.47020000000001,33.2908],"type":"Point"}
}