{
  "type": "Feature",
  "properties": {
    "gn:adm1_name":"Naraken",
    "gn:adm2_name":"Narashi",
    "gn:name":"Wadachou",
    "iso:country":"JP",
    "wof:name":"630-2176",
    "wof:placetype":"postalcode"
},
  "geometry": {"coordinates":[135.9051,34.6613],"type":"Point"}
}