{
  "type": "Feature",
  "properties": {
    "gn:adm1_name":"Toukyouto",
    "gn:adm2_name":"Akirunoshi",
    "gn:name":"Fuchigami",
    "iso:country":"JP",
    "wof:name":"197-0833",
    "wof:placetype":"postalcode"
},
  "geometry": {"coordinates":[139.27379999999999,35.7241],"type":"Point"}
}