{
  "type": "Feature",
  "properties": {
    "gn:adm1_name":"Miyagiken",
    "gn:adm2_name":"Sendaishiaobaku",
    "gn:name":"Sanjoumachi",
    "iso:country":"JP",
    "wof:name":"981-0935",
    "wof:placetype":"postalcode"
},
  "geometry": {"coordinates":[140.85300000000001,38.2808],"type":"Point"}
}