{
  "type": "Feature",
  "properties": {
    "gn:adm1_name":"Kanagawaken",
    "gn:adm2_name":"Chigasakishi",
    "gn:name":"Nishikubo",
    "iso:country":"JP",
    "wof:name":"253-0083",
    "wof:placetype":"postalcode"
},
  "geometry": {"coordinates":[139.3973,35.3483],"type":"Point"}
}