{
  "type": "Feature",
  "properties": {
    "gn:adm1_name":"Niigataken",
    "gn:adm2_name":"Jouetsushi",
    "gn:name":"Higashikyouden",
    "iso:country":"JP",
    "wof:name":"943-0415",
    "wof:placetype":"postalcode"
},
  "geometry": {"coordinates":[138.33600000000001,37.0876],"type":"Point"}
}