{
  "type": "Feature",
  "properties": {
    "gn:adm1_name":"Shigaken",
    "gn:adm2_name":"Koukagunminakuchichou",
    "gn:name":"Minamihayashiguchi",
    "iso:country":"JP",
    "wof:name":"528-0029",
    "wof:placetype":"postalcode"
},
  "geometry": {"coordinates":[136.15979999999999,34.9716],"type":"Point"}
}