{
  "type": "Feature",
  "properties": {
    "gn:adm1_name":"Naraken",
    "gn:adm2_name":"Ikomashi",
    "gn:name":"Higashishinmachi",
    "iso:country":"JP",
    "wof:name":"630-0258",
    "wof:placetype":"postalcode"
},
  "geometry": {"coordinates":[135.70160000000001,34.6925],"type":"Point"}
}