{
  "type": "Feature",
  "properties": {
    "gn:adm1_name":"Aichiken",
    "gn:adm2_name":"Inazawashi",
    "gn:name":"Gichouchou",
    "iso:country":"JP",
    "wof:name":"492-8343",
    "wof:placetype":"postalcode"
},
  "geometry": {"coordinates":[136.76390000000001,35.2363],"type":"Point"}
}