{
  "type": "Feature",
  "properties": {
    "gn:adm1_name":"Aichiken",
    "gn:adm2_name":"Nagoyashinakagawaku",
    "gn:name":"Yanagawachou",
    "iso:country":"JP",
    "wof:name":"454-0014",
    "wof:placetype":"postalcode"
},
  "geometry": {"coordinates":[136.8955,35.1388],"type":"Point"}
}