{
  "type": "Feature",
  "properties": {
    "gn:adm1_name":"Okinawaken",
    "gn:adm2_name":"Nahashi",
    "gn:name":"Mekaru",
    "iso:country":"JP",
    "wof:name":"900-0004",
    "wof:placetype":"postalcode"
},
  "geometry": {"coordinates":[127.6998,26.2317],"type":"Point"}
}