{
  "type": "Feature",
  "properties": {
    "gn:adm1_name":"Kyoutofu",
    "gn:adm2_name":"Kyoutoshiminamiku",
    "gn:name":"Nishikujoukoderachou",
    "iso:country":"JP",
    "wof:name":"601-8404",
    "wof:placetype":"postalcode"
},
  "geometry": {"coordinates":[135.75020000000001,34.9847],"type":"Point"}
}