{
  "type": "Feature",
  "properties": {
    "gn:adm1_name":"Hiroshimaken",
    "gn:adm2_name":"Fukuyamashi",
    "gn:name":"Higashiteshirochou",
    "iso:country":"JP",
    "wof:name":"721-0962",
    "wof:placetype":"postalcode"
},
  "geometry": {"coordinates":[133.40559999999999,34.4855],"type":"Point"}
}