{
  "type": "Feature",
  "properties": {
    "gn:adm1_name":"Saitamaken",
    "gn:adm2_name":"Hidakashi",
    "gn:name":"Shimokayama",
    "iso:country":"JP",
    "wof:name":"350-1233",
    "wof:placetype":"postalcode"
},
  "geometry": {"coordinates":[139.35429999999999,35.8975],"type":"Point"}
}