{
  "type": "Feature",
  "properties": {
    "gn:adm1_name":"Kumamotoken",
    "gn:adm2_name":"Kamotogun'Uekimachi",
    "gn:name":"Nachi",
    "iso:country":"JP",
    "wof:name":"861-0154",
    "wof:placetype":"postalcode"
},
  "geometry": {"coordinates":[130.65629999999999,32.8912],"type":"Point"}
}