{
  "type": "Feature",
  "properties": {
    "gn:adm1_name":"Kanagawaken",
    "gn:adm2_name":"Chigasakishi",
    "gn:name":"Matsuo",
    "iso:country":"JP",
    "wof:name":"253-0065",
    "wof:placetype":"postalcode"
},
  "geometry": {"coordinates":[139.386,35.3267],"type":"Point"}
}