{
  "type": "Feature",
  "properties": {
    "gn:adm1_name":"Fukuiken",
    "gn:adm2_name":"Yoshidagunmatsuokachou",
    "gn:name":"Konoshita",
    "iso:country":"JP",
    "wof:name":"910-1139",
    "wof:placetype":"postalcode"
},
  "geometry": {"coordinates":[136.29409999999999,36.0942],"type":"Point"}
}