{
  "type": "Feature",
  "properties": {
    "gn:adm1_name":"Chibaken",
    "gn:adm2_name":"Tateyamashi",
    "gn:name":"Hougai",
    "iso:country":"JP",
    "wof:name":"294-0013",
    "wof:placetype":"postalcode"
},
  "geometry": {"coordinates":[139.91630000000001,34.989],"type":"Point"}
}