{
  "type": "Feature",
  "properties": {
    "gn:adm1_name":"Fukushimaken",
    "gn:adm2_name":"Iwakishi",
    "gn:name":"Onahamaiwade",
    "iso:country":"JP",
    "wof:name":"971-8121",
    "wof:placetype":"postalcode"
},
  "geometry": {"coordinates":[140.88560000000001,36.9868],"type":"Point"}
}