{
  "type": "Feature",
  "properties": {
    "gn:adm1_name":"Naganoken",
    "gn:adm2_name":"Okayashi",
    "gn:name":"Enryou",
    "iso:country":"JP",
    "wof:name":"394-0051",
    "wof:placetype":"postalcode"
},
  "geometry": {"coordinates":[138.0308,36.0775],"type":"Point"}
}