{
  "type": "Feature",
  "properties": {
    "gn:adm1_name":"Tottoriken",
    "gn:adm2_name":"Kurayoshishi",
    "gn:name":"Tsuwara",
    "iso:country":"JP",
    "wof:name":"682-0951",
    "wof:placetype":"postalcode"
},
  "geometry": {"coordinates":[133.75839999999999,35.4652],"type":"Point"}
}