{
  "type": "Feature",
  "properties": {
    "gn:adm1_name":"Niigataken",
    "gn:adm2_name":"Santougunteradomarimachi",
    "gn:name":"Motomegusa",
    "iso:country":"JP",
    "wof:name":"959-0151",
    "wof:placetype":"postalcode"
},
  "geometry": {"coordinates":[138.81209999999999,37.6092],"type":"Point"}
}