{
  "type": "Feature",
  "properties": {
    "gn:adm1_name":"Ooitaken",
    "gn:adm2_name":"Bungotakadashi",
    "gn:name":"Arao",
    "iso:country":"JP",
    "wof:name":"879-0733",
    "wof:placetype":"postalcode"
},
  "geometry": {"coordinates":[131.4932,33.5637],"type":"Point"}
}