{
  "type": "Feature",
  "properties": {
    "gn:adm1_name":"Kyoutofu",
    "gn:adm2_name":"Kitakuwadagunkeihokuchou",
    "gn:name":"Shimoyuge",
    "iso:country":"JP",
    "wof:name":"601-0534",
    "wof:placetype":"postalcode"
},
  "geometry": {"coordinates":[135.63390000000001,35.1889],"type":"Point"}
}