{
  "type": "Feature",
  "properties": {
    "gn:adm1_name":"Fukushimaken",
    "gn:adm2_name":"Aiduwakamatsushi",
    "gn:name":"Nisshinmachi",
    "iso:country":"JP",
    "wof:name":"965-0861",
    "wof:placetype":"postalcode"
},
  "geometry": {"coordinates":[139.92089999999999,37.4971],"type":"Point"}
}