{
  "type": "Feature",
  "properties": {
    "gn:adm1_name":"Tokushimaken",
    "gn:adm2_name":"Tokushimashi",
    "gn:name":"Ootanichou",
    "iso:country":"JP",
    "wof:name":"770-8031",
    "wof:placetype":"postalcode"
},
  "geometry": {"coordinates":[134.53749999999999,34.0337],"type":"Point"}
}