{
  "type": "Feature",
  "properties": {
    "gn:adm1_name":"Kouchiken",
    "gn:adm2_name":"Hatagun'Ootsukichou",
    "gn:name":"Yoshinosawa",
    "iso:country":"JP",
    "wof:name":"788-0362",
    "wof:placetype":"postalcode"
},
  "geometry": {"coordinates":[132.70580000000001,32.8108],"type":"Point"}
}