{
  "type": "Feature",
  "properties": {
    "gn:adm1_name":"Aichiken",
    "gn:adm2_name":"Kounanshi",
    "gn:name":"Shimamiyachoumizuhori",
    "iso:country":"JP",
    "wof:name":"483-8268",
    "wof:placetype":"postalcode"
},
  "geometry": {"coordinates":[136.8475,35.3342],"type":"Point"}
}