{
  "type": "Feature",
  "properties": {
    "gn:adm1_name":"Hyougoken",
    "gn:adm2_name":"Koubeshisumaku",
    "gn:name":"Mizunochou",
    "iso:country":"JP",
    "wof:name":"654-0062",
    "wof:placetype":"postalcode"
},
  "geometry": {"coordinates":[135.119,34.6546],"type":"Point"}
}