{
  "type": "Feature",
  "properties": {
    "gn:adm1_name":"Gifuken",
    "gn:adm2_name":"Oonogunnyuukawamura",
    "gn:name":"Yamakuchi",
    "iso:country":"JP",
    "wof:name":"506-2122",
    "wof:placetype":"postalcode"
},
  "geometry": {"coordinates":[137.3194,36.1609],"type":"Point"}
}