{
  "type": "Feature",
  "properties": {
    "gn:adm1_name":"Nagasakiken",
    "gn:adm2_name":"Shimoagatagun'Iduharamachi",
    "gn:name":"Kuta",
    "iso:country":"JP",
    "wof:name":"817-0032",
    "wof:placetype":"postalcode"
},
  "geometry": {"coordinates":[129.28229999999999,34.186],"type":"Point"}
}