{
  "type": "Feature",
  "properties": {
    "gn:adm1_name":"Oosakafu",
    "gn:adm2_name":"Takatsukishi",
    "gn:name":"Tondaokamachi",
    "iso:country":"JP",
    "wof:name":"569-1145",
    "wof:placetype":"postalcode"
},
  "geometry": {"coordinates":[135.58760000000001,34.8359],"type":"Point"}
}