{
  "type": "Feature",
  "properties": {
    "gn:adm1_name":"Ishikawaken",
    "gn:adm2_name":"Kagashi",
    "gn:name":"Nankaichishinmachi",
    "iso:country":"JP",
    "wof:name":"922-0324",
    "wof:placetype":"postalcode"
},
  "geometry": {"coordinates":[136.34630000000001,36.3138],"type":"Point"}
}