{
  "type": "Feature",
  "properties": {
    "gn:adm1_name":"Toukyouto",
    "gn:adm2_name":"Shinjukuku",
    "gn:name":"Nishiochiai",
    "iso:country":"JP",
    "wof:name":"161-0031",
    "wof:placetype":"postalcode"
},
  "geometry": {"coordinates":[139.67930000000001,35.723],"type":"Point"}
}