{
  "type": "Feature",
  "properties": {
    "gn:adm1_name":"Shigaken",
    "gn:adm2_name":"Inukamiguntoyosatochou",
    "gn:name":"Mitsuike",
    "iso:country":"JP",
    "wof:name":"529-1177",
    "wof:placetype":"postalcode"
},
  "geometry": {"coordinates":[136.226,35.203],"type":"Point"}
}