{
  "type": "Feature",
  "properties": {
    "gn:adm1_name":"Chibaken",
    "gn:adm2_name":"Isumigunmisakimachi",
    "gn:name":"Iwakuma",
    "iso:country":"JP",
    "wof:name":"299-4505",
    "wof:placetype":"postalcode"
},
  "geometry": {"coordinates":[140.3382,35.325],"type":"Point"}
}