{
  "type": "Feature",
  "properties": {
    "gn:adm1_name":"Toukyouto",
    "gn:adm2_name":"Itabashiku",
    "gn:name":"Tokumaru",
    "iso:country":"JP",
    "wof:name":"175-0083",
    "wof:placetype":"postalcode"
},
  "geometry": {"coordinates":[139.6602,35.7741],"type":"Point"}
}