{
  "type": "Feature",
  "properties": {
    "gn:adm1_name":"Ibarakiken",
    "gn:adm2_name":"Kashimashi",
    "gn:name":"Tayanuma",
    "iso:country":"JP",
    "wof:name":"314-0048",
    "wof:placetype":"postalcode"
},
  "geometry": {"coordinates":[140.63079999999999,35.9861],"type":"Point"}
}