{
  "type": "Feature",
  "properties": {
    "gn:adm1_name":"Mieken",
    "gn:adm2_name":"Iseshi",
    "gn:name":"Shimonochou",
    "iso:country":"JP",
    "wof:name":"516-0003",
    "wof:placetype":"postalcode"
},
  "geometry": {"coordinates":[136.73349999999999,34.5161],"type":"Point"}
}