{
  "type": "Feature",
  "properties": {
    "gn:adm1_name":"Ooitaken",
    "gn:adm2_name":"Usashi",
    "gn:name":"Asou",
    "iso:country":"JP",
    "wof:name":"879-0501",
    "wof:placetype":"postalcode"
},
  "geometry": {"coordinates":[131.2715,33.4686],"type":"Point"}
}