{
  "type": "Feature",
  "properties": {
    "gn:adm1_name":"Naraken",
    "gn:adm2_name":"Yamatokooriyamashi",
    "gn:name":"Nukatabeminamichou",
    "iso:country":"JP",
    "wof:name":"639-1035",
    "wof:placetype":"postalcode"
},
  "geometry": {"coordinates":[135.77199999999999,34.5993],"type":"Point"}
}