{
  "type": "Feature",
  "properties": {
    "gn:adm1_name":"Oosakafu",
    "gn:adm2_name":"Sakaishi",
    "gn:name":"Fukuda",
    "iso:country":"JP",
    "wof:name":"599-8241",
    "wof:placetype":"postalcode"
},
  "geometry": {"coordinates":[135.52440000000001,34.5226],"type":"Point"}
}