{
  "type": "Feature",
  "properties": {
    "gn:adm1_name":"Fukuokaken",
    "gn:adm2_name":"Kasuyagun'Umimachi",
    "gn:name":"Yurigaoka",
    "iso:country":"JP",
    "wof:name":"811-2108",
    "wof:placetype":"postalcode"
},
  "geometry": {"coordinates":[130.53319999999999,33.556],"type":"Point"}
}