{
  "type": "Feature",
  "properties": {
    "gn:adm1_name":"Gifuken",
    "gn:adm2_name":"Kanigunmitakechou",
    "gn:name":"Nakagiri",
    "iso:country":"JP",
    "wof:name":"505-0114",
    "wof:placetype":"postalcode"
},
  "geometry": {"coordinates":[137.16030000000001,35.4241],"type":"Point"}
}