{
  "type": "Feature",
  "properties": {
    "gn:adm1_name":"Ehimeken",
    "gn:adm2_name":"Niihamashi",
    "gn:name":"Nishibarachou",
    "iso:country":"JP",
    "wof:name":"792-0011",
    "wof:placetype":"postalcode"
},
  "geometry": {"coordinates":[133.26859999999999,33.9641],"type":"Point"}
}