{
  "type": "Feature",
  "properties": {
    "gn:adm1_name":"Gifuken",
    "gn:adm2_name":"Gifushi",
    "gn:name":"Akutamikaitoyama",
    "iso:country":"JP",
    "wof:name":"501-3136",
    "wof:placetype":"postalcode"
},
  "geometry": {"coordinates":[136.83779999999999,35.4536],"type":"Point"}
}