{
  "type": "Feature",
  "properties": {
    "gn:adm1_name":"Kumamotoken",
    "gn:adm2_name":"Yatsushirogunsakamotomura",
    "gn:name":"Ichinomata",
    "iso:country":"JP",
    "wof:name":"869-6114",
    "wof:placetype":"postalcode"
},
  "geometry": {"coordinates":[130.68469999999999,32.3652],"type":"Point"}
}