{
  "type": "Feature",
  "properties": {
    "gn:adm1_name":"Aichiken",
    "gn:adm2_name":"Higashikamogun'Asukechou",
    "gn:name":"Norisada",
    "iso:country":"JP",
    "wof:name":"444-2342",
    "wof:placetype":"postalcode"
},
  "geometry": {"coordinates":[137.2551,35.1021],"type":"Point"}
}