{
  "type": "Feature",
  "properties": {
    "gn:adm1_name":"Kouchiken",
    "gn:adm2_name":"Nagaokagun'Ootoyochou",
    "gn:name":"Ogawa",
    "iso:country":"JP",
    "wof:name":"789-0316",
    "wof:placetype":"postalcode"
},
  "geometry": {"coordinates":[133.6687,33.733],"type":"Point"}
}