{
  "type": "Feature",
  "properties": {
    "gn:adm1_name":"Okayamaken",
    "gn:adm2_name":"Okayamashi",
    "gn:name":"Takamatsuharakosai",
    "iso:country":"JP",
    "wof:name":"701-1334",
    "wof:placetype":"postalcode"
},
  "geometry": {"coordinates":[133.8228,34.6845],"type":"Point"}
}