{
  "type": "Feature",
  "properties": {
    "gn:adm1_name":"Okinawaken",
    "gn:adm2_name":"Nakagamigunnakagusukuson",
    "gn:name":"Yagi",
    "iso:country":"JP",
    "wof:name":"901-2405",
    "wof:placetype":"postalcode"
},
  "geometry": {"coordinates":[127.7942,26.2701],"type":"Point"}
}