{
  "type": "Feature",
  "properties": {
    "gn:adm1_name":"Gifuken",
    "gn:adm2_name":"Kanishi",
    "gn:name":"Dota",
    "iso:country":"JP",
    "wof:name":"509-0206",
    "wof:placetype":"postalcode"
},
  "geometry": {"coordinates":[137.0181,35.4257],"type":"Point"}
}