{
  "type": "Feature",
  "properties": {
    "gn:adm1_name":"Hiroshimaken",
    "gn:adm2_name":"Toyotagun'Oosakikamijimachou",
    "gn:name":"Akashi",
    "iso:country":"JP",
    "wof:name":"725-0403",
    "wof:placetype":"postalcode"
},
  "geometry": {"coordinates":[132.87540000000001,34.2092],"type":"Point"}
}