{
  "type": "Feature",
  "properties": {
    "gn:adm1_name":"Niigataken",
    "gn:adm2_name":"Minamikanbaragunsakaemachi",
    "gn:name":"Kitagata",
    "iso:country":"JP",
    "wof:name":"959-1108",
    "wof:placetype":"postalcode"
},
  "geometry": {"coordinates":[138.94220000000001,37.57],"type":"Point"}
}