{
  "type": "Feature",
  "properties": {
    "gn:adm1_name":"Miyazakiken",
    "gn:adm2_name":"Miyakonojoushi",
    "gn:name":"Miyamaruchou",
    "iso:country":"JP",
    "wof:name":"885-0078",
    "wof:placetype":"postalcode"
},
  "geometry": {"coordinates":[131.0575,31.7283],"type":"Point"}
}