{
  "type": "Feature",
  "properties": {
    "gn:adm1_name":"Chibaken",
    "gn:adm2_name":"Kamagayashi",
    "gn:name":"Higashimichinobe",
    "iso:country":"JP",
    "wof:name":"273-0115",
    "wof:placetype":"postalcode"
},
  "geometry": {"coordinates":[139.99969999999999,35.752],"type":"Point"}
}