{
  "type": "Feature",
  "properties": {
    "gn:adm1_name":"Ibarakiken",
    "gn:adm2_name":"Inashikigun'Amimachi",
    "gn:name":"Takaku",
    "iso:country":"JP",
    "wof:name":"300-0305",
    "wof:placetype":"postalcode"
},
  "geometry": {"coordinates":[140.2355,36.0313],"type":"Point"}
}