{
  "type": "Feature",
  "properties": {
    "gn:adm1_name":"Yamagataken",
    "gn:adm2_name":"Nishiokitamagun'Iidemachi",
    "gn:name":"Hirokawara",
    "iso:country":"JP",
    "wof:name":"999-0422",
    "wof:placetype":"postalcode"
},
  "geometry": {"coordinates":[139.8914,37.8843],"type":"Point"}
}