{
  "type": "Feature",
  "properties": {
    "gn:adm1_name":"Wakayamaken",
    "gn:adm2_name":"Hidakagunminabegawamura",
    "gn:name":"Higashikounogawa",
    "iso:country":"JP",
    "wof:name":"645-0202",
    "wof:placetype":"postalcode"
},
  "geometry": {"coordinates":[135.375,33.8527],"type":"Point"}
}