{
  "type": "Feature",
  "properties": {
    "gn:adm1_name":"Tottoriken",
    "gn:adm2_name":"Touhakugunsekiganechou",
    "gn:name":"Sekiganeshuku",
    "iso:country":"JP",
    "wof:name":"682-0411",
    "wof:placetype":"postalcode"
},
  "geometry": {"coordinates":[133.75919999999999,35.3638],"type":"Point"}
}