{
  "type": "Feature",
  "properties": {
    "gn:adm1_name":"Chibaken",
    "gn:adm2_name":"Mobarashi",
    "gn:name":"Sarubukuro",
    "iso:country":"JP",
    "wof:name":"297-0041",
    "wof:placetype":"postalcode"
},
  "geometry": {"coordinates":[140.31360000000001,35.3974],"type":"Point"}
}