{
  "type": "Feature",
  "properties": {
    "gn:adm1_name":"Fukushimaken",
    "gn:adm2_name":"Dategunkawamatamachi",
    "gn:name":"Kuragasaku",
    "iso:country":"JP",
    "wof:name":"960-1477",
    "wof:placetype":"postalcode"
},
  "geometry": {"coordinates":[140.6069,37.6721],"type":"Point"}
}