{
  "type": "Feature",
  "properties": {
    "gn:adm1_name":"Naganoken",
    "gn:adm2_name":"Kitaadumigun'Ikedamachi",
    "gn:name":"Nakau",
    "iso:country":"JP",
    "wof:name":"399-8603",
    "wof:placetype":"postalcode"
},
  "geometry": {"coordinates":[137.89169999999999,36.3731],"type":"Point"}
}