{
  "type": "Feature",
  "properties": {
    "gn:adm1_name":"Ooitaken",
    "gn:adm2_name":"Ooitashi",
    "gn:name":"Kokubudanchi",
    "iso:country":"JP",
    "wof:name":"870-0865",
    "wof:placetype":"postalcode"
},
  "geometry": {"coordinates":[131.55709999999999,33.1987],"type":"Point"}
}