{
  "type": "Feature",
  "properties": {
    "gn:adm1_name":"Fukushimaken",
    "gn:adm2_name":"Tamuragunmiharumachi",
    "gn:name":"Kitsuneda",
    "iso:country":"JP",
    "wof:name":"963-7717",
    "wof:placetype":"postalcode"
},
  "geometry": {"coordinates":[140.4854,37.3955],"type":"Point"}
}