{
  "type": "Feature",
  "properties": {
    "gn:adm1_name":"Shimaneken",
    "gn:adm2_name":"Goutsushi",
    "gn:name":"Arifukuonsenchouhonmyou",
    "iso:country":"JP",
    "wof:name":"695-0155",
    "wof:placetype":"postalcode"
},
  "geometry": {"coordinates":[132.21289999999999,34.9334],"type":"Point"}
}