{
  "type": "Feature",
  "properties": {
    "gn:adm1_name":"Ooitaken",
    "gn:adm2_name":"Nakatsushi",
    "gn:name":"Senbamachi",
    "iso:country":"JP",
    "wof:name":"871-0089",
    "wof:placetype":"postalcode"
},
  "geometry": {"coordinates":[131.19069999999999,33.6081],"type":"Point"}
}