{
  "type": "Feature",
  "properties": {
    "gn:adm1_name":"Hyougoken",
    "gn:adm2_name":"Koubeshikitaku",
    "gn:name":"Naruko",
    "iso:country":"JP",
    "wof:name":"651-1133",
    "wof:placetype":"postalcode"
},
  "geometry": {"coordinates":[135.12729999999999,34.7234],"type":"Point"}
}