{
  "type": "Feature",
  "properties": {
    "gn:adm1_name":"Fukuiken",
    "gn:adm2_name":"Fukuishi",
    "gn:name":"Mitsuyachou",
    "iso:country":"JP",
    "wof:name":"910-0039",
    "wof:placetype":"postalcode"
},
  "geometry": {"coordinates":[136.1909,36.0843],"type":"Point"}
}