{
  "type": "Feature",
  "properties": {
    "gn:adm1_name":"Chibaken",
    "gn:adm2_name":"Chibashiinageku",
    "gn:name":"Konakadaichou",
    "iso:country":"JP",
    "wof:name":"263-0044",
    "wof:placetype":"postalcode"
},
  "geometry": {"coordinates":[140.09309999999999,35.6484],"type":"Point"}
}