{
  "type": "Feature",
  "properties": {
    "gn:adm1_name":"Fukushimaken",
    "gn:adm2_name":"Shirakawashi",
    "gn:name":"Takayamanishi",
    "iso:country":"JP",
    "wof:name":"961-0855",
    "wof:placetype":"postalcode"
},
  "geometry": {"coordinates":[140.1865,37.117],"type":"Point"}
}