{
  "type": "Feature",
  "properties": {
    "gn:adm1_name":"Aichiken",
    "gn:adm2_name":"Okazakishi",
    "gn:name":"Miyaishichou",
    "iso:country":"JP",
    "wof:name":"444-2109",
    "wof:placetype":"postalcode"
},
  "geometry": {"coordinates":[137.20679999999999,35.035],"type":"Point"}
}