{
  "type": "Feature",
  "properties": {
    "gn:adm1_name":"Saitamaken",
    "gn:adm2_name":"Hidakashi",
    "gn:name":"Takaoka",
    "iso:country":"JP",
    "wof:name":"350-1247",
    "wof:placetype":"postalcode"
},
  "geometry": {"coordinates":[139.31659999999999,35.8928],"type":"Point"}
}