{
  "type": "Feature",
  "properties": {
    "gn:adm1_name":"Oosakafu",
    "gn:adm2_name":"Takatsukishi",
    "gn:name":"Ookanmurichou",
    "iso:country":"JP",
    "wof:name":"569-0031",
    "wof:placetype":"postalcode"
},
  "geometry": {"coordinates":[135.6361,34.8337],"type":"Point"}
}