{
  "type": "Feature",
  "properties": {
    "gn:adm1_name":"Kumamotoken",
    "gn:adm2_name":"Kumamotoshi",
    "gn:name":"Kajiomachi",
    "iso:country":"JP",
    "wof:name":"861-5512",
    "wof:placetype":"postalcode"
},
  "geometry": {"coordinates":[130.7243,32.8718],"type":"Point"}
}