{
  "type": "Feature",
  "properties": {
    "gn:adm1_name":"Yamaguchiken",
    "gn:adm2_name":"Kugagunmikawachou",
    "gn:name":"Kogawa",
    "iso:country":"JP",
    "wof:name":"740-0501",
    "wof:placetype":"postalcode"
},
  "geometry": {"coordinates":[132.00110000000001,34.2427],"type":"Point"}
}