{
  "type": "Feature",
  "properties": {
    "gn:adm1_name":"Shimaneken",
    "gn:adm2_name":"Hamadashi",
    "gn:name":"Nishikimachi",
    "iso:country":"JP",
    "wof:name":"697-0042",
    "wof:placetype":"postalcode"
},
  "geometry": {"coordinates":[132.07730000000001,34.8979],"type":"Point"}
}