{
  "type": "Feature",
  "properties": {
    "gn:adm1_name":"Hyougoken",
    "gn:adm2_name":"Himejishi",
    "gn:name":"Hanadachouchokushi",
    "iso:country":"JP",
    "wof:name":"671-0254",
    "wof:placetype":"postalcode"
},
  "geometry": {"coordinates":[134.72239999999999,34.8339],"type":"Point"}
}