{
  "type": "Feature",
  "properties": {
    "gn:adm1_name":"Fukushimaken",
    "gn:adm2_name":"Kitakatashi",
    "gn:name":"Muranishi",
    "iso:country":"JP",
    "wof:name":"966-0067",
    "wof:placetype":"postalcode"
},
  "geometry": {"coordinates":[139.87719999999999,37.6561],"type":"Point"}
}