{
  "type": "Feature",
  "properties": {
    "gn:adm1_name":"Tottoriken",
    "gn:adm2_name":"Saihakugun'Aimichou",
    "gn:name":"Ikeno",
    "iso:country":"JP",
    "wof:name":"683-0218",
    "wof:placetype":"postalcode"
},
  "geometry": {"coordinates":[133.41229999999999,35.3384],"type":"Point"}
}