{
  "type": "Feature",
  "properties": {
    "gn:adm1_name":"Kyoutofu",
    "gn:adm2_name":"Kyoutoshiminamiku",
    "gn:name":"Nishikujougokoudenchou",
    "iso:country":"JP",
    "wof:name":"601-8442",
    "wof:placetype":"postalcode"
},
  "geometry": {"coordinates":[135.7492,34.975],"type":"Point"}
}