{
  "type": "Feature",
  "properties": {
    "gn:adm1_name":"Hyougoken",
    "gn:adm2_name":"Sumotoshi",
    "gn:name":"Aigachouyamadahara",
    "iso:country":"JP",
    "wof:name":"656-2125",
    "wof:placetype":"postalcode"
},
  "geometry": {"coordinates":[134.86420000000001,34.4073],"type":"Point"}
}