{
  "type": "Feature",
  "properties": {
    "gn:adm1_name":"Gunmaken",
    "gn:adm2_name":"Ootashi",
    "gn:name":"Tenrachou",
    "iso:country":"JP",
    "wof:name":"373-0051",
    "wof:placetype":"postalcode"
},
  "geometry": {"coordinates":[139.33449999999999,36.3314],"type":"Point"}
}