{
  "type": "Feature",
  "properties": {
    "gn:adm1_name":"Hyougoken",
    "gn:adm2_name":"Sasayamashi",
    "gn:name":"Ajimakita",
    "iso:country":"JP",
    "wof:name":"669-2224",
    "wof:placetype":"postalcode"
},
  "geometry": {"coordinates":[135.1559,35.0671],"type":"Point"}
}