{
  "type": "Feature",
  "properties": {
    "gn:adm1_name":"Mieken",
    "gn:adm2_name":"Nagagun'Aoyamachou",
    "gn:name":"Ao",
    "iso:country":"JP",
    "wof:name":"518-0226",
    "wof:placetype":"postalcode"
},
  "geometry": {"coordinates":[136.17789999999999,34.6681],"type":"Point"}
}