{
  "type": "Feature",
  "properties": {
    "gn:adm1_name":"Yamagataken",
    "gn:adm2_name":"Higashineshi",
    "gn:name":"Chuuounishi",
    "iso:country":"JP",
    "wof:name":"999-3719",
    "wof:placetype":"postalcode"
},
  "geometry": {"coordinates":[140.3886,38.4384],"type":"Point"}
}