{
  "type": "Feature",
  "properties": {
    "gn:adm1_name":"Kagawaken",
    "gn:adm2_name":"Nakatadogunmannouchou",
    "gn:name":"Yoshinoshimo",
    "iso:country":"JP",
    "wof:name":"766-0022",
    "wof:placetype":"postalcode"
},
  "geometry": {"coordinates":[133.84399999999999,34.1911],"type":"Point"}
}