{
  "type": "Feature",
  "properties": {
    "gn:adm1_name":"Kanagawaken",
    "gn:adm2_name":"Sagamiharashi",
    "gn:name":"Hashimoto",
    "iso:country":"JP",
    "wof:name":"229-1103",
    "wof:placetype":"postalcode"
},
  "geometry": {"coordinates":[139.34270000000001,35.5975],"type":"Point"}
}