{
  "type": "Feature",
  "properties": {
    "gn:adm1_name":"Toyamaken",
    "gn:adm2_name":"Takaokashi",
    "gn:name":"Higashishimozeki",
    "iso:country":"JP",
    "wof:name":"933-0033",
    "wof:placetype":"postalcode"
},
  "geometry": {"coordinates":[137.01929999999999,36.7427],"type":"Point"}
}