{
  "type": "Feature",
  "properties": {
    "gn:adm1_name":"Miyagiken",
    "gn:adm2_name":"Shibatagunshibatamachi",
    "gn:name":"Yokkaichiba",
    "iso:country":"JP",
    "wof:name":"989-1743",
    "wof:placetype":"postalcode"
},
  "geometry": {"coordinates":[140.82050000000001,38.0874],"type":"Point"}
}