{
  "type": "Feature",
  "properties": {
    "gn:adm1_name":"Oosakafu",
    "gn:adm2_name":"Hirakatashi",
    "gn:name":"Kitayama",
    "iso:country":"JP",
    "wof:name":"573-0171",
    "wof:placetype":"postalcode"
},
  "geometry": {"coordinates":[135.70140000000001,34.8401],"type":"Point"}
}