{
  "type": "Feature",
  "properties": {
    "gn:adm1_name":"Shimaneken",
    "gn:adm2_name":"Kanoashiguntsuwanochou",
    "gn:name":"Sasayama",
    "iso:country":"JP",
    "wof:name":"699-5603",
    "wof:placetype":"postalcode"
},
  "geometry": {"coordinates":[131.7954,34.4562],"type":"Point"}
}