{
  "type": "Feature",
  "properties": {
    "gn:adm1_name":"Aichiken",
    "gn:adm2_name":"Inazawashi",
    "gn:name":"Koderachou",
    "iso:country":"JP",
    "wof:name":"492-8265",
    "wof:placetype":"postalcode"
},
  "geometry": {"coordinates":[136.7824,35.2411],"type":"Point"}
}