{
  "type": "Feature",
  "properties": {
    "gn:adm1_name":"Toyamaken",
    "gn:adm2_name":"Kaminiikawagun'Ooyamamachi",
    "gn:name":"Oharaya",
    "iso:country":"JP",
    "wof:name":"930-1328",
    "wof:placetype":"postalcode"
},
  "geometry": {"coordinates":[137.28389999999999,36.6145],"type":"Point"}
}