{
  "type": "Feature",
  "properties": {
    "gn:adm1_name":"Aichiken",
    "gn:adm2_name":"Anjoushi",
    "gn:name":"Sakuraichou",
    "iso:country":"JP",
    "wof:name":"444-1154",
    "wof:placetype":"postalcode"
},
  "geometry": {"coordinates":[137.08920000000001,34.9214],"type":"Point"}
}