{
  "type": "Feature",
  "properties": {
    "gn:adm1_name":"Kyoutofu",
    "gn:adm2_name":"Kyoutoshikamigyouku",
    "gn:name":"Hirohashidonochou",
    "iso:country":"JP",
    "wof:name":"602-0911",
    "wof:placetype":"postalcode"
},
  "geometry": {"coordinates":[135.75880000000001,35.0263],"type":"Point"}
}