{
  "type": "Feature",
  "properties": {
    "gn:adm1_name":"Chibaken",
    "gn:adm2_name":"Inbagunmotonomura",
    "gn:name":"Matsuki",
    "iso:country":"JP",
    "wof:name":"270-2307",
    "wof:placetype":"postalcode"
},
  "geometry": {"coordinates":[140.21430000000001,35.8298],"type":"Point"}
}