{
  "type": "Feature",
  "properties": {
    "gn:adm1_name":"Kyoutofu",
    "gn:adm2_name":"Kyoutoshikitaku",
    "gn:name":"Sugisakamiyakochou",
    "iso:country":"JP",
    "wof:name":"601-0112",
    "wof:placetype":"postalcode"
},
  "geometry": {"coordinates":[135.6979,35.097],"type":"Point"}
}