{
  "type": "Feature",
  "properties": {
    "gn:adm1_name":"Okinawaken",
    "gn:adm2_name":"Ishigakishi",
    "gn:name":"Misakichou",
    "iso:country":"JP",
    "wof:name":"907-0012",
    "wof:placetype":"postalcode"
},
  "geometry": {"coordinates":[124.1559,24.3393],"type":"Point"}
}