{
  "type": "Feature",
  "properties": {
    "gn:adm1_name":"Saitamaken",
    "gn:adm2_name":"Hanyuushi",
    "gn:name":"Myou",
    "iso:country":"JP",
    "wof:name":"348-0002",
    "wof:placetype":"postalcode"
},
  "geometry": {"coordinates":[139.59809999999999,36.1997],"type":"Point"}
}