{
  "type": "Feature",
  "properties": {
    "gn:adm1_name":"Mieken",
    "gn:adm2_name":"Shimagun'Isobechou",
    "gn:name":"Yamada",
    "iso:country":"JP",
    "wof:name":"517-0203",
    "wof:placetype":"postalcode"
},
  "geometry": {"coordinates":[136.82239999999999,34.3879],"type":"Point"}
}