{
  "type": "Feature",
  "properties": {
    "gn:adm1_name":"Yamagataken",
    "gn:adm2_name":"Kitamurayamagun'Ooishidamachi",
    "gn:name":"Midorichou",
    "iso:country":"JP",
    "wof:name":"999-4112",
    "wof:placetype":"postalcode"
},
  "geometry": {"coordinates":[140.37110000000001,38.5933],"type":"Point"}
}