{
  "type": "Feature",
  "properties": {
    "gn:adm1_name":"Kyoutofu",
    "gn:adm2_name":"Yawatashi",
    "gn:name":"Uchizatomiyanomae",
    "iso:country":"JP",
    "wof:name":"614-8241",
    "wof:placetype":"postalcode"
},
  "geometry": {"coordinates":[135.7296,34.8596],"type":"Point"}
}