{
  "type": "Feature",
  "properties": {
    "gn:adm1_name":"Naganoken",
    "gn:adm2_name":"Nakanoshi",
    "gn:name":"Kanai",
    "iso:country":"JP",
    "wof:name":"383-0008",
    "wof:placetype":"postalcode"
},
  "geometry": {"coordinates":[138.36660000000001,36.7716],"type":"Point"}
}