{
  "type": "Feature",
  "properties": {
    "gn:adm1_name":"Wakayamaken",
    "gn:adm2_name":"Wakayamashi",
    "gn:name":"Kitanoshinchiuratamachi",
    "iso:country":"JP",
    "wof:name":"640-8352",
    "wof:placetype":"postalcode"
},
  "geometry": {"coordinates":[135.184,34.2323],"type":"Point"}
}