{
  "type": "Feature",
  "properties": {
    "gn:adm1_name":"Aichiken",
    "gn:adm2_name":"Amagunjimokujichou",
    "gn:name":"Jimokuji",
    "iso:country":"JP",
    "wof:name":"490-1111",
    "wof:placetype":"postalcode"
},
  "geometry": {"coordinates":[136.82310000000001,35.1934],"type":"Point"}
}