{
  "type": "Feature",
  "properties": {
    "gn:adm1_name":"Naganoken",
    "gn:adm2_name":"Shimoinagunminamishinanomura",
    "gn:name":"Wada",
    "iso:country":"JP",
    "wof:name":"399-1311",
    "wof:placetype":"postalcode"
},
  "geometry": {"coordinates":[137.97110000000001,35.328],"type":"Point"}
}