{
  "type": "Feature",
  "properties": {
    "gn:adm1_name":"Sagaken",
    "gn:adm2_name":"Higashimatsuuragunhamatamachou",
    "gn:name":"Fuchinoue",
    "iso:country":"JP",
    "wof:name":"849-5104",
    "wof:placetype":"postalcode"
},
  "geometry": {"coordinates":[130.04509999999999,33.4575],"type":"Point"}
}