{
  "type": "Feature",
  "properties": {
    "gn:adm1_name":"Kyoutofu",
    "gn:adm2_name":"Kyoutoshiminamiku",
    "gn:name":"Kamitobasugatachou",
    "iso:country":"JP",
    "wof:name":"601-8102",
    "wof:placetype":"postalcode"
},
  "geometry": {"coordinates":[135.74719999999999,34.9722],"type":"Point"}
}