{
  "type": "Feature",
  "properties": {
    "gn:adm1_name":"Oosakafu",
    "gn:adm2_name":"Kawachinaganoshi",
    "gn:name":"Nosakuchou",
    "iso:country":"JP",
    "wof:name":"586-0023",
    "wof:placetype":"postalcode"
},
  "geometry": {"coordinates":[135.56120000000001,34.4519],"type":"Point"}
}