{
  "type": "Feature",
  "properties": {
    "gn:adm1_name":"Oosakafu",
    "gn:adm2_name":"Oosakashitaishouku",
    "gn:name":"Kitamura",
    "iso:country":"JP",
    "wof:name":"551-0032",
    "wof:placetype":"postalcode"
},
  "geometry": {"coordinates":[135.46789999999999,34.652],"type":"Point"}
}