{
  "type": "Feature",
  "properties": {
    "gn:adm1_name":"Aichiken",
    "gn:adm2_name":"Nagoyashinakagawaku",
    "gn:name":"Tomidachouhattori",
    "iso:country":"JP",
    "wof:name":"454-0973",
    "wof:placetype":"postalcode"
},
  "geometry": {"coordinates":[136.8134,35.1504],"type":"Point"}
}