{
  "type": "Feature",
  "properties": {
    "gn:adm1_name":"Shimaneken",
    "gn:adm2_name":"Izumoshi",
    "gn:name":"Makikitamachi",
    "iso:country":"JP",
    "wof:name":"693-0211",
    "wof:placetype":"postalcode"
},
  "geometry": {"coordinates":[132.76519999999999,35.3386],"type":"Point"}
}