{
  "type": "Feature",
  "properties": {
    "gn:adm1_name":"Yamaguchiken",
    "gn:adm2_name":"Shimonosekishi",
    "gn:name":"Saiwaimachi",
    "iso:country":"JP",
    "wof:name":"750-0001",
    "wof:placetype":"postalcode"
},
  "geometry": {"coordinates":[130.9434,33.9618],"type":"Point"}
}