{
  "type": "Feature",
  "properties": {
    "gn:adm1_name":"Kumamotoken",
    "gn:adm2_name":"Yatsushirogunsenchoumachi",
    "gn:name":"Oomuta",
    "iso:country":"JP",
    "wof:name":"869-4701",
    "wof:placetype":"postalcode"
},
  "geometry": {"coordinates":[130.6482,32.5451],"type":"Point"}
}