{
  "type": "Feature",
  "properties": {
    "gn:adm1_name":"Fukushimaken",
    "gn:adm2_name":"Iwakishi",
    "gn:name":"Onahamaminamikimigatsukachou",
    "iso:country":"JP",
    "wof:name":"971-8169",
    "wof:placetype":"postalcode"
},
  "geometry": {"coordinates":[140.8998,36.9566],"type":"Point"}
}