{
  "type": "Feature",
  "properties": {
    "gn:adm1_name":"Aichiken",
    "gn:adm2_name":"Nishikamogunfujiokachou",
    "gn:name":"Iino",
    "iso:country":"JP",
    "wof:name":"470-0451",
    "wof:placetype":"postalcode"
},
  "geometry": {"coordinates":[137.20820000000001,35.196],"type":"Point"}
}