{
  "type": "Feature",
  "properties": {
    "gn:adm1_name":"Shigaken",
    "gn:adm2_name":"Oumihachimanshi",
    "gn:name":"Midorimachi",
    "iso:country":"JP",
    "wof:name":"523-0048",
    "wof:placetype":"postalcode"
},
  "geometry": {"coordinates":[136.07400000000001,35.1076],"type":"Point"}
}