{
  "type": "Feature",
  "properties": {
    "gn:adm1_name":"Hiroshimaken",
    "gn:adm2_name":"Hiroshimashiasakitaku",
    "gn:name":"Miirihigashi",
    "iso:country":"JP",
    "wof:name":"731-0212",
    "wof:placetype":"postalcode"
},
  "geometry": {"coordinates":[132.5455,34.5359],"type":"Point"}
}