{
  "type": "Feature",
  "properties": {
    "gn:adm1_name":"Niigataken",
    "gn:adm2_name":"Shironeshi",
    "gn:name":"Oodooriminami",
    "iso:country":"JP",
    "wof:name":"950-1202",
    "wof:placetype":"postalcode"
},
  "geometry": {"coordinates":[139.02180000000001,37.8297],"type":"Point"}
}