{
  "type": "Feature",
  "properties": {
    "gn:adm1_name":"Yamagataken",
    "gn:adm2_name":"Murayamashi",
    "gn:name":"Tateokaitsukamachi",
    "iso:country":"JP",
    "wof:name":"995-0034",
    "wof:placetype":"postalcode"
},
  "geometry": {"coordinates":[140.38829999999999,38.479],"type":"Point"}
}