{
  "type": "Feature",
  "properties": {
    "gn:adm1_name":"Kyoutofu",
    "gn:adm2_name":"Kyoutoshifushimiku",
    "gn:name":"Nousoyakushidou",
    "iso:country":"JP",
    "wof:name":"612-8276",
    "wof:placetype":"postalcode"
},
  "geometry": {"coordinates":[135.72239999999999,34.9093],"type":"Point"}
}