{
  "type": "Feature",
  "properties": {
    "gn:adm1_name":"Niigataken",
    "gn:adm2_name":"Niigatashi",
    "gn:name":"Uchinonishi",
    "iso:country":"JP",
    "wof:name":"950-2151",
    "wof:placetype":"postalcode"
},
  "geometry": {"coordinates":[138.9308,37.8528],"type":"Point"}
}