{
  "type": "Feature",
  "properties": {
    "gn:adm1_name":"Tochigiken",
    "gn:adm2_name":"Tochigishi",
    "gn:name":"Fujimichou",
    "iso:country":"JP",
    "wof:name":"328-0044",
    "wof:placetype":"postalcode"
},
  "geometry": {"coordinates":[139.7278,36.3765],"type":"Point"}
}