{
  "type": "Feature",
  "properties": {
    "gn:adm1_name":"Naganoken",
    "gn:adm2_name":"Naganoshi",
    "gn:name":"Wakatsukinishijou",
    "iso:country":"JP",
    "wof:name":"381-0089",
    "wof:placetype":"postalcode"
},
  "geometry": {"coordinates":[138.24809999999999,36.716],"type":"Point"}
}