{
  "type": "Feature",
  "properties": {
    "gn:adm1_name":"Yamaguchiken",
    "gn:adm2_name":"Onodashi",
    "gn:name":"Hinode",
    "iso:country":"JP",
    "wof:name":"756-0091",
    "wof:placetype":"postalcode"
},
  "geometry": {"coordinates":[131.18350000000001,34.0056],"type":"Point"}
}