{
  "type": "Feature",
  "properties": {
    "gn:adm1_name":"Kanagawaken",
    "gn:adm2_name":"Ashigarakamigunkaiseimachi",
    "gn:name":"Yoshidajima",
    "iso:country":"JP",
    "wof:name":"258-0021",
    "wof:placetype":"postalcode"
},
  "geometry": {"coordinates":[139.13040000000001,35.3341],"type":"Point"}
}