{
  "type": "Feature",
  "properties": {
    "gn:adm1_name":"Kouchiken",
    "gn:adm2_name":"Sukumoshi",
    "gn:name":"Hashikamichougenjuyabu",
    "iso:country":"JP",
    "wof:name":"788-0049",
    "wof:placetype":"postalcode"
},
  "geometry": {"coordinates":[132.70939999999999,33.0151],"type":"Point"}
}