{
  "type": "Feature",
  "properties": {
    "gn:adm1_name":"Ishikawaken",
    "gn:adm2_name":"Kanazawashi",
    "gn:name":"Nakatomachi",
    "iso:country":"JP",
    "wof:name":"920-1336",
    "wof:placetype":"postalcode"
},
  "geometry": {"coordinates":[136.6917,36.5073],"type":"Point"}
}