{
  "type": "Feature",
  "properties": {
    "gn:adm1_name":"Yamaguchiken",
    "gn:adm2_name":"Ooshimagun'Ooshimachou",
    "gn:name":"Higashiyashiro",
    "iso:country":"JP",
    "wof:name":"742-2107",
    "wof:placetype":"postalcode"
},
  "geometry": {"coordinates":[132.21549999999999,33.9102],"type":"Point"}
}