{
  "type": "Feature",
  "properties": {
    "gn:adm1_name":"Hyougoken",
    "gn:adm2_name":"Nishinomiyashi",
    "gn:name":"Kagurachou",
    "iso:country":"JP",
    "wof:name":"662-0977",
    "wof:placetype":"postalcode"
},
  "geometry": {"coordinates":[135.33099999999999,34.738],"type":"Point"}
}