{
  "type": "Feature",
  "properties": {
    "gn:adm1_name":"Niigataken",
    "gn:adm2_name":"Nagaokashi",
    "gn:name":"Takamachi",
    "iso:country":"JP",
    "wof:name":"940-0824",
    "wof:placetype":"postalcode"
},
  "geometry": {"coordinates":[138.86510000000001,37.4165],"type":"Point"}
}