{
  "type": "Feature",
  "properties": {
    "gn:adm1_name":"Naraken",
    "gn:adm2_name":"Yamatokooriyamashi",
    "gn:name":"Yatachou",
    "iso:country":"JP",
    "wof:name":"639-1058",
    "wof:placetype":"postalcode"
},
  "geometry": {"coordinates":[135.74539999999999,34.6476],"type":"Point"}
}