{
  "type": "Feature",
  "properties": {
    "gn:adm1_name":"Nagasakiken",
    "gn:adm2_name":"Minamimatsuuraguntamanourachou",
    "gn:name":"Tannagou",
    "iso:country":"JP",
    "wof:name":"853-0504",
    "wof:placetype":"postalcode"
},
  "geometry": {"coordinates":[128.65819999999999,32.6776],"type":"Point"}
}