{
  "type": "Feature",
  "properties": {
    "gn:adm1_name":"Okayamaken",
    "gn:adm2_name":"Kawakamigunkawakamichou",
    "gn:name":"Nika",
    "iso:country":"JP",
    "wof:name":"716-0207",
    "wof:placetype":"postalcode"
},
  "geometry": {"coordinates":[133.46260000000001,34.7064],"type":"Point"}
}