{
  "type": "Feature",
  "properties": {
    "gn:adm1_name":"Fukuokaken",
    "gn:adm2_name":"Kitakyuushuushikokuraminamiku",
    "gn:name":"Tahara",
    "iso:country":"JP",
    "wof:name":"800-0225",
    "wof:placetype":"postalcode"
},
  "geometry": {"coordinates":[130.93279999999999,33.8262],"type":"Point"}
}