{
  "type": "Feature",
  "properties": {
    "gn:adm1_name":"Gunmaken",
    "gn:adm2_name":"Toneguntonemura",
    "gn:name":"Wakumi",
    "iso:country":"JP",
    "wof:name":"378-0325",
    "wof:placetype":"postalcode"
},
  "geometry": {"coordinates":[139.15539999999999,36.6418],"type":"Point"}
}