{
  "type": "Feature",
  "properties": {
    "gn:adm1_name":"Shigaken",
    "gn:adm2_name":"Ootsushi",
    "gn:name":"Ishizue",
    "iso:country":"JP",
    "wof:name":"520-2272",
    "wof:placetype":"postalcode"
},
  "geometry": {"coordinates":[135.92930000000001,34.9484],"type":"Point"}
}