{
  "type": "Feature",
  "properties": {
    "gn:adm1_name":"Tottoriken",
    "gn:adm2_name":"Saihakugunkishimotochou",
    "gn:name":"Sakachou",
    "iso:country":"JP",
    "wof:name":"689-4122",
    "wof:placetype":"postalcode"
},
  "geometry": {"coordinates":[133.392,35.3817],"type":"Point"}
}