{
  "type": "Feature",
  "properties": {
    "gn:adm1_name":"Yamaguchiken",
    "gn:adm2_name":"Houfushi",
    "gn:name":"Tatara",
    "iso:country":"JP",
    "wof:name":"747-0023",
    "wof:placetype":"postalcode"
},
  "geometry": {"coordinates":[131.58709999999999,34.0602],"type":"Point"}
}