{
  "type": "Feature",
  "properties": {
    "gn:adm1_name":"Chibaken",
    "gn:adm2_name":"Katoriguntounoshoumachi",
    "gn:name":"Kogaino",
    "iso:country":"JP",
    "wof:name":"289-0637",
    "wof:placetype":"postalcode"
},
  "geometry": {"coordinates":[140.64410000000001,35.809],"type":"Point"}
}