{
  "type": "Feature",
  "properties": {
    "gn:adm1_name":"Kyoutofu",
    "gn:adm2_name":"Kyoutoshinakagyouku",
    "gn:name":"Kashiwayachou",
    "iso:country":"JP",
    "wof:name":"604-8014",
    "wof:placetype":"postalcode"
},
  "geometry": {"coordinates":[135.77099999999999,35.0042],"type":"Point"}
}