{
  "type": "Feature",
  "properties": {
    "gn:adm1_name":"Shigaken",
    "gn:adm2_name":"Ikaguntakatsukichou",
    "gn:name":"Yanaginonaka",
    "iso:country":"JP",
    "wof:name":"529-0264",
    "wof:placetype":"postalcode"
},
  "geometry": {"coordinates":[136.21180000000001,35.4685],"type":"Point"}
}