{
  "type": "Feature",
  "properties": {
    "gn:adm1_name":"Hyougoken",
    "gn:adm2_name":"Koubeshitarumiku",
    "gn:name":"Asahigaoka",
    "iso:country":"JP",
    "wof:name":"655-0033",
    "wof:placetype":"postalcode"
},
  "geometry": {"coordinates":[135.0521,34.6356],"type":"Point"}
}