{
  "type": "Feature",
  "properties": {
    "gn:adm1_name":"Hyougoken",
    "gn:adm2_name":"Himejishi",
    "gn:name":"Hiromineyama",
    "iso:country":"JP",
    "wof:name":"670-0891",
    "wof:placetype":"postalcode"
},
  "geometry": {"coordinates":[134.70169999999999,34.8728],"type":"Point"}
}