{
  "type": "Feature",
  "properties": {
    "gn:adm1_name":"Kagoshimaken",
    "gn:adm2_name":"Kanoyashi",
    "gn:name":"Hagitsukachou",
    "iso:country":"JP",
    "wof:name":"893-0036",
    "wof:placetype":"postalcode"
},
  "geometry": {"coordinates":[130.87020000000001,31.3363],"type":"Point"}
}