{
  "type": "Feature",
  "properties": {
    "gn:adm1_name":"Miyazakiken",
    "gn:adm2_name":"Hyuugashi",
    "gn:name":"Haruharachou",
    "iso:country":"JP",
    "wof:name":"883-0035",
    "wof:placetype":"postalcode"
},
  "geometry": {"coordinates":[131.6216,32.4238],"type":"Point"}
}