{
  "type": "Feature",
  "properties": {
    "gn:adm1_name":"Saitamaken",
    "gn:adm2_name":"Hannoushi",
    "gn:name":"Koiwai",
    "iso:country":"JP",
    "wof:name":"357-0066",
    "wof:placetype":"postalcode"
},
  "geometry": {"coordinates":[139.27379999999999,35.8638],"type":"Point"}
}