{
  "type": "Feature",
  "properties": {
    "gn:adm1_name":"Yamaguchiken",
    "gn:adm2_name":"Yoshikigun'Aiochou",
    "gn:name":"Higashi",
    "iso:country":"JP",
    "wof:name":"754-1101",
    "wof:placetype":"postalcode"
},
  "geometry": {"coordinates":[131.4468,34.0163],"type":"Point"}
}