{
  "type": "Feature",
  "properties": {
    "gn:adm1_name":"Kanagawaken",
    "gn:adm2_name":"Yokohamashiaobaku",
    "gn:name":"Matsukazedai",
    "iso:country":"JP",
    "wof:name":"227-0067",
    "wof:placetype":"postalcode"
},
  "geometry": {"coordinates":[139.50700000000001,35.5455],"type":"Point"}
}