{
  "type": "Feature",
  "properties": {
    "gn:adm1_name":"Niigataken",
    "gn:adm2_name":"Jouetsushi",
    "gn:name":"Tonome",
    "iso:country":"JP",
    "wof:name":"943-0178",
    "wof:placetype":"postalcode"
},
  "geometry": {"coordinates":[138.27889999999999,37.1228],"type":"Point"}
}