{
  "type": "Feature",
  "properties": {
    "gn:adm1_name":"Niigataken",
    "gn:adm2_name":"Santougunmishimamachi",
    "gn:name":"Nanokaichi",
    "iso:country":"JP",
    "wof:name":"940-2315",
    "wof:placetype":"postalcode"
},
  "geometry": {"coordinates":[138.7748,37.4826],"type":"Point"}
}