{
  "type": "Feature",
  "properties": {
    "gn:adm1_name":"Tokushimaken",
    "gn:adm2_name":"Awagun'Ichibachou",
    "gn:name":"Itsuki",
    "iso:country":"JP",
    "wof:name":"771-1626",
    "wof:placetype":"postalcode"
},
  "geometry": {"coordinates":[134.316,34.0998],"type":"Point"}
}