{
  "type": "Feature",
  "properties": {
    "gn:adm1_name":"Wakayamaken",
    "gn:adm2_name":"Higashimurogunhonguuchou",
    "gn:name":"Kogomori",
    "iso:country":"JP",
    "wof:name":"647-1722",
    "wof:placetype":"postalcode"
},
  "geometry": {"coordinates":[135.7372,33.8096],"type":"Point"}
}