{
  "type": "Feature",
  "properties": {
    "gn:adm1_name":"Ishikawaken",
    "gn:adm2_name":"Ishikawagunnonoichimachi",
    "gn:name":"Taheiji",
    "iso:country":"JP",
    "wof:name":"921-8845",
    "wof:placetype":"postalcode"
},
  "geometry": {"coordinates":[136.6052,36.5288],"type":"Point"}
}