{
  "type": "Feature",
  "properties": {
    "gn:adm1_name":"Aichiken",
    "gn:adm2_name":"Higashikamogun'Asukechou",
    "gn:name":"Shimokuniya",
    "iso:country":"JP",
    "wof:name":"444-2321",
    "wof:placetype":"postalcode"
},
  "geometry": {"coordinates":[137.2766,35.1037],"type":"Point"}
}