{
  "type": "Feature",
  "properties": {
    "gn:adm1_name":"Kumamotoken",
    "gn:adm2_name":"Araoshi",
    "gn:name":"Kamiide",
    "iso:country":"JP",
    "wof:name":"864-0013",
    "wof:placetype":"postalcode"
},
  "geometry": {"coordinates":[130.4871,32.9974],"type":"Point"}
}