{
  "type": "Feature",
  "properties": {
    "gn:adm1_name":"Tochigiken",
    "gn:adm2_name":"Nikkoushi",
    "gn:name":"Kiyotaki",
    "iso:country":"JP",
    "wof:name":"321-1444",
    "wof:placetype":"postalcode"
},
  "geometry": {"coordinates":[139.5581,36.7367],"type":"Point"}
}