{
  "type": "Feature",
  "properties": {
    "gn:adm1_name":"Toyamaken",
    "gn:adm2_name":"Namerikawashi",
    "gn:name":"Nojiri",
    "iso:country":"JP",
    "wof:name":"936-0831",
    "wof:placetype":"postalcode"
},
  "geometry": {"coordinates":[137.3929,36.7531],"type":"Point"}
}