{
  "type": "Feature",
  "properties": {
    "gn:adm1_name":"Saitamaken",
    "gn:adm2_name":"Kawaguchishi",
    "gn:name":"Shibashinmachi",
    "iso:country":"JP",
    "wof:name":"333-0851",
    "wof:placetype":"postalcode"
},
  "geometry": {"coordinates":[139.69380000000001,35.8293],"type":"Point"}
}