{
  "type": "Feature",
  "properties": {
    "gn:adm1_name":"Hiroshimaken",
    "gn:adm2_name":"Akigunkumanochou",
    "gn:name":"Kakisako",
    "iso:country":"JP",
    "wof:name":"731-4228",
    "wof:placetype":"postalcode"
},
  "geometry": {"coordinates":[132.56569999999999,34.3303],"type":"Point"}
}