{
  "type": "Feature",
  "properties": {
    "gn:adm1_name":"Naganoken",
    "gn:adm2_name":"Sakushi",
    "gn:name":"Tokida",
    "iso:country":"JP",
    "wof:name":"385-0026",
    "wof:placetype":"postalcode"
},
  "geometry": {"coordinates":[138.44460000000001,36.2783],"type":"Point"}
}