{
  "type": "Feature",
  "properties": {
    "gn:adm1_name":"Kanagawaken",
    "gn:adm2_name":"Hadanoshi",
    "gn:name":"Ochiai",
    "iso:country":"JP",
    "wof:name":"257-0025",
    "wof:placetype":"postalcode"
},
  "geometry": {"coordinates":[139.23339999999999,35.3826],"type":"Point"}
}