{
  "type": "Feature",
  "properties": {
    "gn:adm1_name":"Yamagataken",
    "gn:adm2_name":"Sakatashi",
    "gn:name":"Koganemachi",
    "iso:country":"JP",
    "wof:name":"998-0852",
    "wof:placetype":"postalcode"
},
  "geometry": {"coordinates":[139.85810000000001,38.901],"type":"Point"}
}