{
  "type": "Feature",
  "properties": {
    "gn:adm1_name":"Niigataken",
    "gn:adm2_name":"Minamikanbaragunshitadamura",
    "gn:name":"Taya",
    "iso:country":"JP",
    "wof:name":"955-0117",
    "wof:placetype":"postalcode"
},
  "geometry": {"coordinates":[139.0778,37.554],"type":"Point"}
}