{
  "type": "Feature",
  "properties": {
    "gn:adm1_name":"Fukushimaken",
    "gn:adm2_name":"Kitakatashi",
    "gn:name":"Higashikawarada",
    "iso:country":"JP",
    "wof:name":"966-0823",
    "wof:placetype":"postalcode"
},
  "geometry": {"coordinates":[139.876,37.6467],"type":"Point"}
}