{
  "type": "Feature",
  "properties": {
    "gn:adm1_name":"Aichiken",
    "gn:adm2_name":"Oobushi",
    "gn:name":"Komedachou",
    "iso:country":"JP",
    "wof:name":"474-0043",
    "wof:placetype":"postalcode"
},
  "geometry": {"coordinates":[136.92699999999999,34.9879],"type":"Point"}
}