{
  "type": "Feature",
  "properties": {
    "gn:adm1_name":"Toyamaken",
    "gn:adm2_name":"Nishitonamigunfukumitsumachi",
    "gn:name":"Habushin",
    "iso:country":"JP",
    "wof:name":"939-1756",
    "wof:placetype":"postalcode"
},
  "geometry": {"coordinates":[136.86600000000001,36.5264],"type":"Point"}
}