{
  "type": "Feature",
  "properties": {
    "gn:adm1_name":"Niigataken",
    "gn:adm2_name":"Kitauonumagunyunotanimura",
    "gn:name":"Ooyu",
    "iso:country":"JP",
    "wof:name":"946-0088",
    "wof:placetype":"postalcode"
},
  "geometry": {"coordinates":[139.08019999999999,37.1933],"type":"Point"}
}