{
  "type": "Feature",
  "properties": {
    "gn:adm1_name":"Fukuokaken",
    "gn:adm2_name":"Miigunkitanomachi",
    "gn:name":"Akashi",
    "iso:country":"JP",
    "wof:name":"830-1127",
    "wof:placetype":"postalcode"
},
  "geometry": {"coordinates":[130.6063,33.3584],"type":"Point"}
}