{
  "type": "Feature",
  "properties": {
    "gn:adm1_name":"Nagasakiken",
    "gn:adm2_name":"Kamiagatagunkamiagatachou",
    "gn:name":"Sago",
    "iso:country":"JP",
    "wof:name":"817-1603",
    "wof:placetype":"postalcode"
},
  "geometry": {"coordinates":[129.3484,34.6201],"type":"Point"}
}