{
  "type": "Feature",
  "properties": {
    "gn:adm1_name":"Ooitaken",
    "gn:adm2_name":"Saikishi",
    "gn:name":"Ekimae",
    "iso:country":"JP",
    "wof:name":"876-0803",
    "wof:placetype":"postalcode"
},
  "geometry": {"coordinates":[131.90350000000001,32.9718],"type":"Point"}
}