{
  "type": "Feature",
  "properties": {
    "gn:adm1_name":"Aichiken",
    "gn:adm2_name":"Setoshi",
    "gn:name":"Hatanakachou",
    "iso:country":"JP",
    "wof:name":"489-0946",
    "wof:placetype":"postalcode"
},
  "geometry": {"coordinates":[137.07749999999999,35.1972],"type":"Point"}
}