{
  "type": "Feature",
  "properties": {
    "gn:adm1_name":"Saitamaken",
    "gn:adm2_name":"Hikigun'Ogawamachi",
    "gn:name":"Iida",
    "iso:country":"JP",
    "wof:name":"355-0333",
    "wof:placetype":"postalcode"
},
  "geometry": {"coordinates":[139.24549999999999,36.0614],"type":"Point"}
}