{
  "type": "Feature",
  "properties": {
    "gn:adm1_name":"Yamagataken",
    "gn:adm2_name":"Nishiokitamagun'Ogunimachi",
    "gn:name":"Ogunikosakamachi",
    "iso:country":"JP",
    "wof:name":"999-1363",
    "wof:placetype":"postalcode"
},
  "geometry": {"coordinates":[139.74299999999999,38.0615],"type":"Point"}
}