{
  "type": "Feature",
  "properties": {
    "gn:adm1_name":"Naganoken",
    "gn:adm2_name":"Okayashi",
    "gn:name":"Kohan",
    "iso:country":"JP",
    "wof:name":"394-0034",
    "wof:placetype":"postalcode"
},
  "geometry": {"coordinates":[138.0565,36.0571],"type":"Point"}
}