{
  "type": "Feature",
  "properties": {
    "gn:adm1_name":"Toukyouto",
    "gn:adm2_name":"Nerimaku",
    "gn:name":"Nakamura",
    "iso:country":"JP",
    "wof:name":"176-0024",
    "wof:placetype":"postalcode"
},
  "geometry": {"coordinates":[139.64259999999999,35.7326],"type":"Point"}
}