{
  "type": "Feature",
  "properties": {
    "gn:adm1_name":"Hyougoken",
    "gn:adm2_name":"Toyookashi",
    "gn:name":"Mori",
    "iso:country":"JP",
    "wof:name":"668-0806",
    "wof:placetype":"postalcode"
},
  "geometry": {"coordinates":[134.82310000000001,35.5591],"type":"Point"}
}