{
  "type": "Feature",
  "properties": {
    "gn:adm1_name":"Shigaken",
    "gn:adm2_name":"Echigunkotouchou",
    "gn:name":"Kitabodaiji",
    "iso:country":"JP",
    "wof:name":"527-0138",
    "wof:placetype":"postalcode"
},
  "geometry": {"coordinates":[136.23560000000001,35.1443],"type":"Point"}
}