{
  "type": "Feature",
  "properties": {
    "gn:adm1_name":"Aichiken",
    "gn:adm2_name":"Nagoyashimeitouku",
    "gn:name":"Itakachoukamiyashiro",
    "iso:country":"JP",
    "wof:name":"465-0052",
    "wof:placetype":"postalcode"
},
  "geometry": {"coordinates":[137.00909999999999,35.1729],"type":"Point"}
}