{
  "type": "Feature",
  "properties": {
    "gn:adm1_name":"Aichiken",
    "gn:adm2_name":"Nagoyashimidoriku",
    "gn:name":"Rokuden",
    "iso:country":"JP",
    "wof:name":"458-0036",
    "wof:placetype":"postalcode"
},
  "geometry": {"coordinates":[136.96029999999999,35.0786],"type":"Point"}
}