{
  "type": "Feature",
  "properties": {
    "gn:adm1_name":"Chibaken",
    "gn:adm2_name":"Funabashishi",
    "gn:name":"Katsushikachou",
    "iso:country":"JP",
    "wof:name":"273-0032",
    "wof:placetype":"postalcode"
},
  "geometry": {"coordinates":[139.9564,35.7068],"type":"Point"}
}