{
  "type": "Feature",
  "properties": {
    "gn:adm1_name":"Miyazakiken",
    "gn:adm2_name":"Nishimorokatagunsukison",
    "gn:name":"Nasaki",
    "iso:country":"JP",
    "wof:name":"886-0114",
    "wof:placetype":"postalcode"
},
  "geometry": {"coordinates":[131.06129999999999,32.041],"type":"Point"}
}