{
  "type": "Feature",
  "properties": {
    "gn:adm1_name":"Saitamaken",
    "gn:adm2_name":"Kawaguchishi",
    "gn:name":"Chouzou",
    "iso:country":"JP",
    "wof:name":"333-0807",
    "wof:placetype":"postalcode"
},
  "geometry": {"coordinates":[139.75899999999999,35.8602],"type":"Point"}
}