{
  "type": "Feature",
  "properties": {
    "gn:adm1_name":"Aichiken",
    "gn:adm2_name":"Bisaishi",
    "gn:name":"Kaimei",
    "iso:country":"JP",
    "wof:name":"494-0001",
    "wof:placetype":"postalcode"
},
  "geometry": {"coordinates":[136.7662,35.3183],"type":"Point"}
}