{
  "type": "Feature",
  "properties": {
    "gn:adm1_name":"Niigataken",
    "gn:adm2_name":"Minamiuonumagunyuzawamachi",
    "gn:name":"Mitsumata",
    "iso:country":"JP",
    "wof:name":"949-6211",
    "wof:placetype":"postalcode"
},
  "geometry": {"coordinates":[138.77680000000001,36.8976],"type":"Point"}
}