{
  "type": "Feature",
  "properties": {
    "gn:adm1_name":"Gifuken",
    "gn:adm2_name":"Enashi",
    "gn:name":"Kasagichoukawai",
    "iso:country":"JP",
    "wof:name":"509-7207",
    "wof:placetype":"postalcode"
},
  "geometry": {"coordinates":[137.32650000000001,35.4823],"type":"Point"}
}