{
  "type": "Feature",
  "properties": {
    "gn:adm1_name":"Wakayamaken",
    "gn:adm2_name":"Wakayamashi",
    "gn:name":"Hironishi",
    "iso:country":"JP",
    "wof:name":"649-6339",
    "wof:placetype":"postalcode"
},
  "geometry": {"coordinates":[135.239,34.2669],"type":"Point"}
}