{
  "type": "Feature",
  "properties": {
    "gn:adm1_name":"Nagasakiken",
    "gn:adm2_name":"Kitamatsuuragun'Emukaechou",
    "gn:name":"Ebiraomen",
    "iso:country":"JP",
    "wof:name":"859-6114",
    "wof:placetype":"postalcode"
},
  "geometry": {"coordinates":[129.66,33.3158],"type":"Point"}
}