{
  "type": "Feature",
  "properties": {
    "gn:adm1_name":"Niigataken",
    "gn:adm2_name":"Kariwaguntakayanagimachi",
    "gn:name":"Tochigahara",
    "iso:country":"JP",
    "wof:name":"945-1504",
    "wof:placetype":"postalcode"
},
  "geometry": {"coordinates":[138.6456,37.1966],"type":"Point"}
}