{
  "type": "Feature",
  "properties": {
    "gn:adm1_name":"Miyagiken",
    "gn:adm2_name":"Kuriharagunkannarichou",
    "gn:name":"Kamimachihigashiura",
    "iso:country":"JP",
    "wof:name":"989-5153",
    "wof:placetype":"postalcode"
},
  "geometry": {"coordinates":[141.07480000000001,38.8078],"type":"Point"}
}