{
  "type": "Feature",
  "properties": {
    "gn:adm1_name":"Shizuokaken",
    "gn:adm2_name":"Itoushi",
    "gn:name":"Nagisachou",
    "iso:country":"JP",
    "wof:name":"414-0023",
    "wof:placetype":"postalcode"
},
  "geometry": {"coordinates":[139.09999999999999,34.9707],"type":"Point"}
}