{
  "type": "Feature",
  "properties": {
    "gn:adm1_name":"Kanagawaken",
    "gn:adm2_name":"Ebinashi",
    "gn:name":"Kawaraguchi",
    "iso:country":"JP",
    "wof:name":"243-0433",
    "wof:placetype":"postalcode"
},
  "geometry": {"coordinates":[139.37739999999999,35.4479],"type":"Point"}
}