{
  "type": "Feature",
  "properties": {
    "gn:adm1_name":"Kumamotoken",
    "gn:adm2_name":"Kamotogunkamotomachi",
    "gn:name":"Bunda",
    "iso:country":"JP",
    "wof:name":"861-0321",
    "wof:placetype":"postalcode"
},
  "geometry": {"coordinates":[130.72640000000001,32.982],"type":"Point"}
}