{
  "type": "Feature",
  "properties": {
    "gn:adm1_name":"Ishikawaken",
    "gn:adm2_name":"Nanaoshi",
    "gn:name":"Tokiwamachi",
    "iso:country":"JP",
    "wof:name":"926-0862",
    "wof:placetype":"postalcode"
},
  "geometry": {"coordinates":[136.9631,37.049],"type":"Point"}
}