{
  "type": "Feature",
  "properties": {
    "gn:adm1_name":"Ooitaken",
    "gn:adm2_name":"Saikishi",
    "gn:name":"Uchimachi",
    "iso:country":"JP",
    "wof:name":"876-0845",
    "wof:placetype":"postalcode"
},
  "geometry": {"coordinates":[131.8955,32.9573],"type":"Point"}
}