{
  "type": "Feature",
  "properties": {
    "gn:adm1_name":"Shigaken",
    "gn:adm2_name":"Ikagunnishiazaichou",
    "gn:name":"Shiotsuhama",
    "iso:country":"JP",
    "wof:name":"529-0701",
    "wof:placetype":"postalcode"
},
  "geometry": {"coordinates":[136.16589999999999,35.5178],"type":"Point"}
}