{
  "type": "Feature",
  "properties": {
    "gn:adm1_name":"Okinawaken",
    "gn:adm2_name":"Tomigusukushi",
    "gn:name":"Onaga",
    "iso:country":"JP",
    "wof:name":"901-0223",
    "wof:placetype":"postalcode"
},
  "geometry": {"coordinates":[127.6737,26.1585],"type":"Point"}
}