{
  "type": "Feature",
  "properties": {
    "gn:adm1_name":"Kyoutofu",
    "gn:adm2_name":"Yawatashi",
    "gn:name":"Yawatatourin",
    "iso:country":"JP",
    "wof:name":"614-8079",
    "wof:placetype":"postalcode"
},
  "geometry": {"coordinates":[135.70310000000001,34.8682],"type":"Point"}
}