{
  "type": "Feature",
  "properties": {
    "gn:adm1_name":"Okayamaken",
    "gn:adm2_name":"Tomatagunkagaminochou",
    "gn:name":"Baba",
    "iso:country":"JP",
    "wof:name":"708-0366",
    "wof:placetype":"postalcode"
},
  "geometry": {"coordinates":[133.91540000000001,35.1232],"type":"Point"}
}