{
  "type": "Feature",
  "properties": {
    "gn:adm1_name":"Niigataken",
    "gn:adm2_name":"Santougun'Izumozakimachi",
    "gn:name":"Komeda",
    "iso:country":"JP",
    "wof:name":"949-4342",
    "wof:placetype":"postalcode"
},
  "geometry": {"coordinates":[138.70009999999999,37.54],"type":"Point"}
}