{
  "type": "Feature",
  "properties": {
    "gn:adm1_name":"Oosakafu",
    "gn:adm2_name":"Higashioosakashi",
    "gn:name":"Mikuriyanishinochou",
    "iso:country":"JP",
    "wof:name":"577-0037",
    "wof:placetype":"postalcode"
},
  "geometry": {"coordinates":[135.58330000000001,34.6732],"type":"Point"}
}