{
  "type": "Feature",
  "properties": {
    "gn:adm1_name":"Fukuokaken",
    "gn:adm2_name":"Miyakogunkandamachi",
    "gn:name":"Kuukouminamimachi",
    "iso:country":"JP",
    "wof:name":"800-0305",
    "wof:placetype":"postalcode"
},
  "geometry": {"coordinates":[130.97649999999999,33.7728],"type":"Point"}
}