{
  "type": "Feature",
  "properties": {
    "gn:adm1_name":"Tottoriken",
    "gn:adm2_name":"Touhakuguntougouchou",
    "gn:name":"Tabatake",
    "iso:country":"JP",
    "wof:name":"689-0727",
    "wof:placetype":"postalcode"
},
  "geometry": {"coordinates":[133.90620000000001,35.4619],"type":"Point"}
}