{
  "type": "Feature",
  "properties": {
    "gn:adm1_name":"Okinawaken",
    "gn:adm2_name":"Kunigamigun'Oogimison",
    "gn:name":"Ooganeku",
    "iso:country":"JP",
    "wof:name":"905-1305",
    "wof:placetype":"postalcode"
},
  "geometry": {"coordinates":[128.1225,26.7014],"type":"Point"}
}