{
  "type": "Feature",
  "properties": {
    "gn:adm1_name":"Hyougoken",
    "gn:adm2_name":"Kasaishi",
    "gn:name":"Kamodanichou",
    "iso:country":"JP",
    "wof:name":"675-2444",
    "wof:placetype":"postalcode"
},
  "geometry": {"coordinates":[134.84970000000001,34.941],"type":"Point"}
}