{
  "type": "Feature",
  "properties": {
    "gn:adm1_name":"Niigataken",
    "gn:adm2_name":"Nishikanbaragunkatahigashimura",
    "gn:name":"Kunimi",
    "iso:country":"JP",
    "wof:name":"959-0516",
    "wof:placetype":"postalcode"
},
  "geometry": {"coordinates":[138.94380000000001,37.751],"type":"Point"}
}