{
  "type": "Feature",
  "properties": {
    "gn:adm1_name":"Ehimeken",
    "gn:adm2_name":"Yawatahamashi",
    "gn:name":"Yashiro(Choume)",
    "iso:country":"JP",
    "wof:name":"796-8006",
    "wof:placetype":"postalcode"
},
  "geometry": {"coordinates":[132.42959999999999,33.447],"type":"Point"}
}