{
  "type": "Feature",
  "properties": {
    "gn:adm1_name":"Hyougoken",
    "gn:adm2_name":"Takaradukashi",
    "gn:name":"Choujugaoka",
    "iso:country":"JP",
    "wof:name":"665-0001",
    "wof:placetype":"postalcode"
},
  "geometry": {"coordinates":[135.33240000000001,34.811],"type":"Point"}
}