{
  "type": "Feature",
  "properties": {
    "gn:adm1_name":"Ishikawaken",
    "gn:adm2_name":"Nomigunkawakitamachi",
    "gn:name":"Ikanikeisaiganaibaai",
    "iso:country":"JP",
    "wof:name":"923-1200",
    "wof:placetype":"postalcode"
},
  "geometry": {"coordinates":[136.5163,36.4756],"type":"Point"}
}