{
  "type": "Feature",
  "properties": {
    "gn:adm1_name":"Ibarakiken",
    "gn:adm2_name":"Nakagunyamagatamachi",
    "gn:name":"Yawara",
    "iso:country":"JP",
    "wof:name":"319-3103",
    "wof:placetype":"postalcode"
},
  "geometry": {"coordinates":[140.393,36.661],"type":"Point"}
}