{
  "type": "Feature",
  "properties": {
    "gn:adm1_name":"Tochigiken",
    "gn:adm2_name":"Asoguntanumamachi",
    "gn:name":"Funakoshi",
    "iso:country":"JP",
    "wof:name":"327-0305",
    "wof:placetype":"postalcode"
},
  "geometry": {"coordinates":[139.5712,36.4104],"type":"Point"}
}