{
  "type": "Feature",
  "properties": {
    "gn:adm1_name":"Tottoriken",
    "gn:adm2_name":"Saihakugunkishimotochou",
    "gn:name":"Fukuoka",
    "iso:country":"JP",
    "wof:name":"689-4136",
    "wof:placetype":"postalcode"
},
  "geometry": {"coordinates":[133.428,35.3901],"type":"Point"}
}