{
  "type": "Feature",
  "properties": {
    "gn:adm1_name":"Chibaken",
    "gn:adm2_name":"Katoriguntounoshoumachi",
    "gn:name":"Kubonoya",
    "iso:country":"JP",
    "wof:name":"289-0632",
    "wof:placetype":"postalcode"
},
  "geometry": {"coordinates":[140.65260000000001,35.8117],"type":"Point"}
}