{
  "type": "Feature",
  "properties": {
    "gn:adm1_name":"Tokushimaken",
    "gn:adm2_name":"Kaifugunkainanchou",
    "gn:name":"Yoshino",
    "iso:country":"JP",
    "wof:name":"775-0205",
    "wof:placetype":"postalcode"
},
  "geometry": {"coordinates":[134.32810000000001,33.6114],"type":"Point"}
}