{
  "type": "Feature",
  "properties": {
    "gn:adm1_name":"Fukuokaken",
    "gn:adm2_name":"Oomutashi",
    "gn:name":"Suehiromachi",
    "iso:country":"JP",
    "wof:name":"836-0874",
    "wof:placetype":"postalcode"
},
  "geometry": {"coordinates":[130.45750000000001,33.0191],"type":"Point"}
}