{
  "type": "Feature",
  "properties": {
    "gn:adm1_name":"Nagasakiken",
    "gn:adm2_name":"Nishisonogiguntaramichou",
    "gn:name":"Kidokomyou",
    "iso:country":"JP",
    "wof:name":"859-0406",
    "wof:placetype":"postalcode"
},
  "geometry": {"coordinates":[129.97909999999999,32.8359],"type":"Point"}
}