{
  "type": "Feature",
  "properties": {
    "gn:adm1_name":"Ibarakiken",
    "gn:adm2_name":"Tsukubashi",
    "gn:name":"Nishiooi",
    "iso:country":"JP",
    "wof:name":"300-1260",
    "wof:placetype":"postalcode"
},
  "geometry": {"coordinates":[140.12889999999999,36.0154],"type":"Point"}
}