{
  "type": "Feature",
  "properties": {
    "gn:adm1_name":"Tochigiken",
    "gn:adm2_name":"Yaitashi",
    "gn:name":"Shimooota",
    "iso:country":"JP",
    "wof:name":"329-2124",
    "wof:placetype":"postalcode"
},
  "geometry": {"coordinates":[139.9151,36.8218],"type":"Point"}
}