{
  "type": "Feature",
  "properties": {
    "gn:adm1_name":"Saitamaken",
    "gn:adm2_name":"Kazoshi",
    "gn:name":"Togawa",
    "iso:country":"JP",
    "wof:name":"347-0051",
    "wof:placetype":"postalcode"
},
  "geometry": {"coordinates":[139.59569999999999,36.159],"type":"Point"}
}