{
  "type": "Feature",
  "properties": {
    "gn:adm1_name":"Okayamaken",
    "gn:adm2_name":"Okayamashi",
    "gn:name":"Oodarachou",
    "iso:country":"JP",
    "wof:name":"704-8172",
    "wof:placetype":"postalcode"
},
  "geometry": {"coordinates":[134.00489999999999,34.6638],"type":"Point"}
}