{
  "type": "Feature",
  "properties": {
    "gn:adm1_name":"Wakayamaken",
    "gn:adm2_name":"Kaisougunnokamichou",
    "gn:name":"Shimosasa",
    "iso:country":"JP",
    "wof:name":"640-1121",
    "wof:placetype":"postalcode"
},
  "geometry": {"coordinates":[135.31399999999999,34.1565],"type":"Point"}
}