{
  "type": "Feature",
  "properties": {
    "gn:adm1_name":"Gifuken",
    "gn:adm2_name":"Hashimagunkawashimachou",
    "gn:name":"Matsubaramachi",
    "iso:country":"JP",
    "wof:name":"501-6026",
    "wof:placetype":"postalcode"
},
  "geometry": {"coordinates":[136.82650000000001,35.362],"type":"Point"}
}