{
  "type": "Feature",
  "properties": {
    "gn:adm1_name":"Aichiken",
    "gn:adm2_name":"Ichinomiyashi",
    "gn:name":"Yamatochoumiyajihanaike",
    "iso:country":"JP",
    "wof:name":"491-0847",
    "wof:placetype":"postalcode"
},
  "geometry": {"coordinates":[136.80199999999999,35.2879],"type":"Point"}
}