{
  "type": "Feature",
  "properties": {
    "gn:adm1_name":"Fukuokaken",
    "gn:adm2_name":"Chikushigunnakagawamachi",
    "gn:name":"Douzen",
    "iso:country":"JP",
    "wof:name":"811-1254",
    "wof:placetype":"postalcode"
},
  "geometry": {"coordinates":[130.4229,33.5121],"type":"Point"}
}