{
  "type": "Feature",
  "properties": {
    "gn:adm1_name":"Toukyouto",
    "gn:adm2_name":"Koutouku",
    "gn:name":"Monzennakachou",
    "iso:country":"JP",
    "wof:name":"135-0048",
    "wof:placetype":"postalcode"
},
  "geometry": {"coordinates":[139.79490000000001,35.673],"type":"Point"}
}