{
  "type": "Feature",
  "properties": {
    "gn:adm1_name":"Tochigiken",
    "gn:adm2_name":"Shioyagun'Ujiiemachi",
    "gn:name":"Mukougawara",
    "iso:country":"JP",
    "wof:name":"329-1326",
    "wof:placetype":"postalcode"
},
  "geometry": {"coordinates":[139.94229999999999,36.6925],"type":"Point"}
}