{
  "type": "Feature",
  "properties": {
    "gn:adm1_name":"Mieken",
    "gn:adm2_name":"Tsushi",
    "gn:name":"Antouchou",
    "iso:country":"JP",
    "wof:name":"514-0058",
    "wof:placetype":"postalcode"
},
  "geometry": {"coordinates":[136.46860000000001,34.7396],"type":"Point"}
}