{
  "type": "Feature",
  "properties": {
    "gn:adm1_name":"Shizuokaken",
    "gn:adm2_name":"Fujishi",
    "gn:name":"Tajimashinden",
    "iso:country":"JP",
    "wof:name":"417-0032",
    "wof:placetype":"postalcode"
},
  "geometry": {"coordinates":[138.67920000000001,35.1665],"type":"Point"}
}