{
  "type": "Feature",
  "properties": {
    "gn:adm1_name":"Saitamaken",
    "gn:adm2_name":"Hannoushi",
    "gn:name":"Kusumi",
    "iso:country":"JP",
    "wof:name":"357-0068",
    "wof:placetype":"postalcode"
},
  "geometry": {"coordinates":[139.27619999999999,35.8685],"type":"Point"}
}