{
  "type": "Feature",
  "properties": {
    "gn:adm1_name":"Niigataken",
    "gn:adm2_name":"Sadogun'Aikawamachi",
    "gn:name":"Yonchoumehamamachi",
    "iso:country":"JP",
    "wof:name":"952-1567",
    "wof:placetype":"postalcode"
},
  "geometry": {"coordinates":[138.24039999999999,38.0286],"type":"Point"}
}