{
  "type": "Feature",
  "properties": {
    "gn:adm1_name":"Yamagataken",
    "gn:adm2_name":"Yonezawashi",
    "gn:name":"Horikawachou",
    "iso:country":"JP",
    "wof:name":"992-0061",
    "wof:placetype":"postalcode"
},
  "geometry": {"coordinates":[140.09809999999999,37.9056],"type":"Point"}
}