{
  "type": "Feature",
  "properties": {
    "gn:adm1_name":"Gifuken",
    "gn:adm2_name":"Oogakishi",
    "gn:name":"Babachou",
    "iso:country":"JP",
    "wof:name":"503-0922",
    "wof:placetype":"postalcode"
},
  "geometry": {"coordinates":[136.61089999999999,35.3572],"type":"Point"}
}