{
  "type": "Feature",
  "properties": {
    "gn:adm1_name":"Fukuiken",
    "gn:adm2_name":"Fukuishi",
    "gn:name":"Utaidanichou",
    "iso:country":"JP",
    "wof:name":"910-3522",
    "wof:placetype":"postalcode"
},
  "geometry": {"coordinates":[136.03870000000001,36.0421],"type":"Point"}
}