{
  "type": "Feature",
  "properties": {
    "gn:adm1_name":"Miyazakiken",
    "gn:adm2_name":"Miyakonojoushi",
    "gn:name":"Umekitachou",
    "iso:country":"JP",
    "wof:name":"885-0063",
    "wof:placetype":"postalcode"
},
  "geometry": {"coordinates":[131.05459999999999,31.6738],"type":"Point"}
}