{
  "type": "Feature",
  "properties": {
    "gn:adm1_name":"Aichiken",
    "gn:adm2_name":"Nishikamogunfujiokachou",
    "gn:name":"Shimokawaguchi",
    "iso:country":"JP",
    "wof:name":"470-0422",
    "wof:placetype":"postalcode"
},
  "geometry": {"coordinates":[137.2679,35.1856],"type":"Point"}
}