{
  "type": "Feature",
  "properties": {
    "gn:adm1_name":"Kumamotoken",
    "gn:adm2_name":"Kamimashikigunkousamachi",
    "gn:name":"Ikanikeisaiganaibaai",
    "iso:country":"JP",
    "wof:name":"861-4600",
    "wof:placetype":"postalcode"
},
  "geometry": {"coordinates":[130.80930000000001,32.6486],"type":"Point"}
}