{
  "type": "Feature",
  "properties": {
    "gn:adm1_name":"Nagasakiken",
    "gn:adm2_name":"Nagasakishi",
    "gn:name":"Mikawamachi",
    "iso:country":"JP",
    "wof:name":"852-8121",
    "wof:placetype":"postalcode"
},
  "geometry": {"coordinates":[129.89009999999999,32.787],"type":"Point"}
}