{
  "type": "Feature",
  "properties": {
    "gn:adm1_name":"Oosakafu",
    "gn:adm2_name":"Sakaishi",
    "gn:name":"Takao",
    "iso:country":"JP",
    "wof:name":"590-0157",
    "wof:placetype":"postalcode"
},
  "geometry": {"coordinates":[135.46870000000001,34.4967],"type":"Point"}
}