{
  "type": "Feature",
  "properties": {
    "gn:adm1_name":"Aichiken",
    "gn:adm2_name":"Toyotashi",
    "gn:name":"Aidumachou",
    "iso:country":"JP",
    "wof:name":"471-0052",
    "wof:placetype":"postalcode"
},
  "geometry": {"coordinates":[137.14150000000001,35.1065],"type":"Point"}
}