{
  "type": "Feature",
  "properties": {
    "gn:adm1_name":"Okayamaken",
    "gn:adm2_name":"Maniwagun'Ochiaichou",
    "gn:name":"Tahara",
    "iso:country":"JP",
    "wof:name":"719-3104",
    "wof:placetype":"postalcode"
},
  "geometry": {"coordinates":[133.7595,35.0345],"type":"Point"}
}