{
  "type": "Feature",
  "properties": {
    "gn:adm1_name":"Fukushimaken",
    "gn:adm2_name":"Kawanumagunyugawamura",
    "gn:name":"Mikawa",
    "iso:country":"JP",
    "wof:name":"969-3552",
    "wof:placetype":"postalcode"
},
  "geometry": {"coordinates":[139.87479999999999,37.5714],"type":"Point"}
}