{
  "type": "Feature",
  "properties": {
    "gn:adm1_name":"Oosakafu",
    "gn:adm2_name":"Higashioosakashi",
    "gn:name":"Yokomakuranishi",
    "iso:country":"JP",
    "wof:name":"578-0956",
    "wof:placetype":"postalcode"
},
  "geometry": {"coordinates":[135.60470000000001,34.6809],"type":"Point"}
}