{
  "type": "Feature",
  "properties": {
    "gn:adm1_name":"Hyougoken",
    "gn:adm2_name":"Hikamigunhikamichou",
    "gn:name":"Minamiyura",
    "iso:country":"JP",
    "wof:name":"669-3654",
    "wof:placetype":"postalcode"
},
  "geometry": {"coordinates":[135.05500000000001,35.1876],"type":"Point"}
}