{
  "type": "Feature",
  "properties": {
    "gn:adm1_name":"Aichiken",
    "gn:adm2_name":"Nagoyashimizuhoku",
    "gn:name":"Yatomichousakuragaoka",
    "iso:country":"JP",
    "wof:name":"467-0034",
    "wof:placetype":"postalcode"
},
  "geometry": {"coordinates":[136.95679999999999,35.1314],"type":"Point"}
}