{
  "type": "Feature",
  "properties": {
    "gn:adm1_name":"Shimaneken",
    "gn:adm2_name":"Yatsukagunmihonosekichou",
    "gn:name":"Shimoubeo",
    "iso:country":"JP",
    "wof:name":"690-1313",
    "wof:placetype":"postalcode"
},
  "geometry": {"coordinates":[133.172,35.5381],"type":"Point"}
}