{
  "type": "Feature",
  "properties": {
    "gn:adm1_name":"Tokushimaken",
    "gn:adm2_name":"Ananshi",
    "gn:name":"Kusunechou",
    "iso:country":"JP",
    "wof:name":"771-5170",
    "wof:placetype":"postalcode"
},
  "geometry": {"coordinates":[134.56790000000001,33.9273],"type":"Point"}
}