{
  "type": "Feature",
  "properties": {
    "gn:adm1_name":"Chibaken",
    "gn:adm2_name":"Higashikatsushikagunshounanmachi",
    "gn:name":"Midoridai",
    "iso:country":"JP",
    "wof:name":"277-0903",
    "wof:placetype":"postalcode"
},
  "geometry": {"coordinates":[140.00800000000001,35.847],"type":"Point"}
}