{
  "type": "Feature",
  "properties": {
    "gn:adm1_name":"Ehimeken",
    "gn:adm2_name":"Ochigun'Oomishimachou",
    "gn:name":"Utena",
    "iso:country":"JP",
    "wof:name":"794-1305",
    "wof:placetype":"postalcode"
},
  "geometry": {"coordinates":[133.00069999999999,34.2374],"type":"Point"}
}