{
  "type": "Feature",
  "properties": {
    "gn:adm1_name":"Ibarakiken",
    "gn:adm2_name":"Hitachinakashi",
    "gn:name":"Katsutanakaharachou",
    "iso:country":"JP",
    "wof:name":"312-0027",
    "wof:placetype":"postalcode"
},
  "geometry": {"coordinates":[140.51660000000001,36.3925],"type":"Point"}
}