{
  "type": "Feature",
  "properties": {
    "gn:adm1_name":"Shizuokaken",
    "gn:adm2_name":"Iwatagunfukudechou",
    "gn:name":"Fukude",
    "iso:country":"JP",
    "wof:name":"437-1203",
    "wof:placetype":"postalcode"
},
  "geometry": {"coordinates":[137.8828,34.6767],"type":"Point"}
}