{
  "type": "Feature",
  "properties": {
    "gn:adm1_name":"Toyamaken",
    "gn:adm2_name":"Higashitonamigun'Inamimachi",
    "gn:name":"Rentaiji",
    "iso:country":"JP",
    "wof:name":"932-0244",
    "wof:placetype":"postalcode"
},
  "geometry": {"coordinates":[136.96610000000001,36.5519],"type":"Point"}
}