{
  "type": "Feature",
  "properties": {
    "gn:adm1_name":"Nagasakiken",
    "gn:adm2_name":"Kitatakakigun'Iimorichou",
    "gn:name":"Satomyou",
    "iso:country":"JP",
    "wof:name":"854-1123",
    "wof:placetype":"postalcode"
},
  "geometry": {"coordinates":[129.9965,32.7691],"type":"Point"}
}