{
  "type": "Feature",
  "properties": {
    "gn:adm1_name":"Toyamaken",
    "gn:adm2_name":"Himishi",
    "gn:name":"Nakao",
    "iso:country":"JP",
    "wof:name":"935-0064",
    "wof:placetype":"postalcode"
},
  "geometry": {"coordinates":[136.94880000000001,36.8537],"type":"Point"}
}