{
  "type": "Feature",
  "properties": {
    "gn:adm1_name":"Nagasakiken",
    "gn:adm2_name":"Saseboshi",
    "gn:name":"Kamishimachou",
    "iso:country":"JP",
    "wof:name":"857-0067",
    "wof:placetype":"postalcode"
},
  "geometry": {"coordinates":[129.7037,33.1673],"type":"Point"}
}