{
  "type": "Feature",
  "properties": {
    "gn:adm1_name":"Gifuken",
    "gn:adm2_name":"Takayamashi",
    "gn:name":"Echigomachi",
    "iso:country":"JP",
    "wof:name":"506-0033",
    "wof:placetype":"postalcode"
},
  "geometry": {"coordinates":[137.24299999999999,36.1212],"type":"Point"}
}