{
  "type": "Feature",
  "properties": {
    "gn:adm1_name":"Chibaken",
    "gn:adm2_name":"Asahishi",
    "gn:name":"Ashikawa",
    "iso:country":"JP",
    "wof:name":"289-2522",
    "wof:placetype":"postalcode"
},
  "geometry": {"coordinates":[140.65989999999999,35.6976],"type":"Point"}
}