{
  "type": "Feature",
  "properties": {
    "gn:adm1_name":"Shizuokaken",
    "gn:adm2_name":"Iwatashi",
    "gn:name":"Midorigaoka",
    "iso:country":"JP",
    "wof:name":"438-0081",
    "wof:placetype":"postalcode"
},
  "geometry": {"coordinates":[137.86429999999999,34.7489],"type":"Point"}
}