{
  "type": "Feature",
  "properties": {
    "gn:adm1_name":"Oosakafu",
    "gn:adm2_name":"Neyagawashi",
    "gn:name":"Higashikoorienchou",
    "iso:country":"JP",
    "wof:name":"572-0081",
    "wof:placetype":"postalcode"
},
  "geometry": {"coordinates":[135.6377,34.7836],"type":"Point"}
}