{
  "type": "Feature",
  "properties": {
    "gn:adm1_name":"Hyougoken",
    "gn:adm2_name":"Ashiyashi",
    "gn:name":"Kinmitsuchou",
    "iso:country":"JP",
    "wof:name":"659-0065",
    "wof:placetype":"postalcode"
},
  "geometry": {"coordinates":[135.30420000000001,34.7296],"type":"Point"}
}