{
  "type": "Feature",
  "properties": {
    "gn:adm1_name":"Yamagataken",
    "gn:adm2_name":"Obanazawashi",
    "gn:name":"Nyuu",
    "iso:country":"JP",
    "wof:name":"999-4213",
    "wof:placetype":"postalcode"
},
  "geometry": {"coordinates":[140.4444,38.6269],"type":"Point"}
}