{
  "type": "Feature",
  "properties": {
    "gn:adm1_name":"Kyoutofu",
    "gn:adm2_name":"Kyoutoshisakyouku",
    "gn:name":"Shuugakuintsuboechou",
    "iso:country":"JP",
    "wof:name":"606-8075",
    "wof:placetype":"postalcode"
},
  "geometry": {"coordinates":[135.7979,35.0505],"type":"Point"}
}