{
  "type": "Feature",
  "properties": {
    "gn:adm1_name":"Tochigiken",
    "gn:adm2_name":"Kamitsugagunnishikatamachi",
    "gn:name":"Manago",
    "iso:country":"JP",
    "wof:name":"322-0605",
    "wof:placetype":"postalcode"
},
  "geometry": {"coordinates":[139.6987,36.4719],"type":"Point"}
}