{
  "type": "Feature",
  "properties": {
    "gn:adm1_name":"Fukushimaken",
    "gn:adm2_name":"Dategunyanagawamachi",
    "gn:name":"Kibougaoka",
    "iso:country":"JP",
    "wof:name":"960-0729",
    "wof:placetype":"postalcode"
},
  "geometry": {"coordinates":[140.61279999999999,37.8628],"type":"Point"}
}