{
  "type": "Feature",
  "properties": {
    "gn:adm1_name":"Aichiken",
    "gn:adm2_name":"Nagoyashimoriyamaku",
    "gn:name":"Yatsurugi",
    "iso:country":"JP",
    "wof:name":"463-0022",
    "wof:placetype":"postalcode"
},
  "geometry": {"coordinates":[137.00489999999999,35.2062],"type":"Point"}
}