{
  "type": "Feature",
  "properties": {
    "gn:adm1_name":"Ibarakiken",
    "gn:adm2_name":"Shimotsumashi",
    "gn:name":"Kitadaihou",
    "iso:country":"JP",
    "wof:name":"304-0021",
    "wof:placetype":"postalcode"
},
  "geometry": {"coordinates":[139.97579999999999,36.2124],"type":"Point"}
}