{
  "type": "Feature",
  "properties": {
    "gn:adm1_name":"Gifuken",
    "gn:adm2_name":"Kanigunmitakechou",
    "gn:name":"Shuku",
    "iso:country":"JP",
    "wof:name":"505-0113",
    "wof:placetype":"postalcode"
},
  "geometry": {"coordinates":[137.16489999999999,35.4178],"type":"Point"}
}