{
  "type": "Feature",
  "properties": {
    "gn:adm1_name":"Aichiken",
    "gn:adm2_name":"Hekinanshi",
    "gn:name":"Midorimachi",
    "iso:country":"JP",
    "wof:name":"447-0041",
    "wof:placetype":"postalcode"
},
  "geometry": {"coordinates":[137.00380000000001,34.8945],"type":"Point"}
}