{
  "type": "Feature",
  "properties": {
    "gn:adm1_name":"Hyougoken",
    "gn:adm2_name":"Takasagoshi",
    "gn:name":"Kanakedachou",
    "iso:country":"JP",
    "wof:name":"676-0816",
    "wof:placetype":"postalcode"
},
  "geometry": {"coordinates":[134.76660000000001,34.797],"type":"Point"}
}