{
  "type": "Feature",
  "properties": {
    "gn:adm1_name":"Miyagiken",
    "gn:adm2_name":"Kesennumashi",
    "gn:name":"Tanaka",
    "iso:country":"JP",
    "wof:name":"988-0052",
    "wof:placetype":"postalcode"
},
  "geometry": {"coordinates":[141.5566,38.8912],"type":"Point"}
}