{
  "type": "Feature",
  "properties": {
    "gn:adm1_name":"Hyougoken",
    "gn:adm2_name":"Akashishi",
    "gn:name":"Nakaasagirioka",
    "iso:country":"JP",
    "wof:name":"673-0855",
    "wof:placetype":"postalcode"
},
  "geometry": {"coordinates":[135.01050000000001,34.6532],"type":"Point"}
}