{
  "type": "Feature",
  "properties": {
    "gn:adm1_name":"Miyazakiken",
    "gn:adm2_name":"Ebinoshi",
    "gn:name":"Higashinagaeura",
    "iso:country":"JP",
    "wof:name":"889-4231",
    "wof:placetype":"postalcode"
},
  "geometry": {"coordinates":[130.81780000000001,32.0186],"type":"Point"}
}