{
  "type": "Feature",
  "properties": {
    "gn:adm1_name":"Okayamaken",
    "gn:adm2_name":"Okayamashi",
    "gn:name":"Joutoudainishi",
    "iso:country":"JP",
    "wof:name":"709-0624",
    "wof:placetype":"postalcode"
},
  "geometry": {"coordinates":[134.02250000000001,34.6933],"type":"Point"}
}