{
  "type": "Feature",
  "properties": {
    "gn:adm1_name":"Okayamaken",
    "gn:adm2_name":"Okayamashi",
    "gn:name":"Oofuku",
    "iso:country":"JP",
    "wof:name":"701-0204",
    "wof:placetype":"postalcode"
},
  "geometry": {"coordinates":[133.8802,34.6205],"type":"Point"}
}