{
  "type": "Feature",
  "properties": {
    "gn:adm1_name":"Chibaken",
    "gn:adm2_name":"Inbagun'Inbamura",
    "gn:name":"Yoshitaka",
    "iso:country":"JP",
    "wof:name":"270-1603",
    "wof:placetype":"postalcode"
},
  "geometry": {"coordinates":[140.23269999999999,35.7905],"type":"Point"}
}