{
  "type": "Feature",
  "properties": {
    "gn:adm1_name":"Kanagawaken",
    "gn:adm2_name":"Atsugishi",
    "gn:name":"Nakaogino",
    "iso:country":"JP",
    "wof:name":"243-0202",
    "wof:placetype":"postalcode"
},
  "geometry": {"coordinates":[139.3254,35.4867],"type":"Point"}
}