{
  "type": "Feature",
  "properties": {
    "gn:adm1_name":"Toyamaken",
    "gn:adm2_name":"Toyamashi",
    "gn:name":"Kakeomachi",
    "iso:country":"JP",
    "wof:name":"939-8212",
    "wof:placetype":"postalcode"
},
  "geometry": {"coordinates":[137.20910000000001,36.6642],"type":"Point"}
}