{
  "type": "Feature",
  "properties": {
    "gn:adm1_name":"Yamagataken",
    "gn:adm2_name":"Sagaeshi",
    "gn:name":"Hiwada",
    "iso:country":"JP",
    "wof:name":"990-0513",
    "wof:placetype":"postalcode"
},
  "geometry": {"coordinates":[140.25880000000001,38.408],"type":"Point"}
}