{
  "type": "Feature",
  "properties": {
    "gn:adm1_name":"Nagasakiken",
    "gn:adm2_name":"Kitamatsuuragunsazachou",
    "gn:name":"Kaizemen",
    "iso:country":"JP",
    "wof:name":"857-0335",
    "wof:placetype":"postalcode"
},
  "geometry": {"coordinates":[129.6728,33.2595],"type":"Point"}
}