{
  "type": "Feature",
  "properties": {
    "gn:adm1_name":"Hiroshimaken",
    "gn:adm2_name":"Hiroshimashihigashiku",
    "gn:name":"Hesakasakurauemachi",
    "iso:country":"JP",
    "wof:name":"732-0007",
    "wof:placetype":"postalcode"
},
  "geometry": {"coordinates":[132.48480000000001,34.4309],"type":"Point"}
}