{
  "type": "Feature",
  "properties": {
    "gn:adm1_name":"Ehimeken",
    "gn:adm2_name":"Kitauwagunyoshidachou",
    "gn:name":"Fukaura",
    "iso:country":"JP",
    "wof:name":"799-3743",
    "wof:placetype":"postalcode"
},
  "geometry": {"coordinates":[132.5044,33.3218],"type":"Point"}
}