{
  "type": "Feature",
  "properties": {
    "gn:adm1_name":"Saitamaken",
    "gn:adm2_name":"Koshigayashi",
    "gn:name":"Shinmeichou",
    "iso:country":"JP",
    "wof:name":"343-0805",
    "wof:placetype":"postalcode"
},
  "geometry": {"coordinates":[139.76859999999999,35.8959],"type":"Point"}
}