{
  "type": "Feature",
  "properties": {
    "gn:adm1_name":"Miyagiken",
    "gn:adm2_name":"Kesennumashi",
    "gn:name":"Akaiwaminato",
    "iso:country":"JP",
    "wof:name":"988-0103",
    "wof:placetype":"postalcode"
},
  "geometry": {"coordinates":[141.5821,38.8869],"type":"Point"}
}