{
  "type": "Feature",
  "properties": {
    "gn:adm1_name":"Aichiken",
    "gn:adm2_name":"Nagoyashinakagawaku",
    "gn:name":"Maenamichou",
    "iso:country":"JP",
    "wof:name":"454-0025",
    "wof:placetype":"postalcode"
},
  "geometry": {"coordinates":[136.8836,35.15],"type":"Point"}
}