{
  "type": "Feature",
  "properties": {
    "gn:adm1_name":"Kagoshimaken",
    "gn:adm2_name":"Kagoshimashi",
    "gn:name":"Honkoushinmachi",
    "iso:country":"JP",
    "wof:name":"892-0814",
    "wof:placetype":"postalcode"
},
  "geometry": {"coordinates":[130.565,31.5952],"type":"Point"}
}