{
  "type": "Feature",
  "properties": {
    "gn:adm1_name":"Toukyouto",
    "gn:adm2_name":"Minatoku",
    "gn:name":"Shirokanedai",
    "iso:country":"JP",
    "wof:name":"108-0071",
    "wof:placetype":"postalcode"
},
  "geometry": {"coordinates":[139.72559999999999,35.637],"type":"Point"}
}