{
  "type": "Feature",
  "properties": {
    "gn:adm1_name":"Okayamaken",
    "gn:adm2_name":"Okayamashi",
    "gn:name":"Numa",
    "iso:country":"JP",
    "wof:name":"709-0621",
    "wof:placetype":"postalcode"
},
  "geometry": {"coordinates":[134.03559999999999,34.7038],"type":"Point"}
}