{
  "type": "Feature",
  "properties": {
    "gn:adm1_name":"Wakayamaken",
    "gn:adm2_name":"Higashimurogunkozagawachou",
    "gn:name":"Kashiyama",
    "iso:country":"JP",
    "wof:name":"649-4101",
    "wof:placetype":"postalcode"
},
  "geometry": {"coordinates":[135.8081,33.6014],"type":"Point"}
}