{
  "type": "Feature",
  "properties": {
    "gn:adm1_name":"Yamagataken",
    "gn:adm2_name":"Mogamigunmogamimachi",
    "gn:name":"Mitsuzawa",
    "iso:country":"JP",
    "wof:name":"999-6107",
    "wof:placetype":"postalcode"
},
  "geometry": {"coordinates":[140.51599999999999,38.7248],"type":"Point"}
}