{
  "type": "Feature",
  "properties": {
    "gn:adm1_name":"Niigataken",
    "gn:adm2_name":"Shibatashi",
    "gn:name":"Tsukioka",
    "iso:country":"JP",
    "wof:name":"959-2334",
    "wof:placetype":"postalcode"
},
  "geometry": {"coordinates":[139.3092,37.8808],"type":"Point"}
}