{
  "type": "Feature",
  "properties": {
    "gn:adm1_name":"Fukuiken",
    "gn:adm2_name":"Oonoshi",
    "gn:name":"Nonaka",
    "iso:country":"JP",
    "wof:name":"912-0414",
    "wof:placetype":"postalcode"
},
  "geometry": {"coordinates":[136.53399999999999,35.9493],"type":"Point"}
}