{
  "type": "Feature",
  "properties": {
    "gn:adm1_name":"Chibaken",
    "gn:adm2_name":"Mobarashi",
    "gn:name":"Yawatabara",
    "iso:country":"JP",
    "wof:name":"297-0054",
    "wof:placetype":"postalcode"
},
  "geometry": {"coordinates":[140.2715,35.417],"type":"Point"}
}