{
  "type": "Feature",
  "properties": {
    "gn:adm1_name":"Hyougoken",
    "gn:adm2_name":"Shisougunyasutomichou",
    "gn:name":"Suehiro",
    "iso:country":"JP",
    "wof:name":"671-2413",
    "wof:placetype":"postalcode"
},
  "geometry": {"coordinates":[134.60230000000001,35.0139],"type":"Point"}
}