{
  "type": "Feature",
  "properties": {
    "gn:adm1_name":"Sagaken",
    "gn:adm2_name":"Miyakigunkamiminechou",
    "gn:name":"Tsutsumi",
    "iso:country":"JP",
    "wof:name":"849-0124",
    "wof:placetype":"postalcode"
},
  "geometry": {"coordinates":[130.42250000000001,33.3472],"type":"Point"}
}