{
  "type": "Feature",
  "properties": {
    "gn:adm1_name":"Fukuokaken",
    "gn:adm2_name":"Fukuokashihigashiku",
    "gn:name":"Ootake",
    "iso:country":"JP",
    "wof:name":"811-0322",
    "wof:placetype":"postalcode"
},
  "geometry": {"coordinates":[130.33969999999999,33.6532],"type":"Point"}
}