{
  "type": "Feature",
  "properties": {
    "gn:adm1_name":"Mieken",
    "gn:adm2_name":"Yokkaichishi",
    "gn:name":"Shikamachou",
    "iso:country":"JP",
    "wof:name":"512-1113",
    "wof:placetype":"postalcode"
},
  "geometry": {"coordinates":[136.53399999999999,34.9283],"type":"Point"}
}