{
  "type": "Feature",
  "properties": {
    "gn:adm1_name":"Aichiken",
    "gn:adm2_name":"Okazakishi",
    "gn:name":"Yamatsunachou(Choume)",
    "iso:country":"JP",
    "wof:name":"444-3516",
    "wof:placetype":"postalcode"
},
  "geometry": {"coordinates":[137.245,34.8907],"type":"Point"}
}