{
  "type": "Feature",
  "properties": {
    "gn:adm1_name":"Fukuiken",
    "gn:adm2_name":"Sabaeshi",
    "gn:name":"Honmachi",
    "iso:country":"JP",
    "wof:name":"916-0026",
    "wof:placetype":"postalcode"
},
  "geometry": {"coordinates":[136.18510000000001,35.9467],"type":"Point"}
}