{
  "type": "Feature",
  "properties": {
    "gn:adm1_name":"Gifuken",
    "gn:adm2_name":"Yoshikigunkamitakaramura",
    "gn:name":"Kanakido",
    "iso:country":"JP",
    "wof:name":"506-1308",
    "wof:placetype":"postalcode"
},
  "geometry": {"coordinates":[137.42769999999999,36.3335],"type":"Point"}
}