{
  "type": "Feature",
  "properties": {
    "gn:adm1_name":"Kanagawaken",
    "gn:adm2_name":"Kawasakishinakaharaku",
    "gn:name":"Kamikodanaka",
    "iso:country":"JP",
    "wof:name":"211-0053",
    "wof:placetype":"postalcode"
},
  "geometry": {"coordinates":[139.63820000000001,35.5864],"type":"Point"}
}