{
  "type": "Feature",
  "properties": {
    "gn:adm1_name":"Toyamaken",
    "gn:adm2_name":"Toyamashi",
    "gn:name":"Nonaka",
    "iso:country":"JP",
    "wof:name":"931-8422",
    "wof:placetype":"postalcode"
},
  "geometry": {"coordinates":[137.27860000000001,36.7384],"type":"Point"}
}