{
  "type": "Feature",
  "properties": {
    "gn:adm1_name":"Oosakafu",
    "gn:adm2_name":"Toyonakashi",
    "gn:name":"Shiroyamachou",
    "iso:country":"JP",
    "wof:name":"561-0803",
    "wof:placetype":"postalcode"
},
  "geometry": {"coordinates":[135.4768,34.7706],"type":"Point"}
}