{
  "type": "Feature",
  "properties": {
    "gn:adm1_name":"Gifuken",
    "gn:adm2_name":"Mizuhoshi",
    "gn:name":"Juuhachijou",
    "iso:country":"JP",
    "wof:name":"501-0314",
    "wof:placetype":"postalcode"
},
  "geometry": {"coordinates":[136.6583,35.4008],"type":"Point"}
}