{
  "type": "Feature",
  "properties": {
    "gn:adm1_name":"Mieken",
    "gn:adm2_name":"Nabarishi",
    "gn:name":"Sakuragaoka",
    "iso:country":"JP",
    "wof:name":"518-0712",
    "wof:placetype":"postalcode"
},
  "geometry": {"coordinates":[136.09960000000001,34.6212],"type":"Point"}
}