{
  "type": "Feature",
  "properties": {
    "gn:adm1_name":"Naganoken",
    "gn:adm2_name":"Matsumotoshi",
    "gn:name":"Soyano",
    "iso:country":"JP",
    "wof:name":"390-0842",
    "wof:placetype":"postalcode"
},
  "geometry": {"coordinates":[137.95519999999999,36.2191],"type":"Point"}
}