{
  "type": "Feature",
  "properties": {
    "gn:adm1_name":"Hyougoken",
    "gn:adm2_name":"Nishinomiyashi",
    "gn:name":"Nakadonochou",
    "iso:country":"JP",
    "wof:name":"662-0852",
    "wof:placetype":"postalcode"
},
  "geometry": {"coordinates":[135.34829999999999,34.7429],"type":"Point"}
}