{
  "type": "Feature",
  "properties": {
    "gn:adm1_name":"Fukuokaken",
    "gn:adm2_name":"Kurumeshi",
    "gn:name":"Takano",
    "iso:country":"JP",
    "wof:name":"830-0002",
    "wof:placetype":"postalcode"
},
  "geometry": {"coordinates":[130.5257,33.3339],"type":"Point"}
}