{
  "type": "Feature",
  "properties": {
    "gn:adm1_name":"Kagawaken",
    "gn:adm2_name":"Takamatsushi",
    "gn:name":"Kouzaihigashimachi",
    "iso:country":"JP",
    "wof:name":"761-8013",
    "wof:placetype":"postalcode"
},
  "geometry": {"coordinates":[134.00739999999999,34.3426],"type":"Point"}
}