{
  "type": "Feature",
  "properties": {
    "gn:adm1_name":"Gunmaken",
    "gn:adm2_name":"Fujiokashi",
    "gn:name":"Ushita",
    "iso:country":"JP",
    "wof:name":"375-0034",
    "wof:placetype":"postalcode"
},
  "geometry": {"coordinates":[139.0701,36.2107],"type":"Point"}
}