{
  "type": "Feature",
  "properties": {
    "gn:adm1_name":"Okinawaken",
    "gn:adm2_name":"Itomanshi",
    "gn:name":"Zaha",
    "iso:country":"JP",
    "wof:name":"901-0314",
    "wof:placetype":"postalcode"
},
  "geometry": {"coordinates":[127.6884,26.1439],"type":"Point"}
}