{
  "type": "Feature",
  "properties": {
    "gn:adm1_name":"Hyougoken",
    "gn:adm2_name":"Sumotoshi",
    "gn:name":"Nakagawarachounakagawara",
    "iso:country":"JP",
    "wof:name":"656-0002",
    "wof:placetype":"postalcode"
},
  "geometry": {"coordinates":[134.8717,34.3734],"type":"Point"}
}