{
  "type": "Feature",
  "properties": {
    "gn:adm1_name":"Saitamaken",
    "gn:adm2_name":"Hasudashi",
    "gn:name":"Yamanouchi",
    "iso:country":"JP",
    "wof:name":"349-0128",
    "wof:placetype":"postalcode"
},
  "geometry": {"coordinates":[139.64449999999999,35.9852],"type":"Point"}
}