{
  "type": "Feature",
  "properties": {
    "gn:adm1_name":"Niigataken",
    "gn:adm2_name":"Niitsushi",
    "gn:name":"Koganechou",
    "iso:country":"JP",
    "wof:name":"956-0016",
    "wof:placetype":"postalcode"
},
  "geometry": {"coordinates":[139.11080000000001,37.8306],"type":"Point"}
}