{
  "type": "Feature",
  "properties": {
    "gn:adm1_name":"Fukushimaken",
    "gn:adm2_name":"Aiduwakamatsushi",
    "gn:name":"Kouzashimachinakashigou",
    "iso:country":"JP",
    "wof:name":"965-0065",
    "wof:placetype":"postalcode"
},
  "geometry": {"coordinates":[139.88759999999999,37.5238],"type":"Point"}
}