{
  "type": "Feature",
  "properties": {
    "gn:adm1_name":"Kagoshimaken",
    "gn:adm2_name":"Kawanabegunkawanabechou",
    "gn:name":"Nakayamada",
    "iso:country":"JP",
    "wof:name":"897-0132",
    "wof:placetype":"postalcode"
},
  "geometry": {"coordinates":[130.35669999999999,31.3715],"type":"Point"}
}