{
  "type": "Feature",
  "properties": {
    "gn:adm1_name":"Niigataken",
    "gn:adm2_name":"Shibatashi",
    "gn:name":"Kamiakadani",
    "iso:country":"JP",
    "wof:name":"957-0464",
    "wof:placetype":"postalcode"
},
  "geometry": {"coordinates":[139.41579999999999,37.8367],"type":"Point"}
}