{
  "type": "Feature",
  "properties": {
    "gn:adm1_name":"Chibaken",
    "gn:adm2_name":"Shiroishi",
    "gn:name":"Ikenokami",
    "iso:country":"JP",
    "wof:name":"270-1425",
    "wof:placetype":"postalcode"
},
  "geometry": {"coordinates":[140.0514,35.7777],"type":"Point"}
}