{
  "type": "Feature",
  "properties": {
    "gn:adm1_name":"Aichiken",
    "gn:adm2_name":"Komakishi",
    "gn:name":"Koki",
    "iso:country":"JP",
    "wof:name":"485-0058",
    "wof:placetype":"postalcode"
},
  "geometry": {"coordinates":[136.89689999999999,35.279],"type":"Point"}
}