{
  "type": "Feature",
  "properties": {
    "gn:adm1_name":"Chibaken",
    "gn:adm2_name":"Katorigunyamadamachi",
    "gn:name":"Ootogari",
    "iso:country":"JP",
    "wof:name":"289-0425",
    "wof:placetype":"postalcode"
},
  "geometry": {"coordinates":[140.54810000000001,35.7867],"type":"Point"}
}