{
  "type": "Feature",
  "properties": {
    "gn:adm1_name":"Saitamaken",
    "gn:adm2_name":"Kazoshi",
    "gn:name":"Kitakobama",
    "iso:country":"JP",
    "wof:name":"347-0011",
    "wof:placetype":"postalcode"
},
  "geometry": {"coordinates":[139.61510000000001,36.1317],"type":"Point"}
}