{
  "type": "Feature",
  "properties": {
    "gn:adm1_name":"Fukushimaken",
    "gn:adm2_name":"Aiduwakamatsushi",
    "gn:name":"Kouyamachinakanuma",
    "iso:country":"JP",
    "wof:name":"965-0076",
    "wof:placetype":"postalcode"
},
  "geometry": {"coordinates":[139.91579999999999,37.535],"type":"Point"}
}