{
  "type": "Feature",
  "properties": {
    "gn:adm1_name":"Saitamaken",
    "gn:adm2_name":"Kodamagunkodamamachi",
    "gn:name":"Kitabayashi",
    "iso:country":"JP",
    "wof:name":"367-0211",
    "wof:placetype":"postalcode"
},
  "geometry": {"coordinates":[139.13669999999999,36.1977],"type":"Point"}
}