{
  "type": "Feature",
  "properties": {
    "gn:adm1_name":"Ibarakiken",
    "gn:adm2_name":"Hitachinakashi",
    "gn:name":"Oodaira",
    "iso:country":"JP",
    "wof:name":"312-0023",
    "wof:placetype":"postalcode"
},
  "geometry": {"coordinates":[140.5369,36.3813],"type":"Point"}
}