{
  "type": "Feature",
  "properties": {
    "gn:adm1_name":"Hyougoken",
    "gn:adm2_name":"Minougunyokawachou",
    "gn:name":"Kajiya",
    "iso:country":"JP",
    "wof:name":"673-1119",
    "wof:placetype":"postalcode"
},
  "geometry": {"coordinates":[135.1069,34.8798],"type":"Point"}
}