{
  "type": "Feature",
  "properties": {
    "gn:adm1_name":"Mieken",
    "gn:adm2_name":"Yokkaichishi",
    "gn:name":"Higashitarusakachou",
    "iso:country":"JP",
    "wof:name":"510-8035",
    "wof:placetype":"postalcode"
},
  "geometry": {"coordinates":[136.61959999999999,35.006],"type":"Point"}
}