{
  "type": "Feature",
  "properties": {
    "gn:adm1_name":"Chibaken",
    "gn:adm2_name":"Matsudoshi",
    "gn:name":"Mutsumi",
    "iso:country":"JP",
    "wof:name":"270-2204",
    "wof:placetype":"postalcode"
},
  "geometry": {"coordinates":[139.99469999999999,35.7929],"type":"Point"}
}