{
  "type": "Feature",
  "properties": {
    "gn:adm1_name":"Chibaken",
    "gn:adm2_name":"Mobarashi",
    "gn:name":"Takashi",
    "iso:country":"JP",
    "wof:name":"297-0029",
    "wof:placetype":"postalcode"
},
  "geometry": {"coordinates":[140.29599999999999,35.4323],"type":"Point"}
}