{
  "type": "Feature",
  "properties": {
    "gn:adm1_name":"Gifuken",
    "gn:adm2_name":"Gifushi",
    "gn:name":"Yamagataiwahigashi",
    "iso:country":"JP",
    "wof:name":"501-2505",
    "wof:placetype":"postalcode"
},
  "geometry": {"coordinates":[136.827,35.5034],"type":"Point"}
}