{
  "type": "Feature",
  "properties": {
    "gn:adm1_name":"Toyamaken",
    "gn:adm2_name":"Himishi",
    "gn:name":"Ikadani",
    "iso:country":"JP",
    "wof:name":"935-0426",
    "wof:placetype":"postalcode"
},
  "geometry": {"coordinates":[136.97450000000001,36.9181],"type":"Point"}
}