{
  "type": "Feature",
  "properties": {
    "gn:adm1_name":"Shigaken",
    "gn:adm2_name":"Inukamiguntagachou",
    "gn:name":"Tominoo",
    "iso:country":"JP",
    "wof:name":"522-0337",
    "wof:placetype":"postalcode"
},
  "geometry": {"coordinates":[136.2972,35.1973],"type":"Point"}
}