{
  "type": "Feature",
  "properties": {
    "gn:adm1_name":"Yamaguchiken",
    "gn:adm2_name":"Ooshimagun'Ooshimachou",
    "gn:name":"Komatsu",
    "iso:country":"JP",
    "wof:name":"742-2106",
    "wof:placetype":"postalcode"
},
  "geometry": {"coordinates":[132.19159999999999,33.9374],"type":"Point"}
}