{
  "type": "Feature",
  "properties": {
    "gn:adm1_name":"Toyamaken",
    "gn:adm2_name":"Toyamashi",
    "gn:name":"Shinnedukamachi",
    "iso:country":"JP",
    "wof:name":"939-8205",
    "wof:placetype":"postalcode"
},
  "geometry": {"coordinates":[137.20310000000001,36.6796],"type":"Point"}
}