{
  "type": "Feature",
  "properties": {
    "gn:adm1_name":"Fukushimaken",
    "gn:adm2_name":"Minamiaidugunhinoematamura",
    "gn:name":"Hiuchigatake",
    "iso:country":"JP",
    "wof:name":"967-0531",
    "wof:placetype":"postalcode"
},
  "geometry": {"coordinates":[139.27189999999999,37.0065],"type":"Point"}
}