{
  "type": "Feature",
  "properties": {
    "gn:adm1_name":"Gunmaken",
    "gn:adm2_name":"Numatashi",
    "gn:name":"Naramachi",
    "iso:country":"JP",
    "wof:name":"378-0075",
    "wof:placetype":"postalcode"
},
  "geometry": {"coordinates":[139.0718,36.679],"type":"Point"}
}