{
  "type": "Feature",
  "properties": {
    "gn:adm1_name":"Okayamaken",
    "gn:adm2_name":"Kumegunkumechou",
    "gn:name":"Ishiki",
    "iso:country":"JP",
    "wof:name":"709-4615",
    "wof:placetype":"postalcode"
},
  "geometry": {"coordinates":[133.8989,35.0487],"type":"Point"}
}