{
  "type": "Feature",
  "properties": {
    "gn:adm1_name":"Fukuiken",
    "gn:adm2_name":"Fukuishi",
    "gn:name":"Inadashinmachi",
    "iso:country":"JP",
    "wof:name":"910-0156",
    "wof:placetype":"postalcode"
},
  "geometry": {"coordinates":[136.22399999999999,36.1025],"type":"Point"}
}