{
  "type": "Feature",
  "properties": {
    "gn:adm1_name":"Miyagiken",
    "gn:adm2_name":"Shibatagunkawasakimachi",
    "gn:name":"Maekawa(Sonota)",
    "iso:country":"JP",
    "wof:name":"989-1501",
    "wof:placetype":"postalcode"
},
  "geometry": {"coordinates":[140.6317,38.173],"type":"Point"}
}