{
  "type": "Feature",
  "properties": {
    "gn:adm1_name":"Naraken",
    "gn:adm2_name":"Yoshinogunkawakamimura",
    "gn:name":"Ido(Sonota)",
    "iso:country":"JP",
    "wof:name":"639-3558",
    "wof:placetype":"postalcode"
},
  "geometry": {"coordinates":[135.97669999999999,34.3165],"type":"Point"}
}