{
  "type": "Feature",
  "properties": {
    "gn:adm1_name":"Oosakafu",
    "gn:adm2_name":"Tondabayashishi",
    "gn:name":"Asahigaokachou",
    "iso:country":"JP",
    "wof:name":"584-0006",
    "wof:placetype":"postalcode"
},
  "geometry": {"coordinates":[135.60570000000001,34.5223],"type":"Point"}
}