{
  "type": "Feature",
  "properties": {
    "gn:adm1_name":"Oosakafu",
    "gn:adm2_name":"Habikinoshi",
    "gn:name":"Asuka",
    "iso:country":"JP",
    "wof:name":"583-0842",
    "wof:placetype":"postalcode"
},
  "geometry": {"coordinates":[135.63679999999999,34.5345],"type":"Point"}
}