{
  "type": "Feature",
  "properties": {
    "gn:adm1_name":"Oosakafu",
    "gn:adm2_name":"Toyonakashi",
    "gn:name":"Minowa",
    "iso:country":"JP",
    "wof:name":"560-0035",
    "wof:placetype":"postalcode"
},
  "geometry": {"coordinates":[135.45169999999999,34.7858],"type":"Point"}
}