{
  "type": "Feature",
  "properties": {
    "gn:adm1_name":"Kyoutofu",
    "gn:adm2_name":"Ayabeshi",
    "gn:name":"Orochou",
    "iso:country":"JP",
    "wof:name":"623-0001",
    "wof:placetype":"postalcode"
},
  "geometry": {"coordinates":[135.27109999999999,35.3419],"type":"Point"}
}