{
  "type": "Feature",
  "properties": {
    "gn:adm1_name":"Aichiken",
    "gn:adm2_name":"Nagoyashimoriyamaku",
    "gn:name":"Kawamurachou",
    "iso:country":"JP",
    "wof:name":"463-0097",
    "wof:placetype":"postalcode"
},
  "geometry": {"coordinates":[136.96610000000001,35.2121],"type":"Point"}
}