{
  "type": "Feature",
  "properties": {
    "gn:adm1_name":"Kumamotoken",
    "gn:adm2_name":"Kumamotoshi",
    "gn:name":"Arakimachi",
    "iso:country":"JP",
    "wof:name":"861-5501",
    "wof:placetype":"postalcode"
},
  "geometry": {"coordinates":[130.70480000000001,32.8927],"type":"Point"}
}