{
  "type": "Feature",
  "properties": {
    "gn:adm1_name":"Niigataken",
    "gn:adm2_name":"Minamiuonumagunyuzawamachi",
    "gn:name":"Yuzawa",
    "iso:country":"JP",
    "wof:name":"949-6101",
    "wof:placetype":"postalcode"
},
  "geometry": {"coordinates":[138.80860000000001,36.9395],"type":"Point"}
}