{
  "type": "Feature",
  "properties": {
    "gn:adm1_name":"Saitamaken",
    "gn:adm2_name":"Asakashi",
    "gn:name":"Mizonuma",
    "iso:country":"JP",
    "wof:name":"351-0023",
    "wof:placetype":"postalcode"
},
  "geometry": {"coordinates":[139.58969999999999,35.8044],"type":"Point"}
}