{
  "type": "Feature",
  "properties": {
    "gn:adm1_name":"Toukyouto",
    "gn:adm2_name":"Itabashiku",
    "gn:name":"Nakaitabashi",
    "iso:country":"JP",
    "wof:name":"173-0016",
    "wof:placetype":"postalcode"
},
  "geometry": {"coordinates":[139.69739999999999,35.756],"type":"Point"}
}