{
  "type": "Feature",
  "properties": {
    "gn:adm1_name":"Mieken",
    "gn:adm2_name":"Inabeguntouinchou",
    "gn:name":"Tsukushi",
    "iso:country":"JP",
    "wof:name":"511-0253",
    "wof:placetype":"postalcode"
},
  "geometry": {"coordinates":[136.6061,35.0687],"type":"Point"}
}