{
  "type": "Feature",
  "properties": {
    "gn:adm1_name":"Oosakafu",
    "gn:adm2_name":"Izumisanoshi",
    "gn:name":"Shinmachi",
    "iso:country":"JP",
    "wof:name":"598-0051",
    "wof:placetype":"postalcode"
},
  "geometry": {"coordinates":[135.31890000000001,34.4173],"type":"Point"}
}