{
  "type": "Feature",
  "properties": {
    "gn:adm1_name":"Aichiken",
    "gn:adm2_name":"Nagoyashitenpakuku",
    "gn:name":"Hirabaridai",
    "iso:country":"JP",
    "wof:name":"468-0030",
    "wof:placetype":"postalcode"
},
  "geometry": {"coordinates":[137.0035,35.1042],"type":"Point"}
}