{
  "type": "Feature",
  "properties": {
    "gn:adm1_name":"Nagasakiken",
    "gn:adm2_name":"Ikigungounourachou",
    "gn:name":"Watarahigashifure",
    "iso:country":"JP",
    "wof:name":"811-5154",
    "wof:placetype":"postalcode"
},
  "geometry": {"coordinates":[129.65710000000001,33.7641],"type":"Point"}
}