{
  "type": "Feature",
  "properties": {
    "gn:adm1_name":"Kyoutofu",
    "gn:adm2_name":"Kyoutoshisakyouku",
    "gn:name":"Shougoin'Entomichou",
    "iso:country":"JP",
    "wof:name":"606-8323",
    "wof:placetype":"postalcode"
},
  "geometry": {"coordinates":[135.78049999999999,35.0177],"type":"Point"}
}