{
  "type": "Feature",
  "properties": {
    "gn:adm1_name":"Ibarakiken",
    "gn:adm2_name":"Iwaishi",
    "gn:name":"Nekozaneshinden",
    "iso:country":"JP",
    "wof:name":"306-0612",
    "wof:placetype":"postalcode"
},
  "geometry": {"coordinates":[139.9374,36.0493],"type":"Point"}
}