{
  "type": "Feature",
  "properties": {
    "gn:adm1_name":"Niigataken",
    "gn:adm2_name":"Toyosakashi",
    "gn:name":"Hirabayashi",
    "iso:country":"JP",
    "wof:name":"950-3357",
    "wof:placetype":"postalcode"
},
  "geometry": {"coordinates":[139.1927,37.8681],"type":"Point"}
}