{
  "type": "Feature",
  "properties": {
    "gn:adm1_name":"Ehimeken",
    "gn:adm2_name":"Kitauwaguntsushimachou",
    "gn:name":"Nedunaki",
    "iso:country":"JP",
    "wof:name":"798-3346",
    "wof:placetype":"postalcode"
},
  "geometry": {"coordinates":[132.48310000000001,33.0873],"type":"Point"}
}