{
  "type": "Feature",
  "properties": {
    "gn:adm1_name":"Shizuokaken",
    "gn:adm2_name":"Inasagunmikkabichou",
    "gn:name":"Tsutsusaki",
    "iso:country":"JP",
    "wof:name":"431-1405",
    "wof:placetype":"postalcode"
},
  "geometry": {"coordinates":[137.566,34.7967],"type":"Point"}
}