{
  "type": "Feature",
  "properties": {
    "gn:adm1_name":"Fukuiken",
    "gn:adm2_name":"Fukuishi",
    "gn:name":"Mendorichou",
    "iso:country":"JP",
    "wof:name":"910-3378",
    "wof:placetype":"postalcode"
},
  "geometry": {"coordinates":[136.07579999999999,36.1336],"type":"Point"}
}