{
  "type": "Feature",
  "properties": {
    "gn:adm1_name":"Toyamaken",
    "gn:adm2_name":"Imizugunkosugimachi",
    "gn:name":"Tesaki",
    "iso:country":"JP",
    "wof:name":"939-0306",
    "wof:placetype":"postalcode"
},
  "geometry": {"coordinates":[137.11410000000001,36.7191],"type":"Point"}
}