{
  "type": "Feature",
  "properties": {
    "gn:adm1_name":"Fukushimaken",
    "gn:adm2_name":"Shirakawashi",
    "gn:name":"Sugoudate",
    "iso:country":"JP",
    "wof:name":"961-0811",
    "wof:placetype":"postalcode"
},
  "geometry": {"coordinates":[140.2235,37.1141],"type":"Point"}
}