{
  "type": "Feature",
  "properties": {
    "gn:adm1_name":"Toukyouto",
    "gn:adm2_name":"Komaeshi",
    "gn:name":"Izumihonchou",
    "iso:country":"JP",
    "wof:name":"201-0003",
    "wof:placetype":"postalcode"
},
  "geometry": {"coordinates":[139.57579999999999,35.6403],"type":"Point"}
}