{
  "type": "Feature",
  "properties": {
    "gn:adm1_name":"Kyoutofu",
    "gn:adm2_name":"Nakagunmineyamachou",
    "gn:name":"Tanba",
    "iso:country":"JP",
    "wof:name":"627-0011",
    "wof:placetype":"postalcode"
},
  "geometry": {"coordinates":[135.0737,35.6298],"type":"Point"}
}