{
  "type": "Feature",
  "properties": {
    "gn:adm1_name":"Kyoutofu",
    "gn:adm2_name":"Kumanogunkumihamachou",
    "gn:name":"Doi",
    "iso:country":"JP",
    "wof:name":"629-3404",
    "wof:placetype":"postalcode"
},
  "geometry": {"coordinates":[134.8972,35.6054],"type":"Point"}
}