{
  "type": "Feature",
  "properties": {
    "gn:adm1_name":"Aichiken",
    "gn:adm2_name":"Nagoyashichikusaku",
    "gn:name":"Ikeshita",
    "iso:country":"JP",
    "wof:name":"464-0067",
    "wof:placetype":"postalcode"
},
  "geometry": {"coordinates":[136.94470000000001,35.1684],"type":"Point"}
}