{
  "type": "Feature",
  "properties": {
    "gn:adm1_name":"Gifuken",
    "gn:adm2_name":"Mugigun'Itadorimura",
    "gn:name":"Itadorimuranotsuginibanchigakurubaai",
    "iso:country":"JP",
    "wof:name":"501-2901",
    "wof:placetype":"postalcode"
},
  "geometry": {"coordinates":[136.79580000000001,35.7086],"type":"Point"}
}