{
  "type": "Feature",
  "properties": {
    "gn:adm1_name":"Gunmaken",
    "gn:adm2_name":"Tatebayashishi",
    "gn:name":"Obikichou",
    "iso:country":"JP",
    "wof:name":"374-0019",
    "wof:placetype":"postalcode"
},
  "geometry": {"coordinates":[139.54769999999999,36.2471],"type":"Point"}
}