{
  "type": "Feature",
  "properties": {
    "gn:adm1_name":"Hyougoken",
    "gn:adm2_name":"Koubeshihyougoku",
    "gn:name":"Hyougochou",
    "iso:country":"JP",
    "wof:name":"652-0813",
    "wof:placetype":"postalcode"
},
  "geometry": {"coordinates":[135.1737,34.6723],"type":"Point"}
}