{
  "type": "Feature",
  "properties": {
    "gn:adm1_name":"Miyagiken",
    "gn:adm2_name":"Kesennumashi",
    "gn:name":"Hajikamiushirobara",
    "iso:country":"JP",
    "wof:name":"988-0252",
    "wof:placetype":"postalcode"
},
  "geometry": {"coordinates":[141.58410000000001,38.833],"type":"Point"}
}