{
  "type": "Feature",
  "properties": {
    "gn:adm1_name":"Miyagiken",
    "gn:adm2_name":"Sendaishitaihakuku",
    "gn:name":"Oonoda",
    "iso:country":"JP",
    "wof:name":"982-0014",
    "wof:placetype":"postalcode"
},
  "geometry": {"coordinates":[140.87690000000001,38.2142],"type":"Point"}
}