{
  "type": "Feature",
  "properties": {
    "gn:adm1_name":"Aichiken",
    "gn:adm2_name":"Handashi",
    "gn:name":"Heiwachou",
    "iso:country":"JP",
    "wof:name":"475-0963",
    "wof:placetype":"postalcode"
},
  "geometry": {"coordinates":[136.90049999999999,34.9094],"type":"Point"}
}