{
  "type": "Feature",
  "properties": {
    "gn:adm1_name":"Nagasakiken",
    "gn:adm2_name":"Hiradoshi",
    "gn:name":"Furuechou",
    "iso:country":"JP",
    "wof:name":"859-5145",
    "wof:placetype":"postalcode"
},
  "geometry": {"coordinates":[129.512,33.3631],"type":"Point"}
}