{
  "type": "Feature",
  "properties": {
    "gn:adm1_name":"Kanagawaken",
    "gn:adm2_name":"Yokohamashitsudukiku",
    "gn:name":"Ushikubo",
    "iso:country":"JP",
    "wof:name":"224-0012",
    "wof:placetype":"postalcode"
},
  "geometry": {"coordinates":[139.57769999999999,35.5641],"type":"Point"}
}