{
  "type": "Feature",
  "properties": {
    "gn:adm1_name":"Ibarakiken",
    "gn:adm2_name":"Shimotsumashi",
    "gn:name":"Ookishinden",
    "iso:country":"JP",
    "wof:name":"304-0025",
    "wof:placetype":"postalcode"
},
  "geometry": {"coordinates":[139.96860000000001,36.1922],"type":"Point"}
}