{
  "type": "Feature",
  "properties": {
    "gn:adm1_name":"Hyougoken",
    "gn:adm2_name":"Mikatagunhamasakachou",
    "gn:name":"Akasaki",
    "iso:country":"JP",
    "wof:name":"669-6714",
    "wof:placetype":"postalcode"
},
  "geometry": {"coordinates":[134.4941,35.6447],"type":"Point"}
}