{
  "type": "Feature",
  "properties": {
    "gn:adm1_name":"Oosakafu",
    "gn:adm2_name":"Daitoushi",
    "gn:name":"Nishikusunosatochou",
    "iso:country":"JP",
    "wof:name":"574-0005",
    "wof:placetype":"postalcode"
},
  "geometry": {"coordinates":[135.63229999999999,34.7275],"type":"Point"}
}