{
  "type": "Feature",
  "properties": {
    "gn:adm1_name":"Kouchiken",
    "gn:adm2_name":"Takaokagunyusuharachou",
    "gn:name":"Omodani",
    "iso:country":"JP",
    "wof:name":"785-0652",
    "wof:placetype":"postalcode"
},
  "geometry": {"coordinates":[132.87700000000001,33.4499],"type":"Point"}
}