{
  "type": "Feature",
  "properties": {
    "gn:adm1_name":"Yamaguchiken",
    "gn:adm2_name":"Abugun'Abuchou",
    "gn:name":"Fukudakami",
    "iso:country":"JP",
    "wof:name":"758-0612",
    "wof:placetype":"postalcode"
},
  "geometry": {"coordinates":[131.6113,34.529],"type":"Point"}
}