{
  "type": "Feature",
  "properties": {
    "gn:adm1_name":"Fukushimaken",
    "gn:adm2_name":"Iwakishi",
    "gn:name":"Tairaizumizaki",
    "iso:country":"JP",
    "wof:name":"970-0112",
    "wof:placetype":"postalcode"
},
  "geometry": {"coordinates":[140.94659999999999,37.0753],"type":"Point"}
}