{
  "type": "Feature",
  "properties": {
    "gn:adm1_name":"Hyougoken",
    "gn:adm2_name":"Koubeshihigashinadaku",
    "gn:name":"Moriminamimachi",
    "iso:country":"JP",
    "wof:name":"658-0011",
    "wof:placetype":"postalcode"
},
  "geometry": {"coordinates":[135.29220000000001,34.7293],"type":"Point"}
}