{
  "type": "Feature",
  "properties": {
    "gn:adm1_name":"Naraken",
    "gn:adm2_name":"Udagunmuroumura",
    "gn:name":"Ryuuguchi",
    "iso:country":"JP",
    "wof:name":"633-0311",
    "wof:placetype":"postalcode"
},
  "geometry": {"coordinates":[136.0624,34.5662],"type":"Point"}
}