{
  "type": "Feature",
  "properties": {
    "gn:adm1_name":"Niigataken",
    "gn:adm2_name":"Kitakanbaragunsuibaramachi",
    "gn:name":"Ichinoyama",
    "iso:country":"JP",
    "wof:name":"959-2062",
    "wof:placetype":"postalcode"
},
  "geometry": {"coordinates":[139.22640000000001,37.8215],"type":"Point"}
}