{
  "type": "Feature",
  "properties": {
    "gn:adm1_name":"Gifuken",
    "gn:adm2_name":"Gifushi",
    "gn:name":"Kusunokichou",
    "iso:country":"JP",
    "wof:name":"502-0826",
    "wof:placetype":"postalcode"
},
  "geometry": {"coordinates":[136.77189999999999,35.4471],"type":"Point"}
}