{
  "type": "Feature",
  "properties": {
    "gn:adm1_name":"Niigataken",
    "gn:adm2_name":"Iwafunegunkamihayashimura",
    "gn:name":"Koide",
    "iso:country":"JP",
    "wof:name":"959-3413",
    "wof:placetype":"postalcode"
},
  "geometry": {"coordinates":[139.48249999999999,38.1825],"type":"Point"}
}