{
  "type": "Feature",
  "properties": {
    "gn:adm1_name":"Oosakafu",
    "gn:adm2_name":"Ikedashi",
    "gn:name":"Shibutani",
    "iso:country":"JP",
    "wof:name":"563-0028",
    "wof:placetype":"postalcode"
},
  "geometry": {"coordinates":[135.4409,34.8259],"type":"Point"}
}