{
  "type": "Feature",
  "properties": {
    "gn:adm1_name":"Kyoutofu",
    "gn:adm2_name":"Miyadushi",
    "gn:name":"Nakatsu",
    "iso:country":"JP",
    "wof:name":"626-0053",
    "wof:placetype":"postalcode"
},
  "geometry": {"coordinates":[135.2364,35.5547],"type":"Point"}
}