{
  "type": "Feature",
  "properties": {
    "gn:adm1_name":"Kanagawaken",
    "gn:adm2_name":"Miuragunhayamamachi",
    "gn:name":"Isshiki",
    "iso:country":"JP",
    "wof:name":"240-0111",
    "wof:placetype":"postalcode"
},
  "geometry": {"coordinates":[139.58619999999999,35.2661],"type":"Point"}
}