{
  "type": "Feature",
  "properties": {
    "gn:adm1_name":"Fukuokaken",
    "gn:adm2_name":"Ukihagun'Ukihamachi",
    "gn:name":"Nishikumanoue",
    "iso:country":"JP",
    "wof:name":"839-1404",
    "wof:placetype":"postalcode"
},
  "geometry": {"coordinates":[130.7946,33.3379],"type":"Point"}
}