{
  "type": "Feature",
  "properties": {
    "gn:adm1_name":"Tochigiken",
    "gn:adm2_name":"Kuroisoshi",
    "gn:name":"Toyouranakamachi",
    "iso:country":"JP",
    "wof:name":"325-0063",
    "wof:placetype":"postalcode"
},
  "geometry": {"coordinates":[140.0436,36.9666],"type":"Point"}
}