{
  "type": "Feature",
  "properties": {
    "gn:adm1_name":"Naraken",
    "gn:adm2_name":"Kashibashi",
    "gn:name":"Nishimami",
    "iso:country":"JP",
    "wof:name":"639-0222",
    "wof:placetype":"postalcode"
},
  "geometry": {"coordinates":[135.7139,34.5455],"type":"Point"}
}