{
  "type": "Feature",
  "properties": {
    "gn:adm1_name":"Kumamotoken",
    "gn:adm2_name":"Kumagunyunomaemachi",
    "gn:name":"Hamagou",
    "iso:country":"JP",
    "wof:name":"868-0602",
    "wof:placetype":"postalcode"
},
  "geometry": {"coordinates":[130.99950000000001,32.3017],"type":"Point"}
}