{
  "type": "Feature",
  "properties": {
    "gn:adm1_name":"Naganoken",
    "gn:adm2_name":"Chikumashi",
    "gn:name":"Kobuneyama",
    "iso:country":"JP",
    "wof:name":"389-0801",
    "wof:placetype":"postalcode"
},
  "geometry": {"coordinates":[138.12350000000001,36.5126],"type":"Point"}
}