{
  "type": "Feature",
  "properties": {
    "gn:adm1_name":"Saitamaken",
    "gn:adm2_name":"Yoshikawashi",
    "gn:name":"Kawafuji",
    "iso:country":"JP",
    "wof:name":"342-0005",
    "wof:placetype":"postalcode"
},
  "geometry": {"coordinates":[139.84389999999999,35.9031],"type":"Point"}
}