{
  "type": "Feature",
  "properties": {
    "gn:adm1_name":"Gunmaken",
    "gn:adm2_name":"Nittagun'Ojimamachi",
    "gn:name":"Oshikiri",
    "iso:country":"JP",
    "wof:name":"370-0405",
    "wof:placetype":"postalcode"
},
  "geometry": {"coordinates":[139.34119999999999,36.2499],"type":"Point"}
}