{
  "type": "Feature",
  "properties": {
    "gn:adm1_name":"Fukuiken",
    "gn:adm2_name":"Sakaigunmikunichou",
    "gn:name":"Shinmei",
    "iso:country":"JP",
    "wof:name":"913-0047",
    "wof:placetype":"postalcode"
},
  "geometry": {"coordinates":[136.14519999999999,36.2167],"type":"Point"}
}