{
  "type": "Feature",
  "properties": {
    "gn:adm1_name":"Hyougoken",
    "gn:adm2_name":"Himejishi",
    "gn:name":"Sanjouchou(1choume)",
    "iso:country":"JP",
    "wof:name":"670-0953",
    "wof:placetype":"postalcode"
},
  "geometry": {"coordinates":[134.68799999999999,34.8115],"type":"Point"}
}