{
  "type": "Feature",
  "properties": {
    "gn:adm1_name":"Oosakafu",
    "gn:adm2_name":"Izumishi",
    "gn:name":"Kannonjichou",
    "iso:country":"JP",
    "wof:name":"594-0065",
    "wof:placetype":"postalcode"
},
  "geometry": {"coordinates":[135.4366,34.4767],"type":"Point"}
}