{
  "type": "Feature",
  "properties": {
    "gn:adm1_name":"Ibarakiken",
    "gn:adm2_name":"Kashimashi",
    "gn:name":"Miyatsudai",
    "iso:country":"JP",
    "wof:name":"314-0006",
    "wof:placetype":"postalcode"
},
  "geometry": {"coordinates":[140.6473,35.9802],"type":"Point"}
}