{
  "type": "Feature",
  "properties": {
    "gn:adm1_name":"Hyougoken",
    "gn:adm2_name":"Shisougun'Ichinomiyachou",
    "gn:name":"Kuratoko",
    "iso:country":"JP",
    "wof:name":"671-4101",
    "wof:placetype":"postalcode"
},
  "geometry": {"coordinates":[134.6507,35.2323],"type":"Point"}
}