{
  "type": "Feature",
  "properties": {
    "gn:adm1_name":"Kyoutofu",
    "gn:adm2_name":"Kyoutoshikitaku",
    "gn:name":"Murasakinonakakashiwanochou",
    "iso:country":"JP",
    "wof:name":"603-8312",
    "wof:placetype":"postalcode"
},
  "geometry": {"coordinates":[135.7381,35.0349],"type":"Point"}
}