{
  "type": "Feature",
  "properties": {
    "gn:adm1_name":"Ehimeken",
    "gn:adm2_name":"Kamiukenagunkumachou",
    "gn:name":"Tsuyumine",
    "iso:country":"JP",
    "wof:name":"791-1221",
    "wof:placetype":"postalcode"
},
  "geometry": {"coordinates":[132.90389999999999,33.6166],"type":"Point"}
}