{
  "type": "Feature",
  "properties": {
    "gn:adm1_name":"Niigataken",
    "gn:adm2_name":"Higashikubikigunmakimura",
    "gn:name":"Tsuboyama",
    "iso:country":"JP",
    "wof:name":"943-0601",
    "wof:placetype":"postalcode"
},
  "geometry": {"coordinates":[138.39940000000001,37.1185],"type":"Point"}
}