{
  "type": "Feature",
  "properties": {
    "gn:adm1_name":"Aichiken",
    "gn:adm2_name":"Tsushimashi",
    "gn:name":"Takaramachi",
    "iso:country":"JP",
    "wof:name":"496-0808",
    "wof:placetype":"postalcode"
},
  "geometry": {"coordinates":[136.72620000000001,35.179],"type":"Point"}
}