{
  "type": "Feature",
  "properties": {
    "gn:adm1_name":"Kanagawaken",
    "gn:adm2_name":"Iseharashi",
    "gn:name":"Isehara",
    "iso:country":"JP",
    "wof:name":"259-1131",
    "wof:placetype":"postalcode"
},
  "geometry": {"coordinates":[139.3108,35.3983],"type":"Point"}
}