{
  "type": "Feature",
  "properties": {
    "gn:adm1_name":"Aichiken",
    "gn:adm2_name":"Tsushimashi",
    "gn:name":"Kannonchou",
    "iso:country":"JP",
    "wof:name":"496-0861",
    "wof:placetype":"postalcode"
},
  "geometry": {"coordinates":[136.71889999999999,35.1877],"type":"Point"}
}