{
  "type": "Feature",
  "properties": {
    "gn:adm1_name":"Ehimeken",
    "gn:adm2_name":"Oozushi",
    "gn:name":"Niiyakou",
    "iso:country":"JP",
    "wof:name":"795-0072",
    "wof:placetype":"postalcode"
},
  "geometry": {"coordinates":[132.59700000000001,33.5373],"type":"Point"}
}