{
  "type": "Feature",
  "properties": {
    "gn:adm1_name":"Tottoriken",
    "gn:adm2_name":"Touhakuguntougouchou",
    "gn:name":"Nokata",
    "iso:country":"JP",
    "wof:name":"689-0705",
    "wof:placetype":"postalcode"
},
  "geometry": {"coordinates":[133.9188,35.4776],"type":"Point"}
}