{
  "type": "Feature",
  "properties": {
    "gn:adm1_name":"Gunmaken",
    "gn:adm2_name":"Agatsumagunnakanojoumachi",
    "gn:name":"Arigawa",
    "iso:country":"JP",
    "wof:name":"377-0416",
    "wof:placetype":"postalcode"
},
  "geometry": {"coordinates":[138.85849999999999,36.6225],"type":"Point"}
}