{
  "type": "Feature",
  "properties": {
    "gn:adm1_name":"Chibaken",
    "gn:adm2_name":"Chouseigunnagaramachi",
    "gn:name":"Oodukura",
    "iso:country":"JP",
    "wof:name":"297-0223",
    "wof:placetype":"postalcode"
},
  "geometry": {"coordinates":[140.1977,35.4194],"type":"Point"}
}