{
  "type": "Feature",
  "properties": {
    "gn:adm1_name":"Chibaken",
    "gn:adm2_name":"Kisaradushi",
    "gn:name":"Kaifuchi",
    "iso:country":"JP",
    "wof:name":"292-0833",
    "wof:placetype":"postalcode"
},
  "geometry": {"coordinates":[139.92250000000001,35.373],"type":"Point"}
}