{
  "type": "Feature",
  "properties": {
    "gn:adm1_name":"Kyoutofu",
    "gn:adm2_name":"Kyoutoshinakagyouku",
    "gn:name":"Yanagihachimanchou",
    "iso:country":"JP",
    "wof:name":"604-8101",
    "wof:placetype":"postalcode"
},
  "geometry": {"coordinates":[135.76400000000001,35.0102],"type":"Point"}
}