{
  "type": "Feature",
  "properties": {
    "gn:adm1_name":"Hyougoken",
    "gn:adm2_name":"Koubeshichuuouku",
    "gn:name":"Kitanochou",
    "iso:country":"JP",
    "wof:name":"650-0002",
    "wof:placetype":"postalcode"
},
  "geometry": {"coordinates":[135.19040000000001,34.7008],"type":"Point"}
}