{
  "type": "Feature",
  "properties": {
    "gn:adm1_name":"Hyougoken",
    "gn:adm2_name":"Sasayamashi",
    "gn:name":"Chouanji",
    "iso:country":"JP",
    "wof:name":"669-2814",
    "wof:placetype":"postalcode"
},
  "geometry": {"coordinates":[135.15450000000001,35.095],"type":"Point"}
}