{
  "type": "Feature",
  "properties": {
    "gn:adm1_name":"Gunmaken",
    "gn:adm2_name":"Tatebayashishi",
    "gn:name":"Matsunumachou",
    "iso:country":"JP",
    "wof:name":"374-0056",
    "wof:placetype":"postalcode"
},
  "geometry": {"coordinates":[139.5018,36.2536],"type":"Point"}
}