{
  "type": "Feature",
  "properties": {
    "gn:adm1_name":"Fukuokaken",
    "gn:adm2_name":"Kitakyuushuushikokuraminamiku",
    "gn:name":"Yokoshirokitamachi",
    "iso:country":"JP",
    "wof:name":"802-0821",
    "wof:placetype":"postalcode"
},
  "geometry": {"coordinates":[130.89609999999999,33.836],"type":"Point"}
}