{
  "type": "Feature",
  "properties": {
    "gn:adm1_name":"Oosakafu",
    "gn:adm2_name":"Moriguchishi",
    "gn:name":"Satanakamachi",
    "iso:country":"JP",
    "wof:name":"570-0002",
    "wof:placetype":"postalcode"
},
  "geometry": {"coordinates":[135.58600000000001,34.7592],"type":"Point"}
}