{
  "type": "Feature",
  "properties": {
    "gn:adm1_name":"Ishikawaken",
    "gn:adm2_name":"Kahokuguntsubatamachi",
    "gn:name":"Kamioota",
    "iso:country":"JP",
    "wof:name":"929-0309",
    "wof:placetype":"postalcode"
},
  "geometry": {"coordinates":[136.77860000000001,36.748],"type":"Point"}
}