{
  "type": "Feature",
  "properties": {
    "gn:adm1_name":"Yamaguchiken",
    "gn:adm2_name":"Shuunanshi",
    "gn:name":"Tsurumidai",
    "iso:country":"JP",
    "wof:name":"745-0632",
    "wof:placetype":"postalcode"
},
  "geometry": {"coordinates":[131.97389999999999,34.0514],"type":"Point"}
}