{
  "type": "Feature",
  "properties": {
    "gn:adm1_name":"Yamaguchiken",
    "gn:adm2_name":"Hikarishi",
    "gn:name":"Kozuou",
    "iso:country":"JP",
    "wof:name":"743-0061",
    "wof:placetype":"postalcode"
},
  "geometry": {"coordinates":[131.9768,34.02],"type":"Point"}
}