{
  "type": "Feature",
  "properties": {
    "gn:adm1_name":"Niigataken",
    "gn:adm2_name":"Itoigawashi",
    "gn:name":"Horikiri",
    "iso:country":"JP",
    "wof:name":"941-0025",
    "wof:placetype":"postalcode"
},
  "geometry": {"coordinates":[137.92259999999999,37.0408],"type":"Point"}
}