{
  "type": "Feature",
  "properties": {
    "gn:adm1_name":"Kanagawaken",
    "gn:adm2_name":"Yokohamashiminamiku",
    "gn:name":"Shinkawachou",
    "iso:country":"JP",
    "wof:name":"232-0027",
    "wof:placetype":"postalcode"
},
  "geometry": {"coordinates":[139.61959999999999,35.4351],"type":"Point"}
}