{
  "type": "Feature",
  "properties": {
    "gn:adm1_name":"Shigaken",
    "gn:adm2_name":"Higashiazaiguntorahimechou",
    "gn:name":"Karakuni",
    "iso:country":"JP",
    "wof:name":"529-0101",
    "wof:placetype":"postalcode"
},
  "geometry": {"coordinates":[136.24520000000001,35.4229],"type":"Point"}
}