{
  "type": "Feature",
  "properties": {
    "gn:adm1_name":"Oosakafu",
    "gn:adm2_name":"Moriguchishi",
    "gn:name":"Terakatahondoori",
    "iso:country":"JP",
    "wof:name":"570-0048",
    "wof:placetype":"postalcode"
},
  "geometry": {"coordinates":[135.57640000000001,34.7247],"type":"Point"}
}