{
  "type": "Feature",
  "properties": {
    "gn:adm1_name":"Okayamaken",
    "gn:adm2_name":"Maniwagun'Ochiaichou",
    "gn:name":"Ikanikeisaiganaibaai",
    "iso:country":"JP",
    "wof:name":"719-3100",
    "wof:placetype":"postalcode"
},
  "geometry": {"coordinates":[133.75059999999999,35.0779],"type":"Point"}
}