{
  "type": "Feature",
  "properties": {
    "gn:adm1_name":"Ishikawaken",
    "gn:adm2_name":"Hakuiguntogimachi",
    "gn:name":"Kainoki",
    "iso:country":"JP",
    "wof:name":"925-0562",
    "wof:placetype":"postalcode"
},
  "geometry": {"coordinates":[136.7208,37.1762],"type":"Point"}
}