{
  "type": "Feature",
  "properties": {
    "gn:adm1_name":"Hiroshimaken",
    "gn:adm2_name":"Miyoshishi",
    "gn:name":"Shiomachi",
    "iso:country":"JP",
    "wof:name":"729-6205",
    "wof:placetype":"postalcode"
},
  "geometry": {"coordinates":[132.9136,34.7755],"type":"Point"}
}