{
  "type": "Feature",
  "properties": {
    "gn:adm1_name":"Toukyouto",
    "gn:adm2_name":"Niijimaniijimamura",
    "gn:name":"Wakagou",
    "iso:country":"JP",
    "wof:name":"100-0401",
    "wof:placetype":"postalcode"
},
  "geometry": {"coordinates":[139.2818,34.4208],"type":"Point"}
}