{
  "type": "Feature",
  "properties": {
    "gn:adm1_name":"Naganoken",
    "gn:adm2_name":"Iidashi",
    "gn:name":"Minamitokiwamachi",
    "iso:country":"JP",
    "wof:name":"395-0037",
    "wof:placetype":"postalcode"
},
  "geometry": {"coordinates":[137.8271,35.5124],"type":"Point"}
}