{
  "type": "Feature",
  "properties": {
    "gn:adm1_name":"Kagoshimaken",
    "gn:adm2_name":"Airagunyoshimatsuchou",
    "gn:name":"Tsurumaru",
    "iso:country":"JP",
    "wof:name":"899-6101",
    "wof:placetype":"postalcode"
},
  "geometry": {"coordinates":[130.7467,32.0296],"type":"Point"}
}