{
  "type": "Feature",
  "properties": {
    "gn:adm1_name":"Aichiken",
    "gn:adm2_name":"Nishikamogun'Obaramura",
    "gn:name":"Senmi",
    "iso:country":"JP",
    "wof:name":"470-0506",
    "wof:placetype":"postalcode"
},
  "geometry": {"coordinates":[137.30189999999999,35.2584],"type":"Point"}
}