{
  "type": "Feature",
  "properties": {
    "gn:adm1_name":"Tokushimaken",
    "gn:adm2_name":"Itanogun'Itanochou",
    "gn:name":"Tounoso",
    "iso:country":"JP",
    "wof:name":"779-0116",
    "wof:placetype":"postalcode"
},
  "geometry": {"coordinates":[134.4461,34.1265],"type":"Point"}
}