{
  "type": "Feature",
  "properties": {
    "gn:adm1_name":"Naganoken",
    "gn:adm2_name":"Kamiinaguntatsunomachi",
    "gn:name":"Ono",
    "iso:country":"JP",
    "wof:name":"399-0601",
    "wof:placetype":"postalcode"
},
  "geometry": {"coordinates":[137.9598,36.0392],"type":"Point"}
}