{
  "type": "Feature",
  "properties": {
    "gn:adm1_name":"Shigaken",
    "gn:adm2_name":"Oumihachimanshi",
    "gn:name":"Daikuchou",
    "iso:country":"JP",
    "wof:name":"523-0824",
    "wof:placetype":"postalcode"
},
  "geometry": {"coordinates":[136.09280000000001,35.1413],"type":"Point"}
}