{
  "type": "Feature",
  "properties": {
    "gn:adm1_name":"Niigataken",
    "gn:adm2_name":"Nakakubikigun'Itakuramachi",
    "gn:name":"Koishihara",
    "iso:country":"JP",
    "wof:name":"944-0146",
    "wof:placetype":"postalcode"
},
  "geometry": {"coordinates":[138.27289999999999,37.0488],"type":"Point"}
}