{
  "type": "Feature",
  "properties": {
    "gn:adm1_name":"Naraken",
    "gn:adm2_name":"Narashi",
    "gn:name":"Minamikiderachou",
    "iso:country":"JP",
    "wof:name":"630-8303",
    "wof:placetype":"postalcode"
},
  "geometry": {"coordinates":[135.83629999999999,34.6675],"type":"Point"}
}