{
  "type": "Feature",
  "properties": {
    "gn:adm1_name":"Oosakafu",
    "gn:adm2_name":"Takatsukishi",
    "gn:name":"Kitayanagawachou",
    "iso:country":"JP",
    "wof:name":"569-0852",
    "wof:placetype":"postalcode"
},
  "geometry": {"coordinates":[135.59139999999999,34.8263],"type":"Point"}
}