{
  "type": "Feature",
  "properties": {
    "gn:adm1_name":"Oosakafu",
    "gn:adm2_name":"Oosakashihigashiyodogawaku",
    "gn:name":"Kamishinjou",
    "iso:country":"JP",
    "wof:name":"533-0006",
    "wof:placetype":"postalcode"
},
  "geometry": {"coordinates":[135.5309,34.749],"type":"Point"}
}