{
  "type": "Feature",
  "properties": {
    "gn:adm1_name":"Aichiken",
    "gn:adm2_name":"Nishikamogunmiyoshichou",
    "gn:name":"Uchikoshi",
    "iso:country":"JP",
    "wof:name":"470-0213",
    "wof:placetype":"postalcode"
},
  "geometry": {"coordinates":[137.09690000000001,35.0789],"type":"Point"}
}