{
  "type": "Feature",
  "properties": {
    "gn:adm1_name":"Aichiken",
    "gn:adm2_name":"Toyotashi",
    "gn:name":"Homichou",
    "iso:country":"JP",
    "wof:name":"470-0344",
    "wof:placetype":"postalcode"
},
  "geometry": {"coordinates":[137.1276,35.135],"type":"Point"}
}