{
  "type": "Feature",
  "properties": {
    "gn:adm1_name":"Oosakafu",
    "gn:adm2_name":"Ibarakishi",
    "gn:name":"Hashinouchi",
    "iso:country":"JP",
    "wof:name":"567-0805",
    "wof:placetype":"postalcode"
},
  "geometry": {"coordinates":[135.58680000000001,34.8217],"type":"Point"}
}