{
  "type": "Feature",
  "properties": {
    "gn:adm1_name":"Miyagiken",
    "gn:adm2_name":"Kamigunshikamachou",
    "gn:name":"Takane",
    "iso:country":"JP",
    "wof:name":"981-4103",
    "wof:placetype":"postalcode"
},
  "geometry": {"coordinates":[140.80359999999999,38.5576],"type":"Point"}
}