{
  "type": "Feature",
  "properties": {
    "gn:adm1_name":"Fukuokaken",
    "gn:adm2_name":"Ukihaguntanushimarumachi",
    "gn:name":"Kamiharu",
    "iso:country":"JP",
    "wof:name":"839-1221",
    "wof:placetype":"postalcode"
},
  "geometry": {"coordinates":[130.6746,33.3442],"type":"Point"}
}