{
  "type": "Feature",
  "properties": {
    "gn:adm1_name":"Kanagawaken",
    "gn:adm2_name":"Kawasakishitakatsuku",
    "gn:name":"Mukaigaoka",
    "iso:country":"JP",
    "wof:name":"213-0035",
    "wof:placetype":"postalcode"
},
  "geometry": {"coordinates":[139.59379999999999,35.5938],"type":"Point"}
}