{
  "type": "Feature",
  "properties": {
    "gn:adm1_name":"Ibarakiken",
    "gn:adm2_name":"Kitasoumagunfujishiromachi",
    "gn:name":"Fujishiro",
    "iso:country":"JP",
    "wof:name":"300-1512",
    "wof:placetype":"postalcode"
},
  "geometry": {"coordinates":[140.11150000000001,35.9227],"type":"Point"}
}