{
  "type": "Feature",
  "properties": {
    "gn:adm1_name":"Kyoutofu",
    "gn:adm2_name":"Kumanogunkumihamachou",
    "gn:name":"Sano",
    "iso:country":"JP",
    "wof:name":"629-3562",
    "wof:placetype":"postalcode"
},
  "geometry": {"coordinates":[134.9735,35.5785],"type":"Point"}
}