{
  "type": "Feature",
  "properties": {
    "gn:adm1_name":"Shimaneken",
    "gn:adm2_name":"Matsueshi",
    "gn:name":"Kitahorichou",
    "iso:country":"JP",
    "wof:name":"690-0888",
    "wof:placetype":"postalcode"
},
  "geometry": {"coordinates":[133.0538,35.4776],"type":"Point"}
}