{
  "type": "Feature",
  "properties": {
    "gn:adm1_name":"Kagawaken",
    "gn:adm2_name":"Higashikagawashi",
    "gn:name":"Higashiyama",
    "iso:country":"JP",
    "wof:name":"769-2711",
    "wof:placetype":"postalcode"
},
  "geometry": {"coordinates":[134.3442,34.207],"type":"Point"}
}