{
  "type": "Feature",
  "properties": {
    "gn:adm1_name":"Kagoshimaken",
    "gn:adm2_name":"Ooshimagun'Isenchou",
    "gn:name":"Itokina",
    "iso:country":"JP",
    "wof:name":"891-8324",
    "wof:placetype":"postalcode"
},
  "geometry": {"coordinates":[128.9237,27.7298],"type":"Point"}
}