{
  "type": "Feature",
  "properties": {
    "gn:adm1_name":"Naganoken",
    "gn:adm2_name":"Kisogunhiyoshimura",
    "gn:name":"Hiyoshimuraichien",
    "iso:country":"JP",
    "wof:name":"399-6101",
    "wof:placetype":"postalcode"
},
  "geometry": {"coordinates":[137.62459999999999,35.857],"type":"Point"}
}