{
  "type": "Feature",
  "properties": {
    "gn:adm1_name":"Gifuken",
    "gn:adm2_name":"Gifushi",
    "gn:name":"Teramachi",
    "iso:country":"JP",
    "wof:name":"500-8118",
    "wof:placetype":"postalcode"
},
  "geometry": {"coordinates":[136.7663,35.4187],"type":"Point"}
}