{
  "type": "Feature",
  "properties": {
    "gn:adm1_name":"Toyamaken",
    "gn:adm2_name":"Uodushi",
    "gn:name":"Masukata",
    "iso:country":"JP",
    "wof:name":"937-0845",
    "wof:placetype":"postalcode"
},
  "geometry": {"coordinates":[137.41630000000001,36.7621],"type":"Point"}
}