{
  "type": "Feature",
  "properties": {
    "gn:adm1_name":"Wakayamaken",
    "gn:adm2_name":"Wakayamashi",
    "gn:name":"Kitamachi",
    "iso:country":"JP",
    "wof:name":"640-8038",
    "wof:placetype":"postalcode"
},
  "geometry": {"coordinates":[135.17330000000001,34.2359],"type":"Point"}
}