{
  "type": "Feature",
  "properties": {
    "gn:adm1_name":"Ibarakiken",
    "gn:adm2_name":"Kashimagunhokotamachi",
    "gn:name":"Takada",
    "iso:country":"JP",
    "wof:name":"311-1524",
    "wof:placetype":"postalcode"
},
  "geometry": {"coordinates":[140.51840000000001,36.1266],"type":"Point"}
}