{
  "type": "Feature",
  "properties": {
    "gn:adm1_name":"Sagaken",
    "gn:adm2_name":"Higashimatsuuragunchinzeichou",
    "gn:name":"Iwano",
    "iso:country":"JP",
    "wof:name":"847-0323",
    "wof:placetype":"postalcode"
},
  "geometry": {"coordinates":[129.92060000000001,33.4952],"type":"Point"}
}