{
  "type": "Feature",
  "properties": {
    "gn:adm1_name":"Ibarakiken",
    "gn:adm2_name":"Shimotsumashi",
    "gn:name":"Minamihara",
    "iso:country":"JP",
    "wof:name":"304-0075",
    "wof:placetype":"postalcode"
},
  "geometry": {"coordinates":[139.94409999999999,36.2016],"type":"Point"}
}