{
  "type": "Feature",
  "properties": {
    "gn:adm1_name":"Chibaken",
    "gn:adm2_name":"Kisaradushi",
    "gn:name":"Hachimandai",
    "iso:country":"JP",
    "wof:name":"292-0814",
    "wof:placetype":"postalcode"
},
  "geometry": {"coordinates":[139.95140000000001,35.3398],"type":"Point"}
}