{
  "type": "Feature",
  "properties": {
    "gn:adm1_name":"Hyougoken",
    "gn:adm2_name":"Sasayamashi",
    "gn:name":"Fukishin",
    "iso:country":"JP",
    "wof:name":"669-2203",
    "wof:placetype":"postalcode"
},
  "geometry": {"coordinates":[135.18700000000001,35.0645],"type":"Point"}
}