{
  "type": "Feature",
  "properties": {
    "gn:adm1_name":"Ooitaken",
    "gn:adm2_name":"Hitashi",
    "gn:name":"Uchikawamachi",
    "iso:country":"JP",
    "wof:name":"877-0068",
    "wof:placetype":"postalcode"
},
  "geometry": {"coordinates":[130.9042,33.3056],"type":"Point"}
}