{
  "type": "Feature",
  "properties": {
    "gn:adm1_name":"Niigataken",
    "gn:adm2_name":"Odiyashi",
    "gn:name":"Tsubono",
    "iso:country":"JP",
    "wof:name":"947-0044",
    "wof:placetype":"postalcode"
},
  "geometry": {"coordinates":[138.77260000000001,37.34],"type":"Point"}
}