{
  "type": "Feature",
  "properties": {
    "gn:adm1_name":"Chibaken",
    "gn:adm2_name":"Yotsukaidoushi",
    "gn:name":"Wada",
    "iso:country":"JP",
    "wof:name":"284-0035",
    "wof:placetype":"postalcode"
},
  "geometry": {"coordinates":[140.1918,35.6607],"type":"Point"}
}