{
  "type": "Feature",
  "properties": {
    "gn:adm1_name":"Aichiken",
    "gn:adm2_name":"Inuyamashi",
    "gn:name":"Takichiyashiki",
    "iso:country":"JP",
    "wof:name":"484-0961",
    "wof:placetype":"postalcode"
},
  "geometry": {"coordinates":[136.9349,35.3293],"type":"Point"}
}