{
  "type": "Feature",
  "properties": {
    "gn:adm1_name":"Tottoriken",
    "gn:adm2_name":"Yazugunchiduchou",
    "gn:name":"Ooya",
    "iso:country":"JP",
    "wof:name":"689-1442",
    "wof:placetype":"postalcode"
},
  "geometry": {"coordinates":[134.2321,35.2135],"type":"Point"}
}