{
  "type": "Feature",
  "properties": {
    "gn:adm1_name":"Kanagawaken",
    "gn:adm2_name":"Yokohamashiasahiku",
    "gn:name":"Imajukuhigashichou",
    "iso:country":"JP",
    "wof:name":"241-0032",
    "wof:placetype":"postalcode"
},
  "geometry": {"coordinates":[139.53460000000001,35.4822],"type":"Point"}
}