{
  "type": "Feature",
  "properties": {
    "gn:adm1_name":"Nagasakiken",
    "gn:adm2_name":"Minamitakakigunkunimichou",
    "gn:name":"Hijikurobo",
    "iso:country":"JP",
    "wof:name":"859-1315",
    "wof:placetype":"postalcode"
},
  "geometry": {"coordinates":[130.2902,32.8576],"type":"Point"}
}