{
  "type": "Feature",
  "properties": {
    "gn:adm1_name":"Hyougoken",
    "gn:adm2_name":"Takaradukashi",
    "gn:name":"Yamamotomaruhashi",
    "iso:country":"JP",
    "wof:name":"665-0815",
    "wof:placetype":"postalcode"
},
  "geometry": {"coordinates":[135.39330000000001,34.814],"type":"Point"}
}