{
  "type": "Feature",
  "properties": {
    "gn:adm1_name":"Saitamaken",
    "gn:adm2_name":"Saitamashiurawaku",
    "gn:name":"Kitaurawa",
    "iso:country":"JP",
    "wof:name":"330-0074",
    "wof:placetype":"postalcode"
},
  "geometry": {"coordinates":[139.64570000000001,35.8746],"type":"Point"}
}