{
  "type": "Feature",
  "properties": {
    "gn:adm1_name":"Okayamaken",
    "gn:adm2_name":"Aidagunsakutouchou",
    "gn:name":"Tahara",
    "iso:country":"JP",
    "wof:name":"709-4242",
    "wof:placetype":"postalcode"
},
  "geometry": {"coordinates":[134.24860000000001,35.0171],"type":"Point"}
}