{
  "type": "Feature",
  "properties": {
    "gn:adm1_name":"Gifuken",
    "gn:adm2_name":"Oogakishi",
    "gn:name":"Mitsuyachou",
    "iso:country":"JP",
    "wof:name":"503-0012",
    "wof:placetype":"postalcode"
},
  "geometry": {"coordinates":[136.61500000000001,35.3914],"type":"Point"}
}