{
  "type": "Feature",
  "properties": {
    "gn:adm1_name":"Tochigiken",
    "gn:adm2_name":"Shimotsugagun'Iwafunemachi",
    "gn:name":"Maganoshima",
    "iso:country":"JP",
    "wof:name":"329-4306",
    "wof:placetype":"postalcode"
},
  "geometry": {"coordinates":[139.6782,36.3004],"type":"Point"}
}