{
  "type": "Feature",
  "properties": {
    "gn:adm1_name":"Kyoutofu",
    "gn:adm2_name":"Kasagun'Ooechou",
    "gn:name":"Kitaariji",
    "iso:country":"JP",
    "wof:name":"620-0341",
    "wof:placetype":"postalcode"
},
  "geometry": {"coordinates":[135.17519999999999,35.3954],"type":"Point"}
}