{
  "type": "Feature",
  "properties": {
    "gn:adm1_name":"Saitamaken",
    "gn:adm2_name":"Chichibugun'Oganomachi",
    "gn:name":"Iida",
    "iso:country":"JP",
    "wof:name":"368-0111",
    "wof:placetype":"postalcode"
},
  "geometry": {"coordinates":[138.9796,36.0301],"type":"Point"}
}