{
  "type": "Feature",
  "properties": {
    "gn:adm1_name":"Shigaken",
    "gn:adm2_name":"Koukaguntsuchiyamachou",
    "gn:name":"Ooduchi",
    "iso:country":"JP",
    "wof:name":"528-0221",
    "wof:placetype":"postalcode"
},
  "geometry": {"coordinates":[136.29560000000001,34.9629],"type":"Point"}
}