{
  "type": "Feature",
  "properties": {
    "gn:adm1_name":"Kagawaken",
    "gn:adm2_name":"Mitoyoguntoyohamachou",
    "gn:name":"Himehama",
    "iso:country":"JP",
    "wof:name":"769-1601",
    "wof:placetype":"postalcode"
},
  "geometry": {"coordinates":[133.6413,34.0801],"type":"Point"}
}