{
  "type": "Feature",
  "properties": {
    "gn:adm1_name":"Gunmaken",
    "gn:adm2_name":"Ouragun'Itakuramachi",
    "gn:name":"Iino",
    "iso:country":"JP",
    "wof:name":"374-0123",
    "wof:placetype":"postalcode"
},
  "geometry": {"coordinates":[139.6062,36.2107],"type":"Point"}
}