{
  "type": "Feature",
  "properties": {
    "gn:adm1_name":"Okinawaken",
    "gn:adm2_name":"Kunigamigunkinchou",
    "gn:name":"Yaka",
    "iso:country":"JP",
    "wof:name":"904-1203",
    "wof:placetype":"postalcode"
},
  "geometry": {"coordinates":[127.8509,26.4501],"type":"Point"}
}