{
  "type": "Feature",
  "properties": {
    "gn:adm1_name":"Saitamaken",
    "gn:adm2_name":"Todashi",
    "gn:name":"Sasame",
    "iso:country":"JP",
    "wof:name":"335-0034",
    "wof:placetype":"postalcode"
},
  "geometry": {"coordinates":[139.64869999999999,35.8152],"type":"Point"}
}