{
  "type": "Feature",
  "properties": {
    "gn:adm1_name":"Saitamaken",
    "gn:adm2_name":"Tokorozawashi",
    "gn:name":"Minaminagai",
    "iso:country":"JP",
    "wof:name":"359-0011",
    "wof:placetype":"postalcode"
},
  "geometry": {"coordinates":[139.5204,35.8161],"type":"Point"}
}