{
  "type": "Feature",
  "properties": {
    "gn:adm1_name":"Gunmaken",
    "gn:adm2_name":"Tomiokashi",
    "gn:name":"Shimotakao",
    "iso:country":"JP",
    "wof:name":"370-2311",
    "wof:placetype":"postalcode"
},
  "geometry": {"coordinates":[138.91329999999999,36.2839],"type":"Point"}
}