{
  "type": "Feature",
  "properties": {
    "gn:adm1_name":"Fukushimaken",
    "gn:adm2_name":"Kitakatashi",
    "gn:name":"Gonokami",
    "iso:country":"JP",
    "wof:name":"966-0063",
    "wof:placetype":"postalcode"
},
  "geometry": {"coordinates":[139.87870000000001,37.6543],"type":"Point"}
}