{
  "type": "Feature",
  "properties": {
    "gn:adm1_name":"Naraken",
    "gn:adm2_name":"Ikomagunhegurichou",
    "gn:name":"Tsubai",
    "iso:country":"JP",
    "wof:name":"636-0911",
    "wof:placetype":"postalcode"
},
  "geometry": {"coordinates":[135.70930000000001,34.6179],"type":"Point"}
}