{
  "type": "Feature",
  "properties": {
    "gn:adm1_name":"Kyoutofu",
    "gn:adm2_name":"Kyoutoshikamigyouku",
    "gn:name":"Suehirochou",
    "iso:country":"JP",
    "wof:name":"602-8312",
    "wof:placetype":"postalcode"
},
  "geometry": {"coordinates":[135.74109999999999,35.0317],"type":"Point"}
}