{
  "type": "Feature",
  "properties": {
    "gn:adm1_name":"Miyagiken",
    "gn:adm2_name":"Shiogamashi",
    "gn:name":"Tamagawa",
    "iso:country":"JP",
    "wof:name":"985-0042",
    "wof:placetype":"postalcode"
},
  "geometry": {"coordinates":[141.00630000000001,38.3104],"type":"Point"}
}