{
  "type": "Feature",
  "properties": {
    "gn:adm1_name":"Fukuiken",
    "gn:adm2_name":"Mikatagunmikatachou",
    "gn:name":"Tagami",
    "iso:country":"JP",
    "wof:name":"919-1326",
    "wof:placetype":"postalcode"
},
  "geometry": {"coordinates":[135.87950000000001,35.5213],"type":"Point"}
}