{
  "type": "Feature",
  "properties": {
    "gn:adm1_name":"Shizuokaken",
    "gn:adm2_name":"Tagataguntoichou",
    "gn:name":"Koshimoda",
    "iso:country":"JP",
    "wof:name":"410-3304",
    "wof:placetype":"postalcode"
},
  "geometry": {"coordinates":[138.76320000000001,34.876],"type":"Point"}
}