{
  "type": "Feature",
  "properties": {
    "gn:adm1_name":"Ibarakiken",
    "gn:adm2_name":"Inashikigun'Azumamachi",
    "gn:name":"Sawarashitate",
    "iso:country":"JP",
    "wof:name":"300-0725",
    "wof:placetype":"postalcode"
},
  "geometry": {"coordinates":[140.48660000000001,35.9323],"type":"Point"}
}