{
  "type": "Feature",
  "properties": {
    "gn:adm1_name":"Gifuken",
    "gn:adm2_name":"Mizunamishi",
    "gn:name":"Yamadachou",
    "iso:country":"JP",
    "wof:name":"509-6104",
    "wof:placetype":"postalcode"
},
  "geometry": {"coordinates":[137.25,35.3476],"type":"Point"}
}