{
  "type": "Feature",
  "properties": {
    "gn:adm1_name":"Aichiken",
    "gn:adm2_name":"Amaguntobishimamura",
    "gn:name":"Mifuku",
    "iso:country":"JP",
    "wof:name":"490-1432",
    "wof:placetype":"postalcode"
},
  "geometry": {"coordinates":[136.80439999999999,35.0918],"type":"Point"}
}