{
  "type": "Feature",
  "properties": {
    "gn:adm1_name":"Hyougoken",
    "gn:adm2_name":"Tsunagungoshikichou",
    "gn:name":"Tsushitsunokawa",
    "iso:country":"JP",
    "wof:name":"656-1341",
    "wof:placetype":"postalcode"
},
  "geometry": {"coordinates":[134.77459999999999,34.3992],"type":"Point"}
}