{
  "type": "Feature",
  "properties": {
    "gn:adm1_name":"Fukushimaken",
    "gn:adm2_name":"Dategundatemachi",
    "gn:name":"Harajima",
    "iso:country":"JP",
    "wof:name":"960-0404",
    "wof:placetype":"postalcode"
},
  "geometry": {"coordinates":[140.50790000000001,37.8225],"type":"Point"}
}