{
  "type": "Feature",
  "properties": {
    "gn:adm1_name":"Oosakafu",
    "gn:adm2_name":"Toyonogunnosechou",
    "gn:name":"Shimoda",
    "iso:country":"JP",
    "wof:name":"563-0355",
    "wof:placetype":"postalcode"
},
  "geometry": {"coordinates":[135.40790000000001,34.9503],"type":"Point"}
}