{
  "type": "Feature",
  "properties": {
    "gn:adm1_name":"Toyamaken",
    "gn:adm2_name":"Toyamashi",
    "gn:name":"Shimoshinnishichou",
    "iso:country":"JP",
    "wof:name":"930-0807",
    "wof:placetype":"postalcode"
},
  "geometry": {"coordinates":[137.21090000000001,36.7153],"type":"Point"}
}