{
  "type": "Feature",
  "properties": {
    "gn:adm1_name":"Hyougoken",
    "gn:adm2_name":"Akashishi",
    "gn:name":"Kitaasagirioka",
    "iso:country":"JP",
    "wof:name":"673-0857",
    "wof:placetype":"postalcode"
},
  "geometry": {"coordinates":[135.012,34.6577],"type":"Point"}
}