{
  "type": "Feature",
  "properties": {
    "gn:adm1_name":"Hiroshimaken",
    "gn:adm2_name":"Hiroshimashinishiku",
    "gn:name":"Takasudai",
    "iso:country":"JP",
    "wof:name":"733-0876",
    "wof:placetype":"postalcode"
},
  "geometry": {"coordinates":[132.41480000000001,34.3992],"type":"Point"}
}