{
  "type": "Feature",
  "properties": {
    "gn:adm1_name":"Kagoshimaken",
    "gn:adm2_name":"Kumagegunminamitanechou",
    "gn:name":"Shimama",
    "iso:country":"JP",
    "wof:name":"891-3706",
    "wof:placetype":"postalcode"
},
  "geometry": {"coordinates":[130.8689,30.4614],"type":"Point"}
}