{
  "type": "Feature",
  "properties": {
    "gn:adm1_name":"Chibaken",
    "gn:adm2_name":"Katorigunhikatamachi",
    "gn:name":"Seiwaotsu",
    "iso:country":"JP",
    "wof:name":"289-0501",
    "wof:placetype":"postalcode"
},
  "geometry": {"coordinates":[140.61519999999999,35.7731],"type":"Point"}
}