{
  "type": "Feature",
  "properties": {
    "gn:adm1_name":"Aichiken",
    "gn:adm2_name":"Nagoyashiminatoku",
    "gn:name":"Iribachou",
    "iso:country":"JP",
    "wof:name":"455-0802",
    "wof:placetype":"postalcode"
},
  "geometry": {"coordinates":[136.85720000000001,35.1129],"type":"Point"}
}