{
  "type": "Feature",
  "properties": {
    "gn:adm1_name":"Aichiken",
    "gn:adm2_name":"Kariyashi",
    "gn:name":"Saiwaichou",
    "iso:country":"JP",
    "wof:name":"448-0025",
    "wof:placetype":"postalcode"
},
  "geometry": {"coordinates":[137.01580000000001,34.9929],"type":"Point"}
}