{
  "type": "Feature",
  "properties": {
    "gn:adm1_name":"Ibarakiken",
    "gn:adm2_name":"Yuukishi",
    "gn:name":"Fujimichou",
    "iso:country":"JP",
    "wof:name":"307-0003",
    "wof:placetype":"postalcode"
},
  "geometry": {"coordinates":[139.8656,36.3012],"type":"Point"}
}