{
  "type": "Feature",
  "properties": {
    "gn:adm1_name":"Hiroshimaken",
    "gn:adm2_name":"Kamoguntoyosakachou",
    "gn:name":"Yoshiwara",
    "iso:country":"JP",
    "wof:name":"724-0305",
    "wof:placetype":"postalcode"
},
  "geometry": {"coordinates":[132.86269999999999,34.6011],"type":"Point"}
}