{
  "type": "Feature",
  "properties": {
    "gn:adm1_name":"Tochigiken",
    "gn:adm2_name":"Utsunomiyashi",
    "gn:name":"Higashiuramachi",
    "iso:country":"JP",
    "wof:name":"321-0167",
    "wof:placetype":"postalcode"
},
  "geometry": {"coordinates":[139.8546,36.5243],"type":"Point"}
}