{
  "type": "Feature",
  "properties": {
    "gn:adm1_name":"Naraken",
    "gn:adm2_name":"Kitakatsuragigunshinjouchou",
    "gn:name":"Minamihanauchi",
    "iso:country":"JP",
    "wof:name":"639-2126",
    "wof:placetype":"postalcode"
},
  "geometry": {"coordinates":[135.72999999999999,34.481],"type":"Point"}
}