{
  "type": "Feature",
  "properties": {
    "gn:adm1_name":"Fukuiken",
    "gn:adm2_name":"Fukuishi",
    "gn:name":"Matsukagechou",
    "iso:country":"JP",
    "wof:name":"910-3382",
    "wof:placetype":"postalcode"
},
  "geometry": {"coordinates":[136.0558,36.1253],"type":"Point"}
}