{
  "type": "Feature",
  "properties": {
    "gn:adm1_name":"Shizuokaken",
    "gn:adm2_name":"Kamogunminamiizuchou",
    "gn:name":"Irouzaki",
    "iso:country":"JP",
    "wof:name":"415-0156",
    "wof:placetype":"postalcode"
},
  "geometry": {"coordinates":[138.84289999999999,34.6112],"type":"Point"}
}