{
  "type": "Feature",
  "properties": {
    "gn:adm1_name":"Fukuiken",
    "gn:adm2_name":"Yoshidagunmatsuokachou",
    "gn:name":"Ishifune",
    "iso:country":"JP",
    "wof:name":"910-1115",
    "wof:placetype":"postalcode"
},
  "geometry": {"coordinates":[136.29830000000001,36.0855],"type":"Point"}
}