{
  "type": "Feature",
  "properties": {
    "gn:adm1_name":"Gifuken",
    "gn:adm2_name":"Kakamigaharashi",
    "gn:name":"Unumaminamimachi",
    "iso:country":"JP",
    "wof:name":"509-0125",
    "wof:placetype":"postalcode"
},
  "geometry": {"coordinates":[136.94139999999999,35.3956],"type":"Point"}
}