{
  "type": "Feature",
  "properties": {
    "gn:adm1_name":"Naraken",
    "gn:adm2_name":"Yoshinogunhigashiyoshinomura",
    "gn:name":"Nakaguro",
    "iso:country":"JP",
    "wof:name":"633-2424",
    "wof:placetype":"postalcode"
},
  "geometry": {"coordinates":[135.94630000000001,34.3896],"type":"Point"}
}