{
  "type": "Feature",
  "properties": {
    "gn:adm1_name":"Ooitaken",
    "gn:adm2_name":"Ooitashi",
    "gn:name":"Ashizaki",
    "iso:country":"JP",
    "wof:name":"870-0014",
    "wof:placetype":"postalcode"
},
  "geometry": {"coordinates":[131.60310000000001,33.2482],"type":"Point"}
}