{
  "type": "Feature",
  "properties": {
    "gn:adm1_name":"Kanagawaken",
    "gn:adm2_name":"Ashigarakamigun'Ooimachi",
    "gn:name":"Shinokubo",
    "iso:country":"JP",
    "wof:name":"258-0011",
    "wof:placetype":"postalcode"
},
  "geometry": {"coordinates":[139.17019999999999,35.3509],"type":"Point"}
}