{
  "type": "Feature",
  "properties": {
    "gn:adm1_name":"Hyougoken",
    "gn:adm2_name":"Kawanishishi",
    "gn:name":"Tsutsumigataki",
    "iso:country":"JP",
    "wof:name":"666-0123",
    "wof:placetype":"postalcode"
},
  "geometry": {"coordinates":[135.42320000000001,34.8549],"type":"Point"}
}