{
  "type": "Feature",
  "properties": {
    "gn:adm1_name":"Kouchiken",
    "gn:adm2_name":"Agawagun'Inochou",
    "gn:name":"Ikenouchi",
    "iso:country":"JP",
    "wof:name":"781-2121",
    "wof:placetype":"postalcode"
},
  "geometry": {"coordinates":[133.45070000000001,33.5378],"type":"Point"}
}