{
  "type": "Feature",
  "properties": {
    "gn:adm1_name":"Hyougoken",
    "gn:adm2_name":"Nishiwakishi",
    "gn:name":"Kosakachou",
    "iso:country":"JP",
    "wof:name":"677-0017",
    "wof:placetype":"postalcode"
},
  "geometry": {"coordinates":[134.96180000000001,34.9967],"type":"Point"}
}