{
  "type": "Feature",
  "properties": {
    "gn:adm1_name":"Fukushimaken",
    "gn:adm2_name":"Kawanumagun'Aidubangemachi",
    "gn:name":"Toudera",
    "iso:country":"JP",
    "wof:name":"969-6584",
    "wof:placetype":"postalcode"
},
  "geometry": {"coordinates":[139.79949999999999,37.573],"type":"Point"}
}