{
  "type": "Feature",
  "properties": {
    "gn:adm1_name":"Ooitaken",
    "gn:adm2_name":"Ooitashi",
    "gn:name":"Furugou",
    "iso:country":"JP",
    "wof:name":"870-0844",
    "wof:placetype":"postalcode"
},
  "geometry": {"coordinates":[131.6086,33.2151],"type":"Point"}
}