{
  "type": "Feature",
  "properties": {
    "gn:adm1_name":"Aichiken",
    "gn:adm2_name":"Nagoyashikitaku",
    "gn:name":"Chigonomiyatoori",
    "iso:country":"JP",
    "wof:name":"462-0038",
    "wof:placetype":"postalcode"
},
  "geometry": {"coordinates":[136.91720000000001,35.1986],"type":"Point"}
}