{
  "type": "Feature",
  "properties": {
    "gn:adm1_name":"Kyoutofu",
    "gn:adm2_name":"Maidurushi",
    "gn:name":"Nunoshiki",
    "iso:country":"JP",
    "wof:name":"624-0806",
    "wof:placetype":"postalcode"
},
  "geometry": {"coordinates":[135.35210000000001,35.4096],"type":"Point"}
}