{
  "type": "Feature",
  "properties": {
    "gn:adm1_name":"Saitamaken",
    "gn:adm2_name":"Iwatsukishi",
    "gn:name":"Sasakuboshinden",
    "iso:country":"JP",
    "wof:name":"339-0035",
    "wof:placetype":"postalcode"
},
  "geometry": {"coordinates":[139.71100000000001,35.9135],"type":"Point"}
}