{
  "type": "Feature",
  "properties": {
    "gn:adm1_name":"Fukuokaken",
    "gn:adm2_name":"Dazaifushi",
    "gn:name":"Toonokoga",
    "iso:country":"JP",
    "wof:name":"818-0104",
    "wof:placetype":"postalcode"
},
  "geometry": {"coordinates":[130.511,33.5081],"type":"Point"}
}