{
  "type": "Feature",
  "properties": {
    "gn:adm1_name":"Gunmaken",
    "gn:adm2_name":"Tanogunyoshiimachi",
    "gn:name":"Tago",
    "iso:country":"JP",
    "wof:name":"370-2116",
    "wof:placetype":"postalcode"
},
  "geometry": {"coordinates":[138.98759999999999,36.2437],"type":"Point"}
}