{
  "type": "Feature",
  "properties": {
    "gn:adm1_name":"Sagaken",
    "gn:adm2_name":"Ogigun'Ashikarichou",
    "gn:name":"Shimokoga",
    "iso:country":"JP",
    "wof:name":"849-0312",
    "wof:placetype":"postalcode"
},
  "geometry": {"coordinates":[130.22130000000001,33.2259],"type":"Point"}
}