{
  "type": "Feature",
  "properties": {
    "gn:adm1_name":"Wakayamaken",
    "gn:adm2_name":"Kainanshi",
    "gn:name":"Onoda",
    "iso:country":"JP",
    "wof:name":"642-0014",
    "wof:placetype":"postalcode"
},
  "geometry": {"coordinates":[135.25239999999999,34.1701],"type":"Point"}
}