{
  "type": "Feature",
  "properties": {
    "gn:adm1_name":"Kyoutofu",
    "gn:adm2_name":"Sourakugunkamochou",
    "gn:name":"Shoubu",
    "iso:country":"JP",
    "wof:name":"619-1124",
    "wof:placetype":"postalcode"
},
  "geometry": {"coordinates":[135.89179999999999,34.7322],"type":"Point"}
}