{
  "type": "Feature",
  "properties": {
    "gn:adm1_name":"Miyagiken",
    "gn:adm2_name":"Kesennumashi",
    "gn:name":"Sakaechou",
    "iso:country":"JP",
    "wof:name":"988-0012",
    "wof:placetype":"postalcode"
},
  "geometry": {"coordinates":[141.57839999999999,38.9119],"type":"Point"}
}