{
  "type": "Feature",
  "properties": {
    "gn:adm1_name":"Gunmaken",
    "gn:adm2_name":"Nittagun'Ojimamachi",
    "gn:name":"Maegoya",
    "iso:country":"JP",
    "wof:name":"370-0406",
    "wof:placetype":"postalcode"
},
  "geometry": {"coordinates":[139.3246,36.2406],"type":"Point"}
}