{
  "type": "Feature",
  "properties": {
    "gn:adm1_name":"Ibarakiken",
    "gn:adm2_name":"Hitachinakashi",
    "gn:name":"Kaneage",
    "iso:country":"JP",
    "wof:name":"312-0022",
    "wof:placetype":"postalcode"
},
  "geometry": {"coordinates":[140.5394,36.3751],"type":"Point"}
}