{
  "type": "Feature",
  "properties": {
    "gn:adm1_name":"Naganoken",
    "gn:adm2_name":"Shimoinaguntakagimura",
    "gn:name":"Ikanikeisaiganaibaai",
    "iso:country":"JP",
    "wof:name":"395-1100",
    "wof:placetype":"postalcode"
},
  "geometry": {"coordinates":[137.88509999999999,35.5084],"type":"Point"}
}