{
  "type": "Feature",
  "properties": {
    "gn:adm1_name":"Kanagawaken",
    "gn:adm2_name":"Hiratsukashi",
    "gn:name":"Yaezakichou",
    "iso:country":"JP",
    "wof:name":"254-0811",
    "wof:placetype":"postalcode"
},
  "geometry": {"coordinates":[139.34899999999999,35.3259],"type":"Point"}
}