{
  "type": "Feature",
  "properties": {
    "gn:adm1_name":"Mieken",
    "gn:adm2_name":"Wataraigun'Obatachou",
    "gn:name":"Sougou",
    "iso:country":"JP",
    "wof:name":"519-0502",
    "wof:placetype":"postalcode"
},
  "geometry": {"coordinates":[136.666,34.5089],"type":"Point"}
}