{
  "type": "Feature",
  "properties": {
    "gn:adm1_name":"Hyougoken",
    "gn:adm2_name":"Mikishi",
    "gn:name":"Fukui",
    "iso:country":"JP",
    "wof:name":"673-0433",
    "wof:placetype":"postalcode"
},
  "geometry": {"coordinates":[134.98169999999999,34.7923],"type":"Point"}
}