{
  "type": "Feature",
  "properties": {
    "gn:adm1_name":"Hyougoken",
    "gn:adm2_name":"Hikamigun'Ichijimachou",
    "gn:name":"Kamitakeda",
    "iso:country":"JP",
    "wof:name":"669-4341",
    "wof:placetype":"postalcode"
},
  "geometry": {"coordinates":[135.12469999999999,35.2287],"type":"Point"}
}