{
  "type": "Feature",
  "properties": {
    "gn:adm1_name":"Fukuiken",
    "gn:adm2_name":"Fukuishi",
    "gn:name":"Shimomoridashinmachi",
    "iso:country":"JP",
    "wof:name":"910-0143",
    "wof:placetype":"postalcode"
},
  "geometry": {"coordinates":[136.2295,36.1077],"type":"Point"}
}