{
  "type": "Feature",
  "properties": {
    "gn:adm1_name":"Oosakafu",
    "gn:adm2_name":"Kishiwadashi",
    "gn:name":"Miyamotochou",
    "iso:country":"JP",
    "wof:name":"596-0054",
    "wof:placetype":"postalcode"
},
  "geometry": {"coordinates":[135.376,34.461],"type":"Point"}
}