{
  "type": "Feature",
  "properties": {
    "gn:adm1_name":"Shimaneken",
    "gn:adm2_name":"Nakagunyasakamura",
    "gn:name":"Kadota",
    "iso:country":"JP",
    "wof:name":"697-1204",
    "wof:placetype":"postalcode"
},
  "geometry": {"coordinates":[132.14570000000001,34.7928],"type":"Point"}
}