{
  "type": "Feature",
  "properties": {
    "gn:adm1_name":"Gunmaken",
    "gn:adm2_name":"Tanogun'Uenomura",
    "gn:name":"Kawawa",
    "iso:country":"JP",
    "wof:name":"370-1614",
    "wof:placetype":"postalcode"
},
  "geometry": {"coordinates":[138.77379999999999,36.0819],"type":"Point"}
}