{
  "type": "Feature",
  "properties": {
    "gn:adm1_name":"Shigaken",
    "gn:adm2_name":"Ootsushi",
    "gn:name":"Ooishihigashi",
    "iso:country":"JP",
    "wof:name":"520-2264",
    "wof:placetype":"postalcode"
},
  "geometry": {"coordinates":[135.92150000000001,34.9141],"type":"Point"}
}