{
  "type": "Feature",
  "properties": {
    "gn:adm1_name":"Ishikawaken",
    "gn:adm2_name":"Mattoushi",
    "gn:name":"Kamifutakuchimachi",
    "iso:country":"JP",
    "wof:name":"924-0828",
    "wof:placetype":"postalcode"
},
  "geometry": {"coordinates":[136.57490000000001,36.5056],"type":"Point"}
}