{
  "type": "Feature",
  "properties": {
    "gn:adm1_name":"Fukuiken",
    "gn:adm2_name":"Tsurugashi",
    "gn:name":"Irohama",
    "iso:country":"JP",
    "wof:name":"914-0844",
    "wof:placetype":"postalcode"
},
  "geometry": {"coordinates":[136.03489999999999,35.7292],"type":"Point"}
}