{
  "type": "Feature",
  "properties": {
    "gn:adm1_name":"Toyamaken",
    "gn:adm2_name":"Shimoniikawagun'Unadukimachi",
    "gn:name":"Aimotoshin",
    "iso:country":"JP",
    "wof:name":"938-0177",
    "wof:placetype":"postalcode"
},
  "geometry": {"coordinates":[137.5471,36.8784],"type":"Point"}
}