{
  "type": "Feature",
  "properties": {
    "gn:adm1_name":"Aichiken",
    "gn:adm2_name":"Gamagoorishi",
    "gn:name":"Maruyamachou",
    "iso:country":"JP",
    "wof:name":"443-0032",
    "wof:placetype":"postalcode"
},
  "geometry": {"coordinates":[137.23670000000001,34.8192],"type":"Point"}
}