{
  "type": "Feature",
  "properties": {
    "gn:adm1_name":"Mieken",
    "gn:adm2_name":"Yokkaichishi",
    "gn:name":"Kuramachi",
    "iso:country":"JP",
    "wof:name":"510-0045",
    "wof:placetype":"postalcode"
},
  "geometry": {"coordinates":[136.6328,34.9653],"type":"Point"}
}