{
  "type": "Feature",
  "properties": {
    "gn:adm1_name":"Kyoutofu",
    "gn:adm2_name":"Kameokashi",
    "gn:name":"Higashibetsuinchoukamihara",
    "iso:country":"JP",
    "wof:name":"621-0102",
    "wof:placetype":"postalcode"
},
  "geometry": {"coordinates":[135.5607,34.9798],"type":"Point"}
}