{
  "type": "Feature",
  "properties": {
    "gn:adm1_name":"Ibarakiken",
    "gn:adm2_name":"Hitachinakashi",
    "gn:name":"Niidutsumi",
    "iso:country":"JP",
    "wof:name":"311-1254",
    "wof:placetype":"postalcode"
},
  "geometry": {"coordinates":[140.58840000000001,36.3585],"type":"Point"}
}