{
  "type": "Feature",
  "properties": {
    "gn:adm1_name":"Ehimeken",
    "gn:adm2_name":"Matsuyamashi",
    "gn:name":"Fujiwaramachi",
    "iso:country":"JP",
    "wof:name":"790-0034",
    "wof:placetype":"postalcode"
},
  "geometry": {"coordinates":[132.75890000000001,33.8327],"type":"Point"}
}