{
  "type": "Feature",
  "properties": {
    "gn:adm1_name":"Kouchiken",
    "gn:adm2_name":"Nakamurashi",
    "gn:name":"Fuba",
    "iso:country":"JP",
    "wof:name":"787-0017",
    "wof:placetype":"postalcode"
},
  "geometry": {"coordinates":[132.9375,32.9811],"type":"Point"}
}