{
  "type": "Feature",
  "properties": {
    "gn:adm1_name":"Kagoshimaken",
    "gn:adm2_name":"Kagoshimashi",
    "gn:name":"Funatsuchou",
    "iso:country":"JP",
    "wof:name":"892-0831",
    "wof:placetype":"postalcode"
},
  "geometry": {"coordinates":[130.55760000000001,31.5889],"type":"Point"}
}