{
  "type": "Feature",
  "properties": {
    "gn:adm1_name":"Gifuken",
    "gn:adm2_name":"Motosugunneomura",
    "gn:name":"Itasho",
    "iso:country":"JP",
    "wof:name":"501-1524",
    "wof:placetype":"postalcode"
},
  "geometry": {"coordinates":[136.6163,35.6307],"type":"Point"}
}