{
  "type": "Feature",
  "properties": {
    "gn:adm1_name":"Toyamaken",
    "gn:adm2_name":"Toyamashi",
    "gn:name":"Kakeosakaemachi",
    "iso:country":"JP",
    "wof:name":"939-8215",
    "wof:placetype":"postalcode"
},
  "geometry": {"coordinates":[137.20869999999999,36.6676],"type":"Point"}
}