{
  "type": "Feature",
  "properties": {
    "gn:adm1_name":"Yamaguchiken",
    "gn:adm2_name":"Kugagunnishikichou",
    "gn:name":"Usa",
    "iso:country":"JP",
    "wof:name":"740-0901",
    "wof:placetype":"postalcode"
},
  "geometry": {"coordinates":[132.0557,34.4232],"type":"Point"}
}