{
  "type": "Feature",
  "properties": {
    "gn:adm1_name":"Niigataken",
    "gn:adm2_name":"Nakakubikigun'Itakuramachi",
    "gn:name":"Komodate",
    "iso:country":"JP",
    "wof:name":"944-0129",
    "wof:placetype":"postalcode"
},
  "geometry": {"coordinates":[138.3014,37.0141],"type":"Point"}
}