{
  "type": "Feature",
  "properties": {
    "gn:adm1_name":"Kyoutofu",
    "gn:adm2_name":"Maidurushi",
    "gn:name":"Atagonakamachi",
    "iso:country":"JP",
    "wof:name":"625-0031",
    "wof:placetype":"postalcode"
},
  "geometry": {"coordinates":[135.4076,35.4822],"type":"Point"}
}