{
  "type": "Feature",
  "properties": {
    "gn:adm1_name":"Aichiken",
    "gn:adm2_name":"Nagoyashinakagawaku",
    "gn:name":"Ishibachou",
    "iso:country":"JP",
    "wof:name":"454-0023",
    "wof:placetype":"postalcode"
},
  "geometry": {"coordinates":[136.8837,35.1476],"type":"Point"}
}