{
  "type": "Feature",
  "properties": {
    "gn:adm1_name":"Miyagiken",
    "gn:adm2_name":"Tagajoushi",
    "gn:name":"Chuuou",
    "iso:country":"JP",
    "wof:name":"985-0873",
    "wof:placetype":"postalcode"
},
  "geometry": {"coordinates":[141.00550000000001,38.2948],"type":"Point"}
}