{
  "type": "Feature",
  "properties": {
    "gn:adm1_name":"Kyoutofu",
    "gn:adm2_name":"Kyoutoshikamigyouku",
    "gn:name":"Kaikoujichou",
    "iso:country":"JP",
    "wof:name":"602-0946",
    "wof:placetype":"postalcode"
},
  "geometry": {"coordinates":[135.75389999999999,35.028],"type":"Point"}
}