{
  "type": "Feature",
  "properties": {
    "gn:adm1_name":"Miyagiken",
    "gn:adm2_name":"Motoyoshigunmotoyoshichou",
    "gn:name":"Bounokura",
    "iso:country":"JP",
    "wof:name":"988-0383",
    "wof:placetype":"postalcode"
},
  "geometry": {"coordinates":[141.50559999999999,38.8022],"type":"Point"}
}