{
  "type": "Feature",
  "properties": {
    "gn:adm1_name":"Aichiken",
    "gn:adm2_name":"Toyokawashi",
    "gn:name":"Honnogahara",
    "iso:country":"JP",
    "wof:name":"442-0005",
    "wof:placetype":"postalcode"
},
  "geometry": {"coordinates":[137.40360000000001,34.8382],"type":"Point"}
}