{
  "type": "Feature",
  "properties": {
    "gn:adm1_name":"Gifuken",
    "gn:adm2_name":"Ibigun'Ibigawachou",
    "gn:name":"Kotate",
    "iso:country":"JP",
    "wof:name":"501-0611",
    "wof:placetype":"postalcode"
},
  "geometry": {"coordinates":[136.58510000000001,35.4928],"type":"Point"}
}