{
  "type": "Feature",
  "properties": {
    "gn:adm1_name":"Ishikawaken",
    "gn:adm2_name":"Ishikawagunmikawamachi",
    "gn:name":"Hirakamachi",
    "iso:country":"JP",
    "wof:name":"929-0204",
    "wof:placetype":"postalcode"
},
  "geometry": {"coordinates":[136.49180000000001,36.493],"type":"Point"}
}