{
  "type": "Feature",
  "properties": {
    "gn:adm1_name":"Sagaken",
    "gn:adm2_name":"Sagashi",
    "gn:name":"Kosemachiushijima",
    "iso:country":"JP",
    "wof:name":"840-0008",
    "wof:placetype":"postalcode"
},
  "geometry": {"coordinates":[130.31890000000001,33.2539],"type":"Point"}
}