{
  "type": "Feature",
  "properties": {
    "gn:adm1_name":"Gifuken",
    "gn:adm2_name":"Yoshikigunmiyagawamura",
    "gn:name":"Kuwano",
    "iso:country":"JP",
    "wof:name":"509-4543",
    "wof:placetype":"postalcode"
},
  "geometry": {"coordinates":[137.18279999999999,36.4059],"type":"Point"}
}