{
  "type": "Feature",
  "properties": {
    "gn:adm1_name":"Ehimeken",
    "gn:adm2_name":"Kawanoeshi",
    "gn:name":"Kawanoechouyoki",
    "iso:country":"JP",
    "wof:name":"799-0103",
    "wof:placetype":"postalcode"
},
  "geometry": {"coordinates":[133.59520000000001,34.0371],"type":"Point"}
}