{
  "type": "Feature",
  "properties": {
    "gn:adm1_name":"Kyoutofu",
    "gn:adm2_name":"Sourakugunkamochou",
    "gn:name":"Mori",
    "iso:country":"JP",
    "wof:name":"619-1123",
    "wof:placetype":"postalcode"
},
  "geometry": {"coordinates":[135.87029999999999,34.7562],"type":"Point"}
}