{
  "type": "Feature",
  "properties": {
    "gn:adm1_name":"Shizuokaken",
    "gn:adm2_name":"Fujishi",
    "gn:name":"Morishita",
    "iso:country":"JP",
    "wof:name":"416-0949",
    "wof:placetype":"postalcode"
},
  "geometry": {"coordinates":[138.64439999999999,35.1391],"type":"Point"}
}