{
  "type": "Feature",
  "properties": {
    "gn:adm1_name":"Toyamaken",
    "gn:adm2_name":"Toyamashi",
    "gn:name":"Taroumaru",
    "iso:country":"JP",
    "wof:name":"939-8076",
    "wof:placetype":"postalcode"
},
  "geometry": {"coordinates":[137.21719999999999,36.6738],"type":"Point"}
}