{
  "type": "Feature",
  "properties": {
    "gn:adm1_name":"Niigataken",
    "gn:adm2_name":"Minamikanbaragunnakanoshimamachi",
    "gn:name":"Haijimashinden",
    "iso:country":"JP",
    "wof:name":"954-0142",
    "wof:placetype":"postalcode"
},
  "geometry": {"coordinates":[138.87360000000001,37.527],"type":"Point"}
}