{
  "type": "Feature",
  "properties": {
    "gn:adm1_name":"Kumamotoken",
    "gn:adm2_name":"Yatsushiroshi",
    "gn:name":"Uyanagishimomachi",
    "iso:country":"JP",
    "wof:name":"866-0083",
    "wof:placetype":"postalcode"
},
  "geometry": {"coordinates":[130.59719999999999,32.4835],"type":"Point"}
}