{
  "type": "Feature",
  "properties": {
    "gn:adm1_name":"Ooitaken",
    "gn:adm2_name":"Bungotakadashi",
    "gn:name":"Karegawa",
    "iso:country":"JP",
    "wof:name":"879-0721",
    "wof:placetype":"postalcode"
},
  "geometry": {"coordinates":[131.55850000000001,33.5646],"type":"Point"}
}