{
  "type": "Feature",
  "properties": {
    "gn:adm1_name":"Ehimeken",
    "gn:adm2_name":"Higashiuwagun'Uwachou",
    "gn:name":"Nobusato",
    "iso:country":"JP",
    "wof:name":"797-0037",
    "wof:placetype":"postalcode"
},
  "geometry": {"coordinates":[132.51779999999999,33.4338],"type":"Point"}
}