{
  "type": "Feature",
  "properties": {
    "gn:adm1_name":"Saitamaken",
    "gn:adm2_name":"Misatoshi",
    "gn:name":"Izumi",
    "iso:country":"JP",
    "wof:name":"341-0054",
    "wof:placetype":"postalcode"
},
  "geometry": {"coordinates":[139.86150000000001,35.8437],"type":"Point"}
}