{
  "type": "Feature",
  "properties": {
    "gn:adm1_name":"Hiroshimaken",
    "gn:adm2_name":"Kounugunjougechou",
    "gn:name":"Oduka",
    "iso:country":"JP",
    "wof:name":"729-3401",
    "wof:placetype":"postalcode"
},
  "geometry": {"coordinates":[133.1456,34.7399],"type":"Point"}
}