{
  "type": "Feature",
  "properties": {
    "gn:adm1_name":"Hyougoken",
    "gn:adm2_name":"Tsunaguntsunachou",
    "gn:name":"Kisokami",
    "iso:country":"JP",
    "wof:name":"656-2152",
    "wof:placetype":"postalcode"
},
  "geometry": {"coordinates":[134.86060000000001,34.4176],"type":"Point"}
}