{
  "type": "Feature",
  "properties": {
    "gn:adm1_name":"Toyamaken",
    "gn:adm2_name":"Nishitonamigunfukumitsumachi",
    "gn:name":"Yamamoto",
    "iso:country":"JP",
    "wof:name":"939-1666",
    "wof:placetype":"postalcode"
},
  "geometry": {"coordinates":[136.8502,36.5555],"type":"Point"}
}