{
  "type": "Feature",
  "properties": {
    "gn:adm1_name":"Hyougoken",
    "gn:adm2_name":"Himejishi",
    "gn:name":"Hayashidachouyamada",
    "iso:country":"JP",
    "wof:name":"679-4213",
    "wof:placetype":"postalcode"
},
  "geometry": {"coordinates":[134.58699999999999,34.9327],"type":"Point"}
}