{
  "type": "Feature",
  "properties": {
    "gn:adm1_name":"Niigataken",
    "gn:adm2_name":"Minamikanbaragunnakanoshimamachi",
    "gn:name":"Fukuhara",
    "iso:country":"JP",
    "wof:name":"954-0165",
    "wof:placetype":"postalcode"
},
  "geometry": {"coordinates":[138.83760000000001,37.5583],"type":"Point"}
}