{
  "type": "Feature",
  "properties": {
    "gn:adm1_name":"Chibaken",
    "gn:adm2_name":"Sanbugunshibayamamachi",
    "gn:name":"Niida",
    "iso:country":"JP",
    "wof:name":"289-1625",
    "wof:placetype":"postalcode"
},
  "geometry": {"coordinates":[140.39359999999999,35.6955],"type":"Point"}
}