{
  "type": "Feature",
  "properties": {
    "gn:adm1_name":"Ibarakiken",
    "gn:adm2_name":"Nakagunmiwamura",
    "gn:name":"Otano",
    "iso:country":"JP",
    "wof:name":"319-2602",
    "wof:placetype":"postalcode"
},
  "geometry": {"coordinates":[140.27670000000001,36.6702],"type":"Point"}
}