{
  "type": "Feature",
  "properties": {
    "gn:adm1_name":"Fukuokaken",
    "gn:adm2_name":"Fukuokashichuuouku",
    "gn:name":"Tani",
    "iso:country":"JP",
    "wof:name":"810-0031",
    "wof:placetype":"postalcode"
},
  "geometry": {"coordinates":[130.3818,33.5759],"type":"Point"}
}