{
  "type": "Feature",
  "properties": {
    "gn:adm1_name":"Gifuken",
    "gn:adm2_name":"Kakamigaharashi",
    "gn:name":"Oozanochou",
    "iso:country":"JP",
    "wof:name":"504-0931",
    "wof:placetype":"postalcode"
},
  "geometry": {"coordinates":[136.83930000000001,35.383],"type":"Point"}
}