{
  "type": "Feature",
  "properties": {
    "gn:adm1_name":"Kouchiken",
    "gn:adm2_name":"Susakishi",
    "gn:name":"Kajimachi",
    "iso:country":"JP",
    "wof:name":"785-0010",
    "wof:placetype":"postalcode"
},
  "geometry": {"coordinates":[133.29470000000001,33.4031],"type":"Point"}
}