{
  "type": "Feature",
  "properties": {
    "gn:adm1_name":"Gifuken",
    "gn:adm2_name":"Motosugunneomura",
    "gn:name":"Shimooosu",
    "iso:country":"JP",
    "wof:name":"501-1512",
    "wof:placetype":"postalcode"
},
  "geometry": {"coordinates":[136.67150000000001,35.7077],"type":"Point"}
}