{
  "type": "Feature",
  "properties": {
    "gn:adm1_name":"Okayamaken",
    "gn:adm2_name":"Tamanoshi",
    "gn:name":"Kajioka",
    "iso:country":"JP",
    "wof:name":"706-0311",
    "wof:placetype":"postalcode"
},
  "geometry": {"coordinates":[134.0016,34.5554],"type":"Point"}
}