{
  "type": "Feature",
  "properties": {
    "gn:adm1_name":"Fukuokaken",
    "gn:adm2_name":"Kitakyuushuushikokurakitaku",
    "gn:name":"Komonji",
    "iso:country":"JP",
    "wof:name":"802-0037",
    "wof:placetype":"postalcode"
},
  "geometry": {"coordinates":[130.90289999999999,33.8774],"type":"Point"}
}