{
  "type": "Feature",
  "properties": {
    "gn:adm1_name":"Fukushimaken",
    "gn:adm2_name":"Dategundatemachi",
    "gn:name":"Kamikawara",
    "iso:country":"JP",
    "wof:name":"960-0433",
    "wof:placetype":"postalcode"
},
  "geometry": {"coordinates":[140.3878,37.3687],"type":"Point"}
}