{
  "type": "Feature",
  "properties": {
    "gn:adm1_name":"Toukyouto",
    "gn:adm2_name":"Musashimurayamashi",
    "gn:name":"Midorigaoka",
    "iso:country":"JP",
    "wof:name":"208-0012",
    "wof:placetype":"postalcode"
},
  "geometry": {"coordinates":[139.40870000000001,35.7437],"type":"Point"}
}