{
  "type": "Feature",
  "properties": {
    "gn:adm1_name":"Ibarakiken",
    "gn:adm2_name":"Makabegun'Akenomachi",
    "gn:name":"Furuuchi",
    "iso:country":"JP",
    "wof:name":"300-4544",
    "wof:placetype":"postalcode"
},
  "geometry": {"coordinates":[140.00040000000001,36.2591],"type":"Point"}
}