{
  "type": "Feature",
  "properties": {
    "gn:adm1_name":"Saitamaken",
    "gn:adm2_name":"Kawaguchishi",
    "gn:name":"Araijuku",
    "iso:country":"JP",
    "wof:name":"333-0826",
    "wof:placetype":"postalcode"
},
  "geometry": {"coordinates":[139.73570000000001,35.8437],"type":"Point"}
}