{
  "type": "Feature",
  "properties": {
    "gn:adm1_name":"Miyazakiken",
    "gn:adm2_name":"Nichinanshi",
    "gn:name":"Tenpuku",
    "iso:country":"JP",
    "wof:name":"887-0004",
    "wof:placetype":"postalcode"
},
  "geometry": {"coordinates":[131.3973,31.584],"type":"Point"}
}