{
  "type": "Feature",
  "properties": {
    "gn:adm1_name":"Miyagiken",
    "gn:adm2_name":"Watarigunwatarichou",
    "gn:name":"Ookumajinguuji",
    "iso:country":"JP",
    "wof:name":"989-2372",
    "wof:placetype":"postalcode"
},
  "geometry": {"coordinates":[140.8476,38.0504],"type":"Point"}
}