{
  "type": "Feature",
  "properties": {
    "gn:adm1_name":"Hiroshimaken",
    "gn:adm2_name":"Hibagunhiwachou",
    "gn:name":"Moriwaki",
    "iso:country":"JP",
    "wof:name":"727-0321",
    "wof:placetype":"postalcode"
},
  "geometry": {"coordinates":[132.9991,35.028],"type":"Point"}
}