{
  "type": "Feature",
  "properties": {
    "gn:adm1_name":"Fukushimaken",
    "gn:adm2_name":"Kooriyamashi",
    "gn:name":"Kikutamachiakasaka",
    "iso:country":"JP",
    "wof:name":"963-0545",
    "wof:placetype":"postalcode"
},
  "geometry": {"coordinates":[140.36259999999999,37.4635],"type":"Point"}
}