{
  "type": "Feature",
  "properties": {
    "gn:adm1_name":"Shizuokaken",
    "gn:adm2_name":"Tagatagunnakaizuchou",
    "gn:name":"Tokunaga",
    "iso:country":"JP",
    "wof:name":"410-2506",
    "wof:placetype":"postalcode"
},
  "geometry": {"coordinates":[139.03370000000001,34.9449],"type":"Point"}
}