{
  "type": "Feature",
  "properties": {
    "gn:adm1_name":"Toyamaken",
    "gn:adm2_name":"Oyabeshi",
    "gn:name":"Kitaichi",
    "iso:country":"JP",
    "wof:name":"932-0844",
    "wof:placetype":"postalcode"
},
  "geometry": {"coordinates":[136.83009999999999,36.6402],"type":"Point"}
}