{
  "type": "Feature",
  "properties": {
    "gn:adm1_name":"Niigataken",
    "gn:adm2_name":"Nishikubikigunnadachimachi",
    "gn:name":"Nishikamouda",
    "iso:country":"JP",
    "wof:name":"949-1624",
    "wof:placetype":"postalcode"
},
  "geometry": {"coordinates":[138.0985,37.0809],"type":"Point"}
}