{
  "type": "Feature",
  "properties": {
    "gn:adm1_name":"Toyamaken",
    "gn:adm2_name":"Nakaniikawaguntateyamamachi",
    "gn:name":"Takebayashi",
    "iso:country":"JP",
    "wof:name":"930-3206",
    "wof:placetype":"postalcode"
},
  "geometry": {"coordinates":[137.3381,36.6778],"type":"Point"}
}