{
  "type": "Feature",
  "properties": {
    "gn:adm1_name":"Niigataken",
    "gn:adm2_name":"Sadogun'Aikawamachi",
    "gn:name":"Oritosumiyauramachi",
    "iso:country":"JP",
    "wof:name":"952-1573",
    "wof:placetype":"postalcode"
},
  "geometry": {"coordinates":[138.2388,38.0258],"type":"Point"}
}