{
  "type": "Feature",
  "properties": {
    "gn:adm1_name":"Saitamaken",
    "gn:adm2_name":"Minamisaitamagunshiraokamachi",
    "gn:name":"Sanagaya",
    "iso:country":"JP",
    "wof:name":"349-0216",
    "wof:placetype":"postalcode"
},
  "geometry": {"coordinates":[139.67740000000001,36.004],"type":"Point"}
}