{
  "type": "Feature",
  "properties": {
    "gn:adm1_name":"Chibaken",
    "gn:adm2_name":"Asahishi",
    "gn:name":"Idono",
    "iso:country":"JP",
    "wof:name":"289-2531",
    "wof:placetype":"postalcode"
},
  "geometry": {"coordinates":[140.6251,35.7047],"type":"Point"}
}