{
  "type": "Feature",
  "properties": {
    "gn:adm1_name":"Shigaken",
    "gn:adm2_name":"Rittoushi",
    "gn:name":"Ikanikeisaiganaibaai",
    "iso:country":"JP",
    "wof:name":"520-3000",
    "wof:placetype":"postalcode"
},
  "geometry": {"coordinates":[136.02109999999999,35.0165],"type":"Point"}
}