{
  "type": "Feature",
  "properties": {
    "gn:adm1_name":"Kumamotoken",
    "gn:adm2_name":"Amakusagunryuugatakemachi",
    "gn:name":"Takado",
    "iso:country":"JP",
    "wof:name":"866-0202",
    "wof:placetype":"postalcode"
},
  "geometry": {"coordinates":[130.39660000000001,32.3974],"type":"Point"}
}