{
  "type": "Feature",
  "properties": {
    "gn:adm1_name":"Mieken",
    "gn:adm2_name":"Yokkaichishi",
    "gn:name":"Ooyachichou",
    "iso:country":"JP",
    "wof:name":"510-8034",
    "wof:placetype":"postalcode"
},
  "geometry": {"coordinates":[136.6352,35.019],"type":"Point"}
}