{
  "type": "Feature",
  "properties": {
    "gn:adm1_name":"Hyougoken",
    "gn:adm2_name":"Izushigun'Izushichou",
    "gn:name":"Okuyama",
    "iso:country":"JP",
    "wof:name":"668-0251",
    "wof:placetype":"postalcode"
},
  "geometry": {"coordinates":[134.8794,35.4123],"type":"Point"}
}