{
  "type": "Feature",
  "properties": {
    "gn:adm1_name":"Fukushimaken",
    "gn:adm2_name":"Futabagunfutabamachi",
    "gn:name":"Nakahama",
    "iso:country":"JP",
    "wof:name":"979-1402",
    "wof:placetype":"postalcode"
},
  "geometry": {"coordinates":[141.03469999999999,37.4646],"type":"Point"}
}