{
  "type": "Feature",
  "properties": {
    "gn:adm1_name":"Tottoriken",
    "gn:adm2_name":"Ketakagun'Aoyachou",
    "gn:name":"Yoshikawa",
    "iso:country":"JP",
    "wof:name":"689-0534",
    "wof:placetype":"postalcode"
},
  "geometry": {"coordinates":[133.98609999999999,35.5111],"type":"Point"}
}