{
  "type": "Feature",
  "properties": {
    "gn:adm1_name":"Aichiken",
    "gn:adm2_name":"Hazugunkirachou",
    "gn:name":"Miyazaki",
    "iso:country":"JP",
    "wof:name":"444-0513",
    "wof:placetype":"postalcode"
},
  "geometry": {"coordinates":[137.08940000000001,34.7792],"type":"Point"}
}