{
  "type": "Feature",
  "properties": {
    "gn:adm1_name":"Okayamaken",
    "gn:adm2_name":"Bizenshi",
    "gn:name":"Nishikatakami",
    "iso:country":"JP",
    "wof:name":"705-0021",
    "wof:placetype":"postalcode"
},
  "geometry": {"coordinates":[134.1823,34.7449],"type":"Point"}
}