{
  "type": "Feature",
  "properties": {
    "gn:adm1_name":"Gifuken",
    "gn:adm2_name":"Oogakishi",
    "gn:name":"Uchiwara",
    "iso:country":"JP",
    "wof:name":"503-0936",
    "wof:placetype":"postalcode"
},
  "geometry": {"coordinates":[136.61670000000001,35.3178],"type":"Point"}
}