{
  "type": "Feature",
  "properties": {
    "gn:adm1_name":"Shizuokaken",
    "gn:adm2_name":"Inasagunmikkabichou",
    "gn:name":"Ooya",
    "iso:country":"JP",
    "wof:name":"431-1407",
    "wof:placetype":"postalcode"
},
  "geometry": {"coordinates":[137.58840000000001,34.8091],"type":"Point"}
}