{
  "type": "Feature",
  "properties": {
    "gn:adm1_name":"Kanagawaken",
    "gn:adm2_name":"Yokohamashiaobaku",
    "gn:name":"Tsutsujigaoka",
    "iso:country":"JP",
    "wof:name":"227-0055",
    "wof:placetype":"postalcode"
},
  "geometry": {"coordinates":[139.51920000000001,35.5377],"type":"Point"}
}