{
  "type": "Feature",
  "properties": {
    "gn:adm1_name":"Kagawaken",
    "gn:adm2_name":"Takamatsushi",
    "gn:name":"Imajinmachi",
    "iso:country":"JP",
    "wof:name":"760-0043",
    "wof:placetype":"postalcode"
},
  "geometry": {"coordinates":[134.05240000000001,34.344],"type":"Point"}
}