{
  "type": "Feature",
  "properties": {
    "gn:adm1_name":"Tochigiken",
    "gn:adm2_name":"Ashikagashi",
    "gn:name":"Higashisawaragochou",
    "iso:country":"JP",
    "wof:name":"326-0064",
    "wof:placetype":"postalcode"
},
  "geometry": {"coordinates":[139.46369999999999,36.3465],"type":"Point"}
}