{
  "type": "Feature",
  "properties": {
    "gn:adm1_name":"Saitamaken",
    "gn:adm2_name":"Koshigayashi",
    "gn:name":"Nagashima",
    "iso:country":"JP",
    "wof:name":"343-0853",
    "wof:placetype":"postalcode"
},
  "geometry": {"coordinates":[139.7508,35.8839],"type":"Point"}
}