{
  "type": "Feature",
  "properties": {
    "gn:adm1_name":"Hyougoken",
    "gn:adm2_name":"Toyookashi",
    "gn:name":"Kurami",
    "iso:country":"JP",
    "wof:name":"668-0832",
    "wof:placetype":"postalcode"
},
  "geometry": {"coordinates":[134.85560000000001,35.5024],"type":"Point"}
}