{
  "type": "Feature",
  "properties": {
    "gn:adm1_name":"Shigaken",
    "gn:adm2_name":"Oumihachimanshi",
    "gn:name":"Dainakachou",
    "iso:country":"JP",
    "wof:name":"523-0802",
    "wof:placetype":"postalcode"
},
  "geometry": {"coordinates":[136.0977,35.186],"type":"Point"}
}