{
  "type": "Feature",
  "properties": {
    "gn:adm1_name":"Shizuokaken",
    "gn:adm2_name":"Iwatagunfukudechou",
    "gn:name":"Kojima",
    "iso:country":"JP",
    "wof:name":"437-1208",
    "wof:placetype":"postalcode"
},
  "geometry": {"coordinates":[137.8887,34.6892],"type":"Point"}
}