{
  "type": "Feature",
  "properties": {
    "gn:adm1_name":"Hiroshimaken",
    "gn:adm2_name":"Futamigunfunoson",
    "gn:name":"Shimofuno",
    "iso:country":"JP",
    "wof:name":"728-0202",
    "wof:placetype":"postalcode"
},
  "geometry": {"coordinates":[132.79310000000001,34.8623],"type":"Point"}
}