{
  "type": "Feature",
  "properties": {
    "gn:adm1_name":"Chibaken",
    "gn:adm2_name":"Sakurashi",
    "gn:name":"Aosuge",
    "iso:country":"JP",
    "wof:name":"285-0852",
    "wof:placetype":"postalcode"
},
  "geometry": {"coordinates":[140.14879999999999,35.7459],"type":"Point"}
}