{
  "type": "Feature",
  "properties": {
    "gn:adm1_name":"Kyoutofu",
    "gn:adm2_name":"Kyoutoshinakagyouku",
    "gn:name":"Narayachou",
    "iso:country":"JP",
    "wof:name":"604-8033",
    "wof:placetype":"postalcode"
},
  "geometry": {"coordinates":[135.76910000000001,35.0063],"type":"Point"}
}