{
  "type": "Feature",
  "properties": {
    "gn:adm1_name":"Tochigiken",
    "gn:adm2_name":"Utsunomiyashi",
    "gn:name":"Jounan",
    "iso:country":"JP",
    "wof:name":"321-0117",
    "wof:placetype":"postalcode"
},
  "geometry": {"coordinates":[139.88149999999999,36.5141],"type":"Point"}
}