{
  "type": "Feature",
  "properties": {
    "gn:adm1_name":"Tottoriken",
    "gn:adm2_name":"Ketakagunketakachou",
    "gn:name":"Hamamura",
    "iso:country":"JP",
    "wof:name":"689-0331",
    "wof:placetype":"postalcode"
},
  "geometry": {"coordinates":[134.05459999999999,35.514],"type":"Point"}
}