{
  "type": "Feature",
  "properties": {
    "gn:adm1_name":"Fukuokaken",
    "gn:adm2_name":"Ongagunmizumakimachi",
    "gn:name":"Yoshidanishi",
    "iso:country":"JP",
    "wof:name":"807-0046",
    "wof:placetype":"postalcode"
},
  "geometry": {"coordinates":[130.7021,33.8465],"type":"Point"}
}