{
  "type": "Feature",
  "properties": {
    "gn:adm1_name":"Kumamotoken",
    "gn:adm2_name":"Kamimashikigunyabemachi",
    "gn:name":"Ashiyada",
    "iso:country":"JP",
    "wof:name":"861-3541",
    "wof:placetype":"postalcode"
},
  "geometry": {"coordinates":[130.9691,32.6941],"type":"Point"}
}