{
  "type": "Feature",
  "properties": {
    "gn:adm1_name":"Hyougoken",
    "gn:adm2_name":"Nishinomiyashi",
    "gn:name":"Ootanichou",
    "iso:country":"JP",
    "wof:name":"662-0054",
    "wof:placetype":"postalcode"
},
  "geometry": {"coordinates":[135.31960000000001,34.7397],"type":"Point"}
}