{
  "type": "Feature",
  "properties": {
    "gn:adm1_name":"Hyougoken",
    "gn:adm2_name":"Shisougun'Ichinomiyachou",
    "gn:name":"Senchou",
    "iso:country":"JP",
    "wof:name":"671-4108",
    "wof:placetype":"postalcode"
},
  "geometry": {"coordinates":[134.68819999999999,35.1942],"type":"Point"}
}