{
  "type": "Feature",
  "properties": {
    "gn:adm1_name":"Oosakafu",
    "gn:adm2_name":"Oosakashikitaku",
    "gn:name":"Honjounishi",
    "iso:country":"JP",
    "wof:name":"531-0073",
    "wof:placetype":"postalcode"
},
  "geometry": {"coordinates":[135.5052,34.7134],"type":"Point"}
}