{
  "type": "Feature",
  "properties": {
    "gn:adm1_name":"Gunmaken",
    "gn:adm2_name":"Maebashishi",
    "gn:name":"Tsurugayamachi",
    "iso:country":"JP",
    "wof:name":"379-2108",
    "wof:placetype":"postalcode"
},
  "geometry": {"coordinates":[139.16139999999999,36.384],"type":"Point"}
}