{
  "type": "Feature",
  "properties": {
    "gn:adm1_name":"Niigataken",
    "gn:adm2_name":"Iwafunegun'Arakawamachi",
    "gn:name":"Harukiyama",
    "iso:country":"JP",
    "wof:name":"959-3104",
    "wof:placetype":"postalcode"
},
  "geometry": {"coordinates":[139.4623,38.1097],"type":"Point"}
}