{
  "type": "Feature",
  "properties": {
    "gn:adm1_name":"Miyagiken",
    "gn:adm2_name":"Monougunkahokuchou",
    "gn:name":"Nakano",
    "iso:country":"JP",
    "wof:name":"986-0105",
    "wof:placetype":"postalcode"
},
  "geometry": {"coordinates":[141.34979999999999,38.5313],"type":"Point"}
}