{
  "type": "Feature",
  "properties": {
    "gn:adm1_name":"Chibaken",
    "gn:adm2_name":"Katorigunkurimotomachi",
    "gn:name":"Karike",
    "iso:country":"JP",
    "wof:name":"287-0104",
    "wof:placetype":"postalcode"
},
  "geometry": {"coordinates":[140.4992,35.805],"type":"Point"}
}