{
  "type": "Feature",
  "properties": {
    "gn:adm1_name":"Chibaken",
    "gn:adm2_name":"Mobarashi",
    "gn:name":"Chuubu",
    "iso:country":"JP",
    "wof:name":"297-0027",
    "wof:placetype":"postalcode"
},
  "geometry": {"coordinates":[140.28120000000001,35.4323],"type":"Point"}
}