{
  "type": "Feature",
  "properties": {
    "gn:adm1_name":"Shigaken",
    "gn:adm2_name":"Moriyamashi",
    "gn:name":"Tateirichou",
    "iso:country":"JP",
    "wof:name":"524-0031",
    "wof:placetype":"postalcode"
},
  "geometry": {"coordinates":[136.00659999999999,35.0532],"type":"Point"}
}