{
  "type": "Feature",
  "properties": {
    "gn:adm1_name":"Aichiken",
    "gn:adm2_name":"Ichinomiyashi",
    "gn:name":"Mukaiyamaminami",
    "iso:country":"JP",
    "wof:name":"491-0868",
    "wof:placetype":"postalcode"
},
  "geometry": {"coordinates":[136.8091,35.2942],"type":"Point"}
}