{
  "type": "Feature",
  "properties": {
    "gn:adm1_name":"Shigaken",
    "gn:adm2_name":"Nagahamashi",
    "gn:name":"Asahichou",
    "iso:country":"JP",
    "wof:name":"526-0056",
    "wof:placetype":"postalcode"
},
  "geometry": {"coordinates":[136.26900000000001,35.377],"type":"Point"}
}