{
  "type": "Feature",
  "properties": {
    "gn:adm1_name":"Okinawaken",
    "gn:adm2_name":"Shimajirigunkumejimachou",
    "gn:name":"Higa",
    "iso:country":"JP",
    "wof:name":"901-3108",
    "wof:placetype":"postalcode"
},
  "geometry": {"coordinates":[126.801,26.3371],"type":"Point"}
}