{
  "type": "Feature",
  "properties": {
    "gn:adm1_name":"Ishikawaken",
    "gn:adm2_name":"Kanazawashi",
    "gn:name":"Nagatahonmachi",
    "iso:country":"JP",
    "wof:name":"920-0041",
    "wof:placetype":"postalcode"
},
  "geometry": {"coordinates":[136.63919999999999,36.5733],"type":"Point"}
}