{
  "type": "Feature",
  "properties": {
    "gn:adm1_name":"Yamaguchiken",
    "gn:adm2_name":"Shuunanshi",
    "gn:name":"Hanabatakechou",
    "iso:country":"JP",
    "wof:name":"745-0006",
    "wof:placetype":"postalcode"
},
  "geometry": {"coordinates":[131.8109,34.0596],"type":"Point"}
}