{
  "type": "Feature",
  "properties": {
    "gn:adm1_name":"Gifuken",
    "gn:adm2_name":"Gifushi",
    "gn:name":"Mitahora",
    "iso:country":"JP",
    "wof:name":"502-0004",
    "wof:placetype":"postalcode"
},
  "geometry": {"coordinates":[136.78639999999999,35.4771],"type":"Point"}
}