{
  "type": "Feature",
  "properties": {
    "gn:adm1_name":"Aichiken",
    "gn:adm2_name":"Kasugaishi",
    "gn:name":"Takakuradai",
    "iso:country":"JP",
    "wof:name":"487-0017",
    "wof:placetype":"postalcode"
},
  "geometry": {"coordinates":[137.04390000000001,35.2704],"type":"Point"}
}