{
  "type": "Feature",
  "properties": {
    "gn:adm1_name":"Oosakafu",
    "gn:adm2_name":"Hirakatashi",
    "gn:name":"Muranohonmachi",
    "iso:country":"JP",
    "wof:name":"573-0016",
    "wof:placetype":"postalcode"
},
  "geometry": {"coordinates":[135.66759999999999,34.8018],"type":"Point"}
}