{
  "type": "Feature",
  "properties": {
    "gn:adm1_name":"Tottoriken",
    "gn:adm2_name":"Yonagoshi",
    "gn:name":"Indachou",
    "iso:country":"JP",
    "wof:name":"683-0027",
    "wof:placetype":"postalcode"
},
  "geometry": {"coordinates":[133.327,35.4119],"type":"Point"}
}