{
  "type": "Feature",
  "properties": {
    "gn:adm1_name":"Hiroshimaken",
    "gn:adm2_name":"Kureshi",
    "gn:name":"Hirotokumaruchou",
    "iso:country":"JP",
    "wof:name":"737-0102",
    "wof:placetype":"postalcode"
},
  "geometry": {"coordinates":[132.63140000000001,34.2573],"type":"Point"}
}