{
  "type": "Feature",
  "properties": {
    "gn:adm1_name":"Kanagawaken",
    "gn:adm2_name":"Kamakurashi",
    "gn:name":"Takano",
    "iso:country":"JP",
    "wof:name":"247-0054",
    "wof:placetype":"postalcode"
},
  "geometry": {"coordinates":[139.54689999999999,35.3431],"type":"Point"}
}