{
  "type": "Feature",
  "properties": {
    "gn:adm1_name":"Okayamaken",
    "gn:adm2_name":"Okayamashi",
    "gn:name":"Izumida",
    "iso:country":"JP",
    "wof:name":"700-0944",
    "wof:placetype":"postalcode"
},
  "geometry": {"coordinates":[133.91399999999999,34.6266],"type":"Point"}
}