{
  "type": "Feature",
  "properties": {
    "gn:adm1_name":"Kyoutofu",
    "gn:adm2_name":"Kyoutoshiyamashinaku",
    "gn:name":"Otowasawachou",
    "iso:country":"JP",
    "wof:name":"607-8077",
    "wof:placetype":"postalcode"
},
  "geometry": {"coordinates":[135.81960000000001,34.9869],"type":"Point"}
}