{
  "type": "Feature",
  "properties": {
    "gn:adm1_name":"Aichiken",
    "gn:adm2_name":"Bisaishi",
    "gn:name":"Yuuku",
    "iso:country":"JP",
    "wof:name":"494-0017",
    "wof:placetype":"postalcode"
},
  "geometry": {"coordinates":[136.73169999999999,35.2858],"type":"Point"}
}