{
  "type": "Feature",
  "properties": {
    "gn:adm1_name":"Naraken",
    "gn:adm2_name":"Kitakatsuragigunkawaichou",
    "gn:name":"Seiwadai",
    "iso:country":"JP",
    "wof:name":"636-0081",
    "wof:placetype":"postalcode"
},
  "geometry": {"coordinates":[135.71559999999999,34.5859],"type":"Point"}
}