{
  "type": "Feature",
  "properties": {
    "gn:adm1_name":"Tottoriken",
    "gn:adm2_name":"Iwamigun'Iwamichou",
    "gn:name":"Takayama",
    "iso:country":"JP",
    "wof:name":"681-0061",
    "wof:placetype":"postalcode"
},
  "geometry": {"coordinates":[134.34350000000001,35.5656],"type":"Point"}
}