{
  "type": "Feature",
  "properties": {
    "gn:adm1_name":"Kagoshimaken",
    "gn:adm2_name":"Satsumagunmiyanojouchou",
    "gn:name":"Hirakawa",
    "iso:country":"JP",
    "wof:name":"895-1807",
    "wof:placetype":"postalcode"
},
  "geometry": {"coordinates":[130.4119,31.9471],"type":"Point"}
}