{
  "type": "Feature",
  "properties": {
    "gn:adm1_name":"Kumamotoken",
    "gn:adm2_name":"Kumamotoshi",
    "gn:name":"Kamitakahashimachi",
    "iso:country":"JP",
    "wof:name":"860-0061",
    "wof:placetype":"postalcode"
},
  "geometry": {"coordinates":[130.65899999999999,32.787],"type":"Point"}
}