{
  "type": "Feature",
  "properties": {
    "gn:adm1_name":"Aichiken",
    "gn:adm2_name":"Toyokawashi",
    "gn:name":"Sakuragaokachou",
    "iso:country":"JP",
    "wof:name":"442-0064",
    "wof:placetype":"postalcode"
},
  "geometry": {"coordinates":[137.38720000000001,34.8284],"type":"Point"}
}