{
  "type": "Feature",
  "properties": {
    "gn:adm1_name":"Gunmaken",
    "gn:adm2_name":"Tanogunyoshiimachi",
    "gn:name":"Iwai",
    "iso:country":"JP",
    "wof:name":"370-2103",
    "wof:placetype":"postalcode"
},
  "geometry": {"coordinates":[139.0291,36.264],"type":"Point"}
}