{
  "type": "Feature",
  "properties": {
    "gn:adm1_name":"Sagaken",
    "gn:adm2_name":"Imarishi",
    "gn:name":"Hatatsuchoutsurunushiya",
    "iso:country":"JP",
    "wof:name":"848-0114",
    "wof:placetype":"postalcode"
},
  "geometry": {"coordinates":[129.90969999999999,33.3639],"type":"Point"}
}