{
  "type": "Feature",
  "properties": {
    "gn:adm1_name":"Gunmaken",
    "gn:adm2_name":"Ootashi",
    "gn:name":"Naridukachou",
    "iso:country":"JP",
    "wof:name":"373-0006",
    "wof:placetype":"postalcode"
},
  "geometry": {"coordinates":[139.34030000000001,36.3354],"type":"Point"}
}