{
  "type": "Feature",
  "properties": {
    "gn:adm1_name":"Oosakafu",
    "gn:adm2_name":"Higashioosakashi",
    "gn:name":"Shinkenishimachi",
    "iso:country":"JP",
    "wof:name":"577-0028",
    "wof:placetype":"postalcode"
},
  "geometry": {"coordinates":[135.59049999999999,34.6746],"type":"Point"}
}