{
  "type": "Feature",
  "properties": {
    "gn:adm1_name":"Miyagiken",
    "gn:adm2_name":"Kurokawaguntaiwachou",
    "gn:name":"Ono",
    "iso:country":"JP",
    "wof:name":"981-3623",
    "wof:placetype":"postalcode"
},
  "geometry": {"coordinates":[140.85679999999999,38.382],"type":"Point"}
}