{
  "type": "Feature",
  "properties": {
    "gn:adm1_name":"Fukushimaken",
    "gn:adm2_name":"Kitakatashi",
    "gn:name":"Otadukimichishita",
    "iso:country":"JP",
    "wof:name":"966-0813",
    "wof:placetype":"postalcode"
},
  "geometry": {"coordinates":[139.87459999999999,37.6523],"type":"Point"}
}