{
  "type": "Feature",
  "properties": {
    "gn:adm1_name":"Aichiken",
    "gn:adm2_name":"Toyotashi",
    "gn:name":"Koukaichou",
    "iso:country":"JP",
    "wof:name":"444-2221",
    "wof:placetype":"postalcode"
},
  "geometry": {"coordinates":[137.23769999999999,35.0853],"type":"Point"}
}