{
  "type": "Feature",
  "properties": {
    "gn:adm1_name":"Tochigiken",
    "gn:adm2_name":"Nasugunnishinasunomachi",
    "gn:name":"Shinminamigouya",
    "iso:country":"JP",
    "wof:name":"329-2704",
    "wof:placetype":"postalcode"
},
  "geometry": {"coordinates":[139.99459999999999,36.8867],"type":"Point"}
}