{
  "type": "Feature",
  "properties": {
    "gn:adm1_name":"Saitamaken",
    "gn:adm2_name":"Minamisaitamagunmiyashiromachi",
    "gn:name":"Higashikumehara",
    "iso:country":"JP",
    "wof:name":"345-0832",
    "wof:placetype":"postalcode"
},
  "geometry": {"coordinates":[139.703,36.0307],"type":"Point"}
}