{
  "type": "Feature",
  "properties": {
    "gn:adm1_name":"Ehimeken",
    "gn:adm2_name":"Kitauwaguntsushimachou",
    "gn:name":"Magarasu",
    "iso:country":"JP",
    "wof:name":"798-3336",
    "wof:placetype":"postalcode"
},
  "geometry": {"coordinates":[132.46729999999999,33.0593],"type":"Point"}
}