{
  "type": "Feature",
  "properties": {
    "gn:adm1_name":"Gunmaken",
    "gn:adm2_name":"Sawagun'Azumamura",
    "gn:name":"Kamida",
    "iso:country":"JP",
    "wof:name":"379-2225",
    "wof:placetype":"postalcode"
},
  "geometry": {"coordinates":[139.23580000000001,36.3539],"type":"Point"}
}