{
  "type": "Feature",
  "properties": {
    "gn:adm1_name":"Oosakafu",
    "gn:adm2_name":"Higashioosakashi",
    "gn:name":"Minamishijouchou",
    "iso:country":"JP",
    "wof:name":"579-8054",
    "wof:placetype":"postalcode"
},
  "geometry": {"coordinates":[135.64240000000001,34.6571],"type":"Point"}
}