{
  "type": "Feature",
  "properties": {
    "gn:adm1_name":"Shizuokaken",
    "gn:adm2_name":"Shuuchigunharunochou",
    "gn:name":"Omatakyoumaru",
    "iso:country":"JP",
    "wof:name":"437-0608",
    "wof:placetype":"postalcode"
},
  "geometry": {"coordinates":[137.73339999999999,34.7543],"type":"Point"}
}