{
  "type": "Feature",
  "properties": {
    "gn:adm1_name":"Ishikawaken",
    "gn:adm2_name":"Ishikawagunmikawamachi",
    "gn:name":"Wakakusamachi",
    "iso:country":"JP",
    "wof:name":"929-0203",
    "wof:placetype":"postalcode"
},
  "geometry": {"coordinates":[136.56800000000001,36.4849],"type":"Point"}
}