{
  "type": "Feature",
  "properties": {
    "gn:adm1_name":"Ehimeken",
    "gn:adm2_name":"Imabarishi",
    "gn:name":"Gouzakurai",
    "iso:country":"JP",
    "wof:name":"799-1523",
    "wof:placetype":"postalcode"
},
  "geometry": {"coordinates":[133.0377,34.0148],"type":"Point"}
}