{
  "type": "Feature",
  "properties": {
    "gn:adm1_name":"Yamanashiken",
    "gn:adm2_name":"Higashiyatsushirogunyatsushirochou",
    "gn:name":"Kouka",
    "iso:country":"JP",
    "wof:name":"406-0831",
    "wof:placetype":"postalcode"
},
  "geometry": {"coordinates":[138.65430000000001,35.6099],"type":"Point"}
}