{
  "type": "Feature",
  "properties": {
    "gn:adm1_name":"Ehimeken",
    "gn:adm2_name":"Minamiuwagunjouhenchou",
    "gn:name":"Midorikou",
    "iso:country":"JP",
    "wof:name":"798-4134",
    "wof:placetype":"postalcode"
},
  "geometry": {"coordinates":[132.6086,32.9798],"type":"Point"}
}