{
  "type": "Feature",
  "properties": {
    "gn:adm1_name":"Kyoutofu",
    "gn:adm2_name":"Fukuchiyamashi",
    "gn:name":"Komaki",
    "iso:country":"JP",
    "wof:name":"620-0972",
    "wof:placetype":"postalcode"
},
  "geometry": {"coordinates":[135.02189999999999,35.2921],"type":"Point"}
}