{
  "type": "Feature",
  "properties": {
    "gn:adm1_name":"Kyoutofu",
    "gn:adm2_name":"Takenoguntangochou",
    "gn:name":"Takano",
    "iso:country":"JP",
    "wof:name":"627-0221",
    "wof:placetype":"postalcode"
},
  "geometry": {"coordinates":[135.1122,35.7423],"type":"Point"}
}