{
  "type": "Feature",
  "properties": {
    "gn:adm1_name":"Gifuken",
    "gn:adm2_name":"Sekishi",
    "gn:name":"Ueno",
    "iso:country":"JP",
    "wof:name":"501-3951",
    "wof:placetype":"postalcode"
},
  "geometry": {"coordinates":[136.85120000000001,35.4992],"type":"Point"}
}