{
  "type": "Feature",
  "properties": {
    "gn:adm1_name":"Okayamaken",
    "gn:adm2_name":"Tsuyamashi",
    "gn:name":"Uryuubara",
    "iso:country":"JP",
    "wof:name":"708-0844",
    "wof:placetype":"postalcode"
},
  "geometry": {"coordinates":[134.04140000000001,35.0389],"type":"Point"}
}