{
  "type": "Feature",
  "properties": {
    "gn:adm1_name":"Fukuokaken",
    "gn:adm2_name":"Fukuokashinishiku",
    "gn:name":"Tajiri",
    "iso:country":"JP",
    "wof:name":"819-0383",
    "wof:placetype":"postalcode"
},
  "geometry": {"coordinates":[130.24789999999999,33.5833],"type":"Point"}
}