{
  "type": "Feature",
  "properties": {
    "gn:adm1_name":"Gunmaken",
    "gn:adm2_name":"Numatashi",
    "gn:name":"Usunemachi",
    "iso:country":"JP",
    "wof:name":"378-0031",
    "wof:placetype":"postalcode"
},
  "geometry": {"coordinates":[139.0333,36.643],"type":"Point"}
}