{
  "type": "Feature",
  "properties": {
    "gn:adm1_name":"Shigaken",
    "gn:adm2_name":"Inukamigunkourachou",
    "gn:name":"Kitaochi",
    "iso:country":"JP",
    "wof:name":"522-0251",
    "wof:placetype":"postalcode"
},
  "geometry": {"coordinates":[136.2713,35.2071],"type":"Point"}
}