{
  "type": "Feature",
  "properties": {
    "gn:adm1_name":"Kyoutofu",
    "gn:adm2_name":"Kyoutoshiyamashinaku",
    "gn:name":"Ooyakeishigoori",
    "iso:country":"JP",
    "wof:name":"607-8187",
    "wof:placetype":"postalcode"
},
  "geometry": {"coordinates":[135.81620000000001,34.9654],"type":"Point"}
}