{
  "type": "Feature",
  "properties": {
    "gn:adm1_name":"Fukuokaken",
    "gn:adm2_name":"Ongagun'Okagakimachi",
    "gn:name":"Asahidai",
    "iso:country":"JP",
    "wof:name":"811-4215",
    "wof:placetype":"postalcode"
},
  "geometry": {"coordinates":[130.6206,33.8563],"type":"Point"}
}