{
  "type": "Feature",
  "properties": {
    "gn:adm1_name":"Gifuken",
    "gn:adm2_name":"Anpachigun'Anpachichou",
    "gn:name":"Minamijou",
    "iso:country":"JP",
    "wof:name":"503-0123",
    "wof:placetype":"postalcode"
},
  "geometry": {"coordinates":[136.66059999999999,35.3188],"type":"Point"}
}