{
  "type": "Feature",
  "properties": {
    "gn:adm1_name":"Shimaneken",
    "gn:adm2_name":"Minogunhikimichou",
    "gn:name":"Sumikawa",
    "iso:country":"JP",
    "wof:name":"698-1221",
    "wof:placetype":"postalcode"
},
  "geometry": {"coordinates":[131.9512,34.6022],"type":"Point"}
}