{
  "type": "Feature",
  "properties": {
    "gn:adm1_name":"Gifuken",
    "gn:adm2_name":"Hashimagunginanchou",
    "gn:name":"Fuseya",
    "iso:country":"JP",
    "wof:name":"501-6006",
    "wof:placetype":"postalcode"
},
  "geometry": {"coordinates":[136.79069999999999,35.3831],"type":"Point"}
}