{
  "type": "Feature",
  "properties": {
    "gn:adm1_name":"Saitamaken",
    "gn:adm2_name":"Minamisaitamagunmiyashiromachi",
    "gn:name":"Nishikumehara",
    "iso:country":"JP",
    "wof:name":"345-0833",
    "wof:placetype":"postalcode"
},
  "geometry": {"coordinates":[139.6925,36.0353],"type":"Point"}
}