{
  "type": "Feature",
  "properties": {
    "gn:adm1_name":"Hiroshimaken",
    "gn:adm2_name":"Hiroshimashiasaminamiku",
    "gn:name":"Midorii",
    "iso:country":"JP",
    "wof:name":"731-0103",
    "wof:placetype":"postalcode"
},
  "geometry": {"coordinates":[132.47730000000001,34.4704],"type":"Point"}
}