{
  "type": "Feature",
  "properties": {
    "gn:adm1_name":"Gunmaken",
    "gn:adm2_name":"Agatsumaguntsumagoimura",
    "gn:name":"Kanbara(Ookaishiko)",
    "iso:country":"JP",
    "wof:name":"377-1404",
    "wof:placetype":"postalcode"
},
  "geometry": {"coordinates":[138.56829999999999,36.4557],"type":"Point"}
}