{
  "type": "Feature",
  "properties": {
    "gn:adm1_name":"Hyougoken",
    "gn:adm2_name":"Sasayamashi",
    "gn:name":"Soujinaka",
    "iso:country":"JP",
    "wof:name":"669-2443",
    "wof:placetype":"postalcode"
},
  "geometry": {"coordinates":[135.28380000000001,35.0543],"type":"Point"}
}