{
  "type": "Feature",
  "properties": {
    "gn:adm1_name":"Fukushimaken",
    "gn:adm2_name":"Shirakawashi",
    "gn:name":"Usuba",
    "iso:country":"JP",
    "wof:name":"961-0063",
    "wof:placetype":"postalcode"
},
  "geometry": {"coordinates":[140.2209,37.1391],"type":"Point"}
}