{
  "type": "Feature",
  "properties": {
    "gn:adm1_name":"Wakayamaken",
    "gn:adm2_name":"Hidakagun'Inamichou",
    "gn:name":"Nishikounogawa",
    "iso:country":"JP",
    "wof:name":"644-0213",
    "wof:placetype":"postalcode"
},
  "geometry": {"coordinates":[135.304,33.8809],"type":"Point"}
}