{
  "type": "Feature",
  "properties": {
    "gn:adm1_name":"Ibarakiken",
    "gn:adm2_name":"Higashiibarakigun'Ibarakimachi",
    "gn:name":"Nakaishizaki",
    "iso:country":"JP",
    "wof:name":"311-3124",
    "wof:placetype":"postalcode"
},
  "geometry": {"coordinates":[140.48849999999999,36.2876],"type":"Point"}
}