{
  "type": "Feature",
  "properties": {
    "gn:adm1_name":"Tochigiken",
    "gn:adm2_name":"Hagagunmashikomachi",
    "gn:name":"Hanawa",
    "iso:country":"JP",
    "wof:name":"321-4216",
    "wof:placetype":"postalcode"
},
  "geometry": {"coordinates":[140.0772,36.475],"type":"Point"}
}