{
  "type": "Feature",
  "properties": {
    "gn:adm1_name":"Fukuokaken",
    "gn:adm2_name":"Miyakogunkandamachi",
    "gn:name":"Jindenchou",
    "iso:country":"JP",
    "wof:name":"800-0361",
    "wof:placetype":"postalcode"
},
  "geometry": {"coordinates":[130.97980000000001,33.7896],"type":"Point"}
}