{
  "type": "Feature",
  "properties": {
    "gn:adm1_name":"Chibaken",
    "gn:adm2_name":"Chibashiinageku",
    "gn:name":"Inagechou",
    "iso:country":"JP",
    "wof:name":"263-0035",
    "wof:placetype":"postalcode"
},
  "geometry": {"coordinates":[140.08109999999999,35.6426],"type":"Point"}
}