{
  "type": "Feature",
  "properties": {
    "gn:adm1_name":"Saitamaken",
    "gn:adm2_name":"Saitamashinishiku",
    "gn:name":"Sashiougi",
    "iso:country":"JP",
    "wof:name":"331-0047",
    "wof:placetype":"postalcode"
},
  "geometry": {"coordinates":[139.57769999999999,35.9152],"type":"Point"}
}