{
  "type": "Feature",
  "properties": {
    "gn:adm1_name":"Gifuken",
    "gn:adm2_name":"Hashimagunkawashimachou",
    "gn:name":"Watarimachi",
    "iso:country":"JP",
    "wof:name":"501-6028",
    "wof:placetype":"postalcode"
},
  "geometry": {"coordinates":[136.81110000000001,35.3623],"type":"Point"}
}