{
  "type": "Feature",
  "properties": {
    "gn:adm1_name":"Aichiken",
    "gn:adm2_name":"Nagoyashimeitouku",
    "gn:name":"Takayanagichou",
    "iso:country":"JP",
    "wof:name":"465-0034",
    "wof:placetype":"postalcode"
},
  "geometry": {"coordinates":[137.01480000000001,35.1841],"type":"Point"}
}