{
  "type": "Feature",
  "properties": {
    "gn:adm1_name":"Kouchiken",
    "gn:adm2_name":"Tosashimizushi",
    "gn:name":"Shimonokae",
    "iso:country":"JP",
    "wof:name":"787-0242",
    "wof:placetype":"postalcode"
},
  "geometry": {"coordinates":[132.94739999999999,32.874],"type":"Point"}
}