{
  "type": "Feature",
  "properties": {
    "gn:adm1_name":"Kyoutofu",
    "gn:adm2_name":"Kyoutoshikitaku",
    "gn:name":"Koyamakitagen'Ichou",
    "iso:country":"JP",
    "wof:name":"603-8103",
    "wof:placetype":"postalcode"
},
  "geometry": {"coordinates":[135.75450000000001,35.0526],"type":"Point"}
}