{
  "type": "Feature",
  "properties": {
    "gn:adm1_name":"Kagoshimaken",
    "gn:adm2_name":"Kagoshimashi",
    "gn:name":"Seiwa",
    "iso:country":"JP",
    "wof:name":"891-0109",
    "wof:placetype":"postalcode"
},
  "geometry": {"coordinates":[130.51300000000001,31.5364],"type":"Point"}
}