{
  "type": "Feature",
  "properties": {
    "gn:adm1_name":"Ooitaken",
    "gn:adm2_name":"Ooitashi",
    "gn:name":"Keyakidai",
    "iso:country":"JP",
    "wof:name":"879-7762",
    "wof:placetype":"postalcode"
},
  "geometry": {"coordinates":[131.67339999999999,33.1543],"type":"Point"}
}