{
  "type": "Feature",
  "properties": {
    "gn:adm1_name":"Kagawaken",
    "gn:adm2_name":"Marugameshi",
    "gn:name":"Iinochounishibun",
    "iso:country":"JP",
    "wof:name":"763-0086",
    "wof:placetype":"postalcode"
},
  "geometry": {"coordinates":[133.82859999999999,34.2824],"type":"Point"}
}