{
  "type": "Feature",
  "properties": {
    "gn:adm1_name":"Hiroshimaken",
    "gn:adm2_name":"Miharashi",
    "gn:name":"Nakanochou",
    "iso:country":"JP",
    "wof:name":"723-0003",
    "wof:placetype":"postalcode"
},
  "geometry": {"coordinates":[133.10319999999999,34.4152],"type":"Point"}
}