{
  "type": "Feature",
  "properties": {
    "gn:adm1_name":"Miyagiken",
    "gn:adm2_name":"Sendaishiwakabayashiku",
    "gn:name":"Motochabatake",
    "iso:country":"JP",
    "wof:name":"984-0058",
    "wof:placetype":"postalcode"
},
  "geometry": {"coordinates":[140.89089999999999,38.2496],"type":"Point"}
}