{
  "type": "Feature",
  "properties": {
    "gn:adm1_name":"Aichiken",
    "gn:adm2_name":"Inazawashi",
    "gn:name":"Ishikimichikamichou",
    "iso:country":"JP",
    "wof:name":"492-8357",
    "wof:placetype":"postalcode"
},
  "geometry": {"coordinates":[136.75200000000001,35.2439],"type":"Point"}
}