{
  "type": "Feature",
  "properties": {
    "gn:adm1_name":"Hyougoken",
    "gn:adm2_name":"Koubeshinadaku",
    "gn:name":"Rokkousanchou",
    "iso:country":"JP",
    "wof:name":"657-0101",
    "wof:placetype":"postalcode"
},
  "geometry": {"coordinates":[135.23269999999999,34.7567],"type":"Point"}
}