{
  "type": "Feature",
  "properties": {
    "gn:adm1_name":"Chibaken",
    "gn:adm2_name":"Matsudoshi",
    "gn:name":"Higashihiraga",
    "iso:country":"JP",
    "wof:name":"270-0003",
    "wof:placetype":"postalcode"
},
  "geometry": {"coordinates":[139.93430000000001,35.8348],"type":"Point"}
}