{
  "type": "Feature",
  "properties": {
    "gn:adm1_name":"Aichiken",
    "gn:adm2_name":"Gamagoorishi",
    "gn:name":"Matsubarachou",
    "iso:country":"JP",
    "wof:name":"443-0033",
    "wof:placetype":"postalcode"
},
  "geometry": {"coordinates":[137.23220000000001,34.8198],"type":"Point"}
}