{
  "type": "Feature",
  "properties": {
    "gn:adm1_name":"Ehimeken",
    "gn:adm2_name":"Ochigunyugechou",
    "gn:name":"Kario",
    "iso:country":"JP",
    "wof:name":"794-2512",
    "wof:placetype":"postalcode"
},
  "geometry": {"coordinates":[133.21960000000001,34.2673],"type":"Point"}
}