{
  "type": "Feature",
  "properties": {
    "gn:adm1_name":"Hyougoken",
    "gn:adm2_name":"Kakogun'Inamichou",
    "gn:name":"Takokusa",
    "iso:country":"JP",
    "wof:name":"675-1116",
    "wof:placetype":"postalcode"
},
  "geometry": {"coordinates":[134.9342,34.7488],"type":"Point"}
}