{
  "type": "Feature",
  "properties": {
    "gn:adm1_name":"Aichiken",
    "gn:adm2_name":"Toyoakeshi",
    "gn:name":"Magomechou(Tsurune)",
    "iso:country":"JP",
    "wof:name":"470-1133",
    "wof:placetype":"postalcode"
},
  "geometry": {"coordinates":[136.99690000000001,35.0655],"type":"Point"}
}