{
  "type": "Feature",
  "properties": {
    "gn:adm1_name":"Hyougoken",
    "gn:adm2_name":"Asagogunwadayamachou",
    "gn:name":"Ikanikeisaiganaibaai",
    "iso:country":"JP",
    "wof:name":"669-5200",
    "wof:placetype":"postalcode"
},
  "geometry": {"coordinates":[134.84289999999999,35.3565],"type":"Point"}
}