{
  "type": "Feature",
  "properties": {
    "gn:adm1_name":"Shimaneken",
    "gn:adm2_name":"Nakagunyasakamura",
    "gn:name":"Tanohara",
    "iso:country":"JP",
    "wof:name":"697-1123",
    "wof:placetype":"postalcode"
},
  "geometry": {"coordinates":[132.0719,34.7207],"type":"Point"}
}