{
  "type": "Feature",
  "properties": {
    "gn:adm1_name":"Gifuken",
    "gn:adm2_name":"Ibigun'Ibigawachou",
    "gn:name":"Shinguu",
    "iso:country":"JP",
    "wof:name":"501-0628",
    "wof:placetype":"postalcode"
},
  "geometry": {"coordinates":[136.55000000000001,35.4771],"type":"Point"}
}