{
  "type": "Feature",
  "properties": {
    "gn:adm1_name":"Chibaken",
    "gn:adm2_name":"Sanbugunkujuukurimachi",
    "gn:name":"Tanakaaraoi",
    "iso:country":"JP",
    "wof:name":"283-0103",
    "wof:placetype":"postalcode"
},
  "geometry": {"coordinates":[140.4402,35.541],"type":"Point"}
}