{
  "type": "Feature",
  "properties": {
    "gn:adm1_name":"Hyougoken",
    "gn:adm2_name":"Nishinomiyashi",
    "gn:name":"Jougaborichou",
    "iso:country":"JP",
    "wof:name":"662-0856",
    "wof:placetype":"postalcode"
},
  "geometry": {"coordinates":[135.34020000000001,34.7422],"type":"Point"}
}