{
  "type": "Feature",
  "properties": {
    "gn:adm1_name":"Shigaken",
    "gn:adm2_name":"Oumihachimanshi",
    "gn:name":"Goshouchichou",
    "iso:country":"JP",
    "wof:name":"523-0003",
    "wof:placetype":"postalcode"
},
  "geometry": {"coordinates":[136.1328,35.1216],"type":"Point"}
}