{
  "type": "Feature",
  "properties": {
    "gn:adm1_name":"Miyazakiken",
    "gn:adm2_name":"Minaminakagunnangouchou",
    "gn:name":"Tsuyano",
    "iso:country":"JP",
    "wof:name":"889-3201",
    "wof:placetype":"postalcode"
},
  "geometry": {"coordinates":[131.35499999999999,31.5474],"type":"Point"}
}