{
  "type": "Feature",
  "properties": {
    "gn:adm1_name":"Fukuokaken",
    "gn:adm2_name":"Miikeguntakatamachi",
    "gn:name":"Imabuku",
    "iso:country":"JP",
    "wof:name":"839-0214",
    "wof:placetype":"postalcode"
},
  "geometry": {"coordinates":[130.46279999999999,33.11],"type":"Point"}
}