{
  "type": "Feature",
  "properties": {
    "gn:adm1_name":"Yamaguchiken",
    "gn:adm2_name":"Ubeshi",
    "gn:name":"Higashihonmachi",
    "iso:country":"JP",
    "wof:name":"755-0028",
    "wof:placetype":"postalcode"
},
  "geometry": {"coordinates":[131.24719999999999,33.9479],"type":"Point"}
}