{
  "type": "Feature",
  "properties": {
    "gn:adm1_name":"Ooitaken",
    "gn:adm2_name":"Saikishi",
    "gn:name":"Tokiwaminamimachi",
    "iso:country":"JP",
    "wof:name":"876-0852",
    "wof:placetype":"postalcode"
},
  "geometry": {"coordinates":[131.9015,32.9632],"type":"Point"}
}