{
  "type": "Feature",
  "properties": {
    "gn:adm1_name":"Oosakafu",
    "gn:adm2_name":"Higashioosakashi",
    "gn:name":"Nagatahigashi",
    "iso:country":"JP",
    "wof:name":"577-0012",
    "wof:placetype":"postalcode"
},
  "geometry": {"coordinates":[135.59379999999999,34.6806],"type":"Point"}
}