{
  "type": "Feature",
  "properties": {
    "gn:adm1_name":"Aichiken",
    "gn:adm2_name":"Hekinanshi",
    "gn:name":"Tamatsuuramachi",
    "iso:country":"JP",
    "wof:name":"447-0834",
    "wof:placetype":"postalcode"
},
  "geometry": {"coordinates":[136.96539999999999,34.8625],"type":"Point"}
}