{
  "type": "Feature",
  "properties": {
    "gn:adm1_name":"Yamagataken",
    "gn:adm2_name":"Kitamurayamagun'Ooishidamachi",
    "gn:name":"Yokoyama",
    "iso:country":"JP",
    "wof:name":"999-4121",
    "wof:placetype":"postalcode"
},
  "geometry": {"coordinates":[140.3725,38.5808],"type":"Point"}
}