{
  "type": "Feature",
  "properties": {
    "gn:adm1_name":"Kyoutofu",
    "gn:adm2_name":"Jouyoushi",
    "gn:name":"Nagaike",
    "iso:country":"JP",
    "wof:name":"610-0112",
    "wof:placetype":"postalcode"
},
  "geometry": {"coordinates":[135.79570000000001,34.8408],"type":"Point"}
}