{
  "type": "Feature",
  "properties": {
    "gn:adm1_name":"Miyagiken",
    "gn:adm2_name":"Kakudashi",
    "gn:name":"Hanashima",
    "iso:country":"JP",
    "wof:name":"981-1511",
    "wof:placetype":"postalcode"
},
  "geometry": {"coordinates":[140.77430000000001,38.0037],"type":"Point"}
}