{
  "type": "Feature",
  "properties": {
    "gn:adm1_name":"Aichiken",
    "gn:adm2_name":"Handashi",
    "gn:name":"Kitaooyachichou",
    "iso:country":"JP",
    "wof:name":"475-0008",
    "wof:placetype":"postalcode"
},
  "geometry": {"coordinates":[136.94,34.9339],"type":"Point"}
}