{
  "type": "Feature",
  "properties": {
    "gn:adm1_name":"Hyougoken",
    "gn:adm2_name":"Shikamagunyumesakichou",
    "gn:name":"Kochinoshou",
    "iso:country":"JP",
    "wof:name":"671-2113",
    "wof:placetype":"postalcode"
},
  "geometry": {"coordinates":[134.67949999999999,34.9464],"type":"Point"}
}