{
  "type": "Feature",
  "properties": {
    "gn:adm1_name":"Fukuokaken",
    "gn:adm2_name":"Oomutashi",
    "gn:name":"Ichinouramachi",
    "iso:country":"JP",
    "wof:name":"836-0863",
    "wof:placetype":"postalcode"
},
  "geometry": {"coordinates":[130.44980000000001,33.0248],"type":"Point"}
}