{
  "type": "Feature",
  "properties": {
    "gn:adm1_name":"Niigataken",
    "gn:adm2_name":"Niigatashi",
    "gn:name":"Aoyamashinmachi",
    "iso:country":"JP",
    "wof:name":"950-2006",
    "wof:placetype":"postalcode"
},
  "geometry": {"coordinates":[138.99930000000001,37.896],"type":"Point"}
}