{
  "type": "Feature",
  "properties": {
    "gn:adm1_name":"Yamagataken",
    "gn:adm2_name":"Sagaeshi",
    "gn:name":"Takada",
    "iso:country":"JP",
    "wof:name":"991-0013",
    "wof:placetype":"postalcode"
},
  "geometry": {"coordinates":[140.2868,38.3686],"type":"Point"}
}