{
  "type": "Feature",
  "properties": {
    "gn:adm1_name":"Aichiken",
    "gn:adm2_name":"Toyotashi",
    "gn:name":"Umetsubochou",
    "iso:country":"JP",
    "wof:name":"471-0064",
    "wof:placetype":"postalcode"
},
  "geometry": {"coordinates":[137.16139999999999,35.1011],"type":"Point"}
}