{
  "type": "Feature",
  "properties": {
    "gn:adm1_name":"Niigataken",
    "gn:adm2_name":"Niigatashi",
    "gn:name":"Irifunechou",
    "iso:country":"JP",
    "wof:name":"951-8011",
    "wof:placetype":"postalcode"
},
  "geometry": {"coordinates":[139.05760000000001,37.9351],"type":"Point"}
}