{
  "type": "Feature",
  "properties": {
    "gn:adm1_name":"Okinawaken",
    "gn:adm2_name":"Nagoshi",
    "gn:name":"Nago",
    "iso:country":"JP",
    "wof:name":"905-0012",
    "wof:placetype":"postalcode"
},
  "geometry": {"coordinates":[127.99469999999999,26.6011],"type":"Point"}
}