{
  "type": "Feature",
  "properties": {
    "gn:adm1_name":"Tochigiken",
    "gn:adm2_name":"Ashikagashi",
    "gn:name":"Itakurachou",
    "iso:country":"JP",
    "wof:name":"326-0102",
    "wof:placetype":"postalcode"
},
  "geometry": {"coordinates":[139.40880000000001,36.3747],"type":"Point"}
}