{
  "type": "Feature",
  "properties": {
    "gn:adm1_name":"Niigataken",
    "gn:adm2_name":"Kitauonumagunsumonmura",
    "gn:name":"Mifuchisawa",
    "iso:country":"JP",
    "wof:name":"946-0225",
    "wof:placetype":"postalcode"
},
  "geometry": {"coordinates":[138.99969999999999,37.3027],"type":"Point"}
}