{
  "type": "Feature",
  "properties": {
    "gn:adm1_name":"Kyoutofu",
    "gn:adm2_name":"Kameokashi",
    "gn:name":"Nishitsutsujigaokakirishimadai",
    "iso:country":"JP",
    "wof:name":"621-0844",
    "wof:placetype":"postalcode"
},
  "geometry": {"coordinates":[135.58709999999999,34.9987],"type":"Point"}
}