{
  "type": "Feature",
  "properties": {
    "gn:adm1_name":"Ishikawaken",
    "gn:adm2_name":"Komatsushi",
    "gn:name":"Hanatatemachi",
    "iso:country":"JP",
    "wof:name":"923-0174",
    "wof:placetype":"postalcode"
},
  "geometry": {"coordinates":[136.5333,36.2137],"type":"Point"}
}