{
  "type": "Feature",
  "properties": {
    "gn:adm1_name":"Tochigiken",
    "gn:adm2_name":"Sanoshi",
    "gn:name":"Inubushishinmachi",
    "iso:country":"JP",
    "wof:name":"327-0803",
    "wof:placetype":"postalcode"
},
  "geometry": {"coordinates":[139.60489999999999,36.3248],"type":"Point"}
}