{
  "type": "Feature",
  "properties": {
    "gn:adm1_name":"Yamagataken",
    "gn:adm2_name":"Kaminoyamashi",
    "gn:name":"Narage",
    "iso:country":"JP",
    "wof:name":"999-3225",
    "wof:placetype":"postalcode"
},
  "geometry": {"coordinates":[140.30629999999999,38.093],"type":"Point"}
}