{
  "type": "Feature",
  "properties": {
    "gn:adm1_name":"Mieken",
    "gn:adm2_name":"Miegunkusuchou",
    "gn:name":"Ogura",
    "iso:country":"JP",
    "wof:name":"510-0101",
    "wof:placetype":"postalcode"
},
  "geometry": {"coordinates":[136.62979999999999,34.9225],"type":"Point"}
}