{
  "type": "Feature",
  "properties": {
    "gn:adm1_name":"Chibaken",
    "gn:adm2_name":"Choushishi",
    "gn:name":"Miyaharachou",
    "iso:country":"JP",
    "wof:name":"288-0877",
    "wof:placetype":"postalcode"
},
  "geometry": {"coordinates":[140.71250000000001,35.8059],"type":"Point"}
}