{
  "type": "Feature",
  "properties": {
    "gn:adm1_name":"Aichiken",
    "gn:adm2_name":"Nagoyashimizuhoku",
    "gn:name":"Daigishinchou",
    "iso:country":"JP",
    "wof:name":"467-0868",
    "wof:placetype":"postalcode"
},
  "geometry": {"coordinates":[136.92349999999999,35.1268],"type":"Point"}
}