{
  "type": "Feature",
  "properties": {
    "gn:adm1_name":"Niigataken",
    "gn:adm2_name":"Kariwagun'Ogunimachi",
    "gn:name":"Yokosawa",
    "iso:country":"JP",
    "wof:name":"949-5222",
    "wof:placetype":"postalcode"
},
  "geometry": {"coordinates":[138.70179999999999,37.3059],"type":"Point"}
}