{
  "type": "Feature",
  "properties": {
    "gn:adm1_name":"Nagasakiken",
    "gn:adm2_name":"Isahayashi",
    "gn:name":"Hirayamachou",
    "iso:country":"JP",
    "wof:name":"854-0057",
    "wof:placetype":"postalcode"
},
  "geometry": {"coordinates":[130.03559999999999,32.8294],"type":"Point"}
}