{
  "type": "Feature",
  "properties": {
    "gn:adm1_name":"Fukuokaken",
    "gn:adm2_name":"Kitakyuushuushitobataku",
    "gn:name":"Ginza",
    "iso:country":"JP",
    "wof:name":"804-0076",
    "wof:placetype":"postalcode"
},
  "geometry": {"coordinates":[130.81829999999999,33.899],"type":"Point"}
}