{
  "type": "Feature",
  "properties": {
    "gn:adm1_name":"Fukushimaken",
    "gn:adm2_name":"Shirakawashi",
    "gn:name":"Rokutanyama",
    "iso:country":"JP",
    "wof:name":"961-0092",
    "wof:placetype":"postalcode"
},
  "geometry": {"coordinates":[140.2167,37.1417],"type":"Point"}
}