{
  "type": "Feature",
  "properties": {
    "gn:adm1_name":"Kyoutofu",
    "gn:adm2_name":"Maidurushi",
    "gn:name":"Sugiyama",
    "iso:country":"JP",
    "wof:name":"625-0001",
    "wof:placetype":"postalcode"
},
  "geometry": {"coordinates":[135.46270000000001,35.5063],"type":"Point"}
}