{
  "type": "Feature",
  "properties": {
    "gn:adm1_name":"Miyagiken",
    "gn:adm2_name":"Sendaishimiyaginoku",
    "gn:name":"Higashi9banchou",
    "iso:country":"JP",
    "wof:name":"983-0856",
    "wof:placetype":"postalcode"
},
  "geometry": {"coordinates":[140.88939999999999,38.2618],"type":"Point"}
}