{
  "type": "Feature",
  "properties": {
    "gn:adm1_name":"Ehimeken",
    "gn:adm2_name":"Kitauwagunhiromichou",
    "gn:name":"Hiromi",
    "iso:country":"JP",
    "wof:name":"798-1303",
    "wof:placetype":"postalcode"
},
  "geometry": {"coordinates":[132.72069999999999,33.2991],"type":"Point"}
}