{
  "type": "Feature",
  "properties": {
    "gn:adm1_name":"Chibaken",
    "gn:adm2_name":"Sodegaurashi",
    "gn:name":"Oodake",
    "iso:country":"JP",
    "wof:name":"299-0221",
    "wof:placetype":"postalcode"
},
  "geometry": {"coordinates":[140.01519999999999,35.3658],"type":"Point"}
}