{
  "type": "Feature",
  "properties": {
    "gn:adm1_name":"Mieken",
    "gn:adm2_name":"Uenoshi",
    "gn:name":"Hokke",
    "iso:country":"JP",
    "wof:name":"518-0036",
    "wof:placetype":"postalcode"
},
  "geometry": {"coordinates":[136.08510000000001,34.7403],"type":"Point"}
}