{
  "type": "Feature",
  "properties": {
    "gn:adm1_name":"Aichiken",
    "gn:adm2_name":"Amagunjimokujichou",
    "gn:name":"Sakae",
    "iso:country":"JP",
    "wof:name":"490-1103",
    "wof:placetype":"postalcode"
},
  "geometry": {"coordinates":[136.8366,35.2039],"type":"Point"}
}