{
  "type": "Feature",
  "properties": {
    "gn:adm1_name":"Fukuiken",
    "gn:adm2_name":"Nanjougunkounomura",
    "gn:name":"Imaizumi",
    "iso:country":"JP",
    "wof:name":"915-1112",
    "wof:placetype":"postalcode"
},
  "geometry": {"coordinates":[136.06530000000001,35.8299],"type":"Point"}
}