{
  "type": "Feature",
  "properties": {
    "gn:adm1_name":"Tokushimaken",
    "gn:adm2_name":"Tokushimashi",
    "gn:name":"Yamashironishi",
    "iso:country":"JP",
    "wof:name":"770-8054",
    "wof:placetype":"postalcode"
},
  "geometry": {"coordinates":[134.55609999999999,34.0502],"type":"Point"}
}