{
  "type": "Feature",
  "properties": {
    "gn:adm1_name":"Miyagiken",
    "gn:adm2_name":"Ishinomakishi",
    "gn:name":"Kawaguchichou",
    "iso:country":"JP",
    "wof:name":"986-0024",
    "wof:placetype":"postalcode"
},
  "geometry": {"coordinates":[141.31540000000001,38.4206],"type":"Point"}
}