{
  "type": "Feature",
  "properties": {
    "gn:adm1_name":"Oosakafu",
    "gn:adm2_name":"Settsushi",
    "gn:name":"Torikaihacchou",
    "iso:country":"JP",
    "wof:name":"566-0061",
    "wof:placetype":"postalcode"
},
  "geometry": {"coordinates":[135.58760000000001,34.7903],"type":"Point"}
}