{
  "type": "Feature",
  "properties": {
    "gn:adm1_name":"Chibaken",
    "gn:adm2_name":"Yachiyoshi",
    "gn:name":"Kannou",
    "iso:country":"JP",
    "wof:name":"276-0006",
    "wof:placetype":"postalcode"
},
  "geometry": {"coordinates":[140.09909999999999,35.7551],"type":"Point"}
}