{
  "type": "Feature",
  "properties": {
    "gn:adm1_name":"Hiroshimaken",
    "gn:adm2_name":"Hiroshimashinishiku",
    "gn:name":"Shinjouchou",
    "iso:country":"JP",
    "wof:name":"733-0801",
    "wof:placetype":"postalcode"
},
  "geometry": {"coordinates":[132.45150000000001,34.4244],"type":"Point"}
}