{
  "type": "Feature",
  "properties": {
    "gn:adm1_name":"Kagoshimaken",
    "gn:adm2_name":"Kagoshimashi",
    "gn:name":"Yamadachou",
    "iso:country":"JP",
    "wof:name":"891-0104",
    "wof:placetype":"postalcode"
},
  "geometry": {"coordinates":[130.50129999999999,31.561],"type":"Point"}
}