{
  "type": "Feature",
  "properties": {
    "gn:adm1_name":"Aichiken",
    "gn:adm2_name":"Inazawashi",
    "gn:name":"Kugatamiyamaechou",
    "iso:country":"JP",
    "wof:name":"492-8035",
    "wof:placetype":"postalcode"
},
  "geometry": {"coordinates":[136.81809999999999,35.2646],"type":"Point"}
}