{
  "type": "Feature",
  "properties": {
    "gn:adm1_name":"Niigataken",
    "gn:adm2_name":"Kitakanbaragunseiroumachi",
    "gn:name":"Momoyama",
    "iso:country":"JP",
    "wof:name":"957-0115",
    "wof:placetype":"postalcode"
},
  "geometry": {"coordinates":[139.29300000000001,37.978],"type":"Point"}
}