{
  "type": "Feature",
  "properties": {
    "gn:adm1_name":"Gifuken",
    "gn:adm2_name":"Ibigun'Ikedachou",
    "gn:name":"Hagiwara",
    "iso:country":"JP",
    "wof:name":"503-2416",
    "wof:placetype":"postalcode"
},
  "geometry": {"coordinates":[136.5744,35.4524],"type":"Point"}
}