{
  "type": "Feature",
  "properties": {
    "gn:adm1_name":"Sagaken",
    "gn:adm2_name":"Sagashi",
    "gn:name":"Kinryuumachiyakushimaru",
    "iso:country":"JP",
    "wof:name":"849-0904",
    "wof:placetype":"postalcode"
},
  "geometry": {"coordinates":[130.31540000000001,33.3023],"type":"Point"}
}