{
  "type": "Feature",
  "properties": {
    "gn:adm1_name":"Kanagawaken",
    "gn:adm2_name":"Yokohamashiseyaku",
    "gn:name":"Azumanodai",
    "iso:country":"JP",
    "wof:name":"246-0011",
    "wof:placetype":"postalcode"
},
  "geometry": {"coordinates":[139.49789999999999,35.4757],"type":"Point"}
}