{
  "type": "Feature",
  "properties": {
    "gn:adm1_name":"Shigaken",
    "gn:adm2_name":"Koukagunkouseichou",
    "gn:name":"Iwane",
    "iso:country":"JP",
    "wof:name":"520-3252",
    "wof:placetype":"postalcode"
},
  "geometry": {"coordinates":[136.11320000000001,35.0044],"type":"Point"}
}