{
  "type": "Feature",
  "properties": {
    "gn:adm1_name":"Aichiken",
    "gn:adm2_name":"Toyotashi",
    "gn:name":"Matsudairashigachou",
    "iso:country":"JP",
    "wof:name":"444-2223",
    "wof:placetype":"postalcode"
},
  "geometry": {"coordinates":[137.21029999999999,35.0636],"type":"Point"}
}