{
  "type": "Feature",
  "properties": {
    "gn:adm1_name":"Gifuken",
    "gn:adm2_name":"Kakamigaharashi",
    "gn:name":"Kawasakichou",
    "iso:country":"JP",
    "wof:name":"504-0971",
    "wof:placetype":"postalcode"
},
  "geometry": {"coordinates":[136.875,35.4013],"type":"Point"}
}