{
  "type": "Feature",
  "properties": {
    "gn:adm1_name":"Tochigiken",
    "gn:adm2_name":"Oyamashi",
    "gn:name":"Higashinoda",
    "iso:country":"JP",
    "wof:name":"323-0817",
    "wof:placetype":"postalcode"
},
  "geometry": {"coordinates":[139.8039,36.2517],"type":"Point"}
}