{
  "type": "Feature",
  "properties": {
    "gn:adm1_name":"Kanagawaken",
    "gn:adm2_name":"Kawasakishitakatsuku",
    "gn:name":"Shimonoge",
    "iso:country":"JP",
    "wof:name":"213-0006",
    "wof:placetype":"postalcode"
},
  "geometry": {"coordinates":[139.6377,35.5961],"type":"Point"}
}