{
  "type": "Feature",
  "properties": {
    "gn:adm1_name":"Fukuiken",
    "gn:adm2_name":"Sakaigunkanaduchou",
    "gn:name":"Ichihime",
    "iso:country":"JP",
    "wof:name":"919-0621",
    "wof:placetype":"postalcode"
},
  "geometry": {"coordinates":[136.23009999999999,36.2106],"type":"Point"}
}