{
  "type": "Feature",
  "properties": {
    "gn:adm1_name":"Fukuokaken",
    "gn:adm2_name":"Kitakyuushuushimojiku",
    "gn:name":"Okuda",
    "iso:country":"JP",
    "wof:name":"800-0011",
    "wof:placetype":"postalcode"
},
  "geometry": {"coordinates":[130.9573,33.9108],"type":"Point"}
}