{
  "type": "Feature",
  "properties": {
    "gn:adm1_name":"Aichiken",
    "gn:adm2_name":"Toyokawashi",
    "gn:name":"Babachou",
    "iso:country":"JP",
    "wof:name":"442-0811",
    "wof:placetype":"postalcode"
},
  "geometry": {"coordinates":[137.40190000000001,34.82],"type":"Point"}
}