{
  "type": "Feature",
  "properties": {
    "gn:adm1_name":"Naraken",
    "gn:adm2_name":"Yamatokooriyamashi",
    "gn:name":"Nishiokachou",
    "iso:country":"JP",
    "wof:name":"639-1014",
    "wof:placetype":"postalcode"
},
  "geometry": {"coordinates":[135.77959999999999,34.6441],"type":"Point"}
}