{
  "type": "Feature",
  "properties": {
    "gn:adm1_name":"Kanagawaken",
    "gn:adm2_name":"Chigasakishi",
    "gn:name":"Akabane",
    "iso:country":"JP",
    "wof:name":"253-0001",
    "wof:placetype":"postalcode"
},
  "geometry": {"coordinates":[139.4263,35.3495],"type":"Point"}
}