{
  "type": "Feature",
  "properties": {
    "gn:adm1_name":"Mieken",
    "gn:adm2_name":"Nabarishi",
    "gn:name":"Takinohara",
    "iso:country":"JP",
    "wof:name":"518-0411",
    "wof:placetype":"postalcode"
},
  "geometry": {"coordinates":[136.15639999999999,34.6306],"type":"Point"}
}