{
  "type": "Feature",
  "properties": {
    "gn:adm1_name":"Oosakafu",
    "gn:adm2_name":"Sennangunkumatorichou",
    "gn:name":"Wada",
    "iso:country":"JP",
    "wof:name":"590-0417",
    "wof:placetype":"postalcode"
},
  "geometry": {"coordinates":[135.35990000000001,34.3879],"type":"Point"}
}