{
  "type": "Feature",
  "properties": {
    "gn:adm1_name":"Hiroshimaken",
    "gn:adm2_name":"Hiroshimashinakaku",
    "gn:name":"Hashimotochou",
    "iso:country":"JP",
    "wof:name":"730-0015",
    "wof:placetype":"postalcode"
},
  "geometry": {"coordinates":[132.46879999999999,34.3944],"type":"Point"}
}