{
  "type": "Feature",
  "properties": {
    "gn:adm1_name":"Aichiken",
    "gn:adm2_name":"Nagoyashitenpakuku",
    "gn:name":"Shiogamaguchi",
    "iso:country":"JP",
    "wof:name":"468-0073",
    "wof:placetype":"postalcode"
},
  "geometry": {"coordinates":[136.97810000000001,35.1337],"type":"Point"}
}