{
  "type": "Feature",
  "properties": {
    "gn:adm1_name":"Fukushimaken",
    "gn:adm2_name":"Kitakatashi",
    "gn:name":"Nanjou",
    "iso:country":"JP",
    "wof:name":"966-0082",
    "wof:placetype":"postalcode"
},
  "geometry": {"coordinates":[139.87909999999999,37.6523],"type":"Point"}
}