{
  "type": "Feature",
  "properties": {
    "gn:adm1_name":"Hyougoken",
    "gn:adm2_name":"Himejishi",
    "gn:name":"Iwabanachou",
    "iso:country":"JP",
    "wof:name":"670-0028",
    "wof:placetype":"postalcode"
},
  "geometry": {"coordinates":[134.68190000000001,34.8414],"type":"Point"}
}