{
  "type": "Feature",
  "properties": {
    "gn:adm1_name":"Oosakafu",
    "gn:adm2_name":"Yaoshi",
    "gn:name":"Kohatachou",
    "iso:country":"JP",
    "wof:name":"581-0835",
    "wof:placetype":"postalcode"
},
  "geometry": {"coordinates":[135.61320000000001,34.6427],"type":"Point"}
}