{
  "type": "Feature",
  "properties": {
    "gn:adm1_name":"Miyagiken",
    "gn:adm2_name":"Kuriharagun'Ichihasamachou",
    "gn:name":"Sanobara",
    "iso:country":"JP",
    "wof:name":"987-2359",
    "wof:placetype":"postalcode"
},
  "geometry": {"coordinates":[140.8794,38.7534],"type":"Point"}
}