{
  "type": "Feature",
  "properties": {
    "gn:adm1_name":"Toyamaken",
    "gn:adm2_name":"Kaminiikawagun'Ooyamamachi",
    "gn:name":"Mimuroaraya",
    "iso:country":"JP",
    "wof:name":"930-1314",
    "wof:placetype":"postalcode"
},
  "geometry": {"coordinates":[137.2954,36.6129],"type":"Point"}
}