{
  "type": "Feature",
  "properties": {
    "gn:adm1_name":"Yamaguchiken",
    "gn:adm2_name":"Ubeshi",
    "gn:name":"Bunkyouchou",
    "iso:country":"JP",
    "wof:name":"755-0056",
    "wof:placetype":"postalcode"
},
  "geometry": {"coordinates":[131.2304,33.9725],"type":"Point"}
}