{
  "type": "Feature",
  "properties": {
    "gn:adm1_name":"Tochigiken",
    "gn:adm2_name":"Hagagunmotegimachi",
    "gn:name":"Machida",
    "iso:country":"JP",
    "wof:name":"321-3556",
    "wof:placetype":"postalcode"
},
  "geometry": {"coordinates":[140.15600000000001,36.5819],"type":"Point"}
}