{
  "type": "Feature",
  "properties": {
    "gn:adm1_name":"Miyazakiken",
    "gn:adm2_name":"Miyazakishi",
    "gn:name":"Murasumichou",
    "iso:country":"JP",
    "wof:name":"880-0837",
    "wof:placetype":"postalcode"
},
  "geometry": {"coordinates":[131.44800000000001,31.9527],"type":"Point"}
}