{
  "type": "Feature",
  "properties": {
    "gn:adm1_name":"Saitamaken",
    "gn:adm2_name":"Kazoshi",
    "gn:name":"Oogoe",
    "iso:country":"JP",
    "wof:name":"347-0001",
    "wof:placetype":"postalcode"
},
  "geometry": {"coordinates":[139.61940000000001,36.1799],"type":"Point"}
}