{
  "type": "Feature",
  "properties": {
    "gn:adm1_name":"Kanagawaken",
    "gn:adm2_name":"Nakagunninomiyamachi",
    "gn:name":"Ishiki",
    "iso:country":"JP",
    "wof:name":"259-0134",
    "wof:placetype":"postalcode"
},
  "geometry": {"coordinates":[139.2433,35.3183],"type":"Point"}
}