{
  "type": "Feature",
  "properties": {
    "gn:adm1_name":"Yamagataken",
    "gn:adm2_name":"Tendoushi",
    "gn:name":"Majirie",
    "iso:country":"JP",
    "wof:name":"994-0048",
    "wof:placetype":"postalcode"
},
  "geometry": {"coordinates":[140.3663,38.3641],"type":"Point"}
}