{
  "type": "Feature",
  "properties": {
    "gn:adm1_name":"Chibaken",
    "gn:adm2_name":"Isumigun'Onjukumachi",
    "gn:name":"Jikkoku",
    "iso:country":"JP",
    "wof:name":"299-5114",
    "wof:placetype":"postalcode"
},
  "geometry": {"coordinates":[140.327,35.1976],"type":"Point"}
}