{
  "type": "Feature",
  "properties": {
    "gn:adm1_name":"Fukuokaken",
    "gn:adm2_name":"Oonojoushi",
    "gn:name":"Otogana",
    "iso:country":"JP",
    "wof:name":"816-0902",
    "wof:placetype":"postalcode"
},
  "geometry": {"coordinates":[130.49299999999999,33.5466],"type":"Point"}
}