{
  "type": "Feature",
  "properties": {
    "gn:adm1_name":"Aichiken",
    "gn:adm2_name":"Toyotashi",
    "gn:name":"Takasakichou",
    "iso:country":"JP",
    "wof:name":"471-0048",
    "wof:placetype":"postalcode"
},
  "geometry": {"coordinates":[137.11670000000001,35.0939],"type":"Point"}
}