{
  "type": "Feature",
  "properties": {
    "gn:adm1_name":"Gifuken",
    "gn:adm2_name":"Sekishi",
    "gn:name":"Higashinomachi",
    "iso:country":"JP",
    "wof:name":"501-3813",
    "wof:placetype":"postalcode"
},
  "geometry": {"coordinates":[136.94040000000001,35.4901],"type":"Point"}
}