{
  "type": "Feature",
  "properties": {
    "gn:adm1_name":"Kagoshimaken",
    "gn:adm2_name":"Kanoyashi",
    "gn:name":"Kasanoharachou",
    "iso:country":"JP",
    "wof:name":"893-0023",
    "wof:placetype":"postalcode"
},
  "geometry": {"coordinates":[130.88849999999999,31.3893],"type":"Point"}
}