{
  "type": "Feature",
  "properties": {
    "gn:adm1_name":"Yamanashiken",
    "gn:adm2_name":"Higashiyamanashigunkasugaichou",
    "gn:name":"Shizume",
    "iso:country":"JP",
    "wof:name":"406-0015",
    "wof:placetype":"postalcode"
},
  "geometry": {"coordinates":[138.64429999999999,35.6646],"type":"Point"}
}