{
  "type": "Feature",
  "properties": {
    "gn:adm1_name":"Toukyouto",
    "gn:adm2_name":"Hachioujishi",
    "gn:name":"Asahichou",
    "iso:country":"JP",
    "wof:name":"192-0083",
    "wof:placetype":"postalcode"
},
  "geometry": {"coordinates":[139.33920000000001,35.6568],"type":"Point"}
}