{
  "type": "Feature",
  "properties": {
    "gn:adm1_name":"Niigataken",
    "gn:adm2_name":"Kamoshi",
    "gn:name":"Akatani",
    "iso:country":"JP",
    "wof:name":"959-1324",
    "wof:placetype":"postalcode"
},
  "geometry": {"coordinates":[139.05840000000001,37.6672],"type":"Point"}
}