{
  "type": "Feature",
  "properties": {
    "gn:adm1_name":"Kyoutofu",
    "gn:adm2_name":"Kyoutoshinakagyouku",
    "gn:name":"Higashitamayachou",
    "iso:country":"JP",
    "wof:name":"604-0855",
    "wof:placetype":"postalcode"
},
  "geometry": {"coordinates":[135.75880000000001,35.0137],"type":"Point"}
}