{
  "type": "Feature",
  "properties": {
    "gn:adm1_name":"Niigataken",
    "gn:adm2_name":"Nagaokashi",
    "gn:name":"Oomachi",
    "iso:country":"JP",
    "wof:name":"940-0844",
    "wof:placetype":"postalcode"
},
  "geometry": {"coordinates":[138.85990000000001,37.4302],"type":"Point"}
}