{
  "type": "Feature",
  "properties": {
    "gn:adm1_name":"Yamaguchiken",
    "gn:adm2_name":"Houfushi",
    "gn:name":"Ekiminamimachi",
    "iso:country":"JP",
    "wof:name":"747-0801",
    "wof:placetype":"postalcode"
},
  "geometry": {"coordinates":[131.56559999999999,34.0514],"type":"Point"}
}