{
  "type": "Feature",
  "properties": {
    "gn:adm1_name":"Kagoshimaken",
    "gn:adm2_name":"Satsumagunkamikoshikimura",
    "gn:name":"Eishi",
    "iso:country":"JP",
    "wof:name":"896-1203",
    "wof:placetype":"postalcode"
},
  "geometry": {"coordinates":[129.87039999999999,31.8228],"type":"Point"}
}