{
  "type": "Feature",
  "properties": {
    "gn:adm1_name":"Ishikawaken",
    "gn:adm2_name":"Hakuigunshikamachi",
    "gn:name":"Hiuchidani",
    "iso:country":"JP",
    "wof:name":"925-0214",
    "wof:placetype":"postalcode"
},
  "geometry": {"coordinates":[136.80619999999999,37.032],"type":"Point"}
}