{
  "type": "Feature",
  "properties": {
    "gn:adm1_name":"Hyougoken",
    "gn:adm2_name":"Koubeshisumaku",
    "gn:name":"Shirakawadai",
    "iso:country":"JP",
    "wof:name":"654-0103",
    "wof:placetype":"postalcode"
},
  "geometry": {"coordinates":[135.09979999999999,34.6918],"type":"Point"}
}