{
  "type": "Feature",
  "properties": {
    "gn:adm1_name":"Kouchiken",
    "gn:adm2_name":"Kouchishi",
    "gn:name":"Minaminomaruchou",
    "iso:country":"JP",
    "wof:name":"780-8016",
    "wof:placetype":"postalcode"
},
  "geometry": {"coordinates":[133.54830000000001,33.5419],"type":"Point"}
}