{
  "type": "Feature",
  "properties": {
    "gn:adm1_name":"Naraken",
    "gn:adm2_name":"Shikiguntawaramotochou",
    "gn:name":"Muromachi",
    "iso:country":"JP",
    "wof:name":"636-0316",
    "wof:placetype":"postalcode"
},
  "geometry": {"coordinates":[135.78919999999999,34.5551],"type":"Point"}
}