{
  "type": "Feature",
  "properties": {
    "gn:adm1_name":"Fukuokaken",
    "gn:adm2_name":"Kitakyuushuushiwakamatsuku",
    "gn:name":"Yurinomachi",
    "iso:country":"JP",
    "wof:name":"808-0072",
    "wof:placetype":"postalcode"
},
  "geometry": {"coordinates":[130.78360000000001,33.8977],"type":"Point"}
}