{
  "type": "Feature",
  "properties": {
    "gn:adm1_name":"Hiroshimaken",
    "gn:adm2_name":"Akigun'Ondochou",
    "gn:name":"Takasu",
    "iso:country":"JP",
    "wof:name":"737-1206",
    "wof:placetype":"postalcode"
},
  "geometry": {"coordinates":[132.53790000000001,34.1859],"type":"Point"}
}