{
  "type": "Feature",
  "properties": {
    "gn:adm1_name":"Fukuokaken",
    "gn:adm2_name":"Kasugashi",
    "gn:name":"Kasugabarukitamachi",
    "iso:country":"JP",
    "wof:name":"816-0802",
    "wof:placetype":"postalcode"
},
  "geometry": {"coordinates":[130.47139999999999,33.5368],"type":"Point"}
}