{
  "type": "Feature",
  "properties": {
    "gn:adm1_name":"Kouchiken",
    "gn:adm2_name":"Nankokushi",
    "gn:name":"Saidani",
    "iso:country":"JP",
    "wof:name":"783-0068",
    "wof:placetype":"postalcode"
},
  "geometry": {"coordinates":[133.6464,33.6306],"type":"Point"}
}