{
  "type": "Feature",
  "properties": {
    "gn:adm1_name":"Hyougoken",
    "gn:adm2_name":"Akashishi",
    "gn:name":"Ookubochoueigashima",
    "iso:country":"JP",
    "wof:name":"674-0064",
    "wof:placetype":"postalcode"
},
  "geometry": {"coordinates":[134.91820000000001,34.6776],"type":"Point"}
}