{
  "type": "Feature",
  "properties": {
    "gn:adm1_name":"Kagoshimaken",
    "gn:adm2_name":"Makurazakishi",
    "gn:name":"Tategamikitamachi",
    "iso:country":"JP",
    "wof:name":"898-0045",
    "wof:placetype":"postalcode"
},
  "geometry": {"coordinates":[130.27780000000001,31.2768],"type":"Point"}
}