{
  "type": "Feature",
  "properties": {
    "gn:adm1_name":"Kouchiken",
    "gn:adm2_name":"Nagaokagunmotoyamachou",
    "gn:name":"Tachino",
    "iso:country":"JP",
    "wof:name":"781-3619",
    "wof:placetype":"postalcode"
},
  "geometry": {"coordinates":[133.55439999999999,33.7724],"type":"Point"}
}