{
  "type": "Feature",
  "properties": {
    "gn:adm1_name":"Niigataken",
    "gn:adm2_name":"Shibatashi",
    "gn:name":"Shimagata",
    "iso:country":"JP",
    "wof:name":"957-0011",
    "wof:placetype":"postalcode"
},
  "geometry": {"coordinates":[139.34950000000001,37.9589],"type":"Point"}
}