{
  "type": "Feature",
  "properties": {
    "gn:adm1_name":"Hiroshimaken",
    "gn:adm2_name":"Yamagataguntsutsugason",
    "gn:name":"Kamitsutsuga",
    "iso:country":"JP",
    "wof:name":"731-3701",
    "wof:placetype":"postalcode"
},
  "geometry": {"coordinates":[132.23249999999999,34.5488],"type":"Point"}
}