{
  "type": "Feature",
  "properties": {
    "gn:adm1_name":"Okinawaken",
    "gn:adm2_name":"Ginowanshi",
    "gn:name":"Isa",
    "iso:country":"JP",
    "wof:name":"901-2221",
    "wof:placetype":"postalcode"
},
  "geometry": {"coordinates":[127.7559,26.2896],"type":"Point"}
}