{
  "type": "Feature",
  "properties": {
    "gn:adm1_name":"Hyougoken",
    "gn:adm2_name":"Nishinomiyashi",
    "gn:name":"Koushienguchikitamachi",
    "iso:country":"JP",
    "wof:name":"663-8112",
    "wof:placetype":"postalcode"
},
  "geometry": {"coordinates":[135.376,34.7404],"type":"Point"}
}