{
  "type": "Feature",
  "properties": {
    "gn:adm1_name":"Kyoutofu",
    "gn:adm2_name":"Sourakugunkamochou",
    "gn:name":"Ibirao",
    "iso:country":"JP",
    "wof:name":"619-1102",
    "wof:placetype":"postalcode"
},
  "geometry": {"coordinates":[135.87540000000001,34.7683],"type":"Point"}
}