{
  "type": "Feature",
  "properties": {
    "gn:adm1_name":"Okayamaken",
    "gn:adm2_name":"Okayamashi",
    "gn:name":"Hijikai",
    "iso:country":"JP",
    "wof:name":"701-1521",
    "wof:placetype":"postalcode"
},
  "geometry": {"coordinates":[133.81569999999999,34.7515],"type":"Point"}
}