{
  "type": "Feature",
  "properties": {
    "gn:adm1_name":"Ehimeken",
    "gn:adm2_name":"Houjoushi",
    "gn:name":"Innai",
    "iso:country":"JP",
    "wof:name":"799-2423",
    "wof:placetype":"postalcode"
},
  "geometry": {"coordinates":[132.815,33.9603],"type":"Point"}
}