{
  "type": "Feature",
  "properties": {
    "gn:adm1_name":"Niigataken",
    "gn:adm2_name":"Iwafunegunkamihayashimura",
    "gn:name":"Ushiya",
    "iso:country":"JP",
    "wof:name":"959-3436",
    "wof:placetype":"postalcode"
},
  "geometry": {"coordinates":[139.44239999999999,38.1506],"type":"Point"}
}