{
  "type": "Feature",
  "properties": {
    "gn:adm1_name":"Fukuokaken",
    "gn:adm2_name":"Maebarushi",
    "gn:name":"Ooura",
    "iso:country":"JP",
    "wof:name":"819-1135",
    "wof:placetype":"postalcode"
},
  "geometry": {"coordinates":[130.19390000000001,33.5462],"type":"Point"}
}