{
  "type": "Feature",
  "properties": {
    "gn:adm1_name":"Fukuiken",
    "gn:adm2_name":"Sakaigunmikunichou",
    "gn:name":"Midorigaoka",
    "iso:country":"JP",
    "wof:name":"913-0048",
    "wof:placetype":"postalcode"
},
  "geometry": {"coordinates":[136.15309999999999,36.222],"type":"Point"}
}