{
  "type": "Feature",
  "properties": {
    "gn:adm1_name":"Fukuokaken",
    "gn:adm2_name":"Buzenshi",
    "gn:name":"Kajiya",
    "iso:country":"JP",
    "wof:name":"828-0041",
    "wof:placetype":"postalcode"
},
  "geometry": {"coordinates":[131.14080000000001,33.6055],"type":"Point"}
}