{
  "type": "Feature",
  "properties": {
    "gn:adm1_name":"Miyagiken",
    "gn:adm2_name":"Sendaishiaobaku",
    "gn:name":"Nakae",
    "iso:country":"JP",
    "wof:name":"980-0001",
    "wof:placetype":"postalcode"
},
  "geometry": {"coordinates":[140.89259999999999,38.2735],"type":"Point"}
}