{
  "type": "Feature",
  "properties": {
    "gn:adm1_name":"Miyazakiken",
    "gn:adm2_name":"Nobeokashi",
    "gn:name":"Okitamachi",
    "iso:country":"JP",
    "wof:name":"882-0876",
    "wof:placetype":"postalcode"
},
  "geometry": {"coordinates":[131.66900000000001,32.5459],"type":"Point"}
}