{
  "type": "Feature",
  "properties": {
    "gn:adm1_name":"Yamagataken",
    "gn:adm2_name":"Tsuruokashi",
    "gn:name":"Shimokonaka",
    "iso:country":"JP",
    "wof:name":"997-1134",
    "wof:placetype":"postalcode"
},
  "geometry": {"coordinates":[139.75120000000001,38.7211],"type":"Point"}
}