{
  "type": "Feature",
  "properties": {
    "gn:adm1_name":"Wakayamaken",
    "gn:adm2_name":"Wakayamashi",
    "gn:name":"Yakushouji",
    "iso:country":"JP",
    "wof:name":"640-0321",
    "wof:placetype":"postalcode"
},
  "geometry": {"coordinates":[135.23349999999999,34.1843],"type":"Point"}
}