{
  "type": "Feature",
  "properties": {
    "gn:adm1_name":"Hyougoken",
    "gn:adm2_name":"Sasayamashi",
    "gn:name":"Kitanoshinden",
    "iso:country":"JP",
    "wof:name":"669-2825",
    "wof:placetype":"postalcode"
},
  "geometry": {"coordinates":[135.15010000000001,35.0936],"type":"Point"}
}