{
  "type": "Feature",
  "properties": {
    "gn:adm1_name":"Yamagataken",
    "gn:adm2_name":"Yonezawashi",
    "gn:name":"Montoumachi",
    "iso:country":"JP",
    "wof:name":"992-0039",
    "wof:placetype":"postalcode"
},
  "geometry": {"coordinates":[140.10990000000001,37.9091],"type":"Point"}
}