{
  "type": "Feature",
  "properties": {
    "gn:adm1_name":"Fukuokaken",
    "gn:adm2_name":"Oomutashi",
    "gn:name":"Yuumeimachi",
    "iso:country":"JP",
    "wof:name":"836-0842",
    "wof:placetype":"postalcode"
},
  "geometry": {"coordinates":[130.44640000000001,33.0315],"type":"Point"}
}