{
  "type": "Feature",
  "properties": {
    "gn:adm1_name":"Fukushimaken",
    "gn:adm2_name":"Adachigunmotomiyamachi",
    "gn:name":"Niita",
    "iso:country":"JP",
    "wof:name":"969-1103",
    "wof:placetype":"postalcode"
},
  "geometry": {"coordinates":[140.39940000000001,37.4945],"type":"Point"}
}