{
  "type": "Feature",
  "properties": {
    "gn:adm1_name":"Chibaken",
    "gn:adm2_name":"Narashinoshi",
    "gn:name":"Yatsumachi",
    "iso:country":"JP",
    "wof:name":"275-0027",
    "wof:placetype":"postalcode"
},
  "geometry": {"coordinates":[140.01660000000001,35.6798],"type":"Point"}
}