{
  "type": "Feature",
  "properties": {
    "gn:adm1_name":"Tokushimaken",
    "gn:adm2_name":"Miyoshigun'Ikedachou",
    "gn:name":"Itano",
    "iso:country":"JP",
    "wof:name":"778-0014",
    "wof:placetype":"postalcode"
},
  "geometry": {"coordinates":[133.786,34.0227],"type":"Point"}
}