{
  "type": "Feature",
  "properties": {
    "gn:adm1_name":"Aichiken",
    "gn:adm2_name":"Toyokawashi",
    "gn:name":"Wakabatochou",
    "iso:country":"JP",
    "wof:name":"442-0065",
    "wof:placetype":"postalcode"
},
  "geometry": {"coordinates":[137.38489999999999,34.827],"type":"Point"}
}