{
  "type": "Feature",
  "properties": {
    "gn:adm1_name":"Ibarakiken",
    "gn:adm2_name":"Inashikigunmihomura",
    "gn:name":"Nemoto",
    "iso:country":"JP",
    "wof:name":"300-0436",
    "wof:placetype":"postalcode"
},
  "geometry": {"coordinates":[140.34549999999999,36.0248],"type":"Point"}
}