{
  "type": "Feature",
  "properties": {
    "gn:adm1_name":"Fukushimaken",
    "gn:adm2_name":"Dategunkoorimachi",
    "gn:name":"Shimogoori",
    "iso:country":"JP",
    "wof:name":"969-1662",
    "wof:placetype":"postalcode"
},
  "geometry": {"coordinates":[140.53809999999999,37.8517],"type":"Point"}
}