{
  "type": "Feature",
  "properties": {
    "gn:adm1_name":"Gifuken",
    "gn:adm2_name":"Kamogunsakahogichou",
    "gn:name":"Katsuyama",
    "iso:country":"JP",
    "wof:name":"505-0076",
    "wof:placetype":"postalcode"
},
  "geometry": {"coordinates":[136.96799999999999,35.4264],"type":"Point"}
}