{
  "type": "Feature",
  "properties": {
    "gn:adm1_name":"Kagoshimaken",
    "gn:adm2_name":"Kushikinoshi",
    "gn:name":"Kanmyou",
    "iso:country":"JP",
    "wof:name":"896-0052",
    "wof:placetype":"postalcode"
},
  "geometry": {"coordinates":[130.29499999999999,31.7239],"type":"Point"}
}