{
  "type": "Feature",
  "properties": {
    "gn:adm1_name":"Gunmaken",
    "gn:adm2_name":"Takasakishi",
    "gn:name":"Shibasakimachi",
    "iso:country":"JP",
    "wof:name":"370-0035",
    "wof:placetype":"postalcode"
},
  "geometry": {"coordinates":[139.05240000000001,36.3171],"type":"Point"}
}