{
  "type": "Feature",
  "properties": {
    "gn:adm1_name":"Kumamotoken",
    "gn:adm2_name":"Kumamotoshi",
    "gn:name":"Kawachimachiomonogi",
    "iso:country":"JP",
    "wof:name":"861-5345",
    "wof:placetype":"postalcode"
},
  "geometry": {"coordinates":[130.6283,32.8241],"type":"Point"}
}