{
  "type": "Feature",
  "properties": {
    "gn:adm1_name":"Yamagataken",
    "gn:adm2_name":"Sagaeshi",
    "gn:name":"Shinzanchou",
    "iso:country":"JP",
    "wof:name":"991-0012",
    "wof:placetype":"postalcode"
},
  "geometry": {"coordinates":[140.2927,38.3712],"type":"Point"}
}