{
  "type": "Feature",
  "properties": {
    "gn:adm1_name":"Wakayamaken",
    "gn:adm2_name":"Nishimurogun'Ootoumura",
    "gn:name":"Shimokawakami",
    "iso:country":"JP",
    "wof:name":"646-1212",
    "wof:placetype":"postalcode"
},
  "geometry": {"coordinates":[135.63210000000001,33.7508],"type":"Point"}
}