{
  "type": "Feature",
  "properties": {
    "gn:adm1_name":"Aichiken",
    "gn:adm2_name":"Nagoyashinishiku",
    "gn:name":"Chichibutoori",
    "iso:country":"JP",
    "wof:name":"451-0024",
    "wof:placetype":"postalcode"
},
  "geometry": {"coordinates":[136.8954,35.1974],"type":"Point"}
}