{
  "type": "Feature",
  "properties": {
    "gn:adm1_name":"Gifuken",
    "gn:adm2_name":"Mizuhoshi",
    "gn:name":"Hodumi",
    "iso:country":"JP",
    "wof:name":"501-0223",
    "wof:placetype":"postalcode"
},
  "geometry": {"coordinates":[136.6953,35.3852],"type":"Point"}
}