{
  "type": "Feature",
  "properties": {
    "gn:adm1_name":"Nagasakiken",
    "gn:adm2_name":"Saseboshi",
    "gn:name":"Takahanachou",
    "iso:country":"JP",
    "wof:name":"857-0125",
    "wof:placetype":"postalcode"
},
  "geometry": {"coordinates":[129.78620000000001,33.2055],"type":"Point"}
}