{
  "type": "Feature",
  "properties": {
    "gn:adm1_name":"Ibarakiken",
    "gn:adm2_name":"Inashikigun'Amimachi",
    "gn:name":"Ikanikeisaiganaibaai",
    "iso:country":"JP",
    "wof:name":"300-0300",
    "wof:placetype":"postalcode"
},
  "geometry": {"coordinates":[140.2192,36.0234],"type":"Point"}
}