{
  "type": "Feature",
  "properties": {
    "gn:adm1_name":"Mieken",
    "gn:adm2_name":"Hisaishi",
    "gn:name":"Hatagomachi",
    "iso:country":"JP",
    "wof:name":"514-1134",
    "wof:placetype":"postalcode"
},
  "geometry": {"coordinates":[136.47149999999999,34.6758],"type":"Point"}
}