{
  "type": "Feature",
  "properties": {
    "gn:adm1_name":"Toyamaken",
    "gn:adm2_name":"Oyabeshi",
    "gn:name":"Nobana",
    "iso:country":"JP",
    "wof:name":"932-0832",
    "wof:placetype":"postalcode"
},
  "geometry": {"coordinates":[136.8587,36.6707],"type":"Point"}
}