{
  "type": "Feature",
  "properties": {
    "gn:adm1_name":"Ehimeken",
    "gn:adm2_name":"Minamiuwagunmishouchou",
    "gn:name":"Hirayama",
    "iso:country":"JP",
    "wof:name":"798-4102",
    "wof:placetype":"postalcode"
},
  "geometry": {"coordinates":[132.5351,32.9736],"type":"Point"}
}