{
  "type": "Feature",
  "properties": {
    "gn:adm1_name":"Aichiken",
    "gn:adm2_name":"Chitashi",
    "gn:name":"Shinmaiko",
    "iso:country":"JP",
    "wof:name":"478-0036",
    "wof:placetype":"postalcode"
},
  "geometry": {"coordinates":[136.83250000000001,34.9531],"type":"Point"}
}