{
  "type": "Feature",
  "properties": {
    "gn:adm1_name":"Aichiken",
    "gn:adm2_name":"Anjoushi",
    "gn:name":"Takatanachou",
    "iso:country":"JP",
    "wof:name":"446-0053",
    "wof:placetype":"postalcode"
},
  "geometry": {"coordinates":[137.0283,34.9445],"type":"Point"}
}