{
  "type": "Feature",
  "properties": {
    "gn:adm1_name":"Mieken",
    "gn:adm2_name":"Inabeshi",
    "gn:name":"Hokuseichouootsujishinden",
    "iso:country":"JP",
    "wof:name":"511-0425",
    "wof:placetype":"postalcode"
},
  "geometry": {"coordinates":[136.5411,35.1487],"type":"Point"}
}