{
  "type": "Feature",
  "properties": {
    "gn:adm1_name":"Hyougoken",
    "gn:adm2_name":"Itamishi",
    "gn:name":"Nishidai",
    "iso:country":"JP",
    "wof:name":"664-0858",
    "wof:placetype":"postalcode"
},
  "geometry": {"coordinates":[135.41249999999999,34.7791],"type":"Point"}
}