{
  "type": "Feature",
  "properties": {
    "gn:adm1_name":"Hyougoken",
    "gn:adm2_name":"Ibogunshinguuchou",
    "gn:name":"Tokishige",
    "iso:country":"JP",
    "wof:name":"679-5153",
    "wof:placetype":"postalcode"
},
  "geometry": {"coordinates":[134.4684,34.9632],"type":"Point"}
}