{
  "type": "Feature",
  "properties": {
    "gn:adm1_name":"Naganoken",
    "gn:adm2_name":"Matsumotoshi",
    "gn:name":"Yoshikawanomizo",
    "iso:country":"JP",
    "wof:name":"399-0003",
    "wof:placetype":"postalcode"
},
  "geometry": {"coordinates":[137.9562,36.1984],"type":"Point"}
}