{
  "type": "Feature",
  "properties": {
    "gn:adm1_name":"Chibaken",
    "gn:adm2_name":"Isumigun'Ootakimachi",
    "gn:name":"Senzui",
    "iso:country":"JP",
    "wof:name":"298-0207",
    "wof:placetype":"postalcode"
},
  "geometry": {"coordinates":[140.23840000000001,35.2956],"type":"Point"}
}