{
  "type": "Feature",
  "properties": {
    "gn:adm1_name":"Gifuken",
    "gn:adm2_name":"Takayamashi",
    "gn:name":"Fukiyamachi",
    "iso:country":"JP",
    "wof:name":"506-0831",
    "wof:placetype":"postalcode"
},
  "geometry": {"coordinates":[137.2638,36.1426],"type":"Point"}
}