{
  "type": "Feature",
  "properties": {
    "gn:adm1_name":"Kyoutofu",
    "gn:adm2_name":"Kyoutoshikamigyouku",
    "gn:name":"Juuyonkenchou",
    "iso:country":"JP",
    "wof:name":"602-8164",
    "wof:placetype":"postalcode"
},
  "geometry": {"coordinates":[135.74270000000001,35.0209],"type":"Point"}
}