{
  "type": "Feature",
  "properties": {
    "gn:adm1_name":"Miyagiken",
    "gn:adm2_name":"Iwanumashi",
    "gn:name":"Shikishima",
    "iso:country":"JP",
    "wof:name":"989-2476",
    "wof:placetype":"postalcode"
},
  "geometry": {"coordinates":[140.86250000000001,38.1193],"type":"Point"}
}