{
  "type": "Feature",
  "properties": {
    "gn:adm1_name":"Shizuokaken",
    "gn:adm2_name":"Shizuokashi",
    "gn:name":"Furushou",
    "iso:country":"JP",
    "wof:name":"420-0812",
    "wof:placetype":"postalcode"
},
  "geometry": {"coordinates":[138.41990000000001,34.9964],"type":"Point"}
}