{
  "type": "Feature",
  "properties": {
    "gn:adm1_name":"Kanagawaken",
    "gn:adm2_name":"Hiratsukashi",
    "gn:name":"Fujimino",
    "iso:country":"JP",
    "wof:name":"259-1211",
    "wof:placetype":"postalcode"
},
  "geometry": {"coordinates":[139.3038,35.3807],"type":"Point"}
}