{
  "type": "Feature",
  "properties": {
    "gn:adm1_name":"Okinawaken",
    "gn:adm2_name":"Shimajirigun'Iheyason",
    "gn:name":"Maedomari",
    "iso:country":"JP",
    "wof:name":"905-0702",
    "wof:placetype":"postalcode"
},
  "geometry": {"coordinates":[127.9739,27.0416],"type":"Point"}
}