{
  "type": "Feature",
  "properties": {
    "gn:adm1_name":"Fukuokaken",
    "gn:adm2_name":"Munakatashi",
    "gn:name":"Mochiyama",
    "iso:country":"JP",
    "wof:name":"811-3435",
    "wof:placetype":"postalcode"
},
  "geometry": {"coordinates":[130.51070000000001,33.7985],"type":"Point"}
}