{
  "type": "Feature",
  "properties": {
    "gn:adm1_name":"Gifuken",
    "gn:adm2_name":"Minokamoshi",
    "gn:name":"Nakatomichou",
    "iso:country":"JP",
    "wof:name":"505-0033",
    "wof:placetype":"postalcode"
},
  "geometry": {"coordinates":[137.02680000000001,35.4439],"type":"Point"}
}