{
  "type": "Feature",
  "properties": {
    "gn:adm1_name":"Shizuokaken",
    "gn:adm2_name":"Ogasagunkikugawachou",
    "gn:name":"Asahi",
    "iso:country":"JP",
    "wof:name":"439-0017",
    "wof:placetype":"postalcode"
},
  "geometry": {"coordinates":[138.08969999999999,34.7527],"type":"Point"}
}