{
  "type": "Feature",
  "properties": {
    "gn:adm1_name":"Ehimeken",
    "gn:adm2_name":"Onsengunnakajimachou",
    "gn:name":"Futagami",
    "iso:country":"JP",
    "wof:name":"791-4323",
    "wof:placetype":"postalcode"
},
  "geometry": {"coordinates":[132.54050000000001,33.9335],"type":"Point"}
}