{
  "type": "Feature",
  "properties": {
    "gn:adm1_name":"Nagasakiken",
    "gn:adm2_name":"Isahayashi",
    "gn:name":"Matsuzatochou",
    "iso:country":"JP",
    "wof:name":"854-0126",
    "wof:placetype":"postalcode"
},
  "geometry": {"coordinates":[130.0907,32.7972],"type":"Point"}
}