{
  "type": "Feature",
  "properties": {
    "gn:adm1_name":"Kumamotoken",
    "gn:adm2_name":"Ashikitagun'Ashikitamachi",
    "gn:name":"Shiraishi",
    "iso:country":"JP",
    "wof:name":"869-6302",
    "wof:placetype":"postalcode"
},
  "geometry": {"coordinates":[130.6027,32.3007],"type":"Point"}
}