{
  "type": "Feature",
  "properties": {
    "gn:adm1_name":"Toukyouto",
    "gn:adm2_name":"Musashimurayamashi",
    "gn:name":"Mitsugi(Ooaza)",
    "iso:country":"JP",
    "wof:name":"208-0033",
    "wof:placetype":"postalcode"
},
  "geometry": {"coordinates":[139.37440000000001,35.7619],"type":"Point"}
}