{
  "type": "Feature",
  "properties": {
    "gn:adm1_name":"Miyagiken",
    "gn:adm2_name":"Kattagunshichikashukumachi",
    "gn:name":"Yunohara",
    "iso:country":"JP",
    "wof:name":"989-0653",
    "wof:placetype":"postalcode"
},
  "geometry": {"coordinates":[140.32169999999999,38.0128],"type":"Point"}
}