{
  "type": "Feature",
  "properties": {
    "gn:adm1_name":"Miyagiken",
    "gn:adm2_name":"Shiogamashi",
    "gn:name":"Gyuuchou",
    "iso:country":"JP",
    "wof:name":"985-0013",
    "wof:placetype":"postalcode"
},
  "geometry": {"coordinates":[141.0316,38.3069],"type":"Point"}
}