{
  "type": "Feature",
  "properties": {
    "gn:adm1_name":"Oosakafu",
    "gn:adm2_name":"Takatsukishi",
    "gn:name":"Nodahigashi",
    "iso:country":"JP",
    "wof:name":"569-0014",
    "wof:placetype":"postalcode"
},
  "geometry": {"coordinates":[135.6454,34.8539],"type":"Point"}
}