{
  "type": "Feature",
  "properties": {
    "gn:adm1_name":"Kyoutofu",
    "gn:adm2_name":"Yawatashi",
    "gn:name":"Kouduyanakadutsumi",
    "iso:country":"JP",
    "wof:name":"614-8176",
    "wof:placetype":"postalcode"
},
  "geometry": {"coordinates":[135.739,34.8626],"type":"Point"}
}