{
  "type": "Feature",
  "properties": {
    "gn:adm1_name":"Fukushimaken",
    "gn:adm2_name":"Shirakawashi",
    "gn:name":"Izumida",
    "iso:country":"JP",
    "wof:name":"961-0003",
    "wof:placetype":"postalcode"
},
  "geometry": {"coordinates":[140.2491,37.1485],"type":"Point"}
}