{
  "type": "Feature",
  "properties": {
    "gn:adm1_name":"Shigaken",
    "gn:adm2_name":"Oumihachimanshi",
    "gn:name":"Ikesuchou",
    "iso:country":"JP",
    "wof:name":"523-0823",
    "wof:placetype":"postalcode"
},
  "geometry": {"coordinates":[136.09379999999999,35.1426],"type":"Point"}
}