{
  "type": "Feature",
  "properties": {
    "gn:adm1_name":"Hyougoken",
    "gn:adm2_name":"Takagunyachiyochou",
    "gn:name":"Nakanoma",
    "iso:country":"JP",
    "wof:name":"677-0121",
    "wof:placetype":"postalcode"
},
  "geometry": {"coordinates":[134.90360000000001,35.0034],"type":"Point"}
}