{
  "type": "Feature",
  "properties": {
    "gn:adm1_name":"Kumamotoken",
    "gn:adm2_name":"Asogunnishiharamura",
    "gn:name":"Kawahara",
    "iso:country":"JP",
    "wof:name":"861-2404",
    "wof:placetype":"postalcode"
},
  "geometry": {"coordinates":[130.893,32.81],"type":"Point"}
}