{
  "type": "Feature",
  "properties": {
    "gn:adm1_name":"Toyamaken",
    "gn:adm2_name":"Toyamashi",
    "gn:name":"Matsunokishin",
    "iso:country":"JP",
    "wof:name":"930-2212",
    "wof:placetype":"postalcode"
},
  "geometry": {"coordinates":[137.20910000000001,36.7271],"type":"Point"}
}