{
  "type": "Feature",
  "properties": {
    "gn:adm1_name":"Kumamotoken",
    "gn:adm2_name":"Kamimashikigunkousamachi",
    "gn:name":"Furyou",
    "iso:country":"JP",
    "wof:name":"861-4615",
    "wof:placetype":"postalcode"
},
  "geometry": {"coordinates":[130.75749999999999,32.7054],"type":"Point"}
}