{
  "type": "Feature",
  "properties": {
    "gn:adm1_name":"Kyoutofu",
    "gn:adm2_name":"Fukuchiyamashi",
    "gn:name":"Toonoichi",
    "iso:country":"JP",
    "wof:name":"620-0844",
    "wof:placetype":"postalcode"
},
  "geometry": {"coordinates":[135.18260000000001,35.2673],"type":"Point"}
}