{
  "type": "Feature",
  "properties": {
    "gn:adm1_name":"Kyoutofu",
    "gn:adm2_name":"Kyoutoshikitaku",
    "gn:name":"Kinugasakitaaramichou",
    "iso:country":"JP",
    "wof:name":"603-8316",
    "wof:placetype":"postalcode"
},
  "geometry": {"coordinates":[135.73599999999999,35.0396],"type":"Point"}
}