{
  "type": "Feature",
  "properties": {
    "gn:adm1_name":"Aichiken",
    "gn:adm2_name":"Hazugun'Isshikichou",
    "gn:name":"Sougorou",
    "iso:country":"JP",
    "wof:name":"444-0405",
    "wof:placetype":"postalcode"
},
  "geometry": {"coordinates":[137.0361,34.799],"type":"Point"}
}