{
  "type": "Feature",
  "properties": {
    "gn:adm1_name":"Okayamaken",
    "gn:adm2_name":"Kasaokashi",
    "gn:name":"Rokubanchou",
    "iso:country":"JP",
    "wof:name":"714-0087",
    "wof:placetype":"postalcode"
},
  "geometry": {"coordinates":[133.51589999999999,34.4967],"type":"Point"}
}