{
  "type": "Feature",
  "properties": {
    "gn:adm1_name":"Niigataken",
    "gn:adm2_name":"Jouetsushi",
    "gn:name":"Fukuokashinden",
    "iso:country":"JP",
    "wof:name":"942-0232",
    "wof:placetype":"postalcode"
},
  "geometry": {"coordinates":[138.3329,37.1775],"type":"Point"}
}