{
  "type": "Feature",
  "properties": {
    "gn:adm1_name":"Aichiken",
    "gn:adm2_name":"Toyohashishi",
    "gn:name":"Kinutachou",
    "iso:country":"JP",
    "wof:name":"440-0078",
    "wof:placetype":"postalcode"
},
  "geometry": {"coordinates":[137.37970000000001,34.7686],"type":"Point"}
}