{
  "type": "Feature",
  "properties": {
    "gn:adm1_name":"Shigaken",
    "gn:adm2_name":"Oumihachimanshi",
    "gn:name":"Odachou",
    "iso:country":"JP",
    "wof:name":"523-0064",
    "wof:placetype":"postalcode"
},
  "geometry": {"coordinates":[136.0461,35.1148],"type":"Point"}
}