{
  "type": "Feature",
  "properties": {
    "gn:adm1_name":"Niigataken",
    "gn:adm2_name":"Iwafunegunsanpokumachi",
    "gn:name":"Kakinouchi",
    "iso:country":"JP",
    "wof:name":"959-3932",
    "wof:placetype":"postalcode"
},
  "geometry": {"coordinates":[139.54470000000001,38.4775],"type":"Point"}
}