{
  "type": "Feature",
  "properties": {
    "gn:adm1_name":"Wakayamaken",
    "gn:adm2_name":"Aridagunhirogawachou",
    "gn:name":"Tono",
    "iso:country":"JP",
    "wof:name":"643-0062",
    "wof:placetype":"postalcode"
},
  "geometry": {"coordinates":[135.18709999999999,34.0133],"type":"Point"}
}