{
  "type": "Feature",
  "properties": {
    "gn:adm1_name":"Yamagataken",
    "gn:adm2_name":"Yamagatashi",
    "gn:name":"Namiyanagi",
    "iso:country":"JP",
    "wof:name":"990-2386",
    "wof:placetype":"postalcode"
},
  "geometry": {"coordinates":[140.25909999999999,38.263],"type":"Point"}
}