{
  "type": "Feature",
  "properties": {
    "gn:adm1_name":"Miyagiken",
    "gn:adm2_name":"Kamigunkamimachi",
    "gn:name":"Matsuta",
    "iso:country":"JP",
    "wof:name":"981-4364",
    "wof:placetype":"postalcode"
},
  "geometry": {"coordinates":[140.6944,38.6032],"type":"Point"}
}