{
  "type": "Feature",
  "properties": {
    "gn:adm1_name":"Fukuiken",
    "gn:adm2_name":"Tsurugashi",
    "gn:name":"Kuretakechou",
    "iso:country":"JP",
    "wof:name":"914-0802",
    "wof:placetype":"postalcode"
},
  "geometry": {"coordinates":[136.05969999999999,35.6481],"type":"Point"}
}