{
  "type": "Feature",
  "properties": {
    "gn:adm1_name":"Niigataken",
    "gn:adm2_name":"Nakakubikigunsanwamura",
    "gn:name":"Imapo",
    "iso:country":"JP",
    "wof:name":"943-0313",
    "wof:placetype":"postalcode"
},
  "geometry": {"coordinates":[138.36660000000001,37.1184],"type":"Point"}
}