{
  "type": "Feature",
  "properties": {
    "gn:adm1_name":"Aichiken",
    "gn:adm2_name":"Inazawashi",
    "gn:name":"Oridukoumyoujichou",
    "iso:country":"JP",
    "wof:name":"492-8051",
    "wof:placetype":"postalcode"
},
  "geometry": {"coordinates":[136.82650000000001,35.2646],"type":"Point"}
}