{
  "type": "Feature",
  "properties": {
    "gn:adm1_name":"Tochigiken",
    "gn:adm2_name":"Nasugunkarasuyamamachi",
    "gn:name":"Koharazawa",
    "iso:country":"JP",
    "wof:name":"321-0615",
    "wof:placetype":"postalcode"
},
  "geometry": {"coordinates":[140.184,36.5997],"type":"Point"}
}