{
  "type": "Feature",
  "properties": {
    "gn:adm1_name":"Aichiken",
    "gn:adm2_name":"Nagoyashimizuhoku",
    "gn:name":"Komabachou",
    "iso:country":"JP",
    "wof:name":"467-0807",
    "wof:placetype":"postalcode"
},
  "geometry": {"coordinates":[136.93190000000001,35.1374],"type":"Point"}
}