{
  "type": "Feature",
  "properties": {
    "gn:adm1_name":"Nagasakiken",
    "gn:adm2_name":"Nagasakishi",
    "gn:name":"Kominemachi",
    "iso:country":"JP",
    "wof:name":"852-8125",
    "wof:placetype":"postalcode"
},
  "geometry": {"coordinates":[129.87209999999999,32.782],"type":"Point"}
}