{
  "type": "Feature",
  "properties": {
    "gn:adm1_name":"Gifuken",
    "gn:adm2_name":"Yourougunyourouchou",
    "gn:name":"Uwagata",
    "iso:country":"JP",
    "wof:name":"503-1245",
    "wof:placetype":"postalcode"
},
  "geometry": {"coordinates":[136.5376,35.3121],"type":"Point"}
}