{
  "type": "Feature",
  "properties": {
    "gn:adm1_name":"Tokushimaken",
    "gn:adm2_name":"Tokushimashi",
    "gn:name":"Kokufuchouhayabuchi",
    "iso:country":"JP",
    "wof:name":"779-3125",
    "wof:placetype":"postalcode"
},
  "geometry": {"coordinates":[134.48670000000001,34.0663],"type":"Point"}
}