{
  "type": "Feature",
  "properties": {
    "gn:adm1_name":"Fukuokaken",
    "gn:adm2_name":"Ongagun'Okagakimachi",
    "gn:name":"Takakura",
    "iso:country":"JP",
    "wof:name":"811-4234",
    "wof:placetype":"postalcode"
},
  "geometry": {"coordinates":[130.59829999999999,33.847],"type":"Point"}
}