{
  "type": "Feature",
  "properties": {
    "gn:adm1_name":"Niigataken",
    "gn:adm2_name":"Kashiwazakishi",
    "gn:name":"Furumachi",
    "iso:country":"JP",
    "wof:name":"945-1113",
    "wof:placetype":"postalcode"
},
  "geometry": {"coordinates":[138.57579999999999,37.3081],"type":"Point"}
}