{
  "type": "Feature",
  "properties": {
    "gn:adm1_name":"Niigataken",
    "gn:adm2_name":"Iwafunegunsanpokumachi",
    "gn:name":"Yamakumata",
    "iso:country":"JP",
    "wof:name":"959-3917",
    "wof:placetype":"postalcode"
},
  "geometry": {"coordinates":[139.66669999999999,38.4567],"type":"Point"}
}