{
  "type": "Feature",
  "properties": {
    "gn:adm1_name":"Toukyouto",
    "gn:adm2_name":"Kiyoseshi",
    "gn:name":"Asahigaoka",
    "iso:country":"JP",
    "wof:name":"204-0002",
    "wof:placetype":"postalcode"
},
  "geometry": {"coordinates":[139.5394,35.7957],"type":"Point"}
}