{
  "type": "Feature",
  "properties": {
    "gn:adm1_name":"Gunmaken",
    "gn:adm2_name":"Toneguntonemura",
    "gn:name":"Aoki",
    "iso:country":"JP",
    "wof:name":"378-0314",
    "wof:placetype":"postalcode"
},
  "geometry": {"coordinates":[139.16990000000001,36.6287],"type":"Point"}
}