{
  "type": "Feature",
  "properties": {
    "gn:adm1_name":"Okayamaken",
    "gn:adm2_name":"Takahashishi",
    "gn:name":"Shinmachi",
    "iso:country":"JP",
    "wof:name":"716-0012",
    "wof:placetype":"postalcode"
},
  "geometry": {"coordinates":[133.61689999999999,34.7982],"type":"Point"}
}