{
  "type": "Feature",
  "properties": {
    "gn:adm1_name":"Saitamaken",
    "gn:adm2_name":"Honjoushi",
    "gn:name":"Kowaze",
    "iso:country":"JP",
    "wof:name":"367-0011",
    "wof:placetype":"postalcode"
},
  "geometry": {"coordinates":[139.22909999999999,36.2434],"type":"Point"}
}