{
  "type": "Feature",
  "properties": {
    "gn:adm1_name":"Mieken",
    "gn:adm2_name":"Suzukashi",
    "gn:name":"Nomachihigashi",
    "iso:country":"JP",
    "wof:name":"510-0217",
    "wof:placetype":"postalcode"
},
  "geometry": {"coordinates":[136.5692,34.8507],"type":"Point"}
}