{
  "type": "Feature",
  "properties": {
    "gn:adm1_name":"Hiroshimaken",
    "gn:adm2_name":"Yamagatagunchiyodachou",
    "gn:name":"Kurasako",
    "iso:country":"JP",
    "wof:name":"731-1502",
    "wof:placetype":"postalcode"
},
  "geometry": {"coordinates":[132.50559999999999,34.7099],"type":"Point"}
}