{
  "type": "Feature",
  "properties": {
    "gn:adm1_name":"Yamanashiken",
    "gn:adm2_name":"Minamitsurugunfujikawaguchikomachi",
    "gn:name":"Kodachi",
    "iso:country":"JP",
    "wof:name":"401-0302",
    "wof:placetype":"postalcode"
},
  "geometry": {"coordinates":[138.7508,35.5028],"type":"Point"}
}