{
  "type": "Feature",
  "properties": {
    "gn:adm1_name":"Shizuokaken",
    "gn:adm2_name":"Kakegawashi",
    "gn:name":"Juukushu",
    "iso:country":"JP",
    "wof:name":"436-0057",
    "wof:placetype":"postalcode"
},
  "geometry": {"coordinates":[138.0042,34.7738],"type":"Point"}
}