{
  "type": "Feature",
  "properties": {
    "gn:adm1_name":"Saitamaken",
    "gn:adm2_name":"Irumashi",
    "gn:name":"Sayamadai",
    "iso:country":"JP",
    "wof:name":"358-0033",
    "wof:placetype":"postalcode"
},
  "geometry": {"coordinates":[139.36240000000001,35.8033],"type":"Point"}
}