{
  "type": "Feature",
  "properties": {
    "gn:adm1_name":"Niigataken",
    "gn:adm2_name":"Minamikanbaragunshitadamura",
    "gn:name":"Kasabori",
    "iso:country":"JP",
    "wof:name":"955-0123",
    "wof:placetype":"postalcode"
},
  "geometry": {"coordinates":[139.16370000000001,37.5027],"type":"Point"}
}