{
  "type": "Feature",
  "properties": {
    "gn:adm1_name":"Fukuokaken",
    "gn:adm2_name":"Maebarushi",
    "gn:name":"Higashi",
    "iso:country":"JP",
    "wof:name":"819-1122",
    "wof:placetype":"postalcode"
},
  "geometry": {"coordinates":[130.184,33.5328],"type":"Point"}
}