{
  "type": "Feature",
  "properties": {
    "gn:adm1_name":"Kumamotoken",
    "gn:adm2_name":"Kikuchishi",
    "gn:name":"Kikouji",
    "iso:country":"JP",
    "wof:name":"861-1315",
    "wof:placetype":"postalcode"
},
  "geometry": {"coordinates":[130.78370000000001,32.9485],"type":"Point"}
}