{
  "type": "Feature",
  "properties": {
    "gn:adm1_name":"Tottoriken",
    "gn:adm2_name":"Tottorishi",
    "gn:name":"Koeji",
    "iso:country":"JP",
    "wof:name":"689-1124",
    "wof:placetype":"postalcode"
},
  "geometry": {"coordinates":[134.2311,35.4384],"type":"Point"}
}