{
  "type": "Feature",
  "properties": {
    "gn:adm1_name":"Niigataken",
    "gn:adm2_name":"Nagaokashi",
    "gn:name":"Fujisawa",
    "iso:country":"JP",
    "wof:name":"940-2011",
    "wof:placetype":"postalcode"
},
  "geometry": {"coordinates":[138.84039999999999,37.4757],"type":"Point"}
}