{
  "type": "Feature",
  "properties": {
    "gn:adm1_name":"Shizuokaken",
    "gn:adm2_name":"Fujishi",
    "gn:name":"Kamiyaminami",
    "iso:country":"JP",
    "wof:name":"417-0823",
    "wof:placetype":"postalcode"
},
  "geometry": {"coordinates":[138.74520000000001,35.1502],"type":"Point"}
}