{
  "type": "Feature",
  "properties": {
    "gn:adm1_name":"Chibaken",
    "gn:adm2_name":"Nodashi",
    "gn:name":"Yamazaki",
    "iso:country":"JP",
    "wof:name":"278-0022",
    "wof:placetype":"postalcode"
},
  "geometry": {"coordinates":[139.89250000000001,35.9271],"type":"Point"}
}