{
  "type": "Feature",
  "properties": {
    "gn:adm1_name":"Okayamaken",
    "gn:adm2_name":"Odagunbiseichou",
    "gn:name":"Uto",
    "iso:country":"JP",
    "wof:name":"714-1405",
    "wof:placetype":"postalcode"
},
  "geometry": {"coordinates":[133.5778,34.6868],"type":"Point"}
}