{
  "type": "Feature",
  "properties": {
    "gn:adm1_name":"Toukyouto",
    "gn:adm2_name":"Shinagawaku",
    "gn:name":"Nishigotanda",
    "iso:country":"JP",
    "wof:name":"141-0031",
    "wof:placetype":"postalcode"
},
  "geometry": {"coordinates":[139.7184,35.6243],"type":"Point"}
}