{
  "type": "Feature",
  "properties": {
    "gn:adm1_name":"Kanagawaken",
    "gn:adm2_name":"Kawasakishiasaoku",
    "gn:name":"Kuriki",
    "iso:country":"JP",
    "wof:name":"215-0033",
    "wof:placetype":"postalcode"
},
  "geometry": {"coordinates":[139.4734,35.6051],"type":"Point"}
}