{
  "type": "Feature",
  "properties": {
    "gn:adm1_name":"Hyougoken",
    "gn:adm2_name":"Himejishi",
    "gn:name":"Nobusue",
    "iso:country":"JP",
    "wof:name":"670-0966",
    "wof:placetype":"postalcode"
},
  "geometry": {"coordinates":[134.68020000000001,34.8226],"type":"Point"}
}