{
  "type": "Feature",
  "properties": {
    "gn:adm1_name":"Toukyouto",
    "gn:adm2_name":"Setagayaku",
    "gn:name":"Ookura",
    "iso:country":"JP",
    "wof:name":"157-0074",
    "wof:placetype":"postalcode"
},
  "geometry": {"coordinates":[139.61199999999999,35.6304],"type":"Point"}
}