{
  "type": "Feature",
  "properties": {
    "gn:adm1_name":"Oosakafu",
    "gn:adm2_name":"Minamikawachiguntaishichou",
    "gn:name":"Yamada",
    "iso:country":"JP",
    "wof:name":"583-0992",
    "wof:placetype":"postalcode"
},
  "geometry": {"coordinates":[135.65170000000001,34.5161],"type":"Point"}
}