{
  "type": "Feature",
  "properties": {
    "gn:adm1_name":"Fukuokaken",
    "gn:adm2_name":"Itoshimagunshimamachi",
    "gn:name":"Kofuji",
    "iso:country":"JP",
    "wof:name":"819-1321",
    "wof:placetype":"postalcode"
},
  "geometry": {"coordinates":[130.16650000000001,33.562],"type":"Point"}
}