{
  "type": "Feature",
  "properties": {
    "gn:adm1_name":"Aichiken",
    "gn:adm2_name":"Anjoushi",
    "gn:name":"Shindenchou",
    "iso:country":"JP",
    "wof:name":"446-0061",
    "wof:placetype":"postalcode"
},
  "geometry": {"coordinates":[137.09309999999999,34.9671],"type":"Point"}
}