{
  "type": "Feature",
  "properties": {
    "gn:adm1_name":"Nagasakiken",
    "gn:adm2_name":"Higashisonogigunhigashisonogichou",
    "gn:name":"Minegou",
    "iso:country":"JP",
    "wof:name":"859-3806",
    "wof:placetype":"postalcode"
},
  "geometry": {"coordinates":[129.92349999999999,33.0454],"type":"Point"}
}