{
  "type": "Feature",
  "properties": {
    "gn:adm1_name":"Miyagiken",
    "gn:adm2_name":"Shiogamashi",
    "gn:name":"Kaedechou",
    "iso:country":"JP",
    "wof:name":"985-0084",
    "wof:placetype":"postalcode"
},
  "geometry": {"coordinates":[141.0309,38.3313],"type":"Point"}
}