{
  "type": "Feature",
  "properties": {
    "gn:adm1_name":"Kyoutofu",
    "gn:adm2_name":"Kyoutoshiukyouku",
    "gn:name":"Sagatoriimotofukatanichou",
    "iso:country":"JP",
    "wof:name":"616-8439",
    "wof:placetype":"postalcode"
},
  "geometry": {"coordinates":[135.6611,35.0312],"type":"Point"}
}