{
  "type": "Feature",
  "properties": {
    "gn:adm1_name":"Ehimeken",
    "gn:adm2_name":"Iyogunmasakichou",
    "gn:name":"Kitagawara",
    "iso:country":"JP",
    "wof:name":"791-3131",
    "wof:placetype":"postalcode"
},
  "geometry": {"coordinates":[132.70400000000001,33.8011],"type":"Point"}
}