{
  "type": "Feature",
  "properties": {
    "gn:adm1_name":"Miyagiken",
    "gn:adm2_name":"Kuriharagunkannarichou",
    "gn:name":"Iriuda",
    "iso:country":"JP",
    "wof:name":"989-5142",
    "wof:placetype":"postalcode"
},
  "geometry": {"coordinates":[141.07769999999999,38.8102],"type":"Point"}
}