{
  "type": "Feature",
  "properties": {
    "gn:adm1_name":"Kyoutofu",
    "gn:adm2_name":"Kyoutoshifushimiku",
    "gn:name":"Fukakusaichinotsubochou",
    "iso:country":"JP",
    "wof:name":"612-0012",
    "wof:placetype":"postalcode"
},
  "geometry": {"coordinates":[135.76910000000001,34.9684],"type":"Point"}
}