{
  "type": "Feature",
  "properties": {
    "gn:adm1_name":"Shimaneken",
    "gn:adm2_name":"Masudashi",
    "gn:name":"Kushirochou",
    "iso:country":"JP",
    "wof:name":"698-0001",
    "wof:placetype":"postalcode"
},
  "geometry": {"coordinates":[131.8459,34.7005],"type":"Point"}
}