{
  "type": "Feature",
  "properties": {
    "gn:adm1_name":"Chibaken",
    "gn:adm2_name":"Katorigunhikatamachi",
    "gn:name":"Seiwakou",
    "iso:country":"JP",
    "wof:name":"289-0507",
    "wof:placetype":"postalcode"
},
  "geometry": {"coordinates":[140.62270000000001,35.7713],"type":"Point"}
}