{
  "type": "Feature",
  "properties": {
    "gn:adm1_name":"Ibarakiken",
    "gn:adm2_name":"Kashimagun'Asahimura",
    "gn:name":"Takihama",
    "iso:country":"JP",
    "wof:name":"311-1423",
    "wof:placetype":"postalcode"
},
  "geometry": {"coordinates":[140.55500000000001,36.189],"type":"Point"}
}