{
  "type": "Feature",
  "properties": {
    "gn:adm1_name":"Yamanashiken",
    "gn:adm2_name":"Higashiyatsushirogun'Isawachou",
    "gn:name":"Kamihirai",
    "iso:country":"JP",
    "wof:name":"406-0025",
    "wof:placetype":"postalcode"
},
  "geometry": {"coordinates":[138.65969999999999,35.648],"type":"Point"}
}