{
  "type": "Feature",
  "properties": {
    "gn:adm1_name":"Miyazakiken",
    "gn:adm2_name":"Higashiusukiguntougouchou",
    "gn:name":"Yamage",
    "iso:country":"JP",
    "wof:name":"883-0109",
    "wof:placetype":"postalcode"
},
  "geometry": {"coordinates":[131.50550000000001,32.3951],"type":"Point"}
}