{
  "type": "Feature",
  "properties": {
    "gn:adm1_name":"Okayamaken",
    "gn:adm2_name":"Kawakamigunbicchuuchou",
    "gn:name":"Nishiyuno",
    "iso:country":"JP",
    "wof:name":"716-0322",
    "wof:placetype":"postalcode"
},
  "geometry": {"coordinates":[133.40719999999999,34.8435],"type":"Point"}
}