{
  "type": "Feature",
  "properties": {
    "gn:adm1_name":"Kanagawaken",
    "gn:adm2_name":"Kawasakishinakaharaku",
    "gn:name":"Imainishimachi",
    "iso:country":"JP",
    "wof:name":"211-0066",
    "wof:placetype":"postalcode"
},
  "geometry": {"coordinates":[139.64830000000001,35.5751],"type":"Point"}
}