{
  "type": "Feature",
  "properties": {
    "gn:adm1_name":"Kumamotoken",
    "gn:adm2_name":"Tamanagunkikusuimachi",
    "gn:name":"Segawa",
    "iso:country":"JP",
    "wof:name":"865-0135",
    "wof:placetype":"postalcode"
},
  "geometry": {"coordinates":[130.6045,32.9666],"type":"Point"}
}