{
  "type": "Feature",
  "properties": {
    "gn:adm1_name":"Okayamaken",
    "gn:adm2_name":"Katsutagunnagichou",
    "gn:name":"Kaki",
    "iso:country":"JP",
    "wof:name":"708-1312",
    "wof:placetype":"postalcode"
},
  "geometry": {"coordinates":[134.18260000000001,35.1107],"type":"Point"}
}