{
  "type": "Feature",
  "properties": {
    "gn:adm1_name":"Hiroshimaken",
    "gn:adm2_name":"Kamogunkurosechou",
    "gn:name":"Nominoo",
    "iso:country":"JP",
    "wof:name":"724-0622",
    "wof:placetype":"postalcode"
},
  "geometry": {"coordinates":[132.69229999999999,34.3318],"type":"Point"}
}