{
  "type": "Feature",
  "properties": {
    "gn:adm1_name":"Fukuokaken",
    "gn:adm2_name":"Miyakogunkandamachi",
    "gn:name":"Konoegaoka",
    "iso:country":"JP",
    "wof:name":"800-0356",
    "wof:placetype":"postalcode"
},
  "geometry": {"coordinates":[130.9769,33.7661],"type":"Point"}
}