{
  "type": "Feature",
  "properties": {
    "gn:adm1_name":"Niigataken",
    "gn:adm2_name":"Sadogun'Aikawamachi",
    "gn:name":"Ishige",
    "iso:country":"JP",
    "wof:name":"952-2224",
    "wof:placetype":"postalcode"
},
  "geometry": {"coordinates":[138.30510000000001,38.1612],"type":"Point"}
}