{
  "type": "Feature",
  "properties": {
    "gn:adm1_name":"Aichiken",
    "gn:adm2_name":"Amagunjimokujichou",
    "gn:name":"Shouji",
    "iso:country":"JP",
    "wof:name":"490-1106",
    "wof:placetype":"postalcode"
},
  "geometry": {"coordinates":[136.81209999999999,35.2063],"type":"Point"}
}