{
  "type": "Feature",
  "properties": {
    "gn:adm1_name":"Kanagawaken",
    "gn:adm2_name":"Yokohamashitsudukiku",
    "gn:name":"Edahigashichou",
    "iso:country":"JP",
    "wof:name":"224-0004",
    "wof:placetype":"postalcode"
},
  "geometry": {"coordinates":[139.56710000000001,35.5541],"type":"Point"}
}