{
  "type": "Feature",
  "properties": {
    "gn:adm1_name":"Oosakafu",
    "gn:adm2_name":"Ibarakishi",
    "gn:name":"Soujijiekimaechou",
    "iso:country":"JP",
    "wof:name":"567-0802",
    "wof:placetype":"postalcode"
},
  "geometry": {"coordinates":[135.58369999999999,34.828],"type":"Point"}
}