{
  "type": "Feature",
  "properties": {
    "gn:adm1_name":"Tottoriken",
    "gn:adm2_name":"Touhakuguntomarison",
    "gn:name":"Tomari",
    "iso:country":"JP",
    "wof:name":"689-0601",
    "wof:placetype":"postalcode"
},
  "geometry": {"coordinates":[133.94040000000001,35.5152],"type":"Point"}
}