{
  "type": "Feature",
  "properties": {
    "gn:adm1_name":"Ehimeken",
    "gn:adm2_name":"Ochigunyoshiumichou",
    "gn:name":"Fukuda",
    "iso:country":"JP",
    "wof:name":"794-2103",
    "wof:placetype":"postalcode"
},
  "geometry": {"coordinates":[133.04490000000001,34.1545],"type":"Point"}
}