{
  "type": "Feature",
  "properties": {
    "gn:adm1_name":"Sagaken",
    "gn:adm2_name":"Kishimagunkouhokumachi",
    "gn:name":"Hacchou",
    "iso:country":"JP",
    "wof:name":"849-0504",
    "wof:placetype":"postalcode"
},
  "geometry": {"coordinates":[130.1506,33.1988],"type":"Point"}
}