{
  "type": "Feature",
  "properties": {
    "gn:adm1_name":"Hiroshimaken",
    "gn:adm2_name":"Kamogunkouchichou",
    "gn:name":"Koudo",
    "iso:country":"JP",
    "wof:name":"729-1104",
    "wof:placetype":"postalcode"
},
  "geometry": {"coordinates":[132.8339,34.4975],"type":"Point"}
}