{
  "type": "Feature",
  "properties": {
    "gn:adm1_name":"Naganoken",
    "gn:adm2_name":"Higashichikumagun'Akashinamachi",
    "gn:name":"Nakagawate",
    "iso:country":"JP",
    "wof:name":"399-7102",
    "wof:placetype":"postalcode"
},
  "geometry": {"coordinates":[137.93469999999999,36.3466],"type":"Point"}
}