{
  "type": "Feature",
  "properties": {
    "gn:adm1_name":"Kagoshimaken",
    "gn:adm2_name":"Kanoyashi",
    "gn:name":"Kamidanichou",
    "iso:country":"JP",
    "wof:name":"893-0061",
    "wof:placetype":"postalcode"
},
  "geometry": {"coordinates":[130.84100000000001,31.3926],"type":"Point"}
}