{
  "type": "Feature",
  "properties": {
    "gn:adm1_name":"Gunmaken",
    "gn:adm2_name":"Ootashi",
    "gn:name":"Takaramachi",
    "iso:country":"JP",
    "wof:name":"373-0042",
    "wof:placetype":"postalcode"
},
  "geometry": {"coordinates":[139.33240000000001,36.2889],"type":"Point"}
}