{
  "type": "Feature",
  "properties": {
    "gn:adm1_name":"Mieken",
    "gn:adm2_name":"Matsusakashi",
    "gn:name":"Hikarichou",
    "iso:country":"JP",
    "wof:name":"515-0051",
    "wof:placetype":"postalcode"
},
  "geometry": {"coordinates":[136.5172,34.5489],"type":"Point"}
}