{
  "type": "Feature",
  "properties": {
    "gn:adm1_name":"Chibaken",
    "gn:adm2_name":"Kisaradushi",
    "gn:name":"Kiyomidaiminami",
    "iso:country":"JP",
    "wof:name":"292-0042",
    "wof:placetype":"postalcode"
},
  "geometry": {"coordinates":[139.9539,35.3802],"type":"Point"}
}