{
  "type": "Feature",
  "properties": {
    "gn:adm1_name":"Okayamaken",
    "gn:adm2_name":"Okayamashi",
    "gn:name":"Suzaki",
    "iso:country":"JP",
    "wof:name":"702-8042",
    "wof:placetype":"postalcode"
},
  "geometry": {"coordinates":[133.94589999999999,34.6232],"type":"Point"}
}