{
  "type": "Feature",
  "properties": {
    "gn:adm1_name":"Okayamaken",
    "gn:adm2_name":"Odagunyakagechou",
    "gn:name":"Nishigawamo",
    "iso:country":"JP",
    "wof:name":"714-1222",
    "wof:placetype":"postalcode"
},
  "geometry": {"coordinates":[133.5667,34.6232],"type":"Point"}
}