{
  "type": "Feature",
  "properties": {
    "gn:adm1_name":"Oosakafu",
    "gn:adm2_name":"Hirakatashi",
    "gn:name":"Nakamiyanishinochou",
    "iso:country":"JP",
    "wof:name":"573-0021",
    "wof:placetype":"postalcode"
},
  "geometry": {"coordinates":[135.66210000000001,34.817],"type":"Point"}
}