{
  "type": "Feature",
  "properties": {
    "gn:adm1_name":"Oosakafu",
    "gn:adm2_name":"Higashioosakashi",
    "gn:name":"Ajirominami",
    "iso:country":"JP",
    "wof:name":"577-0842",
    "wof:placetype":"postalcode"
},
  "geometry": {"coordinates":[135.56290000000001,34.6603],"type":"Point"}
}