{
  "type": "Feature",
  "properties": {
    "gn:adm1_name":"Ibarakiken",
    "gn:adm2_name":"Higashiibarakigunkatsuramura",
    "gn:name":"Magone",
    "iso:country":"JP",
    "wof:name":"311-4334",
    "wof:placetype":"postalcode"
},
  "geometry": {"coordinates":[140.3407,36.5084],"type":"Point"}
}