{
  "type": "Feature",
  "properties": {
    "gn:adm1_name":"Chibaken",
    "gn:adm2_name":"Katoriguntounoshoumachi",
    "gn:name":"Touwada",
    "iso:country":"JP",
    "wof:name":"289-0636",
    "wof:placetype":"postalcode"
},
  "geometry": {"coordinates":[140.63800000000001,35.7939],"type":"Point"}
}