{
  "type": "Feature",
  "properties": {
    "gn:adm1_name":"Mieken",
    "gn:adm2_name":"Suzukashi",
    "gn:name":"Fukamizochou",
    "iso:country":"JP",
    "wof:name":"519-0321",
    "wof:placetype":"postalcode"
},
  "geometry": {"coordinates":[136.5051,34.9228],"type":"Point"}
}