{
  "type": "Feature",
  "properties": {
    "gn:adm1_name":"Fukuiken",
    "gn:adm2_name":"Sakaigunmikunichou",
    "gn:name":"Kitahonmachi",
    "iso:country":"JP",
    "wof:name":"913-0046",
    "wof:placetype":"postalcode"
},
  "geometry": {"coordinates":[136.14859999999999,36.2153],"type":"Point"}
}