{
  "type": "Feature",
  "properties": {
    "gn:adm1_name":"Chibaken",
    "gn:adm2_name":"Ichiharashi",
    "gn:name":"Nara",
    "iso:country":"JP",
    "wof:name":"290-0164",
    "wof:placetype":"postalcode"
},
  "geometry": {"coordinates":[140.22049999999999,35.4925],"type":"Point"}
}