{
  "type": "Feature",
  "properties": {
    "gn:adm1_name":"Kyoutofu",
    "gn:adm2_name":"Kyoutoshinakagyouku",
    "gn:name":"Kabutoyachou",
    "iso:country":"JP",
    "wof:name":"604-8114",
    "wof:placetype":"postalcode"
},
  "geometry": {"coordinates":[135.76320000000001,35.0068],"type":"Point"}
}