{
  "type": "Feature",
  "properties": {
    "gn:adm1_name":"Oosakafu",
    "gn:adm2_name":"Oosakashisumiyoshiku",
    "gn:name":"Shimizugaoka",
    "iso:country":"JP",
    "wof:name":"558-0033",
    "wof:placetype":"postalcode"
},
  "geometry": {"coordinates":[135.4915,34.6023],"type":"Point"}
}