{
  "type": "Feature",
  "properties": {
    "gn:adm1_name":"Tokushimaken",
    "gn:adm2_name":"Tokushimashi",
    "gn:name":"Sako4banchou",
    "iso:country":"JP",
    "wof:name":"770-0024",
    "wof:placetype":"postalcode"
},
  "geometry": {"coordinates":[134.5334,34.0783],"type":"Point"}
}