{
  "type": "Feature",
  "properties": {
    "gn:adm1_name":"Hyougoken",
    "gn:adm2_name":"Mikatagunmikatachou",
    "gn:name":"Hirano",
    "iso:country":"JP",
    "wof:name":"667-1523",
    "wof:placetype":"postalcode"
},
  "geometry": {"coordinates":[134.53749999999999,35.4383],"type":"Point"}
}