{
  "type": "Feature",
  "properties": {
    "gn:adm1_name":"Naraken",
    "gn:adm2_name":"Yoshinogunshimoichichou",
    "gn:name":"Tateishi",
    "iso:country":"JP",
    "wof:name":"638-0013",
    "wof:placetype":"postalcode"
},
  "geometry": {"coordinates":[135.82830000000001,34.3556],"type":"Point"}
}