{
  "type": "Feature",
  "properties": {
    "gn:adm1_name":"Okayamaken",
    "gn:adm2_name":"Akaiwagunsanyouchou",
    "gn:name":"Shimonibo",
    "iso:country":"JP",
    "wof:name":"709-0836",
    "wof:placetype":"postalcode"
},
  "geometry": {"coordinates":[133.99959999999999,34.7722],"type":"Point"}
}