{
  "type": "Feature",
  "properties": {
    "gn:adm1_name":"Shigaken",
    "gn:adm2_name":"Oumihachimanshi",
    "gn:name":"Nishihongouchouhigashi",
    "iso:country":"JP",
    "wof:name":"523-0818",
    "wof:placetype":"postalcode"
},
  "geometry": {"coordinates":[136.1095,35.1236],"type":"Point"}
}