{
  "type": "Feature",
  "properties": {
    "gn:adm1_name":"Shizuokaken",
    "gn:adm2_name":"Shizuokashi",
    "gn:name":"Aimata",
    "iso:country":"JP",
    "wof:name":"421-1307",
    "wof:placetype":"postalcode"
},
  "geometry": {"coordinates":[138.24039999999999,35.0331],"type":"Point"}
}