{
  "type": "Feature",
  "properties": {
    "gn:adm1_name":"Nagasakiken",
    "gn:adm2_name":"Kitatakakigun'Iimorichou",
    "gn:name":"Ushirodamyou",
    "iso:country":"JP",
    "wof:name":"854-1105",
    "wof:placetype":"postalcode"
},
  "geometry": {"coordinates":[130.03059999999999,32.7686],"type":"Point"}
}