{
  "type": "Feature",
  "properties": {
    "gn:adm1_name":"Kouchiken",
    "gn:adm2_name":"Akishi",
    "gn:name":"Kawakitaotsu",
    "iso:country":"JP",
    "wof:name":"784-0044",
    "wof:placetype":"postalcode"
},
  "geometry": {"coordinates":[133.91739999999999,33.5246],"type":"Point"}
}