{
  "type": "Feature",
  "properties": {
    "gn:adm1_name":"Kyoutofu",
    "gn:adm2_name":"Yawatashi",
    "gn:name":"Minoyamakousui",
    "iso:country":"JP",
    "wof:name":"614-8279",
    "wof:placetype":"postalcode"
},
  "geometry": {"coordinates":[135.7099,34.8542],"type":"Point"}
}