{
  "type": "Feature",
  "properties": {
    "gn:adm1_name":"Hiroshimaken",
    "gn:adm2_name":"Fuchuushi",
    "gn:name":"Kinoyamachou",
    "iso:country":"JP",
    "wof:name":"729-3211",
    "wof:placetype":"postalcode"
},
  "geometry": {"coordinates":[133.20410000000001,34.6279],"type":"Point"}
}