{
  "type": "Feature",
  "properties": {
    "gn:adm1_name":"Toyamaken",
    "gn:adm2_name":"Nishitonamigunfukumitsumachi",
    "gn:name":"Oonishi",
    "iso:country":"JP",
    "wof:name":"939-1752",
    "wof:placetype":"postalcode"
},
  "geometry": {"coordinates":[136.8775,36.5245],"type":"Point"}
}