{
  "type": "Feature",
  "properties": {
    "gn:adm1_name":"Okayamaken",
    "gn:adm2_name":"Akaiwagunyoshiichou",
    "gn:name":"Aida",
    "iso:country":"JP",
    "wof:name":"701-2443",
    "wof:placetype":"postalcode"
},
  "geometry": {"coordinates":[133.99809999999999,34.8541],"type":"Point"}
}