{
  "type": "Feature",
  "properties": {
    "gn:adm1_name":"Kyoutofu",
    "gn:adm2_name":"Kyoutoshishimogyouku",
    "gn:name":"Shichijougoshonouchikitamachi",
    "iso:country":"JP",
    "wof:name":"600-8861",
    "wof:placetype":"postalcode"
},
  "geometry": {"coordinates":[135.7313,34.9871],"type":"Point"}
}