{
  "type": "Feature",
  "properties": {
    "gn:adm1_name":"Gifuken",
    "gn:adm2_name":"Kaidugunkaiduchou",
    "gn:name":"Naiki",
    "iso:country":"JP",
    "wof:name":"503-0641",
    "wof:placetype":"postalcode"
},
  "geometry": {"coordinates":[136.64859999999999,35.2131],"type":"Point"}
}