{
  "type": "Feature",
  "properties": {
    "gn:adm1_name":"Kumamotoken",
    "gn:adm2_name":"Yatsushirogunmiyaharamachi",
    "gn:name":"Miyaharamachi",
    "iso:country":"JP",
    "wof:name":"869-4608",
    "wof:placetype":"postalcode"
},
  "geometry": {"coordinates":[130.6823,32.556],"type":"Point"}
}