{
  "type": "Feature",
  "properties": {
    "gn:adm1_name":"Tokushimaken",
    "gn:adm2_name":"Narutoshi",
    "gn:name":"Ooasachoutakabatake",
    "iso:country":"JP",
    "wof:name":"779-0305",
    "wof:placetype":"postalcode"
},
  "geometry": {"coordinates":[134.53120000000001,34.1536],"type":"Point"}
}