{
  "type": "Feature",
  "properties": {
    "gn:adm1_name":"Okayamaken",
    "gn:adm2_name":"Akaiwagunyoshiichou",
    "gn:name":"Fukuda",
    "iso:country":"JP",
    "wof:name":"701-2504",
    "wof:placetype":"postalcode"
},
  "geometry": {"coordinates":[134.0864,34.9054],"type":"Point"}
}