{
  "type": "Feature",
  "properties": {
    "gn:adm1_name":"Hyougoken",
    "gn:adm2_name":"Sasayamashi",
    "gn:name":"Kamijuku",
    "iso:country":"JP",
    "wof:name":"669-2415",
    "wof:placetype":"postalcode"
},
  "geometry": {"coordinates":[135.28829999999999,35.0678],"type":"Point"}
}