{
  "type": "Feature",
  "properties": {
    "gn:adm1_name":"Ooitaken",
    "gn:adm2_name":"Beppushi",
    "gn:name":"Yanagi",
    "iso:country":"JP",
    "wof:name":"874-0811",
    "wof:placetype":"postalcode"
},
  "geometry": {"coordinates":[131.49600000000001,33.2581],"type":"Point"}
}