{
  "type": "Feature",
  "properties": {
    "gn:adm1_name":"Shizuokaken",
    "gn:adm2_name":"Shizuokashi",
    "gn:name":"Shimizudoubayashi",
    "iso:country":"JP",
    "wof:name":"424-0851",
    "wof:placetype":"postalcode"
},
  "geometry": {"coordinates":[138.47720000000001,35.0062],"type":"Point"}
}