{
  "type": "Feature",
  "properties": {
    "gn:adm1_name":"Chibaken",
    "gn:adm2_name":"Futtsushi",
    "gn:name":"Oshikiri",
    "iso:country":"JP",
    "wof:name":"299-1757",
    "wof:placetype":"postalcode"
},
  "geometry": {"coordinates":[139.92099999999999,35.2164],"type":"Point"}
}