{
  "type": "Feature",
  "properties": {
    "gn:adm1_name":"Ibarakiken",
    "gn:adm2_name":"Niiharigunniiharimura",
    "gn:name":"Fujisawashinden",
    "iso:country":"JP",
    "wof:name":"300-4116",
    "wof:placetype":"postalcode"
},
  "geometry": {"coordinates":[140.1951,36.0774],"type":"Point"}
}