{
  "type": "Feature",
  "properties": {
    "gn:adm1_name":"Niigataken",
    "gn:adm2_name":"Higashikanbaragunkamikawamura",
    "gn:name":"Daigurakou",
    "iso:country":"JP",
    "wof:name":"959-4513",
    "wof:placetype":"postalcode"
},
  "geometry": {"coordinates":[139.56379999999999,37.5329],"type":"Point"}
}