{
  "type": "Feature",
  "properties": {
    "gn:adm1_name":"Yamagataken",
    "gn:adm2_name":"Kaminoyamashi",
    "gn:name":"Kubokawa",
    "iso:country":"JP",
    "wof:name":"999-3215",
    "wof:placetype":"postalcode"
},
  "geometry": {"coordinates":[140.3228,38.1002],"type":"Point"}
}