{
  "type": "Feature",
  "properties": {
    "gn:adm1_name":"Toukyouto",
    "gn:adm2_name":"Setagayaku",
    "gn:name":"Hanegi",
    "iso:country":"JP",
    "wof:name":"156-0042",
    "wof:placetype":"postalcode"
},
  "geometry": {"coordinates":[139.65799999999999,35.6658],"type":"Point"}
}