{
  "type": "Feature",
  "properties": {
    "gn:adm1_name":"Kyoutofu",
    "gn:adm2_name":"Kyoutoshishimogyouku",
    "gn:name":"Chuudoujikitachou",
    "iso:country":"JP",
    "wof:name":"600-8812",
    "wof:placetype":"postalcode"
},
  "geometry": {"coordinates":[135.74109999999999,34.9975],"type":"Point"}
}