{
  "type": "Feature",
  "properties": {
    "gn:adm1_name":"Tokushimaken",
    "gn:adm2_name":"Tokushimashi",
    "gn:name":"Kawauchichou(Suzuekita)",
    "iso:country":"JP",
    "wof:name":"771-0123",
    "wof:placetype":"postalcode"
},
  "geometry": {"coordinates":[134.57310000000001,34.0991],"type":"Point"}
}