{
  "type": "Feature",
  "properties": {
    "gn:adm1_name":"Hiroshimaken",
    "gn:adm2_name":"Kureshi",
    "gn:name":"Nikoukyouchou",
    "iso:country":"JP",
    "wof:name":"737-0816",
    "wof:placetype":"postalcode"
},
  "geometry": {"coordinates":[132.5607,34.2615],"type":"Point"}
}