{
  "type": "Feature",
  "properties": {
    "gn:adm1_name":"Fukuokaken",
    "gn:adm2_name":"Kitakyuushuushikokurakitaku",
    "gn:name":"Higashijounomachi",
    "iso:country":"JP",
    "wof:name":"802-0054",
    "wof:placetype":"postalcode"
},
  "geometry": {"coordinates":[130.88900000000001,33.8585],"type":"Point"}
}