{
  "type": "Feature",
  "properties": {
    "gn:adm1_name":"Kyoutofu",
    "gn:adm2_name":"Otokunigun'Ooyamazakichou",
    "gn:name":"Shimoueno",
    "iso:country":"JP",
    "wof:name":"618-0081",
    "wof:placetype":"postalcode"
},
  "geometry": {"coordinates":[135.69820000000001,34.908],"type":"Point"}
}