{
  "type": "Feature",
  "properties": {
    "gn:adm1_name":"Kyoutofu",
    "gn:adm2_name":"Kasagun'Ooechou",
    "gn:name":"Bitou",
    "iso:country":"JP",
    "wof:name":"620-0356",
    "wof:placetype":"postalcode"
},
  "geometry": {"coordinates":[135.15119999999999,35.3736],"type":"Point"}
}