{
  "type": "Feature",
  "properties": {
    "gn:adm1_name":"Ibarakiken",
    "gn:adm2_name":"Kashimagun'Asahimura",
    "gn:name":"Hiyamizu",
    "iso:country":"JP",
    "wof:name":"311-1413",
    "wof:placetype":"postalcode"
},
  "geometry": {"coordinates":[140.56139999999999,36.2089],"type":"Point"}
}