{
  "type": "Feature",
  "properties": {
    "gn:adm1_name":"Shizuokaken",
    "gn:adm2_name":"Yaidushi",
    "gn:name":"Obama",
    "iso:country":"JP",
    "wof:name":"425-0011",
    "wof:placetype":"postalcode"
},
  "geometry": {"coordinates":[138.33949999999999,34.8946],"type":"Point"}
}