{
  "type": "Feature",
  "properties": {
    "gn:adm1_name":"Hiroshimaken",
    "gn:adm2_name":"Jinsekigunsanwachou",
    "gn:name":"Age",
    "iso:country":"JP",
    "wof:name":"720-1521",
    "wof:placetype":"postalcode"
},
  "geometry": {"coordinates":[133.22890000000001,34.7324],"type":"Point"}
}