{
  "type": "Feature",
  "properties": {
    "gn:adm1_name":"Gunmaken",
    "gn:adm2_name":"Tomiokashi",
    "gn:name":"Ooshima",
    "iso:country":"JP",
    "wof:name":"370-2335",
    "wof:placetype":"postalcode"
},
  "geometry": {"coordinates":[138.8622,36.2397],"type":"Point"}
}