{
  "type": "Feature",
  "properties": {
    "gn:adm1_name":"Fukuiken",
    "gn:adm2_name":"Yoshidagun'Eiheijichou",
    "gn:name":"Ichinono",
    "iso:country":"JP",
    "wof:name":"910-1226",
    "wof:placetype":"postalcode"
},
  "geometry": {"coordinates":[136.33189999999999,36.0664],"type":"Point"}
}