{
  "type": "Feature",
  "properties": {
    "gn:adm1_name":"Wakayamaken",
    "gn:adm2_name":"Goboushi",
    "gn:name":"Nadachounoshima",
    "iso:country":"JP",
    "wof:name":"644-0023",
    "wof:placetype":"postalcode"
},
  "geometry": {"coordinates":[135.17189999999999,33.8438],"type":"Point"}
}