{
  "type": "Feature",
  "properties": {
    "gn:adm1_name":"Yamaguchiken",
    "gn:adm2_name":"Shimonosekishi",
    "gn:name":"Tomitouchou",
    "iso:country":"JP",
    "wof:name":"759-6613",
    "wof:placetype":"postalcode"
},
  "geometry": {"coordinates":[130.92240000000001,34.0212],"type":"Point"}
}