{
  "type": "Feature",
  "properties": {
    "gn:adm1_name":"Niigataken",
    "gn:adm2_name":"Santougunkoshijimachi",
    "gn:name":"Nishino",
    "iso:country":"JP",
    "wof:name":"949-5409",
    "wof:placetype":"postalcode"
},
  "geometry": {"coordinates":[138.804,37.4201],"type":"Point"}
}