{
  "type": "Feature",
  "properties": {
    "gn:adm1_name":"Ishikawaken",
    "gn:adm2_name":"Hakuigunshikamachi",
    "gn:name":"Anaguchi",
    "iso:country":"JP",
    "wof:name":"925-0132",
    "wof:placetype":"postalcode"
},
  "geometry": {"coordinates":[136.80369999999999,36.995],"type":"Point"}
}