{
  "type": "Feature",
  "properties": {
    "gn:adm1_name":"Niigataken",
    "gn:adm2_name":"Jouetsushi",
    "gn:name":"Daigakumae",
    "iso:country":"JP",
    "wof:name":"943-0810",
    "wof:placetype":"postalcode"
},
  "geometry": {"coordinates":[138.22980000000001,37.1348],"type":"Point"}
}