{
  "type": "Feature",
  "properties": {
    "gn:adm1_name":"Niigataken",
    "gn:adm2_name":"Higashikanbaragunkamikawamura",
    "gn:name":"Hinokawaotsu",
    "iso:country":"JP",
    "wof:name":"959-4539",
    "wof:placetype":"postalcode"
},
  "geometry": {"coordinates":[139.43950000000001,37.6118],"type":"Point"}
}