{
  "type": "Feature",
  "properties": {
    "gn:adm1_name":"Naganoken",
    "gn:adm2_name":"Matsumotoshi",
    "gn:name":"Kaichi",
    "iso:country":"JP",
    "wof:name":"390-0876",
    "wof:placetype":"postalcode"
},
  "geometry": {"coordinates":[137.96940000000001,36.2422],"type":"Point"}
}