{
  "type": "Feature",
  "properties": {
    "gn:adm1_name":"Ibarakiken",
    "gn:adm2_name":"Ryuugasakishi",
    "gn:name":"Mizumon",
    "iso:country":"JP",
    "wof:name":"301-0013",
    "wof:placetype":"postalcode"
},
  "geometry": {"coordinates":[140.17500000000001,35.9031],"type":"Point"}
}