{
  "type": "Feature",
  "properties": {
    "gn:adm1_name":"Tottoriken",
    "gn:adm2_name":"Ketakagunshikanochou",
    "gn:name":"Kobesshiyo",
    "iso:country":"JP",
    "wof:name":"689-0413",
    "wof:placetype":"postalcode"
},
  "geometry": {"coordinates":[134.03059999999999,35.451],"type":"Point"}
}