{
  "type": "Feature",
  "properties": {
    "gn:adm1_name":"Hiroshimaken",
    "gn:adm2_name":"Akigunkaitachou",
    "gn:name":"Kubomachi",
    "iso:country":"JP",
    "wof:name":"736-0046",
    "wof:placetype":"postalcode"
},
  "geometry": {"coordinates":[132.52930000000001,34.3709],"type":"Point"}
}