{
  "type": "Feature",
  "properties": {
    "gn:adm1_name":"Gifuken",
    "gn:adm2_name":"Yoshikigunfurukawachou",
    "gn:name":"Nakano",
    "iso:country":"JP",
    "wof:name":"509-4262",
    "wof:placetype":"postalcode"
},
  "geometry": {"coordinates":[137.1583,36.2458],"type":"Point"}
}