{
  "type": "Feature",
  "properties": {
    "gn:adm1_name":"Shimaneken",
    "gn:adm2_name":"Hikawagunsadachou",
    "gn:name":"Miyauchi",
    "iso:country":"JP",
    "wof:name":"693-0503",
    "wof:placetype":"postalcode"
},
  "geometry": {"coordinates":[132.7371,35.2367],"type":"Point"}
}