{
  "type": "Feature",
  "properties": {
    "gn:adm1_name":"Hyougoken",
    "gn:adm2_name":"Ashiyashi",
    "gn:name":"Matsunouchichou",
    "iso:country":"JP",
    "wof:name":"659-0094",
    "wof:placetype":"postalcode"
},
  "geometry": {"coordinates":[135.303,34.7351],"type":"Point"}
}