{
  "type": "Feature",
  "properties": {
    "gn:adm1_name":"Kanagawaken",
    "gn:adm2_name":"Hiratsukashi",
    "gn:name":"Ookami",
    "iso:country":"JP",
    "wof:name":"254-0012",
    "wof:placetype":"postalcode"
},
  "geometry": {"coordinates":[139.36600000000001,35.3869],"type":"Point"}
}