{
  "type": "Feature",
  "properties": {
    "gn:adm1_name":"Niigataken",
    "gn:adm2_name":"Kitakanbaragunkajikawamura",
    "gn:name":"Hirayama",
    "iso:country":"JP",
    "wof:name":"959-2412",
    "wof:placetype":"postalcode"
},
  "geometry": {"coordinates":[139.37180000000001,37.995],"type":"Point"}
}