{
  "type": "Feature",
  "properties": {
    "gn:adm1_name":"Shigaken",
    "gn:adm2_name":"Gamougunryuuouchou",
    "gn:name":"Ukawa",
    "iso:country":"JP",
    "wof:name":"520-2562",
    "wof:placetype":"postalcode"
},
  "geometry": {"coordinates":[136.1112,35.0743],"type":"Point"}
}