{
  "type": "Feature",
  "properties": {
    "gn:adm1_name":"Kumamotoken",
    "gn:adm2_name":"Asogunsoyoumachi",
    "gn:name":"Shimoyama",
    "iso:country":"JP",
    "wof:name":"861-3932",
    "wof:placetype":"postalcode"
},
  "geometry": {"coordinates":[131.20699999999999,32.7589],"type":"Point"}
}