{
  "type": "Feature",
  "properties": {
    "gn:adm1_name":"Niigataken",
    "gn:adm2_name":"Minamiuonumagunshiozawamachi",
    "gn:name":"Hayakawa",
    "iso:country":"JP",
    "wof:name":"949-6543",
    "wof:placetype":"postalcode"
},
  "geometry": {"coordinates":[138.87389999999999,37.028],"type":"Point"}
}