{
  "type": "Feature",
  "properties": {
    "gn:adm1_name":"Niigataken",
    "gn:adm2_name":"Nishikubikigunnoumachi",
    "gn:name":"Mizoo",
    "iso:country":"JP",
    "wof:name":"949-1328",
    "wof:placetype":"postalcode"
},
  "geometry": {"coordinates":[138.05090000000001,37.0618],"type":"Point"}
}