{
  "type": "Feature",
  "properties": {
    "gn:adm1_name":"Yamaguchiken",
    "gn:adm2_name":"Hikarishi",
    "gn:name":"Kizono",
    "iso:country":"JP",
    "wof:name":"743-0046",
    "wof:placetype":"postalcode"
},
  "geometry": {"coordinates":[131.9297,33.9768],"type":"Point"}
}