{
  "type": "Feature",
  "properties": {
    "gn:adm1_name":"Kyoutofu",
    "gn:adm2_name":"Yawatashi",
    "gn:name":"Shimonaraimazato",
    "iso:country":"JP",
    "wof:name":"614-8147",
    "wof:placetype":"postalcode"
},
  "geometry": {"coordinates":[135.72409999999999,34.8705],"type":"Point"}
}