{
  "type": "Feature",
  "properties": {
    "gn:adm1_name":"Hyougoken",
    "gn:adm2_name":"Koubeshihigashinadaku",
    "gn:name":"Uozakikitamachi",
    "iso:country":"JP",
    "wof:name":"658-0082",
    "wof:placetype":"postalcode"
},
  "geometry": {"coordinates":[135.27330000000001,34.718],"type":"Point"}
}