{
  "type": "Feature",
  "properties": {
    "gn:adm1_name":"Kyoutofu",
    "gn:adm2_name":"Kyoutoshiukyouku",
    "gn:name":"Umegahatakagarichou",
    "iso:country":"JP",
    "wof:name":"616-8275",
    "wof:placetype":"postalcode"
},
  "geometry": {"coordinates":[135.68510000000001,35.0416],"type":"Point"}
}