{
  "type": "Feature",
  "properties": {
    "gn:adm1_name":"Niigataken",
    "gn:adm2_name":"Kitakanbaragunsuibaramachi",
    "gn:name":"Suibara",
    "iso:country":"JP",
    "wof:name":"959-2013",
    "wof:placetype":"postalcode"
},
  "geometry": {"coordinates":[139.23509999999999,37.8499],"type":"Point"}
}