{
  "type": "Feature",
  "properties": {
    "gn:adm1_name":"Aichiken",
    "gn:adm2_name":"Nisshinshi",
    "gn:name":"Sakae",
    "iso:country":"JP",
    "wof:name":"470-0113",
    "wof:placetype":"postalcode"
},
  "geometry": {"coordinates":[137.05029999999999,35.1194],"type":"Point"}
}