{
  "type": "Feature",
  "properties": {
    "gn:adm1_name":"Toukyouto",
    "gn:adm2_name":"Higashimurayamashi",
    "gn:name":"Noguchichou",
    "iso:country":"JP",
    "wof:name":"189-0022",
    "wof:placetype":"postalcode"
},
  "geometry": {"coordinates":[139.46000000000001,35.7623],"type":"Point"}
}