{
  "type": "Feature",
  "properties": {
    "gn:adm1_name":"Hyougoken",
    "gn:adm2_name":"Sasayamashi",
    "gn:name":"Miuchi",
    "iso:country":"JP",
    "wof:name":"669-2121",
    "wof:placetype":"postalcode"
},
  "geometry": {"coordinates":[135.15729999999999,35.0296],"type":"Point"}
}