{
  "type": "Feature",
  "properties": {
    "gn:adm1_name":"Saitamaken",
    "gn:adm2_name":"Saitamashiurawaku",
    "gn:name":"Motochou",
    "iso:country":"JP",
    "wof:name":"330-0073",
    "wof:placetype":"postalcode"
},
  "geometry": {"coordinates":[139.6525,35.8721],"type":"Point"}
}