{
  "type": "Feature",
  "properties": {
    "gn:adm1_name":"Kagoshimaken",
    "gn:adm2_name":"Tarumizushi",
    "gn:name":"Ushinefumoto",
    "iso:country":"JP",
    "wof:name":"899-4632",
    "wof:placetype":"postalcode"
},
  "geometry": {"coordinates":[130.7491,31.5603],"type":"Point"}
}