{
  "type": "Feature",
  "properties": {
    "gn:adm1_name":"Shizuokaken",
    "gn:adm2_name":"Kakegawashi",
    "gn:name":"Kobarako",
    "iso:country":"JP",
    "wof:name":"436-0007",
    "wof:placetype":"postalcode"
},
  "geometry": {"coordinates":[138.05670000000001,34.7936],"type":"Point"}
}