{
  "type": "Feature",
  "properties": {
    "gn:adm1_name":"Chibaken",
    "gn:adm2_name":"Isumigun'Isumimachi",
    "gn:name":"Fukaya",
    "iso:country":"JP",
    "wof:name":"298-0125",
    "wof:placetype":"postalcode"
},
  "geometry": {"coordinates":[140.3066,35.2928],"type":"Point"}
}