{
  "type": "Feature",
  "properties": {
    "gn:adm1_name":"Nagasakiken",
    "gn:adm2_name":"Matsuurashi",
    "gn:name":"Mikuriyachouteranoomen",
    "iso:country":"JP",
    "wof:name":"859-4772",
    "wof:placetype":"postalcode"
},
  "geometry": {"coordinates":[129.6609,33.3575],"type":"Point"}
}