{
  "type": "Feature",
  "properties": {
    "gn:adm1_name":"Oosakafu",
    "gn:adm2_name":"Higashioosakashi",
    "gn:name":"Kawanaka",
    "iso:country":"JP",
    "wof:name":"578-0902",
    "wof:placetype":"postalcode"
},
  "geometry": {"coordinates":[135.62790000000001,34.6819],"type":"Point"}
}