{
  "type": "Feature",
  "properties": {
    "gn:adm1_name":"Aichiken",
    "gn:adm2_name":"Nukatagunnukatachou",
    "gn:name":"Kawahara",
    "iso:country":"JP",
    "wof:name":"444-3602",
    "wof:placetype":"postalcode"
},
  "geometry": {"coordinates":[137.14060000000001,34.9833],"type":"Point"}
}