{
  "type": "Feature",
  "properties": {
    "gn:adm1_name":"Ibarakiken",
    "gn:adm2_name":"Tsuchiurashi",
    "gn:name":"Tatsutamachi",
    "iso:country":"JP",
    "wof:name":"300-0041",
    "wof:placetype":"postalcode"
},
  "geometry": {"coordinates":[140.1969,36.088],"type":"Point"}
}