{
  "type": "Feature",
  "properties": {
    "gn:adm1_name":"Oosakafu",
    "gn:adm2_name":"Kadomashi",
    "gn:name":"Kamimabushi",
    "iso:country":"JP",
    "wof:name":"571-0006",
    "wof:placetype":"postalcode"
},
  "geometry": {"coordinates":[135.6146,34.7365],"type":"Point"}
}