{
  "type": "Feature",
  "properties": {
    "gn:adm1_name":"Niigataken",
    "gn:adm2_name":"Nishikanbaragunnakanokuchimura",
    "gn:name":"Rokubu",
    "iso:country":"JP",
    "wof:name":"950-1322",
    "wof:placetype":"postalcode"
},
  "geometry": {"coordinates":[138.98429999999999,37.7115],"type":"Point"}
}