{
  "type": "Feature",
  "properties": {
    "gn:adm1_name":"Hyougoken",
    "gn:adm2_name":"Tsunagungoshikichou",
    "gn:name":"Aiharanakamura",
    "iso:country":"JP",
    "wof:name":"656-1321",
    "wof:placetype":"postalcode"
},
  "geometry": {"coordinates":[134.83519999999999,34.4128],"type":"Point"}
}