{
  "type": "Feature",
  "properties": {
    "gn:adm1_name":"Aichiken",
    "gn:adm2_name":"Setoshi",
    "gn:name":"Minamihishinochou",
    "iso:country":"JP",
    "wof:name":"489-0937",
    "wof:placetype":"postalcode"
},
  "geometry": {"coordinates":[137.07149999999999,35.2002],"type":"Point"}
}