{
  "type": "Feature",
  "properties": {
    "gn:adm1_name":"Ibarakiken",
    "gn:adm2_name":"Kogashi",
    "gn:name":"Nakadashinden",
    "iso:country":"JP",
    "wof:name":"306-0054",
    "wof:placetype":"postalcode"
},
  "geometry": {"coordinates":[139.71100000000001,36.1561],"type":"Point"}
}