{
  "type": "Feature",
  "properties": {
    "gn:adm1_name":"Nagasakiken",
    "gn:adm2_name":"Minamimatsuuragunwakamatsuchou",
    "gn:name":"Hinoshimagou",
    "iso:country":"JP",
    "wof:name":"853-2312",
    "wof:placetype":"postalcode"
},
  "geometry": {"coordinates":[128.96270000000001,32.919],"type":"Point"}
}