{
  "type": "Feature",
  "properties": {
    "gn:adm1_name":"Shizuokaken",
    "gn:adm2_name":"Shimadashi",
    "gn:name":"Minari",
    "iso:country":"JP",
    "wof:name":"427-0233",
    "wof:placetype":"postalcode"
},
  "geometry": {"coordinates":[138.10769999999999,34.9029],"type":"Point"}
}