{
  "type": "Feature",
  "properties": {
    "gn:adm1_name":"Gifuken",
    "gn:adm2_name":"Tajimishi",
    "gn:name":"Toyookachou",
    "iso:country":"JP",
    "wof:name":"507-0034",
    "wof:placetype":"postalcode"
},
  "geometry": {"coordinates":[137.12569999999999,35.3343],"type":"Point"}
}