{
  "type": "Feature",
  "properties": {
    "gn:adm1_name":"Yamagataken",
    "gn:adm2_name":"Higashineshi",
    "gn:name":"Shimaoohori",
    "iso:country":"JP",
    "wof:name":"999-3773",
    "wof:placetype":"postalcode"
},
  "geometry": {"coordinates":[140.35319999999999,38.4382],"type":"Point"}
}