{
  "type": "Feature",
  "properties": {
    "gn:adm1_name":"Saitamaken",
    "gn:adm2_name":"Kawagoeshi",
    "gn:name":"Matobakita",
    "iso:country":"JP",
    "wof:name":"350-1102",
    "wof:placetype":"postalcode"
},
  "geometry": {"coordinates":[139.4392,35.925],"type":"Point"}
}