{
  "type": "Feature",
  "properties": {
    "gn:adm1_name":"Niigataken",
    "gn:adm2_name":"Kitauonumagunsumonmura",
    "gn:name":"Sugawa",
    "iso:country":"JP",
    "wof:name":"946-0221",
    "wof:placetype":"postalcode"
},
  "geometry": {"coordinates":[139.0223,37.3104],"type":"Point"}
}