{
  "type": "Feature",
  "properties": {
    "gn:adm1_name":"Kyoutofu",
    "gn:adm2_name":"Kyoutoshifushimiku",
    "gn:name":"Mukaijimasuitagawarachou",
    "iso:country":"JP",
    "wof:name":"612-8124",
    "wof:placetype":"postalcode"
},
  "geometry": {"coordinates":[135.77680000000001,34.9257],"type":"Point"}
}