{
  "type": "Feature",
  "properties": {
    "gn:adm1_name":"Fukushimaken",
    "gn:adm2_name":"Aiduwakamatsushi",
    "gn:name":"Yamagamachi",
    "iso:country":"JP",
    "wof:name":"965-0876",
    "wof:placetype":"postalcode"
},
  "geometry": {"coordinates":[139.92400000000001,37.4908],"type":"Point"}
}