{
  "type": "Feature",
  "properties": {
    "gn:adm1_name":"Shizuokaken",
    "gn:adm2_name":"Fujiedashi",
    "gn:name":"Shimoaojima",
    "iso:country":"JP",
    "wof:name":"426-0035",
    "wof:placetype":"postalcode"
},
  "geometry": {"coordinates":[138.23869999999999,34.8466],"type":"Point"}
}