{
  "type": "Feature",
  "properties": {
    "gn:adm1_name":"Fukuiken",
    "gn:adm2_name":"Fukuishi",
    "gn:name":"Yuurakuchou",
    "iso:country":"JP",
    "wof:name":"918-8008",
    "wof:placetype":"postalcode"
},
  "geometry": {"coordinates":[136.20519999999999,36.0623],"type":"Point"}
}