{
  "type": "Feature",
  "properties": {
    "gn:adm1_name":"Shizuokaken",
    "gn:adm2_name":"Shimodashi",
    "gn:name":"Kitayugano",
    "iso:country":"JP",
    "wof:name":"413-0714",
    "wof:placetype":"postalcode"
},
  "geometry": {"coordinates":[138.9059,34.7272],"type":"Point"}
}