{
  "type": "Feature",
  "properties": {
    "gn:adm1_name":"Fukuokaken",
    "gn:adm2_name":"Kurumeshi",
    "gn:name":"Miyanojin",
    "iso:country":"JP",
    "wof:name":"839-0801",
    "wof:placetype":"postalcode"
},
  "geometry": {"coordinates":[130.53639999999999,33.3309],"type":"Point"}
}