{
  "type": "Feature",
  "properties": {
    "gn:adm1_name":"Kyoutofu",
    "gn:adm2_name":"Kyoutoshisakyouku",
    "gn:name":"Tanakakamifurukawachou",
    "iso:country":"JP",
    "wof:name":"606-8231",
    "wof:placetype":"postalcode"
},
  "geometry": {"coordinates":[135.78450000000001,35.0401],"type":"Point"}
}