{
  "type": "Feature",
  "properties": {
    "gn:adm1_name":"Niigataken",
    "gn:adm2_name":"Iwafunegun'Asahimura",
    "gn:name":"Komogawa",
    "iso:country":"JP",
    "wof:name":"958-0221",
    "wof:placetype":"postalcode"
},
  "geometry": {"coordinates":[139.60210000000001,38.2932],"type":"Point"}
}