{
  "type": "Feature",
  "properties": {
    "gn:adm1_name":"Hiroshimaken",
    "gn:adm2_name":"Hiroshimashinakaku",
    "gn:name":"Minamiyoshijima",
    "iso:country":"JP",
    "wof:name":"730-0826",
    "wof:placetype":"postalcode"
},
  "geometry": {"coordinates":[132.44290000000001,34.3605],"type":"Point"}
}