{
  "type": "Feature",
  "properties": {
    "gn:adm1_name":"Shigaken",
    "gn:adm2_name":"Hikoneshi",
    "gn:name":"Horichou",
    "iso:country":"JP",
    "wof:name":"522-0237",
    "wof:placetype":"postalcode"
},
  "geometry": {"coordinates":[136.2355,35.2372],"type":"Point"}
}