{
  "type": "Feature",
  "properties": {
    "gn:adm1_name":"Miyagiken",
    "gn:adm2_name":"Kesennumashi",
    "gn:name":"Ooiwaiyama",
    "iso:country":"JP",
    "wof:name":"988-0812",
    "wof:placetype":"postalcode"
},
  "geometry": {"coordinates":[141.59620000000001,38.9246],"type":"Point"}
}