{
  "type": "Feature",
  "properties": {
    "gn:adm1_name":"Okayamaken",
    "gn:adm2_name":"Akaiwagunkumayamachou",
    "gn:name":"Seiriki",
    "iso:country":"JP",
    "wof:name":"709-0715",
    "wof:placetype":"postalcode"
},
  "geometry": {"coordinates":[134.09989999999999,34.7706],"type":"Point"}
}