{
  "type": "Feature",
  "properties": {
    "gn:adm1_name":"Tottoriken",
    "gn:adm2_name":"Hinogunkoufuchou",
    "gn:name":"Miyou",
    "iso:country":"JP",
    "wof:name":"689-4423",
    "wof:placetype":"postalcode"
},
  "geometry": {"coordinates":[133.53700000000001,35.3048],"type":"Point"}
}