{
  "type": "Feature",
  "properties": {
    "gn:adm1_name":"Shizuokaken",
    "gn:adm2_name":"Fukuroishi",
    "gn:name":"Ooya",
    "iso:country":"JP",
    "wof:name":"437-0006",
    "wof:placetype":"postalcode"
},
  "geometry": {"coordinates":[137.87530000000001,34.7938],"type":"Point"}
}