{
  "type": "Feature",
  "properties": {
    "gn:adm1_name":"Hyougoken",
    "gn:adm2_name":"Mikatagunmuraokachou",
    "gn:name":"Yaidani",
    "iso:country":"JP",
    "wof:name":"667-1332",
    "wof:placetype":"postalcode"
},
  "geometry": {"coordinates":[134.60319999999999,35.4067],"type":"Point"}
}