{
  "type": "Feature",
  "properties": {
    "gn:adm1_name":"Kyoutofu",
    "gn:adm2_name":"Kyoutoshihigashiyamaku",
    "gn:name":"Yasakakamimachi",
    "iso:country":"JP",
    "wof:name":"605-0827",
    "wof:placetype":"postalcode"
},
  "geometry": {"coordinates":[135.77959999999999,34.9984],"type":"Point"}
}