{
  "type": "Feature",
  "properties": {
    "gn:adm1_name":"Ooitaken",
    "gn:adm2_name":"Nakatsushi",
    "gn:name":"Yuya",
    "iso:country":"JP",
    "wof:name":"871-0023",
    "wof:placetype":"postalcode"
},
  "geometry": {"coordinates":[131.18940000000001,33.5751],"type":"Point"}
}