{
  "type": "Feature",
  "properties": {
    "gn:adm1_name":"Hyougoken",
    "gn:adm2_name":"Hikamigunkasugachou",
    "gn:name":"Inaduka",
    "iso:country":"JP",
    "wof:name":"669-4135",
    "wof:placetype":"postalcode"
},
  "geometry": {"coordinates":[135.09100000000001,35.1798],"type":"Point"}
}