{
  "type": "Feature",
  "properties": {
    "gn:adm1_name":"Aichiken",
    "gn:adm2_name":"Okazakishi",
    "gn:name":"Yabuta",
    "iso:country":"JP",
    "wof:name":"444-2137",
    "wof:placetype":"postalcode"
},
  "geometry": {"coordinates":[137.1601,34.9877],"type":"Point"}
}