{
  "type": "Feature",
  "properties": {
    "gn:adm1_name":"Hyougoken",
    "gn:adm2_name":"Kakogun'Inamichou",
    "gn:name":"Oka",
    "iso:country":"JP",
    "wof:name":"675-1113",
    "wof:placetype":"postalcode"
},
  "geometry": {"coordinates":[134.91929999999999,34.7376],"type":"Point"}
}