{
  "type": "Feature",
  "properties": {
    "gn:adm1_name":"Shizuokaken",
    "gn:adm2_name":"Iwataguntoyodachou",
    "gn:name":"Ikeda",
    "iso:country":"JP",
    "wof:name":"438-0805",
    "wof:placetype":"postalcode"
},
  "geometry": {"coordinates":[137.81540000000001,34.7355],"type":"Point"}
}