{
  "type": "Feature",
  "properties": {
    "gn:adm1_name":"Kagoshimaken",
    "gn:adm2_name":"Airagunkajikichou",
    "gn:name":"Shinseimachi",
    "iso:country":"JP",
    "wof:name":"899-5223",
    "wof:placetype":"postalcode"
},
  "geometry": {"coordinates":[130.655,31.7391],"type":"Point"}
}