{
  "type": "Feature",
  "properties": {
    "gn:adm1_name":"Niigataken",
    "gn:adm2_name":"Kitakanbaragunyasudamachi",
    "gn:name":"Rokunose",
    "iso:country":"JP",
    "wof:name":"959-2215",
    "wof:placetype":"postalcode"
},
  "geometry": {"coordinates":[139.24799999999999,37.7555],"type":"Point"}
}