{
  "type": "Feature",
  "properties": {
    "gn:adm1_name":"Oosakafu",
    "gn:adm2_name":"Kishiwadashi",
    "gn:name":"Shimoikedachou",
    "iso:country":"JP",
    "wof:name":"596-0811",
    "wof:placetype":"postalcode"
},
  "geometry": {"coordinates":[135.40469999999999,34.4695],"type":"Point"}
}