{
  "type": "Feature",
  "properties": {
    "gn:adm1_name":"Tochigiken",
    "gn:adm2_name":"Kuroisoshi",
    "gn:name":"Nishiiwazaki",
    "iso:country":"JP",
    "wof:name":"325-0101",
    "wof:placetype":"postalcode"
},
  "geometry": {"coordinates":[139.98859999999999,37.0303],"type":"Point"}
}