{
  "type": "Feature",
  "properties": {
    "gn:adm1_name":"Gifuken",
    "gn:adm2_name":"Minoshi",
    "gn:name":"Matsumori",
    "iso:country":"JP",
    "wof:name":"501-3753",
    "wof:placetype":"postalcode"
},
  "geometry": {"coordinates":[136.90969999999999,35.5304],"type":"Point"}
}