{
  "type": "Feature",
  "properties": {
    "gn:adm1_name":"Yamaguchiken",
    "gn:adm2_name":"Shimonosekishi",
    "gn:name":"Choufumukaidachou",
    "iso:country":"JP",
    "wof:name":"752-0996",
    "wof:placetype":"postalcode"
},
  "geometry": {"coordinates":[130.97620000000001,33.9827],"type":"Point"}
}