{
  "type": "Feature",
  "properties": {
    "gn:adm1_name":"Kouchiken",
    "gn:adm2_name":"Nakamurashi",
    "gn:name":"Marunouchi(Sonota)",
    "iso:country":"JP",
    "wof:name":"787-0003",
    "wof:placetype":"postalcode"
},
  "geometry": {"coordinates":[132.9298,32.9986],"type":"Point"}
}