{
  "type": "Feature",
  "properties": {
    "gn:adm1_name":"Kumamotoken",
    "gn:adm2_name":"Kumamotoshi",
    "gn:name":"Tasaki",
    "iso:country":"JP",
    "wof:name":"860-0053",
    "wof:placetype":"postalcode"
},
  "geometry": {"coordinates":[130.68289999999999,32.7823],"type":"Point"}
}