{
  "type": "Feature",
  "properties": {
    "gn:adm1_name":"Gifuken",
    "gn:adm2_name":"Yoshikigunmiyagawamura",
    "gn:name":"Utsubo",
    "iso:country":"JP",
    "wof:name":"509-4545",
    "wof:placetype":"postalcode"
},
  "geometry": {"coordinates":[137.1808,36.3841],"type":"Point"}
}