{
  "type": "Feature",
  "properties": {
    "gn:adm1_name":"Gifuken",
    "gn:adm2_name":"Hashimagunkasamatsuchou",
    "gn:name":"Kisaragichou",
    "iso:country":"JP",
    "wof:name":"501-6084",
    "wof:placetype":"postalcode"
},
  "geometry": {"coordinates":[136.7595,35.3729],"type":"Point"}
}