{
  "type": "Feature",
  "properties": {
    "gn:adm1_name":"Tokushimaken",
    "gn:adm2_name":"Tokushimashi",
    "gn:name":"Kokufuchoukannonji",
    "iso:country":"JP",
    "wof:name":"779-3123",
    "wof:placetype":"postalcode"
},
  "geometry": {"coordinates":[134.47219999999999,34.0696],"type":"Point"}
}