{
  "type": "Feature",
  "properties": {
    "gn:adm1_name":"Ishikawaken",
    "gn:adm2_name":"Kahokugun'Unokemachi",
    "gn:name":"Kiya",
    "iso:country":"JP",
    "wof:name":"929-1111",
    "wof:placetype":"postalcode"
},
  "geometry": {"coordinates":[136.73650000000001,36.722],"type":"Point"}
}