{
  "type": "Feature",
  "properties": {
    "gn:adm1_name":"Shizuokaken",
    "gn:adm2_name":"Shizuokashi",
    "gn:name":"Shimizuumegaoka",
    "iso:country":"JP",
    "wof:name":"424-0938",
    "wof:placetype":"postalcode"
},
  "geometry": {"coordinates":[138.4829,35.0045],"type":"Point"}
}