{
  "type": "Feature",
  "properties": {
    "gn:adm1_name":"Tochigiken",
    "gn:adm2_name":"Utsunomiyashi",
    "gn:name":"Nissatomachi",
    "iso:country":"JP",
    "wof:name":"321-2118",
    "wof:placetype":"postalcode"
},
  "geometry": {"coordinates":[139.82409999999999,36.6275],"type":"Point"}
}