{
  "type": "Feature",
  "properties": {
    "gn:adm1_name":"Kyoutofu",
    "gn:adm2_name":"Kyoutoshinakagyouku",
    "gn:name":"Chigiriyachou",
    "iso:country":"JP",
    "wof:name":"604-8133",
    "wof:placetype":"postalcode"
},
  "geometry": {"coordinates":[135.762,35.0074],"type":"Point"}
}