{
  "type": "Feature",
  "properties": {
    "gn:adm1_name":"Shizuokaken",
    "gn:adm2_name":"Shimadashi",
    "gn:name":"Ouke",
    "iso:country":"JP",
    "wof:name":"427-0013",
    "wof:placetype":"postalcode"
},
  "geometry": {"coordinates":[138.21119999999999,34.8309],"type":"Point"}
}