{
  "type": "Feature",
  "properties": {
    "gn:adm1_name":"Kumamotoken",
    "gn:adm2_name":"Kikuchishi",
    "gn:name":"Dairinji",
    "iso:country":"JP",
    "wof:name":"861-1306",
    "wof:placetype":"postalcode"
},
  "geometry": {"coordinates":[130.8047,32.9745],"type":"Point"}
}