{
  "type": "Feature",
  "properties": {
    "gn:adm1_name":"Kagoshimaken",
    "gn:adm2_name":"Ooshimagunkikaichou",
    "gn:name":"Nakama",
    "iso:country":"JP",
    "wof:name":"891-6211",
    "wof:placetype":"postalcode"
},
  "geometry": {"coordinates":[129.9614,28.3331],"type":"Point"}
}