{
  "type": "Feature",
  "properties": {
    "gn:adm1_name":"Niigataken",
    "gn:adm2_name":"Nishikubikigunnoumachi",
    "gn:name":"Konoura",
    "iso:country":"JP",
    "wof:name":"949-1342",
    "wof:placetype":"postalcode"
},
  "geometry": {"coordinates":[137.9718,37.0826],"type":"Point"}
}