{
  "type": "Feature",
  "properties": {
    "gn:adm1_name":"Kyoutofu",
    "gn:adm2_name":"Maidurushi",
    "gn:name":"Hiranoya",
    "iso:country":"JP",
    "wof:name":"624-0927",
    "wof:placetype":"postalcode"
},
  "geometry": {"coordinates":[135.32769999999999,35.4499],"type":"Point"}
}