{
  "type": "Feature",
  "properties": {
    "gn:adm1_name":"Hyougoken",
    "gn:adm2_name":"Izushigun'Izushichou",
    "gn:name":"Mitsuki",
    "iso:country":"JP",
    "wof:name":"668-0278",
    "wof:placetype":"postalcode"
},
  "geometry": {"coordinates":[134.8339,35.4834],"type":"Point"}
}