{
  "type": "Feature",
  "properties": {
    "gn:adm1_name":"Miyagiken",
    "gn:adm2_name":"Sendaishiaobaku",
    "gn:name":"Akebonomachi",
    "iso:country":"JP",
    "wof:name":"981-0963",
    "wof:placetype":"postalcode"
},
  "geometry": {"coordinates":[140.864,38.2883],"type":"Point"}
}