{
  "type": "Feature",
  "properties": {
    "gn:adm1_name":"Gifuken",
    "gn:adm2_name":"Minokamoshi",
    "gn:name":"Kamonochouichihashi",
    "iso:country":"JP",
    "wof:name":"505-0056",
    "wof:placetype":"postalcode"
},
  "geometry": {"coordinates":[136.96559999999999,35.4681],"type":"Point"}
}