{
  "type": "Feature",
  "properties": {
    "gn:adm1_name":"Aichiken",
    "gn:adm2_name":"Nagoyashihigashiku",
    "gn:name":"Daikanchou",
    "iso:country":"JP",
    "wof:name":"461-0002",
    "wof:placetype":"postalcode"
},
  "geometry": {"coordinates":[136.92250000000001,35.1766],"type":"Point"}
}