{
  "type": "Feature",
  "properties": {
    "gn:adm1_name":"Fukushimaken",
    "gn:adm2_name":"Dategunhobaramachi",
    "gn:name":"Motomachi",
    "iso:country":"JP",
    "wof:name":"960-0605",
    "wof:placetype":"postalcode"
},
  "geometry": {"coordinates":[140.55770000000001,37.8225],"type":"Point"}
}