{
  "type": "Feature",
  "properties": {
    "gn:adm1_name":"Gunmaken",
    "gn:adm2_name":"Sawagunsakaimachi",
    "gn:name":"Doudou",
    "iso:country":"JP",
    "wof:name":"370-0117",
    "wof:placetype":"postalcode"
},
  "geometry": {"coordinates":[139.2516,36.2798],"type":"Point"}
}