{
  "type": "Feature",
  "properties": {
    "gn:adm1_name":"Chibaken",
    "gn:adm2_name":"Inbagunshisuimachi",
    "gn:name":"Motosakura",
    "iso:country":"JP",
    "wof:name":"285-0926",
    "wof:placetype":"postalcode"
},
  "geometry": {"coordinates":[140.25800000000001,35.7209],"type":"Point"}
}