{
  "type": "Feature",
  "properties": {
    "gn:adm1_name":"Miyagiken",
    "gn:adm2_name":"Kamigunshikamachou",
    "gn:name":"Ichinoseki",
    "iso:country":"JP",
    "wof:name":"981-4121",
    "wof:placetype":"postalcode"
},
  "geometry": {"coordinates":[140.85570000000001,38.5361],"type":"Point"}
}