{
  "type": "Feature",
  "properties": {
    "gn:adm1_name":"Niigataken",
    "gn:adm2_name":"Nakakanbaragunkamedamachi",
    "gn:name":"Midorichou",
    "iso:country":"JP",
    "wof:name":"950-0152",
    "wof:placetype":"postalcode"
},
  "geometry": {"coordinates":[139.101,37.8716],"type":"Point"}
}