{
  "type": "Feature",
  "properties": {
    "gn:adm1_name":"Ibarakiken",
    "gn:adm2_name":"Sashimagunsakaimachi",
    "gn:name":"Nishiizumida",
    "iso:country":"JP",
    "wof:name":"306-0431",
    "wof:placetype":"postalcode"
},
  "geometry": {"coordinates":[139.81450000000001,36.1175],"type":"Point"}
}