{
  "type": "Feature",
  "properties": {
    "gn:adm1_name":"Toyamaken",
    "gn:adm2_name":"Tonamishi",
    "gn:name":"Suginoki",
    "iso:country":"JP",
    "wof:name":"939-1355",
    "wof:placetype":"postalcode"
},
  "geometry": {"coordinates":[136.95410000000001,36.6478],"type":"Point"}
}