{
  "type": "Feature",
  "properties": {
    "gn:adm1_name":"Fukuokaken",
    "gn:adm2_name":"Asakuragunmiwamachi",
    "gn:name":"Iyanaga",
    "iso:country":"JP",
    "wof:name":"838-0811",
    "wof:placetype":"postalcode"
},
  "geometry": {"coordinates":[130.65049999999999,33.441],"type":"Point"}
}