{
  "type": "Feature",
  "properties": {
    "gn:adm1_name":"Saitamaken",
    "gn:adm2_name":"Kazoshi",
    "gn:name":"Nakahiyarikawa",
    "iso:country":"JP",
    "wof:name":"347-0008",
    "wof:placetype":"postalcode"
},
  "geometry": {"coordinates":[139.6215,36.1589],"type":"Point"}
}