{
  "type": "Feature",
  "properties": {
    "gn:adm1_name":"Kagawaken",
    "gn:adm2_name":"Marugameshi",
    "gn:name":"Matsuyachou",
    "iso:country":"JP",
    "wof:name":"763-0005",
    "wof:placetype":"postalcode"
},
  "geometry": {"coordinates":[133.79640000000001,34.292],"type":"Point"}
}