{
  "type": "Feature",
  "properties": {
    "gn:adm1_name":"Okayamaken",
    "gn:adm2_name":"Kumegunchuuouchou",
    "gn:name":"Kanabori",
    "iso:country":"JP",
    "wof:name":"709-3712",
    "wof:placetype":"postalcode"
},
  "geometry": {"coordinates":[133.99879999999999,34.9758],"type":"Point"}
}