{
  "type": "Feature",
  "properties": {
    "gn:adm1_name":"Naraken",
    "gn:adm2_name":"Narashi",
    "gn:name":"Imadushichou",
    "iso:country":"JP",
    "wof:name":"630-8243",
    "wof:placetype":"postalcode"
},
  "geometry": {"coordinates":[135.82339999999999,34.6832],"type":"Point"}
}