{
  "type": "Feature",
  "properties": {
    "gn:adm1_name":"Yamaguchiken",
    "gn:adm2_name":"Onodashi",
    "gn:name":"Jiyuugaoka",
    "iso:country":"JP",
    "wof:name":"756-0805",
    "wof:placetype":"postalcode"
},
  "geometry": {"coordinates":[131.1858,33.9842],"type":"Point"}
}