{
  "type": "Feature",
  "properties": {
    "gn:adm1_name":"Niigataken",
    "gn:adm2_name":"Iwafunegun'Arakawamachi",
    "gn:name":"Sasaki",
    "iso:country":"JP",
    "wof:name":"959-3121",
    "wof:placetype":"postalcode"
},
  "geometry": {"coordinates":[139.45930000000001,38.1268],"type":"Point"}
}