{
  "type": "Feature",
  "properties": {
    "gn:adm1_name":"Fukuiken",
    "gn:adm2_name":"Oonoshi",
    "gn:name":"Sabiraki",
    "iso:country":"JP",
    "wof:name":"912-0422",
    "wof:placetype":"postalcode"
},
  "geometry": {"coordinates":[136.55240000000001,35.9377],"type":"Point"}
}