{
  "type": "Feature",
  "properties": {
    "gn:adm1_name":"Kanagawaken",
    "gn:adm2_name":"Yokosukashi",
    "gn:name":"Fukadadai",
    "iso:country":"JP",
    "wof:name":"238-0016",
    "wof:placetype":"postalcode"
},
  "geometry": {"coordinates":[139.67169999999999,35.2747],"type":"Point"}
}