{
  "type": "Feature",
  "properties": {
    "gn:adm1_name":"Gifuken",
    "gn:adm2_name":"Sekishi",
    "gn:name":"Mukouyamachou",
    "iso:country":"JP",
    "wof:name":"501-3933",
    "wof:placetype":"postalcode"
},
  "geometry": {"coordinates":[136.90369999999999,35.4543],"type":"Point"}
}