{
  "type": "Feature",
  "properties": {
    "gn:adm1_name":"Ishikawaken",
    "gn:adm2_name":"Kahokuguntakamatsumachi",
    "gn:name":"Wakamidori",
    "iso:country":"JP",
    "wof:name":"929-1205",
    "wof:placetype":"postalcode"
},
  "geometry": {"coordinates":[136.75409999999999,36.7596],"type":"Point"}
}