{
  "type": "Feature",
  "properties": {
    "gn:adm1_name":"Hyougoken",
    "gn:adm2_name":"Kanzakigunfukusakichou",
    "gn:name":"Oonuki",
    "iso:country":"JP",
    "wof:name":"679-2201",
    "wof:placetype":"postalcode"
},
  "geometry": {"coordinates":[134.78620000000001,34.9484],"type":"Point"}
}