{
  "type": "Feature",
  "properties": {
    "gn:adm1_name":"Tochigiken",
    "gn:adm2_name":"Nasugunkarasuyamamachi",
    "gn:name":"Asahi",
    "iso:country":"JP",
    "wof:name":"321-0624",
    "wof:placetype":"postalcode"
},
  "geometry": {"coordinates":[140.16409999999999,36.6544],"type":"Point"}
}