{
  "type": "Feature",
  "properties": {
    "gn:adm1_name":"Niigataken",
    "gn:adm2_name":"Kariwagunnishiyamamachi",
    "gn:name":"Haidume",
    "iso:country":"JP",
    "wof:name":"949-4114",
    "wof:placetype":"postalcode"
},
  "geometry": {"coordinates":[138.68639999999999,37.4842],"type":"Point"}
}