{
  "type": "Feature",
  "properties": {
    "gn:adm1_name":"Ishikawaken",
    "gn:adm2_name":"Wajimashi",
    "gn:name":"Satomachi",
    "iso:country":"JP",
    "wof:name":"928-0246",
    "wof:placetype":"postalcode"
},
  "geometry": {"coordinates":[137.0343,37.4291],"type":"Point"}
}