{
  "type": "Feature",
  "properties": {
    "gn:adm1_name":"Niigataken",
    "gn:adm2_name":"Nakakubikigunkubikimura",
    "gn:name":"Teradashinden",
    "iso:country":"JP",
    "wof:name":"942-0109",
    "wof:placetype":"postalcode"
},
  "geometry": {"coordinates":[138.33680000000001,37.2034],"type":"Point"}
}