{
  "type": "Feature",
  "properties": {
    "gn:adm1_name":"Chibaken",
    "gn:adm2_name":"Katoriguntakomachi",
    "gn:name":"Nishifuruuchi",
    "iso:country":"JP",
    "wof:name":"289-2314",
    "wof:placetype":"postalcode"
},
  "geometry": {"coordinates":[140.48220000000001,35.7691],"type":"Point"}
}