{
  "type": "Feature",
  "properties": {
    "gn:adm1_name":"Nagasakiken",
    "gn:adm2_name":"Saseboshi",
    "gn:name":"Yoshiokachou",
    "iso:country":"JP",
    "wof:name":"857-0143",
    "wof:placetype":"postalcode"
},
  "geometry": {"coordinates":[129.70349999999999,33.2096],"type":"Point"}
}