{
  "type": "Feature",
  "properties": {
    "gn:adm1_name":"Yamaguchiken",
    "gn:adm2_name":"Onodashi",
    "gn:name":"Matsukaku",
    "iso:country":"JP",
    "wof:name":"756-0887",
    "wof:placetype":"postalcode"
},
  "geometry": {"coordinates":[131.17840000000001,33.9596],"type":"Point"}
}