{
  "type": "Feature",
  "properties": {
    "gn:adm1_name":"Naraken",
    "gn:adm2_name":"Narashi",
    "gn:name":"Myougachou",
    "iso:country":"JP",
    "wof:name":"630-2175",
    "wof:placetype":"postalcode"
},
  "geometry": {"coordinates":[135.90690000000001,34.6555],"type":"Point"}
}