{
  "type": "Feature",
  "properties": {
    "gn:adm1_name":"Chibaken",
    "gn:adm2_name":"Matsudoshi",
    "gn:name":"Higurashi",
    "iso:country":"JP",
    "wof:name":"270-2253",
    "wof:placetype":"postalcode"
},
  "geometry": {"coordinates":[139.9402,35.7896],"type":"Point"}
}