{
  "type": "Feature",
  "properties": {
    "gn:adm1_name":"Miyagiken",
    "gn:adm2_name":"Sendaishitaihakuku",
    "gn:name":"Hiyoridai",
    "iso:country":"JP",
    "wof:name":"982-0811",
    "wof:placetype":"postalcode"
},
  "geometry": {"coordinates":[140.82380000000001,38.2293],"type":"Point"}
}