{
  "type": "Feature",
  "properties": {
    "gn:adm1_name":"Gifuken",
    "gn:adm2_name":"Gifushi",
    "gn:name":"Shimosaigou",
    "iso:country":"JP",
    "wof:name":"501-1175",
    "wof:placetype":"postalcode"
},
  "geometry": {"coordinates":[136.70599999999999,35.4554],"type":"Point"}
}