{
  "type": "Feature",
  "properties": {
    "gn:adm1_name":"Tochigiken",
    "gn:adm2_name":"Asoguntanumamachi",
    "gn:name":"Shiraiwa",
    "iso:country":"JP",
    "wof:name":"327-0302",
    "wof:placetype":"postalcode"
},
  "geometry": {"coordinates":[139.52330000000001,36.4585],"type":"Point"}
}