{
  "type": "Feature",
  "properties": {
    "gn:adm1_name":"Niigataken",
    "gn:adm2_name":"Minamikanbaragunshitadamura",
    "gn:name":"Sasamaki",
    "iso:country":"JP",
    "wof:name":"955-0146",
    "wof:placetype":"postalcode"
},
  "geometry": {"coordinates":[139.03389999999999,37.5466],"type":"Point"}
}