{
  "type": "Feature",
  "properties": {
    "gn:adm1_name":"Gifuken",
    "gn:adm2_name":"Hashimashi",
    "gn:name":"Kuwabarachouheita",
    "iso:country":"JP",
    "wof:name":"501-6328",
    "wof:placetype":"postalcode"
},
  "geometry": {"coordinates":[136.66380000000001,35.2559],"type":"Point"}
}