{
  "type": "Feature",
  "properties": {
    "gn:adm1_name":"Kyoutofu",
    "gn:adm2_name":"Kyoutoshikitaku",
    "gn:name":"Koyamanishigen'Ichou",
    "iso:country":"JP",
    "wof:name":"603-8105",
    "wof:placetype":"postalcode"
},
  "geometry": {"coordinates":[135.7543,35.0514],"type":"Point"}
}