{
  "type": "Feature",
  "properties": {
    "gn:adm1_name":"Ishikawaken",
    "gn:adm2_name":"Kahokuguntsubatamachi",
    "gn:name":"Nakasuka",
    "iso:country":"JP",
    "wof:name":"929-0332",
    "wof:placetype":"postalcode"
},
  "geometry": {"coordinates":[136.72579999999999,36.6699],"type":"Point"}
}