{
  "type": "Feature",
  "properties": {
    "gn:adm1_name":"Hyougoken",
    "gn:adm2_name":"Itamishi",
    "gn:name":"Nakanonishi",
    "iso:country":"JP",
    "wof:name":"664-0023",
    "wof:placetype":"postalcode"
},
  "geometry": {"coordinates":[135.38470000000001,34.7898],"type":"Point"}
}