{
  "type": "Feature",
  "properties": {
    "gn:adm1_name":"Mieken",
    "gn:adm2_name":"Kitamurogunkiinagashimachou",
    "gn:name":"Higashinagashima",
    "iso:country":"JP",
    "wof:name":"519-3204",
    "wof:placetype":"postalcode"
},
  "geometry": {"coordinates":[136.3537,34.2155],"type":"Point"}
}