{
  "type": "Feature",
  "properties": {
    "gn:adm1_name":"Tottoriken",
    "gn:adm2_name":"Yazugunchiduchou",
    "gn:name":"Sakawara",
    "iso:country":"JP",
    "wof:name":"689-1461",
    "wof:placetype":"postalcode"
},
  "geometry": {"coordinates":[134.21600000000001,35.2644],"type":"Point"}
}