{
  "type": "Feature",
  "properties": {
    "gn:adm1_name":"Kagoshimaken",
    "gn:adm2_name":"Ooshimagunchinachou",
    "gn:name":"China",
    "iso:country":"JP",
    "wof:name":"891-9214",
    "wof:placetype":"postalcode"
},
  "geometry": {"coordinates":[128.56970000000001,27.3338],"type":"Point"}
}