{
  "type": "Feature",
  "properties": {
    "gn:adm1_name":"Ishikawaken",
    "gn:adm2_name":"Mattoushi",
    "gn:name":"Amidajimamachi",
    "iso:country":"JP",
    "wof:name":"924-0056",
    "wof:placetype":"postalcode"
},
  "geometry": {"coordinates":[136.51509999999999,36.5045],"type":"Point"}
}