{
  "type": "Feature",
  "properties": {
    "gn:adm1_name":"Ehimeken",
    "gn:adm2_name":"Yawatahamashi",
    "gn:name":"Jinguumae",
    "iso:country":"JP",
    "wof:name":"796-0023",
    "wof:placetype":"postalcode"
},
  "geometry": {"coordinates":[132.43369999999999,33.4596],"type":"Point"}
}