{
  "type": "Feature",
  "properties": {
    "gn:adm1_name":"Okayamaken",
    "gn:adm2_name":"Takahashishi",
    "gn:name":"Hamachou",
    "iso:country":"JP",
    "wof:name":"716-0038",
    "wof:placetype":"postalcode"
},
  "geometry": {"coordinates":[133.61850000000001,34.7896],"type":"Point"}
}