{
  "type": "Feature",
  "properties": {
    "gn:adm1_name":"Niigataken",
    "gn:adm2_name":"Nakakubikigunkubikimura",
    "gn:name":"Yazumi",
    "iso:country":"JP",
    "wof:name":"942-0212",
    "wof:placetype":"postalcode"
},
  "geometry": {"coordinates":[138.38079999999999,37.1977],"type":"Point"}
}