{
  "type": "Feature",
  "properties": {
    "gn:adm1_name":"Yamagataken",
    "gn:adm2_name":"Tendoushi",
    "gn:name":"Shouge",
    "iso:country":"JP",
    "wof:name":"994-0065",
    "wof:placetype":"postalcode"
},
  "geometry": {"coordinates":[140.35380000000001,38.3268],"type":"Point"}
}