{
  "type": "Feature",
  "properties": {
    "gn:adm1_name":"Fukuokaken",
    "gn:adm2_name":"Buzenshi",
    "gn:name":"Toriihata",
    "iso:country":"JP",
    "wof:name":"828-0085",
    "wof:placetype":"postalcode"
},
  "geometry": {"coordinates":[131.0249,33.5489],"type":"Point"}
}