{
  "type": "Feature",
  "properties": {
    "gn:adm1_name":"Fukuokaken",
    "gn:adm2_name":"Munakatagunfukumamachi",
    "gn:name":"Kouyoudai",
    "iso:country":"JP",
    "wof:name":"811-3223",
    "wof:placetype":"postalcode"
},
  "geometry": {"coordinates":[130.4991,33.7704],"type":"Point"}
}