{
  "type": "Feature",
  "properties": {
    "gn:adm1_name":"Gifuken",
    "gn:adm2_name":"Gifushi",
    "gn:name":"Matsukazechou",
    "iso:country":"JP",
    "wof:name":"502-0833",
    "wof:placetype":"postalcode"
},
  "geometry": {"coordinates":[136.77119999999999,35.4443],"type":"Point"}
}