{
  "type": "Feature",
  "properties": {
    "gn:adm1_name":"Saitamaken",
    "gn:adm2_name":"Saitamashinishiku",
    "gn:name":"Uetayahonmurashinden",
    "iso:country":"JP",
    "wof:name":"331-0067",
    "wof:placetype":"postalcode"
},
  "geometry": {"coordinates":[139.55789999999999,35.8921],"type":"Point"}
}