{
  "type": "Feature",
  "properties": {
    "gn:adm1_name":"Ishikawaken",
    "gn:adm2_name":"Mattoushi",
    "gn:name":"Kitayasutamachi",
    "iso:country":"JP",
    "wof:name":"924-0024",
    "wof:placetype":"postalcode"
},
  "geometry": {"coordinates":[136.54949999999999,36.5238],"type":"Point"}
}