{
  "type": "Feature",
  "properties": {
    "gn:adm1_name":"Gifuken",
    "gn:adm2_name":"Yourougunyourouchou",
    "gn:name":"Toyo",
    "iso:country":"JP",
    "wof:name":"503-1334",
    "wof:placetype":"postalcode"
},
  "geometry": {"coordinates":[136.55449999999999,35.3278],"type":"Point"}
}