{
  "type": "Feature",
  "properties": {
    "gn:adm1_name":"Oosakafu",
    "gn:adm2_name":"Oosakashiminatoku",
    "gn:name":"Kaigandoori",
    "iso:country":"JP",
    "wof:name":"552-0022",
    "wof:placetype":"postalcode"
},
  "geometry": {"coordinates":[135.43600000000001,34.6513],"type":"Point"}
}