{
  "type": "Feature",
  "properties": {
    "gn:adm1_name":"Kyoutofu",
    "gn:adm2_name":"Kyoutoshinishikyouku",
    "gn:name":"Katagiharaujiichou",
    "iso:country":"JP",
    "wof:name":"615-8185",
    "wof:placetype":"postalcode"
},
  "geometry": {"coordinates":[135.69460000000001,34.9746],"type":"Point"}
}