{
  "type": "Feature",
  "properties": {
    "gn:adm1_name":"Oosakafu",
    "gn:adm2_name":"Kishiwadashi",
    "gn:name":"Habuchou",
    "iso:country":"JP",
    "wof:name":"596-0825",
    "wof:placetype":"postalcode"
},
  "geometry": {"coordinates":[135.38570000000001,34.4475],"type":"Point"}
}