{
  "type": "Feature",
  "properties": {
    "gn:adm1_name":"Oosakafu",
    "gn:adm2_name":"Neyagawashi",
    "gn:name":"Wakabachou",
    "iso:country":"JP",
    "wof:name":"572-0031",
    "wof:placetype":"postalcode"
},
  "geometry": {"coordinates":[135.6191,34.7707],"type":"Point"}
}