{
  "type": "Feature",
  "properties": {
    "gn:adm1_name":"Kyoutofu",
    "gn:adm2_name":"Kyoutoshiukyouku",
    "gn:name":"Uzumasayasuinishiurachou",
    "iso:country":"JP",
    "wof:name":"616-8065",
    "wof:placetype":"postalcode"
},
  "geometry": {"coordinates":[135.71709999999999,35.0166],"type":"Point"}
}