{
  "type": "Feature",
  "properties": {
    "gn:adm1_name":"Ibarakiken",
    "gn:adm2_name":"Inashikigun'Amimachi",
    "gn:name":"Kaminaga",
    "iso:country":"JP",
    "wof:name":"300-1154",
    "wof:placetype":"postalcode"
},
  "geometry": {"coordinates":[140.2039,36.0065],"type":"Point"}
}