{
  "type": "Feature",
  "properties": {
    "gn:adm1_name":"Niigataken",
    "gn:adm2_name":"Sadogun'Aikawamachi",
    "gn:name":"Futami",
    "iso:country":"JP",
    "wof:name":"952-1641",
    "wof:placetype":"postalcode"
},
  "geometry": {"coordinates":[138.2577,37.9769],"type":"Point"}
}