{
  "type": "Feature",
  "properties": {
    "gn:adm1_name":"Kagoshimaken",
    "gn:adm2_name":"Kagoshimaguntoshimamura",
    "gn:name":"Takarajima",
    "iso:country":"JP",
    "wof:name":"891-5301",
    "wof:placetype":"postalcode"
},
  "geometry": {"coordinates":[129.20490000000001,29.1531],"type":"Point"}
}