{
  "type": "Feature",
  "properties": {
    "gn:adm1_name":"Fukuiken",
    "gn:adm2_name":"Sakaigunmikunichou",
    "gn:name":"Hamaji",
    "iso:country":"JP",
    "wof:name":"913-0005",
    "wof:placetype":"postalcode"
},
  "geometry": {"coordinates":[136.1662,36.2484],"type":"Point"}
}