{
  "type": "Feature",
  "properties": {
    "gn:adm1_name":"Tochigiken",
    "gn:adm2_name":"Oyamashi",
    "gn:name":"Kamihatsuda",
    "iso:country":"JP",
    "wof:name":"323-0069",
    "wof:placetype":"postalcode"
},
  "geometry": {"coordinates":[139.75239999999999,36.3375],"type":"Point"}
}