{
  "type": "Feature",
  "properties": {
    "gn:adm1_name":"Tochigiken",
    "gn:adm2_name":"Shimotsugagunmibumachi",
    "gn:name":"Shimoinaba",
    "iso:country":"JP",
    "wof:name":"321-0237",
    "wof:placetype":"postalcode"
},
  "geometry": {"coordinates":[139.78030000000001,36.4396],"type":"Point"}
}