{
  "type": "Feature",
  "properties": {
    "gn:adm1_name":"Kanagawaken",
    "gn:adm2_name":"Sagamiharashi",
    "gn:name":"Nihonmatsu",
    "iso:country":"JP",
    "wof:name":"229-1137",
    "wof:placetype":"postalcode"
},
  "geometry": {"coordinates":[139.32069999999999,35.5941],"type":"Point"}
}