{
  "type": "Feature",
  "properties": {
    "gn:adm1_name":"Oosakafu",
    "gn:adm2_name":"Kishiwadashi",
    "gn:name":"Kitasakachou",
    "iso:country":"JP",
    "wof:name":"596-0843",
    "wof:placetype":"postalcode"
},
  "geometry": {"coordinates":[135.417,34.4189],"type":"Point"}
}