{
  "type": "Feature",
  "properties": {
    "gn:adm1_name":"Kyoutofu",
    "gn:adm2_name":"Kyoutoshiukyouku",
    "gn:name":"Saiinyakakechou",
    "iso:country":"JP",
    "wof:name":"615-0024",
    "wof:placetype":"postalcode"
},
  "geometry": {"coordinates":[135.72999999999999,34.9999],"type":"Point"}
}