{
  "type": "Feature",
  "properties": {
    "gn:adm1_name":"Shimaneken",
    "gn:adm2_name":"Minogunhikimichou",
    "gn:name":"Shiso",
    "iso:country":"JP",
    "wof:name":"698-1212",
    "wof:placetype":"postalcode"
},
  "geometry": {"coordinates":[132.00620000000001,34.542],"type":"Point"}
}