{
  "type": "Feature",
  "properties": {
    "gn:adm1_name":"Ehimeken",
    "gn:adm2_name":"Kitauwaguntsushimachou",
    "gn:name":"Tanohama",
    "iso:country":"JP",
    "wof:name":"798-3357",
    "wof:placetype":"postalcode"
},
  "geometry": {"coordinates":[132.47470000000001,33.1096],"type":"Point"}
}