{
  "type": "Feature",
  "properties": {
    "gn:adm1_name":"Ibarakiken",
    "gn:adm2_name":"Sashimagunsouwamachi",
    "gn:name":"Isagoishinden",
    "iso:country":"JP",
    "wof:name":"306-0224",
    "wof:placetype":"postalcode"
},
  "geometry": {"coordinates":[139.72890000000001,36.1616],"type":"Point"}
}