{
  "type": "Feature",
  "properties": {
    "gn:adm1_name":"Gifuken",
    "gn:adm2_name":"Takayamashi",
    "gn:name":"Nanukamachi",
    "iso:country":"JP",
    "wof:name":"506-0005",
    "wof:placetype":"postalcode"
},
  "geometry": {"coordinates":[137.25569999999999,36.1491],"type":"Point"}
}