{
  "type": "Feature",
  "properties": {
    "gn:adm1_name":"Gunmaken",
    "gn:adm2_name":"Agatsumaguntsumagoimura",
    "gn:name":"Kamahara(Takaminekougen)",
    "iso:country":"JP",
    "wof:name":"384-0097",
    "wof:placetype":"postalcode"
},
  "geometry": {"coordinates":[138.4693,36.4078],"type":"Point"}
}