{
  "type": "Feature",
  "properties": {
    "gn:adm1_name":"Aichiken",
    "gn:adm2_name":"Nagoyashiminamiku",
    "gn:name":"Honjouchou",
    "iso:country":"JP",
    "wof:name":"457-0053",
    "wof:placetype":"postalcode"
},
  "geometry": {"coordinates":[136.93709999999999,35.0914],"type":"Point"}
}