{
  "type": "Feature",
  "properties": {
    "gn:adm1_name":"Kumamotoken",
    "gn:adm2_name":"Shimomashikigunchuuoumachi",
    "gn:name":"Kayano",
    "iso:country":"JP",
    "wof:name":"861-4405",
    "wof:placetype":"postalcode"
},
  "geometry": {"coordinates":[130.80549999999999,32.6341],"type":"Point"}
}