{
  "type": "Feature",
  "properties": {
    "gn:adm1_name":"Aichiken",
    "gn:adm2_name":"Nagoyashinakagawaku",
    "gn:name":"Tomidachoutoda",
    "iso:country":"JP",
    "wof:name":"454-0961",
    "wof:placetype":"postalcode"
},
  "geometry": {"coordinates":[136.80719999999999,35.1384],"type":"Point"}
}