{
  "type": "Feature",
  "properties": {
    "gn:adm1_name":"Niigataken",
    "gn:adm2_name":"Nakakubikigunsanwamura",
    "gn:name":"Suenoshinden",
    "iso:country":"JP",
    "wof:name":"942-0261",
    "wof:placetype":"postalcode"
},
  "geometry": {"coordinates":[138.3657,37.1632],"type":"Point"}
}