{
  "type": "Feature",
  "properties": {
    "gn:adm1_name":"Tottoriken",
    "gn:adm2_name":"Yazugunwakasachou",
    "gn:name":"Tsukuyone",
    "iso:country":"JP",
    "wof:name":"680-0728",
    "wof:placetype":"postalcode"
},
  "geometry": {"coordinates":[134.47839999999999,35.356],"type":"Point"}
}