{
  "type": "Feature",
  "properties": {
    "gn:adm1_name":"Toukyouto",
    "gn:adm2_name":"Kodairashi",
    "gn:name":"Ogawahigashichou",
    "iso:country":"JP",
    "wof:name":"187-0031",
    "wof:placetype":"postalcode"
},
  "geometry": {"coordinates":[139.46809999999999,35.7358],"type":"Point"}
}