{
  "type": "Feature",
  "properties": {
    "gn:adm1_name":"Naraken",
    "gn:adm2_name":"Udagunhaibarachou",
    "gn:name":"Sasagaku",
    "iso:country":"JP",
    "wof:name":"633-0242",
    "wof:placetype":"postalcode"
},
  "geometry": {"coordinates":[135.94149999999999,34.5234],"type":"Point"}
}