{
  "type": "Feature",
  "properties": {
    "gn:adm1_name":"Kouchiken",
    "gn:adm2_name":"Agawagun'Agawamura",
    "gn:name":"Kae",
    "iso:country":"JP",
    "wof:name":"781-1518",
    "wof:placetype":"postalcode"
},
  "geometry": {"coordinates":[133.17609999999999,33.5684],"type":"Point"}
}