{
  "type": "Feature",
  "properties": {
    "gn:adm1_name":"Shizuokaken",
    "gn:adm2_name":"Hamamatsushi",
    "gn:name":"Kohitomichou",
    "iso:country":"JP",
    "wof:name":"431-1113",
    "wof:placetype":"postalcode"
},
  "geometry": {"coordinates":[137.63489999999999,34.7284],"type":"Point"}
}