{
  "type": "Feature",
  "properties": {
    "gn:adm1_name":"Kagoshimaken",
    "gn:adm2_name":"Kagoshimashi",
    "gn:name":"Koyamadachou(Sonota)",
    "iso:country":"JP",
    "wof:name":"891-1231",
    "wof:placetype":"postalcode"
},
  "geometry": {"coordinates":[130.48740000000001,31.6581],"type":"Point"}
}