{
  "type": "Feature",
  "properties": {
    "gn:adm1_name":"Okayamaken",
    "gn:adm2_name":"Okayamashi",
    "gn:name":"Saidaijishin",
    "iso:country":"JP",
    "wof:name":"704-8127",
    "wof:placetype":"postalcode"
},
  "geometry": {"coordinates":[134.0386,34.6379],"type":"Point"}
}