{
  "type": "Feature",
  "properties": {
    "gn:adm1_name":"Toyamaken",
    "gn:adm2_name":"Nakaniikawagunkamiichimachi",
    "gn:name":"Kamishou",
    "iso:country":"JP",
    "wof:name":"930-0356",
    "wof:placetype":"postalcode"
},
  "geometry": {"coordinates":[137.34559999999999,36.7027],"type":"Point"}
}