{
  "type": "Feature",
  "properties": {
    "gn:adm1_name":"Naraken",
    "gn:adm2_name":"Yamabegunyamazoemura",
    "gn:name":"Kiriyama",
    "iso:country":"JP",
    "wof:name":"630-2205",
    "wof:placetype":"postalcode"
},
  "geometry": {"coordinates":[135.97280000000001,34.6825],"type":"Point"}
}