{
  "type": "Feature",
  "properties": {
    "gn:adm1_name":"Aichiken",
    "gn:adm2_name":"Amagunkaniechou",
    "gn:name":"Honmachikatahori",
    "iso:country":"JP",
    "wof:name":"497-0038",
    "wof:placetype":"postalcode"
},
  "geometry": {"coordinates":[136.7938,35.1339],"type":"Point"}
}