{
  "type": "Feature",
  "properties": {
    "gn:adm1_name":"Shizuokaken",
    "gn:adm2_name":"Tagatagunkannamichou",
    "gn:name":"Hatake",
    "iso:country":"JP",
    "wof:name":"419-0111",
    "wof:placetype":"postalcode"
},
  "geometry": {"coordinates":[138.97020000000001,35.0838],"type":"Point"}
}