{
  "type": "Feature",
  "properties": {
    "gn:adm1_name":"Niigataken",
    "gn:adm2_name":"Nakakubikigunkubikimura",
    "gn:name":"Shimoyoshishinden",
    "iso:country":"JP",
    "wof:name":"942-0146",
    "wof:placetype":"postalcode"
},
  "geometry": {"coordinates":[138.2817,37.1808],"type":"Point"}
}