{
  "type": "Feature",
  "properties": {
    "gn:adm1_name":"Tottoriken",
    "gn:adm2_name":"Yonagoshi",
    "gn:name":"Kaikeshinden",
    "iso:country":"JP",
    "wof:name":"683-0002",
    "wof:placetype":"postalcode"
},
  "geometry": {"coordinates":[133.36709999999999,35.4523],"type":"Point"}
}