{
  "type": "Feature",
  "properties": {
    "gn:adm1_name":"Kyoutofu",
    "gn:adm2_name":"Kyoutoshiyamashinaku",
    "gn:name":"Kanshuujihigashikurisunochou",
    "iso:country":"JP",
    "wof:name":"607-8211",
    "wof:placetype":"postalcode"
},
  "geometry": {"coordinates":[135.80879999999999,34.9697],"type":"Point"}
}