{
  "type": "Feature",
  "properties": {
    "gn:adm1_name":"Hyougoken",
    "gn:adm2_name":"Takaradukashi",
    "gn:name":"Nigawaasahigaoka",
    "iso:country":"JP",
    "wof:name":"665-0065",
    "wof:placetype":"postalcode"
},
  "geometry": {"coordinates":[135.34889999999999,34.7773],"type":"Point"}
}