{
  "type": "Feature",
  "properties": {
    "gn:adm1_name":"Kumamotoken",
    "gn:adm2_name":"Utogunmisumimachi",
    "gn:name":"Maegoshi",
    "iso:country":"JP",
    "wof:name":"869-3206",
    "wof:placetype":"postalcode"
},
  "geometry": {"coordinates":[130.51400000000001,32.6186],"type":"Point"}
}