{
  "type": "Feature",
  "properties": {
    "gn:adm1_name":"Fukuiken",
    "gn:adm2_name":"Sabaeshi",
    "gn:name":"Kumadachou",
    "iso:country":"JP",
    "wof:name":"916-0062",
    "wof:placetype":"postalcode"
},
  "geometry": {"coordinates":[136.1687,35.9495],"type":"Point"}
}