{
  "type": "Feature",
  "properties": {
    "gn:adm1_name":"Kanagawaken",
    "gn:adm2_name":"Yamatoshi",
    "gn:name":"Yanagibashi",
    "iso:country":"JP",
    "wof:name":"242-0022",
    "wof:placetype":"postalcode"
},
  "geometry": {"coordinates":[139.4622,35.4567],"type":"Point"}
}