{
  "type": "Feature",
  "properties": {
    "gn:adm1_name":"Naraken",
    "gn:adm2_name":"Udagunmuroumura",
    "gn:name":"Kuroiwa",
    "iso:country":"JP",
    "wof:name":"633-0425",
    "wof:placetype":"postalcode"
},
  "geometry": {"coordinates":[136.06659999999999,34.5019],"type":"Point"}
}