{
  "type": "Feature",
  "properties": {
    "gn:adm1_name":"Miyagiken",
    "gn:adm2_name":"Motoyoshigunmotoyoshichou",
    "gn:name":"Kohama",
    "iso:country":"JP",
    "wof:name":"988-0321",
    "wof:placetype":"postalcode"
},
  "geometry": {"coordinates":[141.517,38.7622],"type":"Point"}
}