{
  "type": "Feature",
  "properties": {
    "gn:adm1_name":"Gunmaken",
    "gn:adm2_name":"Ootashi",
    "gn:name":"Ishibashichou",
    "iso:country":"JP",
    "wof:name":"373-0007",
    "wof:placetype":"postalcode"
},
  "geometry": {"coordinates":[139.3407,36.3312],"type":"Point"}
}