{
  "type": "Feature",
  "properties": {
    "gn:adm1_name":"Saitamaken",
    "gn:adm2_name":"Fukayashi",
    "gn:name":"Isegata",
    "iso:country":"JP",
    "wof:name":"366-0836",
    "wof:placetype":"postalcode"
},
  "geometry": {"coordinates":[139.26300000000001,36.2047],"type":"Point"}
}