{
  "type": "Feature",
  "properties": {
    "gn:adm1_name":"Saitamaken",
    "gn:adm2_name":"Honjoushi",
    "gn:name":"Ojima",
    "iso:country":"JP",
    "wof:name":"367-0061",
    "wof:placetype":"postalcode"
},
  "geometry": {"coordinates":[139.17089999999999,36.2479],"type":"Point"}
}