{
  "type": "Feature",
  "properties": {
    "gn:adm1_name":"Fukuokaken",
    "gn:adm2_name":"Miyakogunkandamachi",
    "gn:name":"Ogura",
    "iso:country":"JP",
    "wof:name":"800-0353",
    "wof:placetype":"postalcode"
},
  "geometry": {"coordinates":[130.97550000000001,33.7623],"type":"Point"}
}