{
  "type": "Feature",
  "properties": {
    "gn:adm1_name":"Hyougoken",
    "gn:adm2_name":"Miharagunnandanchou",
    "gn:name":"Kashuufukui",
    "iso:country":"JP",
    "wof:name":"656-0516",
    "wof:placetype":"postalcode"
},
  "geometry": {"coordinates":[134.75700000000001,34.2565],"type":"Point"}
}