{
  "type": "Feature",
  "properties": {
    "gn:adm1_name":"Kouchiken",
    "gn:adm2_name":"Akigunkitagawamura",
    "gn:name":"Kotsumo",
    "iso:country":"JP",
    "wof:name":"781-6447",
    "wof:placetype":"postalcode"
},
  "geometry": {"coordinates":[134.04939999999999,33.4788],"type":"Point"}
}