{
  "type": "Feature",
  "properties": {
    "gn:adm1_name":"Naganoken",
    "gn:adm2_name":"Naganoshi",
    "gn:name":"Ichiba",
    "iso:country":"JP",
    "wof:name":"381-2202",
    "wof:placetype":"postalcode"
},
  "geometry": {"coordinates":[138.2269,36.6149],"type":"Point"}
}