{
  "type": "Feature",
  "properties": {
    "gn:adm1_name":"Fukushimaken",
    "gn:adm2_name":"Fukushimashi",
    "gn:name":"Oonami",
    "iso:country":"JP",
    "wof:name":"960-0811",
    "wof:placetype":"postalcode"
},
  "geometry": {"coordinates":[140.54249999999999,37.7489],"type":"Point"}
}