{
  "type": "Feature",
  "properties": {
    "gn:adm1_name":"Aichiken",
    "gn:adm2_name":"Chitaguntaketoyochou",
    "gn:name":"Sunagawa",
    "iso:country":"JP",
    "wof:name":"470-2317",
    "wof:placetype":"postalcode"
},
  "geometry": {"coordinates":[136.91309999999999,34.8662],"type":"Point"}
}