{
  "type": "Feature",
  "properties": {
    "gn:adm1_name":"Saitamaken",
    "gn:adm2_name":"Kawagoeshi",
    "gn:name":"Tamachi",
    "iso:country":"JP",
    "wof:name":"350-1113",
    "wof:placetype":"postalcode"
},
  "geometry": {"coordinates":[139.47559999999999,35.9155],"type":"Point"}
}