{
  "type": "Feature",
  "properties": {
    "gn:adm1_name":"Kanagawaken",
    "gn:adm2_name":"Yokohamashinakaku",
    "gn:name":"Ougichou",
    "iso:country":"JP",
    "wof:name":"231-0027",
    "wof:placetype":"postalcode"
},
  "geometry": {"coordinates":[139.63820000000001,35.4404],"type":"Point"}
}