{
  "type": "Feature",
  "properties": {
    "gn:adm1_name":"Nagasakiken",
    "gn:adm2_name":"Oomurashi",
    "gn:name":"Uematsu",
    "iso:country":"JP",
    "wof:name":"856-0027",
    "wof:placetype":"postalcode"
},
  "geometry": {"coordinates":[129.95599999999999,32.9316],"type":"Point"}
}