{
  "type": "Feature",
  "properties": {
    "gn:adm1_name":"Oosakafu",
    "gn:adm2_name":"Oosakashiikunoku",
    "gn:name":"Katsuyamakita",
    "iso:country":"JP",
    "wof:name":"544-0033",
    "wof:placetype":"postalcode"
},
  "geometry": {"coordinates":[135.53380000000001,34.656],"type":"Point"}
}