{
  "type": "Feature",
  "properties": {
    "gn:adm1_name":"Fukuiken",
    "gn:adm2_name":"Onyuugunkaminakachou",
    "gn:name":"Mochida",
    "iso:country":"JP",
    "wof:name":"919-1506",
    "wof:placetype":"postalcode"
},
  "geometry": {"coordinates":[135.86799999999999,35.4903],"type":"Point"}
}