{
  "type": "Feature",
  "properties": {
    "gn:adm1_name":"Naraken",
    "gn:adm2_name":"Yoshinogunkawakamimura",
    "gn:name":"Takaharadoba",
    "iso:country":"JP",
    "wof:name":"639-3556",
    "wof:placetype":"postalcode"
},
  "geometry": {"coordinates":[135.9503,34.3232],"type":"Point"}
}