{
  "type": "Feature",
  "properties": {
    "gn:adm1_name":"Ishikawaken",
    "gn:adm2_name":"Kanazawashi",
    "gn:name":"Sennosugimachi",
    "iso:country":"JP",
    "wof:name":"920-0115",
    "wof:placetype":"postalcode"
},
  "geometry": {"coordinates":[136.74860000000001,36.6255],"type":"Point"}
}