{
  "type": "Feature",
  "properties": {
    "gn:adm1_name":"Ooitaken",
    "gn:adm2_name":"Tsukumishi",
    "gn:name":"Yato",
    "iso:country":"JP",
    "wof:name":"879-2422",
    "wof:placetype":"postalcode"
},
  "geometry": {"coordinates":[131.8056,33.045],"type":"Point"}
}