{
  "type": "Feature",
  "properties": {
    "gn:adm1_name":"Hyougoken",
    "gn:adm2_name":"Koubeshihyougoku",
    "gn:name":"Kitayamachou",
    "iso:country":"JP",
    "wof:name":"652-0053",
    "wof:placetype":"postalcode"
},
  "geometry": {"coordinates":[135.1568,34.6882],"type":"Point"}
}