{
  "type": "Feature",
  "properties": {
    "gn:adm1_name":"Fukuokaken",
    "gn:adm2_name":"Fukuokashihakataku",
    "gn:name":"Toukoujichou",
    "iso:country":"JP",
    "wof:name":"816-0096",
    "wof:placetype":"postalcode"
},
  "geometry": {"coordinates":[130.43450000000001,33.5754],"type":"Point"}
}