{
  "type": "Feature",
  "properties": {
    "gn:adm1_name":"Ishikawaken",
    "gn:adm2_name":"Komatsushi",
    "gn:name":"Higashamamachi",
    "iso:country":"JP",
    "wof:name":"923-0842",
    "wof:placetype":"postalcode"
},
  "geometry": {"coordinates":[136.47919999999999,36.3758],"type":"Point"}
}