{
  "type": "Feature",
  "properties": {
    "gn:adm1_name":"Ishikawaken",
    "gn:adm2_name":"Kashimaguntoriyamachi",
    "gn:name":"Hitoto",
    "iso:country":"JP",
    "wof:name":"929-1715",
    "wof:placetype":"postalcode"
},
  "geometry": {"coordinates":[136.90309999999999,36.9857],"type":"Point"}
}