{
  "type": "Feature",
  "properties": {
    "gn:adm1_name":"Aichiken",
    "gn:adm2_name":"Kounanshi",
    "gn:name":"Maenochouhigashi",
    "iso:country":"JP",
    "wof:name":"483-8052",
    "wof:placetype":"postalcode"
},
  "geometry": {"coordinates":[136.89420000000001,35.3394],"type":"Point"}
}