{
  "type": "Feature",
  "properties": {
    "gn:adm1_name":"Tochigiken",
    "gn:adm2_name":"Sanoshi",
    "gn:name":"Tenmyouchou",
    "iso:country":"JP",
    "wof:name":"327-0014",
    "wof:placetype":"postalcode"
},
  "geometry": {"coordinates":[139.57239999999999,36.3125],"type":"Point"}
}