{
  "type": "Feature",
  "properties": {
    "gn:adm1_name":"Ehimeken",
    "gn:adm2_name":"Ochiguntamagawachou",
    "gn:name":"Kokanbe",
    "iso:country":"JP",
    "wof:name":"794-0112",
    "wof:placetype":"postalcode"
},
  "geometry": {"coordinates":[132.9682,34.0261],"type":"Point"}
}