{
  "type": "Feature",
  "properties": {
    "gn:adm1_name":"Yamaguchiken",
    "gn:adm2_name":"Abugunsusachou",
    "gn:name":"Susa",
    "iso:country":"JP",
    "wof:name":"759-3411",
    "wof:placetype":"postalcode"
},
  "geometry": {"coordinates":[131.6086,34.6209],"type":"Point"}
}