{
  "type": "Feature",
  "properties": {
    "gn:adm1_name":"Gifuken",
    "gn:adm2_name":"Minokamoshi",
    "gn:name":"Shimoyonedachouyamamoto",
    "iso:country":"JP",
    "wof:name":"505-0012",
    "wof:placetype":"postalcode"
},
  "geometry": {"coordinates":[137.07919999999999,35.473],"type":"Point"}
}