{
  "type": "Feature",
  "properties": {
    "gn:adm1_name":"Okayamaken",
    "gn:adm2_name":"Soujashi",
    "gn:name":"Mizokuchi",
    "iso:country":"JP",
    "wof:name":"719-1135",
    "wof:placetype":"postalcode"
},
  "geometry": {"coordinates":[133.7346,34.6752],"type":"Point"}
}