{
  "type": "Feature",
  "properties": {
    "gn:adm1_name":"Niigataken",
    "gn:adm2_name":"Minamiuonumagunmuikamachi",
    "gn:name":"Yawata",
    "iso:country":"JP",
    "wof:name":"949-6609",
    "wof:placetype":"postalcode"
},
  "geometry": {"coordinates":[138.8819,37.0704],"type":"Point"}
}