{
  "type": "Feature",
  "properties": {
    "gn:adm1_name":"Aichiken",
    "gn:adm2_name":"Nagoyashiminatoku",
    "gn:name":"Akiha",
    "iso:country":"JP",
    "wof:name":"455-0857",
    "wof:placetype":"postalcode"
},
  "geometry": {"coordinates":[136.8201,35.1082],"type":"Point"}
}