{
  "type": "Feature",
  "properties": {
    "gn:adm1_name":"Kumamotoken",
    "gn:adm2_name":"Asogunnishiharamura",
    "gn:name":"Ikanikeisaiganaibaai",
    "iso:country":"JP",
    "wof:name":"861-2400",
    "wof:placetype":"postalcode"
},
  "geometry": {"coordinates":[130.90350000000001,32.8313],"type":"Point"}
}