{
  "type": "Feature",
  "properties": {
    "gn:adm1_name":"Chibaken",
    "gn:adm2_name":"Chibashiwakabaku",
    "gn:name":"Ogurachou",
    "iso:country":"JP",
    "wof:name":"264-0007",
    "wof:placetype":"postalcode"
},
  "geometry": {"coordinates":[140.17519999999999,35.6266],"type":"Point"}
}