{
  "type": "Feature",
  "properties": {
    "gn:adm1_name":"Gunmaken",
    "gn:adm2_name":"Kiryuushi",
    "gn:name":"Motojukuchou",
    "iso:country":"JP",
    "wof:name":"376-0027",
    "wof:placetype":"postalcode"
},
  "geometry": {"coordinates":[139.32730000000001,36.4116],"type":"Point"}
}