{
  "type": "Feature",
  "properties": {
    "gn:adm1_name":"Yamagataken",
    "gn:adm2_name":"Yamagatashi",
    "gn:name":"Tsuchizaka",
    "iso:country":"JP",
    "wof:name":"990-2405",
    "wof:placetype":"postalcode"
},
  "geometry": {"coordinates":[140.36750000000001,38.2035],"type":"Point"}
}