{
  "type": "Feature",
  "properties": {
    "gn:adm1_name":"Fukushimaken",
    "gn:adm2_name":"Nihonmatsushi",
    "gn:name":"Kanairokubo",
    "iso:country":"JP",
    "wof:name":"964-0807",
    "wof:placetype":"postalcode"
},
  "geometry": {"coordinates":[140.43379999999999,37.5842],"type":"Point"}
}