{
  "type": "Feature",
  "properties": {
    "gn:adm1_name":"Naraken",
    "gn:adm2_name":"Tenrishi",
    "gn:name":"Furuchou",
    "iso:country":"JP",
    "wof:name":"632-0014",
    "wof:placetype":"postalcode"
},
  "geometry": {"coordinates":[135.84960000000001,34.5995],"type":"Point"}
}