{
  "type": "Feature",
  "properties": {
    "gn:adm1_name":"Fukushimaken",
    "gn:adm2_name":"Oonumagun'Aiduhongoumachi",
    "gn:name":"Arai",
    "iso:country":"JP",
    "wof:name":"969-6171",
    "wof:placetype":"postalcode"
},
  "geometry": {"coordinates":[139.88030000000001,37.4588],"type":"Point"}
}