{
  "type": "Feature",
  "properties": {
    "gn:adm1_name":"Chibaken",
    "gn:adm2_name":"Katorigunyamadamachi",
    "gn:name":"Furuuchi",
    "iso:country":"JP",
    "wof:name":"289-0412",
    "wof:placetype":"postalcode"
},
  "geometry": {"coordinates":[140.6131,35.7912],"type":"Point"}
}