{
  "type": "Feature",
  "properties": {
    "gn:adm1_name":"Kumamotoken",
    "gn:adm2_name":"Shimomashikigun'Ogawamachi",
    "gn:name":"Shinden",
    "iso:country":"JP",
    "wof:name":"869-0633",
    "wof:placetype":"postalcode"
},
  "geometry": {"coordinates":[130.68680000000001,32.5973],"type":"Point"}
}