{
  "type": "Feature",
  "properties": {
    "gn:adm1_name":"Oosakafu",
    "gn:adm2_name":"Hirakatashi",
    "gn:name":"Shoudainakamachi",
    "iso:country":"JP",
    "wof:name":"573-1152",
    "wof:placetype":"postalcode"
},
  "geometry": {"coordinates":[135.68190000000001,34.8377],"type":"Point"}
}