{
  "type": "Feature",
  "properties": {
    "gn:adm1_name":"Shigaken",
    "gn:adm2_name":"Higashiazaigunkohokuchou",
    "gn:name":"Kawake",
    "iso:country":"JP",
    "wof:name":"529-0316",
    "wof:placetype":"postalcode"
},
  "geometry": {"coordinates":[136.25149999999999,35.4465],"type":"Point"}
}