{
  "type": "Feature",
  "properties": {
    "gn:adm1_name":"Shigaken",
    "gn:adm2_name":"Yasugunyasuchou",
    "gn:name":"Ichimiyake",
    "iso:country":"JP",
    "wof:name":"520-2362",
    "wof:placetype":"postalcode"
},
  "geometry": {"coordinates":[136.0164,35.0709],"type":"Point"}
}