{
  "type": "Feature",
  "properties": {
    "gn:adm1_name":"Kyoutofu",
    "gn:adm2_name":"Kyoutoshinishikyouku",
    "gn:name":"Katagiharasumitachou",
    "iso:country":"JP",
    "wof:name":"615-8145",
    "wof:placetype":"postalcode"
},
  "geometry": {"coordinates":[135.69220000000001,34.9702],"type":"Point"}
}