{
  "type": "Feature",
  "properties": {
    "gn:adm1_name":"Toyamaken",
    "gn:adm2_name":"Nishitonamigunfukumitsumachi",
    "gn:name":"Saikawashichi",
    "iso:country":"JP",
    "wof:name":"939-1681",
    "wof:placetype":"postalcode"
},
  "geometry": {"coordinates":[136.82249999999999,36.5136],"type":"Point"}
}