{
  "type": "Feature",
  "properties": {
    "gn:adm1_name":"Naganoken",
    "gn:adm2_name":"Suwagunshimosuwamachi",
    "gn:name":"Hirasawachou",
    "iso:country":"JP",
    "wof:name":"393-0062",
    "wof:placetype":"postalcode"
},
  "geometry": {"coordinates":[138.0855,36.0756],"type":"Point"}
}