{
  "type": "Feature",
  "properties": {
    "gn:adm1_name":"Shigaken",
    "gn:adm2_name":"Yasugunyasuchou",
    "gn:name":"Kunobe",
    "iso:country":"JP",
    "wof:name":"520-2353",
    "wof:placetype":"postalcode"
},
  "geometry": {"coordinates":[136.0264,35.0733],"type":"Point"}
}