{
  "type": "Feature",
  "properties": {
    "gn:adm1_name":"Fukushimaken",
    "gn:adm2_name":"Fukushimashi",
    "gn:name":"Tokitoumori",
    "iso:country":"JP",
    "wof:name":"960-8125",
    "wof:placetype":"postalcode"
},
  "geometry": {"coordinates":[140.47569999999999,37.7699],"type":"Point"}
}