{
  "type": "Feature",
  "properties": {
    "gn:adm1_name":"Kyoutofu",
    "gn:adm2_name":"Kyoutoshiminamiku",
    "gn:name":"Kaikoujichou",
    "iso:country":"JP",
    "wof:name":"601-8406",
    "wof:placetype":"postalcode"
},
  "geometry": {"coordinates":[135.7508,34.9849],"type":"Point"}
}