{
  "type": "Feature",
  "properties": {
    "gn:adm1_name":"Hyougoken",
    "gn:adm2_name":"Hikamigunhikamichou",
    "gn:name":"Tanimura",
    "iso:country":"JP",
    "wof:name":"669-3572",
    "wof:placetype":"postalcode"
},
  "geometry": {"coordinates":[135.02199999999999,35.1441],"type":"Point"}
}