{
  "type": "Feature",
  "properties": {
    "gn:adm1_name":"Niigataken",
    "gn:adm2_name":"Kitakanbaragunnakajoumachi",
    "gn:name":"Nakakura",
    "iso:country":"JP",
    "wof:name":"959-2716",
    "wof:placetype":"postalcode"
},
  "geometry": {"coordinates":[139.3535,38.0469],"type":"Point"}
}