{
  "type": "Feature",
  "properties": {
    "gn:adm1_name":"Naganoken",
    "gn:adm2_name":"Kitasakugun'Asashinamura",
    "gn:name":"Kuwayama",
    "iso:country":"JP",
    "wof:name":"384-2101",
    "wof:placetype":"postalcode"
},
  "geometry": {"coordinates":[138.39949999999999,36.2844],"type":"Point"}
}