{
  "type": "Feature",
  "properties": {
    "gn:adm1_name":"Nagasakiken",
    "gn:adm2_name":"Saseboshi",
    "gn:name":"Sakibechou",
    "iso:country":"JP",
    "wof:name":"857-1176",
    "wof:placetype":"postalcode"
},
  "geometry": {"coordinates":[129.72819999999999,33.1362],"type":"Point"}
}