{
  "type": "Feature",
  "properties": {
    "gn:adm1_name":"Miyazakiken",
    "gn:adm2_name":"Nobeokashi",
    "gn:name":"Notamachi",
    "iso:country":"JP",
    "wof:name":"882-0801",
    "wof:placetype":"postalcode"
},
  "geometry": {"coordinates":[131.63589999999999,32.5765],"type":"Point"}
}