{
  "type": "Feature",
  "properties": {
    "gn:adm1_name":"Tokushimaken",
    "gn:adm2_name":"Nakagun'Aioichou",
    "gn:name":"Yokoishi",
    "iso:country":"JP",
    "wof:name":"771-5411",
    "wof:placetype":"postalcode"
},
  "geometry": {"coordinates":[134.43979999999999,33.7896],"type":"Point"}
}