{
  "type": "Feature",
  "properties": {
    "gn:adm1_name":"Kyoutofu",
    "gn:adm2_name":"Kyoutoshisakyouku",
    "gn:name":"Shinpontochou",
    "iso:country":"JP",
    "wof:name":"606-8383",
    "wof:placetype":"postalcode"
},
  "geometry": {"coordinates":[135.773,35.014],"type":"Point"}
}