{
  "type": "Feature",
  "properties": {
    "gn:adm1_name":"Aichiken",
    "gn:adm2_name":"Toyotashi",
    "gn:name":"Kamekubichou",
    "iso:country":"JP",
    "wof:name":"470-0375",
    "wof:placetype":"postalcode"
},
  "geometry": {"coordinates":[137.17179999999999,35.1412],"type":"Point"}
}