{
  "type": "Feature",
  "properties": {
    "gn:adm1_name":"Shigaken",
    "gn:adm2_name":"Oumihachimanshi",
    "gn:name":"Hisugichou",
    "iso:country":"JP",
    "wof:name":"523-0889",
    "wof:placetype":"postalcode"
},
  "geometry": {"coordinates":[136.08240000000001,35.1389],"type":"Point"}
}