{
  "type": "Feature",
  "properties": {
    "gn:adm1_name":"Toyamaken",
    "gn:adm2_name":"Takaokashi",
    "gn:name":"Ikarabe",
    "iso:country":"JP",
    "wof:name":"933-0306",
    "wof:placetype":"postalcode"
},
  "geometry": {"coordinates":[136.9486,36.7561],"type":"Point"}
}