{
  "type": "Feature",
  "properties": {
    "gn:adm1_name":"Hyougoken",
    "gn:adm2_name":"Akashishi",
    "gn:name":"Miyanoue",
    "iso:country":"JP",
    "wof:name":"673-0031",
    "wof:placetype":"postalcode"
},
  "geometry": {"coordinates":[134.97149999999999,34.6533],"type":"Point"}
}