{
  "type": "Feature",
  "properties": {
    "gn:adm1_name":"Shigaken",
    "gn:adm2_name":"Kusatsushi",
    "gn:name":"Ashiurachou",
    "iso:country":"JP",
    "wof:name":"525-0002",
    "wof:placetype":"postalcode"
},
  "geometry": {"coordinates":[135.95599999999999,35.0582],"type":"Point"}
}