{
  "type": "Feature",
  "properties": {
    "gn:adm1_name":"Gunmaken",
    "gn:adm2_name":"Tonegunkawabamura",
    "gn:name":"Namashina",
    "iso:country":"JP",
    "wof:name":"378-0113",
    "wof:placetype":"postalcode"
},
  "geometry": {"coordinates":[139.08860000000001,36.6758],"type":"Point"}
}