{
  "type": "Feature",
  "properties": {
    "gn:adm1_name":"Niigataken",
    "gn:adm2_name":"Kitakanbaragunkyougasemura",
    "gn:name":"Midorioka",
    "iso:country":"JP",
    "wof:name":"959-2113",
    "wof:placetype":"postalcode"
},
  "geometry": {"coordinates":[139.18899999999999,37.8417],"type":"Point"}
}