{
  "type": "Feature",
  "properties": {
    "gn:adm1_name":"Ibarakiken",
    "gn:adm2_name":"Shimodateshi",
    "gn:name":"Kou",
    "iso:country":"JP",
    "wof:name":"308-0021",
    "wof:placetype":"postalcode"
},
  "geometry": {"coordinates":[139.97800000000001,36.3115],"type":"Point"}
}