{
  "type": "Feature",
  "properties": {
    "gn:adm1_name":"Fukuiken",
    "gn:adm2_name":"Imadategun'Ikedachou",
    "gn:name":"Hirose",
    "iso:country":"JP",
    "wof:name":"910-2506",
    "wof:placetype":"postalcode"
},
  "geometry": {"coordinates":[136.35429999999999,35.9104],"type":"Point"}
}