{
  "type": "Feature",
  "properties": {
    "gn:adm1_name":"Miyagiken",
    "gn:adm2_name":"Shiogamashi",
    "gn:name":"Tsukimigaoka",
    "iso:country":"JP",
    "wof:name":"985-0066",
    "wof:placetype":"postalcode"
},
  "geometry": {"coordinates":[141.00299999999999,38.3196],"type":"Point"}
}