{
  "type": "Feature",
  "properties": {
    "gn:adm1_name":"Hyougoken",
    "gn:adm2_name":"Akoushi",
    "gn:name":"Miyamaechou",
    "iso:country":"JP",
    "wof:name":"678-0206",
    "wof:placetype":"postalcode"
},
  "geometry": {"coordinates":[134.38630000000001,34.7592],"type":"Point"}
}