{
  "type": "Feature",
  "properties": {
    "gn:adm1_name":"Tottoriken",
    "gn:adm2_name":"Kurayoshishi",
    "gn:name":"Ishiduka",
    "iso:country":"JP",
    "wof:name":"682-0933",
    "wof:placetype":"postalcode"
},
  "geometry": {"coordinates":[133.7843,35.3974],"type":"Point"}
}