{
  "type": "Feature",
  "properties": {
    "gn:adm1_name":"Tokushimaken",
    "gn:adm2_name":"Oegunkamojimachou",
    "gn:name":"Hiyamaji",
    "iso:country":"JP",
    "wof:name":"776-0032",
    "wof:placetype":"postalcode"
},
  "geometry": {"coordinates":[134.3355,34.038],"type":"Point"}
}