{
  "type": "Feature",
  "properties": {
    "gn:adm1_name":"Oosakafu",
    "gn:adm2_name":"Takatsukishi",
    "gn:name":"Higashiamagawa",
    "iso:country":"JP",
    "wof:name":"569-0012",
    "wof:placetype":"postalcode"
},
  "geometry": {"coordinates":[135.64009999999999,34.8447],"type":"Point"}
}