{
  "type": "Feature",
  "properties": {
    "gn:adm1_name":"Naraken",
    "gn:adm2_name":"Narashi",
    "gn:name":"Hiramatsu",
    "iso:country":"JP",
    "wof:name":"631-0846",
    "wof:placetype":"postalcode"
},
  "geometry": {"coordinates":[135.77549999999999,34.6769],"type":"Point"}
}