{
  "type": "Feature",
  "properties": {
    "gn:adm1_name":"Kanagawaken",
    "gn:adm2_name":"Yokohamashikanazawaku",
    "gn:name":"Mizukichou",
    "iso:country":"JP",
    "wof:name":"236-0036",
    "wof:placetype":"postalcode"
},
  "geometry": {"coordinates":[139.58949999999999,35.3387],"type":"Point"}
}