{
  "type": "Feature",
  "properties": {
    "gn:adm1_name":"Shimaneken",
    "gn:adm2_name":"Iishigunmitoyachou",
    "gn:name":"Nakano",
    "iso:country":"JP",
    "wof:name":"690-2523",
    "wof:placetype":"postalcode"
},
  "geometry": {"coordinates":[132.8571,35.2321],"type":"Point"}
}