{
  "type": "Feature",
  "properties": {
    "gn:adm1_name":"Aichiken",
    "gn:adm2_name":"Toyokawashi",
    "gn:name":"Shinyutakamachi",
    "iso:country":"JP",
    "wof:name":"442-0012",
    "wof:placetype":"postalcode"
},
  "geometry": {"coordinates":[137.40379999999999,34.8326],"type":"Point"}
}