{
  "type": "Feature",
  "properties": {
    "gn:adm1_name":"Gifuken",
    "gn:adm2_name":"Anpachigungoudochou",
    "gn:name":"Hachijou",
    "iso:country":"JP",
    "wof:name":"503-2324",
    "wof:placetype":"postalcode"
},
  "geometry": {"coordinates":[136.59989999999999,35.4067],"type":"Point"}
}