{
  "type": "Feature",
  "properties": {
    "gn:adm1_name":"Hiroshimaken",
    "gn:adm2_name":"Fukuyamashi",
    "gn:name":"Ekiyachoumanagura",
    "iso:country":"JP",
    "wof:name":"720-1131",
    "wof:placetype":"postalcode"
},
  "geometry": {"coordinates":[133.33199999999999,34.5535],"type":"Point"}
}