{
  "type": "Feature",
  "properties": {
    "gn:adm1_name":"Aichiken",
    "gn:adm2_name":"Nagoyashinakagawaku",
    "gn:name":"Shoutokuchou",
    "iso:country":"JP",
    "wof:name":"454-0858",
    "wof:placetype":"postalcode"
},
  "geometry": {"coordinates":[136.85290000000001,35.1398],"type":"Point"}
}