{
  "type": "Feature",
  "properties": {
    "gn:adm1_name":"Chibaken",
    "gn:adm2_name":"Matsudoshi",
    "gn:name":"Gokou",
    "iso:country":"JP",
    "wof:name":"270-2213",
    "wof:placetype":"postalcode"
},
  "geometry": {"coordinates":[139.9742,35.7958],"type":"Point"}
}