{
  "type": "Feature",
  "properties": {
    "gn:adm1_name":"Naraken",
    "gn:adm2_name":"Udagunsonimura",
    "gn:name":"Kake",
    "iso:country":"JP",
    "wof:name":"633-1215",
    "wof:placetype":"postalcode"
},
  "geometry": {"coordinates":[136.1121,34.4988],"type":"Point"}
}