{
  "type": "Feature",
  "properties": {
    "gn:adm1_name":"Toyamaken",
    "gn:adm2_name":"Nishitonamigunfukumitsumachi",
    "gn:name":"Takamiya",
    "iso:country":"JP",
    "wof:name":"939-1741",
    "wof:placetype":"postalcode"
},
  "geometry": {"coordinates":[136.87430000000001,36.5461],"type":"Point"}
}