{
  "type": "Feature",
  "properties": {
    "gn:adm1_name":"Shimaneken",
    "gn:adm2_name":"Oochigunmizuhochou",
    "gn:name":"Shimokamedani",
    "iso:country":"JP",
    "wof:name":"696-0223",
    "wof:placetype":"postalcode"
},
  "geometry": {"coordinates":[132.52269999999999,34.8482],"type":"Point"}
}