{
  "type": "Feature",
  "properties": {
    "gn:adm1_name":"Ehimeken",
    "gn:adm2_name":"Oozushi",
    "gn:name":"Haruka",
    "iso:country":"JP",
    "wof:name":"795-0046",
    "wof:placetype":"postalcode"
},
  "geometry": {"coordinates":[132.55629999999999,33.5553],"type":"Point"}
}