{
  "type": "Feature",
  "properties": {
    "gn:adm1_name":"Kyoutofu",
    "gn:adm2_name":"Yawatashi",
    "gn:name":"Uchizatominaminokuchi",
    "iso:country":"JP",
    "wof:name":"614-8246",
    "wof:placetype":"postalcode"
},
  "geometry": {"coordinates":[135.72999999999999,34.8582],"type":"Point"}
}