{
  "type": "Feature",
  "properties": {
    "gn:adm1_name":"Ooitaken",
    "gn:adm2_name":"Bungotakadashi",
    "gn:name":"Shinjou",
    "iso:country":"JP",
    "wof:name":"879-0724",
    "wof:placetype":"postalcode"
},
  "geometry": {"coordinates":[131.53200000000001,33.5587],"type":"Point"}
}