{
  "type": "Feature",
  "properties": {
    "gn:adm1_name":"Shizuokaken",
    "gn:adm2_name":"Iharagunyuichou",
    "gn:name":"Machiyahara",
    "iso:country":"JP",
    "wof:name":"421-3105",
    "wof:placetype":"postalcode"
},
  "geometry": {"coordinates":[138.5574,35.1047],"type":"Point"}
}