{
  "type": "Feature",
  "properties": {
    "gn:adm1_name":"Chibaken",
    "gn:adm2_name":"Nagareyamashi",
    "gn:name":"Kamishinshuku",
    "iso:country":"JP",
    "wof:name":"270-0125",
    "wof:placetype":"postalcode"
},
  "geometry": {"coordinates":[139.90790000000001,35.8863],"type":"Point"}
}