{
  "type": "Feature",
  "properties": {
    "gn:adm1_name":"Aichiken",
    "gn:adm2_name":"Nisshinshi",
    "gn:name":"Sanbongichou",
    "iso:country":"JP",
    "wof:name":"470-0101",
    "wof:placetype":"postalcode"
},
  "geometry": {"coordinates":[137.08170000000001,35.1415],"type":"Point"}
}