{
  "type": "Feature",
  "properties": {
    "gn:adm1_name":"Aichiken",
    "gn:adm2_name":"Chitagunmihamachou",
    "gn:name":"Kouwadai",
    "iso:country":"JP",
    "wof:name":"470-2405",
    "wof:placetype":"postalcode"
},
  "geometry": {"coordinates":[136.90549999999999,34.7719],"type":"Point"}
}