{
  "type": "Feature",
  "properties": {
    "gn:adm1_name":"Miyazakiken",
    "gn:adm2_name":"Ebinoshi",
    "gn:name":"Saigou",
    "iso:country":"JP",
    "wof:name":"889-4241",
    "wof:placetype":"postalcode"
},
  "geometry": {"coordinates":[130.7901,32.0547],"type":"Point"}
}