{
  "type": "Feature",
  "properties": {
    "gn:adm1_name":"Hyougoken",
    "gn:adm2_name":"Izushigun'Izushichou",
    "gn:name":"Katama",
    "iso:country":"JP",
    "wof:name":"668-0279",
    "wof:placetype":"postalcode"
},
  "geometry": {"coordinates":[134.8297,35.4896],"type":"Point"}
}