{
  "type": "Feature",
  "properties": {
    "gn:adm1_name":"Aichiken",
    "gn:adm2_name":"Okazakishi",
    "gn:name":"Iwanakachou",
    "iso:country":"JP",
    "wof:name":"444-3165",
    "wof:placetype":"postalcode"
},
  "geometry": {"coordinates":[137.2467,34.9776],"type":"Point"}
}