{
  "type": "Feature",
  "properties": {
    "gn:adm1_name":"Ishikawaken",
    "gn:adm2_name":"Kanazawashi",
    "gn:name":"Aburaguruma",
    "iso:country":"JP",
    "wof:name":"920-0996",
    "wof:placetype":"postalcode"
},
  "geometry": {"coordinates":[136.65629999999999,36.5575],"type":"Point"}
}