{
  "type": "Feature",
  "properties": {
    "gn:adm1_name":"Fukushimaken",
    "gn:adm2_name":"Soumashi",
    "gn:name":"Motowarou",
    "iso:country":"JP",
    "wof:name":"976-0024",
    "wof:placetype":"postalcode"
},
  "geometry": {"coordinates":[140.94200000000001,37.8087],"type":"Point"}
}