{
  "type": "Feature",
  "properties": {
    "gn:adm1_name":"Chibaken",
    "gn:adm2_name":"Inzaishi",
    "gn:name":"Soufuke",
    "iso:country":"JP",
    "wof:name":"270-1337",
    "wof:placetype":"postalcode"
},
  "geometry": {"coordinates":[140.15010000000001,35.7994],"type":"Point"}
}