{
  "type": "Feature",
  "properties": {
    "gn:adm1_name":"Saitamaken",
    "gn:adm2_name":"Kasukabeshi",
    "gn:name":"Minami",
    "iso:country":"JP",
    "wof:name":"344-0064",
    "wof:placetype":"postalcode"
},
  "geometry": {"coordinates":[139.76140000000001,35.9704],"type":"Point"}
}