{
  "type": "Feature",
  "properties": {
    "gn:adm1_name":"Kagoshimaken",
    "gn:adm2_name":"Sendaishi",
    "gn:name":"Amatatsuchou",
    "iso:country":"JP",
    "wof:name":"895-0011",
    "wof:placetype":"postalcode"
},
  "geometry": {"coordinates":[130.32329999999999,31.8301],"type":"Point"}
}