{
  "type": "Feature",
  "properties": {
    "gn:adm1_name":"Fukushimaken",
    "gn:adm2_name":"Iwakishi",
    "gn:name":"Sanukamachi",
    "iso:country":"JP",
    "wof:name":"974-8223",
    "wof:placetype":"postalcode"
},
  "geometry": {"coordinates":[140.80680000000001,36.9161],"type":"Point"}
}