{
  "type": "Feature",
  "properties": {
    "gn:adm1_name":"Miyagiken",
    "gn:adm2_name":"Sendaishiwakabayashiku",
    "gn:name":"Itsutsubashi(3choume)",
    "iso:country":"JP",
    "wof:name":"984-0022",
    "wof:placetype":"postalcode"
},
  "geometry": {"coordinates":[140.8836,38.253],"type":"Point"}
}