{
  "type": "Feature",
  "properties": {
    "gn:adm1_name":"Shizuokaken",
    "gn:adm2_name":"Kamogunmatsuzakichou",
    "gn:name":"Miyauchi",
    "iso:country":"JP",
    "wof:name":"410-3612",
    "wof:placetype":"postalcode"
},
  "geometry": {"coordinates":[138.78059999999999,34.7525],"type":"Point"}
}