{
  "type": "Feature",
  "properties": {
    "gn:adm1_name":"Mieken",
    "gn:adm2_name":"Uenoshi",
    "gn:name":"Nouninmachi",
    "iso:country":"JP",
    "wof:name":"518-0831",
    "wof:placetype":"postalcode"
},
  "geometry": {"coordinates":[136.13650000000001,34.7674],"type":"Point"}
}