{
  "type": "Feature",
  "properties": {
    "gn:adm1_name":"Aichiken",
    "gn:adm2_name":"Amagunjimokujichou",
    "gn:name":"Mori",
    "iso:country":"JP",
    "wof:name":"490-1107",
    "wof:placetype":"postalcode"
},
  "geometry": {"coordinates":[136.81030000000001,35.2127],"type":"Point"}
}