{
  "type": "Feature",
  "properties": {
    "gn:adm1_name":"Ishikawaken",
    "gn:adm2_name":"Komatsushi",
    "gn:name":"Inumarumachi",
    "iso:country":"JP",
    "wof:name":"923-0015",
    "wof:placetype":"postalcode"
},
  "geometry": {"coordinates":[136.45699999999999,36.4266],"type":"Point"}
}