{
  "type": "Feature",
  "properties": {
    "gn:adm1_name":"Yamagataken",
    "gn:adm2_name":"Sakatashi",
    "gn:name":"Oroshimachi",
    "iso:country":"JP",
    "wof:name":"998-0823",
    "wof:placetype":"postalcode"
},
  "geometry": {"coordinates":[139.85570000000001,38.8868],"type":"Point"}
}