{
  "type": "Feature",
  "properties": {
    "gn:adm1_name":"Miyagiken",
    "gn:adm2_name":"Kamigunkamimachi",
    "gn:name":"Kibune",
    "iso:country":"JP",
    "wof:name":"981-4419",
    "wof:placetype":"postalcode"
},
  "geometry": {"coordinates":[140.80279999999999,38.5878],"type":"Point"}
}