{
  "type": "Feature",
  "properties": {
    "gn:adm1_name":"Kagoshimaken",
    "gn:adm2_name":"Hiokigunkinpouchou",
    "gn:name":"Daizaka",
    "iso:country":"JP",
    "wof:name":"899-3402",
    "wof:placetype":"postalcode"
},
  "geometry": {"coordinates":[130.41159999999999,31.4666],"type":"Point"}
}