{
  "type": "Feature",
  "properties": {
    "gn:adm1_name":"Nagasakiken",
    "gn:adm2_name":"Isahayashi",
    "gn:name":"Kamioowatanomachi",
    "iso:country":"JP",
    "wof:name":"854-0095",
    "wof:placetype":"postalcode"
},
  "geometry": {"coordinates":[130.02279999999999,32.9037],"type":"Point"}
}