{
  "type": "Feature",
  "properties": {
    "gn:adm1_name":"Shigaken",
    "gn:adm2_name":"Higashiazaiguntorahimechou",
    "gn:name":"Ooi",
    "iso:country":"JP",
    "wof:name":"529-0113",
    "wof:placetype":"postalcode"
},
  "geometry": {"coordinates":[136.2645,35.4145],"type":"Point"}
}