{
  "type": "Feature",
  "properties": {
    "gn:adm1_name":"Naganoken",
    "gn:adm2_name":"Uedashi",
    "gn:name":"Yoshida",
    "iso:country":"JP",
    "wof:name":"386-0151",
    "wof:placetype":"postalcode"
},
  "geometry": {"coordinates":[138.3032,36.389],"type":"Point"}
}