{
  "type": "Feature",
  "properties": {
    "gn:adm1_name":"Toyamaken",
    "gn:adm2_name":"Toyamashi",
    "gn:name":"Kurehamitsuduka",
    "iso:country":"JP",
    "wof:name":"930-0136",
    "wof:placetype":"postalcode"
},
  "geometry": {"coordinates":[137.1679,36.7139],"type":"Point"}
}