{
  "type": "Feature",
  "properties": {
    "gn:adm1_name":"Okayamaken",
    "gn:adm2_name":"Mitsugunmitsuchou",
    "gn:name":"Kogura",
    "iso:country":"JP",
    "wof:name":"709-2137",
    "wof:placetype":"postalcode"
},
  "geometry": {"coordinates":[133.83019999999999,34.8224],"type":"Point"}
}