{
  "type": "Feature",
  "properties": {
    "gn:adm1_name":"Kyoutofu",
    "gn:adm2_name":"Kyoutoshifushimiku",
    "gn:name":"Ishidamorinishi",
    "iso:country":"JP",
    "wof:name":"601-1437",
    "wof:placetype":"postalcode"
},
  "geometry": {"coordinates":[135.8013,34.9401],"type":"Point"}
}