{
  "type": "Feature",
  "properties": {
    "gn:adm1_name":"Naraken",
    "gn:adm2_name":"Narashi",
    "gn:name":"Besshiyochou",
    "iso:country":"JP",
    "wof:name":"630-2153",
    "wof:placetype":"postalcode"
},
  "geometry": {"coordinates":[135.93969999999999,34.6574],"type":"Point"}
}