{
  "type": "Feature",
  "properties": {
    "gn:adm1_name":"Kagoshimaken",
    "gn:adm2_name":"Satsumagunkedouinchou",
    "gn:name":"Shimode",
    "iso:country":"JP",
    "wof:name":"895-1501",
    "wof:placetype":"postalcode"
},
  "geometry": {"coordinates":[130.48750000000001,31.8644],"type":"Point"}
}