{
  "type": "Feature",
  "properties": {
    "gn:adm1_name":"Saitamaken",
    "gn:adm2_name":"Hidakashi",
    "gn:name":"Harajuku",
    "iso:country":"JP",
    "wof:name":"350-1205",
    "wof:placetype":"postalcode"
},
  "geometry": {"coordinates":[139.3424,35.9036],"type":"Point"}
}