{
  "type": "Feature",
  "properties": {
    "gn:adm1_name":"Mieken",
    "gn:adm2_name":"Tsushi",
    "gn:name":"Obune",
    "iso:country":"JP",
    "wof:name":"514-0072",
    "wof:placetype":"postalcode"
},
  "geometry": {"coordinates":[136.4599,34.73],"type":"Point"}
}