{
  "type": "Feature",
  "properties": {
    "gn:adm1_name":"Gifuken",
    "gn:adm2_name":"Takayamashi",
    "gn:name":"Fuyutoumachi",
    "iso:country":"JP",
    "wof:name":"506-0001",
    "wof:placetype":"postalcode"
},
  "geometry": {"coordinates":[137.24199999999999,36.1638],"type":"Point"}
}