{
  "type": "Feature",
  "properties": {
    "gn:adm1_name":"Yamagataken",
    "gn:adm2_name":"Yamagatashi",
    "gn:name":"Kubota",
    "iso:country":"JP",
    "wof:name":"990-2482",
    "wof:placetype":"postalcode"
},
  "geometry": {"coordinates":[140.31620000000001,38.2486],"type":"Point"}
}