{
  "type": "Feature",
  "properties": {
    "gn:adm1_name":"Okayamaken",
    "gn:adm2_name":"Tsuyamashi",
    "gn:name":"Odanaka",
    "iso:country":"JP",
    "wof:name":"708-0006",
    "wof:placetype":"postalcode"
},
  "geometry": {"coordinates":[133.98910000000001,35.0645],"type":"Point"}
}