{
  "type": "Feature",
  "properties": {
    "gn:adm1_name":"Niigataken",
    "gn:adm2_name":"Sadogun'Ogimachi",
    "gn:name":"Ettsumi",
    "iso:country":"JP",
    "wof:name":"952-0622",
    "wof:placetype":"postalcode"
},
  "geometry": {"coordinates":[138.22550000000001,37.8351],"type":"Point"}
}