{
  "type": "Feature",
  "properties": {
    "gn:adm1_name":"Oosakafu",
    "gn:adm2_name":"Sakaishi",
    "gn:name":"Kurotsuchichou",
    "iso:country":"JP",
    "wof:name":"591-8024",
    "wof:placetype":"postalcode"
},
  "geometry": {"coordinates":[135.501,34.5648],"type":"Point"}
}