{
  "type": "Feature",
  "properties": {
    "gn:adm1_name":"Naganoken",
    "gn:adm2_name":"Komoroshi",
    "gn:name":"Hibarigaoka",
    "iso:country":"JP",
    "wof:name":"384-0065",
    "wof:placetype":"postalcode"
},
  "geometry": {"coordinates":[138.44669999999999,36.3277],"type":"Point"}
}