{
  "type": "Feature",
  "properties": {
    "gn:adm1_name":"Niigataken",
    "gn:adm2_name":"Toyosakashi",
    "gn:name":"Kayama",
    "iso:country":"JP",
    "wof:name":"950-3322",
    "wof:placetype":"postalcode"
},
  "geometry": {"coordinates":[139.22190000000001,37.9095],"type":"Point"}
}