{
  "type": "Feature",
  "properties": {
    "gn:adm1_name":"Tochigiken",
    "gn:adm2_name":"Kanumashi",
    "gn:name":"Kubochou",
    "iso:country":"JP",
    "wof:name":"322-0051",
    "wof:placetype":"postalcode"
},
  "geometry": {"coordinates":[139.7467,36.5656],"type":"Point"}
}