{
  "type": "Feature",
  "properties": {
    "gn:adm1_name":"Shizuokaken",
    "gn:adm2_name":"Shimodashi",
    "gn:name":"Takouma",
    "iso:country":"JP",
    "wof:name":"415-0034",
    "wof:placetype":"postalcode"
},
  "geometry": {"coordinates":[138.9393,34.6907],"type":"Point"}
}