{
  "type": "Feature",
  "properties": {
    "gn:adm1_name":"Chibaken",
    "gn:adm2_name":"Katorigunkouzakimachi",
    "gn:name":"Juusanmado",
    "iso:country":"JP",
    "wof:name":"289-0225",
    "wof:placetype":"postalcode"
},
  "geometry": {"coordinates":[140.38220000000001,35.9027],"type":"Point"}
}