{
  "type": "Feature",
  "properties": {
    "gn:adm1_name":"Shizuokaken",
    "gn:adm2_name":"Iwatagunryuuyouchou",
    "gn:name":"Nishihiramatsu",
    "iso:country":"JP",
    "wof:name":"438-0217",
    "wof:placetype":"postalcode"
},
  "geometry": {"coordinates":[137.81970000000001,34.6709],"type":"Point"}
}