{
  "type": "Feature",
  "properties": {
    "gn:adm1_name":"Shimaneken",
    "gn:adm2_name":"Oodashi",
    "gn:name":"Toriichoutorigoe",
    "iso:country":"JP",
    "wof:name":"694-0053",
    "wof:placetype":"postalcode"
},
  "geometry": {"coordinates":[132.50030000000001,35.2206],"type":"Point"}
}