{
  "type": "Feature",
  "properties": {
    "gn:adm1_name":"Aichiken",
    "gn:adm2_name":"Nishioshi",
    "gn:name":"Saitouchou",
    "iso:country":"JP",
    "wof:name":"445-0056",
    "wof:placetype":"postalcode"
},
  "geometry": {"coordinates":[137.04820000000001,34.8366],"type":"Point"}
}