{
  "type": "Feature",
  "properties": {
    "gn:adm1_name":"Shizuokaken",
    "gn:adm2_name":"Tenryuushi",
    "gn:name":"Kuma",
    "iso:country":"JP",
    "wof:name":"431-3641",
    "wof:placetype":"postalcode"
},
  "geometry": {"coordinates":[137.74420000000001,34.9644],"type":"Point"}
}