{
  "type": "Feature",
  "properties": {
    "gn:adm1_name":"Aichiken",
    "gn:adm2_name":"Hekinanshi",
    "gn:name":"Fumiwakemachi",
    "iso:country":"JP",
    "wof:name":"447-0054",
    "wof:placetype":"postalcode"
},
  "geometry": {"coordinates":[137.00190000000001,34.8962],"type":"Point"}
}