{
  "type": "Feature",
  "properties": {
    "gn:adm1_name":"Wakayamaken",
    "gn:adm2_name":"Kaisougunmisatochou",
    "gn:name":"Hasemiya",
    "iso:country":"JP",
    "wof:name":"640-1471",
    "wof:placetype":"postalcode"
},
  "geometry": {"coordinates":[135.48439999999999,34.1833],"type":"Point"}
}