{
  "type": "Feature",
  "properties": {
    "gn:adm1_name":"Oosakafu",
    "gn:adm2_name":"Fujiiderashi",
    "gn:name":"Funahashichou",
    "iso:country":"JP",
    "wof:name":"583-0003",
    "wof:placetype":"postalcode"
},
  "geometry": {"coordinates":[135.6233,34.5781],"type":"Point"}
}