{
  "type": "Feature",
  "properties": {
    "gn:adm1_name":"Fukuokaken",
    "gn:adm2_name":"Fukuokashihigashiku",
    "gn:name":"Shimobaru",
    "iso:country":"JP",
    "wof:name":"813-0002",
    "wof:placetype":"postalcode"
},
  "geometry": {"coordinates":[130.4556,33.6715],"type":"Point"}
}