{
  "type": "Feature",
  "properties": {
    "gn:adm1_name":"Gunmaken",
    "gn:adm2_name":"Ouragunchiyodamachi",
    "gn:name":"Kizaki",
    "iso:country":"JP",
    "wof:name":"370-0721",
    "wof:placetype":"postalcode"
},
  "geometry": {"coordinates":[139.458,36.2125],"type":"Point"}
}