{
  "type": "Feature",
  "properties": {
    "gn:adm1_name":"Toukyouto",
    "gn:adm2_name":"Suginamiku",
    "gn:name":"Matsunoki",
    "iso:country":"JP",
    "wof:name":"166-0014",
    "wof:placetype":"postalcode"
},
  "geometry": {"coordinates":[139.6437,35.6919],"type":"Point"}
}