{
  "type": "Feature",
  "properties": {
    "gn:adm1_name":"Toyamaken",
    "gn:adm2_name":"Higashitonamiguntairamura",
    "gn:name":"Nashitani",
    "iso:country":"JP",
    "wof:name":"939-1927",
    "wof:placetype":"postalcode"
},
  "geometry": {"coordinates":[136.9247,36.4416],"type":"Point"}
}