{
  "type": "Feature",
  "properties": {
    "gn:adm1_name":"Miyazakiken",
    "gn:adm2_name":"Miyazakishi",
    "gn:name":"Kyoudukachou",
    "iso:country":"JP",
    "wof:name":"880-0938",
    "wof:placetype":"postalcode"
},
  "geometry": {"coordinates":[131.4126,31.8963],"type":"Point"}
}