{
  "type": "Feature",
  "properties": {
    "gn:adm1_name":"Kagawaken",
    "gn:adm2_name":"Zentsuujishi",
    "gn:name":"Haradachou",
    "iso:country":"JP",
    "wof:name":"765-0032",
    "wof:placetype":"postalcode"
},
  "geometry": {"coordinates":[133.79140000000001,34.2513],"type":"Point"}
}