{
  "type": "Feature",
  "properties": {
    "gn:adm1_name":"Hyougoken",
    "gn:adm2_name":"Kinosakiguntakenochou",
    "gn:name":"Kusakai",
    "iso:country":"JP",
    "wof:name":"669-6215",
    "wof:placetype":"postalcode"
},
  "geometry": {"coordinates":[134.75530000000001,35.651],"type":"Point"}
}