{
  "type": "Feature",
  "properties": {
    "gn:adm1_name":"Toukyouto",
    "gn:adm2_name":"Hachioujishi",
    "gn:name":"Senninchou",
    "iso:country":"JP",
    "wof:name":"193-0835",
    "wof:placetype":"postalcode"
},
  "geometry": {"coordinates":[139.31100000000001,35.6581],"type":"Point"}
}