{
  "type": "Feature",
  "properties": {
    "gn:adm1_name":"Toukyouto",
    "gn:adm2_name":"Itabashiku",
    "gn:name":"Ooyamahigashichou",
    "iso:country":"JP",
    "wof:name":"173-0014",
    "wof:placetype":"postalcode"
},
  "geometry": {"coordinates":[139.70529999999999,35.7491],"type":"Point"}
}