{
  "type": "Feature",
  "properties": {
    "gn:adm1_name":"Toyamaken",
    "gn:adm2_name":"Nakaniikawaguntateyamamachi",
    "gn:name":"Tomarishin",
    "iso:country":"JP",
    "wof:name":"930-0265",
    "wof:placetype":"postalcode"
},
  "geometry": {"coordinates":[137.30019999999999,36.6316],"type":"Point"}
}