{
  "type": "Feature",
  "properties": {
    "gn:adm1_name":"Hyougoken",
    "gn:adm2_name":"Himejishi",
    "gn:name":"Shirakuni",
    "iso:country":"JP",
    "wof:name":"670-0808",
    "wof:placetype":"postalcode"
},
  "geometry": {"coordinates":[134.70660000000001,34.8612],"type":"Point"}
}