{
  "type": "Feature",
  "properties": {
    "gn:adm1_name":"Yamagataken",
    "gn:adm2_name":"Higashitagawagunmikawamachi",
    "gn:name":"Tsutsumino",
    "iso:country":"JP",
    "wof:name":"997-1332",
    "wof:placetype":"postalcode"
},
  "geometry": {"coordinates":[139.86920000000001,38.7685],"type":"Point"}
}