{
  "type": "Feature",
  "properties": {
    "gn:adm1_name":"Ibarakiken",
    "gn:adm2_name":"Niiharigunchiyodamachi",
    "gn:name":"Kamiinayoshi",
    "iso:country":"JP",
    "wof:name":"315-0056",
    "wof:placetype":"postalcode"
},
  "geometry": {"coordinates":[140.2183,36.1324],"type":"Point"}
}