{
  "type": "Feature",
  "properties": {
    "gn:adm1_name":"Gifuken",
    "gn:adm2_name":"Anpachigunsunomatachou",
    "gn:name":"Sunomata",
    "iso:country":"JP",
    "wof:name":"503-0102",
    "wof:placetype":"postalcode"
},
  "geometry": {"coordinates":[136.6832,35.3641],"type":"Point"}
}