{
  "type": "Feature",
  "properties": {
    "gn:adm1_name":"Toyamaken",
    "gn:adm2_name":"Higashitonamigunfukunomachi",
    "gn:name":"Yakeno",
    "iso:country":"JP",
    "wof:name":"939-1516",
    "wof:placetype":"postalcode"
},
  "geometry": {"coordinates":[136.9408,36.5802],"type":"Point"}
}