{
  "type": "Feature",
  "properties": {
    "gn:adm1_name":"Yamaguchiken",
    "gn:adm2_name":"Hikarishi",
    "gn:name":"Chuuou",
    "iso:country":"JP",
    "wof:name":"743-0013",
    "wof:placetype":"postalcode"
},
  "geometry": {"coordinates":[131.94540000000001,33.9591],"type":"Point"}
}