{
  "type": "Feature",
  "properties": {
    "gn:adm1_name":"Wakayamaken",
    "gn:adm2_name":"Higashimurogunkozagawachou",
    "gn:name":"Nakazaki",
    "iso:country":"JP",
    "wof:name":"649-4221",
    "wof:placetype":"postalcode"
},
  "geometry": {"coordinates":[135.77029999999999,33.5646],"type":"Point"}
}