{
  "type": "Feature",
  "properties": {
    "gn:adm1_name":"Kyoutofu",
    "gn:adm2_name":"Kyoutoshiyamashinaku",
    "gn:name":"Ooyakeiwayaden",
    "iso:country":"JP",
    "wof:name":"607-8172",
    "wof:placetype":"postalcode"
},
  "geometry": {"coordinates":[135.82820000000001,34.9697],"type":"Point"}
}