{
  "type": "Feature",
  "properties": {
    "gn:adm1_name":"Fukuokaken",
    "gn:adm2_name":"Munakatashi",
    "gn:name":"Ryougenji",
    "iso:country":"JP",
    "wof:name":"811-4145",
    "wof:placetype":"postalcode"
},
  "geometry": {"coordinates":[130.5856,33.8096],"type":"Point"}
}