{
  "type": "Feature",
  "properties": {
    "gn:adm1_name":"Chibaken",
    "gn:adm2_name":"Naritashi",
    "gn:name":"Minamihadori",
    "iso:country":"JP",
    "wof:name":"286-0805",
    "wof:placetype":"postalcode"
},
  "geometry": {"coordinates":[140.29130000000001,35.8409],"type":"Point"}
}