{
  "type": "Feature",
  "properties": {
    "gn:adm1_name":"Hyougoken",
    "gn:adm2_name":"Sasayamashi",
    "gn:name":"Kurikara",
    "iso:country":"JP",
    "wof:name":"669-2711",
    "wof:placetype":"postalcode"
},
  "geometry": {"coordinates":[135.2259,35.1344],"type":"Point"}
}