{
  "type": "Feature",
  "properties": {
    "gn:adm1_name":"Nagasakiken",
    "gn:adm2_name":"Kamiagatagunminechou",
    "gn:name":"Saka",
    "iso:country":"JP",
    "wof:name":"817-1412",
    "wof:placetype":"postalcode"
},
  "geometry": {"coordinates":[129.37280000000001,34.4569],"type":"Point"}
}