{
  "type": "Feature",
  "properties": {
    "gn:adm1_name":"Kagoshimaken",
    "gn:adm2_name":"Kawanabegunbounotsuchou",
    "gn:name":"Kushi",
    "iso:country":"JP",
    "wof:name":"898-0211",
    "wof:placetype":"postalcode"
},
  "geometry": {"coordinates":[130.19159999999999,31.3573],"type":"Point"}
}