{
  "type": "Feature",
  "properties": {
    "gn:adm1_name":"Tochigiken",
    "gn:adm2_name":"Nasugunkarasuyamamachi",
    "gn:name":"Oosawa",
    "iso:country":"JP",
    "wof:name":"321-0612",
    "wof:placetype":"postalcode"
},
  "geometry": {"coordinates":[140.2056,36.6717],"type":"Point"}
}