{
  "type": "Feature",
  "properties": {
    "gn:adm1_name":"Nagasakiken",
    "gn:adm2_name":"Shimabarashi",
    "gn:name":"Uenohara",
    "iso:country":"JP",
    "wof:name":"855-0853",
    "wof:placetype":"postalcode"
},
  "geometry": {"coordinates":[130.363,32.7799],"type":"Point"}
}