{
  "type": "Feature",
  "properties": {
    "gn:adm1_name":"Tochigiken",
    "gn:adm2_name":"Sanoshi",
    "gn:name":"Wakamiyashimochou",
    "iso:country":"JP",
    "wof:name":"327-0834",
    "wof:placetype":"postalcode"
},
  "geometry": {"coordinates":[139.58779999999999,36.2946],"type":"Point"}
}