{
  "type": "Feature",
  "properties": {
    "gn:adm1_name":"Kyoutofu",
    "gn:adm2_name":"Kusegunkumiyamachou",
    "gn:name":"Shimata",
    "iso:country":"JP",
    "wof:name":"613-0043",
    "wof:placetype":"postalcode"
},
  "geometry": {"coordinates":[135.73179999999999,34.8846],"type":"Point"}
}