{
  "type": "Feature",
  "properties": {
    "gn:adm1_name":"Toyamaken",
    "gn:adm2_name":"Takaokashi",
    "gn:name":"Shibuya",
    "iso:country":"JP",
    "wof:name":"933-0136",
    "wof:placetype":"postalcode"
},
  "geometry": {"coordinates":[137.04179999999999,36.8132],"type":"Point"}
}