{
  "type": "Feature",
  "properties": {
    "gn:adm1_name":"Ooitaken",
    "gn:adm2_name":"Taketashi",
    "gn:name":"Taketa",
    "iso:country":"JP",
    "wof:name":"878-0013",
    "wof:placetype":"postalcode"
},
  "geometry": {"coordinates":[131.39400000000001,32.9645],"type":"Point"}
}