{
  "type": "Feature",
  "properties": {
    "gn:adm1_name":"Saitamaken",
    "gn:adm2_name":"Hikigunyoshimimachi",
    "gn:name":"Arako",
    "iso:country":"JP",
    "wof:name":"355-0131",
    "wof:placetype":"postalcode"
},
  "geometry": {"coordinates":[139.47300000000001,36.0241],"type":"Point"}
}