{
  "type": "Feature",
  "properties": {
    "gn:adm1_name":"Aichiken",
    "gn:adm2_name":"Toyotashi",
    "gn:name":"Jumokuchou",
    "iso:country":"JP",
    "wof:name":"471-0851",
    "wof:placetype":"postalcode"
},
  "geometry": {"coordinates":[137.15170000000001,35.077],"type":"Point"}
}