{
  "type": "Feature",
  "properties": {
    "gn:adm1_name":"Hyougoken",
    "gn:adm2_name":"Kawabegun'Inagawachou",
    "gn:name":"Tsukunami",
    "iso:country":"JP",
    "wof:name":"666-0222",
    "wof:placetype":"postalcode"
},
  "geometry": {"coordinates":[135.35839999999999,34.9363],"type":"Point"}
}