{
  "type": "Feature",
  "properties": {
    "gn:adm1_name":"Hyougoken",
    "gn:adm2_name":"Himejishi",
    "gn:name":"Ootsukuebisumachi",
    "iso:country":"JP",
    "wof:name":"671-1136",
    "wof:placetype":"postalcode"
},
  "geometry": {"coordinates":[134.61000000000001,34.7936],"type":"Point"}
}