{
  "type": "Feature",
  "properties": {
    "gn:adm1_name":"Ooitaken",
    "gn:adm2_name":"Nakatsushi",
    "gn:name":"Kanate",
    "iso:country":"JP",
    "wof:name":"871-0013",
    "wof:placetype":"postalcode"
},
  "geometry": {"coordinates":[131.2028,33.5833],"type":"Point"}
}