{
  "type": "Feature",
  "properties": {
    "gn:adm1_name":"Niigataken",
    "gn:adm2_name":"Nakakanbaragunyokogoshimachi",
    "gn:name":"Kamichou",
    "iso:country":"JP",
    "wof:name":"950-0210",
    "wof:placetype":"postalcode"
},
  "geometry": {"coordinates":[139.14689999999999,37.8479],"type":"Point"}
}