{
  "type": "Feature",
  "properties": {
    "gn:adm1_name":"Hiroshimaken",
    "gn:adm2_name":"Takatagunyoshidachou",
    "gn:name":"Tajihi",
    "iso:country":"JP",
    "wof:name":"731-0544",
    "wof:placetype":"postalcode"
},
  "geometry": {"coordinates":[132.66390000000001,34.6801],"type":"Point"}
}