{
  "type": "Feature",
  "properties": {
    "gn:adm1_name":"Hyougoken",
    "gn:adm2_name":"Tatsunoshi",
    "gn:name":"Tatsunochoudoumoto",
    "iso:country":"JP",
    "wof:name":"679-4129",
    "wof:placetype":"postalcode"
},
  "geometry": {"coordinates":[134.55449999999999,34.8557],"type":"Point"}
}