{
  "type": "Feature",
  "properties": {
    "gn:adm1_name":"Tochigiken",
    "gn:adm2_name":"Kuroisoshi",
    "gn:name":"Saiwaichou",
    "iso:country":"JP",
    "wof:name":"325-0057",
    "wof:placetype":"postalcode"
},
  "geometry": {"coordinates":[140.05600000000001,36.9685],"type":"Point"}
}