{
  "type": "Feature",
  "properties": {
    "gn:adm1_name":"Fukuokaken",
    "gn:adm2_name":"Tagawagunkawaramachi",
    "gn:name":"Kagamiyama",
    "iso:country":"JP",
    "wof:name":"822-1402",
    "wof:placetype":"postalcode"
},
  "geometry": {"coordinates":[130.86019999999999,33.6791],"type":"Point"}
}