{
  "type": "Feature",
  "properties": {
    "gn:adm1_name":"Aichiken",
    "gn:adm2_name":"Inazawashi",
    "gn:name":"Shimizuteramaechou",
    "iso:country":"JP",
    "wof:name":"492-8316",
    "wof:placetype":"postalcode"
},
  "geometry": {"coordinates":[136.75880000000001,35.2574],"type":"Point"}
}