{
  "type": "Feature",
  "properties": {
    "gn:adm1_name":"Niigataken",
    "gn:adm2_name":"Nakakubikigunkakizakimachi",
    "gn:name":"Houonji",
    "iso:country":"JP",
    "wof:name":"949-3211",
    "wof:placetype":"postalcode"
},
  "geometry": {"coordinates":[138.40190000000001,37.2822],"type":"Point"}
}