{
  "type": "Feature",
  "properties": {
    "gn:adm1_name":"Yamagataken",
    "gn:adm2_name":"Tsuruokashi",
    "gn:name":"Jounanmachi",
    "iso:country":"JP",
    "wof:name":"997-0814",
    "wof:placetype":"postalcode"
},
  "geometry": {"coordinates":[139.83189999999999,38.7114],"type":"Point"}
}