{
  "type": "Feature",
  "properties": {
    "gn:adm1_name":"Niigataken",
    "gn:adm2_name":"Minamiuonumagunyamatomachi",
    "gn:name":"Serida",
    "iso:country":"JP",
    "wof:name":"949-7311",
    "wof:placetype":"postalcode"
},
  "geometry": {"coordinates":[138.91890000000001,37.1537],"type":"Point"}
}