{
  "type": "Feature",
  "properties": {
    "gn:adm1_name":"Niigataken",
    "gn:adm2_name":"Araishi",
    "gn:name":"Takayanagi",
    "iso:country":"JP",
    "wof:name":"944-0013",
    "wof:placetype":"postalcode"
},
  "geometry": {"coordinates":[138.26220000000001,37.0335],"type":"Point"}
}