{
  "type": "Feature",
  "properties": {
    "gn:adm1_name":"Naraken",
    "gn:adm2_name":"Yoshinogunnishiyoshinomura",
    "gn:name":"Kouno",
    "iso:country":"JP",
    "wof:name":"637-0113",
    "wof:placetype":"postalcode"
},
  "geometry": {"coordinates":[135.71369999999999,34.3014],"type":"Point"}
}