{
  "type": "Feature",
  "properties": {
    "gn:adm1_name":"Hyougoken",
    "gn:adm2_name":"Nishiwakishi",
    "gn:name":"Ochikatachou",
    "iso:country":"JP",
    "wof:name":"677-0068",
    "wof:placetype":"postalcode"
},
  "geometry": {"coordinates":[134.91669999999999,34.9753],"type":"Point"}
}