{
  "type": "Feature",
  "properties": {
    "gn:adm1_name":"Aichiken",
    "gn:adm2_name":"Anjoushi",
    "gn:name":"Hamatomichou",
    "iso:country":"JP",
    "wof:name":"446-0022",
    "wof:placetype":"postalcode"
},
  "geometry": {"coordinates":[137.0967,34.9542],"type":"Point"}
}