{
  "type": "Feature",
  "properties": {
    "gn:adm1_name":"Kagoshimaken",
    "gn:adm2_name":"Soogunsueyoshichou",
    "gn:name":"Shinmachi",
    "iso:country":"JP",
    "wof:name":"899-8603",
    "wof:placetype":"postalcode"
},
  "geometry": {"coordinates":[131.0206,31.6578],"type":"Point"}
}