{
  "type": "Feature",
  "properties": {
    "gn:adm1_name":"Niigataken",
    "gn:adm2_name":"Higashikanbaragunkamikawamura",
    "gn:name":"Sanpoubunhei",
    "iso:country":"JP",
    "wof:name":"959-4523",
    "wof:placetype":"postalcode"
},
  "geometry": {"coordinates":[139.4922,37.5913],"type":"Point"}
}