{
  "type": "Feature",
  "properties": {
    "gn:adm1_name":"Hyougoken",
    "gn:adm2_name":"Kanzakigun'Ichikawachou",
    "gn:name":"Kamiushio",
    "iso:country":"JP",
    "wof:name":"679-2301",
    "wof:placetype":"postalcode"
},
  "geometry": {"coordinates":[134.828,35.0264],"type":"Point"}
}