{
  "type": "Feature",
  "properties": {
    "gn:adm1_name":"Ibarakiken",
    "gn:adm2_name":"Inashikigun'Azumamachi",
    "gn:name":"Shinbashi",
    "iso:country":"JP",
    "wof:name":"300-0613",
    "wof:placetype":"postalcode"
},
  "geometry": {"coordinates":[140.35390000000001,35.9118],"type":"Point"}
}