{
  "type": "Feature",
  "properties": {
    "gn:adm1_name":"Nagasakiken",
    "gn:adm2_name":"Oomurashi",
    "gn:name":"Nishisanjouchou",
    "iso:country":"JP",
    "wof:name":"856-0825",
    "wof:placetype":"postalcode"
},
  "geometry": {"coordinates":[129.96000000000001,32.9149],"type":"Point"}
}