{
  "type": "Feature",
  "properties": {
    "gn:adm1_name":"Toyamaken",
    "gn:adm2_name":"Shimoniikawagunnyuuzenmachi",
    "gn:name":"Nakazawa",
    "iso:country":"JP",
    "wof:name":"938-0105",
    "wof:placetype":"postalcode"
},
  "geometry": {"coordinates":[137.53909999999999,36.9061],"type":"Point"}
}