{
  "type": "Feature",
  "properties": {
    "gn:adm1_name":"Okayamaken",
    "gn:adm2_name":"Okayamashi",
    "gn:name":"Saiwaichou",
    "iso:country":"JP",
    "wof:name":"700-0903",
    "wof:placetype":"postalcode"
},
  "geometry": {"coordinates":[133.92070000000001,34.6616],"type":"Point"}
}