{
  "type": "Feature",
  "properties": {
    "gn:adm1_name":"Shizuokaken",
    "gn:adm2_name":"Susonoshi",
    "gn:name":"Yobiko",
    "iso:country":"JP",
    "wof:name":"410-1109",
    "wof:placetype":"postalcode"
},
  "geometry": {"coordinates":[138.8706,35.2294],"type":"Point"}
}