{
  "type": "Feature",
  "properties": {
    "gn:adm1_name":"Kouchiken",
    "gn:adm2_name":"Kouchishi",
    "gn:name":"Sakaedachou",
    "iso:country":"JP",
    "wof:name":"780-0061",
    "wof:placetype":"postalcode"
},
  "geometry": {"coordinates":[133.5453,33.5677],"type":"Point"}
}