{
  "type": "Feature",
  "properties": {
    "gn:adm1_name":"Mieken",
    "gn:adm2_name":"Kameyamashi",
    "gn:name":"Minaminochou",
    "iso:country":"JP",
    "wof:name":"519-0156",
    "wof:placetype":"postalcode"
},
  "geometry": {"coordinates":[136.44370000000001,34.854],"type":"Point"}
}