{
  "type": "Feature",
  "properties": {
    "gn:adm1_name":"Naraken",
    "gn:adm2_name":"Yoshinogunyoshinochou",
    "gn:name":"Tachino",
    "iso:country":"JP",
    "wof:name":"639-3112",
    "wof:placetype":"postalcode"
},
  "geometry": {"coordinates":[135.86410000000001,34.3963],"type":"Point"}
}