{
  "type": "Feature",
  "properties": {
    "gn:adm1_name":"Saitamaken",
    "gn:adm2_name":"Kawaguchishi",
    "gn:name":"Maekawachou",
    "iso:country":"JP",
    "wof:name":"333-0841",
    "wof:placetype":"postalcode"
},
  "geometry": {"coordinates":[139.709,35.8418],"type":"Point"}
}