{
  "type": "Feature",
  "properties": {
    "gn:adm1_name":"Niigataken",
    "gn:adm2_name":"Kashiwazakishi",
    "gn:name":"Tokiwadai",
    "iso:country":"JP",
    "wof:name":"945-0834",
    "wof:placetype":"postalcode"
},
  "geometry": {"coordinates":[138.54830000000001,37.3574],"type":"Point"}
}