{
  "type": "Feature",
  "properties": {
    "gn:adm1_name":"Ishikawaken",
    "gn:adm2_name":"Hakuiguntogimachi",
    "gn:name":"Fukuraminato",
    "iso:country":"JP",
    "wof:name":"925-0315",
    "wof:placetype":"postalcode"
},
  "geometry": {"coordinates":[136.7354,37.0816],"type":"Point"}
}