{
  "type": "Feature",
  "properties": {
    "gn:adm1_name":"Kyoutofu",
    "gn:adm2_name":"Kyoutoshinishikyouku",
    "gn:name":"Goryoushigitani",
    "iso:country":"JP",
    "wof:name":"615-8242",
    "wof:placetype":"postalcode"
},
  "geometry": {"coordinates":[135.6876,34.9761],"type":"Point"}
}