{
  "type": "Feature",
  "properties": {
    "gn:adm1_name":"Naraken",
    "gn:adm2_name":"Ikomagunsangouchou",
    "gn:name":"Minamihata",
    "iso:country":"JP",
    "wof:name":"636-0834",
    "wof:placetype":"postalcode"
},
  "geometry": {"coordinates":[135.6619,34.6086],"type":"Point"}
}