{
  "type": "Feature",
  "properties": {
    "gn:adm1_name":"Chibaken",
    "gn:adm2_name":"Chouseigunchounanmachi",
    "gn:name":"Kuramochi",
    "iso:country":"JP",
    "wof:name":"297-0123",
    "wof:placetype":"postalcode"
},
  "geometry": {"coordinates":[140.2175,35.3887],"type":"Point"}
}