{
  "type": "Feature",
  "properties": {
    "gn:adm1_name":"Tochigiken",
    "gn:adm2_name":"Nasugunnasumachi",
    "gn:name":"Yorii",
    "iso:country":"JP",
    "wof:name":"329-3441",
    "wof:placetype":"postalcode"
},
  "geometry": {"coordinates":[140.17449999999999,37.0419],"type":"Point"}
}