{
  "type": "Feature",
  "properties": {
    "gn:adm1_name":"Hiroshimaken",
    "gn:adm2_name":"Hatsukaichishi",
    "gn:name":"Shikigaoka",
    "iso:country":"JP",
    "wof:name":"738-0036",
    "wof:placetype":"postalcode"
},
  "geometry": {"coordinates":[132.29339999999999,34.3474],"type":"Point"}
}