{
  "type": "Feature",
  "properties": {
    "gn:adm1_name":"Wakayamaken",
    "gn:adm2_name":"Wakayamashi",
    "gn:name":"Kandori",
    "iso:country":"JP",
    "wof:name":"640-8411",
    "wof:placetype":"postalcode"
},
  "geometry": {"coordinates":[135.1583,34.2517],"type":"Point"}
}