{
  "type": "Feature",
  "properties": {
    "gn:adm1_name":"Miyagiken",
    "gn:adm2_name":"Shiroishishi",
    "gn:name":"Kitamusousaku",
    "iso:country":"JP",
    "wof:name":"989-0224",
    "wof:placetype":"postalcode"
},
  "geometry": {"coordinates":[140.62970000000001,37.9989],"type":"Point"}
}