{
  "type": "Feature",
  "properties": {
    "gn:adm1_name":"Ishikawaken",
    "gn:adm2_name":"Fugeshigunmonzenmachi",
    "gn:name":"Kiribasami",
    "iso:country":"JP",
    "wof:name":"927-2311",
    "wof:placetype":"postalcode"
},
  "geometry": {"coordinates":[136.7568,37.2234],"type":"Point"}
}