{
  "type": "Feature",
  "properties": {
    "gn:adm1_name":"Chibaken",
    "gn:adm2_name":"Sanbugunyokoshibamachi",
    "gn:name":"Terakata",
    "iso:country":"JP",
    "wof:name":"289-1746",
    "wof:placetype":"postalcode"
},
  "geometry": {"coordinates":[140.46789999999999,35.6758],"type":"Point"}
}