{
  "type": "Feature",
  "properties": {
    "gn:adm1_name":"Chibaken",
    "gn:adm2_name":"Abikoshi",
    "gn:name":"Kounoyamashinden",
    "iso:country":"JP",
    "wof:name":"270-1146",
    "wof:placetype":"postalcode"
},
  "geometry": {"coordinates":[140.03370000000001,35.8616],"type":"Point"}
}