{
  "type": "Feature",
  "properties": {
    "gn:adm1_name":"Ibarakiken",
    "gn:adm2_name":"Ryuugasakishi",
    "gn:name":"Nakanedai",
    "iso:country":"JP",
    "wof:name":"301-0002",
    "wof:placetype":"postalcode"
},
  "geometry": {"coordinates":[140.17269999999999,35.9304],"type":"Point"}
}