{
  "type": "Feature",
  "properties": {
    "gn:adm1_name":"Ehimeken",
    "gn:adm2_name":"Uwajimashi",
    "gn:name":"Kawachi(Yakushidani)",
    "iso:country":"JP",
    "wof:name":"798-0076",
    "wof:placetype":"postalcode"
},
  "geometry": {"coordinates":[132.5573,33.2002],"type":"Point"}
}