{
  "type": "Feature",
  "properties": {
    "gn:adm1_name":"Ishikawaken",
    "gn:adm2_name":"Fugeshigunmonzenmachi",
    "gn:name":"Kyuukawa",
    "iso:country":"JP",
    "wof:name":"927-2321",
    "wof:placetype":"postalcode"
},
  "geometry": {"coordinates":[136.75389999999999,37.2117],"type":"Point"}
}