{
  "type": "Feature",
  "properties": {
    "gn:adm1_name":"Okayamaken",
    "gn:adm2_name":"Aidagun'Aidachou",
    "gn:name":"Jouden",
    "iso:country":"JP",
    "wof:name":"701-2625",
    "wof:placetype":"postalcode"
},
  "geometry": {"coordinates":[134.10329999999999,34.9672],"type":"Point"}
}