{
  "type": "Feature",
  "properties": {
    "gn:adm1_name":"Yamagataken",
    "gn:adm2_name":"Sakatashi",
    "gn:name":"Miyaumi",
    "iso:country":"JP",
    "wof:name":"998-0005",
    "wof:placetype":"postalcode"
},
  "geometry": {"coordinates":[139.8449,38.9694],"type":"Point"}
}