{
  "type": "Feature",
  "properties": {
    "gn:adm1_name":"Kumamotoken",
    "gn:adm2_name":"Kamimashikigunmifunemachi",
    "gn:name":"Takigawa",
    "iso:country":"JP",
    "wof:name":"861-3205",
    "wof:placetype":"postalcode"
},
  "geometry": {"coordinates":[130.7912,32.7151],"type":"Point"}
}