{
  "type": "Feature",
  "properties": {
    "gn:adm1_name":"Kagoshimaken",
    "gn:adm2_name":"Hiokigunkinpouchou",
    "gn:name":"Niiyama",
    "iso:country":"JP",
    "wof:name":"899-3514",
    "wof:placetype":"postalcode"
},
  "geometry": {"coordinates":[130.3486,31.4392],"type":"Point"}
}