{
  "type": "Feature",
  "properties": {
    "gn:adm1_name":"Ooitaken",
    "gn:adm2_name":"Ooitashi",
    "gn:name":"Madokoro",
    "iso:country":"JP",
    "wof:name":"870-0268",
    "wof:placetype":"postalcode"
},
  "geometry": {"coordinates":[131.72329999999999,33.2448],"type":"Point"}
}