{
  "type": "Feature",
  "properties": {
    "gn:adm1_name":"Ehimeken",
    "gn:adm2_name":"Kitauwagunyoshidachou",
    "gn:name":"Tachima",
    "iso:country":"JP",
    "wof:name":"799-3730",
    "wof:placetype":"postalcode"
},
  "geometry": {"coordinates":[132.55289999999999,33.3087],"type":"Point"}
}