{
  "type": "Feature",
  "properties": {
    "gn:adm1_name":"Hyougoken",
    "gn:adm2_name":"Nishinomiyashi",
    "gn:name":"Higashihamachou",
    "iso:country":"JP",
    "wof:name":"662-0924",
    "wof:placetype":"postalcode"
},
  "geometry": {"coordinates":[135.3441,34.7254],"type":"Point"}
}