{
  "type": "Feature",
  "properties": {
    "gn:adm1_name":"Miyazakiken",
    "gn:adm2_name":"Nichinanshi",
    "gn:name":"Zaimokuchou",
    "iso:country":"JP",
    "wof:name":"887-0005",
    "wof:placetype":"postalcode"
},
  "geometry": {"coordinates":[131.40090000000001,31.5866],"type":"Point"}
}