{
  "type": "Feature",
  "properties": {
    "gn:adm1_name":"Toyamaken",
    "gn:adm2_name":"Takaokashi",
    "gn:name":"Tsuno",
    "iso:country":"JP",
    "wof:name":"933-0007",
    "wof:placetype":"postalcode"
},
  "geometry": {"coordinates":[137.036,36.761],"type":"Point"}
}