{
  "type": "Feature",
  "properties": {
    "gn:adm1_name":"Miyagiken",
    "gn:adm2_name":"Shibatagun'Oogawaramachi",
    "gn:name":"Hashimoto",
    "iso:country":"JP",
    "wof:name":"989-1251",
    "wof:placetype":"postalcode"
},
  "geometry": {"coordinates":[140.7235,38.0643],"type":"Point"}
}