{
  "type": "Feature",
  "properties": {
    "gn:adm1_name":"Ehimeken",
    "gn:adm2_name":"Niihamashi",
    "gn:name":"Ochigamichou",
    "iso:country":"JP",
    "wof:name":"792-0883",
    "wof:placetype":"postalcode"
},
  "geometry": {"coordinates":[133.32149999999999,33.9666],"type":"Point"}
}