{
  "type": "Feature",
  "properties": {
    "gn:adm1_name":"Toyamaken",
    "gn:adm2_name":"Oyabeshi",
    "gn:name":"Shimonaka",
    "iso:country":"JP",
    "wof:name":"932-0804",
    "wof:placetype":"postalcode"
},
  "geometry": {"coordinates":[136.9102,36.6658],"type":"Point"}
}