{
  "type": "Feature",
  "properties": {
    "gn:adm1_name":"Toyamaken",
    "gn:adm2_name":"Namerikawashi",
    "gn:name":"Dainichi",
    "iso:country":"JP",
    "wof:name":"936-0813",
    "wof:placetype":"postalcode"
},
  "geometry": {"coordinates":[137.42320000000001,36.7398],"type":"Point"}
}