{
  "type": "Feature",
  "properties": {
    "gn:adm1_name":"Kyoutofu",
    "gn:adm2_name":"Kyoutoshisakyouku",
    "gn:name":"Shuugakuinkawajirichou",
    "iso:country":"JP",
    "wof:name":"606-8026",
    "wof:placetype":"postalcode"
},
  "geometry": {"coordinates":[135.79580000000001,35.0531],"type":"Point"}
}