{
  "type": "Feature",
  "properties": {
    "gn:adm1_name":"Ooitaken",
    "gn:adm2_name":"Oonogun'Ogatamachi",
    "gn:name":"Inoue",
    "iso:country":"JP",
    "wof:name":"879-6613",
    "wof:placetype":"postalcode"
},
  "geometry": {"coordinates":[131.4889,32.9684],"type":"Point"}
}