{
  "type": "Feature",
  "properties": {
    "gn:adm1_name":"Naganoken",
    "gn:adm2_name":"Naganoshi",
    "gn:name":"Higashigochou",
    "iso:country":"JP",
    "wof:name":"380-0832",
    "wof:placetype":"postalcode"
},
  "geometry": {"coordinates":[138.1875,36.6537],"type":"Point"}
}