{
  "type": "Feature",
  "properties": {
    "gn:adm1_name":"Miyazakiken",
    "gn:adm2_name":"Kitamorokataguntakajouchou",
    "gn:name":"Sakuragi",
    "iso:country":"JP",
    "wof:name":"885-1204",
    "wof:placetype":"postalcode"
},
  "geometry": {"coordinates":[131.1216,31.7848],"type":"Point"}
}