{
  "type": "Feature",
  "properties": {
    "gn:adm1_name":"Ibarakiken",
    "gn:adm2_name":"Hitachinakashi",
    "gn:name":"Mitanda",
    "iso:country":"JP",
    "wof:name":"312-0021",
    "wof:placetype":"postalcode"
},
  "geometry": {"coordinates":[140.55260000000001,36.3672],"type":"Point"}
}