{
  "type": "Feature",
  "properties": {
    "gn:adm1_name":"Aichiken",
    "gn:adm2_name":"Nagoyashikitaku",
    "gn:name":"Doubanchou",
    "iso:country":"JP",
    "wof:name":"462-0868",
    "wof:placetype":"postalcode"
},
  "geometry": {"coordinates":[136.92189999999999,35.1984],"type":"Point"}
}