{
  "type": "Feature",
  "properties": {
    "gn:adm1_name":"Fukushimaken",
    "gn:adm2_name":"Fukushimashi",
    "gn:name":"Motouchi(Sonota)",
    "iso:country":"JP",
    "wof:name":"960-0103",
    "wof:placetype":"postalcode"
},
  "geometry": {"coordinates":[140.4907,37.7835],"type":"Point"}
}