{
  "type": "Feature",
  "properties": {
    "gn:adm1_name":"Toukyouto",
    "gn:adm2_name":"Hachioujishi",
    "gn:name":"Nishiterakatamachi",
    "iso:country":"JP",
    "wof:name":"192-0153",
    "wof:placetype":"postalcode"
},
  "geometry": {"coordinates":[139.26849999999999,35.6787],"type":"Point"}
}