{
  "type": "Feature",
  "properties": {
    "gn:adm1_name":"Kyoutofu",
    "gn:adm2_name":"Kyoutoshiminamiku",
    "gn:name":"Karahashiakakanechou",
    "iso:country":"JP",
    "wof:name":"601-8463",
    "wof:placetype":"postalcode"
},
  "geometry": {"coordinates":[135.74170000000001,34.9833],"type":"Point"}
}