{
  "type": "Feature",
  "properties": {
    "gn:adm1_name":"Hyougoken",
    "gn:adm2_name":"Nishinomiyashi",
    "gn:name":"Koushienguchi",
    "iso:country":"JP",
    "wof:name":"663-8113",
    "wof:placetype":"postalcode"
},
  "geometry": {"coordinates":[135.37209999999999,34.7366],"type":"Point"}
}