{
  "type": "Feature",
  "properties": {
    "gn:adm1_name":"Hyougoken",
    "gn:adm2_name":"Takasagoshi",
    "gn:name":"Takasagochouryoushimachi",
    "iso:country":"JP",
    "wof:name":"676-0048",
    "wof:placetype":"postalcode"
},
  "geometry": {"coordinates":[134.80240000000001,34.7441],"type":"Point"}
}