{
  "type": "Feature",
  "properties": {
    "gn:adm1_name":"Aichiken",
    "gn:adm2_name":"Nishioshi",
    "gn:name":"Takabatachou",
    "iso:country":"JP",
    "wof:name":"445-0064",
    "wof:placetype":"postalcode"
},
  "geometry": {"coordinates":[137.0592,34.8631],"type":"Point"}
}