{
  "type": "Feature",
  "properties": {
    "gn:adm1_name":"Shimaneken",
    "gn:adm2_name":"Nimagunyunotsumachi",
    "gn:name":"Idaogimura",
    "iso:country":"JP",
    "wof:name":"699-2504",
    "wof:placetype":"postalcode"
},
  "geometry": {"coordinates":[132.392,35.0586],"type":"Point"}
}