{
  "type": "Feature",
  "properties": {
    "gn:adm1_name":"Okinawaken",
    "gn:adm2_name":"Shimajiriguntamagusukuson",
    "gn:name":"Fusato",
    "iso:country":"JP",
    "wof:name":"901-0611",
    "wof:placetype":"postalcode"
},
  "geometry": {"coordinates":[127.76900000000001,26.1431],"type":"Point"}
}