{
  "type": "Feature",
  "properties": {
    "gn:adm1_name":"Aichiken",
    "gn:adm2_name":"Nagoyashinakaku",
    "gn:name":"Honmaru",
    "iso:country":"JP",
    "wof:name":"460-0031",
    "wof:placetype":"postalcode"
},
  "geometry": {"coordinates":[136.89779999999999,35.1842],"type":"Point"}
}