{
  "type": "Feature",
  "properties": {
    "gn:adm1_name":"Shigaken",
    "gn:adm2_name":"Kanzakigungokashouchou",
    "gn:name":"Obata",
    "iso:country":"JP",
    "wof:name":"529-1422",
    "wof:placetype":"postalcode"
},
  "geometry": {"coordinates":[136.19659999999999,35.1546],"type":"Point"}
}