{
  "type": "Feature",
  "properties": {
    "gn:adm1_name":"Saitamaken",
    "gn:adm2_name":"Iwatsukishi",
    "gn:name":"Oomori",
    "iso:country":"JP",
    "wof:name":"339-0017",
    "wof:placetype":"postalcode"
},
  "geometry": {"coordinates":[139.74700000000001,35.9291],"type":"Point"}
}