{
  "type": "Feature",
  "properties": {
    "gn:adm1_name":"Oosakafu",
    "gn:adm2_name":"Ibarakishi",
    "gn:name":"Ogawachou",
    "iso:country":"JP",
    "wof:name":"567-0873",
    "wof:placetype":"postalcode"
},
  "geometry": {"coordinates":[135.56880000000001,34.8097],"type":"Point"}
}