{
  "type": "Feature",
  "properties": {
    "gn:adm1_name":"Saitamaken",
    "gn:adm2_name":"Koshigayashi",
    "gn:name":"Gamouhonchou",
    "iso:country":"JP",
    "wof:name":"343-0837",
    "wof:placetype":"postalcode"
},
  "geometry": {"coordinates":[139.7972,35.8638],"type":"Point"}
}