{
  "type": "Feature",
  "properties": {
    "gn:adm1_name":"Hyougoken",
    "gn:adm2_name":"Mikatagunhamasakachou",
    "gn:name":"Wada",
    "iso:country":"JP",
    "wof:name":"669-6716",
    "wof:placetype":"postalcode"
},
  "geometry": {"coordinates":[134.51070000000001,35.6402],"type":"Point"}
}