{
  "type": "Feature",
  "properties": {
    "gn:adm1_name":"Chibaken",
    "gn:adm2_name":"Kisaradushi",
    "gn:name":"Iwane",
    "iso:country":"JP",
    "wof:name":"292-0061",
    "wof:placetype":"postalcode"
},
  "geometry": {"coordinates":[139.92939999999999,35.4136],"type":"Point"}
}