{
  "type": "Feature",
  "properties": {
    "gn:adm1_name":"Shizuokaken",
    "gn:adm2_name":"Ogasagundaitouchou",
    "gn:name":"Kamihijikataminemukai",
    "iso:country":"JP",
    "wof:name":"437-1435",
    "wof:placetype":"postalcode"
},
  "geometry": {"coordinates":[138.03980000000001,34.7034],"type":"Point"}
}