{
  "type": "Feature",
  "properties": {
    "gn:adm1_name":"Nagasakiken",
    "gn:adm2_name":"Kitamatsuuragun'Emukaechou",
    "gn:name":"Ikanikeisaiganaibaai",
    "iso:country":"JP",
    "wof:name":"859-6100",
    "wof:placetype":"postalcode"
},
  "geometry": {"coordinates":[129.61349999999999,33.3132],"type":"Point"}
}