{
  "type": "Feature",
  "properties": {
    "gn:adm1_name":"Nagasakiken",
    "gn:adm2_name":"Ikigunkatsumotochou",
    "gn:name":"Honguuminamifure",
    "iso:country":"JP",
    "wof:name":"811-5545",
    "wof:placetype":"postalcode"
},
  "geometry": {"coordinates":[129.68620000000001,33.8134],"type":"Point"}
}