{
  "type": "Feature",
  "properties": {
    "gn:adm1_name":"Ibarakiken",
    "gn:adm2_name":"Higashiibarakigun'Ibarakimachi",
    "gn:name":"Shimoamagai",
    "iso:country":"JP",
    "wof:name":"311-3144",
    "wof:placetype":"postalcode"
},
  "geometry": {"coordinates":[140.4051,36.2326],"type":"Point"}
}