{
  "type": "Feature",
  "properties": {
    "gn:adm1_name":"Toyamaken",
    "gn:adm2_name":"Higashitonamiguntogamura",
    "gn:name":"Sakaue",
    "iso:country":"JP",
    "wof:name":"939-2516",
    "wof:placetype":"postalcode"
},
  "geometry": {"coordinates":[137.0061,36.4247],"type":"Point"}
}