{
  "type": "Feature",
  "properties": {
    "gn:adm1_name":"Gunmaken",
    "gn:adm2_name":"Fujiokashi",
    "gn:name":"Nakajima",
    "iso:country":"JP",
    "wof:name":"375-0001",
    "wof:placetype":"postalcode"
},
  "geometry": {"coordinates":[139.0788,36.2873],"type":"Point"}
}