{
  "type": "Feature",
  "properties": {
    "gn:adm1_name":"Fukuokaken",
    "gn:adm2_name":"Yukuhashishi",
    "gn:name":"Sumazono",
    "iso:country":"JP",
    "wof:name":"824-0072",
    "wof:placetype":"postalcode"
},
  "geometry": {"coordinates":[130.92519999999999,33.7411],"type":"Point"}
}