{
  "type": "Feature",
  "properties": {
    "gn:adm1_name":"Saitamaken",
    "gn:adm2_name":"Kasukabeshi",
    "gn:name":"Yahara",
    "iso:country":"JP",
    "wof:name":"344-0065",
    "wof:placetype":"postalcode"
},
  "geometry": {"coordinates":[139.74690000000001,35.9709],"type":"Point"}
}