{
  "type": "Feature",
  "properties": {
    "gn:adm1_name":"Hyougoken",
    "gn:adm2_name":"Nishinomiyashi",
    "gn:name":"Imaduminatochou",
    "iso:country":"JP",
    "wof:name":"663-8226",
    "wof:placetype":"postalcode"
},
  "geometry": {"coordinates":[135.34989999999999,34.723],"type":"Point"}
}