{
  "type": "Feature",
  "properties": {
    "gn:adm1_name":"Oosakafu",
    "gn:adm2_name":"Sennangunkumatorichou",
    "gn:name":"Shichama",
    "iso:country":"JP",
    "wof:name":"590-0421",
    "wof:placetype":"postalcode"
},
  "geometry": {"coordinates":[135.35890000000001,34.4142],"type":"Point"}
}