{
  "type": "Feature",
  "properties": {
    "gn:adm1_name":"Ooitaken",
    "gn:adm2_name":"Ooitashi",
    "gn:name":"Yokose",
    "iso:country":"JP",
    "wof:name":"870-1173",
    "wof:placetype":"postalcode"
},
  "geometry": {"coordinates":[131.54130000000001,33.1877],"type":"Point"}
}