{
  "type": "Feature",
  "properties": {
    "gn:adm1_name":"Oosakafu",
    "gn:adm2_name":"Izumisanoshi",
    "gn:name":"Hagurazakiuemachi",
    "iso:country":"JP",
    "wof:name":"598-0037",
    "wof:placetype":"postalcode"
},
  "geometry": {"coordinates":[135.29949999999999,34.397],"type":"Point"}
}