{
  "type": "Feature",
  "properties": {
    "gn:adm1_name":"Fukuokaken",
    "gn:adm2_name":"Dazaifushi",
    "gn:name":"Sakamoto",
    "iso:country":"JP",
    "wof:name":"818-0133",
    "wof:placetype":"postalcode"
},
  "geometry": {"coordinates":[130.50729999999999,33.5162],"type":"Point"}
}