{
  "type": "Feature",
  "properties": {
    "gn:adm1_name":"Ishikawaken",
    "gn:adm2_name":"Kagashi",
    "gn:name":"Kamomachi",
    "iso:country":"JP",
    "wof:name":"922-0241",
    "wof:placetype":"postalcode"
},
  "geometry": {"coordinates":[136.3597,36.3087],"type":"Point"}
}