{
  "type": "Feature",
  "properties": {
    "gn:adm1_name":"Shigaken",
    "gn:adm2_name":"Takashimagunshin'Asahichou",
    "gn:name":"Yasuigawa",
    "iso:country":"JP",
    "wof:name":"520-1533",
    "wof:placetype":"postalcode"
},
  "geometry": {"coordinates":[136.024,35.3512],"type":"Point"}
}