{
  "type": "Feature",
  "properties": {
    "gn:adm1_name":"Aichiken",
    "gn:adm2_name":"Setoshi",
    "gn:name":"Nishinaganechou",
    "iso:country":"JP",
    "wof:name":"489-0929",
    "wof:placetype":"postalcode"
},
  "geometry": {"coordinates":[137.07210000000001,35.2135],"type":"Point"}
}