{
  "type": "Feature",
  "properties": {
    "gn:adm1_name":"Yamagataken",
    "gn:adm2_name":"Yonezawashi",
    "gn:name":"Tsunagi",
    "iso:country":"JP",
    "wof:name":"992-1474",
    "wof:placetype":"postalcode"
},
  "geometry": {"coordinates":[140.0675,37.8043],"type":"Point"}
}