{
  "type": "Feature",
  "properties": {
    "gn:adm1_name":"Toyamaken",
    "gn:adm2_name":"Toyamashi",
    "gn:name":"Kamiimamachi",
    "iso:country":"JP",
    "wof:name":"939-8144",
    "wof:placetype":"postalcode"
},
  "geometry": {"coordinates":[137.24969999999999,36.606],"type":"Point"}
}