{
  "type": "Feature",
  "properties": {
    "gn:adm1_name":"Fukuokaken",
    "gn:adm2_name":"Kurumeshi",
    "gn:name":"Ooishimachi",
    "iso:country":"JP",
    "wof:name":"830-0049",
    "wof:placetype":"postalcode"
},
  "geometry": {"coordinates":[130.4949,33.3153],"type":"Point"}
}