{
  "type": "Feature",
  "properties": {
    "gn:adm1_name":"Hyougoken",
    "gn:adm2_name":"Koubeshisumaku",
    "gn:name":"Tsukimiyamachou",
    "iso:country":"JP",
    "wof:name":"654-0063",
    "wof:placetype":"postalcode"
},
  "geometry": {"coordinates":[135.1215,34.6513],"type":"Point"}
}