{
  "type": "Feature",
  "properties": {
    "gn:adm1_name":"Kagoshimaken",
    "gn:adm2_name":"Kumagegunkamiyakuchou",
    "gn:name":"Nagata",
    "iso:country":"JP",
    "wof:name":"891-4201",
    "wof:placetype":"postalcode"
},
  "geometry": {"coordinates":[130.4271,30.3971],"type":"Point"}
}