{
  "type": "Feature",
  "properties": {
    "gn:adm1_name":"Miyagiken",
    "gn:adm2_name":"Sendaishitaihakuku",
    "gn:name":"Keiwamachi",
    "iso:country":"JP",
    "wof:name":"982-0823",
    "wof:placetype":"postalcode"
},
  "geometry": {"coordinates":[140.85470000000001,38.2363],"type":"Point"}
}