{
  "type": "Feature",
  "properties": {
    "gn:adm1_name":"Tottoriken",
    "gn:adm2_name":"Touhakugun'Akasakichou",
    "gn:name":"Oobu",
    "iso:country":"JP",
    "wof:name":"689-2524",
    "wof:placetype":"postalcode"
},
  "geometry": {"coordinates":[133.6266,35.4362],"type":"Point"}
}