{
  "type": "Feature",
  "properties": {
    "gn:adm1_name":"Naganoken",
    "gn:adm2_name":"Nakanoshi",
    "gn:name":"Fukasawa",
    "iso:country":"JP",
    "wof:name":"383-0006",
    "wof:placetype":"postalcode"
},
  "geometry": {"coordinates":[138.38220000000001,36.7756],"type":"Point"}
}