{
  "type": "Feature",
  "properties": {
    "gn:adm1_name":"Chibaken",
    "gn:adm2_name":"Sakurashi",
    "gn:name":"Oota",
    "iso:country":"JP",
    "wof:name":"285-0808",
    "wof:placetype":"postalcode"
},
  "geometry": {"coordinates":[140.21680000000001,35.6932],"type":"Point"}
}