{
  "type": "Feature",
  "properties": {
    "gn:adm1_name":"Kanagawaken",
    "gn:adm2_name":"Yokohamashiseyaku",
    "gn:name":"Oroshihonchou",
    "iso:country":"JP",
    "wof:name":"246-0001",
    "wof:placetype":"postalcode"
},
  "geometry": {"coordinates":[139.4862,35.4997],"type":"Point"}
}