{
  "type": "Feature",
  "properties": {
    "gn:adm1_name":"Miyazakiken",
    "gn:adm2_name":"Higashimorokatagunkunitomichou",
    "gn:name":"Tajiri",
    "iso:country":"JP",
    "wof:name":"880-1104",
    "wof:placetype":"postalcode"
},
  "geometry": {"coordinates":[131.30680000000001,31.9843],"type":"Point"}
}