{
  "type": "Feature",
  "properties": {
    "gn:adm1_name":"Aichiken",
    "gn:adm2_name":"Toyotashi",
    "gn:name":"Senzokuchou",
    "iso:country":"JP",
    "wof:name":"471-0847",
    "wof:placetype":"postalcode"
},
  "geometry": {"coordinates":[137.10810000000001,35.0803],"type":"Point"}
}