{
  "type": "Feature",
  "properties": {
    "gn:adm1_name":"Kyoutofu",
    "gn:adm2_name":"Kyoutoshishimogyouku",
    "gn:name":"Nioitenjinchou",
    "iso:country":"JP",
    "wof:name":"600-8414",
    "wof:placetype":"postalcode"
},
  "geometry": {"coordinates":[135.7603,35.0006],"type":"Point"}
}