{
  "type": "Feature",
  "properties": {
    "gn:adm1_name":"Naraken",
    "gn:adm2_name":"Yoshinogunnishiyoshinomura",
    "gn:name":"Hiranumata",
    "iso:country":"JP",
    "wof:name":"638-0642",
    "wof:placetype":"postalcode"
},
  "geometry": {"coordinates":[135.755,34.3198],"type":"Point"}
}