{
  "type": "Feature",
  "properties": {
    "gn:adm1_name":"Shimaneken",
    "gn:adm2_name":"Oochigun'Oochichou",
    "gn:name":"Soumori",
    "iso:country":"JP",
    "wof:name":"696-1134",
    "wof:placetype":"postalcode"
},
  "geometry": {"coordinates":[132.52590000000001,35.0804],"type":"Point"}
}