{
  "type": "Feature",
  "properties": {
    "gn:adm1_name":"Kouchiken",
    "gn:adm2_name":"Tosashimizushi",
    "gn:name":"Motomachi",
    "iso:country":"JP",
    "wof:name":"787-0304",
    "wof:placetype":"postalcode"
},
  "geometry": {"coordinates":[132.95699999999999,32.78],"type":"Point"}
}