{
  "type": "Feature",
  "properties": {
    "gn:adm1_name":"Hiroshimaken",
    "gn:adm2_name":"Ootakeshi",
    "gn:name":"Kuritanichouhirohara",
    "iso:country":"JP",
    "wof:name":"739-0641",
    "wof:placetype":"postalcode"
},
  "geometry": {"coordinates":[132.1943,34.3272],"type":"Point"}
}