{
  "type": "Feature",
  "properties": {
    "gn:adm1_name":"Aichiken",
    "gn:adm2_name":"Nishioshi",
    "gn:name":"Etakechou",
    "iso:country":"JP",
    "wof:name":"445-0031",
    "wof:placetype":"postalcode"
},
  "geometry": {"coordinates":[137.10400000000001,34.8572],"type":"Point"}
}