{
  "type": "Feature",
  "properties": {
    "gn:adm1_name":"Naraken",
    "gn:adm2_name":"Narashi",
    "gn:name":"Higashishinzaikechou",
    "iso:country":"JP",
    "wof:name":"630-8272",
    "wof:placetype":"postalcode"
},
  "geometry": {"coordinates":[135.79560000000001,34.6862],"type":"Point"}
}