{
  "type": "Feature",
  "properties": {
    "gn:adm1_name":"Nagasakiken",
    "gn:adm2_name":"Kitamatsuuragunsazachou",
    "gn:name":"Koudamen",
    "iso:country":"JP",
    "wof:name":"857-0336",
    "wof:placetype":"postalcode"
},
  "geometry": {"coordinates":[129.66820000000001,33.2587],"type":"Point"}
}