{
  "type": "Feature",
  "properties": {
    "gn:adm1_name":"Aichiken",
    "gn:adm2_name":"Chitagunminamichitachou",
    "gn:name":"Utsumi",
    "iso:country":"JP",
    "wof:name":"470-3321",
    "wof:placetype":"postalcode"
},
  "geometry": {"coordinates":[136.87530000000001,34.7407],"type":"Point"}
}