{
  "type": "Feature",
  "properties": {
    "gn:adm1_name":"Chibaken",
    "gn:adm2_name":"Asahishi",
    "gn:name":"Nittama",
    "iso:country":"JP",
    "wof:name":"289-2525",
    "wof:placetype":"postalcode"
},
  "geometry": {"coordinates":[140.6395,35.7008],"type":"Point"}
}