{
  "type": "Feature",
  "properties": {
    "gn:adm1_name":"Miyagiken",
    "gn:adm2_name":"Kuriharagun'Ichihasamachou",
    "gn:name":"Oohirasawa",
    "iso:country":"JP",
    "wof:name":"987-2348",
    "wof:placetype":"postalcode"
},
  "geometry": {"coordinates":[140.8887,38.7532],"type":"Point"}
}