{
  "type": "Feature",
  "properties": {
    "gn:adm1_name":"Fukushimaken",
    "gn:adm2_name":"Ishikawagun'Asakawamachi",
    "gn:name":"Onuki",
    "iso:country":"JP",
    "wof:name":"963-6207",
    "wof:placetype":"postalcode"
},
  "geometry": {"coordinates":[140.38630000000001,37.0791],"type":"Point"}
}