{
  "type": "Feature",
  "properties": {
    "gn:adm1_name":"Okayamaken",
    "gn:adm2_name":"Tomatagun'Okutsuchou",
    "gn:name":"Nishiya",
    "iso:country":"JP",
    "wof:name":"708-0426",
    "wof:placetype":"postalcode"
},
  "geometry": {"coordinates":[133.89609999999999,35.1723],"type":"Point"}
}