{
  "type": "Feature",
  "properties": {
    "gn:adm1_name":"Mieken",
    "gn:adm2_name":"Matsusakashi",
    "gn:name":"Miozonochou",
    "iso:country":"JP",
    "wof:name":"519-2148",
    "wof:placetype":"postalcode"
},
  "geometry": {"coordinates":[136.49600000000001,34.5092],"type":"Point"}
}