{
  "type": "Feature",
  "properties": {
    "gn:adm1_name":"Miyagiken",
    "gn:adm2_name":"Kesennumashi",
    "gn:name":"Higashiminatochou",
    "iso:country":"JP",
    "wof:name":"988-0001",
    "wof:placetype":"postalcode"
},
  "geometry": {"coordinates":[141.5849,38.9161],"type":"Point"}
}