{
  "type": "Feature",
  "properties": {
    "gn:adm1_name":"Tokushimaken",
    "gn:adm2_name":"Ananshi",
    "gn:name":"Haragasakichou",
    "iso:country":"JP",
    "wof:name":"774-0008",
    "wof:placetype":"postalcode"
},
  "geometry": {"coordinates":[134.67769999999999,33.9315],"type":"Point"}
}