{
  "type": "Feature",
  "properties": {
    "gn:adm1_name":"Kanagawaken",
    "gn:adm2_name":"Yokohamashitsurumiku",
    "gn:name":"Suwazaka",
    "iso:country":"JP",
    "wof:name":"230-0014",
    "wof:placetype":"postalcode"
},
  "geometry": {"coordinates":[139.6688,35.5159],"type":"Point"}
}