{
  "type": "Feature",
  "properties": {
    "gn:adm1_name":"Gunmaken",
    "gn:adm2_name":"Setagunkurohonemura",
    "gn:name":"Mizunuma",
    "iso:country":"JP",
    "wof:name":"376-0141",
    "wof:placetype":"postalcode"
},
  "geometry": {"coordinates":[139.28200000000001,36.5014],"type":"Point"}
}