{
  "type": "Feature",
  "properties": {
    "gn:adm1_name":"Shizuokaken",
    "gn:adm2_name":"Shizuokashi",
    "gn:name":"Shimizuokamachi",
    "iso:country":"JP",
    "wof:name":"424-0931",
    "wof:placetype":"postalcode"
},
  "geometry": {"coordinates":[138.48419999999999,35.0082],"type":"Point"}
}