{
  "type": "Feature",
  "properties": {
    "gn:adm1_name":"Fukuokaken",
    "gn:adm2_name":"Kitakyuushuushiyahatanishiku",
    "gn:name":"Kougasakimachi",
    "iso:country":"JP",
    "wof:name":"806-0041",
    "wof:placetype":"postalcode"
},
  "geometry": {"coordinates":[130.751,33.8652],"type":"Point"}
}