{
  "type": "Feature",
  "properties": {
    "gn:adm1_name":"Niigataken",
    "gn:adm2_name":"Mitsukeshi",
    "gn:name":"Mimitorimachi",
    "iso:country":"JP",
    "wof:name":"954-0043",
    "wof:placetype":"postalcode"
},
  "geometry": {"coordinates":[138.91900000000001,37.5028],"type":"Point"}
}