{
  "type": "Feature",
  "properties": {
    "gn:adm1_name":"Kouchiken",
    "gn:adm2_name":"Nankokushi",
    "gn:name":"Okouchouyoshida",
    "iso:country":"JP",
    "wof:name":"783-0045",
    "wof:placetype":"postalcode"
},
  "geometry": {"coordinates":[133.62960000000001,33.588],"type":"Point"}
}