{
  "type": "Feature",
  "properties": {
    "gn:adm1_name":"Naganoken",
    "gn:adm2_name":"Iiyamashi",
    "gn:name":"Sakai",
    "iso:country":"JP",
    "wof:name":"389-2235",
    "wof:placetype":"postalcode"
},
  "geometry": {"coordinates":[138.386,36.8591],"type":"Point"}
}