{
  "type": "Feature",
  "properties": {
    "gn:adm1_name":"Naraken",
    "gn:adm2_name":"Yoshinogunnishiyoshinomura",
    "gn:name":"Munegawano",
    "iso:country":"JP",
    "wof:name":"637-0237",
    "wof:placetype":"postalcode"
},
  "geometry": {"coordinates":[135.75120000000001,34.2611],"type":"Point"}
}