{
  "type": "Feature",
  "properties": {
    "gn:adm1_name":"Aichiken",
    "gn:adm2_name":"Chitaguntaketoyochou",
    "gn:name":"Hiraida",
    "iso:country":"JP",
    "wof:name":"470-2304",
    "wof:placetype":"postalcode"
},
  "geometry": {"coordinates":[136.90309999999999,34.8607],"type":"Point"}
}