{
  "type": "Feature",
  "properties": {
    "gn:adm1_name":"Shizuokaken",
    "gn:adm2_name":"Susonoshi",
    "gn:name":"Mugitsuka",
    "iso:country":"JP",
    "wof:name":"410-1122",
    "wof:placetype":"postalcode"
},
  "geometry": {"coordinates":[138.91329999999999,35.1636],"type":"Point"}
}