{
  "type": "Feature",
  "properties": {
    "gn:adm1_name":"Ishikawaken",
    "gn:adm2_name":"Kanazawashi",
    "gn:name":"Kitamachi",
    "iso:country":"JP",
    "wof:name":"920-0055",
    "wof:placetype":"postalcode"
},
  "geometry": {"coordinates":[136.6277,36.5829],"type":"Point"}
}