{
  "type": "Feature",
  "properties": {
    "gn:adm1_name":"Kouchiken",
    "gn:adm2_name":"Akishi",
    "gn:name":"Ooiotsu",
    "iso:country":"JP",
    "wof:name":"784-0275",
    "wof:placetype":"postalcode"
},
  "geometry": {"coordinates":[133.98159999999999,33.583],"type":"Point"}
}