{
  "type": "Feature",
  "properties": {
    "gn:adm1_name":"Kanagawaken",
    "gn:adm2_name":"Yamatoshi",
    "gn:name":"Kamisouyagi",
    "iso:country":"JP",
    "wof:name":"242-0029",
    "wof:placetype":"postalcode"
},
  "geometry": {"coordinates":[139.45009999999999,35.4784],"type":"Point"}
}