{
  "type": "Feature",
  "properties": {
    "gn:adm1_name":"Aichiken",
    "gn:adm2_name":"Nagoyashinakamuraku",
    "gn:name":"Gotanjouchou",
    "iso:country":"JP",
    "wof:name":"453-0836",
    "wof:placetype":"postalcode"
},
  "geometry": {"coordinates":[136.85319999999999,35.1597],"type":"Point"}
}