{
  "type": "Feature",
  "properties": {
    "gn:adm1_name":"Naraken",
    "gn:adm2_name":"Udagunmitsuemura",
    "gn:name":"Tsuchiyahara",
    "iso:country":"JP",
    "wof:name":"633-1303",
    "wof:placetype":"postalcode"
},
  "geometry": {"coordinates":[136.13310000000001,34.4824],"type":"Point"}
}