{
  "type": "Feature",
  "properties": {
    "gn:adm1_name":"Toyamaken",
    "gn:adm2_name":"Himishi",
    "gn:name":"Kawata",
    "iso:country":"JP",
    "wof:name":"935-0105",
    "wof:placetype":"postalcode"
},
  "geometry": {"coordinates":[136.96950000000001,36.8003],"type":"Point"}
}