{
  "type": "Feature",
  "properties": {
    "gn:adm1_name":"Tochigiken",
    "gn:adm2_name":"Utsunomiyashi",
    "gn:name":"Kamikoikemachi",
    "iso:country":"JP",
    "wof:name":"321-2104",
    "wof:placetype":"postalcode"
},
  "geometry": {"coordinates":[139.78999999999999,36.6832],"type":"Point"}
}