{
  "type": "Feature",
  "properties": {
    "gn:adm1_name":"Yamagataken",
    "gn:adm2_name":"Yamagatashi",
    "gn:name":"Kamiyanbemachi",
    "iso:country":"JP",
    "wof:name":"990-0004",
    "wof:placetype":"postalcode"
},
  "geometry": {"coordinates":[140.3621,38.2685],"type":"Point"}
}