{
  "type": "Feature",
  "properties": {
    "gn:adm1_name":"Yamagataken",
    "gn:adm2_name":"Nagaishi",
    "gn:name":"Nakaisazawa",
    "iso:country":"JP",
    "wof:name":"993-0024",
    "wof:placetype":"postalcode"
},
  "geometry": {"coordinates":[140.0669,38.0846],"type":"Point"}
}