{
  "type": "Feature",
  "properties": {
    "gn:adm1_name":"Kagoshimaken",
    "gn:adm2_name":"Kanoyashi",
    "gn:name":"Nishihara",
    "iso:country":"JP",
    "wof:name":"893-0064",
    "wof:placetype":"postalcode"
},
  "geometry": {"coordinates":[130.834,31.386],"type":"Point"}
}