{
  "type": "Feature",
  "properties": {
    "gn:adm1_name":"Mieken",
    "gn:adm2_name":"Owaseshi",
    "gn:name":"Kitaurahigashimachi",
    "iso:country":"JP",
    "wof:name":"519-3609",
    "wof:placetype":"postalcode"
},
  "geometry": {"coordinates":[136.19970000000001,34.0805],"type":"Point"}
}