{
  "type": "Feature",
  "properties": {
    "gn:adm1_name":"Aichiken",
    "gn:adm2_name":"Okazakishi",
    "gn:name":"Saikurichou",
    "iso:country":"JP",
    "wof:name":"444-3342",
    "wof:placetype":"postalcode"
},
  "geometry": {"coordinates":[137.2449,34.9609],"type":"Point"}
}