{
  "type": "Feature",
  "properties": {
    "gn:adm1_name":"Gunmaken",
    "gn:adm2_name":"Yamadagun'Oomamamachi",
    "gn:name":"Oomama",
    "iso:country":"JP",
    "wof:name":"376-0101",
    "wof:placetype":"postalcode"
},
  "geometry": {"coordinates":[139.2784,36.4268],"type":"Point"}
}