{
  "type": "Feature",
  "properties": {
    "gn:adm1_name":"Hyougoken",
    "gn:adm2_name":"Mikishi",
    "gn:name":"Shijimichoumisaka",
    "iso:country":"JP",
    "wof:name":"673-0516",
    "wof:placetype":"postalcode"
},
  "geometry": {"coordinates":[135.05080000000001,34.793],"type":"Point"}
}