{
  "type": "Feature",
  "properties": {
    "gn:adm1_name":"Toukyouto",
    "gn:adm2_name":"Choufushi",
    "gn:name":"Nishimachi",
    "iso:country":"JP",
    "wof:name":"182-0032",
    "wof:placetype":"postalcode"
},
  "geometry": {"coordinates":[139.52709999999999,35.6678],"type":"Point"}
}