{
  "type": "Feature",
  "properties": {
    "gn:adm1_name":"Niigataken",
    "gn:adm2_name":"Iwafunegun'Arakawamachi",
    "gn:name":"Nashinoki",
    "iso:country":"JP",
    "wof:name":"959-3105",
    "wof:placetype":"postalcode"
},
  "geometry": {"coordinates":[139.45949999999999,38.1047],"type":"Point"}
}