{
  "type": "Feature",
  "properties": {
    "gn:adm1_name":"Kagawaken",
    "gn:adm2_name":"Marugameshi",
    "gn:name":"Honjimachoukoushou",
    "iso:country":"JP",
    "wof:name":"763-0222",
    "wof:placetype":"postalcode"
},
  "geometry": {"coordinates":[133.78909999999999,34.388],"type":"Point"}
}