{
  "type": "Feature",
  "properties": {
    "gn:adm1_name":"Fukushimaken",
    "gn:adm2_name":"Yamagunshiokawamachi",
    "gn:name":"Ootaki",
    "iso:country":"JP",
    "wof:name":"969-3536",
    "wof:placetype":"postalcode"
},
  "geometry": {"coordinates":[139.84399999999999,37.6112],"type":"Point"}
}