{
  "type": "Feature",
  "properties": {
    "gn:adm1_name":"Tottoriken",
    "gn:adm2_name":"Saihakugunyodoechou",
    "gn:name":"Imadu",
    "iso:country":"JP",
    "wof:name":"689-3401",
    "wof:placetype":"postalcode"
},
  "geometry": {"coordinates":[133.43049999999999,35.4655],"type":"Point"}
}