{
  "type": "Feature",
  "properties": {
    "gn:adm1_name":"Oosakafu",
    "gn:adm2_name":"Ibarakishi",
    "gn:name":"Ootechou",
    "iso:country":"JP",
    "wof:name":"567-0883",
    "wof:placetype":"postalcode"
},
  "geometry": {"coordinates":[135.57159999999999,34.8162],"type":"Point"}
}