{
  "type": "Feature",
  "properties": {
    "gn:adm1_name":"Nagasakiken",
    "gn:adm2_name":"Ikigun'Ashibechou",
    "gn:name":"Fukaehonmurafure",
    "iso:country":"JP",
    "wof:name":"811-5326",
    "wof:placetype":"postalcode"
},
  "geometry": {"coordinates":[129.74549999999999,33.7805],"type":"Point"}
}