{
  "type": "Feature",
  "properties": {
    "gn:adm1_name":"Yamanashiken",
    "gn:adm2_name":"Higashiyatsushirogunmisakachou",
    "gn:name":"Kokuga",
    "iso:country":"JP",
    "wof:name":"406-0808",
    "wof:placetype":"postalcode"
},
  "geometry": {"coordinates":[138.65090000000001,35.6373],"type":"Point"}
}