{
  "type": "Feature",
  "properties": {
    "gn:adm1_name":"Toukyouto",
    "gn:adm2_name":"Katsushikaku",
    "gn:name":"Higashikanamachi",
    "iso:country":"JP",
    "wof:name":"125-0041",
    "wof:placetype":"postalcode"
},
  "geometry": {"coordinates":[139.87530000000001,35.7742],"type":"Point"}
}