{
  "type": "Feature",
  "properties": {
    "gn:adm1_name":"Shigaken",
    "gn:adm2_name":"Kanzakigun'Eigenjichou",
    "gn:name":"Kamifutamata",
    "iso:country":"JP",
    "wof:name":"527-0221",
    "wof:placetype":"postalcode"
},
  "geometry": {"coordinates":[136.2903,35.0684],"type":"Point"}
}