{
  "type": "Feature",
  "properties": {
    "gn:adm1_name":"Tottoriken",
    "gn:adm2_name":"Sakaiminatoshi",
    "gn:name":"Shibachou",
    "iso:country":"JP",
    "wof:name":"684-0066",
    "wof:placetype":"postalcode"
},
  "geometry": {"coordinates":[133.21780000000001,35.5334],"type":"Point"}
}