{
  "type": "Feature",
  "properties": {
    "gn:adm1_name":"Kumamotoken",
    "gn:adm2_name":"Kumamotoshi",
    "gn:name":"Yamanokami",
    "iso:country":"JP",
    "wof:name":"862-0915",
    "wof:placetype":"postalcode"
},
  "geometry": {"coordinates":[130.7748,32.7966],"type":"Point"}
}