{
  "type": "Feature",
  "properties": {
    "gn:adm1_name":"Aichiken",
    "gn:adm2_name":"Inuyamashi",
    "gn:name":"Hagurokikukawa",
    "iso:country":"JP",
    "wof:name":"484-0882",
    "wof:placetype":"postalcode"
},
  "geometry": {"coordinates":[136.9453,35.3442],"type":"Point"}
}