{
  "type": "Feature",
  "properties": {
    "gn:adm1_name":"Fukuiken",
    "gn:adm2_name":"Tsurugashi",
    "gn:name":"Kagurachou",
    "iso:country":"JP",
    "wof:name":"914-0063",
    "wof:placetype":"postalcode"
},
  "geometry": {"coordinates":[136.07040000000001,35.6539],"type":"Point"}
}