{
  "type": "Feature",
  "properties": {
    "gn:adm1_name":"Hiroshimaken",
    "gn:adm2_name":"Higashihiroshimashi",
    "gn:name":"Takayachouinaki",
    "iso:country":"JP",
    "wof:name":"739-2106",
    "wof:placetype":"postalcode"
},
  "geometry": {"coordinates":[132.76859999999999,34.4517],"type":"Point"}
}