{
  "type": "Feature",
  "properties": {
    "gn:adm1_name":"Aichiken",
    "gn:adm2_name":"Tokonameshi",
    "gn:name":"Karasakichou",
    "iso:country":"JP",
    "wof:name":"479-0815",
    "wof:placetype":"postalcode"
},
  "geometry": {"coordinates":[136.8537,34.8684],"type":"Point"}
}