{
  "type": "Feature",
  "properties": {
    "gn:adm1_name":"Shimaneken",
    "gn:adm2_name":"Oodashi",
    "gn:name":"Tomiyamachousaizaka",
    "iso:country":"JP",
    "wof:name":"699-2215",
    "wof:placetype":"postalcode"
},
  "geometry": {"coordinates":[132.5917,35.2111],"type":"Point"}
}