{
  "type": "Feature",
  "properties": {
    "gn:adm1_name":"Okayamaken",
    "gn:adm2_name":"Mitsugunkamogawachou",
    "gn:name":"Shimodoi",
    "iso:country":"JP",
    "wof:name":"709-2551",
    "wof:placetype":"postalcode"
},
  "geometry": {"coordinates":[133.7619,34.8797],"type":"Point"}
}