{
  "type": "Feature",
  "properties": {
    "gn:adm1_name":"Fukuokaken",
    "gn:adm2_name":"Kitakyuushuushiyahatahigashiku",
    "gn:name":"Ishitsubomachi",
    "iso:country":"JP",
    "wof:name":"805-0021",
    "wof:placetype":"postalcode"
},
  "geometry": {"coordinates":[130.84059999999999,33.865],"type":"Point"}
}