{
  "type": "Feature",
  "properties": {
    "gn:adm1_name":"Kagawaken",
    "gn:adm2_name":"Nakatadoguntadotsuchou",
    "gn:name":"Kachuu",
    "iso:country":"JP",
    "wof:name":"764-0002",
    "wof:placetype":"postalcode"
},
  "geometry": {"coordinates":[133.75380000000001,34.2752],"type":"Point"}
}