{
  "type": "Feature",
  "properties": {
    "gn:adm1_name":"Hyougoken",
    "gn:adm2_name":"Koubeshitarumiku",
    "gn:name":"Takamaru",
    "iso:country":"JP",
    "wof:name":"655-0016",
    "wof:placetype":"postalcode"
},
  "geometry": {"coordinates":[135.05680000000001,34.6387],"type":"Point"}
}