{
  "type": "Feature",
  "properties": {
    "gn:adm1_name":"Wakayamaken",
    "gn:adm2_name":"Goboushi",
    "gn:name":"Fujitachoufujii",
    "iso:country":"JP",
    "wof:name":"649-1341",
    "wof:placetype":"postalcode"
},
  "geometry": {"coordinates":[135.1755,33.9079],"type":"Point"}
}