{
  "type": "Feature",
  "properties": {
    "gn:adm1_name":"Fukushimaken",
    "gn:adm2_name":"Higashishirakawagunyamatsurimachi",
    "gn:name":"Sekioka",
    "iso:country":"JP",
    "wof:name":"963-5321",
    "wof:placetype":"postalcode"
},
  "geometry": {"coordinates":[140.40950000000001,36.8656],"type":"Point"}
}