{
  "type": "Feature",
  "properties": {
    "gn:adm1_name":"Kyoutofu",
    "gn:adm2_name":"Kyoutoshikamigyouku",
    "gn:name":"Kitaisedonokamaechou",
    "iso:country":"JP",
    "wof:name":"602-8296",
    "wof:placetype":"postalcode"
},
  "geometry": {"coordinates":[135.74260000000001,35.0265],"type":"Point"}
}