{
  "type": "Feature",
  "properties": {
    "gn:adm1_name":"Ishikawaken",
    "gn:adm2_name":"Suzushi",
    "gn:name":"Wakayamamachikitayama",
    "iso:country":"JP",
    "wof:name":"927-1318",
    "wof:placetype":"postalcode"
},
  "geometry": {"coordinates":[137.1369,37.4532],"type":"Point"}
}