{
  "type": "Feature",
  "properties": {
    "gn:adm1_name":"Gunmaken",
    "gn:adm2_name":"Kanragunshimonitamachi",
    "gn:name":"Yoshizaki",
    "iso:country":"JP",
    "wof:name":"370-2604",
    "wof:placetype":"postalcode"
},
  "geometry": {"coordinates":[138.7895,36.2076],"type":"Point"}
}