{
  "type": "Feature",
  "properties": {
    "gn:adm1_name":"Shimaneken",
    "gn:adm2_name":"Kanoashigunkakinokimura",
    "gn:name":"Oonobara",
    "iso:country":"JP",
    "wof:name":"699-5306",
    "wof:placetype":"postalcode"
},
  "geometry": {"coordinates":[131.8845,34.4274],"type":"Point"}
}