{
  "type": "Feature",
  "properties": {
    "gn:adm1_name":"Hyougoken",
    "gn:adm2_name":"Mikishi",
    "gn:name":"Kuchiyokawachourengeji",
    "iso:country":"JP",
    "wof:name":"673-0734",
    "wof:placetype":"postalcode"
},
  "geometry": {"coordinates":[135.0436,34.8424],"type":"Point"}
}