{
  "type": "Feature",
  "properties": {
    "gn:adm1_name":"Hyougoken",
    "gn:adm2_name":"Aioishi",
    "gn:name":"Kugahonmachi",
    "iso:country":"JP",
    "wof:name":"678-0007",
    "wof:placetype":"postalcode"
},
  "geometry": {"coordinates":[134.47309999999999,34.8146],"type":"Point"}
}