{
  "type": "Feature",
  "properties": {
    "gn:adm1_name":"Mieken",
    "gn:adm2_name":"Hisaishi",
    "gn:name":"Ibachou",
    "iso:country":"JP",
    "wof:name":"514-1108",
    "wof:placetype":"postalcode"
},
  "geometry": {"coordinates":[136.4676,34.6807],"type":"Point"}
}