{
  "type": "Feature",
  "properties": {
    "gn:adm1_name":"Oosakafu",
    "gn:adm2_name":"Shijounawateshi",
    "gn:name":"Nakano(Choume)",
    "iso:country":"JP",
    "wof:name":"575-0052",
    "wof:placetype":"postalcode"
},
  "geometry": {"coordinates":[135.64259999999999,34.74],"type":"Point"}
}