{
  "type": "Feature",
  "properties": {
    "gn:adm1_name":"Fukuokaken",
    "gn:adm2_name":"Kogashi",
    "gn:name":"Netabi",
    "iso:country":"JP",
    "wof:name":"811-3123",
    "wof:placetype":"postalcode"
},
  "geometry": {"coordinates":[130.51730000000001,33.7275],"type":"Point"}
}