{
  "type": "Feature",
  "properties": {
    "gn:adm1_name":"Tochigiken",
    "gn:adm2_name":"Nasugunminaminasumachi",
    "gn:name":"Oogane",
    "iso:country":"JP",
    "wof:name":"321-0522",
    "wof:placetype":"postalcode"
},
  "geometry": {"coordinates":[140.0966,36.6575],"type":"Point"}
}