{
  "type": "Feature",
  "properties": {
    "gn:adm1_name":"Aichiken",
    "gn:adm2_name":"Gamagoorishi",
    "gn:name":"Kaiyouchou",
    "iso:country":"JP",
    "wof:name":"443-0014",
    "wof:placetype":"postalcode"
},
  "geometry": {"coordinates":[137.27350000000001,34.808],"type":"Point"}
}