{
  "type": "Feature",
  "properties": {
    "gn:adm1_name":"Ibarakiken",
    "gn:adm2_name":"Hitachiootashi",
    "gn:name":"Omechou",
    "iso:country":"JP",
    "wof:name":"313-0033",
    "wof:placetype":"postalcode"
},
  "geometry": {"coordinates":[140.566,36.5161],"type":"Point"}
}