{
  "type": "Feature",
  "properties": {
    "gn:adm1_name":"Aichiken",
    "gn:adm2_name":"Nagoyashinakamuraku",
    "gn:name":"Makinochou",
    "iso:country":"JP",
    "wof:name":"453-0871",
    "wof:placetype":"postalcode"
},
  "geometry": {"coordinates":[136.88319999999999,35.1649],"type":"Point"}
}