{
  "type": "Feature",
  "properties": {
    "gn:adm1_name":"Niigataken",
    "gn:adm2_name":"Nakakubikigunkakizakimachi",
    "gn:name":"Ogaya",
    "iso:country":"JP",
    "wof:name":"949-3221",
    "wof:placetype":"postalcode"
},
  "geometry": {"coordinates":[138.44730000000001,37.2866],"type":"Point"}
}