{
  "type": "Feature",
  "properties": {
    "gn:adm1_name":"Ibarakiken",
    "gn:adm2_name":"Namegataguntamatsukurimachi",
    "gn:name":"Hanyuu",
    "iso:country":"JP",
    "wof:name":"311-3507",
    "wof:placetype":"postalcode"
},
  "geometry": {"coordinates":[140.39060000000001,36.1439],"type":"Point"}
}