{
  "type": "Feature",
  "properties": {
    "gn:adm1_name":"Chibaken",
    "gn:adm2_name":"Ichiharashi",
    "gn:name":"Araoi",
    "iso:country":"JP",
    "wof:name":"290-0257",
    "wof:placetype":"postalcode"
},
  "geometry": {"coordinates":[140.10990000000001,35.4716],"type":"Point"}
}