{
  "type": "Feature",
  "properties": {
    "gn:adm1_name":"Kyoutofu",
    "gn:adm2_name":"Kyoutoshifushimiku",
    "gn:name":"Yokooojinuma",
    "iso:country":"JP",
    "wof:name":"612-8249",
    "wof:placetype":"postalcode"
},
  "geometry": {"coordinates":[135.7422,34.923],"type":"Point"}
}