{
  "type": "Feature",
  "properties": {
    "gn:adm1_name":"Shizuokaken",
    "gn:adm2_name":"Fujishi",
    "gn:name":"Tajima",
    "iso:country":"JP",
    "wof:name":"417-0031",
    "wof:placetype":"postalcode"
},
  "geometry": {"coordinates":[138.69409999999999,35.1504],"type":"Point"}
}