{
  "type": "Feature",
  "properties": {
    "gn:adm1_name":"Aichiken",
    "gn:adm2_name":"Toyohashishi",
    "gn:name":"Ekimaeoodoori",
    "iso:country":"JP",
    "wof:name":"440-0888",
    "wof:placetype":"postalcode"
},
  "geometry": {"coordinates":[137.3862,34.7628],"type":"Point"}
}