{
  "type": "Feature",
  "properties": {
    "gn:adm1_name":"Ishikawaken",
    "gn:adm2_name":"Nomigunneagarimachi",
    "gn:name":"Nishitoudamachi",
    "iso:country":"JP",
    "wof:name":"929-0102",
    "wof:placetype":"postalcode"
},
  "geometry": {"coordinates":[136.48849999999999,36.4499],"type":"Point"}
}