{
  "type": "Feature",
  "properties": {
    "gn:adm1_name":"Kyoutofu",
    "gn:adm2_name":"Kyoutoshinishikyouku",
    "gn:name":"Katsurakaminoimaichou",
    "iso:country":"JP",
    "wof:name":"615-8007",
    "wof:placetype":"postalcode"
},
  "geometry": {"coordinates":[135.69980000000001,34.9974],"type":"Point"}
}