{
  "type": "Feature",
  "properties": {
    "gn:adm1_name":"Chibaken",
    "gn:adm2_name":"Sanbugun'Ooamishirasatomachi",
    "gn:name":"Nagakuni",
    "iso:country":"JP",
    "wof:name":"299-3215",
    "wof:placetype":"postalcode"
},
  "geometry": {"coordinates":[140.37020000000001,35.4973],"type":"Point"}
}