{
  "type": "Feature",
  "properties": {
    "gn:adm1_name":"Wakayamaken",
    "gn:adm2_name":"Wakayamashi",
    "gn:name":"Minamiokeyamachi",
    "iso:country":"JP",
    "wof:name":"640-8029",
    "wof:placetype":"postalcode"
},
  "geometry": {"coordinates":[135.17529999999999,34.2352],"type":"Point"}
}