{
  "type": "Feature",
  "properties": {
    "gn:adm1_name":"Shizuokaken",
    "gn:adm2_name":"Fujinomiyashi",
    "gn:name":"Koizumi",
    "iso:country":"JP",
    "wof:name":"418-0022",
    "wof:placetype":"postalcode"
},
  "geometry": {"coordinates":[138.63589999999999,35.2197],"type":"Point"}
}