{
  "type": "Feature",
  "properties": {
    "gn:adm1_name":"Chibaken",
    "gn:adm2_name":"Kimitsushi",
    "gn:name":"Yaehara",
    "iso:country":"JP",
    "wof:name":"299-1171",
    "wof:placetype":"postalcode"
},
  "geometry": {"coordinates":[139.93459999999999,35.3266],"type":"Point"}
}