{
  "type": "Feature",
  "properties": {
    "gn:adm1_name":"Kanagawaken",
    "gn:adm2_name":"Kawasakishiasaoku",
    "gn:name":"Yurigaoka",
    "iso:country":"JP",
    "wof:name":"215-0011",
    "wof:placetype":"postalcode"
},
  "geometry": {"coordinates":[139.5164,35.6067],"type":"Point"}
}