{
  "type": "Feature",
  "properties": {
    "gn:adm1_name":"Yamagataken",
    "gn:adm2_name":"Akumigunyuzamachi",
    "gn:name":"Sugisawa",
    "iso:country":"JP",
    "wof:name":"999-8313",
    "wof:placetype":"postalcode"
},
  "geometry": {"coordinates":[139.9682,39.0113],"type":"Point"}
}