{
  "type": "Feature",
  "properties": {
    "gn:adm1_name":"Wakayamaken",
    "gn:adm2_name":"Hidakagunyurachou",
    "gn:name":"Hata",
    "iso:country":"JP",
    "wof:name":"649-1101",
    "wof:placetype":"postalcode"
},
  "geometry": {"coordinates":[135.14859999999999,33.9808],"type":"Point"}
}