{
  "type": "Feature",
  "properties": {
    "gn:adm1_name":"Gifuken",
    "gn:adm2_name":"Kaidugunkaiduchou",
    "gn:name":"Kamigiri",
    "iso:country":"JP",
    "wof:name":"503-0603",
    "wof:placetype":"postalcode"
},
  "geometry": {"coordinates":[136.6619,35.2419],"type":"Point"}
}