{
  "type": "Feature",
  "properties": {
    "gn:adm1_name":"Shizuokaken",
    "gn:adm2_name":"Iwatagunryuuyouchou",
    "gn:name":"Oka",
    "iso:country":"JP",
    "wof:name":"438-0204",
    "wof:placetype":"postalcode"
},
  "geometry": {"coordinates":[137.81729999999999,34.6755],"type":"Point"}
}