{
  "type": "Feature",
  "properties": {
    "gn:adm1_name":"Nagasakiken",
    "gn:adm2_name":"Saseboshi",
    "gn:name":"Harubunchou",
    "iso:country":"JP",
    "wof:name":"857-0103",
    "wof:placetype":"postalcode"
},
  "geometry": {"coordinates":[129.7208,33.2131],"type":"Point"}
}