{
  "type": "Feature",
  "properties": {
    "gn:adm1_name":"Niigataken",
    "gn:adm2_name":"Itoigawashi",
    "gn:name":"Kajiyama",
    "iso:country":"JP",
    "wof:name":"949-0544",
    "wof:placetype":"postalcode"
},
  "geometry": {"coordinates":[137.8921,37.0418],"type":"Point"}
}