{
  "type": "Feature",
  "properties": {
    "gn:adm1_name":"Yamaguchiken",
    "gn:adm2_name":"Shuunanshi",
    "gn:name":"Enomiyachou",
    "iso:country":"JP",
    "wof:name":"745-0826",
    "wof:placetype":"postalcode"
},
  "geometry": {"coordinates":[131.82980000000001,34.0519],"type":"Point"}
}