{
  "type": "Feature",
  "properties": {
    "gn:adm1_name":"Tokushimaken",
    "gn:adm2_name":"Tokushimashi",
    "gn:name":"Hachimanchou(Nakatsuyama)",
    "iso:country":"JP",
    "wof:name":"770-8071",
    "wof:placetype":"postalcode"
},
  "geometry": {"coordinates":[134.53540000000001,34.061],"type":"Point"}
}