{
  "type": "Feature",
  "properties": {
    "gn:adm1_name":"Fukushimaken",
    "gn:adm2_name":"Ishikawagun'Ishikawamachi",
    "gn:name":"Shiroishi",
    "iso:country":"JP",
    "wof:name":"963-7856",
    "wof:placetype":"postalcode"
},
  "geometry": {"coordinates":[140.43539999999999,37.1379],"type":"Point"}
}