{
  "type": "Feature",
  "properties": {
    "gn:adm1_name":"Ehimeken",
    "gn:adm2_name":"Matsuyamashi",
    "gn:name":"Izumikita",
    "iso:country":"JP",
    "wof:name":"790-0038",
    "wof:placetype":"postalcode"
},
  "geometry": {"coordinates":[132.75839999999999,33.8224],"type":"Point"}
}