{
  "type": "Feature",
  "properties": {
    "gn:adm1_name":"Hyougoken",
    "gn:adm2_name":"Tatsunoshi",
    "gn:name":"Hondachouuchiyama",
    "iso:country":"JP",
    "wof:name":"679-4131",
    "wof:placetype":"postalcode"
},
  "geometry": {"coordinates":[134.5745,34.856],"type":"Point"}
}