{
  "type": "Feature",
  "properties": {
    "gn:adm1_name":"Saitamaken",
    "gn:adm2_name":"Saitamashinishiku",
    "gn:name":"Uetayahon",
    "iso:country":"JP",
    "wof:name":"331-0053",
    "wof:placetype":"postalcode"
},
  "geometry": {"coordinates":[139.59549999999999,35.8901],"type":"Point"}
}