{
  "type": "Feature",
  "properties": {
    "gn:adm1_name":"Shimaneken",
    "gn:adm2_name":"Masudashi",
    "gn:name":"Kamikurodanichou",
    "iso:country":"JP",
    "wof:name":"698-2255",
    "wof:placetype":"postalcode"
},
  "geometry": {"coordinates":[131.7268,34.6037],"type":"Point"}
}