{
  "type": "Feature",
  "properties": {
    "gn:adm1_name":"Niigataken",
    "gn:adm2_name":"Murakamishi",
    "gn:name":"Saikumachi",
    "iso:country":"JP",
    "wof:name":"958-0845",
    "wof:placetype":"postalcode"
},
  "geometry": {"coordinates":[139.47659999999999,38.2223],"type":"Point"}
}