{
  "type": "Feature",
  "properties": {
    "gn:adm1_name":"Oosakafu",
    "gn:adm2_name":"Kishiwadashi",
    "gn:name":"Tenjinyamachou",
    "iso:country":"JP",
    "wof:name":"596-0834",
    "wof:placetype":"postalcode"
},
  "geometry": {"coordinates":[135.39879999999999,34.4286],"type":"Point"}
}