{
  "type": "Feature",
  "properties": {
    "gn:adm1_name":"Fukushimaken",
    "gn:adm2_name":"Nihonmatsushi",
    "gn:name":"Shimoyamada",
    "iso:country":"JP",
    "wof:name":"964-0883",
    "wof:placetype":"postalcode"
},
  "geometry": {"coordinates":[140.41370000000001,37.5757],"type":"Point"}
}