{
  "type": "Feature",
  "properties": {
    "gn:adm1_name":"Sagaken",
    "gn:adm2_name":"Karatsushi",
    "gn:name":"Sugamuta",
    "iso:country":"JP",
    "wof:name":"847-0882",
    "wof:placetype":"postalcode"
},
  "geometry": {"coordinates":[129.9384,33.4239],"type":"Point"}
}