{
  "type": "Feature",
  "properties": {
    "gn:adm1_name":"Yamaguchiken",
    "gn:adm2_name":"Shuunanshi",
    "gn:name":"Shimizuchou",
    "iso:country":"JP",
    "wof:name":"745-0834",
    "wof:placetype":"postalcode"
},
  "geometry": {"coordinates":[131.81800000000001,34.0549],"type":"Point"}
}