{
  "type": "Feature",
  "properties": {
    "gn:adm1_name":"Hiroshimaken",
    "gn:adm2_name":"Onomichishi",
    "gn:name":"Tenmachou",
    "iso:country":"JP",
    "wof:name":"722-0038",
    "wof:placetype":"postalcode"
},
  "geometry": {"coordinates":[133.1892,34.4052],"type":"Point"}
}