{
  "type": "Feature",
  "properties": {
    "gn:adm1_name":"Kyoutofu",
    "gn:adm2_name":"Kyoutoshiyamashinaku",
    "gn:name":"Misasagishimogobyounochou",
    "iso:country":"JP",
    "wof:name":"607-8426",
    "wof:placetype":"postalcode"
},
  "geometry": {"coordinates":[135.80430000000001,34.9942],"type":"Point"}
}