{
  "type": "Feature",
  "properties": {
    "gn:adm1_name":"Wakayamaken",
    "gn:adm2_name":"Wakayamashi",
    "gn:name":"Amiyamachi",
    "iso:country":"JP",
    "wof:name":"640-8238",
    "wof:placetype":"postalcode"
},
  "geometry": {"coordinates":[135.1617,34.2288],"type":"Point"}
}