{
  "type": "Feature",
  "properties": {
    "gn:adm1_name":"Okayamaken",
    "gn:adm2_name":"Okayamashi",
    "gn:name":"Mino",
    "iso:country":"JP",
    "wof:name":"700-0802",
    "wof:placetype":"postalcode"
},
  "geometry": {"coordinates":[133.93620000000001,34.6918],"type":"Point"}
}