{
  "type": "Feature",
  "properties": {
    "gn:adm1_name":"Ishikawaken",
    "gn:adm2_name":"Kanazawashi",
    "gn:name":"Saidamachi",
    "iso:country":"JP",
    "wof:name":"920-3101",
    "wof:placetype":"postalcode"
},
  "geometry": {"coordinates":[136.69139999999999,36.6383],"type":"Point"}
}