{
  "type": "Feature",
  "properties": {
    "gn:adm1_name":"Ooitaken",
    "gn:adm2_name":"Oonogun'Ogatamachi",
    "gn:name":"Tsuji",
    "iso:country":"JP",
    "wof:name":"879-6632",
    "wof:placetype":"postalcode"
},
  "geometry": {"coordinates":[131.44479999999999,32.9568],"type":"Point"}
}