{
  "type": "Feature",
  "properties": {
    "gn:adm1_name":"Naganoken",
    "gn:adm2_name":"Komaganeshi",
    "gn:name":"Shimodaira(Sonota)",
    "iso:country":"JP",
    "wof:name":"399-4101",
    "wof:placetype":"postalcode"
},
  "geometry": {"coordinates":[137.9573,35.734],"type":"Point"}
}