{
  "type": "Feature",
  "properties": {
    "gn:adm1_name":"Niigataken",
    "gn:adm2_name":"Nakakanbaragunkamedamachi",
    "gn:name":"Higashihonchou",
    "iso:country":"JP",
    "wof:name":"950-0126",
    "wof:placetype":"postalcode"
},
  "geometry": {"coordinates":[139.1097,37.8717],"type":"Point"}
}