{
  "type": "Feature",
  "properties": {
    "gn:adm1_name":"Niigataken",
    "gn:adm2_name":"Murakamishi",
    "gn:name":"Kashio",
    "iso:country":"JP",
    "wof:name":"958-0004",
    "wof:placetype":"postalcode"
},
  "geometry": {"coordinates":[139.4487,38.2949],"type":"Point"}
}