{
  "type": "Feature",
  "properties": {
    "gn:adm1_name":"Toyamaken",
    "gn:adm2_name":"Oyabeshi",
    "gn:name":"Uchiondou",
    "iso:country":"JP",
    "wof:name":"932-0106",
    "wof:placetype":"postalcode"
},
  "geometry": {"coordinates":[136.8947,36.6423],"type":"Point"}
}