{
  "type": "Feature",
  "properties": {
    "gn:adm1_name":"Kumamotoken",
    "gn:adm2_name":"Kikuchigunkikuyoumachi",
    "gn:name":"Totsugi",
    "iso:country":"JP",
    "wof:name":"869-1104",
    "wof:placetype":"postalcode"
},
  "geometry": {"coordinates":[130.8588,32.8503],"type":"Point"}
}