{
  "type": "Feature",
  "properties": {
    "gn:adm1_name":"Gifuken",
    "gn:adm2_name":"Yoshikigunkamiokachou",
    "gn:name":"Inishi",
    "iso:country":"JP",
    "wof:name":"506-1106",
    "wof:placetype":"postalcode"
},
  "geometry": {"coordinates":[137.3443,36.3769],"type":"Point"}
}