{
  "type": "Feature",
  "properties": {
    "gn:adm1_name":"Fukushimaken",
    "gn:adm2_name":"Kawanumagun'Aidubangemachi",
    "gn:name":"Tabanematsu",
    "iso:country":"JP",
    "wof:name":"969-6587",
    "wof:placetype":"postalcode"
},
  "geometry": {"coordinates":[139.7482,37.5773],"type":"Point"}
}