{
  "type": "Feature",
  "properties": {
    "gn:adm1_name":"Kumamotoken",
    "gn:adm2_name":"Kikuchishi",
    "gn:name":"Murada",
    "iso:country":"JP",
    "wof:name":"861-1317",
    "wof:placetype":"postalcode"
},
  "geometry": {"coordinates":[130.79660000000001,32.9575],"type":"Point"}
}