{
  "type": "Feature",
  "properties": {
    "gn:adm1_name":"Kyoutofu",
    "gn:adm2_name":"Kyoutoshifushimiku",
    "gn:name":"Momoyamachoutaichourou",
    "iso:country":"JP",
    "wof:name":"612-8034",
    "wof:placetype":"postalcode"
},
  "geometry": {"coordinates":[135.77090000000001,34.9298],"type":"Point"}
}