{
  "type": "Feature",
  "properties": {
    "gn:adm1_name":"Fukushimaken",
    "gn:adm2_name":"Iwakishi",
    "gn:name":"Tabitomachitabiuto(Sonota)",
    "iso:country":"JP",
    "wof:name":"974-0152",
    "wof:placetype":"postalcode"
},
  "geometry": {"coordinates":[140.6902,36.9464],"type":"Point"}
}