{
  "type": "Feature",
  "properties": {
    "gn:adm1_name":"Ibarakiken",
    "gn:adm2_name":"Sashimagunsouwamachi",
    "gn:name":"Shimoheimi",
    "iso:country":"JP",
    "wof:name":"306-0235",
    "wof:placetype":"postalcode"
},
  "geometry": {"coordinates":[139.7312,36.1775],"type":"Point"}
}