{
  "type": "Feature",
  "properties": {
    "gn:adm1_name":"Chibaken",
    "gn:adm2_name":"Nodashi",
    "gn:name":"Banshou",
    "iso:country":"JP",
    "wof:name":"278-0041",
    "wof:placetype":"postalcode"
},
  "geometry": {"coordinates":[139.8588,35.9787],"type":"Point"}
}