{
  "type": "Feature",
  "properties": {
    "gn:adm1_name":"Mieken",
    "gn:adm2_name":"Ichishigun'Ureshinochou",
    "gn:name":"Tengeeji",
    "iso:country":"JP",
    "wof:name":"515-2302",
    "wof:placetype":"postalcode"
},
  "geometry": {"coordinates":[136.46199999999999,34.6324],"type":"Point"}
}