{
  "type": "Feature",
  "properties": {
    "gn:adm1_name":"Okayamaken",
    "gn:adm2_name":"Kurashikishi",
    "gn:name":"Tamashimauwanari",
    "iso:country":"JP",
    "wof:name":"713-8101",
    "wof:placetype":"postalcode"
},
  "geometry": {"coordinates":[133.6926,34.5605],"type":"Point"}
}