{
  "type": "Feature",
  "properties": {
    "gn:adm1_name":"Hyougoken",
    "gn:adm2_name":"Koubeshihyougoku",
    "gn:name":"Isonochou",
    "iso:country":"JP",
    "wof:name":"652-0842",
    "wof:placetype":"postalcode"
},
  "geometry": {"coordinates":[135.17410000000001,34.6675],"type":"Point"}
}