{
  "type": "Feature",
  "properties": {
    "gn:adm1_name":"Saitamaken",
    "gn:adm2_name":"Misatoshi",
    "gn:name":"Sakae",
    "iso:country":"JP",
    "wof:name":"341-0043",
    "wof:placetype":"postalcode"
},
  "geometry": {"coordinates":[139.87270000000001,35.8158],"type":"Point"}
}