{
  "type": "Feature",
  "properties": {
    "gn:adm1_name":"Saitamaken",
    "gn:adm2_name":"Ageoshi",
    "gn:name":"Uenohongou",
    "iso:country":"JP",
    "wof:name":"362-0056",
    "wof:placetype":"postalcode"
},
  "geometry": {"coordinates":[139.5608,35.9355],"type":"Point"}
}