{
  "type": "Feature",
  "properties": {
    "gn:adm1_name":"Fukuiken",
    "gn:adm2_name":"Sabaeshi",
    "gn:name":"Shihoudanichou",
    "iso:country":"JP",
    "wof:name":"916-1106",
    "wof:placetype":"postalcode"
},
  "geometry": {"coordinates":[136.22210000000001,35.9763],"type":"Point"}
}