{
  "type": "Feature",
  "properties": {
    "gn:adm1_name":"Hiroshimaken",
    "gn:adm2_name":"Akigunkaitachou",
    "gn:name":"Minamihonmachi",
    "iso:country":"JP",
    "wof:name":"736-0033",
    "wof:placetype":"postalcode"
},
  "geometry": {"coordinates":[132.5385,34.3627],"type":"Point"}
}