{
  "type": "Feature",
  "properties": {
    "gn:adm1_name":"Naganoken",
    "gn:adm2_name":"Iidashi",
    "gn:name":"Kiribayashi",
    "iso:country":"JP",
    "wof:name":"399-2565",
    "wof:placetype":"postalcode"
},
  "geometry": {"coordinates":[137.82310000000001,35.4711],"type":"Point"}
}