{
  "type": "Feature",
  "properties": {
    "gn:adm1_name":"Ibarakiken",
    "gn:adm2_name":"Shimodateshi",
    "gn:name":"Goshomiya",
    "iso:country":"JP",
    "wof:name":"308-0866",
    "wof:placetype":"postalcode"
},
  "geometry": {"coordinates":[139.94120000000001,36.3346],"type":"Point"}
}