{
  "type": "Feature",
  "properties": {
    "gn:adm1_name":"Chibaken",
    "gn:adm2_name":"Ichiharashi",
    "gn:name":"Ichiba",
    "iso:country":"JP",
    "wof:name":"290-0505",
    "wof:placetype":"postalcode"
},
  "geometry": {"coordinates":[140.18289999999999,35.4051],"type":"Point"}
}