{
  "type": "Feature",
  "properties": {
    "gn:adm1_name":"Toukyouto",
    "gn:adm2_name":"Setagayaku",
    "gn:name":"Komazawakouen",
    "iso:country":"JP",
    "wof:name":"154-0013",
    "wof:placetype":"postalcode"
},
  "geometry": {"coordinates":[139.66030000000001,35.6246],"type":"Point"}
}