{
  "type": "Feature",
  "properties": {
    "gn:adm1_name":"Hyougoken",
    "gn:adm2_name":"Kakogawashi",
    "gn:name":"Noguchichounoguchi",
    "iso:country":"JP",
    "wof:name":"675-0012",
    "wof:placetype":"postalcode"
},
  "geometry": {"coordinates":[134.85650000000001,34.7535],"type":"Point"}
}