{
  "type": "Feature",
  "properties": {
    "gn:adm1_name":"Okayamaken",
    "gn:adm2_name":"Katsutagunshououchou",
    "gn:name":"Taira",
    "iso:country":"JP",
    "wof:name":"709-4334",
    "wof:placetype":"postalcode"
},
  "geometry": {"coordinates":[134.1165,35.0468],"type":"Point"}
}