{
  "type": "Feature",
  "properties": {
    "gn:adm1_name":"Fukushimaken",
    "gn:adm2_name":"Nishishirakawagunyabukimachi",
    "gn:name":"Nakamaru",
    "iso:country":"JP",
    "wof:name":"969-0231",
    "wof:placetype":"postalcode"
},
  "geometry": {"coordinates":[140.36170000000001,37.2189],"type":"Point"}
}