{
  "type": "Feature",
  "properties": {
    "gn:adm1_name":"Naganoken",
    "gn:adm2_name":"Naganoshi",
    "gn:name":"Okadamachi",
    "iso:country":"JP",
    "wof:name":"380-0936",
    "wof:placetype":"postalcode"
},
  "geometry": {"coordinates":[138.18180000000001,36.6454],"type":"Point"}
}