{
  "type": "Feature",
  "properties": {
    "gn:adm1_name":"Fukuokaken",
    "gn:adm2_name":"Maebarushi",
    "gn:name":"Kawabaru",
    "iso:country":"JP",
    "wof:name":"819-1574",
    "wof:placetype":"postalcode"
},
  "geometry": {"coordinates":[130.26929999999999,33.5155],"type":"Point"}
}