{
  "type": "Feature",
  "properties": {
    "gn:adm1_name":"Hyougoken",
    "gn:adm2_name":"Koubeshinadaku",
    "gn:name":"Izumidoori",
    "iso:country":"JP",
    "wof:name":"657-0834",
    "wof:placetype":"postalcode"
},
  "geometry": {"coordinates":[135.2252,34.7106],"type":"Point"}
}