{
  "type": "Feature",
  "properties": {
    "gn:adm1_name":"Hiroshimaken",
    "gn:adm2_name":"Kamogunkurosechou",
    "gn:name":"Kanehiro",
    "iso:country":"JP",
    "wof:name":"724-0616",
    "wof:placetype":"postalcode"
},
  "geometry": {"coordinates":[132.6601,34.3254],"type":"Point"}
}