{
  "type": "Feature",
  "properties": {
    "gn:adm1_name":"Shigaken",
    "gn:adm2_name":"Ootsushi",
    "gn:name":"Hiratsu",
    "iso:country":"JP",
    "wof:name":"520-0862",
    "wof:placetype":"postalcode"
},
  "geometry": {"coordinates":[135.9075,34.9504],"type":"Point"}
}