{
  "type": "Feature",
  "properties": {
    "gn:adm1_name":"Toyamaken",
    "gn:adm2_name":"Shimoniikawagunnyuuzenmachi",
    "gn:name":"Takase",
    "iso:country":"JP",
    "wof:name":"939-0661",
    "wof:placetype":"postalcode"
},
  "geometry": {"coordinates":[137.44929999999999,36.9299],"type":"Point"}
}