{
  "type": "Feature",
  "properties": {
    "gn:adm1_name":"Miyagiken",
    "gn:adm2_name":"Sendaishitaihakuku",
    "gn:name":"Yamadajiyuugaoka",
    "iso:country":"JP",
    "wof:name":"982-0213",
    "wof:placetype":"postalcode"
},
  "geometry": {"coordinates":[140.8116,38.2292],"type":"Point"}
}