{
  "type": "Feature",
  "properties": {
    "gn:adm1_name":"Kanagawaken",
    "gn:adm2_name":"Kawasakishinakaharaku",
    "gn:name":"Imaiminamichou",
    "iso:country":"JP",
    "wof:name":"211-0064",
    "wof:placetype":"postalcode"
},
  "geometry": {"coordinates":[139.6551,35.5722],"type":"Point"}
}