{
  "type": "Feature",
  "properties": {
    "gn:adm1_name":"Fukuiken",
    "gn:adm2_name":"Ooiguntakahamachou",
    "gn:name":"Shimokuramochi",
    "iso:country":"JP",
    "wof:name":"919-2205",
    "wof:placetype":"postalcode"
},
  "geometry": {"coordinates":[135.595,35.486],"type":"Point"}
}