{
  "type": "Feature",
  "properties": {
    "gn:adm1_name":"Ehimeken",
    "gn:adm2_name":"Imabarishi",
    "gn:name":"Kamitoku",
    "iso:country":"JP",
    "wof:name":"799-1511",
    "wof:placetype":"postalcode"
},
  "geometry": {"coordinates":[133.0146,34.0372],"type":"Point"}
}