{
  "type": "Feature",
  "properties": {
    "gn:adm1_name":"Yamaguchiken",
    "gn:adm2_name":"Kugagunshuutouchou",
    "gn:name":"Nishinagano",
    "iso:country":"JP",
    "wof:name":"742-0425",
    "wof:placetype":"postalcode"
},
  "geometry": {"coordinates":[132.01840000000001,34.0903],"type":"Point"}
}