{
  "type": "Feature",
  "properties": {
    "gn:adm1_name":"Toyamaken",
    "gn:adm2_name":"Takaokashi",
    "gn:name":"Joukouji",
    "iso:country":"JP",
    "wof:name":"933-0126",
    "wof:placetype":"postalcode"
},
  "geometry": {"coordinates":[137.03550000000001,36.7825],"type":"Point"}
}