{
  "type": "Feature",
  "properties": {
    "gn:adm1_name":"Shigaken",
    "gn:adm2_name":"Oumihachimanshi",
    "gn:name":"Tagachou",
    "iso:country":"JP",
    "wof:name":"523-0821",
    "wof:placetype":"postalcode"
},
  "geometry": {"coordinates":[136.09440000000001,35.1422],"type":"Point"}
}