{
  "type": "Feature",
  "properties": {
    "gn:adm1_name":"Ehimeken",
    "gn:adm2_name":"Matsuyamashi",
    "gn:name":"Yuramachi",
    "iso:country":"JP",
    "wof:name":"791-8092",
    "wof:placetype":"postalcode"
},
  "geometry": {"coordinates":[132.6781,33.9045],"type":"Point"}
}