{
  "type": "Feature",
  "properties": {
    "gn:adm1_name":"Ibarakiken",
    "gn:adm2_name":"Hitachinakashi",
    "gn:name":"Takeda",
    "iso:country":"JP",
    "wof:name":"312-0025",
    "wof:placetype":"postalcode"
},
  "geometry": {"coordinates":[140.5188,36.3863],"type":"Point"}
}