{
  "type": "Feature",
  "properties": {
    "gn:adm1_name":"Tottoriken",
    "gn:adm2_name":"Hinogunnichinanchou",
    "gn:name":"Hanaguchi",
    "iso:country":"JP",
    "wof:name":"689-5661",
    "wof:placetype":"postalcode"
},
  "geometry": {"coordinates":[133.3683,35.1544],"type":"Point"}
}