{
  "type": "Feature",
  "properties": {
    "gn:adm1_name":"Yamagataken",
    "gn:adm2_name":"Nishiokitamagunshiratakamachi",
    "gn:name":"Ayukai",
    "iso:country":"JP",
    "wof:name":"992-0771",
    "wof:placetype":"postalcode"
},
  "geometry": {"coordinates":[140.07470000000001,38.1892],"type":"Point"}
}