{
  "type": "Feature",
  "properties": {
    "gn:adm1_name":"Yamanashiken",
    "gn:adm2_name":"Nishiyatsushirogun'Ichikawadaimonchou",
    "gn:name":"Yamaga",
    "iso:country":"JP",
    "wof:name":"409-3602",
    "wof:placetype":"postalcode"
},
  "geometry": {"coordinates":[138.50700000000001,35.5232],"type":"Point"}
}