{
  "type": "Feature",
  "properties": {
    "gn:adm1_name":"Ishikawaken",
    "gn:adm2_name":"Fugeshigunnotomachi",
    "gn:name":"Yanami",
    "iso:country":"JP",
    "wof:name":"927-0443",
    "wof:placetype":"postalcode"
},
  "geometry": {"coordinates":[137.09559999999999,37.2795],"type":"Point"}
}