{
  "type": "Feature",
  "properties": {
    "gn:adm1_name":"Yamagataken",
    "gn:adm2_name":"Sakatashi",
    "gn:name":"Sakaikouya",
    "iso:country":"JP",
    "wof:name":"998-0806",
    "wof:placetype":"postalcode"
},
  "geometry": {"coordinates":[139.91820000000001,38.9427],"type":"Point"}
}