{
  "type": "Feature",
  "properties": {
    "gn:adm1_name":"Yamanashiken",
    "gn:adm2_name":"Kitatsurugun'Uenoharamachi",
    "gn:name":"Oozone",
    "iso:country":"JP",
    "wof:name":"409-0131",
    "wof:placetype":"postalcode"
},
  "geometry": {"coordinates":[139.09180000000001,35.6408],"type":"Point"}
}