{
  "type": "Feature",
  "properties": {
    "gn:adm1_name":"Toyamaken",
    "gn:adm2_name":"Nishitonamigunfukumitsumachi",
    "gn:name":"Nanamagari",
    "iso:country":"JP",
    "wof:name":"939-1762",
    "wof:placetype":"postalcode"
},
  "geometry": {"coordinates":[136.85759999999999,36.4988],"type":"Point"}
}