{
  "type": "Feature",
  "properties": {
    "gn:adm1_name":"Niigataken",
    "gn:adm2_name":"Kashiwazakishi",
    "gn:name":"Shinhanachou",
    "iso:country":"JP",
    "wof:name":"945-0062",
    "wof:placetype":"postalcode"
},
  "geometry": {"coordinates":[138.5615,37.3762],"type":"Point"}
}