{
  "type": "Feature",
  "properties": {
    "gn:adm1_name":"Tochigiken",
    "gn:adm2_name":"Utsunomiyashi",
    "gn:name":"Iiyamamachi",
    "iso:country":"JP",
    "wof:name":"321-2101",
    "wof:placetype":"postalcode"
},
  "geometry": {"coordinates":[139.8022,36.7027],"type":"Point"}
}