{
  "type": "Feature",
  "properties": {
    "gn:adm1_name":"Yamaguchiken",
    "gn:adm2_name":"Shimonosekishi",
    "gn:name":"Hikoshimadeshimatsuchou",
    "iso:country":"JP",
    "wof:name":"750-0076",
    "wof:placetype":"postalcode"
},
  "geometry": {"coordinates":[130.92420000000001,33.9236],"type":"Point"}
}