{
  "type": "Feature",
  "properties": {
    "gn:adm1_name":"Ibarakiken",
    "gn:adm2_name":"Yuukishi",
    "gn:name":"Egawashinjuku",
    "iso:country":"JP",
    "wof:name":"307-0042",
    "wof:placetype":"postalcode"
},
  "geometry": {"coordinates":[139.8297,36.2359],"type":"Point"}
}