{
  "type": "Feature",
  "properties": {
    "gn:adm1_name":"Niigataken",
    "gn:adm2_name":"Ryoutsushi",
    "gn:name":"Nagae",
    "iso:country":"JP",
    "wof:name":"952-0027",
    "wof:placetype":"postalcode"
},
  "geometry": {"coordinates":[138.40369999999999,38.0727],"type":"Point"}
}