{
  "type": "Feature",
  "properties": {
    "gn:adm1_name":"Ehimeken",
    "gn:adm2_name":"Matsuyamashi",
    "gn:name":"Kasugamachi",
    "iso:country":"JP",
    "wof:name":"790-0024",
    "wof:placetype":"postalcode"
},
  "geometry": {"coordinates":[132.76509999999999,33.8331],"type":"Point"}
}