{
  "type": "Feature",
  "properties": {
    "gn:adm1_name":"Kanagawaken",
    "gn:adm2_name":"Yokohamashiasahiku",
    "gn:name":"Santandachou",
    "iso:country":"JP",
    "wof:name":"241-0013",
    "wof:placetype":"postalcode"
},
  "geometry": {"coordinates":[139.55439999999999,35.4672],"type":"Point"}
}