{
  "type": "Feature",
  "properties": {
    "gn:adm1_name":"Tochigiken",
    "gn:adm2_name":"Utsunomiyashi",
    "gn:name":"Nibanchou",
    "iso:country":"JP",
    "wof:name":"320-0813",
    "wof:placetype":"postalcode"
},
  "geometry": {"coordinates":[139.88900000000001,36.5584],"type":"Point"}
}