{
  "type": "Feature",
  "properties": {
    "gn:adm1_name":"Aichiken",
    "gn:adm2_name":"Ichinomiyashi",
    "gn:name":"Nishijimachou",
    "iso:country":"JP",
    "wof:name":"491-0062",
    "wof:placetype":"postalcode"
},
  "geometry": {"coordinates":[136.80619999999999,35.3219],"type":"Point"}
}