{
  "type": "Feature",
  "properties": {
    "gn:adm1_name":"Mieken",
    "gn:adm2_name":"Nabarishi",
    "gn:name":"Kikyougaoka1banchou",
    "iso:country":"JP",
    "wof:name":"518-0621",
    "wof:placetype":"postalcode"
},
  "geometry": {"coordinates":[136.11680000000001,34.6458],"type":"Point"}
}