{
  "type": "Feature",
  "properties": {
    "gn:adm1_name":"Miyagiken",
    "gn:adm2_name":"Kesennumashi",
    "gn:name":"Asahichou",
    "iso:country":"JP",
    "wof:name":"988-0034",
    "wof:placetype":"postalcode"
},
  "geometry": {"coordinates":[141.58940000000001,38.8903],"type":"Point"}
}