{
  "type": "Feature",
  "properties": {
    "gn:adm1_name":"Oosakafu",
    "gn:adm2_name":"Yaoshi",
    "gn:name":"Oota",
    "iso:country":"JP",
    "wof:name":"581-0037",
    "wof:placetype":"postalcode"
},
  "geometry": {"coordinates":[135.59379999999999,34.5899],"type":"Point"}
}