{
  "type": "Feature",
  "properties": {
    "gn:adm1_name":"Aichiken",
    "gn:adm2_name":"Owariasahishi",
    "gn:name":"Shiromaechouchigaike",
    "iso:country":"JP",
    "wof:name":"488-0866",
    "wof:placetype":"postalcode"
},
  "geometry": {"coordinates":[137.02449999999999,35.2175],"type":"Point"}
}