{
  "type": "Feature",
  "properties": {
    "gn:adm1_name":"Toyamaken",
    "gn:adm2_name":"Tonamishi",
    "gn:name":"Takanosu",
    "iso:country":"JP",
    "wof:name":"939-1335",
    "wof:placetype":"postalcode"
},
  "geometry": {"coordinates":[136.9263,36.6284],"type":"Point"}
}