{
  "type": "Feature",
  "properties": {
    "gn:adm1_name":"Okayamaken",
    "gn:adm2_name":"Kurashikishi",
    "gn:name":"Fukudachouhigashiduka",
    "iso:country":"JP",
    "wof:name":"712-8045",
    "wof:placetype":"postalcode"
},
  "geometry": {"coordinates":[133.76130000000001,34.5341],"type":"Point"}
}