{
  "type": "Feature",
  "properties": {
    "gn:adm1_name":"Kanagawaken",
    "gn:adm2_name":"Yokohamashinakaku",
    "gn:name":"Honmokumotomachi",
    "iso:country":"JP",
    "wof:name":"231-0822",
    "wof:placetype":"postalcode"
},
  "geometry": {"coordinates":[139.6679,35.4194],"type":"Point"}
}