{
  "type": "Feature",
  "properties": {
    "gn:adm1_name":"Fukuiken",
    "gn:adm2_name":"Fukuishi",
    "gn:name":"Hikimechou",
    "iso:country":"JP",
    "wof:name":"918-8156",
    "wof:placetype":"postalcode"
},
  "geometry": {"coordinates":[136.20060000000001,36.0246],"type":"Point"}
}