{
  "type": "Feature",
  "properties": {
    "gn:adm1_name":"Shizuokaken",
    "gn:adm2_name":"Kakegawashi",
    "gn:name":"Shimotaruki",
    "iso:country":"JP",
    "wof:name":"436-0222",
    "wof:placetype":"postalcode"
},
  "geometry": {"coordinates":[137.98519999999999,34.7857],"type":"Point"}
}