{
  "type": "Feature",
  "properties": {
    "gn:adm1_name":"Miyagiken",
    "gn:adm2_name":"Motoyoshigunmotoyoshichou",
    "gn:name":"Tsunogara",
    "iso:country":"JP",
    "wof:name":"988-0374",
    "wof:placetype":"postalcode"
},
  "geometry": {"coordinates":[141.44239999999999,38.7951],"type":"Point"}
}