{
  "type": "Feature",
  "properties": {
    "gn:adm1_name":"Gifuken",
    "gn:adm2_name":"Kanigunmitakechou",
    "gn:name":"Hie",
    "iso:country":"JP",
    "wof:name":"505-0124",
    "wof:placetype":"postalcode"
},
  "geometry": {"coordinates":[137.10310000000001,35.4432],"type":"Point"}
}