{
  "type": "Feature",
  "properties": {
    "gn:adm1_name":"Naganoken",
    "gn:adm2_name":"Inashi",
    "gn:name":"Tomigata",
    "iso:country":"JP",
    "wof:name":"396-0621",
    "wof:placetype":"postalcode"
},
  "geometry": {"coordinates":[138.0018,35.8081],"type":"Point"}
}