{
  "type": "Feature",
  "properties": {
    "gn:adm1_name":"Chibaken",
    "gn:adm2_name":"Kaijougun'Iiokamachi",
    "gn:name":"Kaminagai",
    "iso:country":"JP",
    "wof:name":"289-2704",
    "wof:placetype":"postalcode"
},
  "geometry": {"coordinates":[140.7449,35.698],"type":"Point"}
}