{
  "type": "Feature",
  "properties": {
    "gn:adm1_name":"Yamaguchiken",
    "gn:adm2_name":"Onodashi",
    "gn:name":"Kakinokizaka",
    "iso:country":"JP",
    "wof:name":"756-0067",
    "wof:placetype":"postalcode"
},
  "geometry": {"coordinates":[131.17939999999999,34.0163],"type":"Point"}
}