{
  "type": "Feature",
  "properties": {
    "gn:adm1_name":"Chibaken",
    "gn:adm2_name":"Kimitsushi",
    "gn:name":"Manobori",
    "iso:country":"JP",
    "wof:name":"299-1115",
    "wof:placetype":"postalcode"
},
  "geometry": {"coordinates":[139.941,35.2779],"type":"Point"}
}