{
  "type": "Feature",
  "properties": {
    "gn:adm1_name":"Mieken",
    "gn:adm2_name":"Minamimurogunmihamachou",
    "gn:name":"Sakamoto",
    "iso:country":"JP",
    "wof:name":"519-5321",
    "wof:placetype":"postalcode"
},
  "geometry": {"coordinates":[135.99629999999999,33.8611],"type":"Point"}
}