{
  "type": "Feature",
  "properties": {
    "gn:adm1_name":"Fukuokaken",
    "gn:adm2_name":"Ongagunmizumakimachi",
    "gn:name":"Tateyashiki",
    "iso:country":"JP",
    "wof:name":"807-0051",
    "wof:placetype":"postalcode"
},
  "geometry": {"coordinates":[130.68819999999999,33.8494],"type":"Point"}
}