{
  "type": "Feature",
  "properties": {
    "gn:adm1_name":"Oosakafu",
    "gn:adm2_name":"Kadomashi",
    "gn:name":"Okimachi",
    "iso:country":"JP",
    "wof:name":"571-0022",
    "wof:placetype":"postalcode"
},
  "geometry": {"coordinates":[135.60169999999999,34.7308],"type":"Point"}
}