{
  "type": "Feature",
  "properties": {
    "gn:adm1_name":"Ishikawaken",
    "gn:adm2_name":"Kanazawashi",
    "gn:name":"Ikedamachi3banchou",
    "iso:country":"JP",
    "wof:name":"920-0985",
    "wof:placetype":"postalcode"
},
  "geometry": {"coordinates":[136.65389999999999,36.5581],"type":"Point"}
}