{
  "type": "Feature",
  "properties": {
    "gn:adm1_name":"Hyougoken",
    "gn:adm2_name":"Himejishi",
    "gn:name":"Aoyamanishi",
    "iso:country":"JP",
    "wof:name":"671-2224",
    "wof:placetype":"postalcode"
},
  "geometry": {"coordinates":[134.6301,34.8435],"type":"Point"}
}