{
  "type": "Feature",
  "properties": {
    "gn:adm1_name":"Hyougoken",
    "gn:adm2_name":"Koubeshisumaku",
    "gn:name":"Yasakadai",
    "iso:country":"JP",
    "wof:name":"654-0161",
    "wof:placetype":"postalcode"
},
  "geometry": {"coordinates":[135.0737,34.6872],"type":"Point"}
}