{
  "type": "Feature",
  "properties": {
    "gn:adm1_name":"Aichiken",
    "gn:adm2_name":"Nagoyashikitaku",
    "gn:name":"Hatookachou",
    "iso:country":"JP",
    "wof:name":"462-0025",
    "wof:placetype":"postalcode"
},
  "geometry": {"coordinates":[136.91309999999999,35.2057],"type":"Point"}
}