{
  "type": "Feature",
  "properties": {
    "gn:adm1_name":"Wakayamaken",
    "gn:adm2_name":"Hidakagunkawabechou",
    "gn:name":"Miyose",
    "iso:country":"JP",
    "wof:name":"649-1312",
    "wof:placetype":"postalcode"
},
  "geometry": {"coordinates":[135.2458,33.94],"type":"Point"}
}