{
  "type": "Feature",
  "properties": {
    "gn:adm1_name":"Oosakafu",
    "gn:adm2_name":"Neyagawashi",
    "gn:name":"Shimokamidachou",
    "iso:country":"JP",
    "wof:name":"572-0054",
    "wof:placetype":"postalcode"
},
  "geometry": {"coordinates":[135.60910000000001,34.7486],"type":"Point"}
}