{
  "type": "Feature",
  "properties": {
    "gn:adm1_name":"Kouchiken",
    "gn:adm2_name":"Nankokushi",
    "gn:name":"Sanbaku",
    "iso:country":"JP",
    "wof:name":"783-0027",
    "wof:placetype":"postalcode"
},
  "geometry": {"coordinates":[133.65790000000001,33.6016],"type":"Point"}
}