{
  "type": "Feature",
  "properties": {
    "gn:adm1_name":"Toukyouto",
    "gn:adm2_name":"Hachioujishi",
    "gn:name":"Miyamachou",
    "iso:country":"JP",
    "wof:name":"192-0152",
    "wof:placetype":"postalcode"
},
  "geometry": {"coordinates":[139.24940000000001,35.6892],"type":"Point"}
}