{
  "type": "Feature",
  "properties": {
    "gn:adm1_name":"Hyougoken",
    "gn:adm2_name":"Sasayamashi",
    "gn:name":"Obara",
    "iso:country":"JP",
    "wof:name":"669-2604",
    "wof:placetype":"postalcode"
},
  "geometry": {"coordinates":[135.3348,35.125],"type":"Point"}
}