{
  "type": "Feature",
  "properties": {
    "gn:adm1_name":"Fukuokaken",
    "gn:adm2_name":"Kitakyuushuushimojiku",
    "gn:name":"Betsuin",
    "iso:country":"JP",
    "wof:name":"800-0035",
    "wof:placetype":"postalcode"
},
  "geometry": {"coordinates":[130.93340000000001,33.8944],"type":"Point"}
}