{
  "type": "Feature",
  "properties": {
    "gn:adm1_name":"Chibaken",
    "gn:adm2_name":"Kamogawashi",
    "gn:name":"Minamikomachi",
    "iso:country":"JP",
    "wof:name":"296-0104",
    "wof:placetype":"postalcode"
},
  "geometry": {"coordinates":[140.03370000000001,35.1263],"type":"Point"}
}