{
  "type": "Feature",
  "properties": {
    "gn:adm1_name":"Chibaken",
    "gn:adm2_name":"Mobarashi",
    "gn:name":"Minamiyoshida",
    "iso:country":"JP",
    "wof:name":"299-4104",
    "wof:placetype":"postalcode"
},
  "geometry": {"coordinates":[140.34,35.4676],"type":"Point"}
}