{
  "type": "Feature",
  "properties": {
    "gn:adm1_name":"Chibaken",
    "gn:adm2_name":"Sanbugun'Ooamishirasatomachi",
    "gn:name":"Hotokeshima",
    "iso:country":"JP",
    "wof:name":"299-3237",
    "wof:placetype":"postalcode"
},
  "geometry": {"coordinates":[140.3246,35.5197],"type":"Point"}
}