{
  "type": "Feature",
  "properties": {
    "gn:adm1_name":"Saitamaken",
    "gn:adm2_name":"Higashimatsuyamashi",
    "gn:name":"Komatsubarachou",
    "iso:country":"JP",
    "wof:name":"355-0013",
    "wof:placetype":"postalcode"
},
  "geometry": {"coordinates":[139.40880000000001,36.0443],"type":"Point"}
}