{
  "type": "Feature",
  "properties": {
    "gn:adm1_name":"Ibarakiken",
    "gn:adm2_name":"Tsukubashi",
    "gn:name":"Kamiyokoba",
    "iso:country":"JP",
    "wof:name":"305-0854",
    "wof:placetype":"postalcode"
},
  "geometry": {"coordinates":[140.08930000000001,36.0431],"type":"Point"}
}