{
  "type": "Feature",
  "properties": {
    "gn:adm1_name":"Toyamaken",
    "gn:adm2_name":"Toyamashi",
    "gn:name":"Nonoue",
    "iso:country":"JP",
    "wof:name":"930-0171",
    "wof:placetype":"postalcode"
},
  "geometry": {"coordinates":[137.142,36.7219],"type":"Point"}
}