{
  "type": "Feature",
  "properties": {
    "gn:adm1_name":"Yamagataken",
    "gn:adm2_name":"Mogamigunfunagatamachi",
    "gn:name":"Horiuchi",
    "iso:country":"JP",
    "wof:name":"999-4604",
    "wof:placetype":"postalcode"
},
  "geometry": {"coordinates":[140.279,38.6563],"type":"Point"}
}