{
  "type": "Feature",
  "properties": {
    "gn:adm1_name":"Toyamaken",
    "gn:adm2_name":"Higashitonamigunfukunomachi",
    "gn:name":"Jikearayashiki",
    "iso:country":"JP",
    "wof:name":"939-1577",
    "wof:placetype":"postalcode"
},
  "geometry": {"coordinates":[136.916,36.5934],"type":"Point"}
}