{
  "type": "Feature",
  "properties": {
    "gn:adm1_name":"Ishikawaken",
    "gn:adm2_name":"Fugeshigunmonzenmachi",
    "gn:name":"Takinoue",
    "iso:country":"JP",
    "wof:name":"927-2111",
    "wof:placetype":"postalcode"
},
  "geometry": {"coordinates":[136.8244,37.306],"type":"Point"}
}