{
  "type": "Feature",
  "properties": {
    "gn:adm1_name":"Okayamaken",
    "gn:adm2_name":"Maniwagun'Ochiaichou",
    "gn:name":"Dando",
    "iso:country":"JP",
    "wof:name":"719-3133",
    "wof:placetype":"postalcode"
},
  "geometry": {"coordinates":[133.78659999999999,34.9799],"type":"Point"}
}