{
  "type": "Feature",
  "properties": {
    "gn:adm1_name":"Toyamaken",
    "gn:adm2_name":"Kaminiikawagun'Ooyamamachi",
    "gn:name":"Hanakiribu",
    "iso:country":"JP",
    "wof:name":"930-1452",
    "wof:placetype":"postalcode"
},
  "geometry": {"coordinates":[137.42949999999999,36.5771],"type":"Point"}
}