{
  "type": "Feature",
  "properties": {
    "gn:adm1_name":"Miyagiken",
    "gn:adm2_name":"Kamigunkamimachi",
    "gn:name":"Fumotoyama",
    "iso:country":"JP",
    "wof:name":"981-4354",
    "wof:placetype":"postalcode"
},
  "geometry": {"coordinates":[140.76750000000001,38.5696],"type":"Point"}
}