{
  "type": "Feature",
  "properties": {
    "gn:adm1_name":"Kumamotoken",
    "gn:adm2_name":"Tamanagunkikusuimachi",
    "gn:name":"Fujita",
    "iso:country":"JP",
    "wof:name":"865-0125",
    "wof:placetype":"postalcode"
},
  "geometry": {"coordinates":[130.60290000000001,32.9882],"type":"Point"}
}