{
  "type": "Feature",
  "properties": {
    "gn:adm1_name":"Yamanashiken",
    "gn:adm2_name":"Higashiyatsushirogun'Ichinomiyachou",
    "gn:name":"Kamiyahagi",
    "iso:country":"JP",
    "wof:name":"405-0059",
    "wof:placetype":"postalcode"
},
  "geometry": {"coordinates":[138.7021,35.6609],"type":"Point"}
}