{
  "type": "Feature",
  "properties": {
    "gn:adm1_name":"Sagaken",
    "gn:adm2_name":"Higashimatsuuragunkyuuragimachi",
    "gn:name":"Motoyama",
    "iso:country":"JP",
    "wof:name":"849-3133",
    "wof:placetype":"postalcode"
},
  "geometry": {"coordinates":[130.03630000000001,33.3302],"type":"Point"}
}