{
  "type": "Feature",
  "properties": {
    "gn:adm1_name":"Fukuiken",
    "gn:adm2_name":"Fukuishi",
    "gn:name":"Gebachou",
    "iso:country":"JP",
    "wof:name":"918-8113",
    "wof:placetype":"postalcode"
},
  "geometry": {"coordinates":[136.24160000000001,36.0379],"type":"Point"}
}