{
  "type": "Feature",
  "properties": {
    "gn:adm1_name":"Kanagawaken",
    "gn:adm2_name":"Yokohamashikanagawaku",
    "gn:name":"Katakura",
    "iso:country":"JP",
    "wof:name":"221-0865",
    "wof:placetype":"postalcode"
},
  "geometry": {"coordinates":[139.6052,35.489],"type":"Point"}
}