{
  "type": "Feature",
  "properties": {
    "gn:adm1_name":"Fukuiken",
    "gn:adm2_name":"Obamashi",
    "gn:name":"Obamaasuka",
    "iso:country":"JP",
    "wof:name":"917-0057",
    "wof:placetype":"postalcode"
},
  "geometry": {"coordinates":[135.73310000000001,35.4907],"type":"Point"}
}