{
  "type": "Feature",
  "properties": {
    "gn:adm1_name":"Okayamaken",
    "gn:adm2_name":"Tsuyamashi",
    "gn:name":"Momiho",
    "iso:country":"JP",
    "wof:name":"708-0803",
    "wof:placetype":"postalcode"
},
  "geometry": {"coordinates":[134.0247,35.0966],"type":"Point"}
}