{
  "type": "Feature",
  "properties": {
    "gn:adm1_name":"Fukuokaken",
    "gn:adm2_name":"Itoshimagunshimamachi",
    "gn:name":"Higashikaiduka",
    "iso:country":"JP",
    "wof:name":"819-1324",
    "wof:placetype":"postalcode"
},
  "geometry": {"coordinates":[130.14869999999999,33.5775],"type":"Point"}
}