{
  "type": "Feature",
  "properties": {
    "gn:adm1_name":"Oosakafu",
    "gn:adm2_name":"Oosakashisumiyoshiku",
    "gn:name":"Bandaihigashi",
    "iso:country":"JP",
    "wof:name":"558-0056",
    "wof:placetype":"postalcode"
},
  "geometry": {"coordinates":[135.50530000000001,34.6177],"type":"Point"}
}