{
  "type": "Feature",
  "properties": {
    "gn:adm1_name":"Gunmaken",
    "gn:adm2_name":"Maebashishi",
    "gn:name":"Nankitsumachi",
    "iso:country":"JP",
    "wof:name":"371-0043",
    "wof:placetype":"postalcode"
},
  "geometry": {"coordinates":[139.0626,36.4265],"type":"Point"}
}