{
  "type": "Feature",
  "properties": {
    "gn:adm1_name":"Ishikawaken",
    "gn:adm2_name":"Nanaoshi",
    "gn:name":"Mimuromachi",
    "iso:country":"JP",
    "wof:name":"926-0007",
    "wof:placetype":"postalcode"
},
  "geometry": {"coordinates":[137.0196,37.0945],"type":"Point"}
}