{
  "type": "Feature",
  "properties": {
    "gn:adm1_name":"Toukyouto",
    "gn:adm2_name":"Setagayaku",
    "gn:name":"Okusawa",
    "iso:country":"JP",
    "wof:name":"158-0083",
    "wof:placetype":"postalcode"
},
  "geometry": {"coordinates":[139.6695,35.6041],"type":"Point"}
}