{
  "type": "Feature",
  "properties": {
    "gn:adm1_name":"Niigataken",
    "gn:adm2_name":"Santougunteradomarimachi",
    "gn:name":"Kitazone",
    "iso:country":"JP",
    "wof:name":"959-0165",
    "wof:placetype":"postalcode"
},
  "geometry": {"coordinates":[138.82669999999999,37.6192],"type":"Point"}
}