{
  "type": "Feature",
  "properties": {
    "gn:adm1_name":"Chibaken",
    "gn:adm2_name":"Mobarashi",
    "gn:name":"Oonobori",
    "iso:country":"JP",
    "wof:name":"297-0072",
    "wof:placetype":"postalcode"
},
  "geometry": {"coordinates":[140.27969999999999,35.466],"type":"Point"}
}