{
  "type": "Feature",
  "properties": {
    "gn:adm1_name":"Chibaken",
    "gn:adm2_name":"Funabashishi",
    "gn:name":"Futagochou",
    "iso:country":"JP",
    "wof:name":"273-0034",
    "wof:placetype":"postalcode"
},
  "geometry": {"coordinates":[139.9478,35.7104],"type":"Point"}
}