{
  "type": "Feature",
  "properties": {
    "gn:adm1_name":"Kagoshimaken",
    "gn:adm2_name":"Kasedashi",
    "gn:name":"Kominato",
    "iso:country":"JP",
    "wof:name":"897-1122",
    "wof:placetype":"postalcode"
},
  "geometry": {"coordinates":[130.26599999999999,31.4116],"type":"Point"}
}