{
  "type": "Feature",
  "properties": {
    "gn:adm1_name":"Ehimeken",
    "gn:adm2_name":"Iyogunnakayamachou",
    "gn:name":"Saretani",
    "iso:country":"JP",
    "wof:name":"791-3201",
    "wof:placetype":"postalcode"
},
  "geometry": {"coordinates":[132.72210000000001,33.6837],"type":"Point"}
}