{
  "type": "Feature",
  "properties": {
    "gn:adm1_name":"Chibaken",
    "gn:adm2_name":"Sakurashi",
    "gn:name":"Iiduka",
    "iso:country":"JP",
    "wof:name":"285-0076",
    "wof:placetype":"postalcode"
},
  "geometry": {"coordinates":[140.23759999999999,35.6448],"type":"Point"}
}