{
  "type": "Feature",
  "properties": {
    "gn:adm1_name":"Shizuokaken",
    "gn:adm2_name":"Hamamatsushi",
    "gn:name":"Takaokanishi",
    "iso:country":"JP",
    "wof:name":"433-8118",
    "wof:placetype":"postalcode"
},
  "geometry": {"coordinates":[137.69829999999999,34.7589],"type":"Point"}
}