{
  "type": "Feature",
  "properties": {
    "gn:adm1_name":"Ooitaken",
    "gn:adm2_name":"Ooitashi",
    "gn:name":"Hirosemachi",
    "iso:country":"JP",
    "wof:name":"870-0847",
    "wof:placetype":"postalcode"
},
  "geometry": {"coordinates":[131.613,33.2192],"type":"Point"}
}