{
  "type": "Feature",
  "properties": {
    "gn:adm1_name":"Miyazakiken",
    "gn:adm2_name":"Nobeokashi",
    "gn:name":"Oroshihonmachi",
    "iso:country":"JP",
    "wof:name":"882-0855",
    "wof:placetype":"postalcode"
},
  "geometry": {"coordinates":[131.68520000000001,32.5772],"type":"Point"}
}