{
  "type": "Feature",
  "properties": {
    "gn:adm1_name":"Ibarakiken",
    "gn:adm2_name":"Tsuchiurashi",
    "gn:name":"Mushikake",
    "iso:country":"JP",
    "wof:name":"300-0066",
    "wof:placetype":"postalcode"
},
  "geometry": {"coordinates":[140.1782,36.0932],"type":"Point"}
}