{
  "type": "Feature",
  "properties": {
    "gn:adm1_name":"Wakayamaken",
    "gn:adm2_name":"Shinguushi",
    "gn:name":"Ikeda",
    "iso:country":"JP",
    "wof:name":"647-0021",
    "wof:placetype":"postalcode"
},
  "geometry": {"coordinates":[135.99529999999999,33.728],"type":"Point"}
}