{
  "type": "Feature",
  "properties": {
    "gn:adm1_name":"Ibarakiken",
    "gn:adm2_name":"Kashimagunkamisumachi",
    "gn:name":"Shibasaki",
    "iso:country":"JP",
    "wof:name":"314-0123",
    "wof:placetype":"postalcode"
},
  "geometry": {"coordinates":[140.6583,35.8675],"type":"Point"}
}