{
  "type": "Feature",
  "properties": {
    "gn:adm1_name":"Hyougoken",
    "gn:adm2_name":"Mikishi",
    "gn:name":"Kuchiyokawachouminamibata",
    "iso:country":"JP",
    "wof:name":"673-0756",
    "wof:placetype":"postalcode"
},
  "geometry": {"coordinates":[135.06569999999999,34.8548],"type":"Point"}
}