{
  "type": "Feature",
  "properties": {
    "gn:adm1_name":"Kyoutofu",
    "gn:adm2_name":"Kyoutoshisakyouku",
    "gn:name":"Tanakashimoyanagichou",
    "iso:country":"JP",
    "wof:name":"606-8204",
    "wof:placetype":"postalcode"
},
  "geometry": {"coordinates":[135.77369999999999,35.0289],"type":"Point"}
}