{
  "type": "Feature",
  "properties": {
    "gn:adm1_name":"Niigataken",
    "gn:adm2_name":"Kashiwazakishi",
    "gn:name":"Koganechou",
    "iso:country":"JP",
    "wof:name":"945-0024",
    "wof:placetype":"postalcode"
},
  "geometry": {"coordinates":[138.58369999999999,37.3859],"type":"Point"}
}