{
  "type": "Feature",
  "properties": {
    "gn:adm1_name":"Kagoshimaken",
    "gn:adm2_name":"Kasedashi",
    "gn:name":"Fumotochou",
    "iso:country":"JP",
    "wof:name":"897-0005",
    "wof:placetype":"postalcode"
},
  "geometry": {"coordinates":[130.3212,31.4137],"type":"Point"}
}