{
  "type": "Feature",
  "properties": {
    "gn:adm1_name":"Tottoriken",
    "gn:adm2_name":"Touhakuguntouhakuchou",
    "gn:name":"Miyoshi",
    "iso:country":"JP",
    "wof:name":"689-2354",
    "wof:placetype":"postalcode"
},
  "geometry": {"coordinates":[133.69280000000001,35.4767],"type":"Point"}
}