{
  "type": "Feature",
  "properties": {
    "gn:adm1_name":"Saitamaken",
    "gn:adm2_name":"Kitakatsushikagunsugitomachi",
    "gn:name":"Kuramatsu",
    "iso:country":"JP",
    "wof:name":"345-0034",
    "wof:placetype":"postalcode"
},
  "geometry": {"coordinates":[139.73869999999999,36.0316],"type":"Point"}
}