{
  "type": "Feature",
  "properties": {
    "gn:adm1_name":"Kumamotoken",
    "gn:adm2_name":"Shimomashikigunchuuoumachi",
    "gn:name":"Nakashouji",
    "iso:country":"JP",
    "wof:name":"861-4407",
    "wof:placetype":"postalcode"
},
  "geometry": {"coordinates":[130.7841,32.6393],"type":"Point"}
}