{
  "type": "Feature",
  "properties": {
    "gn:adm1_name":"Ibarakiken",
    "gn:adm2_name":"Tsuchiurashi",
    "gn:name":"Ottominami",
    "iso:country":"JP",
    "wof:name":"300-0845",
    "wof:placetype":"postalcode"
},
  "geometry": {"coordinates":[140.14840000000001,36.0307],"type":"Point"}
}