{
  "type": "Feature",
  "properties": {
    "gn:adm1_name":"Kyoutofu",
    "gn:adm2_name":"Kyoutoshiukyouku",
    "gn:name":"Saiinsanzouchou",
    "iso:country":"JP",
    "wof:name":"615-0021",
    "wof:placetype":"postalcode"
},
  "geometry": {"coordinates":[135.7321,35.002],"type":"Point"}
}