{
  "type": "Feature",
  "properties": {
    "gn:adm1_name":"Ishikawaken",
    "gn:adm2_name":"Komatsushi",
    "gn:name":"Nishiharamachi",
    "iso:country":"JP",
    "wof:name":"923-0325",
    "wof:placetype":"postalcode"
},
  "geometry": {"coordinates":[136.4502,36.3303],"type":"Point"}
}