{
  "type": "Feature",
  "properties": {
    "gn:adm1_name":"Aichiken",
    "gn:adm2_name":"Inuyamashi",
    "gn:name":"Nitanda",
    "iso:country":"JP",
    "wof:name":"484-0918",
    "wof:placetype":"postalcode"
},
  "geometry": {"coordinates":[136.96109999999999,35.3797],"type":"Point"}
}