{
  "type": "Feature",
  "properties": {
    "gn:adm1_name":"Kyoutofu",
    "gn:adm2_name":"Fukuchiyamashi",
    "gn:name":"Ichinotani",
    "iso:country":"JP",
    "wof:name":"620-0848",
    "wof:placetype":"postalcode"
},
  "geometry": {"coordinates":[135.16650000000001,35.2785],"type":"Point"}
}