{
  "type": "Feature",
  "properties": {
    "gn:adm1_name":"Niigataken",
    "gn:adm2_name":"Sadogunhamochimachi",
    "gn:name":"Hamochihongou",
    "iso:country":"JP",
    "wof:name":"952-0504",
    "wof:placetype":"postalcode"
},
  "geometry": {"coordinates":[138.3176,37.8492],"type":"Point"}
}