{
  "type": "Feature",
  "properties": {
    "gn:adm1_name":"Fukuokaken",
    "gn:adm2_name":"Oomutashi",
    "gn:name":"Kitaisomachi",
    "iso:country":"JP",
    "wof:name":"836-0016",
    "wof:placetype":"postalcode"
},
  "geometry": {"coordinates":[130.44139999999999,33.0418],"type":"Point"}
}