{
  "type": "Feature",
  "properties": {
    "gn:adm1_name":"Shizuokaken",
    "gn:adm2_name":"Fujishi",
    "gn:name":"Mitsuzawa",
    "iso:country":"JP",
    "wof:name":"417-0855",
    "wof:placetype":"postalcode"
},
  "geometry": {"coordinates":[138.7079,35.1832],"type":"Point"}
}