{
  "type": "Feature",
  "properties": {
    "gn:adm1_name":"Fukuiken",
    "gn:adm2_name":"Fukuishi",
    "gn:name":"Wakaechou",
    "iso:country":"JP",
    "wof:name":"910-0831",
    "wof:placetype":"postalcode"
},
  "geometry": {"coordinates":[136.26249999999999,36.0849],"type":"Point"}
}