{
  "type": "Feature",
  "properties": {
    "gn:adm1_name":"Gifuken",
    "gn:adm2_name":"Yoshikigunfurukawachou",
    "gn:name":"Oonochou",
    "iso:country":"JP",
    "wof:name":"509-4255",
    "wof:placetype":"postalcode"
},
  "geometry": {"coordinates":[137.20349999999999,36.2171],"type":"Point"}
}