{
  "type": "Feature",
  "properties": {
    "gn:adm1_name":"Aichiken",
    "gn:adm2_name":"Nukatagunkoutachou",
    "gn:name":"Ookusa",
    "iso:country":"JP",
    "wof:name":"444-0103",
    "wof:placetype":"postalcode"
},
  "geometry": {"coordinates":[137.1781,34.8768],"type":"Point"}
}