{
  "type": "Feature",
  "properties": {
    "gn:adm1_name":"Niigataken",
    "gn:adm2_name":"Niigatashi",
    "gn:name":"Kanbaramachi",
    "iso:country":"JP",
    "wof:name":"950-0083",
    "wof:placetype":"postalcode"
},
  "geometry": {"coordinates":[139.06729999999999,37.9189],"type":"Point"}
}