{
  "type": "Feature",
  "properties": {
    "gn:adm1_name":"Kumamotoken",
    "gn:adm2_name":"Kamimashikigunseiwason",
    "gn:name":"Konakadake",
    "iso:country":"JP",
    "wof:name":"861-3803",
    "wof:placetype":"postalcode"
},
  "geometry": {"coordinates":[131.05359999999999,32.6677],"type":"Point"}
}