{
  "type": "Feature",
  "properties": {
    "gn:adm1_name":"Kouchiken",
    "gn:adm2_name":"Akiguntouyouchou",
    "gn:name":"Shirahama",
    "iso:country":"JP",
    "wof:name":"781-7413",
    "wof:placetype":"postalcode"
},
  "geometry": {"coordinates":[134.2927,33.5445],"type":"Point"}
}