{
  "type": "Feature",
  "properties": {
    "gn:adm1_name":"Okayamaken",
    "gn:adm2_name":"Takahashishi",
    "gn:name":"Tamagawachoutama",
    "iso:country":"JP",
    "wof:name":"716-0052",
    "wof:placetype":"postalcode"
},
  "geometry": {"coordinates":[133.59970000000001,34.7582],"type":"Point"}
}