{
  "type": "Feature",
  "properties": {
    "gn:adm1_name":"Shizuokaken",
    "gn:adm2_name":"Haibaragunnakakawanechou",
    "gn:name":"Tokuyama",
    "iso:country":"JP",
    "wof:name":"428-0301",
    "wof:placetype":"postalcode"
},
  "geometry": {"coordinates":[138.1165,35.0674],"type":"Point"}
}