{
  "type": "Feature",
  "properties": {
    "gn:adm1_name":"Fukushimaken",
    "gn:adm2_name":"Shirakawashi",
    "gn:name":"Tamachi",
    "iso:country":"JP",
    "wof:name":"961-0073",
    "wof:placetype":"postalcode"
},
  "geometry": {"coordinates":[140.22120000000001,37.1306],"type":"Point"}
}