{
  "type": "Feature",
  "properties": {
    "gn:adm1_name":"Niigataken",
    "gn:adm2_name":"Niitsushi",
    "gn:name":"Kitakamishinden",
    "iso:country":"JP",
    "wof:name":"956-0021",
    "wof:placetype":"postalcode"
},
  "geometry": {"coordinates":[139.11429999999999,37.8139],"type":"Point"}
}