{
  "type": "Feature",
  "properties": {
    "gn:adm1_name":"Aichiken",
    "gn:adm2_name":"Nishikamogunmiyoshichou",
    "gn:name":"Nishijintoriyama",
    "iso:country":"JP",
    "wof:name":"470-0221",
    "wof:placetype":"postalcode"
},
  "geometry": {"coordinates":[137.07759999999999,35.0881],"type":"Point"}
}