{
  "type": "Feature",
  "properties": {
    "gn:adm1_name":"Tottoriken",
    "gn:adm2_name":"Yazugunkawaharachou",
    "gn:name":"Ogouchi",
    "iso:country":"JP",
    "wof:name":"680-1253",
    "wof:placetype":"postalcode"
},
  "geometry": {"coordinates":[134.14189999999999,35.3697],"type":"Point"}
}