{
  "type": "Feature",
  "properties": {
    "gn:adm1_name":"Oosakafu",
    "gn:adm2_name":"Takatsukishi",
    "gn:name":"Wakamatsuchou",
    "iso:country":"JP",
    "wof:name":"569-0054",
    "wof:placetype":"postalcode"
},
  "geometry": {"coordinates":[135.62870000000001,34.8349],"type":"Point"}
}