{
  "type": "Feature",
  "properties": {
    "gn:adm1_name":"Oosakafu",
    "gn:adm2_name":"Daitoushi",
    "gn:name":"Nakakusunosatochou",
    "iso:country":"JP",
    "wof:name":"574-0006",
    "wof:placetype":"postalcode"
},
  "geometry": {"coordinates":[135.6352,34.729],"type":"Point"}
}