{
  "type": "Feature",
  "properties": {
    "gn:adm1_name":"Wakayamaken",
    "gn:adm2_name":"Higashimurogunkumanogawachou",
    "gn:name":"Nokiyamamoto",
    "iso:country":"JP",
    "wof:name":"647-1213",
    "wof:placetype":"postalcode"
},
  "geometry": {"coordinates":[135.87780000000001,33.7831],"type":"Point"}
}