{
  "type": "Feature",
  "properties": {
    "gn:adm1_name":"Miyagiken",
    "gn:adm2_name":"Monougun'Ogatsuchou",
    "gn:name":"Oohama",
    "iso:country":"JP",
    "wof:name":"986-1302",
    "wof:placetype":"postalcode"
},
  "geometry": {"coordinates":[141.5119,38.5137],"type":"Point"}
}