{
  "type": "Feature",
  "properties": {
    "gn:adm1_name":"Chibaken",
    "gn:adm2_name":"Katsuurashi",
    "gn:name":"Hanazato",
    "iso:country":"JP",
    "wof:name":"299-5203",
    "wof:placetype":"postalcode"
},
  "geometry": {"coordinates":[140.30940000000001,35.2119],"type":"Point"}
}