{
  "type": "Feature",
  "properties": {
    "gn:adm1_name":"Yamagataken",
    "gn:adm2_name":"Nanyoushi",
    "gn:name":"Nakanome",
    "iso:country":"JP",
    "wof:name":"999-2242",
    "wof:placetype":"postalcode"
},
  "geometry": {"coordinates":[140.1523,38.0341],"type":"Point"}
}