{
  "type": "Feature",
  "properties": {
    "gn:adm1_name":"Mieken",
    "gn:adm2_name":"Miegunkawagoechou",
    "gn:name":"Toushinden",
    "iso:country":"JP",
    "wof:name":"510-8111",
    "wof:placetype":"postalcode"
},
  "geometry": {"coordinates":[136.68199999999999,35.0326],"type":"Point"}
}