{
  "type": "Feature",
  "properties": {
    "gn:adm1_name":"Kagoshimaken",
    "gn:adm2_name":"Kushikinoshi",
    "gn:name":"Asahimachi",
    "iso:country":"JP",
    "wof:name":"896-0015",
    "wof:placetype":"postalcode"
},
  "geometry": {"coordinates":[130.2688,31.7178],"type":"Point"}
}