{
  "type": "Feature",
  "properties": {
    "gn:adm1_name":"Hiroshimaken",
    "gn:adm2_name":"Miharashi",
    "gn:name":"Nutahigashichounouso",
    "iso:country":"JP",
    "wof:name":"723-0146",
    "wof:placetype":"postalcode"
},
  "geometry": {"coordinates":[133.0076,34.3994],"type":"Point"}
}