{
  "type": "Feature",
  "properties": {
    "gn:adm1_name":"Niigataken",
    "gn:adm2_name":"Niigatashi",
    "gn:name":"Akatsuka",
    "iso:country":"JP",
    "wof:name":"950-2261",
    "wof:placetype":"postalcode"
},
  "geometry": {"coordinates":[138.8845,37.8172],"type":"Point"}
}