{
  "type": "Feature",
  "properties": {
    "gn:adm1_name":"Kyoutofu",
    "gn:adm2_name":"Kyoutoshikitaku",
    "gn:name":"Hiranohacchouyanagichou",
    "iso:country":"JP",
    "wof:name":"603-8345",
    "wof:placetype":"postalcode"
},
  "geometry": {"coordinates":[135.7303,35.0311],"type":"Point"}
}