{
  "type": "Feature",
  "properties": {
    "gn:adm1_name":"Aichiken",
    "gn:adm2_name":"Nagoyashiatsutaku",
    "gn:name":"Nakadachou",
    "iso:country":"JP",
    "wof:name":"456-0014",
    "wof:placetype":"postalcode"
},
  "geometry": {"coordinates":[136.9074,35.1354],"type":"Point"}
}