{
  "type": "Feature",
  "properties": {
    "gn:adm1_name":"Hyougoken",
    "gn:adm2_name":"Koubeshinagataku",
    "gn:name":"Oohashichou",
    "iso:country":"JP",
    "wof:name":"653-0037",
    "wof:placetype":"postalcode"
},
  "geometry": {"coordinates":[135.14519999999999,34.655],"type":"Point"}
}