{
  "type": "Feature",
  "properties": {
    "gn:adm1_name":"Tottoriken",
    "gn:adm2_name":"Yazugunwakasachou",
    "gn:name":"Takano",
    "iso:country":"JP",
    "wof:name":"680-0712",
    "wof:placetype":"postalcode"
},
  "geometry": {"coordinates":[134.38,35.3548],"type":"Point"}
}