{
  "type": "Feature",
  "properties": {
    "gn:adm1_name":"Okinawaken",
    "gn:adm2_name":"Okinawashi",
    "gn:name":"Yamauchi",
    "iso:country":"JP",
    "wof:name":"904-0034",
    "wof:placetype":"postalcode"
},
  "geometry": {"coordinates":[127.7848,26.326],"type":"Point"}
}