{
  "type": "Feature",
  "properties": {
    "gn:adm1_name":"Kanagawaken",
    "gn:adm2_name":"Yokosukashi",
    "gn:name":"Oppamachou",
    "iso:country":"JP",
    "wof:name":"237-0064",
    "wof:placetype":"postalcode"
},
  "geometry": {"coordinates":[139.62569999999999,35.3133],"type":"Point"}
}