{
  "type": "Feature",
  "properties": {
    "gn:adm1_name":"Aichiken",
    "gn:adm2_name":"Nagoyashichikusaku",
    "gn:name":"Maruyamachou",
    "iso:country":"JP",
    "wof:name":"464-0843",
    "wof:placetype":"postalcode"
},
  "geometry": {"coordinates":[136.94659999999999,35.1625],"type":"Point"}
}