{
  "type": "Feature",
  "properties": {
    "gn:adm1_name":"Kumamotoken",
    "gn:adm2_name":"Minamatashi",
    "gn:name":"Marushimachou",
    "iso:country":"JP",
    "wof:name":"867-0058",
    "wof:placetype":"postalcode"
},
  "geometry": {"coordinates":[130.38980000000001,32.2128],"type":"Point"}
}