{
  "type": "Feature",
  "properties": {
    "gn:adm1_name":"Aichiken",
    "gn:adm2_name":"Nagoyashiminamiku",
    "gn:name":"Hakuunchou",
    "iso:country":"JP",
    "wof:name":"457-0025",
    "wof:placetype":"postalcode"
},
  "geometry": {"coordinates":[136.93960000000001,35.0967],"type":"Point"}
}