{
  "type": "Feature",
  "properties": {
    "gn:adm1_name":"Shizuokaken",
    "gn:adm2_name":"Shizuokashi",
    "gn:name":"Shimizuokitsuazumachou",
    "iso:country":"JP",
    "wof:name":"424-0203",
    "wof:placetype":"postalcode"
},
  "geometry": {"coordinates":[138.53309999999999,35.0625],"type":"Point"}
}