{
  "type": "Feature",
  "properties": {
    "gn:adm1_name":"Oosakafu",
    "gn:adm2_name":"Suitashi",
    "gn:name":"Yamadanishi",
    "iso:country":"JP",
    "wof:name":"565-0824",
    "wof:placetype":"postalcode"
},
  "geometry": {"coordinates":[135.52269999999999,34.7976],"type":"Point"}
}