{
  "type": "Feature",
  "properties": {
    "gn:adm1_name":"Ehimeken",
    "gn:adm2_name":"Niihamashi",
    "gn:name":"Oujichou",
    "iso:country":"JP",
    "wof:name":"792-0008",
    "wof:placetype":"postalcode"
},
  "geometry": {"coordinates":[133.26220000000001,33.9528],"type":"Point"}
}