{
  "type": "Feature",
  "properties": {
    "gn:adm1_name":"Hyougoken",
    "gn:adm2_name":"Koubeshinishiku",
    "gn:name":"Karibadai",
    "iso:country":"JP",
    "wof:name":"651-2272",
    "wof:placetype":"postalcode"
},
  "geometry": {"coordinates":[135.0318,34.7226],"type":"Point"}
}