{
  "type": "Feature",
  "properties": {
    "gn:adm1_name":"Miyagiken",
    "gn:adm2_name":"Kuriharaguntakashimizumachi",
    "gn:name":"Motomachi",
    "iso:country":"JP",
    "wof:name":"987-2187",
    "wof:placetype":"postalcode"
},
  "geometry": {"coordinates":[141.01070000000001,38.6543],"type":"Point"}
}