{
  "type": "Feature",
  "properties": {
    "gn:adm1_name":"Gifuken",
    "gn:adm2_name":"Oonogunnyuukawamura",
    "gn:name":"Boukata",
    "iso:country":"JP",
    "wof:name":"506-2121",
    "wof:placetype":"postalcode"
},
  "geometry": {"coordinates":[137.31829999999999,36.1701],"type":"Point"}
}