{
  "type": "Feature",
  "properties": {
    "gn:adm1_name":"Shigaken",
    "gn:adm2_name":"Oumihachimanshi",
    "gn:name":"Tsudachou",
    "iso:country":"JP",
    "wof:name":"523-0086",
    "wof:placetype":"postalcode"
},
  "geometry": {"coordinates":[136.0694,35.1523],"type":"Point"}
}