{
  "type": "Feature",
  "properties": {
    "gn:adm1_name":"Aichiken",
    "gn:adm2_name":"Ichinomiyashi",
    "gn:name":"Kitagatachoukitagata",
    "iso:country":"JP",
    "wof:name":"493-8001",
    "wof:placetype":"postalcode"
},
  "geometry": {"coordinates":[136.78030000000001,35.3611],"type":"Point"}
}