{
  "type": "Feature",
  "properties": {
    "gn:adm1_name":"Aichiken",
    "gn:adm2_name":"Nagoyashiminatoku",
    "gn:name":"Saiwaichou",
    "iso:country":"JP",
    "wof:name":"455-0041",
    "wof:placetype":"postalcode"
},
  "geometry": {"coordinates":[136.8733,35.0989],"type":"Point"}
}