{
  "type": "Feature",
  "properties": {
    "gn:adm1_name":"Shizuokaken",
    "gn:adm2_name":"Hamamatsushi",
    "gn:name":"Sekishichou",
    "iso:country":"JP",
    "wof:name":"431-3114",
    "wof:placetype":"postalcode"
},
  "geometry": {"coordinates":[137.76580000000001,34.7685],"type":"Point"}
}