{
  "type": "Feature",
  "properties": {
    "gn:adm1_name":"Naraken",
    "gn:adm2_name":"Tenrishi",
    "gn:name":"Takenouchichou",
    "iso:country":"JP",
    "wof:name":"632-0041",
    "wof:placetype":"postalcode"
},
  "geometry": {"coordinates":[135.8502,34.5784],"type":"Point"}
}