{
  "type": "Feature",
  "properties": {
    "gn:adm1_name":"Fukuokaken",
    "gn:adm2_name":"Fukuokashinishiku",
    "gn:name":"Yoshitake",
    "iso:country":"JP",
    "wof:name":"819-0036",
    "wof:placetype":"postalcode"
},
  "geometry": {"coordinates":[130.31270000000001,33.535],"type":"Point"}
}