{
  "type": "Feature",
  "properties": {
    "gn:adm1_name":"Niigataken",
    "gn:adm2_name":"Jouetsushi",
    "gn:name":"Takamori",
    "iso:country":"JP",
    "wof:name":"943-0182",
    "wof:placetype":"postalcode"
},
  "geometry": {"coordinates":[138.29419999999999,37.138],"type":"Point"}
}