{
  "type": "Feature",
  "properties": {
    "gn:adm1_name":"Chibaken",
    "gn:adm2_name":"Isumigun'Ootakimachi",
    "gn:name":"Harauchi",
    "iso:country":"JP",
    "wof:name":"298-0237",
    "wof:placetype":"postalcode"
},
  "geometry": {"coordinates":[140.22829999999999,35.2499],"type":"Point"}
}