{
  "type": "Feature",
  "properties": {
    "gn:adm1_name":"Aichiken",
    "gn:adm2_name":"Inuyamashi",
    "gn:name":"Kitadaimon",
    "iso:country":"JP",
    "wof:name":"484-0823",
    "wof:placetype":"postalcode"
},
  "geometry": {"coordinates":[136.96209999999999,35.3323],"type":"Point"}
}