{
  "type": "Feature",
  "properties": {
    "gn:adm1_name":"Oosakafu",
    "gn:adm2_name":"Oosakashihigashinariku",
    "gn:name":"Ooimazatominami",
    "iso:country":"JP",
    "wof:name":"537-0013",
    "wof:placetype":"postalcode"
},
  "geometry": {"coordinates":[135.5498,34.6665],"type":"Point"}
}