{
  "type": "Feature",
  "properties": {
    "gn:adm1_name":"Toukyouto",
    "gn:adm2_name":"Kodairashi",
    "gn:name":"Ogawachou",
    "iso:country":"JP",
    "wof:name":"187-0032",
    "wof:placetype":"postalcode"
},
  "geometry": {"coordinates":[139.45689999999999,35.7294],"type":"Point"}
}