{
  "type": "Feature",
  "properties": {
    "gn:adm1_name":"Yamaguchiken",
    "gn:adm2_name":"Ootsugunyuyachou",
    "gn:name":"Ushirobata",
    "iso:country":"JP",
    "wof:name":"759-4711",
    "wof:placetype":"postalcode"
},
  "geometry": {"coordinates":[131.0438,34.4083],"type":"Point"}
}