{
  "type": "Feature",
  "properties": {
    "gn:adm1_name":"Mieken",
    "gn:adm2_name":"Ayamagun'Ayamachou",
    "gn:name":"Higashiyamataun",
    "iso:country":"JP",
    "wof:name":"518-1307",
    "wof:placetype":"postalcode"
},
  "geometry": {"coordinates":[136.15889999999999,34.7571],"type":"Point"}
}