{
  "type": "Feature",
  "properties": {
    "gn:adm1_name":"Saitamaken",
    "gn:adm2_name":"Iwatsukishi",
    "gn:name":"Kagiage",
    "iso:country":"JP",
    "wof:name":"339-0024",
    "wof:placetype":"postalcode"
},
  "geometry": {"coordinates":[139.74080000000001,35.8995],"type":"Point"}
}