{
  "type": "Feature",
  "properties": {
    "gn:adm1_name":"Toukyouto",
    "gn:adm2_name":"Shinjukuku",
    "gn:name":"Nishishinjukushinjukusenta^Biru(Chikai.Kaisoufumei)",
    "iso:country":"JP",
    "wof:name":"163-0690",
    "wof:placetype":"postalcode"
},
  "geometry": {"coordinates":[139.69319999999999,35.6914],"type":"Point"}
}