{
  "type": "Feature",
  "properties": {
    "gn:adm1_name":"Ehimeken",
    "gn:adm2_name":"Imabarishi",
    "gn:name":"Tokiwachou",
    "iso:country":"JP",
    "wof:name":"794-0015",
    "wof:placetype":"postalcode"
},
  "geometry": {"coordinates":[132.99590000000001,34.0623],"type":"Point"}
}