{
  "type": "Feature",
  "properties": {
    "gn:adm1_name":"Chibaken",
    "gn:adm2_name":"Isumigun'Isumimachi",
    "gn:name":"Rakumachi",
    "iso:country":"JP",
    "wof:name":"298-0122",
    "wof:placetype":"postalcode"
},
  "geometry": {"coordinates":[140.2235,35.8526],"type":"Point"}
}