{
  "type": "Feature",
  "properties": {
    "gn:adm1_name":"Shimaneken",
    "gn:adm2_name":"Ooharagundaitouchou",
    "gn:name":"Kamikuno",
    "iso:country":"JP",
    "wof:name":"699-1211",
    "wof:placetype":"postalcode"
},
  "geometry": {"coordinates":[133.04580000000001,35.2687],"type":"Point"}
}