{
  "type": "Feature",
  "properties": {
    "gn:adm1_name":"Naganoken",
    "gn:adm2_name":"Uedashi",
    "gn:name":"Nakano",
    "iso:country":"JP",
    "wof:name":"386-1325",
    "wof:placetype":"postalcode"
},
  "geometry": {"coordinates":[138.19399999999999,36.3627],"type":"Point"}
}