{
  "type": "Feature",
  "properties": {
    "gn:adm1_name":"Fukuokaken",
    "gn:adm2_name":"Miyakogunsaigawamachi",
    "gn:name":"Ookuma",
    "iso:country":"JP",
    "wof:name":"824-0212",
    "wof:placetype":"postalcode"
},
  "geometry": {"coordinates":[130.93279999999999,33.6378],"type":"Point"}
}