{
  "type": "Feature",
  "properties": {
    "gn:adm1_name":"Yamaguchiken",
    "gn:adm2_name":"Shimonosekishi",
    "gn:name":"Choufukanayachou",
    "iso:country":"JP",
    "wof:name":"752-0959",
    "wof:placetype":"postalcode"
},
  "geometry": {"coordinates":[130.99000000000001,34.002],"type":"Point"}
}