{
  "type": "Feature",
  "properties": {
    "gn:adm1_name":"Hiroshimaken",
    "gn:adm2_name":"Kureshi",
    "gn:name":"Yoshiuratankochou",
    "iso:country":"JP",
    "wof:name":"737-0843",
    "wof:placetype":"postalcode"
},
  "geometry": {"coordinates":[132.5316,34.2555],"type":"Point"}
}