{
  "type": "Feature",
  "properties": {
    "gn:adm1_name":"Niigataken",
    "gn:adm2_name":"Sadogun'Ogimachi",
    "gn:name":"Kobie",
    "iso:country":"JP",
    "wof:name":"952-0602",
    "wof:placetype":"postalcode"
},
  "geometry": {"coordinates":[138.28370000000001,37.839],"type":"Point"}
}