{
  "type": "Feature",
  "properties": {
    "gn:adm1_name":"Toyamaken",
    "gn:adm2_name":"Toyamashi",
    "gn:name":"Nakafugo",
    "iso:country":"JP",
    "wof:name":"930-0832",
    "wof:placetype":"postalcode"
},
  "geometry": {"coordinates":[137.24610000000001,36.7102],"type":"Point"}
}