{
  "type": "Feature",
  "properties": {
    "gn:adm1_name":"Niigataken",
    "gn:adm2_name":"Nagaokashi",
    "gn:name":"Miyabara",
    "iso:country":"JP",
    "wof:name":"940-0083",
    "wof:placetype":"postalcode"
},
  "geometry": {"coordinates":[138.84399999999999,37.4364],"type":"Point"}
}