{
  "type": "Feature",
  "properties": {
    "gn:adm1_name":"Ishikawaken",
    "gn:adm2_name":"Kanazawashi",
    "gn:name":"Hogo",
    "iso:country":"JP",
    "wof:name":"921-8052",
    "wof:placetype":"postalcode"
},
  "geometry": {"coordinates":[136.61850000000001,36.5569],"type":"Point"}
}