{
  "type": "Feature",
  "properties": {
    "gn:adm1_name":"Mieken",
    "gn:adm2_name":"Inabeshi",
    "gn:name":"Fujiwarachoushinodachi",
    "iso:country":"JP",
    "wof:name":"511-0522",
    "wof:placetype":"postalcode"
},
  "geometry": {"coordinates":[136.45509999999999,35.2119],"type":"Point"}
}