{
  "type": "Feature",
  "properties": {
    "gn:adm1_name":"Hyougoken",
    "gn:adm2_name":"Yabugunyoukachou",
    "gn:name":"Ooe",
    "iso:country":"JP",
    "wof:name":"667-0015",
    "wof:placetype":"postalcode"
},
  "geometry": {"coordinates":[134.8143,35.4182],"type":"Point"}
}