{
  "type": "Feature",
  "properties": {
    "gn:adm1_name":"Fukuokaken",
    "gn:adm2_name":"Yukuhashishi",
    "gn:name":"Higashitokunaga",
    "iso:country":"JP",
    "wof:name":"824-0025",
    "wof:placetype":"postalcode"
},
  "geometry": {"coordinates":[131.00739999999999,33.6855],"type":"Point"}
}