{
  "type": "Feature",
  "properties": {
    "gn:adm1_name":"Kyoutofu",
    "gn:adm2_name":"Kusegunkumiyamachou",
    "gn:name":"Shimotsuya",
    "iso:country":"JP",
    "wof:name":"613-0035",
    "wof:placetype":"postalcode"
},
  "geometry": {"coordinates":[135.73920000000001,34.8778],"type":"Point"}
}