{
  "type": "Feature",
  "properties": {
    "gn:adm1_name":"Wakayamaken",
    "gn:adm2_name":"Nagagun'Uchitachou",
    "gn:name":"Jinryou",
    "iso:country":"JP",
    "wof:name":"649-6442",
    "wof:placetype":"postalcode"
},
  "geometry": {"coordinates":[135.3646,34.2866],"type":"Point"}
}