{
  "type": "Feature",
  "properties": {
    "gn:adm1_name":"Yamagataken",
    "gn:adm2_name":"Yamagatashi",
    "gn:name":"Kitada",
    "iso:country":"JP",
    "wof:name":"990-0896",
    "wof:placetype":"postalcode"
},
  "geometry": {"coordinates":[140.30439999999999,38.3078],"type":"Point"}
}