{
  "type": "Feature",
  "properties": {
    "gn:adm1_name":"Gunmaken",
    "gn:adm2_name":"Takasakishi",
    "gn:name":"Yanakamachi",
    "iso:country":"JP",
    "wof:name":"370-1203",
    "wof:placetype":"postalcode"
},
  "geometry": {"coordinates":[139.05009999999999,36.3095],"type":"Point"}
}