{
  "type": "Feature",
  "properties": {
    "gn:adm1_name":"Gifuken",
    "gn:adm2_name":"Tajimishi",
    "gn:name":"Tsuduharachou",
    "iso:country":"JP",
    "wof:name":"507-0046",
    "wof:placetype":"postalcode"
},
  "geometry": {"coordinates":[137.07550000000001,35.3213],"type":"Point"}
}