{
  "type": "Feature",
  "properties": {
    "gn:adm1_name":"Kumamotoken",
    "gn:adm2_name":"Kikuchishi",
    "gn:name":"Akahoshi",
    "iso:country":"JP",
    "wof:name":"861-1311",
    "wof:placetype":"postalcode"
},
  "geometry": {"coordinates":[130.81020000000001,32.9638],"type":"Point"}
}