{
  "type": "Feature",
  "properties": {
    "gn:adm1_name":"Saitamaken",
    "gn:adm2_name":"Kawagoeshi",
    "gn:name":"Sugama",
    "iso:country":"JP",
    "wof:name":"350-0832",
    "wof:placetype":"postalcode"
},
  "geometry": {"coordinates":[139.49600000000001,35.951],"type":"Point"}
}