{
  "type": "Feature",
  "properties": {
    "gn:adm1_name":"Aichiken",
    "gn:adm2_name":"Setoshi",
    "gn:name":"Ochiaichou",
    "iso:country":"JP",
    "wof:name":"480-1205",
    "wof:placetype":"postalcode"
},
  "geometry": {"coordinates":[137.1242,35.2521],"type":"Point"}
}