{
  "type": "Feature",
  "properties": {
    "gn:adm1_name":"Fukuokaken",
    "gn:adm2_name":"Kitakyuushuushimojiku",
    "gn:name":"Oimatsuchou",
    "iso:country":"JP",
    "wof:name":"801-0864",
    "wof:placetype":"postalcode"
},
  "geometry": {"coordinates":[130.9691,33.9463],"type":"Point"}
}