{
  "type": "Feature",
  "properties": {
    "gn:adm1_name":"Miyazakiken",
    "gn:adm2_name":"Koyugunnishimerason",
    "gn:name":"Koshinoo",
    "iso:country":"JP",
    "wof:name":"881-1301",
    "wof:placetype":"postalcode"
},
  "geometry": {"coordinates":[131.24600000000001,32.1973],"type":"Point"}
}