{
  "type": "Feature",
  "properties": {
    "gn:adm1_name":"Hyougoken",
    "gn:adm2_name":"Koubeshichuuouku",
    "gn:name":"Nakajimadoori",
    "iso:country":"JP",
    "wof:name":"651-0052",
    "wof:placetype":"postalcode"
},
  "geometry": {"coordinates":[135.20820000000001,34.7128],"type":"Point"}
}