{
  "type": "Feature",
  "properties": {
    "gn:adm1_name":"Oosakafu",
    "gn:adm2_name":"Kawachinaganoshi",
    "gn:name":"Kusunokichouhigashi",
    "iso:country":"JP",
    "wof:name":"586-0003",
    "wof:placetype":"postalcode"
},
  "geometry": {"coordinates":[135.56379999999999,34.4698],"type":"Point"}
}