{
  "type": "Feature",
  "properties": {
    "gn:adm1_name":"Fukuiken",
    "gn:adm2_name":"Tsurugashi",
    "gn:name":"Itsuhata",
    "iso:country":"JP",
    "wof:name":"914-0267",
    "wof:placetype":"postalcode"
},
  "geometry": {"coordinates":[136.08940000000001,35.7072],"type":"Point"}
}