{
  "type": "Feature",
  "properties": {
    "gn:adm1_name":"Fukushimaken",
    "gn:adm2_name":"Dategundatemachi",
    "gn:name":"Ubagafutokoro",
    "iso:country":"JP",
    "wof:name":"960-0424",
    "wof:placetype":"postalcode"
},
  "geometry": {"coordinates":[140.46039999999999,37.4164],"type":"Point"}
}