{
  "type": "Feature",
  "properties": {
    "gn:adm1_name":"Kagoshimaken",
    "gn:adm2_name":"Izumishi",
    "gn:name":"Fukunoechou",
    "iso:country":"JP",
    "wof:name":"899-0133",
    "wof:placetype":"postalcode"
},
  "geometry": {"coordinates":[130.3186,32.1014],"type":"Point"}
}