{
  "type": "Feature",
  "properties": {
    "gn:adm1_name":"Naraken",
    "gn:adm2_name":"Kashibashi",
    "gn:name":"Shimoda",
    "iso:country":"JP",
    "wof:name":"639-0233",
    "wof:placetype":"postalcode"
},
  "geometry": {"coordinates":[135.7002,34.5465],"type":"Point"}
}