{
  "type": "Feature",
  "properties": {
    "gn:adm1_name":"Oosakafu",
    "gn:adm2_name":"Higashioosakashi",
    "gn:name":"Shinjouhigashi",
    "iso:country":"JP",
    "wof:name":"578-0951",
    "wof:placetype":"postalcode"
},
  "geometry": {"coordinates":[135.608,34.6876],"type":"Point"}
}