{
  "type": "Feature",
  "properties": {
    "gn:adm1_name":"Okayamaken",
    "gn:adm2_name":"Tsuyamashi",
    "gn:name":"Horisaka",
    "iso:country":"JP",
    "wof:name":"708-1103",
    "wof:placetype":"postalcode"
},
  "geometry": {"coordinates":[134.07419999999999,35.1239],"type":"Point"}
}