{
  "type": "Feature",
  "properties": {
    "gn:adm1_name":"Chibaken",
    "gn:adm2_name":"Naritashi",
    "gn:name":"Tsuchimuro",
    "iso:country":"JP",
    "wof:name":"286-0815",
    "wof:placetype":"postalcode"
},
  "geometry": {"coordinates":[140.3639,35.8353],"type":"Point"}
}