{
  "type": "Feature",
  "properties": {
    "gn:adm1_name":"Tottoriken",
    "gn:adm2_name":"Touhakugunhoujouchou",
    "gn:name":"Yumihara",
    "iso:country":"JP",
    "wof:name":"689-2104",
    "wof:placetype":"postalcode"
},
  "geometry": {"coordinates":[133.8124,35.4906],"type":"Point"}
}