{
  "type": "Feature",
  "properties": {
    "gn:adm1_name":"Nagasakiken",
    "gn:adm2_name":"Nagasakishi",
    "gn:name":"Yagamimachi",
    "iso:country":"JP",
    "wof:name":"851-0133",
    "wof:placetype":"postalcode"
},
  "geometry": {"coordinates":[129.95140000000001,32.7763],"type":"Point"}
}