{
  "type": "Feature",
  "properties": {
    "gn:adm1_name":"Gunmaken",
    "gn:adm2_name":"Kiryuushi",
    "gn:name":"Azumachou",
    "iso:country":"JP",
    "wof:name":"376-0032",
    "wof:placetype":"postalcode"
},
  "geometry": {"coordinates":[139.34180000000001,36.4131],"type":"Point"}
}