{
  "type": "Feature",
  "properties": {
    "gn:adm1_name":"Chibaken",
    "gn:adm2_name":"Naritashi",
    "gn:name":"Tsuchiya",
    "iso:country":"JP",
    "wof:name":"286-0021",
    "wof:placetype":"postalcode"
},
  "geometry": {"coordinates":[140.31700000000001,35.7911],"type":"Point"}
}