{
  "type": "Feature",
  "properties": {
    "gn:adm1_name":"Niigataken",
    "gn:adm2_name":"Kitakanbaragunnakajoumachi",
    "gn:name":"Miyaze",
    "iso:country":"JP",
    "wof:name":"959-2704",
    "wof:placetype":"postalcode"
},
  "geometry": {"coordinates":[139.38749999999999,38.0748],"type":"Point"}
}