{
  "type": "Feature",
  "properties": {
    "gn:adm1_name":"Ibarakiken",
    "gn:adm2_name":"Kujigundaigomachi",
    "gn:name":"Yada",
    "iso:country":"JP",
    "wof:name":"319-3552",
    "wof:placetype":"postalcode"
},
  "geometry": {"coordinates":[140.35740000000001,36.7889],"type":"Point"}
}