{
  "type": "Feature",
  "properties": {
    "gn:adm1_name":"Naraken",
    "gn:adm2_name":"Yoshinogun'Ootoumura",
    "gn:name":"Nakabara",
    "iso:country":"JP",
    "wof:name":"637-0415",
    "wof:placetype":"postalcode"
},
  "geometry": {"coordinates":[135.71430000000001,34.1886],"type":"Point"}
}