{
  "type": "Feature",
  "properties": {
    "gn:adm1_name":"Chibaken",
    "gn:adm2_name":"Kashiwashi",
    "gn:name":"Minamikashiwa",
    "iso:country":"JP",
    "wof:name":"277-0855",
    "wof:placetype":"postalcode"
},
  "geometry": {"coordinates":[139.95400000000001,35.846],"type":"Point"}
}