{
  "type": "Feature",
  "properties": {
    "gn:adm1_name":"Gunmaken",
    "gn:adm2_name":"Maebashishi",
    "gn:name":"Sumiyoshichou",
    "iso:country":"JP",
    "wof:name":"371-0021",
    "wof:placetype":"postalcode"
},
  "geometry": {"coordinates":[139.06950000000001,36.3969],"type":"Point"}
}