{
  "type": "Feature",
  "properties": {
    "gn:adm1_name":"Okinawaken",
    "gn:adm2_name":"Shimajirigunsashikichou",
    "gn:name":"Tedokon",
    "iso:country":"JP",
    "wof:name":"901-1402",
    "wof:placetype":"postalcode"
},
  "geometry": {"coordinates":[127.8004,26.1701],"type":"Point"}
}