{
  "type": "Feature",
  "properties": {
    "gn:adm1_name":"Tottoriken",
    "gn:adm2_name":"Yonagoshi",
    "gn:name":"Chamachi",
    "iso:country":"JP",
    "wof:name":"683-0041",
    "wof:placetype":"postalcode"
},
  "geometry": {"coordinates":[133.33250000000001,35.4251],"type":"Point"}
}