{
  "type": "Feature",
  "properties": {
    "gn:adm1_name":"Oosakafu",
    "gn:adm2_name":"Izumiootsushi",
    "gn:name":"Kawaharachou",
    "iso:country":"JP",
    "wof:name":"595-0044",
    "wof:placetype":"postalcode"
},
  "geometry": {"coordinates":[135.3929,34.5008],"type":"Point"}
}