{
  "type": "Feature",
  "properties": {
    "gn:adm1_name":"Toukyouto",
    "gn:adm2_name":"Itabashiku",
    "gn:name":"Kumanochou",
    "iso:country":"JP",
    "wof:name":"173-0025",
    "wof:placetype":"postalcode"
},
  "geometry": {"coordinates":[139.7063,35.7435],"type":"Point"}
}