{
  "type": "Feature",
  "properties": {
    "gn:adm1_name":"Yamagataken",
    "gn:adm2_name":"Yamagatashi",
    "gn:name":"Domeki",
    "iso:country":"JP",
    "wof:name":"990-2361",
    "wof:placetype":"postalcode"
},
  "geometry": {"coordinates":[140.27969999999999,38.2267],"type":"Point"}
}