{
  "type": "Feature",
  "properties": {
    "gn:adm1_name":"Nagasakiken",
    "gn:adm2_name":"Minamimatsuuraguntomiechou",
    "gn:name":"Tsuchitorigou",
    "iso:country":"JP",
    "wof:name":"853-0214",
    "wof:placetype":"postalcode"
},
  "geometry": {"coordinates":[128.7791,32.6085],"type":"Point"}
}