{
  "type": "Feature",
  "properties": {
    "gn:adm1_name":"Kyoutofu",
    "gn:adm2_name":"Yosagun'Inechou",
    "gn:name":"Touge",
    "iso:country":"JP",
    "wof:name":"626-0417",
    "wof:placetype":"postalcode"
},
  "geometry": {"coordinates":[135.2723,35.7107],"type":"Point"}
}