{
  "type": "Feature",
  "properties": {
    "gn:adm1_name":"Okayamaken",
    "gn:adm2_name":"Kurashikishi",
    "gn:name":"Yabe",
    "iso:country":"JP",
    "wof:name":"701-0105",
    "wof:placetype":"postalcode"
},
  "geometry": {"coordinates":[133.81979999999999,34.6654],"type":"Point"}
}