{
  "type": "Feature",
  "properties": {
    "gn:adm1_name":"Hyougoken",
    "gn:adm2_name":"Izushigun'Izushichou",
    "gn:name":"Torii",
    "iso:country":"JP",
    "wof:name":"668-0272",
    "wof:placetype":"postalcode"
},
  "geometry": {"coordinates":[134.85640000000001,35.4817],"type":"Point"}
}