{
  "type": "Feature",
  "properties": {
    "gn:adm1_name":"Fukushimaken",
    "gn:adm2_name":"Sukagawashi",
    "gn:name":"Sakaemachi",
    "iso:country":"JP",
    "wof:name":"962-0858",
    "wof:placetype":"postalcode"
},
  "geometry": {"coordinates":[140.3716,37.2977],"type":"Point"}
}