{
  "type": "Feature",
  "properties": {
    "gn:adm1_name":"Kyoutofu",
    "gn:adm2_name":"Kyoutoshifushimiku",
    "gn:name":"Mukaijimawatashibachou",
    "iso:country":"JP",
    "wof:name":"612-8135",
    "wof:placetype":"postalcode"
},
  "geometry": {"coordinates":[135.7886,34.9178],"type":"Point"}
}