{
  "type": "Feature",
  "properties": {
    "gn:adm1_name":"Kagoshimaken",
    "gn:adm2_name":"Kimotsukigunkouyamachou",
    "gn:name":"Nosaki",
    "iso:country":"JP",
    "wof:name":"893-1201",
    "wof:placetype":"postalcode"
},
  "geometry": {"coordinates":[130.97900000000001,31.3457],"type":"Point"}
}