{
  "type": "Feature",
  "properties": {
    "gn:adm1_name":"Yamagataken",
    "gn:adm2_name":"Yonezawashi",
    "gn:name":"Banseichoutatsuzawa",
    "iso:country":"JP",
    "wof:name":"992-1201",
    "wof:placetype":"postalcode"
},
  "geometry": {"coordinates":[140.14519999999999,37.8819],"type":"Point"}
}