{
  "type": "Feature",
  "properties": {
    "gn:adm1_name":"Yamanashiken",
    "gn:adm2_name":"Minamikomagunhayakawachou",
    "gn:name":"Koujuu",
    "iso:country":"JP",
    "wof:name":"409-2732",
    "wof:placetype":"postalcode"
},
  "geometry": {"coordinates":[138.36750000000001,35.4082],"type":"Point"}
}