{
  "type": "Feature",
  "properties": {
    "gn:adm1_name":"Fukushimaken",
    "gn:adm2_name":"Kooriyamashi",
    "gn:name":"Akagimachi",
    "iso:country":"JP",
    "wof:name":"963-8006",
    "wof:placetype":"postalcode"
},
  "geometry": {"coordinates":[140.38249999999999,37.4027],"type":"Point"}
}