{
  "type": "Feature",
  "properties": {
    "gn:adm1_name":"Kyoutofu",
    "gn:adm2_name":"Yosagun'Inechou",
    "gn:name":"Oohara",
    "iso:country":"JP",
    "wof:name":"626-0422",
    "wof:placetype":"postalcode"
},
  "geometry": {"coordinates":[135.29509999999999,35.6852],"type":"Point"}
}