{
  "type": "Feature",
  "properties": {
    "gn:adm1_name":"Chibaken",
    "gn:adm2_name":"Sawarashi",
    "gn:name":"Oone",
    "iso:country":"JP",
    "wof:name":"287-0026",
    "wof:placetype":"postalcode"
},
  "geometry": {"coordinates":[140.60939999999999,35.8513],"type":"Point"}
}