{
  "type": "Feature",
  "properties": {
    "gn:adm1_name":"Gifuken",
    "gn:adm2_name":"Gifushi",
    "gn:name":"Odadukachou",
    "iso:country":"JP",
    "wof:name":"500-8135",
    "wof:placetype":"postalcode"
},
  "geometry": {"coordinates":[136.77979999999999,35.4177],"type":"Point"}
}