{
  "type": "Feature",
  "properties": {
    "gn:adm1_name":"Mieken",
    "gn:adm2_name":"Takiguntakichou",
    "gn:name":"Inouchibayashi",
    "iso:country":"JP",
    "wof:name":"519-2186",
    "wof:placetype":"postalcode"
},
  "geometry": {"coordinates":[136.51400000000001,34.501],"type":"Point"}
}