{
  "type": "Feature",
  "properties": {
    "gn:adm1_name":"Hyougoken",
    "gn:adm2_name":"Akoushi",
    "gn:name":"Nishihamachou",
    "iso:country":"JP",
    "wof:name":"678-0208",
    "wof:placetype":"postalcode"
},
  "geometry": {"coordinates":[134.3733,34.747],"type":"Point"}
}