{
  "type": "Feature",
  "properties": {
    "gn:adm1_name":"Hyougoken",
    "gn:adm2_name":"Sandashi",
    "gn:name":"Shimoaono",
    "iso:country":"JP",
    "wof:name":"669-1302",
    "wof:placetype":"postalcode"
},
  "geometry": {"coordinates":[135.2081,34.9608],"type":"Point"}
}