{
  "type": "Feature",
  "properties": {
    "gn:adm1_name":"Fukushimaken",
    "gn:adm2_name":"Soumashi",
    "gn:name":"Iwanoko",
    "iso:country":"JP",
    "wof:name":"976-0025",
    "wof:placetype":"postalcode"
},
  "geometry": {"coordinates":[140.964,37.8061],"type":"Point"}
}