{
  "type": "Feature",
  "properties": {
    "gn:adm1_name":"Kyoutofu",
    "gn:adm2_name":"Sourakugunseikachou",
    "gn:name":"Zakuro",
    "iso:country":"JP",
    "wof:name":"619-0234",
    "wof:placetype":"postalcode"
},
  "geometry": {"coordinates":[135.7595,34.7318],"type":"Point"}
}