{
  "type": "Feature",
  "properties": {
    "gn:adm1_name":"Ishikawaken",
    "gn:adm2_name":"Fugeshigunmonzenmachi",
    "gn:name":"Ikeda",
    "iso:country":"JP",
    "wof:name":"927-2354",
    "wof:placetype":"postalcode"
},
  "geometry": {"coordinates":[136.72399999999999,37.257],"type":"Point"}
}