{
  "type": "Feature",
  "properties": {
    "gn:adm1_name":"Aichiken",
    "gn:adm2_name":"Nagoyashimoriyamaku",
    "gn:name":"Seko(Choume)",
    "iso:country":"JP",
    "wof:name":"463-0068",
    "wof:placetype":"postalcode"
},
  "geometry": {"coordinates":[136.9376,35.212],"type":"Point"}
}