{
  "type": "Feature",
  "properties": {
    "gn:adm1_name":"Saitamaken",
    "gn:adm2_name":"Todashi",
    "gn:name":"Niizominami",
    "iso:country":"JP",
    "wof:name":"335-0026",
    "wof:placetype":"postalcode"
},
  "geometry": {"coordinates":[139.66640000000001,35.8082],"type":"Point"}
}