{
  "type": "Feature",
  "properties": {
    "gn:adm1_name":"Fukuokaken",
    "gn:adm2_name":"Ongagun'Okagakimachi",
    "gn:name":"Togiri",
    "iso:country":"JP",
    "wof:name":"811-4222",
    "wof:placetype":"postalcode"
},
  "geometry": {"coordinates":[130.63980000000001,33.8384],"type":"Point"}
}