{
  "type": "Feature",
  "properties": {
    "gn:adm1_name":"Chibaken",
    "gn:adm2_name":"Chibashiinageku",
    "gn:name":"Roppouchou",
    "iso:country":"JP",
    "wof:name":"263-0004",
    "wof:placetype":"postalcode"
},
  "geometry": {"coordinates":[140.143,35.6572],"type":"Point"}
}