{
  "type": "Feature",
  "properties": {
    "gn:adm1_name":"Ishikawaken",
    "gn:adm2_name":"Nanaoshi",
    "gn:name":"Shouwamachi",
    "iso:country":"JP",
    "wof:name":"926-0801",
    "wof:placetype":"postalcode"
},
  "geometry": {"coordinates":[136.9666,37.0492],"type":"Point"}
}