{
  "type": "Feature",
  "properties": {
    "gn:adm1_name":"Chibaken",
    "gn:adm2_name":"Kamogawashi",
    "gn:name":"Hanabusa",
    "iso:country":"JP",
    "wof:name":"296-0032",
    "wof:placetype":"postalcode"
},
  "geometry": {"coordinates":[140.09100000000001,35.1229],"type":"Point"}
}