{
  "type": "Feature",
  "properties": {
    "gn:adm1_name":"Yamaguchiken",
    "gn:adm2_name":"Iwakunishi",
    "gn:name":"Iwakuni",
    "iso:country":"JP",
    "wof:name":"741-0062",
    "wof:placetype":"postalcode"
},
  "geometry": {"coordinates":[132.18180000000001,34.1648],"type":"Point"}
}