{
  "type": "Feature",
  "properties": {
    "gn:adm1_name":"Yamagataken",
    "gn:adm2_name":"Shinjoushi",
    "gn:name":"Sumiyoshimachi",
    "iso:country":"JP",
    "wof:name":"996-0022",
    "wof:placetype":"postalcode"
},
  "geometry": {"coordinates":[140.30340000000001,38.7665],"type":"Point"}
}