{
  "type": "Feature",
  "properties": {
    "gn:adm1_name":"Kagoshimaken",
    "gn:adm2_name":"Kanoyashi",
    "gn:name":"Shimotakakumachou",
    "iso:country":"JP",
    "wof:name":"893-0132",
    "wof:placetype":"postalcode"
},
  "geometry": {"coordinates":[130.87979999999999,31.4657],"type":"Point"}
}