{
  "type": "Feature",
  "properties": {
    "gn:adm1_name":"Ishikawaken",
    "gn:adm2_name":"Suzushi",
    "gn:name":"Shimizumachi",
    "iso:country":"JP",
    "wof:name":"927-1324",
    "wof:placetype":"postalcode"
},
  "geometry": {"coordinates":[137.11760000000001,37.4852],"type":"Point"}
}