{
  "type": "Feature",
  "properties": {
    "gn:adm1_name":"Aichiken",
    "gn:adm2_name":"Okazakishi",
    "gn:name":"Hacchouchou",
    "iso:country":"JP",
    "wof:name":"444-0923",
    "wof:placetype":"postalcode"
},
  "geometry": {"coordinates":[137.1515,34.9571],"type":"Point"}
}