{
  "type": "Feature",
  "properties": {
    "gn:adm1_name":"Yamagataken",
    "gn:adm2_name":"Higashitagawagunhaguromachi",
    "gn:name":"Kurose",
    "iso:country":"JP",
    "wof:name":"997-0151",
    "wof:placetype":"postalcode"
},
  "geometry": {"coordinates":[139.88560000000001,38.7189],"type":"Point"}
}