{
  "type": "Feature",
  "properties": {
    "gn:adm1_name":"Kouchiken",
    "gn:adm2_name":"Kamiguntosayamadachou",
    "gn:name":"Takaramachi",
    "iso:country":"JP",
    "wof:name":"782-0034",
    "wof:placetype":"postalcode"
},
  "geometry": {"coordinates":[133.68379999999999,33.6024],"type":"Point"}
}