{
  "type": "Feature",
  "properties": {
    "gn:adm1_name":"Shizuokaken",
    "gn:adm2_name":"Shizuokashi",
    "gn:name":"Shimizutozurasawa",
    "iso:country":"JP",
    "wof:name":"424-0406",
    "wof:placetype":"postalcode"
},
  "geometry": {"coordinates":[138.45599999999999,35.1218],"type":"Point"}
}