{
  "type": "Feature",
  "properties": {
    "gn:adm1_name":"Gifuken",
    "gn:adm2_name":"Gujouguntakasumura",
    "gn:name":"Oowashi",
    "iso:country":"JP",
    "wof:name":"501-5303",
    "wof:placetype":"postalcode"
},
  "geometry": {"coordinates":[136.87899999999999,35.9475],"type":"Point"}
}