{
  "type": "Feature",
  "properties": {
    "gn:adm1_name":"Yamagataken",
    "gn:adm2_name":"Shinjoushi",
    "gn:name":"Tsunozawa",
    "iso:country":"JP",
    "wof:name":"996-0052",
    "wof:placetype":"postalcode"
},
  "geometry": {"coordinates":[140.28100000000001,38.7261],"type":"Point"}
}