{
  "type": "Feature",
  "properties": {
    "gn:adm1_name":"Miyagiken",
    "gn:adm2_name":"Kesennumashi",
    "gn:name":"Matsuzakikatahama",
    "iso:country":"JP",
    "wof:name":"988-0113",
    "wof:placetype":"postalcode"
},
  "geometry": {"coordinates":[141.5857,38.8742],"type":"Point"}
}