{
  "type": "Feature",
  "properties": {
    "gn:adm1_name":"Yamagataken",
    "gn:adm2_name":"Yonezawashi",
    "gn:name":"Kibamachi",
    "iso:country":"JP",
    "wof:name":"992-0058",
    "wof:placetype":"postalcode"
},
  "geometry": {"coordinates":[140.09389999999999,37.9172],"type":"Point"}
}