{
  "type": "Feature",
  "properties": {
    "gn:adm1_name":"Fukushimaken",
    "gn:adm2_name":"Yamagunyamatomachi",
    "gn:name":"Kuyabana",
    "iso:country":"JP",
    "wof:name":"969-4127",
    "wof:placetype":"postalcode"
},
  "geometry": {"coordinates":[139.77549999999999,37.6413],"type":"Point"}
}