{
  "type": "Feature",
  "properties": {
    "gn:adm1_name":"Kyoutofu",
    "gn:adm2_name":"Kyoutoshinakagyouku",
    "gn:name":"Mibushinmeichou",
    "iso:country":"JP",
    "wof:name":"604-8861",
    "wof:placetype":"postalcode"
},
  "geometry": {"coordinates":[135.73869999999999,35.0076],"type":"Point"}
}