{
  "type": "Feature",
  "properties": {
    "gn:adm1_name":"Chibaken",
    "gn:adm2_name":"Funabashishi",
    "gn:name":"Kosaku",
    "iso:country":"JP",
    "wof:name":"273-0037",
    "wof:placetype":"postalcode"
},
  "geometry": {"coordinates":[139.96420000000001,35.7219],"type":"Point"}
}