{
  "type": "Feature",
  "properties": {
    "gn:adm1_name":"Mieken",
    "gn:adm2_name":"Inabeshi",
    "gn:name":"Hokuseichoushinmachi",
    "iso:country":"JP",
    "wof:name":"511-0436",
    "wof:placetype":"postalcode"
},
  "geometry": {"coordinates":[136.4906,35.1292],"type":"Point"}
}