{
  "type": "Feature",
  "properties": {
    "gn:adm1_name":"Hyougoken",
    "gn:adm2_name":"Takasagoshi",
    "gn:name":"Ihohigashi",
    "iso:country":"JP",
    "wof:name":"676-0071",
    "wof:placetype":"postalcode"
},
  "geometry": {"coordinates":[134.79230000000001,34.7714],"type":"Point"}
}