{
  "type": "Feature",
  "properties": {
    "gn:adm1_name":"Kouchiken",
    "gn:adm2_name":"Nakamurashi",
    "gn:name":"Arakawa",
    "iso:country":"JP",
    "wof:name":"787-0668",
    "wof:placetype":"postalcode"
},
  "geometry": {"coordinates":[132.86369999999999,32.9767],"type":"Point"}
}