{
  "type": "Feature",
  "properties": {
    "gn:adm1_name":"Ishikawaken",
    "gn:adm2_name":"Mattoushi",
    "gn:name":"Genpeijimamachi",
    "iso:country":"JP",
    "wof:name":"924-0052",
    "wof:placetype":"postalcode"
},
  "geometry": {"coordinates":[136.5213,36.4862],"type":"Point"}
}