{
  "type": "Feature",
  "properties": {
    "gn:adm1_name":"Gifuken",
    "gn:adm2_name":"Kakamigaharashi",
    "gn:name":"Maedonishimachi",
    "iso:country":"JP",
    "wof:name":"504-0923",
    "wof:placetype":"postalcode"
},
  "geometry": {"coordinates":[136.8733,35.3836],"type":"Point"}
}