{
  "type": "Feature",
  "properties": {
    "gn:adm1_name":"Naraken",
    "gn:adm2_name":"Narashi",
    "gn:name":"Hirookachou",
    "iso:country":"JP",
    "wof:name":"630-1101",
    "wof:placetype":"postalcode"
},
  "geometry": {"coordinates":[135.9265,34.7527],"type":"Point"}
}