{
  "type": "Feature",
  "properties": {
    "gn:adm1_name":"Fukuokaken",
    "gn:adm2_name":"Ookawashi",
    "gn:name":"Gebayashi",
    "iso:country":"JP",
    "wof:name":"831-0002",
    "wof:placetype":"postalcode"
},
  "geometry": {"coordinates":[130.40479999999999,33.2279],"type":"Point"}
}