{
  "type": "Feature",
  "properties": {
    "gn:adm1_name":"Kumamotoken",
    "gn:adm2_name":"Asogunsoyoumachi",
    "gn:name":"Hougano",
    "iso:country":"JP",
    "wof:name":"861-3904",
    "wof:placetype":"postalcode"
},
  "geometry": {"coordinates":[131.11590000000001,32.6929],"type":"Point"}
}