{
  "type": "Feature",
  "properties": {
    "gn:adm1_name":"Naganoken",
    "gn:adm2_name":"Kamiminochiguntogakushimura",
    "gn:name":"Togakushi",
    "iso:country":"JP",
    "wof:name":"381-4101",
    "wof:placetype":"postalcode"
},
  "geometry": {"coordinates":[138.08250000000001,36.7379],"type":"Point"}
}