{
  "type": "Feature",
  "properties": {
    "gn:adm1_name":"Chibaken",
    "gn:adm2_name":"Kisaradushi",
    "gn:name":"Mafune",
    "iso:country":"JP",
    "wof:name":"292-0802",
    "wof:placetype":"postalcode"
},
  "geometry": {"coordinates":[139.93379999999999,35.36],"type":"Point"}
}