{
  "type": "Feature",
  "properties": {
    "gn:adm1_name":"Kyoutofu",
    "gn:adm2_name":"Kyoutoshinishikyouku",
    "gn:name":"Ushigasedoudenchou",
    "iso:country":"JP",
    "wof:name":"615-8052",
    "wof:placetype":"postalcode"
},
  "geometry": {"coordinates":[135.7166,34.9692],"type":"Point"}
}