{
  "type": "Feature",
  "properties": {
    "gn:adm1_name":"Okayamaken",
    "gn:adm2_name":"Kumegunkumenanchou",
    "gn:name":"Koumenaka",
    "iso:country":"JP",
    "wof:name":"709-3627",
    "wof:placetype":"postalcode"
},
  "geometry": {"coordinates":[133.9332,34.8954],"type":"Point"}
}