{
  "type": "Feature",
  "properties": {
    "gn:adm1_name":"Okinawaken",
    "gn:adm2_name":"Okinawashi",
    "gn:name":"Hiyagon",
    "iso:country":"JP",
    "wof:name":"904-2173",
    "wof:placetype":"postalcode"
},
  "geometry": {"coordinates":[127.82089999999999,26.3157],"type":"Point"}
}