{
  "type": "Feature",
  "properties": {
    "gn:adm1_name":"Gifuken",
    "gn:adm2_name":"Kanishi",
    "gn:name":"Tokunominami",
    "iso:country":"JP",
    "wof:name":"509-0205",
    "wof:placetype":"postalcode"
},
  "geometry": {"coordinates":[137.0402,35.4207],"type":"Point"}
}