{
  "type": "Feature",
  "properties": {
    "gn:adm1_name":"Shizuokaken",
    "gn:adm2_name":"Fujiedashi",
    "gn:name":"Setonoya",
    "iso:country":"JP",
    "wof:name":"426-0131",
    "wof:placetype":"postalcode"
},
  "geometry": {"coordinates":[138.20249999999999,34.9553],"type":"Point"}
}