{
  "type": "Feature",
  "properties": {
    "gn:adm1_name":"Shizuokaken",
    "gn:adm2_name":"Fujinomiyashi",
    "gn:name":"Tanakachou",
    "iso:country":"JP",
    "wof:name":"418-0075",
    "wof:placetype":"postalcode"
},
  "geometry": {"coordinates":[138.61770000000001,35.2169],"type":"Point"}
}