{
  "type": "Feature",
  "properties": {
    "gn:adm1_name":"Wakayamaken",
    "gn:adm2_name":"Wakayamashi",
    "gn:name":"Higashisakanouechou",
    "iso:country":"JP",
    "wof:name":"640-8247",
    "wof:placetype":"postalcode"
},
  "geometry": {"coordinates":[135.16579999999999,34.228],"type":"Point"}
}