{
  "type": "Feature",
  "properties": {
    "gn:adm1_name":"Shimaneken",
    "gn:adm2_name":"Oochigunhasumimura",
    "gn:name":"Yukita",
    "iso:country":"JP",
    "wof:name":"696-0506",
    "wof:placetype":"postalcode"
},
  "geometry": {"coordinates":[132.5949,34.8754],"type":"Point"}
}