{
  "type": "Feature",
  "properties": {
    "gn:adm1_name":"Naganoken",
    "gn:adm2_name":"Suwagunshimosuwamachi",
    "gn:name":"Tanakamachi",
    "iso:country":"JP",
    "wof:name":"393-0078",
    "wof:placetype":"postalcode"
},
  "geometry": {"coordinates":[138.08279999999999,36.0786],"type":"Point"}
}