{
  "type": "Feature",
  "properties": {
    "gn:adm1_name":"Fukushimaken",
    "gn:adm2_name":"Yamagunshiokawamachi",
    "gn:name":"Shinagawa",
    "iso:country":"JP",
    "wof:name":"969-3537",
    "wof:placetype":"postalcode"
},
  "geometry": {"coordinates":[139.8546,37.6131],"type":"Point"}
}