{
  "type": "Feature",
  "properties": {
    "gn:adm1_name":"Shimaneken",
    "gn:adm2_name":"Matsueshi",
    "gn:name":"Aobadai",
    "iso:country":"JP",
    "wof:name":"690-0022",
    "wof:placetype":"postalcode"
},
  "geometry": {"coordinates":[133.10489999999999,35.4461],"type":"Point"}
}