{
  "type": "Feature",
  "properties": {
    "gn:adm1_name":"Fukuokaken",
    "gn:adm2_name":"Kitakyuushuushiyahatanishiku",
    "gn:name":"Shimokoujaku",
    "iso:country":"JP",
    "wof:name":"807-0075",
    "wof:placetype":"postalcode"
},
  "geometry": {"coordinates":[130.74260000000001,33.8271],"type":"Point"}
}