{
  "type": "Feature",
  "properties": {
    "gn:adm1_name":"Hyougoken",
    "gn:adm2_name":"Himejishi",
    "gn:name":"Hirohatakukosaka",
    "iso:country":"JP",
    "wof:name":"671-1156",
    "wof:placetype":"postalcode"
},
  "geometry": {"coordinates":[134.61920000000001,34.8069],"type":"Point"}
}