{
  "type": "Feature",
  "properties": {
    "gn:adm1_name":"Nagasakiken",
    "gn:adm2_name":"Shimabarashi",
    "gn:name":"Aobamachi",
    "iso:country":"JP",
    "wof:name":"855-0855",
    "wof:placetype":"postalcode"
},
  "geometry": {"coordinates":[130.35550000000001,32.7846],"type":"Point"}
}