{
  "type": "Feature",
  "properties": {
    "gn:adm1_name":"Tottoriken",
    "gn:adm2_name":"Yazugunwakasachou",
    "gn:name":"Nakahara",
    "iso:country":"JP",
    "wof:name":"680-0732",
    "wof:placetype":"postalcode"
},
  "geometry": {"coordinates":[134.44550000000001,35.2919],"type":"Point"}
}