{
  "type": "Feature",
  "properties": {
    "gn:adm1_name":"Chibaken",
    "gn:adm2_name":"Kashiwashi",
    "gn:name":"Sakuradai",
    "iso:country":"JP",
    "wof:name":"277-0012",
    "wof:placetype":"postalcode"
},
  "geometry": {"coordinates":[139.98140000000001,35.8604],"type":"Point"}
}