{
  "type": "Feature",
  "properties": {
    "gn:adm1_name":"Aichiken",
    "gn:adm2_name":"Chitaguntaketoyochou",
    "gn:name":"Kitakomatsudani",
    "iso:country":"JP",
    "wof:name":"470-2379",
    "wof:placetype":"postalcode"
},
  "geometry": {"coordinates":[136.89259999999999,34.8489],"type":"Point"}
}