{
  "type": "Feature",
  "properties": {
    "gn:adm1_name":"Oosakafu",
    "gn:adm2_name":"Neyagawashi",
    "gn:name":"Koorihondoorichou",
    "iso:country":"JP",
    "wof:name":"572-0082",
    "wof:placetype":"postalcode"
},
  "geometry": {"coordinates":[135.63300000000001,34.7854],"type":"Point"}
}