{
  "type": "Feature",
  "properties": {
    "gn:adm1_name":"Saitamaken",
    "gn:adm2_name":"Saitamashinishiku",
    "gn:name":"Hirakataryouryouke",
    "iso:country":"JP",
    "wof:name":"331-0072",
    "wof:placetype":"postalcode"
},
  "geometry": {"coordinates":[139.5624,35.9246],"type":"Point"}
}