{
  "type": "Feature",
  "properties": {
    "gn:adm1_name":"Fukuokaken",
    "gn:adm2_name":"Kitakyuushuushiyahatanishiku",
    "gn:name":"Katsukinishi",
    "iso:country":"JP",
    "wof:name":"807-1103",
    "wof:placetype":"postalcode"
},
  "geometry": {"coordinates":[130.72929999999999,33.8038],"type":"Point"}
}