{
  "type": "Feature",
  "properties": {
    "gn:adm1_name":"Chibaken",
    "gn:adm2_name":"Touganeshi",
    "gn:name":"Yamada",
    "iso:country":"JP",
    "wof:name":"283-0823",
    "wof:placetype":"postalcode"
},
  "geometry": {"coordinates":[140.30009999999999,35.5707],"type":"Point"}
}