{
  "type": "Feature",
  "properties": {
    "gn:adm1_name":"Nagasakiken",
    "gn:adm2_name":"Nishisonogigunsotomechou",
    "gn:name":"Kounourakuchibukugou",
    "iso:country":"JP",
    "wof:name":"851-2401",
    "wof:placetype":"postalcode"
},
  "geometry": {"coordinates":[129.67689999999999,32.8967],"type":"Point"}
}