{
  "type": "Feature",
  "properties": {
    "gn:adm1_name":"Miyagiken",
    "gn:adm2_name":"Kuriharaguntakashimizumachi",
    "gn:name":"Sodeyama",
    "iso:country":"JP",
    "wof:name":"987-2183",
    "wof:placetype":"postalcode"
},
  "geometry": {"coordinates":[141.00970000000001,38.6639],"type":"Point"}
}