{
  "type": "Feature",
  "properties": {
    "gn:adm1_name":"Kouchiken",
    "gn:adm2_name":"Kouchishi",
    "gn:name":"Honmachi",
    "iso:country":"JP",
    "wof:name":"780-0870",
    "wof:placetype":"postalcode"
},
  "geometry": {"coordinates":[133.53489999999999,33.5586],"type":"Point"}
}