{
  "type": "Feature",
  "properties": {
    "gn:adm1_name":"Tokushimaken",
    "gn:adm2_name":"Oegunkamojimachou",
    "gn:name":"Kiraiotsu",
    "iso:country":"JP",
    "wof:name":"776-0007",
    "wof:placetype":"postalcode"
},
  "geometry": {"coordinates":[134.36539999999999,34.0791],"type":"Point"}
}