{
  "type": "Feature",
  "properties": {
    "gn:adm1_name":"Oosakafu",
    "gn:adm2_name":"Sennanshi",
    "gn:name":"Shindachimakino",
    "iso:country":"JP",
    "wof:name":"590-0522",
    "wof:placetype":"postalcode"
},
  "geometry": {"coordinates":[135.27930000000001,34.3608],"type":"Point"}
}