{
  "type": "Feature",
  "properties": {
    "gn:adm1_name":"Miyagiken",
    "gn:adm2_name":"Kesennumashi",
    "gn:name":"Matsuzakitakaya",
    "iso:country":"JP",
    "wof:name":"988-0124",
    "wof:placetype":"postalcode"
},
  "geometry": {"coordinates":[141.57339999999999,38.8714],"type":"Point"}
}