{
  "type": "Feature",
  "properties": {
    "gn:adm1_name":"Wakayamaken",
    "gn:adm2_name":"Kaisougunshimotsuchou",
    "gn:name":"Ookubo",
    "iso:country":"JP",
    "wof:name":"649-0155",
    "wof:placetype":"postalcode"
},
  "geometry": {"coordinates":[135.2088,34.1121],"type":"Point"}
}