{
  "type": "Feature",
  "properties": {
    "gn:adm1_name":"Fukushimaken",
    "gn:adm2_name":"Ishikawagun'Ishikawamachi",
    "gn:name":"Mamegahira",
    "iso:country":"JP",
    "wof:name":"963-7816",
    "wof:placetype":"postalcode"
},
  "geometry": {"coordinates":[140.44409999999999,37.1283],"type":"Point"}
}