{
  "type": "Feature",
  "properties": {
    "gn:adm1_name":"Kagawaken",
    "gn:adm2_name":"Higashikagawashi",
    "gn:name":"Iza",
    "iso:country":"JP",
    "wof:name":"769-2703",
    "wof:placetype":"postalcode"
},
  "geometry": {"coordinates":[134.3794,34.2371],"type":"Point"}
}