{
  "type": "Feature",
  "properties": {
    "gn:adm1_name":"Toukyouto",
    "gn:adm2_name":"Itabashiku",
    "gn:name":"Minamichou",
    "iso:country":"JP",
    "wof:name":"173-0027",
    "wof:placetype":"postalcode"
},
  "geometry": {"coordinates":[139.70140000000001,35.74],"type":"Point"}
}