{
  "type": "Feature",
  "properties": {
    "gn:adm1_name":"Ehimeken",
    "gn:adm2_name":"Kitagunnagahamachou",
    "gn:name":"Kurontakou",
    "iso:country":"JP",
    "wof:name":"799-3407",
    "wof:placetype":"postalcode"
},
  "geometry": {"coordinates":[132.4913,33.615],"type":"Point"}
}