{
  "type": "Feature",
  "properties": {
    "gn:adm1_name":"Ishikawaken",
    "gn:adm2_name":"Ishikawaguntorigoemura",
    "gn:name":"Mitsuyano",
    "iso:country":"JP",
    "wof:name":"920-2345",
    "wof:placetype":"postalcode"
},
  "geometry": {"coordinates":[136.6414,36.3214],"type":"Point"}
}