{
  "type": "Feature",
  "properties": {
    "gn:adm1_name":"Fukuiken",
    "gn:adm2_name":"Fukuishi",
    "gn:name":"Keya",
    "iso:country":"JP",
    "wof:name":"918-8003",
    "wof:placetype":"postalcode"
},
  "geometry": {"coordinates":[136.21449999999999,36.0573],"type":"Point"}
}