{
  "type": "Feature",
  "properties": {
    "gn:adm1_name":"Kumamotoken",
    "gn:adm2_name":"Asoguntakamorimachi",
    "gn:name":"Ikanikeisaiganaibaai",
    "iso:country":"JP",
    "wof:name":"869-1600",
    "wof:placetype":"postalcode"
},
  "geometry": {"coordinates":[131.2533,32.9088],"type":"Point"}
}