{
  "type": "Feature",
  "properties": {
    "gn:adm1_name":"Hiroshimaken",
    "gn:adm2_name":"Higashihiroshimashi",
    "gn:name":"Shiwaryuutsuu",
    "iso:country":"JP",
    "wof:name":"739-0263",
    "wof:placetype":"postalcode"
},
  "geometry": {"coordinates":[132.6542,34.4675],"type":"Point"}
}