{
  "type": "Feature",
  "properties": {
    "gn:adm1_name":"Chibaken",
    "gn:adm2_name":"Kisaradushi",
    "gn:name":"Shimomiyada",
    "iso:country":"JP",
    "wof:name":"292-0217",
    "wof:placetype":"postalcode"
},
  "geometry": {"coordinates":[140.023,35.3494],"type":"Point"}
}