{
  "type": "Feature",
  "properties": {
    "gn:adm1_name":"Fukushimaken",
    "gn:adm2_name":"Kitakatashi",
    "gn:name":"Suwa",
    "iso:country":"JP",
    "wof:name":"966-0896",
    "wof:placetype":"postalcode"
},
  "geometry": {"coordinates":[139.86859999999999,37.6541],"type":"Point"}
}