{
  "type": "Feature",
  "properties": {
    "gn:adm1_name":"Kanagawaken",
    "gn:adm2_name":"Hadanoshi",
    "gn:name":"Naganuki",
    "iso:country":"JP",
    "wof:name":"257-0024",
    "wof:placetype":"postalcode"
},
  "geometry": {"coordinates":[139.24119999999999,35.3842],"type":"Point"}
}