{
  "type": "Feature",
  "properties": {
    "gn:adm1_name":"Gifuken",
    "gn:adm2_name":"Gujougunmeihoumura",
    "gn:name":"Okuzumi",
    "iso:country":"JP",
    "wof:name":"501-4304",
    "wof:placetype":"postalcode"
},
  "geometry": {"coordinates":[137.06180000000001,35.8952],"type":"Point"}
}