{
  "type": "Feature",
  "properties": {
    "gn:adm1_name":"Oosakafu",
    "gn:adm2_name":"Yaoshi",
    "gn:name":"Higashikyuuhouji",
    "iso:country":"JP",
    "wof:name":"581-0002",
    "wof:placetype":"postalcode"
},
  "geometry": {"coordinates":[135.5926,34.6295],"type":"Point"}
}