{
  "type": "Feature",
  "properties": {
    "gn:adm1_name":"Wakayamaken",
    "gn:adm2_name":"Wakayamashi",
    "gn:name":"Minamibata",
    "iso:country":"JP",
    "wof:name":"640-0315",
    "wof:placetype":"postalcode"
},
  "geometry": {"coordinates":[135.25890000000001,34.1915],"type":"Point"}
}