{
  "type": "Feature",
  "properties": {
    "gn:adm1_name":"Niigataken",
    "gn:adm2_name":"Kitakanbaragunsasakamimura",
    "gn:name":"Sawaguchi",
    "iso:country":"JP",
    "wof:name":"959-1913",
    "wof:placetype":"postalcode"
},
  "geometry": {"coordinates":[139.28530000000001,37.8509],"type":"Point"}
}