{
  "type": "Feature",
  "properties": {
    "gn:adm1_name":"Fukuokaken",
    "gn:adm2_name":"Ookawashi",
    "gn:name":"Doukaijima",
    "iso:country":"JP",
    "wof:name":"831-0007",
    "wof:placetype":"postalcode"
},
  "geometry": {"coordinates":[130.3768,33.2377],"type":"Point"}
}