{
  "type": "Feature",
  "properties": {
    "gn:adm1_name":"Saitamaken",
    "gn:adm2_name":"Saitamashisakuraku",
    "gn:name":"Nishibori",
    "iso:country":"JP",
    "wof:name":"338-0832",
    "wof:placetype":"postalcode"
},
  "geometry": {"coordinates":[139.63079999999999,35.8579],"type":"Point"}
}