{
  "type": "Feature",
  "properties": {
    "gn:adm1_name":"Mieken",
    "gn:adm2_name":"Wataraigunwataraichou",
    "gn:name":"Makae",
    "iso:country":"JP",
    "wof:name":"516-2117",
    "wof:placetype":"postalcode"
},
  "geometry": {"coordinates":[136.55719999999999,34.4381],"type":"Point"}
}