{
  "type": "Feature",
  "properties": {
    "gn:adm1_name":"Miyagiken",
    "gn:adm2_name":"Kattagunshichikashukumachi",
    "gn:name":"Yatsuwake",
    "iso:country":"JP",
    "wof:name":"989-0548",
    "wof:placetype":"postalcode"
},
  "geometry": {"coordinates":[140.41079999999999,38.0111],"type":"Point"}
}