{
  "type": "Feature",
  "properties": {
    "gn:adm1_name":"Ooitaken",
    "gn:adm2_name":"Ooitashi",
    "gn:name":"Morimachi",
    "iso:country":"JP",
    "wof:name":"870-0127",
    "wof:placetype":"postalcode"
},
  "geometry": {"coordinates":[131.6808,33.2266],"type":"Point"}
}