{
  "type": "Feature",
  "properties": {
    "gn:adm1_name":"Toyamaken",
    "gn:adm2_name":"Higashitonamigunfukunomachi",
    "gn:name":"Hyakuchou",
    "iso:country":"JP",
    "wof:name":"939-1517",
    "wof:placetype":"postalcode"
},
  "geometry": {"coordinates":[136.93170000000001,36.5894],"type":"Point"}
}