{
  "type": "Feature",
  "properties": {
    "gn:adm1_name":"Ibarakiken",
    "gn:adm2_name":"Shimotsumashi",
    "gn:name":"Fukuda",
    "iso:country":"JP",
    "wof:name":"304-0027",
    "wof:placetype":"postalcode"
},
  "geometry": {"coordinates":[139.96440000000001,36.2014],"type":"Point"}
}