{
  "type": "Feature",
  "properties": {
    "gn:adm1_name":"Yamaguchiken",
    "gn:adm2_name":"Shuunanshi",
    "gn:name":"Kawamagari",
    "iso:country":"JP",
    "wof:name":"745-0852",
    "wof:placetype":"postalcode"
},
  "geometry": {"coordinates":[131.8115,34.1048],"type":"Point"}
}