{
  "type": "Feature",
  "properties": {
    "gn:adm1_name":"Chibaken",
    "gn:adm2_name":"Chouseigunmutsuzawamachi",
    "gn:name":"Chourakuji",
    "iso:country":"JP",
    "wof:name":"299-4421",
    "wof:placetype":"postalcode"
},
  "geometry": {"coordinates":[140.30099999999999,35.359],"type":"Point"}
}