{
  "type": "Feature",
  "properties": {
    "gn:adm1_name":"Okayamaken",
    "gn:adm2_name":"Aidagun'Ooharachou",
    "gn:name":"Awano",
    "iso:country":"JP",
    "wof:name":"707-0437",
    "wof:placetype":"postalcode"
},
  "geometry": {"coordinates":[134.2722,35.078],"type":"Point"}
}