{
  "type": "Feature",
  "properties": {
    "gn:adm1_name":"Niigataken",
    "gn:adm2_name":"Jouetsushi",
    "gn:name":"Mitsuhashi",
    "iso:country":"JP",
    "wof:name":"942-0043",
    "wof:placetype":"postalcode"
},
  "geometry": {"coordinates":[138.27379999999999,37.1643],"type":"Point"}
}