{
  "type": "Feature",
  "properties": {
    "gn:adm1_name":"Gifuken",
    "gn:adm2_name":"Yoshikigunkamiokachou",
    "gn:name":"Higashimachi",
    "iso:country":"JP",
    "wof:name":"506-1111",
    "wof:placetype":"postalcode"
},
  "geometry": {"coordinates":[137.30119999999999,36.3326],"type":"Point"}
}