{
  "type": "Feature",
  "properties": {
    "gn:adm1_name":"Tochigiken",
    "gn:adm2_name":"Shimotsugagun'Oohiramachi",
    "gn:name":"Shimotakashima",
    "iso:country":"JP",
    "wof:name":"329-4414",
    "wof:placetype":"postalcode"
},
  "geometry": {"coordinates":[139.7415,36.3349],"type":"Point"}
}