{
  "type": "Feature",
  "properties": {
    "gn:adm1_name":"Fukushimaken",
    "gn:adm2_name":"Dategundatemachi",
    "gn:name":"Emukai",
    "iso:country":"JP",
    "wof:name":"960-0457",
    "wof:placetype":"postalcode"
},
  "geometry": {"coordinates":[140.9777,37.6996],"type":"Point"}
}