{
  "type": "Feature",
  "properties": {
    "gn:adm1_name":"Saitamaken",
    "gn:adm2_name":"Higashimatsuyamashi",
    "gn:name":"Yamazakichou",
    "iso:country":"JP",
    "wof:name":"355-0033",
    "wof:placetype":"postalcode"
},
  "geometry": {"coordinates":[139.42429999999999,36.0295],"type":"Point"}
}