{
  "type": "Feature",
  "properties": {
    "gn:adm1_name":"Aichiken",
    "gn:adm2_name":"Taharashi",
    "gn:name":"Minamikanbechou",
    "iso:country":"JP",
    "wof:name":"441-3424",
    "wof:placetype":"postalcode"
},
  "geometry": {"coordinates":[137.27850000000001,34.6366],"type":"Point"}
}