{
  "type": "Feature",
  "properties": {
    "gn:adm1_name":"Kouchiken",
    "gn:adm2_name":"Kouchishi",
    "gn:name":"Misonochou",
    "iso:country":"JP",
    "wof:name":"780-0034",
    "wof:placetype":"postalcode"
},
  "geometry": {"coordinates":[133.53360000000001,33.5745],"type":"Point"}
}