{
  "type": "Feature",
  "properties": {
    "gn:adm1_name":"Oosakafu",
    "gn:adm2_name":"Hannanshi",
    "gn:name":"Tottori",
    "iso:country":"JP",
    "wof:name":"599-0204",
    "wof:placetype":"postalcode"
},
  "geometry": {"coordinates":[135.232,34.3523],"type":"Point"}
}