{
  "type": "Feature",
  "properties": {
    "gn:adm1_name":"Niigataken",
    "gn:adm2_name":"Niigatashi",
    "gn:name":"Kitayama",
    "iso:country":"JP",
    "wof:name":"950-0116",
    "wof:placetype":"postalcode"
},
  "geometry": {"coordinates":[139.11879999999999,37.8746],"type":"Point"}
}