{
  "type": "Feature",
  "properties": {
    "gn:adm1_name":"Yamaguchiken",
    "gn:adm2_name":"Shimonosekishi",
    "gn:name":"Takaramachi",
    "iso:country":"JP",
    "wof:name":"751-0822",
    "wof:placetype":"postalcode"
},
  "geometry": {"coordinates":[130.9393,33.9816],"type":"Point"}
}