{
  "type": "Feature",
  "properties": {
    "gn:adm1_name":"Niigataken",
    "gn:adm2_name":"Niigatashi",
    "gn:name":"Fujinoki",
    "iso:country":"JP",
    "wof:name":"950-2138",
    "wof:placetype":"postalcode"
},
  "geometry": {"coordinates":[138.91759999999999,37.8216],"type":"Point"}
}