{
  "type": "Feature",
  "properties": {
    "gn:adm1_name":"Gifuken",
    "gn:adm2_name":"Yoshikigunkokufuchou",
    "gn:name":"Tsurusu",
    "iso:country":"JP",
    "wof:name":"509-4112",
    "wof:placetype":"postalcode"
},
  "geometry": {"coordinates":[137.20830000000001,36.2241],"type":"Point"}
}