{
  "type": "Feature",
  "properties": {
    "gn:adm1_name":"Ishikawaken",
    "gn:adm2_name":"Kagashi",
    "gn:name":"Kashiwanomachi",
    "iso:country":"JP",
    "wof:name":"922-0262",
    "wof:placetype":"postalcode"
},
  "geometry": {"coordinates":[136.39320000000001,36.277],"type":"Point"}
}