{
  "type": "Feature",
  "properties": {
    "gn:adm1_name":"Hyougoken",
    "gn:adm2_name":"Mikatagun'Onsenchou",
    "gn:name":"Tando",
    "iso:country":"JP",
    "wof:name":"669-6813",
    "wof:placetype":"postalcode"
},
  "geometry": {"coordinates":[134.494,35.5097],"type":"Point"}
}