{
  "type": "Feature",
  "properties": {
    "gn:adm1_name":"Hyougoken",
    "gn:adm2_name":"Sandashi",
    "gn:name":"Inokusa",
    "iso:country":"JP",
    "wof:name":"669-1356",
    "wof:placetype":"postalcode"
},
  "geometry": {"coordinates":[135.1816,34.9477],"type":"Point"}
}