{
  "type": "Feature",
  "properties": {
    "gn:adm1_name":"Tokushimaken",
    "gn:adm2_name":"Tokushimashi",
    "gn:name":"Iitanichou",
    "iso:country":"JP",
    "wof:name":"771-4265",
    "wof:placetype":"postalcode"
},
  "geometry": {"coordinates":[134.5497,33.9724],"type":"Point"}
}