{
  "type": "Feature",
  "properties": {
    "gn:adm1_name":"Kyoutofu",
    "gn:adm2_name":"Kitakuwadagunkeihokuchou",
    "gn:name":"Akaishi",
    "iso:country":"JP",
    "wof:name":"601-0541",
    "wof:placetype":"postalcode"
},
  "geometry": {"coordinates":[135.61789999999999,35.2089],"type":"Point"}
}