{
  "type": "Feature",
  "properties": {
    "gn:adm1_name":"Yamaguchiken",
    "gn:adm2_name":"Shuunanshi",
    "gn:name":"Nogamichou",
    "iso:country":"JP",
    "wof:name":"745-0042",
    "wof:placetype":"postalcode"
},
  "geometry": {"coordinates":[131.80099999999999,34.0564],"type":"Point"}
}