{
  "type": "Feature",
  "properties": {
    "gn:adm1_name":"Yamagataken",
    "gn:adm2_name":"Nishiokitamagun'Ogunimachi",
    "gn:name":"Isaryou",
    "iso:country":"JP",
    "wof:name":"999-1322",
    "wof:placetype":"postalcode"
},
  "geometry": {"coordinates":[139.81610000000001,38.0519],"type":"Point"}
}