{
  "type": "Feature",
  "properties": {
    "gn:adm1_name":"Nagasakiken",
    "gn:adm2_name":"Kitamatsuuragunshikamachichou",
    "gn:name":"Nakanomen",
    "iso:country":"JP",
    "wof:name":"859-6205",
    "wof:placetype":"postalcode"
},
  "geometry": {"coordinates":[129.60769999999999,33.2707],"type":"Point"}
}