{
  "type": "Feature",
  "properties": {
    "gn:adm1_name":"Hyougoken",
    "gn:adm2_name":"Asagogunsantouchou",
    "gn:name":"Yofudo",
    "iso:country":"JP",
    "wof:name":"669-5136",
    "wof:placetype":"postalcode"
},
  "geometry": {"coordinates":[134.87540000000001,35.2813],"type":"Point"}
}