{
  "type": "Feature",
  "properties": {
    "gn:adm1_name":"Shizuokaken",
    "gn:adm2_name":"Kamogunhigashiizuchou",
    "gn:name":"Ikanikeisaiganaibaai",
    "iso:country":"JP",
    "wof:name":"413-0300",
    "wof:placetype":"postalcode"
},
  "geometry": {"coordinates":[139.05009999999999,34.7945],"type":"Point"}
}