{
  "type": "Feature",
  "properties": {
    "gn:adm1_name":"Miyagiken",
    "gn:adm2_name":"Kuriharaguntakashimizumachi",
    "gn:name":"Ipponmatsu",
    "iso:country":"JP",
    "wof:name":"987-2115",
    "wof:placetype":"postalcode"
},
  "geometry": {"coordinates":[141.01400000000001,38.6616],"type":"Point"}
}