{
  "type": "Feature",
  "properties": {
    "gn:adm1_name":"Miyagiken",
    "gn:adm2_name":"Shibatagun'Oogawaramachi",
    "gn:name":"Nishimachi",
    "iso:country":"JP",
    "wof:name":"989-1244",
    "wof:placetype":"postalcode"
},
  "geometry": {"coordinates":[140.7345,38.0516],"type":"Point"}
}