{
  "type": "Feature",
  "properties": {
    "gn:adm1_name":"Sagaken",
    "gn:adm2_name":"Sagashi",
    "gn:name":"Oroshihonmachi",
    "iso:country":"JP",
    "wof:name":"849-0933",
    "wof:placetype":"postalcode"
},
  "geometry": {"coordinates":[130.2784,33.2737],"type":"Point"}
}