{
  "type": "Feature",
  "properties": {
    "gn:adm1_name":"Shimaneken",
    "gn:adm2_name":"Hamadashi",
    "gn:name":"Kousachou",
    "iso:country":"JP",
    "wof:name":"697-0007",
    "wof:placetype":"postalcode"
},
  "geometry": {"coordinates":[132.1069,34.9051],"type":"Point"}
}