{
  "type": "Feature",
  "properties": {
    "gn:adm1_name":"Shimaneken",
    "gn:adm2_name":"Yatsukagunyatsukachou",
    "gn:name":"Eshima",
    "iso:country":"JP",
    "wof:name":"690-1401",
    "wof:placetype":"postalcode"
},
  "geometry": {"coordinates":[133.19370000000001,35.5117],"type":"Point"}
}