{
  "type": "Feature",
  "properties": {
    "gn:adm1_name":"Shimaneken",
    "gn:adm2_name":"Yatsukagunhigashiizumochou",
    "gn:name":"Adakae",
    "iso:country":"JP",
    "wof:name":"699-0108",
    "wof:placetype":"postalcode"
},
  "geometry": {"coordinates":[133.1317,35.4312],"type":"Point"}
}