{
  "type": "Feature",
  "properties": {
    "gn:adm1_name":"Niigataken",
    "gn:adm2_name":"Kitakanbaragunnakajoumachi",
    "gn:name":"Juuniten",
    "iso:country":"JP",
    "wof:name":"959-2619",
    "wof:placetype":"postalcode"
},
  "geometry": {"coordinates":[139.40969999999999,38.0927],"type":"Point"}
}