{
  "type": "Feature",
  "properties": {
    "gn:adm1_name":"Toyamaken",
    "gn:adm2_name":"Nakaniikawaguntateyamamachi",
    "gn:name":"Sawahata",
    "iso:country":"JP",
    "wof:name":"930-0212",
    "wof:placetype":"postalcode"
},
  "geometry": {"coordinates":[137.32490000000001,36.677],"type":"Point"}
}