{
  "type": "Feature",
  "properties": {
    "gn:adm1_name":"Tottoriken",
    "gn:adm2_name":"Yonagoshi",
    "gn:name":"Miyoshi",
    "iso:country":"JP",
    "wof:name":"683-0034",
    "wof:placetype":"postalcode"
},
  "geometry": {"coordinates":[133.34360000000001,35.4198],"type":"Point"}
}