{
  "type": "Feature",
  "properties": {
    "gn:adm1_name":"Kouchiken",
    "gn:adm2_name":"Kouchishi",
    "gn:name":"Takaramachi",
    "iso:country":"JP",
    "wof:name":"780-0914",
    "wof:placetype":"postalcode"
},
  "geometry": {"coordinates":[133.52780000000001,33.5686],"type":"Point"}
}