{
  "type": "Feature",
  "properties": {
    "gn:adm1_name":"Kagoshimaken",
    "gn:adm2_name":"Sendaishi",
    "gn:name":"Miyazatochou",
    "iso:country":"JP",
    "wof:name":"895-0056",
    "wof:placetype":"postalcode"
},
  "geometry": {"coordinates":[130.28139999999999,31.8147],"type":"Point"}
}