{
  "type": "Feature",
  "properties": {
    "gn:adm1_name":"Kyoutofu",
    "gn:adm2_name":"Kyoutoshishimogyouku",
    "gn:name":"Takatsujichou",
    "iso:country":"JP",
    "wof:name":"600-8434",
    "wof:placetype":"postalcode"
},
  "geometry": {"coordinates":[135.7602,34.9997],"type":"Point"}
}