{
  "type": "Feature",
  "properties": {
    "gn:adm1_name":"Yamaguchiken",
    "gn:adm2_name":"Kugagunmiwachou",
    "gn:name":"Oonegawa",
    "iso:country":"JP",
    "wof:name":"740-1217",
    "wof:placetype":"postalcode"
},
  "geometry": {"coordinates":[132.126,34.2299],"type":"Point"}
}