{
  "type": "Feature",
  "properties": {
    "gn:adm1_name":"Kyoutofu",
    "gn:adm2_name":"Kameokashi",
    "gn:name":"Higashibetsuinchoukaibara",
    "iso:country":"JP",
    "wof:name":"621-0115",
    "wof:placetype":"postalcode"
},
  "geometry": {"coordinates":[135.56059999999999,34.9261],"type":"Point"}
}