{
  "type": "Feature",
  "properties": {
    "gn:adm1_name":"Kumamotoken",
    "gn:adm2_name":"Shimomashikiguntomochimachi",
    "gn:name":"Niwada",
    "iso:country":"JP",
    "wof:name":"861-4733",
    "wof:placetype":"postalcode"
},
  "geometry": {"coordinates":[130.8631,32.6214],"type":"Point"}
}