{
  "type": "Feature",
  "properties": {
    "gn:adm1_name":"Aichiken",
    "gn:adm2_name":"Nagoyashihigashiku",
    "gn:name":"Meirinchou",
    "iso:country":"JP",
    "wof:name":"461-0031",
    "wof:placetype":"postalcode"
},
  "geometry": {"coordinates":[136.93530000000001,35.1835],"type":"Point"}
}