{
  "type": "Feature",
  "properties": {
    "gn:adm1_name":"Fukushimaken",
    "gn:adm2_name":"Yamagunyamatomachi",
    "gn:name":"Kohata",
    "iso:country":"JP",
    "wof:name":"969-4103",
    "wof:placetype":"postalcode"
},
  "geometry": {"coordinates":[139.77549999999999,37.6583],"type":"Point"}
}