{
  "type": "Feature",
  "properties": {
    "gn:adm1_name":"Aichiken",
    "gn:adm2_name":"Nishioshi",
    "gn:name":"Sugawarachou",
    "iso:country":"JP",
    "wof:name":"445-0815",
    "wof:placetype":"postalcode"
},
  "geometry": {"coordinates":[137.05590000000001,34.8744],"type":"Point"}
}