{
  "type": "Feature",
  "properties": {
    "gn:adm1_name":"Ishikawaken",
    "gn:adm2_name":"Kanazawashi",
    "gn:name":"Yunokimachi",
    "iso:country":"JP",
    "wof:name":"920-0146",
    "wof:placetype":"postalcode"
},
  "geometry": {"coordinates":[136.7543,36.5719],"type":"Point"}
}