{
  "type": "Feature",
  "properties": {
    "gn:adm1_name":"Aichiken",
    "gn:adm2_name":"Owariasahishi",
    "gn:name":"Higashidaidouchouyamanouchi",
    "iso:country":"JP",
    "wof:name":"488-0803",
    "wof:placetype":"postalcode"
},
  "geometry": {"coordinates":[137.0361,35.2137],"type":"Point"}
}