{
  "type": "Feature",
  "properties": {
    "gn:adm1_name":"Yamagataken",
    "gn:adm2_name":"Higashitagawagun'Asahimura",
    "gn:name":"Arasawa",
    "iso:country":"JP",
    "wof:name":"997-0621",
    "wof:placetype":"postalcode"
},
  "geometry": {"coordinates":[139.78399999999999,38.6982],"type":"Point"}
}