{
  "type": "Feature",
  "properties": {
    "gn:adm1_name":"Fukuokaken",
    "gn:adm2_name":"Oomutashi",
    "gn:name":"Yotsuyamamachi",
    "iso:country":"JP",
    "wof:name":"836-0067",
    "wof:placetype":"postalcode"
},
  "geometry": {"coordinates":[130.41,33.0058],"type":"Point"}
}