{
  "type": "Feature",
  "properties": {
    "gn:adm1_name":"Wakayamaken",
    "gn:adm2_name":"Nishimurogun'Ootoumura",
    "gn:name":"Shimotsuyu",
    "iso:country":"JP",
    "wof:name":"646-1337",
    "wof:placetype":"postalcode"
},
  "geometry": {"coordinates":[135.566,33.6741],"type":"Point"}
}