{
  "type": "Feature",
  "properties": {
    "gn:adm1_name":"Ishikawaken",
    "gn:adm2_name":"Hakuiguntogimachi",
    "gn:name":"Inashiki",
    "iso:country":"JP",
    "wof:name":"925-0563",
    "wof:placetype":"postalcode"
},
  "geometry": {"coordinates":[136.71029999999999,37.1715],"type":"Point"}
}