{
  "type": "Feature",
  "properties": {
    "gn:adm1_name":"Tochigiken",
    "gn:adm2_name":"Nasugunkurobanemachi",
    "gn:name":"Horinouchi",
    "iso:country":"JP",
    "wof:name":"324-0235",
    "wof:placetype":"postalcode"
},
  "geometry": {"coordinates":[140.13030000000001,36.8793],"type":"Point"}
}