{
  "type": "Feature",
  "properties": {
    "gn:adm1_name":"Gifuken",
    "gn:adm2_name":"Kakamigaharashi",
    "gn:name":"Ryokuennishi",
    "iso:country":"JP",
    "wof:name":"509-0116",
    "wof:placetype":"postalcode"
},
  "geometry": {"coordinates":[136.9442,35.4131],"type":"Point"}
}