{
  "type": "Feature",
  "properties": {
    "gn:adm1_name":"Tottoriken",
    "gn:adm2_name":"Yazugunmochigasechou",
    "gn:name":"Enami",
    "iso:country":"JP",
    "wof:name":"689-1229",
    "wof:placetype":"postalcode"
},
  "geometry": {"coordinates":[134.1353,35.3088],"type":"Point"}
}