{
  "type": "Feature",
  "properties": {
    "gn:adm1_name":"Wakayamaken",
    "gn:adm2_name":"Wakayamashi",
    "gn:name":"Souzaka",
    "iso:country":"JP",
    "wof:name":"640-0341",
    "wof:placetype":"postalcode"
},
  "geometry": {"coordinates":[135.23140000000001,34.1964],"type":"Point"}
}