{
  "type": "Feature",
  "properties": {
    "gn:adm1_name":"Shimaneken",
    "gn:adm2_name":"Hiratashi",
    "gn:name":"Mitsuchou",
    "iso:country":"JP",
    "wof:name":"691-0053",
    "wof:placetype":"postalcode"
},
  "geometry": {"coordinates":[132.8261,35.4942],"type":"Point"}
}