{
  "type": "Feature",
  "properties": {
    "gn:adm1_name":"Kyoutofu",
    "gn:adm2_name":"Kyoutoshinakagyouku",
    "gn:name":"Iseyachou",
    "iso:country":"JP",
    "wof:name":"604-8066",
    "wof:placetype":"postalcode"
},
  "geometry": {"coordinates":[135.7664,35.0068],"type":"Point"}
}