{
  "type": "Feature",
  "properties": {
    "gn:adm1_name":"Fukuokaken",
    "gn:adm2_name":"Yukuhashishi",
    "gn:name":"Teranawate",
    "iso:country":"JP",
    "wof:name":"824-0042",
    "wof:placetype":"postalcode"
},
  "geometry": {"coordinates":[130.96170000000001,33.7095],"type":"Point"}
}