{
  "type": "Feature",
  "properties": {
    "gn:adm1_name":"Toyamaken",
    "gn:adm2_name":"Oyabeshi",
    "gn:name":"Yanagihara",
    "iso:country":"JP",
    "wof:name":"932-0807",
    "wof:placetype":"postalcode"
},
  "geometry": {"coordinates":[136.90129999999999,36.6801],"type":"Point"}
}