{
  "type": "Feature",
  "properties": {
    "gn:adm1_name":"Aichiken",
    "gn:adm2_name":"Nishioshi",
    "gn:name":"Sakuragichou",
    "iso:country":"JP",
    "wof:name":"445-0853",
    "wof:placetype":"postalcode"
},
  "geometry": {"coordinates":[137.0558,34.8646],"type":"Point"}
}