{
  "type": "Feature",
  "properties": {
    "gn:adm1_name":"Aichiken",
    "gn:adm2_name":"Inazawashi",
    "gn:name":"Shimakoyasukachou",
    "iso:country":"JP",
    "wof:name":"492-8201",
    "wof:placetype":"postalcode"
},
  "geometry": {"coordinates":[136.80340000000001,35.2698],"type":"Point"}
}