{
  "type": "Feature",
  "properties": {
    "gn:adm1_name":"Ishikawaken",
    "gn:adm2_name":"Wajimashi",
    "gn:name":"Hikariuramachi",
    "iso:country":"JP",
    "wof:name":"928-0067",
    "wof:placetype":"postalcode"
},
  "geometry": {"coordinates":[136.8767,37.4026],"type":"Point"}
}