{
  "type": "Feature",
  "properties": {
    "gn:adm1_name":"Gifuken",
    "gn:adm2_name":"Minokamoshi",
    "gn:name":"Ibukachou",
    "iso:country":"JP",
    "wof:name":"505-0008",
    "wof:placetype":"postalcode"
},
  "geometry": {"coordinates":[137.0061,35.5036],"type":"Point"}
}