{
  "type": "Feature",
  "properties": {
    "gn:adm1_name":"Naganoken",
    "gn:adm2_name":"Shimoinaguntakagimura",
    "gn:name":"Tomida",
    "iso:country":"JP",
    "wof:name":"395-1106",
    "wof:placetype":"postalcode"
},
  "geometry": {"coordinates":[137.8854,35.4842],"type":"Point"}
}