{
  "type": "Feature",
  "properties": {
    "gn:adm1_name":"Fukushimaken",
    "gn:adm2_name":"Dategunhobaramachi",
    "gn:name":"Kubo",
    "iso:country":"JP",
    "wof:name":"960-0602",
    "wof:placetype":"postalcode"
},
  "geometry": {"coordinates":[140.56039999999999,37.8259],"type":"Point"}
}