{
  "type": "Feature",
  "properties": {
    "gn:adm1_name":"Tochigiken",
    "gn:adm2_name":"Mookashi",
    "gn:name":"Kakura",
    "iso:country":"JP",
    "wof:name":"321-4347",
    "wof:placetype":"postalcode"
},
  "geometry": {"coordinates":[139.9563,36.4285],"type":"Point"}
}