{
  "type": "Feature",
  "properties": {
    "gn:adm1_name":"Tochigiken",
    "gn:adm2_name":"Oyamashi",
    "gn:name":"Mukaino",
    "iso:country":"JP",
    "wof:name":"323-0805",
    "wof:placetype":"postalcode"
},
  "geometry": {"coordinates":[139.8595,36.3196],"type":"Point"}
}