{
  "type": "Feature",
  "properties": {
    "gn:adm1_name":"Aichiken",
    "gn:adm2_name":"Handashi",
    "gn:name":"Seishirochou",
    "iso:country":"JP",
    "wof:name":"475-0917",
    "wof:placetype":"postalcode"
},
  "geometry": {"coordinates":[136.91409999999999,34.8983],"type":"Point"}
}