{
  "type": "Feature",
  "properties": {
    "gn:adm1_name":"Oosakafu",
    "gn:adm2_name":"Yaoshi",
    "gn:name":"Chiduka",
    "iso:country":"JP",
    "wof:name":"581-0862",
    "wof:placetype":"postalcode"
},
  "geometry": {"coordinates":[135.63929999999999,34.6323],"type":"Point"}
}