{
  "type": "Feature",
  "properties": {
    "gn:adm1_name":"Ishikawaken",
    "gn:adm2_name":"Fugeshigun'Anamizumachi",
    "gn:name":"Nakaiminami",
    "iso:country":"JP",
    "wof:name":"927-0016",
    "wof:placetype":"postalcode"
},
  "geometry": {"coordinates":[136.94380000000001,37.2303],"type":"Point"}
}