{
  "type": "Feature",
  "properties": {
    "gn:adm1_name":"Kagoshimaken",
    "gn:adm2_name":"Ooshimaguntokunoshimachou",
    "gn:name":"Kaminomine",
    "iso:country":"JP",
    "wof:name":"891-7113",
    "wof:placetype":"postalcode"
},
  "geometry": {"coordinates":[129.0274,27.7717],"type":"Point"}
}