{
  "type": "Feature",
  "properties": {
    "gn:adm1_name":"Toyamaken",
    "gn:adm2_name":"Oyabeshi",
    "gn:name":"Ujishin",
    "iso:country":"JP",
    "wof:name":"932-0036",
    "wof:placetype":"postalcode"
},
  "geometry": {"coordinates":[136.8887,36.689],"type":"Point"}
}