{
  "type": "Feature",
  "properties": {
    "gn:adm1_name":"Nagasakiken",
    "gn:adm2_name":"Ikigun'Ashibechou",
    "gn:name":"Fukaesakaefure",
    "iso:country":"JP",
    "wof:name":"811-5321",
    "wof:placetype":"postalcode"
},
  "geometry": {"coordinates":[129.74780000000001,33.7689],"type":"Point"}
}