{
  "type": "Feature",
  "properties": {
    "gn:adm1_name":"Oosakafu",
    "gn:adm2_name":"Habikinoshi",
    "gn:name":"Hirose",
    "iso:country":"JP",
    "wof:name":"583-0845",
    "wof:placetype":"postalcode"
},
  "geometry": {"coordinates":[135.61529999999999,34.5303],"type":"Point"}
}