{
  "type": "Feature",
  "properties": {
    "gn:adm1_name":"Hiroshimaken",
    "gn:adm2_name":"Higashihiroshimashi",
    "gn:name":"Kagamiyamakita",
    "iso:country":"JP",
    "wof:name":"739-0045",
    "wof:placetype":"postalcode"
},
  "geometry": {"coordinates":[132.7199,34.407],"type":"Point"}
}