{
  "type": "Feature",
  "properties": {
    "gn:adm1_name":"Niigataken",
    "gn:adm2_name":"Kashiwazakishi",
    "gn:name":"Asahigaoka",
    "iso:country":"JP",
    "wof:name":"945-0814",
    "wof:placetype":"postalcode"
},
  "geometry": {"coordinates":[138.57409999999999,37.3518],"type":"Point"}
}