{
  "type": "Feature",
  "properties": {
    "gn:adm1_name":"Yamagataken",
    "gn:adm2_name":"Yonezawashi",
    "gn:name":"Misawa",
    "iso:country":"JP",
    "wof:name":"992-1202",
    "wof:placetype":"postalcode"
},
  "geometry": {"coordinates":[140.1431,37.8777],"type":"Point"}
}