{
  "type": "Feature",
  "properties": {
    "gn:adm1_name":"Kouchiken",
    "gn:adm2_name":"Nagaokagun'Ootoyochou",
    "gn:name":"Nishigawa",
    "iso:country":"JP",
    "wof:name":"789-0165",
    "wof:placetype":"postalcode"
},
  "geometry": {"coordinates":[133.7698,33.7865],"type":"Point"}
}