{
  "type": "Feature",
  "properties": {
    "gn:adm1_name":"Miyazakiken",
    "gn:adm2_name":"Miyazakishi",
    "gn:name":"Tanigawachou",
    "iso:country":"JP",
    "wof:name":"880-0909",
    "wof:placetype":"postalcode"
},
  "geometry": {"coordinates":[131.4102,31.9051],"type":"Point"}
}