{
  "type": "Feature",
  "properties": {
    "gn:adm1_name":"Naraken",
    "gn:adm2_name":"Sakuraishi",
    "gn:name":"Takata",
    "iso:country":"JP",
    "wof:name":"633-0043",
    "wof:placetype":"postalcode"
},
  "geometry": {"coordinates":[135.8467,34.497],"type":"Point"}
}