{
  "type": "Feature",
  "properties": {
    "gn:adm1_name":"Naraken",
    "gn:adm2_name":"Narashi",
    "gn:name":"Sakaharachou",
    "iso:country":"JP",
    "wof:name":"630-1241",
    "wof:placetype":"postalcode"
},
  "geometry": {"coordinates":[135.9402,34.7202],"type":"Point"}
}