{
  "type": "Feature",
  "properties": {
    "gn:adm1_name":"Miyagiken",
    "gn:adm2_name":"Kesennumashi",
    "gn:name":"Shimoyatsuse",
    "iso:country":"JP",
    "wof:name":"988-0851",
    "wof:placetype":"postalcode"
},
  "geometry": {"coordinates":[141.5155,38.9216],"type":"Point"}
}