{
  "type": "Feature",
  "properties": {
    "gn:adm1_name":"Toukyouto",
    "gn:adm2_name":"Koganeishi",
    "gn:name":"Honchou",
    "iso:country":"JP",
    "wof:name":"184-0004",
    "wof:placetype":"postalcode"
},
  "geometry": {"coordinates":[139.50649999999999,35.7031],"type":"Point"}
}