{
  "type": "Feature",
  "properties": {
    "gn:adm1_name":"Aichiken",
    "gn:adm2_name":"Kounanshi",
    "gn:name":"Higashinochougoumae",
    "iso:country":"JP",
    "wof:name":"483-8421",
    "wof:placetype":"postalcode"
},
  "geometry": {"coordinates":[136.85169999999999,35.3348],"type":"Point"}
}