{
  "type": "Feature",
  "properties": {
    "gn:adm1_name":"Aichiken",
    "gn:adm2_name":"Aichigunnagakutechou",
    "gn:name":"Maeguma",
    "iso:country":"JP",
    "wof:name":"480-1102",
    "wof:placetype":"postalcode"
},
  "geometry": {"coordinates":[137.06569999999999,35.18],"type":"Point"}
}