{
  "type": "Feature",
  "properties": {
    "gn:adm1_name":"Ibarakiken",
    "gn:adm2_name":"Kujigunkanasagoumachi",
    "gn:name":"Iwate",
    "iso:country":"JP",
    "wof:name":"313-0112",
    "wof:placetype":"postalcode"
},
  "geometry": {"coordinates":[140.476,36.5624],"type":"Point"}
}