{
  "type": "Feature",
  "properties": {
    "gn:adm1_name":"Ibarakiken",
    "gn:adm2_name":"Tsukubashi",
    "gn:name":"Aduma",
    "iso:country":"JP",
    "wof:name":"305-0031",
    "wof:placetype":"postalcode"
},
  "geometry": {"coordinates":[140.11240000000001,36.0844],"type":"Point"}
}