{
  "type": "Feature",
  "properties": {
    "gn:adm1_name":"Tottoriken",
    "gn:adm2_name":"Iwamigunkokufuchou",
    "gn:name":"Yamane",
    "iso:country":"JP",
    "wof:name":"680-0133",
    "wof:placetype":"postalcode"
},
  "geometry": {"coordinates":[134.31469999999999,35.4492],"type":"Point"}
}