{
  "type": "Feature",
  "properties": {
    "gn:adm1_name":"Tochigiken",
    "gn:adm2_name":"Shioyaguntakanezawamachi",
    "gn:name":"Hirata",
    "iso:country":"JP",
    "wof:name":"329-1206",
    "wof:placetype":"postalcode"
},
  "geometry": {"coordinates":[140.0309,36.6434],"type":"Point"}
}