{
  "type": "Feature",
  "properties": {
    "gn:adm1_name":"Okayamaken",
    "gn:adm2_name":"Katsutagunnagichou",
    "gn:name":"Toyosawa",
    "iso:country":"JP",
    "wof:name":"708-1323",
    "wof:placetype":"postalcode"
},
  "geometry": {"coordinates":[134.17580000000001,35.1232],"type":"Point"}
}