{
  "type": "Feature",
  "properties": {
    "gn:adm1_name":"Saitamaken",
    "gn:adm2_name":"Tokorozawashi",
    "gn:name":"Kitano",
    "iso:country":"JP",
    "wof:name":"359-1152",
    "wof:placetype":"postalcode"
},
  "geometry": {"coordinates":[139.42679999999999,35.7917],"type":"Point"}
}