{
  "type": "Feature",
  "properties": {
    "gn:adm1_name":"Fukuiken",
    "gn:adm2_name":"Sakaigun'Awarachou",
    "gn:name":"Funatsu",
    "iso:country":"JP",
    "wof:name":"910-4105",
    "wof:placetype":"postalcode"
},
  "geometry": {"coordinates":[136.18960000000001,36.2274],"type":"Point"}
}