{
  "type": "Feature",
  "properties": {
    "gn:adm1_name":"Miyagiken",
    "gn:adm2_name":"Shiogamashi",
    "gn:name":"Fujikura",
    "iso:country":"JP",
    "wof:name":"985-0004",
    "wof:placetype":"postalcode"
},
  "geometry": {"coordinates":[141.02760000000001,38.3267],"type":"Point"}
}