{
  "type": "Feature",
  "properties": {
    "gn:adm1_name":"Gifuken",
    "gn:adm2_name":"Yoshikigunkamiokachou",
    "gn:name":"Wariishi",
    "iso:country":"JP",
    "wof:name":"506-1112",
    "wof:placetype":"postalcode"
},
  "geometry": {"coordinates":[137.28270000000001,36.3661],"type":"Point"}
}