{
  "type": "Feature",
  "properties": {
    "gn:adm1_name":"Yamanashiken",
    "gn:adm2_name":"Higashiyamanashigunmakiokachou",
    "gn:name":"Magidaira",
    "iso:country":"JP",
    "wof:name":"404-0006",
    "wof:placetype":"postalcode"
},
  "geometry": {"coordinates":[138.63929999999999,35.7445],"type":"Point"}
}