{
  "type": "Feature",
  "properties": {
    "gn:adm1_name":"Kagoshimaken",
    "gn:adm2_name":"Kumagegunkamiyakuchou",
    "gn:name":"Yoshida",
    "iso:country":"JP",
    "wof:name":"891-4202",
    "wof:placetype":"postalcode"
},
  "geometry": {"coordinates":[130.4623,30.4326],"type":"Point"}
}