{
  "type": "Feature",
  "properties": {
    "gn:adm1_name":"Hyougoken",
    "gn:adm2_name":"Hikamigunkaibarachou",
    "gn:name":"Ikanikeisaiganaibaai",
    "iso:country":"JP",
    "wof:name":"669-3300",
    "wof:placetype":"postalcode"
},
  "geometry": {"coordinates":[135.0283,35.2306],"type":"Point"}
}