{
  "type": "Feature",
  "properties": {
    "gn:adm1_name":"Hyougoken",
    "gn:adm2_name":"Himejishi",
    "gn:name":"Aboshikutakada",
    "iso:country":"JP",
    "wof:name":"671-1226",
    "wof:placetype":"postalcode"
},
  "geometry": {"coordinates":[134.58150000000001,34.8115],"type":"Point"}
}