{
  "type": "Feature",
  "properties": {
    "gn:adm1_name":"Aichiken",
    "gn:adm2_name":"Toyotashi",
    "gn:name":"Hiromichou",
    "iso:country":"JP",
    "wof:name":"470-1215",
    "wof:placetype":"postalcode"
},
  "geometry": {"coordinates":[137.1172,35.0026],"type":"Point"}
}