{
  "type": "Feature",
  "properties": {
    "gn:adm1_name":"Kumamotoken",
    "gn:adm2_name":"Shimomashikigunmatsubasemachi",
    "gn:name":"Mifune",
    "iso:country":"JP",
    "wof:name":"869-0546",
    "wof:placetype":"postalcode"
},
  "geometry": {"coordinates":[130.6601,32.6271],"type":"Point"}
}