{
  "type": "Feature",
  "properties": {
    "gn:adm1_name":"Gifuken",
    "gn:adm2_name":"Gifushi",
    "gn:name":"Kanouaramachi",
    "iso:country":"JP",
    "wof:name":"500-8422",
    "wof:placetype":"postalcode"
},
  "geometry": {"coordinates":[136.76740000000001,35.4041],"type":"Point"}
}