{
  "type": "Feature",
  "properties": {
    "gn:adm1_name":"Ehimeken",
    "gn:adm2_name":"Oozushi",
    "gn:name":"Takayama",
    "iso:country":"JP",
    "wof:name":"795-0024",
    "wof:placetype":"postalcode"
},
  "geometry": {"coordinates":[132.51859999999999,33.5157],"type":"Point"}
}