{
  "type": "Feature",
  "properties": {
    "gn:adm1_name":"Kumamotoken",
    "gn:adm2_name":"Minamatashi",
    "gn:name":"Tenjinchou",
    "iso:country":"JP",
    "wof:name":"867-0041",
    "wof:placetype":"postalcode"
},
  "geometry": {"coordinates":[130.4058,32.2108],"type":"Point"}
}