{
  "type": "Feature",
  "properties": {
    "gn:adm1_name":"Niigataken",
    "gn:adm2_name":"Gosenshi",
    "gn:name":"Konagashi",
    "iso:country":"JP",
    "wof:name":"959-1613",
    "wof:placetype":"postalcode"
},
  "geometry": {"coordinates":[139.2517,37.7423],"type":"Point"}
}