{
  "type": "Feature",
  "properties": {
    "gn:adm1_name":"Tottoriken",
    "gn:adm2_name":"Kurayoshishi",
    "gn:name":"Fukudumi",
    "iso:country":"JP",
    "wof:name":"682-0644",
    "wof:placetype":"postalcode"
},
  "geometry": {"coordinates":[133.73949999999999,35.4209],"type":"Point"}
}