{
  "type": "Feature",
  "properties": {
    "gn:adm1_name":"Niigataken",
    "gn:adm2_name":"Kitakanbaragunshiunjimachi",
    "gn:name":"Manoharasoto",
    "iso:country":"JP",
    "wof:name":"957-0232",
    "wof:placetype":"postalcode"
},
  "geometry": {"coordinates":[139.3039,38.004],"type":"Point"}
}