{
  "type": "Feature",
  "properties": {
    "gn:adm1_name":"Ooitaken",
    "gn:adm2_name":"Hitagun'Amagasemachi",
    "gn:name":"Akaiwa",
    "iso:country":"JP",
    "wof:name":"879-4202",
    "wof:placetype":"postalcode"
},
  "geometry": {"coordinates":[131.04499999999999,33.2558],"type":"Point"}
}