{
  "type": "Feature",
  "properties": {
    "gn:adm1_name":"Gifuken",
    "gn:adm2_name":"Gifushi",
    "gn:name":"Imojima",
    "iso:country":"JP",
    "wof:name":"500-8234",
    "wof:placetype":"postalcode"
},
  "geometry": {"coordinates":[136.80950000000001,35.3925],"type":"Point"}
}