{
  "type": "Feature",
  "properties": {
    "gn:adm1_name":"Niigataken",
    "gn:adm2_name":"Iwafunegunsanpokumachi",
    "gn:name":"Neya",
    "iso:country":"JP",
    "wof:name":"959-3946",
    "wof:placetype":"postalcode"
},
  "geometry": {"coordinates":[139.51300000000001,38.4865],"type":"Point"}
}