{
  "type": "Feature",
  "properties": {
    "gn:adm1_name":"Hyougoken",
    "gn:adm2_name":"Amagasakishi",
    "gn:name":"Shioe(Sonota)",
    "iso:country":"JP",
    "wof:name":"661-0976",
    "wof:placetype":"postalcode"
},
  "geometry": {"coordinates":[135.43119999999999,34.7366],"type":"Point"}
}