{
  "type": "Feature",
  "properties": {
    "gn:adm1_name":"Hyougoken",
    "gn:adm2_name":"Sayougunsayouchou",
    "gn:name":"Hon'Iden",
    "iso:country":"JP",
    "wof:name":"679-5306",
    "wof:placetype":"postalcode"
},
  "geometry": {"coordinates":[134.3631,35.0203],"type":"Point"}
}