{
  "type": "Feature",
  "properties": {
    "gn:adm1_name":"Okinawaken",
    "gn:adm2_name":"Kunigamigunmotobuchou",
    "gn:name":"Toyohara",
    "iso:country":"JP",
    "wof:name":"905-0204",
    "wof:placetype":"postalcode"
},
  "geometry": {"coordinates":[127.8897,26.688],"type":"Point"}
}