{
  "type": "Feature",
  "properties": {
    "gn:adm1_name":"Miyazakiken",
    "gn:adm2_name":"Saitoshi",
    "gn:name":"Minou",
    "iso:country":"JP",
    "wof:name":"881-0101",
    "wof:placetype":"postalcode"
},
  "geometry": {"coordinates":[131.34950000000001,32.1113],"type":"Point"}
}