{
  "type": "Feature",
  "properties": {
    "gn:adm1_name":"Naganoken",
    "gn:adm2_name":"Komoroshi",
    "gn:name":"Ookubo",
    "iso:country":"JP",
    "wof:name":"384-0071",
    "wof:placetype":"postalcode"
},
  "geometry": {"coordinates":[138.39330000000001,36.3251],"type":"Point"}
}