{
  "type": "Feature",
  "properties": {
    "gn:adm1_name":"Mieken",
    "gn:adm2_name":"Suzukashi",
    "gn:name":"Yasudukachou",
    "iso:country":"JP",
    "wof:name":"513-0818",
    "wof:placetype":"postalcode"
},
  "geometry": {"coordinates":[136.5745,34.8672],"type":"Point"}
}