{
  "type": "Feature",
  "properties": {
    "gn:adm1_name":"Shigaken",
    "gn:adm2_name":"Ikagunkinomotochou",
    "gn:name":"Sugimoto",
    "iso:country":"JP",
    "wof:name":"529-0404",
    "wof:placetype":"postalcode"
},
  "geometry": {"coordinates":[136.25149999999999,35.5578],"type":"Point"}
}