{
  "type": "Feature",
  "properties": {
    "gn:adm1_name":"Aichiken",
    "gn:adm2_name":"Bisaishi",
    "gn:name":"Kitaima",
    "iso:country":"JP",
    "wof:name":"494-0004",
    "wof:placetype":"postalcode"
},
  "geometry": {"coordinates":[136.7559,35.295],"type":"Point"}
}