{
  "type": "Feature",
  "properties": {
    "gn:adm1_name":"Niigataken",
    "gn:adm2_name":"Iwafunegun'Asahimura",
    "gn:name":"Kuroda",
    "iso:country":"JP",
    "wof:name":"958-0224",
    "wof:placetype":"postalcode"
},
  "geometry": {"coordinates":[139.54990000000001,38.2905],"type":"Point"}
}