{
  "type": "Feature",
  "properties": {
    "gn:adm1_name":"Yamaguchiken",
    "gn:adm2_name":"Yamaguchishi",
    "gn:name":"Yabarachou",
    "iso:country":"JP",
    "wof:name":"753-0825",
    "wof:placetype":"postalcode"
},
  "geometry": {"coordinates":[131.45070000000001,34.1555],"type":"Point"}
}