{
  "type": "Feature",
  "properties": {
    "gn:adm1_name":"Niigataken",
    "gn:adm2_name":"Kitakanbaragunnakajoumachi",
    "gn:name":"Higashihonchou",
    "iso:country":"JP",
    "wof:name":"959-2643",
    "wof:placetype":"postalcode"
},
  "geometry": {"coordinates":[139.40819999999999,38.0558],"type":"Point"}
}