{
  "type": "Feature",
  "properties": {
    "gn:adm1_name":"Hyougoken",
    "gn:adm2_name":"Takaradukashi",
    "gn:name":"Akurakita",
    "iso:country":"JP",
    "wof:name":"665-0821",
    "wof:placetype":"postalcode"
},
  "geometry": {"coordinates":[135.37100000000001,34.8057],"type":"Point"}
}