{
  "type": "Feature",
  "properties": {
    "gn:adm1_name":"Miyagiken",
    "gn:adm2_name":"Shibatagunshibatamachi",
    "gn:name":"Kamikawana",
    "iso:country":"JP",
    "wof:name":"989-1742",
    "wof:placetype":"postalcode"
},
  "geometry": {"coordinates":[140.81360000000001,38.0999],"type":"Point"}
}