{
  "type": "Feature",
  "properties": {
    "gn:adm1_name":"Gifuken",
    "gn:adm2_name":"Yoshikigunmiyagawamura",
    "gn:name":"Sugihara",
    "iso:country":"JP",
    "wof:name":"509-4542",
    "wof:placetype":"postalcode"
},
  "geometry": {"coordinates":[137.1908,36.4147],"type":"Point"}
}