{
  "type": "Feature",
  "properties": {
    "gn:adm1_name":"Aichiken",
    "gn:adm2_name":"Toyohashishi",
    "gn:name":"Miyashitachou",
    "iso:country":"JP",
    "wof:name":"440-0044",
    "wof:placetype":"postalcode"
},
  "geometry": {"coordinates":[137.41730000000001,34.7607],"type":"Point"}
}