{
  "type": "Feature",
  "properties": {
    "gn:adm1_name":"Gifuken",
    "gn:adm2_name":"Gifushi",
    "gn:name":"Furuichibajinden",
    "iso:country":"JP",
    "wof:name":"501-1127",
    "wof:placetype":"postalcode"
},
  "geometry": {"coordinates":[136.7311,35.4625],"type":"Point"}
}