{
  "type": "Feature",
  "properties": {
    "gn:adm1_name":"Okayamaken",
    "gn:adm2_name":"Atetsuguntesseichou",
    "gn:name":"Kamikoujiro",
    "iso:country":"JP",
    "wof:name":"719-3702",
    "wof:placetype":"postalcode"
},
  "geometry": {"coordinates":[133.33930000000001,34.9625],"type":"Point"}
}