{
  "type": "Feature",
  "properties": {
    "gn:adm1_name":"Gunmaken",
    "gn:adm2_name":"Numatashi",
    "gn:name":"Boushindenmachi",
    "iso:country":"JP",
    "wof:name":"378-0017",
    "wof:placetype":"postalcode"
},
  "geometry": {"coordinates":[139.04580000000001,36.6419],"type":"Point"}
}