{
  "type": "Feature",
  "properties": {
    "gn:adm1_name":"Naganoken",
    "gn:adm2_name":"Kamiinagunnakagawamura",
    "gn:name":"Ikanikeisaiganaibaai",
    "iso:country":"JP",
    "wof:name":"399-3800",
    "wof:placetype":"postalcode"
},
  "geometry": {"coordinates":[137.93610000000001,35.6315],"type":"Point"}
}