{
  "type": "Feature",
  "properties": {
    "gn:adm1_name":"Gifuken",
    "gn:adm2_name":"Yourougunyourouchou",
    "gn:name":"Ta",
    "iso:country":"JP",
    "wof:name":"503-1271",
    "wof:placetype":"postalcode"
},
  "geometry": {"coordinates":[136.5797,35.2724],"type":"Point"}
}