{
  "type": "Feature",
  "properties": {
    "gn:adm1_name":"Toukyouto",
    "gn:adm2_name":"Fuchuushi",
    "gn:name":"Tenjinchou",
    "iso:country":"JP",
    "wof:name":"183-0053",
    "wof:placetype":"postalcode"
},
  "geometry": {"coordinates":[139.49029999999999,35.6818],"type":"Point"}
}