{
  "type": "Feature",
  "properties": {
    "gn:adm1_name":"Kyoutofu",
    "gn:adm2_name":"Kyoutoshisakyouku",
    "gn:name":"Iwakuraminamimiyakechou",
    "iso:country":"JP",
    "wof:name":"606-0023",
    "wof:placetype":"postalcode"
},
  "geometry": {"coordinates":[135.78970000000001,35.0654],"type":"Point"}
}