{
  "type": "Feature",
  "properties": {
    "gn:adm1_name":"Fukuokaken",
    "gn:adm2_name":"Mizumagun'Ookimachi",
    "gn:name":"Hacchoumuta",
    "iso:country":"JP",
    "wof:name":"830-0416",
    "wof:placetype":"postalcode"
},
  "geometry": {"coordinates":[130.43459999999999,33.2094],"type":"Point"}
}