{
  "type": "Feature",
  "properties": {
    "gn:adm1_name":"Tottoriken",
    "gn:adm2_name":"Tottorishi",
    "gn:name":"Akisato",
    "iso:country":"JP",
    "wof:name":"680-0902",
    "wof:placetype":"postalcode"
},
  "geometry": {"coordinates":[134.2131,35.5183],"type":"Point"}
}