{
  "type": "Feature",
  "properties": {
    "gn:adm1_name":"Miyagiken",
    "gn:adm2_name":"Kesennumashi",
    "gn:name":"Shinden",
    "iso:country":"JP",
    "wof:name":"988-0829",
    "wof:placetype":"postalcode"
},
  "geometry": {"coordinates":[141.5496,38.9113],"type":"Point"}
}