{
  "type": "Feature",
  "properties": {
    "gn:adm1_name":"Naraken",
    "gn:adm2_name":"Yoshinogun'Ootoumura",
    "gn:name":"Sudare",
    "iso:country":"JP",
    "wof:name":"637-0419",
    "wof:placetype":"postalcode"
},
  "geometry": {"coordinates":[135.74260000000001,34.2247],"type":"Point"}
}