{
  "type": "Feature",
  "properties": {
    "gn:adm1_name":"Toyamaken",
    "gn:adm2_name":"Toyamashi",
    "gn:name":"Minamikuriyama",
    "iso:country":"JP",
    "wof:name":"939-8176",
    "wof:placetype":"postalcode"
},
  "geometry": {"coordinates":[137.2045,36.6193],"type":"Point"}
}