{
  "type": "Feature",
  "properties": {
    "gn:adm1_name":"Nagasakiken",
    "gn:adm2_name":"Higashisonogigunhasamichou",
    "gn:name":"Nagaogou",
    "iso:country":"JP",
    "wof:name":"859-3705",
    "wof:placetype":"postalcode"
},
  "geometry": {"coordinates":[129.94210000000001,33.1305],"type":"Point"}
}