{
  "type": "Feature",
  "properties": {
    "gn:adm1_name":"Shizuokaken",
    "gn:adm2_name":"Susonoshi",
    "gn:name":"Suyama",
    "iso:country":"JP",
    "wof:name":"410-1231",
    "wof:placetype":"postalcode"
},
  "geometry": {"coordinates":[138.83949999999999,35.2543],"type":"Point"}
}