{
  "type": "Feature",
  "properties": {
    "gn:adm1_name":"Kagoshimaken",
    "gn:adm2_name":"Kumagegunkamiyakuchou",
    "gn:name":"Shitogo",
    "iso:country":"JP",
    "wof:name":"891-4204",
    "wof:placetype":"postalcode"
},
  "geometry": {"coordinates":[130.51910000000001,30.4477],"type":"Point"}
}