{
  "type": "Feature",
  "properties": {
    "gn:adm1_name":"Miyagiken",
    "gn:adm2_name":"Kamigunkamimachi",
    "gn:name":"Kitashimohara",
    "iso:country":"JP",
    "wof:name":"981-4322",
    "wof:placetype":"postalcode"
},
  "geometry": {"coordinates":[140.786,38.5763],"type":"Point"}
}