{
  "type": "Feature",
  "properties": {
    "gn:adm1_name":"Chibaken",
    "gn:adm2_name":"Chouseigunshirakomachi",
    "gn:name":"Odoroki",
    "iso:country":"JP",
    "wof:name":"299-4214",
    "wof:placetype":"postalcode"
},
  "geometry": {"coordinates":[140.38669999999999,35.436],"type":"Point"}
}