{
  "type": "Feature",
  "properties": {
    "gn:adm1_name":"Wakayamaken",
    "gn:adm2_name":"Kaisougunshimotsuchou",
    "gn:name":"Ichitsubo",
    "iso:country":"JP",
    "wof:name":"649-0145",
    "wof:placetype":"postalcode"
},
  "geometry": {"coordinates":[135.19550000000001,34.1169],"type":"Point"}
}