{
  "type": "Feature",
  "properties": {
    "gn:adm1_name":"Gifuken",
    "gn:adm2_name":"Mashitagungerochou",
    "gn:name":"Kadowasa",
    "iso:country":"JP",
    "wof:name":"509-2424",
    "wof:placetype":"postalcode"
},
  "geometry": {"coordinates":[137.285,35.7078],"type":"Point"}
}