{
  "type": "Feature",
  "properties": {
    "gn:adm1_name":"Naraken",
    "gn:adm2_name":"Narashi",
    "gn:name":"Utahimechou",
    "iso:country":"JP",
    "wof:name":"631-0802",
    "wof:placetype":"postalcode"
},
  "geometry": {"coordinates":[135.7963,34.7037],"type":"Point"}
}