{
  "type": "Feature",
  "properties": {
    "gn:adm1_name":"Mieken",
    "gn:adm2_name":"Inabeguntouinchou",
    "gn:name":"Nakagami",
    "iso:country":"JP",
    "wof:name":"511-0254",
    "wof:placetype":"postalcode"
},
  "geometry": {"coordinates":[136.5967,35.0561],"type":"Point"}
}