{
  "type": "Feature",
  "properties": {
    "gn:adm1_name":"Toyamaken",
    "gn:adm2_name":"Nakaniikawaguntateyamamachi",
    "gn:name":"Zashubou",
    "iso:country":"JP",
    "wof:name":"930-3238",
    "wof:placetype":"postalcode"
},
  "geometry": {"coordinates":[137.37350000000001,36.5982],"type":"Point"}
}