{
  "type": "Feature",
  "properties": {
    "gn:adm1_name":"Mieken",
    "gn:adm2_name":"Ayamagun'Ayamachou",
    "gn:name":"Nishiyubune",
    "iso:country":"JP",
    "wof:name":"518-1301",
    "wof:placetype":"postalcode"
},
  "geometry": {"coordinates":[136.19210000000001,34.8635],"type":"Point"}
}