{
  "type": "Feature",
  "properties": {
    "gn:adm1_name":"Ooitaken",
    "gn:adm2_name":"Oonogunmiemachi",
    "gn:name":"Matsuo",
    "iso:country":"JP",
    "wof:name":"879-7123",
    "wof:placetype":"postalcode"
},
  "geometry": {"coordinates":[131.61369999999999,32.9673],"type":"Point"}
}