{
  "type": "Feature",
  "properties": {
    "gn:adm1_name":"Toyamaken",
    "gn:adm2_name":"Toyamashi",
    "gn:name":"Hoshiichou",
    "iso:country":"JP",
    "wof:name":"930-0065",
    "wof:placetype":"postalcode"
},
  "geometry": {"coordinates":[137.2133,36.6846],"type":"Point"}
}