{
  "type": "Feature",
  "properties": {
    "gn:adm1_name":"Toukyouto",
    "gn:adm2_name":"Shibuyaku",
    "gn:name":"Sarugakuchou",
    "iso:country":"JP",
    "wof:name":"150-0033",
    "wof:placetype":"postalcode"
},
  "geometry": {"coordinates":[139.702,35.6501],"type":"Point"}
}