{
  "type": "Feature",
  "properties": {
    "gn:adm1_name":"Wakayamaken",
    "gn:adm2_name":"Kaisougunnokamichou",
    "gn:name":"Umemoto",
    "iso:country":"JP",
    "wof:name":"640-1113",
    "wof:placetype":"postalcode"
},
  "geometry": {"coordinates":[135.3289,34.1251],"type":"Point"}
}