{
  "type": "Feature",
  "properties": {
    "gn:adm1_name":"Yamaguchiken",
    "gn:adm2_name":"Shuunanshi",
    "gn:name":"Akiduki",
    "iso:country":"JP",
    "wof:name":"745-0825",
    "wof:placetype":"postalcode"
},
  "geometry": {"coordinates":[131.8297,34.0571],"type":"Point"}
}