{
  "type": "Feature",
  "properties": {
    "gn:adm1_name":"Miyagiken",
    "gn:adm2_name":"Ishinomakishi",
    "gn:name":"Nishiyamachou",
    "iso:country":"JP",
    "wof:name":"986-0876",
    "wof:placetype":"postalcode"
},
  "geometry": {"coordinates":[141.29249999999999,38.4344],"type":"Point"}
}