{
  "type": "Feature",
  "properties": {
    "gn:adm1_name":"Okayamaken",
    "gn:adm2_name":"Aidagun'Aidachou",
    "gn:name":"Minami",
    "iso:country":"JP",
    "wof:name":"701-2616",
    "wof:placetype":"postalcode"
},
  "geometry": {"coordinates":[134.1849,34.9192],"type":"Point"}
}