{
  "type": "Feature",
  "properties": {
    "gn:adm1_name":"Gifuken",
    "gn:adm2_name":"Sekishi",
    "gn:name":"Ikanikeisaiganaibaai",
    "iso:country":"JP",
    "wof:name":"501-3200",
    "wof:placetype":"postalcode"
},
  "geometry": {"coordinates":[136.92509999999999,35.4809],"type":"Point"}
}