{
  "type": "Feature",
  "properties": {
    "gn:adm1_name":"Yamanashiken",
    "gn:adm2_name":"Koufushi",
    "gn:name":"Nishitakahashichou",
    "iso:country":"JP",
    "wof:name":"400-0826",
    "wof:placetype":"postalcode"
},
  "geometry": {"coordinates":[138.59870000000001,35.6403],"type":"Point"}
}