{
  "type": "Feature",
  "properties": {
    "gn:adm1_name":"Okayamaken",
    "gn:adm2_name":"Aidagunmimasakachou",
    "gn:name":"Iden",
    "iso:country":"JP",
    "wof:name":"707-0052",
    "wof:placetype":"postalcode"
},
  "geometry": {"coordinates":[134.12139999999999,34.9826],"type":"Point"}
}