{
  "type": "Feature",
  "properties": {
    "gn:adm1_name":"Hiroshimaken",
    "gn:adm2_name":"Jinsekigunsanwachou",
    "gn:name":"Tokiyasu",
    "iso:country":"JP",
    "wof:name":"720-1603",
    "wof:placetype":"postalcode"
},
  "geometry": {"coordinates":[133.3254,34.6918],"type":"Point"}
}