{
  "type": "Feature",
  "properties": {
    "gn:adm1_name":"Ishikawaken",
    "gn:adm2_name":"Komatsushi",
    "gn:name":"Furukawamachi",
    "iso:country":"JP",
    "wof:name":"923-0944",
    "wof:placetype":"postalcode"
},
  "geometry": {"coordinates":[136.44229999999999,36.4037],"type":"Point"}
}