{
  "type": "Feature",
  "properties": {
    "gn:adm1_name":"Ibarakiken",
    "gn:adm2_name":"Yuukigunyachiyomachi",
    "gn:name":"Ashigayashinden",
    "iso:country":"JP",
    "wof:name":"300-3556",
    "wof:placetype":"postalcode"
},
  "geometry": {"coordinates":[139.8904,36.1321],"type":"Point"}
}