{
  "type": "Feature",
  "properties": {
    "gn:adm1_name":"Hyougoken",
    "gn:adm2_name":"Katouguntakinochou",
    "gn:name":"Sakuradai",
    "iso:country":"JP",
    "wof:name":"679-0223",
    "wof:placetype":"postalcode"
},
  "geometry": {"coordinates":[134.9161,34.9136],"type":"Point"}
}