{
  "type": "Feature",
  "properties": {
    "gn:adm1_name":"Tochigiken",
    "gn:adm2_name":"Mookashi",
    "gn:name":"Wakatabi(Sonota)",
    "iso:country":"JP",
    "wof:name":"321-4352",
    "wof:placetype":"postalcode"
},
  "geometry": {"coordinates":[139.94999999999999,36.4001],"type":"Point"}
}