{
  "type": "Feature",
  "properties": {
    "gn:adm1_name":"Tochigiken",
    "gn:adm2_name":"Shioyagun'Ujiiemachi",
    "gn:name":"Baba",
    "iso:country":"JP",
    "wof:name":"329-1321",
    "wof:placetype":"postalcode"
},
  "geometry": {"coordinates":[139.95769999999999,36.6922],"type":"Point"}
}