{
  "type": "Feature",
  "properties": {
    "gn:adm1_name":"Fukuokaken",
    "gn:adm2_name":"Maebarushi",
    "gn:name":"Zuibaiji",
    "iso:country":"JP",
    "wof:name":"819-1581",
    "wof:placetype":"postalcode"
},
  "geometry": {"coordinates":[130.2457,33.5063],"type":"Point"}
}