{
  "type": "Feature",
  "properties": {
    "gn:adm1_name":"Aichiken",
    "gn:adm2_name":"Nagoyashiatsutaku",
    "gn:name":"Sawakami",
    "iso:country":"JP",
    "wof:name":"456-0012",
    "wof:placetype":"postalcode"
},
  "geometry": {"coordinates":[136.904,35.1387],"type":"Point"}
}