{
  "type": "Feature",
  "properties": {
    "gn:adm1_name":"Gifuken",
    "gn:adm2_name":"Gifushi",
    "gn:name":"Gomo",
    "iso:country":"JP",
    "wof:name":"501-1171",
    "wof:placetype":"postalcode"
},
  "geometry": {"coordinates":[136.70779999999999,35.4736],"type":"Point"}
}