{
  "type": "Feature",
  "properties": {
    "gn:adm1_name":"Hiroshimaken",
    "gn:adm2_name":"Fukuyamashi",
    "gn:name":"Kinoshouchou",
    "iso:country":"JP",
    "wof:name":"720-0082",
    "wof:placetype":"postalcode"
},
  "geometry": {"coordinates":[133.3562,34.4975],"type":"Point"}
}