{
  "type": "Feature",
  "properties": {
    "gn:adm1_name":"Kagoshimaken",
    "gn:adm2_name":"Kimotsukigunkouyamachou",
    "gn:name":"Maeda",
    "iso:country":"JP",
    "wof:name":"893-1206",
    "wof:placetype":"postalcode"
},
  "geometry": {"coordinates":[130.93979999999999,31.3449],"type":"Point"}
}