{
  "type": "Feature",
  "properties": {
    "gn:adm1_name":"Kyoutofu",
    "gn:adm2_name":"Nakagunmineyamachou",
    "gn:name":"Fudan",
    "iso:country":"JP",
    "wof:name":"627-0013",
    "wof:placetype":"postalcode"
},
  "geometry": {"coordinates":[135.05680000000001,35.6299],"type":"Point"}
}