{
  "type": "Feature",
  "properties": {
    "gn:adm1_name":"Kanagawaken",
    "gn:adm2_name":"Nakagun'Ooisomachi",
    "gn:name":"Ooiso",
    "iso:country":"JP",
    "wof:name":"255-0003",
    "wof:placetype":"postalcode"
},
  "geometry": {"coordinates":[139.31710000000001,35.3116],"type":"Point"}
}