{
  "type": "Feature",
  "properties": {
    "gn:adm1_name":"Okayamaken",
    "gn:adm2_name":"Akaiwagun'Akasakachou",
    "gn:name":"Soubun",
    "iso:country":"JP",
    "wof:name":"701-2203",
    "wof:placetype":"postalcode"
},
  "geometry": {"coordinates":[134.01900000000001,34.8449],"type":"Point"}
}