{
  "type": "Feature",
  "properties": {
    "gn:adm1_name":"Toukyouto",
    "gn:adm2_name":"Akishimashi",
    "gn:name":"Mihorichou",
    "iso:country":"JP",
    "wof:name":"196-0001",
    "wof:placetype":"postalcode"
},
  "geometry": {"coordinates":[139.357,35.7224],"type":"Point"}
}