{
  "type": "Feature",
  "properties": {
    "gn:adm1_name":"Kagawaken",
    "gn:adm2_name":"Sakaideshi",
    "gn:name":"Shouwachou",
    "iso:country":"JP",
    "wof:name":"762-0004",
    "wof:placetype":"postalcode"
},
  "geometry": {"coordinates":[133.86420000000001,34.3244],"type":"Point"}
}