{
  "type": "Feature",
  "properties": {
    "gn:adm1_name":"Kumamotoken",
    "gn:adm2_name":"Ashikitagun'Ashikitamachi",
    "gn:name":"Tsuge",
    "iso:country":"JP",
    "wof:name":"869-6303",
    "wof:placetype":"postalcode"
},
  "geometry": {"coordinates":[130.59479999999999,32.2725],"type":"Point"}
}