{
  "type": "Feature",
  "properties": {
    "gn:adm1_name":"Ehimeken",
    "gn:adm2_name":"Uwajimashi",
    "gn:name":"Wareimotomachi",
    "iso:country":"JP",
    "wof:name":"798-0015",
    "wof:placetype":"postalcode"
},
  "geometry": {"coordinates":[132.5676,33.228],"type":"Point"}
}