{
  "type": "Feature",
  "properties": {
    "gn:adm1_name":"Aichiken",
    "gn:adm2_name":"Handashi",
    "gn:name":"Higashiooyachichou",
    "iso:country":"JP",
    "wof:name":"475-0003",
    "wof:placetype":"postalcode"
},
  "geometry": {"coordinates":[136.9461,34.9311],"type":"Point"}
}