{
  "type": "Feature",
  "properties": {
    "gn:adm1_name":"Aichiken",
    "gn:adm2_name":"Setoshi",
    "gn:name":"Magotachou",
    "iso:country":"JP",
    "wof:name":"489-0914",
    "wof:placetype":"postalcode"
},
  "geometry": {"coordinates":[137.07669999999999,35.2241],"type":"Point"}
}