{
  "type": "Feature",
  "properties": {
    "gn:adm1_name":"Chibaken",
    "gn:adm2_name":"Choushishi",
    "gn:name":"Uematsuchou",
    "iso:country":"JP",
    "wof:name":"288-0071",
    "wof:placetype":"postalcode"
},
  "geometry": {"coordinates":[140.85149999999999,35.7358],"type":"Point"}
}