{
  "type": "Feature",
  "properties": {
    "gn:adm1_name":"Shimaneken",
    "gn:adm2_name":"Hamadashi",
    "gn:name":"Tsumachou",
    "iso:country":"JP",
    "wof:name":"697-1327",
    "wof:placetype":"postalcode"
},
  "geometry": {"coordinates":[132.0147,34.8611],"type":"Point"}
}