{
  "type": "Feature",
  "properties": {
    "gn:adm1_name":"Aichiken",
    "gn:adm2_name":"Okazakishi",
    "gn:name":"Tatsumidai",
    "iso:country":"JP",
    "wof:name":"444-0873",
    "wof:placetype":"postalcode"
},
  "geometry": {"coordinates":[137.17859999999999,34.9366],"type":"Point"}
}