{
  "type": "Feature",
  "properties": {
    "gn:adm1_name":"Shizuokaken",
    "gn:adm2_name":"Haibaragunkanayachou",
    "gn:name":"Kanayakawara",
    "iso:country":"JP",
    "wof:name":"428-0021",
    "wof:placetype":"postalcode"
},
  "geometry": {"coordinates":[138.1318,34.8291],"type":"Point"}
}