{
  "type": "Feature",
  "properties": {
    "gn:adm1_name":"Miyagiken",
    "gn:adm2_name":"Kuriharaguntsukidatechou",
    "gn:name":"Tateshita",
    "iso:country":"JP",
    "wof:name":"987-2241",
    "wof:placetype":"postalcode"
},
  "geometry": {"coordinates":[141.01159999999999,38.7278],"type":"Point"}
}