{
  "type": "Feature",
  "properties": {
    "gn:adm1_name":"Kyoutofu",
    "gn:adm2_name":"Kusegunkumiyamachou",
    "gn:name":"Fujiwada",
    "iso:country":"JP",
    "wof:name":"613-0044",
    "wof:placetype":"postalcode"
},
  "geometry": {"coordinates":[135.72200000000001,34.8903],"type":"Point"}
}