{
  "type": "Feature",
  "properties": {
    "gn:adm1_name":"Saitamaken",
    "gn:adm2_name":"Kawagoeshi",
    "gn:name":"Kawagoe",
    "iso:country":"JP",
    "wof:name":"350-0852",
    "wof:placetype":"postalcode"
},
  "geometry": {"coordinates":[139.50380000000001,35.9318],"type":"Point"}
}