{
  "type": "Feature",
  "properties": {
    "gn:adm1_name":"Kouchiken",
    "gn:adm2_name":"Akishi",
    "gn:name":"Nishihama",
    "iso:country":"JP",
    "wof:name":"784-0020",
    "wof:placetype":"postalcode"
},
  "geometry": {"coordinates":[133.88929999999999,33.5051],"type":"Point"}
}