{
  "type": "Feature",
  "properties": {
    "gn:adm1_name":"Shizuokaken",
    "gn:adm2_name":"Hamamatsushi",
    "gn:name":"Ooyagichou",
    "iso:country":"JP",
    "wof:name":"430-0842",
    "wof:placetype":"postalcode"
},
  "geometry": {"coordinates":[137.7587,34.6786],"type":"Point"}
}