{
  "type": "Feature",
  "properties": {
    "gn:adm1_name":"Yamanashiken",
    "gn:adm2_name":"Ootsukishi",
    "gn:name":"Nigiokamachiiwadono",
    "iso:country":"JP",
    "wof:name":"401-0002",
    "wof:placetype":"postalcode"
},
  "geometry": {"coordinates":[138.9571,35.622],"type":"Point"}
}