{
  "type": "Feature",
  "properties": {
    "gn:adm1_name":"Ehimeken",
    "gn:adm2_name":"Ochigunhakatachou",
    "gn:name":"Kitaura",
    "iso:country":"JP",
    "wof:name":"794-2304",
    "wof:placetype":"postalcode"
},
  "geometry": {"coordinates":[133.0977,34.2275],"type":"Point"}
}