{
  "type": "Feature",
  "properties": {
    "gn:adm1_name":"Ibarakiken",
    "gn:adm2_name":"Hitachishi",
    "gn:name":"Higashitagachou",
    "iso:country":"JP",
    "wof:name":"316-0004",
    "wof:placetype":"postalcode"
},
  "geometry": {"coordinates":[140.63319999999999,36.547],"type":"Point"}
}