{
  "type": "Feature",
  "properties": {
    "gn:adm1_name":"Ibarakiken",
    "gn:adm2_name":"Itakoshi",
    "gn:name":"Magarimatsu",
    "iso:country":"JP",
    "wof:name":"311-2447",
    "wof:placetype":"postalcode"
},
  "geometry": {"coordinates":[140.5703,35.9512],"type":"Point"}
}