{
  "type": "Feature",
  "properties": {
    "gn:adm1_name":"Tochigiken",
    "gn:adm2_name":"Tochigishi",
    "gn:name":"Fujitamachi",
    "iso:country":"JP",
    "wof:name":"328-0026",
    "wof:placetype":"postalcode"
},
  "geometry": {"coordinates":[139.7636,36.3715],"type":"Point"}
}