{
  "type": "Feature",
  "properties": {
    "gn:adm1_name":"Aichiken",
    "gn:adm2_name":"Nishikasugaigunnishibiwajimachou",
    "gn:name":"Kobaduka",
    "iso:country":"JP",
    "wof:name":"452-0061",
    "wof:placetype":"postalcode"
},
  "geometry": {"coordinates":[136.8571,35.2019],"type":"Point"}
}