{
  "type": "Feature",
  "properties": {
    "gn:adm1_name":"Okayamaken",
    "gn:adm2_name":"Okayamashi",
    "gn:name":"Shijou",
    "iso:country":"JP",
    "wof:name":"702-8052",
    "wof:placetype":"postalcode"
},
  "geometry": {"coordinates":[133.94579999999999,34.6013],"type":"Point"}
}