{
  "type": "Feature",
  "properties": {
    "gn:adm1_name":"Tochigiken",
    "gn:adm2_name":"Utsunomiyashi",
    "gn:name":"Babadoori",
    "iso:country":"JP",
    "wof:name":"320-0026",
    "wof:placetype":"postalcode"
},
  "geometry": {"coordinates":[139.8861,36.5611],"type":"Point"}
}