{
  "type": "Feature",
  "properties": {
    "gn:adm1_name":"Ibarakiken",
    "gn:adm2_name":"Mitoshi",
    "gn:name":"Wakamiyachou",
    "iso:country":"JP",
    "wof:name":"310-0014",
    "wof:placetype":"postalcode"
},
  "geometry": {"coordinates":[140.50540000000001,36.3706],"type":"Point"}
}