{
  "type": "Feature",
  "properties": {
    "gn:adm1_name":"Saitamaken",
    "gn:adm2_name":"Tokorozawashi",
    "gn:name":"Ushinuma",
    "iso:country":"JP",
    "wof:name":"359-0026",
    "wof:placetype":"postalcode"
},
  "geometry": {"coordinates":[139.48840000000001,35.7958],"type":"Point"}
}