{
  "type": "Feature",
  "properties": {
    "gn:adm1_name":"Gifuken",
    "gn:adm2_name":"Ibigun'Ikedachou",
    "gn:name":"Ganjouji",
    "iso:country":"JP",
    "wof:name":"503-2405",
    "wof:placetype":"postalcode"
},
  "geometry": {"coordinates":[136.55199999999999,35.448],"type":"Point"}
}