{
  "type": "Feature",
  "properties": {
    "gn:adm1_name":"Toukyouto",
    "gn:adm2_name":"Setagayaku",
    "gn:name":"Tamagawadai",
    "iso:country":"JP",
    "wof:name":"158-0096",
    "wof:placetype":"postalcode"
},
  "geometry": {"coordinates":[139.631,35.6238],"type":"Point"}
}