{
  "type": "Feature",
  "properties": {
    "gn:adm1_name":"Ooitaken",
    "gn:adm2_name":"Ooitashi",
    "gn:name":"Takajoushinmachi",
    "iso:country":"JP",
    "wof:name":"870-0156",
    "wof:placetype":"postalcode"
},
  "geometry": {"coordinates":[131.65190000000001,33.2429],"type":"Point"}
}