{
  "type": "Feature",
  "properties": {
    "gn:adm1_name":"Gunmaken",
    "gn:adm2_name":"Fujiokashi",
    "gn:name":"Kamiochiai",
    "iso:country":"JP",
    "wof:name":"375-0057",
    "wof:placetype":"postalcode"
},
  "geometry": {"coordinates":[139.04069999999999,36.2643],"type":"Point"}
}