{
  "type": "Feature",
  "properties": {
    "gn:adm1_name":"Aichiken",
    "gn:adm2_name":"Inuyamashi",
    "gn:name":"Yamagami",
    "iso:country":"JP",
    "wof:name":"484-0876",
    "wof:placetype":"postalcode"
},
  "geometry": {"coordinates":[136.94929999999999,35.3363],"type":"Point"}
}