{
  "type": "Feature",
  "properties": {
    "gn:adm1_name":"Toyamaken",
    "gn:adm2_name":"Tonamishi",
    "gn:name":"Chuuoumachi",
    "iso:country":"JP",
    "wof:name":"939-1375",
    "wof:placetype":"postalcode"
},
  "geometry": {"coordinates":[136.95439999999999,36.6397],"type":"Point"}
}