{
  "type": "Feature",
  "properties": {
    "gn:adm1_name":"Ibarakiken",
    "gn:adm2_name":"Takahagishi",
    "gn:name":"Akiyama",
    "iso:country":"JP",
    "wof:name":"318-0024",
    "wof:placetype":"postalcode"
},
  "geometry": {"coordinates":[140.67949999999999,36.7155],"type":"Point"}
}