{
  "type": "Feature",
  "properties": {
    "gn:adm1_name":"Miyazakiken",
    "gn:adm2_name":"Miyazakishi",
    "gn:name":"Tayoshi",
    "iso:country":"JP",
    "wof:name":"880-0911",
    "wof:placetype":"postalcode"
},
  "geometry": {"coordinates":[131.43639999999999,31.8814],"type":"Point"}
}