{
  "type": "Feature",
  "properties": {
    "gn:adm1_name":"Toukyouto",
    "gn:adm2_name":"Meguroku",
    "gn:name":"Oookayama",
    "iso:country":"JP",
    "wof:name":"152-0033",
    "wof:placetype":"postalcode"
},
  "geometry": {"coordinates":[139.68260000000001,35.6104],"type":"Point"}
}