{
  "type": "Feature",
  "properties": {
    "gn:adm1_name":"Shimaneken",
    "gn:adm2_name":"Yatsukaguntamayuchou",
    "gn:name":"Oodani",
    "iso:country":"JP",
    "wof:name":"699-0205",
    "wof:placetype":"postalcode"
},
  "geometry": {"coordinates":[132.99619999999999,35.391],"type":"Point"}
}