{
  "type": "Feature",
  "properties": {
    "gn:adm1_name":"Kanagawaken",
    "gn:adm2_name":"Kawasakishikawasakiku",
    "gn:name":"Asanochou",
    "iso:country":"JP",
    "wof:name":"210-0854",
    "wof:placetype":"postalcode"
},
  "geometry": {"coordinates":[139.72460000000001,35.5138],"type":"Point"}
}