{
  "type": "Feature",
  "properties": {
    "gn:adm1_name":"Shigaken",
    "gn:adm2_name":"Rittoushi",
    "gn:name":"Nakazawa",
    "iso:country":"JP",
    "wof:name":"520-3025",
    "wof:placetype":"postalcode"
},
  "geometry": {"coordinates":[135.97210000000001,35.027],"type":"Point"}
}