{
  "type": "Feature",
  "properties": {
    "gn:adm1_name":"Niigataken",
    "gn:adm2_name":"Nakakanbaragunkamedamachi",
    "gn:name":"Ogizone",
    "iso:country":"JP",
    "wof:name":"950-0154",
    "wof:placetype":"postalcode"
},
  "geometry": {"coordinates":[139.09960000000001,37.8666],"type":"Point"}
}