{
  "type": "Feature",
  "properties": {
    "gn:adm1_name":"Sagaken",
    "gn:adm2_name":"Kishimagun'Ariakechou",
    "gn:name":"Tanoue",
    "iso:country":"JP",
    "wof:name":"849-1205",
    "wof:placetype":"postalcode"
},
  "geometry": {"coordinates":[130.1037,33.1566],"type":"Point"}
}