{
  "type": "Feature",
  "properties": {
    "gn:adm1_name":"Toyamaken",
    "gn:adm2_name":"Toyamashi",
    "gn:name":"Aoyanagishin",
    "iso:country":"JP",
    "wof:name":"939-8163",
    "wof:placetype":"postalcode"
},
  "geometry": {"coordinates":[137.2311,36.6131],"type":"Point"}
}