{
  "type": "Feature",
  "properties": {
    "gn:adm1_name":"Fukushimaken",
    "gn:adm2_name":"Iwakishi",
    "gn:name":"Watanabemachikamikamado",
    "iso:country":"JP",
    "wof:name":"972-8336",
    "wof:placetype":"postalcode"
},
  "geometry": {"coordinates":[140.7962,36.9846],"type":"Point"}
}