{
  "type": "Feature",
  "properties": {
    "gn:adm1_name":"Kumamotoken",
    "gn:adm2_name":"Yatsushiroshi",
    "gn:name":"Hinaguheiseimachi",
    "iso:country":"JP",
    "wof:name":"869-5138",
    "wof:placetype":"postalcode"
},
  "geometry": {"coordinates":[130.56950000000001,32.4323],"type":"Point"}
}