{
  "type": "Feature",
  "properties": {
    "gn:adm1_name":"Aichiken",
    "gn:adm2_name":"Tokonameshi",
    "gn:name":"Hirouchi",
    "iso:country":"JP",
    "wof:name":"479-0055",
    "wof:placetype":"postalcode"
},
  "geometry": {"coordinates":[136.84569999999999,34.8939],"type":"Point"}
}