{
  "type": "Feature",
  "properties": {
    "gn:adm1_name":"Oosakafu",
    "gn:adm2_name":"Higashioosakashi",
    "gn:name":"Ikeshimachou",
    "iso:country":"JP",
    "wof:name":"579-8064",
    "wof:placetype":"postalcode"
},
  "geometry": {"coordinates":[135.6317,34.6517],"type":"Point"}
}