{
  "type": "Feature",
  "properties": {
    "gn:adm1_name":"Hiroshimaken",
    "gn:adm2_name":"Jinsekigunyukichou",
    "gn:name":"Ueno",
    "iso:country":"JP",
    "wof:name":"720-1624",
    "wof:placetype":"postalcode"
},
  "geometry": {"coordinates":[133.33969999999999,34.7208],"type":"Point"}
}