{
  "type": "Feature",
  "properties": {
    "gn:adm1_name":"Miyagiken",
    "gn:adm2_name":"Kattagunshichikashukumachi",
    "gn:name":"Kamimachijiri",
    "iso:country":"JP",
    "wof:name":"989-0513",
    "wof:placetype":"postalcode"
},
  "geometry": {"coordinates":[140.4462,37.9914],"type":"Point"}
}