{
  "type": "Feature",
  "properties": {
    "gn:adm1_name":"Kyoutofu",
    "gn:adm2_name":"Kyoutoshifushimiku",
    "gn:name":"Momoyamachouhondakouzuke",
    "iso:country":"JP",
    "wof:name":"612-8027",
    "wof:placetype":"postalcode"
},
  "geometry": {"coordinates":[135.77520000000001,34.9301],"type":"Point"}
}