{
  "type": "Feature",
  "properties": {
    "gn:adm1_name":"Kagawaken",
    "gn:adm2_name":"Takamatsushi",
    "gn:name":"Kinashichousaryou",
    "iso:country":"JP",
    "wof:name":"761-8022",
    "wof:placetype":"postalcode"
},
  "geometry": {"coordinates":[133.9931,34.3333],"type":"Point"}
}