{
  "type": "Feature",
  "properties": {
    "gn:adm1_name":"Saitamaken",
    "gn:adm2_name":"Kukishi",
    "gn:name":"Kukishin",
    "iso:country":"JP",
    "wof:name":"346-0032",
    "wof:placetype":"postalcode"
},
  "geometry": {"coordinates":[139.6643,36.0761],"type":"Point"}
}