{
  "type": "Feature",
  "properties": {
    "gn:adm1_name":"Miyagiken",
    "gn:adm2_name":"Kuriharagunkurikomamachi",
    "gn:name":"Sappirai",
    "iso:country":"JP",
    "wof:name":"989-5312",
    "wof:placetype":"postalcode"
},
  "geometry": {"coordinates":[141.0111,38.8185],"type":"Point"}
}