{
  "type": "Feature",
  "properties": {
    "gn:adm1_name":"Gunmaken",
    "gn:adm2_name":"Ouragun'Itakuramachi",
    "gn:name":"Momiya",
    "iso:country":"JP",
    "wof:name":"374-0134",
    "wof:placetype":"postalcode"
},
  "geometry": {"coordinates":[139.58410000000001,36.2353],"type":"Point"}
}