{
  "type": "Feature",
  "properties": {
    "gn:adm1_name":"Fukuokaken",
    "gn:adm2_name":"Fukuokashiminamiku",
    "gn:name":"Minamioohashi",
    "iso:country":"JP",
    "wof:name":"815-0034",
    "wof:placetype":"postalcode"
},
  "geometry": {"coordinates":[130.42169999999999,33.5521],"type":"Point"}
}