{
  "type": "Feature",
  "properties": {
    "gn:adm1_name":"Mieken",
    "gn:adm2_name":"Suzukashi",
    "gn:name":"Kitatamagakichou",
    "iso:country":"JP",
    "wof:name":"513-0813",
    "wof:placetype":"postalcode"
},
  "geometry": {"coordinates":[136.58799999999999,34.8658],"type":"Point"}
}