{
  "type": "Feature",
  "properties": {
    "gn:adm1_name":"Toyamaken",
    "gn:adm2_name":"Nakaniikawagunkamiichimachi",
    "gn:name":"Shakusenji",
    "iso:country":"JP",
    "wof:name":"930-0431",
    "wof:placetype":"postalcode"
},
  "geometry": {"coordinates":[137.4083,36.6875],"type":"Point"}
}