{
  "type": "Feature",
  "properties": {
    "gn:adm1_name":"Fukushimaken",
    "gn:adm2_name":"Shirakawashi",
    "gn:name":"Shinmichi",
    "iso:country":"JP",
    "wof:name":"961-0037",
    "wof:placetype":"postalcode"
},
  "geometry": {"coordinates":[140.2251,37.0913],"type":"Point"}
}