{
  "type": "Feature",
  "properties": {
    "gn:adm1_name":"Fukushimaken",
    "gn:adm2_name":"Nihonmatsushi",
    "gn:name":"Hiraishisanchoume",
    "iso:country":"JP",
    "wof:name":"964-0992",
    "wof:placetype":"postalcode"
},
  "geometry": {"coordinates":[140.45439999999999,37.5563],"type":"Point"}
}