{
  "type": "Feature",
  "properties": {
    "gn:adm1_name":"Yamanashiken",
    "gn:adm2_name":"Higashiyatsushirogun'Ichinomiyachou",
    "gn:name":"Shioda",
    "iso:country":"JP",
    "wof:name":"405-0064",
    "wof:placetype":"postalcode"
},
  "geometry": {"coordinates":[138.69,35.6336],"type":"Point"}
}