{
  "type": "Feature",
  "properties": {
    "gn:adm1_name":"Kanagawaken",
    "gn:adm2_name":"Hadanoshi",
    "gn:name":"Matsubarachou",
    "iso:country":"JP",
    "wof:name":"259-1313",
    "wof:placetype":"postalcode"
},
  "geometry": {"coordinates":[139.18530000000001,35.3767],"type":"Point"}
}