{
  "type": "Feature",
  "properties": {
    "gn:adm1_name":"Mieken",
    "gn:adm2_name":"Nagagun'Aoyamachou",
    "gn:name":"Taki",
    "iso:country":"JP",
    "wof:name":"518-0201",
    "wof:placetype":"postalcode"
},
  "geometry": {"coordinates":[136.23519999999999,34.7066],"type":"Point"}
}