{
  "type": "Feature",
  "properties": {
    "gn:adm1_name":"Fukushimaken",
    "gn:adm2_name":"Nishishirakawagunnishigoumura",
    "gn:name":"Ishidukaminami",
    "iso:country":"JP",
    "wof:name":"961-8043",
    "wof:placetype":"postalcode"
},
  "geometry": {"coordinates":[140.18039999999999,37.1235],"type":"Point"}
}