{
  "type": "Feature",
  "properties": {
    "gn:adm1_name":"Naganoken",
    "gn:adm2_name":"Naganoshi",
    "gn:name":"Naniaitei",
    "iso:country":"JP",
    "wof:name":"381-3161",
    "wof:placetype":"postalcode"
},
  "geometry": {"coordinates":[138.07759999999999,36.6329],"type":"Point"}
}