{
  "type": "Feature",
  "properties": {
    "gn:adm1_name":"Shimaneken",
    "gn:adm2_name":"Ooharagundaitouchou",
    "gn:name":"Higashiayou",
    "iso:country":"JP",
    "wof:name":"699-1224",
    "wof:placetype":"postalcode"
},
  "geometry": {"coordinates":[132.97049999999999,35.3024],"type":"Point"}
}