{
  "type": "Feature",
  "properties": {
    "gn:adm1_name":"Miyagiken",
    "gn:adm2_name":"Igugunmarumorimachi",
    "gn:name":"Kinuma",
    "iso:country":"JP",
    "wof:name":"981-2106",
    "wof:placetype":"postalcode"
},
  "geometry": {"coordinates":[140.77269999999999,37.9422],"type":"Point"}
}