{
  "type": "Feature",
  "properties": {
    "gn:adm1_name":"Fukushimaken",
    "gn:adm2_name":"Higashishirakawaguntanaguramachi",
    "gn:name":"Kanazawauchi",
    "iso:country":"JP",
    "wof:name":"963-6106",
    "wof:placetype":"postalcode"
},
  "geometry": {"coordinates":[140.35589999999999,37.0534],"type":"Point"}
}