{
  "type": "Feature",
  "properties": {
    "gn:adm1_name":"Toyamaken",
    "gn:adm2_name":"Uodushi",
    "gn:name":"Suehirochou",
    "iso:country":"JP",
    "wof:name":"937-0059",
    "wof:placetype":"postalcode"
},
  "geometry": {"coordinates":[137.39940000000001,36.8206],"type":"Point"}
}