{
  "type": "Feature",
  "properties": {
    "gn:adm1_name":"Chibaken",
    "gn:adm2_name":"Sanbugunyokoshibamachi",
    "gn:name":"Yatsudai",
    "iso:country":"JP",
    "wof:name":"289-1743",
    "wof:placetype":"postalcode"
},
  "geometry": {"coordinates":[140.4571,35.6952],"type":"Point"}
}