{
  "type": "Feature",
  "properties": {
    "gn:adm1_name":"Kagoshimaken",
    "gn:adm2_name":"Ooshimagunsetouchichou",
    "gn:name":"Keten",
    "iso:country":"JP",
    "wof:name":"894-1853",
    "wof:placetype":"postalcode"
},
  "geometry": {"coordinates":[129.21719999999999,28.229],"type":"Point"}
}