{
  "type": "Feature",
  "properties": {
    "gn:adm1_name":"Tochigiken",
    "gn:adm2_name":"Nasugunnishinasunomachi",
    "gn:name":"Azumachou",
    "iso:country":"JP",
    "wof:name":"329-2721",
    "wof:placetype":"postalcode"
},
  "geometry": {"coordinates":[139.9872,36.8882],"type":"Point"}
}