{
  "type": "Feature",
  "properties": {
    "gn:adm1_name":"Niigataken",
    "gn:adm2_name":"Nakakubikigunkakizakimachi",
    "gn:name":"Takegahana",
    "iso:country":"JP",
    "wof:name":"949-3201",
    "wof:placetype":"postalcode"
},
  "geometry": {"coordinates":[138.4075,37.2957],"type":"Point"}
}