{
  "type": "Feature",
  "properties": {
    "gn:adm1_name":"Saitamaken",
    "gn:adm2_name":"Niizashi",
    "gn:name":"Higashi",
    "iso:country":"JP",
    "wof:name":"352-0002",
    "wof:placetype":"postalcode"
},
  "geometry": {"coordinates":[139.57130000000001,35.812],"type":"Point"}
}