{
  "type": "Feature",
  "properties": {
    "gn:adm1_name":"Ibarakiken",
    "gn:adm2_name":"Higashiibarakigun'Ibarakimachi",
    "gn:name":"Umawatari",
    "iso:country":"JP",
    "wof:name":"311-3111",
    "wof:placetype":"postalcode"
},
  "geometry": {"coordinates":[140.40110000000001,36.3138],"type":"Point"}
}