{
  "type": "Feature",
  "properties": {
    "gn:adm1_name":"Fukushimaken",
    "gn:adm2_name":"Oonumagun'Aidutakadamachi",
    "gn:name":"Onta",
    "iso:country":"JP",
    "wof:name":"969-6205",
    "wof:placetype":"postalcode"
},
  "geometry": {"coordinates":[139.84110000000001,37.4716],"type":"Point"}
}