{
  "type": "Feature",
  "properties": {
    "gn:adm1_name":"Yamagataken",
    "gn:adm2_name":"Murayamashi",
    "gn:name":"Tateokatate",
    "iso:country":"JP",
    "wof:name":"995-0021",
    "wof:placetype":"postalcode"
},
  "geometry": {"coordinates":[140.3931,38.4825],"type":"Point"}
}