{
  "type": "Feature",
  "properties": {
    "gn:adm1_name":"Kouchiken",
    "gn:adm2_name":"Hatagunmiharamura",
    "gn:name":"Hirono",
    "iso:country":"JP",
    "wof:name":"787-0814",
    "wof:placetype":"postalcode"
},
  "geometry": {"coordinates":[132.83009999999999,32.8909],"type":"Point"}
}