{
  "type": "Feature",
  "properties": {
    "gn:adm1_name":"Chibaken",
    "gn:adm2_name":"Sanbugunshibayamamachi",
    "gn:name":"Miyazaki",
    "iso:country":"JP",
    "wof:name":"289-1614",
    "wof:placetype":"postalcode"
},
  "geometry": {"coordinates":[140.43639999999999,35.7079],"type":"Point"}
}