{
  "type": "Feature",
  "properties": {
    "gn:adm1_name":"Niigataken",
    "gn:adm2_name":"Niigatashi",
    "gn:name":"Kamegai",
    "iso:country":"JP",
    "wof:name":"950-2033",
    "wof:placetype":"postalcode"
},
  "geometry": {"coordinates":[138.97989999999999,37.8692],"type":"Point"}
}