{
  "type": "Feature",
  "properties": {
    "gn:adm1_name":"Hyougoken",
    "gn:adm2_name":"Hikamigunsannanchou",
    "gn:name":"Kanaya",
    "iso:country":"JP",
    "wof:name":"669-3128",
    "wof:placetype":"postalcode"
},
  "geometry": {"coordinates":[135.0341,35.0863],"type":"Point"}
}