{
  "type": "Feature",
  "properties": {
    "gn:adm1_name":"Kyoutofu",
    "gn:adm2_name":"Kyoutoshiyamashinaku",
    "gn:name":"Kawatakiyomizuyakidanchichou",
    "iso:country":"JP",
    "wof:name":"607-8322",
    "wof:placetype":"postalcode"
},
  "geometry": {"coordinates":[135.79470000000001,34.9798],"type":"Point"}
}