{
  "type": "Feature",
  "properties": {
    "gn:adm1_name":"Kagawaken",
    "gn:adm2_name":"Sakaideshi",
    "gn:name":"Aobachou",
    "iso:country":"JP",
    "wof:name":"762-0037",
    "wof:placetype":"postalcode"
},
  "geometry": {"coordinates":[133.8526,34.3076],"type":"Point"}
}