{
  "type": "Feature",
  "properties": {
    "gn:adm1_name":"Nagasakiken",
    "gn:adm2_name":"Fukueshi",
    "gn:name":"Tanourachou",
    "iso:country":"JP",
    "wof:name":"853-2173",
    "wof:placetype":"postalcode"
},
  "geometry": {"coordinates":[128.8493,32.7775],"type":"Point"}
}