{
  "type": "Feature",
  "properties": {
    "gn:adm1_name":"Kyoutofu",
    "gn:adm2_name":"Kyoutoshifushimiku",
    "gn:name":"Tsuchibashichou",
    "iso:country":"JP",
    "wof:name":"612-8312",
    "wof:placetype":"postalcode"
},
  "geometry": {"coordinates":[135.76159999999999,34.9449],"type":"Point"}
}