{
  "type": "Feature",
  "properties": {
    "gn:adm1_name":"Gifuken",
    "gn:adm2_name":"Gifushi",
    "gn:name":"Shinsakaemachi",
    "iso:country":"JP",
    "wof:name":"500-8855",
    "wof:placetype":"postalcode"
},
  "geometry": {"coordinates":[136.75229999999999,35.4113],"type":"Point"}
}