{
  "type": "Feature",
  "properties": {
    "gn:adm1_name":"Ibarakiken",
    "gn:adm2_name":"Iwaishi",
    "gn:name":"Nakazato",
    "iso:country":"JP",
    "wof:name":"306-0634",
    "wof:placetype":"postalcode"
},
  "geometry": {"coordinates":[139.90389999999999,36.0205],"type":"Point"}
}