{
  "type": "Feature",
  "properties": {
    "gn:adm1_name":"Hyougoken",
    "gn:adm2_name":"Asagogun'Asagochou",
    "gn:name":"Iwatsu",
    "iso:country":"JP",
    "wof:name":"679-3433",
    "wof:placetype":"postalcode"
},
  "geometry": {"coordinates":[134.79660000000001,35.2038],"type":"Point"}
}