{
  "type": "Feature",
  "properties": {
    "gn:adm1_name":"Ishikawaken",
    "gn:adm2_name":"Komatsushi",
    "gn:name":"Sandanimachi",
    "iso:country":"JP",
    "wof:name":"923-0844",
    "wof:placetype":"postalcode"
},
  "geometry": {"coordinates":[136.45779999999999,36.3716],"type":"Point"}
}