{
  "type": "Feature",
  "properties": {
    "gn:adm1_name":"Miyagiken",
    "gn:adm2_name":"Watarigunwatarichou",
    "gn:name":"Ookumajuumonji",
    "iso:country":"JP",
    "wof:name":"989-2303",
    "wof:placetype":"postalcode"
},
  "geometry": {"coordinates":[140.87649999999999,38.0704],"type":"Point"}
}