{
  "type": "Feature",
  "properties": {
    "gn:adm1_name":"Toyamaken",
    "gn:adm2_name":"Toyamashi",
    "gn:name":"Nakaoki",
    "iso:country":"JP",
    "wof:name":"930-0101",
    "wof:placetype":"postalcode"
},
  "geometry": {"coordinates":[137.1574,36.7367],"type":"Point"}
}