{
  "type": "Feature",
  "properties": {
    "gn:adm1_name":"Ibarakiken",
    "gn:adm2_name":"Shimotsumashi",
    "gn:name":"Shitamiya",
    "iso:country":"JP",
    "wof:name":"304-0013",
    "wof:placetype":"postalcode"
},
  "geometry": {"coordinates":[139.98480000000001,36.2245],"type":"Point"}
}