{
  "type": "Feature",
  "properties": {
    "gn:adm1_name":"Fukuiken",
    "gn:adm2_name":"Oonoshi",
    "gn:name":"Minamikasugano",
    "iso:country":"JP",
    "wof:name":"912-0066",
    "wof:placetype":"postalcode"
},
  "geometry": {"coordinates":[136.4941,35.9635],"type":"Point"}
}