{
  "type": "Feature",
  "properties": {
    "gn:adm1_name":"Ishikawaken",
    "gn:adm2_name":"Wajimashi",
    "gn:name":"Miimachinaka",
    "iso:country":"JP",
    "wof:name":"929-2362",
    "wof:placetype":"postalcode"
},
  "geometry": {"coordinates":[136.9177,37.3194],"type":"Point"}
}