{
  "type": "Feature",
  "properties": {
    "gn:adm1_name":"Tokushimaken",
    "gn:adm2_name":"Miyoshigun'Ikedachou",
    "gn:name":"Nakanishi",
    "iso:country":"JP",
    "wof:name":"779-5161",
    "wof:placetype":"postalcode"
},
  "geometry": {"coordinates":[133.7895,34.006],"type":"Point"}
}