{
  "type": "Feature",
  "properties": {
    "gn:adm1_name":"Aichiken",
    "gn:adm2_name":"Tsushimashi",
    "gn:name":"Shiroyamachou",
    "iso:country":"JP",
    "wof:name":"496-0862",
    "wof:placetype":"postalcode"
},
  "geometry": {"coordinates":[136.72130000000001,35.184],"type":"Point"}
}