{
  "type": "Feature",
  "properties": {
    "gn:adm1_name":"Shizuokaken",
    "gn:adm2_name":"Shizuokashi",
    "gn:name":"Takumi",
    "iso:country":"JP",
    "wof:name":"421-2224",
    "wof:placetype":"postalcode"
},
  "geometry": {"coordinates":[138.30199999999999,35.1191],"type":"Point"}
}