{
  "type": "Feature",
  "properties": {
    "gn:adm1_name":"Kanagawaken",
    "gn:adm2_name":"Fujisawashi",
    "gn:name":"Shirahata",
    "iso:country":"JP",
    "wof:name":"251-0051",
    "wof:placetype":"postalcode"
},
  "geometry": {"coordinates":[139.4803,35.3563],"type":"Point"}
}