{
  "type": "Feature",
  "properties": {
    "gn:adm1_name":"Hyougoken",
    "gn:adm2_name":"Akashishi",
    "gn:name":"Hitomaruchou",
    "iso:country":"JP",
    "wof:name":"673-0877",
    "wof:placetype":"postalcode"
},
  "geometry": {"coordinates":[135.00030000000001,34.6491],"type":"Point"}
}