{
  "type": "Feature",
  "properties": {
    "gn:adm1_name":"Kagawaken",
    "gn:adm2_name":"Sakaideshi",
    "gn:name":"Muromachi",
    "iso:country":"JP",
    "wof:name":"762-0007",
    "wof:placetype":"postalcode"
},
  "geometry": {"coordinates":[133.8614,34.3165],"type":"Point"}
}