{
  "type": "Feature",
  "properties": {
    "gn:adm1_name":"Mieken",
    "gn:adm2_name":"Yokkaichishi",
    "gn:name":"Nishiakuragawa",
    "iso:country":"JP",
    "wof:name":"510-0812",
    "wof:placetype":"postalcode"
},
  "geometry": {"coordinates":[136.61789999999999,34.9897],"type":"Point"}
}