{
  "type": "Feature",
  "properties": {
    "gn:adm1_name":"Hiroshimaken",
    "gn:adm2_name":"Miharashi",
    "gn:name":"En'Ichichou",
    "iso:country":"JP",
    "wof:name":"723-0015",
    "wof:placetype":"postalcode"
},
  "geometry": {"coordinates":[133.07769999999999,34.3935],"type":"Point"}
}