{
  "type": "Feature",
  "properties": {
    "gn:adm1_name":"Gifuken",
    "gn:adm2_name":"Mizuhoshi",
    "gn:name":"Tadakoshi",
    "iso:country":"JP",
    "wof:name":"501-0221",
    "wof:placetype":"postalcode"
},
  "geometry": {"coordinates":[136.68819999999999,35.3993],"type":"Point"}
}