{
  "type": "Feature",
  "properties": {
    "gn:adm1_name":"Chibaken",
    "gn:adm2_name":"Abikoshi",
    "gn:name":"Nedoshinden",
    "iso:country":"JP",
    "wof:name":"270-1156",
    "wof:placetype":"postalcode"
},
  "geometry": {"coordinates":[139.99799999999999,35.8689],"type":"Point"}
}