{
  "type": "Feature",
  "properties": {
    "gn:adm1_name":"Kyoutofu",
    "gn:adm2_name":"Nagaokakyoushi",
    "gn:name":"Imazato",
    "iso:country":"JP",
    "wof:name":"617-0814",
    "wof:placetype":"postalcode"
},
  "geometry": {"coordinates":[135.68969999999999,34.9362],"type":"Point"}
}