{
  "type": "Feature",
  "properties": {
    "gn:adm1_name":"Kanagawaken",
    "gn:adm2_name":"Kawasakishitamaku",
    "gn:name":"Sugesengoku",
    "iso:country":"JP",
    "wof:name":"214-0006",
    "wof:placetype":"postalcode"
},
  "geometry": {"coordinates":[139.52529999999999,35.6277],"type":"Point"}
}