{
  "type": "Feature",
  "properties": {
    "gn:adm1_name":"Kagoshimaken",
    "gn:adm2_name":"Ooshimagunchinachou",
    "gn:name":"Tamina",
    "iso:country":"JP",
    "wof:name":"891-9231",
    "wof:placetype":"postalcode"
},
  "geometry": {"coordinates":[128.54040000000001,27.3864],"type":"Point"}
}