{
  "type": "Feature",
  "properties": {
    "gn:adm1_name":"Kumamotoken",
    "gn:adm2_name":"Hitoyoshishi",
    "gn:name":"Kamitashiromachi",
    "iso:country":"JP",
    "wof:name":"868-0801",
    "wof:placetype":"postalcode"
},
  "geometry": {"coordinates":[130.80690000000001,32.1681],"type":"Point"}
}