{
  "type": "Feature",
  "properties": {
    "gn:adm1_name":"Kumamotoken",
    "gn:adm2_name":"Kumamotoshi",
    "gn:name":"Kawabatamachi",
    "iso:country":"JP",
    "wof:name":"860-0039",
    "wof:placetype":"postalcode"
},
  "geometry": {"coordinates":[130.69499999999999,32.7932],"type":"Point"}
}