{
  "type": "Feature",
  "properties": {
    "gn:adm1_name":"Ehimeken",
    "gn:adm2_name":"Oozushi",
    "gn:name":"Yasarai",
    "iso:country":"JP",
    "wof:name":"795-0006",
    "wof:placetype":"postalcode"
},
  "geometry": {"coordinates":[132.5412,33.47],"type":"Point"}
}