{
  "type": "Feature",
  "properties": {
    "gn:adm1_name":"Chibaken",
    "gn:adm2_name":"Matsudoshi",
    "gn:name":"Yoshiichou",
    "iso:country":"JP",
    "wof:name":"271-0066",
    "wof:placetype":"postalcode"
},
  "geometry": {"coordinates":[139.9066,35.7903],"type":"Point"}
}