{
  "type": "Feature",
  "properties": {
    "gn:adm1_name":"Ibarakiken",
    "gn:adm2_name":"Hitachinakashi",
    "gn:name":"Tanakaushiro",
    "iso:country":"JP",
    "wof:name":"311-1235",
    "wof:placetype":"postalcode"
},
  "geometry": {"coordinates":[140.5821,36.348],"type":"Point"}
}