{
  "type": "Feature",
  "properties": {
    "gn:adm1_name":"Kagawaken",
    "gn:adm2_name":"Shouzuguntonoshouchou",
    "gn:name":"Mime",
    "iso:country":"JP",
    "wof:name":"761-4143",
    "wof:placetype":"postalcode"
},
  "geometry": {"coordinates":[134.2285,34.5242],"type":"Point"}
}