{
  "type": "Feature",
  "properties": {
    "gn:adm1_name":"Ibarakiken",
    "gn:adm2_name":"Kitasoumaguntonemachi",
    "gn:name":"Tatsugi",
    "iso:country":"JP",
    "wof:name":"300-1616",
    "wof:placetype":"postalcode"
},
  "geometry": {"coordinates":[140.17420000000001,35.8701],"type":"Point"}
}