{
  "type": "Feature",
  "properties": {
    "gn:adm1_name":"Gifuken",
    "gn:adm2_name":"Gifushi",
    "gn:name":"Nagaramiyaguchichou",
    "iso:country":"JP",
    "wof:name":"502-0027",
    "wof:placetype":"postalcode"
},
  "geometry": {"coordinates":[136.77969999999999,35.4441],"type":"Point"}
}