{
  "type": "Feature",
  "properties": {
    "gn:adm1_name":"Kumamotoken",
    "gn:adm2_name":"Asoguntakamorimachi",
    "gn:name":"Shitagiri",
    "iso:country":"JP",
    "wof:name":"869-1815",
    "wof:placetype":"postalcode"
},
  "geometry": {"coordinates":[131.23320000000001,32.7986],"type":"Point"}
}