{
  "type": "Feature",
  "properties": {
    "gn:adm1_name":"Niigataken",
    "gn:adm2_name":"Kitakanbaragunnakajoumachi",
    "gn:name":"Kurashikichou",
    "iso:country":"JP",
    "wof:name":"959-2653",
    "wof:placetype":"postalcode"
},
  "geometry": {"coordinates":[139.40539999999999,38.0651],"type":"Point"}
}