{
  "type": "Feature",
  "properties": {
    "gn:adm1_name":"Fukuokaken",
    "gn:adm2_name":"Ogoorishi",
    "gn:name":"Ikanikeisaiganaibaai",
    "iso:country":"JP",
    "wof:name":"838-0100",
    "wof:placetype":"postalcode"
},
  "geometry": {"coordinates":[130.56309999999999,33.443],"type":"Point"}
}