{
  "type": "Feature",
  "properties": {
    "gn:adm1_name":"Shimaneken",
    "gn:adm2_name":"Izumoshi",
    "gn:name":"Chiimiyachou",
    "iso:country":"JP",
    "wof:name":"693-0033",
    "wof:placetype":"postalcode"
},
  "geometry": {"coordinates":[132.72020000000001,35.3365],"type":"Point"}
}