{
  "type": "Feature",
  "properties": {
    "gn:adm1_name":"Miyagiken",
    "gn:adm2_name":"Kurokawagun'Oohiramura",
    "gn:name":"Oouri",
    "iso:country":"JP",
    "wof:name":"981-3601",
    "wof:placetype":"postalcode"
},
  "geometry": {"coordinates":[140.85140000000001,38.4774],"type":"Point"}
}