{
  "type": "Feature",
  "properties": {
    "gn:adm1_name":"Hyougoken",
    "gn:adm2_name":"Asagogun'Ikunochou",
    "gn:name":"Inono",
    "iso:country":"JP",
    "wof:name":"679-3325",
    "wof:placetype":"postalcode"
},
  "geometry": {"coordinates":[134.81190000000001,35.1629],"type":"Point"}
}