{
  "type": "Feature",
  "properties": {
    "gn:adm1_name":"Shigaken",
    "gn:adm2_name":"Gamougunhinochou",
    "gn:name":"Nekoda",
    "iso:country":"JP",
    "wof:name":"529-1646",
    "wof:placetype":"postalcode"
},
  "geometry": {"coordinates":[136.22389999999999,35.0069],"type":"Point"}
}