{
  "type": "Feature",
  "properties": {
    "gn:adm1_name":"Toyamaken",
    "gn:adm2_name":"Toyamashi",
    "gn:name":"Okudamachi",
    "iso:country":"JP",
    "wof:name":"930-0818",
    "wof:placetype":"postalcode"
},
  "geometry": {"coordinates":[137.2201,36.7106],"type":"Point"}
}