{
  "type": "Feature",
  "properties": {
    "gn:adm1_name":"Kagoshimaken",
    "gn:adm2_name":"Kagoshimaguntoshimamura",
    "gn:name":"Suwanosejima",
    "iso:country":"JP",
    "wof:name":"891-5203",
    "wof:placetype":"postalcode"
},
  "geometry": {"coordinates":[129.70349999999999,29.6139],"type":"Point"}
}