{
  "type": "Feature",
  "properties": {
    "gn:adm1_name":"Niigataken",
    "gn:adm2_name":"Kitakanbaragunsuibaramachi",
    "gn:name":"Kamifukuoka",
    "iso:country":"JP",
    "wof:name":"959-2073",
    "wof:placetype":"postalcode"
},
  "geometry": {"coordinates":[139.19120000000001,37.7984],"type":"Point"}
}