{
  "type": "Feature",
  "properties": {
    "gn:adm1_name":"Chibaken",
    "gn:adm2_name":"Sakurashi",
    "gn:name":"Iinomachi",
    "iso:country":"JP",
    "wof:name":"285-0009",
    "wof:placetype":"postalcode"
},
  "geometry": {"coordinates":[140.2039,35.7499],"type":"Point"}
}