{
  "type": "Feature",
  "properties": {
    "gn:adm1_name":"Naganoken",
    "gn:adm2_name":"Kamiminochigunshinshuushinmachi",
    "gn:name":"Takebusa",
    "iso:country":"JP",
    "wof:name":"381-2411",
    "wof:placetype":"postalcode"
},
  "geometry": {"coordinates":[138.0146,36.5645],"type":"Point"}
}