{
  "type": "Feature",
  "properties": {
    "gn:adm1_name":"Ishikawaken",
    "gn:adm2_name":"Suzugun'Uchiuramachi",
    "gn:name":"Kagatani",
    "iso:country":"JP",
    "wof:name":"927-0613",
    "wof:placetype":"postalcode"
},
  "geometry": {"coordinates":[137.23419999999999,37.3241],"type":"Point"}
}