{
  "type": "Feature",
  "properties": {
    "gn:adm1_name":"Chibaken",
    "gn:adm2_name":"Kimitsushi",
    "gn:name":"Kazusakoito",
    "iso:country":"JP",
    "wof:name":"292-1149",
    "wof:placetype":"postalcode"
},
  "geometry": {"coordinates":[139.99629999999999,35.3157],"type":"Point"}
}