{
  "type": "Feature",
  "properties": {
    "gn:adm1_name":"Fukuokaken",
    "gn:adm2_name":"Kitakyuushuushiyahatanishiku",
    "gn:name":"Yuubarumachi",
    "iso:country":"JP",
    "wof:name":"807-0813",
    "wof:placetype":"postalcode"
},
  "geometry": {"coordinates":[130.7388,33.8707],"type":"Point"}
}