{
  "type": "Feature",
  "properties": {
    "gn:adm1_name":"Fukuokaken",
    "gn:adm2_name":"Yukuhashishi",
    "gn:name":"Shimodukuma",
    "iso:country":"JP",
    "wof:name":"824-0062",
    "wof:placetype":"postalcode"
},
  "geometry": {"coordinates":[130.96039999999999,33.7306],"type":"Point"}
}