{
  "type": "Feature",
  "properties": {
    "gn:adm1_name":"Hyougoken",
    "gn:adm2_name":"Himejishi",
    "gn:name":"Nozatodaiwamachi",
    "iso:country":"JP",
    "wof:name":"670-0815",
    "wof:placetype":"postalcode"
},
  "geometry": {"coordinates":[134.70320000000001,34.847],"type":"Point"}
}