{
  "type": "Feature",
  "properties": {
    "gn:adm1_name":"Toukyouto",
    "gn:adm2_name":"Oumeshi",
    "gn:name":"Osoki",
    "iso:country":"JP",
    "wof:name":"198-0003",
    "wof:placetype":"postalcode"
},
  "geometry": {"coordinates":[139.28280000000001,35.8207],"type":"Point"}
}