{
  "type": "Feature",
  "properties": {
    "gn:adm1_name":"Kouchiken",
    "gn:adm2_name":"Nakamurashi",
    "gn:name":"Gudoutaguro",
    "iso:country":"JP",
    "wof:name":"787-0051",
    "wof:placetype":"postalcode"
},
  "geometry": {"coordinates":[132.91990000000001,32.9863],"type":"Point"}
}