{
  "type": "Feature",
  "properties": {
    "gn:adm1_name":"Kagawaken",
    "gn:adm2_name":"Sakaideshi",
    "gn:name":"Shiroganechou",
    "iso:country":"JP",
    "wof:name":"762-0042",
    "wof:placetype":"postalcode"
},
  "geometry": {"coordinates":[133.84620000000001,34.3155],"type":"Point"}
}