{
  "type": "Feature",
  "properties": {
    "gn:adm1_name":"Naganoken",
    "gn:adm2_name":"Suwagunshimosuwamachi",
    "gn:name":"Higashimachiue",
    "iso:country":"JP",
    "wof:name":"393-0006",
    "wof:placetype":"postalcode"
},
  "geometry": {"coordinates":[138.0865,36.0951],"type":"Point"}
}