{
  "type": "Feature",
  "properties": {
    "gn:adm1_name":"Ishikawaken",
    "gn:adm2_name":"Kahokuguntsubatamachi",
    "gn:name":"Inokawachi",
    "iso:country":"JP",
    "wof:name":"929-0445",
    "wof:placetype":"postalcode"
},
  "geometry": {"coordinates":[136.74770000000001,36.6542],"type":"Point"}
}