{
  "type": "Feature",
  "properties": {
    "gn:adm1_name":"Wakayamaken",
    "gn:adm2_name":"Wakayamashi",
    "gn:name":"Nishikuramaechou",
    "iso:country":"JP",
    "wof:name":"640-8205",
    "wof:placetype":"postalcode"
},
  "geometry": {"coordinates":[135.16569999999999,34.237],"type":"Point"}
}