{
  "type": "Feature",
  "properties": {
    "gn:adm1_name":"Hiroshimaken",
    "gn:adm2_name":"Futamigunkimitason",
    "gn:name":"Izumyoshida",
    "iso:country":"JP",
    "wof:name":"728-0405",
    "wof:placetype":"postalcode"
},
  "geometry": {"coordinates":[132.85929999999999,34.9024],"type":"Point"}
}