{
  "type": "Feature",
  "properties": {
    "gn:adm1_name":"Shizuokaken",
    "gn:adm2_name":"Numadushi",
    "gn:name":"Matsusawachou",
    "iso:country":"JP",
    "wof:name":"410-0014",
    "wof:placetype":"postalcode"
},
  "geometry": {"coordinates":[138.86349999999999,35.1272],"type":"Point"}
}