{
  "type": "Feature",
  "properties": {
    "gn:adm1_name":"Toyamaken",
    "gn:adm2_name":"Takaokashi",
    "gn:name":"Togiyamachi",
    "iso:country":"JP",
    "wof:name":"933-0927",
    "wof:placetype":"postalcode"
},
  "geometry": {"coordinates":[137.0086,36.7468],"type":"Point"}
}