{
  "type": "Feature",
  "properties": {
    "gn:adm1_name":"Chibaken",
    "gn:adm2_name":"Kashiwashi",
    "gn:name":"Akanechou",
    "iso:country":"JP",
    "wof:name":"277-0027",
    "wof:placetype":"postalcode"
},
  "geometry": {"coordinates":[139.97810000000001,35.8506],"type":"Point"}
}