{
  "type": "Feature",
  "properties": {
    "gn:adm1_name":"Niigataken",
    "gn:adm2_name":"Nagaokashi",
    "gn:name":"Hasugata",
    "iso:country":"JP",
    "wof:name":"940-2023",
    "wof:placetype":"postalcode"
},
  "geometry": {"coordinates":[138.8246,37.4672],"type":"Point"}
}