{
  "type": "Feature",
  "properties": {
    "gn:adm1_name":"Niigataken",
    "gn:adm2_name":"Nagaokashi",
    "gn:name":"Wakigawashindenmachi(970banchi)",
    "iso:country":"JP",
    "wof:name":"954-0181",
    "wof:placetype":"postalcode"
},
  "geometry": {"coordinates":[138.8494,37.5299],"type":"Point"}
}