{
  "type": "Feature",
  "properties": {
    "gn:adm1_name":"Fukuokaken",
    "gn:adm2_name":"Kitakyuushuushiyahatanishiku",
    "gn:name":"Takamidai",
    "iso:country":"JP",
    "wof:name":"807-0853",
    "wof:placetype":"postalcode"
},
  "geometry": {"coordinates":[130.72460000000001,33.84],"type":"Point"}
}