{
  "type": "Feature",
  "properties": {
    "gn:adm1_name":"Kouchiken",
    "gn:adm2_name":"Susakishi",
    "gn:name":"Kamibun'Otsu",
    "iso:country":"JP",
    "wof:name":"785-0027",
    "wof:placetype":"postalcode"
},
  "geometry": {"coordinates":[133.226,33.4008],"type":"Point"}
}