{
  "type": "Feature",
  "properties": {
    "gn:adm1_name":"Niigataken",
    "gn:adm2_name":"Nakakubikigunmyoukoumura",
    "gn:name":"Sekiyama(Sonota)",
    "iso:country":"JP",
    "wof:name":"949-2235",
    "wof:placetype":"postalcode"
},
  "geometry": {"coordinates":[138.21809999999999,36.9319],"type":"Point"}
}