{
  "type": "Feature",
  "properties": {
    "gn:adm1_name":"Niigataken",
    "gn:adm2_name":"Sadogun'Aikawamachi",
    "gn:name":"Suwamachi",
    "iso:country":"JP",
    "wof:name":"952-1525",
    "wof:placetype":"postalcode"
},
  "geometry": {"coordinates":[138.2516,38.0362],"type":"Point"}
}