{
  "type": "Feature",
  "properties": {
    "gn:adm1_name":"Kumamotoken",
    "gn:adm2_name":"Asogun'Asomachi",
    "gn:name":"Imamachi",
    "iso:country":"JP",
    "wof:name":"869-2315",
    "wof:placetype":"postalcode"
},
  "geometry": {"coordinates":[131.0701,32.9712],"type":"Point"}
}