{
  "type": "Feature",
  "properties": {
    "gn:adm1_name":"Kyoutofu",
    "gn:adm2_name":"Kyoutoshiyamashinaku",
    "gn:name":"Onoyumidenchou",
    "iso:country":"JP",
    "wof:name":"607-8253",
    "wof:placetype":"postalcode"
},
  "geometry": {"coordinates":[135.81450000000001,34.9635],"type":"Point"}
}