{
  "type": "Feature",
  "properties": {
    "gn:adm1_name":"Chibaken",
    "gn:adm2_name":"Isumigun'Ootakimachi",
    "gn:name":"Horinouchi",
    "iso:country":"JP",
    "wof:name":"298-0224",
    "wof:placetype":"postalcode"
},
  "geometry": {"coordinates":[140.2602,35.261],"type":"Point"}
}