{
  "type": "Feature",
  "properties": {
    "gn:adm1_name":"Saitamaken",
    "gn:adm2_name":"Kumagayashi",
    "gn:name":"Betsupu",
    "iso:country":"JP",
    "wof:name":"360-0856",
    "wof:placetype":"postalcode"
},
  "geometry": {"coordinates":[139.33670000000001,36.1836],"type":"Point"}
}