{
  "type": "Feature",
  "properties": {
    "gn:adm1_name":"Hyougoken",
    "gn:adm2_name":"Miharagunseidanchou",
    "gn:name":"Matsuhoejiri",
    "iso:country":"JP",
    "wof:name":"656-0303",
    "wof:placetype":"postalcode"
},
  "geometry": {"coordinates":[134.74590000000001,34.3281],"type":"Point"}
}