{
  "type": "Feature",
  "properties": {
    "gn:adm1_name":"Kagoshimaken",
    "gn:adm2_name":"Hiokigunkooriyamachou",
    "gn:name":"Nishimata",
    "iso:country":"JP",
    "wof:name":"891-1106",
    "wof:placetype":"postalcode"
},
  "geometry": {"coordinates":[130.45269999999999,31.6858],"type":"Point"}
}