{
  "type": "Feature",
  "properties": {
    "gn:adm1_name":"Ehimeken",
    "gn:adm2_name":"Uwajimashi",
    "gn:name":"Sumiyoshichou",
    "iso:country":"JP",
    "wof:name":"798-0003",
    "wof:placetype":"postalcode"
},
  "geometry": {"coordinates":[132.55600000000001,33.2272],"type":"Point"}
}