{
  "type": "Feature",
  "properties": {
    "gn:adm1_name":"Fukuiken",
    "gn:adm2_name":"Fukuishi",
    "gn:name":"Kurimorichou",
    "iso:country":"JP",
    "wof:name":"910-0137",
    "wof:placetype":"postalcode"
},
  "geometry": {"coordinates":[136.2406,36.1176],"type":"Point"}
}