{
  "type": "Feature",
  "properties": {
    "gn:adm1_name":"Aichiken",
    "gn:adm2_name":"Amagunsayachou",
    "gn:name":"Higashiho",
    "iso:country":"JP",
    "wof:name":"496-0912",
    "wof:placetype":"postalcode"
},
  "geometry": {"coordinates":[136.71770000000001,35.1443],"type":"Point"}
}