{
  "type": "Feature",
  "properties": {
    "gn:adm1_name":"Miyagiken",
    "gn:adm2_name":"Oshikagun'Onagawachou",
    "gn:name":"Washinokamihama",
    "iso:country":"JP",
    "wof:name":"986-2243",
    "wof:placetype":"postalcode"
},
  "geometry": {"coordinates":[141.44390000000001,38.4405],"type":"Point"}
}