{
  "type": "Feature",
  "properties": {
    "gn:adm1_name":"Fukuokaken",
    "gn:adm2_name":"Oonojoushi",
    "gn:name":"Mizuhomachi",
    "iso:country":"JP",
    "wof:name":"816-0933",
    "wof:placetype":"postalcode"
},
  "geometry": {"coordinates":[130.4769,33.5325],"type":"Point"}
}