{
  "type": "Feature",
  "properties": {
    "gn:adm1_name":"Ishikawaken",
    "gn:adm2_name":"Ishikawaguntorigoemura",
    "gn:name":"Kamashimizu",
    "iso:country":"JP",
    "wof:name":"920-2341",
    "wof:placetype":"postalcode"
},
  "geometry": {"coordinates":[136.61089999999999,36.3628],"type":"Point"}
}