{
  "type": "Feature",
  "properties": {
    "gn:adm1_name":"Fukuiken",
    "gn:adm2_name":"Fukuishi",
    "gn:name":"Furuichi",
    "iso:country":"JP",
    "wof:name":"910-0152",
    "wof:placetype":"postalcode"
},
  "geometry": {"coordinates":[136.22640000000001,36.1051],"type":"Point"}
}