{
  "type": "Feature",
  "properties": {
    "gn:adm1_name":"Shizuokaken",
    "gn:adm2_name":"Ogasagun'Ogasachou",
    "gn:name":"Furuya",
    "iso:country":"JP",
    "wof:name":"437-1502",
    "wof:placetype":"postalcode"
},
  "geometry": {"coordinates":[138.12880000000001,34.7125],"type":"Point"}
}