{
  "type": "Feature",
  "properties": {
    "gn:adm1_name":"Fukuokaken",
    "gn:adm2_name":"Ogoorishi",
    "gn:name":"Fukiage",
    "iso:country":"JP",
    "wof:name":"838-0111",
    "wof:placetype":"postalcode"
},
  "geometry": {"coordinates":[130.58279999999999,33.4143],"type":"Point"}
}