{
  "type": "Feature",
  "properties": {
    "gn:adm1_name":"Niigataken",
    "gn:adm2_name":"Nakakubikigunmyoukoumura",
    "gn:name":"Kitatayashinden",
    "iso:country":"JP",
    "wof:name":"949-2203",
    "wof:placetype":"postalcode"
},
  "geometry": {"coordinates":[138.2414,36.9841],"type":"Point"}
}