{
  "type": "Feature",
  "properties": {
    "gn:adm1_name":"Aichiken",
    "gn:adm2_name":"Kasugaishi",
    "gn:name":"Oshizawadai",
    "iso:country":"JP",
    "wof:name":"487-0005",
    "wof:placetype":"postalcode"
},
  "geometry": {"coordinates":[137.06440000000001,35.2815],"type":"Point"}
}