{
  "type": "Feature",
  "properties": {
    "gn:adm1_name":"Gunmaken",
    "gn:adm2_name":"Kitagunmagunyoshiokamachi",
    "gn:name":"Minamishimo",
    "iso:country":"JP",
    "wof:name":"370-3604",
    "wof:placetype":"postalcode"
},
  "geometry": {"coordinates":[139.00239999999999,36.438],"type":"Point"}
}