{
  "type": "Feature",
  "properties": {
    "gn:adm1_name":"Niigataken",
    "gn:adm2_name":"Jouetsushi",
    "gn:name":"Shouwamachi",
    "iso:country":"JP",
    "wof:name":"943-0891",
    "wof:placetype":"postalcode"
},
  "geometry": {"coordinates":[138.23580000000001,37.1211],"type":"Point"}
}