{
  "type": "Feature",
  "properties": {
    "gn:adm1_name":"Miyazakiken",
    "gn:adm2_name":"Minaminakagunkitagouchou",
    "gn:name":"Oofuji",
    "iso:country":"JP",
    "wof:name":"889-2401",
    "wof:placetype":"postalcode"
},
  "geometry": {"coordinates":[131.37799999999999,31.6547],"type":"Point"}
}