{
  "type": "Feature",
  "properties": {
    "gn:adm1_name":"Aichiken",
    "gn:adm2_name":"Kasugaishi",
    "gn:name":"Asayamachou",
    "iso:country":"JP",
    "wof:name":"486-0857",
    "wof:placetype":"postalcode"
},
  "geometry": {"coordinates":[136.98349999999999,35.2553],"type":"Point"}
}