{
  "type": "Feature",
  "properties": {
    "gn:adm1_name":"Toukyouto",
    "gn:adm2_name":"Fuchuushi",
    "gn:name":"Nishifuchou",
    "iso:country":"JP",
    "wof:name":"183-0031",
    "wof:placetype":"postalcode"
},
  "geometry": {"coordinates":[139.45490000000001,35.6759],"type":"Point"}
}