{
  "type": "Feature",
  "properties": {
    "gn:adm1_name":"Shizuokaken",
    "gn:adm2_name":"Iwatagunsakumachou",
    "gn:name":"Ooi",
    "iso:country":"JP",
    "wof:name":"431-3902",
    "wof:placetype":"postalcode"
},
  "geometry": {"coordinates":[137.8475,35.0841],"type":"Point"}
}