{
  "type": "Feature",
  "properties": {
    "gn:adm1_name":"Miyazakiken",
    "gn:adm2_name":"Miyazakishi",
    "gn:name":"Nakatsusechou",
    "iso:country":"JP",
    "wof:name":"880-0025",
    "wof:placetype":"postalcode"
},
  "geometry": {"coordinates":[131.41720000000001,31.9228],"type":"Point"}
}