{
  "type": "Feature",
  "properties": {
    "gn:adm1_name":"Kyoutofu",
    "gn:adm2_name":"Kyoutoshifushimiku",
    "gn:name":"Yokooojimisudoromachiatochou",
    "iso:country":"JP",
    "wof:name":"612-8239",
    "wof:placetype":"postalcode"
},
  "geometry": {"coordinates":[135.75210000000001,34.9309],"type":"Point"}
}