{
  "type": "Feature",
  "properties": {
    "gn:adm1_name":"Okayamaken",
    "gn:adm2_name":"Mitsugunmitsuchou",
    "gn:name":"Kase",
    "iso:country":"JP",
    "wof:name":"709-2131",
    "wof:placetype":"postalcode"
},
  "geometry": {"coordinates":[133.92689999999999,34.8375],"type":"Point"}
}