{
  "type": "Feature",
  "properties": {
    "gn:adm1_name":"Fukushimaken",
    "gn:adm2_name":"Nishishirakawagun'Omotegoumura",
    "gn:name":"Kaneyama",
    "iso:country":"JP",
    "wof:name":"961-0416",
    "wof:placetype":"postalcode"
},
  "geometry": {"coordinates":[140.298,37.0559],"type":"Point"}
}