{
  "type": "Feature",
  "properties": {
    "gn:adm1_name":"Hiroshimaken",
    "gn:adm2_name":"Mitsugigunmitsugichou",
    "gn:name":"Takao",
    "iso:country":"JP",
    "wof:name":"722-0353",
    "wof:placetype":"postalcode"
},
  "geometry": {"coordinates":[133.13820000000001,34.5179],"type":"Point"}
}