{
  "type": "Feature",
  "properties": {
    "gn:adm1_name":"Saitamaken",
    "gn:adm2_name":"Kumagayashi",
    "gn:name":"Tode",
    "iso:country":"JP",
    "wof:name":"360-0022",
    "wof:placetype":"postalcode"
},
  "geometry": {"coordinates":[139.40819999999999,36.1381],"type":"Point"}
}