{
  "type": "Feature",
  "properties": {
    "gn:adm1_name":"Kyoutofu",
    "gn:adm2_name":"Kyoutoshikamigyouku",
    "gn:name":"Kanzechou",
    "iso:country":"JP",
    "wof:name":"602-8441",
    "wof:placetype":"postalcode"
},
  "geometry": {"coordinates":[135.749,35.0305],"type":"Point"}
}