{
  "type": "Feature",
  "properties": {
    "gn:adm1_name":"Nagasakiken",
    "gn:adm2_name":"Minamitakakigun'Adumachou",
    "gn:name":"Kobamyou",
    "iso:country":"JP",
    "wof:name":"859-1102",
    "wof:placetype":"postalcode"
},
  "geometry": {"coordinates":[130.23099999999999,32.8076],"type":"Point"}
}