{
  "type": "Feature",
  "properties": {
    "gn:adm1_name":"Chibaken",
    "gn:adm2_name":"Kimitsushi",
    "gn:name":"Sugiyatsu",
    "iso:country":"JP",
    "wof:name":"299-1135",
    "wof:placetype":"postalcode"
},
  "geometry": {"coordinates":[139.91050000000001,35.3085],"type":"Point"}
}