{
  "type": "Feature",
  "properties": {
    "gn:adm1_name":"Oosakafu",
    "gn:adm2_name":"Kaidukashi",
    "gn:name":"Nishikikitamachi",
    "iso:country":"JP",
    "wof:name":"597-0092",
    "wof:placetype":"postalcode"
},
  "geometry": {"coordinates":[135.34379999999999,34.4598],"type":"Point"}
}