{
  "type": "Feature",
  "properties": {
    "gn:adm1_name":"Toukyouto",
    "gn:adm2_name":"Chiyodaku",
    "gn:name":"Uchikanda",
    "iso:country":"JP",
    "wof:name":"101-0047",
    "wof:placetype":"postalcode"
},
  "geometry": {"coordinates":[139.7679,35.691],"type":"Point"}
}