{
  "type": "Feature",
  "properties": {
    "gn:adm1_name":"Wakayamaken",
    "gn:adm2_name":"Wakayamashi",
    "gn:name":"Asahi",
    "iso:country":"JP",
    "wof:name":"640-0344",
    "wof:placetype":"postalcode"
},
  "geometry": {"coordinates":[135.21979999999999,34.1941],"type":"Point"}
}