{
  "type": "Feature",
  "properties": {
    "gn:adm1_name":"Fukuokaken",
    "gn:adm2_name":"Munakatagunfukumamachi",
    "gn:name":"Odake",
    "iso:country":"JP",
    "wof:name":"811-3226",
    "wof:placetype":"postalcode"
},
  "geometry": {"coordinates":[130.51570000000001,33.779],"type":"Point"}
}