{
  "type": "Feature",
  "properties": {
    "gn:adm1_name":"Saitamaken",
    "gn:adm2_name":"Satteshi",
    "gn:name":"Sakae",
    "iso:country":"JP",
    "wof:name":"340-0154",
    "wof:placetype":"postalcode"
},
  "geometry": {"coordinates":[139.7208,36.0569],"type":"Point"}
}