{
  "type": "Feature",
  "properties": {
    "gn:adm1_name":"Tottoriken",
    "gn:adm2_name":"Sakaiminatoshi",
    "gn:name":"Mugikakichou",
    "iso:country":"JP",
    "wof:name":"684-0052",
    "wof:placetype":"postalcode"
},
  "geometry": {"coordinates":[133.25069999999999,35.51],"type":"Point"}
}