{
  "type": "Feature",
  "properties": {
    "gn:adm1_name":"Niigataken",
    "gn:adm2_name":"Shironeshi",
    "gn:name":"Shinyamazakichou",
    "iso:country":"JP",
    "wof:name":"950-1245",
    "wof:placetype":"postalcode"
},
  "geometry": {"coordinates":[139.00620000000001,37.8085],"type":"Point"}
}