{
  "type": "Feature",
  "properties": {
    "gn:adm1_name":"Hyougoken",
    "gn:adm2_name":"Akoushi",
    "gn:name":"Mitsuhichou",
    "iso:country":"JP",
    "wof:name":"678-0245",
    "wof:placetype":"postalcode"
},
  "geometry": {"coordinates":[134.37739999999999,34.7536],"type":"Point"}
}