{
  "type": "Feature",
  "properties": {
    "gn:adm1_name":"Shigaken",
    "gn:adm2_name":"Ootsushi",
    "gn:name":"Katsuragawakidoguchichou",
    "iso:country":"JP",
    "wof:name":"520-0477",
    "wof:placetype":"postalcode"
},
  "geometry": {"coordinates":[135.86199999999999,35.2272],"type":"Point"}
}