{
  "type": "Feature",
  "properties": {
    "gn:adm1_name":"Wakayamaken",
    "gn:adm2_name":"Wakayamashi",
    "gn:name":"Ujiyabushita",
    "iso:country":"JP",
    "wof:name":"640-8071",
    "wof:placetype":"postalcode"
},
  "geometry": {"coordinates":[135.17750000000001,34.2433],"type":"Point"}
}