{
  "type": "Feature",
  "properties": {
    "gn:adm1_name":"Fukuiken",
    "gn:adm2_name":"Tsurugashi",
    "gn:name":"Kushikawa",
    "iso:country":"JP",
    "wof:name":"914-0821",
    "wof:placetype":"postalcode"
},
  "geometry": {"coordinates":[136.04089999999999,35.6528],"type":"Point"}
}