{
  "type": "Feature",
  "properties": {
    "gn:adm1_name":"Shizuokaken",
    "gn:adm2_name":"Gotenbashi",
    "gn:name":"Midono",
    "iso:country":"JP",
    "wof:name":"412-0001",
    "wof:placetype":"postalcode"
},
  "geometry": {"coordinates":[138.8914,35.339],"type":"Point"}
}