{
  "type": "Feature",
  "properties": {
    "gn:adm1_name":"Fukushimaken",
    "gn:adm2_name":"Kooriyamashi",
    "gn:name":"Midorigaokahigashi",
    "iso:country":"JP",
    "wof:name":"963-0702",
    "wof:placetype":"postalcode"
},
  "geometry": {"coordinates":[140.43600000000001,37.3812],"type":"Point"}
}