{
  "type": "Feature",
  "properties": {
    "gn:adm1_name":"Oosakafu",
    "gn:adm2_name":"Yaoshi",
    "gn:name":"Ookubo",
    "iso:country":"JP",
    "wof:name":"581-0863",
    "wof:placetype":"postalcode"
},
  "geometry": {"coordinates":[135.64420000000001,34.6299],"type":"Point"}
}