{
  "type": "Feature",
  "properties": {
    "gn:adm1_name":"Toyamaken",
    "gn:adm2_name":"Toyamashi",
    "gn:name":"Yoshikura",
    "iso:country":"JP",
    "wof:name":"939-8244",
    "wof:placetype":"postalcode"
},
  "geometry": {"coordinates":[137.19159999999999,36.6223],"type":"Point"}
}