{
  "type": "Feature",
  "properties": {
    "gn:adm1_name":"Yamagataken",
    "gn:adm2_name":"Higashitagawagun'Amarumemachi",
    "gn:name":"Oono",
    "iso:country":"JP",
    "wof:name":"999-7747",
    "wof:placetype":"postalcode"
},
  "geometry": {"coordinates":[139.90119999999999,38.8086],"type":"Point"}
}