{
  "type": "Feature",
  "properties": {
    "gn:adm1_name":"Hyougoken",
    "gn:adm2_name":"Himejishi",
    "gn:name":"Shikitouchoutoyokuni",
    "iso:country":"JP",
    "wof:name":"671-0219",
    "wof:placetype":"postalcode"
},
  "geometry": {"coordinates":[134.74369999999999,34.8431],"type":"Point"}
}