{
  "type": "Feature",
  "properties": {
    "gn:adm1_name":"Miyagiken",
    "gn:adm2_name":"Tagajoushi",
    "gn:name":"Niida",
    "iso:country":"JP",
    "wof:name":"985-0854",
    "wof:placetype":"postalcode"
},
  "geometry": {"coordinates":[140.96440000000001,38.2928],"type":"Point"}
}