{
  "type": "Feature",
  "properties": {
    "gn:adm1_name":"Fukuokaken",
    "gn:adm2_name":"Munakatashi",
    "gn:name":"Magari",
    "iso:country":"JP",
    "wof:name":"811-3413",
    "wof:placetype":"postalcode"
},
  "geometry": {"coordinates":[130.5625,33.7973],"type":"Point"}
}