{
  "type": "Feature",
  "properties": {
    "gn:adm1_name":"Ibarakiken",
    "gn:adm2_name":"Hitachinakashi",
    "gn:name":"Takaba",
    "iso:country":"JP",
    "wof:name":"312-0062",
    "wof:placetype":"postalcode"
},
  "geometry": {"coordinates":[140.5376,36.4253],"type":"Point"}
}