{
  "type": "Feature",
  "properties": {
    "gn:adm1_name":"Miyazakiken",
    "gn:adm2_name":"Hyuugashi",
    "gn:name":"Saiwaki",
    "iso:country":"JP",
    "wof:name":"889-1112",
    "wof:placetype":"postalcode"
},
  "geometry": {"coordinates":[131.61109999999999,32.3442],"type":"Point"}
}