{
  "type": "Feature",
  "properties": {
    "gn:adm1_name":"Toyamaken",
    "gn:adm2_name":"Takaokashi",
    "gn:name":"Toideyoshizumishin",
    "iso:country":"JP",
    "wof:name":"939-1115",
    "wof:placetype":"postalcode"
},
  "geometry": {"coordinates":[136.98859999999999,36.6718],"type":"Point"}
}