{
  "type": "Feature",
  "properties": {
    "gn:adm1_name":"Ishikawaken",
    "gn:adm2_name":"Ishikawagunkawachimura",
    "gn:name":"Kubo",
    "iso:country":"JP",
    "wof:name":"920-2313",
    "wof:placetype":"postalcode"
},
  "geometry": {"coordinates":[136.6377,36.3854],"type":"Point"}
}