{
  "type": "Feature",
  "properties": {
    "gn:adm1_name":"Hyougoken",
    "gn:adm2_name":"Kawanishishi",
    "gn:name":"Higashiuneno",
    "iso:country":"JP",
    "wof:name":"666-0117",
    "wof:placetype":"postalcode"
},
  "geometry": {"coordinates":[135.41030000000001,34.8861],"type":"Point"}
}