{
  "type": "Feature",
  "properties": {
    "gn:adm1_name":"Kyoutofu",
    "gn:adm2_name":"Kyoutoshikamigyouku",
    "gn:name":"Bueijinchou",
    "iso:country":"JP",
    "wof:name":"602-8029",
    "wof:placetype":"postalcode"
},
  "geometry": {"coordinates":[135.75790000000001,35.019],"type":"Point"}
}