{
  "type": "Feature",
  "properties": {
    "gn:adm1_name":"Hyougoken",
    "gn:adm2_name":"Mikatagun'Onsenchou",
    "gn:name":"Ishibashi",
    "iso:country":"JP",
    "wof:name":"669-6953",
    "wof:placetype":"postalcode"
},
  "geometry": {"coordinates":[134.4513,35.5009],"type":"Point"}
}