{
  "type": "Feature",
  "properties": {
    "gn:adm1_name":"Sagaken",
    "gn:adm2_name":"Sagashi",
    "gn:name":"Shin'Einishi",
    "iso:country":"JP",
    "wof:name":"840-0859",
    "wof:placetype":"postalcode"
},
  "geometry": {"coordinates":[130.27330000000001,33.2524],"type":"Point"}
}