{
  "type": "Feature",
  "properties": {
    "gn:adm1_name":"Hyougoken",
    "gn:adm2_name":"Koubeshichuuouku",
    "gn:name":"Nunobikichou",
    "iso:country":"JP",
    "wof:name":"651-0097",
    "wof:placetype":"postalcode"
},
  "geometry": {"coordinates":[135.19450000000001,34.6984],"type":"Point"}
}