{
  "type": "Feature",
  "properties": {
    "gn:adm1_name":"Ehimeken",
    "gn:adm2_name":"Houjoushi",
    "gn:name":"Takata",
    "iso:country":"JP",
    "wof:name":"799-2422",
    "wof:placetype":"postalcode"
},
  "geometry": {"coordinates":[132.80080000000001,33.9679],"type":"Point"}
}