{
  "type": "Feature",
  "properties": {
    "gn:adm1_name":"Okayamaken",
    "gn:adm2_name":"Akaiwagunsanyouchou",
    "gn:name":"Takaya",
    "iso:country":"JP",
    "wof:name":"709-0811",
    "wof:placetype":"postalcode"
},
  "geometry": {"coordinates":[134.02260000000001,34.7584],"type":"Point"}
}