{
  "type": "Feature",
  "properties": {
    "gn:adm1_name":"Chibaken",
    "gn:adm2_name":"Mobarashi",
    "gn:name":"Ooshiba",
    "iso:country":"JP",
    "wof:name":"297-0033",
    "wof:placetype":"postalcode"
},
  "geometry": {"coordinates":[140.31710000000001,35.4096],"type":"Point"}
}