{
  "type": "Feature",
  "properties": {
    "gn:adm1_name":"Okayamaken",
    "gn:adm2_name":"Okayamashi",
    "gn:name":"Matsuhamachou",
    "iso:country":"JP",
    "wof:name":"702-8038",
    "wof:placetype":"postalcode"
},
  "geometry": {"coordinates":[133.94149999999999,34.6127],"type":"Point"}
}