{
  "type": "Feature",
  "properties": {
    "gn:adm1_name":"Hyougoken",
    "gn:adm2_name":"Amagasakishi",
    "gn:name":"Higashitakasuchou",
    "iso:country":"JP",
    "wof:name":"660-0841",
    "wof:placetype":"postalcode"
},
  "geometry": {"coordinates":[135.41229999999999,34.7074],"type":"Point"}
}