{
  "type": "Feature",
  "properties": {
    "gn:adm1_name":"Fukushimaken",
    "gn:adm2_name":"Dategunkunimimachi",
    "gn:name":"Tottori",
    "iso:country":"JP",
    "wof:name":"969-1783",
    "wof:placetype":"postalcode"
},
  "geometry": {"coordinates":[140.5264,37.8912],"type":"Point"}
}