{
  "type": "Feature",
  "properties": {
    "gn:adm1_name":"Kyoutofu",
    "gn:adm2_name":"Sourakugunwadukachou",
    "gn:name":"Yubune",
    "iso:country":"JP",
    "wof:name":"619-1203",
    "wof:placetype":"postalcode"
},
  "geometry": {"coordinates":[135.94900000000001,34.8307],"type":"Point"}
}