{
  "type": "Feature",
  "properties": {
    "gn:adm1_name":"Aichiken",
    "gn:adm2_name":"Komakishi",
    "gn:name":"Takane",
    "iso:country":"JP",
    "wof:name":"485-0803",
    "wof:placetype":"postalcode"
},
  "geometry": {"coordinates":[136.97640000000001,35.2905],"type":"Point"}
}