{
  "type": "Feature",
  "properties": {
    "gn:adm1_name":"Yamaguchiken",
    "gn:adm2_name":"Abugun'Abuchou",
    "gn:name":"Kiyo",
    "iso:country":"JP",
    "wof:name":"759-3621",
    "wof:placetype":"postalcode"
},
  "geometry": {"coordinates":[131.50540000000001,34.5346],"type":"Point"}
}