{
  "type": "Feature",
  "properties": {
    "gn:adm1_name":"Ishikawaken",
    "gn:adm2_name":"Komatsushi",
    "gn:name":"Hondaikuchou",
    "iso:country":"JP",
    "wof:name":"923-0936",
    "wof:placetype":"postalcode"
},
  "geometry": {"coordinates":[136.446,36.4012],"type":"Point"}
}