{
  "type": "Feature",
  "properties": {
    "gn:adm1_name":"Kyoutofu",
    "gn:adm2_name":"Miyadushi",
    "gn:name":"Kaibara",
    "iso:country":"JP",
    "wof:name":"626-0063",
    "wof:placetype":"postalcode"
},
  "geometry": {"coordinates":[135.2157,35.5334],"type":"Point"}
}