{
  "type": "Feature",
  "properties": {
    "gn:adm1_name":"Gifuken",
    "gn:adm2_name":"Takayamashi",
    "gn:name":"Akebonomachi",
    "iso:country":"JP",
    "wof:name":"506-0806",
    "wof:placetype":"postalcode"
},
  "geometry": {"coordinates":[137.26740000000001,36.1477],"type":"Point"}
}