{
  "type": "Feature",
  "properties": {
    "gn:adm1_name":"Kouchiken",
    "gn:adm2_name":"Takaokagunhayamamura",
    "gn:name":"Kabanokawa",
    "iso:country":"JP",
    "wof:name":"785-0206",
    "wof:placetype":"postalcode"
},
  "geometry": {"coordinates":[133.23179999999999,33.4468],"type":"Point"}
}