{
  "type": "Feature",
  "properties": {
    "gn:adm1_name":"Shigaken",
    "gn:adm2_name":"Koukagunkouseichou",
    "gn:name":"Hiramatsu",
    "iso:country":"JP",
    "wof:name":"520-3232",
    "wof:placetype":"postalcode"
},
  "geometry": {"coordinates":[136.07830000000001,34.9982],"type":"Point"}
}