{
  "type": "Feature",
  "properties": {
    "gn:adm1_name":"Aichiken",
    "gn:adm2_name":"Inuyamashi",
    "gn:name":"Hagurosakae",
    "iso:country":"JP",
    "wof:name":"484-0893",
    "wof:placetype":"postalcode"
},
  "geometry": {"coordinates":[136.9554,35.3571],"type":"Point"}
}