{
  "type": "Feature",
  "properties": {
    "gn:adm1_name":"Wakayamaken",
    "gn:adm2_name":"Nagagun'Uchitachou",
    "gn:name":"Kurotsuchi",
    "iso:country":"JP",
    "wof:name":"649-6412",
    "wof:placetype":"postalcode"
},
  "geometry": {"coordinates":[135.40889999999999,34.236],"type":"Point"}
}