{
  "type": "Feature",
  "properties": {
    "gn:adm1_name":"Kyoutofu",
    "gn:adm2_name":"Kyoutoshifushimiku",
    "gn:name":"Shimonakachou",
    "iso:country":"JP",
    "wof:name":"612-8216",
    "wof:placetype":"postalcode"
},
  "geometry": {"coordinates":[135.75659999999999,34.9293],"type":"Point"}
}