{
  "type": "Feature",
  "properties": {
    "gn:adm1_name":"Ibarakiken",
    "gn:adm2_name":"Sashimagunsashimamachi",
    "gn:name":"Kuriyamashinden",
    "iso:country":"JP",
    "wof:name":"306-0513",
    "wof:placetype":"postalcode"
},
  "geometry": {"coordinates":[139.9111,36.1058],"type":"Point"}
}