{
  "type": "Feature",
  "properties": {
    "gn:adm1_name":"Gunmaken",
    "gn:adm2_name":"Agatsumagunnakanojoumachi",
    "gn:name":"Yamada(Sonota)",
    "iso:country":"JP",
    "wof:name":"377-0434",
    "wof:placetype":"postalcode"
},
  "geometry": {"coordinates":[138.79660000000001,36.5963],"type":"Point"}
}