{
  "type": "Feature",
  "properties": {
    "gn:adm1_name":"Mieken",
    "gn:adm2_name":"Wataraigunwataraichou",
    "gn:name":"Ookubo",
    "iso:country":"JP",
    "wof:name":"516-2106",
    "wof:placetype":"postalcode"
},
  "geometry": {"coordinates":[136.5924,34.4377],"type":"Point"}
}