{
  "type": "Feature",
  "properties": {
    "gn:adm1_name":"Fukushimaken",
    "gn:adm2_name":"Higashishirakawaguntanaguramachi",
    "gn:name":"Sakasagawa",
    "iso:country":"JP",
    "wof:name":"963-6103",
    "wof:placetype":"postalcode"
},
  "geometry": {"coordinates":[140.37430000000001,37.0569],"type":"Point"}
}