{
  "type": "Feature",
  "properties": {
    "gn:adm1_name":"Niigataken",
    "gn:adm2_name":"Minamikanbaragunsakaemachi",
    "gn:name":"Fukushimashinden",
    "iso:country":"JP",
    "wof:name":"959-1156",
    "wof:placetype":"postalcode"
},
  "geometry": {"coordinates":[138.91839999999999,37.5969],"type":"Point"}
}