{
  "type": "Feature",
  "properties": {
    "gn:adm1_name":"Kanagawaken",
    "gn:adm2_name":"Yokohamashiasahiku",
    "gn:name":"Shirane",
    "iso:country":"JP",
    "wof:name":"241-0005",
    "wof:placetype":"postalcode"
},
  "geometry": {"coordinates":[139.54830000000001,35.4845],"type":"Point"}
}