{
  "type": "Feature",
  "properties": {
    "gn:adm1_name":"Toukyouto",
    "gn:adm2_name":"Akirunoshi",
    "gn:name":"Hirasawa",
    "iso:country":"JP",
    "wof:name":"197-0812",
    "wof:placetype":"postalcode"
},
  "geometry": {"coordinates":[139.31100000000001,35.7321],"type":"Point"}
}