{
  "type": "Feature",
  "properties": {
    "gn:adm1_name":"Oosakafu",
    "gn:adm2_name":"Sennangunkumatorichou",
    "gn:name":"Satsukigaoka",
    "iso:country":"JP",
    "wof:name":"590-0445",
    "wof:placetype":"postalcode"
},
  "geometry": {"coordinates":[135.3708,34.399],"type":"Point"}
}