{
  "type": "Feature",
  "properties": {
    "gn:adm1_name":"Mieken",
    "gn:adm2_name":"Nabarishi",
    "gn:name":"Umegaokakita3banchou",
    "iso:country":"JP",
    "wof:name":"518-0748",
    "wof:placetype":"postalcode"
},
  "geometry": {"coordinates":[136.08619999999999,34.6382],"type":"Point"}
}