{
  "type": "Feature",
  "properties": {
    "gn:adm1_name":"Ishikawaken",
    "gn:adm2_name":"Hakuishi",
    "gn:name":"Takidanimachi",
    "iso:country":"JP",
    "wof:name":"925-0002",
    "wof:placetype":"postalcode"
},
  "geometry": {"coordinates":[136.7783,36.9534],"type":"Point"}
}