{
  "type": "Feature",
  "properties": {
    "gn:adm1_name":"Naganoken",
    "gn:adm2_name":"Inashi",
    "gn:name":"Misuzu",
    "iso:country":"JP",
    "wof:name":"396-0111",
    "wof:placetype":"postalcode"
},
  "geometry": {"coordinates":[138.00640000000001,35.8416],"type":"Point"}
}