{
  "type": "Feature",
  "properties": {
    "gn:adm1_name":"Toukyouto",
    "gn:adm2_name":"Komaeshi",
    "gn:name":"Nishiizumi",
    "iso:country":"JP",
    "wof:name":"201-0011",
    "wof:placetype":"postalcode"
},
  "geometry": {"coordinates":[139.56389999999999,35.6386],"type":"Point"}
}