{
  "type": "Feature",
  "properties": {
    "gn:adm1_name":"Yamaguchiken",
    "gn:adm2_name":"Shuunanshi",
    "gn:name":"Ginza",
    "iso:country":"JP",
    "wof:name":"745-0032",
    "wof:placetype":"postalcode"
},
  "geometry": {"coordinates":[131.80500000000001,34.0506],"type":"Point"}
}