{
  "type": "Feature",
  "properties": {
    "gn:adm1_name":"Yamagataken",
    "gn:adm2_name":"Nagaishi",
    "gn:name":"Saiwaichou",
    "iso:country":"JP",
    "wof:name":"993-0051",
    "wof:placetype":"postalcode"
},
  "geometry": {"coordinates":[140.02930000000001,38.112],"type":"Point"}
}