{
  "type": "Feature",
  "properties": {
    "gn:adm1_name":"Toukyouto",
    "gn:adm2_name":"Shinjukuku",
    "gn:name":"Honshiochou",
    "iso:country":"JP",
    "wof:name":"160-0003",
    "wof:placetype":"postalcode"
},
  "geometry": {"coordinates":[139.7295,35.6894],"type":"Point"}
}