{
  "type": "Feature",
  "properties": {
    "gn:adm1_name":"Fukushimaken",
    "gn:adm2_name":"Dategunkawamatamachi",
    "gn:name":"Tsubogasaku",
    "iso:country":"JP",
    "wof:name":"960-1483",
    "wof:placetype":"postalcode"
},
  "geometry": {"coordinates":[140.60499999999999,37.672],"type":"Point"}
}