{
  "type": "Feature",
  "properties": {
    "gn:adm1_name":"Hyougoken",
    "gn:adm2_name":"Koubeshichuuouku",
    "gn:name":"Minatojimanakamachi",
    "iso:country":"JP",
    "wof:name":"650-0046",
    "wof:placetype":"postalcode"
},
  "geometry": {"coordinates":[135.21250000000001,34.6688],"type":"Point"}
}