{
  "type": "Feature",
  "properties": {
    "gn:adm1_name":"Kagoshimaken",
    "gn:adm2_name":"Ooshimagun'Amagichou",
    "gn:name":"Setaki",
    "iso:country":"JP",
    "wof:name":"891-7623",
    "wof:placetype":"postalcode"
},
  "geometry": {"coordinates":[128.91030000000001,27.779],"type":"Point"}
}