{
  "type": "Feature",
  "properties": {
    "gn:adm1_name":"Kumamotoken",
    "gn:adm2_name":"Shimomashikiguntomiaimachi",
    "gn:name":"Kokuchou",
    "iso:country":"JP",
    "wof:name":"861-4162",
    "wof:placetype":"postalcode"
},
  "geometry": {"coordinates":[130.66669999999999,32.7176],"type":"Point"}
}