{
  "type": "Feature",
  "properties": {
    "gn:adm1_name":"Hyougoken",
    "gn:adm2_name":"Nishiwakishi",
    "gn:name":"Nishidachou",
    "iso:country":"JP",
    "wof:name":"677-0003",
    "wof:placetype":"postalcode"
},
  "geometry": {"coordinates":[134.95959999999999,35.0128],"type":"Point"}
}