{
  "type": "Feature",
  "properties": {
    "gn:adm1_name":"Shigaken",
    "gn:adm2_name":"Koukagunminakuchichou",
    "gn:name":"Hakkou",
    "iso:country":"JP",
    "wof:name":"528-0021",
    "wof:placetype":"postalcode"
},
  "geometry": {"coordinates":[136.16990000000001,34.9705],"type":"Point"}
}