{
  "type": "Feature",
  "properties": {
    "gn:adm1_name":"Shimaneken",
    "gn:adm2_name":"Izumoshi",
    "gn:name":"Imaichichou",
    "iso:country":"JP",
    "wof:name":"693-0001",
    "wof:placetype":"postalcode"
},
  "geometry": {"coordinates":[132.75800000000001,35.3644],"type":"Point"}
}