{
  "type": "Feature",
  "properties": {
    "gn:adm1_name":"Miyagiken",
    "gn:adm2_name":"Motoyoshigunmotoyoshichou",
    "gn:name":"Saruuchi",
    "iso:country":"JP",
    "wof:name":"988-0279",
    "wof:placetype":"postalcode"
},
  "geometry": {"coordinates":[141.54429999999999,38.8093],"type":"Point"}
}