{
  "type": "Feature",
  "properties": {
    "gn:adm1_name":"Ibarakiken",
    "gn:adm2_name":"Kogashi",
    "gn:name":"Asahichou",
    "iso:country":"JP",
    "wof:name":"306-0012",
    "wof:placetype":"postalcode"
},
  "geometry": {"coordinates":[139.72329999999999,36.1974],"type":"Point"}
}