{
  "type": "Feature",
  "properties": {
    "gn:adm1_name":"Toyamaken",
    "gn:adm2_name":"Toyamashi",
    "gn:name":"Oshiage",
    "iso:country":"JP",
    "wof:name":"939-8243",
    "wof:placetype":"postalcode"
},
  "geometry": {"coordinates":[137.1893,36.6152],"type":"Point"}
}