{
  "type": "Feature",
  "properties": {
    "gn:adm1_name":"Gifuken",
    "gn:adm2_name":"Sekishi",
    "gn:name":"Tentokuchou",
    "iso:country":"JP",
    "wof:name":"501-3915",
    "wof:placetype":"postalcode"
},
  "geometry": {"coordinates":[136.9323,35.4768],"type":"Point"}
}