{
  "type": "Feature",
  "properties": {
    "gn:adm1_name":"Saitamaken",
    "gn:adm2_name":"Irumashi",
    "gn:name":"Shinkou",
    "iso:country":"JP",
    "wof:name":"358-0055",
    "wof:placetype":"postalcode"
},
  "geometry": {"coordinates":[139.35489999999999,35.8553],"type":"Point"}
}