{
  "type": "Feature",
  "properties": {
    "gn:adm1_name":"Fukuokaken",
    "gn:adm2_name":"Asakuragunmiwamachi",
    "gn:name":"Takoe",
    "iso:country":"JP",
    "wof:name":"838-0822",
    "wof:placetype":"postalcode"
},
  "geometry": {"coordinates":[130.6258,33.429],"type":"Point"}
}