{
  "type": "Feature",
  "properties": {
    "gn:adm1_name":"Hiroshimaken",
    "gn:adm2_name":"Hiroshimashiakiku",
    "gn:name":"Senonishi",
    "iso:country":"JP",
    "wof:name":"739-0313",
    "wof:placetype":"postalcode"
},
  "geometry": {"coordinates":[132.5924,34.4294],"type":"Point"}
}