{
  "type": "Feature",
  "properties": {
    "gn:adm1_name":"Wakayamaken",
    "gn:adm2_name":"Hashimotoshi",
    "gn:name":"Sudachoushimohyougo",
    "iso:country":"JP",
    "wof:name":"648-0016",
    "wof:placetype":"postalcode"
},
  "geometry": {"coordinates":[135.63220000000001,34.3238],"type":"Point"}
}