{
  "type": "Feature",
  "properties": {
    "gn:adm1_name":"Wakayamaken",
    "gn:adm2_name":"Hidakagunminabegawamura",
    "gn:name":"Higashihonjou",
    "iso:country":"JP",
    "wof:name":"645-0021",
    "wof:placetype":"postalcode"
},
  "geometry": {"coordinates":[135.33609999999999,33.8033],"type":"Point"}
}