{
  "type": "Feature",
  "properties": {
    "gn:adm1_name":"Hyougoken",
    "gn:adm2_name":"Tsunagun'Ichinomiyachou",
    "gn:name":"Irino",
    "iso:country":"JP",
    "wof:name":"656-1552",
    "wof:placetype":"postalcode"
},
  "geometry": {"coordinates":[134.83000000000001,34.4311],"type":"Point"}
}