{
  "type": "Feature",
  "properties": {
    "gn:adm1_name":"Kanagawaken",
    "gn:adm2_name":"Yokosukashi",
    "gn:name":"Natsushimachou",
    "iso:country":"JP",
    "wof:name":"237-0061",
    "wof:placetype":"postalcode"
},
  "geometry": {"coordinates":[139.64359999999999,35.322],"type":"Point"}
}