{
  "type": "Feature",
  "properties": {
    "gn:adm1_name":"Aichiken",
    "gn:adm2_name":"Chitagunhigashiurachou",
    "gn:name":"Ishihama",
    "iso:country":"JP",
    "wof:name":"470-2103",
    "wof:placetype":"postalcode"
},
  "geometry": {"coordinates":[136.9658,34.9669],"type":"Point"}
}