{
  "type": "Feature",
  "properties": {
    "gn:adm1_name":"Kyoutofu",
    "gn:adm2_name":"Kyoutoshikamigyouku",
    "gn:name":"Nishinokuchichou",
    "iso:country":"JP",
    "wof:name":"602-0925",
    "wof:placetype":"postalcode"
},
  "geometry": {"coordinates":[135.75479999999999,35.0264],"type":"Point"}
}