{
  "type": "Feature",
  "properties": {
    "gn:adm1_name":"Fukuiken",
    "gn:adm2_name":"Nyuugun'Asahichou",
    "gn:name":"Kanaya",
    "iso:country":"JP",
    "wof:name":"916-0151",
    "wof:placetype":"postalcode"
},
  "geometry": {"coordinates":[136.11089999999999,35.9656],"type":"Point"}
}