{
  "type": "Feature",
  "properties": {
    "gn:adm1_name":"Gunmaken",
    "gn:adm2_name":"Ouragun'Ooizumimachi",
    "gn:name":"Sengoku",
    "iso:country":"JP",
    "wof:name":"370-0533",
    "wof:placetype":"postalcode"
},
  "geometry": {"coordinates":[139.39660000000001,36.2428],"type":"Point"}
}