{
  "type": "Feature",
  "properties": {
    "gn:adm1_name":"Toyamaken",
    "gn:adm2_name":"Toyamashi",
    "gn:name":"Taroumarunishimachi",
    "iso:country":"JP",
    "wof:name":"939-8271",
    "wof:placetype":"postalcode"
},
  "geometry": {"coordinates":[137.20920000000001,36.677],"type":"Point"}
}