{
  "type": "Feature",
  "properties": {
    "gn:adm1_name":"Aichiken",
    "gn:adm2_name":"Komakishi",
    "gn:name":"Kokinishi",
    "iso:country":"JP",
    "wof:name":"485-0057",
    "wof:placetype":"postalcode"
},
  "geometry": {"coordinates":[136.89160000000001,35.2768],"type":"Point"}
}