{
  "type": "Feature",
  "properties": {
    "gn:adm1_name":"Naganoken",
    "gn:adm2_name":"Naganoshi",
    "gn:name":"Matsushiromachinishijou",
    "iso:country":"JP",
    "wof:name":"381-1232",
    "wof:placetype":"postalcode"
},
  "geometry": {"coordinates":[138.2046,36.5498],"type":"Point"}
}