{
  "type": "Feature",
  "properties": {
    "gn:adm1_name":"Fukuiken",
    "gn:adm2_name":"Nyuugun'Otachou",
    "gn:name":"Naka",
    "iso:country":"JP",
    "wof:name":"916-0204",
    "wof:placetype":"postalcode"
},
  "geometry": {"coordinates":[136.05170000000001,35.962],"type":"Point"}
}