{
  "type": "Feature",
  "properties": {
    "gn:adm1_name":"Kagoshimaken",
    "gn:adm2_name":"Ibusukishi",
    "gn:name":"Iwamoto",
    "iso:country":"JP",
    "wof:name":"891-0315",
    "wof:placetype":"postalcode"
},
  "geometry": {"coordinates":[130.60140000000001,31.2901],"type":"Point"}
}