{
  "type": "Feature",
  "properties": {
    "gn:adm1_name":"Ibarakiken",
    "gn:adm2_name":"Kashimagunkamisumachi",
    "gn:name":"Nikkawa",
    "iso:country":"JP",
    "wof:name":"314-0114",
    "wof:placetype":"postalcode"
},
  "geometry": {"coordinates":[140.69579999999999,35.8587],"type":"Point"}
}