{
  "type": "Feature",
  "properties": {
    "gn:adm1_name":"Nagasakiken",
    "gn:adm2_name":"Isahayashi",
    "gn:name":"Tenjinchou",
    "iso:country":"JP",
    "wof:name":"854-0123",
    "wof:placetype":"postalcode"
},
  "geometry": {"coordinates":[130.06020000000001,32.8002],"type":"Point"}
}