{
  "type": "Feature",
  "properties": {
    "gn:adm1_name":"Yamagataken",
    "gn:adm2_name":"Nanyoushi",
    "gn:name":"Ringou",
    "iso:country":"JP",
    "wof:name":"992-0477",
    "wof:placetype":"postalcode"
},
  "geometry": {"coordinates":[140.08779999999999,38.0536],"type":"Point"}
}