{
  "type": "Feature",
  "properties": {
    "gn:adm1_name":"Miyazakiken",
    "gn:adm2_name":"Nobeokashi",
    "gn:name":"Furukawamachi",
    "iso:country":"JP",
    "wof:name":"882-0063",
    "wof:placetype":"postalcode"
},
  "geometry": {"coordinates":[131.65010000000001,32.5871],"type":"Point"}
}