{
  "type": "Feature",
  "properties": {
    "gn:adm1_name":"Tottoriken",
    "gn:adm2_name":"Saihakugunyodoechou",
    "gn:name":"Fukuoka",
    "iso:country":"JP",
    "wof:name":"689-3411",
    "wof:placetype":"postalcode"
},
  "geometry": {"coordinates":[133.4435,35.4551],"type":"Point"}
}