{
  "type": "Feature",
  "properties": {
    "gn:adm1_name":"Kyoutofu",
    "gn:adm2_name":"Kyoutoshinakagyouku",
    "gn:name":"Mibuamagaikechou",
    "iso:country":"JP",
    "wof:name":"604-8874",
    "wof:placetype":"postalcode"
},
  "geometry": {"coordinates":[135.74019999999999,35.0072],"type":"Point"}
}