{
  "type": "Feature",
  "properties": {
    "gn:adm1_name":"Fukuiken",
    "gn:adm2_name":"Oonogun'Izumimura",
    "gn:name":"Nagano",
    "iso:country":"JP",
    "wof:name":"912-0214",
    "wof:placetype":"postalcode"
},
  "geometry": {"coordinates":[136.6677,35.8823],"type":"Point"}
}