{
  "type": "Feature",
  "properties": {
    "gn:adm1_name":"Niigataken",
    "gn:adm2_name":"Kitakanbaragunsasakamimura",
    "gn:name":"Hatae",
    "iso:country":"JP",
    "wof:name":"959-1924",
    "wof:placetype":"postalcode"
},
  "geometry": {"coordinates":[139.29849999999999,37.8241],"type":"Point"}
}