{
  "type": "Feature",
  "properties": {
    "gn:adm1_name":"Kyoutofu",
    "gn:adm2_name":"Maidurushi",
    "gn:name":"Shin",
    "iso:country":"JP",
    "wof:name":"624-0933",
    "wof:placetype":"postalcode"
},
  "geometry": {"coordinates":[135.32419999999999,35.449],"type":"Point"}
}