{
  "type": "Feature",
  "properties": {
    "gn:adm1_name":"Gifuken",
    "gn:adm2_name":"Sekishi",
    "gn:name":"Hasamadai",
    "iso:country":"JP",
    "wof:name":"501-3925",
    "wof:placetype":"postalcode"
},
  "geometry": {"coordinates":[136.92490000000001,35.4508],"type":"Point"}
}