{
  "type": "Feature",
  "properties": {
    "gn:adm1_name":"Gifuken",
    "gn:adm2_name":"Kamogunkawabechou",
    "gn:name":"Nakano",
    "iso:country":"JP",
    "wof:name":"509-0312",
    "wof:placetype":"postalcode"
},
  "geometry": {"coordinates":[137.0788,35.4909],"type":"Point"}
}