{
  "type": "Feature",
  "properties": {
    "gn:adm1_name":"Kyoutofu",
    "gn:adm2_name":"Kyoutoshifushimiku",
    "gn:name":"Momoyamafukushimadayuukitamachi",
    "iso:country":"JP",
    "wof:name":"612-0061",
    "wof:placetype":"postalcode"
},
  "geometry": {"coordinates":[135.7698,34.9392],"type":"Point"}
}