{
  "type": "Feature",
  "properties": {
    "gn:adm1_name":"Ishikawaken",
    "gn:adm2_name":"Nomiguntatsunokuchimachi",
    "gn:name":"Araya",
    "iso:country":"JP",
    "wof:name":"923-1233",
    "wof:placetype":"postalcode"
},
  "geometry": {"coordinates":[136.5257,36.4441],"type":"Point"}
}