{
  "type": "Feature",
  "properties": {
    "gn:adm1_name":"Ibarakiken",
    "gn:adm2_name":"Yuukigunyachiyomachi",
    "gn:name":"Hacchou",
    "iso:country":"JP",
    "wof:name":"300-3523",
    "wof:placetype":"postalcode"
},
  "geometry": {"coordinates":[139.90010000000001,36.1949],"type":"Point"}
}