{
  "type": "Feature",
  "properties": {
    "gn:adm1_name":"Ishikawaken",
    "gn:adm2_name":"Nomigunteraimachi",
    "gn:name":"Akitsune",
    "iso:country":"JP",
    "wof:name":"923-1103",
    "wof:placetype":"postalcode"
},
  "geometry": {"coordinates":[136.51650000000001,36.4475],"type":"Point"}
}