{
  "type": "Feature",
  "properties": {
    "gn:adm1_name":"Kyoutofu",
    "gn:adm2_name":"Ayabeshi",
    "gn:name":"Oitomichou",
    "iso:country":"JP",
    "wof:name":"623-1134",
    "wof:placetype":"postalcode"
},
  "geometry": {"coordinates":[135.47730000000001,35.4352],"type":"Point"}
}