{
  "type": "Feature",
  "properties": {
    "gn:adm1_name":"Ehimeken",
    "gn:adm2_name":"Matsuyamashi",
    "gn:name":"Idomachi",
    "iso:country":"JP",
    "wof:name":"791-1114",
    "wof:placetype":"postalcode"
},
  "geometry": {"coordinates":[132.78100000000001,33.7979],"type":"Point"}
}