{
  "type": "Feature",
  "properties": {
    "gn:adm1_name":"Naraken",
    "gn:adm2_name":"Narashi",
    "gn:name":"Obiraochou",
    "iso:country":"JP",
    "wof:name":"630-1243",
    "wof:placetype":"postalcode"
},
  "geometry": {"coordinates":[135.92529999999999,34.6819],"type":"Point"}
}