{
  "type": "Feature",
  "properties": {
    "gn:adm1_name":"Tottoriken",
    "gn:adm2_name":"Kurayoshishi",
    "gn:name":"Kitano",
    "iso:country":"JP",
    "wof:name":"682-0857",
    "wof:placetype":"postalcode"
},
  "geometry": {"coordinates":[133.79949999999999,35.4207],"type":"Point"}
}