{
  "type": "Feature",
  "properties": {
    "gn:adm1_name":"Fukuokaken",
    "gn:adm2_name":"Ongagun'Ongachou",
    "gn:name":"Ongagawa",
    "iso:country":"JP",
    "wof:name":"811-4307",
    "wof:placetype":"postalcode"
},
  "geometry": {"coordinates":[130.6722,33.8489],"type":"Point"}
}