{
  "type": "Feature",
  "properties": {
    "gn:adm1_name":"Chibaken",
    "gn:adm2_name":"Nodashi",
    "gn:name":"Sekiyadouchimachi",
    "iso:country":"JP",
    "wof:name":"270-0204",
    "wof:placetype":"postalcode"
},
  "geometry": {"coordinates":[139.78559999999999,36.0744],"type":"Point"}
}