{
  "type": "Feature",
  "properties": {
    "gn:adm1_name":"Kagoshimaken",
    "gn:adm2_name":"Ooshimagunsetouchichou",
    "gn:name":"Koniya(Funatsu)",
    "iso:country":"JP",
    "wof:name":"894-1506",
    "wof:placetype":"postalcode"
},
  "geometry": {"coordinates":[129.3142,28.1468],"type":"Point"}
}