{
  "type": "Feature",
  "properties": {
    "gn:adm1_name":"Gifuken",
    "gn:adm2_name":"Gifushi",
    "gn:name":"Kadoyaseihiki",
    "iso:country":"JP",
    "wof:name":"501-2527",
    "wof:placetype":"postalcode"
},
  "geometry": {"coordinates":[136.83179999999999,35.4983],"type":"Point"}
}