{
  "type": "Feature",
  "properties": {
    "gn:adm1_name":"Fukuiken",
    "gn:adm2_name":"Onyuugunkaminakachou",
    "gn:name":"Nagae",
    "iso:country":"JP",
    "wof:name":"919-1505",
    "wof:placetype":"postalcode"
},
  "geometry": {"coordinates":[135.86750000000001,35.4958],"type":"Point"}
}