{
  "type": "Feature",
  "properties": {
    "gn:adm1_name":"Fukuokaken",
    "gn:adm2_name":"Munakatashi",
    "gn:name":"Kubara",
    "iso:country":"JP",
    "wof:name":"811-3437",
    "wof:placetype":"postalcode"
},
  "geometry": {"coordinates":[130.54669999999999,33.7942],"type":"Point"}
}