{
  "type": "Feature",
  "properties": {
    "gn:adm1_name":"Fukushimaken",
    "gn:adm2_name":"Dategunkawamatamachi",
    "gn:name":"Kogami",
    "iso:country":"JP",
    "wof:name":"960-1407",
    "wof:placetype":"postalcode"
},
  "geometry": {"coordinates":[140.58250000000001,37.6765],"type":"Point"}
}