{
  "type": "Feature",
  "properties": {
    "gn:adm1_name":"Kagoshimaken",
    "gn:adm2_name":"Nishinoomoteshi",
    "gn:name":"Ikeda",
    "iso:country":"JP",
    "wof:name":"891-3114",
    "wof:placetype":"postalcode"
},
  "geometry": {"coordinates":[130.995,30.7298],"type":"Point"}
}