{
  "type": "Feature",
  "properties": {
    "gn:adm1_name":"Chibaken",
    "gn:adm2_name":"Kimitsushi",
    "gn:name":"Nutazawa",
    "iso:country":"JP",
    "wof:name":"292-1177",
    "wof:placetype":"postalcode"
},
  "geometry": {"coordinates":[140.0163,35.21],"type":"Point"}
}