{
  "type": "Feature",
  "properties": {
    "gn:adm1_name":"Kyoutofu",
    "gn:adm2_name":"Kyoutoshikamigyouku",
    "gn:name":"Nishikaminochou",
    "iso:country":"JP",
    "wof:name":"602-8361",
    "wof:placetype":"postalcode"
},
  "geometry": {"coordinates":[135.73599999999999,35.0229],"type":"Point"}
}