{
  "type": "Feature",
  "properties": {
    "gn:adm1_name":"Ehimeken",
    "gn:adm2_name":"Higashiuwagunnomurachou",
    "gn:name":"Nakatoogawa",
    "iso:country":"JP",
    "wof:name":"797-1325",
    "wof:placetype":"postalcode"
},
  "geometry": {"coordinates":[132.6694,33.4126],"type":"Point"}
}