{
  "type": "Feature",
  "properties": {
    "gn:adm1_name":"Ehimeken",
    "gn:adm2_name":"Umagundoichou",
    "gn:name":"Fujiwara",
    "iso:country":"JP",
    "wof:name":"799-0703",
    "wof:placetype":"postalcode"
},
  "geometry": {"coordinates":[133.44390000000001,33.9681],"type":"Point"}
}