{
  "type": "Feature",
  "properties": {
    "gn:adm1_name":"Fukuokaken",
    "gn:adm2_name":"Yamatogunmitsuhashimachi",
    "gn:name":"Okida",
    "iso:country":"JP",
    "wof:name":"832-0801",
    "wof:placetype":"postalcode"
},
  "geometry": {"coordinates":[130.44759999999999,33.1822],"type":"Point"}
}