{
  "type": "Feature",
  "properties": {
    "gn:adm1_name":"Niigataken",
    "gn:adm2_name":"Kitakanbaragunseiroumachi",
    "gn:name":"Sanga",
    "iso:country":"JP",
    "wof:name":"957-0122",
    "wof:placetype":"postalcode"
},
  "geometry": {"coordinates":[139.27590000000001,37.9613],"type":"Point"}
}