{
  "type": "Feature",
  "properties": {
    "gn:adm1_name":"Chibaken",
    "gn:adm2_name":"Abikoshi",
    "gn:name":"Honchou",
    "iso:country":"JP",
    "wof:name":"270-1151",
    "wof:placetype":"postalcode"
},
  "geometry": {"coordinates":[140.01179999999999,35.8716],"type":"Point"}
}