{
  "type": "Feature",
  "properties": {
    "gn:adm1_name":"Kumamotoken",
    "gn:adm2_name":"Kumamotoshi",
    "gn:name":"Minamikumamoto",
    "iso:country":"JP",
    "wof:name":"860-0812",
    "wof:placetype":"postalcode"
},
  "geometry": {"coordinates":[130.71100000000001,32.7883],"type":"Point"}
}