{
  "type": "Feature",
  "properties": {
    "gn:adm1_name":"Ibarakiken",
    "gn:adm2_name":"Tsuchiurashi",
    "gn:name":"Nakatsumachi",
    "iso:country":"JP",
    "wof:name":"300-0009",
    "wof:placetype":"postalcode"
},
  "geometry": {"coordinates":[140.1917,36.1246],"type":"Point"}
}