{
  "type": "Feature",
  "properties": {
    "gn:adm1_name":"Gunmaken",
    "gn:adm2_name":"Sawaguntamamuramachi",
    "gn:name":"Shimonomiya",
    "iso:country":"JP",
    "wof:name":"370-1112",
    "wof:placetype":"postalcode"
},
  "geometry": {"coordinates":[139.14879999999999,36.3021],"type":"Point"}
}