{
  "type": "Feature",
  "properties": {
    "gn:adm1_name":"Aichiken",
    "gn:adm2_name":"Toyohashishi",
    "gn:name":"Hatakedachou",
    "iso:country":"JP",
    "wof:name":"441-8121",
    "wof:placetype":"postalcode"
},
  "geometry": {"coordinates":[137.39429999999999,34.7085],"type":"Point"}
}