{
  "type": "Feature",
  "properties": {
    "gn:adm1_name":"Toyamaken",
    "gn:adm2_name":"Imizugun'Ooshimamachi",
    "gn:name":"Wakasugi",
    "iso:country":"JP",
    "wof:name":"939-0272",
    "wof:placetype":"postalcode"
},
  "geometry": {"coordinates":[137.05330000000001,36.7421],"type":"Point"}
}