{
  "type": "Feature",
  "properties": {
    "gn:adm1_name":"Kyoutofu",
    "gn:adm2_name":"Kyoutoshishimogyouku",
    "gn:name":"Konyachou",
    "iso:country":"JP",
    "wof:name":"600-8130",
    "wof:placetype":"postalcode"
},
  "geometry": {"coordinates":[135.7647,34.9911],"type":"Point"}
}