{
  "type": "Feature",
  "properties": {
    "gn:adm1_name":"Niigataken",
    "gn:adm2_name":"Nishikanbaragunmakimachi",
    "gn:name":"Matsuyamashinden",
    "iso:country":"JP",
    "wof:name":"953-0016",
    "wof:placetype":"postalcode"
},
  "geometry": {"coordinates":[138.86930000000001,37.7955],"type":"Point"}
}