{
  "type": "Feature",
  "properties": {
    "gn:adm1_name":"Naraken",
    "gn:adm2_name":"Goseshi",
    "gn:name":"Uchitani",
    "iso:country":"JP",
    "wof:name":"639-2267",
    "wof:placetype":"postalcode"
},
  "geometry": {"coordinates":[135.72130000000001,34.3948],"type":"Point"}
}