{
  "type": "Feature",
  "properties": {
    "gn:adm1_name":"Yamagataken",
    "gn:adm2_name":"Higashineshi",
    "gn:name":"Osanagikouji",
    "iso:country":"JP",
    "wof:name":"999-3757",
    "wof:placetype":"postalcode"
},
  "geometry": {"coordinates":[140.38929999999999,38.408],"type":"Point"}
}