{
  "type": "Feature",
  "properties": {
    "gn:adm1_name":"Fukushimaken",
    "gn:adm2_name":"Yamagunyamatomachi",
    "gn:name":"Sawajiri",
    "iso:country":"JP",
    "wof:name":"969-4166",
    "wof:placetype":"postalcode"
},
  "geometry": {"coordinates":[139.75749999999999,37.6415],"type":"Point"}
}