{
  "type": "Feature",
  "properties": {
    "gn:adm1_name":"Saitamaken",
    "gn:adm2_name":"Hannoushi",
    "gn:name":"Maeganuki",
    "iso:country":"JP",
    "wof:name":"357-0043",
    "wof:placetype":"postalcode"
},
  "geometry": {"coordinates":[139.31530000000001,35.8388],"type":"Point"}
}