{
  "type": "Feature",
  "properties": {
    "gn:adm1_name":"Niigataken",
    "gn:adm2_name":"Iwafunegunsekikawamura",
    "gn:name":"Nakamaruke",
    "iso:country":"JP",
    "wof:name":"959-3206",
    "wof:placetype":"postalcode"
},
  "geometry": {"coordinates":[139.57169999999999,38.1451],"type":"Point"}
}