{
  "type": "Feature",
  "properties": {
    "gn:adm1_name":"Toyamaken",
    "gn:adm2_name":"Nakaniikawagunkamiichimachi",
    "gn:name":"Kagichou",
    "iso:country":"JP",
    "wof:name":"930-0346",
    "wof:placetype":"postalcode"
},
  "geometry": {"coordinates":[137.3614,36.704],"type":"Point"}
}