{
  "type": "Feature",
  "properties": {
    "gn:adm1_name":"Naganoken",
    "gn:adm2_name":"Kamiinagunminowamachi",
    "gn:name":"Higashiminowa",
    "iso:country":"JP",
    "wof:name":"399-4602",
    "wof:placetype":"postalcode"
},
  "geometry": {"coordinates":[137.9984,35.9335],"type":"Point"}
}