{
  "type": "Feature",
  "properties": {
    "gn:adm1_name":"Kyoutofu",
    "gn:adm2_name":"Kyoutoshikitaku",
    "gn:name":"Oomiyahigashisoumonguchichou",
    "iso:country":"JP",
    "wof:name":"603-8833",
    "wof:placetype":"postalcode"
},
  "geometry": {"coordinates":[135.74629999999999,35.0575],"type":"Point"}
}