{
  "type": "Feature",
  "properties": {
    "gn:adm1_name":"Chibaken",
    "gn:adm2_name":"Shiroishi",
    "gn:name":"Shiroi",
    "iso:country":"JP",
    "wof:name":"270-1421",
    "wof:placetype":"postalcode"
},
  "geometry": {"coordinates":[140.06440000000001,35.8022],"type":"Point"}
}