{
  "type": "Feature",
  "properties": {
    "gn:adm1_name":"Tokushimaken",
    "gn:adm2_name":"Tokushimashi",
    "gn:name":"Higashishinmachi",
    "iso:country":"JP",
    "wof:name":"770-0912",
    "wof:placetype":"postalcode"
},
  "geometry": {"coordinates":[134.54810000000001,34.0697],"type":"Point"}
}