{
  "type": "Feature",
  "properties": {
    "gn:adm1_name":"Mieken",
    "gn:adm2_name":"Ayamagunshimagaharamura",
    "gn:name":"Nakaya",
    "iso:country":"JP",
    "wof:name":"519-1708",
    "wof:placetype":"postalcode"
},
  "geometry": {"coordinates":[136.0633,34.7805],"type":"Point"}
}