{
  "type": "Feature",
  "properties": {
    "gn:adm1_name":"Fukuiken",
    "gn:adm2_name":"Sabaeshi",
    "gn:name":"Yokogoshichou",
    "iso:country":"JP",
    "wof:name":"916-0036",
    "wof:placetype":"postalcode"
},
  "geometry": {"coordinates":[136.20230000000001,35.9471],"type":"Point"}
}