{
  "type": "Feature",
  "properties": {
    "gn:adm1_name":"Aichiken",
    "gn:adm2_name":"Handashi",
    "gn:name":"Genpeichou",
    "iso:country":"JP",
    "wof:name":"475-0816",
    "wof:placetype":"postalcode"
},
  "geometry": {"coordinates":[136.93639999999999,34.8932],"type":"Point"}
}