{
  "type": "Feature",
  "properties": {
    "gn:adm1_name":"Aichiken",
    "gn:adm2_name":"Inuyamashi",
    "gn:name":"Shimoyashiki",
    "iso:country":"JP",
    "wof:name":"484-0044",
    "wof:placetype":"postalcode"
},
  "geometry": {"coordinates":[136.97569999999999,35.3464],"type":"Point"}
}