{
  "type": "Feature",
  "properties": {
    "gn:adm1_name":"Oosakafu",
    "gn:adm2_name":"Izumiootsushi",
    "gn:name":"Ayai",
    "iso:country":"JP",
    "wof:name":"595-0001",
    "wof:placetype":"postalcode"
},
  "geometry": {"coordinates":[135.43559999999999,34.5139],"type":"Point"}
}