{
  "type": "Feature",
  "properties": {
    "gn:adm1_name":"Kanagawaken",
    "gn:adm2_name":"Odawarashi",
    "gn:name":"Minamikamonomiya",
    "iso:country":"JP",
    "wof:name":"250-0875",
    "wof:placetype":"postalcode"
},
  "geometry": {"coordinates":[139.17840000000001,35.2725],"type":"Point"}
}