{
  "type": "Feature",
  "properties": {
    "gn:adm1_name":"Nagasakiken",
    "gn:adm2_name":"Nagasakishi",
    "gn:name":"Tsutsujigaoka",
    "iso:country":"JP",
    "wof:name":"851-0102",
    "wof:placetype":"postalcode"
},
  "geometry": {"coordinates":[129.9615,32.8083],"type":"Point"}
}