{
  "type": "Feature",
  "properties": {
    "gn:adm1_name":"Nagasakiken",
    "gn:adm2_name":"Isahayashi",
    "gn:name":"Kurosakimachi",
    "iso:country":"JP",
    "wof:name":"854-0033",
    "wof:placetype":"postalcode"
},
  "geometry": {"coordinates":[130.0994,32.834],"type":"Point"}
}