{
  "type": "Feature",
  "properties": {
    "gn:adm1_name":"Toukyouto",
    "gn:adm2_name":"Suginamiku",
    "gn:name":"Amanuma",
    "iso:country":"JP",
    "wof:name":"167-0032",
    "wof:placetype":"postalcode"
},
  "geometry": {"coordinates":[139.62370000000001,35.7076],"type":"Point"}
}