{
  "type": "Feature",
  "properties": {
    "gn:adm1_name":"Tokushimaken",
    "gn:adm2_name":"Nakagunkaminakachou",
    "gn:name":"Haigyuu",
    "iso:country":"JP",
    "wof:name":"771-5518",
    "wof:placetype":"postalcode"
},
  "geometry": {"coordinates":[134.32599999999999,33.8217],"type":"Point"}
}