{
  "type": "Feature",
  "properties": {
    "gn:adm1_name":"Shizuokaken",
    "gn:adm2_name":"Shizuokashi",
    "gn:name":"Nakahira",
    "iso:country":"JP",
    "wof:name":"421-2305",
    "wof:placetype":"postalcode"
},
  "geometry": {"coordinates":[138.3595,35.1711],"type":"Point"}
}