{
  "type": "Feature",
  "properties": {
    "gn:adm1_name":"Aichiken",
    "gn:adm2_name":"Nagoyashinakagawaku",
    "gn:name":"Hokke",
    "iso:country":"JP",
    "wof:name":"454-0933",
    "wof:placetype":"postalcode"
},
  "geometry": {"coordinates":[136.8468,35.1273],"type":"Point"}
}