{
  "type": "Feature",
  "properties": {
    "gn:adm1_name":"Niigataken",
    "gn:adm2_name":"Santougunteradomarimachi",
    "gn:name":"Ooji",
    "iso:country":"JP",
    "wof:name":"940-2503",
    "wof:placetype":"postalcode"
},
  "geometry": {"coordinates":[138.78809999999999,37.638],"type":"Point"}
}