{
  "type": "Feature",
  "properties": {
    "gn:adm1_name":"Aichiken",
    "gn:adm2_name":"Nagoyashichikusaku",
    "gn:name":"Tashirochou(Shikannonmichinishi)",
    "iso:country":"JP",
    "wof:name":"464-0052",
    "wof:placetype":"postalcode"
},
  "geometry": {"coordinates":[136.95349999999999,35.1727],"type":"Point"}
}