{
  "type": "Feature",
  "properties": {
    "gn:adm1_name":"Naraken",
    "gn:adm2_name":"Narashi",
    "gn:name":"Nishishinzaikegoushochou",
    "iso:country":"JP",
    "wof:name":"630-8251",
    "wof:placetype":"postalcode"
},
  "geometry": {"coordinates":[135.82550000000001,34.6882],"type":"Point"}
}