{
  "type": "Feature",
  "properties": {
    "gn:adm1_name":"Oosakafu",
    "gn:adm2_name":"Oosakashihigashinariku",
    "gn:name":"Tamatsu",
    "iso:country":"JP",
    "wof:name":"537-0023",
    "wof:placetype":"postalcode"
},
  "geometry": {"coordinates":[135.53729999999999,34.6695],"type":"Point"}
}