{
  "type": "Feature",
  "properties": {
    "gn:adm1_name":"Ibarakiken",
    "gn:adm2_name":"Kashimagun'Asahimura",
    "gn:name":"Kaduori",
    "iso:country":"JP",
    "wof:name":"311-1422",
    "wof:placetype":"postalcode"
},
  "geometry": {"coordinates":[140.56059999999999,36.1999],"type":"Point"}
}