{
  "type": "Feature",
  "properties": {
    "gn:adm1_name":"Gifuken",
    "gn:adm2_name":"Sekishi",
    "gn:name":"Yuuhigaoka",
    "iso:country":"JP",
    "wof:name":"501-3254",
    "wof:placetype":"postalcode"
},
  "geometry": {"coordinates":[136.9015,35.4843],"type":"Point"}
}