{
  "type": "Feature",
  "properties": {
    "gn:adm1_name":"Niigataken",
    "gn:adm2_name":"Nakakanbaragunyokogoshimachi",
    "gn:name":"Agano",
    "iso:country":"JP",
    "wof:name":"950-0217",
    "wof:placetype":"postalcode"
},
  "geometry": {"coordinates":[139.16739999999999,37.8293],"type":"Point"}
}