{
  "type": "Feature",
  "properties": {
    "gn:adm1_name":"Ishikawaken",
    "gn:adm2_name":"Ishikawagunkawachimura",
    "gn:name":"Nakanomi",
    "iso:country":"JP",
    "wof:name":"920-2311",
    "wof:placetype":"postalcode"
},
  "geometry": {"coordinates":[136.637,36.3884],"type":"Point"}
}