{
  "type": "Feature",
  "properties": {
    "gn:adm1_name":"Nagasakiken",
    "gn:adm2_name":"Shimabarashi",
    "gn:name":"Nakagumimachi",
    "iso:country":"JP",
    "wof:name":"855-0822",
    "wof:placetype":"postalcode"
},
  "geometry": {"coordinates":[130.37370000000001,32.7738],"type":"Point"}
}