{
  "type": "Feature",
  "properties": {
    "gn:adm1_name":"Aichiken",
    "gn:adm2_name":"Tokonameshi",
    "gn:name":"Furuyashiro",
    "iso:country":"JP",
    "wof:name":"479-0043",
    "wof:placetype":"postalcode"
},
  "geometry": {"coordinates":[136.85169999999999,34.8902],"type":"Point"}
}