{
  "type": "Feature",
  "properties": {
    "gn:adm1_name":"Ehimeken",
    "gn:adm2_name":"Oozushi",
    "gn:name":"Nishioozu",
    "iso:country":"JP",
    "wof:name":"795-0013",
    "wof:placetype":"postalcode"
},
  "geometry": {"coordinates":[132.5301,33.504],"type":"Point"}
}