{
  "type": "Feature",
  "properties": {
    "gn:adm1_name":"Kyoutofu",
    "gn:adm2_name":"Kyoutoshishimogyouku",
    "gn:name":"Minamifudoudouchou",
    "iso:country":"JP",
    "wof:name":"600-8234",
    "wof:placetype":"postalcode"
},
  "geometry": {"coordinates":[135.7544,34.9866],"type":"Point"}
}