{
  "type": "Feature",
  "properties": {
    "gn:adm1_name":"Aichiken",
    "gn:adm2_name":"Nishioshi",
    "gn:name":"Higashiazaichou",
    "iso:country":"JP",
    "wof:name":"445-0003",
    "wof:placetype":"postalcode"
},
  "geometry": {"coordinates":[137.1087,34.8913],"type":"Point"}
}