{
  "type": "Feature",
  "properties": {
    "gn:adm1_name":"Hyougoken",
    "gn:adm2_name":"Sasayamashi",
    "gn:name":"Hadakasu",
    "iso:country":"JP",
    "wof:name":"669-2505",
    "wof:placetype":"postalcode"
},
  "geometry": {"coordinates":[135.36199999999999,35.0719],"type":"Point"}
}