{
  "type": "Feature",
  "properties": {
    "gn:adm1_name":"Shizuokaken",
    "gn:adm2_name":"Shizuokashi",
    "gn:name":"Dodayuuchou",
    "iso:country":"JP",
    "wof:name":"420-0018",
    "wof:placetype":"postalcode"
},
  "geometry": {"coordinates":[138.3734,34.9784],"type":"Point"}
}