{
  "type": "Feature",
  "properties": {
    "gn:adm1_name":"Aichiken",
    "gn:adm2_name":"Hekinanshi",
    "gn:name":"Nakagomachi",
    "iso:country":"JP",
    "wof:name":"447-0042",
    "wof:placetype":"postalcode"
},
  "geometry": {"coordinates":[137.0025,34.8911],"type":"Point"}
}