{
  "type": "Feature",
  "properties": {
    "gn:adm1_name":"Ehimeken",
    "gn:adm2_name":"Minamiuwagun'Uchiumimura",
    "gn:name":"Sunokawa",
    "iso:country":"JP",
    "wof:name":"798-3703",
    "wof:placetype":"postalcode"
},
  "geometry": {"coordinates":[132.4888,33.0377],"type":"Point"}
}