{
  "type": "Feature",
  "properties": {
    "gn:adm1_name":"Toyamaken",
    "gn:adm2_name":"Toyamashi",
    "gn:name":"Mizuhashihatakera",
    "iso:country":"JP",
    "wof:name":"939-3521",
    "wof:placetype":"postalcode"
},
  "geometry": {"coordinates":[137.30459999999999,36.7467],"type":"Point"}
}