{
  "type": "Feature",
  "properties": {
    "gn:adm1_name":"Aichiken",
    "gn:adm2_name":"Nagoyashishouwaku",
    "gn:name":"Kamiyamachou",
    "iso:country":"JP",
    "wof:name":"466-0836",
    "wof:placetype":"postalcode"
},
  "geometry": {"coordinates":[136.94810000000001,35.1385],"type":"Point"}
}