{
  "type": "Feature",
  "properties": {
    "gn:adm1_name":"Shigaken",
    "gn:adm2_name":"Moriyamashi",
    "gn:name":"Ishidachou",
    "iso:country":"JP",
    "wof:name":"524-0014",
    "wof:placetype":"postalcode"
},
  "geometry": {"coordinates":[135.97829999999999,35.0722],"type":"Point"}
}