{
  "type": "Feature",
  "properties": {
    "gn:adm1_name":"Ibarakiken",
    "gn:adm2_name":"Kashimagun'Asahimura",
    "gn:name":"Tsukuriya",
    "iso:country":"JP",
    "wof:name":"311-1415",
    "wof:placetype":"postalcode"
},
  "geometry": {"coordinates":[140.52080000000001,36.2317],"type":"Point"}
}