{
  "type": "Feature",
  "properties": {
    "gn:adm1_name":"Yamaguchiken",
    "gn:adm2_name":"Iwakunishi",
    "gn:name":"Yokoyama",
    "iso:country":"JP",
    "wof:name":"741-0081",
    "wof:placetype":"postalcode"
},
  "geometry": {"coordinates":[132.17670000000001,34.1713],"type":"Point"}
}