{
  "type": "Feature",
  "properties": {
    "gn:adm1_name":"Niigataken",
    "gn:adm2_name":"Niitsushi",
    "gn:name":"Minamichou",
    "iso:country":"JP",
    "wof:name":"956-0032",
    "wof:placetype":"postalcode"
},
  "geometry": {"coordinates":[139.10839999999999,37.793],"type":"Point"}
}