{
  "type": "Feature",
  "properties": {
    "gn:adm1_name":"Kyoutofu",
    "gn:adm2_name":"Ayabeshi",
    "gn:name":"Hoshibarachou",
    "iso:country":"JP",
    "wof:name":"623-0007",
    "wof:placetype":"postalcode"
},
  "geometry": {"coordinates":[135.26429999999999,35.3382],"type":"Point"}
}