{
  "type": "Feature",
  "properties": {
    "gn:adm1_name":"Kyoutofu",
    "gn:adm2_name":"Kyoutoshishimogyouku",
    "gn:name":"Nishishinyashikiageyachou",
    "iso:country":"JP",
    "wof:name":"600-8828",
    "wof:placetype":"postalcode"
},
  "geometry": {"coordinates":[135.74340000000001,34.992],"type":"Point"}
}