{
  "type": "Feature",
  "properties": {
    "gn:adm1_name":"Hiroshimaken",
    "gn:adm2_name":"Seragunserachou",
    "gn:name":"Tokuichi",
    "iso:country":"JP",
    "wof:name":"722-1203",
    "wof:placetype":"postalcode"
},
  "geometry": {"coordinates":[132.9819,34.6491],"type":"Point"}
}