{
  "type": "Feature",
  "properties": {
    "gn:adm1_name":"Saitamaken",
    "gn:adm2_name":"Kitamotoshi",
    "gn:name":"Asahi",
    "iso:country":"JP",
    "wof:name":"364-0011",
    "wof:placetype":"postalcode"
},
  "geometry": {"coordinates":[139.5556,36.0368],"type":"Point"}
}