{
  "type": "Feature",
  "properties": {
    "gn:adm1_name":"Kouchiken",
    "gn:adm2_name":"Tosaguntosayamamura",
    "gn:name":"Nishigawa",
    "iso:country":"JP",
    "wof:name":"781-3213",
    "wof:placetype":"postalcode"
},
  "geometry": {"coordinates":[133.55600000000001,33.6388],"type":"Point"}
}