{
  "type": "Feature",
  "properties": {
    "gn:adm1_name":"Shizuokaken",
    "gn:adm2_name":"Ogasagunkikugawachou",
    "gn:name":"Kozawa",
    "iso:country":"JP",
    "wof:name":"439-0014",
    "wof:placetype":"postalcode"
},
  "geometry": {"coordinates":[138.12180000000001,34.7466],"type":"Point"}
}