{
  "type": "Feature",
  "properties": {
    "gn:adm1_name":"Shizuokaken",
    "gn:adm2_name":"Fukuroishi",
    "gn:name":"Takao",
    "iso:country":"JP",
    "wof:name":"437-0023",
    "wof:placetype":"postalcode"
},
  "geometry": {"coordinates":[137.9265,34.7395],"type":"Point"}
}