{
  "type": "Feature",
  "properties": {
    "gn:adm1_name":"Tochigiken",
    "gn:adm2_name":"Asogunkuzuumachi",
    "gn:name":"Toyoshiro",
    "iso:country":"JP",
    "wof:name":"327-0512",
    "wof:placetype":"postalcode"
},
  "geometry": {"coordinates":[139.5949,36.4245],"type":"Point"}
}