{
  "type": "Feature",
  "properties": {
    "gn:adm1_name":"Okinawaken",
    "gn:adm2_name":"Kunigamigunnakijinson",
    "gn:name":"Shoshi",
    "iso:country":"JP",
    "wof:name":"905-0426",
    "wof:placetype":"postalcode"
},
  "geometry": {"coordinates":[127.9421,26.6966],"type":"Point"}
}