{
  "type": "Feature",
  "properties": {
    "gn:adm1_name":"Okayamaken",
    "gn:adm2_name":"Odagunyakagechou",
    "gn:name":"Ikanikeisaiganaibaai",
    "iso:country":"JP",
    "wof:name":"714-1200",
    "wof:placetype":"postalcode"
},
  "geometry": {"coordinates":[133.54920000000001,34.6199],"type":"Point"}
}