{
  "type": "Feature",
  "properties": {
    "gn:adm1_name":"Ehimeken",
    "gn:adm2_name":"Matsuyamashi",
    "gn:name":"Iwaidanimachi",
    "iso:country":"JP",
    "wof:name":"790-0834",
    "wof:placetype":"postalcode"
},
  "geometry": {"coordinates":[132.7851,33.8556],"type":"Point"}
}