{
  "type": "Feature",
  "properties": {
    "gn:adm1_name":"Fukuokaken",
    "gn:adm2_name":"Fukuokashinishiku",
    "gn:name":"Kamiyamato",
    "iso:country":"JP",
    "wof:name":"819-0054",
    "wof:placetype":"postalcode"
},
  "geometry": {"coordinates":[130.3038,33.5729],"type":"Point"}
}