{
  "type": "Feature",
  "properties": {
    "gn:adm1_name":"Nagasakiken",
    "gn:adm2_name":"Isahayashi",
    "gn:name":"Mawatarimachi",
    "iso:country":"JP",
    "wof:name":"854-0075",
    "wof:placetype":"postalcode"
},
  "geometry": {"coordinates":[130.02170000000001,32.8417],"type":"Point"}
}