{
  "type": "Feature",
  "properties": {
    "gn:adm1_name":"Toyamaken",
    "gn:adm2_name":"Tonamishi",
    "gn:name":"Nabeshima",
    "iso:country":"JP",
    "wof:name":"939-1362",
    "wof:placetype":"postalcode"
},
  "geometry": {"coordinates":[136.9633,36.6337],"type":"Point"}
}