{
  "type": "Feature",
  "properties": {
    "gn:adm1_name":"Kouchiken",
    "gn:adm2_name":"Nakamurashi",
    "gn:name":"Masaki",
    "iso:country":"JP",
    "wof:name":"787-0160",
    "wof:placetype":"postalcode"
},
  "geometry": {"coordinates":[132.9709,32.943],"type":"Point"}
}