{
  "type": "Feature",
  "properties": {
    "gn:adm1_name":"Kumamotoken",
    "gn:adm2_name":"Kumamotoshi",
    "gn:name":"Mutaguchimachi",
    "iso:country":"JP",
    "wof:name":"861-5261",
    "wof:placetype":"postalcode"
},
  "geometry": {"coordinates":[130.63480000000001,32.7605],"type":"Point"}
}