{
  "type": "Feature",
  "properties": {
    "gn:adm1_name":"Hyougoken",
    "gn:adm2_name":"Ashiyashi",
    "gn:name":"Miyagawachou",
    "iso:country":"JP",
    "wof:name":"659-0063",
    "wof:placetype":"postalcode"
},
  "geometry": {"coordinates":[135.31139999999999,34.7295],"type":"Point"}
}