{
  "type": "Feature",
  "properties": {
    "gn:adm1_name":"Yamanashiken",
    "gn:adm2_name":"Kitatsurugun'Uenoharamachi",
    "gn:name":"Yuzurihara",
    "iso:country":"JP",
    "wof:name":"409-0111",
    "wof:placetype":"postalcode"
},
  "geometry": {"coordinates":[139.08770000000001,35.6714],"type":"Point"}
}