{
  "type": "Feature",
  "properties": {
    "gn:adm1_name":"Nagasakiken",
    "gn:adm2_name":"Nishisonogigunsotomechou",
    "gn:name":"Kounouraougiyamagou",
    "iso:country":"JP",
    "wof:name":"851-2411",
    "wof:placetype":"postalcode"
},
  "geometry": {"coordinates":[129.72720000000001,32.8954],"type":"Point"}
}