{
  "type": "Feature",
  "properties": {
    "gn:adm1_name":"Kumamotoken",
    "gn:adm2_name":"Utoshi",
    "gn:name":"Hashirigatamachi",
    "iso:country":"JP",
    "wof:name":"869-0404",
    "wof:placetype":"postalcode"
},
  "geometry": {"coordinates":[130.64529999999999,32.7048],"type":"Point"}
}