{
  "type": "Feature",
  "properties": {
    "gn:adm1_name":"Hyougoken",
    "gn:adm2_name":"Takagunkamichou",
    "gn:name":"Kannonji",
    "iso:country":"JP",
    "wof:name":"679-1338",
    "wof:placetype":"postalcode"
},
  "geometry": {"coordinates":[134.92490000000001,35.1115],"type":"Point"}
}