{
  "type": "Feature",
  "properties": {
    "gn:adm1_name":"Kouchiken",
    "gn:adm2_name":"Nakamurashi",
    "gn:name":"Yasunami",
    "iso:country":"JP",
    "wof:name":"787-0008",
    "wof:placetype":"postalcode"
},
  "geometry": {"coordinates":[132.93700000000001,33.0064],"type":"Point"}
}