{
  "type": "Feature",
  "properties": {
    "gn:adm1_name":"Mieken",
    "gn:adm2_name":"Uenoshi",
    "gn:name":"Midorigaokanakamachi",
    "iso:country":"JP",
    "wof:name":"518-0834",
    "wof:placetype":"postalcode"
},
  "geometry": {"coordinates":[136.1446,34.762],"type":"Point"}
}