{
  "type": "Feature",
  "properties": {
    "gn:adm1_name":"Fukuiken",
    "gn:adm2_name":"Tsurugashi",
    "gn:name":"Nouma",
    "iso:country":"JP",
    "wof:name":"914-0833",
    "wof:placetype":"postalcode"
},
  "geometry": {"coordinates":[136.02539999999999,35.6844],"type":"Point"}
}