{
  "type": "Feature",
  "properties": {
    "gn:adm1_name":"Shigaken",
    "gn:adm2_name":"Takashimaguntakashimachou",
    "gn:name":"Ukawa",
    "iso:country":"JP",
    "wof:name":"520-1122",
    "wof:placetype":"postalcode"
},
  "geometry": {"coordinates":[136.0016,35.2719],"type":"Point"}
}