{
  "type": "Feature",
  "properties": {
    "gn:adm1_name":"Ibarakiken",
    "gn:adm2_name":"Makabegunsekijoumachi",
    "gn:name":"Nakamurashinden",
    "iso:country":"JP",
    "wof:name":"308-0108",
    "wof:placetype":"postalcode"
},
  "geometry": {"coordinates":[139.9813,36.2926],"type":"Point"}
}