{
  "type": "Feature",
  "properties": {
    "gn:adm1_name":"Fukushimaken",
    "gn:adm2_name":"Tamuragunfunehikimachi",
    "gn:name":"Ishimori",
    "iso:country":"JP",
    "wof:name":"963-4313",
    "wof:placetype":"postalcode"
},
  "geometry": {"coordinates":[140.55799999999999,37.4612],"type":"Point"}
}