{
  "type": "Feature",
  "properties": {
    "gn:adm1_name":"Fukuokaken",
    "gn:adm2_name":"Mizumagunjoujimamachi",
    "gn:name":"Joujima",
    "iso:country":"JP",
    "wof:name":"830-0207",
    "wof:placetype":"postalcode"
},
  "geometry": {"coordinates":[130.42859999999999,33.2572],"type":"Point"}
}