{
  "type": "Feature",
  "properties": {
    "gn:adm1_name":"Yamanashiken",
    "gn:adm2_name":"Kitatsurugun'Uenoharamachi",
    "gn:name":"Inume",
    "iso:country":"JP",
    "wof:name":"409-0124",
    "wof:placetype":"postalcode"
},
  "geometry": {"coordinates":[139.0342,35.6266],"type":"Point"}
}