{
  "type": "Feature",
  "properties": {
    "gn:adm1_name":"Aichiken",
    "gn:adm2_name":"Nagoyashinakamuraku",
    "gn:name":"Meirakuchou",
    "iso:country":"JP",
    "wof:name":"453-0024",
    "wof:placetype":"postalcode"
},
  "geometry": {"coordinates":[136.86490000000001,35.1691],"type":"Point"}
}