{
  "type": "Feature",
  "properties": {
    "gn:adm1_name":"Toyamaken",
    "gn:adm2_name":"Namerikawashi",
    "gn:name":"Tanakamachi",
    "iso:country":"JP",
    "wof:name":"936-0057",
    "wof:placetype":"postalcode"
},
  "geometry": {"coordinates":[137.3374,36.7624],"type":"Point"}
}