{
  "type": "Feature",
  "properties": {
    "gn:adm1_name":"Hyougoken",
    "gn:adm2_name":"Mikatagun'Onsenchou",
    "gn:name":"Miyawaki",
    "iso:country":"JP",
    "wof:name":"669-6944",
    "wof:placetype":"postalcode"
},
  "geometry": {"coordinates":[134.44409999999999,35.5276],"type":"Point"}
}