{
  "type": "Feature",
  "properties": {
    "gn:adm1_name":"Shizuokaken",
    "gn:adm2_name":"Fujiedashi",
    "gn:name":"Taishinjima",
    "iso:country":"JP",
    "wof:name":"426-0043",
    "wof:placetype":"postalcode"
},
  "geometry": {"coordinates":[138.27260000000001,34.8318],"type":"Point"}
}