{
  "type": "Feature",
  "properties": {
    "gn:adm1_name":"Nagasakiken",
    "gn:adm2_name":"Kitamatsuuragunsechibaruchou",
    "gn:name":"Nagatashiromen",
    "iso:country":"JP",
    "wof:name":"859-6411",
    "wof:placetype":"postalcode"
},
  "geometry": {"coordinates":[129.73679999999999,33.2498],"type":"Point"}
}