{
  "type": "Feature",
  "properties": {
    "gn:adm1_name":"Niigataken",
    "gn:adm2_name":"Jouetsushi",
    "gn:name":"Nishiichinokuchi",
    "iso:country":"JP",
    "wof:name":"943-0152",
    "wof:placetype":"postalcode"
},
  "geometry": {"coordinates":[138.27869999999999,37.1166],"type":"Point"}
}