{
  "type": "Feature",
  "properties": {
    "gn:adm1_name":"Gifuken",
    "gn:adm2_name":"Yamagatashi",
    "gn:name":"Katahara",
    "iso:country":"JP",
    "wof:name":"501-2303",
    "wof:placetype":"postalcode"
},
  "geometry": {"coordinates":[136.73599999999999,35.6206],"type":"Point"}
}