{
  "type": "Feature",
  "properties": {
    "gn:adm1_name":"Toyamaken",
    "gn:adm2_name":"Kurobeshi",
    "gn:name":"Kubono",
    "iso:country":"JP",
    "wof:name":"938-0047",
    "wof:placetype":"postalcode"
},
  "geometry": {"coordinates":[137.44900000000001,36.8493],"type":"Point"}
}