{
  "type": "Feature",
  "properties": {
    "gn:adm1_name":"Fukuokaken",
    "gn:adm2_name":"Maebarushi",
    "gn:name":"Ita",
    "iso:country":"JP",
    "wof:name":"819-1562",
    "wof:placetype":"postalcode"
},
  "geometry": {"coordinates":[130.23699999999999,33.5466],"type":"Point"}
}