{
  "type": "Feature",
  "properties": {
    "gn:adm1_name":"Fukuiken",
    "gn:adm2_name":"Fukuishi",
    "gn:name":"Saburoumaru",
    "iso:country":"JP",
    "wof:name":"910-0033",
    "wof:placetype":"postalcode"
},
  "geometry": {"coordinates":[136.19220000000001,36.0787],"type":"Point"}
}