{
  "type": "Feature",
  "properties": {
    "gn:adm1_name":"Toukyouto",
    "gn:adm2_name":"Hamurashi",
    "gn:name":"Sakaechou",
    "iso:country":"JP",
    "wof:name":"205-0002",
    "wof:placetype":"postalcode"
},
  "geometry": {"coordinates":[139.30869999999999,35.7731],"type":"Point"}
}