{
  "type": "Feature",
  "properties": {
    "gn:adm1_name":"Niigataken",
    "gn:adm2_name":"Iwafunegunkamihayashimura",
    "gn:name":"Kamisukebuchi",
    "iso:country":"JP",
    "wof:name":"959-3403",
    "wof:placetype":"postalcode"
},
  "geometry": {"coordinates":[139.47730000000001,38.2055],"type":"Point"}
}