{
  "type": "Feature",
  "properties": {
    "gn:adm1_name":"Aichiken",
    "gn:adm2_name":"Shinshiroshi",
    "gn:name":"Yabe",
    "iso:country":"JP",
    "wof:name":"441-1301",
    "wof:placetype":"postalcode"
},
  "geometry": {"coordinates":[137.50559999999999,34.9188],"type":"Point"}
}