{
  "type": "Feature",
  "properties": {
    "gn:adm1_name":"Ibarakiken",
    "gn:adm2_name":"Kasamashi",
    "gn:name":"Kasama",
    "iso:country":"JP",
    "wof:name":"309-1611",
    "wof:placetype":"postalcode"
},
  "geometry": {"coordinates":[140.25640000000001,36.3821],"type":"Point"}
}