{
  "type": "Feature",
  "properties": {
    "gn:adm1_name":"Aichiken",
    "gn:adm2_name":"Ichinomiyashi",
    "gn:name":"Yamatochouoho",
    "iso:country":"JP",
    "wof:name":"491-0924",
    "wof:placetype":"postalcode"
},
  "geometry": {"coordinates":[136.79660000000001,35.2737],"type":"Point"}
}