{
  "type": "Feature",
  "properties": {
    "gn:adm1_name":"Niigataken",
    "gn:adm2_name":"Jouetsushi",
    "gn:name":"Nakanakamurashinden",
    "iso:country":"JP",
    "wof:name":"943-0164",
    "wof:placetype":"postalcode"
},
  "geometry": {"coordinates":[138.25489999999999,37.1369],"type":"Point"}
}