{
  "type": "Feature",
  "properties": {
    "gn:adm1_name":"Aichiken",
    "gn:adm2_name":"Inazawashi",
    "gn:name":"Inokuchiishidukachou",
    "iso:country":"JP",
    "wof:name":"492-8163",
    "wof:placetype":"postalcode"
},
  "geometry": {"coordinates":[136.81950000000001,35.2391],"type":"Point"}
}