{
  "type": "Feature",
  "properties": {
    "gn:adm1_name":"Niigataken",
    "gn:adm2_name":"Nishikanbaragunkatahigashimura",
    "gn:name":"Shoumyou",
    "iso:country":"JP",
    "wof:name":"959-0514",
    "wof:placetype":"postalcode"
},
  "geometry": {"coordinates":[138.9581,37.7515],"type":"Point"}
}