{
  "type": "Feature",
  "properties": {
    "gn:adm1_name":"Oosakafu",
    "gn:adm2_name":"Sakaishi",
    "gn:name":"Takamatsu",
    "iso:country":"JP",
    "wof:name":"599-8121",
    "wof:placetype":"postalcode"
},
  "geometry": {"coordinates":[135.53450000000001,34.5295],"type":"Point"}
}