{
  "type": "Feature",
  "properties": {
    "gn:adm1_name":"Ooitaken",
    "gn:adm2_name":"Saikishi",
    "gn:name":"Mejimadanchi",
    "iso:country":"JP",
    "wof:name":"876-0825",
    "wof:placetype":"postalcode"
},
  "geometry": {"coordinates":[131.91579999999999,32.9589],"type":"Point"}
}