{
  "type": "Feature",
  "properties": {
    "gn:adm1_name":"Mieken",
    "gn:adm2_name":"Kuwanashi",
    "gn:name":"Ekimotochou",
    "iso:country":"JP",
    "wof:name":"511-0071",
    "wof:placetype":"postalcode"
},
  "geometry": {"coordinates":[136.68559999999999,35.0685],"type":"Point"}
}