{
  "type": "Feature",
  "properties": {
    "gn:adm1_name":"Niigataken",
    "gn:adm2_name":"Koshigunyamakoshimura",
    "gn:name":"Tanesuhara",
    "iso:country":"JP",
    "wof:name":"947-0201",
    "wof:placetype":"postalcode"
},
  "geometry": {"coordinates":[138.929,37.3539],"type":"Point"}
}