{
  "type": "Feature",
  "properties": {
    "gn:adm1_name":"Gunmaken",
    "gn:adm2_name":"Annakashi",
    "gn:name":"Nakajuku",
    "iso:country":"JP",
    "wof:name":"379-0115",
    "wof:placetype":"postalcode"
},
  "geometry": {"coordinates":[138.91650000000001,36.3331],"type":"Point"}
}