{
  "type": "Feature",
  "properties": {
    "gn:adm1_name":"Chibaken",
    "gn:adm2_name":"Inzaishi",
    "gn:name":"Funao",
    "iso:country":"JP",
    "wof:name":"270-1345",
    "wof:placetype":"postalcode"
},
  "geometry": {"coordinates":[140.1283,35.7853],"type":"Point"}
}