{
  "type": "Feature",
  "properties": {
    "gn:adm1_name":"Oosakafu",
    "gn:adm2_name":"Oosakashikitaku",
    "gn:name":"Naniwachou",
    "iso:country":"JP",
    "wof:name":"530-0022",
    "wof:placetype":"postalcode"
},
  "geometry": {"coordinates":[135.5103,34.7083],"type":"Point"}
}