{
  "type": "Feature",
  "properties": {
    "gn:adm1_name":"Gunmaken",
    "gn:adm2_name":"Ouragunmeiwamachi",
    "gn:name":"Minamiooshima",
    "iso:country":"JP",
    "wof:name":"370-0701",
    "wof:placetype":"postalcode"
},
  "geometry": {"coordinates":[139.5377,36.2149],"type":"Point"}
}