{
  "type": "Feature",
  "properties": {
    "gn:adm1_name":"Mieken",
    "gn:adm2_name":"Shimagun'Agochou",
    "gn:name":"Ugata",
    "iso:country":"JP",
    "wof:name":"517-0501",
    "wof:placetype":"postalcode"
},
  "geometry": {"coordinates":[136.82589999999999,34.3305],"type":"Point"}
}