{
  "type": "Feature",
  "properties": {
    "gn:adm1_name":"Shigaken",
    "gn:adm2_name":"Nagahamashi",
    "gn:name":"Kunitomochou",
    "iso:country":"JP",
    "wof:name":"526-0001",
    "wof:placetype":"postalcode"
},
  "geometry": {"coordinates":[136.2818,35.4097],"type":"Point"}
}