{
  "type": "Feature",
  "properties": {
    "gn:adm1_name":"Okayamaken",
    "gn:adm2_name":"Kurashikishi",
    "gn:name":"Itsukaichi",
    "iso:country":"JP",
    "wof:name":"710-0041",
    "wof:placetype":"postalcode"
},
  "geometry": {"coordinates":[133.79480000000001,34.5997],"type":"Point"}
}