{
  "type": "Feature",
  "properties": {
    "gn:adm1_name":"Toyamaken",
    "gn:adm2_name":"Higashitonamigunfukunomachi",
    "gn:name":"Maeda",
    "iso:country":"JP",
    "wof:name":"939-1549",
    "wof:placetype":"postalcode"
},
  "geometry": {"coordinates":[136.892,36.5884],"type":"Point"}
}