{
  "type": "Feature",
  "properties": {
    "gn:adm1_name":"Fukuokaken",
    "gn:adm2_name":"Chikugoshi",
    "gn:name":"Ichijou",
    "iso:country":"JP",
    "wof:name":"833-0001",
    "wof:placetype":"postalcode"
},
  "geometry": {"coordinates":[130.5104,33.246],"type":"Point"}
}