{
  "type": "Feature",
  "properties": {
    "gn:adm1_name":"Mieken",
    "gn:adm2_name":"Inabeshi",
    "gn:name":"Fujiwarachoufuruta",
    "iso:country":"JP",
    "wof:name":"511-0521",
    "wof:placetype":"postalcode"
},
  "geometry": {"coordinates":[136.4599,35.2253],"type":"Point"}
}