{
  "type": "Feature",
  "properties": {
    "gn:adm1_name":"Nagasakiken",
    "gn:adm2_name":"Ikigun'Ashibechou",
    "gn:name":"Hakozakitaisoufure",
    "iso:country":"JP",
    "wof:name":"811-5462",
    "wof:placetype":"postalcode"
},
  "geometry": {"coordinates":[129.7551,33.8177],"type":"Point"}
}