{
  "type": "Feature",
  "properties": {
    "gn:adm1_name":"Gifuken",
    "gn:adm2_name":"Motosugun'Itonukichou",
    "gn:name":"Shime",
    "iso:country":"JP",
    "wof:name":"501-0418",
    "wof:placetype":"postalcode"
},
  "geometry": {"coordinates":[136.6541,35.4476],"type":"Point"}
}