{
  "type": "Feature",
  "properties": {
    "gn:adm1_name":"Kyoutofu",
    "gn:adm2_name":"Kyoutoshisakyouku",
    "gn:name":"Kamitakanoikenouchichou",
    "iso:country":"JP",
    "wof:name":"606-0057",
    "wof:placetype":"postalcode"
},
  "geometry": {"coordinates":[135.7945,35.065],"type":"Point"}
}