{
  "type": "Feature",
  "properties": {
    "gn:adm1_name":"Toyamaken",
    "gn:adm2_name":"Himishi",
    "gn:name":"Ogume",
    "iso:country":"JP",
    "wof:name":"935-0263",
    "wof:placetype":"postalcode"
},
  "geometry": {"coordinates":[136.9024,36.8468],"type":"Point"}
}