{
  "type": "Feature",
  "properties": {
    "gn:adm1_name":"Hyougoken",
    "gn:adm2_name":"Koubeshikitaku",
    "gn:name":"Hinomine",
    "iso:country":"JP",
    "wof:name":"651-1233",
    "wof:placetype":"postalcode"
},
  "geometry": {"coordinates":[135.14519999999999,34.7586],"type":"Point"}
}