{
  "type": "Feature",
  "properties": {
    "gn:adm1_name":"Oosakafu",
    "gn:adm2_name":"Izumishi",
    "gn:name":"Onoichou",
    "iso:country":"JP",
    "wof:name":"594-0006",
    "wof:placetype":"postalcode"
},
  "geometry": {"coordinates":[135.44210000000001,34.5058],"type":"Point"}
}