{
  "type": "Feature",
  "properties": {
    "gn:adm1_name":"Aichiken",
    "gn:adm2_name":"Nishikasugaigunnishibiwajimachou",
    "gn:name":"Suirichou",
    "iso:country":"JP",
    "wof:name":"452-0016",
    "wof:placetype":"postalcode"
},
  "geometry": {"coordinates":[136.8672,35.1973],"type":"Point"}
}