{
  "type": "Feature",
  "properties": {
    "gn:adm1_name":"Nagasakiken",
    "gn:adm2_name":"Minamitakakigun'Adumachou",
    "gn:name":"Tanohiramyou",
    "iso:country":"JP",
    "wof:name":"859-1105",
    "wof:placetype":"postalcode"
},
  "geometry": {"coordinates":[130.2175,32.8233],"type":"Point"}
}