{
  "type": "Feature",
  "properties": {
    "gn:adm1_name":"Ehimeken",
    "gn:adm2_name":"Ochiguntamagawachou",
    "gn:name":"Surugi",
    "iso:country":"JP",
    "wof:name":"794-0104",
    "wof:placetype":"postalcode"
},
  "geometry": {"coordinates":[132.93809999999999,34.0224],"type":"Point"}
}