{
  "type": "Feature",
  "properties": {
    "gn:adm1_name":"Ibarakiken",
    "gn:adm2_name":"Makabegunsekijoumachi",
    "gn:name":"Inuduka",
    "iso:country":"JP",
    "wof:name":"308-0117",
    "wof:placetype":"postalcode"
},
  "geometry": {"coordinates":[139.94900000000001,36.2522],"type":"Point"}
}