{
  "type": "Feature",
  "properties": {
    "gn:adm1_name":"Ooitaken",
    "gn:adm2_name":"Ooitashi",
    "gn:name":"Aosaki",
    "iso:country":"JP",
    "wof:name":"870-0278",
    "wof:placetype":"postalcode"
},
  "geometry": {"coordinates":[131.70670000000001,33.2581],"type":"Point"}
}