{
  "type": "Feature",
  "properties": {
    "gn:adm1_name":"Miyagiken",
    "gn:adm2_name":"Toodagunkogotachou",
    "gn:name":"Sekine",
    "iso:country":"JP",
    "wof:name":"987-0006",
    "wof:placetype":"postalcode"
},
  "geometry": {"coordinates":[141.00219999999999,38.5689],"type":"Point"}
}