{
  "type": "Feature",
  "properties": {
    "gn:adm1_name":"Miyagiken",
    "gn:adm2_name":"Kuriharagun'Ichihasamachou",
    "gn:name":"Nakakozou",
    "iso:country":"JP",
    "wof:name":"987-2361",
    "wof:placetype":"postalcode"
},
  "geometry": {"coordinates":[140.87190000000001,38.7527],"type":"Point"}
}