{
  "type": "Feature",
  "properties": {
    "gn:adm1_name":"Gunmaken",
    "gn:adm2_name":"Takasakishi",
    "gn:name":"Motomachi",
    "iso:country":"JP",
    "wof:name":"370-0813",
    "wof:placetype":"postalcode"
},
  "geometry": {"coordinates":[139.00389999999999,36.3306],"type":"Point"}
}