{
  "type": "Feature",
  "properties": {
    "gn:adm1_name":"Aichiken",
    "gn:adm2_name":"Nagoyashimoriyamaku",
    "gn:name":"Shinmorichou",
    "iso:country":"JP",
    "wof:name":"463-0071",
    "wof:placetype":"postalcode"
},
  "geometry": {"coordinates":[136.953,35.2083],"type":"Point"}
}