{
  "type": "Feature",
  "properties": {
    "gn:adm1_name":"Chibaken",
    "gn:adm2_name":"Higashikatsushikagunshounanmachi",
    "gn:name":"Iwai",
    "iso:country":"JP",
    "wof:name":"270-1445",
    "wof:placetype":"postalcode"
},
  "geometry": {"coordinates":[140.03049999999999,35.8487],"type":"Point"}
}