{
  "type": "Feature",
  "properties": {
    "gn:adm1_name":"Kumamotoken",
    "gn:adm2_name":"Hitoyoshishi",
    "gn:name":"Higashiaidakamimachi",
    "iso:country":"JP",
    "wof:name":"868-0043",
    "wof:placetype":"postalcode"
},
  "geometry": {"coordinates":[130.76849999999999,32.1975],"type":"Point"}
}