{
  "type": "Feature",
  "properties": {
    "gn:adm1_name":"Fukuiken",
    "gn:adm2_name":"Oonoshi",
    "gn:name":"Mikawachou",
    "iso:country":"JP",
    "wof:name":"912-0036",
    "wof:placetype":"postalcode"
},
  "geometry": {"coordinates":[136.49700000000001,35.9856],"type":"Point"}
}