{
  "type": "Feature",
  "properties": {
    "gn:adm1_name":"Aichiken",
    "gn:adm2_name":"Tsushimashi",
    "gn:name":"Nikkou",
    "iso:country":"JP",
    "wof:name":"496-0028",
    "wof:placetype":"postalcode"
},
  "geometry": {"coordinates":[136.7527,35.178],"type":"Point"}
}