{
  "type": "Feature",
  "properties": {
    "gn:adm1_name":"Miyagiken",
    "gn:adm2_name":"Kuriharaguntakashimizumachi",
    "gn:name":"Mizunote",
    "iso:country":"JP",
    "wof:name":"987-2131",
    "wof:placetype":"postalcode"
},
  "geometry": {"coordinates":[141.0155,38.657],"type":"Point"}
}