{
  "type": "Feature",
  "properties": {
    "gn:adm1_name":"Aichiken",
    "gn:adm2_name":"Nagoyashinishiku",
    "gn:name":"Sengen",
    "iso:country":"JP",
    "wof:name":"451-0035",
    "wof:placetype":"postalcode"
},
  "geometry": {"coordinates":[136.88900000000001,35.1849],"type":"Point"}
}