{
  "type": "Feature",
  "properties": {
    "gn:adm1_name":"Kyoutofu",
    "gn:adm2_name":"Sourakugunkiduchou",
    "gn:name":"Kaseyama",
    "iso:country":"JP",
    "wof:name":"619-0211",
    "wof:placetype":"postalcode"
},
  "geometry": {"coordinates":[135.84020000000001,34.7425],"type":"Point"}
}