{
  "type": "Feature",
  "properties": {
    "gn:adm1_name":"Chibaken",
    "gn:adm2_name":"Matsudoshi",
    "gn:name":"Tokiwadairafutabachou",
    "iso:country":"JP",
    "wof:name":"270-2262",
    "wof:placetype":"postalcode"
},
  "geometry": {"coordinates":[139.94810000000001,35.7962],"type":"Point"}
}