{
  "type": "Feature",
  "properties": {
    "gn:adm1_name":"Miyagiken",
    "gn:adm2_name":"Sendaishiaobaku",
    "gn:name":"Mukaida",
    "iso:country":"JP",
    "wof:name":"989-3215",
    "wof:placetype":"postalcode"
},
  "geometry": {"coordinates":[140.79259999999999,38.2801],"type":"Point"}
}