{
  "type": "Feature",
  "properties": {
    "gn:adm1_name":"Kumamotoken",
    "gn:adm2_name":"Kamimashikigunkousamachi",
    "gn:name":"Nitago",
    "iso:country":"JP",
    "wof:name":"861-4603",
    "wof:placetype":"postalcode"
},
  "geometry": {"coordinates":[130.8057,32.6509],"type":"Point"}
}