{
  "type": "Feature",
  "properties": {
    "gn:adm1_name":"Kyoutofu",
    "gn:adm2_name":"Kyoutoshinishikyouku",
    "gn:name":"Ooharanokamizatomomijichou",
    "iso:country":"JP",
    "wof:name":"610-1124",
    "wof:placetype":"postalcode"
},
  "geometry": {"coordinates":[135.6892,34.9499],"type":"Point"}
}