{
  "type": "Feature",
  "properties": {
    "gn:adm1_name":"Hiroshimaken",
    "gn:adm2_name":"Akigunkaitachou",
    "gn:name":"Une",
    "iso:country":"JP",
    "wof:name":"736-0005",
    "wof:placetype":"postalcode"
},
  "geometry": {"coordinates":[132.5496,34.3792],"type":"Point"}
}