{
  "type": "Feature",
  "properties": {
    "gn:adm1_name":"Okayamaken",
    "gn:adm2_name":"Akaiwagunsanyouchou",
    "gn:name":"Itsukaichi",
    "iso:country":"JP",
    "wof:name":"709-0831",
    "wof:placetype":"postalcode"
},
  "geometry": {"coordinates":[134.01259999999999,34.7713],"type":"Point"}
}