{
  "type": "Feature",
  "properties": {
    "gn:adm1_name":"Kanagawaken",
    "gn:adm2_name":"Minamiashigarashi",
    "gn:name":"Nuda",
    "iso:country":"JP",
    "wof:name":"250-0106",
    "wof:placetype":"postalcode"
},
  "geometry": {"coordinates":[139.10140000000001,35.333],"type":"Point"}
}