{
  "type": "Feature",
  "properties": {
    "gn:adm1_name":"Saitamaken",
    "gn:adm2_name":"Kodamagunkodamamachi",
    "gn:name":"Shimomashimo",
    "iso:country":"JP",
    "wof:name":"367-0207",
    "wof:placetype":"postalcode"
},
  "geometry": {"coordinates":[139.14439999999999,36.2168],"type":"Point"}
}