{
  "type": "Feature",
  "properties": {
    "gn:adm1_name":"Kyoutofu",
    "gn:adm2_name":"Kyoutoshiukyouku",
    "gn:name":"Sagashakadoumonzenminamichuuinchou",
    "iso:country":"JP",
    "wof:name":"616-8424",
    "wof:placetype":"postalcode"
},
  "geometry": {"coordinates":[135.67330000000001,35.0222],"type":"Point"}
}