{
  "type": "Feature",
  "properties": {
    "gn:adm1_name":"Hyougoken",
    "gn:adm2_name":"Koubeshihyougoku",
    "gn:name":"Nishimiyauchichou",
    "iso:country":"JP",
    "wof:name":"652-0891",
    "wof:placetype":"postalcode"
},
  "geometry": {"coordinates":[135.17179999999999,34.6693],"type":"Point"}
}