{
  "type": "Feature",
  "properties": {
    "gn:adm1_name":"Fukushimaken",
    "gn:adm2_name":"Shirakawashi",
    "gn:name":"Michihigashi",
    "iso:country":"JP",
    "wof:name":"961-0031",
    "wof:placetype":"postalcode"
},
  "geometry": {"coordinates":[140.23159999999999,37.1016],"type":"Point"}
}