{
  "type": "Feature",
  "properties": {
    "gn:adm1_name":"Ibarakiken",
    "gn:adm2_name":"Inashikigun'Azumamachi",
    "gn:name":"Tegakumishinden",
    "iso:country":"JP",
    "wof:name":"300-0741",
    "wof:placetype":"postalcode"
},
  "geometry": {"coordinates":[140.41810000000001,35.923],"type":"Point"}
}