{
  "type": "Feature",
  "properties": {
    "gn:adm1_name":"Fukushimaken",
    "gn:adm2_name":"Nihonmatsushi",
    "gn:name":"Nakamachi",
    "iso:country":"JP",
    "wof:name":"964-0991",
    "wof:placetype":"postalcode"
},
  "geometry": {"coordinates":[140.4545,37.5614],"type":"Point"}
}