{
  "type": "Feature",
  "properties": {
    "gn:adm1_name":"Fukuokaken",
    "gn:adm2_name":"Kitakyuushuushikokuraminamiku",
    "gn:name":"Nukiyayoigaoka",
    "iso:country":"JP",
    "wof:name":"800-0234",
    "wof:placetype":"postalcode"
},
  "geometry": {"coordinates":[130.93049999999999,33.8067],"type":"Point"}
}