{
  "type": "Feature",
  "properties": {
    "gn:adm1_name":"Hyougoken",
    "gn:adm2_name":"Miharagunseidanchou",
    "gn:name":"Anaganishiji",
    "iso:country":"JP",
    "wof:name":"656-0663",
    "wof:placetype":"postalcode"
},
  "geometry": {"coordinates":[134.67160000000001,34.312],"type":"Point"}
}