{
  "type": "Feature",
  "properties": {
    "gn:adm1_name":"Toyamaken",
    "gn:adm2_name":"Takaokashi",
    "gn:name":"Aobachou",
    "iso:country":"JP",
    "wof:name":"933-0061",
    "wof:placetype":"postalcode"
},
  "geometry": {"coordinates":[137.0343,36.7612],"type":"Point"}
}