{
  "type": "Feature",
  "properties": {
    "gn:adm1_name":"Okayamaken",
    "gn:adm2_name":"Akaiwagunsetochou",
    "gn:name":"Kan'Onji",
    "iso:country":"JP",
    "wof:name":"709-0863",
    "wof:placetype":"postalcode"
},
  "geometry": {"coordinates":[134.01060000000001,34.7244],"type":"Point"}
}