{
  "type": "Feature",
  "properties": {
    "gn:adm1_name":"Hiroshimaken",
    "gn:adm2_name":"Ootakeshi",
    "gn:name":"Kuritanichouokutanijiri",
    "iso:country":"JP",
    "wof:name":"739-0642",
    "wof:placetype":"postalcode"
},
  "geometry": {"coordinates":[132.1918,34.3018],"type":"Point"}
}