{
  "type": "Feature",
  "properties": {
    "gn:adm1_name":"Kyoutofu",
    "gn:adm2_name":"Nakagunmineyamachou",
    "gn:name":"Ninbari",
    "iso:country":"JP",
    "wof:name":"627-0043",
    "wof:placetype":"postalcode"
},
  "geometry": {"coordinates":[135.0506,35.6083],"type":"Point"}
}