{
  "type": "Feature",
  "properties": {
    "gn:adm1_name":"Fukushimaken",
    "gn:adm2_name":"Oonumagun'Aiduhongoumachi",
    "gn:name":"Iehigashikou",
    "iso:country":"JP",
    "wof:name":"969-6112",
    "wof:placetype":"postalcode"
},
  "geometry": {"coordinates":[139.9023,37.4507],"type":"Point"}
}