{
  "type": "Feature",
  "properties": {
    "gn:adm1_name":"Saitamaken",
    "gn:adm2_name":"Fukayashi",
    "gn:name":"Ooduka",
    "iso:country":"JP",
    "wof:name":"366-0003",
    "wof:placetype":"postalcode"
},
  "geometry": {"coordinates":[139.27350000000001,36.2265],"type":"Point"}
}