{
  "type": "Feature",
  "properties": {
    "gn:adm1_name":"Kumamotoken",
    "gn:adm2_name":"Kamotogun'Uekimachi",
    "gn:name":"Daiwa",
    "iso:country":"JP",
    "wof:name":"861-0143",
    "wof:placetype":"postalcode"
},
  "geometry": {"coordinates":[130.6712,32.8817],"type":"Point"}
}