{
  "type": "Feature",
  "properties": {
    "gn:adm1_name":"Chibaken",
    "gn:adm2_name":"Kisaradushi",
    "gn:name":"Ookubo",
    "iso:country":"JP",
    "wof:name":"292-0815",
    "wof:placetype":"postalcode"
},
  "geometry": {"coordinates":[139.93360000000001,35.3432],"type":"Point"}
}