{
  "type": "Feature",
  "properties": {
    "gn:adm1_name":"Naraken",
    "gn:adm2_name":"Goseshi",
    "gn:name":"Takama",
    "iso:country":"JP",
    "wof:name":"639-2336",
    "wof:placetype":"postalcode"
},
  "geometry": {"coordinates":[135.69820000000001,34.419],"type":"Point"}
}