{
  "type": "Feature",
  "properties": {
    "gn:adm1_name":"Okayamaken",
    "gn:adm2_name":"Okayamashi",
    "gn:name":"Kamitsuchida",
    "iso:country":"JP",
    "wof:name":"701-1465",
    "wof:placetype":"postalcode"
},
  "geometry": {"coordinates":[133.80410000000001,34.7062],"type":"Point"}
}