{
  "type": "Feature",
  "properties": {
    "gn:adm1_name":"Yamaguchiken",
    "gn:adm2_name":"Iwakunishi",
    "gn:name":"Nagano",
    "iso:country":"JP",
    "wof:name":"740-0045",
    "wof:placetype":"postalcode"
},
  "geometry": {"coordinates":[132.19839999999999,34.0555],"type":"Point"}
}