{
  "type": "Feature",
  "properties": {
    "gn:adm1_name":"Kanagawaken",
    "gn:adm2_name":"Iseharashi",
    "gn:name":"Okazaki",
    "iso:country":"JP",
    "wof:name":"259-1135",
    "wof:placetype":"postalcode"
},
  "geometry": {"coordinates":[139.31290000000001,35.3803],"type":"Point"}
}