{
  "type": "Feature",
  "properties": {
    "gn:adm1_name":"Fukuiken",
    "gn:adm2_name":"Ooiguntakahamachou",
    "gn:name":"Imadera",
    "iso:country":"JP",
    "wof:name":"919-2376",
    "wof:placetype":"postalcode"
},
  "geometry": {"coordinates":[135.4796,35.4964],"type":"Point"}
}