{
  "type": "Feature",
  "properties": {
    "gn:adm1_name":"Chibaken",
    "gn:adm2_name":"Narashinoshi",
    "gn:name":"Saginumadai",
    "iso:country":"JP",
    "wof:name":"275-0015",
    "wof:placetype":"postalcode"
},
  "geometry": {"coordinates":[140.03700000000001,35.6805],"type":"Point"}
}