{
  "type": "Feature",
  "properties": {
    "gn:adm1_name":"Oosakafu",
    "gn:adm2_name":"Oosakashinishiku",
    "gn:name":"Ajigawa",
    "iso:country":"JP",
    "wof:name":"550-0026",
    "wof:placetype":"postalcode"
},
  "geometry": {"coordinates":[135.46690000000001,34.6784],"type":"Point"}
}