{
  "type": "Feature",
  "properties": {
    "gn:adm1_name":"Hyougoken",
    "gn:adm2_name":"Amagasakishi",
    "gn:name":"Tomatsuchou",
    "iso:country":"JP",
    "wof:name":"661-0003",
    "wof:placetype":"postalcode"
},
  "geometry": {"coordinates":[135.4023,34.7578],"type":"Point"}
}