{
  "type": "Feature",
  "properties": {
    "gn:adm1_name":"Fukushimaken",
    "gn:adm2_name":"Kooriyamashi",
    "gn:name":"Kayanoki",
    "iso:country":"JP",
    "wof:name":"963-8829",
    "wof:placetype":"postalcode"
},
  "geometry": {"coordinates":[140.3972,37.3872],"type":"Point"}
}