{
  "type": "Feature",
  "properties": {
    "gn:adm1_name":"Fukuiken",
    "gn:adm2_name":"Mikatagunmihamachou",
    "gn:name":"Sagaki",
    "iso:country":"JP",
    "wof:name":"919-1132",
    "wof:placetype":"postalcode"
},
  "geometry": {"coordinates":[135.95609999999999,35.609],"type":"Point"}
}