{
  "type": "Feature",
  "properties": {
    "gn:adm1_name":"Fukuokaken",
    "gn:adm2_name":"Nakamashi",
    "gn:name":"Nakasokoino",
    "iso:country":"JP",
    "wof:name":"809-0002",
    "wof:placetype":"postalcode"
},
  "geometry": {"coordinates":[130.6782,33.8219],"type":"Point"}
}