{
  "type": "Feature",
  "properties": {
    "gn:adm1_name":"Niigataken",
    "gn:adm2_name":"Nishikanbaragun'Ajikatamura",
    "gn:name":"Ajikata",
    "iso:country":"JP",
    "wof:name":"950-1261",
    "wof:placetype":"postalcode"
},
  "geometry": {"coordinates":[139.00909999999999,37.7798],"type":"Point"}
}