{
  "type": "Feature",
  "properties": {
    "gn:adm1_name":"Ibarakiken",
    "gn:adm2_name":"Tsukubashi",
    "gn:name":"Toukoudai",
    "iso:country":"JP",
    "wof:name":"300-2635",
    "wof:placetype":"postalcode"
},
  "geometry": {"coordinates":[140.06610000000001,36.0945],"type":"Point"}
}