{
  "type": "Feature",
  "properties": {
    "gn:adm1_name":"Niigataken",
    "gn:adm2_name":"Sadogun'Akadomarimura",
    "gn:name":"Akadomari",
    "iso:country":"JP",
    "wof:name":"952-0711",
    "wof:placetype":"postalcode"
},
  "geometry": {"coordinates":[138.40860000000001,37.868],"type":"Point"}
}