{
  "type": "Feature",
  "properties": {
    "gn:adm1_name":"Okayamaken",
    "gn:adm2_name":"Maniwagunkatsuyamachou",
    "gn:name":"Shibara",
    "iso:country":"JP",
    "wof:name":"717-0014",
    "wof:placetype":"postalcode"
},
  "geometry": {"coordinates":[133.7123,35.0996],"type":"Point"}
}