{
  "type": "Feature",
  "properties": {
    "gn:adm1_name":"Aichiken",
    "gn:adm2_name":"Kounanshi",
    "gn:name":"Ushirohibochouhigashitakase",
    "iso:country":"JP",
    "wof:name":"483-8344",
    "wof:placetype":"postalcode"
},
  "geometry": {"coordinates":[136.84700000000001,35.3462],"type":"Point"}
}