{
  "type": "Feature",
  "properties": {
    "gn:adm1_name":"Aichiken",
    "gn:adm2_name":"Shinshiroshi",
    "gn:name":"Takehiro",
    "iso:country":"JP",
    "wof:name":"441-1305",
    "wof:placetype":"postalcode"
},
  "geometry": {"coordinates":[137.52610000000001,34.9158],"type":"Point"}
}