{
  "type": "Feature",
  "properties": {
    "gn:adm1_name":"Hyougoken",
    "gn:adm2_name":"Itamishi",
    "gn:name":"Sakuragaoka",
    "iso:country":"JP",
    "wof:name":"664-0897",
    "wof:placetype":"postalcode"
},
  "geometry": {"coordinates":[135.41,34.7851],"type":"Point"}
}