{
  "type": "Feature",
  "properties": {
    "gn:adm1_name":"Kyoutofu",
    "gn:adm2_name":"Kyoutoshiyamashinaku",
    "gn:name":"Otowanakashibachou",
    "iso:country":"JP",
    "wof:name":"607-8069",
    "wof:placetype":"postalcode"
},
  "geometry": {"coordinates":[135.8237,34.9844],"type":"Point"}
}