{
  "type": "Feature",
  "properties": {
    "gn:adm1_name":"Tottoriken",
    "gn:adm2_name":"Touhakugunmisasachou",
    "gn:name":"Ooze",
    "iso:country":"JP",
    "wof:name":"682-0121",
    "wof:placetype":"postalcode"
},
  "geometry": {"coordinates":[133.8664,35.4098],"type":"Point"}
}