{
  "type": "Feature",
  "properties": {
    "gn:adm1_name":"Kouchiken",
    "gn:adm2_name":"Kouchishi",
    "gn:name":"Hattanchou",
    "iso:country":"JP",
    "wof:name":"780-0912",
    "wof:placetype":"postalcode"
},
  "geometry": {"coordinates":[133.5239,33.5677],"type":"Point"}
}