{
  "type": "Feature",
  "properties": {
    "gn:adm1_name":"Fukuokaken",
    "gn:adm2_name":"Tagawashi",
    "gn:name":"Kotobukimachi",
    "iso:country":"JP",
    "wof:name":"825-0017",
    "wof:placetype":"postalcode"
},
  "geometry": {"coordinates":[130.81229999999999,33.6469],"type":"Point"}
}