{
  "type": "Feature",
  "properties": {
    "gn:adm1_name":"Yamagataken",
    "gn:adm2_name":"Higashineshi",
    "gn:name":"Itagakikitadoori",
    "iso:country":"JP",
    "wof:name":"999-3744",
    "wof:placetype":"postalcode"
},
  "geometry": {"coordinates":[140.39250000000001,38.413],"type":"Point"}
}