{
  "type": "Feature",
  "properties": {
    "gn:adm1_name":"Aichiken",
    "gn:adm2_name":"Nishikasugaigunkiyosuchou",
    "gn:name":"Nishitanaka",
    "iso:country":"JP",
    "wof:name":"452-0933",
    "wof:placetype":"postalcode"
},
  "geometry": {"coordinates":[136.8501,35.2148],"type":"Point"}
}