{
  "type": "Feature",
  "properties": {
    "gn:adm1_name":"Naganoken",
    "gn:adm2_name":"Minamiadumigun'Azusagawamura",
    "gn:name":"Yamato",
    "iso:country":"JP",
    "wof:name":"390-1701",
    "wof:placetype":"postalcode"
},
  "geometry": {"coordinates":[137.89320000000001,36.2344],"type":"Point"}
}