{
  "type": "Feature",
  "properties": {
    "gn:adm1_name":"Hyougoken",
    "gn:adm2_name":"Amagasakishi",
    "gn:name":"Ougimachi",
    "iso:country":"JP",
    "wof:name":"660-0096",
    "wof:placetype":"postalcode"
},
  "geometry": {"coordinates":[135.41300000000001,34.7401],"type":"Point"}
}