{
  "type": "Feature",
  "properties": {
    "gn:adm1_name":"Kagoshimaken",
    "gn:adm2_name":"Satsumagunkamikoshikimura",
    "gn:name":"Nakakoshiki",
    "iso:country":"JP",
    "wof:name":"896-1201",
    "wof:placetype":"postalcode"
},
  "geometry": {"coordinates":[129.86539999999999,31.8356],"type":"Point"}
}