{
  "type": "Feature",
  "properties": {
    "gn:adm1_name":"Tottoriken",
    "gn:adm2_name":"Touhakugunmisasachou",
    "gn:name":"Sougenji",
    "iso:country":"JP",
    "wof:name":"682-0374",
    "wof:placetype":"postalcode"
},
  "geometry": {"coordinates":[133.8389,35.3368],"type":"Point"}
}