{
  "type": "Feature",
  "properties": {
    "gn:adm1_name":"Chibaken",
    "gn:adm2_name":"Katorigun'Omigawamachi",
    "gn:name":"Gogouchi",
    "iso:country":"JP",
    "wof:name":"289-0328",
    "wof:placetype":"postalcode"
},
  "geometry": {"coordinates":[140.6233,35.8263],"type":"Point"}
}