{
  "type": "Feature",
  "properties": {
    "gn:adm1_name":"Chibaken",
    "gn:adm2_name":"Katsuurashi",
    "gn:name":"Komatsuno",
    "iso:country":"JP",
    "wof:name":"299-5219",
    "wof:placetype":"postalcode"
},
  "geometry": {"coordinates":[140.27160000000001,35.1977],"type":"Point"}
}