{
  "type": "Feature",
  "properties": {
    "gn:adm1_name":"Ishikawaken",
    "gn:adm2_name":"Fugeshigunmonzenmachi",
    "gn:name":"Kazahara",
    "iso:country":"JP",
    "wof:name":"927-2143",
    "wof:placetype":"postalcode"
},
  "geometry": {"coordinates":[136.77010000000001,37.2573],"type":"Point"}
}