{
  "type": "Feature",
  "properties": {
    "gn:adm1_name":"Ibarakiken",
    "gn:adm2_name":"Tsukubashi",
    "gn:name":"Shimana",
    "iso:country":"JP",
    "wof:name":"300-2655",
    "wof:placetype":"postalcode"
},
  "geometry": {"coordinates":[140.05369999999999,36.0627],"type":"Point"}
}