{
  "type": "Feature",
  "properties": {
    "gn:adm1_name":"Gifuken",
    "gn:adm2_name":"Kamogunhichisouchou",
    "gn:name":"Kamiasou",
    "iso:country":"JP",
    "wof:name":"509-0401",
    "wof:placetype":"postalcode"
},
  "geometry": {"coordinates":[137.12379999999999,35.5513],"type":"Point"}
}