{
  "type": "Feature",
  "properties": {
    "gn:adm1_name":"Naraken",
    "gn:adm2_name":"Goseshi",
    "gn:name":"Gokurakuji",
    "iso:country":"JP",
    "wof:name":"639-2337",
    "wof:placetype":"postalcode"
},
  "geometry": {"coordinates":[135.70650000000001,34.4238],"type":"Point"}
}