{
  "type": "Feature",
  "properties": {
    "gn:adm1_name":"Toyamaken",
    "gn:adm2_name":"Nakaniikawagunkamiichimachi",
    "gn:name":"Orito",
    "iso:country":"JP",
    "wof:name":"930-0435",
    "wof:placetype":"postalcode"
},
  "geometry": {"coordinates":[137.44380000000001,36.6862],"type":"Point"}
}