{
  "type": "Feature",
  "properties": {
    "gn:adm1_name":"Fukushimaken",
    "gn:adm2_name":"Kitakatashi",
    "gn:name":"Hosoda",
    "iso:country":"JP",
    "wof:name":"966-0816",
    "wof:placetype":"postalcode"
},
  "geometry": {"coordinates":[139.87309999999999,37.6515],"type":"Point"}
}