{
  "type": "Feature",
  "properties": {
    "gn:adm1_name":"Oosakafu",
    "gn:adm2_name":"Neyagawashi",
    "gn:name":"Naritanishimachi",
    "iso:country":"JP",
    "wof:name":"572-0005",
    "wof:placetype":"postalcode"
},
  "geometry": {"coordinates":[135.63800000000001,34.7789],"type":"Point"}
}