{
  "type": "Feature",
  "properties": {
    "gn:adm1_name":"Fukushimaken",
    "gn:adm2_name":"Fukushimashi",
    "gn:name":"Higashihamachou",
    "iso:country":"JP",
    "wof:name":"960-8132",
    "wof:placetype":"postalcode"
},
  "geometry": {"coordinates":[140.48519999999999,37.7621],"type":"Point"}
}