{
  "type": "Feature",
  "properties": {
    "gn:adm1_name":"Kumamotoken",
    "gn:adm2_name":"Tamanagunkikusuimachi",
    "gn:name":"Ooya",
    "iso:country":"JP",
    "wof:name":"865-0112",
    "wof:placetype":"postalcode"
},
  "geometry": {"coordinates":[130.63929999999999,33.0053],"type":"Point"}
}