{
  "type": "Feature",
  "properties": {
    "gn:adm1_name":"Yamaguchiken",
    "gn:adm2_name":"Hagishi",
    "gn:name":"Hamasakichou",
    "iso:country":"JP",
    "wof:name":"758-0022",
    "wof:placetype":"postalcode"
},
  "geometry": {"coordinates":[131.40100000000001,34.4203],"type":"Point"}
}