{
  "type": "Feature",
  "properties": {
    "gn:adm1_name":"Wakayamaken",
    "gn:adm2_name":"Nagagun'Iwadechou",
    "gn:name":"Funato",
    "iso:country":"JP",
    "wof:name":"649-6225",
    "wof:placetype":"postalcode"
},
  "geometry": {"coordinates":[135.3117,34.2489],"type":"Point"}
}