{
  "type": "Feature",
  "properties": {
    "gn:adm1_name":"Saitamaken",
    "gn:adm2_name":"Asakashi",
    "gn:name":"Sakaechou",
    "iso:country":"JP",
    "wof:name":"351-0012",
    "wof:placetype":"postalcode"
},
  "geometry": {"coordinates":[139.59899999999999,35.789],"type":"Point"}
}