{
  "type": "Feature",
  "properties": {
    "gn:adm1_name":"Nagasakiken",
    "gn:adm2_name":"Nagasakishi",
    "gn:name":"Nishiki",
    "iso:country":"JP",
    "wof:name":"852-8045",
    "wof:placetype":"postalcode"
},
  "geometry": {"coordinates":[129.8535,32.7893],"type":"Point"}
}