{
  "type": "Feature",
  "properties": {
    "gn:adm1_name":"Kyoutofu",
    "gn:adm2_name":"Sourakugunseikachou",
    "gn:name":"Shimokoma",
    "iso:country":"JP",
    "wof:name":"619-0245",
    "wof:placetype":"postalcode"
},
  "geometry": {"coordinates":[135.7886,34.7763],"type":"Point"}
}