{
  "type": "Feature",
  "properties": {
    "gn:adm1_name":"Aichiken",
    "gn:adm2_name":"Okazakishi",
    "gn:name":"Oobatachou",
    "iso:country":"JP",
    "wof:name":"444-3502",
    "wof:placetype":"postalcode"
},
  "geometry": {"coordinates":[137.273,34.9076],"type":"Point"}
}