{
  "type": "Feature",
  "properties": {
    "gn:adm1_name":"Toyamaken",
    "gn:adm2_name":"Neigunhosoirimura",
    "gn:name":"Sasadu",
    "iso:country":"JP",
    "wof:name":"939-2181",
    "wof:placetype":"postalcode"
},
  "geometry": {"coordinates":[137.2159,36.5562],"type":"Point"}
}