{
  "type": "Feature",
  "properties": {
    "gn:adm1_name":"Yamanashiken",
    "gn:adm2_name":"Minamikomagunminobuchou",
    "gn:name":"Hinoue",
    "iso:country":"JP",
    "wof:name":"409-2414",
    "wof:placetype":"postalcode"
},
  "geometry": {"coordinates":[138.45779999999999,35.3395],"type":"Point"}
}