{
  "type": "Feature",
  "properties": {
    "gn:adm1_name":"Ishikawaken",
    "gn:adm2_name":"Komatsushi",
    "gn:name":"Zaimokuchou",
    "iso:country":"JP",
    "wof:name":"923-0916",
    "wof:placetype":"postalcode"
},
  "geometry": {"coordinates":[136.4504,36.4073],"type":"Point"}
}