{
  "type": "Feature",
  "properties": {
    "gn:adm1_name":"Hyougoken",
    "gn:adm2_name":"Kakogunharimachou",
    "gn:name":"Ikanikeisaiganaibaai",
    "iso:country":"JP",
    "wof:name":"675-0100",
    "wof:placetype":"postalcode"
},
  "geometry": {"coordinates":[134.87729999999999,34.7132],"type":"Point"}
}