{
  "type": "Feature",
  "properties": {
    "gn:adm1_name":"Aichiken",
    "gn:adm2_name":"Toyohashishi",
    "gn:name":"Uchibarichou",
    "iso:country":"JP",
    "wof:name":"441-8147",
    "wof:placetype":"postalcode"
},
  "geometry": {"coordinates":[137.37639999999999,34.7292],"type":"Point"}
}