{
  "type": "Feature",
  "properties": {
    "gn:adm1_name":"Fukuokaken",
    "gn:adm2_name":"Yukuhashishi",
    "gn:name":"Shimohieda",
    "iso:country":"JP",
    "wof:name":"824-0054",
    "wof:placetype":"postalcode"
},
  "geometry": {"coordinates":[130.93889999999999,33.7058],"type":"Point"}
}