{
  "type": "Feature",
  "properties": {
    "gn:adm1_name":"Toukyouto",
    "gn:adm2_name":"Suginamiku",
    "gn:name":"Kugayama",
    "iso:country":"JP",
    "wof:name":"168-0082",
    "wof:placetype":"postalcode"
},
  "geometry": {"coordinates":[139.59899999999999,35.6878],"type":"Point"}
}