{
  "type": "Feature",
  "properties": {
    "gn:adm1_name":"Kouchiken",
    "gn:adm2_name":"Sukumoshi",
    "gn:name":"Hashikamichouhashikami",
    "iso:country":"JP",
    "wof:name":"788-0046",
    "wof:placetype":"postalcode"
},
  "geometry": {"coordinates":[132.7687,32.9804],"type":"Point"}
}