{
  "type": "Feature",
  "properties": {
    "gn:adm1_name":"Kyoutofu",
    "gn:adm2_name":"Nakagunmineyamachou",
    "gn:name":"Koumyouji",
    "iso:country":"JP",
    "wof:name":"627-0035",
    "wof:placetype":"postalcode"
},
  "geometry": {"coordinates":[135.0615,35.6173],"type":"Point"}
}