{
  "type": "Feature",
  "properties": {
    "gn:adm1_name":"Naraken",
    "gn:adm2_name":"Udagunhaibarachou",
    "gn:name":"Akanedai",
    "iso:country":"JP",
    "wof:name":"633-0256",
    "wof:placetype":"postalcode"
},
  "geometry": {"coordinates":[135.94990000000001,34.5338],"type":"Point"}
}