{
  "type": "Feature",
  "properties": {
    "gn:adm1_name":"Tokushimaken",
    "gn:adm2_name":"Nakagun'Aioichou",
    "gn:name":"Asou",
    "iso:country":"JP",
    "wof:name":"771-5401",
    "wof:placetype":"postalcode"
},
  "geometry": {"coordinates":[134.48650000000001,33.8314],"type":"Point"}
}