{
  "type": "Feature",
  "properties": {
    "gn:adm1_name":"Naganoken",
    "gn:adm2_name":"Naganoshi",
    "gn:name":"Matsushiromachitoyosaka",
    "iso:country":"JP",
    "wof:name":"381-1222",
    "wof:placetype":"postalcode"
},
  "geometry": {"coordinates":[138.22749999999999,36.5451],"type":"Point"}
}