{
  "type": "Feature",
  "properties": {
    "gn:adm1_name":"Oosakafu",
    "gn:adm2_name":"Kashiwarashi",
    "gn:name":"Hongou",
    "iso:country":"JP",
    "wof:name":"582-0001",
    "wof:placetype":"postalcode"
},
  "geometry": {"coordinates":[135.61590000000001,34.5903],"type":"Point"}
}