{
  "type": "Feature",
  "properties": {
    "gn:adm1_name":"Miyagiken",
    "gn:adm2_name":"Motoyoshigunmotoyoshichou",
    "gn:name":"Koganezawa",
    "iso:country":"JP",
    "wof:name":"988-0285",
    "wof:placetype":"postalcode"
},
  "geometry": {"coordinates":[141.53110000000001,38.7978],"type":"Point"}
}