{
  "type": "Feature",
  "properties": {
    "gn:adm1_name":"Gunmaken",
    "gn:adm2_name":"Agatsumagunnakanojoumachi",
    "gn:name":"Yokoo",
    "iso:country":"JP",
    "wof:name":"377-0415",
    "wof:placetype":"postalcode"
},
  "geometry": {"coordinates":[138.86080000000001,36.6014],"type":"Point"}
}