{
  "type": "Feature",
  "properties": {
    "gn:adm1_name":"Shigaken",
    "gn:adm2_name":"Inukamigunkourachou",
    "gn:name":"Yokozeki",
    "iso:country":"JP",
    "wof:name":"522-0262",
    "wof:placetype":"postalcode"
},
  "geometry": {"coordinates":[136.26560000000001,35.203],"type":"Point"}
}