{
  "type": "Feature",
  "properties": {
    "gn:adm1_name":"Aichiken",
    "gn:adm2_name":"Higashikamogun'Asahichou",
    "gn:name":"Ikuma",
    "iso:country":"JP",
    "wof:name":"444-2807",
    "wof:placetype":"postalcode"
},
  "geometry": {"coordinates":[137.39099999999999,35.1939],"type":"Point"}
}