{
  "type": "Feature",
  "properties": {
    "gn:adm1_name":"Shizuokaken",
    "gn:adm2_name":"Iwatashi",
    "gn:name":"Kitajima",
    "iso:country":"JP",
    "wof:name":"438-0064",
    "wof:placetype":"postalcode"
},
  "geometry": {"coordinates":[137.83850000000001,34.6954],"type":"Point"}
}