{
  "type": "Feature",
  "properties": {
    "gn:adm1_name":"Niigataken",
    "gn:adm2_name":"Santougunmishimamachi",
    "gn:name":"Miyasawa",
    "iso:country":"JP",
    "wof:name":"940-2301",
    "wof:placetype":"postalcode"
},
  "geometry": {"coordinates":[138.78559999999999,37.5093],"type":"Point"}
}