{
  "type": "Feature",
  "properties": {
    "gn:adm1_name":"Kagoshimaken",
    "gn:adm2_name":"Ookuchishi",
    "gn:name":"Aoki",
    "iso:country":"JP",
    "wof:name":"895-2504",
    "wof:placetype":"postalcode"
},
  "geometry": {"coordinates":[130.64699999999999,32.0615],"type":"Point"}
}