{
  "type": "Feature",
  "properties": {
    "gn:adm1_name":"Chibaken",
    "gn:adm2_name":"Chibashichuuouku",
    "gn:name":"Minamioyumichou",
    "iso:country":"JP",
    "wof:name":"260-0814",
    "wof:placetype":"postalcode"
},
  "geometry": {"coordinates":[140.14500000000001,35.5569],"type":"Point"}
}