{
  "type": "Feature",
  "properties": {
    "gn:adm1_name":"Kagawaken",
    "gn:adm2_name":"Sakaideshi",
    "gn:name":"Kazashichou",
    "iso:country":"JP",
    "wof:name":"762-0038",
    "wof:placetype":"postalcode"
},
  "geometry": {"coordinates":[133.85669999999999,34.3078],"type":"Point"}
}