{
  "type": "Feature",
  "properties": {
    "gn:adm1_name":"Aichiken",
    "gn:adm2_name":"Kounanshi",
    "gn:name":"Yamajirichouhonmaru",
    "iso:country":"JP",
    "wof:name":"483-8038",
    "wof:placetype":"postalcode"
},
  "geometry": {"coordinates":[136.88890000000001,35.3502],"type":"Point"}
}