{
  "type": "Feature",
  "properties": {
    "gn:adm1_name":"Chibaken",
    "gn:adm2_name":"Naritashi",
    "gn:name":"Ashida",
    "iso:country":"JP",
    "wof:name":"286-0831",
    "wof:placetype":"postalcode"
},
  "geometry": {"coordinates":[140.32550000000001,35.8207],"type":"Point"}
}