{
  "type": "Feature",
  "properties": {
    "gn:adm1_name":"Kagawaken",
    "gn:adm2_name":"Marugameshi",
    "gn:name":"Furutaimachi",
    "iso:country":"JP",
    "wof:name":"763-0001",
    "wof:placetype":"postalcode"
},
  "geometry": {"coordinates":[133.7998,34.2924],"type":"Point"}
}