{
  "type": "Feature",
  "properties": {
    "gn:adm1_name":"Hyougoken",
    "gn:adm2_name":"Tsunagun'Awajichou",
    "gn:name":"Iwaya",
    "iso:country":"JP",
    "wof:name":"656-2401",
    "wof:placetype":"postalcode"
},
  "geometry": {"coordinates":[135.01509999999999,34.5908],"type":"Point"}
}