{
  "type": "Feature",
  "properties": {
    "gn:adm1_name":"Saitamaken",
    "gn:adm2_name":"Kitakatsushikagunwashimiyamachi",
    "gn:name":"Kuzume",
    "iso:country":"JP",
    "wof:name":"340-0214",
    "wof:placetype":"postalcode"
},
  "geometry": {"coordinates":[139.65459999999999,36.0927],"type":"Point"}
}