{
  "type": "Feature",
  "properties": {
    "gn:adm1_name":"Chibaken",
    "gn:adm2_name":"Kisaradushi",
    "gn:name":"Nakajima",
    "iso:country":"JP",
    "wof:name":"292-0008",
    "wof:placetype":"postalcode"
},
  "geometry": {"coordinates":[139.92420000000001,35.434],"type":"Point"}
}