{
  "type": "Feature",
  "properties": {
    "gn:adm1_name":"Kyoutofu",
    "gn:adm2_name":"Kyoutoshifushimiku",
    "gn:name":"Ginzachou",
    "iso:country":"JP",
    "wof:name":"612-8089",
    "wof:placetype":"postalcode"
},
  "geometry": {"coordinates":[135.76400000000001,34.9354],"type":"Point"}
}