{
  "type": "Feature",
  "properties": {
    "gn:adm1_name":"Hyougoken",
    "gn:adm2_name":"Shisougunyamasakichou",
    "gn:name":"No",
    "iso:country":"JP",
    "wof:name":"671-2543",
    "wof:placetype":"postalcode"
},
  "geometry": {"coordinates":[134.54830000000001,34.9932],"type":"Point"}
}