{
  "type": "Feature",
  "properties": {
    "gn:adm1_name":"Tottoriken",
    "gn:adm2_name":"Kurayoshishi",
    "gn:name":"Idebata",
    "iso:country":"JP",
    "wof:name":"682-0006",
    "wof:placetype":"postalcode"
},
  "geometry": {"coordinates":[133.83459999999999,35.468],"type":"Point"}
}