{
  "type": "Feature",
  "properties": {
    "gn:adm1_name":"Niigataken",
    "gn:adm2_name":"Shironeshi",
    "gn:name":"Nakayama",
    "iso:country":"JP",
    "wof:name":"950-1421",
    "wof:placetype":"postalcode"
},
  "geometry": {"coordinates":[139.0531,37.7804],"type":"Point"}
}