{
  "type": "Feature",
  "properties": {
    "gn:adm1_name":"Mieken",
    "gn:adm2_name":"Yokkaichishi",
    "gn:name":"Hadu",
    "iso:country":"JP",
    "wof:name":"510-0012",
    "wof:placetype":"postalcode"
},
  "geometry": {"coordinates":[136.63079999999999,35.0019],"type":"Point"}
}