{
  "type": "Feature",
  "properties": {
    "gn:adm1_name":"Kyoutofu",
    "gn:adm2_name":"Ayabeshi",
    "gn:name":"Ariokachou",
    "iso:country":"JP",
    "wof:name":"623-0006",
    "wof:placetype":"postalcode"
},
  "geometry": {"coordinates":[135.26070000000001,35.3231],"type":"Point"}
}