{
  "type": "Feature",
  "properties": {
    "gn:adm1_name":"Okayamaken",
    "gn:adm2_name":"Soujashi",
    "gn:name":"Nagara",
    "iso:country":"JP",
    "wof:name":"719-1111",
    "wof:placetype":"postalcode"
},
  "geometry": {"coordinates":[133.78960000000001,34.6897],"type":"Point"}
}