{
  "type": "Feature",
  "properties": {
    "gn:adm1_name":"Miyagiken",
    "gn:adm2_name":"Ishinomakishi",
    "gn:name":"Sawada",
    "iso:country":"JP",
    "wof:name":"986-2102",
    "wof:placetype":"postalcode"
},
  "geometry": {"coordinates":[141.38130000000001,38.4388],"type":"Point"}
}