{
  "type": "Feature",
  "properties": {
    "gn:adm1_name":"Niigataken",
    "gn:adm2_name":"Niitsushi",
    "gn:name":"Shinkanazawachou",
    "iso:country":"JP",
    "wof:name":"956-0815",
    "wof:placetype":"postalcode"
},
  "geometry": {"coordinates":[139.14529999999999,37.7975],"type":"Point"}
}