{
  "type": "Feature",
  "properties": {
    "gn:adm1_name":"Kumamotoken",
    "gn:adm2_name":"Kamimashikigunmashikimachi",
    "gn:name":"Kamijin",
    "iso:country":"JP",
    "wof:name":"861-2203",
    "wof:placetype":"postalcode"
},
  "geometry": {"coordinates":[130.8569,32.8045],"type":"Point"}
}