{
  "type": "Feature",
  "properties": {
    "gn:adm1_name":"Niigataken",
    "gn:adm2_name":"Kitakanbaragunkajikawamura",
    "gn:name":"Shimonishiyama",
    "iso:country":"JP",
    "wof:name":"959-2417",
    "wof:placetype":"postalcode"
},
  "geometry": {"coordinates":[139.37370000000001,37.9989],"type":"Point"}
}