{
  "type": "Feature",
  "properties": {
    "gn:adm1_name":"Niigataken",
    "gn:adm2_name":"Nishikanbaraguntsukigatamura",
    "gn:name":"Tsuriyose",
    "iso:country":"JP",
    "wof:name":"950-1313",
    "wof:placetype":"postalcode"
},
  "geometry": {"coordinates":[138.97790000000001,37.7373],"type":"Point"}
}