{
  "type": "Feature",
  "properties": {
    "gn:adm1_name":"Mieken",
    "gn:adm2_name":"Inabeshi",
    "gn:name":"Inabechoukitakanai",
    "iso:country":"JP",
    "wof:name":"511-0223",
    "wof:placetype":"postalcode"
},
  "geometry": {"coordinates":[136.5608,35.104],"type":"Point"}
}