{
  "type": "Feature",
  "properties": {
    "gn:adm1_name":"Hyougoken",
    "gn:adm2_name":"Takaradukashi",
    "gn:name":"Yamamotominami",
    "iso:country":"JP",
    "wof:name":"665-0882",
    "wof:placetype":"postalcode"
},
  "geometry": {"coordinates":[135.3878,34.8164],"type":"Point"}
}