{
  "type": "Feature",
  "properties": {
    "gn:adm1_name":"Gifuken",
    "gn:adm2_name":"Enagunkushiharamura",
    "gn:name":"Matsubayashi",
    "iso:country":"JP",
    "wof:name":"509-7806",
    "wof:placetype":"postalcode"
},
  "geometry": {"coordinates":[137.4365,35.2582],"type":"Point"}
}