{
  "type": "Feature",
  "properties": {
    "gn:adm1_name":"Toyamaken",
    "gn:adm2_name":"Takaokashi",
    "gn:name":"Koufukumachi",
    "iso:country":"JP",
    "wof:name":"933-0067",
    "wof:placetype":"postalcode"
},
  "geometry": {"coordinates":[137.03030000000001,36.7636],"type":"Point"}
}