{
  "type": "Feature",
  "properties": {
    "gn:adm1_name":"Toyamaken",
    "gn:adm2_name":"Kurobeshi",
    "gn:name":"Tamomi",
    "iso:country":"JP",
    "wof:name":"938-0813",
    "wof:placetype":"postalcode"
},
  "geometry": {"coordinates":[137.51230000000001,36.8243],"type":"Point"}
}