{
  "type": "Feature",
  "properties": {
    "gn:adm1_name":"Tottoriken",
    "gn:adm2_name":"Yonagoshi",
    "gn:name":"Hatagasaki",
    "iso:country":"JP",
    "wof:name":"683-0845",
    "wof:placetype":"postalcode"
},
  "geometry": {"coordinates":[133.3133,35.44],"type":"Point"}
}