{
  "type": "Feature",
  "properties": {
    "gn:adm1_name":"Niigataken",
    "gn:adm2_name":"Shironeshi",
    "gn:name":"Hosaka",
    "iso:country":"JP",
    "wof:name":"950-1233",
    "wof:placetype":"postalcode"
},
  "geometry": {"coordinates":[139.02010000000001,37.7884],"type":"Point"}
}