{
  "type": "Feature",
  "properties": {
    "gn:adm1_name":"Fukuokaken",
    "gn:adm2_name":"Munakatashi",
    "gn:name":"Midorimachi",
    "iso:country":"JP",
    "wof:name":"811-4172",
    "wof:placetype":"postalcode"
},
  "geometry": {"coordinates":[130.5874,33.7963],"type":"Point"}
}