{
  "type": "Feature",
  "properties": {
    "gn:adm1_name":"Tochigiken",
    "gn:adm2_name":"Tochigishi",
    "gn:name":"Nonakamachi",
    "iso:country":"JP",
    "wof:name":"328-0124",
    "wof:placetype":"postalcode"
},
  "geometry": {"coordinates":[139.7175,36.4001],"type":"Point"}
}