{
  "type": "Feature",
  "properties": {
    "gn:adm1_name":"Kyoutofu",
    "gn:adm2_name":"Kyoutoshiukyouku",
    "gn:name":"Sagatenryuujishiinochou",
    "iso:country":"JP",
    "wof:name":"616-8357",
    "wof:placetype":"postalcode"
},
  "geometry": {"coordinates":[135.68450000000001,35.019],"type":"Point"}
}