{
  "type": "Feature",
  "properties": {
    "gn:adm1_name":"Okinawaken",
    "gn:adm2_name":"Kunigamigun'Onnason",
    "gn:name":"Fuchaku",
    "iso:country":"JP",
    "wof:name":"904-0413",
    "wof:placetype":"postalcode"
},
  "geometry": {"coordinates":[127.8079,26.4545],"type":"Point"}
}