{
  "type": "Feature",
  "properties": {
    "gn:adm1_name":"Gifuken",
    "gn:adm2_name":"Hashimashi",
    "gn:name":"Ajikachou",
    "iso:country":"JP",
    "wof:name":"501-6207",
    "wof:placetype":"postalcode"
},
  "geometry": {"coordinates":[136.72049999999999,35.3428],"type":"Point"}
}