{
  "type": "Feature",
  "properties": {
    "gn:adm1_name":"Kanagawaken",
    "gn:adm2_name":"Sagamiharashi",
    "gn:name":"Fujimi",
    "iso:country":"JP",
    "wof:name":"229-0036",
    "wof:placetype":"postalcode"
},
  "geometry": {"coordinates":[139.3792,35.5678],"type":"Point"}
}