{
  "type": "Feature",
  "properties": {
    "gn:adm1_name":"Naganoken",
    "gn:adm2_name":"Iidashi",
    "gn:name":"Asahimachi",
    "iso:country":"JP",
    "wof:name":"395-0055",
    "wof:placetype":"postalcode"
},
  "geometry": {"coordinates":[137.81710000000001,35.5137],"type":"Point"}
}