{
  "type": "Feature",
  "properties": {
    "gn:adm1_name":"Yamaguchiken",
    "gn:adm2_name":"Yanaishi",
    "gn:name":"Shinjou",
    "iso:country":"JP",
    "wof:name":"742-0033",
    "wof:placetype":"postalcode"
},
  "geometry": {"coordinates":[132.0873,33.9718],"type":"Point"}
}