{
  "type": "Feature",
  "properties": {
    "gn:adm1_name":"Yamagataken",
    "gn:adm2_name":"Akumigunyuzamachi",
    "gn:name":"Yoshide",
    "iso:country":"JP",
    "wof:name":"999-8302",
    "wof:placetype":"postalcode"
},
  "geometry": {"coordinates":[139.93700000000001,39.0242],"type":"Point"}
}