{
  "type": "Feature",
  "properties": {
    "gn:adm1_name":"Niigataken",
    "gn:adm2_name":"Minamikanbaragunsakaemachi",
    "gn:name":"Sannou",
    "iso:country":"JP",
    "wof:name":"959-1118",
    "wof:placetype":"postalcode"
},
  "geometry": {"coordinates":[138.91550000000001,37.5742],"type":"Point"}
}