{
  "type": "Feature",
  "properties": {
    "gn:adm1_name":"Naganoken",
    "gn:adm2_name":"Sakushi",
    "gn:name":"Uchiyama",
    "iso:country":"JP",
    "wof:name":"385-0031",
    "wof:placetype":"postalcode"
},
  "geometry": {"coordinates":[138.53749999999999,36.2282],"type":"Point"}
}