{
  "type": "Feature",
  "properties": {
    "gn:adm1_name":"Ishikawaken",
    "gn:adm2_name":"Kashimagunnakajimamachi",
    "gn:name":"Oodaira",
    "iso:country":"JP",
    "wof:name":"929-2207",
    "wof:placetype":"postalcode"
},
  "geometry": {"coordinates":[136.78809999999999,37.1444],"type":"Point"}
}