{
  "type": "Feature",
  "properties": {
    "gn:adm1_name":"Oosakafu",
    "gn:adm2_name":"Oosakashinishiyodogawaku",
    "gn:name":"Chifune",
    "iso:country":"JP",
    "wof:name":"555-0013",
    "wof:placetype":"postalcode"
},
  "geometry": {"coordinates":[135.452,34.7102],"type":"Point"}
}