{
  "type": "Feature",
  "properties": {
    "gn:adm1_name":"Niigataken",
    "gn:adm2_name":"Minamikanbaragunshitadamura",
    "gn:name":"Nagano",
    "iso:country":"JP",
    "wof:name":"955-0132",
    "wof:placetype":"postalcode"
},
  "geometry": {"coordinates":[139.11959999999999,37.5355],"type":"Point"}
}