{
  "type": "Feature",
  "properties": {
    "gn:adm1_name":"Shigaken",
    "gn:adm2_name":"Moriyamashi",
    "gn:name":"Hoshikachou",
    "iso:country":"JP",
    "wof:name":"524-0063",
    "wof:placetype":"postalcode"
},
  "geometry": {"coordinates":[135.96129999999999,35.0616],"type":"Point"}
}