{
  "type": "Feature",
  "properties": {
    "gn:adm1_name":"Tokushimaken",
    "gn:adm2_name":"Tokushimashi",
    "gn:name":"Minamisako7banchou",
    "iso:country":"JP",
    "wof:name":"770-0037",
    "wof:placetype":"postalcode"
},
  "geometry": {"coordinates":[134.5249,34.0745],"type":"Point"}
}