{
  "type": "Feature",
  "properties": {
    "gn:adm1_name":"Fukushimaken",
    "gn:adm2_name":"Yamagunyamatomachi",
    "gn:name":"Hirono",
    "iso:country":"JP",
    "wof:name":"969-4131",
    "wof:placetype":"postalcode"
},
  "geometry": {"coordinates":[139.77070000000001,37.6418],"type":"Point"}
}