{
  "type": "Feature",
  "properties": {
    "gn:adm1_name":"Fukuokaken",
    "gn:adm2_name":"Oomutashi",
    "gn:name":"Matsubaramachi",
    "iso:country":"JP",
    "wof:name":"836-0033",
    "wof:placetype":"postalcode"
},
  "geometry": {"coordinates":[130.43989999999999,33.0318],"type":"Point"}
}