{
  "type": "Feature",
  "properties": {
    "gn:adm1_name":"Kumamotoken",
    "gn:adm2_name":"Kumamotoshi",
    "gn:name":"Shinshigai",
    "iso:country":"JP",
    "wof:name":"860-0803",
    "wof:placetype":"postalcode"
},
  "geometry": {"coordinates":[130.70650000000001,32.7991],"type":"Point"}
}