{
  "type": "Feature",
  "properties": {
    "gn:adm1_name":"Kumamotoken",
    "gn:adm2_name":"Kumamotoshi",
    "gn:name":"Edu",
    "iso:country":"JP",
    "wof:name":"862-0942",
    "wof:placetype":"postalcode"
},
  "geometry": {"coordinates":[130.73490000000001,32.7774],"type":"Point"}
}