{
  "type": "Feature",
  "properties": {
    "gn:adm1_name":"Kagawaken",
    "gn:adm2_name":"Kan'Onjishi",
    "gn:name":"Ibukichou",
    "iso:country":"JP",
    "wof:name":"768-0071",
    "wof:placetype":"postalcode"
},
  "geometry": {"coordinates":[133.5351,34.1285],"type":"Point"}
}