{
  "type": "Feature",
  "properties": {
    "gn:adm1_name":"Aichiken",
    "gn:adm2_name":"Toyohashishi",
    "gn:name":"Fujimichou",
    "iso:country":"JP",
    "wof:name":"441-3126",
    "wof:placetype":"postalcode"
},
  "geometry": {"coordinates":[137.39400000000001,34.7491],"type":"Point"}
}