{
  "type": "Feature",
  "properties": {
    "gn:adm1_name":"Fukuokaken",
    "gn:adm2_name":"Yameshi",
    "gn:name":"Unoike",
    "iso:country":"JP",
    "wof:name":"834-0055",
    "wof:placetype":"postalcode"
},
  "geometry": {"coordinates":[130.529,33.208],"type":"Point"}
}