{
  "type": "Feature",
  "properties": {
    "gn:adm1_name":"Kyoutofu",
    "gn:adm2_name":"Kyoutoshisakyouku",
    "gn:name":"Ichijoujihigashisuginomiyachou",
    "iso:country":"JP",
    "wof:name":"606-8113",
    "wof:placetype":"postalcode"
},
  "geometry": {"coordinates":[135.7877,35.0465],"type":"Point"}
}