{
  "type": "Feature",
  "properties": {
    "gn:adm1_name":"Fukuokaken",
    "gn:adm2_name":"Chikujougunyoshitomimachi",
    "gn:name":"Niryou",
    "iso:country":"JP",
    "wof:name":"871-0833",
    "wof:placetype":"postalcode"
},
  "geometry": {"coordinates":[131.16380000000001,33.6008],"type":"Point"}
}