{
  "type": "Feature",
  "properties": {
    "gn:adm1_name":"Kumamotoken",
    "gn:adm2_name":"Kumagunmizukamimura",
    "gn:name":"Yuyama",
    "iso:country":"JP",
    "wof:name":"868-0703",
    "wof:placetype":"postalcode"
},
  "geometry": {"coordinates":[131.0478,32.321],"type":"Point"}
}