{
  "type": "Feature",
  "properties": {
    "gn:adm1_name":"Hyougoken",
    "gn:adm2_name":"Nishinomiyashi",
    "gn:name":"Notochou",
    "iso:country":"JP",
    "wof:name":"662-0838",
    "wof:placetype":"postalcode"
},
  "geometry": {"coordinates":[135.35079999999999,34.7513],"type":"Point"}
}