{
  "type": "Feature",
  "properties": {
    "gn:adm1_name":"Hiroshimaken",
    "gn:adm2_name":"Hiroshimashihigashiku",
    "gn:name":"Fukuda",
    "iso:country":"JP",
    "wof:name":"732-0029",
    "wof:placetype":"postalcode"
},
  "geometry": {"coordinates":[132.5472,34.4524],"type":"Point"}
}