{
  "type": "Feature",
  "properties": {
    "gn:adm1_name":"Fukushimaken",
    "gn:adm2_name":"Tamuragunfunehikimachi",
    "gn:name":"Imaizumi",
    "iso:country":"JP",
    "wof:name":"963-4311",
    "wof:placetype":"postalcode"
},
  "geometry": {"coordinates":[140.60210000000001,37.422],"type":"Point"}
}