{
  "type": "Feature",
  "properties": {
    "gn:adm1_name":"Hyougoken",
    "gn:adm2_name":"Kanzakigunfukusakichou",
    "gn:name":"Minamitawara",
    "iso:country":"JP",
    "wof:name":"679-2203",
    "wof:placetype":"postalcode"
},
  "geometry": {"coordinates":[134.75970000000001,34.9443],"type":"Point"}
}