{
  "type": "Feature",
  "properties": {
    "gn:adm1_name":"Aichiken",
    "gn:adm2_name":"Owariasahishi",
    "gn:name":"Inbamotochouhosoda",
    "iso:country":"JP",
    "wof:name":"488-0843",
    "wof:placetype":"postalcode"
},
  "geometry": {"coordinates":[137.01009999999999,35.2085],"type":"Point"}
}