{
  "type": "Feature",
  "properties": {
    "gn:adm1_name":"Ishikawaken",
    "gn:adm2_name":"Kanazawashi",
    "gn:name":"Konohanamachi",
    "iso:country":"JP",
    "wof:name":"920-0852",
    "wof:placetype":"postalcode"
},
  "geometry": {"coordinates":[136.65170000000001,36.5776],"type":"Point"}
}