{
  "type": "Feature",
  "properties": {
    "gn:adm1_name":"Ooitaken",
    "gn:adm2_name":"Usagun'Innaimachi",
    "gn:name":"Mikutsu",
    "iso:country":"JP",
    "wof:name":"872-0301",
    "wof:placetype":"postalcode"
},
  "geometry": {"coordinates":[131.32660000000001,33.4495],"type":"Point"}
}