{
  "type": "Feature",
  "properties": {
    "gn:adm1_name":"Ishikawaken",
    "gn:adm2_name":"Kagashi",
    "gn:name":"Kawaminamimachi(Yodomachi)",
    "iso:country":"JP",
    "wof:name":"922-0276",
    "wof:placetype":"postalcode"
},
  "geometry": {"coordinates":[136.35489999999999,36.2755],"type":"Point"}
}