{
  "type": "Feature",
  "properties": {
    "gn:adm1_name":"Oosakafu",
    "gn:adm2_name":"Toyonakashi",
    "gn:name":"Katsube",
    "iso:country":"JP",
    "wof:name":"561-0894",
    "wof:placetype":"postalcode"
},
  "geometry": {"coordinates":[135.4555,34.7764],"type":"Point"}
}