{
  "type": "Feature",
  "properties": {
    "gn:adm1_name":"Kyoutofu",
    "gn:adm2_name":"Nakagun'Oomiyachou",
    "gn:name":"Kusumi",
    "iso:country":"JP",
    "wof:name":"629-2511",
    "wof:placetype":"postalcode"
},
  "geometry": {"coordinates":[135.1327,35.6155],"type":"Point"}
}