{
  "type": "Feature",
  "properties": {
    "gn:adm1_name":"Fukushimaken",
    "gn:adm2_name":"Kooriyamashi",
    "gn:name":"Mihotamachinabeyama",
    "iso:country":"JP",
    "wof:name":"963-0123",
    "wof:placetype":"postalcode"
},
  "geometry": {"coordinates":[140.2869,37.3462],"type":"Point"}
}