{
  "type": "Feature",
  "properties": {
    "gn:adm1_name":"Toyamaken",
    "gn:adm2_name":"Takaokashi",
    "gn:name":"Ikarinishimachi",
    "iso:country":"JP",
    "wof:name":"933-0971",
    "wof:placetype":"postalcode"
},
  "geometry": {"coordinates":[136.9905,36.7775],"type":"Point"}
}