{
  "type": "Feature",
  "properties": {
    "gn:adm1_name":"Niigataken",
    "gn:adm2_name":"Minamikanbaragunnakanoshimamachi",
    "gn:name":"Kamegayashinden",
    "iso:country":"JP",
    "wof:name":"954-0177",
    "wof:placetype":"postalcode"
},
  "geometry": {"coordinates":[138.8664,37.5555],"type":"Point"}
}