{
  "type": "Feature",
  "properties": {
    "gn:adm1_name":"Yamaguchiken",
    "gn:adm2_name":"Abugun'Abuchou",
    "gn:name":"Sougou",
    "iso:country":"JP",
    "wof:name":"759-3502",
    "wof:placetype":"postalcode"
},
  "geometry": {"coordinates":[131.5615,34.586],"type":"Point"}
}