{
  "type": "Feature",
  "properties": {
    "gn:adm1_name":"Fukushimaken",
    "gn:adm2_name":"Kooriyamashi",
    "gn:name":"Momomidai",
    "iso:country":"JP",
    "wof:name":"963-8018",
    "wof:placetype":"postalcode"
},
  "geometry": {"coordinates":[140.3707,37.4039],"type":"Point"}
}