{
  "type": "Feature",
  "properties": {
    "gn:adm1_name":"Hyougoken",
    "gn:adm2_name":"Takaradukashi",
    "gn:name":"Nagatani",
    "iso:country":"JP",
    "wof:name":"669-1204",
    "wof:placetype":"postalcode"
},
  "geometry": {"coordinates":[135.3193,34.9175],"type":"Point"}
}