{
  "type": "Feature",
  "properties": {
    "gn:adm1_name":"Oosakafu",
    "gn:adm2_name":"Tondabayashishi",
    "gn:name":"Kongoufushamadai",
    "iso:country":"JP",
    "wof:name":"584-0065",
    "wof:placetype":"postalcode"
},
  "geometry": {"coordinates":[135.56540000000001,34.4873],"type":"Point"}
}