{
  "type": "Feature",
  "properties": {
    "gn:adm1_name":"Tokushimaken",
    "gn:adm2_name":"Mimagun'Anabukichou",
    "gn:name":"Furumiya",
    "iso:country":"JP",
    "wof:name":"777-0007",
    "wof:placetype":"postalcode"
},
  "geometry": {"coordinates":[134.1421,33.9602],"type":"Point"}
}