{
  "type": "Feature",
  "properties": {
    "gn:adm1_name":"Naganoken",
    "gn:adm2_name":"Komoroshi",
    "gn:name":"Sakanoue",
    "iso:country":"JP",
    "wof:name":"384-0018",
    "wof:placetype":"postalcode"
},
  "geometry": {"coordinates":[138.4315,36.3311],"type":"Point"}
}