{
  "type": "Feature",
  "properties": {
    "gn:adm1_name":"Toyamaken",
    "gn:adm2_name":"Neigunyamadamura",
    "gn:name":"Jouyama",
    "iso:country":"JP",
    "wof:name":"930-2122",
    "wof:placetype":"postalcode"
},
  "geometry": {"coordinates":[137.08099999999999,36.5939],"type":"Point"}
}