{
  "type": "Feature",
  "properties": {
    "gn:adm1_name":"Hiroshimaken",
    "gn:adm2_name":"Hiroshimashinishiku",
    "gn:name":"Misasamachi",
    "iso:country":"JP",
    "wof:name":"733-0003",
    "wof:placetype":"postalcode"
},
  "geometry": {"coordinates":[132.4537,34.4135],"type":"Point"}
}