{
  "type": "Feature",
  "properties": {
    "gn:adm1_name":"Aichiken",
    "gn:adm2_name":"Takahamashi",
    "gn:name":"Aomichou",
    "iso:country":"JP",
    "wof:name":"444-1324",
    "wof:placetype":"postalcode"
},
  "geometry": {"coordinates":[136.98500000000001,34.9194],"type":"Point"}
}