{
  "type": "Feature",
  "properties": {
    "gn:adm1_name":"Kyoutofu",
    "gn:adm2_name":"Miyadushi",
    "gn:name":"Higashino",
    "iso:country":"JP",
    "wof:name":"626-0222",
    "wof:placetype":"postalcode"
},
  "geometry": {"coordinates":[135.19739999999999,35.6444],"type":"Point"}
}