{
  "type": "Feature",
  "properties": {
    "gn:adm1_name":"Kanagawaken",
    "gn:adm2_name":"Yokohamashitotsukaku",
    "gn:name":"Kamishinano",
    "iso:country":"JP",
    "wof:name":"244-0806",
    "wof:placetype":"postalcode"
},
  "geometry": {"coordinates":[139.55189999999999,35.4347],"type":"Point"}
}