{
  "type": "Feature",
  "properties": {
    "gn:adm1_name":"Oosakafu",
    "gn:adm2_name":"Takatsukishi",
    "gn:name":"Amashinmachi",
    "iso:country":"JP",
    "wof:name":"569-1106",
    "wof:placetype":"postalcode"
},
  "geometry": {"coordinates":[135.62729999999999,34.8571],"type":"Point"}
}