{
  "type": "Feature",
  "properties": {
    "gn:adm1_name":"Miyagiken",
    "gn:adm2_name":"Motoyoshigunmotoyoshichou",
    "gn:name":"Nagane",
    "iso:country":"JP",
    "wof:name":"988-0264",
    "wof:placetype":"postalcode"
},
  "geometry": {"coordinates":[141.56780000000001,38.8207],"type":"Point"}
}