{
  "type": "Feature",
  "properties": {
    "gn:adm1_name":"Ishikawaken",
    "gn:adm2_name":"Komatsushi",
    "gn:name":"Tonomachi",
    "iso:country":"JP",
    "wof:name":"923-0919",
    "wof:placetype":"postalcode"
},
  "geometry": {"coordinates":[136.44970000000001,36.4112],"type":"Point"}
}