{
  "type": "Feature",
  "properties": {
    "gn:adm1_name":"Aichiken",
    "gn:adm2_name":"Okazakishi",
    "gn:name":"Shimowadachou",
    "iso:country":"JP",
    "wof:name":"444-0212",
    "wof:placetype":"postalcode"
},
  "geometry": {"coordinates":[137.1456,34.9083],"type":"Point"}
}