{
  "type": "Feature",
  "properties": {
    "gn:adm1_name":"Sagaken",
    "gn:adm2_name":"Karatsushi",
    "gn:name":"Futago",
    "iso:country":"JP",
    "wof:name":"847-0861",
    "wof:placetype":"postalcode"
},
  "geometry": {"coordinates":[129.95820000000001,33.46],"type":"Point"}
}