{
  "type": "Feature",
  "properties": {
    "gn:adm1_name":"Aichiken",
    "gn:adm2_name":"Minamishitaragunhouraichou",
    "gn:name":"Shiose",
    "iso:country":"JP",
    "wof:name":"441-1956",
    "wof:placetype":"postalcode"
},
  "geometry": {"coordinates":[137.4973,34.9831],"type":"Point"}
}