{
  "type": "Feature",
  "properties": {
    "gn:adm1_name":"Niigataken",
    "gn:adm2_name":"Higashikubikigunyasudukamachi",
    "gn:name":"Ishibashi",
    "iso:country":"JP",
    "wof:name":"942-0404",
    "wof:placetype":"postalcode"
},
  "geometry": {"coordinates":[138.44759999999999,37.118],"type":"Point"}
}