{
  "type": "Feature",
  "properties": {
    "gn:adm1_name":"Kyoutofu",
    "gn:adm2_name":"Kyoutoshiminamiku",
    "gn:name":"Kisshouinsatonouchichou",
    "iso:country":"JP",
    "wof:name":"601-8339",
    "wof:placetype":"postalcode"
},
  "geometry": {"coordinates":[135.73259999999999,34.9736],"type":"Point"}
}