{
  "type": "Feature",
  "properties": {
    "gn:adm1_name":"Fukuokaken",
    "gn:adm2_name":"Chikushigunnakagawamachi",
    "gn:name":"Katanawanishi",
    "iso:country":"JP",
    "wof:name":"811-1202",
    "wof:placetype":"postalcode"
},
  "geometry": {"coordinates":[130.4127,33.5185],"type":"Point"}
}