{
  "type": "Feature",
  "properties": {
    "gn:adm1_name":"Kanagawaken",
    "gn:adm2_name":"Sagamiharashi",
    "gn:name":"Hoshigaoka",
    "iso:country":"JP",
    "wof:name":"229-0038",
    "wof:placetype":"postalcode"
},
  "geometry": {"coordinates":[139.37049999999999,35.5609],"type":"Point"}
}