{
  "type": "Feature",
  "properties": {
    "gn:adm1_name":"Chibaken",
    "gn:adm2_name":"Awagunkyonanmachi",
    "gn:name":"Ichiibara",
    "iso:country":"JP",
    "wof:name":"299-1905",
    "wof:placetype":"postalcode"
},
  "geometry": {"coordinates":[139.88980000000001,35.1441],"type":"Point"}
}