{
  "type": "Feature",
  "properties": {
    "gn:adm1_name":"Tottoriken",
    "gn:adm2_name":"Yonagoshi",
    "gn:name":"Wadachou",
    "iso:country":"JP",
    "wof:name":"683-0102",
    "wof:placetype":"postalcode"
},
  "geometry": {"coordinates":[133.2679,35.4848],"type":"Point"}
}