{
  "type": "Feature",
  "properties": {
    "gn:adm1_name":"Naganoken",
    "gn:adm2_name":"Shimotakaigunnozawaonsenmura",
    "gn:name":"Ikanikeisaiganaibaai",
    "iso:country":"JP",
    "wof:name":"389-2500",
    "wof:placetype":"postalcode"
},
  "geometry": {"coordinates":[138.4263,36.9339],"type":"Point"}
}