{
  "type": "Feature",
  "properties": {
    "gn:adm1_name":"Toyamaken",
    "gn:adm2_name":"Takaokashi",
    "gn:name":"Fushikikofumotomachi",
    "iso:country":"JP",
    "wof:name":"933-0115",
    "wof:placetype":"postalcode"
},
  "geometry": {"coordinates":[137.04490000000001,36.7908],"type":"Point"}
}