{
  "type": "Feature",
  "properties": {
    "gn:adm1_name":"Tottoriken",
    "gn:adm2_name":"Kurayoshishi",
    "gn:name":"Higashiiwakuramachi",
    "iso:country":"JP",
    "wof:name":"682-0873",
    "wof:placetype":"postalcode"
},
  "geometry": {"coordinates":[133.8194,35.4326],"type":"Point"}
}