{
  "type": "Feature",
  "properties": {
    "gn:adm1_name":"Kagoshimaken",
    "gn:adm2_name":"Isagunhishikarichou",
    "gn:name":"Shimode",
    "iso:country":"JP",
    "wof:name":"895-2702",
    "wof:placetype":"postalcode"
},
  "geometry": {"coordinates":[130.61420000000001,32.0225],"type":"Point"}
}