{
  "type": "Feature",
  "properties": {
    "gn:adm1_name":"Toyamaken",
    "gn:adm2_name":"Takaokashi",
    "gn:name":"Kuniyoshi",
    "iso:country":"JP",
    "wof:name":"933-0968",
    "wof:placetype":"postalcode"
},
  "geometry": {"coordinates":[136.9659,36.7596],"type":"Point"}
}