{
  "type": "Feature",
  "properties": {
    "gn:adm1_name":"Oosakafu",
    "gn:adm2_name":"Neyagawashi",
    "gn:name":"Higashiootoshichou",
    "iso:country":"JP",
    "wof:name":"572-0042",
    "wof:placetype":"postalcode"
},
  "geometry": {"coordinates":[135.6182,34.7638],"type":"Point"}
}