{
  "type": "Feature",
  "properties": {
    "gn:adm1_name":"Naganoken",
    "gn:adm2_name":"Okayashi",
    "gn:name":"Tsukamachou",
    "iso:country":"JP",
    "wof:name":"394-0026",
    "wof:placetype":"postalcode"
},
  "geometry": {"coordinates":[138.0532,36.0631],"type":"Point"}
}