{
  "type": "Feature",
  "properties": {
    "gn:adm1_name":"Miyagiken",
    "gn:adm2_name":"Shiroishishi",
    "gn:name":"Oohata",
    "iso:country":"JP",
    "wof:name":"989-0208",
    "wof:placetype":"postalcode"
},
  "geometry": {"coordinates":[140.6285,38.0072],"type":"Point"}
}