{
  "type": "Feature",
  "properties": {
    "gn:adm1_name":"Kanagawaken",
    "gn:adm2_name":"Yokohamashinakaku",
    "gn:name":"Kotobukichou",
    "iso:country":"JP",
    "wof:name":"231-0026",
    "wof:placetype":"postalcode"
},
  "geometry": {"coordinates":[139.63939999999999,35.4395],"type":"Point"}
}