{
  "type": "Feature",
  "properties": {
    "gn:adm1_name":"Shigaken",
    "gn:adm2_name":"Koukagun'Ishibechou",
    "gn:name":"Ishibekita",
    "iso:country":"JP",
    "wof:name":"520-3113",
    "wof:placetype":"postalcode"
},
  "geometry": {"coordinates":[136.0538,35.0189],"type":"Point"}
}