{
  "type": "Feature",
  "properties": {
    "gn:adm1_name":"Naganoken",
    "gn:adm2_name":"Shiojirishi",
    "gn:name":"Nagaune",
    "iso:country":"JP",
    "wof:name":"399-0715",
    "wof:placetype":"postalcode"
},
  "geometry": {"coordinates":[137.97290000000001,36.1124],"type":"Point"}
}