{
  "type": "Feature",
  "properties": {
    "gn:adm1_name":"Hiroshimaken",
    "gn:adm2_name":"Futamigunsakugison",
    "gn:name":"Ooyama",
    "iso:country":"JP",
    "wof:name":"728-0132",
    "wof:placetype":"postalcode"
},
  "geometry": {"coordinates":[132.75219999999999,34.8244],"type":"Point"}
}