{
  "type": "Feature",
  "properties": {
    "gn:adm1_name":"Naraken",
    "gn:adm2_name":"Narashi",
    "gn:name":"Nishikitsujichou",
    "iso:country":"JP",
    "wof:name":"630-8325",
    "wof:placetype":"postalcode"
},
  "geometry": {"coordinates":[135.82409999999999,34.6743],"type":"Point"}
}