{
  "type": "Feature",
  "properties": {
    "gn:adm1_name":"Toyamaken",
    "gn:adm2_name":"Kurobeshi",
    "gn:name":"Nakashin",
    "iso:country":"JP",
    "wof:name":"938-0027",
    "wof:placetype":"postalcode"
},
  "geometry": {"coordinates":[137.43450000000001,36.885],"type":"Point"}
}