{
  "type": "Feature",
  "properties": {
    "gn:adm1_name":"Kagoshimaken",
    "gn:adm2_name":"Ooshimagunsetouchichou",
    "gn:name":"Saneku",
    "iso:country":"JP",
    "wof:name":"894-2403",
    "wof:placetype":"postalcode"
},
  "geometry": {"coordinates":[129.18450000000001,28.1862],"type":"Point"}
}