{
  "type": "Feature",
  "properties": {
    "gn:adm1_name":"Hiroshimaken",
    "gn:adm2_name":"Onomichishi",
    "gn:name":"Boujichou",
    "iso:country":"JP",
    "wof:name":"722-0041",
    "wof:placetype":"postalcode"
},
  "geometry": {"coordinates":[133.20529999999999,34.4193],"type":"Point"}
}