{
  "type": "Feature",
  "properties": {
    "gn:adm1_name":"Naganoken",
    "gn:adm2_name":"Shimoinaguntakamorimachi",
    "gn:name":"Izuhara",
    "iso:country":"JP",
    "wof:name":"399-3107",
    "wof:placetype":"postalcode"
},
  "geometry": {"coordinates":[137.87479999999999,35.5704],"type":"Point"}
}