{
  "type": "Feature",
  "properties": {
    "gn:adm1_name":"Miyazakiken",
    "gn:adm2_name":"Miyakonojoushi",
    "gn:name":"Sekinoochou",
    "iso:country":"JP",
    "wof:name":"885-0113",
    "wof:placetype":"postalcode"
},
  "geometry": {"coordinates":[131.00319999999999,31.7632],"type":"Point"}
}