{
  "type": "Feature",
  "properties": {
    "gn:adm1_name":"Kagoshimaken",
    "gn:adm2_name":"Kimotsukigunkushirachou",
    "gn:name":"Kamiobaru",
    "iso:country":"JP",
    "wof:name":"893-1605",
    "wof:placetype":"postalcode"
},
  "geometry": {"coordinates":[130.9205,31.3825],"type":"Point"}
}