{
  "type": "Feature",
  "properties": {
    "gn:adm1_name":"Wakayamaken",
    "gn:adm2_name":"Goboushi",
    "gn:name":"Gobou",
    "iso:country":"JP",
    "wof:name":"644-0001",
    "wof:placetype":"postalcode"
},
  "geometry": {"coordinates":[135.15729999999999,33.8886],"type":"Point"}
}