{
  "type": "Feature",
  "properties": {
    "gn:adm1_name":"Miyagiken",
    "gn:adm2_name":"Toodagunwakuyachou",
    "gn:name":"Yoshizumi",
    "iso:country":"JP",
    "wof:name":"987-0283",
    "wof:placetype":"postalcode"
},
  "geometry": {"coordinates":[141.19460000000001,38.5655],"type":"Point"}
}