{
  "type": "Feature",
  "properties": {
    "gn:adm1_name":"Aichiken",
    "gn:adm2_name":"Nagoyashinishiku",
    "gn:name":"Jousai",
    "iso:country":"JP",
    "wof:name":"451-0031",
    "wof:placetype":"postalcode"
},
  "geometry": {"coordinates":[136.89400000000001,35.1887],"type":"Point"}
}