{
  "type": "Feature",
  "properties": {
    "gn:adm1_name":"Shizuokaken",
    "gn:adm2_name":"Shizuokashi",
    "gn:name":"Shimizukitawaki",
    "iso:country":"JP",
    "wof:name":"424-0052",
    "wof:placetype":"postalcode"
},
  "geometry": {"coordinates":[138.4633,35.0191],"type":"Point"}
}