{
  "type": "Feature",
  "properties": {
    "gn:adm1_name":"Hiroshimaken",
    "gn:adm2_name":"Kureshi",
    "gn:name":"Kitashioyachou",
    "iso:country":"JP",
    "wof:name":"737-0836",
    "wof:placetype":"postalcode"
},
  "geometry": {"coordinates":[132.54390000000001,34.2547],"type":"Point"}
}