{
  "type": "Feature",
  "properties": {
    "gn:adm1_name":"Fukuiken",
    "gn:adm2_name":"Sakaigunkanaduchou",
    "gn:name":"Oomizo",
    "iso:country":"JP",
    "wof:name":"919-0628",
    "wof:placetype":"postalcode"
},
  "geometry": {"coordinates":[136.22319999999999,36.2117],"type":"Point"}
}