{
  "type": "Feature",
  "properties": {
    "gn:adm1_name":"Hyougoken",
    "gn:adm2_name":"Himejishi",
    "gn:name":"Arashiyamachou",
    "iso:country":"JP",
    "wof:name":"670-0029",
    "wof:placetype":"postalcode"
},
  "geometry": {"coordinates":[134.68369999999999,34.8413],"type":"Point"}
}