{
  "type": "Feature",
  "properties": {
    "gn:adm1_name":"Shimaneken",
    "gn:adm2_name":"Nimagunyunotsumachi",
    "gn:name":"Yunotsukamimura",
    "iso:country":"JP",
    "wof:name":"699-2513",
    "wof:placetype":"postalcode"
},
  "geometry": {"coordinates":[132.36369999999999,35.0723],"type":"Point"}
}