{
  "type": "Feature",
  "properties": {
    "gn:adm1_name":"Gunmaken",
    "gn:adm2_name":"Ootashi",
    "gn:name":"Yoshizawachou",
    "iso:country":"JP",
    "wof:name":"373-0019",
    "wof:placetype":"postalcode"
},
  "geometry": {"coordinates":[139.37039999999999,36.3493],"type":"Point"}
}