{
  "type": "Feature",
  "properties": {
    "gn:adm1_name":"Niigataken",
    "gn:adm2_name":"Kitauonumagunkawaguchimachi",
    "gn:name":"Ushigashima",
    "iso:country":"JP",
    "wof:name":"949-7505",
    "wof:placetype":"postalcode"
},
  "geometry": {"coordinates":[138.8443,37.2804],"type":"Point"}
}