{
  "type": "Feature",
  "properties": {
    "gn:adm1_name":"Shizuokaken",
    "gn:adm2_name":"Shizuokashi",
    "gn:name":"Naganuma",
    "iso:country":"JP",
    "wof:name":"420-0813",
    "wof:placetype":"postalcode"
},
  "geometry": {"coordinates":[138.41460000000001,34.9904],"type":"Point"}
}