{
  "type": "Feature",
  "properties": {
    "gn:adm1_name":"Fukushimaken",
    "gn:adm2_name":"Iwasegun'Iwasemura",
    "gn:name":"Yazawa",
    "iso:country":"JP",
    "wof:name":"962-0311",
    "wof:placetype":"postalcode"
},
  "geometry": {"coordinates":[140.29310000000001,37.3124],"type":"Point"}
}