{
  "type": "Feature",
  "properties": {
    "gn:adm1_name":"Ibarakiken",
    "gn:adm2_name":"Tsukubashi",
    "gn:name":"Ooho(Sonota)",
    "iso:country":"JP",
    "wof:name":"300-3256",
    "wof:placetype":"postalcode"
},
  "geometry": {"coordinates":[140.07409999999999,36.1512],"type":"Point"}
}