{
  "type": "Feature",
  "properties": {
    "gn:adm1_name":"Okayamaken",
    "gn:adm2_name":"Wakegunyoshinagachou",
    "gn:name":"Fukumitsu",
    "iso:country":"JP",
    "wof:name":"709-0222",
    "wof:placetype":"postalcode"
},
  "geometry": {"coordinates":[134.2226,34.8104],"type":"Point"}
}