{
  "type": "Feature",
  "properties": {
    "gn:adm1_name":"Kyoutofu",
    "gn:adm2_name":"Kyoutoshifushimiku",
    "gn:name":"Fukakusanakanogouyamachou",
    "iso:country":"JP",
    "wof:name":"612-0818",
    "wof:placetype":"postalcode"
},
  "geometry": {"coordinates":[135.78389999999999,34.9578],"type":"Point"}
}