{
  "type": "Feature",
  "properties": {
    "gn:adm1_name":"Naganoken",
    "gn:adm2_name":"Komoroshi",
    "gn:name":"Tei",
    "iso:country":"JP",
    "wof:name":"384-0804",
    "wof:placetype":"postalcode"
},
  "geometry": {"coordinates":[138.41800000000001,36.3262],"type":"Point"}
}