{
  "type": "Feature",
  "properties": {
    "gn:adm1_name":"Tottoriken",
    "gn:adm2_name":"Kurayoshishi",
    "gn:name":"Fukuba",
    "iso:country":"JP",
    "wof:name":"682-0013",
    "wof:placetype":"postalcode"
},
  "geometry": {"coordinates":[133.8535,35.4634],"type":"Point"}
}