{
  "type": "Feature",
  "properties": {
    "gn:adm1_name":"Toukyouto",
    "gn:adm2_name":"Shinjukuku",
    "gn:name":"Nishigokenchou",
    "iso:country":"JP",
    "wof:name":"162-0812",
    "wof:placetype":"postalcode"
},
  "geometry": {"coordinates":[139.73759999999999,35.707],"type":"Point"}
}