{
  "type": "Feature",
  "properties": {
    "gn:adm1_name":"Naraken",
    "gn:adm2_name":"Narashi",
    "gn:name":"Tsunofurichou",
    "iso:country":"JP",
    "wof:name":"630-8224",
    "wof:placetype":"postalcode"
},
  "geometry": {"coordinates":[135.8272,34.682],"type":"Point"}
}