{
  "type": "Feature",
  "properties": {
    "gn:adm1_name":"Hyougoken",
    "gn:adm2_name":"Yabugun'Ooyachou",
    "gn:name":"Kabo",
    "iso:country":"JP",
    "wof:name":"667-0315",
    "wof:placetype":"postalcode"
},
  "geometry": {"coordinates":[134.66669999999999,35.3365],"type":"Point"}
}