{
  "type": "Feature",
  "properties": {
    "gn:adm1_name":"Toyamaken",
    "gn:adm2_name":"Toyamashi",
    "gn:name":"Higashiiwasemura",
    "iso:country":"JP",
    "wof:name":"931-8359",
    "wof:placetype":"postalcode"
},
  "geometry": {"coordinates":[137.22999999999999,36.7576],"type":"Point"}
}