{
  "type": "Feature",
  "properties": {
    "gn:adm1_name":"Ishikawaken",
    "gn:adm2_name":"Kanazawashi",
    "gn:name":"Hirooka",
    "iso:country":"JP",
    "wof:name":"920-0031",
    "wof:placetype":"postalcode"
},
  "geometry": {"coordinates":[136.64490000000001,36.5792],"type":"Point"}
}