{
  "type": "Feature",
  "properties": {
    "gn:adm1_name":"Yamagataken",
    "gn:adm2_name":"Tsuruokashi",
    "gn:name":"Tanisada",
    "iso:country":"JP",
    "wof:name":"997-0366",
    "wof:placetype":"postalcode"
},
  "geometry": {"coordinates":[139.8295,38.6596],"type":"Point"}
}