{
  "type": "Feature",
  "properties": {
    "gn:adm1_name":"Hiroshimaken",
    "gn:adm2_name":"Futamigunkisachou",
    "gn:name":"Yanochi",
    "iso:country":"JP",
    "wof:name":"729-4208",
    "wof:placetype":"postalcode"
},
  "geometry": {"coordinates":[132.9846,34.7422],"type":"Point"}
}