{
  "type": "Feature",
  "properties": {
    "gn:adm1_name":"Tochigiken",
    "gn:adm2_name":"Kamitsugagun'Ashiomachi",
    "gn:name":"Akakura",
    "iso:country":"JP",
    "wof:name":"321-1502",
    "wof:placetype":"postalcode"
},
  "geometry": {"coordinates":[139.44560000000001,36.666],"type":"Point"}
}