{
  "type": "Feature",
  "properties": {
    "gn:adm1_name":"Okayamaken",
    "gn:adm2_name":"Okayamashi",
    "gn:name":"Tomiyoshi",
    "iso:country":"JP",
    "wof:name":"701-1133",
    "wof:placetype":"postalcode"
},
  "geometry": {"coordinates":[133.86449999999999,34.7359],"type":"Point"}
}