{
  "type": "Feature",
  "properties": {
    "gn:adm1_name":"Naraken",
    "gn:adm2_name":"Yamatotakadashi",
    "gn:name":"Isonokitachou",
    "iso:country":"JP",
    "wof:name":"635-0094",
    "wof:placetype":"postalcode"
},
  "geometry": {"coordinates":[135.7346,34.5095],"type":"Point"}
}