{
  "type": "Feature",
  "properties": {
    "gn:adm1_name":"Tottoriken",
    "gn:adm2_name":"Kurayoshishi",
    "gn:name":"Shimoyonadumi",
    "iso:country":"JP",
    "wof:name":"682-0601",
    "wof:placetype":"postalcode"
},
  "geometry": {"coordinates":[133.76660000000001,35.4237],"type":"Point"}
}