{
  "type": "Feature",
  "properties": {
    "gn:adm1_name":"Oosakafu",
    "gn:adm2_name":"Daitoushi",
    "gn:name":"Eiwachou",
    "iso:country":"JP",
    "wof:name":"574-0032",
    "wof:placetype":"postalcode"
},
  "geometry": {"coordinates":[135.6249,34.702],"type":"Point"}
}