{
  "type": "Feature",
  "properties": {
    "gn:adm1_name":"Aichiken",
    "gn:adm2_name":"Chitaguntaketoyochou",
    "gn:name":"Minamiokoshi",
    "iso:country":"JP",
    "wof:name":"470-2556",
    "wof:placetype":"postalcode"
},
  "geometry": {"coordinates":[136.90880000000001,34.8425],"type":"Point"}
}