{
  "type": "Feature",
  "properties": {
    "gn:adm1_name":"Hiroshimaken",
    "gn:adm2_name":"Kureshi",
    "gn:name":"Miyahara",
    "iso:country":"JP",
    "wof:name":"737-0024",
    "wof:placetype":"postalcode"
},
  "geometry": {"coordinates":[132.5609,34.2294],"type":"Point"}
}