{
  "type": "Feature",
  "properties": {
    "gn:adm1_name":"Kumamotoken",
    "gn:adm2_name":"Ashikitaguntanouramachi",
    "gn:name":"Yokoigi",
    "iso:country":"JP",
    "wof:name":"869-5301",
    "wof:placetype":"postalcode"
},
  "geometry": {"coordinates":[130.54409999999999,32.3615],"type":"Point"}
}