{
  "type": "Feature",
  "properties": {
    "gn:adm1_name":"Aichiken",
    "gn:adm2_name":"Amagunyatomichou",
    "gn:name":"Gonosankawahira",
    "iso:country":"JP",
    "wof:name":"498-0018",
    "wof:placetype":"postalcode"
},
  "geometry": {"coordinates":[136.70779999999999,35.1254],"type":"Point"}
}