{
  "type": "Feature",
  "properties": {
    "gn:adm1_name":"Chibaken",
    "gn:adm2_name":"Kisaradushi",
    "gn:name":"Yamamotonanamagari",
    "iso:country":"JP",
    "wof:name":"292-0203",
    "wof:placetype":"postalcode"
},
  "geometry": {"coordinates":[140.08410000000001,35.3457],"type":"Point"}
}