{
  "type": "Feature",
  "properties": {
    "gn:adm1_name":"Fukushimaken",
    "gn:adm2_name":"Dategunhobaramachi",
    "gn:name":"Muraoka",
    "iso:country":"JP",
    "wof:name":"960-0666",
    "wof:placetype":"postalcode"
},
  "geometry": {"coordinates":[140.5641,37.805],"type":"Point"}
}