{
  "type": "Feature",
  "properties": {
    "gn:adm1_name":"Kouchiken",
    "gn:adm2_name":"Tosagun'Ookawamura",
    "gn:name":"Ikanikeisaiganaibaai",
    "iso:country":"JP",
    "wof:name":"781-3700",
    "wof:placetype":"postalcode"
},
  "geometry": {"coordinates":[133.3784,33.8006],"type":"Point"}
}