{
  "type": "Feature",
  "properties": {
    "gn:adm1_name":"Oosakafu",
    "gn:adm2_name":"Neyagawashi",
    "gn:name":"Sanranishimachi",
    "iso:country":"JP",
    "wof:name":"572-0818",
    "wof:placetype":"postalcode"
},
  "geometry": {"coordinates":[135.62289999999999,34.7462],"type":"Point"}
}