{
  "type": "Feature",
  "properties": {
    "gn:adm1_name":"Nagasakiken",
    "gn:adm2_name":"Shimabarashi",
    "gn:name":"Sakigakemachi",
    "iso:country":"JP",
    "wof:name":"855-0035",
    "wof:placetype":"postalcode"
},
  "geometry": {"coordinates":[130.36699999999999,32.7932],"type":"Point"}
}