{
  "type": "Feature",
  "properties": {
    "gn:adm1_name":"Toyamaken",
    "gn:adm2_name":"Toyamashi",
    "gn:name":"Sugitani",
    "iso:country":"JP",
    "wof:name":"930-0152",
    "wof:placetype":"postalcode"
},
  "geometry": {"coordinates":[137.13919999999999,36.6831],"type":"Point"}
}