{
  "type": "Feature",
  "properties": {
    "gn:adm1_name":"Tokushimaken",
    "gn:adm2_name":"Nakagun'Aioichou",
    "gn:name":"Yananoue",
    "iso:country":"JP",
    "wof:name":"771-5402",
    "wof:placetype":"postalcode"
},
  "geometry": {"coordinates":[134.49019999999999,33.825],"type":"Point"}
}