{
  "type": "Feature",
  "properties": {
    "gn:adm1_name":"Hyougoken",
    "gn:adm2_name":"Himejishi",
    "gn:name":"Higashitsujii",
    "iso:country":"JP",
    "wof:name":"670-0084",
    "wof:placetype":"postalcode"
},
  "geometry": {"coordinates":[134.67760000000001,34.8469],"type":"Point"}
}