{
  "type": "Feature",
  "properties": {
    "gn:adm1_name":"Kyoutofu",
    "gn:adm2_name":"Kyoutoshiukyouku",
    "gn:name":"Sagakoshihatanakanochou",
    "iso:country":"JP",
    "wof:name":"616-8487",
    "wof:placetype":"postalcode"
},
  "geometry": {"coordinates":[135.61199999999999,35.0853],"type":"Point"}
}