{
  "type": "Feature",
  "properties": {
    "gn:adm1_name":"Miyagiken",
    "gn:adm2_name":"Sendaishiizumiku",
    "gn:name":"Akedoori",
    "iso:country":"JP",
    "wof:name":"981-3206",
    "wof:placetype":"postalcode"
},
  "geometry": {"coordinates":[140.85669999999999,38.3553],"type":"Point"}
}