{
  "type": "Feature",
  "properties": {
    "gn:adm1_name":"Kyoutofu",
    "gn:adm2_name":"Kyoutoshifushimiku",
    "gn:name":"Fukakusaookamedaniooyamachou",
    "iso:country":"JP",
    "wof:name":"612-0847",
    "wof:placetype":"postalcode"
},
  "geometry": {"coordinates":[135.7784,34.9467],"type":"Point"}
}