{
  "type": "Feature",
  "properties": {
    "gn:adm1_name":"Chibaken",
    "gn:adm2_name":"Futtsushi",
    "gn:name":"Kami",
    "iso:country":"JP",
    "wof:name":"293-0041",
    "wof:placetype":"postalcode"
},
  "geometry": {"coordinates":[139.89709999999999,35.285],"type":"Point"}
}