{
  "type": "Feature",
  "properties": {
    "gn:adm1_name":"Oosakafu",
    "gn:adm2_name":"Sennangunkumatorichou",
    "gn:name":"Gomonhigashi",
    "iso:country":"JP",
    "wof:name":"590-0414",
    "wof:placetype":"postalcode"
},
  "geometry": {"coordinates":[135.35339999999999,34.3958],"type":"Point"}
}