{
  "type": "Feature",
  "properties": {
    "gn:adm1_name":"Aichiken",
    "gn:adm2_name":"Setoshi",
    "gn:name":"Kitawakichou",
    "iso:country":"JP",
    "wof:name":"489-0918",
    "wof:placetype":"postalcode"
},
  "geometry": {"coordinates":[137.07249999999999,35.2239],"type":"Point"}
}