{
  "type": "Feature",
  "properties": {
    "gn:adm1_name":"Naraken",
    "gn:adm2_name":"Yoshinogunhigashiyoshinomura",
    "gn:name":"Sebato",
    "iso:country":"JP",
    "wof:name":"633-2441",
    "wof:placetype":"postalcode"
},
  "geometry": {"coordinates":[136.00040000000001,34.3759],"type":"Point"}
}