{
  "type": "Feature",
  "properties": {
    "gn:adm1_name":"Shimaneken",
    "gn:adm2_name":"Ooharagunkisukichou",
    "gn:name":"Kisuki",
    "iso:country":"JP",
    "wof:name":"699-1332",
    "wof:placetype":"postalcode"
},
  "geometry": {"coordinates":[132.90260000000001,35.2894],"type":"Point"}
}