{
  "type": "Feature",
  "properties": {
    "gn:adm1_name":"Tottoriken",
    "gn:adm2_name":"Kurayoshishi",
    "gn:name":"Ootanichaya",
    "iso:country":"JP",
    "wof:name":"682-0948",
    "wof:placetype":"postalcode"
},
  "geometry": {"coordinates":[133.80250000000001,35.4462],"type":"Point"}
}