{
  "type": "Feature",
  "properties": {
    "gn:adm1_name":"Niigataken",
    "gn:adm2_name":"Gosenshi",
    "gn:name":"Tsuchibori",
    "iso:country":"JP",
    "wof:name":"959-1643",
    "wof:placetype":"postalcode"
},
  "geometry": {"coordinates":[139.21940000000001,37.7314],"type":"Point"}
}