{
  "type": "Feature",
  "properties": {
    "gn:adm1_name":"Niigataken",
    "gn:adm2_name":"Nishikanbaragunyahikomura",
    "gn:name":"Ikanikeisaiganaibaai",
    "iso:country":"JP",
    "wof:name":"959-0300",
    "wof:placetype":"postalcode"
},
  "geometry": {"coordinates":[138.8417,37.6925],"type":"Point"}
}