{
  "type": "Feature",
  "properties": {
    "gn:adm1_name":"Aichiken",
    "gn:adm2_name":"Nagoyashimidoriku",
    "gn:name":"Hosoguchi",
    "iso:country":"JP",
    "wof:name":"458-0006",
    "wof:placetype":"postalcode"
},
  "geometry": {"coordinates":[136.98830000000001,35.0876],"type":"Point"}
}