{
  "type": "Feature",
  "properties": {
    "gn:adm1_name":"Tochigiken",
    "gn:adm2_name":"Kanumashi",
    "gn:name":"Matsubara",
    "iso:country":"JP",
    "wof:name":"322-0012",
    "wof:placetype":"postalcode"
},
  "geometry": {"coordinates":[139.8159,36.551],"type":"Point"}
}