{
  "type": "Feature",
  "properties": {
    "gn:adm1_name":"Kyoutofu",
    "gn:adm2_name":"Ujishi",
    "gn:name":"Myoujouchou",
    "iso:country":"JP",
    "wof:name":"611-0014",
    "wof:placetype":"postalcode"
},
  "geometry": {"coordinates":[135.8176,34.8952],"type":"Point"}
}