{
  "type": "Feature",
  "properties": {
    "gn:adm1_name":"Wakayamaken",
    "gn:adm2_name":"Nagagun'Iwadechou",
    "gn:name":"Nishino",
    "iso:country":"JP",
    "wof:name":"649-6235",
    "wof:placetype":"postalcode"
},
  "geometry": {"coordinates":[135.3091,34.2578],"type":"Point"}
}