{
  "type": "Feature",
  "properties": {
    "gn:adm1_name":"Yamagataken",
    "gn:adm2_name":"Nagaishi",
    "gn:name":"Motomachi",
    "iso:country":"JP",
    "wof:name":"993-0007",
    "wof:placetype":"postalcode"
},
  "geometry": {"coordinates":[140.03729999999999,38.1049],"type":"Point"}
}