{
  "type": "Feature",
  "properties": {
    "gn:adm1_name":"Ooitaken",
    "gn:adm2_name":"Naoirigun'Ogimachi",
    "gn:name":"Eraharu",
    "iso:country":"JP",
    "wof:name":"879-6113",
    "wof:placetype":"postalcode"
},
  "geometry": {"coordinates":[131.31139999999999,32.9237],"type":"Point"}
}