{
  "type": "Feature",
  "properties": {
    "gn:adm1_name":"Miyagiken",
    "gn:adm2_name":"Toodagunkogotachou",
    "gn:name":"Keshouzaka",
    "iso:country":"JP",
    "wof:name":"987-0034",
    "wof:placetype":"postalcode"
},
  "geometry": {"coordinates":[141.06780000000001,38.5349],"type":"Point"}
}