{
  "type": "Feature",
  "properties": {
    "gn:adm1_name":"Toukyouto",
    "gn:adm2_name":"Hinoshi",
    "gn:name":"Fujimachi",
    "iso:country":"JP",
    "wof:name":"191-0064",
    "wof:placetype":"postalcode"
},
  "geometry": {"coordinates":[139.37559999999999,35.6594],"type":"Point"}
}