{
  "type": "Feature",
  "properties": {
    "gn:adm1_name":"Saitamaken",
    "gn:adm2_name":"Kitamotoshi",
    "gn:name":"Miyauchi",
    "iso:country":"JP",
    "wof:name":"364-0002",
    "wof:placetype":"postalcode"
},
  "geometry": {"coordinates":[139.53829999999999,36.0394],"type":"Point"}
}