{
  "type": "Feature",
  "properties": {
    "gn:adm1_name":"Kanagawaken",
    "gn:adm2_name":"Kamakurashi",
    "gn:name":"Ougigayatsu",
    "iso:country":"JP",
    "wof:name":"248-0011",
    "wof:placetype":"postalcode"
},
  "geometry": {"coordinates":[139.5489,35.3256],"type":"Point"}
}