{
  "type": "Feature",
  "properties": {
    "gn:adm1_name":"Toyamaken",
    "gn:adm2_name":"Neigunfuchuumachi",
    "gn:name":"Usaka",
    "iso:country":"JP",
    "wof:name":"939-2711",
    "wof:placetype":"postalcode"
},
  "geometry": {"coordinates":[137.18780000000001,36.6742],"type":"Point"}
}