{
  "type": "Feature",
  "properties": {
    "gn:adm1_name":"Ishikawaken",
    "gn:adm2_name":"Kanazawashi",
    "gn:name":"Kasaichimachi",
    "iso:country":"JP",
    "wof:name":"920-0851",
    "wof:placetype":"postalcode"
},
  "geometry": {"coordinates":[136.655,36.578],"type":"Point"}
}