{
  "type": "Feature",
  "properties": {
    "gn:adm1_name":"Fukuiken",
    "gn:adm2_name":"Nanjougun'Imajouchou",
    "gn:name":"Yunoo",
    "iso:country":"JP",
    "wof:name":"919-0101",
    "wof:placetype":"postalcode"
},
  "geometry": {"coordinates":[136.19569999999999,35.7971],"type":"Point"}
}