{
  "type": "Feature",
  "properties": {
    "gn:adm1_name":"Fukuiken",
    "gn:adm2_name":"Obamashi",
    "gn:name":"Obamakifune",
    "iso:country":"JP",
    "wof:name":"917-0059",
    "wof:placetype":"postalcode"
},
  "geometry": {"coordinates":[135.73570000000001,35.4921],"type":"Point"}
}