{
  "type": "Feature",
  "properties": {
    "gn:adm1_name":"Niigataken",
    "gn:adm2_name":"Tookamachishi",
    "gn:name":"Yokkamachi",
    "iso:country":"JP",
    "wof:name":"948-0006",
    "wof:placetype":"postalcode"
},
  "geometry": {"coordinates":[138.7646,37.1495],"type":"Point"}
}