{
  "type": "Feature",
  "properties": {
    "gn:adm1_name":"Kyoutofu",
    "gn:adm2_name":"Kyoutoshiminamiku",
    "gn:name":"Kisshouin'Ishiharahigashinokuchi",
    "iso:country":"JP",
    "wof:name":"601-8361",
    "wof:placetype":"postalcode"
},
  "geometry": {"coordinates":[135.73179999999999,34.9636],"type":"Point"}
}