{
  "type": "Feature",
  "properties": {
    "gn:adm1_name":"Hiroshimaken",
    "gn:adm2_name":"Higashihiroshimashi",
    "gn:name":"Saijouchoudoyomaru",
    "iso:country":"JP",
    "wof:name":"739-0003",
    "wof:placetype":"postalcode"
},
  "geometry": {"coordinates":[132.7561,34.4276],"type":"Point"}
}