{
  "type": "Feature",
  "properties": {
    "gn:adm1_name":"Niigataken",
    "gn:adm2_name":"Niigatashi",
    "gn:name":"Warino",
    "iso:country":"JP",
    "wof:name":"950-0321",
    "wof:placetype":"postalcode"
},
  "geometry": {"coordinates":[139.09399999999999,37.8401],"type":"Point"}
}