{
  "type": "Feature",
  "properties": {
    "gn:adm1_name":"Fukuiken",
    "gn:adm2_name":"Tsurugashi",
    "gn:name":"Midorigaokachou",
    "iso:country":"JP",
    "wof:name":"914-0133",
    "wof:placetype":"postalcode"
},
  "geometry": {"coordinates":[136.05670000000001,35.6075],"type":"Point"}
}