{
  "type": "Feature",
  "properties": {
    "gn:adm1_name":"Hiroshimaken",
    "gn:adm2_name":"Akigunkaitachou",
    "gn:name":"Soda",
    "iso:country":"JP",
    "wof:name":"736-0003",
    "wof:placetype":"postalcode"
},
  "geometry": {"coordinates":[132.55029999999999,34.375],"type":"Point"}
}