{
  "type": "Feature",
  "properties": {
    "gn:adm1_name":"Okinawaken",
    "gn:adm2_name":"Shimajiriguntamagusukuson",
    "gn:name":"Kakinohana",
    "iso:country":"JP",
    "wof:name":"901-0601",
    "wof:placetype":"postalcode"
},
  "geometry": {"coordinates":[127.7925,26.1496],"type":"Point"}
}