{
  "type": "Feature",
  "properties": {
    "gn:adm1_name":"Aichiken",
    "gn:adm2_name":"Shinshiroshi",
    "gn:name":"Katsuobuchi",
    "iso:country":"JP",
    "wof:name":"441-1327",
    "wof:placetype":"postalcode"
},
  "geometry": {"coordinates":[137.5205,34.9225],"type":"Point"}
}