{
  "type": "Feature",
  "properties": {
    "gn:adm1_name":"Gunmaken",
    "gn:adm2_name":"Fujiokashi",
    "gn:name":"Kamikurisu",
    "iso:country":"JP",
    "wof:name":"375-0016",
    "wof:placetype":"postalcode"
},
  "geometry": {"coordinates":[139.0685,36.2634],"type":"Point"}
}