{
  "type": "Feature",
  "properties": {
    "gn:adm1_name":"Toukyouto",
    "gn:adm2_name":"Taitouku",
    "gn:name":"Yanaka",
    "iso:country":"JP",
    "wof:name":"110-0001",
    "wof:placetype":"postalcode"
},
  "geometry": {"coordinates":[139.76650000000001,35.7248],"type":"Point"}
}