{
  "type": "Feature",
  "properties": {
    "gn:adm1_name":"Niigataken",
    "gn:adm2_name":"Araishi",
    "gn:name":"Mitsumata",
    "iso:country":"JP",
    "wof:name":"944-0074",
    "wof:placetype":"postalcode"
},
  "geometry": {"coordinates":[138.20599999999999,37.0153],"type":"Point"}
}