{
  "type": "Feature",
  "properties": {
    "gn:adm1_name":"Fukuiken",
    "gn:adm2_name":"Yoshidagun'Eiheijichou",
    "gn:name":"Domeki",
    "iso:country":"JP",
    "wof:name":"910-1218",
    "wof:placetype":"postalcode"
},
  "geometry": {"coordinates":[136.3623,36.085],"type":"Point"}
}