{
  "type": "Feature",
  "properties": {
    "gn:adm1_name":"Gunmaken",
    "gn:adm2_name":"Tonegunminakamimachi",
    "gn:name":"Awazawa",
    "iso:country":"JP",
    "wof:name":"379-1723",
    "wof:placetype":"postalcode"
},
  "geometry": {"coordinates":[139.01339999999999,36.8086],"type":"Point"}
}