{
  "type": "Feature",
  "properties": {
    "gn:adm1_name":"Naraken",
    "gn:adm2_name":"Kashiharashi",
    "gn:name":"Kinomotochou",
    "iso:country":"JP",
    "wof:name":"634-0025",
    "wof:placetype":"postalcode"
},
  "geometry": {"coordinates":[135.81399999999999,34.4975],"type":"Point"}
}