{
  "type": "Feature",
  "properties": {
    "gn:adm1_name":"Kumamotoken",
    "gn:adm2_name":"Minamatashi",
    "gn:name":"Kotsunagi",
    "iso:country":"JP",
    "wof:name":"867-0001",
    "wof:placetype":"postalcode"
},
  "geometry": {"coordinates":[130.4418,32.215],"type":"Point"}
}