{
  "type": "Feature",
  "properties": {
    "gn:adm1_name":"Aichiken",
    "gn:adm2_name":"Inazawashi",
    "gn:name":"Oridudoyamachou",
    "iso:country":"JP",
    "wof:name":"492-8077",
    "wof:placetype":"postalcode"
},
  "geometry": {"coordinates":[136.83199999999999,35.2537],"type":"Point"}
}