{
  "type": "Feature",
  "properties": {
    "gn:adm1_name":"Fukuokaken",
    "gn:adm2_name":"Yukuhashishi",
    "gn:name":"Kanaya",
    "iso:country":"JP",
    "wof:name":"824-0004",
    "wof:placetype":"postalcode"
},
  "geometry": {"coordinates":[130.9922,33.7295],"type":"Point"}
}