{
  "type": "Feature",
  "properties": {
    "gn:adm1_name":"Kyoutofu",
    "gn:adm2_name":"Kyoutoshihigashiyamaku",
    "gn:name":"Kamibentenchou",
    "iso:country":"JP",
    "wof:name":"605-0822",
    "wof:placetype":"postalcode"
},
  "geometry": {"coordinates":[135.7783,35.0007],"type":"Point"}
}