{
  "type": "Feature",
  "properties": {
    "gn:adm1_name":"Fukuiken",
    "gn:adm2_name":"Oonoshi",
    "gn:name":"Akanechou",
    "iso:country":"JP",
    "wof:name":"912-0068",
    "wof:placetype":"postalcode"
},
  "geometry": {"coordinates":[136.4864,35.9714],"type":"Point"}
}