{
  "type": "Feature",
  "properties": {
    "gn:adm1_name":"Nagasakiken",
    "gn:adm2_name":"Shimabarashi",
    "gn:name":"Minatomichi",
    "iso:country":"JP",
    "wof:name":"855-0831",
    "wof:placetype":"postalcode"
},
  "geometry": {"coordinates":[130.37090000000001,32.7801],"type":"Point"}
}