{
  "type": "Feature",
  "properties": {
    "gn:adm1_name":"Hiroshimaken",
    "gn:adm2_name":"Fukuyamashi",
    "gn:name":"Hikinochouhigashi",
    "iso:country":"JP",
    "wof:name":"721-0944",
    "wof:placetype":"postalcode"
},
  "geometry": {"coordinates":[133.4272,34.4962],"type":"Point"}
}