{
  "type": "Feature",
  "properties": {
    "gn:adm1_name":"Gifuken",
    "gn:adm2_name":"Mugigunhoradomura",
    "gn:name":"Tsuugenji",
    "iso:country":"JP",
    "wof:name":"501-2802",
    "wof:placetype":"postalcode"
},
  "geometry": {"coordinates":[136.81729999999999,35.6078],"type":"Point"}
}