{
  "type": "Feature",
  "properties": {
    "gn:adm1_name":"Hyougoken",
    "gn:adm2_name":"Sasayamashi",
    "gn:name":"Ooyamakami",
    "iso:country":"JP",
    "wof:name":"669-2803",
    "wof:placetype":"postalcode"
},
  "geometry": {"coordinates":[135.13380000000001,35.0963],"type":"Point"}
}