{
  "type": "Feature",
  "properties": {
    "gn:adm1_name":"Ishikawaken",
    "gn:adm2_name":"Kanazawashi",
    "gn:name":"Teraji",
    "iso:country":"JP",
    "wof:name":"921-8178",
    "wof:placetype":"postalcode"
},
  "geometry": {"coordinates":[136.63990000000001,36.5363],"type":"Point"}
}