{
  "type": "Feature",
  "properties": {
    "gn:adm1_name":"Hyougoken",
    "gn:adm2_name":"Koubeshisumaku",
    "gn:name":"Yukihirachou",
    "iso:country":"JP",
    "wof:name":"654-0037",
    "wof:placetype":"postalcode"
},
  "geometry": {"coordinates":[135.1336,34.6497],"type":"Point"}
}