{
  "type": "Feature",
  "properties": {
    "gn:adm1_name":"Toukyouto",
    "gn:adm2_name":"Itabashiku",
    "gn:name":"Shimura",
    "iso:country":"JP",
    "wof:name":"174-0056",
    "wof:placetype":"postalcode"
},
  "geometry": {"coordinates":[139.691,35.7761],"type":"Point"}
}