{
  "type": "Feature",
  "properties": {
    "gn:adm1_name":"Naraken",
    "gn:adm2_name":"Ikomashi",
    "gn:name":"Motomachi",
    "iso:country":"JP",
    "wof:name":"630-0257",
    "wof:placetype":"postalcode"
},
  "geometry": {"coordinates":[135.69589999999999,34.692],"type":"Point"}
}