{
  "type": "Feature",
  "properties": {
    "gn:adm1_name":"Shigaken",
    "gn:adm2_name":"Takashimagun'Adogawachou",
    "gn:name":"Shimoogawa",
    "iso:country":"JP",
    "wof:name":"520-1223",
    "wof:placetype":"postalcode"
},
  "geometry": {"coordinates":[136.0343,35.3136],"type":"Point"}
}