{
  "type": "Feature",
  "properties": {
    "gn:adm1_name":"Gifuken",
    "gn:adm2_name":"Gujougunshirotorichou",
    "gn:name":"Nozoe",
    "iso:country":"JP",
    "wof:name":"501-5113",
    "wof:placetype":"postalcode"
},
  "geometry": {"coordinates":[136.9008,35.893],"type":"Point"}
}