{
  "type": "Feature",
  "properties": {
    "gn:adm1_name":"Shimaneken",
    "gn:adm2_name":"Oochigunkawamotomachi",
    "gn:name":"Mimata",
    "iso:country":"JP",
    "wof:name":"696-1223",
    "wof:placetype":"postalcode"
},
  "geometry": {"coordinates":[132.46369999999999,35.0122],"type":"Point"}
}