{
  "type": "Feature",
  "properties": {
    "gn:adm1_name":"Yamaguchiken",
    "gn:adm2_name":"Shuunanshi",
    "gn:name":"Adouji",
    "iso:country":"JP",
    "wof:name":"745-0124",
    "wof:placetype":"postalcode"
},
  "geometry": {"coordinates":[131.84,34.1125],"type":"Point"}
}