{
  "type": "Feature",
  "properties": {
    "gn:adm1_name":"Mieken",
    "gn:adm2_name":"Tobashi",
    "gn:name":"Arashimachou",
    "iso:country":"JP",
    "wof:name":"517-0021",
    "wof:placetype":"postalcode"
},
  "geometry": {"coordinates":[136.86150000000001,34.4672],"type":"Point"}
}