{
  "type": "Feature",
  "properties": {
    "gn:adm1_name":"Yamagataken",
    "gn:adm2_name":"Mogamigunmamurogawamachi",
    "gn:name":"Ikanikeisaiganaibaai",
    "iso:country":"JP",
    "wof:name":"999-5300",
    "wof:placetype":"postalcode"
},
  "geometry": {"coordinates":[140.2482,38.9441],"type":"Point"}
}