{
  "type": "Feature",
  "properties": {
    "gn:adm1_name":"Ishikawaken",
    "gn:adm2_name":"Kanazawashi",
    "gn:name":"Enkoujihonmachi",
    "iso:country":"JP",
    "wof:name":"921-8176",
    "wof:placetype":"postalcode"
},
  "geometry": {"coordinates":[136.6429,36.5334],"type":"Point"}
}