{
  "type": "Feature",
  "properties": {
    "gn:adm1_name":"Yamagataken",
    "gn:adm2_name":"Higashiokitamaguntakahatamachi",
    "gn:name":"Kanabara",
    "iso:country":"JP",
    "wof:name":"992-0311",
    "wof:placetype":"postalcode"
},
  "geometry": {"coordinates":[140.23330000000001,37.997],"type":"Point"}
}