{
  "type": "Feature",
  "properties": {
    "gn:adm1_name":"Hyougoken",
    "gn:adm2_name":"Ashiyashi",
    "gn:name":"Kurekawachou",
    "iso:country":"JP",
    "wof:name":"659-0051",
    "wof:placetype":"postalcode"
},
  "geometry": {"coordinates":[135.31200000000001,34.7261],"type":"Point"}
}