{
  "type": "Feature",
  "properties": {
    "gn:adm1_name":"Yamaguchiken",
    "gn:adm2_name":"Shuunanshi",
    "gn:name":"Komatsubara",
    "iso:country":"JP",
    "wof:name":"745-0641",
    "wof:placetype":"postalcode"
},
  "geometry": {"coordinates":[131.99590000000001,34.0398],"type":"Point"}
}