{
  "type": "Feature",
  "properties": {
    "gn:adm1_name":"Fukuokaken",
    "gn:adm2_name":"Mizumagunjoujimamachi",
    "gn:name":"Egami",
    "iso:country":"JP",
    "wof:name":"830-0213",
    "wof:placetype":"postalcode"
},
  "geometry": {"coordinates":[130.42920000000001,33.2333],"type":"Point"}
}