{
  "type": "Feature",
  "properties": {
    "gn:adm1_name":"Shigaken",
    "gn:adm2_name":"Ootsushi",
    "gn:name":"Ooginosato",
    "iso:country":"JP",
    "wof:name":"520-0246",
    "wof:placetype":"postalcode"
},
  "geometry": {"coordinates":[135.89060000000001,35.1066],"type":"Point"}
}