{
  "type": "Feature",
  "properties": {
    "gn:adm1_name":"Kagoshimaken",
    "gn:adm2_name":"Ooshimagun'Isenchou",
    "gn:name":"Inutabu",
    "iso:country":"JP",
    "wof:name":"891-8327",
    "wof:placetype":"postalcode"
},
  "geometry": {"coordinates":[128.90309999999999,27.7143],"type":"Point"}
}