{
  "type": "Feature",
  "properties": {
    "gn:adm1_name":"Aichiken",
    "gn:adm2_name":"Kariyashi",
    "gn:name":"Nakajimachou",
    "iso:country":"JP",
    "wof:name":"448-0815",
    "wof:placetype":"postalcode"
},
  "geometry": {"coordinates":[137.00229999999999,34.9784],"type":"Point"}
}