{
  "type": "Feature",
  "properties": {
    "gn:adm1_name":"Fukuokaken",
    "gn:adm2_name":"Miikeguntakatamachi",
    "gn:name":"Maiduru",
    "iso:country":"JP",
    "wof:name":"835-0131",
    "wof:placetype":"postalcode"
},
  "geometry": {"coordinates":[130.51949999999999,33.1152],"type":"Point"}
}