{
  "type": "Feature",
  "properties": {
    "gn:adm1_name":"Gunmaken",
    "gn:adm2_name":"Tatebayashishi",
    "gn:name":"Misonochou",
    "iso:country":"JP",
    "wof:name":"374-0039",
    "wof:placetype":"postalcode"
},
  "geometry": {"coordinates":[139.5333,36.2337],"type":"Point"}
}