{
  "type": "Feature",
  "properties": {
    "gn:adm1_name":"Ibarakiken",
    "gn:adm2_name":"Tsukubashi",
    "gn:name":"Kamiooshima",
    "iso:country":"JP",
    "wof:name":"300-4351",
    "wof:placetype":"postalcode"
},
  "geometry": {"coordinates":[140.0634,36.2239],"type":"Point"}
}