{
  "type": "Feature",
  "properties": {
    "gn:adm1_name":"Miyazakiken",
    "gn:adm2_name":"Nishimorokatagunnojirichou",
    "gn:name":"Ikanikeisaiganaibaai",
    "iso:country":"JP",
    "wof:name":"886-0200",
    "wof:placetype":"postalcode"
},
  "geometry": {"coordinates":[131.10249999999999,31.9657],"type":"Point"}
}