{
  "type": "Feature",
  "properties": {
    "gn:adm1_name":"Naganoken",
    "gn:adm2_name":"Shimominochiguntoyotamura",
    "gn:name":"Anada",
    "iso:country":"JP",
    "wof:name":"389-2103",
    "wof:placetype":"postalcode"
},
  "geometry": {"coordinates":[138.3142,36.7862],"type":"Point"}
}