{
  "type": "Feature",
  "properties": {
    "gn:adm1_name":"Fukuokaken",
    "gn:adm2_name":"Ongagun'Ongachou",
    "gn:name":"Oira",
    "iso:country":"JP",
    "wof:name":"811-4311",
    "wof:placetype":"postalcode"
},
  "geometry": {"coordinates":[130.68600000000001,33.8345],"type":"Point"}
}