{
  "type": "Feature",
  "properties": {
    "gn:adm1_name":"Niigataken",
    "gn:adm2_name":"Nakakanbaragunkamedamachi",
    "gn:name":"Izumichou",
    "iso:country":"JP",
    "wof:name":"950-0155",
    "wof:placetype":"postalcode"
},
  "geometry": {"coordinates":[139.0959,37.8655],"type":"Point"}
}