{
  "type": "Feature",
  "properties": {
    "gn:adm1_name":"Niigataken",
    "gn:adm2_name":"Ryoutsushi",
    "gn:name":"Masaragawa",
    "iso:country":"JP",
    "wof:name":"952-3201",
    "wof:placetype":"postalcode"
},
  "geometry": {"coordinates":[138.4451,38.289],"type":"Point"}
}