{
  "type": "Feature",
  "properties": {
    "gn:adm1_name":"Chibaken",
    "gn:adm2_name":"Kamagayashi",
    "gn:name":"Kitahatsutomi",
    "iso:country":"JP",
    "wof:name":"273-0126",
    "wof:placetype":"postalcode"
},
  "geometry": {"coordinates":[139.9905,35.7782],"type":"Point"}
}