{
  "type": "Feature",
  "properties": {
    "gn:adm1_name":"Niigataken",
    "gn:adm2_name":"Mitsukeshi",
    "gn:name":"Horimizomachi",
    "iso:country":"JP",
    "wof:name":"954-0014",
    "wof:placetype":"postalcode"
},
  "geometry": {"coordinates":[138.96369999999999,37.5277],"type":"Point"}
}