{
  "type": "Feature",
  "properties": {
    "gn:adm1_name":"Mieken",
    "gn:adm2_name":"Iseshi",
    "gn:name":"Iwabuchi",
    "iso:country":"JP",
    "wof:name":"516-0037",
    "wof:placetype":"postalcode"
},
  "geometry": {"coordinates":[136.71289999999999,34.4877],"type":"Point"}
}