{
  "type": "Feature",
  "properties": {
    "gn:adm1_name":"Aichiken",
    "gn:adm2_name":"Kounanshi",
    "gn:name":"Miyatachouizumi",
    "iso:country":"JP",
    "wof:name":"483-8375",
    "wof:placetype":"postalcode"
},
  "geometry": {"coordinates":[136.84209999999999,35.3551],"type":"Point"}
}