{
  "type": "Feature",
  "properties": {
    "gn:adm1_name":"Shizuokaken",
    "gn:adm2_name":"Kakegawashi",
    "gn:name":"Aoichou",
    "iso:country":"JP",
    "wof:name":"436-0018",
    "wof:placetype":"postalcode"
},
  "geometry": {"coordinates":[138.02789999999999,34.7711],"type":"Point"}
}