{
  "type": "Feature",
  "properties": {
    "gn:adm1_name":"Toukyouto",
    "gn:adm2_name":"Machidashi",
    "gn:name":"Yakushidai",
    "iso:country":"JP",
    "wof:name":"195-0073",
    "wof:placetype":"postalcode"
},
  "geometry": {"coordinates":[139.4537,35.5796],"type":"Point"}
}