{
  "type": "Feature",
  "properties": {
    "gn:adm1_name":"Ibarakiken",
    "gn:adm2_name":"Hitachishi",
    "gn:name":"Oomikachou",
    "iso:country":"JP",
    "wof:name":"319-1221",
    "wof:placetype":"postalcode"
},
  "geometry": {"coordinates":[140.62289999999999,36.512],"type":"Point"}
}