{
  "type": "Feature",
  "properties": {
    "gn:adm1_name":"Fukuokaken",
    "gn:adm2_name":"Maebarushi",
    "gn:name":"Nishinodou",
    "iso:country":"JP",
    "wof:name":"819-1575",
    "wof:placetype":"postalcode"
},
  "geometry": {"coordinates":[130.2568,33.5277],"type":"Point"}
}