{
  "type": "Feature",
  "properties": {
    "gn:adm1_name":"Oosakafu",
    "gn:adm2_name":"Oosakashisumiyoshiku",
    "gn:name":"Asaka",
    "iso:country":"JP",
    "wof:name":"558-0021",
    "wof:placetype":"postalcode"
},
  "geometry": {"coordinates":[135.50960000000001,34.5912],"type":"Point"}
}