{
  "type": "Feature",
  "properties": {
    "gn:adm1_name":"Fukushimaken",
    "gn:adm2_name":"Futabagun'Ookumamachi",
    "gn:name":"Kuma",
    "iso:country":"JP",
    "wof:name":"979-1305",
    "wof:placetype":"postalcode"
},
  "geometry": {"coordinates":[140.9933,37.3937],"type":"Point"}
}