{
  "type": "Feature",
  "properties": {
    "gn:adm1_name":"Tochigiken",
    "gn:adm2_name":"Kuroisoshi",
    "gn:name":"Miharachou",
    "iso:country":"JP",
    "wof:name":"325-0037",
    "wof:placetype":"postalcode"
},
  "geometry": {"coordinates":[140.0352,36.9819],"type":"Point"}
}