{
  "type": "Feature",
  "properties": {
    "gn:adm1_name":"Toyamaken",
    "gn:adm2_name":"Nakaniikawagunkamiichimachi",
    "gn:name":"Kaminakamachi",
    "iso:country":"JP",
    "wof:name":"930-0333",
    "wof:placetype":"postalcode"
},
  "geometry": {"coordinates":[137.36519999999999,36.7057],"type":"Point"}
}