{
  "type": "Feature",
  "properties": {
    "gn:adm1_name":"Ehimeken",
    "gn:adm2_name":"Niihamashi",
    "gn:name":"Kotobukichou",
    "iso:country":"JP",
    "wof:name":"792-0822",
    "wof:placetype":"postalcode"
},
  "geometry": {"coordinates":[133.30170000000001,33.9418],"type":"Point"}
}