{
  "type": "Feature",
  "properties": {
    "gn:adm1_name":"Kagoshimaken",
    "gn:adm2_name":"Kanoyashi",
    "gn:name":"Hanaokachou",
    "iso:country":"JP",
    "wof:name":"891-2304",
    "wof:placetype":"postalcode"
},
  "geometry": {"coordinates":[130.7757,31.4112],"type":"Point"}
}