{
  "type": "Feature",
  "properties": {
    "gn:adm1_name":"Kanagawaken",
    "gn:adm2_name":"Yokohamashinakaku",
    "gn:name":"Yoshidamachi",
    "iso:country":"JP",
    "wof:name":"231-0041",
    "wof:placetype":"postalcode"
},
  "geometry": {"coordinates":[139.6326,35.4463],"type":"Point"}
}