{
  "type": "Feature",
  "properties": {
    "gn:adm1_name":"Okinawaken",
    "gn:adm2_name":"Kunigamigun'Oogimison",
    "gn:name":"Nuuha",
    "iso:country":"JP",
    "wof:name":"905-1304",
    "wof:placetype":"postalcode"
},
  "geometry": {"coordinates":[128.13130000000001,26.6986],"type":"Point"}
}