{
  "type": "Feature",
  "properties": {
    "gn:adm1_name":"Gifuken",
    "gn:adm2_name":"Gifushi",
    "gn:name":"Shimadahigashimachi",
    "iso:country":"JP",
    "wof:name":"500-8315",
    "wof:placetype":"postalcode"
},
  "geometry": {"coordinates":[136.74170000000001,35.4169],"type":"Point"}
}