{
  "type": "Feature",
  "properties": {
    "gn:adm1_name":"Saitamaken",
    "gn:adm2_name":"Kawaguchishi",
    "gn:name":"Kitaharadai",
    "iso:country":"JP",
    "wof:name":"333-0815",
    "wof:placetype":"postalcode"
},
  "geometry": {"coordinates":[139.73599999999999,35.8682],"type":"Point"}
}