{
  "type": "Feature",
  "properties": {
    "gn:adm1_name":"Mieken",
    "gn:adm2_name":"Nabarishi",
    "gn:name":"Kikyougaoka5banchou",
    "iso:country":"JP",
    "wof:name":"518-0625",
    "wof:placetype":"postalcode"
},
  "geometry": {"coordinates":[136.12620000000001,34.6407],"type":"Point"}
}