{
  "type": "Feature",
  "properties": {
    "gn:adm1_name":"Gifuken",
    "gn:adm2_name":"Gifushi",
    "gn:name":"Akitsumachi",
    "iso:country":"JP",
    "wof:name":"500-8067",
    "wof:placetype":"postalcode"
},
  "geometry": {"coordinates":[136.76249999999999,35.4238],"type":"Point"}
}