{
  "type": "Feature",
  "properties": {
    "gn:adm1_name":"Oosakafu",
    "gn:adm2_name":"Toyonakashi",
    "gn:name":"Shounaitakaramachi",
    "iso:country":"JP",
    "wof:name":"561-0836",
    "wof:placetype":"postalcode"
},
  "geometry": {"coordinates":[135.4624,34.7453],"type":"Point"}
}