{
  "type": "Feature",
  "properties": {
    "gn:adm1_name":"Aichiken",
    "gn:adm2_name":"Toyohashishi",
    "gn:name":"Nogurochou",
    "iso:country":"JP",
    "wof:name":"441-8022",
    "wof:placetype":"postalcode"
},
  "geometry": {"coordinates":[137.38220000000001,34.7589],"type":"Point"}
}