{
  "type": "Feature",
  "properties": {
    "gn:adm1_name":"Wakayamaken",
    "gn:adm2_name":"Hidakagunnakatsumura",
    "gn:name":"Harabiura",
    "iso:country":"JP",
    "wof:name":"644-1133",
    "wof:placetype":"postalcode"
},
  "geometry": {"coordinates":[135.34129999999999,33.9797],"type":"Point"}
}