{
  "type": "Feature",
  "properties": {
    "gn:adm1_name":"Wakayamaken",
    "gn:adm2_name":"Nagagun'Iwadechou",
    "gn:name":"Nishianjou",
    "iso:country":"JP",
    "wof:name":"649-6255",
    "wof:placetype":"postalcode"
},
  "geometry": {"coordinates":[135.29750000000001,34.2808],"type":"Point"}
}