{
  "type": "Feature",
  "properties": {
    "gn:adm1_name":"Aichiken",
    "gn:adm2_name":"Minamishitaragunhouraichou",
    "gn:name":"Shimoyoshida",
    "iso:country":"JP",
    "wof:name":"441-1621",
    "wof:placetype":"postalcode"
},
  "geometry": {"coordinates":[137.61500000000001,34.9114],"type":"Point"}
}