{
  "type": "Feature",
  "properties": {
    "gn:adm1_name":"Hyougoken",
    "gn:adm2_name":"Hikamigunkasugachou",
    "gn:name":"Ikeo",
    "iso:country":"JP",
    "wof:name":"669-4121",
    "wof:placetype":"postalcode"
},
  "geometry": {"coordinates":[135.12629999999999,35.1908],"type":"Point"}
}