{
  "type": "Feature",
  "properties": {
    "gn:adm1_name":"Gifuken",
    "gn:adm2_name":"Yoshikigunkamiokachou",
    "gn:name":"Yoshida",
    "iso:country":"JP",
    "wof:name":"506-1144",
    "wof:placetype":"postalcode"
},
  "geometry": {"coordinates":[137.2895,36.3068],"type":"Point"}
}