{
  "type": "Feature",
  "properties": {
    "gn:adm1_name":"Kagoshimaken",
    "gn:adm2_name":"Airagun'Airachou",
    "gn:name":"Kitayama",
    "iso:country":"JP",
    "wof:name":"899-5541",
    "wof:placetype":"postalcode"
},
  "geometry": {"coordinates":[130.60140000000001,31.8336],"type":"Point"}
}