{
  "type": "Feature",
  "properties": {
    "gn:adm1_name":"Ishikawaken",
    "gn:adm2_name":"Kanazawashi",
    "gn:name":"Tsudumidoumachi",
    "iso:country":"JP",
    "wof:name":"920-0161",
    "wof:placetype":"postalcode"
},
  "geometry": {"coordinates":[136.7456,36.6217],"type":"Point"}
}