{
  "type": "Feature",
  "properties": {
    "gn:adm1_name":"Miyagiken",
    "gn:adm2_name":"Kesennumashi",
    "gn:name":"Uoichibamae",
    "iso:country":"JP",
    "wof:name":"988-0037",
    "wof:placetype":"postalcode"
},
  "geometry": {"coordinates":[141.58000000000001,38.8989],"type":"Point"}
}