{
  "type": "Feature",
  "properties": {
    "gn:adm1_name":"Tochigiken",
    "gn:adm2_name":"Nasugunkurobanemachi",
    "gn:name":"Kawakami",
    "iso:country":"JP",
    "wof:name":"324-0214",
    "wof:placetype":"postalcode"
},
  "geometry": {"coordinates":[140.2148,36.879],"type":"Point"}
}