{
  "type": "Feature",
  "properties": {
    "gn:adm1_name":"Saitamaken",
    "gn:adm2_name":"Fukayashi",
    "gn:name":"Uchigashima",
    "iso:country":"JP",
    "wof:name":"366-0831",
    "wof:placetype":"postalcode"
},
  "geometry": {"coordinates":[139.27260000000001,36.2183],"type":"Point"}
}