{
  "type": "Feature",
  "properties": {
    "gn:adm1_name":"Tottoriken",
    "gn:adm2_name":"Yonagoshi",
    "gn:name":"Fukuman",
    "iso:country":"JP",
    "wof:name":"689-3523",
    "wof:placetype":"postalcode"
},
  "geometry": {"coordinates":[133.41030000000001,35.401],"type":"Point"}
}