{
  "type": "Feature",
  "properties": {
    "gn:adm1_name":"Hiroshimaken",
    "gn:adm2_name":"Fukuyamashi",
    "gn:name":"Minomichou",
    "iso:country":"JP",
    "wof:name":"720-0832",
    "wof:placetype":"postalcode"
},
  "geometry": {"coordinates":[133.37780000000001,34.4488],"type":"Point"}
}