{
  "type": "Feature",
  "properties": {
    "gn:adm1_name":"Aichiken",
    "gn:adm2_name":"Tsushimashi",
    "gn:name":"Miyagawachou",
    "iso:country":"JP",
    "wof:name":"496-0853",
    "wof:placetype":"postalcode"
},
  "geometry": {"coordinates":[136.7183,35.1696],"type":"Point"}
}