{
  "type": "Feature",
  "properties": {
    "gn:adm1_name":"Yamaguchiken",
    "gn:adm2_name":"Asagunsanyouchou",
    "gn:name":"Tsubuta",
    "iso:country":"JP",
    "wof:name":"757-0011",
    "wof:placetype":"postalcode"
},
  "geometry": {"coordinates":[131.11490000000001,34.0211],"type":"Point"}
}