{
  "type": "Feature",
  "properties": {
    "gn:adm1_name":"Hyougoken",
    "gn:adm2_name":"Himejishi",
    "gn:name":"Shosha",
    "iso:country":"JP",
    "wof:name":"671-2201",
    "wof:placetype":"postalcode"
},
  "geometry": {"coordinates":[134.6574,34.872],"type":"Point"}
}