{
  "type": "Feature",
  "properties": {
    "gn:adm1_name":"Ishikawaken",
    "gn:adm2_name":"Fugeshigun'Anamizumachi",
    "gn:name":"Zuihou",
    "iso:country":"JP",
    "wof:name":"927-0013",
    "wof:placetype":"postalcode"
},
  "geometry": {"coordinates":[136.952,37.2454],"type":"Point"}
}