{
  "type": "Feature",
  "properties": {
    "gn:adm1_name":"Niigataken",
    "gn:adm2_name":"Minamiuonumagunyamatomachi",
    "gn:name":"Arakane",
    "iso:country":"JP",
    "wof:name":"949-7235",
    "wof:placetype":"postalcode"
},
  "geometry": {"coordinates":[138.96969999999999,37.1535],"type":"Point"}
}