{
  "type": "Feature",
  "properties": {
    "gn:adm1_name":"Tottoriken",
    "gn:adm2_name":"Tottorishi",
    "gn:name":"Koyamachouminami",
    "iso:country":"JP",
    "wof:name":"680-0945",
    "wof:placetype":"postalcode"
},
  "geometry": {"coordinates":[134.17779999999999,35.5133],"type":"Point"}
}