{
  "type": "Feature",
  "properties": {
    "gn:adm1_name":"Shizuokaken",
    "gn:adm2_name":"Fujishi",
    "gn:name":"Mitojimamotochou",
    "iso:country":"JP",
    "wof:name":"416-0922",
    "wof:placetype":"postalcode"
},
  "geometry": {"coordinates":[138.6491,35.1503],"type":"Point"}
}