{
  "type": "Feature",
  "properties": {
    "gn:adm1_name":"Tottoriken",
    "gn:adm2_name":"Yazugunkoogechou",
    "gn:name":"Nishimikado",
    "iso:country":"JP",
    "wof:name":"680-0441",
    "wof:placetype":"postalcode"
},
  "geometry": {"coordinates":[134.27000000000001,35.3967],"type":"Point"}
}