{
  "type": "Feature",
  "properties": {
    "gn:adm1_name":"Kouchiken",
    "gn:adm2_name":"Nakamurashi",
    "gn:name":"Kusu",
    "iso:country":"JP",
    "wof:name":"787-1227",
    "wof:placetype":"postalcode"
},
  "geometry": {"coordinates":[132.82769999999999,33.0437],"type":"Point"}
}