{
  "type": "Feature",
  "properties": {
    "gn:adm1_name":"Kagoshimaken",
    "gn:adm2_name":"Kasedashi",
    "gn:name":"Toujinbara",
    "iso:country":"JP",
    "wof:name":"897-1121",
    "wof:placetype":"postalcode"
},
  "geometry": {"coordinates":[130.30189999999999,31.4207],"type":"Point"}
}