{
  "type": "Feature",
  "properties": {
    "gn:adm1_name":"Ishikawaken",
    "gn:adm2_name":"Kagashi",
    "gn:name":"Okunoyamachi",
    "iso:country":"JP",
    "wof:name":"922-0856",
    "wof:placetype":"postalcode"
},
  "geometry": {"coordinates":[136.27940000000001,36.284],"type":"Point"}
}