{
  "type": "Feature",
  "properties": {
    "gn:adm1_name":"Ooitaken",
    "gn:adm2_name":"Oonogunkiyokawamura",
    "gn:name":"Ooshirotani",
    "iso:country":"JP",
    "wof:name":"879-6922",
    "wof:placetype":"postalcode"
},
  "geometry": {"coordinates":[131.5119,32.8957],"type":"Point"}
}