{
  "type": "Feature",
  "properties": {
    "gn:adm1_name":"Mieken",
    "gn:adm2_name":"Matsusakashi",
    "gn:name":"Ushikusachou",
    "iso:country":"JP",
    "wof:name":"515-0116",
    "wof:placetype":"postalcode"
},
  "geometry": {"coordinates":[136.59719999999999,34.5838],"type":"Point"}
}