{
  "type": "Feature",
  "properties": {
    "gn:adm1_name":"Wakayamaken",
    "gn:adm2_name":"Wakayamashi",
    "gn:name":"Higashinunoechou",
    "iso:country":"JP",
    "wof:name":"640-8066",
    "wof:placetype":"postalcode"
},
  "geometry": {"coordinates":[135.17189999999999,34.2393],"type":"Point"}
}