{
  "type": "Feature",
  "properties": {
    "gn:adm1_name":"Kyoutofu",
    "gn:adm2_name":"Kyoutoshisakyouku",
    "gn:name":"Iwakuraoosagichou",
    "iso:country":"JP",
    "wof:name":"606-0001",
    "wof:placetype":"postalcode"
},
  "geometry": {"coordinates":[135.7876,35.0664],"type":"Point"}
}