{
  "type": "Feature",
  "properties": {
    "gn:adm1_name":"Naraken",
    "gn:adm2_name":"Sakuraishi",
    "gn:name":"Kitayama",
    "iso:country":"JP",
    "wof:name":"633-0034",
    "wof:placetype":"postalcode"
},
  "geometry": {"coordinates":[135.85149999999999,34.4749],"type":"Point"}
}