{
  "type": "Feature",
  "properties": {
    "gn:adm1_name":"Hiroshimaken",
    "gn:adm2_name":"Hiroshimashiasaminamiku",
    "gn:name":"Kawauchi",
    "iso:country":"JP",
    "wof:name":"731-0102",
    "wof:placetype":"postalcode"
},
  "geometry": {"coordinates":[132.48609999999999,34.4642],"type":"Point"}
}