{
  "type": "Feature",
  "properties": {
    "gn:adm1_name":"Fukuiken",
    "gn:adm2_name":"Katsuyamashi",
    "gn:name":"Osowachouhouki",
    "iso:country":"JP",
    "wof:name":"911-0835",
    "wof:placetype":"postalcode"
},
  "geometry": {"coordinates":[136.49469999999999,36.0354],"type":"Point"}
}