{
  "type": "Feature",
  "properties": {
    "gn:adm1_name":"Okayamaken",
    "gn:adm2_name":"Kawakamigunnariwachou",
    "gn:name":"Shimohara",
    "iso:country":"JP",
    "wof:name":"716-0111",
    "wof:placetype":"postalcode"
},
  "geometry": {"coordinates":[133.54300000000001,34.7825],"type":"Point"}
}