{
  "type": "Feature",
  "properties": {
    "gn:adm1_name":"Kanagawaken",
    "gn:adm2_name":"Aikougun'Aikawamachi",
    "gn:name":"Tanazawa",
    "iso:country":"JP",
    "wof:name":"243-0304",
    "wof:placetype":"postalcode"
},
  "geometry": {"coordinates":[139.3372,35.5099],"type":"Point"}
}