{
  "type": "Feature",
  "properties": {
    "gn:adm1_name":"Toyamaken",
    "gn:adm2_name":"Takaokashi",
    "gn:name":"Shinseimachi",
    "iso:country":"JP",
    "wof:name":"933-0904",
    "wof:placetype":"postalcode"
},
  "geometry": {"coordinates":[137.01609999999999,36.7603],"type":"Point"}
}