{
  "type": "Feature",
  "properties": {
    "gn:adm1_name":"Oosakafu",
    "gn:adm2_name":"Neyagawashi",
    "gn:name":"Ishiduminamimachi",
    "iso:country":"JP",
    "wof:name":"572-0024",
    "wof:placetype":"postalcode"
},
  "geometry": {"coordinates":[135.62270000000001,34.7742],"type":"Point"}
}