{
  "type": "Feature",
  "properties": {
    "gn:adm1_name":"Kyoutofu",
    "gn:adm2_name":"Kyoutoshifushimiku",
    "gn:name":"Fukakusanakagawarachou",
    "iso:country":"JP",
    "wof:name":"612-0002",
    "wof:placetype":"postalcode"
},
  "geometry": {"coordinates":[135.76650000000001,34.9719],"type":"Point"}
}