{
  "type": "Feature",
  "properties": {
    "gn:adm1_name":"Miyagiken",
    "gn:adm2_name":"Sendaishiaobaku",
    "gn:name":"Aobamachi",
    "iso:country":"JP",
    "wof:name":"981-0916",
    "wof:placetype":"postalcode"
},
  "geometry": {"coordinates":[140.86500000000001,38.2827],"type":"Point"}
}