{
  "type": "Feature",
  "properties": {
    "gn:adm1_name":"Nagasakiken",
    "gn:adm2_name":"Isahayashi",
    "gn:name":"Shoukyuujichou",
    "iso:country":"JP",
    "wof:name":"859-0302",
    "wof:placetype":"postalcode"
},
  "geometry": {"coordinates":[130.08750000000001,32.8733],"type":"Point"}
}