{
  "type": "Feature",
  "properties": {
    "gn:adm1_name":"Niigataken",
    "gn:adm2_name":"Niitsushi",
    "gn:name":"Tajima",
    "iso:country":"JP",
    "wof:name":"956-0013",
    "wof:placetype":"postalcode"
},
  "geometry": {"coordinates":[139.11680000000001,37.8298],"type":"Point"}
}