{
  "type": "Feature",
  "properties": {
    "gn:adm1_name":"Miyagiken",
    "gn:adm2_name":"Kesennumashi",
    "gn:name":"Matsukawa",
    "iso:country":"JP",
    "wof:name":"988-0852",
    "wof:placetype":"postalcode"
},
  "geometry": {"coordinates":[141.54730000000001,38.9162],"type":"Point"}
}