{
  "type": "Feature",
  "properties": {
    "gn:adm1_name":"Naraken",
    "gn:adm2_name":"Kashiharashi",
    "gn:name":"Kumechou",
    "iso:country":"JP",
    "wof:name":"634-0063",
    "wof:placetype":"postalcode"
},
  "geometry": {"coordinates":[135.7927,34.4838],"type":"Point"}
}