{
  "type": "Feature",
  "properties": {
    "gn:adm1_name":"Fukushimaken",
    "gn:adm2_name":"Dategunkawamatamachi",
    "gn:name":"Ebigasaku",
    "iso:country":"JP",
    "wof:name":"960-1485",
    "wof:placetype":"postalcode"
},
  "geometry": {"coordinates":[140.6046,37.6745],"type":"Point"}
}