{
  "type": "Feature",
  "properties": {
    "gn:adm1_name":"Tokushimaken",
    "gn:adm2_name":"Itanogunkitajimachou",
    "gn:name":"Nakamura",
    "iso:country":"JP",
    "wof:name":"771-0203",
    "wof:placetype":"postalcode"
},
  "geometry": {"coordinates":[134.5532,34.1274],"type":"Point"}
}