{
  "type": "Feature",
  "properties": {
    "gn:adm1_name":"Chibaken",
    "gn:adm2_name":"Ichiharashi",
    "gn:name":"Ishikawa",
    "iso:country":"JP",
    "wof:name":"290-0511",
    "wof:placetype":"postalcode"
},
  "geometry": {"coordinates":[140.17099999999999,35.3924],"type":"Point"}
}