{
  "type": "Feature",
  "properties": {
    "gn:adm1_name":"Shizuokaken",
    "gn:adm2_name":"Shizuokashi",
    "gn:name":"Akazawa",
    "iso:country":"JP",
    "wof:name":"421-1305",
    "wof:placetype":"postalcode"
},
  "geometry": {"coordinates":[138.25960000000001,35.0365],"type":"Point"}
}