{
  "type": "Feature",
  "properties": {
    "gn:adm1_name":"Okayamaken",
    "gn:adm2_name":"Okayamashi",
    "gn:name":"Higashiune",
    "iso:country":"JP",
    "wof:name":"701-0211",
    "wof:placetype":"postalcode"
},
  "geometry": {"coordinates":[133.8768,34.6065],"type":"Point"}
}