{
  "type": "Feature",
  "properties": {
    "gn:adm1_name":"Kyoutofu",
    "gn:adm2_name":"Miyadushi",
    "gn:name":"Nakanochou",
    "iso:country":"JP",
    "wof:name":"626-0046",
    "wof:placetype":"postalcode"
},
  "geometry": {"coordinates":[135.19720000000001,35.5327],"type":"Point"}
}