{
  "type": "Feature",
  "properties": {
    "gn:adm1_name":"Kagawaken",
    "gn:adm2_name":"Takamatsushi",
    "gn:name":"Shiogamichou",
    "iso:country":"JP",
    "wof:name":"760-0062",
    "wof:placetype":"postalcode"
},
  "geometry": {"coordinates":[134.05520000000001,34.3384],"type":"Point"}
}