{
  "type": "Feature",
  "properties": {
    "gn:adm1_name":"Ehimeken",
    "gn:adm2_name":"Houjoushi",
    "gn:name":"Sarukawabara",
    "iso:country":"JP",
    "wof:name":"799-2419",
    "wof:placetype":"postalcode"
},
  "geometry": {"coordinates":[132.83760000000001,33.9773],"type":"Point"}
}