{
  "type": "Feature",
  "properties": {
    "gn:adm1_name":"Saitamaken",
    "gn:adm2_name":"Hikigun'Ogawamachi",
    "gn:name":"Ogawa",
    "iso:country":"JP",
    "wof:name":"355-0321",
    "wof:placetype":"postalcode"
},
  "geometry": {"coordinates":[139.26990000000001,36.0548],"type":"Point"}
}