{
  "type": "Feature",
  "properties": {
    "gn:adm1_name":"Tochigiken",
    "gn:adm2_name":"Shimotsugagunfujiokamachi",
    "gn:name":"Nippa",
    "iso:country":"JP",
    "wof:name":"329-0314",
    "wof:placetype":"postalcode"
},
  "geometry": {"coordinates":[139.71789999999999,36.2699],"type":"Point"}
}