{
  "type": "Feature",
  "properties": {
    "gn:adm1_name":"Naraken",
    "gn:adm2_name":"Narashi",
    "gn:name":"Tanakachou",
    "iso:country":"JP",
    "wof:name":"630-8432",
    "wof:placetype":"postalcode"
},
  "geometry": {"coordinates":[135.83179999999999,34.6397],"type":"Point"}
}