{
  "type": "Feature",
  "properties": {
    "gn:adm1_name":"Kyoutofu",
    "gn:adm2_name":"Kyoutoshisakyouku",
    "gn:name":"Kamitakanofurukawachou",
    "iso:country":"JP",
    "wof:name":"606-0043",
    "wof:placetype":"postalcode"
},
  "geometry": {"coordinates":[135.79060000000001,35.0612],"type":"Point"}
}