{
  "type": "Feature",
  "properties": {
    "gn:adm1_name":"Okinawaken",
    "gn:adm2_name":"Hirarashi",
    "gn:name":"Higashinakasone",
    "iso:country":"JP",
    "wof:name":"906-0007",
    "wof:placetype":"postalcode"
},
  "geometry": {"coordinates":[125.29170000000001,24.8041],"type":"Point"}
}