{
  "type": "Feature",
  "properties": {
    "gn:adm1_name":"Kanagawaken",
    "gn:adm2_name":"Yokohamashiminamiku",
    "gn:name":"Besshiyo",
    "iso:country":"JP",
    "wof:name":"232-0064",
    "wof:placetype":"postalcode"
},
  "geometry": {"coordinates":[139.58789999999999,35.4151],"type":"Point"}
}