{
  "type": "Feature",
  "properties": {
    "gn:adm1_name":"Hyougoken",
    "gn:adm2_name":"Takaradukashi",
    "gn:name":"Mefugaoka",
    "iso:country":"JP",
    "wof:name":"665-0853",
    "wof:placetype":"postalcode"
},
  "geometry": {"coordinates":[135.35650000000001,34.8172],"type":"Point"}
}