{
  "type": "Feature",
  "properties": {
    "gn:adm1_name":"Naganoken",
    "gn:adm2_name":"Naganoshi",
    "gn:name":"Tomitake",
    "iso:country":"JP",
    "wof:name":"381-0006",
    "wof:placetype":"postalcode"
},
  "geometry": {"coordinates":[138.24549999999999,36.6718],"type":"Point"}
}