{
  "type": "Feature",
  "properties": {
    "gn:adm1_name":"Naganoken",
    "gn:adm2_name":"Uedashi",
    "gn:name":"Shimomuroga",
    "iso:country":"JP",
    "wof:name":"386-1542",
    "wof:placetype":"postalcode"
},
  "geometry": {"coordinates":[138.17320000000001,36.3951],"type":"Point"}
}