{
  "type": "Feature",
  "properties": {
    "gn:adm1_name":"Ishikawaken",
    "gn:adm2_name":"Kashimagunkashimamachi",
    "gn:name":"Higashibaba",
    "iso:country":"JP",
    "wof:name":"929-1725",
    "wof:placetype":"postalcode"
},
  "geometry": {"coordinates":[136.89340000000001,36.9668],"type":"Point"}
}