{
  "type": "Feature",
  "properties": {
    "gn:adm1_name":"Niigataken",
    "gn:adm2_name":"Kitakanbaragunyasudamachi",
    "gn:name":"Sentouji",
    "iso:country":"JP",
    "wof:name":"959-2224",
    "wof:placetype":"postalcode"
},
  "geometry": {"coordinates":[139.19470000000001,37.7817],"type":"Point"}
}