{
  "type": "Feature",
  "properties": {
    "gn:adm1_name":"Gifuken",
    "gn:adm2_name":"Tajimishi",
    "gn:name":"Heiwamachi",
    "iso:country":"JP",
    "wof:name":"507-0827",
    "wof:placetype":"postalcode"
},
  "geometry": {"coordinates":[137.11869999999999,35.3275],"type":"Point"}
}