{
  "type": "Feature",
  "properties": {
    "gn:adm1_name":"Kouchiken",
    "gn:adm2_name":"Sukumoshi",
    "gn:name":"Ekimaechou",
    "iso:country":"JP",
    "wof:name":"788-0010",
    "wof:placetype":"postalcode"
},
  "geometry": {"coordinates":[132.7141,32.932],"type":"Point"}
}