{
  "type": "Feature",
  "properties": {
    "gn:adm1_name":"Mieken",
    "gn:adm2_name":"Shimagun'Isobechou",
    "gn:name":"Matoya",
    "iso:country":"JP",
    "wof:name":"517-0204",
    "wof:placetype":"postalcode"
},
  "geometry": {"coordinates":[136.86410000000001,34.3699],"type":"Point"}
}