{
  "type": "Feature",
  "properties": {
    "gn:adm1_name":"Sagaken",
    "gn:adm2_name":"Sagashi",
    "gn:name":"Takagimachi",
    "iso:country":"JP",
    "wof:name":"840-0822",
    "wof:placetype":"postalcode"
},
  "geometry": {"coordinates":[130.30760000000001,33.2555],"type":"Point"}
}