{
  "type": "Feature",
  "properties": {
    "gn:adm1_name":"Naraken",
    "gn:adm2_name":"Yoshinogun'Ooyodochou",
    "gn:name":"Tsuchida",
    "iso:country":"JP",
    "wof:name":"638-0811",
    "wof:placetype":"postalcode"
},
  "geometry": {"coordinates":[135.79949999999999,34.3884],"type":"Point"}
}