{
  "type": "Feature",
  "properties": {
    "gn:adm1_name":"Kyoutofu",
    "gn:adm2_name":"Maidurushi",
    "gn:name":"Nishiya",
    "iso:country":"JP",
    "wof:name":"625-0142",
    "wof:placetype":"postalcode"
},
  "geometry": {"coordinates":[135.4109,35.5249],"type":"Point"}
}