{
  "type": "Feature",
  "properties": {
    "gn:adm1_name":"Toukyouto",
    "gn:adm2_name":"Hachioujishi",
    "gn:name":"Matsugi",
    "iso:country":"JP",
    "wof:name":"192-0362",
    "wof:placetype":"postalcode"
},
  "geometry": {"coordinates":[139.39230000000001,35.6237],"type":"Point"}
}