{
  "type": "Feature",
  "properties": {
    "gn:adm1_name":"Niigataken",
    "gn:adm2_name":"Kitakanbaragunseiroumachi",
    "gn:name":"Mano",
    "iso:country":"JP",
    "wof:name":"957-0111",
    "wof:placetype":"postalcode"
},
  "geometry": {"coordinates":[139.29409999999999,37.9832],"type":"Point"}
}