{
  "type": "Feature",
  "properties": {
    "gn:adm1_name":"Gifuken",
    "gn:adm2_name":"Yoshikigunkamiokachou",
    "gn:name":"Maruyama",
    "iso:country":"JP",
    "wof:name":"506-1142",
    "wof:placetype":"postalcode"
},
  "geometry": {"coordinates":[137.31319999999999,36.3006],"type":"Point"}
}