{
  "type": "Feature",
  "properties": {
    "gn:adm1_name":"Hyougoken",
    "gn:adm2_name":"Onoshi",
    "gn:name":"Miwachou",
    "iso:country":"JP",
    "wof:name":"675-1357",
    "wof:placetype":"postalcode"
},
  "geometry": {"coordinates":[134.91839999999999,34.8721],"type":"Point"}
}