{
  "type": "Feature",
  "properties": {
    "gn:adm1_name":"Nagasakiken",
    "gn:adm2_name":"Kitamatsuuragunsazachou",
    "gn:name":"Hasuwamen",
    "iso:country":"JP",
    "wof:name":"857-0341",
    "wof:placetype":"postalcode"
},
  "geometry": {"coordinates":[129.65090000000001,33.2348],"type":"Point"}
}