{
  "type": "Feature",
  "properties": {
    "gn:adm1_name":"Fukuiken",
    "gn:adm2_name":"Yoshidagunmatsuokachou",
    "gn:name":"Yoshino",
    "iso:country":"JP",
    "wof:name":"910-1121",
    "wof:placetype":"postalcode"
},
  "geometry": {"coordinates":[136.29650000000001,36.0768],"type":"Point"}
}