{
  "type": "Feature",
  "properties": {
    "gn:adm1_name":"Niigataken",
    "gn:adm2_name":"Toyosakashi",
    "gn:name":"Sudo",
    "iso:country":"JP",
    "wof:name":"950-3373",
    "wof:placetype":"postalcode"
},
  "geometry": {"coordinates":[139.18809999999999,37.918],"type":"Point"}
}