{
  "type": "Feature",
  "properties": {
    "gn:adm1_name":"Niigataken",
    "gn:adm2_name":"Araishi",
    "gn:name":"Otoyoshi",
    "iso:country":"JP",
    "wof:name":"944-0082",
    "wof:placetype":"postalcode"
},
  "geometry": {"coordinates":[138.2414,37.0493],"type":"Point"}
}