{
  "type": "Feature",
  "properties": {
    "gn:adm1_name":"Kagoshimaken",
    "gn:adm2_name":"Satsumaguntsurudachou",
    "gn:name":"Tsuruda",
    "iso:country":"JP",
    "wof:name":"895-2101",
    "wof:placetype":"postalcode"
},
  "geometry": {"coordinates":[130.49789999999999,31.9507],"type":"Point"}
}