{
  "type": "Feature",
  "properties": {
    "gn:adm1_name":"Kagawaken",
    "gn:adm2_name":"Ayautagun'Utaduchou",
    "gn:name":"Hama2banchou",
    "iso:country":"JP",
    "wof:name":"769-0202",
    "wof:placetype":"postalcode"
},
  "geometry": {"coordinates":[133.81,34.3083],"type":"Point"}
}