{
  "type": "Feature",
  "properties": {
    "gn:adm1_name":"Tochigiken",
    "gn:adm2_name":"Kanumashi",
    "gn:name":"Niregimachi",
    "iso:country":"JP",
    "wof:name":"322-0526",
    "wof:placetype":"postalcode"
},
  "geometry": {"coordinates":[139.7509,36.5076],"type":"Point"}
}