{
  "type": "Feature",
  "properties": {
    "gn:adm1_name":"Shigaken",
    "gn:adm2_name":"Ootsushi",
    "gn:name":"Kamitanakamihiranochou",
    "iso:country":"JP",
    "wof:name":"520-2113",
    "wof:placetype":"postalcode"
},
  "geometry": {"coordinates":[135.9615,34.9634],"type":"Point"}
}