{
  "type": "Feature",
  "properties": {
    "gn:adm1_name":"Mieken",
    "gn:adm2_name":"Wataraigunwataraichou",
    "gn:name":"Hiuchiishi",
    "iso:country":"JP",
    "wof:name":"516-1234",
    "wof:placetype":"postalcode"
},
  "geometry": {"coordinates":[136.59819999999999,34.3845],"type":"Point"}
}