{
  "type": "Feature",
  "properties": {
    "gn:adm1_name":"Yamaguchiken",
    "gn:adm2_name":"Kugagunshuutouchou",
    "gn:name":"Tajiri",
    "iso:country":"JP",
    "wof:name":"742-0414",
    "wof:placetype":"postalcode"
},
  "geometry": {"coordinates":[132.06319999999999,34.0257],"type":"Point"}
}