{
  "type": "Feature",
  "properties": {
    "gn:adm1_name":"Aichiken",
    "gn:adm2_name":"Chitashi",
    "gn:name":"Daikouji",
    "iso:country":"JP",
    "wof:name":"478-0022",
    "wof:placetype":"postalcode"
},
  "geometry": {"coordinates":[136.8587,34.9444],"type":"Point"}
}