{
  "type": "Feature",
  "properties": {
    "gn:adm1_name":"Kumamotoken",
    "gn:adm2_name":"Tamanashi",
    "gn:name":"Ryuuganji",
    "iso:country":"JP",
    "wof:name":"865-0061",
    "wof:placetype":"postalcode"
},
  "geometry": {"coordinates":[130.55240000000001,32.9379],"type":"Point"}
}