{
  "type": "Feature",
  "properties": {
    "gn:adm1_name":"Toukyouto",
    "gn:adm2_name":"Setagayaku",
    "gn:name":"Higashitamagawa",
    "iso:country":"JP",
    "wof:name":"158-0084",
    "wof:placetype":"postalcode"
},
  "geometry": {"coordinates":[139.67599999999999,35.5965],"type":"Point"}
}