{
  "type": "Feature",
  "properties": {
    "gn:adm1_name":"Ibarakiken",
    "gn:adm2_name":"Tsukubashi",
    "gn:name":"Amakubo",
    "iso:country":"JP",
    "wof:name":"305-0005",
    "wof:placetype":"postalcode"
},
  "geometry": {"coordinates":[140.10839999999999,36.0973],"type":"Point"}
}