{
  "type": "Feature",
  "properties": {
    "gn:adm1_name":"Fukuiken",
    "gn:adm2_name":"Fukuishi",
    "gn:name":"Amasugouchou",
    "iso:country":"JP",
    "wof:name":"910-0041",
    "wof:placetype":"postalcode"
},
  "geometry": {"coordinates":[136.1688,36.1231],"type":"Point"}
}