{
  "type": "Feature",
  "properties": {
    "gn:adm1_name":"Kumamotoken",
    "gn:adm2_name":"Kamotogun'Uekimachi",
    "gn:name":"Uekoga",
    "iso:country":"JP",
    "wof:name":"861-0152",
    "wof:placetype":"postalcode"
},
  "geometry": {"coordinates":[130.65690000000001,32.8795],"type":"Point"}
}