{
  "type": "Feature",
  "properties": {
    "gn:adm1_name":"Saitamaken",
    "gn:adm2_name":"Kukishi",
    "gn:name":"Hinokuchi",
    "iso:country":"JP",
    "wof:name":"346-0025",
    "wof:placetype":"postalcode"
},
  "geometry": {"coordinates":[139.65119999999999,36.0406],"type":"Point"}
}