{
  "type": "Feature",
  "properties": {
    "gn:adm1_name":"Toyamaken",
    "gn:adm2_name":"Toyamashi",
    "gn:name":"Yokatatamachi",
    "iso:country":"JP",
    "wof:name":"930-2253",
    "wof:placetype":"postalcode"
},
  "geometry": {"coordinates":[137.19489999999999,36.7581],"type":"Point"}
}