{
  "type": "Feature",
  "properties": {
    "gn:adm1_name":"Shizuokaken",
    "gn:adm2_name":"Kamogunhigashiizuchou",
    "gn:name":"Katase",
    "iso:country":"JP",
    "wof:name":"413-0303",
    "wof:placetype":"postalcode"
},
  "geometry": {"coordinates":[139.0592,34.8072],"type":"Point"}
}