{
  "type": "Feature",
  "properties": {
    "gn:adm1_name":"Gifuken",
    "gn:adm2_name":"Gifushi",
    "gn:name":"Murayama",
    "iso:country":"JP",
    "wof:name":"501-1107",
    "wof:placetype":"postalcode"
},
  "geometry": {"coordinates":[136.71549999999999,35.4843],"type":"Point"}
}