{
  "type": "Feature",
  "properties": {
    "gn:adm1_name":"Hiroshimaken",
    "gn:adm2_name":"Hiroshimashiminamiku",
    "gn:name":"Hijiyamakouen",
    "iso:country":"JP",
    "wof:name":"732-0815",
    "wof:placetype":"postalcode"
},
  "geometry": {"coordinates":[132.4726,34.3836],"type":"Point"}
}