{
  "type": "Feature",
  "properties": {
    "gn:adm1_name":"Fukuiken",
    "gn:adm2_name":"Obamashi",
    "gn:name":"Ozaki",
    "iso:country":"JP",
    "wof:name":"917-0032",
    "wof:placetype":"postalcode"
},
  "geometry": {"coordinates":[135.74379999999999,35.474],"type":"Point"}
}