{
  "type": "Feature",
  "properties": {
    "gn:adm1_name":"Ishikawaken",
    "gn:adm2_name":"Fugeshigunmonzenmachi",
    "gn:name":"Koshiboso",
    "iso:country":"JP",
    "wof:name":"927-2344",
    "wof:placetype":"postalcode"
},
  "geometry": {"coordinates":[136.70339999999999,37.2423],"type":"Point"}
}