{
  "type": "Feature",
  "properties": {
    "gn:adm1_name":"Hiroshimaken",
    "gn:adm2_name":"Shoubarashi",
    "gn:name":"Honmurachou",
    "iso:country":"JP",
    "wof:name":"727-0623",
    "wof:placetype":"postalcode"
},
  "geometry": {"coordinates":[133.08359999999999,34.8423],"type":"Point"}
}