{
  "type": "Feature",
  "properties": {
    "gn:adm1_name":"Oosakafu",
    "gn:adm2_name":"Ibarakishi",
    "gn:name":"Ninjouji",
    "iso:country":"JP",
    "wof:name":"568-0085",
    "wof:placetype":"postalcode"
},
  "geometry": {"coordinates":[135.54159999999999,34.8954],"type":"Point"}
}