{
  "type": "Feature",
  "properties": {
    "gn:adm1_name":"Fukuokaken",
    "gn:adm2_name":"Kitakyuushuushikokuraminamiku",
    "gn:name":"Nishimizumachi",
    "iso:country":"JP",
    "wof:name":"802-0812",
    "wof:placetype":"postalcode"
},
  "geometry": {"coordinates":[130.89259999999999,33.8523],"type":"Point"}
}