{
  "type": "Feature",
  "properties": {
    "gn:adm1_name":"Kagoshimaken",
    "gn:adm2_name":"Ooshimagunsetouchichou",
    "gn:name":"Setake",
    "iso:country":"JP",
    "wof:name":"894-2401",
    "wof:placetype":"postalcode"
},
  "geometry": {"coordinates":[129.20959999999999,28.1654],"type":"Point"}
}