{
  "type": "Feature",
  "properties": {
    "gn:adm1_name":"Gunmaken",
    "gn:adm2_name":"Tonegunkawabamura",
    "gn:name":"Tenjin",
    "iso:country":"JP",
    "wof:name":"378-0114",
    "wof:placetype":"postalcode"
},
  "geometry": {"coordinates":[139.08789999999999,36.6897],"type":"Point"}
}