{
  "type": "Feature",
  "properties": {
    "gn:adm1_name":"Kouchiken",
    "gn:adm2_name":"Sukumoshi",
    "gn:name":"Wada",
    "iso:country":"JP",
    "wof:name":"788-0052",
    "wof:placetype":"postalcode"
},
  "geometry": {"coordinates":[132.74539999999999,32.9429],"type":"Point"}
}