{
  "type": "Feature",
  "properties": {
    "gn:adm1_name":"Hyougoken",
    "gn:adm2_name":"Koubeshinishiku",
    "gn:name":"Nakano",
    "iso:country":"JP",
    "wof:name":"651-2136",
    "wof:placetype":"postalcode"
},
  "geometry": {"coordinates":[134.9716,34.6786],"type":"Point"}
}