{
  "type": "Feature",
  "properties": {
    "gn:adm1_name":"Tochigiken",
    "gn:adm2_name":"Kawachigunkamikawachimachi",
    "gn:name":"Takamatsu",
    "iso:country":"JP",
    "wof:name":"321-0416",
    "wof:placetype":"postalcode"
},
  "geometry": {"coordinates":[139.87430000000001,36.6674],"type":"Point"}
}