{
  "type": "Feature",
  "properties": {
    "gn:adm1_name":"Gifuken",
    "gn:adm2_name":"Gifushi",
    "gn:name":"Higashinakajima",
    "iso:country":"JP",
    "wof:name":"500-8235",
    "wof:placetype":"postalcode"
},
  "geometry": {"coordinates":[136.8075,35.389],"type":"Point"}
}