{
  "type": "Feature",
  "properties": {
    "gn:adm1_name":"Ehimeken",
    "gn:adm2_name":"Saijoushi",
    "gn:name":"Sakamotokou",
    "iso:country":"JP",
    "wof:name":"793-0067",
    "wof:placetype":"postalcode"
},
  "geometry": {"coordinates":[133.1439,33.8905],"type":"Point"}
}