{
  "type": "Feature",
  "properties": {
    "gn:adm1_name":"Niigataken",
    "gn:adm2_name":"Gosenshi",
    "gn:name":"Shimojou",
    "iso:country":"JP",
    "wof:name":"959-1803",
    "wof:placetype":"postalcode"
},
  "geometry": {"coordinates":[139.1677,37.7633],"type":"Point"}
}