{
  "type": "Feature",
  "properties": {
    "gn:adm1_name":"Toyamaken",
    "gn:adm2_name":"Toyamashi",
    "gn:name":"Midorichou",
    "iso:country":"JP",
    "wof:name":"930-0038",
    "wof:placetype":"postalcode"
},
  "geometry": {"coordinates":[137.22819999999999,36.6911],"type":"Point"}
}