{
  "type": "Feature",
  "properties": {
    "gn:adm1_name":"Gifuken",
    "gn:adm2_name":"Tokishi",
    "gn:name":"Hidachouhida(Sonota)",
    "iso:country":"JP",
    "wof:name":"509-5115",
    "wof:placetype":"postalcode"
},
  "geometry": {"coordinates":[137.21690000000001,35.3521],"type":"Point"}
}