{
  "type": "Feature",
  "properties": {
    "gn:adm1_name":"Ishikawaken",
    "gn:adm2_name":"Fugeshigun'Anamizumachi",
    "gn:name":"Shigaura",
    "iso:country":"JP",
    "wof:name":"927-0035",
    "wof:placetype":"postalcode"
},
  "geometry": {"coordinates":[136.90889999999999,37.2039],"type":"Point"}
}