{
  "type": "Feature",
  "properties": {
    "gn:adm1_name":"Kouchiken",
    "gn:adm2_name":"Kamiguntosayamadachou",
    "gn:name":"Sakoyabu",
    "iso:country":"JP",
    "wof:name":"782-0008",
    "wof:placetype":"postalcode"
},
  "geometry": {"coordinates":[133.7251,33.6176],"type":"Point"}
}