{
  "type": "Feature",
  "properties": {
    "gn:adm1_name":"Oosakafu",
    "gn:adm2_name":"Kadomashi",
    "gn:name":"Kamishimachou",
    "iso:country":"JP",
    "wof:name":"571-0071",
    "wof:placetype":"postalcode"
},
  "geometry": {"coordinates":[135.6103,34.7447],"type":"Point"}
}