{
  "type": "Feature",
  "properties": {
    "gn:adm1_name":"Aichiken",
    "gn:adm2_name":"Hekinanshi",
    "gn:name":"Nakayamamachi",
    "iso:country":"JP",
    "wof:name":"447-0035",
    "wof:placetype":"postalcode"
},
  "geometry": {"coordinates":[137.0017,34.8859],"type":"Point"}
}