{
  "type": "Feature",
  "properties": {
    "gn:adm1_name":"Chibaken",
    "gn:adm2_name":"Kashiwashi",
    "gn:name":"Minamisakasai",
    "iso:country":"JP",
    "wof:name":"277-0043",
    "wof:placetype":"postalcode"
},
  "geometry": {"coordinates":[139.97399999999999,35.8052],"type":"Point"}
}