{
  "type": "Feature",
  "properties": {
    "gn:adm1_name":"Fukuokaken",
    "gn:adm2_name":"Miyakogunkandamachi",
    "gn:name":"Yobaru",
    "iso:country":"JP",
    "wof:name":"800-0323",
    "wof:placetype":"postalcode"
},
  "geometry": {"coordinates":[130.98230000000001,33.756],"type":"Point"}
}