{
  "type": "Feature",
  "properties": {
    "gn:adm1_name":"Miyazakiken",
    "gn:adm2_name":"Higashimorokatagunkunitomichou",
    "gn:name":"Yatsushirominamimata",
    "iso:country":"JP",
    "wof:name":"880-1223",
    "wof:placetype":"postalcode"
},
  "geometry": {"coordinates":[131.30539999999999,32.037],"type":"Point"}
}