{
  "type": "Feature",
  "properties": {
    "gn:adm1_name":"Aichiken",
    "gn:adm2_name":"Anjoushi",
    "gn:name":"Misonochou",
    "iso:country":"JP",
    "wof:name":"446-0076",
    "wof:placetype":"postalcode"
},
  "geometry": {"coordinates":[137.04910000000001,34.9773],"type":"Point"}
}