{
  "type": "Feature",
  "properties": {
    "gn:adm1_name":"Kagawaken",
    "gn:adm2_name":"Takamatsushi",
    "gn:name":"Higashihazemachi",
    "iso:country":"JP",
    "wof:name":"761-8054",
    "wof:placetype":"postalcode"
},
  "geometry": {"coordinates":[134.04060000000001,34.3206],"type":"Point"}
}