{
  "type": "Feature",
  "properties": {
    "gn:adm1_name":"Toyamaken",
    "gn:adm2_name":"Shimoniikawagun'Unadukimachi",
    "gn:name":"Kurimushi",
    "iso:country":"JP",
    "wof:name":"938-0178",
    "wof:placetype":"postalcode"
},
  "geometry": {"coordinates":[137.55609999999999,36.8663],"type":"Point"}
}