{
  "type": "Feature",
  "properties": {
    "gn:adm1_name":"Niigataken",
    "gn:adm2_name":"Shibatashi",
    "gn:name":"Shinhokouji",
    "iso:country":"JP",
    "wof:name":"959-2444",
    "wof:placetype":"postalcode"
},
  "geometry": {"coordinates":[139.37020000000001,37.971],"type":"Point"}
}