{
  "type": "Feature",
  "properties": {
    "gn:adm1_name":"Shigaken",
    "gn:adm2_name":"Ootsushi",
    "gn:name":"Minamishiga",
    "iso:country":"JP",
    "wof:name":"520-0011",
    "wof:placetype":"postalcode"
},
  "geometry": {"coordinates":[135.85839999999999,35.0363],"type":"Point"}
}