{
  "type": "Feature",
  "properties": {
    "gn:adm1_name":"Shizuokaken",
    "gn:adm2_name":"Ogasagundaitouchou",
    "gn:name":"Takase",
    "iso:country":"JP",
    "wof:name":"437-1401",
    "wof:placetype":"postalcode"
},
  "geometry": {"coordinates":[138.04900000000001,34.7238],"type":"Point"}
}