{
  "type": "Feature",
  "properties": {
    "gn:adm1_name":"Kouchiken",
    "gn:adm2_name":"Kamiguntosayamadachou",
    "gn:name":"Aratani",
    "iso:country":"JP",
    "wof:name":"782-0072",
    "wof:placetype":"postalcode"
},
  "geometry": {"coordinates":[133.72880000000001,33.6447],"type":"Point"}
}