{
  "type": "Feature",
  "properties": {
    "gn:adm1_name":"Tottoriken",
    "gn:adm2_name":"Touhakugunmisasachou",
    "gn:name":"Akamatsu",
    "iso:country":"JP",
    "wof:name":"682-0172",
    "wof:placetype":"postalcode"
},
  "geometry": {"coordinates":[133.85329999999999,35.376],"type":"Point"}
}