{
  "type": "Feature",
  "properties": {
    "gn:adm1_name":"Tochigiken",
    "gn:adm2_name":"Kawachigunkaminokawamachi",
    "gn:name":"Sakaue",
    "iso:country":"JP",
    "wof:name":"329-0613",
    "wof:placetype":"postalcode"
},
  "geometry": {"coordinates":[139.91390000000001,36.4066],"type":"Point"}
}