{
  "type": "Feature",
  "properties": {
    "gn:adm1_name":"Aichiken",
    "gn:adm2_name":"Setoshi",
    "gn:name":"Teramotochou",
    "iso:country":"JP",
    "wof:name":"489-0838",
    "wof:placetype":"postalcode"
},
  "geometry": {"coordinates":[137.11009999999999,35.2265],"type":"Point"}
}