{
  "type": "Feature",
  "properties": {
    "gn:adm1_name":"Fukuokaken",
    "gn:adm2_name":"Fukuokashihakataku",
    "gn:name":"Gintenchou",
    "iso:country":"JP",
    "wof:name":"816-0079",
    "wof:placetype":"postalcode"
},
  "geometry": {"coordinates":[130.4631,33.5456],"type":"Point"}
}