{
  "type": "Feature",
  "properties": {
    "gn:adm1_name":"Kagoshimaken",
    "gn:adm2_name":"Kagoshimashi",
    "gn:name":"Koumenchou",
    "iso:country":"JP",
    "wof:name":"891-1402",
    "wof:placetype":"postalcode"
},
  "geometry": {"coordinates":[130.69669999999999,31.6138],"type":"Point"}
}