{
  "type": "Feature",
  "properties": {
    "gn:adm1_name":"Toyamaken",
    "gn:adm2_name":"Takaokashi",
    "gn:name":"Sengokumachi",
    "iso:country":"JP",
    "wof:name":"933-0847",
    "wof:placetype":"postalcode"
},
  "geometry": {"coordinates":[136.99590000000001,36.7465],"type":"Point"}
}