{
  "type": "Feature",
  "properties": {
    "gn:adm1_name":"Oosakafu",
    "gn:adm2_name":"Ibarakishi",
    "gn:name":"Nishiai",
    "iso:country":"JP",
    "wof:name":"567-0008",
    "wof:placetype":"postalcode"
},
  "geometry": {"coordinates":[135.55789999999999,34.8453],"type":"Point"}
}