{
  "type": "Feature",
  "properties": {
    "gn:adm1_name":"Hyougoken",
    "gn:adm2_name":"Tatsunoshi",
    "gn:name":"Issaichousumiyoshi",
    "iso:country":"JP",
    "wof:name":"679-4023",
    "wof:placetype":"postalcode"
},
  "geometry": {"coordinates":[134.5042,34.8512],"type":"Point"}
}