{
  "type": "Feature",
  "properties": {
    "gn:adm1_name":"Fukuokaken",
    "gn:adm2_name":"Chikushigunnakagawamachi",
    "gn:name":"Nakabarumiharugaoka",
    "iso:country":"JP",
    "wof:name":"811-1212",
    "wof:placetype":"postalcode"
},
  "geometry": {"coordinates":[130.4436,33.509],"type":"Point"}
}