{
  "type": "Feature",
  "properties": {
    "gn:adm1_name":"Saitamaken",
    "gn:adm2_name":"Fujimishi",
    "gn:name":"Midorinominami",
    "iso:country":"JP",
    "wof:name":"354-0007",
    "wof:placetype":"postalcode"
},
  "geometry": {"coordinates":[139.56370000000001,35.8656],"type":"Point"}
}