{
  "type": "Feature",
  "properties": {
    "gn:adm1_name":"Chibaken",
    "gn:adm2_name":"Inbagunmotonomura",
    "gn:name":"Shougen",
    "iso:country":"JP",
    "wof:name":"270-2301",
    "wof:placetype":"postalcode"
},
  "geometry": {"coordinates":[140.2105,35.8337],"type":"Point"}
}