{
  "type": "Feature",
  "properties": {
    "gn:adm1_name":"Fukushimaken",
    "gn:adm2_name":"Adachigun'Ootamamura",
    "gn:name":"Tamanoi(Babadaira)",
    "iso:country":"JP",
    "wof:name":"964-0091",
    "wof:placetype":"postalcode"
},
  "geometry": {"coordinates":[140.3536,37.5791],"type":"Point"}
}