{
  "type": "Feature",
  "properties": {
    "gn:adm1_name":"Niigataken",
    "gn:adm2_name":"Niigatashi",
    "gn:name":"Hosoyama",
    "iso:country":"JP",
    "wof:name":"950-0102",
    "wof:placetype":"postalcode"
},
  "geometry": {"coordinates":[139.15020000000001,37.8894],"type":"Point"}
}