{
  "type": "Feature",
  "properties": {
    "gn:adm1_name":"Kyoutofu",
    "gn:adm2_name":"Ayabeshi",
    "gn:name":"Jinguujichou",
    "iso:country":"JP",
    "wof:name":"623-0026",
    "wof:placetype":"postalcode"
},
  "geometry": {"coordinates":[135.25129999999999,35.2981],"type":"Point"}
}