{
  "type": "Feature",
  "properties": {
    "gn:adm1_name":"Aichiken",
    "gn:adm2_name":"Inazawashi",
    "gn:name":"Akaiketennouchou",
    "iso:country":"JP",
    "wof:name":"492-8012",
    "wof:placetype":"postalcode"
},
  "geometry": {"coordinates":[136.82210000000001,35.2727],"type":"Point"}
}