{
  "type": "Feature",
  "properties": {
    "gn:adm1_name":"Yamanashiken",
    "gn:adm2_name":"Minamitsurugunfujikawaguchikomachi",
    "gn:name":"Katsuyama",
    "iso:country":"JP",
    "wof:name":"401-0310",
    "wof:placetype":"postalcode"
},
  "geometry": {"coordinates":[138.74019999999999,35.5022],"type":"Point"}
}