{
  "type": "Feature",
  "properties": {
    "gn:adm1_name":"Niigataken",
    "gn:adm2_name":"Itoigawashi",
    "gn:name":"Ueyoko",
    "iso:country":"JP",
    "wof:name":"949-0553",
    "wof:placetype":"postalcode"
},
  "geometry": {"coordinates":[137.89590000000001,36.9404],"type":"Point"}
}