{
  "type": "Feature",
  "properties": {
    "gn:adm1_name":"Hyougoken",
    "gn:adm2_name":"Shisougunhagachou",
    "gn:name":"Nojiri",
    "iso:country":"JP",
    "wof:name":"671-4214",
    "wof:placetype":"postalcode"
},
  "geometry": {"coordinates":[134.52850000000001,35.1864],"type":"Point"}
}