{
  "type": "Feature",
  "properties": {
    "gn:adm1_name":"Hyougoken",
    "gn:adm2_name":"Asagogunwadayamachou",
    "gn:name":"Shirai",
    "iso:country":"JP",
    "wof:name":"669-5220",
    "wof:placetype":"postalcode"
},
  "geometry": {"coordinates":[134.9068,35.352],"type":"Point"}
}