{
  "type": "Feature",
  "properties": {
    "gn:adm1_name":"Mieken",
    "gn:adm2_name":"Uenoshi",
    "gn:name":"Shimokousakamachi",
    "iso:country":"JP",
    "wof:name":"518-0877",
    "wof:placetype":"postalcode"
},
  "geometry": {"coordinates":[136.1207,34.7663],"type":"Point"}
}