{
  "type": "Feature",
  "properties": {
    "gn:adm1_name":"Miyagiken",
    "gn:adm2_name":"Toodagunkogotachou",
    "gn:name":"Shindaidokoro",
    "iso:country":"JP",
    "wof:name":"987-0068",
    "wof:placetype":"postalcode"
},
  "geometry": {"coordinates":[141.0838,38.5302],"type":"Point"}
}