{
  "type": "Feature",
  "properties": {
    "gn:adm1_name":"Fukushimaken",
    "gn:adm2_name":"Dategunyanagawamachi",
    "gn:name":"Yasuji",
    "iso:country":"JP",
    "wof:name":"960-0713",
    "wof:placetype":"postalcode"
},
  "geometry": {"coordinates":[140.59989999999999,37.853],"type":"Point"}
}