{
  "type": "Feature",
  "properties": {
    "gn:adm1_name":"Fukushimaken",
    "gn:adm2_name":"Oonumagunshouwamura",
    "gn:name":"Ryouhara",
    "iso:country":"JP",
    "wof:name":"968-0213",
    "wof:placetype":"postalcode"
},
  "geometry": {"coordinates":[139.66300000000001,37.3096],"type":"Point"}
}