{
  "type": "Feature",
  "properties": {
    "gn:adm1_name":"Aichiken",
    "gn:adm2_name":"Nagoyashikitaku",
    "gn:name":"Kamiiidanishimachi",
    "iso:country":"JP",
    "wof:name":"462-0809",
    "wof:placetype":"postalcode"
},
  "geometry": {"coordinates":[136.9282,35.2039],"type":"Point"}
}