{
  "type": "Feature",
  "properties": {
    "gn:adm1_name":"Kyoutofu",
    "gn:adm2_name":"Kyoutoshisakyouku",
    "gn:name":"Kitashirakawauryuuzanchou",
    "iso:country":"JP",
    "wof:name":"606-8271",
    "wof:placetype":"postalcode"
},
  "geometry": {"coordinates":[135.79349999999999,35.0373],"type":"Point"}
}