{
  "type": "Feature",
  "properties": {
    "gn:adm1_name":"Shizuokaken",
    "gn:adm2_name":"Shidagun'Okabechou",
    "gn:name":"Nyufune",
    "iso:country":"JP",
    "wof:name":"421-1115",
    "wof:placetype":"postalcode"
},
  "geometry": {"coordinates":[138.24719999999999,34.955],"type":"Point"}
}