{
  "type": "Feature",
  "properties": {
    "gn:adm1_name":"Aichiken",
    "gn:adm2_name":"Kariyashi",
    "gn:name":"Takasuchou",
    "iso:country":"JP",
    "wof:name":"448-0812",
    "wof:placetype":"postalcode"
},
  "geometry": {"coordinates":[137.01130000000001,34.9766],"type":"Point"}
}