{
  "type": "Feature",
  "properties": {
    "gn:adm1_name":"Fukushimaken",
    "gn:adm2_name":"Futabagunkawauchimura",
    "gn:name":"Kamikawauchi",
    "iso:country":"JP",
    "wof:name":"979-1201",
    "wof:placetype":"postalcode"
},
  "geometry": {"coordinates":[140.77959999999999,37.3519],"type":"Point"}
}