{
  "type": "Feature",
  "properties": {
    "gn:adm1_name":"Toyamaken",
    "gn:adm2_name":"Higashitonamiguntogamura",
    "gn:name":"Oshiba",
    "iso:country":"JP",
    "wof:name":"939-2504",
    "wof:placetype":"postalcode"
},
  "geometry": {"coordinates":[137.02420000000001,36.4801],"type":"Point"}
}