{
  "type": "Feature",
  "properties": {
    "gn:adm1_name":"Chibaken",
    "gn:adm2_name":"Nodashi",
    "gn:name":"Kinosaki",
    "iso:country":"JP",
    "wof:name":"278-0002",
    "wof:placetype":"postalcode"
},
  "geometry": {"coordinates":[139.91079999999999,35.956],"type":"Point"}
}