{
  "type": "Feature",
  "properties": {
    "gn:adm1_name":"Niigataken",
    "gn:adm2_name":"Nakakubikigunkakizakimachi",
    "gn:name":"Kawata",
    "iso:country":"JP",
    "wof:name":"949-3237",
    "wof:placetype":"postalcode"
},
  "geometry": {"coordinates":[138.41749999999999,37.2663],"type":"Point"}
}