{
  "type": "Feature",
  "properties": {
    "gn:adm1_name":"Chibaken",
    "gn:adm2_name":"Funabashishi",
    "gn:name":"Kanehorichou",
    "iso:country":"JP",
    "wof:name":"274-0054",
    "wof:placetype":"postalcode"
},
  "geometry": {"coordinates":[140.06450000000001,35.7539],"type":"Point"}
}