{
  "type": "Feature",
  "properties": {
    "gn:adm1_name":"Nagasakiken",
    "gn:adm2_name":"Nagasakishi",
    "gn:name":"Shikimimachi",
    "iso:country":"JP",
    "wof:name":"851-1137",
    "wof:placetype":"postalcode"
},
  "geometry": {"coordinates":[129.79159999999999,32.787],"type":"Point"}
}