{
  "type": "Feature",
  "properties": {
    "gn:adm1_name":"Yamagataken",
    "gn:adm2_name":"Nishimurayamagun'Ooemachi",
    "gn:name":"Douyashiki",
    "iso:country":"JP",
    "wof:name":"990-1132",
    "wof:placetype":"postalcode"
},
  "geometry": {"coordinates":[140.17500000000001,38.3689],"type":"Point"}
}