{
  "type": "Feature",
  "properties": {
    "gn:adm1_name":"Yamaguchiken",
    "gn:adm2_name":"Shuunanshi",
    "gn:name":"Urayamakaisaku",
    "iso:country":"JP",
    "wof:name":"745-0857",
    "wof:placetype":"postalcode"
},
  "geometry": {"coordinates":[131.79339999999999,34.0678],"type":"Point"}
}