{
  "type": "Feature",
  "properties": {
    "gn:adm1_name":"Aichiken",
    "gn:adm2_name":"Inazawashi",
    "gn:name":"Nishijima",
    "iso:country":"JP",
    "wof:name":"492-8328",
    "wof:placetype":"postalcode"
},
  "geometry": {"coordinates":[136.7467,35.2571],"type":"Point"}
}