{
  "type": "Feature",
  "properties": {
    "gn:adm1_name":"Shimaneken",
    "gn:adm2_name":"Ooharagundaitouchou",
    "gn:name":"Shiota",
    "iso:country":"JP",
    "wof:name":"699-1262",
    "wof:placetype":"postalcode"
},
  "geometry": {"coordinates":[133.036,35.2913],"type":"Point"}
}