{
  "type": "Feature",
  "properties": {
    "gn:adm1_name":"Shizuokaken",
    "gn:adm2_name":"Numadushi",
    "gn:name":"Nakasawada",
    "iso:country":"JP",
    "wof:name":"410-0006",
    "wof:placetype":"postalcode"
},
  "geometry": {"coordinates":[138.8526,35.1233],"type":"Point"}
}