{
  "type": "Feature",
  "properties": {
    "gn:adm1_name":"Hyougoken",
    "gn:adm2_name":"Yabugun'Ooyachou",
    "gn:name":"Wada",
    "iso:country":"JP",
    "wof:name":"667-0435",
    "wof:placetype":"postalcode"
},
  "geometry": {"coordinates":[134.66550000000001,35.2947],"type":"Point"}
}