{
  "type": "Feature",
  "properties": {
    "gn:adm1_name":"Kumamotoken",
    "gn:adm2_name":"Kikuchishi",
    "gn:name":"Fukagawa",
    "iso:country":"JP",
    "wof:name":"861-1304",
    "wof:placetype":"postalcode"
},
  "geometry": {"coordinates":[130.8023,32.9688],"type":"Point"}
}