{
  "type": "Feature",
  "properties": {
    "gn:adm1_name":"Gifuken",
    "gn:adm2_name":"Gifushi",
    "gn:name":"Kamikidaijinishi",
    "iso:country":"JP",
    "wof:name":"502-0863",
    "wof:placetype":"postalcode"
},
  "geometry": {"coordinates":[136.73859999999999,35.4737],"type":"Point"}
}