{
  "type": "Feature",
  "properties": {
    "gn:adm1_name":"Ishikawaken",
    "gn:adm2_name":"Kahokuguntsubatamachi",
    "gn:name":"Hara",
    "iso:country":"JP",
    "wof:name":"929-0421",
    "wof:placetype":"postalcode"
},
  "geometry": {"coordinates":[136.78489999999999,36.6638],"type":"Point"}
}