{
  "type": "Feature",
  "properties": {
    "gn:adm1_name":"Shizuokaken",
    "gn:adm2_name":"Suntougun'Oyamachou",
    "gn:name":"Kamifurushiro",
    "iso:country":"JP",
    "wof:name":"410-1323",
    "wof:placetype":"postalcode"
},
  "geometry": {"coordinates":[138.94649999999999,35.3381],"type":"Point"}
}