{
  "type": "Feature",
  "properties": {
    "gn:adm1_name":"Yamagataken",
    "gn:adm2_name":"Yonezawashi",
    "gn:name":"Tateyamayagomachi",
    "iso:country":"JP",
    "wof:name":"992-0071",
    "wof:placetype":"postalcode"
},
  "geometry": {"coordinates":[140.06030000000001,37.915],"type":"Point"}
}