{
  "type": "Feature",
  "properties": {
    "gn:adm1_name":"Fukushimaken",
    "gn:adm2_name":"Higashishirakawagunsamegawamura",
    "gn:name":"Nishiyama",
    "iso:country":"JP",
    "wof:name":"963-8408",
    "wof:placetype":"postalcode"
},
  "geometry": {"coordinates":[140.4853,37.0686],"type":"Point"}
}