{
  "type": "Feature",
  "properties": {
    "gn:adm1_name":"Ehimeken",
    "gn:adm2_name":"Ochigunkikumachou",
    "gn:name":"Kawakami",
    "iso:country":"JP",
    "wof:name":"799-2307",
    "wof:placetype":"postalcode"
},
  "geometry": {"coordinates":[132.8614,34.0163],"type":"Point"}
}