{
  "type": "Feature",
  "properties": {
    "gn:adm1_name":"Hyougoken",
    "gn:adm2_name":"Asagogunsantouchou",
    "gn:name":"Kanaura",
    "iso:country":"JP",
    "wof:name":"669-5115",
    "wof:placetype":"postalcode"
},
  "geometry": {"coordinates":[134.92330000000001,35.3342],"type":"Point"}
}