{
  "type": "Feature",
  "properties": {
    "gn:adm1_name":"Hyougoken",
    "gn:adm2_name":"Mikatagun'Onsenchou",
    "gn:name":"Chihara",
    "iso:country":"JP",
    "wof:name":"669-6941",
    "wof:placetype":"postalcode"
},
  "geometry": {"coordinates":[134.4444,35.5556],"type":"Point"}
}