{
  "type": "Feature",
  "properties": {
    "gn:adm1_name":"Kouchiken",
    "gn:adm2_name":"Takaokagunyusuharachou",
    "gn:name":"Kamihonmura",
    "iso:country":"JP",
    "wof:name":"785-0606",
    "wof:placetype":"postalcode"
},
  "geometry": {"coordinates":[132.96619999999999,33.4362],"type":"Point"}
}