{
  "type": "Feature",
  "properties": {
    "gn:adm1_name":"Kagoshimaken",
    "gn:adm2_name":"Kagoshimashi",
    "gn:name":"Taniyamashioyachou",
    "iso:country":"JP",
    "wof:name":"891-0121",
    "wof:placetype":"postalcode"
},
  "geometry": {"coordinates":[130.51740000000001,31.5142],"type":"Point"}
}