{
  "type": "Feature",
  "properties": {
    "gn:adm1_name":"Kyoutofu",
    "gn:adm2_name":"Kyoutoshiukyouku",
    "gn:name":"Umedugotouchou",
    "iso:country":"JP",
    "wof:name":"615-0933",
    "wof:placetype":"postalcode"
},
  "geometry": {"coordinates":[135.70269999999999,35.0039],"type":"Point"}
}