{
  "type": "Feature",
  "properties": {
    "gn:adm1_name":"Gunmaken",
    "gn:adm2_name":"Nittagunnittamachi",
    "gn:name":"Mizuki",
    "iso:country":"JP",
    "wof:name":"370-0311",
    "wof:placetype":"postalcode"
},
  "geometry": {"coordinates":[139.31059999999999,36.3106],"type":"Point"}
}