{
  "type": "Feature",
  "properties": {
    "gn:adm1_name":"Chibaken",
    "gn:adm2_name":"Sanbugun'Ooamishirasatomachi",
    "gn:name":"Kiminomoriminami",
    "iso:country":"JP",
    "wof:name":"299-3241",
    "wof:placetype":"postalcode"
},
  "geometry": {"coordinates":[140.30160000000001,35.5522],"type":"Point"}
}