{
  "type": "Feature",
  "properties": {
    "gn:adm1_name":"Kyoutofu",
    "gn:adm2_name":"Kyoutoshinakagyouku",
    "gn:name":"Nanachoume",
    "iso:country":"JP",
    "wof:name":"604-0076",
    "wof:placetype":"postalcode"
},
  "geometry": {"coordinates":[135.75239999999999,35.0167],"type":"Point"}
}