{
  "type": "Feature",
  "properties": {
    "gn:adm1_name":"Mieken",
    "gn:adm2_name":"Agegunkawagechou",
    "gn:name":"Ueno",
    "iso:country":"JP",
    "wof:name":"510-0304",
    "wof:placetype":"postalcode"
},
  "geometry": {"coordinates":[136.54949999999999,34.793],"type":"Point"}
}