{
  "type": "Feature",
  "properties": {
    "gn:adm1_name":"Ishikawaken",
    "gn:adm2_name":"Kashimagunnakajimamachi",
    "gn:name":"Kasashi",
    "iso:country":"JP",
    "wof:name":"929-2233",
    "wof:placetype":"postalcode"
},
  "geometry": {"coordinates":[136.8509,37.0927],"type":"Point"}
}