{
  "type": "Feature",
  "properties": {
    "gn:adm1_name":"Kanagawaken",
    "gn:adm2_name":"Kawasakishinakaharaku",
    "gn:name":"Miyauchi",
    "iso:country":"JP",
    "wof:name":"211-0051",
    "wof:placetype":"postalcode"
},
  "geometry": {"coordinates":[139.64189999999999,35.5904],"type":"Point"}
}