{
  "type": "Feature",
  "properties": {
    "gn:adm1_name":"Ehimeken",
    "gn:adm2_name":"Onsengunkawauchichou",
    "gn:name":"Kitagata",
    "iso:country":"JP",
    "wof:name":"791-0303",
    "wof:placetype":"postalcode"
},
  "geometry": {"coordinates":[132.90309999999999,33.8053],"type":"Point"}
}