{
  "type": "Feature",
  "properties": {
    "gn:adm1_name":"Ehimeken",
    "gn:adm2_name":"Kamiukenagun'Omogomura",
    "gn:name":"Hongumi",
    "iso:country":"JP",
    "wof:name":"791-1706",
    "wof:placetype":"postalcode"
},
  "geometry": {"coordinates":[133.0155,33.6738],"type":"Point"}
}