{
  "type": "Feature",
  "properties": {
    "gn:adm1_name":"Aichiken",
    "gn:adm2_name":"Hekinanshi",
    "gn:name":"Nakaemachi",
    "iso:country":"JP",
    "wof:name":"447-0812",
    "wof:placetype":"postalcode"
},
  "geometry": {"coordinates":[136.98910000000001,34.8609],"type":"Point"}
}