{
  "type": "Feature",
  "properties": {
    "gn:adm1_name":"Oosakafu",
    "gn:adm2_name":"Ibarakishi",
    "gn:name":"Wakasonochou",
    "iso:country":"JP",
    "wof:name":"567-0894",
    "wof:placetype":"postalcode"
},
  "geometry": {"coordinates":[135.58099999999999,34.8028],"type":"Point"}
}