{
  "type": "Feature",
  "properties": {
    "gn:adm1_name":"Kanagawaken",
    "gn:adm2_name":"Ashigarashimogunhakonemachi",
    "gn:name":"Ashinoyu",
    "iso:country":"JP",
    "wof:name":"250-0523",
    "wof:placetype":"postalcode"
},
  "geometry": {"coordinates":[139.04259999999999,35.2216],"type":"Point"}
}