{
  "type": "Feature",
  "properties": {
    "gn:adm1_name":"Shimaneken",
    "gn:adm2_name":"Iishigunkakeyamachi",
    "gn:name":"Kakeya",
    "iso:country":"JP",
    "wof:name":"690-2701",
    "wof:placetype":"postalcode"
},
  "geometry": {"coordinates":[132.8169,35.1996],"type":"Point"}
}