{
  "type": "Feature",
  "properties": {
    "gn:adm1_name":"Kyoutofu",
    "gn:adm2_name":"Kyoutoshikitaku",
    "gn:name":"Shichikunishitakanawachou",
    "iso:country":"JP",
    "wof:name":"603-8205",
    "wof:placetype":"postalcode"
},
  "geometry": {"coordinates":[135.7484,35.0464],"type":"Point"}
}