{
  "type": "Feature",
  "properties": {
    "gn:adm1_name":"Shizuokaken",
    "gn:adm2_name":"Numadushi",
    "gn:name":"Higashishiiji",
    "iso:country":"JP",
    "wof:name":"410-0302",
    "wof:placetype":"postalcode"
},
  "geometry": {"coordinates":[138.83750000000001,35.123],"type":"Point"}
}