{
  "type": "Feature",
  "properties": {
    "gn:adm1_name":"Ishikawaken",
    "gn:adm2_name":"Kashimaguntatsuruhamamachi",
    "gn:name":"Sugimori",
    "iso:country":"JP",
    "wof:name":"929-2112",
    "wof:placetype":"postalcode"
},
  "geometry": {"coordinates":[136.8903,37.0495],"type":"Point"}
}