{
  "type": "Feature",
  "properties": {
    "gn:adm1_name":"Fukuokaken",
    "gn:adm2_name":"Yukuhashishi",
    "gn:name":"Osagi",
    "iso:country":"JP",
    "wof:name":"824-0058",
    "wof:placetype":"postalcode"
},
  "geometry": {"coordinates":[130.93729999999999,33.7177],"type":"Point"}
}