{
  "type": "Feature",
  "properties": {
    "gn:adm1_name":"Gunmaken",
    "gn:adm2_name":"Isesakishi",
    "gn:name":"Higashihonmachi",
    "iso:country":"JP",
    "wof:name":"372-0025",
    "wof:placetype":"postalcode"
},
  "geometry": {"coordinates":[139.20529999999999,36.3189],"type":"Point"}
}