{
  "type": "Feature",
  "properties": {
    "gn:adm1_name":"Niigataken",
    "gn:adm2_name":"Kashiwazakishi",
    "gn:name":"Kamihara",
    "iso:country":"JP",
    "wof:name":"945-0021",
    "wof:placetype":"postalcode"
},
  "geometry": {"coordinates":[138.5959,37.3892],"type":"Point"}
}