{
  "type": "Feature",
  "properties": {
    "gn:adm1_name":"Saitamaken",
    "gn:adm2_name":"Kawagoeshi",
    "gn:name":"Minamitajima",
    "iso:country":"JP",
    "wof:name":"350-0027",
    "wof:placetype":"postalcode"
},
  "geometry": {"coordinates":[139.50810000000001,35.9013],"type":"Point"}
}