{
  "type": "Feature",
  "properties": {
    "gn:adm1_name":"Naraken",
    "gn:adm2_name":"Ikomagun'Andochou",
    "gn:name":"Kashinokidai",
    "iso:country":"JP",
    "wof:name":"639-1063",
    "wof:placetype":"postalcode"
},
  "geometry": {"coordinates":[135.75989999999999,34.6006],"type":"Point"}
}