{
  "type": "Feature",
  "properties": {
    "gn:adm1_name":"Tochigiken",
    "gn:adm2_name":"Kanumashi",
    "gn:name":"Nasaharamachi",
    "iso:country":"JP",
    "wof:name":"322-0528",
    "wof:placetype":"postalcode"
},
  "geometry": {"coordinates":[139.751,36.5206],"type":"Point"}
}