{
  "type": "Feature",
  "properties": {
    "gn:adm1_name":"Miyagiken",
    "gn:adm2_name":"Monougunkahokuchou",
    "gn:name":"Fukuji",
    "iso:country":"JP",
    "wof:name":"986-0115",
    "wof:placetype":"postalcode"
},
  "geometry": {"coordinates":[141.3869,38.5287],"type":"Point"}
}