{
  "type": "Feature",
  "properties": {
    "gn:adm1_name":"Niigataken",
    "gn:adm2_name":"Nagaokashi",
    "gn:name":"Nagaminemachi",
    "iso:country":"JP",
    "wof:name":"940-2142",
    "wof:placetype":"postalcode"
},
  "geometry": {"coordinates":[138.78309999999999,37.4346],"type":"Point"}
}