{
  "type": "Feature",
  "properties": {
    "gn:adm1_name":"Nagasakiken",
    "gn:adm2_name":"Nagasakishi",
    "gn:name":"Shinnakagawamachi",
    "iso:country":"JP",
    "wof:name":"850-0014",
    "wof:placetype":"postalcode"
},
  "geometry": {"coordinates":[129.8903,32.7511],"type":"Point"}
}