{
  "type": "Feature",
  "properties": {
    "gn:adm1_name":"Fukuiken",
    "gn:adm2_name":"Nanjougun'Imajouchou",
    "gn:name":"Nagasawa",
    "iso:country":"JP",
    "wof:name":"919-0118",
    "wof:placetype":"postalcode"
},
  "geometry": {"coordinates":[136.23750000000001,35.7976],"type":"Point"}
}