{
  "type": "Feature",
  "properties": {
    "gn:adm1_name":"Gifuken",
    "gn:adm2_name":"Kanigunmitakechou",
    "gn:name":"Ijiri",
    "iso:country":"JP",
    "wof:name":"505-0115",
    "wof:placetype":"postalcode"
},
  "geometry": {"coordinates":[137.15190000000001,35.4296],"type":"Point"}
}