{
  "type": "Feature",
  "properties": {
    "gn:adm1_name":"Toyamaken",
    "gn:adm2_name":"Himishi",
    "gn:name":"Sono",
    "iso:country":"JP",
    "wof:name":"935-0041",
    "wof:placetype":"postalcode"
},
  "geometry": {"coordinates":[136.98500000000001,36.8327],"type":"Point"}
}