{
  "type": "Feature",
  "properties": {
    "gn:adm1_name":"Shigaken",
    "gn:adm2_name":"Sakatagun'Oumichou",
    "gn:name":"Notose",
    "iso:country":"JP",
    "wof:name":"521-0082",
    "wof:placetype":"postalcode"
},
  "geometry": {"coordinates":[136.32079999999999,35.3333],"type":"Point"}
}