{
  "type": "Feature",
  "properties": {
    "gn:adm1_name":"Mieken",
    "gn:adm2_name":"Tsushi",
    "gn:name":"Kawazoechou",
    "iso:country":"JP",
    "wof:name":"514-0044",
    "wof:placetype":"postalcode"
},
  "geometry": {"coordinates":[136.4948,34.7117],"type":"Point"}
}