{
  "type": "Feature",
  "properties": {
    "gn:adm1_name":"Gifuken",
    "gn:adm2_name":"Gifushi",
    "gn:name":"Hinakura",
    "iso:country":"JP",
    "wof:name":"501-1181",
    "wof:placetype":"postalcode"
},
  "geometry": {"coordinates":[136.70060000000001,35.5197],"type":"Point"}
}