{
  "type": "Feature",
  "properties": {
    "gn:adm1_name":"Chibaken",
    "gn:adm2_name":"Urayasushi",
    "gn:name":"Takasu",
    "iso:country":"JP",
    "wof:name":"279-0023",
    "wof:placetype":"postalcode"
},
  "geometry": {"coordinates":[139.91390000000001,35.6378],"type":"Point"}
}