{
  "type": "Feature",
  "properties": {
    "gn:adm1_name":"Shizuokaken",
    "gn:adm2_name":"Shizuokashi",
    "gn:name":"Warabino",
    "iso:country":"JP",
    "wof:name":"421-2308",
    "wof:placetype":"postalcode"
},
  "geometry": {"coordinates":[138.36160000000001,35.128],"type":"Point"}
}