{
  "type": "Feature",
  "properties": {
    "gn:adm1_name":"Sagaken",
    "gn:adm2_name":"Kishimagunkitagatamachi",
    "gn:name":"Ashihara",
    "iso:country":"JP",
    "wof:name":"849-2203",
    "wof:placetype":"postalcode"
},
  "geometry": {"coordinates":[130.07419999999999,33.2083],"type":"Point"}
}