{
  "type": "Feature",
  "properties": {
    "gn:adm1_name":"Okayamaken",
    "gn:adm2_name":"Katsutagunshououchou",
    "gn:name":"Fukuyoshi",
    "iso:country":"JP",
    "wof:name":"709-4322",
    "wof:placetype":"postalcode"
},
  "geometry": {"coordinates":[134.09110000000001,35.0466],"type":"Point"}
}