{
  "type": "Feature",
  "properties": {
    "gn:adm1_name":"Kouchiken",
    "gn:adm2_name":"Susakishi",
    "gn:name":"Uranouchifukura",
    "iso:country":"JP",
    "wof:name":"785-0172",
    "wof:placetype":"postalcode"
},
  "geometry": {"coordinates":[133.40610000000001,33.4107],"type":"Point"}
}