{
  "type": "Feature",
  "properties": {
    "gn:adm1_name":"Gifuken",
    "gn:adm2_name":"Mashitagunhagiwarachou",
    "gn:name":"Jouro",
    "iso:country":"JP",
    "wof:name":"509-2518",
    "wof:placetype":"postalcode"
},
  "geometry": {"coordinates":[137.20599999999999,35.9047],"type":"Point"}
}