{
  "type": "Feature",
  "properties": {
    "gn:adm1_name":"Fukushimaken",
    "gn:adm2_name":"Iwakishi",
    "gn:name":"Tairakoizumi",
    "iso:country":"JP",
    "wof:name":"970-8041",
    "wof:placetype":"postalcode"
},
  "geometry": {"coordinates":[140.9221,37.0303],"type":"Point"}
}