{
  "type": "Feature",
  "properties": {
    "gn:adm1_name":"Ibarakiken",
    "gn:adm2_name":"Makabegun'Akenomachi",
    "gn:name":"Nabeyama",
    "iso:country":"JP",
    "wof:name":"300-4506",
    "wof:placetype":"postalcode"
},
  "geometry": {"coordinates":[140.02950000000001,36.2726],"type":"Point"}
}