{
  "type": "Feature",
  "properties": {
    "gn:adm1_name":"Oosakafu",
    "gn:adm2_name":"Oosakashiminatoku",
    "gn:name":"Yuunagi",
    "iso:country":"JP",
    "wof:name":"552-0004",
    "wof:placetype":"postalcode"
},
  "geometry": {"coordinates":[135.45240000000001,34.6625],"type":"Point"}
}