{
  "type": "Feature",
  "properties": {
    "gn:adm1_name":"Hiroshimaken",
    "gn:adm2_name":"Fuchuushi",
    "gn:name":"Saburoumaruchou",
    "iso:country":"JP",
    "wof:name":"726-0026",
    "wof:placetype":"postalcode"
},
  "geometry": {"coordinates":[133.18899999999999,34.5432],"type":"Point"}
}