{
  "type": "Feature",
  "properties": {
    "gn:adm1_name":"Kagawaken",
    "gn:adm2_name":"Nakatadogunmannouchou",
    "gn:name":"Kumon",
    "iso:country":"JP",
    "wof:name":"766-0011",
    "wof:placetype":"postalcode"
},
  "geometry": {"coordinates":[133.82060000000001,34.2166],"type":"Point"}
}