{
  "type": "Feature",
  "properties": {
    "gn:adm1_name":"Niigataken",
    "gn:adm2_name":"Shironeshi",
    "gn:name":"Juugoken",
    "iso:country":"JP",
    "wof:name":"950-1232",
    "wof:placetype":"postalcode"
},
  "geometry": {"coordinates":[139.01689999999999,37.781],"type":"Point"}
}