{
  "type": "Feature",
  "properties": {
    "gn:adm1_name":"Shigaken",
    "gn:adm2_name":"Hikoneshi",
    "gn:name":"Shiromachi",
    "iso:country":"JP",
    "wof:name":"522-0068",
    "wof:placetype":"postalcode"
},
  "geometry": {"coordinates":[136.2456,35.2755],"type":"Point"}
}