{
  "type": "Feature",
  "properties": {
    "gn:adm1_name":"Saitamaken",
    "gn:adm2_name":"Minamisaitamagunshiraokamachi",
    "gn:name":"Teratsuka",
    "iso:country":"JP",
    "wof:name":"349-0214",
    "wof:placetype":"postalcode"
},
  "geometry": {"coordinates":[139.67140000000001,36.0254],"type":"Point"}
}