{
  "type": "Feature",
  "properties": {
    "gn:adm1_name":"Mieken",
    "gn:adm2_name":"Kuwanashi",
    "gn:name":"Shinkuramochi",
    "iso:country":"JP",
    "wof:name":"511-0855",
    "wof:placetype":"postalcode"
},
  "geometry": {"coordinates":[136.6643,35.0603],"type":"Point"}
}