{
  "type": "Feature",
  "properties": {
    "gn:adm1_name":"Naganoken",
    "gn:adm2_name":"Suwagunshimosuwamachi",
    "gn:name":"Yudanakamachi",
    "iso:country":"JP",
    "wof:name":"393-0017",
    "wof:placetype":"postalcode"
},
  "geometry": {"coordinates":[138.08750000000001,36.077],"type":"Point"}
}