{
  "type": "Feature",
  "properties": {
    "gn:adm1_name":"Gunmaken",
    "gn:adm2_name":"Isesakishi",
    "gn:name":"Tsutsumishitamachi",
    "iso:country":"JP",
    "wof:name":"372-0004",
    "wof:placetype":"postalcode"
},
  "geometry": {"coordinates":[139.19589999999999,36.3386],"type":"Point"}
}