{
  "type": "Feature",
  "properties": {
    "gn:adm1_name":"Aichiken",
    "gn:adm2_name":"Nishikamogun'Obaramura",
    "gn:name":"Yuya",
    "iso:country":"JP",
    "wof:name":"470-0563",
    "wof:placetype":"postalcode"
},
  "geometry": {"coordinates":[137.28819999999999,35.2415],"type":"Point"}
}