{
  "type": "Feature",
  "properties": {
    "gn:adm1_name":"Yamaguchiken",
    "gn:adm2_name":"Kugagunmiwachou",
    "gn:name":"Nishibata",
    "iso:country":"JP",
    "wof:name":"740-1232",
    "wof:placetype":"postalcode"
},
  "geometry": {"coordinates":[132.07050000000001,34.2127],"type":"Point"}
}