{
  "type": "Feature",
  "properties": {
    "gn:adm1_name":"Naraken",
    "gn:adm2_name":"Narashi",
    "gn:name":"Kangokuchou",
    "iso:country":"JP",
    "wof:name":"630-8242",
    "wof:placetype":"postalcode"
},
  "geometry": {"coordinates":[135.8254,34.6835],"type":"Point"}
}