{
  "type": "Feature",
  "properties": {
    "gn:adm1_name":"Ooitaken",
    "gn:adm2_name":"Saikishi",
    "gn:name":"Monze",
    "iso:country":"JP",
    "wof:name":"876-0061",
    "wof:placetype":"postalcode"
},
  "geometry": {"coordinates":[131.8629,32.9706],"type":"Point"}
}