{
  "type": "Feature",
  "properties": {
    "gn:adm1_name":"Yamagataken",
    "gn:adm2_name":"Yamagatashi",
    "gn:name":"Ootemachi",
    "iso:country":"JP",
    "wof:name":"990-0046",
    "wof:placetype":"postalcode"
},
  "geometry": {"coordinates":[140.3338,38.2569],"type":"Point"}
}