{
  "type": "Feature",
  "properties": {
    "gn:adm1_name":"Ishikawaken",
    "gn:adm2_name":"Nanaoshi",
    "gn:name":"Furuyashikimachi",
    "iso:country":"JP",
    "wof:name":"926-0024",
    "wof:placetype":"postalcode"
},
  "geometry": {"coordinates":[136.97450000000001,37.0236],"type":"Point"}
}