{
  "type": "Feature",
  "properties": {
    "gn:adm1_name":"Mieken",
    "gn:adm2_name":"Matsusakashi",
    "gn:name":"Uegawachou",
    "iso:country":"JP",
    "wof:name":"515-0041",
    "wof:placetype":"postalcode"
},
  "geometry": {"coordinates":[136.56059999999999,34.5504],"type":"Point"}
}