{
  "type": "Feature",
  "properties": {
    "gn:adm1_name":"Miyagiken",
    "gn:adm2_name":"Shiogamashi",
    "gn:name":"Asahichou",
    "iso:country":"JP",
    "wof:name":"985-0026",
    "wof:placetype":"postalcode"
},
  "geometry": {"coordinates":[141.0214,38.3137],"type":"Point"}
}