{
  "type": "Feature",
  "properties": {
    "gn:adm1_name":"Ibarakiken",
    "gn:adm2_name":"Kujigunkanasagoumachi",
    "gn:name":"Araji",
    "iso:country":"JP",
    "wof:name":"313-0132",
    "wof:placetype":"postalcode"
},
  "geometry": {"coordinates":[140.4529,36.5308],"type":"Point"}
}