{
  "type": "Feature",
  "properties": {
    "gn:adm1_name":"Naraken",
    "gn:adm2_name":"Udagunhaibarachou",
    "gn:name":"Harumigaoka",
    "iso:country":"JP",
    "wof:name":"633-0257",
    "wof:placetype":"postalcode"
},
  "geometry": {"coordinates":[135.94890000000001,34.5312],"type":"Point"}
}