{
  "type": "Feature",
  "properties": {
    "gn:adm1_name":"Yamaguchiken",
    "gn:adm2_name":"Abugunmutsumison",
    "gn:name":"Kibekami",
    "iso:country":"JP",
    "wof:name":"758-0304",
    "wof:placetype":"postalcode"
},
  "geometry": {"coordinates":[131.5872,34.4396],"type":"Point"}
}