{
  "type": "Feature",
  "properties": {
    "gn:adm1_name":"Okayamaken",
    "gn:adm2_name":"Soujashi",
    "gn:name":"Yashiro",
    "iso:country":"JP",
    "wof:name":"719-1146",
    "wof:placetype":"postalcode"
},
  "geometry": {"coordinates":[133.7055,34.667],"type":"Point"}
}