{
  "type": "Feature",
  "properties": {
    "gn:adm1_name":"Yamaguchiken",
    "gn:adm2_name":"Shimonosekishi",
    "gn:name":"Maeshouyachou",
    "iso:country":"JP",
    "wof:name":"751-0803",
    "wof:placetype":"postalcode"
},
  "geometry": {"coordinates":[130.9667,34.0073],"type":"Point"}
}