{
  "type": "Feature",
  "properties": {
    "gn:adm1_name":"Tokushimaken",
    "gn:adm2_name":"Itanogun'Itanochou",
    "gn:name":"Kurodani",
    "iso:country":"JP",
    "wof:name":"779-0113",
    "wof:placetype":"postalcode"
},
  "geometry": {"coordinates":[134.4308,34.1424],"type":"Point"}
}