{
  "type": "Feature",
  "properties": {
    "gn:adm1_name":"Ehimeken",
    "gn:adm2_name":"Iyoshi",
    "gn:name":"Ikanikeisaiganaibaai",
    "iso:country":"JP",
    "wof:name":"799-3100",
    "wof:placetype":"postalcode"
},
  "geometry": {"coordinates":[132.71100000000001,33.6416],"type":"Point"}
}