{
  "type": "Feature",
  "properties": {
    "gn:adm1_name":"Chibaken",
    "gn:adm2_name":"Funabashishi",
    "gn:name":"Nishinarashino",
    "iso:country":"JP",
    "wof:name":"274-0815",
    "wof:placetype":"postalcode"
},
  "geometry": {"coordinates":[140.0368,35.7223],"type":"Point"}
}