{
  "type": "Feature",
  "properties": {
    "gn:adm1_name":"Aichiken",
    "gn:adm2_name":"Kasugaishi",
    "gn:name":"Wakakusadoori",
    "iso:country":"JP",
    "wof:name":"486-0914",
    "wof:placetype":"postalcode"
},
  "geometry": {"coordinates":[136.95959999999999,35.2391],"type":"Point"}
}