{
  "type": "Feature",
  "properties": {
    "gn:adm1_name":"Ibarakiken",
    "gn:adm2_name":"Namegatagun'Asoumachi",
    "gn:name":"Aonuma",
    "iso:country":"JP",
    "wof:name":"311-3831",
    "wof:placetype":"postalcode"
},
  "geometry": {"coordinates":[140.5103,36.0306],"type":"Point"}
}