{
  "type": "Feature",
  "properties": {
    "gn:adm1_name":"Shizuokaken",
    "gn:adm2_name":"Fujiedashi",
    "gn:name":"Kiyosato",
    "iso:country":"JP",
    "wof:name":"426-0223",
    "wof:placetype":"postalcode"
},
  "geometry": {"coordinates":[138.26230000000001,34.8956],"type":"Point"}
}