{
  "type": "Feature",
  "properties": {
    "gn:adm1_name":"Okinawaken",
    "gn:adm2_name":"Itomanshi",
    "gn:name":"Uegusuku",
    "iso:country":"JP",
    "wof:name":"901-0332",
    "wof:placetype":"postalcode"
},
  "geometry": {"coordinates":[127.7045,26.1071],"type":"Point"}
}