{
  "type": "Feature",
  "properties": {
    "gn:adm1_name":"Hyougoken",
    "gn:adm2_name":"Takaradukashi",
    "gn:name":"Nigawadanchi",
    "iso:country":"JP",
    "wof:name":"665-0066",
    "wof:placetype":"postalcode"
},
  "geometry": {"coordinates":[135.3501,34.7803],"type":"Point"}
}