{
  "type": "Feature",
  "properties": {
    "gn:adm1_name":"Mieken",
    "gn:adm2_name":"Ayamagun'Ooyamadamura",
    "gn:name":"Okubano",
    "iso:country":"JP",
    "wof:name":"518-1427",
    "wof:placetype":"postalcode"
},
  "geometry": {"coordinates":[136.25620000000001,34.7325],"type":"Point"}
}