{
  "type": "Feature",
  "properties": {
    "gn:adm1_name":"Ibarakiken",
    "gn:adm2_name":"Tsukubashi",
    "gn:name":"Tsukuba",
    "iso:country":"JP",
    "wof:name":"300-4352",
    "wof:placetype":"postalcode"
},
  "geometry": {"coordinates":[140.09800000000001,36.2105],"type":"Point"}
}