{
  "type": "Feature",
  "properties": {
    "gn:adm1_name":"Yamagataken",
    "gn:adm2_name":"Sakatashi",
    "gn:name":"Kigawa",
    "iso:country":"JP",
    "wof:name":"999-7773",
    "wof:placetype":"postalcode"
},
  "geometry": {"coordinates":[139.87979999999999,38.8613],"type":"Point"}
}