{
  "type": "Feature",
  "properties": {
    "gn:adm1_name":"Niigataken",
    "gn:adm2_name":"Nagaokashi",
    "gn:name":"Horigane",
    "iso:country":"JP",
    "wof:name":"940-0868",
    "wof:placetype":"postalcode"
},
  "geometry": {"coordinates":[138.87350000000001,37.4608],"type":"Point"}
}