{
  "type": "Feature",
  "properties": {
    "gn:adm1_name":"Wakayamaken",
    "gn:adm2_name":"Kainanshi",
    "gn:name":"Minamiakasaka",
    "iso:country":"JP",
    "wof:name":"642-0017",
    "wof:placetype":"postalcode"
},
  "geometry": {"coordinates":[135.23949999999999,34.1582],"type":"Point"}
}