{
  "type": "Feature",
  "properties": {
    "gn:adm1_name":"Gifuken",
    "gn:adm2_name":"Oogakishi",
    "gn:name":"Tsumurachou",
    "iso:country":"JP",
    "wof:name":"503-0003",
    "wof:placetype":"postalcode"
},
  "geometry": {"coordinates":[136.64529999999999,35.382],"type":"Point"}
}