{
  "type": "Feature",
  "properties": {
    "gn:adm1_name":"Toyamaken",
    "gn:adm2_name":"Tonamishi",
    "gn:name":"Higashisaiwaichou",
    "iso:country":"JP",
    "wof:name":"939-1385",
    "wof:placetype":"postalcode"
},
  "geometry": {"coordinates":[136.96299999999999,36.6364],"type":"Point"}
}