{
  "type": "Feature",
  "properties": {
    "gn:adm1_name":"Niigataken",
    "gn:adm2_name":"Minamikanbaragunsakaemachi",
    "gn:name":"Wakamiyashinden",
    "iso:country":"JP",
    "wof:name":"959-1105",
    "wof:placetype":"postalcode"
},
  "geometry": {"coordinates":[138.92679999999999,37.5954],"type":"Point"}
}