{
  "type": "Feature",
  "properties": {
    "gn:adm1_name":"Mieken",
    "gn:adm2_name":"Nabarishi",
    "gn:name":"Kikyougaokaminami4banchou",
    "iso:country":"JP",
    "wof:name":"518-0634",
    "wof:placetype":"postalcode"
},
  "geometry": {"coordinates":[136.12569999999999,34.6345],"type":"Point"}
}