{
  "type": "Feature",
  "properties": {
    "gn:adm1_name":"Aichiken",
    "gn:adm2_name":"Tokonameshi",
    "gn:name":"Shinkaichou",
    "iso:country":"JP",
    "wof:name":"479-0837",
    "wof:placetype":"postalcode"
},
  "geometry": {"coordinates":[136.83330000000001,34.8877],"type":"Point"}
}