{
  "type": "Feature",
  "properties": {
    "gn:adm1_name":"Aichiken",
    "gn:adm2_name":"Nakashimagunheiwachou",
    "gn:name":"Toujou",
    "iso:country":"JP",
    "wof:name":"490-1321",
    "wof:placetype":"postalcode"
},
  "geometry": {"coordinates":[136.7474,35.2043],"type":"Point"}
}