{
  "type": "Feature",
  "properties": {
    "gn:adm1_name":"Niigataken",
    "gn:adm2_name":"Niitsushi",
    "gn:name":"Deto",
    "iso:country":"JP",
    "wof:name":"956-0046",
    "wof:placetype":"postalcode"
},
  "geometry": {"coordinates":[139.06780000000001,37.7855],"type":"Point"}
}