{
  "type": "Feature",
  "properties": {
    "gn:adm1_name":"Toukyouto",
    "gn:adm2_name":"Kitaku",
    "gn:name":"Nishigahara",
    "iso:country":"JP",
    "wof:name":"114-0024",
    "wof:placetype":"postalcode"
},
  "geometry": {"coordinates":[139.74109999999999,35.7435],"type":"Point"}
}