{
  "type": "Feature",
  "properties": {
    "gn:adm1_name":"Shimaneken",
    "gn:adm2_name":"Izumoshi",
    "gn:name":"Koshichou",
    "iso:country":"JP",
    "wof:name":"693-0031",
    "wof:placetype":"postalcode"
},
  "geometry": {"coordinates":[132.74209999999999,35.3401],"type":"Point"}
}