{
  "type": "Feature",
  "properties": {
    "gn:adm1_name":"Fukushimaken",
    "gn:adm2_name":"Oonumagunkaneyamamachi",
    "gn:name":"Tamanashi",
    "iso:country":"JP",
    "wof:name":"968-0014",
    "wof:placetype":"postalcode"
},
  "geometry": {"coordinates":[139.5488,37.4128],"type":"Point"}
}