{
  "type": "Feature",
  "properties": {
    "gn:adm1_name":"Kyoutofu",
    "gn:adm2_name":"Kyoutoshinishikyouku",
    "gn:name":"Yamadahakodukachou",
    "iso:country":"JP",
    "wof:name":"615-8255",
    "wof:placetype":"postalcode"
},
  "geometry": {"coordinates":[135.6857,34.9851],"type":"Point"}
}