{
  "type": "Feature",
  "properties": {
    "gn:adm1_name":"Chibaken",
    "gn:adm2_name":"Yachimatashi",
    "gn:name":"Yachimataro",
    "iso:country":"JP",
    "wof:name":"289-1144",
    "wof:placetype":"postalcode"
},
  "geometry": {"coordinates":[140.28219999999999,35.6705],"type":"Point"}
}