{
  "type": "Feature",
  "properties": {
    "gn:adm1_name":"Toukyouto",
    "gn:adm2_name":"Suginamiku",
    "gn:name":"Wada",
    "iso:country":"JP",
    "wof:name":"166-0012",
    "wof:placetype":"postalcode"
},
  "geometry": {"coordinates":[139.66,35.6928],"type":"Point"}
}