{
  "type": "Feature",
  "properties": {
    "gn:adm1_name":"Kouchiken",
    "gn:adm2_name":"Kamiguntosayamadachou",
    "gn:name":"Matsumoto",
    "iso:country":"JP",
    "wof:name":"782-0025",
    "wof:placetype":"postalcode"
},
  "geometry": {"coordinates":[133.67429999999999,33.5906],"type":"Point"}
}