{
  "type": "Feature",
  "properties": {
    "gn:adm1_name":"Aichiken",
    "gn:adm2_name":"Inuyamashi",
    "gn:name":"Gakudenkobari",
    "iso:country":"JP",
    "wof:name":"484-0841",
    "wof:placetype":"postalcode"
},
  "geometry": {"coordinates":[136.9564,35.3261],"type":"Point"}
}