{
  "type": "Feature",
  "properties": {
    "gn:adm1_name":"Niigataken",
    "gn:adm2_name":"Mitsukeshi",
    "gn:name":"Nikamachi",
    "iso:country":"JP",
    "wof:name":"954-0068",
    "wof:placetype":"postalcode"
},
  "geometry": {"coordinates":[138.90690000000001,37.5262],"type":"Point"}
}