{
  "type": "Feature",
  "properties": {
    "gn:adm1_name":"Hiroshimaken",
    "gn:adm2_name":"Higashihiroshimashi",
    "gn:name":"Shiwachoukanmuri",
    "iso:country":"JP",
    "wof:name":"739-0265",
    "wof:placetype":"postalcode"
},
  "geometry": {"coordinates":[132.6454,34.4606],"type":"Point"}
}