{
  "type": "Feature",
  "properties": {
    "gn:adm1_name":"Naraken",
    "gn:adm2_name":"Yoshinoguntenkawamura",
    "gn:name":"Komoriyama",
    "iso:country":"JP",
    "wof:name":"638-0551",
    "wof:placetype":"postalcode"
},
  "geometry": {"coordinates":[135.8023,34.1966],"type":"Point"}
}