{
  "type": "Feature",
  "properties": {
    "gn:adm1_name":"Fukushimaken",
    "gn:adm2_name":"Kawanumagun'Aidubangemachi",
    "gn:name":"Daidou",
    "iso:country":"JP",
    "wof:name":"969-6561",
    "wof:placetype":"postalcode"
},
  "geometry": {"coordinates":[139.8124,37.5679],"type":"Point"}
}