{
  "type": "Feature",
  "properties": {
    "gn:adm1_name":"Shimaneken",
    "gn:adm2_name":"Oochigunkawamotomachi",
    "gn:name":"Inbara",
    "iso:country":"JP",
    "wof:name":"696-0003",
    "wof:placetype":"postalcode"
},
  "geometry": {"coordinates":[132.4735,34.9654],"type":"Point"}
}