{
  "type": "Feature",
  "properties": {
    "gn:adm1_name":"Oosakafu",
    "gn:adm2_name":"Toyonakashi",
    "gn:name":"Kitamidorigaoka",
    "iso:country":"JP",
    "wof:name":"560-0001",
    "wof:placetype":"postalcode"
},
  "geometry": {"coordinates":[135.47739999999999,34.8182],"type":"Point"}
}