{
  "type": "Feature",
  "properties": {
    "gn:adm1_name":"Saitamaken",
    "gn:adm2_name":"Chichibugun'Arakawamura",
    "gn:name":"Kuna",
    "iso:country":"JP",
    "wof:name":"369-1801",
    "wof:placetype":"postalcode"
},
  "geometry": {"coordinates":[139.05770000000001,35.9632],"type":"Point"}
}