{
  "type": "Feature",
  "properties": {
    "gn:adm1_name":"Saitamaken",
    "gn:adm2_name":"Kumagayashi",
    "gn:name":"Takayanagi",
    "iso:country":"JP",
    "wof:name":"360-0855",
    "wof:placetype":"postalcode"
},
  "geometry": {"coordinates":[139.34299999999999,36.1731],"type":"Point"}
}