{
  "type": "Feature",
  "properties": {
    "gn:adm1_name":"Miyagiken",
    "gn:adm2_name":"Motoyoshigunmotoyoshichou",
    "gn:name":"Hayashinosawa",
    "iso:country":"JP",
    "wof:name":"988-0302",
    "wof:placetype":"postalcode"
},
  "geometry": {"coordinates":[141.51589999999999,38.8021],"type":"Point"}
}