{
  "type": "Feature",
  "properties": {
    "gn:adm1_name":"Aichiken",
    "gn:adm2_name":"Nagoyashimizuhoku",
    "gn:name":"Hakuryuuchou",
    "iso:country":"JP",
    "wof:name":"467-0826",
    "wof:placetype":"postalcode"
},
  "geometry": {"coordinates":[136.92830000000001,35.123],"type":"Point"}
}