{
  "type": "Feature",
  "properties": {
    "gn:adm1_name":"Hiroshimaken",
    "gn:adm2_name":"Hiroshimashinakaku",
    "gn:name":"Sakaimachi",
    "iso:country":"JP",
    "wof:name":"730-0853",
    "wof:placetype":"postalcode"
},
  "geometry": {"coordinates":[132.4469,34.3945],"type":"Point"}
}