{
  "type": "Feature",
  "properties": {
    "gn:adm1_name":"Kagoshimaken",
    "gn:adm2_name":"Kagoshimagunsakurajimachou",
    "gn:name":"Take",
    "iso:country":"JP",
    "wof:name":"891-1416",
    "wof:placetype":"postalcode"
},
  "geometry": {"coordinates":[130.61850000000001,31.6127],"type":"Point"}
}