{
  "type": "Feature",
  "properties": {
    "gn:adm1_name":"Fukushimaken",
    "gn:adm2_name":"Oonumagun'Aiduhongoumachi",
    "gn:name":"Hidoro",
    "iso:country":"JP",
    "wof:name":"969-6176",
    "wof:placetype":"postalcode"
},
  "geometry": {"coordinates":[139.8777,37.4602],"type":"Point"}
}