{
  "type": "Feature",
  "properties": {
    "gn:adm1_name":"Nagasakiken",
    "gn:adm2_name":"Kamiagatagunkamitsushimachou",
    "gn:name":"Ooura",
    "iso:country":"JP",
    "wof:name":"817-1722",
    "wof:placetype":"postalcode"
},
  "geometry": {"coordinates":[129.43620000000001,34.67],"type":"Point"}
}