{
  "type": "Feature",
  "properties": {
    "gn:adm1_name":"Aichiken",
    "gn:adm2_name":"Nishikamogun'Obaramura",
    "gn:name":"Oodaira",
    "iso:country":"JP",
    "wof:name":"470-0555",
    "wof:placetype":"postalcode"
},
  "geometry": {"coordinates":[137.24350000000001,35.2445],"type":"Point"}
}