{
  "type": "Feature",
  "properties": {
    "gn:adm1_name":"Saitamaken",
    "gn:adm2_name":"Iwatsukishi",
    "gn:name":"Haramachi",
    "iso:country":"JP",
    "wof:name":"339-0047",
    "wof:placetype":"postalcode"
},
  "geometry": {"coordinates":[139.69739999999999,35.9405],"type":"Point"}
}