{
  "type": "Feature",
  "properties": {
    "gn:adm1_name":"Oosakafu",
    "gn:adm2_name":"Izumishi",
    "gn:name":"Kuzunohachou",
    "iso:country":"JP",
    "wof:name":"594-0081",
    "wof:placetype":"postalcode"
},
  "geometry": {"coordinates":[135.43709999999999,34.5106],"type":"Point"}
}