{
  "type": "Feature",
  "properties": {
    "gn:adm1_name":"Hiroshimaken",
    "gn:adm2_name":"Jinsekigunyukichou",
    "gn:name":"Ono",
    "iso:country":"JP",
    "wof:name":"720-1901",
    "wof:placetype":"postalcode"
},
  "geometry": {"coordinates":[133.31139999999999,34.8332],"type":"Point"}
}