{
  "type": "Feature",
  "properties": {
    "gn:adm1_name":"Hyougoken",
    "gn:adm2_name":"Mikishi",
    "gn:name":"Shijimichouabuta",
    "iso:country":"JP",
    "wof:name":"673-0502",
    "wof:placetype":"postalcode"
},
  "geometry": {"coordinates":[135.02180000000001,34.7998],"type":"Point"}
}