{
  "type": "Feature",
  "properties": {
    "gn:adm1_name":"Aichiken",
    "gn:adm2_name":"Nishikamogun'Obaramura",
    "gn:name":"Kajiyashiki",
    "iso:country":"JP",
    "wof:name":"470-0533",
    "wof:placetype":"postalcode"
},
  "geometry": {"coordinates":[137.28729999999999,35.2255],"type":"Point"}
}