{
  "type": "Feature",
  "properties": {
    "gn:adm1_name":"Ibarakiken",
    "gn:adm2_name":"Tsukubashi",
    "gn:name":"Shimohiratsuka",
    "iso:country":"JP",
    "wof:name":"305-0813",
    "wof:placetype":"postalcode"
},
  "geometry": {"coordinates":[140.0907,36.0911],"type":"Point"}
}