{
  "type": "Feature",
  "properties": {
    "gn:adm1_name":"Okayamaken",
    "gn:adm2_name":"Tamanoshi",
    "gn:name":"Nagao",
    "iso:country":"JP",
    "wof:name":"706-0151",
    "wof:placetype":"postalcode"
},
  "geometry": {"coordinates":[133.88980000000001,34.4946],"type":"Point"}
}