{
  "type": "Feature",
  "properties": {
    "gn:adm1_name":"Okayamaken",
    "gn:adm2_name":"Maniwagun'Ochiaichou",
    "gn:name":"Kamiichize",
    "iso:country":"JP",
    "wof:name":"719-3141",
    "wof:placetype":"postalcode"
},
  "geometry": {"coordinates":[133.74979999999999,35.0329],"type":"Point"}
}