{
  "type": "Feature",
  "properties": {
    "gn:adm1_name":"Ishikawaken",
    "gn:adm2_name":"Kanazawashi",
    "gn:name":"Yakushimachi",
    "iso:country":"JP",
    "wof:name":"920-0174",
    "wof:placetype":"postalcode"
},
  "geometry": {"coordinates":[136.71690000000001,36.6021],"type":"Point"}
}