{
  "type": "Feature",
  "properties": {
    "gn:adm1_name":"Niigataken",
    "gn:adm2_name":"Shibatashi",
    "gn:name":"Higashimiyauchi",
    "iso:country":"JP",
    "wof:name":"959-2528",
    "wof:placetype":"postalcode"
},
  "geometry": {"coordinates":[139.3783,37.9596],"type":"Point"}
}