{
  "type": "Feature",
  "properties": {
    "gn:adm1_name":"Toyamaken",
    "gn:adm2_name":"Nakaniikawagunkamiichimachi",
    "gn:name":"Tsutsumidani",
    "iso:country":"JP",
    "wof:name":"930-0453",
    "wof:placetype":"postalcode"
},
  "geometry": {"coordinates":[137.3784,36.6901],"type":"Point"}
}