{
  "type": "Feature",
  "properties": {
    "gn:adm1_name":"Kagawaken",
    "gn:adm2_name":"Sakaideshi",
    "gn:name":"Ejirichou",
    "iso:country":"JP",
    "wof:name":"762-0011",
    "wof:placetype":"postalcode"
},
  "geometry": {"coordinates":[133.87299999999999,34.3199],"type":"Point"}
}