{
  "type": "Feature",
  "properties": {
    "gn:adm1_name":"Oosakafu",
    "gn:adm2_name":"Oosakashifukushimaku",
    "gn:name":"Ebie",
    "iso:country":"JP",
    "wof:name":"553-0001",
    "wof:placetype":"postalcode"
},
  "geometry": {"coordinates":[135.47219999999999,34.6976],"type":"Point"}
}