{
  "type": "Feature",
  "properties": {
    "gn:adm1_name":"Fukuiken",
    "gn:adm2_name":"Ooiguntakahamachou",
    "gn:name":"Wakamiya",
    "iso:country":"JP",
    "wof:name":"919-2227",
    "wof:placetype":"postalcode"
},
  "geometry": {"coordinates":[135.54499999999999,35.4909],"type":"Point"}
}