{
  "type": "Feature",
  "properties": {
    "gn:adm1_name":"Okayamaken",
    "gn:adm2_name":"Niimishi",
    "gn:name":"Kanaya",
    "iso:country":"JP",
    "wof:name":"718-0016",
    "wof:placetype":"postalcode"
},
  "geometry": {"coordinates":[133.46600000000001,34.9745],"type":"Point"}
}