{
  "type": "Feature",
  "properties": {
    "gn:adm1_name":"Naganoken",
    "gn:adm2_name":"Shimotakaigunnozawaonsenmura",
    "gn:name":"Nanagamaki",
    "iso:country":"JP",
    "wof:name":"389-2612",
    "wof:placetype":"postalcode"
},
  "geometry": {"coordinates":[138.46270000000001,36.973],"type":"Point"}
}