{
  "type": "Feature",
  "properties": {
    "gn:adm1_name":"Fukushimaken",
    "gn:adm2_name":"Kawanumagun'Aidubangemachi",
    "gn:name":"Niidate",
    "iso:country":"JP",
    "wof:name":"969-6505",
    "wof:placetype":"postalcode"
},
  "geometry": {"coordinates":[139.81229999999999,37.5711],"type":"Point"}
}