{
  "type": "Feature",
  "properties": {
    "gn:adm1_name":"Kouchiken",
    "gn:adm2_name":"Kouchishi",
    "gn:name":"Inarichou",
    "iso:country":"JP",
    "wof:name":"780-0814",
    "wof:placetype":"postalcode"
},
  "geometry": {"coordinates":[133.55959999999999,33.5559],"type":"Point"}
}