{
  "type": "Feature",
  "properties": {
    "gn:adm1_name":"Fukushimaken",
    "gn:adm2_name":"Oonumagunmishimamachi",
    "gn:name":"Miyashita",
    "iso:country":"JP",
    "wof:name":"969-7511",
    "wof:placetype":"postalcode"
},
  "geometry": {"coordinates":[139.64449999999999,37.4713],"type":"Point"}
}