{
  "type": "Feature",
  "properties": {
    "gn:adm1_name":"Gunmaken",
    "gn:adm2_name":"Sawagunsakaimachi",
    "gn:name":"Nakajima",
    "iso:country":"JP",
    "wof:name":"370-0133",
    "wof:placetype":"postalcode"
},
  "geometry": {"coordinates":[139.25129999999999,36.2654],"type":"Point"}
}