{
  "type": "Feature",
  "properties": {
    "gn:adm1_name":"Shizuokaken",
    "gn:adm2_name":"Tagatagunnirayamachou",
    "gn:name":"Tachibanadai",
    "iso:country":"JP",
    "wof:name":"410-2111",
    "wof:placetype":"postalcode"
},
  "geometry": {"coordinates":[138.95230000000001,35.022],"type":"Point"}
}