{
  "type": "Feature",
  "properties": {
    "gn:adm1_name":"Kyoutofu",
    "gn:adm2_name":"Kumanogunkumihamachou",
    "gn:name":"Niidani",
    "iso:country":"JP",
    "wof:name":"629-3572",
    "wof:placetype":"postalcode"
},
  "geometry": {"coordinates":[134.93940000000001,35.5765],"type":"Point"}
}