{
  "type": "Feature",
  "properties": {
    "gn:adm1_name":"Kouchiken",
    "gn:adm2_name":"Takaokagunsakawachou",
    "gn:name":"Minekou",
    "iso:country":"JP",
    "wof:name":"789-1225",
    "wof:placetype":"postalcode"
},
  "geometry": {"coordinates":[133.21379999999999,33.4973],"type":"Point"}
}