{
  "type": "Feature",
  "properties": {
    "gn:adm1_name":"Oosakafu",
    "gn:adm2_name":"Higashioosakashi",
    "gn:name":"Takaidamotomachi",
    "iso:country":"JP",
    "wof:name":"577-0054",
    "wof:placetype":"postalcode"
},
  "geometry": {"coordinates":[135.57490000000001,34.6664],"type":"Point"}
}