{
  "type": "Feature",
  "properties": {
    "gn:adm1_name":"Yamaguchiken",
    "gn:adm2_name":"Kumageguntabusechou",
    "gn:name":"Shukui",
    "iso:country":"JP",
    "wof:name":"742-1503",
    "wof:placetype":"postalcode"
},
  "geometry": {"coordinates":[132.02289999999999,33.9735],"type":"Point"}
}