{
  "type": "Feature",
  "properties": {
    "gn:adm1_name":"Shigaken",
    "gn:adm2_name":"Oumihachimanshi",
    "gn:name":"Enamichou",
    "iso:country":"JP",
    "wof:name":"523-0832",
    "wof:placetype":"postalcode"
},
  "geometry": {"coordinates":[136.0933,35.14],"type":"Point"}
}