{
  "type": "Feature",
  "properties": {
    "gn:adm1_name":"Sagaken",
    "gn:adm2_name":"Miyakigunminechou",
    "gn:name":"Higashitsu",
    "iso:country":"JP",
    "wof:name":"840-1104",
    "wof:placetype":"postalcode"
},
  "geometry": {"coordinates":[130.4186,33.276],"type":"Point"}
}