{
  "type": "Feature",
  "properties": {
    "gn:adm1_name":"Gunmaken",
    "gn:adm2_name":"Takasakishi",
    "gn:name":"Shiroganechou",
    "iso:country":"JP",
    "wof:name":"370-0825",
    "wof:placetype":"postalcode"
},
  "geometry": {"coordinates":[139.00810000000001,36.3258],"type":"Point"}
}