{
  "type": "Feature",
  "properties": {
    "gn:adm1_name":"Miyagiken",
    "gn:adm2_name":"Iwanumashi",
    "gn:name":"Byoudou",
    "iso:country":"JP",
    "wof:name":"989-2457",
    "wof:placetype":"postalcode"
},
  "geometry": {"coordinates":[140.8434,38.1131],"type":"Point"}
}