{
  "type": "Feature",
  "properties": {
    "gn:adm1_name":"Kagawaken",
    "gn:adm2_name":"Shouzuguntonoshouchou",
    "gn:name":"Koumagoe",
    "iso:country":"JP",
    "wof:name":"761-4153",
    "wof:placetype":"postalcode"
},
  "geometry": {"coordinates":[134.21369999999999,34.5074],"type":"Point"}
}