{
  "type": "Feature",
  "properties": {
    "gn:adm1_name":"Miyagiken",
    "gn:adm2_name":"Kesennumashi",
    "gn:name":"Bentenchou",
    "iso:country":"JP",
    "wof:name":"988-0036",
    "wof:placetype":"postalcode"
},
  "geometry": {"coordinates":[141.58070000000001,38.8957],"type":"Point"}
}