{
  "type": "Feature",
  "properties": {
    "gn:adm1_name":"Yamaguchiken",
    "gn:adm2_name":"Shuunanshi",
    "gn:name":"Tokuyama(Sonota)",
    "iso:country":"JP",
    "wof:name":"745-0851",
    "wof:placetype":"postalcode"
},
  "geometry": {"coordinates":[131.8158,34.0624],"type":"Point"}
}