{
  "type": "Feature",
  "properties": {
    "gn:adm1_name":"Ehimeken",
    "gn:adm2_name":"Ochigunyoshiumichou",
    "gn:name":"Tanoura",
    "iso:country":"JP",
    "wof:name":"794-2101",
    "wof:placetype":"postalcode"
},
  "geometry": {"coordinates":[133.0291,34.1847],"type":"Point"}
}