{
  "type": "Feature",
  "properties": {
    "gn:adm1_name":"Fukushimaken",
    "gn:adm2_name":"Sukagawashi",
    "gn:name":"Oobukuromachi",
    "iso:country":"JP",
    "wof:name":"962-0032",
    "wof:placetype":"postalcode"
},
  "geometry": {"coordinates":[140.3579,37.2841],"type":"Point"}
}