{
  "type": "Feature",
  "properties": {
    "gn:adm1_name":"Chibaken",
    "gn:adm2_name":"Katorigunkouzakimachi",
    "gn:name":"Shikinooka",
    "iso:country":"JP",
    "wof:name":"289-0204",
    "wof:placetype":"postalcode"
},
  "geometry": {"coordinates":[140.4144,35.8891],"type":"Point"}
}