{
  "type": "Feature",
  "properties": {
    "gn:adm1_name":"Nagasakiken",
    "gn:adm2_name":"Matsuurashi",
    "gn:name":"Imafukuchoutobishimamen",
    "iso:country":"JP",
    "wof:name":"859-4529",
    "wof:placetype":"postalcode"
},
  "geometry": {"coordinates":[129.7782,33.3959],"type":"Point"}
}