{
  "type": "Feature",
  "properties": {
    "gn:adm1_name":"Kyoutofu",
    "gn:adm2_name":"Fukuchiyamashi",
    "gn:name":"Higashihonmachi",
    "iso:country":"JP",
    "wof:name":"620-0047",
    "wof:placetype":"postalcode"
},
  "geometry": {"coordinates":[135.12049999999999,35.3002],"type":"Point"}
}