{
  "type": "Feature",
  "properties": {
    "gn:adm1_name":"Okayamaken",
    "gn:adm2_name":"Mitsugunkamogawachou",
    "gn:name":"Hosoda",
    "iso:country":"JP",
    "wof:name":"709-2421",
    "wof:placetype":"postalcode"
},
  "geometry": {"coordinates":[133.7809,34.8962],"type":"Point"}
}