{
  "type": "Feature",
  "properties": {
    "gn:adm1_name":"Hiroshimaken",
    "gn:adm2_name":"Fuchuushi",
    "gn:name":"Kawasachou",
    "iso:country":"JP",
    "wof:name":"729-3221",
    "wof:placetype":"postalcode"
},
  "geometry": {"coordinates":[133.1917,34.5912],"type":"Point"}
}