{
  "type": "Feature",
  "properties": {
    "gn:adm1_name":"Niigataken",
    "gn:adm2_name":"Minamikanbaragunsakaemachi",
    "gn:name":"Senbanoshinden",
    "iso:country":"JP",
    "wof:name":"959-1124",
    "wof:placetype":"postalcode"
},
  "geometry": {"coordinates":[138.90190000000001,37.5797],"type":"Point"}
}