{
  "type": "Feature",
  "properties": {
    "gn:adm1_name":"Miyagiken",
    "gn:adm2_name":"Toodagunwakuyachou",
    "gn:name":"Nagaechou",
    "iso:country":"JP",
    "wof:name":"987-0143",
    "wof:placetype":"postalcode"
},
  "geometry": {"coordinates":[141.1344,38.5373],"type":"Point"}
}