{
  "type": "Feature",
  "properties": {
    "gn:adm1_name":"Yamagataken",
    "gn:adm2_name":"Kaminoyamashi",
    "gn:name":"Asahidai",
    "iso:country":"JP",
    "wof:name":"999-3164",
    "wof:placetype":"postalcode"
},
  "geometry": {"coordinates":[140.2825,38.1688],"type":"Point"}
}