{
  "type": "Feature",
  "properties": {
    "gn:adm1_name":"Kyoutofu",
    "gn:adm2_name":"Kyoutoshiukyouku",
    "gn:name":"Hanazonouchihatachou",
    "iso:country":"JP",
    "wof:name":"616-8045",
    "wof:placetype":"postalcode"
},
  "geometry": {"coordinates":[135.715,35.0185],"type":"Point"}
}