{
  "type": "Feature",
  "properties": {
    "gn:adm1_name":"Hiroshimaken",
    "gn:adm2_name":"Hiroshimashinishiku",
    "gn:name":"Mitakiyama",
    "iso:country":"JP",
    "wof:name":"733-0805",
    "wof:placetype":"postalcode"
},
  "geometry": {"coordinates":[132.43799999999999,34.4207],"type":"Point"}
}