{
  "type": "Feature",
  "properties": {
    "gn:adm1_name":"Kumamotoken",
    "gn:adm2_name":"Kikuchigun'Oodumachi",
    "gn:name":"Oobayashi",
    "iso:country":"JP",
    "wof:name":"869-1219",
    "wof:placetype":"postalcode"
},
  "geometry": {"coordinates":[130.9135,32.8723],"type":"Point"}
}