{
  "type": "Feature",
  "properties": {
    "gn:adm1_name":"Ishikawaken",
    "gn:adm2_name":"Komatsushi",
    "gn:name":"Ogoyamachi",
    "iso:country":"JP",
    "wof:name":"923-0172",
    "wof:placetype":"postalcode"
},
  "geometry": {"coordinates":[136.5316,36.2992],"type":"Point"}
}