{
  "type": "Feature",
  "properties": {
    "gn:adm1_name":"Wakayamaken",
    "gn:adm2_name":"Higashimurogunhonguuchou",
    "gn:name":"Fushiogami",
    "iso:country":"JP",
    "wof:name":"647-1743",
    "wof:placetype":"postalcode"
},
  "geometry": {"coordinates":[135.75839999999999,33.8657],"type":"Point"}
}