{
  "type": "Feature",
  "properties": {
    "gn:adm1_name":"Ibarakiken",
    "gn:adm2_name":"Inashikigun'Amimachi",
    "gn:name":"Oogata",
    "iso:country":"JP",
    "wof:name":"300-0323",
    "wof:placetype":"postalcode"
},
  "geometry": {"coordinates":[140.2688,35.9899],"type":"Point"}
}