{
  "type": "Feature",
  "properties": {
    "gn:adm1_name":"Fukuokaken",
    "gn:adm2_name":"Maebarushi",
    "gn:name":"Kamiari",
    "iso:country":"JP",
    "wof:name":"819-1123",
    "wof:placetype":"postalcode"
},
  "geometry": {"coordinates":[130.17449999999999,33.544],"type":"Point"}
}