{
  "type": "Feature",
  "properties": {
    "gn:adm1_name":"Aichiken",
    "gn:adm2_name":"Okazakishi",
    "gn:name":"Shounachou",
    "iso:country":"JP",
    "wof:name":"444-0221",
    "wof:placetype":"postalcode"
},
  "geometry": {"coordinates":[137.13229999999999,34.8919],"type":"Point"}
}