{
  "type": "Feature",
  "properties": {
    "gn:adm1_name":"Yamagataken",
    "gn:adm2_name":"Sakatashi",
    "gn:name":"Tegurada",
    "iso:country":"JP",
    "wof:name":"998-0811",
    "wof:placetype":"postalcode"
},
  "geometry": {"coordinates":[139.90600000000001,38.9143],"type":"Point"}
}