{
  "type": "Feature",
  "properties": {
    "gn:adm1_name":"Niigataken",
    "gn:adm2_name":"Sadogun'Aikawamachi",
    "gn:name":"Kitaebisu",
    "iso:country":"JP",
    "wof:name":"952-2133",
    "wof:placetype":"postalcode"
},
  "geometry": {"coordinates":[138.25569999999999,38.0933],"type":"Point"}
}