{
  "type": "Feature",
  "properties": {
    "gn:adm1_name":"Oosakafu",
    "gn:adm2_name":"Toyonoguntoyonochou",
    "gn:name":"Yoshikawa",
    "iso:country":"JP",
    "wof:name":"563-0101",
    "wof:placetype":"postalcode"
},
  "geometry": {"coordinates":[135.4451,34.913],"type":"Point"}
}