{
  "type": "Feature",
  "properties": {
    "gn:adm1_name":"Kumamotoken",
    "gn:adm2_name":"Utoshi",
    "gn:name":"Uratamachi",
    "iso:country":"JP",
    "wof:name":"869-0445",
    "wof:placetype":"postalcode"
},
  "geometry": {"coordinates":[130.65819999999999,32.6862],"type":"Point"}
}