{
  "type": "Feature",
  "properties": {
    "gn:adm1_name":"Hyougoken",
    "gn:adm2_name":"Koubeshinagataku",
    "gn:name":"Ichiriyamachou",
    "iso:country":"JP",
    "wof:name":"653-0878",
    "wof:placetype":"postalcode"
},
  "geometry": {"coordinates":[135.13210000000001,34.6865],"type":"Point"}
}