{
  "type": "Feature",
  "properties": {
    "gn:adm1_name":"Gifuken",
    "gn:adm2_name":"Nakatsugawashi",
    "gn:name":"Yodogawachou",
    "iso:country":"JP",
    "wof:name":"508-0034",
    "wof:placetype":"postalcode"
},
  "geometry": {"coordinates":[137.5069,35.4987],"type":"Point"}
}