{
  "type": "Feature",
  "properties": {
    "gn:adm1_name":"Mieken",
    "gn:adm2_name":"Wataraigun'Obatachou",
    "gn:name":"Miyamae",
    "iso:country":"JP",
    "wof:name":"519-0504",
    "wof:placetype":"postalcode"
},
  "geometry": {"coordinates":[136.67590000000001,34.4955],"type":"Point"}
}