{
  "type": "Feature",
  "properties": {
    "gn:adm1_name":"Niigataken",
    "gn:adm2_name":"Higashikubikigun'Uragawaramura",
    "gn:name":"Tsubono",
    "iso:country":"JP",
    "wof:name":"942-0325",
    "wof:placetype":"postalcode"
},
  "geometry": {"coordinates":[138.4101,37.1115],"type":"Point"}
}