{
  "type": "Feature",
  "properties": {
    "gn:adm1_name":"Fukuokaken",
    "gn:adm2_name":"Miigunkitanomachi",
    "gn:name":"Nakashima",
    "iso:country":"JP",
    "wof:name":"830-1105",
    "wof:placetype":"postalcode"
},
  "geometry": {"coordinates":[130.5924,33.3416],"type":"Point"}
}