{
  "type": "Feature",
  "properties": {
    "gn:adm1_name":"Ibarakiken",
    "gn:adm2_name":"Nakagunnakamachi",
    "gn:name":"Ikanikeisaiganaibaai",
    "iso:country":"JP",
    "wof:name":"311-0100",
    "wof:placetype":"postalcode"
},
  "geometry": {"coordinates":[140.42250000000001,36.5017],"type":"Point"}
}