{
  "type": "Feature",
  "properties": {
    "gn:adm1_name":"Kyoutofu",
    "gn:adm2_name":"Kyoutoshishimogyouku",
    "gn:name":"Takatsujinishinotouinchou",
    "iso:country":"JP",
    "wof:name":"600-8465",
    "wof:placetype":"postalcode"
},
  "geometry": {"coordinates":[135.7552,34.9994],"type":"Point"}
}