{
  "type": "Feature",
  "properties": {
    "gn:adm1_name":"Ishikawaken",
    "gn:adm2_name":"Ishikawaguntorigoemura",
    "gn:name":"Mitsuse",
    "iso:country":"JP",
    "wof:name":"920-2354",
    "wof:placetype":"postalcode"
},
  "geometry": {"coordinates":[136.5975,36.3047],"type":"Point"}
}