{
  "type": "Feature",
  "properties": {
    "gn:adm1_name":"Kanagawaken",
    "gn:adm2_name":"Atsugishi",
    "gn:name":"Morinosatoaoyama",
    "iso:country":"JP",
    "wof:name":"243-0123",
    "wof:placetype":"postalcode"
},
  "geometry": {"coordinates":[139.3109,35.4496],"type":"Point"}
}