{
  "type": "Feature",
  "properties": {
    "gn:adm1_name":"Kyoutofu",
    "gn:adm2_name":"Kyoutoshisakyouku",
    "gn:name":"Joudojiminamidachou",
    "iso:country":"JP",
    "wof:name":"606-8403",
    "wof:placetype":"postalcode"
},
  "geometry": {"coordinates":[135.79679999999999,35.0256],"type":"Point"}
}