{
  "type": "Feature",
  "properties": {
    "gn:adm1_name":"Yamanashiken",
    "gn:adm2_name":"Tsurushi",
    "gn:name":"Shishidome",
    "iso:country":"JP",
    "wof:name":"402-0032",
    "wof:placetype":"postalcode"
},
  "geometry": {"coordinates":[138.87739999999999,35.5243],"type":"Point"}
}