{
  "type": "Feature",
  "properties": {
    "gn:adm1_name":"Toyamaken",
    "gn:adm2_name":"Kaminiikawagun'Oosawanomachi",
    "gn:name":"Yokodoi",
    "iso:country":"JP",
    "wof:name":"939-2216",
    "wof:placetype":"postalcode"
},
  "geometry": {"coordinates":[137.21899999999999,36.5716],"type":"Point"}
}