{
  "type": "Feature",
  "properties": {
    "gn:adm1_name":"Naganoken",
    "gn:adm2_name":"Komoroshi",
    "gn:name":"Ikenomae",
    "iso:country":"JP",
    "wof:name":"384-0096",
    "wof:placetype":"postalcode"
},
  "geometry": {"coordinates":[138.4639,36.3005],"type":"Point"}
}