{
  "type": "Feature",
  "properties": {
    "gn:adm1_name":"Fukuiken",
    "gn:adm2_name":"Fukuishi",
    "gn:name":"Sugayachou",
    "iso:country":"JP",
    "wof:name":"910-0035",
    "wof:placetype":"postalcode"
},
  "geometry": {"coordinates":[136.1908,36.0745],"type":"Point"}
}