{
  "type": "Feature",
  "properties": {
    "gn:adm1_name":"Oosakafu",
    "gn:adm2_name":"Yaoshi",
    "gn:name":"Taishidou",
    "iso:country":"JP",
    "wof:name":"581-0063",
    "wof:placetype":"postalcode"
},
  "geometry": {"coordinates":[135.5866,34.6156],"type":"Point"}
}