{
  "type": "Feature",
  "properties": {
    "gn:adm1_name":"Hyougoken",
    "gn:adm2_name":"Takasagoshi",
    "gn:name":"Araichouotabi",
    "iso:country":"JP",
    "wof:name":"676-0005",
    "wof:placetype":"postalcode"
},
  "geometry": {"coordinates":[134.79480000000001,34.7636],"type":"Point"}
}