{
  "type": "Feature",
  "properties": {
    "gn:adm1_name":"Hiroshimaken",
    "gn:adm2_name":"Kureshi",
    "gn:name":"Nishishioyachou",
    "iso:country":"JP",
    "wof:name":"737-0838",
    "wof:placetype":"postalcode"
},
  "geometry": {"coordinates":[132.54040000000001,34.2497],"type":"Point"}
}