{
  "type": "Feature",
  "properties": {
    "gn:adm1_name":"Niigataken",
    "gn:adm2_name":"Itoigawashi",
    "gn:name":"Shintetsu",
    "iso:country":"JP",
    "wof:name":"941-0065",
    "wof:placetype":"postalcode"
},
  "geometry": {"coordinates":[137.85769999999999,37.0413],"type":"Point"}
}