{
  "type": "Feature",
  "properties": {
    "gn:adm1_name":"Fukushimaken",
    "gn:adm2_name":"Oonumagunniitsurumura",
    "gn:name":"Wadame",
    "iso:country":"JP",
    "wof:name":"969-6401",
    "wof:placetype":"postalcode"
},
  "geometry": {"coordinates":[139.83240000000001,37.5267],"type":"Point"}
}