{
  "type": "Feature",
  "properties": {
    "gn:adm1_name":"Shizuokaken",
    "gn:adm2_name":"Fujiedashi",
    "gn:name":"Kamiyabuta",
    "iso:country":"JP",
    "wof:name":"426-0202",
    "wof:placetype":"postalcode"
},
  "geometry": {"coordinates":[138.25399999999999,34.8918],"type":"Point"}
}