{
  "type": "Feature",
  "properties": {
    "gn:adm1_name":"Kouchiken",
    "gn:adm2_name":"Agawagun'Agawamura",
    "gn:name":"Kita",
    "iso:country":"JP",
    "wof:name":"781-1754",
    "wof:placetype":"postalcode"
},
  "geometry": {"coordinates":[133.1506,33.5735],"type":"Point"}
}