{
  "type": "Feature",
  "properties": {
    "gn:adm1_name":"Fukushimaken",
    "gn:adm2_name":"Fukushimashi",
    "gn:name":"Nekobuchi",
    "iso:country":"JP",
    "wof:name":"960-8233",
    "wof:placetype":"postalcode"
},
  "geometry": {"coordinates":[140.47900000000001,37.7788],"type":"Point"}
}