{
  "type": "Feature",
  "properties": {
    "gn:adm1_name":"Tochigiken",
    "gn:adm2_name":"Utsunomiyashi",
    "gn:name":"Nishiosakabemachi",
    "iso:country":"JP",
    "wof:name":"321-0917",
    "wof:placetype":"postalcode"
},
  "geometry": {"coordinates":[139.9282,36.499],"type":"Point"}
}