{
  "type": "Feature",
  "properties": {
    "gn:adm1_name":"Shimaneken",
    "gn:adm2_name":"Masudashi",
    "gn:name":"Doichou",
    "iso:country":"JP",
    "wof:name":"698-0016",
    "wof:placetype":"postalcode"
},
  "geometry": {"coordinates":[131.85599999999999,34.6696],"type":"Point"}
}