{
  "type": "Feature",
  "properties": {
    "gn:adm1_name":"Tochigiken",
    "gn:adm2_name":"Nasugunyudukamimura",
    "gn:name":"Hiruhata",
    "iso:country":"JP",
    "wof:name":"324-0411",
    "wof:placetype":"postalcode"
},
  "geometry": {"coordinates":[140.09719999999999,36.8028],"type":"Point"}
}