{
  "type": "Feature",
  "properties": {
    "gn:adm1_name":"Ibarakiken",
    "gn:adm2_name":"Tsukubashi",
    "gn:name":"Umegaoka",
    "iso:country":"JP",
    "wof:name":"300-1275",
    "wof:placetype":"postalcode"
},
  "geometry": {"coordinates":[140.09190000000001,35.9864],"type":"Point"}
}