{
  "type": "Feature",
  "properties": {
    "gn:adm1_name":"Tokushimaken",
    "gn:adm2_name":"Awagun'Awachou",
    "gn:name":"Ikanikeisaiganaibaai",
    "iso:country":"JP",
    "wof:name":"771-1700",
    "wof:placetype":"postalcode"
},
  "geometry": {"coordinates":[134.34989999999999,34.1131],"type":"Point"}
}