{
  "type": "Feature",
  "properties": {
    "gn:adm1_name":"Shigaken",
    "gn:adm2_name":"Inukamiguntagachou",
    "gn:name":"Narasaki",
    "iso:country":"JP",
    "wof:name":"522-0336",
    "wof:placetype":"postalcode"
},
  "geometry": {"coordinates":[136.28970000000001,35.1974],"type":"Point"}
}