{
  "type": "Feature",
  "properties": {
    "gn:adm1_name":"Tottoriken",
    "gn:adm2_name":"Kurayoshishi",
    "gn:name":"Kamogawachou",
    "iso:country":"JP",
    "wof:name":"682-0923",
    "wof:placetype":"postalcode"
},
  "geometry": {"coordinates":[133.81120000000001,35.4355],"type":"Point"}
}