{
  "type": "Feature",
  "properties": {
    "gn:adm1_name":"Ibarakiken",
    "gn:adm2_name":"Mitoshi",
    "gn:name":"Hirasuchou",
    "iso:country":"JP",
    "wof:name":"310-0853",
    "wof:placetype":"postalcode"
},
  "geometry": {"coordinates":[140.4341,36.3279],"type":"Point"}
}