{
  "type": "Feature",
  "properties": {
    "gn:adm1_name":"Aichiken",
    "gn:adm2_name":"Kariyashi",
    "gn:name":"Yabachou",
    "iso:country":"JP",
    "wof:name":"448-0035",
    "wof:placetype":"postalcode"
},
  "geometry": {"coordinates":[136.9984,34.9973],"type":"Point"}
}