{
  "type": "Feature",
  "properties": {
    "gn:adm1_name":"Toukyouto",
    "gn:adm2_name":"Shinagawaku",
    "gn:name":"Yashio",
    "iso:country":"JP",
    "wof:name":"140-0003",
    "wof:placetype":"postalcode"
},
  "geometry": {"coordinates":[139.756,35.6003],"type":"Point"}
}