{
  "type": "Feature",
  "properties": {
    "gn:adm1_name":"Kyoutofu",
    "gn:adm2_name":"Kyoutoshiminamiku",
    "gn:name":"Higashikujouhigashimatsunokichou",
    "iso:country":"JP",
    "wof:name":"601-8029",
    "wof:placetype":"postalcode"
},
  "geometry": {"coordinates":[135.76560000000001,34.975],"type":"Point"}
}