{
  "type": "Feature",
  "properties": {
    "gn:adm1_name":"Niigataken",
    "gn:adm2_name":"Kariwagun'Ogunimachi",
    "gn:name":"Aramachi",
    "iso:country":"JP",
    "wof:name":"949-5215",
    "wof:placetype":"postalcode"
},
  "geometry": {"coordinates":[138.70609999999999,37.2919],"type":"Point"}
}