{
  "type": "Feature",
  "properties": {
    "gn:adm1_name":"Tochigiken",
    "gn:adm2_name":"Nasugunshiobaramachi",
    "gn:name":"Shimooonuki",
    "iso:country":"JP",
    "wof:name":"329-2815",
    "wof:placetype":"postalcode"
},
  "geometry": {"coordinates":[139.9289,36.8803],"type":"Point"}
}