{
  "type": "Feature",
  "properties": {
    "gn:adm1_name":"Aichiken",
    "gn:adm2_name":"Atsumigun'Atsumichou",
    "gn:name":"Kameyama",
    "iso:country":"JP",
    "wof:name":"441-3625",
    "wof:placetype":"postalcode"
},
  "geometry": {"coordinates":[137.06739999999999,34.6089],"type":"Point"}
}