{
  "type": "Feature",
  "properties": {
    "gn:adm1_name":"Oosakafu",
    "gn:adm2_name":"Toyonogunnosechou",
    "gn:name":"Koyama",
    "iso:country":"JP",
    "wof:name":"563-0367",
    "wof:placetype":"postalcode"
},
  "geometry": {"coordinates":[135.3828,34.965],"type":"Point"}
}