{
  "type": "Feature",
  "properties": {
    "gn:adm1_name":"Yamagataken",
    "gn:adm2_name":"Higashimurayamagunyamanobemachi",
    "gn:name":"Yanazawa",
    "iso:country":"JP",
    "wof:name":"990-0351",
    "wof:placetype":"postalcode"
},
  "geometry": {"coordinates":[140.19409999999999,38.2628],"type":"Point"}
}