{
  "type": "Feature",
  "properties": {
    "gn:adm1_name":"Aichiken",
    "gn:adm2_name":"Nagoyashikitaku",
    "gn:name":"Meijou",
    "iso:country":"JP",
    "wof:name":"462-0846",
    "wof:placetype":"postalcode"
},
  "geometry": {"coordinates":[136.90479999999999,35.1902],"type":"Point"}
}