{
  "type": "Feature",
  "properties": {
    "gn:adm1_name":"Tokushimaken",
    "gn:adm2_name":"Narutoshi",
    "gn:name":"Muyachoutateiwa",
    "iso:country":"JP",
    "wof:name":"772-0017",
    "wof:placetype":"postalcode"
},
  "geometry": {"coordinates":[134.6174,34.1723],"type":"Point"}
}