{
  "type": "Feature",
  "properties": {
    "gn:adm1_name":"Ishikawaken",
    "gn:adm2_name":"Mattoushi",
    "gn:name":"Miyamarumachi",
    "iso:country":"JP",
    "wof:name":"924-0033",
    "wof:placetype":"postalcode"
},
  "geometry": {"coordinates":[136.55080000000001,36.5071],"type":"Point"}
}