{
  "type": "Feature",
  "properties": {
    "gn:adm1_name":"Aichiken",
    "gn:adm2_name":"Takahamashi",
    "gn:name":"Yoshikawachou",
    "iso:country":"JP",
    "wof:name":"444-1335",
    "wof:placetype":"postalcode"
},
  "geometry": {"coordinates":[136.9838,34.9378],"type":"Point"}
}