{
  "type": "Feature",
  "properties": {
    "gn:adm1_name":"Nagasakiken",
    "gn:adm2_name":"Hiradoshi",
    "gn:name":"Ooshijikichou",
    "iso:country":"JP",
    "wof:name":"859-5532",
    "wof:placetype":"postalcode"
},
  "geometry": {"coordinates":[129.39400000000001,33.2025],"type":"Point"}
}