{
  "type": "Feature",
  "properties": {
    "gn:adm1_name":"Fukuokaken",
    "gn:adm2_name":"Chikugoshi",
    "gn:name":"Kamikitajima",
    "iso:country":"JP",
    "wof:name":"833-0033",
    "wof:placetype":"postalcode"
},
  "geometry": {"coordinates":[130.4923,33.1976],"type":"Point"}
}