{
  "type": "Feature",
  "properties": {
    "gn:adm1_name":"Yamanashiken",
    "gn:adm2_name":"Nishiyatsushirogunshimobechou",
    "gn:name":"Kirifusagi",
    "iso:country":"JP",
    "wof:name":"409-3115",
    "wof:placetype":"postalcode"
},
  "geometry": {"coordinates":[138.49700000000001,35.481],"type":"Point"}
}