{
  "type": "Feature",
  "properties": {
    "gn:adm1_name":"Yamaguchiken",
    "gn:adm2_name":"Shuunanshi",
    "gn:name":"Shiigichou",
    "iso:country":"JP",
    "wof:name":"746-0008",
    "wof:placetype":"postalcode"
},
  "geometry": {"coordinates":[131.78139999999999,34.0665],"type":"Point"}
}