{
  "type": "Feature",
  "properties": {
    "gn:adm1_name":"Wakayamaken",
    "gn:adm2_name":"Wakayamashi",
    "gn:name":"Shingyomachi",
    "iso:country":"JP",
    "wof:name":"640-8074",
    "wof:placetype":"postalcode"
},
  "geometry": {"coordinates":[135.17359999999999,34.2419],"type":"Point"}
}