{
  "type": "Feature",
  "properties": {
    "gn:adm1_name":"Toukyouto",
    "gn:adm2_name":"Fuchuushi",
    "gn:name":"Miyoshichou",
    "iso:country":"JP",
    "wof:name":"183-0045",
    "wof:placetype":"postalcode"
},
  "geometry": {"coordinates":[139.4665,35.6729],"type":"Point"}
}