{
  "type": "Feature",
  "properties": {
    "gn:adm1_name":"Nagasakiken",
    "gn:adm2_name":"Nagasakishi",
    "gn:name":"Kozonemachi",
    "iso:country":"JP",
    "wof:name":"850-0937",
    "wof:placetype":"postalcode"
},
  "geometry": {"coordinates":[129.8672,32.7339],"type":"Point"}
}