{
  "type": "Feature",
  "properties": {
    "gn:adm1_name":"Shigaken",
    "gn:adm2_name":"Oumihachimanshi",
    "gn:name":"Okishimachou",
    "iso:country":"JP",
    "wof:name":"523-0801",
    "wof:placetype":"postalcode"
},
  "geometry": {"coordinates":[136.0564,35.2005],"type":"Point"}
}