{
  "type": "Feature",
  "properties": {
    "gn:adm1_name":"Nagasakiken",
    "gn:adm2_name":"Kitamatsuuraguntakashimachou",
    "gn:name":"Kuroshimamen",
    "iso:country":"JP",
    "wof:name":"859-4309",
    "wof:placetype":"postalcode"
},
  "geometry": {"coordinates":[129.72380000000001,33.4565],"type":"Point"}
}