{
  "type": "Feature",
  "properties": {
    "gn:adm1_name":"Toyamaken",
    "gn:adm2_name":"Nishitonamigunfukumitsumachi",
    "gn:name":"Nakanogou",
    "iso:country":"JP",
    "wof:name":"939-1625",
    "wof:placetype":"postalcode"
},
  "geometry": {"coordinates":[136.8638,36.5649],"type":"Point"}
}