{
  "type": "Feature",
  "properties": {
    "gn:adm1_name":"Naganoken",
    "gn:adm2_name":"Naganoshi",
    "gn:name":"Sanbonyanaginishi",
    "iso:country":"JP",
    "wof:name":"381-2244",
    "wof:placetype":"postalcode"
},
  "geometry": {"coordinates":[138.1634,36.6163],"type":"Point"}
}