{
  "type": "Feature",
  "properties": {
    "gn:adm1_name":"Saitamaken",
    "gn:adm2_name":"Soukashi",
    "gn:name":"Kitayachou",
    "iso:country":"JP",
    "wof:name":"340-0047",
    "wof:placetype":"postalcode"
},
  "geometry": {"coordinates":[139.78710000000001,35.8446],"type":"Point"}
}