{
  "type": "Feature",
  "properties": {
    "gn:adm1_name":"Niigataken",
    "gn:adm2_name":"Kariwagunnishiyamamachi",
    "gn:name":"Oosaki",
    "iso:country":"JP",
    "wof:name":"949-4204",
    "wof:placetype":"postalcode"
},
  "geometry": {"coordinates":[138.64070000000001,37.4971],"type":"Point"}
}