{
  "type": "Feature",
  "properties": {
    "gn:adm1_name":"Saitamaken",
    "gn:adm2_name":"Hasudashi",
    "gn:name":"Kurohama",
    "iso:country":"JP",
    "wof:name":"349-0101",
    "wof:placetype":"postalcode"
},
  "geometry": {"coordinates":[139.66990000000001,35.9898],"type":"Point"}
}