{
  "type": "Feature",
  "properties": {
    "gn:adm1_name":"Fukuokaken",
    "gn:adm2_name":"Ongagun'Ashiyamachi",
    "gn:name":"Sendoumachi",
    "iso:country":"JP",
    "wof:name":"807-0121",
    "wof:placetype":"postalcode"
},
  "geometry": {"coordinates":[130.66919999999999,33.8912],"type":"Point"}
}