{
  "type": "Feature",
  "properties": {
    "gn:adm1_name":"Kyoutofu",
    "gn:adm2_name":"Yawatashi",
    "gn:name":"Hashimotonishiyamamoto",
    "iso:country":"JP",
    "wof:name":"614-8314",
    "wof:placetype":"postalcode"
},
  "geometry": {"coordinates":[135.68709999999999,34.8847],"type":"Point"}
}