{
  "type": "Feature",
  "properties": {
    "gn:adm1_name":"Toyamaken",
    "gn:adm2_name":"Neigunfuchuumachi",
    "gn:name":"Gejou",
    "iso:country":"JP",
    "wof:name":"939-2758",
    "wof:placetype":"postalcode"
},
  "geometry": {"coordinates":[137.1497,36.6719],"type":"Point"}
}