{
  "type": "Feature",
  "properties": {
    "gn:adm1_name":"Mieken",
    "gn:adm2_name":"Kuwanagunnagashimachou",
    "gn:name":"Sugie",
    "iso:country":"JP",
    "wof:name":"511-1108",
    "wof:placetype":"postalcode"
},
  "geometry": {"coordinates":[136.679,35.122],"type":"Point"}
}