{
  "type": "Feature",
  "properties": {
    "gn:adm1_name":"Aichiken",
    "gn:adm2_name":"Nagoyashinakamuraku",
    "gn:name":"Ooakichou",
    "iso:country":"JP",
    "wof:name":"453-0042",
    "wof:placetype":"postalcode"
},
  "geometry": {"coordinates":[136.8673,35.1741],"type":"Point"}
}