{
  "type": "Feature",
  "properties": {
    "gn:adm1_name":"Aichiken",
    "gn:adm2_name":"Nagoyashinishiku",
    "gn:name":"Amadukachou",
    "iso:country":"JP",
    "wof:name":"451-0021",
    "wof:placetype":"postalcode"
},
  "geometry": {"coordinates":[136.8948,35.2002],"type":"Point"}
}