{
  "type": "Feature",
  "properties": {
    "gn:adm1_name":"Naraken",
    "gn:adm2_name":"Udagunmuroumura",
    "gn:name":"Kamikasama",
    "iso:country":"JP",
    "wof:name":"632-0202",
    "wof:placetype":"postalcode"
},
  "geometry": {"coordinates":[136.0324,34.609],"type":"Point"}
}