{
  "type": "Feature",
  "properties": {
    "gn:adm1_name":"Miyazakiken",
    "gn:adm2_name":"Miyazakishi",
    "gn:name":"Aoshimanishi",
    "iso:country":"JP",
    "wof:name":"889-2163",
    "wof:placetype":"postalcode"
},
  "geometry": {"coordinates":[131.4622,31.8022],"type":"Point"}
}