{
  "type": "Feature",
  "properties": {
    "gn:adm1_name":"Yamaguchiken",
    "gn:adm2_name":"Ubeshi",
    "gn:name":"Nishihirabara",
    "iso:country":"JP",
    "wof:name":"755-0808",
    "wof:placetype":"postalcode"
},
  "geometry": {"coordinates":[131.22470000000001,33.975],"type":"Point"}
}