{
  "type": "Feature",
  "properties": {
    "gn:adm1_name":"Okinawaken",
    "gn:adm2_name":"Nahashi",
    "gn:name":"Matsuyama",
    "iso:country":"JP",
    "wof:name":"900-0032",
    "wof:placetype":"postalcode"
},
  "geometry": {"coordinates":[127.67919999999999,26.2192],"type":"Point"}
}