{
  "type": "Feature",
  "properties": {
    "gn:adm1_name":"Naraken",
    "gn:adm2_name":"Tenrishi",
    "gn:name":"Iwamurochou",
    "iso:country":"JP",
    "wof:name":"632-0076",
    "wof:placetype":"postalcode"
},
  "geometry": {"coordinates":[135.81229999999999,34.5941],"type":"Point"}
}