{
  "type": "Feature",
  "properties": {
    "gn:adm1_name":"Gifuken",
    "gn:adm2_name":"Kakamigaharashi",
    "gn:name":"Soharamidorimachi",
    "iso:country":"JP",
    "wof:name":"504-0902",
    "wof:placetype":"postalcode"
},
  "geometry": {"coordinates":[136.8648,35.4015],"type":"Point"}
}