{
  "type": "Feature",
  "properties": {
    "gn:adm1_name":"Fukuokaken",
    "gn:adm2_name":"Chikushinoshi",
    "gn:name":"Haru",
    "iso:country":"JP",
    "wof:name":"818-0005",
    "wof:placetype":"postalcode"
},
  "geometry": {"coordinates":[130.5471,33.517],"type":"Point"}
}