{
  "type": "Feature",
  "properties": {
    "gn:adm1_name":"Aichiken",
    "gn:adm2_name":"Nagoyashitenpakuku",
    "gn:name":"Ikemi",
    "iso:country":"JP",
    "wof:name":"468-0067",
    "wof:placetype":"postalcode"
},
  "geometry": {"coordinates":[136.96600000000001,35.1257],"type":"Point"}
}