{
  "type": "Feature",
  "properties": {
    "gn:adm1_name":"Shizuokaken",
    "gn:adm2_name":"Hamamatsushi",
    "gn:name":"Ebitsuka",
    "iso:country":"JP",
    "wof:name":"432-8033",
    "wof:placetype":"postalcode"
},
  "geometry": {"coordinates":[137.7313,34.6987],"type":"Point"}
}