{
  "type": "Feature",
  "properties": {
    "gn:adm1_name":"Naganoken",
    "gn:adm2_name":"Naganoshi",
    "gn:name":"Kitagou",
    "iso:country":"JP",
    "wof:name":"381-0075",
    "wof:placetype":"postalcode"
},
  "geometry": {"coordinates":[138.1713,36.7077],"type":"Point"}
}