{
  "type": "Feature",
  "properties": {
    "gn:adm1_name":"Niigataken",
    "gn:adm2_name":"Kitakanbaragunkajikawamura",
    "gn:name":"Kanazawa",
    "iso:country":"JP",
    "wof:name":"959-2479",
    "wof:placetype":"postalcode"
},
  "geometry": {"coordinates":[139.38560000000001,38.0306],"type":"Point"}
}