{
  "type": "Feature",
  "properties": {
    "gn:adm1_name":"Oosakafu",
    "gn:adm2_name":"Kishiwadashi",
    "gn:name":"Hatamachi",
    "iso:country":"JP",
    "wof:name":"596-0831",
    "wof:placetype":"postalcode"
},
  "geometry": {"coordinates":[135.38560000000001,34.4394],"type":"Point"}
}