{
  "type": "Feature",
  "properties": {
    "gn:adm1_name":"Aichiken",
    "gn:adm2_name":"Shinshiroshi",
    "gn:name":"Mukaino",
    "iso:country":"JP",
    "wof:name":"441-1366",
    "wof:placetype":"postalcode"
},
  "geometry": {"coordinates":[137.5034,34.8994],"type":"Point"}
}