{
  "type": "Feature",
  "properties": {
    "gn:adm1_name":"Aichiken",
    "gn:adm2_name":"Kounanshi",
    "gn:name":"Wadachoutenjin",
    "iso:country":"JP",
    "wof:name":"483-8024",
    "wof:placetype":"postalcode"
},
  "geometry": {"coordinates":[136.8903,35.3563],"type":"Point"}
}