{
  "type": "Feature",
  "properties": {
    "gn:adm1_name":"Shimaneken",
    "gn:adm2_name":"Hikawagunhikawachou",
    "gn:name":"Kanba",
    "iso:country":"JP",
    "wof:name":"699-0503",
    "wof:placetype":"postalcode"
},
  "geometry": {"coordinates":[132.8535,35.386],"type":"Point"}
}