{
  "type": "Feature",
  "properties": {
    "gn:adm1_name":"Naganoken",
    "gn:adm2_name":"Komoroshi",
    "gn:name":"Ichi",
    "iso:country":"JP",
    "wof:name":"384-0083",
    "wof:placetype":"postalcode"
},
  "geometry": {"coordinates":[138.44450000000001,36.2889],"type":"Point"}
}