{
  "type": "Feature",
  "properties": {
    "gn:adm1_name":"Okinawaken",
    "gn:adm2_name":"Shimajirigunhaebaruchou",
    "gn:name":"Oona",
    "iso:country":"JP",
    "wof:name":"901-1101",
    "wof:placetype":"postalcode"
},
  "geometry": {"coordinates":[127.7347,26.2078],"type":"Point"}
}