{
  "type": "Feature",
  "properties": {
    "gn:adm1_name":"Fukushimaken",
    "gn:adm2_name":"Tamuragunfunehikimachi",
    "gn:name":"Arawata",
    "iso:country":"JP",
    "wof:name":"963-4322",
    "wof:placetype":"postalcode"
},
  "geometry": {"coordinates":[140.53299999999999,37.4703],"type":"Point"}
}