{
  "type": "Feature",
  "properties": {
    "gn:adm1_name":"Okinawaken",
    "gn:adm2_name":"Kunigamigunmotobuchou",
    "gn:name":"Higashi",
    "iso:country":"JP",
    "wof:name":"905-0211",
    "wof:placetype":"postalcode"
},
  "geometry": {"coordinates":[127.9002,26.6581],"type":"Point"}
}