{
  "type": "Feature",
  "properties": {
    "gn:adm1_name":"Aichiken",
    "gn:adm2_name":"Nagoyashinakaku",
    "gn:name":"Marunouchi",
    "iso:country":"JP",
    "wof:name":"460-0002",
    "wof:placetype":"postalcode"
},
  "geometry": {"coordinates":[136.9007,35.1752],"type":"Point"}
}