{
  "type": "Feature",
  "properties": {
    "gn:adm1_name":"Shizuokaken",
    "gn:adm2_name":"Kakegawashi",
    "gn:name":"Shiroshita",
    "iso:country":"JP",
    "wof:name":"436-0091",
    "wof:placetype":"postalcode"
},
  "geometry": {"coordinates":[138.0153,34.7738],"type":"Point"}
}