{
  "type": "Feature",
  "properties": {
    "gn:adm1_name":"Kumamotoken",
    "gn:adm2_name":"Asogunsoyoumachi",
    "gn:name":"Kashiwa",
    "iso:country":"JP",
    "wof:name":"861-3923",
    "wof:placetype":"postalcode"
},
  "geometry": {"coordinates":[131.17619999999999,32.7416],"type":"Point"}
}