{
  "type": "Feature",
  "properties": {
    "gn:adm1_name":"Chibaken",
    "gn:adm2_name":"Chouseigunshirakomachi",
    "gn:name":"Goi",
    "iso:country":"JP",
    "wof:name":"299-4211",
    "wof:placetype":"postalcode"
},
  "geometry": {"coordinates":[140.3845,35.4479],"type":"Point"}
}