{
  "type": "Feature",
  "properties": {
    "gn:adm1_name":"Hyougoken",
    "gn:adm2_name":"Nishinomiyashi",
    "gn:name":"Uegahara4banchou",
    "iso:country":"JP",
    "wof:name":"662-0894",
    "wof:placetype":"postalcode"
},
  "geometry": {"coordinates":[135.34880000000001,34.7616],"type":"Point"}
}