{
  "type": "Feature",
  "properties": {
    "gn:adm1_name":"Fukuokaken",
    "gn:adm2_name":"Buzenshi",
    "gn:name":"Kishii",
    "iso:country":"JP",
    "wof:name":"828-0043",
    "wof:placetype":"postalcode"
},
  "geometry": {"coordinates":[131.13820000000001,33.5951],"type":"Point"}
}