{
  "type": "Feature",
  "properties": {
    "gn:adm1_name":"Kanagawaken",
    "gn:adm2_name":"Odawarashi",
    "gn:name":"Isaida",
    "iso:country":"JP",
    "wof:name":"250-0056",
    "wof:placetype":"postalcode"
},
  "geometry": {"coordinates":[139.15430000000001,35.2686],"type":"Point"}
}