{
  "type": "Feature",
  "properties": {
    "gn:adm1_name":"Hiroshimaken",
    "gn:adm2_name":"Fukuyamashi",
    "gn:name":"Funamachi",
    "iso:country":"JP",
    "wof:name":"720-0043",
    "wof:placetype":"postalcode"
},
  "geometry": {"coordinates":[133.36779999999999,34.4871],"type":"Point"}
}