{
  "type": "Feature",
  "properties": {
    "gn:adm1_name":"Toyamaken",
    "gn:adm2_name":"Namerikawashi",
    "gn:name":"Nomachi",
    "iso:country":"JP",
    "wof:name":"936-0883",
    "wof:placetype":"postalcode"
},
  "geometry": {"coordinates":[137.3664,36.7629],"type":"Point"}
}