{
  "type": "Feature",
  "properties": {
    "gn:adm1_name":"Naganoken",
    "gn:adm2_name":"Komaganeshi",
    "gn:name":"Higashimachi",
    "iso:country":"JP",
    "wof:name":"399-4106",
    "wof:placetype":"postalcode"
},
  "geometry": {"coordinates":[137.93860000000001,35.7364],"type":"Point"}
}