{
  "type": "Feature",
  "properties": {
    "gn:adm1_name":"Oosakafu",
    "gn:adm2_name":"Daitoushi",
    "gn:name":"Shindennakamachi",
    "iso:country":"JP",
    "wof:name":"574-0056",
    "wof:placetype":"postalcode"
},
  "geometry": {"coordinates":[135.60380000000001,34.71],"type":"Point"}
}