{
  "type": "Feature",
  "properties": {
    "gn:adm1_name":"Miyagiken",
    "gn:adm2_name":"Motoyoshigunmotoyoshichou",
    "gn:name":"Tsuyamatsuo",
    "iso:country":"JP",
    "wof:name":"988-0309",
    "wof:placetype":"postalcode"
},
  "geometry": {"coordinates":[141.50399999999999,38.7875],"type":"Point"}
}