{
  "type": "Feature",
  "properties": {
    "gn:adm1_name":"Naganoken",
    "gn:adm2_name":"Kamiinaguntakatoomachi",
    "gn:name":"Nishitakatoo",
    "iso:country":"JP",
    "wof:name":"396-0211",
    "wof:placetype":"postalcode"
},
  "geometry": {"coordinates":[138.0556,35.8367],"type":"Point"}
}