{
  "type": "Feature",
  "properties": {
    "gn:adm1_name":"Kouchiken",
    "gn:adm2_name":"Tosagunkagamimura",
    "gn:name":"Matobuchi",
    "iso:country":"JP",
    "wof:name":"781-3111",
    "wof:placetype":"postalcode"
},
  "geometry": {"coordinates":[133.44659999999999,33.61],"type":"Point"}
}