{
  "type": "Feature",
  "properties": {
    "gn:adm1_name":"Gifuken",
    "gn:adm2_name":"Motosugunmotosuchou",
    "gn:name":"Koumi",
    "iso:country":"JP",
    "wof:name":"501-1235",
    "wof:placetype":"postalcode"
},
  "geometry": {"coordinates":[136.64609999999999,35.5386],"type":"Point"}
}