{
  "type": "Feature",
  "properties": {
    "gn:adm1_name":"Ooitaken",
    "gn:adm2_name":"Usagun'Ajimumachi",
    "gn:name":"Sada",
    "iso:country":"JP",
    "wof:name":"872-0651",
    "wof:placetype":"postalcode"
},
  "geometry": {"coordinates":[131.39359999999999,33.447],"type":"Point"}
}