{
  "type": "Feature",
  "properties": {
    "gn:adm1_name":"Tokushimaken",
    "gn:adm2_name":"Mimagun'Anabukichou",
    "gn:name":"Mishima(Mainakashima)",
    "iso:country":"JP",
    "wof:name":"777-0002",
    "wof:placetype":"postalcode"
},
  "geometry": {"coordinates":[134.1412,34.0583],"type":"Point"}
}