{
  "type": "Feature",
  "properties": {
    "gn:adm1_name":"Kouchiken",
    "gn:adm2_name":"Nankokushi",
    "gn:name":"Myouken",
    "iso:country":"JP",
    "wof:name":"783-0007",
    "wof:placetype":"postalcode"
},
  "geometry": {"coordinates":[133.6242,33.5701],"type":"Point"}
}