{
  "type": "Feature",
  "properties": {
    "gn:adm1_name":"Hyougoken",
    "gn:adm2_name":"Himejishi",
    "gn:name":"Shikamakuagamiyachou",
    "iso:country":"JP",
    "wof:name":"672-8080",
    "wof:placetype":"postalcode"
},
  "geometry": {"coordinates":[134.6405,34.8057],"type":"Point"}
}