{
  "type": "Feature",
  "properties": {
    "gn:adm1_name":"Fukuokaken",
    "gn:adm2_name":"Oomutashi",
    "gn:name":"Shinsakaemachi",
    "iso:country":"JP",
    "wof:name":"836-0041",
    "wof:placetype":"postalcode"
},
  "geometry": {"coordinates":[130.44810000000001,33.0383],"type":"Point"}
}