{
  "type": "Feature",
  "properties": {
    "gn:adm1_name":"Aichiken",
    "gn:adm2_name":"Nishikamogun'Obaramura",
    "gn:name":"Hiraiwa",
    "iso:country":"JP",
    "wof:name":"470-0514",
    "wof:placetype":"postalcode"
},
  "geometry": {"coordinates":[137.3306,35.2456],"type":"Point"}
}