{
  "type": "Feature",
  "properties": {
    "gn:adm1_name":"Aichiken",
    "gn:adm2_name":"Inuyamashi",
    "gn:name":"Gakuden'Uchikubo",
    "iso:country":"JP",
    "wof:name":"484-0048",
    "wof:placetype":"postalcode"
},
  "geometry": {"coordinates":[136.94999999999999,35.3185],"type":"Point"}
}