{
  "type": "Feature",
  "properties": {
    "gn:adm1_name":"Aichiken",
    "gn:adm2_name":"Toyoakeshi",
    "gn:name":"Anochou(Inaba)",
    "iso:country":"JP",
    "wof:name":"470-1144",
    "wof:placetype":"postalcode"
},
  "geometry": {"coordinates":[137.0103,35.0471],"type":"Point"}
}