{
  "type": "Feature",
  "properties": {
    "gn:adm1_name":"Gunmaken",
    "gn:adm2_name":"Kiryuushi",
    "gn:name":"Tsutsumichou",
    "iso:country":"JP",
    "wof:name":"376-0042",
    "wof:placetype":"postalcode"
},
  "geometry": {"coordinates":[139.32419999999999,36.4176],"type":"Point"}
}