{
  "type": "Feature",
  "properties": {
    "gn:adm1_name":"Hiroshimaken",
    "gn:adm2_name":"Higashihiroshimashi",
    "gn:name":"Saijouchoujike(Sonota)",
    "iso:country":"JP",
    "wof:name":"739-0041",
    "wof:placetype":"postalcode"
},
  "geometry": {"coordinates":[132.7252,34.4314],"type":"Point"}
}