{
  "type": "Feature",
  "properties": {
    "gn:adm1_name":"Niigataken",
    "gn:adm2_name":"Jouetsushi",
    "gn:name":"Gokashoshinden",
    "iso:country":"JP",
    "wof:name":"943-0842",
    "wof:placetype":"postalcode"
},
  "geometry": {"coordinates":[138.26820000000001,37.0887],"type":"Point"}
}