{
  "type": "Feature",
  "properties": {
    "gn:adm1_name":"Aichiken",
    "gn:adm2_name":"Kounanshi",
    "gn:name":"Osakichouueda",
    "iso:country":"JP",
    "wof:name":"483-8161",
    "wof:placetype":"postalcode"
},
  "geometry": {"coordinates":[136.88040000000001,35.3314],"type":"Point"}
}