{
  "type": "Feature",
  "properties": {
    "gn:adm1_name":"Niigataken",
    "gn:adm2_name":"Nakakubikigunkakizakimachi",
    "gn:name":"Iwade",
    "iso:country":"JP",
    "wof:name":"949-3376",
    "wof:placetype":"postalcode"
},
  "geometry": {"coordinates":[138.4409,37.2488],"type":"Point"}
}