{
  "type": "Feature",
  "properties": {
    "gn:adm1_name":"Naraken",
    "gn:adm2_name":"Kitakatsuragigunshinjouchou",
    "gn:name":"Nishimuro",
    "iso:country":"JP",
    "wof:name":"639-2103",
    "wof:placetype":"postalcode"
},
  "geometry": {"coordinates":[135.72749999999999,34.4942],"type":"Point"}
}