{
  "type": "Feature",
  "properties": {
    "gn:adm1_name":"Toukyouto",
    "gn:adm2_name":"Adachiku",
    "gn:name":"Senjuasahichou",
    "iso:country":"JP",
    "wof:name":"120-0026",
    "wof:placetype":"postalcode"
},
  "geometry": {"coordinates":[139.8074,35.7491],"type":"Point"}
}