{
  "type": "Feature",
  "properties": {
    "gn:adm1_name":"Miyazakiken",
    "gn:adm2_name":"Miyazakishi",
    "gn:name":"Shimokitakatamachi",
    "iso:country":"JP",
    "wof:name":"880-0035",
    "wof:placetype":"postalcode"
},
  "geometry": {"coordinates":[131.41919999999999,31.944],"type":"Point"}
}