{
  "type": "Feature",
  "properties": {
    "gn:adm1_name":"Toyamaken",
    "gn:adm2_name":"Shimoniikawagunnyuuzenmachi",
    "gn:name":"Sodezawa",
    "iso:country":"JP",
    "wof:name":"939-0652",
    "wof:placetype":"postalcode"
},
  "geometry": {"coordinates":[137.482,36.9094],"type":"Point"}
}