{
  "type": "Feature",
  "properties": {
    "gn:adm1_name":"Kouchiken",
    "gn:adm2_name":"Tosagunhongawamura",
    "gn:name":"Oomori",
    "iso:country":"JP",
    "wof:name":"781-2603",
    "wof:placetype":"postalcode"
},
  "geometry": {"coordinates":[133.30260000000001,33.708],"type":"Point"}
}