{
  "type": "Feature",
  "properties": {
    "gn:adm1_name":"Mieken",
    "gn:adm2_name":"Takiguntakichou",
    "gn:name":"Toba",
    "iso:country":"JP",
    "wof:name":"519-2161",
    "wof:placetype":"postalcode"
},
  "geometry": {"coordinates":[136.58709999999999,34.4983],"type":"Point"}
}