{
  "type": "Feature",
  "properties": {
    "gn:adm1_name":"Toyamaken",
    "gn:adm2_name":"Takaokashi",
    "gn:name":"Iguchihongou",
    "iso:country":"JP",
    "wof:name":"933-0807",
    "wof:placetype":"postalcode"
},
  "geometry": {"coordinates":[137.0292,36.7361],"type":"Point"}
}