{
  "type": "Feature",
  "properties": {
    "gn:adm1_name":"Wakayamaken",
    "gn:adm2_name":"Aridagunhirogawachou",
    "gn:name":"Hiro",
    "iso:country":"JP",
    "wof:name":"643-0071",
    "wof:placetype":"postalcode"
},
  "geometry": {"coordinates":[135.17490000000001,34.0262],"type":"Point"}
}