{
  "type": "Feature",
  "properties": {
    "gn:adm1_name":"Kyoutofu",
    "gn:adm2_name":"Kyoutoshikamigyouku",
    "gn:name":"Yanagifurochou",
    "iso:country":"JP",
    "wof:name":"602-0838",
    "wof:placetype":"postalcode"
},
  "geometry": {"coordinates":[135.76689999999999,35.0299],"type":"Point"}
}