{
  "type": "Feature",
  "properties": {
    "gn:adm1_name":"Chibaken",
    "gn:adm2_name":"Inbagunshisuimachi",
    "gn:name":"Ijino",
    "iso:country":"JP",
    "wof:name":"285-0902",
    "wof:placetype":"postalcode"
},
  "geometry": {"coordinates":[140.28919999999999,35.7467],"type":"Point"}
}