{
  "type": "Feature",
  "properties": {
    "gn:adm1_name":"Naraken",
    "gn:adm2_name":"Narashi",
    "gn:name":"Suganodai",
    "iso:country":"JP",
    "wof:name":"631-0043",
    "wof:placetype":"postalcode"
},
  "geometry": {"coordinates":[135.7593,34.6785],"type":"Point"}
}