{
  "type": "Feature",
  "properties": {
    "gn:adm1_name":"Saitamaken",
    "gn:adm2_name":"Iwatsukishi",
    "gn:name":"Ooto",
    "iso:country":"JP",
    "wof:name":"339-0014",
    "wof:placetype":"postalcode"
},
  "geometry": {"coordinates":[139.7381,35.9335],"type":"Point"}
}