{
  "type": "Feature",
  "properties": {
    "gn:adm1_name":"Ishikawaken",
    "gn:adm2_name":"Kanazawashi",
    "gn:name":"Minamishinbomachi",
    "iso:country":"JP",
    "wof:name":"920-0064",
    "wof:placetype":"postalcode"
},
  "geometry": {"coordinates":[136.63560000000001,36.5986],"type":"Point"}
}