{
  "type": "Feature",
  "properties": {
    "gn:adm1_name":"Mieken",
    "gn:adm2_name":"Kuwanagunnagashimachou",
    "gn:name":"Shimosakate",
    "iso:country":"JP",
    "wof:name":"511-1106",
    "wof:placetype":"postalcode"
},
  "geometry": {"coordinates":[136.67679999999999,35.1117],"type":"Point"}
}