{
  "type": "Feature",
  "properties": {
    "gn:adm1_name":"Saitamaken",
    "gn:adm2_name":"Kounosushi",
    "gn:name":"Raiden",
    "iso:country":"JP",
    "wof:name":"365-0077",
    "wof:placetype":"postalcode"
},
  "geometry": {"coordinates":[139.5087,36.0635],"type":"Point"}
}