{
  "type": "Feature",
  "properties": {
    "gn:adm1_name":"Ishikawaken",
    "gn:adm2_name":"Kahokugun'Uchinadamachi",
    "gn:name":"Mukaiawagasaki",
    "iso:country":"JP",
    "wof:name":"920-0274",
    "wof:placetype":"postalcode"
},
  "geometry": {"coordinates":[136.636,36.6329],"type":"Point"}
}