{
  "type": "Feature",
  "properties": {
    "gn:adm1_name":"Naraken",
    "gn:adm2_name":"Yamatotakadashi",
    "gn:name":"Ikejiri",
    "iso:country":"JP",
    "wof:name":"635-0021",
    "wof:placetype":"postalcode"
},
  "geometry": {"coordinates":[135.74809999999999,34.5268],"type":"Point"}
}