{
  "type": "Feature",
  "properties": {
    "gn:adm1_name":"Ehimeken",
    "gn:adm2_name":"Onsengunkawauchichou",
    "gn:name":"Myouga",
    "iso:country":"JP",
    "wof:name":"791-0323",
    "wof:placetype":"postalcode"
},
  "geometry": {"coordinates":[133.00640000000001,33.7799],"type":"Point"}
}