{
  "type": "Feature",
  "properties": {
    "gn:adm1_name":"Naganoken",
    "gn:adm2_name":"Kitasakugunmiyotamachi",
    "gn:name":"Ikanikeisaiganaibaai",
    "iso:country":"JP",
    "wof:name":"389-0200",
    "wof:placetype":"postalcode"
},
  "geometry": {"coordinates":[138.49430000000001,36.3105],"type":"Point"}
}