{
  "type": "Feature",
  "properties": {
    "gn:adm1_name":"Hyougoken",
    "gn:adm2_name":"Nishinomiyashi",
    "gn:name":"Najiokonomoto",
    "iso:country":"JP",
    "wof:name":"669-1136",
    "wof:placetype":"postalcode"
},
  "geometry": {"coordinates":[135.3167,34.8244],"type":"Point"}
}