{
  "type": "Feature",
  "properties": {
    "gn:adm1_name":"Hyougoken",
    "gn:adm2_name":"Tsunaguntsunachou",
    "gn:name":"Ikanikeisaiganaibaai",
    "iso:country":"JP",
    "wof:name":"656-2100",
    "wof:placetype":"postalcode"
},
  "geometry": {"coordinates":[135.0086,34.5606],"type":"Point"}
}