{
  "type": "Feature",
  "properties": {
    "gn:adm1_name":"Toukyouto",
    "gn:adm2_name":"Ooshimaooshimamachi",
    "gn:name":"Nomashi",
    "iso:country":"JP",
    "wof:name":"100-0104",
    "wof:placetype":"postalcode"
},
  "geometry": {"coordinates":[139.3605,34.7241],"type":"Point"}
}