{
  "type": "Feature",
  "properties": {
    "gn:adm1_name":"Niigataken",
    "gn:adm2_name":"Nakakubikigunnakagoumura",
    "gn:name":"Sakamotoshinden",
    "iso:country":"JP",
    "wof:name":"949-2303",
    "wof:placetype":"postalcode"
},
  "geometry": {"coordinates":[138.23410000000001,36.9872],"type":"Point"}
}