{
  "type": "Feature",
  "properties": {
    "gn:adm1_name":"Aichiken",
    "gn:adm2_name":"Toyohashishi",
    "gn:name":"Hashira9banchou",
    "iso:country":"JP",
    "wof:name":"441-8055",
    "wof:placetype":"postalcode"
},
  "geometry": {"coordinates":[137.3828,34.744],"type":"Point"}
}