{
  "type": "Feature",
  "properties": {
    "gn:adm1_name":"Toyamaken",
    "gn:adm2_name":"Toyamashi",
    "gn:name":"Jinduuhonmachi",
    "iso:country":"JP",
    "wof:name":"930-0008",
    "wof:placetype":"postalcode"
},
  "geometry": {"coordinates":[137.20820000000001,36.7008],"type":"Point"}
}