{
  "type": "Feature",
  "properties": {
    "gn:adm1_name":"Fukuokaken",
    "gn:adm2_name":"Kurumeshi",
    "gn:name":"Arakimachiima",
    "iso:country":"JP",
    "wof:name":"830-0065",
    "wof:placetype":"postalcode"
},
  "geometry": {"coordinates":[130.49539999999999,33.2556],"type":"Point"}
}