{
  "type": "Feature",
  "properties": {
    "gn:adm1_name":"Fukuokaken",
    "gn:adm2_name":"Asakuragunyasumachi",
    "gn:name":"Ishibitsu",
    "iso:country":"JP",
    "wof:name":"838-0225",
    "wof:placetype":"postalcode"
},
  "geometry": {"coordinates":[130.5814,33.4656],"type":"Point"}
}