{
  "type": "Feature",
  "properties": {
    "gn:adm1_name":"Fukushimaken",
    "gn:adm2_name":"Nihonmatsushi",
    "gn:name":"Kitoujirouuchi",
    "iso:country":"JP",
    "wof:name":"964-0808",
    "wof:placetype":"postalcode"
},
  "geometry": {"coordinates":[140.43600000000001,37.5816],"type":"Point"}
}