{
  "type": "Feature",
  "properties": {
    "gn:adm1_name":"Yamaguchiken",
    "gn:adm2_name":"Shimonosekishi",
    "gn:name":"Choufukanayahamachou",
    "iso:country":"JP",
    "wof:name":"752-0958",
    "wof:placetype":"postalcode"
},
  "geometry": {"coordinates":[130.99119999999999,34.002],"type":"Point"}
}