{
  "type": "Feature",
  "properties": {
    "gn:adm1_name":"Aichiken",
    "gn:adm2_name":"Hekinanshi",
    "gn:name":"Hiromimachi",
    "iso:country":"JP",
    "wof:name":"447-0067",
    "wof:placetype":"postalcode"
},
  "geometry": {"coordinates":[136.99799999999999,34.9142],"type":"Point"}
}