{
  "type": "Feature",
  "properties": {
    "gn:adm1_name":"Tottoriken",
    "gn:adm2_name":"Saihakugunsaihakuchou",
    "gn:name":"Kamobe",
    "iso:country":"JP",
    "wof:name":"683-0341",
    "wof:placetype":"postalcode"
},
  "geometry": {"coordinates":[133.3306,35.3312],"type":"Point"}
}