{
  "type": "Feature",
  "properties": {
    "gn:adm1_name":"Kyoutofu",
    "gn:adm2_name":"Kyoutoshiukyouku",
    "gn:name":"Sagaogurayamayamamotochou",
    "iso:country":"JP",
    "wof:name":"616-8396",
    "wof:placetype":"postalcode"
},
  "geometry": {"coordinates":[135.66990000000001,35.0192],"type":"Point"}
}