{
  "type": "Feature",
  "properties": {
    "gn:adm1_name":"Yamanashiken",
    "gn:adm2_name":"Minamiarupusushi",
    "gn:name":"Tsukahara",
    "iso:country":"JP",
    "wof:name":"400-0426",
    "wof:placetype":"postalcode"
},
  "geometry": {"coordinates":[138.4538,35.5949],"type":"Point"}
}