{
  "type": "Feature",
  "properties": {
    "gn:adm1_name":"Niigataken",
    "gn:adm2_name":"Nishikubikigun'Oumimachi",
    "gn:name":"Hashidate",
    "iso:country":"JP",
    "wof:name":"949-0306",
    "wof:placetype":"postalcode"
},
  "geometry": {"coordinates":[137.7621,36.9772],"type":"Point"}
}