{
  "type": "Feature",
  "properties": {
    "gn:adm1_name":"Mieken",
    "gn:adm2_name":"Matsusakashi",
    "gn:name":"Kouseichou",
    "iso:country":"JP",
    "wof:name":"515-0013",
    "wof:placetype":"postalcode"
},
  "geometry": {"coordinates":[136.55430000000001,34.5709],"type":"Point"}
}