{
  "type": "Feature",
  "properties": {
    "gn:adm1_name":"Shigaken",
    "gn:adm2_name":"Hikoneshi",
    "gn:name":"Ishiderachou",
    "iso:country":"JP",
    "wof:name":"521-1101",
    "wof:placetype":"postalcode"
},
  "geometry": {"coordinates":[136.18020000000001,35.2365],"type":"Point"}
}