{
  "type": "Feature",
  "properties": {
    "gn:adm1_name":"Shizuokaken",
    "gn:adm2_name":"Ogasagunkikugawachou",
    "gn:name":"Kurasawa",
    "iso:country":"JP",
    "wof:name":"439-0002",
    "wof:placetype":"postalcode"
},
  "geometry": {"coordinates":[138.12899999999999,34.7879],"type":"Point"}
}