{
  "type": "Feature",
  "properties": {
    "gn:adm1_name":"Yamaguchiken",
    "gn:adm2_name":"Shuunanshi",
    "gn:name":"Satsukichou",
    "iso:country":"JP",
    "wof:name":"745-0811",
    "wof:placetype":"postalcode"
},
  "geometry": {"coordinates":[131.82919999999999,34.0377],"type":"Point"}
}