{
  "type": "Feature",
  "properties": {
    "gn:adm1_name":"Ehimeken",
    "gn:adm2_name":"Onsengunnakajimachou",
    "gn:name":"Miyano",
    "iso:country":"JP",
    "wof:name":"791-4504",
    "wof:placetype":"postalcode"
},
  "geometry": {"coordinates":[132.61349999999999,33.9586],"type":"Point"}
}