{
  "type": "Feature",
  "properties": {
    "gn:adm1_name":"Shigaken",
    "gn:adm2_name":"Gamougunryuuouchou",
    "gn:name":"Yuge",
    "iso:country":"JP",
    "wof:name":"520-2501",
    "wof:placetype":"postalcode"
},
  "geometry": {"coordinates":[136.11420000000001,35.0873],"type":"Point"}
}