{
  "type": "Feature",
  "properties": {
    "gn:adm1_name":"Saitamaken",
    "gn:adm2_name":"Hannoushi",
    "gn:name":"Kosedo",
    "iso:country":"JP",
    "wof:name":"357-0067",
    "wof:placetype":"postalcode"
},
  "geometry": {"coordinates":[139.26509999999999,35.8694],"type":"Point"}
}