{
  "type": "Feature",
  "properties": {
    "gn:adm1_name":"Ehimeken",
    "gn:adm2_name":"Shuusougunkomatsuchou",
    "gn:name":"Myouguchi",
    "iso:country":"JP",
    "wof:name":"799-1104",
    "wof:placetype":"postalcode"
},
  "geometry": {"coordinates":[133.08420000000001,33.887],"type":"Point"}
}