{
  "type": "Feature",
  "properties": {
    "gn:adm1_name":"Niigataken",
    "gn:adm2_name":"Iwafunegun'Asahimura",
    "gn:name":"Kosudo",
    "iso:country":"JP",
    "wof:name":"958-0204",
    "wof:placetype":"postalcode"
},
  "geometry": {"coordinates":[139.5617,38.3262],"type":"Point"}
}