{
  "type": "Feature",
  "properties": {
    "gn:adm1_name":"Naraken",
    "gn:adm2_name":"Yamatokooriyamashi",
    "gn:name":"Idonochou",
    "iso:country":"JP",
    "wof:name":"639-1104",
    "wof:placetype":"postalcode"
},
  "geometry": {"coordinates":[135.81489999999999,34.6348],"type":"Point"}
}