{
  "type": "Feature",
  "properties": {
    "gn:adm1_name":"Yamanashiken",
    "gn:adm2_name":"Koufushi",
    "gn:name":"Sakaorichou",
    "iso:country":"JP",
    "wof:name":"400-0804",
    "wof:placetype":"postalcode"
},
  "geometry": {"coordinates":[138.6002,35.6619],"type":"Point"}
}