{
  "type": "Feature",
  "properties": {
    "gn:adm1_name":"Shigaken",
    "gn:adm2_name":"Ootsushi",
    "gn:name":"Goryouchou",
    "iso:country":"JP",
    "wof:name":"520-0037",
    "wof:placetype":"postalcode"
},
  "geometry": {"coordinates":[135.85489999999999,35.0181],"type":"Point"}
}