{
  "type": "Feature",
  "properties": {
    "gn:adm1_name":"Yamagataken",
    "gn:adm2_name":"Yamagatashi",
    "gn:name":"Minamimatsubara",
    "iso:country":"JP",
    "wof:name":"990-2312",
    "wof:placetype":"postalcode"
},
  "geometry": {"coordinates":[140.30840000000001,38.1987],"type":"Point"}
}