{
  "type": "Feature",
  "properties": {
    "gn:adm1_name":"Shizuokaken",
    "gn:adm2_name":"Tagatagunkannamichou",
    "gn:name":"Tsukamoto",
    "iso:country":"JP",
    "wof:name":"419-0124",
    "wof:placetype":"postalcode"
},
  "geometry": {"coordinates":[138.93350000000001,35.0783],"type":"Point"}
}