{
  "type": "Feature",
  "properties": {
    "gn:adm1_name":"Yamagataken",
    "gn:adm2_name":"Nishiokitamagun'Ogunimachi",
    "gn:name":"Tazawagashira",
    "iso:country":"JP",
    "wof:name":"999-1344",
    "wof:placetype":"postalcode"
},
  "geometry": {"coordinates":[139.75569999999999,38.0788],"type":"Point"}
}