{
  "type": "Feature",
  "properties": {
    "gn:adm1_name":"Nagasakiken",
    "gn:adm2_name":"Nagasakishi",
    "gn:name":"Yanagidamachi",
    "iso:country":"JP",
    "wof:name":"850-0982",
    "wof:placetype":"postalcode"
},
  "geometry": {"coordinates":[129.84469999999999,32.6857],"type":"Point"}
}