{
  "type": "Feature",
  "properties": {
    "gn:adm1_name":"Mieken",
    "gn:adm2_name":"Matsusakashi",
    "gn:name":"Hayamazechou",
    "iso:country":"JP",
    "wof:name":"515-0217",
    "wof:placetype":"postalcode"
},
  "geometry": {"coordinates":[136.58959999999999,34.5425],"type":"Point"}
}