{
  "type": "Feature",
  "properties": {
    "gn:adm1_name":"Kyoutofu",
    "gn:adm2_name":"Kyoutoshiyamashinaku",
    "gn:name":"Kawatayamada",
    "iso:country":"JP",
    "wof:name":"607-8327",
    "wof:placetype":"postalcode"
},
  "geometry": {"coordinates":[135.79320000000001,34.9777],"type":"Point"}
}