{
  "type": "Feature",
  "properties": {
    "gn:adm1_name":"Aichiken",
    "gn:adm2_name":"Hazugun'Isshikichou",
    "gn:name":"Fujie",
    "iso:country":"JP",
    "wof:name":"444-0414",
    "wof:placetype":"postalcode"
},
  "geometry": {"coordinates":[137.02629999999999,34.8017],"type":"Point"}
}