{
  "type": "Feature",
  "properties": {
    "gn:adm1_name":"Naraken",
    "gn:adm2_name":"Udagunhaibarachou",
    "gn:name":"Sawa",
    "iso:country":"JP",
    "wof:name":"633-0226",
    "wof:placetype":"postalcode"
},
  "geometry": {"coordinates":[135.96789999999999,34.4925],"type":"Point"}
}