{
  "type": "Feature",
  "properties": {
    "gn:adm1_name":"Saitamaken",
    "gn:adm2_name":"Oosatogunyoriimachi",
    "gn:name":"Youdo",
    "iso:country":"JP",
    "wof:name":"369-1201",
    "wof:placetype":"postalcode"
},
  "geometry": {"coordinates":[139.20500000000001,36.1546],"type":"Point"}
}