{
  "type": "Feature",
  "properties": {
    "gn:adm1_name":"Ibarakiken",
    "gn:adm2_name":"Kogashi",
    "gn:name":"Nakada",
    "iso:country":"JP",
    "wof:name":"306-0053",
    "wof:placetype":"postalcode"
},
  "geometry": {"coordinates":[139.71260000000001,36.1484],"type":"Point"}
}