{
  "type": "Feature",
  "properties": {
    "gn:adm1_name":"Shigaken",
    "gn:adm2_name":"Youkaichishi",
    "gn:name":"Gochichou",
    "iso:country":"JP",
    "wof:name":"527-0044",
    "wof:placetype":"postalcode"
},
  "geometry": {"coordinates":[136.2321,35.0971],"type":"Point"}
}