{
  "type": "Feature",
  "properties": {
    "gn:adm1_name":"Kyoutofu",
    "gn:adm2_name":"Kyoutoshikamigyouku",
    "gn:name":"Kamitounodanchou",
    "iso:country":"JP",
    "wof:name":"602-0815",
    "wof:placetype":"postalcode"
},
  "geometry": {"coordinates":[135.76599999999999,35.0312],"type":"Point"}
}