{
  "type": "Feature",
  "properties": {
    "gn:adm1_name":"Kanagawaken",
    "gn:adm2_name":"Yokosukashi",
    "gn:name":"Morisaki",
    "iso:country":"JP",
    "wof:name":"238-0023",
    "wof:placetype":"postalcode"
},
  "geometry": {"coordinates":[139.6763,35.2476],"type":"Point"}
}