{
  "type": "Feature",
  "properties": {
    "gn:adm1_name":"Kyoutofu",
    "gn:adm2_name":"Kyoutoshinishikyouku",
    "gn:name":"Goryouuchimachi",
    "iso:country":"JP",
    "wof:name":"615-8235",
    "wof:placetype":"postalcode"
},
  "geometry": {"coordinates":[135.69110000000001,34.9794],"type":"Point"}
}