{
  "type": "Feature",
  "properties": {
    "gn:adm1_name":"Tochigiken",
    "gn:adm2_name":"Kuroisoshi",
    "gn:name":"Daikokuchou",
    "iso:country":"JP",
    "wof:name":"325-0046",
    "wof:placetype":"postalcode"
},
  "geometry": {"coordinates":[140.04810000000001,36.9706],"type":"Point"}
}