{
  "type": "Feature",
  "properties": {
    "gn:adm1_name":"Kyoutofu",
    "gn:adm2_name":"Kyoutoshisakyouku",
    "gn:name":"Iwakuranagatanichou",
    "iso:country":"JP",
    "wof:name":"606-0026",
    "wof:placetype":"postalcode"
},
  "geometry": {"coordinates":[135.791,35.0807],"type":"Point"}
}