{
  "type": "Feature",
  "properties": {
    "gn:adm1_name":"Kumamotoken",
    "gn:adm2_name":"Tamanashi",
    "gn:name":"Ishinuki",
    "iso:country":"JP",
    "wof:name":"865-0008",
    "wof:placetype":"postalcode"
},
  "geometry": {"coordinates":[130.5616,32.961],"type":"Point"}
}