{
  "type": "Feature",
  "properties": {
    "gn:adm1_name":"Niigataken",
    "gn:adm2_name":"Nakakubikigunyoshikawamachi",
    "gn:name":"Shimoozawa",
    "iso:country":"JP",
    "wof:name":"949-3406",
    "wof:placetype":"postalcode"
},
  "geometry": {"coordinates":[138.44720000000001,37.214],"type":"Point"}
}