{
  "type": "Feature",
  "properties": {
    "gn:adm1_name":"Fukushimaken",
    "gn:adm2_name":"Fukushimashi",
    "gn:name":"Tanakajima",
    "iso:country":"JP",
    "wof:name":"960-8227",
    "wof:placetype":"postalcode"
},
  "geometry": {"coordinates":[140.4845,37.7725],"type":"Point"}
}