{
  "type": "Feature",
  "properties": {
    "gn:adm1_name":"Oosakafu",
    "gn:adm2_name":"Higashioosakashi",
    "gn:name":"Mikurya",
    "iso:country":"JP",
    "wof:name":"577-0032",
    "wof:placetype":"postalcode"
},
  "geometry": {"coordinates":[135.58680000000001,34.6718],"type":"Point"}
}