{
  "type": "Feature",
  "properties": {
    "gn:adm1_name":"Fukuiken",
    "gn:adm2_name":"Sakaigunmikunichou",
    "gn:name":"Nonaka",
    "iso:country":"JP",
    "wof:name":"913-0015",
    "wof:placetype":"postalcode"
},
  "geometry": {"coordinates":[136.17089999999999,36.1946],"type":"Point"}
}