{
  "type": "Feature",
  "properties": {
    "gn:adm1_name":"Fukushimaken",
    "gn:adm2_name":"Futabaguntomiokamachi",
    "gn:name":"Kobama",
    "iso:country":"JP",
    "wof:name":"979-1111",
    "wof:placetype":"postalcode"
},
  "geometry": {"coordinates":[141.0154,37.3392],"type":"Point"}
}