{
  "type": "Feature",
  "properties": {
    "gn:adm1_name":"Kanagawaken",
    "gn:adm2_name":"Yokohamashimidoriku",
    "gn:name":"Nishihatsusakuchou",
    "iso:country":"JP",
    "wof:name":"226-0024",
    "wof:placetype":"postalcode"
},
  "geometry": {"coordinates":[139.5284,35.5287],"type":"Point"}
}