{
  "type": "Feature",
  "properties": {
    "gn:adm1_name":"Kumamotoken",
    "gn:adm2_name":"Amakusagunreihokumachi",
    "gn:name":"Shiki",
    "iso:country":"JP",
    "wof:name":"863-2503",
    "wof:placetype":"postalcode"
},
  "geometry": {"coordinates":[130.05500000000001,32.5083],"type":"Point"}
}