{
  "type": "Feature",
  "properties": {
    "gn:adm1_name":"Wakayamaken",
    "gn:adm2_name":"Hashimotoshi",
    "gn:name":"Hashitani",
    "iso:country":"JP",
    "wof:name":"648-0095",
    "wof:placetype":"postalcode"
},
  "geometry": {"coordinates":[135.60470000000001,34.347],"type":"Point"}
}