{
  "type": "Feature",
  "properties": {
    "gn:adm1_name":"Wakayamaken",
    "gn:adm2_name":"Wakayamashi",
    "gn:name":"Hirosetoorichou",
    "iso:country":"JP",
    "wof:name":"640-8113",
    "wof:placetype":"postalcode"
},
  "geometry": {"coordinates":[135.1816,34.2265],"type":"Point"}
}