{
  "type": "Feature",
  "properties": {
    "gn:adm1_name":"Aichiken",
    "gn:adm2_name":"Higashikamogun'Asahichou",
    "gn:name":"Mandiyou",
    "iso:country":"JP",
    "wof:name":"444-2845",
    "wof:placetype":"postalcode"
},
  "geometry": {"coordinates":[137.38749999999999,35.2236],"type":"Point"}
}