{
  "type": "Feature",
  "properties": {
    "gn:adm1_name":"Aichiken",
    "gn:adm2_name":"Toyoakeshi",
    "gn:name":"Sakaechou(Minamiyakata)",
    "iso:country":"JP",
    "wof:name":"470-1168",
    "wof:placetype":"postalcode"
},
  "geometry": {"coordinates":[136.97890000000001,35.057],"type":"Point"}
}