{
  "type": "Feature",
  "properties": {
    "gn:adm1_name":"Toukyouto",
    "gn:adm2_name":"Hachioujishi",
    "gn:name":"Sandamachi",
    "iso:country":"JP",
    "wof:name":"193-0832",
    "wof:placetype":"postalcode"
},
  "geometry": {"coordinates":[139.31030000000001,35.651],"type":"Point"}
}