{
  "type": "Feature",
  "properties": {
    "gn:adm1_name":"Mieken",
    "gn:adm2_name":"Kuwanashi",
    "gn:name":"Aioichou",
    "iso:country":"JP",
    "wof:name":"511-0016",
    "wof:placetype":"postalcode"
},
  "geometry": {"coordinates":[136.6925,35.0669],"type":"Point"}
}