{
  "type": "Feature",
  "properties": {
    "gn:adm1_name":"Niigataken",
    "gn:adm2_name":"Sadogunmanomachi",
    "gn:name":"Yoshioka",
    "iso:country":"JP",
    "wof:name":"952-0312",
    "wof:placetype":"postalcode"
},
  "geometry": {"coordinates":[138.35560000000001,37.9678],"type":"Point"}
}