{
  "type": "Feature",
  "properties": {
    "gn:adm1_name":"Naganoken",
    "gn:adm2_name":"Shimoinaguntakamorimachi",
    "gn:name":"Yoshida",
    "iso:country":"JP",
    "wof:name":"399-3102",
    "wof:placetype":"postalcode"
},
  "geometry": {"coordinates":[137.88069999999999,35.5582],"type":"Point"}
}