{
  "type": "Feature",
  "properties": {
    "gn:adm1_name":"Tokushimaken",
    "gn:adm2_name":"Ananshi",
    "gn:name":"Nanamichou",
    "iso:country":"JP",
    "wof:name":"774-0012",
    "wof:placetype":"postalcode"
},
  "geometry": {"coordinates":[134.67910000000001,33.9217],"type":"Point"}
}