{
  "type": "Feature",
  "properties": {
    "gn:adm1_name":"Kumamotoken",
    "gn:adm2_name":"Kumamotoshi",
    "gn:name":"Imamachi",
    "iso:country":"JP",
    "wof:name":"861-5251",
    "wof:placetype":"postalcode"
},
  "geometry": {"coordinates":[130.6568,32.7672],"type":"Point"}
}