{
  "type": "Feature",
  "properties": {
    "gn:adm1_name":"Ishikawaken",
    "gn:adm2_name":"Kagashi",
    "gn:name":"Daishoujimitsumachi",
    "iso:country":"JP",
    "wof:name":"922-0853",
    "wof:placetype":"postalcode"
},
  "geometry": {"coordinates":[136.2927,36.3031],"type":"Point"}
}