{
  "type": "Feature",
  "properties": {
    "gn:adm1_name":"Kanagawaken",
    "gn:adm2_name":"Yokohamashiminamiku",
    "gn:name":"Mutsumichou",
    "iso:country":"JP",
    "wof:name":"232-0041",
    "wof:placetype":"postalcode"
},
  "geometry": {"coordinates":[139.61920000000001,35.4307],"type":"Point"}
}