{
  "type": "Feature",
  "properties": {
    "gn:adm1_name":"Tochigiken",
    "gn:adm2_name":"Kanumashi",
    "gn:name":"Kamizaimokuchou",
    "iso:country":"JP",
    "wof:name":"322-0065",
    "wof:placetype":"postalcode"
},
  "geometry": {"coordinates":[139.7473,36.569],"type":"Point"}
}