{
  "type": "Feature",
  "properties": {
    "gn:adm1_name":"Kyoutofu",
    "gn:adm2_name":"Kyoutoshifushimiku",
    "gn:name":"Momoyamachouitakurasuou",
    "iso:country":"JP",
    "wof:name":"612-8028",
    "wof:placetype":"postalcode"
},
  "geometry": {"coordinates":[135.77629999999999,34.9333],"type":"Point"}
}