{
  "type": "Feature",
  "properties": {
    "gn:adm1_name":"Hyougoken",
    "gn:adm2_name":"Koubeshisumaku",
    "gn:name":"Myoujinchou",
    "iso:country":"JP",
    "wof:name":"654-0002",
    "wof:placetype":"postalcode"
},
  "geometry": {"coordinates":[135.12819999999999,34.666],"type":"Point"}
}