{
  "type": "Feature",
  "properties": {
    "gn:adm1_name":"Mieken",
    "gn:adm2_name":"Kumanoshi",
    "gn:name":"Asukachoukomata",
    "iso:country":"JP",
    "wof:name":"519-4562",
    "wof:placetype":"postalcode"
},
  "geometry": {"coordinates":[136.11250000000001,33.9589],"type":"Point"}
}