{
  "type": "Feature",
  "properties": {
    "gn:adm1_name":"Yamanashiken",
    "gn:adm2_name":"Minamikomagunminobuchou",
    "gn:name":"Shimoyama",
    "iso:country":"JP",
    "wof:name":"409-2522",
    "wof:placetype":"postalcode"
},
  "geometry": {"coordinates":[138.44200000000001,35.4127],"type":"Point"}
}