{
  "type": "Feature",
  "properties": {
    "gn:adm1_name":"Naganoken",
    "gn:adm2_name":"Chiisagataguntakeshimura",
    "gn:name":"Yori",
    "iso:country":"JP",
    "wof:name":"386-0505",
    "wof:placetype":"postalcode"
},
  "geometry": {"coordinates":[138.2253,36.2599],"type":"Point"}
}