{
  "type": "Feature",
  "properties": {
    "gn:adm1_name":"Chibaken",
    "gn:adm2_name":"Matsudoshi",
    "gn:name":"Nijusseikigaokakakinokichou",
    "iso:country":"JP",
    "wof:name":"271-0088",
    "wof:placetype":"postalcode"
},
  "geometry": {"coordinates":[139.9058,35.772],"type":"Point"}
}