{
  "type": "Feature",
  "properties": {
    "gn:adm1_name":"Saitamaken",
    "gn:adm2_name":"Saitamashiurawaku",
    "gn:name":"Misaki",
    "iso:country":"JP",
    "wof:name":"330-0041",
    "wof:placetype":"postalcode"
},
  "geometry": {"coordinates":[139.65960000000001,35.8914],"type":"Point"}
}