{
  "type": "Feature",
  "properties": {
    "gn:adm1_name":"Toyamaken",
    "gn:adm2_name":"Tonamishi",
    "gn:name":"Wakakusamachi",
    "iso:country":"JP",
    "wof:name":"939-1356",
    "wof:placetype":"postalcode"
},
  "geometry": {"coordinates":[136.9494,36.6436],"type":"Point"}
}