{
  "type": "Feature",
  "properties": {
    "gn:adm1_name":"Fukuokaken",
    "gn:adm2_name":"Ukihagun'Ukihamachi",
    "gn:name":"Ikanikeisaiganaibaai",
    "iso:country":"JP",
    "wof:name":"839-1400",
    "wof:placetype":"postalcode"
},
  "geometry": {"coordinates":[130.76560000000001,33.3423],"type":"Point"}
}