{
  "type": "Feature",
  "properties": {
    "gn:adm1_name":"Oosakafu",
    "gn:adm2_name":"Izumisanoshi",
    "gn:name":"Nodechou",
    "iso:country":"JP",
    "wof:name":"598-0041",
    "wof:placetype":"postalcode"
},
  "geometry": {"coordinates":[135.3107,34.4144],"type":"Point"}
}