{
  "type": "Feature",
  "properties": {
    "gn:adm1_name":"Fukuokaken",
    "gn:adm2_name":"Tagawashi",
    "gn:name":"Kasugamachi",
    "iso:country":"JP",
    "wof:name":"826-0026",
    "wof:placetype":"postalcode"
},
  "geometry": {"coordinates":[130.7963,33.63],"type":"Point"}
}