{
  "type": "Feature",
  "properties": {
    "gn:adm1_name":"Shimaneken",
    "gn:adm2_name":"Hamadashi",
    "gn:name":"Ootsujichou",
    "iso:country":"JP",
    "wof:name":"697-0053",
    "wof:placetype":"postalcode"
},
  "geometry": {"coordinates":[132.071,34.8959],"type":"Point"}
}