{
  "type": "Feature",
  "properties": {
    "gn:adm1_name":"Kagawaken",
    "gn:adm2_name":"Kagawagunshionoechou",
    "gn:name":"Yasuharashimo(Dai1gou)",
    "iso:country":"JP",
    "wof:name":"761-1501",
    "wof:placetype":"postalcode"
},
  "geometry": {"coordinates":[134.05189999999999,34.1913],"type":"Point"}
}