{
  "type": "Feature",
  "properties": {
    "gn:adm1_name":"Kyoutofu",
    "gn:adm2_name":"Kyoutoshisakyouku",
    "gn:name":"Iwakuranishigawarachou",
    "iso:country":"JP",
    "wof:name":"606-0014",
    "wof:placetype":"postalcode"
},
  "geometry": {"coordinates":[135.7824,35.0725],"type":"Point"}
}