{
  "type": "Feature",
  "properties": {
    "gn:adm1_name":"Gifuken",
    "gn:adm2_name":"Mashitagunhagiwarachou",
    "gn:name":"Atotsu",
    "iso:country":"JP",
    "wof:name":"509-2504",
    "wof:placetype":"postalcode"
},
  "geometry": {"coordinates":[137.21899999999999,35.8574],"type":"Point"}
}