{
  "type": "Feature",
  "properties": {
    "gn:adm1_name":"Sagaken",
    "gn:adm2_name":"Tosushi",
    "gn:name":"Iidamachi",
    "iso:country":"JP",
    "wof:name":"841-0022",
    "wof:placetype":"postalcode"
},
  "geometry": {"coordinates":[130.5395,33.3797],"type":"Point"}
}