{
  "type": "Feature",
  "properties": {
    "gn:adm1_name":"Tottoriken",
    "gn:adm2_name":"Tottorishi",
    "gn:name":"Sudu",
    "iso:country":"JP",
    "wof:name":"680-0875",
    "wof:placetype":"postalcode"
},
  "geometry": {"coordinates":[134.22450000000001,35.4677],"type":"Point"}
}