{
  "type": "Feature",
  "properties": {
    "gn:adm1_name":"Niigataken",
    "gn:adm2_name":"Kariwagunnishiyamamachi",
    "gn:name":"Betsuyama",
    "iso:country":"JP",
    "wof:name":"949-4111",
    "wof:placetype":"postalcode"
},
  "geometry": {"coordinates":[138.6917,37.4879],"type":"Point"}
}