{
  "type": "Feature",
  "properties": {
    "gn:adm1_name":"Hyougoken",
    "gn:adm2_name":"Sasayamashi",
    "gn:name":"Ookuma",
    "iso:country":"JP",
    "wof:name":"669-2318",
    "wof:placetype":"postalcode"
},
  "geometry": {"coordinates":[135.2319,35.0869],"type":"Point"}
}