{
  "type": "Feature",
  "properties": {
    "gn:adm1_name":"Shizuokaken",
    "gn:adm2_name":"Shuuchigunmorimachi",
    "gn:name":"Nishimata",
    "iso:country":"JP",
    "wof:name":"437-0207",
    "wof:placetype":"postalcode"
},
  "geometry": {"coordinates":[137.9443,34.8792],"type":"Point"}
}