{
  "type": "Feature",
  "properties": {
    "gn:adm1_name":"Toyamaken",
    "gn:adm2_name":"Nishitonamigunfukuokamachi",
    "gn:name":"Ejiri",
    "iso:country":"JP",
    "wof:name":"939-0128",
    "wof:placetype":"postalcode"
},
  "geometry": {"coordinates":[137.03,36.7622],"type":"Point"}
}