{
  "type": "Feature",
  "properties": {
    "gn:adm1_name":"Gifuken",
    "gn:adm2_name":"Kanigunmitakechou",
    "gn:name":"Furuyashiki",
    "iso:country":"JP",
    "wof:name":"505-0123",
    "wof:placetype":"postalcode"
},
  "geometry": {"coordinates":[137.11250000000001,35.4278],"type":"Point"}
}