{
  "type": "Feature",
  "properties": {
    "gn:adm1_name":"Gifuken",
    "gn:adm2_name":"Hashimagunkasamatsuchou",
    "gn:name":"Izumichou",
    "iso:country":"JP",
    "wof:name":"501-6061",
    "wof:placetype":"postalcode"
},
  "geometry": {"coordinates":[136.75649999999999,35.3648],"type":"Point"}
}