{
  "type": "Feature",
  "properties": {
    "gn:adm1_name":"Oosakafu",
    "gn:adm2_name":"Suitashi",
    "gn:name":"Kishibenaka",
    "iso:country":"JP",
    "wof:name":"564-0002",
    "wof:placetype":"postalcode"
},
  "geometry": {"coordinates":[135.5351,34.7778],"type":"Point"}
}