{
  "type": "Feature",
  "properties": {
    "gn:adm1_name":"Fukuokaken",
    "gn:adm2_name":"Kitakyuushuushimojiku",
    "gn:name":"Ootsumi",
    "iso:country":"JP",
    "wof:name":"801-0811",
    "wof:placetype":"postalcode"
},
  "geometry": {"coordinates":[130.99520000000001,33.9305],"type":"Point"}
}