{
  "type": "Feature",
  "properties": {
    "gn:adm1_name":"Yamaguchiken",
    "gn:adm2_name":"Ubeshi",
    "gn:name":"Aioichou",
    "iso:country":"JP",
    "wof:name":"755-0043",
    "wof:placetype":"postalcode"
},
  "geometry": {"coordinates":[131.245,33.9539],"type":"Point"}
}