{
  "type": "Feature",
  "properties": {
    "gn:adm1_name":"Nagasakiken",
    "gn:adm2_name":"Fukueshi",
    "gn:name":"Konyamachi",
    "iso:country":"JP",
    "wof:name":"853-0016",
    "wof:placetype":"postalcode"
},
  "geometry": {"coordinates":[128.8484,32.6908],"type":"Point"}
}