{
  "type": "Feature",
  "properties": {
    "gn:adm1_name":"Okinawaken",
    "gn:adm2_name":"Nakagamigunyomitanson",
    "gn:name":"Takashiho",
    "iso:country":"JP",
    "wof:name":"904-0323",
    "wof:placetype":"postalcode"
},
  "geometry": {"coordinates":[127.73269999999999,26.4099],"type":"Point"}
}