{
  "type": "Feature",
  "properties": {
    "gn:adm1_name":"Miyagiken",
    "gn:adm2_name":"Kesennumashi",
    "gn:name":"Kannarisawa",
    "iso:country":"JP",
    "wof:name":"988-0831",
    "wof:placetype":"postalcode"
},
  "geometry": {"coordinates":[141.52539999999999,38.9036],"type":"Point"}
}