{
  "type": "Feature",
  "properties": {
    "gn:adm1_name":"Kanagawaken",
    "gn:adm2_name":"Kouzagunsamukawamachi",
    "gn:name":"Koyurugi",
    "iso:country":"JP",
    "wof:name":"253-0102",
    "wof:placetype":"postalcode"
},
  "geometry": {"coordinates":[139.3965,35.3864],"type":"Point"}
}