{
  "type": "Feature",
  "properties": {
    "gn:adm1_name":"Gunmaken",
    "gn:adm2_name":"Agatsumaguntsumagoimura",
    "gn:name":"Kanbara(Fujiwara)",
    "iso:country":"JP",
    "wof:name":"377-1615",
    "wof:placetype":"postalcode"
},
  "geometry": {"coordinates":[138.54939999999999,36.4851],"type":"Point"}
}