{
  "type": "Feature",
  "properties": {
    "gn:adm1_name":"Hyougoken",
    "gn:adm2_name":"Katouguntoujouchou",
    "gn:name":"Minamiyama",
    "iso:country":"JP",
    "wof:name":"673-1341",
    "wof:placetype":"postalcode"
},
  "geometry": {"coordinates":[135.0018,34.91],"type":"Point"}
}