{
  "type": "Feature",
  "properties": {
    "gn:adm1_name":"Shizuokaken",
    "gn:adm2_name":"Iwatashi",
    "gn:name":"Mukasatakenouchi",
    "iso:country":"JP",
    "wof:name":"438-0013",
    "wof:placetype":"postalcode"
},
  "geometry": {"coordinates":[137.8732,34.7636],"type":"Point"}
}