{
  "type": "Feature",
  "properties": {
    "gn:adm1_name":"Fukuokaken",
    "gn:adm2_name":"Buzenshi",
    "gn:name":"Shimokawachi",
    "iso:country":"JP",
    "wof:name":"828-0074",
    "wof:placetype":"postalcode"
},
  "geometry": {"coordinates":[131.0968,33.5623],"type":"Point"}
}