{
  "type": "Feature",
  "properties": {
    "gn:adm1_name":"Fukuokaken",
    "gn:adm2_name":"Kitakyuushuushimojiku",
    "gn:name":"Hikarimachi",
    "iso:country":"JP",
    "wof:name":"800-0046",
    "wof:placetype":"postalcode"
},
  "geometry": {"coordinates":[130.92150000000001,33.8875],"type":"Point"}
}