{
  "type": "Feature",
  "properties": {
    "gn:adm1_name":"Yamagataken",
    "gn:adm2_name":"Kaminoyamashi",
    "gn:name":"Yotsuya",
    "iso:country":"JP",
    "wof:name":"999-3162",
    "wof:placetype":"postalcode"
},
  "geometry": {"coordinates":[140.28540000000001,38.1681],"type":"Point"}
}