{
  "type": "Feature",
  "properties": {
    "gn:adm1_name":"Tottoriken",
    "gn:adm2_name":"Iwamigunfukubeson",
    "gn:name":"Kuritani",
    "iso:country":"JP",
    "wof:name":"689-0111",
    "wof:placetype":"postalcode"
},
  "geometry": {"coordinates":[134.29740000000001,35.5397],"type":"Point"}
}