{
  "type": "Feature",
  "properties": {
    "gn:adm1_name":"Mieken",
    "gn:adm2_name":"Kumanoshi",
    "gn:name":"Kamikawachounagahara",
    "iso:country":"JP",
    "wof:name":"519-4444",
    "wof:placetype":"postalcode"
},
  "geometry": {"coordinates":[136.0127,33.9451],"type":"Point"}
}