{
  "type": "Feature",
  "properties": {
    "gn:adm1_name":"Ishikawaken",
    "gn:adm2_name":"Mattoushi",
    "gn:name":"Fujinokimachi",
    "iso:country":"JP",
    "wof:name":"924-0832",
    "wof:placetype":"postalcode"
},
  "geometry": {"coordinates":[136.5804,36.4835],"type":"Point"}
}