{
  "type": "Feature",
  "properties": {
    "gn:adm1_name":"Hyougoken",
    "gn:adm2_name":"Akoushi",
    "gn:name":"Manago",
    "iso:country":"JP",
    "wof:name":"678-0174",
    "wof:placetype":"postalcode"
},
  "geometry": {"coordinates":[134.4169,34.7665],"type":"Point"}
}