{
  "type": "Feature",
  "properties": {
    "gn:adm1_name":"Kyoutofu",
    "gn:adm2_name":"Kyoutoshikamigyouku",
    "gn:name":"Nishijouzenjichou",
    "iso:country":"JP",
    "wof:name":"602-8326",
    "wof:placetype":"postalcode"
},
  "geometry": {"coordinates":[135.74029999999999,35.0296],"type":"Point"}
}