{
  "type": "Feature",
  "properties": {
    "gn:adm1_name":"Nagasakiken",
    "gn:adm2_name":"Nagasakishi",
    "gn:name":"Chidimachi",
    "iso:country":"JP",
    "wof:name":"851-0245",
    "wof:placetype":"postalcode"
},
  "geometry": {"coordinates":[129.87729999999999,32.6557],"type":"Point"}
}