{
  "type": "Feature",
  "properties": {
    "gn:adm1_name":"Sagaken",
    "gn:adm2_name":"Higashimatsuuragunhamatamachou",
    "gn:name":"Yokotakami",
    "iso:country":"JP",
    "wof:name":"849-5121",
    "wof:placetype":"postalcode"
},
  "geometry": {"coordinates":[130.04390000000001,33.4381],"type":"Point"}
}