{
  "type": "Feature",
  "properties": {
    "gn:adm1_name":"Ehimeken",
    "gn:adm2_name":"Yawatahamashi",
    "gn:name":"Gou",
    "iso:country":"JP",
    "wof:name":"796-8020",
    "wof:placetype":"postalcode"
},
  "geometry": {"coordinates":[132.45920000000001,33.4666],"type":"Point"}
}