{
  "type": "Feature",
  "properties": {
    "gn:adm1_name":"Tokushimaken",
    "gn:adm2_name":"Tokushimashi",
    "gn:name":"Minamidekijimachou",
    "iso:country":"JP",
    "wof:name":"770-0824",
    "wof:placetype":"postalcode"
},
  "geometry": {"coordinates":[134.54560000000001,34.0765],"type":"Point"}
}