{
  "type": "Feature",
  "properties": {
    "gn:adm1_name":"Kagawaken",
    "gn:adm2_name":"Takamatsushi",
    "gn:name":"Kasugachou",
    "iso:country":"JP",
    "wof:name":"761-0101",
    "wof:placetype":"postalcode"
},
  "geometry": {"coordinates":[134.0915,34.3314],"type":"Point"}
}