{
  "type": "Feature",
  "properties": {
    "gn:adm1_name":"Tokushimaken",
    "gn:adm2_name":"Itanogun'Itanochou",
    "gn:name":"Shimonoshou",
    "iso:country":"JP",
    "wof:name":"779-0118",
    "wof:placetype":"postalcode"
},
  "geometry": {"coordinates":[134.45179999999999,34.1234],"type":"Point"}
}