{
  "type": "Feature",
  "properties": {
    "gn:adm1_name":"Chibaken",
    "gn:adm2_name":"Yotsukaidoushi",
    "gn:name":"Onagi",
    "iso:country":"JP",
    "wof:name":"284-0042",
    "wof:placetype":"postalcode"
},
  "geometry": {"coordinates":[140.1816,35.657],"type":"Point"}
}