{
  "type": "Feature",
  "properties": {
    "gn:adm1_name":"Kyoutofu",
    "gn:adm2_name":"Kyoutoshikamigyouku",
    "gn:name":"Kinshachou",
    "iso:country":"JP",
    "wof:name":"602-0876",
    "wof:placetype":"postalcode"
},
  "geometry": {"coordinates":[135.76859999999999,35.0184],"type":"Point"}
}