{
  "type": "Feature",
  "properties": {
    "gn:adm1_name":"Hyougoken",
    "gn:adm2_name":"Mikatagun'Onsenchou",
    "gn:name":"Kirioka",
    "iso:country":"JP",
    "wof:name":"669-6815",
    "wof:placetype":"postalcode"
},
  "geometry": {"coordinates":[134.4854,35.531],"type":"Point"}
}