{
  "type": "Feature",
  "properties": {
    "gn:adm1_name":"Wakayamaken",
    "gn:adm2_name":"Tanabeshi",
    "gn:name":"Honmachi",
    "iso:country":"JP",
    "wof:name":"646-0046",
    "wof:placetype":"postalcode"
},
  "geometry": {"coordinates":[135.37459999999999,33.7337],"type":"Point"}
}