{
  "type": "Feature",
  "properties": {
    "gn:adm1_name":"Ehimeken",
    "gn:adm2_name":"Nishiuwagunmikamechou",
    "gn:name":"Nigyuu",
    "iso:country":"JP",
    "wof:name":"796-0903",
    "wof:placetype":"postalcode"
},
  "geometry": {"coordinates":[132.40379999999999,33.3762],"type":"Point"}
}