{
  "type": "Feature",
  "properties": {
    "gn:adm1_name":"Kyoutofu",
    "gn:adm2_name":"Kasagun'Ooechou",
    "gn:name":"Koumori",
    "iso:country":"JP",
    "wof:name":"620-0301",
    "wof:placetype":"postalcode"
},
  "geometry": {"coordinates":[135.14609999999999,35.391],"type":"Point"}
}