{
  "type": "Feature",
  "properties": {
    "gn:adm1_name":"Okinawaken",
    "gn:adm2_name":"Shimajirigun'Oozatoson",
    "gn:name":"Furugen",
    "iso:country":"JP",
    "wof:name":"901-1207",
    "wof:placetype":"postalcode"
},
  "geometry": {"coordinates":[127.7466,26.1905],"type":"Point"}
}