{
  "type": "Feature",
  "properties": {
    "gn:adm1_name":"Fukushimaken",
    "gn:adm2_name":"Aiduwakamatsushi",
    "gn:name":"Kitatakizawa",
    "iso:country":"JP",
    "wof:name":"965-0015",
    "wof:placetype":"postalcode"
},
  "geometry": {"coordinates":[139.94880000000001,37.5125],"type":"Point"}
}