{
  "type": "Feature",
  "properties": {
    "gn:adm1_name":"Aichiken",
    "gn:adm2_name":"Setoshi",
    "gn:name":"Shimojinyachou",
    "iso:country":"JP",
    "wof:name":"489-0051",
    "wof:placetype":"postalcode"
},
  "geometry": {"coordinates":[137.08940000000001,35.229],"type":"Point"}
}