{
  "type": "Feature",
  "properties": {
    "gn:adm1_name":"Yamanashiken",
    "gn:adm2_name":"Higashiyatsushirogun'Ichinomiyachou",
    "gn:name":"Takeharada",
    "iso:country":"JP",
    "wof:name":"405-0076",
    "wof:placetype":"postalcode"
},
  "geometry": {"coordinates":[138.6738,35.6488],"type":"Point"}
}