{
  "type": "Feature",
  "properties": {
    "gn:adm1_name":"Hyougoken",
    "gn:adm2_name":"Izushigun'Izushichou",
    "gn:name":"Shimotani",
    "iso:country":"JP",
    "wof:name":"668-0211",
    "wof:placetype":"postalcode"
},
  "geometry": {"coordinates":[134.88120000000001,35.4607],"type":"Point"}
}