{
  "type": "Feature",
  "properties": {
    "gn:adm1_name":"Aichiken",
    "gn:adm2_name":"Taharashi",
    "gn:name":"Kousaki",
    "iso:country":"JP",
    "wof:name":"441-3407",
    "wof:placetype":"postalcode"
},
  "geometry": {"coordinates":[137.27979999999999,34.7109],"type":"Point"}
}