{
  "type": "Feature",
  "properties": {
    "gn:adm1_name":"Kagoshimaken",
    "gn:adm2_name":"Ooshimagunkikaichou",
    "gn:name":"Ikanikeisaiganaibaai",
    "iso:country":"JP",
    "wof:name":"891-6200",
    "wof:placetype":"postalcode"
},
  "geometry": {"coordinates":[129.95910000000001,28.297],"type":"Point"}
}