{
  "type": "Feature",
  "properties": {
    "gn:adm1_name":"Shizuokaken",
    "gn:adm2_name":"Yaidushi",
    "gn:name":"Noaki",
    "iso:country":"JP",
    "wof:name":"425-0017",
    "wof:placetype":"postalcode"
},
  "geometry": {"coordinates":[138.33369999999999,34.8978],"type":"Point"}
}