{
  "type": "Feature",
  "properties": {
    "gn:adm1_name":"Fukuiken",
    "gn:adm2_name":"Sabaeshi",
    "gn:name":"Ishoudanichou",
    "iso:country":"JP",
    "wof:name":"916-0076",
    "wof:placetype":"postalcode"
},
  "geometry": {"coordinates":[136.13470000000001,35.9418],"type":"Point"}
}