{
  "type": "Feature",
  "properties": {
    "gn:adm1_name":"Okayamaken",
    "gn:adm2_name":"Kurashikishi",
    "gn:name":"Mizushimaminamisaiwaichou",
    "iso:country":"JP",
    "wof:name":"712-8063",
    "wof:placetype":"postalcode"
},
  "geometry": {"coordinates":[133.7397,34.5383],"type":"Point"}
}