{
  "type": "Feature",
  "properties": {
    "gn:adm1_name":"Ibarakiken",
    "gn:adm2_name":"Mitoshi",
    "gn:name":"Narusawachou",
    "iso:country":"JP",
    "wof:name":"311-4207",
    "wof:placetype":"postalcode"
},
  "geometry": {"coordinates":[140.3998,36.431],"type":"Point"}
}