{
  "type": "Feature",
  "properties": {
    "gn:adm1_name":"Gifuken",
    "gn:adm2_name":"Sekishi",
    "gn:name":"Higashihiyoshichou",
    "iso:country":"JP",
    "wof:name":"501-3883",
    "wof:placetype":"postalcode"
},
  "geometry": {"coordinates":[136.91540000000001,35.4878],"type":"Point"}
}