{
  "type": "Feature",
  "properties": {
    "gn:adm1_name":"Kyoutofu",
    "gn:adm2_name":"Kyoutoshisakyouku",
    "gn:name":"Shimogamotsukamotochou",
    "iso:country":"JP",
    "wof:name":"606-0856",
    "wof:placetype":"postalcode"
},
  "geometry": {"coordinates":[135.77520000000001,35.0453],"type":"Point"}
}