{
  "type": "Feature",
  "properties": {
    "gn:adm1_name":"Aichiken",
    "gn:adm2_name":"Nagoyashishouwaku",
    "gn:name":"Motomiyachou",
    "iso:country":"JP",
    "wof:name":"466-0851",
    "wof:placetype":"postalcode"
},
  "geometry": {"coordinates":[136.94669999999999,35.1577],"type":"Point"}
}