{
  "type": "Feature",
  "properties": {
    "gn:adm1_name":"Shigaken",
    "gn:adm2_name":"Moriyamashi",
    "gn:name":"Amurachou",
    "iso:country":"JP",
    "wof:name":"524-0035",
    "wof:placetype":"postalcode"
},
  "geometry": {"coordinates":[135.99189999999999,35.0407],"type":"Point"}
}