{
  "type": "Feature",
  "properties": {
    "gn:adm1_name":"Gifuken",
    "gn:adm2_name":"Nakatsugawashi",
    "gn:name":"Naegi",
    "iso:country":"JP",
    "wof:name":"508-0101",
    "wof:placetype":"postalcode"
},
  "geometry": {"coordinates":[137.46899999999999,35.5253],"type":"Point"}
}