{
  "type": "Feature",
  "properties": {
    "gn:adm1_name":"Kumamotoken",
    "gn:adm2_name":"Kumagunsagaramura",
    "gn:name":"Kawabe",
    "iso:country":"JP",
    "wof:name":"868-0093",
    "wof:placetype":"postalcode"
},
  "geometry": {"coordinates":[130.82329999999999,32.2601],"type":"Point"}
}