{
  "type": "Feature",
  "properties": {
    "gn:adm1_name":"Hyougoken",
    "gn:adm2_name":"Koubeshichuuouku",
    "gn:name":"Tachibanadoori",
    "iso:country":"JP",
    "wof:name":"650-0016",
    "wof:placetype":"postalcode"
},
  "geometry": {"coordinates":[135.1755,34.6818],"type":"Point"}
}