{
  "type": "Feature",
  "properties": {
    "gn:adm1_name":"Kumamotoken",
    "gn:adm2_name":"Ashikitaguntanouramachi",
    "gn:name":"Imuta",
    "iso:country":"JP",
    "wof:name":"869-5307",
    "wof:placetype":"postalcode"
},
  "geometry": {"coordinates":[130.5239,32.397],"type":"Point"}
}