{
  "type": "Feature",
  "properties": {
    "gn:adm1_name":"Hyougoken",
    "gn:adm2_name":"Asagogunwadayamachou",
    "gn:name":"Tono",
    "iso:country":"JP",
    "wof:name":"669-5255",
    "wof:placetype":"postalcode"
},
  "geometry": {"coordinates":[134.82079999999999,35.3077],"type":"Point"}
}