{
  "type": "Feature",
  "properties": {
    "gn:adm1_name":"Fukuokaken",
    "gn:adm2_name":"Ookawashi",
    "gn:name":"Goubaru",
    "iso:country":"JP",
    "wof:name":"831-0028",
    "wof:placetype":"postalcode"
},
  "geometry": {"coordinates":[130.38999999999999,33.2069],"type":"Point"}
}