{
  "type": "Feature",
  "properties": {
    "gn:adm1_name":"Gifuken",
    "gn:adm2_name":"Mugigunkaminohomura",
    "gn:name":"Kaminohomuranotsuginibanchigakurubaai",
    "iso:country":"JP",
    "wof:name":"501-3601",
    "wof:placetype":"postalcode"
},
  "geometry": {"coordinates":[137.03909999999999,35.6271],"type":"Point"}
}