{
  "type": "Feature",
  "properties": {
    "gn:adm1_name":"Kyoutofu",
    "gn:adm2_name":"Kyoutoshinakagyouku",
    "gn:name":"Moriyamachou",
    "iso:country":"JP",
    "wof:name":"604-0953",
    "wof:placetype":"postalcode"
},
  "geometry": {"coordinates":[135.76509999999999,35.0116],"type":"Point"}
}