{
  "type": "Feature",
  "properties": {
    "gn:adm1_name":"Aichiken",
    "gn:adm2_name":"Toyotashi",
    "gn:name":"Kakimotochou",
    "iso:country":"JP",
    "wof:name":"471-0855",
    "wof:placetype":"postalcode"
},
  "geometry": {"coordinates":[137.1242,35.0732],"type":"Point"}
}