{
  "type": "Feature",
  "properties": {
    "gn:adm1_name":"Ishikawaken",
    "gn:adm2_name":"Kanazawashi",
    "gn:name":"Teradumachi",
    "iso:country":"JP",
    "wof:name":"920-1315",
    "wof:placetype":"postalcode"
},
  "geometry": {"coordinates":[136.727,36.4742],"type":"Point"}
}