{
  "type": "Feature",
  "properties": {
    "gn:adm1_name":"Aichiken",
    "gn:adm2_name":"Nagoyashichikusaku",
    "gn:name":"Shin'Ikechou",
    "iso:country":"JP",
    "wof:name":"464-0027",
    "wof:placetype":"postalcode"
},
  "geometry": {"coordinates":[136.97479999999999,35.1619],"type":"Point"}
}