{
  "type": "Feature",
  "properties": {
    "gn:adm1_name":"Chibaken",
    "gn:adm2_name":"Katorigun'Omigawamachi",
    "gn:name":"Kinouchimushihatakamikoboriiriaichioodaira",
    "iso:country":"JP",
    "wof:name":"289-0308",
    "wof:placetype":"postalcode"
},
  "geometry": {"coordinates":[140.55189999999999,35.8607],"type":"Point"}
}