{
  "type": "Feature",
  "properties": {
    "gn:adm1_name":"Saitamaken",
    "gn:adm2_name":"Tokorozawashi",
    "gn:name":"Kume",
    "iso:country":"JP",
    "wof:name":"359-1131",
    "wof:placetype":"postalcode"
},
  "geometry": {"coordinates":[139.465,35.7798],"type":"Point"}
}