{
  "type": "Feature",
  "properties": {
    "gn:adm1_name":"Kumamotoken",
    "gn:adm2_name":"Araoshi",
    "gn:name":"Kawanobori(Sonota)",
    "iso:country":"JP",
    "wof:name":"864-0131",
    "wof:placetype":"postalcode"
},
  "geometry": {"coordinates":[130.47370000000001,32.9729],"type":"Point"}
}