{
  "type": "Feature",
  "properties": {
    "gn:adm1_name":"Miyazakiken",
    "gn:adm2_name":"Miyazakishi",
    "gn:name":"Ooyodo",
    "iso:country":"JP",
    "wof:name":"880-0902",
    "wof:placetype":"postalcode"
},
  "geometry": {"coordinates":[131.422,31.8977],"type":"Point"}
}