{
  "type": "Feature",
  "properties": {
    "gn:adm1_name":"Gifuken",
    "gn:adm2_name":"Enashi",
    "gn:name":"Osashimachoushouge",
    "iso:country":"JP",
    "wof:name":"509-7203",
    "wof:placetype":"postalcode"
},
  "geometry": {"coordinates":[137.4169,35.4465],"type":"Point"}
}