{
  "type": "Feature",
  "properties": {
    "gn:adm1_name":"Kyoutofu",
    "gn:adm2_name":"Kyoutoshinishikyouku",
    "gn:name":"Katsuranozatochou",
    "iso:country":"JP",
    "wof:name":"615-8073",
    "wof:placetype":"postalcode"
},
  "geometry": {"coordinates":[135.70410000000001,34.98],"type":"Point"}
}