{
  "type": "Feature",
  "properties": {
    "gn:adm1_name":"Fukushimaken",
    "gn:adm2_name":"Ishikawagun'Ishikawamachi",
    "gn:name":"Minamiyamagata",
    "iso:country":"JP",
    "wof:name":"963-7812",
    "wof:placetype":"postalcode"
},
  "geometry": {"coordinates":[140.47620000000001,37.1133],"type":"Point"}
}