{
  "type": "Feature",
  "properties": {
    "gn:adm1_name":"Niigataken",
    "gn:adm2_name":"Niitsushi",
    "gn:name":"Kawane",
    "iso:country":"JP",
    "wof:name":"956-0055",
    "wof:placetype":"postalcode"
},
  "geometry": {"coordinates":[139.07599999999999,37.7901],"type":"Point"}
}