{
  "type": "Feature",
  "properties": {
    "gn:adm1_name":"Ishikawaken",
    "gn:adm2_name":"Kagashi",
    "gn:name":"Hakomiyamachi",
    "iso:country":"JP",
    "wof:name":"922-0303",
    "wof:placetype":"postalcode"
},
  "geometry": {"coordinates":[136.41079999999999,36.3296],"type":"Point"}
}