{
  "type": "Feature",
  "properties": {
    "gn:adm1_name":"Fukuokaken",
    "gn:adm2_name":"Ukihaguntanushimarumachi",
    "gn:name":"Takatori",
    "iso:country":"JP",
    "wof:name":"839-1202",
    "wof:placetype":"postalcode"
},
  "geometry": {"coordinates":[130.72569999999999,33.3456],"type":"Point"}
}