{
  "type": "Feature",
  "properties": {
    "gn:adm1_name":"Niigataken",
    "gn:adm2_name":"Santougunkoshijimachi",
    "gn:name":"Iwano(Sonota)",
    "iso:country":"JP",
    "wof:name":"949-5405",
    "wof:placetype":"postalcode"
},
  "geometry": {"coordinates":[138.80099999999999,37.374],"type":"Point"}
}