{
  "type": "Feature",
  "properties": {
    "gn:adm1_name":"Fukuokaken",
    "gn:adm2_name":"Yanagawashi",
    "gn:name":"Koga",
    "iso:country":"JP",
    "wof:name":"832-0082",
    "wof:placetype":"postalcode"
},
  "geometry": {"coordinates":[130.3878,33.1599],"type":"Point"}
}