{
  "type": "Feature",
  "properties": {
    "gn:adm1_name":"Shigaken",
    "gn:adm2_name":"Kusatsushi",
    "gn:name":"Shibukawa",
    "iso:country":"JP",
    "wof:name":"525-0026",
    "wof:placetype":"postalcode"
},
  "geometry": {"coordinates":[135.96600000000001,35.0242],"type":"Point"}
}