{
  "type": "Feature",
  "properties": {
    "gn:adm1_name":"Fukushimaken",
    "gn:adm2_name":"Iwakishi",
    "gn:name":"Tairatsurugai",
    "iso:country":"JP",
    "wof:name":"970-0227",
    "wof:placetype":"postalcode"
},
  "geometry": {"coordinates":[140.9496,37.0198],"type":"Point"}
}