{
  "type": "Feature",
  "properties": {
    "gn:adm1_name":"Niigataken",
    "gn:adm2_name":"Nakakanbaragunkosudomachi",
    "gn:name":"Suita",
    "iso:country":"JP",
    "wof:name":"956-0123",
    "wof:placetype":"postalcode"
},
  "geometry": {"coordinates":[139.0659,37.7303],"type":"Point"}
}