{
  "type": "Feature",
  "properties": {
    "gn:adm1_name":"Ibarakiken",
    "gn:adm2_name":"Moriyashi",
    "gn:name":"Oogashiwa",
    "iso:country":"JP",
    "wof:name":"302-0116",
    "wof:placetype":"postalcode"
},
  "geometry": {"coordinates":[139.97450000000001,35.9444],"type":"Point"}
}