{
  "type": "Feature",
  "properties": {
    "gn:adm1_name":"Chibaken",
    "gn:adm2_name":"Ichikawashi",
    "gn:name":"Motokitakata",
    "iso:country":"JP",
    "wof:name":"272-0816",
    "wof:placetype":"postalcode"
},
  "geometry": {"coordinates":[139.94540000000001,35.7283],"type":"Point"}
}