{
  "type": "Feature",
  "properties": {
    "gn:adm1_name":"Hyougoken",
    "gn:adm2_name":"Onoshi",
    "gn:name":"Wakimotochou",
    "iso:country":"JP",
    "wof:name":"675-1305",
    "wof:placetype":"postalcode"
},
  "geometry": {"coordinates":[135.0111,34.8625],"type":"Point"}
}