{
  "type": "Feature",
  "properties": {
    "gn:adm1_name":"Tochigiken",
    "gn:adm2_name":"Ootawarashi",
    "gn:name":"Kajiya",
    "iso:country":"JP",
    "wof:name":"324-0046",
    "wof:placetype":"postalcode"
},
  "geometry": {"coordinates":[139.99959999999999,36.8537],"type":"Point"}
}