{
  "type": "Feature",
  "properties": {
    "gn:adm1_name":"Kagoshimaken",
    "gn:adm2_name":"Kasedashi",
    "gn:name":"Murahara",
    "iso:country":"JP",
    "wof:name":"897-0001",
    "wof:placetype":"postalcode"
},
  "geometry": {"coordinates":[130.32740000000001,31.4233],"type":"Point"}
}