{
  "type": "Feature",
  "properties": {
    "gn:adm1_name":"Kagawaken",
    "gn:adm2_name":"Zentsuujishi",
    "gn:name":"Ikanohonmachi",
    "iso:country":"JP",
    "wof:name":"765-0014",
    "wof:placetype":"postalcode"
},
  "geometry": {"coordinates":[133.78639999999999,34.2245],"type":"Point"}
}