{
  "type": "Feature",
  "properties": {
    "gn:adm1_name":"Aichiken",
    "gn:adm2_name":"Inazawashi",
    "gn:name":"Nishijimachou",
    "iso:country":"JP",
    "wof:name":"492-8329",
    "wof:placetype":"postalcode"
},
  "geometry": {"coordinates":[136.74340000000001,35.2584],"type":"Point"}
}