{
  "type": "Feature",
  "properties": {
    "gn:adm1_name":"Kanagawaken",
    "gn:adm2_name":"Odawarashi",
    "gn:name":"Ishibashi",
    "iso:country":"JP",
    "wof:name":"250-0022",
    "wof:placetype":"postalcode"
},
  "geometry": {"coordinates":[139.1396,35.225],"type":"Point"}
}