{
  "type": "Feature",
  "properties": {
    "gn:adm1_name":"Saitamaken",
    "gn:adm2_name":"Minamisaitamagunmiyashiromachi",
    "gn:name":"Kokunou",
    "iso:country":"JP",
    "wof:name":"345-0834",
    "wof:placetype":"postalcode"
},
  "geometry": {"coordinates":[139.69489999999999,36.0437],"type":"Point"}
}