{
  "type": "Feature",
  "properties": {
    "gn:adm1_name":"Aichiken",
    "gn:adm2_name":"Kitashitaraguntoyonemura",
    "gn:name":"Misawa",
    "iso:country":"JP",
    "wof:name":"449-0401",
    "wof:placetype":"postalcode"
},
  "geometry": {"coordinates":[137.7353,35.1894],"type":"Point"}
}