{
  "type": "Feature",
  "properties": {
    "gn:adm1_name":"Fukuiken",
    "gn:adm2_name":"Fukuishi",
    "gn:name":"Kagetsu",
    "iso:country":"JP",
    "wof:name":"910-0022",
    "wof:placetype":"postalcode"
},
  "geometry": {"coordinates":[136.20769999999999,36.0696],"type":"Point"}
}