{
  "type": "Feature",
  "properties": {
    "gn:adm1_name":"Fukushimaken",
    "gn:adm2_name":"Dategunkoorimachi",
    "gn:name":"Higashidan",
    "iso:country":"JP",
    "wof:name":"969-1606",
    "wof:placetype":"postalcode"
},
  "geometry": {"coordinates":[140.5198,37.8531],"type":"Point"}
}