{
  "type": "Feature",
  "properties": {
    "gn:adm1_name":"Gifuken",
    "gn:adm2_name":"Tajimishi",
    "gn:name":"Onadachouiwagane",
    "iso:country":"JP",
    "wof:name":"507-0005",
    "wof:placetype":"postalcode"
},
  "geometry": {"coordinates":[137.13319999999999,35.3676],"type":"Point"}
}