{
  "type": "Feature",
  "properties": {
    "gn:adm1_name":"Fukushimaken",
    "gn:adm2_name":"Dategundatemachi",
    "gn:name":"Yashikima",
    "iso:country":"JP",
    "wof:name":"960-0448",
    "wof:placetype":"postalcode"
},
  "geometry": {"coordinates":[140.49799999999999,37.8161],"type":"Point"}
}