{
  "type": "Feature",
  "properties": {
    "gn:adm1_name":"Niigataken",
    "gn:adm2_name":"Kitakanbaragunkajikawamura",
    "gn:name":"Kanayama",
    "iso:country":"JP",
    "wof:name":"959-2473",
    "wof:placetype":"postalcode"
},
  "geometry": {"coordinates":[139.38839999999999,38.0131],"type":"Point"}
}