{
  "type": "Feature",
  "properties": {
    "gn:adm1_name":"Gifuken",
    "gn:adm2_name":"Gifushi",
    "gn:name":"Nagaraooji",
    "iso:country":"JP",
    "wof:name":"502-0031",
    "wof:placetype":"postalcode"
},
  "geometry": {"coordinates":[136.7756,35.4448],"type":"Point"}
}