{
  "type": "Feature",
  "properties": {
    "gn:adm1_name":"Saitamaken",
    "gn:adm2_name":"Kawagoeshi",
    "gn:name":"Suna",
    "iso:country":"JP",
    "wof:name":"350-1133",
    "wof:placetype":"postalcode"
},
  "geometry": {"coordinates":[139.49760000000001,35.8942],"type":"Point"}
}