{
  "type": "Feature",
  "properties": {
    "gn:adm1_name":"Fukushimaken",
    "gn:adm2_name":"Kitakatashi",
    "gn:name":"Machinishi",
    "iso:country":"JP",
    "wof:name":"966-0857",
    "wof:placetype":"postalcode"
},
  "geometry": {"coordinates":[139.864,37.6473],"type":"Point"}
}