{
  "type": "Feature",
  "properties": {
    "gn:adm1_name":"Tottoriken",
    "gn:adm2_name":"Kurayoshishi",
    "gn:name":"Owara",
    "iso:country":"JP",
    "wof:name":"682-0904",
    "wof:placetype":"postalcode"
},
  "geometry": {"coordinates":[133.77340000000001,35.457],"type":"Point"}
}