{
  "type": "Feature",
  "properties": {
    "gn:adm1_name":"Kagawaken",
    "gn:adm2_name":"Marugameshi",
    "gn:name":"Hiroshimachouenoura",
    "iso:country":"JP",
    "wof:name":"763-0102",
    "wof:placetype":"postalcode"
},
  "geometry": {"coordinates":[133.71530000000001,34.3657],"type":"Point"}
}