{
  "type": "Feature",
  "properties": {
    "gn:adm1_name":"Miyagiken",
    "gn:adm2_name":"Tagajoushi",
    "gn:name":"Machimae",
    "iso:country":"JP",
    "wof:name":"985-0845",
    "wof:placetype":"postalcode"
},
  "geometry": {"coordinates":[141.00460000000001,38.2851],"type":"Point"}
}