{
  "type": "Feature",
  "properties": {
    "gn:adm1_name":"Niigataken",
    "gn:adm2_name":"Jouetsushi",
    "gn:name":"Nishiyoshio",
    "iso:country":"JP",
    "wof:name":"949-1731",
    "wof:placetype":"postalcode"
},
  "geometry": {"coordinates":[138.1285,37.1209],"type":"Point"}
}