{
  "type": "Feature",
  "properties": {
    "gn:adm1_name":"Kanagawaken",
    "gn:adm2_name":"Yokohamashikanagawaku",
    "gn:name":"Kiribatake",
    "iso:country":"JP",
    "wof:name":"221-0832",
    "wof:placetype":"postalcode"
},
  "geometry": {"coordinates":[139.62700000000001,35.4735],"type":"Point"}
}