{
  "type": "Feature",
  "properties": {
    "gn:adm1_name":"Oosakafu",
    "gn:adm2_name":"Kawachinaganoshi",
    "gn:name":"Amanochou",
    "iso:country":"JP",
    "wof:name":"586-0086",
    "wof:placetype":"postalcode"
},
  "geometry": {"coordinates":[135.5307,34.4314],"type":"Point"}
}