{
  "type": "Feature",
  "properties": {
    "gn:adm1_name":"Kumamotoken",
    "gn:adm2_name":"Amakusagun'Ooyanomachi",
    "gn:name":"Iwa",
    "iso:country":"JP",
    "wof:name":"869-3604",
    "wof:placetype":"postalcode"
},
  "geometry": {"coordinates":[130.47219999999999,32.5695],"type":"Point"}
}