{
  "type": "Feature",
  "properties": {
    "gn:adm1_name":"Fukushimaken",
    "gn:adm2_name":"Oonumagun'Aiduhongoumachi",
    "gn:name":"Teranomae",
    "iso:country":"JP",
    "wof:name":"969-6122",
    "wof:placetype":"postalcode"
},
  "geometry": {"coordinates":[139.89189999999999,37.4503],"type":"Point"}
}