{
  "type": "Feature",
  "properties": {
    "gn:adm1_name":"Okayamaken",
    "gn:adm2_name":"Asakuchigunkamogatachou",
    "gn:name":"Jitoukami",
    "iso:country":"JP",
    "wof:name":"719-0233",
    "wof:placetype":"postalcode"
},
  "geometry": {"coordinates":[133.59020000000001,34.5573],"type":"Point"}
}