{
  "type": "Feature",
  "properties": {
    "gn:adm1_name":"Fukuiken",
    "gn:adm2_name":"Nanjougun'Imajouchou",
    "gn:name":"Arai",
    "iso:country":"JP",
    "wof:name":"919-0123",
    "wof:placetype":"postalcode"
},
  "geometry": {"coordinates":[136.19749999999999,35.7428],"type":"Point"}
}