{
  "type": "Feature",
  "properties": {
    "gn:adm1_name":"Aichiken",
    "gn:adm2_name":"Nagoyashimeitouku",
    "gn:name":"Sakuragaoka",
    "iso:country":"JP",
    "wof:name":"465-0096",
    "wof:placetype":"postalcode"
},
  "geometry": {"coordinates":[136.9898,35.1693],"type":"Point"}
}