{
  "type": "Feature",
  "properties": {
    "gn:adm1_name":"Saitamaken",
    "gn:adm2_name":"Fujimishi",
    "gn:name":"Tsuruma",
    "iso:country":"JP",
    "wof:name":"354-0021",
    "wof:placetype":"postalcode"
},
  "geometry": {"coordinates":[139.54589999999999,35.8468],"type":"Point"}
}