{
  "type": "Feature",
  "properties": {
    "gn:adm1_name":"Sagaken",
    "gn:adm2_name":"Imarishi",
    "gn:name":"Kurogawachoumuta",
    "iso:country":"JP",
    "wof:name":"848-0143",
    "wof:placetype":"postalcode"
},
  "geometry": {"coordinates":[129.89879999999999,33.312],"type":"Point"}
}