{
  "type": "Feature",
  "properties": {
    "gn:adm1_name":"Toyamaken",
    "gn:adm2_name":"Toyamashi",
    "gn:name":"Mizuhashitachimachi",
    "iso:country":"JP",
    "wof:name":"939-0526",
    "wof:placetype":"postalcode"
},
  "geometry": {"coordinates":[137.31039999999999,36.7533],"type":"Point"}
}