{
  "type": "Feature",
  "properties": {
    "gn:adm1_name":"Fukuiken",
    "gn:adm2_name":"Fukuishi",
    "gn:name":"Nishiitagakichou",
    "iso:country":"JP",
    "wof:name":"918-8102",
    "wof:placetype":"postalcode"
},
  "geometry": {"coordinates":[136.22839999999999,36.0527],"type":"Point"}
}