{
  "type": "Feature",
  "properties": {
    "gn:adm1_name":"Nagasakiken",
    "gn:adm2_name":"Saseboshi",
    "gn:name":"Susamachi",
    "iso:country":"JP",
    "wof:name":"857-0812",
    "wof:placetype":"postalcode"
},
  "geometry": {"coordinates":[129.73099999999999,33.1767],"type":"Point"}
}