{
  "type": "Feature",
  "properties": {
    "gn:adm1_name":"Yamaguchiken",
    "gn:adm2_name":"Shimonosekishi",
    "gn:name":"Daigakuchou",
    "iso:country":"JP",
    "wof:name":"751-0831",
    "wof:placetype":"postalcode"
},
  "geometry": {"coordinates":[130.93520000000001,33.9891],"type":"Point"}
}