{
  "type": "Feature",
  "properties": {
    "gn:adm1_name":"Naraken",
    "gn:adm2_name":"Yoshinogunyoshinochou",
    "gn:name":"Misono",
    "iso:country":"JP",
    "wof:name":"639-3444",
    "wof:placetype":"postalcode"
},
  "geometry": {"coordinates":[135.88810000000001,34.3779],"type":"Point"}
}