{
  "type": "Feature",
  "properties": {
    "gn:adm1_name":"Tochigiken",
    "gn:adm2_name":"Asoguntanumamachi",
    "gn:name":"Yoshimizuekimae",
    "iso:country":"JP",
    "wof:name":"327-0315",
    "wof:placetype":"postalcode"
},
  "geometry": {"coordinates":[139.577,36.3449],"type":"Point"}
}