{
  "type": "Feature",
  "properties": {
    "gn:adm1_name":"Aichiken",
    "gn:adm2_name":"Higashikamogun'Inabuchou",
    "gn:name":"Otagi",
    "iso:country":"JP",
    "wof:name":"441-2525",
    "wof:placetype":"postalcode"
},
  "geometry": {"coordinates":[137.453,35.186],"type":"Point"}
}