{
  "type": "Feature",
  "properties": {
    "gn:adm1_name":"Niigataken",
    "gn:adm2_name":"Nakakubikigunkakizakimachi",
    "gn:name":"Higashiyokoyama",
    "iso:country":"JP",
    "wof:name":"949-3364",
    "wof:placetype":"postalcode"
},
  "geometry": {"coordinates":[138.48060000000001,37.2245],"type":"Point"}
}