{
  "type": "Feature",
  "properties": {
    "gn:adm1_name":"Chibaken",
    "gn:adm2_name":"Yotsukaidoushi",
    "gn:name":"Yoshioka",
    "iso:country":"JP",
    "wof:name":"284-0032",
    "wof:placetype":"postalcode"
},
  "geometry": {"coordinates":[140.19569999999999,35.6437],"type":"Point"}
}