{
  "type": "Feature",
  "properties": {
    "gn:adm1_name":"Fukuiken",
    "gn:adm2_name":"Nyuugun'Otachou",
    "gn:name":"Taira",
    "iso:country":"JP",
    "wof:name":"916-0224",
    "wof:placetype":"postalcode"
},
  "geometry": {"coordinates":[136.05289999999999,35.9465],"type":"Point"}
}