{
  "type": "Feature",
  "properties": {
    "gn:adm1_name":"Tottoriken",
    "gn:adm2_name":"Saihakugun'Aimichou",
    "gn:name":"Maruyama",
    "iso:country":"JP",
    "wof:name":"683-0211",
    "wof:placetype":"postalcode"
},
  "geometry": {"coordinates":[133.36779999999999,35.3777],"type":"Point"}
}