{
  "type": "Feature",
  "properties": {
    "gn:adm1_name":"Miyagiken",
    "gn:adm2_name":"Sendaishimiyaginoku",
    "gn:name":"Odawarayamamotochou",
    "iso:country":"JP",
    "wof:name":"983-0817",
    "wof:placetype":"postalcode"
},
  "geometry": {"coordinates":[140.8871,38.2648],"type":"Point"}
}