{
  "type": "Feature",
  "properties": {
    "gn:adm1_name":"Kyoutofu",
    "gn:adm2_name":"Kyoutoshinakagyouku",
    "gn:name":"Mibunishidoinouchichou",
    "iso:country":"JP",
    "wof:name":"604-8847",
    "wof:placetype":"postalcode"
},
  "geometry": {"coordinates":[135.73339999999999,35.0024],"type":"Point"}
}