{
  "type": "Feature",
  "properties": {
    "gn:adm1_name":"Niigataken",
    "gn:adm2_name":"Sanjoushi",
    "gn:name":"Higashiuradate",
    "iso:country":"JP",
    "wof:name":"955-0081",
    "wof:placetype":"postalcode"
},
  "geometry": {"coordinates":[138.95920000000001,37.6362],"type":"Point"}
}