{
  "type": "Feature",
  "properties": {
    "gn:adm1_name":"Naraken",
    "gn:adm2_name":"Kitakatsuragigunkouryouchou",
    "gn:name":"Oono",
    "iso:country":"JP",
    "wof:name":"635-0803",
    "wof:placetype":"postalcode"
},
  "geometry": {"coordinates":[135.745,34.569],"type":"Point"}
}