{
  "type": "Feature",
  "properties": {
    "gn:adm1_name":"Shizuokaken",
    "gn:adm2_name":"Fujinomiyashi",
    "gn:name":"Chuuouchou",
    "iso:country":"JP",
    "wof:name":"418-0065",
    "wof:placetype":"postalcode"
},
  "geometry": {"coordinates":[138.61519999999999,35.2236],"type":"Point"}
}