{
  "type": "Feature",
  "properties": {
    "gn:adm1_name":"Hyougoken",
    "gn:adm2_name":"Akashishi",
    "gn:name":"Ookuradanikariguchi",
    "iso:country":"JP",
    "wof:name":"673-0863",
    "wof:placetype":"postalcode"
},
  "geometry": {"coordinates":[135.01830000000001,34.6457],"type":"Point"}
}