{
  "type": "Feature",
  "properties": {
    "gn:adm1_name":"Fukuokaken",
    "gn:adm2_name":"Kurumeshi",
    "gn:name":"Miyanojinmachiwakamatsu",
    "iso:country":"JP",
    "wof:name":"839-0804",
    "wof:placetype":"postalcode"
},
  "geometry": {"coordinates":[130.55799999999999,33.342],"type":"Point"}
}