{
  "type": "Feature",
  "properties": {
    "gn:adm1_name":"Aichiken",
    "gn:adm2_name":"Nagoyashimizuhoku",
    "gn:name":"Meizenchou",
    "iso:country":"JP",
    "wof:name":"467-0852",
    "wof:placetype":"postalcode"
},
  "geometry": {"coordinates":[136.92089999999999,35.1131],"type":"Point"}
}