{
  "type": "Feature",
  "properties": {
    "gn:adm1_name":"Miyagiken",
    "gn:adm2_name":"Kuriharagunkannarichou",
    "gn:name":"Tateshita",
    "iso:country":"JP",
    "wof:name":"989-5161",
    "wof:placetype":"postalcode"
},
  "geometry": {"coordinates":[141.08150000000001,38.8136],"type":"Point"}
}