{
  "type": "Feature",
  "properties": {
    "gn:adm1_name":"Sagaken",
    "gn:adm2_name":"Karatsushi",
    "gn:name":"Egawamachi",
    "iso:country":"JP",
    "wof:name":"847-0853",
    "wof:placetype":"postalcode"
},
  "geometry": {"coordinates":[129.96360000000001,33.4534],"type":"Point"}
}