{
  "type": "Feature",
  "properties": {
    "gn:adm1_name":"Gunmaken",
    "gn:adm2_name":"Tatebayashishi",
    "gn:name":"Narushimachou",
    "iso:country":"JP",
    "wof:name":"374-0055",
    "wof:placetype":"postalcode"
},
  "geometry": {"coordinates":[139.5052,36.2478],"type":"Point"}
}