{
  "type": "Feature",
  "properties": {
    "gn:adm1_name":"Hyougoken",
    "gn:adm2_name":"Hikamigunsannanchou",
    "gn:name":"Ikedani",
    "iso:country":"JP",
    "wof:name":"669-3125",
    "wof:placetype":"postalcode"
},
  "geometry": {"coordinates":[135.05119999999999,35.0821],"type":"Point"}
}