{
  "type": "Feature",
  "properties": {
    "gn:adm1_name":"Aichiken",
    "gn:adm2_name":"Setoshi",
    "gn:name":"Hachimanchou",
    "iso:country":"JP",
    "wof:name":"489-0862",
    "wof:placetype":"postalcode"
},
  "geometry": {"coordinates":[137.1036,35.2024],"type":"Point"}
}