{
  "type": "Feature",
  "properties": {
    "gn:adm1_name":"Kanagawaken",
    "gn:adm2_name":"Yokohamashinakaku",
    "gn:name":"Honmokufutou",
    "iso:country":"JP",
    "wof:name":"231-0811",
    "wof:placetype":"postalcode"
},
  "geometry": {"coordinates":[139.67310000000001,35.4352],"type":"Point"}
}