{
  "type": "Feature",
  "properties": {
    "gn:adm1_name":"Niigataken",
    "gn:adm2_name":"Nakakubikigunnakagoumura",
    "gn:name":"Fujisawa",
    "iso:country":"JP",
    "wof:name":"949-2302",
    "wof:placetype":"postalcode"
},
  "geometry": {"coordinates":[138.23099999999999,36.989],"type":"Point"}
}