{
  "type": "Feature",
  "properties": {
    "gn:adm1_name":"Mieken",
    "gn:adm2_name":"Matsusakashi",
    "gn:name":"Miyamachi",
    "iso:country":"JP",
    "wof:name":"515-0015",
    "wof:placetype":"postalcode"
},
  "geometry": {"coordinates":[136.54239999999999,34.5762],"type":"Point"}
}