{
  "type": "Feature",
  "properties": {
    "gn:adm1_name":"Miyagiken",
    "gn:adm2_name":"Sendaishiwakabayashiku",
    "gn:name":"Minamiishikirimachi",
    "iso:country":"JP",
    "wof:name":"984-0804",
    "wof:placetype":"postalcode"
},
  "geometry": {"coordinates":[140.88999999999999,38.2421],"type":"Point"}
}