{
  "type": "Feature",
  "properties": {
    "gn:adm1_name":"Kouchiken",
    "gn:adm2_name":"Takaokagunnakatosachou",
    "gn:name":"Ikanikeisaiganaibaai",
    "iso:country":"JP",
    "wof:name":"789-1300",
    "wof:placetype":"postalcode"
},
  "geometry": {"coordinates":[133.2311,33.3119],"type":"Point"}
}