{
  "type": "Feature",
  "properties": {
    "gn:adm1_name":"Oosakafu",
    "gn:adm2_name":"Shijounawateshi",
    "gn:name":"Kiyotakinakamachi",
    "iso:country":"JP",
    "wof:name":"575-0061",
    "wof:placetype":"postalcode"
},
  "geometry": {"coordinates":[135.65389999999999,34.7404],"type":"Point"}
}