{
  "type": "Feature",
  "properties": {
    "gn:adm1_name":"Kanagawaken",
    "gn:adm2_name":"Fujisawashi",
    "gn:name":"Hananoki",
    "iso:country":"JP",
    "wof:name":"251-0874",
    "wof:placetype":"postalcode"
},
  "geometry": {"coordinates":[139.47569999999999,35.3521],"type":"Point"}
}