{
  "type": "Feature",
  "properties": {
    "gn:adm1_name":"Shizuokaken",
    "gn:adm2_name":"Hamamatsushi",
    "gn:name":"Itayamachihamamatsuakutotawa^(19kai)",
    "iso:country":"JP",
    "wof:name":"430-7719",
    "wof:placetype":"postalcode"
},
  "geometry": {"coordinates":[137.7354,34.7067],"type":"Point"}
}