{
  "type": "Feature",
  "properties": {
    "gn:adm1_name":"Naraken",
    "gn:adm2_name":"Yoshinogunnishiyoshinomura",
    "gn:name":"Yonaka",
    "iso:country":"JP",
    "wof:name":"638-0662",
    "wof:placetype":"postalcode"
},
  "geometry": {"coordinates":[135.73759999999999,34.3106],"type":"Point"}
}