{
  "type": "Feature",
  "properties": {
    "gn:adm1_name":"Gifuken",
    "gn:adm2_name":"Takayamashi",
    "gn:name":"Akahokimachi",
    "iso:country":"JP",
    "wof:name":"506-0045",
    "wof:placetype":"postalcode"
},
  "geometry": {"coordinates":[137.22900000000001,36.1603],"type":"Point"}
}