{
  "type": "Feature",
  "properties": {
    "gn:adm1_name":"Tottoriken",
    "gn:adm2_name":"Iwamigunkokufuchou",
    "gn:name":"Shimokihara",
    "iso:country":"JP",
    "wof:name":"680-0207",
    "wof:placetype":"postalcode"
},
  "geometry": {"coordinates":[134.36750000000001,35.4789],"type":"Point"}
}