{
  "type": "Feature",
  "properties": {
    "gn:adm1_name":"Tottoriken",
    "gn:adm2_name":"Tottorishi",
    "gn:name":"Negidani",
    "iso:country":"JP",
    "wof:name":"689-1113",
    "wof:placetype":"postalcode"
},
  "geometry": {"coordinates":[134.2544,35.4371],"type":"Point"}
}