{
  "type": "Feature",
  "properties": {
    "gn:adm1_name":"Ibarakiken",
    "gn:adm2_name":"Ishiokashi",
    "gn:name":"Kokufu",
    "iso:country":"JP",
    "wof:name":"315-0014",
    "wof:placetype":"postalcode"
},
  "geometry": {"coordinates":[140.27610000000001,36.1878],"type":"Point"}
}