{
  "type": "Feature",
  "properties": {
    "gn:adm1_name":"Ishikawaken",
    "gn:adm2_name":"Hakuiguntogimachi",
    "gn:name":"Nakayama",
    "iso:country":"JP",
    "wof:name":"925-0304",
    "wof:placetype":"postalcode"
},
  "geometry": {"coordinates":[136.7818,37.0907],"type":"Point"}
}