{
  "type": "Feature",
  "properties": {
    "gn:adm1_name":"Yamanashiken",
    "gn:adm2_name":"Minamikomagunnakatomichou",
    "gn:name":"Youkaichiba",
    "iso:country":"JP",
    "wof:name":"409-3421",
    "wof:placetype":"postalcode"
},
  "geometry": {"coordinates":[138.4418,35.4518],"type":"Point"}
}