{
  "type": "Feature",
  "properties": {
    "gn:adm1_name":"Ishikawaken",
    "gn:adm2_name":"Hakuiguntogimachi",
    "gn:name":"Shishizu",
    "iso:country":"JP",
    "wof:name":"925-0576",
    "wof:placetype":"postalcode"
},
  "geometry": {"coordinates":[136.68870000000001,37.1806],"type":"Point"}
}