{
  "type": "Feature",
  "properties": {
    "gn:adm1_name":"Toyamaken",
    "gn:adm2_name":"Himishi",
    "gn:name":"Miuchi",
    "iso:country":"JP",
    "wof:name":"935-0267",
    "wof:placetype":"postalcode"
},
  "geometry": {"coordinates":[136.88470000000001,36.833],"type":"Point"}
}