{
  "type": "Feature",
  "properties": {
    "gn:adm1_name":"Niigataken",
    "gn:adm2_name":"Araishi",
    "gn:name":"Nakamachi",
    "iso:country":"JP",
    "wof:name":"944-0045",
    "wof:placetype":"postalcode"
},
  "geometry": {"coordinates":[138.251,37.0264],"type":"Point"}
}