{
  "type": "Feature",
  "properties": {
    "gn:adm1_name":"Oosakafu",
    "gn:adm2_name":"Toyonoguntoyonochou",
    "gn:name":"Nomaguchi",
    "iso:country":"JP",
    "wof:name":"563-0218",
    "wof:placetype":"postalcode"
},
  "geometry": {"coordinates":[135.48500000000001,34.9322],"type":"Point"}
}