{
  "type": "Feature",
  "properties": {
    "gn:adm1_name":"Chibaken",
    "gn:adm2_name":"Ichiharashi",
    "gn:name":"Wakamiya",
    "iso:country":"JP",
    "wof:name":"290-0006",
    "wof:placetype":"postalcode"
},
  "geometry": {"coordinates":[140.13409999999999,35.5276],"type":"Point"}
}