{
  "type": "Feature",
  "properties": {
    "gn:adm1_name":"Miyazakiken",
    "gn:adm2_name":"Miyazakishi",
    "gn:name":"Dekijimachou",
    "iso:country":"JP",
    "wof:name":"880-0861",
    "wof:placetype":"postalcode"
},
  "geometry": {"coordinates":[131.4375,31.9027],"type":"Point"}
}