{
  "type": "Feature",
  "properties": {
    "gn:adm1_name":"Mieken",
    "gn:adm2_name":"Tsushi",
    "gn:name":"Katadayakuoujichou",
    "iso:country":"JP",
    "wof:name":"514-0086",
    "wof:placetype":"postalcode"
},
  "geometry": {"coordinates":[136.42420000000001,34.7129],"type":"Point"}
}