{
  "type": "Feature",
  "properties": {
    "gn:adm1_name":"Kanagawaken",
    "gn:adm2_name":"Yokohamashinakaku",
    "gn:name":"Honmokumakado",
    "iso:country":"JP",
    "wof:name":"231-0825",
    "wof:placetype":"postalcode"
},
  "geometry": {"coordinates":[139.65629999999999,35.42],"type":"Point"}
}