{
  "type": "Feature",
  "properties": {
    "gn:adm1_name":"Miyazakiken",
    "gn:adm2_name":"Miyakonojoushi",
    "gn:name":"Shimozuruchou",
    "iso:country":"JP",
    "wof:name":"885-1102",
    "wof:placetype":"postalcode"
},
  "geometry": {"coordinates":[131.10990000000001,31.8194],"type":"Point"}
}