{
  "type": "Feature",
  "properties": {
    "gn:adm1_name":"Sagaken",
    "gn:adm2_name":"Karatsushi",
    "gn:name":"Sashihamamachi",
    "iso:country":"JP",
    "wof:name":"847-0115",
    "wof:placetype":"postalcode"
},
  "geometry": {"coordinates":[129.93719999999999,33.4764],"type":"Point"}
}