{
  "type": "Feature",
  "properties": {
    "gn:adm1_name":"Fukushimaken",
    "gn:adm2_name":"Higashishirakawaguntanaguramachi",
    "gn:name":"Kodume",
    "iso:country":"JP",
    "wof:name":"963-6152",
    "wof:placetype":"postalcode"
},
  "geometry": {"coordinates":[140.34270000000001,37.0377],"type":"Point"}
}