{
  "type": "Feature",
  "properties": {
    "gn:adm1_name":"Saitamaken",
    "gn:adm2_name":"Sakadoshi",
    "gn:name":"Higashisakado",
    "iso:country":"JP",
    "wof:name":"350-0205",
    "wof:placetype":"postalcode"
},
  "geometry": {"coordinates":[139.446,35.9537],"type":"Point"}
}