{
  "type": "Feature",
  "properties": {
    "gn:adm1_name":"Ehimeken",
    "gn:adm2_name":"Iyogunhirotamura",
    "gn:name":"Tamatani",
    "iso:country":"JP",
    "wof:name":"791-2202",
    "wof:placetype":"postalcode"
},
  "geometry": {"coordinates":[132.792,33.6682],"type":"Point"}
}