{
  "type": "Feature",
  "properties": {
    "gn:adm1_name":"Chibaken",
    "gn:adm2_name":"Katsuurashi",
    "gn:name":"Shiraki",
    "iso:country":"JP",
    "wof:name":"299-5214",
    "wof:placetype":"postalcode"
},
  "geometry": {"coordinates":[140.29329999999999,35.1931],"type":"Point"}
}