{
  "type": "Feature",
  "properties": {
    "gn:adm1_name":"Hyougoken",
    "gn:adm2_name":"Nishiwakishi",
    "gn:name":"Wabuchou",
    "iso:country":"JP",
    "wof:name":"677-0053",
    "wof:placetype":"postalcode"
},
  "geometry": {"coordinates":[134.97489999999999,34.9785],"type":"Point"}
}