{
  "type": "Feature",
  "properties": {
    "gn:adm1_name":"Aichiken",
    "gn:adm2_name":"Komakishi",
    "gn:name":"Shinooka",
    "iso:country":"JP",
    "wof:name":"485-0815",
    "wof:placetype":"postalcode"
},
  "geometry": {"coordinates":[136.98509999999999,35.3047],"type":"Point"}
}