{
  "type": "Feature",
  "properties": {
    "gn:adm1_name":"Aichiken",
    "gn:adm2_name":"Nagoyashimeitouku",
    "gn:name":"Makinohara",
    "iso:country":"JP",
    "wof:name":"465-0072",
    "wof:placetype":"postalcode"
},
  "geometry": {"coordinates":[136.99889999999999,35.1503],"type":"Point"}
}