{
  "type": "Feature",
  "properties": {
    "gn:adm1_name":"Toukyouto",
    "gn:adm2_name":"Setagayaku",
    "gn:name":"Komazawa",
    "iso:country":"JP",
    "wof:name":"154-0012",
    "wof:placetype":"postalcode"
},
  "geometry": {"coordinates":[139.6566,35.6307],"type":"Point"}
}