{
  "type": "Feature",
  "properties": {
    "gn:adm1_name":"Kyoutofu",
    "gn:adm2_name":"Ayabeshi",
    "gn:name":"Nishimachi",
    "iso:country":"JP",
    "wof:name":"623-0016",
    "wof:placetype":"postalcode"
},
  "geometry": {"coordinates":[135.25659999999999,35.2999],"type":"Point"}
}