{
  "type": "Feature",
  "properties": {
    "gn:adm1_name":"Saitamaken",
    "gn:adm2_name":"Tokorozawashi",
    "gn:name":"Sayamagaoka",
    "iso:country":"JP",
    "wof:name":"359-1161",
    "wof:placetype":"postalcode"
},
  "geometry": {"coordinates":[139.41409999999999,35.8104],"type":"Point"}
}