{
  "type": "Feature",
  "properties": {
    "gn:adm1_name":"Fukuokaken",
    "gn:adm2_name":"Kitakyuushuushitobataku",
    "gn:name":"Kannonjichou",
    "iso:country":"JP",
    "wof:name":"804-0043",
    "wof:placetype":"postalcode"
},
  "geometry": {"coordinates":[130.83070000000001,33.8837],"type":"Point"}
}