{
  "type": "Feature",
  "properties": {
    "gn:adm1_name":"Kanagawaken",
    "gn:adm2_name":"Yokohamashitsurumiku",
    "gn:name":"Mukaichou",
    "iso:country":"JP",
    "wof:name":"230-0037",
    "wof:placetype":"postalcode"
},
  "geometry": {"coordinates":[139.68899999999999,35.5054],"type":"Point"}
}