{
  "type": "Feature",
  "properties": {
    "gn:adm1_name":"Saitamaken",
    "gn:adm2_name":"Higashimatsuyamashi",
    "gn:name":"Tagi",
    "iso:country":"JP",
    "wof:name":"355-0053",
    "wof:placetype":"postalcode"
},
  "geometry": {"coordinates":[139.39080000000001,35.9885],"type":"Point"}
}