{
  "type": "Feature",
  "properties": {
    "gn:adm1_name":"Shizuokaken",
    "gn:adm2_name":"Haibaragunkawanechou",
    "gn:name":"Minari",
    "iso:country":"JP",
    "wof:name":"428-0103",
    "wof:placetype":"postalcode"
},
  "geometry": {"coordinates":[138.08959999999999,34.9406],"type":"Point"}
}