{
  "type": "Feature",
  "properties": {
    "gn:adm1_name":"Fukuokaken",
    "gn:adm2_name":"Oomutashi",
    "gn:name":"Izumomachi",
    "iso:country":"JP",
    "wof:name":"836-0854",
    "wof:placetype":"postalcode"
},
  "geometry": {"coordinates":[130.45060000000001,33.0308],"type":"Point"}
}