{
  "type": "Feature",
  "properties": {
    "gn:adm1_name":"Tottoriken",
    "gn:adm2_name":"Iwamigun'Iwamichou",
    "gn:name":"Ikedani",
    "iso:country":"JP",
    "wof:name":"681-0047",
    "wof:placetype":"postalcode"
},
  "geometry": {"coordinates":[134.33680000000001,35.5204],"type":"Point"}
}