{
  "type": "Feature",
  "properties": {
    "gn:adm1_name":"Ibarakiken",
    "gn:adm2_name":"Kujigunsuifumura",
    "gn:name":"Kuniyasu",
    "iso:country":"JP",
    "wof:name":"313-0221",
    "wof:placetype":"postalcode"
},
  "geometry": {"coordinates":[140.4881,36.5988],"type":"Point"}
}