{
  "type": "Feature",
  "properties": {
    "gn:adm1_name":"Mieken",
    "gn:adm2_name":"Tsushi",
    "gn:name":"Takasuchou",
    "iso:country":"JP",
    "wof:name":"514-0011",
    "wof:placetype":"postalcode"
},
  "geometry": {"coordinates":[136.52510000000001,34.7263],"type":"Point"}
}