{
  "type": "Feature",
  "properties": {
    "gn:adm1_name":"Oosakafu",
    "gn:adm2_name":"Minooshi",
    "gn:name":"Ishimaru",
    "iso:country":"JP",
    "wof:name":"562-0027",
    "wof:placetype":"postalcode"
},
  "geometry": {"coordinates":[135.4958,34.8394],"type":"Point"}
}