{
  "type": "Feature",
  "properties": {
    "gn:adm1_name":"Fukushimaken",
    "gn:adm2_name":"Iwakishi",
    "gn:name":"Numabemachi",
    "iso:country":"JP",
    "wof:name":"979-0154",
    "wof:placetype":"postalcode"
},
  "geometry": {"coordinates":[140.7473,36.9186],"type":"Point"}
}