{
  "type": "Feature",
  "properties": {
    "gn:adm1_name":"Oosakafu",
    "gn:adm2_name":"Oosakashikonohanaku",
    "gn:name":"Shimaya",
    "iso:country":"JP",
    "wof:name":"554-0024",
    "wof:placetype":"postalcode"
},
  "geometry": {"coordinates":[135.44110000000001,34.6752],"type":"Point"}
}