{
  "type": "Feature",
  "properties": {
    "gn:adm1_name":"Ehimeken",
    "gn:adm2_name":"Kitauwagunhiromichou",
    "gn:name":"Shiba",
    "iso:country":"JP",
    "wof:name":"798-1355",
    "wof:placetype":"postalcode"
},
  "geometry": {"coordinates":[132.67789999999999,33.2481],"type":"Point"}
}