{
  "type": "Feature",
  "properties": {
    "gn:adm1_name":"Ehimeken",
    "gn:adm2_name":"Matsuyamashi",
    "gn:name":"Minamimachi",
    "iso:country":"JP",
    "wof:name":"790-0856",
    "wof:placetype":"postalcode"
},
  "geometry": {"coordinates":[132.78039999999999,33.8466],"type":"Point"}
}