{
  "type": "Feature",
  "properties": {
    "gn:adm1_name":"Ibarakiken",
    "gn:adm2_name":"Yuukigunyachiyomachi",
    "gn:name":"Hiratsuka",
    "iso:country":"JP",
    "wof:name":"300-3561",
    "wof:placetype":"postalcode"
},
  "geometry": {"coordinates":[139.86770000000001,36.1571],"type":"Point"}
}