{
  "type": "Feature",
  "properties": {
    "gn:adm1_name":"Fukuokaken",
    "gn:adm2_name":"Fukuokashihakataku",
    "gn:name":"Tsukiguma",
    "iso:country":"JP",
    "wof:name":"816-0058",
    "wof:placetype":"postalcode"
},
  "geometry": {"coordinates":[130.4665,33.5754],"type":"Point"}
}