{
  "type": "Feature",
  "properties": {
    "gn:adm1_name":"Fukushimaken",
    "gn:adm2_name":"Kitakatashi",
    "gn:name":"Yashikimen",
    "iso:country":"JP",
    "wof:name":"966-0056",
    "wof:placetype":"postalcode"
},
  "geometry": {"coordinates":[139.88210000000001,37.6486],"type":"Point"}
}