{
  "type": "Feature",
  "properties": {
    "gn:adm1_name":"Chibaken",
    "gn:adm2_name":"Sakurashi",
    "gn:name":"Massaki",
    "iso:country":"JP",
    "wof:name":"285-0851",
    "wof:placetype":"postalcode"
},
  "geometry": {"coordinates":[140.15219999999999,35.7515],"type":"Point"}
}