{
  "type": "Feature",
  "properties": {
    "gn:adm1_name":"Mieken",
    "gn:adm2_name":"Owaseshi",
    "gn:name":"Izumichou",
    "iso:country":"JP",
    "wof:name":"519-3646",
    "wof:placetype":"postalcode"
},
  "geometry": {"coordinates":[136.18100000000001,34.07],"type":"Point"}
}