{
  "type": "Feature",
  "properties": {
    "gn:adm1_name":"Mieken",
    "gn:adm2_name":"Matsusakashi",
    "gn:name":"Chiharachou",
    "iso:country":"JP",
    "wof:name":"515-1202",
    "wof:placetype":"postalcode"
},
  "geometry": {"coordinates":[136.46889999999999,34.4941],"type":"Point"}
}