{
  "type": "Feature",
  "properties": {
    "gn:adm1_name":"Hyougoken",
    "gn:adm2_name":"Mikatagunhamasakachou",
    "gn:name":"Fukutomi",
    "iso:country":"JP",
    "wof:name":"669-6732",
    "wof:placetype":"postalcode"
},
  "geometry": {"coordinates":[134.46969999999999,35.622],"type":"Point"}
}