{
  "type": "Feature",
  "properties": {
    "gn:adm1_name":"Oosakafu",
    "gn:adm2_name":"Oosakashichuuouku",
    "gn:name":"Houenzaka",
    "iso:country":"JP",
    "wof:name":"540-0006",
    "wof:placetype":"postalcode"
},
  "geometry": {"coordinates":[135.52510000000001,34.6795],"type":"Point"}
}