{
  "type": "Feature",
  "properties": {
    "gn:adm1_name":"Mieken",
    "gn:adm2_name":"Suzukashi",
    "gn:name":"Nagoshinmachi",
    "iso:country":"JP",
    "wof:name":"513-0041",
    "wof:placetype":"postalcode"
},
  "geometry": {"coordinates":[136.6354,34.9014],"type":"Point"}
}