{
  "type": "Feature",
  "properties": {
    "gn:adm1_name":"Aichiken",
    "gn:adm2_name":"Nagoyashiminatoku",
    "gn:name":"Iriba",
    "iso:country":"JP",
    "wof:name":"455-0803",
    "wof:placetype":"postalcode"
},
  "geometry": {"coordinates":[136.85380000000001,35.1104],"type":"Point"}
}