{
  "type": "Feature",
  "properties": {
    "gn:adm1_name":"Kyoutofu",
    "gn:adm2_name":"Kyoutoshikitaku",
    "gn:name":"Kamigamoooyanagichou",
    "iso:country":"JP",
    "wof:name":"603-8037",
    "wof:placetype":"postalcode"
},
  "geometry": {"coordinates":[135.74359999999999,35.0697],"type":"Point"}
}