{
  "type": "Feature",
  "properties": {
    "gn:adm1_name":"Shigaken",
    "gn:adm2_name":"Kusatsushi",
    "gn:name":"Kamigasa",
    "iso:country":"JP",
    "wof:name":"525-0028",
    "wof:placetype":"postalcode"
},
  "geometry": {"coordinates":[135.94470000000001,35.0307],"type":"Point"}
}