{
  "type": "Feature",
  "properties": {
    "gn:adm1_name":"Ishikawaken",
    "gn:adm2_name":"Hakuiguntogimachi",
    "gn:name":"Chinoura",
    "iso:country":"JP",
    "wof:name":"925-0572",
    "wof:placetype":"postalcode"
},
  "geometry": {"coordinates":[136.67679999999999,37.1429],"type":"Point"}
}