{
  "type": "Feature",
  "properties": {
    "gn:adm1_name":"Toukyouto",
    "gn:adm2_name":"Nerimaku",
    "gn:name":"Sakuradai",
    "iso:country":"JP",
    "wof:name":"176-0002",
    "wof:placetype":"postalcode"
},
  "geometry": {"coordinates":[139.66249999999999,35.7431],"type":"Point"}
}