{
  "type": "Feature",
  "properties": {
    "gn:adm1_name":"Yamagataken",
    "gn:adm2_name":"Tendoushi",
    "gn:name":"Kitame",
    "iso:country":"JP",
    "wof:name":"994-0042",
    "wof:placetype":"postalcode"
},
  "geometry": {"coordinates":[140.37379999999999,38.3477],"type":"Point"}
}