{
  "type": "Feature",
  "properties": {
    "gn:adm1_name":"Hiroshimaken",
    "gn:adm2_name":"Hatsukaichishi",
    "gn:name":"Shikigaokakami",
    "iso:country":"JP",
    "wof:name":"738-0038",
    "wof:placetype":"postalcode"
},
  "geometry": {"coordinates":[132.28729999999999,34.3472],"type":"Point"}
}