{
  "type": "Feature",
  "properties": {
    "gn:adm1_name":"Oosakafu",
    "gn:adm2_name":"Kadomashi",
    "gn:name":"Ookurachou",
    "iso:country":"JP",
    "wof:name":"571-0068",
    "wof:placetype":"postalcode"
},
  "geometry": {"coordinates":[135.59309999999999,34.7449],"type":"Point"}
}