{
  "type": "Feature",
  "properties": {
    "gn:adm1_name":"Toyamaken",
    "gn:adm2_name":"Imizugunshimomura",
    "gn:name":"Shiraishi",
    "iso:country":"JP",
    "wof:name":"933-0207",
    "wof:placetype":"postalcode"
},
  "geometry": {"coordinates":[137.13079999999999,36.7284],"type":"Point"}
}