{
  "type": "Feature",
  "properties": {
    "gn:adm1_name":"Oosakafu",
    "gn:adm2_name":"Sakaishi",
    "gn:name":"Hamaderasuwanomorichounishi",
    "iso:country":"JP",
    "wof:name":"592-8347",
    "wof:placetype":"postalcode"
},
  "geometry": {"coordinates":[135.44659999999999,34.5503],"type":"Point"}
}