{
  "type": "Feature",
  "properties": {
    "gn:adm1_name":"Naganoken",
    "gn:adm2_name":"Iidashi",
    "gn:name":"Kamikawaji",
    "iso:country":"JP",
    "wof:name":"399-2564",
    "wof:placetype":"postalcode"
},
  "geometry": {"coordinates":[137.81460000000001,35.4625],"type":"Point"}
}