{
  "type": "Feature",
  "properties": {
    "gn:adm1_name":"Niigataken",
    "gn:adm2_name":"Araishi",
    "gn:name":"Kaminaka",
    "iso:country":"JP",
    "wof:name":"944-0052",
    "wof:placetype":"postalcode"
},
  "geometry": {"coordinates":[138.2312,37.0161],"type":"Point"}
}