{
  "type": "Feature",
  "properties": {
    "gn:adm1_name":"Kumamotoken",
    "gn:adm2_name":"Kumamotoshi",
    "gn:name":"Hiyoshi",
    "iso:country":"JP",
    "wof:name":"861-4109",
    "wof:placetype":"postalcode"
},
  "geometry": {"coordinates":[130.68539999999999,32.7597],"type":"Point"}
}