{
  "type": "Feature",
  "properties": {
    "gn:adm1_name":"Saitamaken",
    "gn:adm2_name":"Koshigayashi",
    "gn:name":"Osogawa",
    "iso:country":"JP",
    "wof:name":"343-0802",
    "wof:placetype":"postalcode"
},
  "geometry": {"coordinates":[139.75229999999999,35.9192],"type":"Point"}
}