{
  "type": "Feature",
  "properties": {
    "gn:adm1_name":"Wakayamaken",
    "gn:adm2_name":"Wakayamashi",
    "gn:name":"Hirai",
    "iso:country":"JP",
    "wof:name":"640-8442",
    "wof:placetype":"postalcode"
},
  "geometry": {"coordinates":[135.16659999999999,34.2608],"type":"Point"}
}