{
  "type": "Feature",
  "properties": {
    "gn:adm1_name":"Naganoken",
    "gn:adm2_name":"Naganoshi",
    "gn:name":"Inada",
    "iso:country":"JP",
    "wof:name":"381-0042",
    "wof:placetype":"postalcode"
},
  "geometry": {"coordinates":[138.22409999999999,36.6735],"type":"Point"}
}