{
  "type": "Feature",
  "properties": {
    "gn:adm1_name":"Ishikawaken",
    "gn:adm2_name":"Hakuigunshikamachi",
    "gn:name":"Machi",
    "iso:country":"JP",
    "wof:name":"925-0167",
    "wof:placetype":"postalcode"
},
  "geometry": {"coordinates":[136.76339999999999,37.0156],"type":"Point"}
}