{
  "type": "Feature",
  "properties": {
    "gn:adm1_name":"Aichiken",
    "gn:adm2_name":"Komakishi",
    "gn:name":"Hikarigaoka",
    "iso:country":"JP",
    "wof:name":"485-0811",
    "wof:placetype":"postalcode"
},
  "geometry": {"coordinates":[136.99180000000001,35.3012],"type":"Point"}
}