{
  "type": "Feature",
  "properties": {
    "gn:adm1_name":"Wakayamaken",
    "gn:adm2_name":"Wakayamashi",
    "gn:name":"Matsubara",
    "iso:country":"JP",
    "wof:name":"640-0342",
    "wof:placetype":"postalcode"
},
  "geometry": {"coordinates":[135.233,34.1916],"type":"Point"}
}