{
  "type": "Feature",
  "properties": {
    "gn:adm1_name":"Shizuokaken",
    "gn:adm2_name":"Gotenbashi",
    "gn:name":"Hotozawa",
    "iso:country":"JP",
    "wof:name":"412-0046",
    "wof:placetype":"postalcode"
},
  "geometry": {"coordinates":[138.9007,35.2953],"type":"Point"}
}