{
  "type": "Feature",
  "properties": {
    "gn:adm1_name":"Saitamaken",
    "gn:adm2_name":"Kawagoeshi",
    "gn:name":"Shibui",
    "iso:country":"JP",
    "wof:name":"350-0013",
    "wof:placetype":"postalcode"
},
  "geometry": {"coordinates":[139.5368,35.8822],"type":"Point"}
}