{
  "type": "Feature",
  "properties": {
    "gn:adm1_name":"Niigataken",
    "gn:adm2_name":"Kashiwazakishi",
    "gn:name":"Sanwachou(Sonota)",
    "iso:country":"JP",
    "wof:name":"945-0034",
    "wof:placetype":"postalcode"
},
  "geometry": {"coordinates":[138.5789,37.3662],"type":"Point"}
}