{
  "type": "Feature",
  "properties": {
    "gn:adm1_name":"Toukyouto",
    "gn:adm2_name":"Shinjukuku",
    "gn:name":"Nakachou",
    "iso:country":"JP",
    "wof:name":"162-0835",
    "wof:placetype":"postalcode"
},
  "geometry": {"coordinates":[139.73560000000001,35.6991],"type":"Point"}
}