{
  "type": "Feature",
  "properties": {
    "gn:adm1_name":"Fukuokaken",
    "gn:adm2_name":"Tagawashi",
    "gn:name":"Hiramatsumachi",
    "iso:country":"JP",
    "wof:name":"826-0032",
    "wof:placetype":"postalcode"
},
  "geometry": {"coordinates":[130.8031,33.634],"type":"Point"}
}