{
  "type": "Feature",
  "properties": {
    "gn:adm1_name":"Gunmaken",
    "gn:adm2_name":"Fujiokashi",
    "gn:name":"Shimotoduka",
    "iso:country":"JP",
    "wof:name":"375-0012",
    "wof:placetype":"postalcode"
},
  "geometry": {"coordinates":[139.09379999999999,36.2557],"type":"Point"}
}