{
  "type": "Feature",
  "properties": {
    "gn:adm1_name":"Shizuokaken",
    "gn:adm2_name":"Iwatashi",
    "gn:name":"Kamioonogou",
    "iso:country":"JP",
    "wof:name":"438-0051",
    "wof:placetype":"postalcode"
},
  "geometry": {"coordinates":[137.85329999999999,34.6926],"type":"Point"}
}