{
  "type": "Feature",
  "properties": {
    "gn:adm1_name":"Hyougoken",
    "gn:adm2_name":"Kasaishi",
    "gn:name":"Wakaichou",
    "iso:country":"JP",
    "wof:name":"675-2456",
    "wof:placetype":"postalcode"
},
  "geometry": {"coordinates":[134.828,34.9692],"type":"Point"}
}