{
  "type": "Feature",
  "properties": {
    "gn:adm1_name":"Fukuiken",
    "gn:adm2_name":"Fukuishi",
    "gn:name":"Ejirigaokachou",
    "iso:country":"JP",
    "wof:name":"918-8175",
    "wof:placetype":"postalcode"
},
  "geometry": {"coordinates":[136.18790000000001,35.9926],"type":"Point"}
}