{
  "type": "Feature",
  "properties": {
    "gn:adm1_name":"Kouchiken",
    "gn:adm2_name":"Tosagunkagamimura",
    "gn:name":"Kazurayama",
    "iso:country":"JP",
    "wof:name":"781-3123",
    "wof:placetype":"postalcode"
},
  "geometry": {"coordinates":[133.43459999999999,33.5969],"type":"Point"}
}