{
  "type": "Feature",
  "properties": {
    "gn:adm1_name":"Toukyouto",
    "gn:adm2_name":"Akirunoshi",
    "gn:name":"Sannai",
    "iso:country":"JP",
    "wof:name":"190-0162",
    "wof:placetype":"postalcode"
},
  "geometry": {"coordinates":[139.23070000000001,35.7345],"type":"Point"}
}