{
  "type": "Feature",
  "properties": {
    "gn:adm1_name":"Oosakafu",
    "gn:adm2_name":"Takatsukishi",
    "gn:name":"Sawaragichou",
    "iso:country":"JP",
    "wof:name":"569-0084",
    "wof:placetype":"postalcode"
},
  "geometry": {"coordinates":[135.63040000000001,34.8477],"type":"Point"}
}