{
  "type": "Feature",
  "properties": {
    "gn:adm1_name":"Saitamaken",
    "gn:adm2_name":"Kitamotoshi",
    "gn:name":"Motojuku",
    "iso:country":"JP",
    "wof:name":"364-0005",
    "wof:placetype":"postalcode"
},
  "geometry": {"coordinates":[139.5419,36.0284],"type":"Point"}
}