{
  "type": "Feature",
  "properties": {
    "gn:adm1_name":"Toyamaken",
    "gn:adm2_name":"Himishi",
    "gn:name":"Kaidu",
    "iso:country":"JP",
    "wof:name":"935-0045",
    "wof:placetype":"postalcode"
},
  "geometry": {"coordinates":[136.9649,36.8258],"type":"Point"}
}