{
  "type": "Feature",
  "properties": {
    "gn:adm1_name":"Aichiken",
    "gn:adm2_name":"Shinshiroshi",
    "gn:name":"Kasaiwa",
    "iso:country":"JP",
    "wof:name":"441-1329",
    "wof:placetype":"postalcode"
},
  "geometry": {"coordinates":[137.50380000000001,34.8962],"type":"Point"}
}