{
  "type": "Feature",
  "properties": {
    "gn:adm1_name":"Niigataken",
    "gn:adm2_name":"Nakakubikigunkiyosatomura",
    "gn:name":"Akaike",
    "iso:country":"JP",
    "wof:name":"943-0527",
    "wof:placetype":"postalcode"
},
  "geometry": {"coordinates":[138.38220000000001,37.0333],"type":"Point"}
}