{
  "type": "Feature",
  "properties": {
    "gn:adm1_name":"Gifuken",
    "gn:adm2_name":"Ibiguntanigumimura",
    "gn:name":"Nagase",
    "iso:country":"JP",
    "wof:name":"501-1303",
    "wof:placetype":"postalcode"
},
  "geometry": {"coordinates":[136.6396,35.524],"type":"Point"}
}