{
  "type": "Feature",
  "properties": {
    "gn:adm1_name":"Miyagiken",
    "gn:adm2_name":"Kattagunshichikashukumachi",
    "gn:name":"Tanakamichishita",
    "iso:country":"JP",
    "wof:name":"989-0632",
    "wof:placetype":"postalcode"
},
  "geometry": {"coordinates":[140.33420000000001,38.0049],"type":"Point"}
}