{
  "type": "Feature",
  "properties": {
    "gn:adm1_name":"Fukuiken",
    "gn:adm2_name":"Fukuishi",
    "gn:name":"Takagi",
    "iso:country":"JP",
    "wof:name":"910-0805",
    "wof:placetype":"postalcode"
},
  "geometry": {"coordinates":[136.2277,36.0949],"type":"Point"}
}