{
  "type": "Feature",
  "properties": {
    "gn:adm1_name":"Fukuokaken",
    "gn:adm2_name":"Tagawagun'Itodamachi",
    "gn:name":"Shimoitoda",
    "iso:country":"JP",
    "wof:name":"822-1312",
    "wof:placetype":"postalcode"
},
  "geometry": {"coordinates":[130.77719999999999,33.6601],"type":"Point"}
}