{
  "type": "Feature",
  "properties": {
    "gn:adm1_name":"Oosakafu",
    "gn:adm2_name":"Sakaishi",
    "gn:name":"Tazono",
    "iso:country":"JP",
    "wof:name":"599-8246",
    "wof:placetype":"postalcode"
},
  "geometry": {"coordinates":[135.51169999999999,34.5103],"type":"Point"}
}