{
  "type": "Feature",
  "properties": {
    "gn:adm1_name":"Nagasakiken",
    "gn:adm2_name":"Shimabarashi",
    "gn:name":"Shinbabamachi",
    "iso:country":"JP",
    "wof:name":"855-0033",
    "wof:placetype":"postalcode"
},
  "geometry": {"coordinates":[130.3665,32.798],"type":"Point"}
}