{
  "type": "Feature",
  "properties": {
    "gn:adm1_name":"Kanagawaken",
    "gn:adm2_name":"Hiratsukashi",
    "gn:name":"Ooshima",
    "iso:country":"JP",
    "wof:name":"254-0001",
    "wof:placetype":"postalcode"
},
  "geometry": {"coordinates":[139.34309999999999,35.379],"type":"Point"}
}