{
  "type": "Feature",
  "properties": {
    "gn:adm1_name":"Ooitaken",
    "gn:adm2_name":"Usagun'Innaimachi",
    "gn:name":"Yamashiro",
    "iso:country":"JP",
    "wof:name":"872-0332",
    "wof:placetype":"postalcode"
},
  "geometry": {"coordinates":[131.31630000000001,33.4184],"type":"Point"}
}