{
  "type": "Feature",
  "properties": {
    "gn:adm1_name":"Mieken",
    "gn:adm2_name":"Miegunkomonochou",
    "gn:name":"Komono",
    "iso:country":"JP",
    "wof:name":"510-1233",
    "wof:placetype":"postalcode"
},
  "geometry": {"coordinates":[136.50239999999999,35.0114],"type":"Point"}
}