{
  "type": "Feature",
  "properties": {
    "gn:adm1_name":"Tottoriken",
    "gn:adm2_name":"Touhakuguntouhakuchou",
    "gn:name":"Yamata",
    "iso:country":"JP",
    "wof:name":"689-2343",
    "wof:placetype":"postalcode"
},
  "geometry": {"coordinates":[133.68260000000001,35.4614],"type":"Point"}
}