{
  "type": "Feature",
  "properties": {
    "gn:adm1_name":"Fukushimaken",
    "gn:adm2_name":"Iwakishi",
    "gn:name":"Kawamaemachishimookeuri",
    "iso:country":"JP",
    "wof:name":"979-3202",
    "wof:placetype":"postalcode"
},
  "geometry": {"coordinates":[140.7379,37.2498],"type":"Point"}
}