{
  "type": "Feature",
  "properties": {
    "gn:adm1_name":"Shizuokaken",
    "gn:adm2_name":"Shizuokashi",
    "gn:name":"Mise",
    "iso:country":"JP",
    "wof:name":"422-8057",
    "wof:placetype":"postalcode"
},
  "geometry": {"coordinates":[138.38910000000001,34.9585],"type":"Point"}
}