{
  "type": "Feature",
  "properties": {
    "gn:adm1_name":"Naganoken",
    "gn:adm2_name":"Shiojirishi",
    "gn:name":"Daimon(Banchi)",
    "iso:country":"JP",
    "wof:name":"399-0744",
    "wof:placetype":"postalcode"
},
  "geometry": {"coordinates":[137.94800000000001,36.1186],"type":"Point"}
}