{
  "type": "Feature",
  "properties": {
    "gn:adm1_name":"Mieken",
    "gn:adm2_name":"Iseshi",
    "gn:name":"Fujisatochou",
    "iso:country":"JP",
    "wof:name":"516-0043",
    "wof:placetype":"postalcode"
},
  "geometry": {"coordinates":[136.7037,34.4745],"type":"Point"}
}