{
  "type": "Feature",
  "properties": {
    "gn:adm1_name":"Okinawaken",
    "gn:adm2_name":"Nakagamigunkitanakagusukuson",
    "gn:name":"Oogusuku",
    "iso:country":"JP",
    "wof:name":"901-2314",
    "wof:placetype":"postalcode"
},
  "geometry": {"coordinates":[127.80070000000001,26.2901],"type":"Point"}
}