{
  "type": "Feature",
  "properties": {
    "gn:adm1_name":"Hyougoken",
    "gn:adm2_name":"Kasaishi",
    "gn:name":"Kuwaharadachou",
    "iso:country":"JP",
    "wof:name":"675-2111",
    "wof:placetype":"postalcode"
},
  "geometry": {"coordinates":[134.88640000000001,34.8763],"type":"Point"}
}