{
  "type": "Feature",
  "properties": {
    "gn:adm1_name":"Aichiken",
    "gn:adm2_name":"Nagoyashimoriyamaku",
    "gn:name":"Wakitachou",
    "iso:country":"JP",
    "wof:name":"463-0024",
    "wof:placetype":"postalcode"
},
  "geometry": {"coordinates":[137.00479999999999,35.2029],"type":"Point"}
}