{
  "type": "Feature",
  "properties": {
    "gn:adm1_name":"Naganoken",
    "gn:adm2_name":"Kamitakaigun'Obusemachi",
    "gn:name":"Tsusumi",
    "iso:country":"JP",
    "wof:name":"381-0208",
    "wof:placetype":"postalcode"
},
  "geometry": {"coordinates":[138.32210000000001,36.7058],"type":"Point"}
}