{
  "type": "Feature",
  "properties": {
    "gn:adm1_name":"Toyamaken",
    "gn:adm2_name":"Takaokashi",
    "gn:name":"Tounode",
    "iso:country":"JP",
    "wof:name":"933-0975",
    "wof:placetype":"postalcode"
},
  "geometry": {"coordinates":[136.9776,36.7562],"type":"Point"}
}