{
  "type": "Feature",
  "properties": {
    "gn:adm1_name":"Okinawaken",
    "gn:adm2_name":"Tomigusukushi",
    "gn:name":"Toyosaki",
    "iso:country":"JP",
    "wof:name":"901-0225",
    "wof:placetype":"postalcode"
},
  "geometry": {"coordinates":[127.6575,26.1583],"type":"Point"}
}