{
  "type": "Feature",
  "properties": {
    "gn:adm1_name":"Hiroshimaken",
    "gn:adm2_name":"Hiroshimashihigashiku",
    "gn:name":"Hesakakazukou",
    "iso:country":"JP",
    "wof:name":"732-0017",
    "wof:placetype":"postalcode"
},
  "geometry": {"coordinates":[132.49270000000001,34.4316],"type":"Point"}
}