{
  "type": "Feature",
  "properties": {
    "gn:adm1_name":"Shimaneken",
    "gn:adm2_name":"Izumoshi",
    "gn:name":"Himebarachou",
    "iso:country":"JP",
    "wof:name":"693-0061",
    "wof:placetype":"postalcode"
},
  "geometry": {"coordinates":[132.75290000000001,35.3723],"type":"Point"}
}