{
  "type": "Feature",
  "properties": {
    "gn:adm1_name":"Niigataken",
    "gn:adm2_name":"Higashikanbaraguntsugawamachi",
    "gn:name":"Kiyokawa",
    "iso:country":"JP",
    "wof:name":"959-4401",
    "wof:placetype":"postalcode"
},
  "geometry": {"coordinates":[139.44589999999999,37.6882],"type":"Point"}
}