{
  "type": "Feature",
  "properties": {
    "gn:adm1_name":"Toyamaken",
    "gn:adm2_name":"Higashitonamigunfukunomachi",
    "gn:name":"Eda",
    "iso:country":"JP",
    "wof:name":"939-1526",
    "wof:placetype":"postalcode"
},
  "geometry": {"coordinates":[136.92740000000001,36.5651],"type":"Point"}
}