{
  "type": "Feature",
  "properties": {
    "gn:adm1_name":"Okinawaken",
    "gn:adm2_name":"Kunigamigunmotobuchou",
    "gn:name":"Tancha",
    "iso:country":"JP",
    "wof:name":"905-0213",
    "wof:placetype":"postalcode"
},
  "geometry": {"coordinates":[127.8903,26.6577],"type":"Point"}
}