{
  "type": "Feature",
  "properties": {
    "gn:adm1_name":"Hiroshimaken",
    "gn:adm2_name":"Hiroshimashihigashiku",
    "gn:name":"Atagomachi",
    "iso:country":"JP",
    "wof:name":"732-0054",
    "wof:placetype":"postalcode"
},
  "geometry": {"coordinates":[132.48240000000001,34.3966],"type":"Point"}
}