{
  "type": "Feature",
  "properties": {
    "gn:adm1_name":"Shizuokaken",
    "gn:adm2_name":"Hamakitashi",
    "gn:name":"Kibune",
    "iso:country":"JP",
    "wof:name":"434-0038",
    "wof:placetype":"postalcode"
},
  "geometry": {"coordinates":[137.78440000000001,34.7966],"type":"Point"}
}