{
  "type": "Feature",
  "properties": {
    "gn:adm1_name":"Kyoutofu",
    "gn:adm2_name":"Kyoutoshiyamashinaku",
    "gn:name":"Nishinoyousumichou",
    "iso:country":"JP",
    "wof:name":"607-8342",
    "wof:placetype":"postalcode"
},
  "geometry": {"coordinates":[135.80889999999999,34.985],"type":"Point"}
}