{
  "type": "Feature",
  "properties": {
    "gn:adm1_name":"Niigataken",
    "gn:adm2_name":"Jouetsushi",
    "gn:name":"Nakadashinden",
    "iso:country":"JP",
    "wof:name":"943-0174",
    "wof:placetype":"postalcode"
},
  "geometry": {"coordinates":[138.26769999999999,37.1368],"type":"Point"}
}