{
  "type": "Feature",
  "properties": {
    "gn:adm1_name":"Hyougoken",
    "gn:adm2_name":"Hikamigunhikamichou",
    "gn:name":"Agenarimatsu",
    "iso:country":"JP",
    "wof:name":"669-3606",
    "wof:placetype":"postalcode"
},
  "geometry": {"coordinates":[135.02940000000001,35.1695],"type":"Point"}
}