{
  "type": "Feature",
  "properties": {
    "gn:adm1_name":"Kyoutofu",
    "gn:adm2_name":"Kyoutoshisakyouku",
    "gn:name":"Tanakanishihinokuchichou",
    "iso:country":"JP",
    "wof:name":"606-8221",
    "wof:placetype":"postalcode"
},
  "geometry": {"coordinates":[135.78299999999999,35.0339],"type":"Point"}
}