{
  "type": "Feature",
  "properties": {
    "gn:adm1_name":"Kanagawaken",
    "gn:adm2_name":"Kawasakishinakaharaku",
    "gn:name":"Kosugi",
    "iso:country":"JP",
    "wof:name":"211-0061",
    "wof:placetype":"postalcode"
},
  "geometry": {"coordinates":[139.65770000000001,35.5768],"type":"Point"}
}