{
  "type": "Feature",
  "properties": {
    "gn:adm1_name":"Hiroshimaken",
    "gn:adm2_name":"Kounugunsouryouchou",
    "gn:name":"Kamedani",
    "iso:country":"JP",
    "wof:name":"729-3702",
    "wof:placetype":"postalcode"
},
  "geometry": {"coordinates":[133.0968,34.7735],"type":"Point"}
}