{
  "type": "Feature",
  "properties": {
    "gn:adm1_name":"Gifuken",
    "gn:adm2_name":"Enagunkamiyahagichou",
    "gn:name":"Kozasahara",
    "iso:country":"JP",
    "wof:name":"509-7504",
    "wof:placetype":"postalcode"
},
  "geometry": {"coordinates":[137.5189,35.2981],"type":"Point"}
}