{
  "type": "Feature",
  "properties": {
    "gn:adm1_name":"Shimaneken",
    "gn:adm2_name":"Nakagunkanagichou",
    "gn:name":"Oguni",
    "iso:country":"JP",
    "wof:name":"697-0213",
    "wof:placetype":"postalcode"
},
  "geometry": {"coordinates":[132.20320000000001,34.8153],"type":"Point"}
}