{
  "type": "Feature",
  "properties": {
    "gn:adm1_name":"Miyagiken",
    "gn:adm2_name":"Sendaishimiyaginoku",
    "gn:name":"Odawarahirochou",
    "iso:country":"JP",
    "wof:name":"983-0815",
    "wof:placetype":"postalcode"
},
  "geometry": {"coordinates":[140.88990000000001,38.2644],"type":"Point"}
}