{
  "type": "Feature",
  "properties": {
    "gn:adm1_name":"Chibaken",
    "gn:adm2_name":"Kamogawashi",
    "gn:name":"Emihigashimakado",
    "iso:country":"JP",
    "wof:name":"299-2844",
    "wof:placetype":"postalcode"
},
  "geometry": {"coordinates":[140.0488,35.0591],"type":"Point"}
}