{
  "type": "Feature",
  "properties": {
    "gn:adm1_name":"Tokushimaken",
    "gn:adm2_name":"Miyoshigun'Ikedachou",
    "gn:name":"Uematsu",
    "iso:country":"JP",
    "wof:name":"778-0010",
    "wof:placetype":"postalcode"
},
  "geometry": {"coordinates":[133.8108,34.0221],"type":"Point"}
}