{
  "type": "Feature",
  "properties": {
    "gn:adm1_name":"Yamanashiken",
    "gn:adm2_name":"Nishiyatsushirogunshimobechou",
    "gn:name":"Yunooku",
    "iso:country":"JP",
    "wof:name":"409-2941",
    "wof:placetype":"postalcode"
},
  "geometry": {"coordinates":[138.49600000000001,35.4023],"type":"Point"}
}