{
  "type": "Feature",
  "properties": {
    "gn:adm1_name":"Gifuken",
    "gn:adm2_name":"Gifushi",
    "gn:name":"Dannoshimamiyamachi",
    "iso:country":"JP",
    "wof:name":"502-0924",
    "wof:placetype":"postalcode"
},
  "geometry": {"coordinates":[136.7277,35.4365],"type":"Point"}
}