{
  "type": "Feature",
  "properties": {
    "gn:adm1_name":"Oosakafu",
    "gn:adm2_name":"Izumisanoshi",
    "gn:name":"Takamatsuhigashi",
    "iso:country":"JP",
    "wof:name":"598-0012",
    "wof:placetype":"postalcode"
},
  "geometry": {"coordinates":[135.31610000000001,34.4062],"type":"Point"}
}