{
  "type": "Feature",
  "properties": {
    "gn:adm1_name":"Fukushimaken",
    "gn:adm2_name":"Nihonmatsushi",
    "gn:name":"Nagatamidouuchi",
    "iso:country":"JP",
    "wof:name":"964-0017",
    "wof:placetype":"postalcode"
},
  "geometry": {"coordinates":[140.404,37.6001],"type":"Point"}
}