{
  "type": "Feature",
  "properties": {
    "gn:adm1_name":"Ibarakiken",
    "gn:adm2_name":"Iwaishi",
    "gn:name":"Iwai",
    "iso:country":"JP",
    "wof:name":"306-0631",
    "wof:placetype":"postalcode"
},
  "geometry": {"coordinates":[139.88650000000001,36.0508],"type":"Point"}
}