{
  "type": "Feature",
  "properties": {
    "gn:adm1_name":"Miyagiken",
    "gn:adm2_name":"Shiroishishi",
    "gn:name":"Shindatechou",
    "iso:country":"JP",
    "wof:name":"989-0246",
    "wof:placetype":"postalcode"
},
  "geometry": {"coordinates":[140.6198,37.9943],"type":"Point"}
}