{
  "type": "Feature",
  "properties": {
    "gn:adm1_name":"Gunmaken",
    "gn:adm2_name":"Kiryuushi",
    "gn:name":"Suehirochou",
    "iso:country":"JP",
    "wof:name":"376-0045",
    "wof:placetype":"postalcode"
},
  "geometry": {"coordinates":[139.33580000000001,36.4113],"type":"Point"}
}