{
  "type": "Feature",
  "properties": {
    "gn:adm1_name":"Okinawaken",
    "gn:adm2_name":"Kunigamigun'Onnason",
    "gn:name":"Kisenbaru",
    "iso:country":"JP",
    "wof:name":"904-0403",
    "wof:placetype":"postalcode"
},
  "geometry": {"coordinates":[127.90989999999999,26.4875],"type":"Point"}
}