{
  "type": "Feature",
  "properties": {
    "gn:adm1_name":"Kyoutofu",
    "gn:adm2_name":"Kyoutoshiyamashinaku",
    "gn:name":"Hinookaishidukachou",
    "iso:country":"JP",
    "wof:name":"607-8498",
    "wof:placetype":"postalcode"
},
  "geometry": {"coordinates":[135.80029999999999,34.992],"type":"Point"}
}