{
  "type": "Feature",
  "properties": {
    "gn:adm1_name":"Nagasakiken",
    "gn:adm2_name":"Nagasakishi",
    "gn:name":"Aburagimachi",
    "iso:country":"JP",
    "wof:name":"852-8035",
    "wof:placetype":"postalcode"
},
  "geometry": {"coordinates":[129.8519,32.7806],"type":"Point"}
}