{
  "type": "Feature",
  "properties": {
    "gn:adm1_name":"Niigataken",
    "gn:adm2_name":"Nagaokashi",
    "gn:name":"Kamazawamachi",
    "iso:country":"JP",
    "wof:name":"940-1114",
    "wof:placetype":"postalcode"
},
  "geometry": {"coordinates":[138.85740000000001,37.3965],"type":"Point"}
}