{
  "type": "Feature",
  "properties": {
    "gn:adm1_name":"Yamagataken",
    "gn:adm2_name":"Sakatashi",
    "gn:name":"Azumachou",
    "iso:country":"JP",
    "wof:name":"998-0875",
    "wof:placetype":"postalcode"
},
  "geometry": {"coordinates":[139.86109999999999,38.9087],"type":"Point"}
}