{
  "type": "Feature",
  "properties": {
    "gn:adm1_name":"Okayamaken",
    "gn:adm2_name":"Okugun'Okuchou",
    "gn:name":"Honjou",
    "iso:country":"JP",
    "wof:name":"701-4214",
    "wof:placetype":"postalcode"
},
  "geometry": {"coordinates":[134.1225,34.6586],"type":"Point"}
}