{
  "type": "Feature",
  "properties": {
    "gn:adm1_name":"Ibarakiken",
    "gn:adm2_name":"Makabegunsekijoumachi",
    "gn:name":"Fujigaya",
    "iso:country":"JP",
    "wof:name":"308-0112",
    "wof:placetype":"postalcode"
},
  "geometry": {"coordinates":[139.95679999999999,36.2528],"type":"Point"}
}