{
  "type": "Feature",
  "properties": {
    "gn:adm1_name":"Toukyouto",
    "gn:adm2_name":"Setagayaku",
    "gn:name":"Okamoto",
    "iso:country":"JP",
    "wof:name":"157-0076",
    "wof:placetype":"postalcode"
},
  "geometry": {"coordinates":[139.6182,35.6251],"type":"Point"}
}