{
  "type": "Feature",
  "properties": {
    "gn:adm1_name":"Kyoutofu",
    "gn:adm2_name":"Kyoutoshiyamashinaku",
    "gn:name":"Ootsukamotoyashikichou",
    "iso:country":"JP",
    "wof:name":"607-8126",
    "wof:placetype":"postalcode"
},
  "geometry": {"coordinates":[135.82560000000001,34.977],"type":"Point"}
}