{
  "type": "Feature",
  "properties": {
    "gn:adm1_name":"Oosakafu",
    "gn:adm2_name":"Kashiwarashi",
    "gn:name":"Kokubuichiba",
    "iso:country":"JP",
    "wof:name":"582-0022",
    "wof:placetype":"postalcode"
},
  "geometry": {"coordinates":[135.6465,34.5681],"type":"Point"}
}