{
  "type": "Feature",
  "properties": {
    "gn:adm1_name":"Toyamaken",
    "gn:adm2_name":"Imizugundaimonmachi",
    "gn:name":"Honden",
    "iso:country":"JP",
    "wof:name":"939-0244",
    "wof:placetype":"postalcode"
},
  "geometry": {"coordinates":[137.0505,36.7339],"type":"Point"}
}