{
  "type": "Feature",
  "properties": {
    "gn:adm1_name":"Toukyouto",
    "gn:adm2_name":"Hachioujishi",
    "gn:name":"Inumemachi",
    "iso:country":"JP",
    "wof:name":"193-0802",
    "wof:placetype":"postalcode"
},
  "geometry": {"coordinates":[139.3065,35.6885],"type":"Point"}
}