{
  "type": "Feature",
  "properties": {
    "gn:adm1_name":"Gunmaken",
    "gn:adm2_name":"Isesakishi",
    "gn:name":"Inuichou",
    "iso:country":"JP",
    "wof:name":"372-0005",
    "wof:placetype":"postalcode"
},
  "geometry": {"coordinates":[139.19130000000001,36.3396],"type":"Point"}
}