{
  "type": "Feature",
  "properties": {
    "gn:adm1_name":"Miyazakiken",
    "gn:adm2_name":"Nishimorokatagunsukison",
    "gn:name":"Nakahara",
    "iso:country":"JP",
    "wof:name":"886-0111",
    "wof:placetype":"postalcode"
},
  "geometry": {"coordinates":[131.06899999999999,32.0836],"type":"Point"}
}