{
  "type": "Feature",
  "properties": {
    "gn:adm1_name":"Hiroshimaken",
    "gn:adm2_name":"Miyoshishi",
    "gn:name":"Yamagamachi",
    "iso:country":"JP",
    "wof:name":"728-0001",
    "wof:placetype":"postalcode"
},
  "geometry": {"coordinates":[132.82810000000001,34.8438],"type":"Point"}
}