{
  "type": "Feature",
  "properties": {
    "gn:adm1_name":"Ibarakiken",
    "gn:adm2_name":"Tsuchiurashi",
    "gn:name":"Yahagi",
    "iso:country":"JP",
    "wof:name":"300-0801",
    "wof:placetype":"postalcode"
},
  "geometry": {"coordinates":[140.15620000000001,36.0939],"type":"Point"}
}