{
  "type": "Feature",
  "properties": {
    "gn:adm1_name":"Toyamaken",
    "gn:adm2_name":"Takaokashi",
    "gn:name":"Oota(Tanpo)",
    "iso:country":"JP",
    "wof:name":"933-0134",
    "wof:placetype":"postalcode"
},
  "geometry": {"coordinates":[137.03139999999999,36.8183],"type":"Point"}
}