{
  "type": "Feature",
  "properties": {
    "gn:adm1_name":"Tottoriken",
    "gn:adm2_name":"Yazugunsajison",
    "gn:name":"Yodo",
    "iso:country":"JP",
    "wof:name":"689-1323",
    "wof:placetype":"postalcode"
},
  "geometry": {"coordinates":[134.07579999999999,35.3276],"type":"Point"}
}