{
  "type": "Feature",
  "properties": {
    "gn:adm1_name":"Ishikawaken",
    "gn:adm2_name":"Hakuigun'Oshimizumachi",
    "gn:name":"Uwadade",
    "iso:country":"JP",
    "wof:name":"929-1321",
    "wof:placetype":"postalcode"
},
  "geometry": {"coordinates":[136.76410000000001,36.8095],"type":"Point"}
}