{
  "type": "Feature",
  "properties": {
    "gn:adm1_name":"Ooitaken",
    "gn:adm2_name":"Ooitashi",
    "gn:name":"Mitsuyoshishinmachi",
    "iso:country":"JP",
    "wof:name":"870-1135",
    "wof:placetype":"postalcode"
},
  "geometry": {"coordinates":[131.5992,33.1895],"type":"Point"}
}