{
  "type": "Feature",
  "properties": {
    "gn:adm1_name":"Okayamaken",
    "gn:adm2_name":"Shitsukigunyoshiichou",
    "gn:name":"Kawai",
    "iso:country":"JP",
    "wof:name":"714-2114",
    "wof:placetype":"postalcode"
},
  "geometry": {"coordinates":[133.41,34.6509],"type":"Point"}
}