{
  "type": "Feature",
  "properties": {
    "gn:adm1_name":"Yamagataken",
    "gn:adm2_name":"Obanazawashi",
    "gn:name":"Tomiyama",
    "iso:country":"JP",
    "wof:name":"999-4206",
    "wof:placetype":"postalcode"
},
  "geometry": {"coordinates":[140.4888,38.6446],"type":"Point"}
}