{
  "type": "Feature",
  "properties": {
    "gn:adm1_name":"Fukushimaken",
    "gn:adm2_name":"Dategunhobaramachi",
    "gn:name":"Nozaki",
    "iso:country":"JP",
    "wof:name":"960-0673",
    "wof:placetype":"postalcode"
},
  "geometry": {"coordinates":[140.5573,37.8148],"type":"Point"}
}