{
  "type": "Feature",
  "properties": {
    "gn:adm1_name":"Gunmaken",
    "gn:adm2_name":"Fujiokashi",
    "gn:name":"Tatsuishi",
    "iso:country":"JP",
    "wof:name":"375-0002",
    "wof:placetype":"postalcode"
},
  "geometry": {"coordinates":[139.08619999999999,36.2804],"type":"Point"}
}