{
  "type": "Feature",
  "properties": {
    "gn:adm1_name":"Ibarakiken",
    "gn:adm2_name":"Tsukubashi",
    "gn:name":"Houyoudai",
    "iso:country":"JP",
    "wof:name":"300-1254",
    "wof:placetype":"postalcode"
},
  "geometry": {"coordinates":[140.12530000000001,35.9814],"type":"Point"}
}