{
  "type": "Feature",
  "properties": {
    "gn:adm1_name":"Fukuiken",
    "gn:adm2_name":"Tsurugashi",
    "gn:name":"Matsubachou",
    "iso:country":"JP",
    "wof:name":"914-0807",
    "wof:placetype":"postalcode"
},
  "geometry": {"coordinates":[136.04669999999999,35.6516],"type":"Point"}
}