{
  "type": "Feature",
  "properties": {
    "gn:adm1_name":"Saitamaken",
    "gn:adm2_name":"Kawagoeshi",
    "gn:name":"Matoba",
    "iso:country":"JP",
    "wof:name":"350-1101",
    "wof:placetype":"postalcode"
},
  "geometry": {"coordinates":[139.43209999999999,35.9155],"type":"Point"}
}