{
  "type": "Feature",
  "properties": {
    "gn:adm1_name":"Aichiken",
    "gn:adm2_name":"Kounanshi",
    "gn:name":"Minamyamachounaka",
    "iso:country":"JP",
    "wof:name":"483-8155",
    "wof:placetype":"postalcode"
},
  "geometry": {"coordinates":[136.87719999999999,35.3153],"type":"Point"}
}