{
  "type": "Feature",
  "properties": {
    "gn:adm1_name":"Niigataken",
    "gn:adm2_name":"Odiyashi",
    "gn:name":"Yokowatashi",
    "iso:country":"JP",
    "wof:name":"947-0002",
    "wof:placetype":"postalcode"
},
  "geometry": {"coordinates":[138.82169999999999,37.3264],"type":"Point"}
}