{
  "type": "Feature",
  "properties": {
    "gn:adm1_name":"Shimaneken",
    "gn:adm2_name":"Hamadashi",
    "gn:name":"Konyachou",
    "iso:country":"JP",
    "wof:name":"697-0031",
    "wof:placetype":"postalcode"
},
  "geometry": {"coordinates":[132.0805,34.8979],"type":"Point"}
}