{
  "type": "Feature",
  "properties": {
    "gn:adm1_name":"Aichiken",
    "gn:adm2_name":"Amagunyatomichou",
    "gn:name":"Maegasushinden",
    "iso:country":"JP",
    "wof:name":"498-0017",
    "wof:placetype":"postalcode"
},
  "geometry": {"coordinates":[136.72309999999999,35.1079],"type":"Point"}
}