{
  "type": "Feature",
  "properties": {
    "gn:adm1_name":"Toyamaken",
    "gn:adm2_name":"Higashitonamigunjouhanamachi",
    "gn:name":"Rikyuu",
    "iso:country":"JP",
    "wof:name":"939-1811",
    "wof:placetype":"postalcode"
},
  "geometry": {"coordinates":[136.90700000000001,36.5123],"type":"Point"}
}