{
  "type": "Feature",
  "properties": {
    "gn:adm1_name":"Shigaken",
    "gn:adm2_name":"Yasugunchuuzuchou",
    "gn:name":"Kigou",
    "iso:country":"JP",
    "wof:name":"524-0203",
    "wof:placetype":"postalcode"
},
  "geometry": {"coordinates":[136.0043,35.1336],"type":"Point"}
}