{
  "type": "Feature",
  "properties": {
    "gn:adm1_name":"Yamaguchiken",
    "gn:adm2_name":"Yamaguchishi",
    "gn:name":"Sufuchou",
    "iso:country":"JP",
    "wof:name":"753-0822",
    "wof:placetype":"postalcode"
},
  "geometry": {"coordinates":[131.45439999999999,34.1609],"type":"Point"}
}