{
  "type": "Feature",
  "properties": {
    "gn:adm1_name":"Kagoshimaken",
    "gn:adm2_name":"Ooshimaguntatsugouchou",
    "gn:name":"Oogachi",
    "iso:country":"JP",
    "wof:name":"894-0105",
    "wof:placetype":"postalcode"
},
  "geometry": {"coordinates":[129.583,28.3945],"type":"Point"}
}