{
  "type": "Feature",
  "properties": {
    "gn:adm1_name":"Ishikawaken",
    "gn:adm2_name":"Fugeshigunmonzenmachi",
    "gn:name":"Oogama",
    "iso:country":"JP",
    "wof:name":"927-2341",
    "wof:placetype":"postalcode"
},
  "geometry": {"coordinates":[136.71870000000001,37.2139],"type":"Point"}
}