{
  "type": "Feature",
  "properties": {
    "gn:adm1_name":"Mieken",
    "gn:adm2_name":"Tsushi",
    "gn:name":"Marunouchi",
    "iso:country":"JP",
    "wof:name":"514-0033",
    "wof:placetype":"postalcode"
},
  "geometry": {"coordinates":[136.50739999999999,34.7161],"type":"Point"}
}