{
  "type": "Feature",
  "properties": {
    "gn:adm1_name":"Ishikawaken",
    "gn:adm2_name":"Fugeshigunyanagidamura",
    "gn:name":"Ikari",
    "iso:country":"JP",
    "wof:name":"928-0332",
    "wof:placetype":"postalcode"
},
  "geometry": {"coordinates":[137.05529999999999,37.375],"type":"Point"}
}