{
  "type": "Feature",
  "properties": {
    "gn:adm1_name":"Ibarakiken",
    "gn:adm2_name":"Sashimagunsakaimachi",
    "gn:name":"Wago",
    "iso:country":"JP",
    "wof:name":"306-0415",
    "wof:placetype":"postalcode"
},
  "geometry": {"coordinates":[139.828,36.1126],"type":"Point"}
}