{
  "type": "Feature",
  "properties": {
    "gn:adm1_name":"Tokushimaken",
    "gn:adm2_name":"Narutoshi",
    "gn:name":"Setochouakinokami(Sonota)",
    "iso:country":"JP",
    "wof:name":"771-0360",
    "wof:placetype":"postalcode"
},
  "geometry": {"coordinates":[134.58189999999999,34.2051],"type":"Point"}
}