{
  "type": "Feature",
  "properties": {
    "gn:adm1_name":"Fukuokaken",
    "gn:adm2_name":"Oomutashi",
    "gn:name":"Tenjinmachi",
    "iso:country":"JP",
    "wof:name":"836-0015",
    "wof:placetype":"postalcode"
},
  "geometry": {"coordinates":[130.4427,33.0402],"type":"Point"}
}