{
  "type": "Feature",
  "properties": {
    "gn:adm1_name":"Hyougoken",
    "gn:adm2_name":"Kinosakigunkasumichou",
    "gn:name":"Kuto",
    "iso:country":"JP",
    "wof:name":"669-6411",
    "wof:placetype":"postalcode"
},
  "geometry": {"coordinates":[134.68360000000001,35.6429],"type":"Point"}
}