{
  "type": "Feature",
  "properties": {
    "gn:adm1_name":"Kagoshimaken",
    "gn:adm2_name":"Makurazakishi",
    "gn:name":"Miharamachi",
    "iso:country":"JP",
    "wof:name":"898-0056",
    "wof:placetype":"postalcode"
},
  "geometry": {"coordinates":[130.31200000000001,31.2772],"type":"Point"}
}