{
  "type": "Feature",
  "properties": {
    "gn:adm1_name":"Ibarakiken",
    "gn:adm2_name":"Tsuchiurashi",
    "gn:name":"Kasashimachi",
    "iso:country":"JP",
    "wof:name":"300-0008",
    "wof:placetype":"postalcode"
},
  "geometry": {"coordinates":[140.19210000000001,36.1242],"type":"Point"}
}