{
  "type": "Feature",
  "properties": {
    "gn:adm1_name":"Kyoutofu",
    "gn:adm2_name":"Amatagunmiwachou",
    "gn:name":"Daito",
    "iso:country":"JP",
    "wof:name":"620-1302",
    "wof:placetype":"postalcode"
},
  "geometry": {"coordinates":[135.27680000000001,35.2565],"type":"Point"}
}