{
  "type": "Feature",
  "properties": {
    "gn:adm1_name":"Ishikawaken",
    "gn:adm2_name":"Nomigunkawakitamachi",
    "gn:name":"Koroba",
    "iso:country":"JP",
    "wof:name":"923-1274",
    "wof:placetype":"postalcode"
},
  "geometry": {"coordinates":[136.51439999999999,36.4743],"type":"Point"}
}