{
  "type": "Feature",
  "properties": {
    "gn:adm1_name":"Oosakafu",
    "gn:adm2_name":"Hirakatashi",
    "gn:name":"Makinohonmachi",
    "iso:country":"JP",
    "wof:name":"573-1144",
    "wof:placetype":"postalcode"
},
  "geometry": {"coordinates":[135.673,34.8396],"type":"Point"}
}