{
  "type": "Feature",
  "properties": {
    "gn:adm1_name":"Aichiken",
    "gn:adm2_name":"Nagoyashikitaku",
    "gn:name":"Mizukirichou",
    "iso:country":"JP",
    "wof:name":"462-0833",
    "wof:placetype":"postalcode"
},
  "geometry": {"coordinates":[136.91999999999999,35.1927],"type":"Point"}
}