{
  "type": "Feature",
  "properties": {
    "gn:adm1_name":"Oosakafu",
    "gn:adm2_name":"Izumishi",
    "gn:name":"Midorigaoka",
    "iso:country":"JP",
    "wof:name":"594-1155",
    "wof:placetype":"postalcode"
},
  "geometry": {"coordinates":[135.4572,34.446],"type":"Point"}
}