{
  "type": "Feature",
  "properties": {
    "gn:adm1_name":"Oosakafu",
    "gn:adm2_name":"Sakaishi",
    "gn:name":"Fuseo",
    "iso:country":"JP",
    "wof:name":"599-8254",
    "wof:placetype":"postalcode"
},
  "geometry": {"coordinates":[135.4949,34.5125],"type":"Point"}
}