{
  "type": "Feature",
  "properties": {
    "gn:adm1_name":"Fukuiken",
    "gn:adm2_name":"Fukuishi",
    "gn:name":"Shimotougouchou(Shinmura)",
    "iso:country":"JP",
    "wof:name":"919-0373",
    "wof:placetype":"postalcode"
},
  "geometry": {"coordinates":[136.26050000000001,36.019],"type":"Point"}
}