{
  "type": "Feature",
  "properties": {
    "gn:adm1_name":"Toyamaken",
    "gn:adm2_name":"Nakaniikawaguntateyamamachi",
    "gn:name":"Suetaniguchi",
    "iso:country":"JP",
    "wof:name":"930-0244",
    "wof:placetype":"postalcode"
},
  "geometry": {"coordinates":[137.33609999999999,36.6245],"type":"Point"}
}