{
  "type": "Feature",
  "properties": {
    "gn:adm1_name":"Ooitaken",
    "gn:adm2_name":"Nakatsushi",
    "gn:name":"Ebisumachi",
    "iso:country":"JP",
    "wof:name":"871-0065",
    "wof:placetype":"postalcode"
},
  "geometry": {"coordinates":[131.1917,33.6016],"type":"Point"}
}