{
  "type": "Feature",
  "properties": {
    "gn:adm1_name":"Niigataken",
    "gn:adm2_name":"Tookamachishi",
    "gn:name":"Takadachou(3choume)",
    "iso:country":"JP",
    "wof:name":"948-0065",
    "wof:placetype":"postalcode"
},
  "geometry": {"coordinates":[138.75229999999999,37.1329],"type":"Point"}
}