{
  "type": "Feature",
  "properties": {
    "gn:adm1_name":"Nagasakiken",
    "gn:adm2_name":"Isahayashi",
    "gn:name":"Shirahamachou",
    "iso:country":"JP",
    "wof:name":"859-0304",
    "wof:placetype":"postalcode"
},
  "geometry": {"coordinates":[130.09710000000001,32.878],"type":"Point"}
}