{
  "type": "Feature",
  "properties": {
    "gn:adm1_name":"Ooitaken",
    "gn:adm2_name":"Hitashi",
    "gn:name":"Oomiyamachi",
    "iso:country":"JP",
    "wof:name":"877-0055",
    "wof:placetype":"postalcode"
},
  "geometry": {"coordinates":[130.94759999999999,33.2994],"type":"Point"}
}