{
  "type": "Feature",
  "properties": {
    "gn:adm1_name":"Ishikawaken",
    "gn:adm2_name":"Fugeshigunmonzenmachi",
    "gn:name":"Tamura",
    "iso:country":"JP",
    "wof:name":"927-2105",
    "wof:placetype":"postalcode"
},
  "geometry": {"coordinates":[136.7911,37.2973],"type":"Point"}
}