{
  "type": "Feature",
  "properties": {
    "gn:adm1_name":"Shizuokaken",
    "gn:adm2_name":"Numadushi",
    "gn:name":"Sugizakichou",
    "iso:country":"JP",
    "wof:name":"410-0033",
    "wof:placetype":"postalcode"
},
  "geometry": {"coordinates":[138.86590000000001,35.1075],"type":"Point"}
}