{
  "type": "Feature",
  "properties": {
    "gn:adm1_name":"Kyoutofu",
    "gn:adm2_name":"Kyoutoshiminamiku",
    "gn:name":"Kisshouinshimizuchou",
    "iso:country":"JP",
    "wof:name":"601-8329",
    "wof:placetype":"postalcode"
},
  "geometry": {"coordinates":[135.73240000000001,34.9792],"type":"Point"}
}