{
  "type": "Feature",
  "properties": {
    "gn:adm1_name":"Yamagataken",
    "gn:adm2_name":"Yonezawashi",
    "gn:name":"Sasanomachi",
    "iso:country":"JP",
    "wof:name":"992-1441",
    "wof:placetype":"postalcode"
},
  "geometry": {"coordinates":[140.0943,37.8902],"type":"Point"}
}