{
  "type": "Feature",
  "properties": {
    "gn:adm1_name":"Gifuken",
    "gn:adm2_name":"Oogakishi",
    "gn:name":"Irikata",
    "iso:country":"JP",
    "wof:name":"503-0962",
    "wof:placetype":"postalcode"
},
  "geometry": {"coordinates":[136.59970000000001,35.3284],"type":"Point"}
}