{
  "type": "Feature",
  "properties": {
    "gn:adm1_name":"Saitamaken",
    "gn:adm2_name":"Kitasaitamagunkawasatomachi",
    "gn:name":"Hiroda",
    "iso:country":"JP",
    "wof:name":"365-0005",
    "wof:placetype":"postalcode"
},
  "geometry": {"coordinates":[139.51060000000001,36.0628],"type":"Point"}
}