{
  "type": "Feature",
  "properties": {
    "gn:adm1_name":"Kanagawaken",
    "gn:adm2_name":"Chigasakishi",
    "gn:name":"Matsugaoka",
    "iso:country":"JP",
    "wof:name":"253-0025",
    "wof:placetype":"postalcode"
},
  "geometry": {"coordinates":[139.4238,35.3272],"type":"Point"}
}