{
  "type": "Feature",
  "properties": {
    "gn:adm1_name":"Niigataken",
    "gn:adm2_name":"Sanjoushi",
    "gn:name":"Shimada",
    "iso:country":"JP",
    "wof:name":"955-0842",
    "wof:placetype":"postalcode"
},
  "geometry": {"coordinates":[138.9462,37.6274],"type":"Point"}
}