{
  "type": "Feature",
  "properties": {
    "gn:adm1_name":"Fukuokaken",
    "gn:adm2_name":"Miigunkitanomachi",
    "gn:name":"Yaegame",
    "iso:country":"JP",
    "wof:name":"830-1102",
    "wof:placetype":"postalcode"
},
  "geometry": {"coordinates":[130.62360000000001,33.3543],"type":"Point"}
}