{
  "type": "Feature",
  "properties": {
    "gn:adm1_name":"Hiroshimaken",
    "gn:adm2_name":"Ootakeshi",
    "gn:name":"Honmachi",
    "iso:country":"JP",
    "wof:name":"739-0613",
    "wof:placetype":"postalcode"
},
  "geometry": {"coordinates":[132.21860000000001,34.2107],"type":"Point"}
}