{
  "type": "Feature",
  "properties": {
    "gn:adm1_name":"Aichiken",
    "gn:adm2_name":"Nishioshi",
    "gn:name":"Adumachou",
    "iso:country":"JP",
    "wof:name":"445-0861",
    "wof:placetype":"postalcode"
},
  "geometry": {"coordinates":[137.05330000000001,34.8651],"type":"Point"}
}