{
  "type": "Feature",
  "properties": {
    "gn:adm1_name":"Chibaken",
    "gn:adm2_name":"Mobarashi",
    "gn:name":"Oshibi",
    "iso:country":"JP",
    "wof:name":"297-0075",
    "wof:placetype":"postalcode"
},
  "geometry": {"coordinates":[140.2723,35.447],"type":"Point"}
}