{
  "type": "Feature",
  "properties": {
    "gn:adm1_name":"Ibarakiken",
    "gn:adm2_name":"Hitachishi",
    "gn:name":"Nakanarusawachou",
    "iso:country":"JP",
    "wof:name":"316-0033",
    "wof:placetype":"postalcode"
},
  "geometry": {"coordinates":[140.6404,36.5763],"type":"Point"}
}