{
  "type": "Feature",
  "properties": {
    "gn:adm1_name":"Hyougoken",
    "gn:adm2_name":"Koubeshikitaku",
    "gn:name":"Ougochoumikage",
    "iso:country":"JP",
    "wof:name":"651-1621",
    "wof:placetype":"postalcode"
},
  "geometry": {"coordinates":[135.14009999999999,34.8307],"type":"Point"}
}