{
  "type": "Feature",
  "properties": {
    "gn:adm1_name":"Naganoken",
    "gn:adm2_name":"Komoroshi",
    "gn:name":"Mimitori",
    "iso:country":"JP",
    "wof:name":"384-0084",
    "wof:placetype":"postalcode"
},
  "geometry": {"coordinates":[138.4298,36.2887],"type":"Point"}
}