{
  "type": "Feature",
  "properties": {
    "gn:adm1_name":"Tokushimaken",
    "gn:adm2_name":"Tokushimashi",
    "gn:name":"Kokufuchouhigashitakawa",
    "iso:country":"JP",
    "wof:name":"779-3105",
    "wof:placetype":"postalcode"
},
  "geometry": {"coordinates":[134.4819,34.0922],"type":"Point"}
}