{
  "type": "Feature",
  "properties": {
    "gn:adm1_name":"Kyoutofu",
    "gn:adm2_name":"Kyoutoshinakagyouku",
    "gn:name":"Nishinokyoukurumazakachou",
    "iso:country":"JP",
    "wof:name":"604-8405",
    "wof:placetype":"postalcode"
},
  "geometry": {"coordinates":[135.73830000000001,35.0171],"type":"Point"}
}