{
  "type": "Feature",
  "properties": {
    "gn:adm1_name":"Niigataken",
    "gn:adm2_name":"Nishikanbaragunyahikomura",
    "gn:name":"Nakayama",
    "iso:country":"JP",
    "wof:name":"959-0312",
    "wof:placetype":"postalcode"
},
  "geometry": {"coordinates":[138.84999999999999,37.6936],"type":"Point"}
}