{
  "type": "Feature",
  "properties": {
    "gn:adm1_name":"Toyamaken",
    "gn:adm2_name":"Higashitonamiguntairamura",
    "gn:name":"Kogurusu",
    "iso:country":"JP",
    "wof:name":"939-1926",
    "wof:placetype":"postalcode"
},
  "geometry": {"coordinates":[136.9443,36.4409],"type":"Point"}
}