{
  "type": "Feature",
  "properties": {
    "gn:adm1_name":"Fukushimaken",
    "gn:adm2_name":"Iwakishi",
    "gn:name":"Yoshimamachishimoyoshima",
    "iso:country":"JP",
    "wof:name":"970-1151",
    "wof:placetype":"postalcode"
},
  "geometry": {"coordinates":[140.86850000000001,37.0593],"type":"Point"}
}