{
  "type": "Feature",
  "properties": {
    "gn:adm1_name":"Niigataken",
    "gn:adm2_name":"Iwafunegunsekikawamura",
    "gn:name":"Miyanomae",
    "iso:country":"JP",
    "wof:name":"959-3202",
    "wof:placetype":"postalcode"
},
  "geometry": {"coordinates":[139.53569999999999,38.1358],"type":"Point"}
}