{
  "type": "Feature",
  "properties": {
    "gn:adm1_name":"Ooitaken",
    "gn:adm2_name":"Oonogunmiemachi",
    "gn:name":"Ashikari",
    "iso:country":"JP",
    "wof:name":"879-7105",
    "wof:placetype":"postalcode"
},
  "geometry": {"coordinates":[131.60769999999999,32.998],"type":"Point"}
}