{
  "type": "Feature",
  "properties": {
    "gn:adm1_name":"Toyamaken",
    "gn:adm2_name":"Higashitonamigun'Inamimachi",
    "gn:name":"Sakaemachi",
    "iso:country":"JP",
    "wof:name":"932-0213",
    "wof:placetype":"postalcode"
},
  "geometry": {"coordinates":[136.97319999999999,36.5637],"type":"Point"}
}