{
  "type": "Feature",
  "properties": {
    "gn:adm1_name":"Ishikawaken",
    "gn:adm2_name":"Kagashi",
    "gn:name":"Kosuganamimachi",
    "iso:country":"JP",
    "wof:name":"922-0424",
    "wof:placetype":"postalcode"
},
  "geometry": {"coordinates":[136.34780000000001,36.3183],"type":"Point"}
}