{
  "type": "Feature",
  "properties": {
    "gn:adm1_name":"Aichiken",
    "gn:adm2_name":"Oobushi",
    "gn:name":"Kitayamachou",
    "iso:country":"JP",
    "wof:name":"474-0072",
    "wof:placetype":"postalcode"
},
  "geometry": {"coordinates":[136.96770000000001,35.0315],"type":"Point"}
}