{
  "type": "Feature",
  "properties": {
    "gn:adm1_name":"Toyamaken",
    "gn:adm2_name":"Higashitonamigunfukunomachi",
    "gn:name":"Bande",
    "iso:country":"JP",
    "wof:name":"939-1541",
    "wof:placetype":"postalcode"
},
  "geometry": {"coordinates":[136.89670000000001,36.5909],"type":"Point"}
}