{
  "type": "Feature",
  "properties": {
    "gn:adm1_name":"Fukuiken",
    "gn:adm2_name":"Obamashi",
    "gn:name":"Obamasuzuka",
    "iso:country":"JP",
    "wof:name":"917-0087",
    "wof:placetype":"postalcode"
},
  "geometry": {"coordinates":[135.74260000000001,35.4991],"type":"Point"}
}