{
  "type": "Feature",
  "properties": {
    "gn:adm1_name":"Tottoriken",
    "gn:adm2_name":"Tottorishi",
    "gn:name":"Kuritanichou",
    "iso:country":"JP",
    "wof:name":"680-0012",
    "wof:placetype":"postalcode"
},
  "geometry": {"coordinates":[134.24189999999999,35.5037],"type":"Point"}
}