{
  "type": "Feature",
  "properties": {
    "gn:adm1_name":"Naraken",
    "gn:adm2_name":"Yoshinogunkawakamimura",
    "gn:name":"Shiraya",
    "iso:country":"JP",
    "wof:name":"639-3555",
    "wof:placetype":"postalcode"
},
  "geometry": {"coordinates":[135.96729999999999,34.3359],"type":"Point"}
}