{
  "type": "Feature",
  "properties": {
    "gn:adm1_name":"Hyougoken",
    "gn:adm2_name":"Ibogunshinguuchou",
    "gn:name":"Shimonoda",
    "iso:country":"JP",
    "wof:name":"679-4333",
    "wof:placetype":"postalcode"
},
  "geometry": {"coordinates":[134.5377,34.892],"type":"Point"}
}