{
  "type": "Feature",
  "properties": {
    "gn:adm1_name":"Ishikawaken",
    "gn:adm2_name":"Kanazawashi",
    "gn:name":"Hiyoshimachi",
    "iso:country":"JP",
    "wof:name":"920-0033",
    "wof:placetype":"postalcode"
},
  "geometry": {"coordinates":[136.64619999999999,36.5759],"type":"Point"}
}