{
  "type": "Feature",
  "properties": {
    "gn:adm1_name":"Hiroshimaken",
    "gn:adm2_name":"Hiroshimashisaekiku",
    "gn:name":"Itsukaichikou",
    "iso:country":"JP",
    "wof:name":"731-5161",
    "wof:placetype":"postalcode"
},
  "geometry": {"coordinates":[132.35419999999999,34.3521],"type":"Point"}
}