{
  "type": "Feature",
  "properties": {
    "gn:adm1_name":"Hyougoken",
    "gn:adm2_name":"Sasayamashi",
    "gn:name":"Higashikosa",
    "iso:country":"JP",
    "wof:name":"669-2201",
    "wof:placetype":"postalcode"
},
  "geometry": {"coordinates":[135.18879999999999,35.0737],"type":"Point"}
}