{
  "type": "Feature",
  "properties": {
    "gn:adm1_name":"Yamaguchiken",
    "gn:adm2_name":"Shuunanshi",
    "gn:name":"Nagatachou",
    "iso:country":"JP",
    "wof:name":"746-0054",
    "wof:placetype":"postalcode"
},
  "geometry": {"coordinates":[131.7243,34.0624],"type":"Point"}
}