{
  "type": "Feature",
  "properties": {
    "gn:adm1_name":"Gifuken",
    "gn:adm2_name":"Yoshikigunkamiokachou",
    "gn:name":"Nokubi",
    "iso:country":"JP",
    "wof:name":"506-1141",
    "wof:placetype":"postalcode"
},
  "geometry": {"coordinates":[137.31379999999999,36.3046],"type":"Point"}
}