{
  "type": "Feature",
  "properties": {
    "gn:adm1_name":"Chibaken",
    "gn:adm2_name":"Chouseigun'Ichinomiyamachi",
    "gn:name":"Miyabara",
    "iso:country":"JP",
    "wof:name":"299-4312",
    "wof:placetype":"postalcode"
},
  "geometry": {"coordinates":[140.36199999999999,35.382],"type":"Point"}
}