{
  "type": "Feature",
  "properties": {
    "gn:adm1_name":"Kanagawaken",
    "gn:adm2_name":"Iseharashi",
    "gn:name":"Shimohirama",
    "iso:country":"JP",
    "wof:name":"259-1125",
    "wof:placetype":"postalcode"
},
  "geometry": {"coordinates":[139.32149999999999,35.3843],"type":"Point"}
}