{
  "type": "Feature",
  "properties": {
    "gn:adm1_name":"Gifuken",
    "gn:adm2_name":"Takayamashi",
    "gn:name":"Nishinoisshikimachi",
    "iso:country":"JP",
    "wof:name":"506-0031",
    "wof:placetype":"postalcode"
},
  "geometry": {"coordinates":[137.2474,36.134],"type":"Point"}
}