{
  "type": "Feature",
  "properties": {
    "gn:adm1_name":"Okayamaken",
    "gn:adm2_name":"Atetsuguntetsutachou",
    "gn:name":"Tabuchi",
    "iso:country":"JP",
    "wof:name":"718-0312",
    "wof:placetype":"postalcode"
},
  "geometry": {"coordinates":[133.3828,34.926],"type":"Point"}
}