{
  "type": "Feature",
  "properties": {
    "gn:adm1_name":"Saitamaken",
    "gn:adm2_name":"Kodamagunkodamamachi",
    "gn:name":"Tabata",
    "iso:country":"JP",
    "wof:name":"367-0222",
    "wof:placetype":"postalcode"
},
  "geometry": {"coordinates":[139.11279999999999,36.1962],"type":"Point"}
}