{
  "type": "Feature",
  "properties": {
    "gn:adm1_name":"Ehimeken",
    "gn:adm2_name":"Nishiuwagunsetochou",
    "gn:name":"Ashinaru",
    "iso:country":"JP",
    "wof:name":"796-0501",
    "wof:placetype":"postalcode"
},
  "geometry": {"coordinates":[132.2679,33.4717],"type":"Point"}
}