{
  "type": "Feature",
  "properties": {
    "gn:adm1_name":"Oosakafu",
    "gn:adm2_name":"Sakaishi",
    "gn:name":"Notouchou",
    "iso:country":"JP",
    "wof:name":"591-8013",
    "wof:placetype":"postalcode"
},
  "geometry": {"coordinates":[135.5438,34.5619],"type":"Point"}
}