{
  "type": "Feature",
  "properties": {
    "gn:adm1_name":"Naraken",
    "gn:adm2_name":"Kitakatsuragigunkouryouchou",
    "gn:name":"Minami",
    "iso:country":"JP",
    "wof:name":"635-0818",
    "wof:placetype":"postalcode"
},
  "geometry": {"coordinates":[135.75129999999999,34.5631],"type":"Point"}
}