{
  "type": "Feature",
  "properties": {
    "gn:adm1_name":"Hiroshimaken",
    "gn:adm2_name":"Hibaguntakanochou",
    "gn:name":"Okumonden",
    "iso:country":"JP",
    "wof:name":"727-0422",
    "wof:placetype":"postalcode"
},
  "geometry": {"coordinates":[132.90119999999999,35.0067],"type":"Point"}
}