{
  "type": "Feature",
  "properties": {
    "gn:adm1_name":"Aichiken",
    "gn:adm2_name":"Amagunjimokujichou",
    "gn:name":"Ishitsukuri",
    "iso:country":"JP",
    "wof:name":"490-1102",
    "wof:placetype":"postalcode"
},
  "geometry": {"coordinates":[136.81620000000001,35.206],"type":"Point"}
}