{
  "type": "Feature",
  "properties": {
    "gn:adm1_name":"Hiroshimaken",
    "gn:adm2_name":"Akigunfuchuuchou",
    "gn:name":"Momoyama",
    "iso:country":"JP",
    "wof:name":"735-0026",
    "wof:placetype":"postalcode"
},
  "geometry": {"coordinates":[132.50739999999999,34.379],"type":"Point"}
}