{
  "type": "Feature",
  "properties": {
    "gn:adm1_name":"Wakayamaken",
    "gn:adm2_name":"Wakayamashi",
    "gn:name":"Aridayamachi",
    "iso:country":"JP",
    "wof:name":"640-8248",
    "wof:placetype":"postalcode"
},
  "geometry": {"coordinates":[135.1661,34.2276],"type":"Point"}
}