{
  "type": "Feature",
  "properties": {
    "gn:adm1_name":"Kumamotoken",
    "gn:adm2_name":"Yatsushiroshi",
    "gn:name":"Miyajimachi",
    "iso:country":"JP",
    "wof:name":"866-0805",
    "wof:placetype":"postalcode"
},
  "geometry": {"coordinates":[130.63849999999999,32.5013],"type":"Point"}
}