{
  "type": "Feature",
  "properties": {
    "gn:adm1_name":"Ibarakiken",
    "gn:adm2_name":"Takahagishi",
    "gn:name":"Yokokawa",
    "iso:country":"JP",
    "wof:name":"318-0101",
    "wof:placetype":"postalcode"
},
  "geometry": {"coordinates":[140.63900000000001,36.8094],"type":"Point"}
}