{
  "type": "Feature",
  "properties": {
    "gn:adm1_name":"Saitamaken",
    "gn:adm2_name":"Sayamashi",
    "gn:name":"Minamiiriso",
    "iso:country":"JP",
    "wof:name":"350-1316",
    "wof:placetype":"postalcode"
},
  "geometry": {"coordinates":[139.42840000000001,35.8348],"type":"Point"}
}