{
  "type": "Feature",
  "properties": {
    "gn:adm1_name":"Niigataken",
    "gn:adm2_name":"Murakamishi",
    "gn:name":"Chuugenmachi",
    "iso:country":"JP",
    "wof:name":"958-0823",
    "wof:placetype":"postalcode"
},
  "geometry": {"coordinates":[139.49039999999999,38.2191],"type":"Point"}
}