{
  "type": "Feature",
  "properties": {
    "gn:adm1_name":"Ishikawaken",
    "gn:adm2_name":"Kagashi",
    "gn:name":"Daishoujinakachou",
    "iso:country":"JP",
    "wof:name":"922-0051",
    "wof:placetype":"postalcode"
},
  "geometry": {"coordinates":[136.31180000000001,36.3088],"type":"Point"}
}