{
  "type": "Feature",
  "properties": {
    "gn:adm1_name":"Hyougoken",
    "gn:adm2_name":"Koubeshisumaku",
    "gn:name":"Yourouchou",
    "iso:country":"JP",
    "wof:name":"654-0006",
    "wof:placetype":"postalcode"
},
  "geometry": {"coordinates":[135.13130000000001,34.6644],"type":"Point"}
}