{
  "type": "Feature",
  "properties": {
    "gn:adm1_name":"Chibaken",
    "gn:adm2_name":"Isumigunmisakimachi",
    "gn:name":"Nakadaki",
    "iso:country":"JP",
    "wof:name":"299-4623",
    "wof:placetype":"postalcode"
},
  "geometry": {"coordinates":[140.37110000000001,35.2994],"type":"Point"}
}