{
  "type": "Feature",
  "properties": {
    "gn:adm1_name":"Tottoriken",
    "gn:adm2_name":"Saihakugunnakayamachou",
    "gn:name":"Tanaka",
    "iso:country":"JP",
    "wof:name":"689-3114",
    "wof:placetype":"postalcode"
},
  "geometry": {"coordinates":[133.5925,35.5217],"type":"Point"}
}