{
  "type": "Feature",
  "properties": {
    "gn:adm1_name":"Shizuokaken",
    "gn:adm2_name":"Iwatashi",
    "gn:name":"Samejima",
    "iso:country":"JP",
    "wof:name":"438-0055",
    "wof:placetype":"postalcode"
},
  "geometry": {"coordinates":[137.8449,34.675],"type":"Point"}
}