{
  "type": "Feature",
  "properties": {
    "gn:adm1_name":"Nagasakiken",
    "gn:adm2_name":"Ikigunkatsumotochou",
    "gn:name":"Honguunakafure",
    "iso:country":"JP",
    "wof:name":"811-5546",
    "wof:placetype":"postalcode"
},
  "geometry": {"coordinates":[129.68029999999999,33.8224],"type":"Point"}
}