{
  "type": "Feature",
  "properties": {
    "gn:adm1_name":"Sagaken",
    "gn:adm2_name":"Sagashi",
    "gn:name":"Takakisemachinagase",
    "iso:country":"JP",
    "wof:name":"849-0917",
    "wof:placetype":"postalcode"
},
  "geometry": {"coordinates":[130.28829999999999,33.2939],"type":"Point"}
}