{
  "type": "Feature",
  "properties": {
    "gn:adm1_name":"Toyamaken",
    "gn:adm2_name":"Nishitonamigunfukumitsumachi",
    "gn:name":"Koyama",
    "iso:country":"JP",
    "wof:name":"939-1665",
    "wof:placetype":"postalcode"
},
  "geometry": {"coordinates":[136.8458,36.5499],"type":"Point"}
}