{
  "type": "Feature",
  "properties": {
    "gn:adm1_name":"Kumamotoken",
    "gn:adm2_name":"Shimomashikigunchuuoumachi",
    "gn:name":"Sakamoto",
    "iso:country":"JP",
    "wof:name":"861-4415",
    "wof:placetype":"postalcode"
},
  "geometry": {"coordinates":[130.81960000000001,32.5785],"type":"Point"}
}