{
  "type": "Feature",
  "properties": {
    "gn:adm1_name":"Aichiken",
    "gn:adm2_name":"Higashikamogun'Asukechou",
    "gn:name":"Tochimoto",
    "iso:country":"JP",
    "wof:name":"444-2324",
    "wof:placetype":"postalcode"
},
  "geometry": {"coordinates":[137.2911,35.0918],"type":"Point"}
}