{
  "type": "Feature",
  "properties": {
    "gn:adm1_name":"Niigataken",
    "gn:adm2_name":"Iwafunegunsanpokumachi",
    "gn:name":"Arakawa",
    "iso:country":"JP",
    "wof:name":"959-3923",
    "wof:placetype":"postalcode"
},
  "geometry": {"coordinates":[139.59970000000001,38.4562],"type":"Point"}
}