{
  "type": "Feature",
  "properties": {
    "gn:adm1_name":"Tottoriken",
    "gn:adm2_name":"Hinogunmizokuchichou",
    "gn:name":"Iwatate",
    "iso:country":"JP",
    "wof:name":"689-4214",
    "wof:placetype":"postalcode"
},
  "geometry": {"coordinates":[133.48750000000001,35.3646],"type":"Point"}
}