{
  "type": "Feature",
  "properties": {
    "gn:adm1_name":"Hiroshimaken",
    "gn:adm2_name":"Kureshi",
    "gn:name":"Yakeyamanishi",
    "iso:country":"JP",
    "wof:name":"737-0903",
    "wof:placetype":"postalcode"
},
  "geometry": {"coordinates":[132.55080000000001,34.2901],"type":"Point"}
}