{
  "type": "Feature",
  "properties": {
    "gn:adm1_name":"Kanagawaken",
    "gn:adm2_name":"Atsugishi",
    "gn:name":"Hase",
    "iso:country":"JP",
    "wof:name":"243-0036",
    "wof:placetype":"postalcode"
},
  "geometry": {"coordinates":[139.33600000000001,35.4324],"type":"Point"}
}