{
  "type": "Feature",
  "properties": {
    "gn:adm1_name":"Miyagiken",
    "gn:adm2_name":"Kesennumashi",
    "gn:name":"Shitanda",
    "iso:country":"JP",
    "wof:name":"988-0063",
    "wof:placetype":"postalcode"
},
  "geometry": {"coordinates":[141.55760000000001,38.9009],"type":"Point"}
}