{
  "type": "Feature",
  "properties": {
    "gn:adm1_name":"Miyagiken",
    "gn:adm2_name":"Miyagigunrifuchou",
    "gn:name":"Shirakashidai",
    "iso:country":"JP",
    "wof:name":"981-0134",
    "wof:placetype":"postalcode"
},
  "geometry": {"coordinates":[140.96260000000001,38.3489],"type":"Point"}
}