{
  "type": "Feature",
  "properties": {
    "gn:adm1_name":"Kyoutofu",
    "gn:adm2_name":"Yawatashi",
    "gn:name":"Nojirishouhata",
    "iso:country":"JP",
    "wof:name":"614-8196",
    "wof:placetype":"postalcode"
},
  "geometry": {"coordinates":[135.74369999999999,34.8627],"type":"Point"}
}