{
  "type": "Feature",
  "properties": {
    "gn:adm1_name":"Kanagawaken",
    "gn:adm2_name":"Yokohamashihodogayaku",
    "gn:name":"Tokiwadai",
    "iso:country":"JP",
    "wof:name":"240-0067",
    "wof:placetype":"postalcode"
},
  "geometry": {"coordinates":[139.589,35.4725],"type":"Point"}
}