{
  "type": "Feature",
  "properties": {
    "gn:adm1_name":"Miyazakiken",
    "gn:adm2_name":"Hyuugashi",
    "gn:name":"Hososhima",
    "iso:country":"JP",
    "wof:name":"883-0001",
    "wof:placetype":"postalcode"
},
  "geometry": {"coordinates":[131.66480000000001,32.4261],"type":"Point"}
}