{
  "type": "Feature",
  "properties": {
    "gn:adm1_name":"Niigataken",
    "gn:adm2_name":"Gosenshi",
    "gn:name":"Nakagawashin",
    "iso:country":"JP",
    "wof:name":"959-1632",
    "wof:placetype":"postalcode"
},
  "geometry": {"coordinates":[139.22309999999999,37.7211],"type":"Point"}
}