{
  "type": "Feature",
  "properties": {
    "gn:adm1_name":"Shizuokaken",
    "gn:adm2_name":"Shizuokashi",
    "gn:name":"Yunoki",
    "iso:country":"JP",
    "wof:name":"420-0821",
    "wof:placetype":"postalcode"
},
  "geometry": {"coordinates":[138.4067,34.9822],"type":"Point"}
}