{
  "type": "Feature",
  "properties": {
    "gn:adm1_name":"Wakayamaken",
    "gn:adm2_name":"Kainanshi",
    "gn:name":"Nanayama",
    "iso:country":"JP",
    "wof:name":"640-0441",
    "wof:placetype":"postalcode"
},
  "geometry": {"coordinates":[135.3081,34.1928],"type":"Point"}
}