{
  "type": "Feature",
  "properties": {
    "gn:adm1_name":"Miyagiken",
    "gn:adm2_name":"Oshikagun'Onagawachou",
    "gn:name":"Iigohama",
    "iso:country":"JP",
    "wof:name":"986-2222",
    "wof:placetype":"postalcode"
},
  "geometry": {"coordinates":[141.48220000000001,38.3986],"type":"Point"}
}