{
  "type": "Feature",
  "properties": {
    "gn:adm1_name":"Gifuken",
    "gn:adm2_name":"Sekishi",
    "gn:name":"Jikkenchou",
    "iso:country":"JP",
    "wof:name":"501-3878",
    "wof:placetype":"postalcode"
},
  "geometry": {"coordinates":[136.91370000000001,35.4851],"type":"Point"}
}