{
  "type": "Feature",
  "properties": {
    "gn:adm1_name":"Ooitaken",
    "gn:adm2_name":"Usukishi",
    "gn:name":"Kakidaki",
    "iso:country":"JP",
    "wof:name":"875-0073",
    "wof:placetype":"postalcode"
},
  "geometry": {"coordinates":[131.7518,33.0934],"type":"Point"}
}