{
  "type": "Feature",
  "properties": {
    "gn:adm1_name":"Yamaguchiken",
    "gn:adm2_name":"Onodashi",
    "gn:name":"Onoda",
    "iso:country":"JP",
    "wof:name":"756-0817",
    "wof:placetype":"postalcode"
},
  "geometry": {"coordinates":[131.17789999999999,33.9639],"type":"Point"}
}