{
  "type": "Feature",
  "properties": {
    "gn:adm1_name":"Gifuken",
    "gn:adm2_name":"Hashimagunkasamatsuchou",
    "gn:name":"Shoueichou",
    "iso:country":"JP",
    "wof:name":"501-6091",
    "wof:placetype":"postalcode"
},
  "geometry": {"coordinates":[136.76390000000001,35.377],"type":"Point"}
}