{
  "type": "Feature",
  "properties": {
    "gn:adm1_name":"Kyoutofu",
    "gn:adm2_name":"Kyoutoshifushimiku",
    "gn:name":"Momoyamachouyamanoshita",
    "iso:country":"JP",
    "wof:name":"612-8002",
    "wof:placetype":"postalcode"
},
  "geometry": {"coordinates":[135.79480000000001,34.9377],"type":"Point"}
}