{
  "type": "Feature",
  "properties": {
    "gn:adm1_name":"Aichiken",
    "gn:adm2_name":"Taharashi",
    "gn:name":"Ikeshirichou",
    "iso:country":"JP",
    "wof:name":"441-3505",
    "wof:placetype":"postalcode"
},
  "geometry": {"coordinates":[137.1816,34.6061],"type":"Point"}
}