{
  "type": "Feature",
  "properties": {
    "gn:adm1_name":"Kyoutofu",
    "gn:adm2_name":"Kyoutoshiukyouku",
    "gn:name":"Uzumasayasuimatsumotochou",
    "iso:country":"JP",
    "wof:name":"616-8085",
    "wof:placetype":"postalcode"
},
  "geometry": {"coordinates":[135.71719999999999,35.0105],"type":"Point"}
}