{
  "type": "Feature",
  "properties": {
    "gn:adm1_name":"Tottoriken",
    "gn:adm2_name":"Saihakugunkishimotochou",
    "gn:name":"Yoshisada",
    "iso:country":"JP",
    "wof:name":"689-4131",
    "wof:placetype":"postalcode"
},
  "geometry": {"coordinates":[133.41739999999999,35.3727],"type":"Point"}
}