{
  "type": "Feature",
  "properties": {
    "gn:adm1_name":"Niigataken",
    "gn:adm2_name":"Murakamishi",
    "gn:name":"Kagamachi",
    "iso:country":"JP",
    "wof:name":"958-0875",
    "wof:placetype":"postalcode"
},
  "geometry": {"coordinates":[139.48009999999999,38.2286],"type":"Point"}
}