{
  "type": "Feature",
  "properties": {
    "gn:adm1_name":"Ishikawaken",
    "gn:adm2_name":"Komatsushi",
    "gn:name":"Kofumachi",
    "iso:country":"JP",
    "wof:name":"923-0055",
    "wof:placetype":"postalcode"
},
  "geometry": {"coordinates":[136.5016,36.4103],"type":"Point"}
}