{
  "type": "Feature",
  "properties": {
    "gn:adm1_name":"Niigataken",
    "gn:adm2_name":"Sadogun'Aikawamachi",
    "gn:name":"Minamikatabe",
    "iso:country":"JP",
    "wof:name":"952-2226",
    "wof:placetype":"postalcode"
},
  "geometry": {"coordinates":[138.30289999999999,38.1506],"type":"Point"}
}