{
  "type": "Feature",
  "properties": {
    "gn:adm1_name":"Shimaneken",
    "gn:adm2_name":"Ooharagunkamomachi",
    "gn:name":"Daisai",
    "iso:country":"JP",
    "wof:name":"699-1101",
    "wof:placetype":"postalcode"
},
  "geometry": {"coordinates":[132.91720000000001,35.3366],"type":"Point"}
}