{
  "type": "Feature",
  "properties": {
    "gn:adm1_name":"Niigataken",
    "gn:adm2_name":"Nishikubikigun'Oumimachi",
    "gn:name":"Tonami",
    "iso:country":"JP",
    "wof:name":"949-0308",
    "wof:placetype":"postalcode"
},
  "geometry": {"coordinates":[137.72790000000001,37.0012],"type":"Point"}
}