{
  "type": "Feature",
  "properties": {
    "gn:adm1_name":"Gunmaken",
    "gn:adm2_name":"Setagunniisatomura",
    "gn:name":"Yamakami",
    "iso:country":"JP",
    "wof:name":"376-0125",
    "wof:placetype":"postalcode"
},
  "geometry": {"coordinates":[139.23140000000001,36.4279],"type":"Point"}
}