{
  "type": "Feature",
  "properties": {
    "gn:adm1_name":"Toyamaken",
    "gn:adm2_name":"Toyamashi",
    "gn:name":"Uwanokotobukichou",
    "iso:country":"JP",
    "wof:name":"939-8197",
    "wof:placetype":"postalcode"
},
  "geometry": {"coordinates":[137.21610000000001,36.6379],"type":"Point"}
}