{
  "type": "Feature",
  "properties": {
    "gn:adm1_name":"Fukuokaken",
    "gn:adm2_name":"Fukuokashihigashiku",
    "gn:name":"Sharyou",
    "iso:country":"JP",
    "wof:name":"812-0068",
    "wof:placetype":"postalcode"
},
  "geometry": {"coordinates":[130.43299999999999,33.6114],"type":"Point"}
}