{
  "type": "Feature",
  "properties": {
    "gn:adm1_name":"Tokushimaken",
    "gn:adm2_name":"Tokushimashi",
    "gn:name":"Kawauchichou(Tomihisa)",
    "iso:country":"JP",
    "wof:name":"771-0111",
    "wof:placetype":"postalcode"
},
  "geometry": {"coordinates":[134.59059999999999,34.1062],"type":"Point"}
}