{
  "type": "Feature",
  "properties": {
    "gn:adm1_name":"Saitamaken",
    "gn:adm2_name":"Kitamotoshi",
    "gn:name":"Furuichiba",
    "iso:country":"JP",
    "wof:name":"364-0003",
    "wof:placetype":"postalcode"
},
  "geometry": {"coordinates":[139.54759999999999,36.0388],"type":"Point"}
}