{
  "type": "Feature",
  "properties": {
    "gn:adm1_name":"Aichiken",
    "gn:adm2_name":"Toyotashi",
    "gn:name":"Outakichou",
    "iso:country":"JP",
    "wof:name":"444-2206",
    "wof:placetype":"postalcode"
},
  "geometry": {"coordinates":[137.23599999999999,35.0722],"type":"Point"}
}