{
  "type": "Feature",
  "properties": {
    "gn:adm1_name":"Kyoutofu",
    "gn:adm2_name":"Kyoutoshiukyouku",
    "gn:name":"Umegahatainoshirichou",
    "iso:country":"JP",
    "wof:name":"616-8272",
    "wof:placetype":"postalcode"
},
  "geometry": {"coordinates":[135.68690000000001,35.039],"type":"Point"}
}