{
  "type": "Feature",
  "properties": {
    "gn:adm1_name":"Kyoutofu",
    "gn:adm2_name":"Kameokashi",
    "gn:name":"Yanagimachi",
    "iso:country":"JP",
    "wof:name":"621-0868",
    "wof:placetype":"postalcode"
},
  "geometry": {"coordinates":[135.5789,35.0097],"type":"Point"}
}