{
  "type": "Feature",
  "properties": {
    "gn:adm1_name":"Wakayamaken",
    "gn:adm2_name":"Kaisougunshimotsuchou",
    "gn:name":"Shiotsu",
    "iso:country":"JP",
    "wof:name":"649-0131",
    "wof:placetype":"postalcode"
},
  "geometry": {"coordinates":[135.16679999999999,34.1337],"type":"Point"}
}