{
  "type": "Feature",
  "properties": {
    "gn:adm1_name":"Niigataken",
    "gn:adm2_name":"Shibatashi",
    "gn:name":"Shimokusugawa",
    "iso:country":"JP",
    "wof:name":"957-0335",
    "wof:placetype":"postalcode"
},
  "geometry": {"coordinates":[139.39840000000001,37.9365],"type":"Point"}
}