{
  "type": "Feature",
  "properties": {
    "gn:adm1_name":"Naraken",
    "gn:adm2_name":"Ikomagunsangouchou",
    "gn:name":"Shigisanhigashi",
    "iso:country":"JP",
    "wof:name":"636-0831",
    "wof:placetype":"postalcode"
},
  "geometry": {"coordinates":[135.6765,34.607],"type":"Point"}
}