{
  "type": "Feature",
  "properties": {
    "gn:adm1_name":"Hiroshimaken",
    "gn:adm2_name":"Hiroshimashiminamiku",
    "gn:name":"Yamashirochou",
    "iso:country":"JP",
    "wof:name":"734-0035",
    "wof:placetype":"postalcode"
},
  "geometry": {"coordinates":[132.477,34.3689],"type":"Point"}
}