{
  "type": "Feature",
  "properties": {
    "gn:adm1_name":"Hiroshimaken",
    "gn:adm2_name":"Higashihiroshimashi",
    "gn:name":"Saijouchouumaki",
    "iso:country":"JP",
    "wof:name":"739-0033",
    "wof:placetype":"postalcode"
},
  "geometry": {"coordinates":[132.7285,34.366],"type":"Point"}
}