{
  "type": "Feature",
  "properties": {
    "gn:adm1_name":"Nagasakiken",
    "gn:adm2_name":"Higashisonogigunhigashisonogichou",
    "gn:name":"Oonegotogou",
    "iso:country":"JP",
    "wof:name":"859-3811",
    "wof:placetype":"postalcode"
},
  "geometry": {"coordinates":[129.89080000000001,33.0582],"type":"Point"}
}