{
  "type": "Feature",
  "properties": {
    "gn:adm1_name":"Ishikawaken",
    "gn:adm2_name":"Nanaoshi",
    "gn:name":"Tadatsumachi",
    "iso:country":"JP",
    "wof:name":"926-0844",
    "wof:placetype":"postalcode"
},
  "geometry": {"coordinates":[136.92160000000001,37.0507],"type":"Point"}
}