{
  "type": "Feature",
  "properties": {
    "gn:adm1_name":"Kyoutofu",
    "gn:adm2_name":"Kyoutoshikamigyouku",
    "gn:name":"Shinyanaginobanbakashirachou",
    "iso:country":"JP",
    "wof:name":"602-8279",
    "wof:placetype":"postalcode"
},
  "geometry": {"coordinates":[135.74449999999999,35.0236],"type":"Point"}
}