{
  "type": "Feature",
  "properties": {
    "gn:adm1_name":"Chibaken",
    "gn:adm2_name":"Isumigun'Isumimachi",
    "gn:name":"Komatai",
    "iso:country":"JP",
    "wof:name":"298-0101",
    "wof:placetype":"postalcode"
},
  "geometry": {"coordinates":[140.32069999999999,35.3315],"type":"Point"}
}