{
  "type": "Feature",
  "properties": {
    "gn:adm1_name":"Yamaguchiken",
    "gn:adm2_name":"Ubeshi",
    "gn:name":"Nakayama",
    "iso:country":"JP",
    "wof:name":"755-0058",
    "wof:placetype":"postalcode"
},
  "geometry": {"coordinates":[131.24260000000001,33.9837],"type":"Point"}
}