{
  "type": "Feature",
  "properties": {
    "gn:adm1_name":"Kyoutofu",
    "gn:adm2_name":"Yawatashi",
    "gn:name":"Minoyamamiyanose",
    "iso:country":"JP",
    "wof:name":"614-8277",
    "wof:placetype":"postalcode"
},
  "geometry": {"coordinates":[135.7116,34.8516],"type":"Point"}
}