{
  "type": "Feature",
  "properties": {
    "gn:adm1_name":"Tottoriken",
    "gn:adm2_name":"Ketakagunketakachou",
    "gn:name":"Shimomitsumoto",
    "iso:country":"JP",
    "wof:name":"689-0213",
    "wof:placetype":"postalcode"
},
  "geometry": {"coordinates":[134.08080000000001,35.4929],"type":"Point"}
}