{
  "type": "Feature",
  "properties": {
    "gn:adm1_name":"Oosakafu",
    "gn:adm2_name":"Oosakashichuuouku",
    "gn:name":"Morinomiyachuuou",
    "iso:country":"JP",
    "wof:name":"540-0003",
    "wof:placetype":"postalcode"
},
  "geometry": {"coordinates":[135.53139999999999,34.6798],"type":"Point"}
}