{
  "type": "Feature",
  "properties": {
    "gn:adm1_name":"Fukuiken",
    "gn:adm2_name":"Fukuishi",
    "gn:name":"Shimomoridafujimakichou",
    "iso:country":"JP",
    "wof:name":"910-0145",
    "wof:placetype":"postalcode"
},
  "geometry": {"coordinates":[136.227,36.1095],"type":"Point"}
}