{
  "type": "Feature",
  "properties": {
    "gn:adm1_name":"Chibaken",
    "gn:adm2_name":"Urayasushi",
    "gn:name":"Hinode",
    "iso:country":"JP",
    "wof:name":"279-0013",
    "wof:placetype":"postalcode"
},
  "geometry": {"coordinates":[139.92500000000001,35.6453],"type":"Point"}
}