{
  "type": "Feature",
  "properties": {
    "gn:adm1_name":"Oosakafu",
    "gn:adm2_name":"Oosakashihiranoku",
    "gn:name":"Hiranoichimachi",
    "iso:country":"JP",
    "wof:name":"547-0042",
    "wof:placetype":"postalcode"
},
  "geometry": {"coordinates":[135.55779999999999,34.6273],"type":"Point"}
}