{
  "type": "Feature",
  "properties": {
    "gn:adm1_name":"Yamanashiken",
    "gn:adm2_name":"Minamikomagunkajikazawachou",
    "gn:name":"Jukkoku",
    "iso:country":"JP",
    "wof:name":"400-0606",
    "wof:placetype":"postalcode"
},
  "geometry": {"coordinates":[138.39760000000001,35.5076],"type":"Point"}
}