{
  "type": "Feature",
  "properties": {
    "gn:adm1_name":"Saitamaken",
    "gn:adm2_name":"Kodamagunmisatomachi",
    "gn:name":"Anashi",
    "iso:country":"JP",
    "wof:name":"367-0103",
    "wof:placetype":"postalcode"
},
  "geometry": {"coordinates":[139.18459999999999,36.1947],"type":"Point"}
}