{
  "type": "Feature",
  "properties": {
    "gn:adm1_name":"Aichiken",
    "gn:adm2_name":"Nishikasugaigunkiyosuchou",
    "gn:name":"Joujou",
    "iso:country":"JP",
    "wof:name":"452-0944",
    "wof:placetype":"postalcode"
},
  "geometry": {"coordinates":[136.83170000000001,35.2065],"type":"Point"}
}