{
  "type": "Feature",
  "properties": {
    "gn:adm1_name":"Kumamotoken",
    "gn:adm2_name":"Asogun'Asomachi",
    "gn:name":"Nagakusa",
    "iso:country":"JP",
    "wof:name":"869-2231",
    "wof:placetype":"postalcode"
},
  "geometry": {"coordinates":[131.02379999999999,32.9306],"type":"Point"}
}