{
  "type": "Feature",
  "properties": {
    "gn:adm1_name":"Wakayamaken",
    "gn:adm2_name":"Higashimurogunhonguuchou",
    "gn:name":"Minoodani",
    "iso:country":"JP",
    "wof:name":"647-1713",
    "wof:placetype":"postalcode"
},
  "geometry": {"coordinates":[135.78039999999999,33.7785],"type":"Point"}
}