{
  "type": "Feature",
  "properties": {
    "gn:adm1_name":"Wakayamaken",
    "gn:adm2_name":"Wakayamashi",
    "gn:name":"Yoshida",
    "iso:country":"JP",
    "wof:name":"640-8343",
    "wof:placetype":"postalcode"
},
  "geometry": {"coordinates":[135.18729999999999,34.235],"type":"Point"}
}