{
  "type": "Feature",
  "properties": {
    "gn:adm1_name":"Niigataken",
    "gn:adm2_name":"Minamiuonumagunshiozawamachi",
    "gn:name":"Kimizawa",
    "iso:country":"JP",
    "wof:name":"949-6366",
    "wof:placetype":"postalcode"
},
  "geometry": {"coordinates":[138.8022,37.01],"type":"Point"}
}