{
  "type": "Feature",
  "properties": {
    "gn:adm1_name":"Kagoshimaken",
    "gn:adm2_name":"Kagoshimashi",
    "gn:name":"Usukichou",
    "iso:country":"JP",
    "wof:name":"890-0074",
    "wof:placetype":"postalcode"
},
  "geometry": {"coordinates":[130.52780000000001,31.5519],"type":"Point"}
}