{
  "type": "Feature",
  "properties": {
    "gn:adm1_name":"Oosakafu",
    "gn:adm2_name":"Sakaishi",
    "gn:name":"Kusao",
    "iso:country":"JP",
    "wof:name":"599-8127",
    "wof:placetype":"postalcode"
},
  "geometry": {"coordinates":[135.53200000000001,34.5216],"type":"Point"}
}