{
  "type": "Feature",
  "properties": {
    "gn:adm1_name":"Fukuiken",
    "gn:adm2_name":"Sakaigunmikunichou",
    "gn:name":"Rakuen",
    "iso:country":"JP",
    "wof:name":"913-0021",
    "wof:placetype":"postalcode"
},
  "geometry": {"coordinates":[136.16120000000001,36.2033],"type":"Point"}
}