{
  "type": "Feature",
  "properties": {
    "gn:adm1_name":"Ibarakiken",
    "gn:adm2_name":"Ishiokashi",
    "gn:name":"Kanoko",
    "iso:country":"JP",
    "wof:name":"315-0005",
    "wof:placetype":"postalcode"
},
  "geometry": {"coordinates":[140.2586,36.2052],"type":"Point"}
}