{
  "type": "Feature",
  "properties": {
    "gn:adm1_name":"Gifuken",
    "gn:adm2_name":"Enagun'Akechichou",
    "gn:name":"Yokodoori",
    "iso:country":"JP",
    "wof:name":"509-7724",
    "wof:placetype":"postalcode"
},
  "geometry": {"coordinates":[137.37389999999999,35.2773],"type":"Point"}
}