{
  "type": "Feature",
  "properties": {
    "gn:adm1_name":"Shigaken",
    "gn:adm2_name":"Gamougunhinochou",
    "gn:name":"Kawara",
    "iso:country":"JP",
    "wof:name":"529-1613",
    "wof:placetype":"postalcode"
},
  "geometry": {"coordinates":[136.28579999999999,35.045],"type":"Point"}
}