{
  "type": "Feature",
  "properties": {
    "gn:adm1_name":"Saitamaken",
    "gn:adm2_name":"Higashimatsuyamashi",
    "gn:name":"Ookurobe",
    "iso:country":"JP",
    "wof:name":"355-0046",
    "wof:placetype":"postalcode"
},
  "geometry": {"coordinates":[139.40360000000001,35.9968],"type":"Point"}
}