{
  "type": "Feature",
  "properties": {
    "gn:adm1_name":"Yamanashiken",
    "gn:adm2_name":"Minamitsurugundoushimura",
    "gn:name":"Takenomoto",
    "iso:country":"JP",
    "wof:name":"402-0209",
    "wof:placetype":"postalcode"
},
  "geometry": {"coordinates":[139.03319999999999,35.5278],"type":"Point"}
}