{
  "type": "Feature",
  "properties": {
    "gn:adm1_name":"Aichiken",
    "gn:adm2_name":"Inuyamashi",
    "gn:name":"Haguroinabahigashi",
    "iso:country":"JP",
    "wof:name":"484-0899",
    "wof:placetype":"postalcode"
},
  "geometry": {"coordinates":[136.94919999999999,35.359],"type":"Point"}
}