{
  "type": "Feature",
  "properties": {
    "gn:adm1_name":"Kouchiken",
    "gn:adm2_name":"Tosashi",
    "gn:name":"Takaokachoutei",
    "iso:country":"JP",
    "wof:name":"781-1104",
    "wof:placetype":"postalcode"
},
  "geometry": {"coordinates":[133.411,33.5087],"type":"Point"}
}