{
  "type": "Feature",
  "properties": {
    "gn:adm1_name":"Hyougoken",
    "gn:adm2_name":"Koubeshichuuouku",
    "gn:name":"Nishimachi",
    "iso:country":"JP",
    "wof:name":"650-0038",
    "wof:placetype":"postalcode"
},
  "geometry": {"coordinates":[135.19,34.6879],"type":"Point"}
}