{
  "type": "Feature",
  "properties": {
    "gn:adm1_name":"Shimaneken",
    "gn:adm2_name":"Matsueshi",
    "gn:name":"Kurodachou",
    "iso:country":"JP",
    "wof:name":"690-0876",
    "wof:placetype":"postalcode"
},
  "geometry": {"coordinates":[133.04320000000001,35.4794],"type":"Point"}
}