{
  "type": "Feature",
  "properties": {
    "gn:adm1_name":"Aichiken",
    "gn:adm2_name":"Handashi",
    "gn:name":"Kasugachou",
    "iso:country":"JP",
    "wof:name":"475-0923",
    "wof:placetype":"postalcode"
},
  "geometry": {"coordinates":[136.91739999999999,34.8846],"type":"Point"}
}