{
  "type": "Feature",
  "properties": {
    "gn:adm1_name":"Ishikawaken",
    "gn:adm2_name":"Wajimashi",
    "gn:name":"Kawaimachi",
    "iso:country":"JP",
    "wof:name":"928-0001",
    "wof:placetype":"postalcode"
},
  "geometry": {"coordinates":[136.90440000000001,37.3936],"type":"Point"}
}