{
  "type": "Feature",
  "properties": {
    "gn:adm1_name":"Shigaken",
    "gn:adm2_name":"Kusatsushi",
    "gn:name":"Kawara",
    "iso:country":"JP",
    "wof:name":"525-0021",
    "wof:placetype":"postalcode"
},
  "geometry": {"coordinates":[135.95529999999999,35.034],"type":"Point"}
}