{
  "type": "Feature",
  "properties": {
    "gn:adm1_name":"Mieken",
    "gn:adm2_name":"Kumanoshi",
    "gn:name":"Hadasuchou",
    "iso:country":"JP",
    "wof:name":"519-4207",
    "wof:placetype":"postalcode"
},
  "geometry": {"coordinates":[136.1387,33.9132],"type":"Point"}
}