{
  "type": "Feature",
  "properties": {
    "gn:adm1_name":"Gifuken",
    "gn:adm2_name":"Yoshikigunkamitakaramura",
    "gn:name":"Hirayu",
    "iso:country":"JP",
    "wof:name":"506-1433",
    "wof:placetype":"postalcode"
},
  "geometry": {"coordinates":[137.55269999999999,36.1915],"type":"Point"}
}