{
  "type": "Feature",
  "properties": {
    "gn:adm1_name":"Ibarakiken",
    "gn:adm2_name":"Nakagunnakamachi",
    "gn:name":"Tsuda",
    "iso:country":"JP",
    "wof:name":"311-0112",
    "wof:placetype":"postalcode"
},
  "geometry": {"coordinates":[140.4896,36.4132],"type":"Point"}
}