{
  "type": "Feature",
  "properties": {
    "gn:adm1_name":"Miyagiken",
    "gn:adm2_name":"Sendaishiwakabayashiku",
    "gn:name":"Aramachi",
    "iso:country":"JP",
    "wof:name":"984-0073",
    "wof:placetype":"postalcode"
},
  "geometry": {"coordinates":[140.88399999999999,38.249],"type":"Point"}
}