{
  "type": "Feature",
  "properties": {
    "gn:adm1_name":"Shizuokaken",
    "gn:adm2_name":"Shizuokashi",
    "gn:name":"Nibanchou",
    "iso:country":"JP",
    "wof:name":"420-0072",
    "wof:placetype":"postalcode"
},
  "geometry": {"coordinates":[138.37209999999999,34.9754],"type":"Point"}
}