{
  "type": "Feature",
  "properties": {
    "gn:adm1_name":"Niigataken",
    "gn:adm2_name":"Itoigawashi",
    "gn:name":"Shinkouji",
    "iso:country":"JP",
    "wof:name":"941-0041",
    "wof:placetype":"postalcode"
},
  "geometry": {"coordinates":[137.89949999999999,37.0235],"type":"Point"}
}