{
  "type": "Feature",
  "properties": {
    "gn:adm1_name":"Miyazakiken",
    "gn:adm2_name":"Miyazakishi",
    "gn:name":"Joudoechou",
    "iso:country":"JP",
    "wof:name":"880-0876",
    "wof:placetype":"postalcode"
},
  "geometry": {"coordinates":[131.434,31.9134],"type":"Point"}
}