{
  "type": "Feature",
  "properties": {
    "gn:adm1_name":"Kyoutofu",
    "gn:adm2_name":"Kyoutoshikamigyouku",
    "gn:name":"Koudouuchichou",
    "iso:country":"JP",
    "wof:name":"602-0835",
    "wof:placetype":"postalcode"
},
  "geometry": {"coordinates":[135.76660000000001,35.0293],"type":"Point"}
}