{
  "type": "Feature",
  "properties": {
    "gn:adm1_name":"Mieken",
    "gn:adm2_name":"Yokkaichishi",
    "gn:name":"Sakuradai",
    "iso:country":"JP",
    "wof:name":"512-1214",
    "wof:placetype":"postalcode"
},
  "geometry": {"coordinates":[136.5343,34.9859],"type":"Point"}
}