{
  "type": "Feature",
  "properties": {
    "gn:adm1_name":"Hiroshimaken",
    "gn:adm2_name":"Onomichishi",
    "gn:name":"Shoutokuchou",
    "iso:country":"JP",
    "wof:name":"722-0004",
    "wof:placetype":"postalcode"
},
  "geometry": {"coordinates":[133.1661,34.3968],"type":"Point"}
}