{
  "type": "Feature",
  "properties": {
    "gn:adm1_name":"Aichiken",
    "gn:adm2_name":"Ichinomiyashi",
    "gn:name":"Yamatochoumyoukouji",
    "iso:country":"JP",
    "wof:name":"491-0922",
    "wof:placetype":"postalcode"
},
  "geometry": {"coordinates":[136.80269999999999,35.2824],"type":"Point"}
}