{
  "type": "Feature",
  "properties": {
    "gn:adm1_name":"Aichiken",
    "gn:adm2_name":"Toyohashishi",
    "gn:name":"Tamenakamachi",
    "iso:country":"JP",
    "wof:name":"440-0027",
    "wof:placetype":"postalcode"
},
  "geometry": {"coordinates":[137.44640000000001,34.7595],"type":"Point"}
}