{
  "type": "Feature",
  "properties": {
    "gn:adm1_name":"Gifuken",
    "gn:adm2_name":"Hashimagunginanchou",
    "gn:name":"Ishiharase",
    "iso:country":"JP",
    "wof:name":"501-6015",
    "wof:placetype":"postalcode"
},
  "geometry": {"coordinates":[136.7654,35.3781],"type":"Point"}
}