{
  "type": "Feature",
  "properties": {
    "gn:adm1_name":"Yamaguchiken",
    "gn:adm2_name":"Mineshi",
    "gn:name":"Higashiatsuchouyamanaka",
    "iso:country":"JP",
    "wof:name":"759-2141",
    "wof:placetype":"postalcode"
},
  "geometry": {"coordinates":[131.1893,34.1281],"type":"Point"}
}