{
  "type": "Feature",
  "properties": {
    "gn:adm1_name":"Kouchiken",
    "gn:adm2_name":"Tosagun'Ookawamura",
    "gn:name":"Oohira",
    "iso:country":"JP",
    "wof:name":"781-3714",
    "wof:placetype":"postalcode"
},
  "geometry": {"coordinates":[133.37780000000001,33.804],"type":"Point"}
}