{
  "type": "Feature",
  "properties": {
    "gn:adm1_name":"Okayamaken",
    "gn:adm2_name":"Tsuyamashi",
    "gn:name":"Chikanaga",
    "iso:country":"JP",
    "wof:name":"708-1112",
    "wof:placetype":"postalcode"
},
  "geometry": {"coordinates":[134.0778,35.0818],"type":"Point"}
}