{
  "type": "Feature",
  "properties": {
    "gn:adm1_name":"Chibaken",
    "gn:adm2_name":"Inzaishi",
    "gn:name":"Ikanikeisaiganaibaai",
    "iso:country":"JP",
    "wof:name":"270-1300",
    "wof:placetype":"postalcode"
},
  "geometry": {"coordinates":[140.09950000000001,35.8097],"type":"Point"}
}