{
  "type": "Feature",
  "properties": {
    "gn:adm1_name":"Gifuken",
    "gn:adm2_name":"Fuwagunsekigaharachou",
    "gn:name":"Imasu",
    "iso:country":"JP",
    "wof:name":"503-1543",
    "wof:placetype":"postalcode"
},
  "geometry": {"coordinates":[136.4308,35.3413],"type":"Point"}
}