{
  "type": "Feature",
  "properties": {
    "gn:adm1_name":"Gifuken",
    "gn:adm2_name":"Gifushi",
    "gn:name":"Sagiyamakiyosuchou",
    "iso:country":"JP",
    "wof:name":"502-0853",
    "wof:placetype":"postalcode"
},
  "geometry": {"coordinates":[136.75960000000001,35.4447],"type":"Point"}
}