{
  "type": "Feature",
  "properties": {
    "gn:adm1_name":"Fukuokaken",
    "gn:adm2_name":"Oomutashi",
    "gn:name":"Shouwabiraki",
    "iso:country":"JP",
    "wof:name":"836-0001",
    "wof:placetype":"postalcode"
},
  "geometry": {"coordinates":[130.4315,33.0638],"type":"Point"}
}