{
  "type": "Feature",
  "properties": {
    "gn:adm1_name":"Aichiken",
    "gn:adm2_name":"Owariasahishi",
    "gn:name":"Nishidaidouchougorinduka",
    "iso:country":"JP",
    "wof:name":"488-0813",
    "wof:placetype":"postalcode"
},
  "geometry": {"coordinates":[137.03210000000001,35.2138],"type":"Point"}
}