{
  "type": "Feature",
  "properties": {
    "gn:adm1_name":"Ishikawaken",
    "gn:adm2_name":"Hakuiguntogimachi",
    "gn:name":"Jiho",
    "iso:country":"JP",
    "wof:name":"925-0422",
    "wof:placetype":"postalcode"
},
  "geometry": {"coordinates":[136.80250000000001,37.2124],"type":"Point"}
}