{
  "type": "Feature",
  "properties": {
    "gn:adm1_name":"Fukuiken",
    "gn:adm2_name":"Nyuugunmiyazakimura",
    "gn:name":"Kashidu",
    "iso:country":"JP",
    "wof:name":"916-0272",
    "wof:placetype":"postalcode"
},
  "geometry": {"coordinates":[136.089,35.9386],"type":"Point"}
}