{
  "type": "Feature",
  "properties": {
    "gn:adm1_name":"Fukuokaken",
    "gn:adm2_name":"Kitakyuushuushitobataku",
    "gn:name":"Sanrokumachi",
    "iso:country":"JP",
    "wof:name":"804-0091",
    "wof:placetype":"postalcode"
},
  "geometry": {"coordinates":[130.83500000000001,33.8992],"type":"Point"}
}