{
  "type": "Feature",
  "properties": {
    "gn:adm1_name":"Tochigiken",
    "gn:adm2_name":"Utsunomiyashi",
    "gn:name":"Esojimamachi",
    "iso:country":"JP",
    "wof:name":"321-0102",
    "wof:placetype":"postalcode"
},
  "geometry": {"coordinates":[139.8767,36.5293],"type":"Point"}
}