{
  "type": "Feature",
  "properties": {
    "gn:adm1_name":"Ibarakiken",
    "gn:adm2_name":"Higashiibarakigun'Uchiharamachi",
    "gn:name":"Koibuchi",
    "iso:country":"JP",
    "wof:name":"319-0323",
    "wof:placetype":"postalcode"
},
  "geometry": {"coordinates":[140.3708,36.3424],"type":"Point"}
}