{
  "type": "Feature",
  "properties": {
    "gn:adm1_name":"Saitamaken",
    "gn:adm2_name":"Koshigayashi",
    "gn:name":"Hirakataminamichou",
    "iso:country":"JP",
    "wof:name":"343-0001",
    "wof:placetype":"postalcode"
},
  "geometry": {"coordinates":[139.78219999999999,35.9428],"type":"Point"}
}