{
  "type": "Feature",
  "properties": {
    "gn:adm1_name":"Okinawaken",
    "gn:adm2_name":"Shimajirigunsashikichou",
    "gn:name":"Sashiki",
    "iso:country":"JP",
    "wof:name":"901-1403",
    "wof:placetype":"postalcode"
},
  "geometry": {"coordinates":[127.78959999999999,26.1671],"type":"Point"}
}