{
  "type": "Feature",
  "properties": {
    "gn:adm1_name":"Wakayamaken",
    "gn:adm2_name":"Kainanshi",
    "gn:name":"Torii",
    "iso:country":"JP",
    "wof:name":"642-0033",
    "wof:placetype":"postalcode"
},
  "geometry": {"coordinates":[135.21629999999999,34.1494],"type":"Point"}
}