{
  "type": "Feature",
  "properties": {
    "gn:adm1_name":"Okinawaken",
    "gn:adm2_name":"Okinawashi",
    "gn:name":"Miyazato",
    "iso:country":"JP",
    "wof:name":"904-2165",
    "wof:placetype":"postalcode"
},
  "geometry": {"coordinates":[127.8198,26.3377],"type":"Point"}
}