{
  "type": "Feature",
  "properties": {
    "gn:adm1_name":"Gifuken",
    "gn:adm2_name":"Sekishi",
    "gn:name":"Oosugi",
    "iso:country":"JP",
    "wof:name":"501-3922",
    "wof:placetype":"postalcode"
},
  "geometry": {"coordinates":[136.95230000000001,35.4538],"type":"Point"}
}