{
  "type": "Feature",
  "properties": {
    "gn:adm1_name":"Naraken",
    "gn:adm2_name":"Kashibashi",
    "gn:name":"Gokasho",
    "iso:country":"JP",
    "wof:name":"639-0221",
    "wof:placetype":"postalcode"
},
  "geometry": {"coordinates":[135.71700000000001,34.5493],"type":"Point"}
}