{
  "type": "Feature",
  "properties": {
    "gn:adm1_name":"Ooitaken",
    "gn:adm2_name":"Kitsukishi",
    "gn:name":"Naka",
    "iso:country":"JP",
    "wof:name":"873-0012",
    "wof:placetype":"postalcode"
},
  "geometry": {"coordinates":[131.58930000000001,33.4083],"type":"Point"}
}