{
  "type": "Feature",
  "properties": {
    "gn:adm1_name":"Ibarakiken",
    "gn:adm2_name":"Inashikigunmihomura",
    "gn:name":"Oosukadu",
    "iso:country":"JP",
    "wof:name":"300-0422",
    "wof:placetype":"postalcode"
},
  "geometry": {"coordinates":[140.31280000000001,36.0221],"type":"Point"}
}