{
  "type": "Feature",
  "properties": {
    "gn:adm1_name":"Hiroshimaken",
    "gn:adm2_name":"Kureshi",
    "gn:name":"Saiwaichou",
    "iso:country":"JP",
    "wof:name":"737-0028",
    "wof:placetype":"postalcode"
},
  "geometry": {"coordinates":[132.56229999999999,34.2394],"type":"Point"}
}