{
  "type": "Feature",
  "properties": {
    "gn:adm1_name":"Fukushimaken",
    "gn:adm2_name":"Yamagunyamatomachi",
    "gn:name":"Shimizujiri",
    "iso:country":"JP",
    "wof:name":"969-4117",
    "wof:placetype":"postalcode"
},
  "geometry": {"coordinates":[139.89060000000001,37.6371],"type":"Point"}
}