{
  "type": "Feature",
  "properties": {
    "gn:adm1_name":"Kyoutofu",
    "gn:adm2_name":"Kameokashi",
    "gn:name":"Kitakawaramachi",
    "iso:country":"JP",
    "wof:name":"621-0802",
    "wof:placetype":"postalcode"
},
  "geometry": {"coordinates":[135.56870000000001,35.0206],"type":"Point"}
}