{
  "type": "Feature",
  "properties": {
    "gn:adm1_name":"Chibaken",
    "gn:adm2_name":"Chouseigunchouseimura",
    "gn:name":"Sone",
    "iso:country":"JP",
    "wof:name":"299-4344",
    "wof:placetype":"postalcode"
},
  "geometry": {"coordinates":[140.345,35.4232],"type":"Point"}
}