{
  "type": "Feature",
  "properties": {
    "gn:adm1_name":"Saitamaken",
    "gn:adm2_name":"Hikigunkawajimamachi",
    "gn:name":"Hiranuma",
    "iso:country":"JP",
    "wof:name":"350-0131",
    "wof:placetype":"postalcode"
},
  "geometry": {"coordinates":[139.4744,35.9828],"type":"Point"}
}