{
  "type": "Feature",
  "properties": {
    "gn:adm1_name":"Fukushimaken",
    "gn:adm2_name":"Aiduwakamatsushi",
    "gn:name":"Ootomachioyahirasawa",
    "iso:country":"JP",
    "wof:name":"969-5145",
    "wof:placetype":"postalcode"
},
  "geometry": {"coordinates":[139.91999999999999,37.3759],"type":"Point"}
}