{
  "type": "Feature",
  "properties": {
    "gn:adm1_name":"Ibarakiken",
    "gn:adm2_name":"Hitachishi",
    "gn:name":"Oowadachou",
    "iso:country":"JP",
    "wof:name":"319-1234",
    "wof:placetype":"postalcode"
},
  "geometry": {"coordinates":[140.58349999999999,36.5093],"type":"Point"}
}