{
  "type": "Feature",
  "properties": {
    "gn:adm1_name":"Naganoken",
    "gn:adm2_name":"Kamiminochigunmuremura",
    "gn:name":"Hiraide",
    "iso:country":"JP",
    "wof:name":"389-1213",
    "wof:placetype":"postalcode"
},
  "geometry": {"coordinates":[138.24700000000001,36.7306],"type":"Point"}
}