{
  "type": "Feature",
  "properties": {
    "gn:adm1_name":"Toyamaken",
    "gn:adm2_name":"Takaokashi",
    "gn:name":"Rengeji",
    "iso:country":"JP",
    "wof:name":"933-0802",
    "wof:placetype":"postalcode"
},
  "geometry": {"coordinates":[137.03659999999999,36.7376],"type":"Point"}
}