{
  "type": "Feature",
  "properties": {
    "gn:adm1_name":"Tochigiken",
    "gn:adm2_name":"Nasugunkurobanemachi",
    "gn:name":"Kitanogami",
    "iso:country":"JP",
    "wof:name":"324-0231",
    "wof:placetype":"postalcode"
},
  "geometry": {"coordinates":[140.16800000000001,36.8701],"type":"Point"}
}