{
  "type": "Feature",
  "properties": {
    "gn:adm1_name":"Saitamaken",
    "gn:adm2_name":"Honjoushi",
    "gn:name":"Kotobuki",
    "iso:country":"JP",
    "wof:name":"367-0023",
    "wof:placetype":"postalcode"
},
  "geometry": {"coordinates":[139.20509999999999,36.2316],"type":"Point"}
}