{
  "type": "Feature",
  "properties": {
    "gn:adm1_name":"Fukushimaken",
    "gn:adm2_name":"Soumagun'Iitatemura",
    "gn:name":"Maeta",
    "iso:country":"JP",
    "wof:name":"960-1636",
    "wof:placetype":"postalcode"
},
  "geometry": {"coordinates":[140.6927,37.7221],"type":"Point"}
}