{
  "type": "Feature",
  "properties": {
    "gn:adm1_name":"Ehimeken",
    "gn:adm2_name":"Niihamashi",
    "gn:name":"Toyamachou",
    "iso:country":"JP",
    "wof:name":"792-0823",
    "wof:placetype":"postalcode"
},
  "geometry": {"coordinates":[133.31039999999999,33.9397],"type":"Point"}
}