{
  "type": "Feature",
  "properties": {
    "gn:adm1_name":"Fukuiken",
    "gn:adm2_name":"Sakaigunmikunichou",
    "gn:name":"Tonoshima",
    "iso:country":"JP",
    "wof:name":"913-0026",
    "wof:placetype":"postalcode"
},
  "geometry": {"coordinates":[136.15260000000001,36.2062],"type":"Point"}
}