{
  "type": "Feature",
  "properties": {
    "gn:adm1_name":"Chibaken",
    "gn:adm2_name":"Katorigunkouzakimachi",
    "gn:name":"Kouzakihonshuku",
    "iso:country":"JP",
    "wof:name":"289-0221",
    "wof:placetype":"postalcode"
},
  "geometry": {"coordinates":[140.4042,35.9031],"type":"Point"}
}