{
  "type": "Feature",
  "properties": {
    "gn:adm1_name":"Miyagiken",
    "gn:adm2_name":"Tomeguntoyosatochou",
    "gn:name":"Shinmachi",
    "iso:country":"JP",
    "wof:name":"987-0365",
    "wof:placetype":"postalcode"
},
  "geometry": {"coordinates":[141.25299999999999,38.5844],"type":"Point"}
}