{
  "type": "Feature",
  "properties": {
    "gn:adm1_name":"Gifuken",
    "gn:adm2_name":"Gifushi",
    "gn:name":"Sumiyoshichou",
    "iso:country":"JP",
    "wof:name":"500-8826",
    "wof:placetype":"postalcode"
},
  "geometry": {"coordinates":[136.75980000000001,35.4209],"type":"Point"}
}