{
  "type": "Feature",
  "properties": {
    "gn:adm1_name":"Nagasakiken",
    "gn:adm2_name":"Kitamatsuuragunyoshiichou",
    "gn:name":"Haruakemen",
    "iso:country":"JP",
    "wof:name":"859-6323",
    "wof:placetype":"postalcode"
},
  "geometry": {"coordinates":[129.7079,33.2694],"type":"Point"}
}