{
  "type": "Feature",
  "properties": {
    "gn:adm1_name":"Niigataken",
    "gn:adm2_name":"Itoigawashi",
    "gn:name":"Nishitsuka",
    "iso:country":"JP",
    "wof:name":"949-1213",
    "wof:placetype":"postalcode"
},
  "geometry": {"coordinates":[137.96180000000001,37.0234],"type":"Point"}
}