{
  "type": "Feature",
  "properties": {
    "gn:adm1_name":"Kyoutofu",
    "gn:adm2_name":"Kyoutoshiukyouku",
    "gn:name":"Tokiwaumadukachou",
    "iso:country":"JP",
    "wof:name":"616-8225",
    "wof:placetype":"postalcode"
},
  "geometry": {"coordinates":[135.70509999999999,35.0207],"type":"Point"}
}