{
  "type": "Feature",
  "properties": {
    "gn:adm1_name":"Toyamaken",
    "gn:adm2_name":"Takaokashi",
    "gn:name":"Kidu",
    "iso:country":"JP",
    "wof:name":"933-0857",
    "wof:placetype":"postalcode"
},
  "geometry": {"coordinates":[136.9973,36.7358],"type":"Point"}
}