{
  "type": "Feature",
  "properties": {
    "gn:adm1_name":"Oosakafu",
    "gn:adm2_name":"Sennangunkumatorichou",
    "gn:name":"Juugaoka",
    "iso:country":"JP",
    "wof:name":"590-0423",
    "wof:placetype":"postalcode"
},
  "geometry": {"coordinates":[135.35939999999999,34.4065],"type":"Point"}
}