{
  "type": "Feature",
  "properties": {
    "gn:adm1_name":"Gifuken",
    "gn:adm2_name":"Oogakishi",
    "gn:name":"Takasagochou",
    "iso:country":"JP",
    "wof:name":"503-0889",
    "wof:placetype":"postalcode"
},
  "geometry": {"coordinates":[136.61590000000001,35.3633],"type":"Point"}
}