{
  "type": "Feature",
  "properties": {
    "gn:adm1_name":"Kouchiken",
    "gn:adm2_name":"Kouchishi",
    "gn:name":"Seto",
    "iso:country":"JP",
    "wof:name":"781-0250",
    "wof:placetype":"postalcode"
},
  "geometry": {"coordinates":[133.5455,33.5077],"type":"Point"}
}