{
  "type": "Feature",
  "properties": {
    "gn:adm1_name":"Fukuiken",
    "gn:adm2_name":"Katsuyamashi",
    "gn:name":"Aradochoukitamiyaji",
    "iso:country":"JP",
    "wof:name":"911-0047",
    "wof:placetype":"postalcode"
},
  "geometry": {"coordinates":[136.46629999999999,36.084],"type":"Point"}
}