{
  "type": "Feature",
  "properties": {
    "gn:adm1_name":"Tokushimaken",
    "gn:adm2_name":"Tokushimashi",
    "gn:name":"Shoumachi",
    "iso:country":"JP",
    "wof:name":"770-0044",
    "wof:placetype":"postalcode"
},
  "geometry": {"coordinates":[134.50980000000001,34.0754],"type":"Point"}
}