{
  "type": "Feature",
  "properties": {
    "gn:adm1_name":"Shizuokaken",
    "gn:adm2_name":"Shizuokashi",
    "gn:name":"Tsushimachou",
    "iso:country":"JP",
    "wof:name":"422-8056",
    "wof:placetype":"postalcode"
},
  "geometry": {"coordinates":[138.38249999999999,34.96],"type":"Point"}
}