{
  "type": "Feature",
  "properties": {
    "gn:adm1_name":"Hyougoken",
    "gn:adm2_name":"Himejishi",
    "gn:name":"Shikamakufujimigaokachou",
    "iso:country":"JP",
    "wof:name":"672-8098",
    "wof:placetype":"postalcode"
},
  "geometry": {"coordinates":[134.6429,34.8163],"type":"Point"}
}