{
  "type": "Feature",
  "properties": {
    "gn:adm1_name":"Sagaken",
    "gn:adm2_name":"Higashimatsuuragungenkaichou",
    "gn:name":"Hokawadu",
    "iso:country":"JP",
    "wof:name":"847-1446",
    "wof:placetype":"postalcode"
},
  "geometry": {"coordinates":[129.84700000000001,33.5093],"type":"Point"}
}