{
  "type": "Feature",
  "properties": {
    "gn:adm1_name":"Miyagiken",
    "gn:adm2_name":"Miyagigunshichigahamamachi",
    "gn:name":"Shiomidaiminami",
    "iso:country":"JP",
    "wof:name":"985-0822",
    "wof:placetype":"postalcode"
},
  "geometry": {"coordinates":[141.05850000000001,38.2936],"type":"Point"}
}