{
  "type": "Feature",
  "properties": {
    "gn:adm1_name":"Ishikawaken",
    "gn:adm2_name":"Fugeshigunmonzenmachi",
    "gn:name":"Kaifuki",
    "iso:country":"JP",
    "wof:name":"927-2121",
    "wof:placetype":"postalcode"
},
  "geometry": {"coordinates":[136.86060000000001,37.2868],"type":"Point"}
}