{
  "type": "Feature",
  "properties": {
    "gn:adm1_name":"Hyougoken",
    "gn:adm2_name":"Kakogawashi",
    "gn:name":"Kakogawachoumizonokuchi",
    "iso:country":"JP",
    "wof:name":"675-0064",
    "wof:placetype":"postalcode"
},
  "geometry": {"coordinates":[134.8432,34.7657],"type":"Point"}
}