{
  "type": "Feature",
  "properties": {
    "gn:adm1_name":"Nagasakiken",
    "gn:adm2_name":"Minamitakakigunchidiwachou",
    "gn:name":"Ki",
    "iso:country":"JP",
    "wof:name":"854-0406",
    "wof:placetype":"postalcode"
},
  "geometry": {"coordinates":[130.2166,32.7858],"type":"Point"}
}