{
  "type": "Feature",
  "properties": {
    "gn:adm1_name":"Miyagiken",
    "gn:adm2_name":"Sendaishiaobaku",
    "gn:name":"Aramakichuuou",
    "iso:country":"JP",
    "wof:name":"981-0964",
    "wof:placetype":"postalcode"
},
  "geometry": {"coordinates":[140.85849999999999,38.2909],"type":"Point"}
}