{
  "type": "Feature",
  "properties": {
    "gn:adm1_name":"Tottoriken",
    "gn:adm2_name":"Tottorishi",
    "gn:name":"Kotobukichou",
    "iso:country":"JP",
    "wof:name":"680-0813",
    "wof:placetype":"postalcode"
},
  "geometry": {"coordinates":[134.22540000000001,35.5048],"type":"Point"}
}