{
  "type": "Feature",
  "properties": {
    "gn:adm1_name":"Kyoutofu",
    "gn:adm2_name":"Kyoutoshifushimiku",
    "gn:name":"Nousochou",
    "iso:country":"JP",
    "wof:name":"612-8275",
    "wof:placetype":"postalcode"
},
  "geometry": {"coordinates":[135.71940000000001,34.9093],"type":"Point"}
}