{
  "type": "Feature",
  "properties": {
    "gn:adm1_name":"Sagaken",
    "gn:adm2_name":"Imarishi",
    "gn:name":"Kurogawachouookurogawa",
    "iso:country":"JP",
    "wof:name":"848-0123",
    "wof:placetype":"postalcode"
},
  "geometry": {"coordinates":[129.8612,33.3342],"type":"Point"}
}