{
  "type": "Feature",
  "properties": {
    "gn:adm1_name":"Naganoken",
    "gn:adm2_name":"Higashichikumagun'Akashinamachi",
    "gn:name":"Higashikawate",
    "iso:country":"JP",
    "wof:name":"399-7101",
    "wof:placetype":"postalcode"
},
  "geometry": {"coordinates":[137.95529999999999,36.3781],"type":"Point"}
}