{
  "type": "Feature",
  "properties": {
    "gn:adm1_name":"Kagawaken",
    "gn:adm2_name":"Ayautagunhanzanchou",
    "gn:name":"Santoki",
    "iso:country":"JP",
    "wof:name":"762-0086",
    "wof:placetype":"postalcode"
},
  "geometry": {"coordinates":[133.8477,34.2588],"type":"Point"}
}