{
  "type": "Feature",
  "properties": {
    "gn:adm1_name":"Aichiken",
    "gn:adm2_name":"Tokonameshi",
    "gn:name":"Furumichi",
    "iso:country":"JP",
    "wof:name":"479-0006",
    "wof:placetype":"postalcode"
},
  "geometry": {"coordinates":[136.85939999999999,34.8891],"type":"Point"}
}