{
  "type": "Feature",
  "properties": {
    "gn:adm1_name":"Kyoutofu",
    "gn:adm2_name":"Kyoutoshihigashiyamaku",
    "gn:name":"Miyoshichou",
    "iso:country":"JP",
    "wof:name":"605-0081",
    "wof:placetype":"postalcode"
},
  "geometry": {"coordinates":[135.77549999999999,35.007],"type":"Point"}
}