{
  "type": "Feature",
  "properties": {
    "gn:adm1_name":"Aichiken",
    "gn:adm2_name":"Okazakishi",
    "gn:name":"Takichou",
    "iso:country":"JP",
    "wof:name":"444-3173",
    "wof:placetype":"postalcode"
},
  "geometry": {"coordinates":[137.1985,34.9811],"type":"Point"}
}