{
  "type": "Feature",
  "properties": {
    "gn:adm1_name":"Kagoshimaken",
    "gn:adm2_name":"Tarumizushi",
    "gn:name":"Honjou",
    "iso:country":"JP",
    "wof:name":"891-2112",
    "wof:placetype":"postalcode"
},
  "geometry": {"coordinates":[130.71420000000001,31.4822],"type":"Point"}
}