{
  "type": "Feature",
  "properties": {
    "gn:adm1_name":"Fukushimaken",
    "gn:adm2_name":"Tamuragun'Onomachi",
    "gn:name":"Yoshinobe",
    "iso:country":"JP",
    "wof:name":"963-3525",
    "wof:placetype":"postalcode"
},
  "geometry": {"coordinates":[140.60159999999999,37.3317],"type":"Point"}
}