{
  "type": "Feature",
  "properties": {
    "gn:adm1_name":"Kouchiken",
    "gn:adm2_name":"Tosashi",
    "gn:name":"Takaokachouhei",
    "iso:country":"JP",
    "wof:name":"781-1103",
    "wof:placetype":"postalcode"
},
  "geometry": {"coordinates":[133.43109999999999,33.5026],"type":"Point"}
}