{
  "type": "Feature",
  "properties": {
    "gn:adm1_name":"Miyazakiken",
    "gn:adm2_name":"Kushimashi",
    "gn:name":"Oono",
    "iso:country":"JP",
    "wof:name":"888-0221",
    "wof:placetype":"postalcode"
},
  "geometry": {"coordinates":[131.33539999999999,31.4011],"type":"Point"}
}