{
  "type": "Feature",
  "properties": {
    "gn:adm1_name":"Saitamaken",
    "gn:adm2_name":"Chichibugunminanomachi",
    "gn:name":"Oofuchi",
    "iso:country":"JP",
    "wof:name":"369-1623",
    "wof:placetype":"postalcode"
},
  "geometry": {"coordinates":[139.09790000000001,36.0734],"type":"Point"}
}