{
  "type": "Feature",
  "properties": {
    "gn:adm1_name":"Naraken",
    "gn:adm2_name":"Goseshi",
    "gn:name":"Deyashiki",
    "iso:country":"JP",
    "wof:name":"639-2202",
    "wof:placetype":"postalcode"
},
  "geometry": {"coordinates":[135.7518,34.4721],"type":"Point"}
}