{
  "type": "Feature",
  "properties": {
    "gn:adm1_name":"Yamagataken",
    "gn:adm2_name":"Higashiokitamaguntakahatamachi",
    "gn:name":"Shionomori",
    "iso:country":"JP",
    "wof:name":"992-0314",
    "wof:placetype":"postalcode"
},
  "geometry": {"coordinates":[140.18600000000001,37.9915],"type":"Point"}
}