{
  "type": "Feature",
  "properties": {
    "gn:adm1_name":"Tottoriken",
    "gn:adm2_name":"Hinogunhinochou",
    "gn:name":"Neu",
    "iso:country":"JP",
    "wof:name":"689-4503",
    "wof:placetype":"postalcode"
},
  "geometry": {"coordinates":[133.44200000000001,35.2395],"type":"Point"}
}