{
  "type": "Feature",
  "properties": {
    "gn:adm1_name":"Okayamaken",
    "gn:adm2_name":"Kumegunkumenanchou",
    "gn:name":"Shimomomi",
    "iso:country":"JP",
    "wof:name":"709-3624",
    "wof:placetype":"postalcode"
},
  "geometry": {"coordinates":[133.90620000000001,34.9109],"type":"Point"}
}