{
  "type": "Feature",
  "properties": {
    "gn:adm1_name":"Hyougoken",
    "gn:adm2_name":"Takaradukashi",
    "gn:name":"Takatsukasa",
    "iso:country":"JP",
    "wof:name":"665-0051",
    "wof:placetype":"postalcode"
},
  "geometry": {"coordinates":[135.36330000000001,34.7857],"type":"Point"}
}