{
  "type": "Feature",
  "properties": {
    "gn:adm1_name":"Shigaken",
    "gn:adm2_name":"Moriyamashi",
    "gn:name":"Yokoechou",
    "iso:country":"JP",
    "wof:name":"524-0053",
    "wof:placetype":"postalcode"
},
  "geometry": {"coordinates":[135.9693,35.0548],"type":"Point"}
}