{
  "type": "Feature",
  "properties": {
    "gn:adm1_name":"Oosakafu",
    "gn:adm2_name":"Matsubarashi",
    "gn:name":"Shindou",
    "iso:country":"JP",
    "wof:name":"580-0015",
    "wof:placetype":"postalcode"
},
  "geometry": {"coordinates":[135.55439999999999,34.569],"type":"Point"}
}