{
  "type": "Feature",
  "properties": {
    "gn:adm1_name":"Kanagawaken",
    "gn:adm2_name":"Chigasakishi",
    "gn:name":"Heiwachou",
    "iso:country":"JP",
    "wof:name":"253-0024",
    "wof:placetype":"postalcode"
},
  "geometry": {"coordinates":[139.4289,35.3268],"type":"Point"}
}