{
  "type": "Feature",
  "properties": {
    "gn:adm1_name":"Saitamaken",
    "gn:adm2_name":"Kitamotoshi",
    "gn:name":"Chuuou",
    "iso:country":"JP",
    "wof:name":"364-0031",
    "wof:placetype":"postalcode"
},
  "geometry": {"coordinates":[139.53229999999999,36.0312],"type":"Point"}
}