{
  "type": "Feature",
  "properties": {
    "gn:adm1_name":"Hiroshimaken",
    "gn:adm2_name":"Hatsukaichishi",
    "gn:name":"Sagatahonmachi",
    "iso:country":"JP",
    "wof:name":"738-0003",
    "wof:placetype":"postalcode"
},
  "geometry": {"coordinates":[132.34360000000001,34.36],"type":"Point"}
}