{
  "type": "Feature",
  "properties": {
    "gn:adm1_name":"Yamagataken",
    "gn:adm2_name":"Higashitagawaguntachikawamachi",
    "gn:name":"Shinazawa",
    "iso:country":"JP",
    "wof:name":"999-6608",
    "wof:placetype":"postalcode"
},
  "geometry": {"coordinates":[140.00239999999999,38.6866],"type":"Point"}
}