{
  "type": "Feature",
  "properties": {
    "gn:adm1_name":"Aichiken",
    "gn:adm2_name":"Tokonameshi",
    "gn:name":"Haramatsuchou",
    "iso:country":"JP",
    "wof:name":"479-0832",
    "wof:placetype":"postalcode"
},
  "geometry": {"coordinates":[136.83949999999999,34.8937],"type":"Point"}
}