{
  "type": "Feature",
  "properties": {
    "gn:adm1_name":"Shizuokaken",
    "gn:adm2_name":"Susonoshi",
    "gn:name":"Kune",
    "iso:country":"JP",
    "wof:name":"410-1111",
    "wof:placetype":"postalcode"
},
  "geometry": {"coordinates":[138.91900000000001,35.1868],"type":"Point"}
}