{
  "type": "Feature",
  "properties": {
    "gn:adm1_name":"Fukushimaken",
    "gn:adm2_name":"Nihonmatsushi",
    "gn:name":"Choujamiya",
    "iso:country":"JP",
    "wof:name":"964-0852",
    "wof:placetype":"postalcode"
},
  "geometry": {"coordinates":[140.42339999999999,37.56],"type":"Point"}
}