{
  "type": "Feature",
  "properties": {
    "gn:adm1_name":"Shizuokaken",
    "gn:adm2_name":"Kamogunmatsuzakichou",
    "gn:name":"Ena",
    "iso:country":"JP",
    "wof:name":"410-3624",
    "wof:placetype":"postalcode"
},
  "geometry": {"coordinates":[138.7807,34.757],"type":"Point"}
}