{
  "type": "Feature",
  "properties": {
    "gn:adm1_name":"Aichiken",
    "gn:adm2_name":"Higashikamogunshimoyamamura",
    "gn:name":"Habu",
    "iso:country":"JP",
    "wof:name":"444-3206",
    "wof:placetype":"postalcode"
},
  "geometry": {"coordinates":[137.38990000000001,35.0395],"type":"Point"}
}