{
  "type": "Feature",
  "properties": {
    "gn:adm1_name":"Yamanashiken",
    "gn:adm2_name":"Higashiyatsushirogun'Isawachou",
    "gn:name":"Hirose",
    "iso:country":"JP",
    "wof:name":"406-0035",
    "wof:placetype":"postalcode"
},
  "geometry": {"coordinates":[138.62459999999999,35.6405],"type":"Point"}
}