{
  "type": "Feature",
  "properties": {
    "gn:adm1_name":"Toyamaken",
    "gn:adm2_name":"Kurobeshi",
    "gn:name":"Shinmachi",
    "iso:country":"JP",
    "wof:name":"938-0056",
    "wof:placetype":"postalcode"
},
  "geometry": {"coordinates":[137.4186,36.8658],"type":"Point"}
}