{
  "type": "Feature",
  "properties": {
    "gn:adm1_name":"Shigaken",
    "gn:adm2_name":"Oumihachimanshi",
    "gn:name":"Nishinoshouchou",
    "iso:country":"JP",
    "wof:name":"523-0816",
    "wof:placetype":"postalcode"
},
  "geometry": {"coordinates":[136.11109999999999,35.1343],"type":"Point"}
}