{
  "type": "Feature",
  "properties": {
    "gn:adm1_name":"Fukuiken",
    "gn:adm2_name":"Nyuugun'Asahichou",
    "gn:name":"Gumiwara",
    "iso:country":"JP",
    "wof:name":"916-0155",
    "wof:placetype":"postalcode"
},
  "geometry": {"coordinates":[136.0966,35.9649],"type":"Point"}
}