{
  "type": "Feature",
  "properties": {
    "gn:adm1_name":"Ibarakiken",
    "gn:adm2_name":"Yuukigunyachiyomachi",
    "gn:name":"Narita",
    "iso:country":"JP",
    "wof:name":"300-3506",
    "wof:placetype":"postalcode"
},
  "geometry": {"coordinates":[139.87020000000001,36.1981],"type":"Point"}
}