{
  "type": "Feature",
  "properties": {
    "gn:adm1_name":"Aichiken",
    "gn:adm2_name":"Inazawashi",
    "gn:name":"Amaikenamiyosechou",
    "iso:country":"JP",
    "wof:name":"492-8283",
    "wof:placetype":"postalcode"
},
  "geometry": {"coordinates":[136.77180000000001,35.255],"type":"Point"}
}