{
  "type": "Feature",
  "properties": {
    "gn:adm1_name":"Fukushimaken",
    "gn:adm2_name":"Yamagunnishiaidumachi",
    "gn:name":"Kaminojiri",
    "iso:country":"JP",
    "wof:name":"969-4512",
    "wof:placetype":"postalcode"
},
  "geometry": {"coordinates":[139.63040000000001,37.6245],"type":"Point"}
}