{
  "type": "Feature",
  "properties": {
    "gn:adm1_name":"Tochigiken",
    "gn:adm2_name":"Nasugunnishinasunomachi",
    "gn:name":"Saiwaichou",
    "iso:country":"JP",
    "wof:name":"329-2724",
    "wof:placetype":"postalcode"
},
  "geometry": {"coordinates":[139.9828,36.876],"type":"Point"}
}