{
  "type": "Feature",
  "properties": {
    "gn:adm1_name":"Chibaken",
    "gn:adm2_name":"Ichiharashi",
    "gn:name":"Goinishi",
    "iso:country":"JP",
    "wof:name":"290-0038",
    "wof:placetype":"postalcode"
},
  "geometry": {"coordinates":[140.07050000000001,35.5147],"type":"Point"}
}