{
  "type": "Feature",
  "properties": {
    "gn:adm1_name":"Ishikawaken",
    "gn:adm2_name":"Kagashi",
    "gn:name":"Daishoujiteramachi",
    "iso:country":"JP",
    "wof:name":"922-0054",
    "wof:placetype":"postalcode"
},
  "geometry": {"coordinates":[136.31280000000001,36.3072],"type":"Point"}
}