{
  "type": "Feature",
  "properties": {
    "gn:adm1_name":"Oosakafu",
    "gn:adm2_name":"Kishiwadashi",
    "gn:name":"Minamimachi",
    "iso:country":"JP",
    "wof:name":"596-0067",
    "wof:placetype":"postalcode"
},
  "geometry": {"coordinates":[135.3648,34.4573],"type":"Point"}
}