{
  "type": "Feature",
  "properties": {
    "gn:adm1_name":"Kagoshimaken",
    "gn:adm2_name":"Kagoshimashi",
    "gn:name":"Nishimurasakibaruchou",
    "iso:country":"JP",
    "wof:name":"890-0083",
    "wof:placetype":"postalcode"
},
  "geometry": {"coordinates":[130.52879999999999,31.5561],"type":"Point"}
}