{
  "type": "Feature",
  "properties": {
    "gn:adm1_name":"Kouchiken",
    "gn:adm2_name":"Nakamurashi",
    "gn:name":"Higashimachi",
    "iso:country":"JP",
    "wof:name":"787-0023",
    "wof:placetype":"postalcode"
},
  "geometry": {"coordinates":[132.93870000000001,32.9954],"type":"Point"}
}