{
  "type": "Feature",
  "properties": {
    "gn:adm1_name":"Hiroshimaken",
    "gn:adm2_name":"Toyotagunhongouchou",
    "gn:name":"Hongou",
    "iso:country":"JP",
    "wof:name":"729-0412",
    "wof:placetype":"postalcode"
},
  "geometry": {"coordinates":[132.98949999999999,34.4097],"type":"Point"}
}