{
  "type": "Feature",
  "properties": {
    "gn:adm1_name":"Ibarakiken",
    "gn:adm2_name":"Higashiibarakigun'Ibarakimachi",
    "gn:name":"Oodo",
    "iso:country":"JP",
    "wof:name":"311-3114",
    "wof:placetype":"postalcode"
},
  "geometry": {"coordinates":[140.4151,36.32],"type":"Point"}
}