{
  "type": "Feature",
  "properties": {
    "gn:adm1_name":"Hyougoken",
    "gn:adm2_name":"Miharagunnandanchou",
    "gn:name":"Fukurakou",
    "iso:country":"JP",
    "wof:name":"656-0501",
    "wof:placetype":"postalcode"
},
  "geometry": {"coordinates":[134.72309999999999,34.2583],"type":"Point"}
}