{
  "type": "Feature",
  "properties": {
    "gn:adm1_name":"Nagasakiken",
    "gn:adm2_name":"Hiradoshi",
    "gn:name":"Kasugachou",
    "iso:country":"JP",
    "wof:name":"859-5373",
    "wof:placetype":"postalcode"
},
  "geometry": {"coordinates":[129.44450000000001,33.3425],"type":"Point"}
}