{
  "type": "Feature",
  "properties": {
    "gn:adm1_name":"Tokushimaken",
    "gn:adm2_name":"Ananshi",
    "gn:name":"Saimichou",
    "iso:country":"JP",
    "wof:name":"774-0015",
    "wof:placetype":"postalcode"
},
  "geometry": {"coordinates":[134.67320000000001,33.9135],"type":"Point"}
}