{
  "type": "Feature",
  "properties": {
    "gn:adm1_name":"Hyougoken",
    "gn:adm2_name":"Onoshi",
    "gn:name":"Kamihonmachi",
    "iso:country":"JP",
    "wof:name":"675-1379",
    "wof:placetype":"postalcode"
},
  "geometry": {"coordinates":[134.93510000000001,34.8494],"type":"Point"}
}