{
  "type": "Feature",
  "properties": {
    "gn:adm1_name":"Hyougoken",
    "gn:adm2_name":"Kanzakigun'Ichikawachou",
    "gn:name":"Hoki",
    "iso:country":"JP",
    "wof:name":"679-2312",
    "wof:placetype":"postalcode"
},
  "geometry": {"coordinates":[134.77189999999999,34.9721],"type":"Point"}
}