{
  "type": "Feature",
  "properties": {
    "gn:adm1_name":"Nagasakiken",
    "gn:adm2_name":"Saseboshi",
    "gn:name":"Yokoochou",
    "iso:country":"JP",
    "wof:name":"857-0018",
    "wof:placetype":"postalcode"
},
  "geometry": {"coordinates":[129.71700000000001,33.1959],"type":"Point"}
}