{
  "type": "Feature",
  "properties": {
    "gn:adm1_name":"Wakayamaken",
    "gn:adm2_name":"Hidakagun'Inamichou",
    "gn:name":"Tsui",
    "iso:country":"JP",
    "wof:name":"649-1535",
    "wof:placetype":"postalcode"
},
  "geometry": {"coordinates":[135.20339999999999,33.8154],"type":"Point"}
}