{
  "type": "Feature",
  "properties": {
    "gn:adm1_name":"Okayamaken",
    "gn:adm2_name":"Okayamashi",
    "gn:name":"Naradu",
    "iso:country":"JP",
    "wof:name":"701-1202",
    "wof:placetype":"postalcode"
},
  "geometry": {"coordinates":[133.8827,34.6817],"type":"Point"}
}