{
  "type": "Feature",
  "properties": {
    "gn:adm1_name":"Yamaguchiken",
    "gn:adm2_name":"Kumageguntabusechou",
    "gn:name":"Kamitabuse",
    "iso:country":"JP",
    "wof:name":"742-1515",
    "wof:placetype":"postalcode"
},
  "geometry": {"coordinates":[132.0102,33.943],"type":"Point"}
}