{
  "type": "Feature",
  "properties": {
    "gn:adm1_name":"Gunmaken",
    "gn:adm2_name":"Numatashi",
    "gn:name":"Kaminumasumachi",
    "iso:country":"JP",
    "wof:name":"378-0011",
    "wof:placetype":"postalcode"
},
  "geometry": {"coordinates":[139.0625,36.6424],"type":"Point"}
}