{
  "type": "Feature",
  "properties": {
    "gn:adm1_name":"Chibaken",
    "gn:adm2_name":"Futtsushi",
    "gn:name":"Maekubo",
    "iso:country":"JP",
    "wof:name":"293-0004",
    "wof:placetype":"postalcode"
},
  "geometry": {"coordinates":[139.8818,35.315],"type":"Point"}
}