{
  "type": "Feature",
  "properties": {
    "gn:adm1_name":"Saitamaken",
    "gn:adm2_name":"Kitakatsushikagunkurihashimachi",
    "gn:name":"Higashi",
    "iso:country":"JP",
    "wof:name":"349-1103",
    "wof:placetype":"postalcode"
},
  "geometry": {"coordinates":[139.70230000000001,36.1328],"type":"Point"}
}