{
  "type": "Feature",
  "properties": {
    "gn:adm1_name":"Kyoutofu",
    "gn:adm2_name":"Kyoutoshifushimiku",
    "gn:name":"Ogurisuyamaguchichou",
    "iso:country":"JP",
    "wof:name":"601-1454",
    "wof:placetype":"postalcode"
},
  "geometry": {"coordinates":[135.803,34.9479],"type":"Point"}
}