{
  "type": "Feature",
  "properties": {
    "gn:adm1_name":"Yamaguchiken",
    "gn:adm2_name":"Houfushi",
    "gn:name":"Matsubarachou",
    "iso:country":"JP",
    "wof:name":"747-0804",
    "wof:placetype":"postalcode"
},
  "geometry": {"coordinates":[131.5685,34.0428],"type":"Point"}
}