{
  "type": "Feature",
  "properties": {
    "gn:adm1_name":"Miyazakiken",
    "gn:adm2_name":"Higashiusukiguntougouchou",
    "gn:name":"Yamagetei",
    "iso:country":"JP",
    "wof:name":"883-0103",
    "wof:placetype":"postalcode"
},
  "geometry": {"coordinates":[131.5147,32.3797],"type":"Point"}
}