{
  "type": "Feature",
  "properties": {
    "gn:adm1_name":"Kanagawaken",
    "gn:adm2_name":"Yokohamashinishiku",
    "gn:name":"Kusunokichou",
    "iso:country":"JP",
    "wof:name":"220-0003",
    "wof:placetype":"postalcode"
},
  "geometry": {"coordinates":[139.6138,35.4673],"type":"Point"}
}