{
  "type": "Feature",
  "properties": {
    "gn:adm1_name":"Kyoutofu",
    "gn:adm2_name":"Kyoutoshiyamashinaku",
    "gn:name":"Ooyakegokudenchou",
    "iso:country":"JP",
    "wof:name":"607-8192",
    "wof:placetype":"postalcode"
},
  "geometry": {"coordinates":[135.81469999999999,34.9691],"type":"Point"}
}