{
  "type": "Feature",
  "properties": {
    "gn:adm1_name":"Okayamaken",
    "gn:adm2_name":"Okayamashi",
    "gn:name":"Tsushimasasagase",
    "iso:country":"JP",
    "wof:name":"700-0088",
    "wof:placetype":"postalcode"
},
  "geometry": {"coordinates":[133.90199999999999,34.6858],"type":"Point"}
}