{
  "type": "Feature",
  "properties": {
    "gn:adm1_name":"Niigataken",
    "gn:adm2_name":"Niigatashi",
    "gn:name":"Kamiwada",
    "iso:country":"JP",
    "wof:name":"950-0326",
    "wof:placetype":"postalcode"
},
  "geometry": {"coordinates":[139.05860000000001,37.8402],"type":"Point"}
}