{
  "type": "Feature",
  "properties": {
    "gn:adm1_name":"Okayamaken",
    "gn:adm2_name":"Aidagunnishiawakurason",
    "gn:name":"Kageishi",
    "iso:country":"JP",
    "wof:name":"707-0503",
    "wof:placetype":"postalcode"
},
  "geometry": {"coordinates":[134.33019999999999,35.1848],"type":"Point"}
}