{
  "type": "Feature",
  "properties": {
    "gn:adm1_name":"Hyougoken",
    "gn:adm2_name":"Akashishi",
    "gn:name":"Fujie(Wakabayashi)",
    "iso:country":"JP",
    "wof:name":"673-0045",
    "wof:placetype":"postalcode"
},
  "geometry": {"coordinates":[134.95310000000001,34.6669],"type":"Point"}
}