{
  "type": "Feature",
  "properties": {
    "gn:adm1_name":"Yamagataken",
    "gn:adm2_name":"Higashineshi",
    "gn:name":"Sekiyama",
    "iso:country":"JP",
    "wof:name":"999-3724",
    "wof:placetype":"postalcode"
},
  "geometry": {"coordinates":[140.477,38.4144],"type":"Point"}
}