{
  "type": "Feature",
  "properties": {
    "gn:adm1_name":"Kouchiken",
    "gn:adm2_name":"Nakamurashi",
    "gn:name":"Isawa",
    "iso:country":"JP",
    "wof:name":"787-0150",
    "wof:placetype":"postalcode"
},
  "geometry": {"coordinates":[132.9674,32.9744],"type":"Point"}
}