{
  "type": "Feature",
  "properties": {
    "gn:adm1_name":"Toukyouto",
    "gn:adm2_name":"Koutouku",
    "gn:name":"Shiomi",
    "iso:country":"JP",
    "wof:name":"135-0052",
    "wof:placetype":"postalcode"
},
  "geometry": {"coordinates":[139.815,35.6577],"type":"Point"}
}