{
  "type": "Feature",
  "properties": {
    "gn:adm1_name":"Kouchiken",
    "gn:adm2_name":"Nagaokagun'Ootoyochou",
    "gn:name":"Minamidaiou",
    "iso:country":"JP",
    "wof:name":"789-0163",
    "wof:placetype":"postalcode"
},
  "geometry": {"coordinates":[133.7861,33.7676],"type":"Point"}
}