{
  "type": "Feature",
  "properties": {
    "gn:adm1_name":"Naganoken",
    "gn:adm2_name":"Nakanoshi",
    "gn:name":"Angenji",
    "iso:country":"JP",
    "wof:name":"383-0052",
    "wof:placetype":"postalcode"
},
  "geometry": {"coordinates":[138.33150000000001,36.7391],"type":"Point"}
}