{
  "type": "Feature",
  "properties": {
    "gn:adm1_name":"Niigataken",
    "gn:adm2_name":"Nishikubikigunnadachimachi",
    "gn:name":"Tanoue",
    "iso:country":"JP",
    "wof:name":"949-1609",
    "wof:placetype":"postalcode"
},
  "geometry": {"coordinates":[138.10839999999999,37.1332],"type":"Point"}
}