{
  "type": "Feature",
  "properties": {
    "gn:adm1_name":"Okinawaken",
    "gn:adm2_name":"Nahashi",
    "gn:name":"Kagamizu",
    "iso:country":"JP",
    "wof:name":"901-0142",
    "wof:placetype":"postalcode"
},
  "geometry": {"coordinates":[127.6521,26.2105],"type":"Point"}
}