{
  "type": "Feature",
  "properties": {
    "gn:adm1_name":"Naganoken",
    "gn:adm2_name":"Matsumotoshi",
    "gn:name":"Takamiyakita",
    "iso:country":"JP",
    "wof:name":"390-0836",
    "wof:placetype":"postalcode"
},
  "geometry": {"coordinates":[137.95910000000001,36.2174],"type":"Point"}
}