{
  "type": "Feature",
  "properties": {
    "gn:adm1_name":"Niigataken",
    "gn:adm2_name":"Jouetsushi",
    "gn:name":"Arimagawa",
    "iso:country":"JP",
    "wof:name":"949-1702",
    "wof:placetype":"postalcode"
},
  "geometry": {"coordinates":[138.14359999999999,37.1624],"type":"Point"}
}