{
  "type": "Feature",
  "properties": {
    "gn:adm1_name":"Toyamaken",
    "gn:adm2_name":"Takaokashi",
    "gn:name":"Kanayahonmachi",
    "iso:country":"JP",
    "wof:name":"933-0945",
    "wof:placetype":"postalcode"
},
  "geometry": {"coordinates":[137.00649999999999,36.7517],"type":"Point"}
}