{
  "type": "Feature",
  "properties": {
    "gn:adm1_name":"Oosakafu",
    "gn:adm2_name":"Takatsukishi",
    "gn:name":"Hagitanitsukimidai",
    "iso:country":"JP",
    "wof:name":"569-1053",
    "wof:placetype":"postalcode"
},
  "geometry": {"coordinates":[135.58029999999999,34.8805],"type":"Point"}
}