{
  "type": "Feature",
  "properties": {
    "gn:adm1_name":"Hyougoken",
    "gn:adm2_name":"Koubeshichuuouku",
    "gn:name":"Kusunokichou",
    "iso:country":"JP",
    "wof:name":"650-0017",
    "wof:placetype":"postalcode"
},
  "geometry": {"coordinates":[135.17400000000001,34.684],"type":"Point"}
}