{
  "type": "Feature",
  "properties": {
    "gn:adm1_name":"Kyoutofu",
    "gn:adm2_name":"Kyoutoshihigashiyamaku",
    "gn:name":"Oohashichou",
    "iso:country":"JP",
    "wof:name":"605-0009",
    "wof:placetype":"postalcode"
},
  "geometry": {"coordinates":[135.77350000000001,35.0093],"type":"Point"}
}