{
  "type": "Feature",
  "properties": {
    "gn:adm1_name":"Niigataken",
    "gn:adm2_name":"Iwafunegunsekikawamura",
    "gn:name":"Kowada",
    "iso:country":"JP",
    "wof:name":"959-3211",
    "wof:placetype":"postalcode"
},
  "geometry": {"coordinates":[139.566,38.1322],"type":"Point"}
}