{
  "type": "Feature",
  "properties": {
    "gn:adm1_name":"Kumamotoken",
    "gn:adm2_name":"Utoshi",
    "gn:name":"Akasemachi",
    "iso:country":"JP",
    "wof:name":"869-3175",
    "wof:placetype":"postalcode"
},
  "geometry": {"coordinates":[130.5154,32.6563],"type":"Point"}
}