{
  "type": "Feature",
  "properties": {
    "gn:adm1_name":"Saitamaken",
    "gn:adm2_name":"Higashimatsuyamashi",
    "gn:name":"Kaminomoto",
    "iso:country":"JP",
    "wof:name":"355-0073",
    "wof:placetype":"postalcode"
},
  "geometry": {"coordinates":[139.40029999999999,36.0257],"type":"Point"}
}