{
  "type": "Feature",
  "properties": {
    "gn:adm1_name":"Gifuken",
    "gn:adm2_name":"Mashitagungerochou",
    "gn:name":"Nojiri",
    "iso:country":"JP",
    "wof:name":"509-2313",
    "wof:placetype":"postalcode"
},
  "geometry": {"coordinates":[137.30789999999999,35.7592],"type":"Point"}
}