{
  "type": "Feature",
  "properties": {
    "gn:adm1_name":"Kyoutofu",
    "gn:adm2_name":"Yawatashi",
    "gn:name":"Otokoyamatakezono",
    "iso:country":"JP",
    "wof:name":"614-8376",
    "wof:placetype":"postalcode"
},
  "geometry": {"coordinates":[135.6962,34.856],"type":"Point"}
}