{
  "type": "Feature",
  "properties": {
    "gn:adm1_name":"Okinawaken",
    "gn:adm2_name":"Kunigamigunkunigamison",
    "gn:name":"Yona",
    "iso:country":"JP",
    "wof:name":"905-1427",
    "wof:placetype":"postalcode"
},
  "geometry": {"coordinates":[128.2055,26.7647],"type":"Point"}
}