{
  "type": "Feature",
  "properties": {
    "gn:adm1_name":"Fukuokaken",
    "gn:adm2_name":"Fukuokashihigashiku",
    "gn:name":"Hakomatsu",
    "iso:country":"JP",
    "wof:name":"812-0061",
    "wof:placetype":"postalcode"
},
  "geometry": {"coordinates":[130.42920000000001,33.623],"type":"Point"}
}