{
  "type": "Feature",
  "properties": {
    "gn:adm1_name":"Fukuokaken",
    "gn:adm2_name":"Kogashi",
    "gn:name":"Oyamada",
    "iso:country":"JP",
    "wof:name":"811-3126",
    "wof:placetype":"postalcode"
},
  "geometry": {"coordinates":[130.506,33.7154],"type":"Point"}
}