{
  "type": "Feature",
  "properties": {
    "gn:adm1_name":"Saitamaken",
    "gn:adm2_name":"Kitasaitamagun'Ootonemachi",
    "gn:name":"Nakawata",
    "iso:country":"JP",
    "wof:name":"349-1131",
    "wof:placetype":"postalcode"
},
  "geometry": {"coordinates":[139.6865,36.155],"type":"Point"}
}