{
  "type": "Feature",
  "properties": {
    "gn:adm1_name":"Kyoutofu",
    "gn:adm2_name":"Maidurushi",
    "gn:name":"Hatta",
    "iso:country":"JP",
    "wof:name":"624-0954",
    "wof:placetype":"postalcode"
},
  "geometry": {"coordinates":[135.26820000000001,35.4564],"type":"Point"}
}