{
  "type": "Feature",
  "properties": {
    "gn:adm1_name":"Saitamaken",
    "gn:adm2_name":"Kitakatsushikagunsugitomachi",
    "gn:name":"Fukawa",
    "iso:country":"JP",
    "wof:name":"345-0012",
    "wof:placetype":"postalcode"
},
  "geometry": {"coordinates":[139.78790000000001,36.0391],"type":"Point"}
}