{
  "type": "Feature",
  "properties": {
    "gn:adm1_name":"Fukushimaken",
    "gn:adm2_name":"Oonumagun'Aiduhongoumachi",
    "gn:name":"Michikami",
    "iso:country":"JP",
    "wof:name":"969-6164",
    "wof:placetype":"postalcode"
},
  "geometry": {"coordinates":[139.88140000000001,37.4547],"type":"Point"}
}