{
  "type": "Feature",
  "properties": {
    "gn:adm1_name":"Ibarakiken",
    "gn:adm2_name":"Takahagishi",
    "gn:name":"Wakaguri",
    "iso:country":"JP",
    "wof:name":"318-0102",
    "wof:placetype":"postalcode"
},
  "geometry": {"coordinates":[140.63120000000001,36.7738],"type":"Point"}
}