{
  "type": "Feature",
  "properties": {
    "gn:adm1_name":"Mieken",
    "gn:adm2_name":"Inabeshi",
    "gn:name":"Hokuseichoushimohira",
    "iso:country":"JP",
    "wof:name":"511-0418",
    "wof:placetype":"postalcode"
},
  "geometry": {"coordinates":[136.5196,35.1688],"type":"Point"}
}