{
  "type": "Feature",
  "properties": {
    "gn:adm1_name":"Mieken",
    "gn:adm2_name":"Takigunmeiwachou",
    "gn:name":"Naiza",
    "iso:country":"JP",
    "wof:name":"515-0343",
    "wof:placetype":"postalcode"
},
  "geometry": {"coordinates":[136.62379999999999,34.5827],"type":"Point"}
}