{
  "type": "Feature",
  "properties": {
    "gn:adm1_name":"Niigataken",
    "gn:adm2_name":"Kariwagunnishiyamamachi",
    "gn:name":"Hamatsuda",
    "iso:country":"JP",
    "wof:name":"949-4205",
    "wof:placetype":"postalcode"
},
  "geometry": {"coordinates":[138.6429,37.4832],"type":"Point"}
}