{
  "type": "Feature",
  "properties": {
    "gn:adm1_name":"Miyagiken",
    "gn:adm2_name":"Sendaishimiyaginoku",
    "gn:name":"Shinden",
    "iso:country":"JP",
    "wof:name":"983-0038",
    "wof:placetype":"postalcode"
},
  "geometry": {"coordinates":[140.9248,38.2753],"type":"Point"}
}