{
  "type": "Feature",
  "properties": {
    "gn:adm1_name":"Kagoshimaken",
    "gn:adm2_name":"Airagun'Airachou",
    "gn:name":"Nishimiyajimamachi",
    "iso:country":"JP",
    "wof:name":"899-5433",
    "wof:placetype":"postalcode"
},
  "geometry": {"coordinates":[130.62180000000001,31.725],"type":"Point"}
}