{
  "type": "Feature",
  "properties": {
    "gn:adm1_name":"Ishikawaken",
    "gn:adm2_name":"Fugeshigun'Anamizumachi",
    "gn:name":"Yuigaoka",
    "iso:country":"JP",
    "wof:name":"927-0024",
    "wof:placetype":"postalcode"
},
  "geometry": {"coordinates":[136.91999999999999,37.2301],"type":"Point"}
}