{
  "type": "Feature",
  "properties": {
    "gn:adm1_name":"Toyamaken",
    "gn:adm2_name":"Oyabeshi",
    "gn:name":"Shima",
    "iso:country":"JP",
    "wof:name":"932-0825",
    "wof:placetype":"postalcode"
},
  "geometry": {"coordinates":[136.8758,36.6625],"type":"Point"}
}