{
  "type": "Feature",
  "properties": {
    "gn:adm1_name":"Yamagataken",
    "gn:adm2_name":"Nanyoushi",
    "gn:name":"Koiwasawa",
    "iso:country":"JP",
    "wof:name":"999-2203",
    "wof:placetype":"postalcode"
},
  "geometry": {"coordinates":[140.20439999999999,38.0923],"type":"Point"}
}