{
  "type": "Feature",
  "properties": {
    "gn:adm1_name":"Niigataken",
    "gn:adm2_name":"Ryoutsushi",
    "gn:name":"Hiramatsu",
    "iso:country":"JP",
    "wof:name":"952-3115",
    "wof:placetype":"postalcode"
},
  "geometry": {"coordinates":[138.4803,38.1898],"type":"Point"}
}