{
  "type": "Feature",
  "properties": {
    "gn:adm1_name":"Shizuokaken",
    "gn:adm2_name":"Shimadashi",
    "gn:name":"Ooyanagi",
    "iso:country":"JP",
    "wof:name":"427-0101",
    "wof:placetype":"postalcode"
},
  "geometry": {"coordinates":[138.2243,34.8127],"type":"Point"}
}