{
  "type": "Feature",
  "properties": {
    "gn:adm1_name":"Shizuokaken",
    "gn:adm2_name":"Ogasagundaitouchou",
    "gn:name":"Oosaka",
    "iso:country":"JP",
    "wof:name":"437-1421",
    "wof:placetype":"postalcode"
},
  "geometry": {"coordinates":[138.04310000000001,34.6739],"type":"Point"}
}