{
  "type": "Feature",
  "properties": {
    "gn:adm1_name":"Fukuiken",
    "gn:adm2_name":"Ooiguntakahamachou",
    "gn:name":"Uwase",
    "iso:country":"JP",
    "wof:name":"919-2356",
    "wof:placetype":"postalcode"
},
  "geometry": {"coordinates":[135.47810000000001,35.5514],"type":"Point"}
}