{
  "type": "Feature",
  "properties": {
    "gn:adm1_name":"Wakayamaken",
    "gn:adm2_name":"Wakayamashi",
    "gn:name":"Misonochou",
    "iso:country":"JP",
    "wof:name":"640-8331",
    "wof:placetype":"postalcode"
},
  "geometry": {"coordinates":[135.1891,34.231],"type":"Point"}
}