{
  "type": "Feature",
  "properties": {
    "gn:adm1_name":"Miyagiken",
    "gn:adm2_name":"Kuriharagunkurikomamachi",
    "gn:name":"Sakurada",
    "iso:country":"JP",
    "wof:name":"989-5322",
    "wof:placetype":"postalcode"
},
  "geometry": {"coordinates":[140.9956,38.7927],"type":"Point"}
}