{
  "type": "Feature",
  "properties": {
    "gn:adm1_name":"Kagoshimaken",
    "gn:adm2_name":"Ooshimagunwadomarichou",
    "gn:name":"Kunigami",
    "iso:country":"JP",
    "wof:name":"891-9101",
    "wof:placetype":"postalcode"
},
  "geometry": {"coordinates":[128.68690000000001,27.4278],"type":"Point"}
}