{
  "type": "Feature",
  "properties": {
    "gn:adm1_name":"Hyougoken",
    "gn:adm2_name":"Ashiyashi",
    "gn:name":"Asahigaokachou",
    "iso:country":"JP",
    "wof:name":"659-0012",
    "wof:placetype":"postalcode"
},
  "geometry": {"coordinates":[135.30709999999999,34.7463],"type":"Point"}
}