{
  "type": "Feature",
  "properties": {
    "gn:adm1_name":"Oosakafu",
    "gn:adm2_name":"Sennangunkumatorichou",
    "gn:name":"Noda",
    "iso:country":"JP",
    "wof:name":"590-0451",
    "wof:placetype":"postalcode"
},
  "geometry": {"coordinates":[135.35489999999999,34.4005],"type":"Point"}
}