{
  "type": "Feature",
  "properties": {
    "gn:adm1_name":"Shizuokaken",
    "gn:adm2_name":"Haibaragunkawanechou",
    "gn:name":"Sasamakami",
    "iso:country":"JP",
    "wof:name":"428-0211",
    "wof:placetype":"postalcode"
},
  "geometry": {"coordinates":[138.1524,35.0207],"type":"Point"}
}