{
  "type": "Feature",
  "properties": {
    "gn:adm1_name":"Hyougoken",
    "gn:adm2_name":"Nishinomiyashi",
    "gn:name":"Houjougaoka",
    "iso:country":"JP",
    "wof:name":"669-1112",
    "wof:placetype":"postalcode"
},
  "geometry": {"coordinates":[135.32990000000001,34.814],"type":"Point"}
}