{
  "type": "Feature",
  "properties": {
    "gn:adm1_name":"Naganoken",
    "gn:adm2_name":"Shimominochigunsakaemura",
    "gn:name":"Toyosakae",
    "iso:country":"JP",
    "wof:name":"389-2701",
    "wof:placetype":"postalcode"
},
  "geometry": {"coordinates":[138.51679999999999,36.9847],"type":"Point"}
}