{
  "type": "Feature",
  "properties": {
    "gn:adm1_name":"Kanagawaken",
    "gn:adm2_name":"Hiratsukashi",
    "gn:name":"Tamura",
    "iso:country":"JP",
    "wof:name":"254-0013",
    "wof:placetype":"postalcode"
},
  "geometry": {"coordinates":[139.36340000000001,35.3738],"type":"Point"}
}