{
  "type": "Feature",
  "properties": {
    "gn:adm1_name":"Ibarakiken",
    "gn:adm2_name":"Kitasoumaguntonemachi",
    "gn:name":"Oshitsukeshinden",
    "iso:country":"JP",
    "wof:name":"300-1634",
    "wof:placetype":"postalcode"
},
  "geometry": {"coordinates":[140.1378,35.8664],"type":"Point"}
}