{
  "type": "Feature",
  "properties": {
    "gn:adm1_name":"Kyoutofu",
    "gn:adm2_name":"Kyoutoshiminamiku",
    "gn:name":"Kisshouinhigashisunanochou",
    "iso:country":"JP",
    "wof:name":"601-8334",
    "wof:placetype":"postalcode"
},
  "geometry": {"coordinates":[135.73339999999999,34.9697],"type":"Point"}
}