{
  "type": "Feature",
  "properties": {
    "gn:adm1_name":"Oosakafu",
    "gn:adm2_name":"Kadomashi",
    "gn:name":"Noguchi",
    "iso:country":"JP",
    "wof:name":"571-0024",
    "wof:placetype":"postalcode"
},
  "geometry": {"coordinates":[135.60509999999999,34.728],"type":"Point"}
}