{
  "type": "Feature",
  "properties": {
    "gn:adm1_name":"Gifuken",
    "gn:adm2_name":"Yoshikigunkokufuchou",
    "gn:name":"Murayama",
    "iso:country":"JP",
    "wof:name":"509-4124",
    "wof:placetype":"postalcode"
},
  "geometry": {"coordinates":[137.25280000000001,36.1969],"type":"Point"}
}