{
  "type": "Feature",
  "properties": {
    "gn:adm1_name":"Aichiken",
    "gn:adm2_name":"Ichinomiyashi",
    "gn:name":"Kitagatachousone",
    "iso:country":"JP",
    "wof:name":"493-8002",
    "wof:placetype":"postalcode"
},
  "geometry": {"coordinates":[136.78280000000001,35.3532],"type":"Point"}
}