{
  "type": "Feature",
  "properties": {
    "gn:adm1_name":"Nagasakiken",
    "gn:adm2_name":"Ikigun'Ashibechou",
    "gn:name":"Sumiyoshimaefure",
    "iso:country":"JP",
    "wof:name":"811-5743",
    "wof:placetype":"postalcode"
},
  "geometry": {"coordinates":[129.70079999999999,33.7805],"type":"Point"}
}