{
  "type": "Feature",
  "properties": {
    "gn:adm1_name":"Naraken",
    "gn:adm2_name":"Yamatokooriyamashi",
    "gn:name":"Higashiokachou",
    "iso:country":"JP",
    "wof:name":"639-1137",
    "wof:placetype":"postalcode"
},
  "geometry": {"coordinates":[135.7817,34.6438],"type":"Point"}
}