{
  "type": "Feature",
  "properties": {
    "gn:adm1_name":"Toukyouto",
    "gn:adm2_name":"Chiyodaku",
    "gn:name":"Koukyogaien",
    "iso:country":"JP",
    "wof:name":"100-0002",
    "wof:placetype":"postalcode"
},
  "geometry": {"coordinates":[139.75899999999999,35.679],"type":"Point"}
}