{
  "type": "Feature",
  "properties": {
    "gn:adm1_name":"Hyougoken",
    "gn:adm2_name":"Sumotoshi",
    "gn:name":"Nakatsugawagumi",
    "iso:country":"JP",
    "wof:name":"656-2532",
    "wof:placetype":"postalcode"
},
  "geometry": {"coordinates":[134.91309999999999,34.2577],"type":"Point"}
}