{
  "type": "Feature",
  "properties": {
    "gn:adm1_name":"Aichiken",
    "gn:adm2_name":"Nagoyashihigashiku",
    "gn:name":"Iidamachi",
    "iso:country":"JP",
    "wof:name":"461-0013",
    "wof:placetype":"postalcode"
},
  "geometry": {"coordinates":[136.9186,35.1792],"type":"Point"}
}