{
  "type": "Feature",
  "properties": {
    "gn:adm1_name":"Oosakafu",
    "gn:adm2_name":"Kishiwadashi",
    "gn:name":"Ikejirichou",
    "iso:country":"JP",
    "wof:name":"596-0813",
    "wof:placetype":"postalcode"
},
  "geometry": {"coordinates":[135.4128,34.4603],"type":"Point"}
}