{
  "type": "Feature",
  "properties": {
    "gn:adm1_name":"Okayamaken",
    "gn:adm2_name":"Kasaokashi",
    "gn:name":"Mobira",
    "iso:country":"JP",
    "wof:name":"714-0062",
    "wof:placetype":"postalcode"
},
  "geometry": {"coordinates":[133.45820000000001,34.4897],"type":"Point"}
}