{
  "type": "Feature",
  "properties": {
    "gn:adm1_name":"Ehimeken",
    "gn:adm2_name":"Matsuyamashi",
    "gn:name":"Toiyachou",
    "iso:country":"JP",
    "wof:name":"791-8018",
    "wof:placetype":"postalcode"
},
  "geometry": {"coordinates":[132.75139999999999,33.8642],"type":"Point"}
}