{
  "type": "Feature",
  "properties": {
    "gn:adm1_name":"Miyazakiken",
    "gn:adm2_name":"Nobeokashi",
    "gn:name":"Shiroishimachi",
    "iso:country":"JP",
    "wof:name":"882-0014",
    "wof:placetype":"postalcode"
},
  "geometry": {"coordinates":[131.71090000000001,32.6165],"type":"Point"}
}