{
  "type": "Feature",
  "properties": {
    "gn:adm1_name":"Kanagawaken",
    "gn:adm2_name":"Yokohamashiseyaku",
    "gn:name":"Minamidai",
    "iso:country":"JP",
    "wof:name":"246-0032",
    "wof:placetype":"postalcode"
},
  "geometry": {"coordinates":[139.48929999999999,35.4634],"type":"Point"}
}