{
  "type": "Feature",
  "properties": {
    "gn:adm1_name":"Sagaken",
    "gn:adm2_name":"Sagashi",
    "gn:name":"Matsubara",
    "iso:country":"JP",
    "wof:name":"840-0831",
    "wof:placetype":"postalcode"
},
  "geometry": {"coordinates":[130.30340000000001,33.2522],"type":"Point"}
}