{
  "type": "Feature",
  "properties": {
    "gn:adm1_name":"Aichiken",
    "gn:adm2_name":"Higashikamogun'Asahichou",
    "gn:name":"Ootsubo",
    "iso:country":"JP",
    "wof:name":"444-2822",
    "wof:placetype":"postalcode"
},
  "geometry": {"coordinates":[137.3391,35.2072],"type":"Point"}
}