{
  "type": "Feature",
  "properties": {
    "gn:adm1_name":"Naganoken",
    "gn:adm2_name":"Uedashi",
    "gn:name":"Chuuoukita",
    "iso:country":"JP",
    "wof:name":"386-0011",
    "wof:placetype":"postalcode"
},
  "geometry": {"coordinates":[138.25470000000001,36.41],"type":"Point"}
}