{
  "type": "Feature",
  "properties": {
    "gn:adm1_name":"Yamagataken",
    "gn:adm2_name":"Yonezawashi",
    "gn:name":"Asagawa",
    "iso:country":"JP",
    "wof:name":"992-0112",
    "wof:placetype":"postalcode"
},
  "geometry": {"coordinates":[140.15190000000001,37.9524],"type":"Point"}
}