{
  "type": "Feature",
  "properties": {
    "gn:adm1_name":"Kyoutofu",
    "gn:adm2_name":"Ujishi",
    "gn:name":"Ogurachou",
    "iso:country":"JP",
    "wof:name":"611-0042",
    "wof:placetype":"postalcode"
},
  "geometry": {"coordinates":[135.78110000000001,34.8939],"type":"Point"}
}