{
  "type": "Feature",
  "properties": {
    "gn:adm1_name":"Aichiken",
    "gn:adm2_name":"Hazugunhazuchou",
    "gn:name":"Terabe",
    "iso:country":"JP",
    "wof:name":"444-0702",
    "wof:placetype":"postalcode"
},
  "geometry": {"coordinates":[137.1249,34.7878],"type":"Point"}
}