{
  "type": "Feature",
  "properties": {
    "gn:adm1_name":"Chibaken",
    "gn:adm2_name":"Ichiharashi",
    "gn:name":"Koshikiya",
    "iso:country":"JP",
    "wof:name":"290-0528",
    "wof:placetype":"postalcode"
},
  "geometry": {"coordinates":[140.172,35.3307],"type":"Point"}
}