{
  "type": "Feature",
  "properties": {
    "gn:adm1_name":"Aichiken",
    "gn:adm2_name":"Ichinomiyashi",
    "gn:name":"Kamiyama",
    "iso:country":"JP",
    "wof:name":"491-0904",
    "wof:placetype":"postalcode"
},
  "geometry": {"coordinates":[136.78919999999999,35.3036],"type":"Point"}
}