{
  "type": "Feature",
  "properties": {
    "gn:adm1_name":"Hyougoken",
    "gn:adm2_name":"Mikishi",
    "gn:name":"Kasasoukano",
    "iso:country":"JP",
    "wof:name":"673-0723",
    "wof:placetype":"postalcode"
},
  "geometry": {"coordinates":[135.00290000000001,34.8455],"type":"Point"}
}