{
  "type": "Feature",
  "properties": {
    "gn:adm1_name":"Kyoutofu",
    "gn:adm2_name":"Kyoutoshisakyouku",
    "gn:name":"Kamitakanokurumajichou",
    "iso:country":"JP",
    "wof:name":"606-0053",
    "wof:placetype":"postalcode"
},
  "geometry": {"coordinates":[135.79230000000001,35.0626],"type":"Point"}
}