{
  "type": "Feature",
  "properties": {
    "gn:adm1_name":"Aichiken",
    "gn:adm2_name":"Nagoyashiminatoku",
    "gn:name":"Shiomichou",
    "iso:country":"JP",
    "wof:name":"455-0028",
    "wof:placetype":"postalcode"
},
  "geometry": {"coordinates":[136.87430000000001,35.0615],"type":"Point"}
}