{
  "type": "Feature",
  "properties": {
    "gn:adm1_name":"Saitamaken",
    "gn:adm2_name":"Hanyuushi",
    "gn:name":"Goudo",
    "iso:country":"JP",
    "wof:name":"348-0024",
    "wof:placetype":"postalcode"
},
  "geometry": {"coordinates":[139.56219999999999,36.1426],"type":"Point"}
}