{
  "type": "Feature",
  "properties": {
    "gn:adm1_name":"Chibaken",
    "gn:adm2_name":"Kimitsushi",
    "gn:name":"Koyamano",
    "iso:country":"JP",
    "wof:name":"299-1126",
    "wof:placetype":"postalcode"
},
  "geometry": {"coordinates":[139.91569999999999,35.2922],"type":"Point"}
}