{
  "type": "Feature",
  "properties": {
    "gn:adm1_name":"Gifuken",
    "gn:adm2_name":"Minoshi",
    "gn:name":"Chiunechou",
    "iso:country":"JP",
    "wof:name":"501-3734",
    "wof:placetype":"postalcode"
},
  "geometry": {"coordinates":[136.91030000000001,35.5384],"type":"Point"}
}