{
  "type": "Feature",
  "properties": {
    "gn:adm1_name":"Fukushimaken",
    "gn:adm2_name":"Ishikawagun'Asakawamachi",
    "gn:name":"Higashioohata",
    "iso:country":"JP",
    "wof:name":"963-6218",
    "wof:placetype":"postalcode"
},
  "geometry": {"coordinates":[140.41839999999999,37.0763],"type":"Point"}
}