{
  "type": "Feature",
  "properties": {
    "gn:adm1_name":"Toukyouto",
    "gn:adm2_name":"Fuchuushi",
    "gn:name":"Koremasa",
    "iso:country":"JP",
    "wof:name":"183-0014",
    "wof:placetype":"postalcode"
},
  "geometry": {"coordinates":[139.49019999999999,35.6594],"type":"Point"}
}