{
  "type": "Feature",
  "properties": {
    "gn:adm1_name":"Niigataken",
    "gn:adm2_name":"Niigatashi",
    "gn:name":"Tokimekihigashi",
    "iso:country":"JP",
    "wof:name":"950-1105",
    "wof:placetype":"postalcode"
},
  "geometry": {"coordinates":[139.01179999999999,37.8771],"type":"Point"}
}