{
  "type": "Feature",
  "properties": {
    "gn:adm1_name":"Shimaneken",
    "gn:adm2_name":"Okigunsaigouchou",
    "gn:name":"Misakimachi",
    "iso:country":"JP",
    "wof:name":"685-0021",
    "wof:placetype":"postalcode"
},
  "geometry": {"coordinates":[133.32679999999999,36.1891],"type":"Point"}
}