{
  "type": "Feature",
  "properties": {
    "gn:adm1_name":"Hyougoken",
    "gn:adm2_name":"Onoshi",
    "gn:name":"Asahichou",
    "iso:country":"JP",
    "wof:name":"675-1356",
    "wof:placetype":"postalcode"
},
  "geometry": {"coordinates":[134.94139999999999,34.8565],"type":"Point"}
}