{
  "type": "Feature",
  "properties": {
    "gn:adm1_name":"Shizuokaken",
    "gn:adm2_name":"Shizuokashi",
    "gn:name":"Yujima",
    "iso:country":"JP",
    "wof:name":"421-2102",
    "wof:placetype":"postalcode"
},
  "geometry": {"coordinates":[138.36179999999999,35.1125],"type":"Point"}
}