{
  "type": "Feature",
  "properties": {
    "gn:adm1_name":"Kanagawaken",
    "gn:adm2_name":"Iseharashi",
    "gn:name":"Takamori",
    "iso:country":"JP",
    "wof:name":"259-1114",
    "wof:placetype":"postalcode"
},
  "geometry": {"coordinates":[139.3288,35.4142],"type":"Point"}
}