{
  "type": "Feature",
  "properties": {
    "gn:adm1_name":"Toyamaken",
    "gn:adm2_name":"Takaokashi",
    "gn:name":"Onmadashimachi",
    "iso:country":"JP",
    "wof:name":"933-0926",
    "wof:placetype":"postalcode"
},
  "geometry": {"coordinates":[137.00890000000001,36.7455],"type":"Point"}
}