{
  "type": "Feature",
  "properties": {
    "gn:adm1_name":"Kyoutofu",
    "gn:adm2_name":"Kyoutoshikamigyouku",
    "gn:name":"Chuushochou",
    "iso:country":"JP",
    "wof:name":"602-8126",
    "wof:placetype":"postalcode"
},
  "geometry": {"coordinates":[135.7484,35.0187],"type":"Point"}
}