{
  "type": "Feature",
  "properties": {
    "gn:adm1_name":"Shizuokaken",
    "gn:adm2_name":"Iwataguntoyodachou",
    "gn:name":"Miyanoisshiki",
    "iso:country":"JP",
    "wof:name":"438-0816",
    "wof:placetype":"postalcode"
},
  "geometry": {"coordinates":[137.82849999999999,34.7194],"type":"Point"}
}