{
  "type": "Feature",
  "properties": {
    "gn:adm1_name":"Sagaken",
    "gn:adm2_name":"Imarishi",
    "gn:name":"Kurogawachoukuroshio",
    "iso:country":"JP",
    "wof:name":"848-0146",
    "wof:placetype":"postalcode"
},
  "geometry": {"coordinates":[129.84559999999999,33.3193],"type":"Point"}
}