{
  "type": "Feature",
  "properties": {
    "gn:adm1_name":"Fukuokaken",
    "gn:adm2_name":"Kitakyuushuushiyahatanishiku",
    "gn:name":"Warikogawa",
    "iso:country":"JP",
    "wof:name":"806-0064",
    "wof:placetype":"postalcode"
},
  "geometry": {"coordinates":[130.75819999999999,33.84],"type":"Point"}
}