{
  "type": "Feature",
  "properties": {
    "gn:adm1_name":"Fukuokaken",
    "gn:adm2_name":"Oomutashi",
    "gn:name":"Nishihamadamachi",
    "iso:country":"JP",
    "wof:name":"836-0027",
    "wof:placetype":"postalcode"
},
  "geometry": {"coordinates":[130.43780000000001,33.0349],"type":"Point"}
}