{
  "type": "Feature",
  "properties": {
    "gn:adm1_name":"Miyagiken",
    "gn:adm2_name":"Shiroishishi",
    "gn:name":"Nagamachi",
    "iso:country":"JP",
    "wof:name":"989-0274",
    "wof:placetype":"postalcode"
},
  "geometry": {"coordinates":[140.6224,38.0062],"type":"Point"}
}