{
  "type": "Feature",
  "properties": {
    "gn:adm1_name":"Ehimeken",
    "gn:adm2_name":"Higashiuwagunshirokawachou",
    "gn:name":"Kubono",
    "iso:country":"JP",
    "wof:name":"797-1703",
    "wof:placetype":"postalcode"
},
  "geometry": {"coordinates":[132.78980000000001,33.4061],"type":"Point"}
}