{
  "type": "Feature",
  "properties": {
    "gn:adm1_name":"Miyazakiken",
    "gn:adm2_name":"Ebinoshi",
    "gn:name":"Shimauchi",
    "iso:country":"JP",
    "wof:name":"889-4152",
    "wof:placetype":"postalcode"
},
  "geometry": {"coordinates":[130.7825,32.0505],"type":"Point"}
}