{
  "type": "Feature",
  "properties": {
    "gn:adm1_name":"Aichiken",
    "gn:adm2_name":"Nagoyashiminamiku",
    "gn:name":"Daidouchou",
    "iso:country":"JP",
    "wof:name":"457-0811",
    "wof:placetype":"postalcode"
},
  "geometry": {"coordinates":[136.9109,35.0796],"type":"Point"}
}