{
  "type": "Feature",
  "properties": {
    "gn:adm1_name":"Fukuokaken",
    "gn:adm2_name":"Kitakyuushuushimojiku",
    "gn:name":"Katagamikaigan",
    "iso:country":"JP",
    "wof:name":"800-0061",
    "wof:placetype":"postalcode"
},
  "geometry": {"coordinates":[130.94280000000001,33.9294],"type":"Point"}
}