{
  "type": "Feature",
  "properties": {
    "gn:adm1_name":"Kyoutofu",
    "gn:adm2_name":"Kyoutoshiminamiku",
    "gn:name":"Kisshouinnishinoshoufuchinonishichou",
    "iso:country":"JP",
    "wof:name":"601-8302",
    "wof:placetype":"postalcode"
},
  "geometry": {"coordinates":[135.72839999999999,34.9829],"type":"Point"}
}