{
  "type": "Feature",
  "properties": {
    "gn:adm1_name":"Kouchiken",
    "gn:adm2_name":"Kouchishi",
    "gn:name":"Yokohamaminamimachi",
    "iso:country":"JP",
    "wof:name":"781-0244",
    "wof:placetype":"postalcode"
},
  "geometry": {"coordinates":[133.53970000000001,33.5126],"type":"Point"}
}