{
  "type": "Feature",
  "properties": {
    "gn:adm1_name":"Tochigiken",
    "gn:adm2_name":"Mookashi",
    "gn:name":"Tamachi",
    "iso:country":"JP",
    "wof:name":"321-4325",
    "wof:placetype":"postalcode"
},
  "geometry": {"coordinates":[140.01079999999999,36.4376],"type":"Point"}
}