{
  "type": "Feature",
  "properties": {
    "gn:adm1_name":"Niigataken",
    "gn:adm2_name":"Niitsushi",
    "gn:name":"Oojika",
    "iso:country":"JP",
    "wof:name":"956-0004",
    "wof:placetype":"postalcode"
},
  "geometry": {"coordinates":[139.09970000000001,37.7962],"type":"Point"}
}