{
  "type": "Feature",
  "properties": {
    "gn:adm1_name":"Shimaneken",
    "gn:adm2_name":"Yatsukagunmihonosekichou",
    "gn:name":"Kumodu",
    "iso:country":"JP",
    "wof:name":"690-1502",
    "wof:placetype":"postalcode"
},
  "geometry": {"coordinates":[133.28100000000001,35.5707],"type":"Point"}
}