{
  "type": "Feature",
  "properties": {
    "gn:adm1_name":"Ehimeken",
    "gn:adm2_name":"Minamiuwagun'Ipponmatsuchou",
    "gn:name":"Koyama",
    "iso:country":"JP",
    "wof:name":"798-4403",
    "wof:placetype":"postalcode"
},
  "geometry": {"coordinates":[132.66569999999999,32.9593],"type":"Point"}
}