{
  "type": "Feature",
  "properties": {
    "gn:adm1_name":"Shigaken",
    "gn:adm2_name":"Ootsushi",
    "gn:name":"Nishinoshou",
    "iso:country":"JP",
    "wof:name":"520-0818",
    "wof:placetype":"postalcode"
},
  "geometry": {"coordinates":[135.88679999999999,35.0011],"type":"Point"}
}