{
  "type": "Feature",
  "properties": {
    "gn:adm1_name":"Ishikawaken",
    "gn:adm2_name":"Komatsushi",
    "gn:name":"Birugawamachi",
    "iso:country":"JP",
    "wof:name":"923-0011",
    "wof:placetype":"postalcode"
},
  "geometry": {"coordinates":[136.46119999999999,36.4311],"type":"Point"}
}