{
  "type": "Feature",
  "properties": {
    "gn:adm1_name":"Yamagataken",
    "gn:adm2_name":"Tsuruokashi",
    "gn:name":"Daibumachi",
    "iso:country":"JP",
    "wof:name":"997-0049",
    "wof:placetype":"postalcode"
},
  "geometry": {"coordinates":[139.81489999999999,38.7398],"type":"Point"}
}