{
  "type": "Feature",
  "properties": {
    "gn:adm1_name":"Toyamaken",
    "gn:adm2_name":"Toyamashi",
    "gn:name":"Shimizumotomachi",
    "iso:country":"JP",
    "wof:name":"930-0034",
    "wof:placetype":"postalcode"
},
  "geometry": {"coordinates":[137.23099999999999,36.6874],"type":"Point"}
}