{
  "type": "Feature",
  "properties": {
    "gn:adm1_name":"Ehimeken",
    "gn:adm2_name":"Matsuyamashi",
    "gn:name":"Sugitatemachi",
    "iso:country":"JP",
    "wof:name":"791-0105",
    "wof:placetype":"postalcode"
},
  "geometry": {"coordinates":[132.84469999999999,33.8621],"type":"Point"}
}