{
  "type": "Feature",
  "properties": {
    "gn:adm1_name":"Chibaken",
    "gn:adm2_name":"Kimitsushi",
    "gn:name":"Higashiinohara",
    "iso:country":"JP",
    "wof:name":"292-1161",
    "wof:placetype":"postalcode"
},
  "geometry": {"coordinates":[140.00620000000001,35.2577],"type":"Point"}
}