{
  "type": "Feature",
  "properties": {
    "gn:adm1_name":"Fukushimaken",
    "gn:adm2_name":"Dategunkunimimachi",
    "gn:name":"Nishiooeda",
    "iso:country":"JP",
    "wof:name":"969-1722",
    "wof:placetype":"postalcode"
},
  "geometry": {"coordinates":[140.5838,37.8774],"type":"Point"}
}