{
  "type": "Feature",
  "properties": {
    "gn:adm1_name":"Toyamaken",
    "gn:adm2_name":"Higashitonamigunshougawamachi",
    "gn:name":"Shou",
    "iso:country":"JP",
    "wof:name":"932-0302",
    "wof:placetype":"postalcode"
},
  "geometry": {"coordinates":[136.99700000000001,36.5948],"type":"Point"}
}