{
  "type": "Feature",
  "properties": {
    "gn:adm1_name":"Ehimeken",
    "gn:adm2_name":"Onsengunshigenobuchou",
    "gn:name":"Yamanouchi",
    "iso:country":"JP",
    "wof:name":"791-0201",
    "wof:placetype":"postalcode"
},
  "geometry": {"coordinates":[132.90960000000001,33.8498],"type":"Point"}
}