{
  "type": "Feature",
  "properties": {
    "gn:adm1_name":"Aichiken",
    "gn:adm2_name":"Okazakishi",
    "gn:name":"Miaishinmachi",
    "iso:country":"JP",
    "wof:name":"444-0801",
    "wof:placetype":"postalcode"
},
  "geometry": {"coordinates":[137.1994,34.9255],"type":"Point"}
}