{
  "type": "Feature",
  "properties": {
    "gn:adm1_name":"Tottoriken",
    "gn:adm2_name":"Sakaiminatoshi",
    "gn:name":"Hinodechou",
    "iso:country":"JP",
    "wof:name":"684-0024",
    "wof:placetype":"postalcode"
},
  "geometry": {"coordinates":[133.23050000000001,35.5448],"type":"Point"}
}