{
  "type": "Feature",
  "properties": {
    "gn:adm1_name":"Shizuokaken",
    "gn:adm2_name":"Tagatagunnirayamachou",
    "gn:name":"Chuujou",
    "iso:country":"JP",
    "wof:name":"410-2121",
    "wof:placetype":"postalcode"
},
  "geometry": {"coordinates":[138.94309999999999,35.0431],"type":"Point"}
}