{
  "type": "Feature",
  "properties": {
    "gn:adm1_name":"Chibaken",
    "gn:adm2_name":"Nodashi",
    "gn:name":"Higashihoushubana",
    "iso:country":"JP",
    "wof:name":"270-0226",
    "wof:placetype":"postalcode"
},
  "geometry": {"coordinates":[139.82089999999999,36.0261],"type":"Point"}
}