{
  "type": "Feature",
  "properties": {
    "gn:adm1_name":"Kyoutofu",
    "gn:adm2_name":"Kyoutoshiukyouku",
    "gn:name":"Umegahatakubotanichou",
    "iso:country":"JP",
    "wof:name":"616-8281",
    "wof:placetype":"postalcode"
},
  "geometry": {"coordinates":[135.6806,35.0476],"type":"Point"}
}