{
  "type": "Feature",
  "properties": {
    "gn:adm1_name":"Aichiken",
    "gn:adm2_name":"Komakishi",
    "gn:name":"Akebonochou",
    "iso:country":"JP",
    "wof:name":"485-0047",
    "wof:placetype":"postalcode"
},
  "geometry": {"coordinates":[136.9076,35.2931],"type":"Point"}
}