{
  "type": "Feature",
  "properties": {
    "gn:adm1_name":"Ishikawaken",
    "gn:adm2_name":"Kagashi",
    "gn:name":"Shoumachi",
    "iso:country":"JP",
    "wof:name":"922-0332",
    "wof:placetype":"postalcode"
},
  "geometry": {"coordinates":[136.37559999999999,36.3163],"type":"Point"}
}