{
  "type": "Feature",
  "properties": {
    "gn:adm1_name":"Oosakafu",
    "gn:adm2_name":"Kishiwadashi",
    "gn:name":"Isonokamichou",
    "iso:country":"JP",
    "wof:name":"596-0001",
    "wof:placetype":"postalcode"
},
  "geometry": {"coordinates":[135.3896,34.4884],"type":"Point"}
}