{
  "type": "Feature",
  "properties": {
    "gn:adm1_name":"Aichiken",
    "gn:adm2_name":"Toyotashi",
    "gn:name":"Shimobayashichou",
    "iso:country":"JP",
    "wof:name":"471-0878",
    "wof:placetype":"postalcode"
},
  "geometry": {"coordinates":[137.16239999999999,35.0696],"type":"Point"}
}