{
  "type": "Feature",
  "properties": {
    "gn:adm1_name":"Kouchiken",
    "gn:adm2_name":"Tosashimizushi",
    "gn:name":"Shimokawaguchi",
    "iso:country":"JP",
    "wof:name":"787-0559",
    "wof:placetype":"postalcode"
},
  "geometry": {"coordinates":[132.83969999999999,32.7849],"type":"Point"}
}