{
  "type": "Feature",
  "properties": {
    "gn:adm1_name":"Aichiken",
    "gn:adm2_name":"Toyohashishi",
    "gn:name":"Shinsakaechou",
    "iso:country":"JP",
    "wof:name":"441-8016",
    "wof:placetype":"postalcode"
},
  "geometry": {"coordinates":[137.3647,34.7653],"type":"Point"}
}