{
  "type": "Feature",
  "properties": {
    "gn:adm1_name":"Kyoutofu",
    "gn:adm2_name":"Kyoutoshinakagyouku",
    "gn:name":"Oikenochou",
    "iso:country":"JP",
    "wof:name":"604-0022",
    "wof:placetype":"postalcode"
},
  "geometry": {"coordinates":[135.75800000000001,35.0116],"type":"Point"}
}