{
  "type": "Feature",
  "properties": {
    "gn:adm1_name":"Aichiken",
    "gn:adm2_name":"Nagoyashimidoriku",
    "gn:name":"Narumichou(Hosone)",
    "iso:country":"JP",
    "wof:name":"458-0827",
    "wof:placetype":"postalcode"
},
  "geometry": {"coordinates":[136.9718,35.0714],"type":"Point"}
}