{
  "type": "Feature",
  "properties": {
    "gn:adm1_name":"Kagawaken",
    "gn:adm2_name":"Kagawagunshionoechou",
    "gn:name":"Kaminishikou",
    "iso:country":"JP",
    "wof:name":"761-1613",
    "wof:placetype":"postalcode"
},
  "geometry": {"coordinates":[134.0797,34.1335],"type":"Point"}
}