{
  "type": "Feature",
  "properties": {
    "gn:adm1_name":"Ishikawaken",
    "gn:adm2_name":"Kanazawashi",
    "gn:name":"Shimenonakamachi",
    "iso:country":"JP",
    "wof:name":"920-0058",
    "wof:placetype":"postalcode"
},
  "geometry": {"coordinates":[136.6165,36.5769],"type":"Point"}
}