{
  "type": "Feature",
  "properties": {
    "gn:adm1_name":"Tochigiken",
    "gn:adm2_name":"Utsunomiyashi",
    "gn:name":"Ekimaedoori",
    "iso:country":"JP",
    "wof:name":"321-0964",
    "wof:placetype":"postalcode"
},
  "geometry": {"coordinates":[139.89680000000001,36.5605],"type":"Point"}
}