{
  "type": "Feature",
  "properties": {
    "gn:adm1_name":"Gunmaken",
    "gn:adm2_name":"Annakashi",
    "gn:name":"Nishikamiakima",
    "iso:country":"JP",
    "wof:name":"379-0101",
    "wof:placetype":"postalcode"
},
  "geometry": {"coordinates":[138.83070000000001,36.3568],"type":"Point"}
}