{
  "type": "Feature",
  "properties": {
    "gn:adm1_name":"Naganoken",
    "gn:adm2_name":"Chiisagataguntakeshimura",
    "gn:name":"Shimohon'Iri",
    "iso:country":"JP",
    "wof:name":"386-0506",
    "wof:placetype":"postalcode"
},
  "geometry": {"coordinates":[138.20849999999999,36.2734],"type":"Point"}
}