{
  "type": "Feature",
  "properties": {
    "gn:adm1_name":"Toyamaken",
    "gn:adm2_name":"Kurobeshi",
    "gn:name":"Amidadou",
    "iso:country":"JP",
    "wof:name":"938-0824",
    "wof:placetype":"postalcode"
},
  "geometry": {"coordinates":[137.4803,36.8365],"type":"Point"}
}