{
  "type": "Feature",
  "properties": {
    "gn:adm1_name":"Kagawaken",
    "gn:adm2_name":"Takamatsushi",
    "gn:name":"Miyawakichou",
    "iso:country":"JP",
    "wof:name":"760-0005",
    "wof:placetype":"postalcode"
},
  "geometry": {"coordinates":[134.0359,34.3367],"type":"Point"}
}