{
  "type": "Feature",
  "properties": {
    "gn:adm1_name":"Kumamotoken",
    "gn:adm2_name":"Yatsushirogunryuuhokumachi",
    "gn:name":"Shimachi",
    "iso:country":"JP",
    "wof:name":"869-4814",
    "wof:placetype":"postalcode"
},
  "geometry": {"coordinates":[130.67310000000001,32.5814],"type":"Point"}
}