{
  "type": "Feature",
  "properties": {
    "gn:adm1_name":"Naganoken",
    "gn:adm2_name":"Shimoinagun'Achimura",
    "gn:name":"Kasuga",
    "iso:country":"JP",
    "wof:name":"395-0301",
    "wof:placetype":"postalcode"
},
  "geometry": {"coordinates":[137.7552,35.4516],"type":"Point"}
}