{
  "type": "Feature",
  "properties": {
    "gn:adm1_name":"Mieken",
    "gn:adm2_name":"Yokkaichishi",
    "gn:name":"Onoechou",
    "iso:country":"JP",
    "wof:name":"510-0059",
    "wof:placetype":"postalcode"
},
  "geometry": {"coordinates":[136.63390000000001,34.9602],"type":"Point"}
}