{
  "type": "Feature",
  "properties": {
    "gn:adm1_name":"Gifuken",
    "gn:adm2_name":"Tokishi",
    "gn:name":"Izuminakamorichou",
    "iso:country":"JP",
    "wof:name":"509-5106",
    "wof:placetype":"postalcode"
},
  "geometry": {"coordinates":[137.1874,35.3665],"type":"Point"}
}