{
  "type": "Feature",
  "properties": {
    "gn:adm1_name":"Niigataken",
    "gn:adm2_name":"Kitauonumagunhirokamimura",
    "gn:name":"Higashinaka",
    "iso:country":"JP",
    "wof:name":"946-0113",
    "wof:placetype":"postalcode"
},
  "geometry": {"coordinates":[138.96449999999999,37.2613],"type":"Point"}
}