{
  "type": "Feature",
  "properties": {
    "gn:adm1_name":"Kyoutofu",
    "gn:adm2_name":"Kyoutoshinakagyouku",
    "gn:name":"Nishinokyoushokushichou",
    "iso:country":"JP",
    "wof:name":"604-8381",
    "wof:placetype":"postalcode"
},
  "geometry": {"coordinates":[135.74469999999999,35.0111],"type":"Point"}
}