{
  "type": "Feature",
  "properties": {
    "gn:adm1_name":"Saitamaken",
    "gn:adm2_name":"Minamisaitamagunmiyashiromachi",
    "gn:name":"Monma",
    "iso:country":"JP",
    "wof:name":"345-0801",
    "wof:placetype":"postalcode"
},
  "geometry": {"coordinates":[139.72929999999999,36.0248],"type":"Point"}
}