{
  "type": "Feature",
  "properties": {
    "gn:adm1_name":"Aichiken",
    "gn:adm2_name":"Hekinanshi",
    "gn:name":"Shiotamachi",
    "iso:country":"JP",
    "wof:name":"447-0887",
    "wof:placetype":"postalcode"
},
  "geometry": {"coordinates":[136.99080000000001,34.874],"type":"Point"}
}