{
  "type": "Feature",
  "properties": {
    "gn:adm1_name":"Toyamaken",
    "gn:adm2_name":"Nakaniikawaguntateyamamachi",
    "gn:name":"Higashinakanoshin",
    "iso:country":"JP",
    "wof:name":"930-1365",
    "wof:placetype":"postalcode"
},
  "geometry": {"coordinates":[137.32749999999999,36.5952],"type":"Point"}
}