{
  "type": "Feature",
  "properties": {
    "gn:adm1_name":"Hyougoken",
    "gn:adm2_name":"Sandashi",
    "gn:name":"Ninji",
    "iso:country":"JP",
    "wof:name":"669-1505",
    "wof:placetype":"postalcode"
},
  "geometry": {"coordinates":[135.23509999999999,34.9312],"type":"Point"}
}