{
  "type": "Feature",
  "properties": {
    "gn:adm1_name":"Shigaken",
    "gn:adm2_name":"Gamougungamouchou",
    "gn:name":"Tera",
    "iso:country":"JP",
    "wof:name":"529-1504",
    "wof:placetype":"postalcode"
},
  "geometry": {"coordinates":[136.2518,35.0917],"type":"Point"}
}