{
  "type": "Feature",
  "properties": {
    "gn:adm1_name":"Gunmaken",
    "gn:adm2_name":"Maebashishi",
    "gn:name":"Kitashirotamachi",
    "iso:country":"JP",
    "wof:name":"371-0055",
    "wof:placetype":"postalcode"
},
  "geometry": {"coordinates":[139.0735,36.4115],"type":"Point"}
}