{
  "type": "Feature",
  "properties": {
    "gn:adm1_name":"Tottoriken",
    "gn:adm2_name":"Yonagoshi",
    "gn:name":"Teramachi",
    "iso:country":"JP",
    "wof:name":"683-0831",
    "wof:placetype":"postalcode"
},
  "geometry": {"coordinates":[133.32749999999999,35.4342],"type":"Point"}
}