{
  "type": "Feature",
  "properties": {
    "gn:adm1_name":"Kyoutofu",
    "gn:adm2_name":"Kyoutoshifushimiku",
    "gn:name":"Nishidaikokuchou",
    "iso:country":"JP",
    "wof:name":"612-8337",
    "wof:placetype":"postalcode"
},
  "geometry": {"coordinates":[135.75710000000001,34.9404],"type":"Point"}
}