{
  "type": "Feature",
  "properties": {
    "gn:adm1_name":"Mieken",
    "gn:adm2_name":"Yokkaichishi",
    "gn:name":"Akuragawachou",
    "iso:country":"JP",
    "wof:name":"510-0803",
    "wof:placetype":"postalcode"
},
  "geometry": {"coordinates":[136.62719999999999,34.9857],"type":"Point"}
}