{
  "type": "Feature",
  "properties": {
    "gn:adm1_name":"Chibaken",
    "gn:adm2_name":"Sakurashi",
    "gn:name":"Omotechou",
    "iso:country":"JP",
    "wof:name":"285-0811",
    "wof:placetype":"postalcode"
},
  "geometry": {"coordinates":[140.226,35.7109],"type":"Point"}
}