{
  "type": "Feature",
  "properties": {
    "gn:adm1_name":"Hyougoken",
    "gn:adm2_name":"Koubeshitarumiku",
    "gn:name":"Hoshigaoka",
    "iso:country":"JP",
    "wof:name":"655-0032",
    "wof:placetype":"postalcode"
},
  "geometry": {"coordinates":[135.04849999999999,34.6404],"type":"Point"}
}