{
  "type": "Feature",
  "properties": {
    "gn:adm1_name":"Fukuiken",
    "gn:adm2_name":"Fukuishi",
    "gn:name":"Nishibesshochou",
    "iso:country":"JP",
    "wof:name":"910-3512",
    "wof:placetype":"postalcode"
},
  "geometry": {"coordinates":[136.06530000000001,36.0303],"type":"Point"}
}