{
  "type": "Feature",
  "properties": {
    "gn:adm1_name":"Shigaken",
    "gn:adm2_name":"Ootsushi",
    "gn:name":"Shouyou",
    "iso:country":"JP",
    "wof:name":"520-2135",
    "wof:placetype":"postalcode"
},
  "geometry": {"coordinates":[135.91900000000001,34.9644],"type":"Point"}
}