{
  "type": "Feature",
  "properties": {
    "gn:adm1_name":"Mieken",
    "gn:adm2_name":"Ayamagun'Ayamachou",
    "gn:name":"Segai",
    "iso:country":"JP",
    "wof:name":"518-1319",
    "wof:placetype":"postalcode"
},
  "geometry": {"coordinates":[136.16919999999999,34.8328],"type":"Point"}
}