{
  "type": "Feature",
  "properties": {
    "gn:adm1_name":"Hyougoken",
    "gn:adm2_name":"Takaradukashi",
    "gn:name":"Yamamotodai",
    "iso:country":"JP",
    "wof:name":"665-0885",
    "wof:placetype":"postalcode"
},
  "geometry": {"coordinates":[135.3793,34.8242],"type":"Point"}
}