{
  "type": "Feature",
  "properties": {
    "gn:adm1_name":"Fukushimaken",
    "gn:adm2_name":"Fukushimashi",
    "gn:name":"Kanayagawa",
    "iso:country":"JP",
    "wof:name":"960-1248",
    "wof:placetype":"postalcode"
},
  "geometry": {"coordinates":[140.45590000000001,37.6837],"type":"Point"}
}