{
  "type": "Feature",
  "properties": {
    "gn:adm1_name":"Miyagiken",
    "gn:adm2_name":"Monougunnarusechou",
    "gn:name":"Jougetsutsumi",
    "iso:country":"JP",
    "wof:name":"981-0305",
    "wof:placetype":"postalcode"
},
  "geometry": {"coordinates":[141.11369999999999,38.4082],"type":"Point"}
}