{
  "type": "Feature",
  "properties": {
    "gn:adm1_name":"Gifuken",
    "gn:adm2_name":"Gujougunmeihoumura",
    "gn:name":"Ootani",
    "iso:country":"JP",
    "wof:name":"501-4301",
    "wof:placetype":"postalcode"
},
  "geometry": {"coordinates":[137.0273,35.8452],"type":"Point"}
}