{
  "type": "Feature",
  "properties": {
    "gn:adm1_name":"Hiroshimaken",
    "gn:adm2_name":"Hiroshimashinakaku",
    "gn:name":"Ebasakaemachi",
    "iso:country":"JP",
    "wof:name":"730-0836",
    "wof:placetype":"postalcode"
},
  "geometry": {"coordinates":[132.42869999999999,34.3652],"type":"Point"}
}