{
  "type": "Feature",
  "properties": {
    "gn:adm1_name":"Wakayamaken",
    "gn:adm2_name":"Higashimurogunkozagawachou",
    "gn:name":"Tachiai",
    "iso:country":"JP",
    "wof:name":"649-4233",
    "wof:placetype":"postalcode"
},
  "geometry": {"coordinates":[135.7296,33.5368],"type":"Point"}
}