{
  "type": "Feature",
  "properties": {
    "gn:adm1_name":"Shizuokaken",
    "gn:adm2_name":"Shizuokashi",
    "gn:name":"Shimizuhanzaemonshinden",
    "iso:country":"JP",
    "wof:name":"424-0056",
    "wof:placetype":"postalcode"
},
  "geometry": {"coordinates":[138.45310000000001,35.0157],"type":"Point"}
}