{
  "type": "Feature",
  "properties": {
    "gn:adm1_name":"Wakayamaken",
    "gn:adm2_name":"Nagagunmomoyamachou",
    "gn:name":"Mogami",
    "iso:country":"JP",
    "wof:name":"649-6111",
    "wof:placetype":"postalcode"
},
  "geometry": {"coordinates":[135.35599999999999,34.2098],"type":"Point"}
}