{
  "type": "Feature",
  "properties": {
    "gn:adm1_name":"Mieken",
    "gn:adm2_name":"Matsusakashi",
    "gn:name":"Kawaimachi",
    "iso:country":"JP",
    "wof:name":"515-0818",
    "wof:placetype":"postalcode"
},
  "geometry": {"coordinates":[136.51949999999999,34.582],"type":"Point"}
}