{
  "type": "Feature",
  "properties": {
    "gn:adm1_name":"Fukuiken",
    "gn:adm2_name":"Fukuishi",
    "gn:name":"Hanandouminami",
    "iso:country":"JP",
    "wof:name":"918-8015",
    "wof:placetype":"postalcode"
},
  "geometry": {"coordinates":[136.2124,36.0342],"type":"Point"}
}