{
  "type": "Feature",
  "properties": {
    "gn:adm1_name":"Naganoken",
    "gn:adm2_name":"Matsumotoshi",
    "gn:name":"Sawamura",
    "iso:country":"JP",
    "wof:name":"390-0877",
    "wof:placetype":"postalcode"
},
  "geometry": {"coordinates":[137.9691,36.2504],"type":"Point"}
}