{
  "type": "Feature",
  "properties": {
    "gn:adm1_name":"Oosakafu",
    "gn:adm2_name":"Minamikawachigunkananchou",
    "gn:name":"Shimokawachi",
    "iso:country":"JP",
    "wof:name":"585-0023",
    "wof:placetype":"postalcode"
},
  "geometry": {"coordinates":[135.6506,34.4708],"type":"Point"}
}