{
  "type": "Feature",
  "properties": {
    "gn:adm1_name":"Ishikawaken",
    "gn:adm2_name":"Hakuigunshikamachi",
    "gn:name":"Kawashiri",
    "iso:country":"JP",
    "wof:name":"925-0168",
    "wof:placetype":"postalcode"
},
  "geometry": {"coordinates":[136.76689999999999,37.0068],"type":"Point"}
}