{
  "type": "Feature",
  "properties": {
    "gn:adm1_name":"Ehimeken",
    "gn:adm2_name":"Imabarishi",
    "gn:name":"Yamaji",
    "iso:country":"JP",
    "wof:name":"794-0072",
    "wof:placetype":"postalcode"
},
  "geometry": {"coordinates":[132.9761,34.0603],"type":"Point"}
}