{
  "type": "Feature",
  "properties": {
    "gn:adm1_name":"Fukuiken",
    "gn:adm2_name":"Fukuishi",
    "gn:name":"Wadanakachou",
    "iso:country":"JP",
    "wof:name":"918-8235",
    "wof:placetype":"postalcode"
},
  "geometry": {"coordinates":[136.25149999999999,36.0437],"type":"Point"}
}