{
  "type": "Feature",
  "properties": {
    "gn:adm1_name":"Tottoriken",
    "gn:adm2_name":"Yonagoshi",
    "gn:name":"Atagochou",
    "iso:country":"JP",
    "wof:name":"683-0046",
    "wof:placetype":"postalcode"
},
  "geometry": {"coordinates":[133.32990000000001,35.4212],"type":"Point"}
}