{
  "type": "Feature",
  "properties": {
    "gn:adm1_name":"Okayamaken",
    "gn:adm2_name":"Tsukubogunhayashimachou",
    "gn:name":"Ikanikeisaiganaibaai",
    "iso:country":"JP",
    "wof:name":"701-0300",
    "wof:placetype":"postalcode"
},
  "geometry": {"coordinates":[133.8304,34.6156],"type":"Point"}
}