{
  "type": "Feature",
  "properties": {
    "gn:adm1_name":"Toukyouto",
    "gn:adm2_name":"Setagayaku",
    "gn:name":"Sangendiyaya",
    "iso:country":"JP",
    "wof:name":"154-0024",
    "wof:placetype":"postalcode"
},
  "geometry": {"coordinates":[139.6688,35.6417],"type":"Point"}
}