{
  "type": "Feature",
  "properties": {
    "gn:adm1_name":"Sagaken",
    "gn:adm2_name":"Imarishi",
    "gn:name":"Ookawachoukomanaki",
    "iso:country":"JP",
    "wof:name":"849-5253",
    "wof:placetype":"postalcode"
},
  "geometry": {"coordinates":[129.96889999999999,33.324],"type":"Point"}
}