{
  "type": "Feature",
  "properties": {
    "gn:adm1_name":"Aichiken",
    "gn:adm2_name":"Setoshi",
    "gn:name":"Higashihonmachi",
    "iso:country":"JP",
    "wof:name":"489-0816",
    "wof:placetype":"postalcode"
},
  "geometry": {"coordinates":[137.10290000000001,35.2237],"type":"Point"}
}