{
  "type": "Feature",
  "properties": {
    "gn:adm1_name":"Ehimeken",
    "gn:adm2_name":"Ochigunkikumachou",
    "gn:name":"Kawanouchi",
    "iso:country":"JP",
    "wof:name":"799-2306",
    "wof:placetype":"postalcode"
},
  "geometry": {"coordinates":[132.88040000000001,34.0134],"type":"Point"}
}