{
  "type": "Feature",
  "properties": {
    "gn:adm1_name":"Mieken",
    "gn:adm2_name":"Kameyamashi",
    "gn:name":"Egamuro",
    "iso:country":"JP",
    "wof:name":"519-0121",
    "wof:placetype":"postalcode"
},
  "geometry": {"coordinates":[136.45480000000001,34.8567],"type":"Point"}
}