{
  "type": "Feature",
  "properties": {
    "gn:adm1_name":"Yamanashiken",
    "gn:adm2_name":"Higashiyatsushirogunsakaigawamura",
    "gn:name":"Maemada",
    "iso:country":"JP",
    "wof:name":"406-0843",
    "wof:placetype":"postalcode"
},
  "geometry": {"coordinates":[138.62960000000001,35.6037],"type":"Point"}
}