{
  "type": "Feature",
  "properties": {
    "gn:adm1_name":"Nagasakiken",
    "gn:adm2_name":"Kitatakakigunkonagaichou",
    "gn:name":"Uchikoshimyou",
    "iso:country":"JP",
    "wof:name":"859-0151",
    "wof:placetype":"postalcode"
},
  "geometry": {"coordinates":[130.16390000000001,32.9231],"type":"Point"}
}