{
  "type": "Feature",
  "properties": {
    "gn:adm1_name":"Mieken",
    "gn:adm2_name":"Kuwanashi",
    "gn:name":"Motoakasuka",
    "iso:country":"JP",
    "wof:name":"511-0037",
    "wof:placetype":"postalcode"
},
  "geometry": {"coordinates":[136.69999999999999,35.0611],"type":"Point"}
}