{
  "type": "Feature",
  "properties": {
    "gn:adm1_name":"Okinawaken",
    "gn:adm2_name":"Kunigamigunkunigamison",
    "gn:name":"Ura",
    "iso:country":"JP",
    "wof:name":"905-1429",
    "wof:placetype":"postalcode"
},
  "geometry": {"coordinates":[128.18989999999999,26.7527],"type":"Point"}
}