{
  "type": "Feature",
  "properties": {
    "gn:adm1_name":"Miyagiken",
    "gn:adm2_name":"Kesennumashi",
    "gn:name":"Oobayashi",
    "iso:country":"JP",
    "wof:name":"988-0821",
    "wof:placetype":"postalcode"
},
  "geometry": {"coordinates":[141.53639999999999,38.9122],"type":"Point"}
}