{
  "type": "Feature",
  "properties": {
    "gn:adm1_name":"Fukushimaken",
    "gn:adm2_name":"Kooriyamashi",
    "gn:name":"Konanmachimiyo",
    "iso:country":"JP",
    "wof:name":"963-1522",
    "wof:placetype":"postalcode"
},
  "geometry": {"coordinates":[140.11529999999999,37.376],"type":"Point"}
}