{
  "type": "Feature",
  "properties": {
    "gn:adm1_name":"Aichiken",
    "gn:adm2_name":"Nagoyashinakamuraku",
    "gn:name":"Nagono",
    "iso:country":"JP",
    "wof:name":"450-0001",
    "wof:placetype":"postalcode"
},
  "geometry": {"coordinates":[136.89089999999999,35.173],"type":"Point"}
}