{
  "type": "Feature",
  "properties": {
    "gn:adm1_name":"Fukushimaken",
    "gn:adm2_name":"Tamuragun'Onomachi",
    "gn:name":"Ikanikeisaiganaibaai",
    "iso:country":"JP",
    "wof:name":"963-3400",
    "wof:placetype":"postalcode"
},
  "geometry": {"coordinates":[140.6191,37.2514],"type":"Point"}
}