{
  "type": "Feature",
  "properties": {
    "gn:adm1_name":"Kagawaken",
    "gn:adm2_name":"Kan'Onjishi",
    "gn:name":"Sakamotochou",
    "iso:country":"JP",
    "wof:name":"768-0067",
    "wof:placetype":"postalcode"
},
  "geometry": {"coordinates":[133.66139999999999,34.1253],"type":"Point"}
}