{
  "type": "Feature",
  "properties": {
    "gn:adm1_name":"Gunmaken",
    "gn:adm2_name":"Ootashi",
    "gn:name":"Motegichou",
    "iso:country":"JP",
    "wof:name":"373-0809",
    "wof:placetype":"postalcode"
},
  "geometry": {"coordinates":[139.4117,36.2977],"type":"Point"}
}