{
  "type": "Feature",
  "properties": {
    "gn:adm1_name":"Hyougoken",
    "gn:adm2_name":"Amagasakishi",
    "gn:name":"Mukonosouhonmachi",
    "iso:country":"JP",
    "wof:name":"661-0031",
    "wof:placetype":"postalcode"
},
  "geometry": {"coordinates":[135.3947,34.7592],"type":"Point"}
}