{
  "type": "Feature",
  "properties": {
    "gn:adm1_name":"Mieken",
    "gn:adm2_name":"Yokkaichishi",
    "gn:name":"Kawaichou",
    "iso:country":"JP",
    "wof:name":"510-0853",
    "wof:placetype":"postalcode"
},
  "geometry": {"coordinates":[136.62520000000001,34.9282],"type":"Point"}
}