{
  "type": "Feature",
  "properties": {
    "gn:adm1_name":"Fukuokaken",
    "gn:adm2_name":"Chikushinoshi",
    "gn:name":"Amayama",
    "iso:country":"JP",
    "wof:name":"818-0012",
    "wof:placetype":"postalcode"
},
  "geometry": {"coordinates":[130.55799999999999,33.4797],"type":"Point"}
}