{
  "type": "Feature",
  "properties": {
    "gn:adm1_name":"Wakayamaken",
    "gn:adm2_name":"Wakayamashi",
    "gn:name":"Ido",
    "iso:country":"JP",
    "wof:name":"640-0352",
    "wof:placetype":"postalcode"
},
  "geometry": {"coordinates":[135.22790000000001,34.197],"type":"Point"}
}