{
  "type": "Feature",
  "properties": {
    "gn:adm1_name":"Shizuokaken",
    "gn:adm2_name":"Haibaragunkawanechou",
    "gn:name":"Sasamado",
    "iso:country":"JP",
    "wof:name":"428-0101",
    "wof:placetype":"postalcode"
},
  "geometry": {"coordinates":[138.09020000000001,34.9619],"type":"Point"}
}