{
  "type": "Feature",
  "properties": {
    "gn:adm1_name":"Okayamaken",
    "gn:adm2_name":"Okayamashi",
    "gn:name":"Chuuouchou",
    "iso:country":"JP",
    "wof:name":"700-0836",
    "wof:placetype":"postalcode"
},
  "geometry": {"coordinates":[133.92490000000001,34.6575],"type":"Point"}
}