{
  "type": "Feature",
  "properties": {
    "gn:adm1_name":"Kyoutofu",
    "gn:adm2_name":"Kyoutoshisakyouku",
    "gn:name":"Kitashirakawatsutachou",
    "iso:country":"JP",
    "wof:name":"606-8262",
    "wof:placetype":"postalcode"
},
  "geometry": {"coordinates":[135.78729999999999,35.0338],"type":"Point"}
}