{
  "type": "Feature",
  "properties": {
    "gn:adm1_name":"Shigaken",
    "gn:adm2_name":"Ootsushi",
    "gn:name":"Ogoto",
    "iso:country":"JP",
    "wof:name":"520-0101",
    "wof:placetype":"postalcode"
},
  "geometry": {"coordinates":[135.89920000000001,35.0936],"type":"Point"}
}