{
  "type": "Feature",
  "properties": {
    "gn:adm1_name":"Niigataken",
    "gn:adm2_name":"Santougunmishimamachi",
    "gn:name":"Fujikawa",
    "iso:country":"JP",
    "wof:name":"940-2302",
    "wof:placetype":"postalcode"
},
  "geometry": {"coordinates":[138.78989999999999,37.509],"type":"Point"}
}