{
  "type": "Feature",
  "properties": {
    "gn:adm1_name":"Aichiken",
    "gn:adm2_name":"Takahamashi",
    "gn:name":"Hongouchou",
    "iso:country":"JP",
    "wof:name":"444-1311",
    "wof:placetype":"postalcode"
},
  "geometry": {"coordinates":[137.0042,34.9302],"type":"Point"}
}