{
  "type": "Feature",
  "properties": {
    "gn:adm1_name":"Ibarakiken",
    "gn:adm2_name":"Tsuchiurashi",
    "gn:name":"Sakuramachi",
    "iso:country":"JP",
    "wof:name":"300-0037",
    "wof:placetype":"postalcode"
},
  "geometry": {"coordinates":[140.20060000000001,36.0783],"type":"Point"}
}