{
  "type": "Feature",
  "properties": {
    "gn:adm1_name":"Shizuokaken",
    "gn:adm2_name":"Hamamatsushi",
    "gn:name":"Kamigayachou",
    "iso:country":"JP",
    "wof:name":"432-8005",
    "wof:placetype":"postalcode"
},
  "geometry": {"coordinates":[137.6773,34.7254],"type":"Point"}
}