{
  "type": "Feature",
  "properties": {
    "gn:adm1_name":"Nagasakiken",
    "gn:adm2_name":"Nishisonogigunnagayochou",
    "gn:name":"Yoshimutagou",
    "iso:country":"JP",
    "wof:name":"851-2126",
    "wof:placetype":"postalcode"
},
  "geometry": {"coordinates":[129.8802,32.8167],"type":"Point"}
}