{
  "type": "Feature",
  "properties": {
    "gn:adm1_name":"Kumamotoken",
    "gn:adm2_name":"Yatsushiroguntouyoumura",
    "gn:name":"Kita",
    "iso:country":"JP",
    "wof:name":"869-4302",
    "wof:placetype":"postalcode"
},
  "geometry": {"coordinates":[130.7362,32.5452],"type":"Point"}
}