{
  "type": "Feature",
  "properties": {
    "gn:adm1_name":"Gifuken",
    "gn:adm2_name":"Gifushi",
    "gn:name":"Hibarichou",
    "iso:country":"JP",
    "wof:name":"500-8877",
    "wof:placetype":"postalcode"
},
  "geometry": {"coordinates":[136.75460000000001,35.4186],"type":"Point"}
}