{
  "type": "Feature",
  "properties": {
    "gn:adm1_name":"Mieken",
    "gn:adm2_name":"Takigunmeiwachou",
    "gn:name":"Youkawa",
    "iso:country":"JP",
    "wof:name":"515-0344",
    "wof:placetype":"postalcode"
},
  "geometry": {"coordinates":[136.62639999999999,34.5776],"type":"Point"}
}