{
  "type": "Feature",
  "properties": {
    "gn:adm1_name":"Aichiken",
    "gn:adm2_name":"Chitaguntaketoyochou",
    "gn:name":"Nakane",
    "iso:country":"JP",
    "wof:name":"470-2334",
    "wof:placetype":"postalcode"
},
  "geometry": {"coordinates":[136.91069999999999,34.8537],"type":"Point"}
}