{
  "type": "Feature",
  "properties": {
    "gn:adm1_name":"Chibaken",
    "gn:adm2_name":"Katorigunkouzakimachi",
    "gn:name":"Koori",
    "iso:country":"JP",
    "wof:name":"289-0202",
    "wof:placetype":"postalcode"
},
  "geometry": {"coordinates":[140.4135,35.894],"type":"Point"}
}