{
  "type": "Feature",
  "properties": {
    "gn:adm1_name":"Yamaguchiken",
    "gn:adm2_name":"Onodashi",
    "gn:name":"Minatomachi",
    "iso:country":"JP",
    "wof:name":"756-0834",
    "wof:placetype":"postalcode"
},
  "geometry": {"coordinates":[131.17660000000001,33.9742],"type":"Point"}
}