{
  "type": "Feature",
  "properties": {
    "gn:adm1_name":"Ooitaken",
    "gn:adm2_name":"Ooitashi",
    "gn:name":"Soudakitamachi",
    "iso:country":"JP",
    "wof:name":"870-1138",
    "wof:placetype":"postalcode"
},
  "geometry": {"coordinates":[131.608,33.1897],"type":"Point"}
}