{
  "type": "Feature",
  "properties": {
    "gn:adm1_name":"Naganoken",
    "gn:adm2_name":"Kamiminochigunnakajoumura",
    "gn:name":"Hidaka",
    "iso:country":"JP",
    "wof:name":"381-3201",
    "wof:placetype":"postalcode"
},
  "geometry": {"coordinates":[138.05000000000001,36.6074],"type":"Point"}
}