{
  "type": "Feature",
  "properties": {
    "gn:adm1_name":"Hyougoken",
    "gn:adm2_name":"Akoushi",
    "gn:name":"Isohamachou",
    "iso:country":"JP",
    "wof:name":"678-0250",
    "wof:placetype":"postalcode"
},
  "geometry": {"coordinates":[134.37440000000001,34.7587],"type":"Point"}
}