{
  "type": "Feature",
  "properties": {
    "gn:adm1_name":"Saitamaken",
    "gn:adm2_name":"Kounosushi",
    "gn:name":"Miyamae",
    "iso:country":"JP",
    "wof:name":"365-0051",
    "wof:placetype":"postalcode"
},
  "geometry": {"coordinates":[139.49289999999999,36.0706],"type":"Point"}
}