{
  "type": "Feature",
  "properties": {
    "gn:adm1_name":"Mieken",
    "gn:adm2_name":"Kuwanashi",
    "gn:name":"Izumi",
    "iso:country":"JP",
    "wof:name":"511-0838",
    "wof:placetype":"postalcode"
},
  "geometry": {"coordinates":[136.68539999999999,35.0432],"type":"Point"}
}