{
  "type": "Feature",
  "properties": {
    "gn:adm1_name":"Kyoutofu",
    "gn:adm2_name":"Kameokashi",
    "gn:name":"Kitakosechou",
    "iso:country":"JP",
    "wof:name":"621-0811",
    "wof:placetype":"postalcode"
},
  "geometry": {"coordinates":[135.58590000000001,35.0119],"type":"Point"}
}