{
  "type": "Feature",
  "properties": {
    "gn:adm1_name":"Gunmaken",
    "gn:adm2_name":"Agatsumaguntakayamamura",
    "gn:name":"Shittaka",
    "iso:country":"JP",
    "wof:name":"377-0701",
    "wof:placetype":"postalcode"
},
  "geometry": {"coordinates":[138.90979999999999,36.6224],"type":"Point"}
}