{
  "type": "Feature",
  "properties": {
    "gn:adm1_name":"Aichiken",
    "gn:adm2_name":"Anjoushi",
    "gn:name":"Furuichou",
    "iso:country":"JP",
    "wof:name":"446-0025",
    "wof:placetype":"postalcode"
},
  "geometry": {"coordinates":[137.09200000000001,34.9349],"type":"Point"}
}