{
  "type": "Feature",
  "properties": {
    "gn:adm1_name":"Kanagawaken",
    "gn:adm2_name":"Yokohamashiaobaku",
    "gn:name":"Utsukushigaoka",
    "iso:country":"JP",
    "wof:name":"225-0002",
    "wof:placetype":"postalcode"
},
  "geometry": {"coordinates":[139.55500000000001,35.5794],"type":"Point"}
}