{
  "type": "Feature",
  "properties": {
    "gn:adm1_name":"Oosakafu",
    "gn:adm2_name":"Izumisanoshi",
    "gn:name":"Matsubara",
    "iso:country":"JP",
    "wof:name":"598-0045",
    "wof:placetype":"postalcode"
},
  "geometry": {"coordinates":[135.30260000000001,34.4052],"type":"Point"}
}