{
  "type": "Feature",
  "properties": {
    "gn:adm1_name":"Saitamaken",
    "gn:adm2_name":"Satteshi",
    "gn:name":"Endouuchi",
    "iso:country":"JP",
    "wof:name":"340-0104",
    "wof:placetype":"postalcode"
},
  "geometry": {"coordinates":[139.7107,36.0913],"type":"Point"}
}