{
  "type": "Feature",
  "properties": {
    "gn:adm1_name":"Ishikawaken",
    "gn:adm2_name":"Kanazawashi",
    "gn:name":"Fushimidai",
    "iso:country":"JP",
    "wof:name":"921-8177",
    "wof:placetype":"postalcode"
},
  "geometry": {"coordinates":[136.6378,36.5335],"type":"Point"}
}