{
  "type": "Feature",
  "properties": {
    "gn:adm1_name":"Hyougoken",
    "gn:adm2_name":"Kawabegun'Inagawachou",
    "gn:name":"Sashikumi",
    "iso:country":"JP",
    "wof:name":"666-0253",
    "wof:placetype":"postalcode"
},
  "geometry": {"coordinates":[135.3776,34.8816],"type":"Point"}
}