{
  "type": "Feature",
  "properties": {
    "gn:adm1_name":"Oosakafu",
    "gn:adm2_name":"Toyonogunnosechou",
    "gn:name":"Jiou",
    "iso:country":"JP",
    "wof:name":"563-0121",
    "wof:placetype":"postalcode"
},
  "geometry": {"coordinates":[135.4598,34.9561],"type":"Point"}
}