{
  "type": "Feature",
  "properties": {
    "gn:adm1_name":"Ehimeken",
    "gn:adm2_name":"Iyomishimashi",
    "gn:name":"Kinshachouhiranoyama",
    "iso:country":"JP",
    "wof:name":"799-0642",
    "wof:placetype":"postalcode"
},
  "geometry": {"coordinates":[133.5275,33.9279],"type":"Point"}
}