{
  "type": "Feature",
  "properties": {
    "gn:adm1_name":"Chibaken",
    "gn:adm2_name":"Kimitsushi",
    "gn:name":"Kaefuchi",
    "iso:country":"JP",
    "wof:name":"292-0404",
    "wof:placetype":"postalcode"
},
  "geometry": {"coordinates":[140.04929999999999,35.3277],"type":"Point"}
}