{
  "type": "Feature",
  "properties": {
    "gn:adm1_name":"Yamaguchiken",
    "gn:adm2_name":"Shimonosekishi",
    "gn:name":"Kiyosuehonmachi",
    "iso:country":"JP",
    "wof:name":"750-1154",
    "wof:placetype":"postalcode"
},
  "geometry": {"coordinates":[131.02260000000001,34.06],"type":"Point"}
}