{
  "type": "Feature",
  "properties": {
    "gn:adm1_name":"Kyoutofu",
    "gn:adm2_name":"Kyoutoshifushimiku",
    "gn:name":"Shimotobaserikawachou",
    "iso:country":"JP",
    "wof:name":"612-8391",
    "wof:placetype":"postalcode"
},
  "geometry": {"coordinates":[135.7569,34.946],"type":"Point"}
}