{
  "type": "Feature",
  "properties": {
    "gn:adm1_name":"Saitamaken",
    "gn:adm2_name":"Kitakatsushikagunwashimiyamachi",
    "gn:name":"Washimiya",
    "iso:country":"JP",
    "wof:name":"340-0217",
    "wof:placetype":"postalcode"
},
  "geometry": {"coordinates":[139.66380000000001,36.0993],"type":"Point"}
}