{
  "type": "Feature",
  "properties": {
    "gn:adm1_name":"Fukushimaken",
    "gn:adm2_name":"Adachigun'Adachimachi",
    "gn:name":"Yonazawa",
    "iso:country":"JP",
    "wof:name":"969-1402",
    "wof:placetype":"postalcode"
},
  "geometry": {"coordinates":[140.43369999999999,37.5858],"type":"Point"}
}