{
  "type": "Feature",
  "properties": {
    "gn:adm1_name":"Mieken",
    "gn:adm2_name":"Kuwanaguntadochou",
    "gn:name":"Yui",
    "iso:country":"JP",
    "wof:name":"511-0101",
    "wof:placetype":"postalcode"
},
  "geometry": {"coordinates":[136.6388,35.1394],"type":"Point"}
}