{
  "type": "Feature",
  "properties": {
    "gn:adm1_name":"Toyamaken",
    "gn:adm2_name":"Higashitonamigun'Inamimachi",
    "gn:name":"Jikuya",
    "iso:country":"JP",
    "wof:name":"932-0205",
    "wof:placetype":"postalcode"
},
  "geometry": {"coordinates":[136.9443,36.5855],"type":"Point"}
}