{
  "type": "Feature",
  "properties": {
    "gn:adm1_name":"Shizuokaken",
    "gn:adm2_name":"Numadushi",
    "gn:name":"Numakitachou",
    "iso:country":"JP",
    "wof:name":"410-0058",
    "wof:placetype":"postalcode"
},
  "geometry": {"coordinates":[138.85339999999999,35.1143],"type":"Point"}
}