{
  "type": "Feature",
  "properties": {
    "gn:adm1_name":"Ibarakiken",
    "gn:adm2_name":"Hitachishi",
    "gn:name":"Takasuzuchou",
    "iso:country":"JP",
    "wof:name":"317-0066",
    "wof:placetype":"postalcode"
},
  "geometry": {"coordinates":[140.6446,36.6044],"type":"Point"}
}