{
  "type": "Feature",
  "properties": {
    "gn:adm1_name":"Saitamaken",
    "gn:adm2_name":"Koshigayashi",
    "gn:name":"Sengendaihigashi",
    "iso:country":"JP",
    "wof:name":"343-0042",
    "wof:placetype":"postalcode"
},
  "geometry": {"coordinates":[139.77860000000001,35.9344],"type":"Point"}
}