{
  "type": "Feature",
  "properties": {
    "gn:adm1_name":"Kumamotoken",
    "gn:adm2_name":"Kamotogun'Uekimachi",
    "gn:name":"Tomiou",
    "iso:country":"JP",
    "wof:name":"861-0162",
    "wof:placetype":"postalcode"
},
  "geometry": {"coordinates":[130.66999999999999,32.9105],"type":"Point"}
}