{
  "type": "Feature",
  "properties": {
    "gn:adm1_name":"Saitamaken",
    "gn:adm2_name":"Oosatogunyoriimachi",
    "gn:name":"Fuubu",
    "iso:country":"JP",
    "wof:name":"369-1235",
    "wof:placetype":"postalcode"
},
  "geometry": {"coordinates":[139.1489,36.1036],"type":"Point"}
}