{
  "type": "Feature",
  "properties": {
    "gn:adm1_name":"Saitamaken",
    "gn:adm2_name":"Saitamashichuuouku",
    "gn:name":"Sakuraoka",
    "iso:country":"JP",
    "wof:name":"338-0005",
    "wof:placetype":"postalcode"
},
  "geometry": {"coordinates":[139.61529999999999,35.88],"type":"Point"}
}