{
  "type": "Feature",
  "properties": {
    "gn:adm1_name":"Kumamotoken",
    "gn:adm2_name":"Hitoyoshishi",
    "gn:name":"Minonomachi",
    "iso:country":"JP",
    "wof:name":"868-0061",
    "wof:placetype":"postalcode"
},
  "geometry": {"coordinates":[130.76779999999999,32.1857],"type":"Point"}
}