{
  "type": "Feature",
  "properties": {
    "gn:adm1_name":"Oosakafu",
    "gn:adm2_name":"Shijounawateshi",
    "gn:name":"Tsukawakichou",
    "iso:country":"JP",
    "wof:name":"575-0024",
    "wof:placetype":"postalcode"
},
  "geometry": {"coordinates":[135.64160000000001,34.736],"type":"Point"}
}