{
  "type": "Feature",
  "properties": {
    "gn:adm1_name":"Kyoutofu",
    "gn:adm2_name":"Kyoutoshiukyouku",
    "gn:name":"Nishikyougokuhashiagarichou",
    "iso:country":"JP",
    "wof:name":"615-0832",
    "wof:placetype":"postalcode"
},
  "geometry": {"coordinates":[135.7166,34.985],"type":"Point"}
}