{
  "type": "Feature",
  "properties": {
    "gn:adm1_name":"Kanagawaken",
    "gn:adm2_name":"Ashigarashimogunhakonemachi",
    "gn:name":"Miyagino",
    "iso:country":"JP",
    "wof:name":"250-0401",
    "wof:placetype":"postalcode"
},
  "geometry": {"coordinates":[139.05029999999999,35.2555],"type":"Point"}
}