{
  "type": "Feature",
  "properties": {
    "gn:adm1_name":"Kanagawaken",
    "gn:adm2_name":"Hiratsukashi",
    "gn:name":"Idenawa",
    "iso:country":"JP",
    "wof:name":"254-0915",
    "wof:placetype":"postalcode"
},
  "geometry": {"coordinates":[139.3022,35.3313],"type":"Point"}
}