{
  "type": "Feature",
  "properties": {
    "gn:adm1_name":"Hiroshimaken",
    "gn:adm2_name":"Kureshi",
    "gn:name":"Hiroooshingai",
    "iso:country":"JP",
    "wof:name":"737-0141",
    "wof:placetype":"postalcode"
},
  "geometry": {"coordinates":[132.626,34.2341],"type":"Point"}
}