{
  "type": "Feature",
  "properties": {
    "gn:adm1_name":"Hyougoken",
    "gn:adm2_name":"Tsunagungoshikichou",
    "gn:name":"Hiroishinaka",
    "iso:country":"JP",
    "wof:name":"656-1334",
    "wof:placetype":"postalcode"
},
  "geometry": {"coordinates":[134.80009999999999,34.3725],"type":"Point"}
}