{
  "type": "Feature",
  "properties": {
    "gn:adm1_name":"Okinawaken",
    "gn:adm2_name":"Yaeyamaguntaketomichou",
    "gn:name":"Komi",
    "iso:country":"JP",
    "wof:name":"907-1432",
    "wof:placetype":"postalcode"
},
  "geometry": {"coordinates":[123.9098,24.3229],"type":"Point"}
}