{
  "type": "Feature",
  "properties": {
    "gn:adm1_name":"Kyoutofu",
    "gn:adm2_name":"Fukuchiyamashi",
    "gn:name":"Iwaihigashimachi",
    "iso:country":"JP",
    "wof:name":"620-0064",
    "wof:placetype":"postalcode"
},
  "geometry": {"coordinates":[135.1087,35.311],"type":"Point"}
}