{
  "type": "Feature",
  "properties": {
    "gn:adm1_name":"Niigataken",
    "gn:adm2_name":"Sadogun'Aikawamachi",
    "gn:name":"Tachibana",
    "iso:country":"JP",
    "wof:name":"952-1644",
    "wof:placetype":"postalcode"
},
  "geometry": {"coordinates":[138.23330000000001,37.9806],"type":"Point"}
}