{
  "type": "Feature",
  "properties": {
    "gn:adm1_name":"Aichiken",
    "gn:adm2_name":"Nagoyashinakagawaku",
    "gn:name":"Honmaedachou",
    "iso:country":"JP",
    "wof:name":"454-0914",
    "wof:placetype":"postalcode"
},
  "geometry": {"coordinates":[136.83699999999999,35.1439],"type":"Point"}
}