{
  "type": "Feature",
  "properties": {
    "gn:adm1_name":"Kagoshimaken",
    "gn:adm2_name":"Ooshimagunyamatoson",
    "gn:name":"Ooganeku",
    "iso:country":"JP",
    "wof:name":"894-3107",
    "wof:placetype":"postalcode"
},
  "geometry": {"coordinates":[129.352,28.3597],"type":"Point"}
}