{
  "type": "Feature",
  "properties": {
    "gn:adm1_name":"Fukushimaken",
    "gn:adm2_name":"Dategunyanagawamachi",
    "gn:name":"Motojinnai",
    "iso:country":"JP",
    "wof:name":"960-0743",
    "wof:placetype":"postalcode"
},
  "geometry": {"coordinates":[140.6087,37.8564],"type":"Point"}
}