{
  "type": "Feature",
  "properties": {
    "gn:adm1_name":"Gifuken",
    "gn:adm2_name":"Gifushi",
    "gn:name":"Kanoukurokichou",
    "iso:country":"JP",
    "wof:name":"500-8461",
    "wof:placetype":"postalcode"
},
  "geometry": {"coordinates":[136.74860000000001,35.408],"type":"Point"}
}