{
  "type": "Feature",
  "properties": {
    "gn:adm1_name":"Kouchiken",
    "gn:adm2_name":"Takaokagunsakawachou",
    "gn:name":"Nishigumi",
    "iso:country":"JP",
    "wof:name":"789-1234",
    "wof:placetype":"postalcode"
},
  "geometry": {"coordinates":[133.2774,33.4769],"type":"Point"}
}