{
  "type": "Feature",
  "properties": {
    "gn:adm1_name":"Sagaken",
    "gn:adm2_name":"Karatsushi",
    "gn:name":"Kyoumachi",
    "iso:country":"JP",
    "wof:name":"847-0045",
    "wof:placetype":"postalcode"
},
  "geometry": {"coordinates":[129.97020000000001,33.447],"type":"Point"}
}