{
  "type": "Feature",
  "properties": {
    "gn:adm1_name":"Kagoshimaken",
    "gn:adm2_name":"Ooshimagunkikaichou",
    "gn:name":"Onotsu",
    "iso:country":"JP",
    "wof:name":"891-6142",
    "wof:placetype":"postalcode"
},
  "geometry": {"coordinates":[130.00219999999999,28.3647],"type":"Point"}
}