{
  "type": "Feature",
  "properties": {
    "gn:adm1_name":"Aichiken",
    "gn:adm2_name":"Nagoyashimeitouku",
    "gn:name":"Fujisatochou",
    "iso:country":"JP",
    "wof:name":"465-0036",
    "wof:placetype":"postalcode"
},
  "geometry": {"coordinates":[137.01560000000001,35.1893],"type":"Point"}
}