{
  "type": "Feature",
  "properties": {
    "gn:adm1_name":"Gunmaken",
    "gn:adm2_name":"Ouragun'Ouramachi",
    "gn:name":"Akiduma",
    "iso:country":"JP",
    "wof:name":"370-0606",
    "wof:placetype":"postalcode"
},
  "geometry": {"coordinates":[139.4615,36.2822],"type":"Point"}
}