{
  "type": "Feature",
  "properties": {
    "gn:adm1_name":"Niigataken",
    "gn:adm2_name":"Niigatashi",
    "gn:name":"Aoyamasuidou",
    "iso:country":"JP",
    "wof:name":"950-2005",
    "wof:placetype":"postalcode"
},
  "geometry": {"coordinates":[138.99639999999999,37.892],"type":"Point"}
}