{
  "type": "Feature",
  "properties": {
    "gn:adm1_name":"Naraken",
    "gn:adm2_name":"Udagun'Ooudachou",
    "gn:name":"Kamihon",
    "iso:country":"JP",
    "wof:name":"633-2172",
    "wof:placetype":"postalcode"
},
  "geometry": {"coordinates":[135.93270000000001,34.4828],"type":"Point"}
}