{
  "type": "Feature",
  "properties": {
    "gn:adm1_name":"Miyagiken",
    "gn:adm2_name":"Shibatagun'Oogawaramachi",
    "gn:name":"Nishikichou",
    "iso:country":"JP",
    "wof:name":"989-1217",
    "wof:placetype":"postalcode"
},
  "geometry": {"coordinates":[140.74459999999999,38.0462],"type":"Point"}
}