{
  "type": "Feature",
  "properties": {
    "gn:adm1_name":"Naraken",
    "gn:adm2_name":"Narashi",
    "gn:name":"Hannyajichou",
    "iso:country":"JP",
    "wof:name":"630-8102",
    "wof:placetype":"postalcode"
},
  "geometry": {"coordinates":[135.8365,34.6996],"type":"Point"}
}