{
  "type": "Feature",
  "properties": {
    "gn:adm1_name":"Mieken",
    "gn:adm2_name":"Ayamagun'Ayamachou",
    "gn:name":"Uchiho",
    "iso:country":"JP",
    "wof:name":"518-1321",
    "wof:placetype":"postalcode"
},
  "geometry": {"coordinates":[136.17410000000001,34.8824],"type":"Point"}
}