{
  "type": "Feature",
  "properties": {
    "gn:adm1_name":"Oosakafu",
    "gn:adm2_name":"Minooshi",
    "gn:name":"Shimotodoromi",
    "iso:country":"JP",
    "wof:name":"563-0252",
    "wof:placetype":"postalcode"
},
  "geometry": {"coordinates":[135.45820000000001,34.8788],"type":"Point"}
}