{
  "type": "Feature",
  "properties": {
    "gn:adm1_name":"Toukyouto",
    "gn:adm2_name":"Mitakashi",
    "gn:name":"Mure",
    "iso:country":"JP",
    "wof:name":"181-0002",
    "wof:placetype":"postalcode"
},
  "geometry": {"coordinates":[139.57929999999999,35.6869],"type":"Point"}
}