{
  "type": "Feature",
  "properties": {
    "gn:adm1_name":"Fukuokaken",
    "gn:adm2_name":"Tagawashi",
    "gn:name":"Ita",
    "iso:country":"JP",
    "wof:name":"825-0002",
    "wof:placetype":"postalcode"
},
  "geometry": {"coordinates":[130.82310000000001,33.6468],"type":"Point"}
}