{
  "type": "Feature",
  "properties": {
    "gn:adm1_name":"Naganoken",
    "gn:adm2_name":"Kamiinagunnakagawamura",
    "gn:name":"Katagiri",
    "iso:country":"JP",
    "wof:name":"399-3802",
    "wof:placetype":"postalcode"
},
  "geometry": {"coordinates":[137.92420000000001,35.6335],"type":"Point"}
}