{
  "type": "Feature",
  "properties": {
    "gn:adm1_name":"Nagasakiken",
    "gn:adm2_name":"Hiradoshi",
    "gn:name":"Ikanikeisaiganaibaai",
    "iso:country":"JP",
    "wof:name":"859-5100",
    "wof:placetype":"postalcode"
},
  "geometry": {"coordinates":[129.39789999999999,33.199],"type":"Point"}
}