{
  "type": "Feature",
  "properties": {
    "gn:adm1_name":"Kanagawaken",
    "gn:adm2_name":"Ashigarakamigunyamakitamachi",
    "gn:name":"Yubure",
    "iso:country":"JP",
    "wof:name":"258-0123",
    "wof:placetype":"postalcode"
},
  "geometry": {"coordinates":[139.03550000000001,35.3807],"type":"Point"}
}