{
  "type": "Feature",
  "properties": {
    "gn:adm1_name":"Tochigiken",
    "gn:adm2_name":"Ashikagashi",
    "gn:name":"Shimadachou",
    "iso:country":"JP",
    "wof:name":"326-0337",
    "wof:placetype":"postalcode"
},
  "geometry": {"coordinates":[139.45070000000001,36.3004],"type":"Point"}
}