{
  "type": "Feature",
  "properties": {
    "gn:adm1_name":"Gifuken",
    "gn:adm2_name":"Gifushi",
    "gn:name":"Iwasaki",
    "iso:country":"JP",
    "wof:name":"502-0005",
    "wof:placetype":"postalcode"
},
  "geometry": {"coordinates":[136.77780000000001,35.469],"type":"Point"}
}