{
  "type": "Feature",
  "properties": {
    "gn:adm1_name":"Naganoken",
    "gn:adm2_name":"Nakanoshi",
    "gn:name":"Iwai",
    "iso:country":"JP",
    "wof:name":"383-0001",
    "wof:placetype":"postalcode"
},
  "geometry": {"coordinates":[138.36510000000001,36.8274],"type":"Point"}
}