{
  "type": "Feature",
  "properties": {
    "gn:adm1_name":"Tochigiken",
    "gn:adm2_name":"Hagagunmashikomachi",
    "gn:name":"Higashidai",
    "iso:country":"JP",
    "wof:name":"321-4227",
    "wof:placetype":"postalcode"
},
  "geometry": {"coordinates":[140.0712,36.4492],"type":"Point"}
}