{
  "type": "Feature",
  "properties": {
    "gn:adm1_name":"Okayamaken",
    "gn:adm2_name":"Niimishi",
    "gn:name":"Tarumi",
    "iso:country":"JP",
    "wof:name":"719-2642",
    "wof:placetype":"postalcode"
},
  "geometry": {"coordinates":[133.51429999999999,34.942],"type":"Point"}
}