{
  "type": "Feature",
  "properties": {
    "gn:adm1_name":"Ibarakiken",
    "gn:adm2_name":"Shimodateshi",
    "gn:name":"Narita",
    "iso:country":"JP",
    "wof:name":"308-0821",
    "wof:placetype":"postalcode"
},
  "geometry": {"coordinates":[139.9949,36.3064],"type":"Point"}
}